{
  "type": "Feature",
  "properties": {
    "gn:admin1_code":"10",
    "gn:admin2_code":"0.0",
    "gn:admin3_code":"1059.0",
    "gn:admin4_code":"1059168.0",
    "gn:asciiname":"Vogelsang",
    "gn:country_code":"DE",
    "gn:dem":21,
    "gn:feature_class":"P",
    "gn:feature_code":"PPL",
    "gn:name":"Vogelsang",
    "gn:population":0,
    "gn:timezone":"Europe/Berlin",
    "iso:country":"DE",
    "name:ceb_x_preferred":[
        "Vogelsang"
    ],
    "name:ces_x_preferred":[
        "Vogelsang"
    ],
    "name:deu_x_preferred":[
        "Vogelsang"
    ],
    "name:epo_x_preferred":[
        "Vogelsang"
    ],
    "name:fra_x_preferred":[
        "Vogelsang"
    ],
    "name:ita_x_preferred":[
        "Vogelsang"
    ],
    "name:nld_x_preferred":[
        "Vogelsang"
    ],
    "name:pol_x_preferred":[
        "Vogelsang"
    ],
    "name:rus_x_preferred":[
        "\u0424\u043e\u0433\u0435\u043b\u044c\u0437\u0430\u043d\u0433"
    ],
    "name:swe_x_preferred":[
        "Vogelsang"
    ],
    "wof:name":"Vogelsang",
    "wof:placetype":"neighbourhood"
},
  "geometry": {"coordinates":[9.89949,54.69922],"type":"Point"}
}