{
  "type": "Feature",
  "properties": {
    "gn:admin1_code":"2",
    "gn:admin2_code":"94.0",
    "gn:admin3_code":"9472.0",
    "gn:admin4_code":"9472119.0",
    "gn:asciiname":"Katzeneichen",
    "gn:country_code":"DE",
    "gn:dem":398,
    "gn:feature_class":"P",
    "gn:feature_code":"PPL",
    "gn:name":"Katzeneichen",
    "gn:population":0,
    "gn:timezone":"Europe/Berlin",
    "iso:country":"DE",
    "wof:name":"Katzeneichen",
    "wof:placetype":"neighbourhood"
},
  "geometry": {"coordinates":[11.64908,50.00638],"type":"Point"}
}