{
  "type": "Feature",
  "properties": {
    "gn:admin1_code":"14",
    "gn:admin2_code":"0.0",
    "gn:admin3_code":"15086.0",
    "gn:admin4_code":"15086015.0",
    "gn:asciiname":"Kirchguetter",
    "gn:country_code":"DE",
    "gn:dem":45,
    "gn:feature_class":"P",
    "gn:feature_code":"PPL",
    "gn:name":"Kirchg\u00fctter",
    "gn:population":0,
    "gn:timezone":"Europe/Berlin",
    "iso:country":"DE",
    "wof:name":"Kirchguetter",
    "wof:placetype":"neighbourhood"
},
  "geometry": {"coordinates":[11.91667,52.26667],"type":"Point"}
}