{
  "type": "Feature",
  "properties": {
    "gn:admin1_code":"2",
    "gn:admin2_code":"97.0",
    "gn:admin3_code":"9777.0",
    "gn:admin4_code":"9777159.0",
    "gn:asciiname":"Kappel",
    "gn:country_code":"DE",
    "gn:dem":894,
    "gn:feature_class":"P",
    "gn:feature_code":"PPL",
    "gn:name":"Kappel",
    "gn:population":0,
    "gn:timezone":"Europe/Berlin",
    "iso:country":"DE",
    "name:als_x_preferred":[
        "Kappel"
    ],
    "name:ceb_x_preferred":[
        "Kappel"
    ],
    "name:deu_x_preferred":[
        "Kappel"
    ],
    "name:epo_x_preferred":[
        "Kappel"
    ],
    "name:fra_x_preferred":[
        "Kappel"
    ],
    "name:ita_x_preferred":[
        "Kappel"
    ],
    "name:nld_x_preferred":[
        "Kappel"
    ],
    "name:pol_x_preferred":[
        "Kappel"
    ],
    "name:spa_x_preferred":[
        "Kappel"
    ],
    "name:swe_x_preferred":[
        "Kappel"
    ],
    "name:vol_x_preferred":[
        "Kappel"
    ],
    "wof:name":"Kappel",
    "wof:placetype":"neighbourhood"
},
  "geometry": {"coordinates":[10.53529,47.60512],"type":"Point"}
}