{
  "type": "Feature",
  "properties": {
    "gn:admin1_code":"5.0",
    "gn:admin2_code":"65.0",
    "gn:admin3_code":"6533.0",
    "gn:admin4_code":"6533018.0",
    "gn:asciiname":"Aulenhausen",
    "gn:country_code":"DE",
    "gn:dem":283,
    "gn:feature_class":"P",
    "gn:feature_code":"PPL",
    "gn:name":"Aulenhausen",
    "gn:population":0,
    "gn:timezone":"Europe/Berlin",
    "iso:country":"DE",
    "wof:name":"Aulenhausen",
    "wof:placetype":"neighbourhood"
},
  "geometry": {"coordinates":[8.32455,50.4334],"type":"Point"}
}