{
  "type": "Feature",
  "properties": {
    "gn:country":"DE",
    "gn:fcode":"PPL",
    "gn:population":134,
    "iso:country":"DE",
    "name:bak_x_preferred":[
        "\u0422\u0438\u043b\u044c\u0437\u0435\u043d"
    ],
    "name:ceb_x_preferred":[
        "Tylsen"
    ],
    "name:deu_x_preferred":[
        "Tylsen"
    ],
    "name:epo_x_preferred":[
        "Tylsen"
    ],
    "name:fas_x_preferred":[
        "\u062a\u06cc\u0644\u0633\u0646"
    ],
    "name:kaz_x_preferred":[
        "\u0422\u0438\u043b\u044c\u0437\u0435\u043d"
    ],
    "name:kir_x_preferred":[
        "\u0422\u0438\u043b\u044c\u0437\u0435\u043d"
    ],
    "name:nld_x_preferred":[
        "Tylsen"
    ],
    "name:ron_x_preferred":[
        "Tylsen"
    ],
    "name:rus_x_preferred":[
        "\u0422\u0438\u043b\u044c\u0437\u0435\u043d"
    ],
    "name:uzb_x_preferred":[
        "Tylsen"
    ],
    "name:vie_x_preferred":[
        "Tylsen"
    ],
    "name:vol_x_preferred":[
        "Tylsen"
    ],
    "qs_pg:aaroncc":"DE",
    "qs_pg:gn_country":"DE",
    "qs_pg:gn_fcode":"PPL",
    "qs_pg:gn_pop":134,
    "qs_pg:name":"Tylsen",
    "qs_pg:name_adm0":"Deutschland",
    "qs_pg:name_adm1":"Sachsen-Anhalt",
    "qs_pg:photos_9k":1,
    "qs_pg:photos_9r":1,
    "qs_pg:photos_all":10,
    "qs_pg:photos_sr":0,
    "qs_pg:pop_sr":1,
    "qs_pg:qs_pg_placetype":"locality",
    "qs_pg:qs_pg_placetype_gp":"Town",
    "qs_pg:woe_adm0":23424829,
    "woe:adm0_id":23424829,
    "woe:name_adm0":"Deutschland",
    "woe:name_adm1":"Sachsen-Anhalt",
    "woe:placetype":"Town",
    "wof:name":"Tylsen",
    "wof:placetype":"neighbourhood",
    "wof:population":134
},
  "geometry": {"coordinates":[11.03341,52.81572],"type":"Point"}
}