{
  "type": "Feature",
  "properties": {
    "gn:admin1_code":"13",
    "gn:admin2_code":"0.0",
    "gn:admin3_code":"14626.0",
    "gn:admin4_code":"14626170.0",
    "gn:asciiname":"Charlottenruh",
    "gn:country_code":"DE",
    "gn:dem":300,
    "gn:feature_class":"P",
    "gn:feature_code":"PPL",
    "gn:name":"Charlottenruh",
    "gn:population":0,
    "gn:timezone":"Europe/Berlin",
    "iso:country":"DE",
    "wof:name":"Charlottenruh",
    "wof:placetype":"neighbourhood"
},
  "geometry": {"coordinates":[14.70417,50.90812],"type":"Point"}
}