{
  "type": "Feature",
  "properties": {
    "gn:admin1_code":"7",
    "gn:admin2_code":"57.0",
    "gn:admin3_code":"5754.0",
    "gn:admin4_code":"5754004.0",
    "gn:asciiname":"Kasum",
    "gn:country_code":"DE",
    "gn:dem":91,
    "gn:feature_class":"P",
    "gn:feature_code":"PPL",
    "gn:name":"Kasum",
    "gn:population":0,
    "gn:timezone":"Europe/Berlin",
    "iso:country":"DE",
    "wof:name":"Kasum",
    "wof:placetype":"neighbourhood"
},
  "geometry": {"coordinates":[8.25722,52.06561],"type":"Point"}
}