{
  "type": "Feature",
  "properties": {
    "gn:admin1_code":"12.0",
    "gn:admin2_code":"0.0",
    "gn:admin3_code":"13072.0",
    "gn:admin4_code":"13072016.0",
    "gn:asciiname":"Alt Vorwerk",
    "gn:country_code":"DE",
    "gn:dem":34,
    "gn:feature_class":"P",
    "gn:feature_code":"PPL",
    "gn:name":"Alt Vorwerk",
    "gn:population":0,
    "gn:timezone":"Europe/Berlin",
    "iso:country":"DE",
    "wof:name":"Alt Vorwerk",
    "wof:placetype":"neighbourhood"
},
  "geometry": {"coordinates":[12.61007,53.92729],"type":"Point"}
}