{
  "type": "Feature",
  "properties": {
    "gn:admin1_code":"2",
    "gn:admin2_code":"94.0",
    "gn:admin3_code":"9477.0",
    "gn:admin4_code":"9477128.0",
    "gn:asciiname":"Frankenberg",
    "gn:country_code":"DE",
    "gn:dem":330,
    "gn:feature_class":"P",
    "gn:feature_code":"PPL",
    "gn:name":"Frankenberg",
    "gn:population":0,
    "gn:timezone":"Europe/Berlin",
    "iso:country":"DE",
    "name:ceb_x_preferred":[
        "Frankenberg"
    ],
    "name:deu_x_preferred":[
        "Frankenberg"
    ],
    "name:epo_x_preferred":[
        "Frankenberg"
    ],
    "name:est_x_preferred":[
        "Frankenberg"
    ],
    "name:fas_x_preferred":[
        "\u0641\u0631\u0627\u0646\u06a9\u0646\u0628\u0631\u06af"
    ],
    "name:fra_x_preferred":[
        "Frankenberg"
    ],
    "name:hun_x_preferred":[
        "Frankenberg"
    ],
    "name:ita_x_preferred":[
        "Frankenberg"
    ],
    "name:jpn_x_preferred":[
        "\u30d5\u30e9\u30f3\u30b1\u30f3\u30d9\u30eb\u30af"
    ],
    "name:mkd_x_preferred":[
        "\u0424\u0440\u0430\u043d\u043a\u0435\u043d\u0431\u0435\u0440\u0433"
    ],
    "name:nld_x_preferred":[
        "Frankenberg"
    ],
    "name:pol_x_preferred":[
        "Frankenberg"
    ],
    "name:ron_x_preferred":[
        "Frankenberg"
    ],
    "name:rus_x_preferred":[
        "\u0424\u0440\u0430\u043d\u043a\u0435\u043d\u0431\u0435\u0440\u0433"
    ],
    "name:swe_x_preferred":[
        "Frankenberg"
    ],
    "wof:name":"Frankenberg",
    "wof:placetype":"neighbourhood"
},
  "geometry": {"coordinates":[11.39113,50.08405],"type":"Point"}
}