{
  "type": "Feature",
  "properties": {
    "gn:admin1_code":"2",
    "gn:admin2_code":"92.0",
    "gn:admin3_code":"9274.0",
    "gn:admin4_code":"9274193.0",
    "gn:asciiname":"Kasbach",
    "gn:country_code":"DE",
    "gn:dem":470,
    "gn:feature_class":"P",
    "gn:feature_code":"PPL",
    "gn:name":"Kasbach",
    "gn:population":0,
    "gn:timezone":"Europe/Berlin",
    "iso:country":"DE",
    "wof:name":"Kasbach",
    "wof:placetype":"neighbourhood"
},
  "geometry": {"coordinates":[12.30418,48.35737],"type":"Point"}
}