{
  "type": "Feature",
  "properties": {
    "gn:country":"DE",
    "gn:fcode":"PPL",
    "gn:population":0,
    "iso:country":"DE",
    "name:ast_x_preferred":[
        "Schweizerm\u00fchle"
    ],
    "name:deu_x_preferred":[
        "Schweizerm\u00fchle"
    ],
    "name:eng_x_preferred":[
        "Schweizerm\u00fchle"
    ],
    "name:fra_x_preferred":[
        "Schweizerm\u00fchle"
    ],
    "name:nld_x_preferred":[
        "Schweizerm\u00fchle"
    ],
    "qs_pg:aaroncc":"DE",
    "qs_pg:gn_country":"DE",
    "qs_pg:gn_fcode":"PPL",
    "qs_pg:gn_pop":0,
    "qs_pg:name":"Schweizerm\u00fchle",
    "qs_pg:name_adm0":"Deutschland",
    "qs_pg:name_adm1":"Sachsen",
    "qs_pg:photos":10,
    "qs_pg:photos_1k":2,
    "qs_pg:photos_9k":1,
    "qs_pg:photos_9r":1,
    "qs_pg:photos_all":10,
    "qs_pg:photos_sr":1,
    "qs_pg:pop_sr":0,
    "qs_pg:qs_pg_placetype":"locality",
    "qs_pg:qs_pg_placetype_gp":"Town",
    "qs_pg:woe_adm0":23424829,
    "woe:adm0_id":23424829,
    "woe:name_adm0":"Deutschland",
    "woe:name_adm1":"Sachsen",
    "woe:placetype":"Town",
    "wof:name":"Schweizerm\u00fchle",
    "wof:placetype":"neighbourhood"
},
  "geometry": {"coordinates":[14.04392,50.84757],"type":"Point"}
}