{
  "type": "Feature",
  "properties": {
    "gn:gn_country":"DE",
    "gn:gn_fcode":"PPLA4",
    "gn:gn_pop":274,
    "gn:population":274,
    "iso:country":"DE",
    "name:bak_x_preferred":[
        "\u041c\u0435\u0445\u0435\u043b\u044c\u0440\u043e\u0434\u0430"
    ],
    "name:baq_x_preferred":[
        "Mechelroda"
    ],
    "name:chi_x_preferred":[
        "\u6885\u6b47\u5c14\u7f57\u8fbe"
    ],
    "name:dut_x_preferred":[
        "Mechelroda"
    ],
    "name:eng_x_preferred":[
        "Mechelroda"
    ],
    "name:epo_x_preferred":[
        "Mechelroda"
    ],
    "name:fre_x_preferred":[
        "Mechelroda"
    ],
    "name:ger_x_preferred":[
        "Mechelroda"
    ],
    "name:hun_x_preferred":[
        "Mechelroda"
    ],
    "name:ita_x_preferred":[
        "Mechelroda"
    ],
    "name:kaz_x_preferred":[
        "\u041c\u0435\u0445\u0435\u043b\u044c\u0440\u043e\u0434\u0430"
    ],
    "name:kir_x_preferred":[
        "\u041c\u0435\u0445\u0435\u043b\u044c\u0440\u043e\u0434\u0430"
    ],
    "name:mac_x_preferred":[
        "\u041c\u0435\u0445\u0435\u043b\u0440\u043e\u0434\u0430"
    ],
    "name:may_x_preferred":[
        "Mechelroda"
    ],
    "name:per_x_preferred":[
        "\u0645\u0627\u0634\u0644\u0631\u0648\u062f\u0627"
    ],
    "name:pol_x_preferred":[
        "Mechelroda"
    ],
    "name:rum_x_preferred":[
        "Mechelroda"
    ],
    "name:rus_x_preferred":[
        "\u041c\u0435\u0445\u0435\u043b\u044c\u0440\u043e\u0434\u0430"
    ],
    "name:srp_x_preferred":[
        "\u041c\u0435\u0445\u0435\u043b\u0440\u043e\u0434\u0430"
    ],
    "name:ukr_x_preferred":[
        "\u041c\u0435\u0445\u0435\u043b\u044c\u0440\u043e\u0434\u0430"
    ],
    "name:uzb_x_preferred":[
        "Mechelroda"
    ],
    "name:vie_x_preferred":[
        "Mechelroda"
    ],
    "name:vol_x_preferred":[
        "Mechelroda"
    ],
    "name:war_x_preferred":[
        "Mechelroda"
    ],
    "qs_pg:aaroncc":"DE",
    "qs_pg:gn_country":"DE",
    "qs_pg:gn_fcode":"PPLA4",
    "qs_pg:gn_pop":274,
    "qs_pg:name":"Mechelroda",
    "qs_pg:photos_9r":0,
    "qs_pg:photos_sr":0,
    "qs_pg:pop_sr":2,
    "qs_pg:qs_pg_placetype":"locality",
    "wof:name":"Mechelroda",
    "wof:placetype":"locality",
    "wof:population":274
},
  "geometry": {"coordinates":[11.37806,50.91126],"type":"Point"}
}