{
  "type": "Feature",
  "properties": {
    "gn:admin1_code":"8",
    "gn:admin2_code":"0.0",
    "gn:admin3_code":"7134.0",
    "gn:admin4_code":"7134045.0",
    "gn:asciiname":"Enzweiler",
    "gn:country_code":"DE",
    "gn:dem":293,
    "gn:feature_class":"P",
    "gn:feature_code":"PPL",
    "gn:name":"Enzweiler",
    "gn:population":0,
    "gn:timezone":"Europe/Berlin",
    "iso:country":"DE",
    "wof:name":"Enzweiler",
    "wof:placetype":"neighbourhood"
},
  "geometry": {"coordinates":[7.29838,49.694],"type":"Point"}
}