{
  "type": "Feature",
  "properties": {
    "gn:admin1_code":"2",
    "gn:admin2_code":"96.0",
    "gn:admin3_code":"9679.0",
    "gn:admin4_code":"9679201.0",
    "gn:asciiname":"Hilpertshausen",
    "gn:country_code":"DE",
    "gn:dem":296,
    "gn:feature_class":"P",
    "gn:feature_code":"PPL",
    "gn:name":"Hilpertshausen",
    "gn:population":0,
    "gn:timezone":"Europe/Berlin",
    "iso:country":"DE",
    "wof:name":"Hilpertshausen",
    "wof:placetype":"neighbourhood"
},
  "geometry": {"coordinates":[10.0122,49.89621],"type":"Point"}
}