{
  "type": "Feature",
  "properties": {
    "gn:admin1_code":"10",
    "gn:admin2_code":"0.0",
    "gn:admin3_code":"1060.0",
    "gn:admin4_code":"1060063.0",
    "gn:asciiname":"Ohe",
    "gn:country_code":"DE",
    "gn:dem":23,
    "gn:feature_class":"P",
    "gn:feature_code":"PPL",
    "gn:name":"Ohe",
    "gn:population":0,
    "gn:timezone":"Europe/Berlin",
    "iso:country":"DE",
    "name:ceb_x_preferred":[
        "Ohe"
    ],
    "name:deu_x_preferred":[
        "Ohe"
    ],
    "name:nld_x_preferred":[
        "Ohe"
    ],
    "name:swe_x_preferred":[
        "Ohe"
    ],
    "wof:name":"Ohe",
    "wof:placetype":"neighbourhood"
},
  "geometry": {"coordinates":[9.95658,53.6577],"type":"Point"}
}