{
  "type": "Feature",
  "properties": {
    "gn:admin1_code":"2",
    "gn:admin2_code":"93.0",
    "gn:admin3_code":"9374.0",
    "gn:admin4_code":"9374165.0",
    "gn:asciiname":"Spielberg",
    "gn:country_code":"DE",
    "gn:dem":581,
    "gn:feature_class":"P",
    "gn:feature_code":"PPL",
    "gn:name":"Spielberg",
    "gn:population":0,
    "gn:timezone":"Europe/Berlin",
    "iso:country":"DE",
    "wof:name":"Spielberg",
    "wof:placetype":"neighbourhood"
},
  "geometry": {"coordinates":[12.32804,49.70295],"type":"Point"}
}