{
  "type": "Feature",
  "properties": {
    "gn:admin1_code":"13",
    "gn:admin2_code":"0.0",
    "gn:admin3_code":"14521.0",
    "gn:admin4_code":"14521390.0",
    "gn:asciiname":"Mooshaide",
    "gn:country_code":"DE",
    "gn:dem":652,
    "gn:feature_class":"P",
    "gn:feature_code":"PPL",
    "gn:name":"Mooshaide",
    "gn:population":0,
    "gn:timezone":"Europe/Berlin",
    "iso:country":"DE",
    "name:und_x_variant":[
        "Moosheide"
    ],
    "wof:name":"Mooshaide",
    "wof:placetype":"neighbourhood"
},
  "geometry": {"coordinates":[13.13799,50.64645],"type":"Point"}
}