{
  "type": "Feature",
  "properties": {
    "gn:admin1_code":"13.0",
    "gn:admin2_code":"0.0",
    "gn:admin3_code":"14729.0",
    "gn:admin4_code":"14729150.0",
    "gn:asciiname":"Altdorf",
    "gn:country_code":"DE",
    "gn:dem":218,
    "gn:feature_class":"P",
    "gn:feature_code":"PPL",
    "gn:name":"Altdorf",
    "gn:population":0,
    "gn:timezone":"Europe/Berlin",
    "iso:country":"DE",
    "name:als_x_preferred":[
        "Altdorf"
    ],
    "name:ben_x_preferred":[
        "\u0986\u09b2\u09a1\u09b0\u09cd\u09ab"
    ],
    "name:ceb_x_preferred":[
        "Altdorf"
    ],
    "name:dan_x_preferred":[
        "Altdorf"
    ],
    "name:deu_x_preferred":[
        "Altdorf"
    ],
    "name:epo_x_preferred":[
        "Altdorf"
    ],
    "name:eus_x_preferred":[
        "Altdorf"
    ],
    "name:fra_x_preferred":[
        "Altdorf"
    ],
    "name:hin_x_preferred":[
        "\u0906\u0932\u094d\u091f\u0921\u0949\u0930\u094d\u092b\u093c"
    ],
    "name:hun_x_preferred":[
        "Altdorf"
    ],
    "name:hye_x_preferred":[
        "\u0531\u056c\u057f\u0564\u0578\u0580\u0586"
    ],
    "name:ita_x_preferred":[
        "Altdorf"
    ],
    "name:lmo_x_preferred":[
        "Altdorf"
    ],
    "name:ltz_x_preferred":[
        "Altdorf"
    ],
    "name:nld_x_preferred":[
        "Altdorf"
    ],
    "name:pol_x_preferred":[
        "Altdorf"
    ],
    "name:por_x_preferred":[
        "Altdorf"
    ],
    "name:roh_x_preferred":[
        "Altdorf"
    ],
    "name:rus_x_preferred":[
        "\u0410\u043b\u044c\u0442\u0434\u043e\u0440\u0444"
    ],
    "name:slk_x_preferred":[
        "Altdorf"
    ],
    "name:spa_x_preferred":[
        "Altdorf"
    ],
    "name:swe_x_preferred":[
        "Altdorf"
    ],
    "name:vol_x_preferred":[
        "Altdorf"
    ],
    "wof:name":"Altdorf",
    "wof:placetype":"neighbourhood"
},
  "geometry": {"coordinates":[12.68312,51.05466],"type":"Point"}
}