{
  "type": "Feature",
  "properties": {
    "gn:admin1_code":"13.0",
    "gn:admin2_code":"0.0",
    "gn:admin3_code":"14729.0",
    "gn:admin4_code":"14729150.0",
    "gn:asciiname":"Altdorf",
    "gn:country_code":"DE",
    "gn:dem":218,
    "gn:feature_class":"P",
    "gn:feature_code":"PPL",
    "gn:name":"Altdorf",
    "gn:population":0,
    "gn:timezone":"Europe/Berlin",
    "iso:country":"DE",
    "wof:name":"Altdorf",
    "wof:placetype":"neighbourhood"
},
  "geometry": {"coordinates":[12.68312,51.05466],"type":"Point"}
}