{
  "type": "Feature",
  "properties": {
    "gn:admin1_code":"2",
    "gn:admin2_code":"93.0",
    "gn:admin3_code":"9373.0",
    "gn:admin4_code":"9373115.0",
    "gn:asciiname":"Langenried",
    "gn:country_code":"DE",
    "gn:dem":511,
    "gn:feature_class":"P",
    "gn:feature_code":"PPL",
    "gn:name":"Langenried",
    "gn:population":0,
    "gn:timezone":"Europe/Berlin",
    "iso:country":"DE",
    "wof:name":"Langenried",
    "wof:placetype":"neighbourhood"
},
  "geometry": {"coordinates":[11.6207,49.09809],"type":"Point"}
}