{
  "type": "Feature",
  "properties": {
    "gn:admin1_code":"2.0",
    "gn:admin2_code":"096",
    "gn:admin3_code":"9674.0",
    "gn:admin4_code":"9674221.0",
    "gn:asciiname":"Ziegelanger",
    "gn:country_code":"DE",
    "gn:dem":230,
    "gn:feature_class":"P",
    "gn:feature_code":"PPL",
    "gn:name":"Ziegelanger",
    "gn:population":0,
    "gn:timezone":"Europe/Berlin",
    "iso:country":"DE",
    "wof:name":"Ziegelanger",
    "wof:placetype":"neighbourhood"
},
  "geometry": {"coordinates":[10.61638,49.99979],"type":"Point"}
}