{
  "type": "Feature",
  "properties": {
    "gn:admin1_code":"5",
    "gn:admin2_code":"64.0",
    "gn:admin3_code":"6437.0",
    "gn:admin4_code":"6437003.0",
    "gn:asciiname":"Nieder-Kainsbach",
    "gn:country_code":"DE",
    "gn:dem":190,
    "gn:feature_class":"P",
    "gn:feature_code":"PPL",
    "gn:name":"Nieder-Kainsbach",
    "gn:population":0,
    "gn:timezone":"Europe/Berlin",
    "iso:country":"DE",
    "wof:name":"Nieder-Kainsbach",
    "wof:placetype":"neighbourhood"
},
  "geometry": {"coordinates":[8.88303,49.75404],"type":"Point"}
}