{
  "type": "Feature",
  "properties": {
    "gn:admin1_code":"7",
    "gn:admin2_code":"59.0",
    "gn:admin3_code":"5954.0",
    "gn:admin4_code":"5954032.0",
    "gn:asciiname":"Oberwengern",
    "gn:country_code":"DE",
    "gn:dem":210,
    "gn:feature_class":"P",
    "gn:feature_code":"PPL",
    "gn:name":"Oberwengern",
    "gn:population":0,
    "gn:timezone":"Europe/Berlin",
    "iso:country":"DE",
    "wof:name":"Oberwengern",
    "wof:placetype":"neighbourhood"
},
  "geometry": {"coordinates":[7.37277,51.37578],"type":"Point"}
}