{
  "type": "Feature",
  "properties": {
    "gn:gn_country":"DE",
    "gn:gn_fcode":"PPLA4",
    "gn:gn_pop":283,
    "gn:population":283,
    "iso:country":"DE",
    "name:baq_x_preferred":[
        "Bisterschied"
    ],
    "name:chi_x_preferred":[
        "\u6bd4\u65af\u7279\u5c14\u5e2d\u5fb7"
    ],
    "name:dut_x_preferred":[
        "Bisterschied"
    ],
    "name:eng_x_preferred":[
        "Bisterschied"
    ],
    "name:epo_x_preferred":[
        "Bisterschied"
    ],
    "name:fre_x_preferred":[
        "Bisterschied"
    ],
    "name:ger_x_preferred":[
        "Bisterschied"
    ],
    "name:hun_x_preferred":[
        "Bisterschied"
    ],
    "name:ita_x_preferred":[
        "Bisterschied"
    ],
    "name:jpn_x_preferred":[
        "\u30d3\u30b9\u30bf\u30fc\u30b7\u30fc\u30c8"
    ],
    "name:kaz_x_preferred":[
        "\u0411\u0438\u0441\u0442\u0435\u0440\u0448\u0438\u0434"
    ],
    "name:kir_x_preferred":[
        "\u0411\u0438\u0441\u0442\u0435\u0440\u0448\u0438\u0434"
    ],
    "name:may_x_preferred":[
        "Bisterschied"
    ],
    "name:pol_x_preferred":[
        "Bisterschied"
    ],
    "name:por_x_preferred":[
        "Bisterschied"
    ],
    "name:rum_x_preferred":[
        "Bisterschied"
    ],
    "name:rus_x_preferred":[
        "\u0411\u0438\u0441\u0442\u0435\u0440\u0448\u0438\u0434"
    ],
    "name:spa_x_preferred":[
        "Bisterschied"
    ],
    "name:srp_x_preferred":[
        "\u0411\u0438\u0441\u0442\u0435\u0440\u0448\u0438\u0434"
    ],
    "name:swe_x_preferred":[
        "Bisterschied"
    ],
    "name:ukr_x_preferred":[
        "\u0411\u0456\u0441\u0442\u0435\u0440\u0448\u0438\u0434"
    ],
    "name:uzb_x_preferred":[
        "Bisterschied"
    ],
    "name:vie_x_preferred":[
        "Bisterschied"
    ],
    "name:vol_x_preferred":[
        "Bisterschied"
    ],
    "name:war_x_preferred":[
        "Bisterschied"
    ],
    "qs_pg:aaroncc":"DE",
    "qs_pg:gn_country":"DE",
    "qs_pg:gn_fcode":"PPLA4",
    "qs_pg:gn_pop":283,
    "qs_pg:name":"Bisterschied",
    "qs_pg:photos_9r":0,
    "qs_pg:photos_sr":0,
    "qs_pg:pop_sr":2,
    "qs_pg:qs_pg_placetype":"locality",
    "wof:name":"Bisterschied",
    "wof:placetype":"locality",
    "wof:population":283
},
  "geometry": {"coordinates":[7.75,49.65],"type":"Point"}
}