{
  "type": "Feature",
  "properties": {
    "gn:country":"DE",
    "gn:fcode":"PPL",
    "gn:population":0,
    "iso:country":"DE",
    "name:als_x_preferred":[
        "Schlatt"
    ],
    "name:ceb_x_preferred":[
        "Schlatt"
    ],
    "name:deu_x_preferred":[
        "Schlatt"
    ],
    "name:epo_x_preferred":[
        "Schlatt"
    ],
    "name:eus_x_preferred":[
        "Schlatt"
    ],
    "name:fra_x_preferred":[
        "Schlatt"
    ],
    "name:ita_x_preferred":[
        "Schlatt"
    ],
    "name:lmo_x_preferred":[
        "Schlatt"
    ],
    "name:nld_x_preferred":[
        "Schlatt"
    ],
    "name:pol_x_preferred":[
        "Schlatt"
    ],
    "name:rus_x_preferred":[
        "\u0428\u043b\u0430\u0442"
    ],
    "name:spa_x_preferred":[
        "Schlatt"
    ],
    "name:swe_x_preferred":[
        "Schlatt"
    ],
    "name:vol_x_preferred":[
        "Schlatt"
    ],
    "qs_pg:aaroncc":"DE",
    "qs_pg:gn_country":"DE",
    "qs_pg:gn_fcode":"PPL",
    "qs_pg:gn_pop":0,
    "qs_pg:name":"Schlatt",
    "qs_pg:name_adm0":"Deutschland",
    "qs_pg:name_adm1":"Baden-W\u00fcrttemberg",
    "qs_pg:photos_9k":1,
    "qs_pg:photos_9r":1,
    "qs_pg:photos_all":1,
    "qs_pg:photos_sr":0,
    "qs_pg:pop_sr":0,
    "qs_pg:qs_pg_placetype":"locality",
    "qs_pg:qs_pg_placetype_gp":"Town",
    "qs_pg:woe_adm0":23424829,
    "woe:adm0_id":23424829,
    "woe:name_adm0":"Deutschland",
    "woe:name_adm1":"Baden-W\u00fcrttemberg",
    "woe:placetype":"Town",
    "wof:name":"Schlatt",
    "wof:placetype":"neighbourhood"
},
  "geometry": {"coordinates":[9.02527,48.34393],"type":"Point"}
}