{
  "type": "Feature",
  "properties": {
    "gn:admin1_code":"2",
    "gn:admin2_code":"97.0",
    "gn:admin3_code":"9778.0",
    "gn:admin4_code":"9778164.0",
    "gn:asciiname":"Dilpersried",
    "gn:country_code":"DE",
    "gn:dem":686,
    "gn:feature_class":"P",
    "gn:feature_code":"PPL",
    "gn:name":"Dilpersried",
    "gn:population":0,
    "gn:timezone":"Europe/Berlin",
    "iso:country":"DE",
    "wof:name":"Dilpersried",
    "wof:placetype":"neighbourhood"
},
  "geometry": {"coordinates":[10.08506,47.86201],"type":"Point"}
}