{
  "type": "Feature",
  "properties": {
    "gn:admin1_code":"5.0",
    "gn:admin2_code":"66.0",
    "gn:admin3_code":"6635.0",
    "gn:admin4_code":"6635013.0",
    "gn:asciiname":"Battenhausen",
    "gn:country_code":"DE",
    "gn:dem":501,
    "gn:feature_class":"P",
    "gn:feature_code":"PPL",
    "gn:name":"Battenhausen",
    "gn:population":0,
    "gn:timezone":"Europe/Berlin",
    "iso:country":"DE",
    "wof:name":"Battenhausen",
    "wof:placetype":"neighbourhood"
},
  "geometry": {"coordinates":[9.0279,51.03131],"type":"Point"}
}