{
  "type": "Feature",
  "properties": {
    "gn:gn_country":"DE",
    "gn:gn_fcode":"PPLA4",
    "gn:gn_pop":301,
    "gn:population":301,
    "iso:country":"DE",
    "name:baq_x_preferred":[
        "G\u00f6senroth"
    ],
    "name:chi_x_preferred":[
        "\u683c\u68ee\u7f57\u7279"
    ],
    "name:dut_x_preferred":[
        "G\u00f6senroth"
    ],
    "name:eng_x_preferred":[
        "G\u00f6senroth"
    ],
    "name:epo_x_preferred":[
        "G\u00f6senroth"
    ],
    "name:fre_x_preferred":[
        "G\u00f6senroth"
    ],
    "name:ger_x_preferred":[
        "G\u00f6senroth"
    ],
    "name:hun_x_preferred":[
        "G\u00f6senroth"
    ],
    "name:ita_x_preferred":[
        "G\u00f6senroth"
    ],
    "name:jpn_x_preferred":[
        "\u30b2\u30fc\u30bc\u30f3\u30ed\u30fc\u30c8"
    ],
    "name:kaz_x_preferred":[
        "\u0413\u0451\u0437\u0435\u043d\u0440\u043e\u0442"
    ],
    "name:kir_x_preferred":[
        "\u0413\u04e9\u0437\u0435\u043d\u0440\u043e\u0442"
    ],
    "name:may_x_preferred":[
        "G\u00f6senroth"
    ],
    "name:per_x_preferred":[
        "\u06af\u0648\u0632\u0646\u0631\u0648\u062a"
    ],
    "name:pol_x_preferred":[
        "G\u00f6senroth"
    ],
    "name:por_x_preferred":[
        "G\u00f6senroth"
    ],
    "name:rum_x_preferred":[
        "G\u00f6senroth"
    ],
    "name:rus_x_preferred":[
        "\u0413\u0451\u0437\u0435\u043d\u0440\u043e\u0442"
    ],
    "name:srp_x_preferred":[
        "\u0413\u0435\u0437\u0435\u043d\u0440\u043e\u0442"
    ],
    "name:ukr_x_preferred":[
        "\u0413\u0435\u0437\u0435\u043d\u0440\u043e\u0442"
    ],
    "name:uzb_x_preferred":[
        "G\u00f6senroth"
    ],
    "name:vie_x_preferred":[
        "G\u00f6senroth"
    ],
    "name:vol_x_preferred":[
        "G\u00f6senroth"
    ],
    "name:war_x_preferred":[
        "G\u00f6senroth"
    ],
    "qs_pg:aaroncc":"DE",
    "qs_pg:gn_country":"DE",
    "qs_pg:gn_fcode":"PPLA4",
    "qs_pg:gn_pop":301,
    "qs_pg:name":"G\u00f6senroth",
    "qs_pg:photos_9r":0,
    "qs_pg:photos_sr":0,
    "qs_pg:pop_sr":2,
    "qs_pg:qs_pg_placetype":"locality",
    "wof:name":"G\u00f6senroth",
    "wof:placetype":"locality",
    "wof:population":301
},
  "geometry": {"coordinates":[7.33333,49.88333],"type":"Point"}
}