{
  "type": "Feature",
  "properties": {
    "gn:admin1_code":"11.0",
    "gn:admin2_code":"0.0",
    "gn:admin3_code":"12071.0",
    "gn:admin4_code":"12071304.0",
    "gn:asciiname":"Drehnower Vorstadt",
    "gn:country_code":"DE",
    "gn:dem":60,
    "gn:feature_class":"P",
    "gn:feature_code":"PPL",
    "gn:name":"Drehnower Vorstadt",
    "gn:population":0,
    "gn:timezone":"Europe/Berlin",
    "iso:country":"DE",
    "wof:name":"Drehnower Vorstadt",
    "wof:placetype":"neighbourhood"
},
  "geometry": {"coordinates":[14.40059,51.8607],"type":"Point"}
}