{
  "type": "Feature",
  "properties": {
    "gn:admin1_code":"13",
    "gn:admin2_code":"0.0",
    "gn:admin3_code":"14625.0",
    "gn:admin4_code":"14625610.0",
    "gn:asciiname":"Grube",
    "gn:country_code":"DE",
    "gn:dem":199,
    "gn:feature_class":"P",
    "gn:feature_code":"PPL",
    "gn:name":"Grube",
    "gn:population":0,
    "gn:timezone":"Europe/Berlin",
    "iso:country":"DE",
    "name:hsb_x_preferred":[
        "Jama"
    ],
    "wof:name":"Grube",
    "wof:placetype":"neighbourhood"
},
  "geometry": {"coordinates":[14.67856,51.15508],"type":"Point"}
}