{
  "type": "Feature",
  "properties": {
    "gn:admin1_code":"2",
    "gn:admin2_code":"93.0",
    "gn:admin3_code":"9372.0",
    "gn:admin4_code":"9372157.0",
    "gn:asciiname":"Kleinschonthal",
    "gn:country_code":"DE",
    "gn:dem":459,
    "gn:feature_class":"P",
    "gn:feature_code":"PPL",
    "gn:name":"Kleinsch\u00f6nthal",
    "gn:population":0,
    "gn:timezone":"Europe/Berlin",
    "iso:country":"DE",
    "wof:name":"Kleinschonthal",
    "wof:placetype":"neighbourhood"
},
  "geometry": {"coordinates":[12.60741,49.35117],"type":"Point"}
}