{
  "type": "Feature",
  "properties": {
    "gn:admin1_code":"8",
    "gn:admin2_code":"0.0",
    "gn:admin3_code":"7336.0",
    "gn:admin4_code":"7336070.0",
    "gn:asciiname":"Mayweilerhof",
    "gn:country_code":"DE",
    "gn:dem":374,
    "gn:feature_class":"P",
    "gn:feature_code":"PPL",
    "gn:name":"Mayweilerhof",
    "gn:population":0,
    "gn:timezone":"Europe/Berlin",
    "iso:country":"DE",
    "wof:name":"Mayweilerhof",
    "wof:placetype":"neighbourhood"
},
  "geometry": {"coordinates":[7.41379,49.57189],"type":"Point"}
}