{
  "type": "Feature",
  "properties": {
    "gn:admin1_code":"13",
    "gn:admin2_code":"0.0",
    "gn:admin3_code":"14627.0",
    "gn:admin4_code":"14627130.0",
    "gn:asciiname":"Klappendorf",
    "gn:country_code":"DE",
    "gn:dem":129,
    "gn:feature_class":"P",
    "gn:feature_code":"PPL",
    "gn:name":"Klappendorf",
    "gn:population":0,
    "gn:timezone":"Europe/Berlin",
    "iso:country":"DE",
    "wof:name":"Klappendorf",
    "wof:placetype":"neighbourhood"
},
  "geometry": {"coordinates":[13.33307,51.23108],"type":"Point"}
}