{
  "type": "Feature",
  "properties": {
    "gn:admin1_code":"2",
    "gn:admin2_code":"91.0",
    "gn:admin3_code":"9175.0",
    "gn:admin4_code":"9175113.0",
    "gn:asciiname":"Gailling",
    "gn:country_code":"DE",
    "gn:dem":583,
    "gn:feature_class":"P",
    "gn:feature_code":"PPL",
    "gn:name":"Gailling",
    "gn:population":0,
    "gn:timezone":"Europe/Berlin",
    "iso:country":"DE",
    "wof:name":"Gailling",
    "wof:placetype":"neighbourhood"
},
  "geometry": {"coordinates":[11.90171,47.99096],"type":"Point"}
}