{
  "type": "Feature",
  "properties": {
    "gn:admin1_code":"8",
    "gn:admin2_code":"0.0",
    "gn:admin3_code":"7134.0",
    "gn:admin4_code":"7134058.0",
    "gn:asciiname":"Heupweiler",
    "gn:country_code":"DE",
    "gn:dem":392,
    "gn:feature_class":"P",
    "gn:feature_code":"PPL",
    "gn:name":"Heupweiler",
    "gn:population":0,
    "gn:timezone":"Europe/Berlin",
    "iso:country":"DE",
    "wof:name":"Heupweiler",
    "wof:placetype":"neighbourhood"
},
  "geometry": {"coordinates":[7.18816,49.68548],"type":"Point"}
}