{
  "type": "Feature",
  "properties": {
    "gn:admin1_code":"7.0",
    "gn:admin2_code":"51.0",
    "gn:admin3_code":"5158.0",
    "gn:admin4_code":"5158016.0",
    "gn:asciiname":"Auf dem Sand",
    "gn:country_code":"DE",
    "gn:dem":47,
    "gn:feature_class":"P",
    "gn:feature_code":"PPL",
    "gn:name":"Auf dem Sand",
    "gn:population":0,
    "gn:timezone":"Europe/Berlin",
    "iso:country":"DE",
    "wof:name":"Auf dem Sand",
    "wof:placetype":"neighbourhood"
},
  "geometry": {"coordinates":[6.91667,51.16667],"type":"Point"}
}