{
  "type": "Feature",
  "properties": {
    "gn:admin1_code":"6.0",
    "gn:admin2_code":"0.0",
    "gn:admin3_code":"3151.0",
    "gn:admin4_code":"3151011.0",
    "gn:asciiname":"Alt Isenhagen",
    "gn:country_code":"DE",
    "gn:dem":67,
    "gn:feature_class":"P",
    "gn:feature_code":"PPL",
    "gn:name":"Alt Isenhagen",
    "gn:population":0,
    "gn:timezone":"Europe/Berlin",
    "iso:country":"DE",
    "wof:name":"Alt Isenhagen",
    "wof:placetype":"neighbourhood"
},
  "geometry": {"coordinates":[10.65262,52.72954],"type":"Point"}
}