{
  "type": "Feature",
  "properties": {
    "gn:admin1_code":"12",
    "gn:admin2_code":"0.0",
    "gn:admin3_code":"13071.0",
    "gn:admin4_code":"13071163.0",
    "gn:asciiname":"Schmiedenfelde",
    "gn:country_code":"DE",
    "gn:dem":59,
    "gn:feature_class":"P",
    "gn:feature_code":"PPL",
    "gn:name":"Schmiedenfelde",
    "gn:population":0,
    "gn:timezone":"Europe/Berlin",
    "iso:country":"DE",
    "wof:name":"Schmiedenfelde",
    "wof:placetype":"neighbourhood"
},
  "geometry": {"coordinates":[13.16243,53.68144],"type":"Point"}
}