{
  "type": "Feature",
  "properties": {
    "iso:country":"DE",
    "name:cat_x_preferred":[
        "Gro\u00df Borstel"
    ],
    "name:deu_x_preferred":[
        "Gro\u00df Borstel"
    ],
    "name:dut_x_preferred":[
        "Gro\u00df Borstel"
    ],
    "name:eng_x_preferred":[
        "Gro\u00df Borstel"
    ],
    "name:fre_x_preferred":[
        "Hamburg-Gro\u00df Borstel"
    ],
    "name:ger_x_preferred":[
        "Gro\u00df Borstel"
    ],
    "name:hun_x_preferred":[
        "Gro\u00df Borstel"
    ],
    "name:ita_x_preferred":[
        "Gross Borstel"
    ],
    "name:lat_x_preferred":[
        "Hamburg-Gro\u00df Borstel"
    ],
    "name:oci_x_preferred":[
        "Gro\u00df Borstel"
    ],
    "name:pol_x_preferred":[
        "Gro\u00df Borstel"
    ],
    "name:rus_x_preferred":[
        "\u0413\u0440\u043e\u0441\u0441-\u0411\u043e\u0440\u0441\u0442\u0435\u043b\u044c"
    ],
    "name:spa_x_preferred":[
        "Gro\u00df Borstel"
    ],
    "name:tam_x_preferred":[
        "\u0bb9\u0bbe\u0bae\u0bcd\u0baa\u0bc6\u0bb0\u0bcd\u0b95\u0bcd-\u0b95\u0bbf\u0bb0\u0bca\u0baa\u0bcd \u0baa\u0bbf\u0bb0\u0bca\u0bb8\u0bcd\u0b9f\u0bc6\u0bb2\u0bcd"
    ],
    "wof:name":"Gross Borstel",
    "wof:placetype":"neighbourhood"
},
  "geometry": {"coordinates":[9.98200161299816,53.61005786401608],"type":"Point"}
}