{
  "type": "Feature",
  "properties": {
    "gn:admin1_code":"6",
    "gn:admin2_code":"0.0",
    "gn:admin3_code":"3462.0",
    "gn:admin4_code":"3462019.0",
    "gn:asciiname":"Burmoenken",
    "gn:country_code":"DE",
    "gn:dem":2,
    "gn:feature_class":"P",
    "gn:feature_code":"PPL",
    "gn:name":"Burm\u00f6nken",
    "gn:population":0,
    "gn:timezone":"Europe/Berlin",
    "iso:country":"DE",
    "wof:name":"Burmoenken",
    "wof:placetype":"neighbourhood"
},
  "geometry": {"coordinates":[7.81399,53.55291],"type":"Point"}
}