{
  "type": "Feature",
  "properties": {
    "gn:admin1_code":"5",
    "gn:admin2_code":"65.0",
    "gn:admin3_code":"6535.0",
    "gn:admin4_code":"6535014.0",
    "gn:asciiname":"Ober Breidenbach",
    "gn:country_code":"DE",
    "gn:dem":394,
    "gn:feature_class":"P",
    "gn:feature_code":"PPL",
    "gn:name":"Ober Breidenbach",
    "gn:population":0,
    "gn:timezone":"Europe/Berlin",
    "iso:country":"DE",
    "wof:name":"Ober Breidenbach",
    "wof:placetype":"neighbourhood"
},
  "geometry": {"coordinates":[9.23055,50.67766],"type":"Point"}
}