{
  "type": "Feature",
  "properties": {
    "gn:admin1_code":"2",
    "gn:admin2_code":"93.0",
    "gn:admin3_code":"9372.0",
    "gn:admin4_code":"9372161.0",
    "gn:asciiname":"Kollenzendorf",
    "gn:country_code":"DE",
    "gn:dem":407,
    "gn:feature_class":"P",
    "gn:feature_code":"PPL",
    "gn:name":"Kollenzendorf",
    "gn:population":0,
    "gn:timezone":"Europe/Berlin",
    "iso:country":"DE",
    "wof:name":"Kollenzendorf",
    "wof:placetype":"neighbourhood"
},
  "geometry": {"coordinates":[12.5491,49.25174000000001],"type":"Point"}
}