{
  "type": "Feature",
  "properties": {
    "gn:admin1_code":"1",
    "gn:admin2_code":"81.0",
    "gn:admin3_code":"8135.0",
    "gn:admin4_code":"8135010.0",
    "gn:asciiname":"Hochstatterhof",
    "gn:country_code":"DE",
    "gn:dem":582,
    "gn:feature_class":"P",
    "gn:feature_code":"PPL",
    "gn:name":"Hochstatterhof",
    "gn:population":0,
    "gn:timezone":"Europe/Berlin",
    "iso:country":"DE",
    "wof:name":"Hochstatterhof",
    "wof:placetype":"neighbourhood"
},
  "geometry": {"coordinates":[10.34869,48.72558],"type":"Point"}
}