{
  "type": "Feature",
  "properties": {
    "gn:admin1_code":"2",
    "gn:admin2_code":"94.0",
    "gn:admin3_code":"9472.0",
    "gn:admin4_code":"9472199.0",
    "gn:asciiname":"Gebhardtshof",
    "gn:country_code":"DE",
    "gn:dem":412,
    "gn:feature_class":"P",
    "gn:feature_code":"PPL",
    "gn:name":"Gebhardtshof",
    "gn:population":0,
    "gn:timezone":"Europe/Berlin",
    "iso:country":"DE",
    "wof:name":"Gebhardtshof",
    "wof:placetype":"neighbourhood"
},
  "geometry": {"coordinates":[11.68132,49.91419000000001],"type":"Point"}
}