{
  "type": "Feature",
  "properties": {
    "gn:admin1_code":"2",
    "gn:admin2_code":"94.0",
    "gn:admin3_code":"9471.0",
    "gn:admin4_code":"9471208.0",
    "gn:asciiname":"Erlau",
    "gn:country_code":"DE",
    "gn:dem":270,
    "gn:feature_class":"P",
    "gn:feature_code":"PPL",
    "gn:name":"Erlau",
    "gn:population":0,
    "gn:timezone":"Europe/Berlin",
    "iso:country":"DE",
    "name:bak_x_preferred":[
        "\u042d\u0440\u043b\u0430\u0443"
    ],
    "name:ceb_x_preferred":[
        "Erlau"
    ],
    "name:deu_x_preferred":[
        "Erlau"
    ],
    "name:epo_x_preferred":[
        "Erlau"
    ],
    "name:est_x_preferred":[
        "Erlau vald"
    ],
    "name:eus_x_preferred":[
        "Erlau"
    ],
    "name:fas_x_preferred":[
        "\u0627\u0631\u0644\u0627\u0648"
    ],
    "name:fra_x_preferred":[
        "Erlau"
    ],
    "name:glg_x_preferred":[
        "Erlau"
    ],
    "name:hun_x_preferred":[
        "Erlau"
    ],
    "name:ita_x_preferred":[
        "Erlau"
    ],
    "name:kaz_x_preferred":[
        "\u042d\u0440\u043b\u0430\u0443"
    ],
    "name:kir_x_preferred":[
        "\u042d\u0440\u043b\u0430\u0443"
    ],
    "name:mkd_x_preferred":[
        "\u0415\u0440\u043b\u0430\u0443"
    ],
    "name:msa_x_preferred":[
        "Erlau"
    ],
    "name:nld_x_preferred":[
        "Erlau"
    ],
    "name:pol_x_preferred":[
        "Erlau"
    ],
    "name:ron_x_preferred":[
        "Erlau"
    ],
    "name:rus_x_preferred":[
        "\u042d\u0440\u043b\u0430\u0443"
    ],
    "name:spa_x_preferred":[
        "Erlau"
    ],
    "name:srp_x_preferred":[
        "\u0415\u0440\u043b\u0430\u0443"
    ],
    "name:ukr_x_preferred":[
        "\u0415\u0440\u043b\u0430\u0443"
    ],
    "name:uzb_x_preferred":[
        "Erlau"
    ],
    "name:vie_x_preferred":[
        "Erlau"
    ],
    "name:vol_x_preferred":[
        "Erlau"
    ],
    "name:war_x_preferred":[
        "Erlau"
    ],
    "name:zho_x_preferred":[
        "\u57c3\u5c14\u52b3"
    ],
    "wof:name":"Erlau",
    "wof:placetype":"neighbourhood"
},
  "geometry": {"coordinates":[10.80021,49.87355],"type":"Point"}
}