{
  "type": "Feature",
  "properties": {
    "gn:population":1170,
    "iso:country":"DE",
    "name:cat_x_preferred":[
        "Engeln"
    ],
    "name:ceb_x_preferred":[
        "Engeln"
    ],
    "name:che_x_preferred":[
        "\u042d\u043d\u0433\u0435\u043b\u044c\u043d"
    ],
    "name:deu_x_preferred":[
        "Engeln"
    ],
    "name:eng_x_preferred":[
        "Engeln"
    ],
    "name:epo_x_preferred":[
        "Engeln"
    ],
    "name:fas_x_preferred":[
        "\u0627\u0646\u06af\u0644\u0646"
    ],
    "name:fra_x_preferred":[
        "Engeln"
    ],
    "name:gle_x_preferred":[
        "Engeln"
    ],
    "name:hbs_x_preferred":[
        "Engeln"
    ],
    "name:ita_x_preferred":[
        "Engeln"
    ],
    "name:kaz_x_preferred":[
        "\u042d\u043d\u0433\u0435\u043b\u044c\u043d"
    ],
    "name:kir_x_preferred":[
        "\u042d\u043d\u0433\u0435\u043b\u044c\u043d"
    ],
    "name:lld_x_preferred":[
        "Engeln"
    ],
    "name:mkd_x_preferred":[
        "\u0415\u043d\u0433\u0435\u043b\u043d"
    ],
    "name:nds_x_preferred":[
        "Engeln"
    ],
    "name:nld_x_preferred":[
        "Engeln"
    ],
    "name:nob_x_preferred":[
        "Engeln"
    ],
    "name:pol_x_preferred":[
        "Engeln"
    ],
    "name:por_x_preferred":[
        "Engeln"
    ],
    "name:ron_x_preferred":[
        "Engeln"
    ],
    "name:rus_x_preferred":[
        "\u042d\u043d\u0433\u0435\u043b\u044c\u043d"
    ],
    "name:srp_x_preferred":[
        "\u0415\u043d\u0433\u0435\u043b\u043d"
    ],
    "name:tat_x_preferred":[
        "\u042d\u043d\u0433\u0435\u043b\u044c\u043d"
    ],
    "name:uzb_x_preferred":[
        "Engeln"
    ],
    "name:vie_x_preferred":[
        "Engeln"
    ],
    "name:vol_x_preferred":[
        "Engeln"
    ],
    "name:war_x_preferred":[
        "Engeln"
    ],
    "qs:a0":"Bundesrepublik Deutschland",
    "qs:a1":"*Niedersachsen",
    "qs:a1r":"0",
    "qs:a2":"Diepholz",
    "qs:adm0":"Bundesrepublik Deutschland",
    "qs:la_lc":"*",
    "qs:level":"locality",
    "qs:loc":"Engeln",
    "qs:loc_alt":"Engeln",
    "qs:pop":0,
    "qs:type":"buffered point",
    "wd:wordcount":29,
    "wof:name":"Engeln",
    "wof:placetype":"neighbourhood",
    "wof:population":1170
},
  "geometry": {"coordinates":[8.919017,52.790656],"type":"Point"}
}