{
  "type": "Feature",
  "properties": {
    "gn:admin1_code":"7",
    "gn:admin2_code":"53.0",
    "gn:admin3_code":"5378.0",
    "gn:admin4_code":"5378024.0",
    "gn:asciiname":"Grossloederich",
    "gn:country_code":"DE",
    "gn:dem":181,
    "gn:feature_class":"P",
    "gn:feature_code":"PPL",
    "gn:name":"Gro\u00dfl\u00f6derich",
    "gn:population":0,
    "gn:timezone":"Europe/Berlin",
    "iso:country":"DE",
    "wof:name":"Grossloederich",
    "wof:placetype":"neighbourhood"
},
  "geometry": {"coordinates":[7.2284,50.93214],"type":"Point"}
}