{
  "type": "Feature",
  "properties": {
    "gn:admin1_code":"7.0",
    "gn:admin2_code":"055",
    "gn:admin3_code":"5566.0",
    "gn:admin4_code":"5566056.0",
    "gn:asciiname":"Wiehe",
    "gn:country_code":"DE",
    "gn:dem":155,
    "gn:feature_class":"P",
    "gn:feature_code":"PPL",
    "gn:name":"Wiehe",
    "gn:population":0,
    "gn:timezone":"Europe/Berlin",
    "iso:country":"DE",
    "name:ara_x_preferred":[
        "\u0641\u064a\u0647\u0647"
    ],
    "name:azb_x_preferred":[
        "\u0648\u06cc\u0647\u0647"
    ],
    "name:bak_x_preferred":[
        "\u0412\u0438\u044d"
    ],
    "name:deu_x_preferred":[
        "Wiehe"
    ],
    "name:epo_x_preferred":[
        "Wiehe"
    ],
    "name:fas_x_preferred":[
        "\u0648\u06cc\u0647\u0647"
    ],
    "name:fra_x_preferred":[
        "Wiehe"
    ],
    "name:hun_x_preferred":[
        "Wiehe"
    ],
    "name:ita_x_preferred":[
        "Wiehe"
    ],
    "name:jav_x_preferred":[
        "Wiehe"
    ],
    "name:kaz_x_preferred":[
        "\u0412\u0438\u044d"
    ],
    "name:kir_x_preferred":[
        "\u0412\u0438\u044d"
    ],
    "name:mkd_x_preferred":[
        "\u0412\u0438\u0435"
    ],
    "name:msa_x_preferred":[
        "Wiehe"
    ],
    "name:nld_x_preferred":[
        "Wiehe"
    ],
    "name:pol_x_preferred":[
        "Wiehe"
    ],
    "name:por_x_preferred":[
        "Wiehe"
    ],
    "name:ron_x_preferred":[
        "Wiehe"
    ],
    "name:rus_x_preferred":[
        "\u0412\u0438\u044d"
    ],
    "name:spa_x_preferred":[
        "Wiehe"
    ],
    "name:srp_x_preferred":[
        "\u0412\u0438\u0445\u0435"
    ],
    "name:swe_x_preferred":[
        "Wiehe"
    ],
    "name:tur_x_preferred":[
        "Wiehe"
    ],
    "name:ukr_x_preferred":[
        "\u0412\u0456\u0435"
    ],
    "name:uzb_x_preferred":[
        "Wiehe"
    ],
    "name:vie_x_preferred":[
        "Wiehe"
    ],
    "name:vol_x_preferred":[
        "Wiehe"
    ],
    "name:war_x_preferred":[
        "Wiehe"
    ],
    "wof:name":"Wiehe",
    "wof:placetype":"neighbourhood"
},
  "geometry": {"coordinates":[7.77515,52.29405],"type":"Point"}
}