{
  "type": "Feature",
  "properties": {
    "gn:admin1_code":"2",
    "gn:admin2_code":"91.0",
    "gn:admin3_code":"9172.0",
    "gn:admin4_code":"9172114.0",
    "gn:asciiname":"Marzoll",
    "gn:country_code":"DE",
    "gn:dem":466,
    "gn:feature_class":"P",
    "gn:feature_code":"PPL",
    "gn:name":"Marzoll",
    "gn:population":0,
    "gn:timezone":"Europe/Berlin",
    "iso:country":"DE",
    "wof:name":"Marzoll",
    "wof:placetype":"neighbourhood"
},
  "geometry": {"coordinates":[12.92979,47.75433],"type":"Point"}
}