{
  "type": "Feature",
  "properties": {
    "gn:admin1_code":"2",
    "gn:admin2_code":"95.0",
    "gn:admin3_code":"9576.0",
    "gn:admin4_code":"9576147.0",
    "gn:asciiname":"Wasserzell",
    "gn:country_code":"DE",
    "gn:dem":362,
    "gn:feature_class":"P",
    "gn:feature_code":"PPL",
    "gn:name":"Wasserzell",
    "gn:population":0,
    "gn:timezone":"Europe/Berlin",
    "iso:country":"DE",
    "wof:name":"Wasserzell",
    "wof:placetype":"neighbourhood"
},
  "geometry": {"coordinates":[10.95019,49.17578],"type":"Point"}
}