{
  "type": "Feature",
  "properties": {
    "gn:admin1_code":"13",
    "gn:admin2_code":"0.0",
    "gn:admin3_code":"14524.0",
    "gn:admin4_code":"14524170.0",
    "gn:asciiname":"Stenn",
    "gn:country_code":"DE",
    "gn:dem":360,
    "gn:feature_class":"P",
    "gn:feature_code":"PPL",
    "gn:name":"Stenn",
    "gn:population":0,
    "gn:timezone":"Europe/Berlin",
    "iso:country":"DE",
    "wof:name":"Stenn",
    "wof:placetype":"neighbourhood"
},
  "geometry": {"coordinates":[12.43118,50.67619000000001],"type":"Point"}
}