{
  "type": "Feature",
  "properties": {
    "gn:admin1_code":"15.0",
    "gn:admin2_code":"00",
    "gn:admin3_code":"16063.0",
    "gn:admin4_code":"16063098.0",
    "gn:asciiname":"Wolfsbehringen",
    "gn:country_code":"DE",
    "gn:dem":286,
    "gn:feature_class":"P",
    "gn:feature_code":"PPL",
    "gn:name":"Wolfsbehringen",
    "gn:population":0,
    "gn:timezone":"Europe/Berlin",
    "iso:country":"DE",
    "wof:name":"Wolfsbehringen",
    "wof:placetype":"neighbourhood"
},
  "geometry": {"coordinates":[10.49175,51.00643],"type":"Point"}
}