{
  "type": "Feature",
  "properties": {
    "gn:admin1_code":"2.0",
    "gn:admin2_code":"93.0",
    "gn:admin3_code":"9376.0",
    "gn:admin4_code":"9376146.0",
    "gn:asciiname":"Alletsried",
    "gn:country_code":"DE",
    "gn:dem":518,
    "gn:feature_class":"P",
    "gn:feature_code":"PPL",
    "gn:name":"Alletsried",
    "gn:population":0,
    "gn:timezone":"Europe/Berlin",
    "iso:country":"DE",
    "wof:name":"Alletsried",
    "wof:placetype":"neighbourhood"
},
  "geometry": {"coordinates":[12.48142,49.30997],"type":"Point"}
}