{
  "type": "Feature",
  "properties": {
    "gn:admin1_code":"7",
    "gn:admin2_code":"51.0",
    "gn:admin3_code":"5162.0",
    "gn:admin4_code":"5162008.0",
    "gn:asciiname":"Neurath",
    "gn:country_code":"DE",
    "gn:dem":75,
    "gn:feature_class":"P",
    "gn:feature_code":"PPL",
    "gn:name":"Neurath",
    "gn:population":0,
    "gn:timezone":"Europe/Berlin",
    "iso:country":"DE",
    "name:nor_x_preferred":[
        "Neurath"
    ],
    "wof:name":"Neurath",
    "wof:placetype":"neighbourhood"
},
  "geometry": {"coordinates":[6.59596,51.03912],"type":"Point"}
}