{
  "type": "Feature",
  "properties": {
    "gn:admin1_code":"1",
    "gn:admin2_code":"84.0",
    "gn:admin3_code":"8425.0",
    "gn:admin4_code":"8425002.0",
    "gn:asciiname":"Hausen ob Allmendingen",
    "gn:cc2":"DE",
    "gn:country_code":"DE",
    "gn:dem":593,
    "gn:feature_class":"P",
    "gn:feature_code":"PPL",
    "gn:name":"Hausen ob Allmendingen",
    "gn:population":0,
    "gn:timezone":"Europe/Berlin",
    "iso:country":"DE",
    "name:und_x_variant":[
        "Hausen"
    ],
    "wof:name":"Hausen ob Allmendingen",
    "wof:placetype":"neighbourhood"
},
  "geometry": {"coordinates":[9.73541,48.31248],"type":"Point"}
}