{
  "type": "Feature",
  "properties": {
    "gn:admin1_code":"2",
    "gn:admin2_code":"92.0",
    "gn:admin3_code":"9276.0",
    "gn:admin4_code":"9276116.0",
    "gn:asciiname":"Scheibe",
    "gn:country_code":"DE",
    "gn:dem":681,
    "gn:feature_class":"P",
    "gn:feature_code":"PPLL",
    "gn:name":"Scheibe",
    "gn:population":0,
    "gn:timezone":"Europe/Berlin",
    "iso:country":"DE",
    "name:ceb_x_preferred":[
        "Scheibe"
    ],
    "name:deu_x_preferred":[
        "Scheibe"
    ],
    "name:ita_x_preferred":[
        "Scheibe"
    ],
    "name:mhr_x_preferred":[
        "\u0428\u0430\u0439\u0431\u0435"
    ],
    "name:pol_x_preferred":[
        "Scheibe"
    ],
    "name:rus_x_preferred":[
        "\u0428\u0430\u0439\u0431\u0435"
    ],
    "name:swe_x_preferred":[
        "Scheibe"
    ],
    "wof:name":"Scheibe",
    "wof:placetype":"neighbourhood"
},
  "geometry": {"coordinates":[13.09459,48.89982],"type":"Point"}
}