{
  "type": "Feature",
  "properties": {
    "gn:admin1_code":"13.0",
    "gn:admin2_code":"00",
    "gn:admin3_code":"14523.0",
    "gn:admin4_code":"14523160.0",
    "gn:asciiname":"Winselburg",
    "gn:country_code":"DE",
    "gn:dem":890,
    "gn:feature_class":"P",
    "gn:feature_code":"PPL",
    "gn:name":"Winselburg",
    "gn:population":0,
    "gn:timezone":"Europe/Berlin",
    "iso:country":"DE",
    "wof:name":"Winselburg",
    "wof:placetype":"neighbourhood"
},
  "geometry": {"coordinates":[12.47098,50.41187],"type":"Point"}
}