{
  "type": "Feature",
  "properties": {
    "gn:admin1_code":"1",
    "gn:admin2_code":"84.0",
    "gn:admin3_code":"8436.0",
    "gn:admin4_code":"8436014.0",
    "gn:asciiname":"Engetweiler",
    "gn:country_code":"DE",
    "gn:dem":640,
    "gn:feature_class":"P",
    "gn:feature_code":"PPL",
    "gn:name":"Engetweiler",
    "gn:population":0,
    "gn:timezone":"Europe/Berlin",
    "iso:country":"DE",
    "wof:name":"Engetweiler",
    "wof:placetype":"neighbourhood"
},
  "geometry": {"coordinates":[9.78112,47.86124],"type":"Point"}
}