{
  "type": "Feature",
  "properties": {
    "gn:admin1_code":"5",
    "gn:admin2_code":"64.0",
    "gn:admin3_code":"6431.0",
    "gn:admin4_code":"6431017.0",
    "gn:asciiname":"Nieder-Mumbach",
    "gn:country_code":"DE",
    "gn:dem":179,
    "gn:feature_class":"P",
    "gn:feature_code":"PPL",
    "gn:name":"Nieder-Mumbach",
    "gn:population":0,
    "gn:timezone":"Europe/Berlin",
    "iso:country":"DE",
    "wof:name":"Nieder-Mumbach",
    "wof:placetype":"neighbourhood"
},
  "geometry": {"coordinates":[8.73972,49.58167],"type":"Point"}
}