{
  "type": "Feature",
  "properties": {
    "gn:admin1_code":"6",
    "gn:admin2_code":"0.0",
    "gn:admin3_code":"3351.0",
    "gn:admin4_code":"3351004.0",
    "gn:asciiname":"Dohnsen",
    "gn:country_code":"DE",
    "gn:dem":78,
    "gn:feature_class":"P",
    "gn:feature_code":"PPL",
    "gn:name":"Dohnsen",
    "gn:population":0,
    "gn:timezone":"Europe/Berlin",
    "iso:country":"DE",
    "name:ceb_x_preferred":[
        "Dohnsen"
    ],
    "name:deu_x_preferred":[
        "Dohnsen"
    ],
    "name:fas_x_preferred":[
        "\u062f\u0648\u0647\u0646\u0632\u0646"
    ],
    "wof:name":"Dohnsen",
    "wof:placetype":"neighbourhood"
},
  "geometry": {"coordinates":[10.02485,52.82165],"type":"Point"}
}