{
  "type": "Feature",
  "properties": {
    "gn:admin1_code":"10",
    "gn:admin2_code":"0.0",
    "gn:admin3_code":"1058.0",
    "gn:admin4_code":"1058035.0",
    "gn:asciiname":"Freienberg",
    "gn:country_code":"DE",
    "gn:dem":20,
    "gn:feature_class":"P",
    "gn:feature_code":"PPL",
    "gn:name":"Freienberg",
    "gn:population":0,
    "gn:timezone":"Europe/Berlin",
    "iso:country":"DE",
    "wof:name":"Freienberg",
    "wof:placetype":"neighbourhood"
},
  "geometry": {"coordinates":[9.78333,54.36666999999999],"type":"Point"}
}