{
  "type": "Feature",
  "properties": {
    "gn:admin1_code":"6",
    "gn:admin2_code":"0.0",
    "gn:admin3_code":"3256.0",
    "gn:admin4_code":"3256021.0",
    "gn:asciiname":"Lemke",
    "gn:country_code":"DE",
    "gn:dem":35,
    "gn:feature_class":"P",
    "gn:feature_code":"PPL",
    "gn:name":"Lemke",
    "gn:population":0,
    "gn:timezone":"Europe/Berlin",
    "iso:country":"DE",
    "name:deu_x_preferred":[
        "Lemke"
    ],
    "wof:name":"Lemke",
    "wof:placetype":"neighbourhood"
},
  "geometry": {"coordinates":[9.14641,52.65989],"type":"Point"}
}