{
  "type": "Feature",
  "properties": {
    "gn:admin1_code":"10",
    "gn:admin2_code":"0.0",
    "gn:admin3_code":"1054.0",
    "gn:admin4_code":"1054050.0",
    "gn:asciiname":"Mitteltritt",
    "gn:cc2":"DE",
    "gn:country_code":"DE",
    "gn:dem":3,
    "gn:feature_class":"P",
    "gn:feature_code":"PPL",
    "gn:name":"Mitteltritt",
    "gn:population":0,
    "gn:timezone":"Europe/Berlin",
    "iso:country":"DE",
    "name:und_x_variant":[
        "Mittelrittswarft",
        "Mitteltritt"
    ],
    "wof:name":"Mitteltritt",
    "wof:placetype":"neighbourhood"
},
  "geometry": {"coordinates":[8.52757,54.57014],"type":"Point"}
}