{
  "type": "Feature",
  "properties": {
    "gn:admin1_code":"1",
    "gn:admin2_code":"82.0",
    "gn:admin3_code":"8226.0",
    "gn:admin4_code":"8226027.0",
    "gn:asciiname":"Heddesbach",
    "gn:country_code":"DE",
    "gn:dem":199,
    "gn:feature_class":"P",
    "gn:feature_code":"PPLA4",
    "gn:name":"Heddesbach",
    "gn:population":518,
    "gn:timezone":"Europe/Berlin",
    "iso:country":"DE",
    "name:jpn_x_preferred":[
        "\u30d8\u30c3\u30c7\u30b9\u30d0\u30c3\u30cf"
    ],
    "name:kaz_x_preferred":[
        "\u0425\u0435\u0434\u0434\u0435\u0441\u0431\u0430\u0445"
    ],
    "name:rus_x_preferred":[
        "\u0425\u0435\u0434\u0434\u0435\u0441\u0431\u0430\u0445"
    ],
    "name:srp_x_preferred":[
        "\u0425\u0435\u0434\u0435\u0441\u0431\u0430\u0445"
    ],
    "name:ukr_x_preferred":[
        "\u0413\u0435\u0434\u0434\u0435\u0441\u0431\u0430\u0445"
    ],
    "name:zho_x_preferred":[
        "\u9ed1\u5fb7\u65af\u5df4\u8d6b"
    ],
    "wof:name":"Heddesbach",
    "wof:placetype":"locality",
    "wof:population":518
},
  "geometry": {"coordinates":[8.82806,49.48028],"type":"Point"}
}