{
  "type": "Feature",
  "properties": {
    "gn:admin1_code":"1",
    "gn:admin2_code":"82.0",
    "gn:admin3_code":"8216.0",
    "gn:admin4_code":"8216017.0",
    "gn:asciiname":"Scheuern",
    "gn:country_code":"DE",
    "gn:dem":218,
    "gn:feature_class":"P",
    "gn:feature_code":"PPL",
    "gn:name":"Scheuern",
    "gn:population":0,
    "gn:timezone":"Europe/Berlin",
    "iso:country":"DE",
    "wof:name":"Scheuern",
    "wof:placetype":"neighbourhood"
},
  "geometry": {"coordinates":[8.34694,48.75762],"type":"Point"}
}