{
  "type": "Feature",
  "properties": {
    "gn:admin1_code":"1",
    "gn:admin2_code":"82.0",
    "gn:admin3_code":"8216.0",
    "gn:admin4_code":"8216017.0",
    "gn:asciiname":"Scheuern",
    "gn:country_code":"DE",
    "gn:dem":218,
    "gn:feature_class":"P",
    "gn:feature_code":"PPL",
    "gn:name":"Scheuern",
    "gn:population":0,
    "gn:timezone":"Europe/Berlin",
    "iso:country":"DE",
    "name:ceb_x_preferred":[
        "Scheuern"
    ],
    "name:deu_x_preferred":[
        "Scheuern"
    ],
    "name:epo_x_preferred":[
        "Scheuern"
    ],
    "name:eus_x_preferred":[
        "Scheuern"
    ],
    "name:fas_x_preferred":[
        "\u0634\u0648\u06cc\u0631\u0646"
    ],
    "name:fra_x_preferred":[
        "Scheuern"
    ],
    "name:hun_x_preferred":[
        "Scheuern"
    ],
    "name:ita_x_preferred":[
        "Scheuern"
    ],
    "name:msa_x_preferred":[
        "Scheuern"
    ],
    "name:nld_x_preferred":[
        "Scheuern"
    ],
    "name:pol_x_preferred":[
        "Scheuern"
    ],
    "name:por_x_preferred":[
        "Scheuern"
    ],
    "name:ron_x_preferred":[
        "Scheuern"
    ],
    "name:rus_x_preferred":[
        "\u0428\u043e\u0439\u0435\u0440\u043d"
    ],
    "name:spa_x_preferred":[
        "Scheuern"
    ],
    "name:srp_x_preferred":[
        "\u0428\u043e\u0458\u0435\u0440\u043d"
    ],
    "name:ukr_x_preferred":[
        "\u0428\u043e\u0454\u0440\u043d"
    ],
    "name:uzb_x_preferred":[
        "Scheuern"
    ],
    "name:vie_x_preferred":[
        "Scheuern"
    ],
    "name:vol_x_preferred":[
        "Scheuern"
    ],
    "name:war_x_preferred":[
        "Scheuern"
    ],
    "name:zho_x_preferred":[
        "\u7ecd\u4f0a\u5c14\u6069"
    ],
    "wof:name":"Scheuern",
    "wof:placetype":"neighbourhood"
},
  "geometry": {"coordinates":[8.34694,48.75762],"type":"Point"}
}