{
  "type": "Feature",
  "properties": {
    "gn:admin1_code":"7",
    "gn:admin2_code":"53.0",
    "gn:admin3_code":"5374.0",
    "gn:admin4_code":"5374032.0",
    "gn:asciiname":"Malzhagen",
    "gn:country_code":"DE",
    "gn:dem":253,
    "gn:feature_class":"P",
    "gn:feature_code":"PPL",
    "gn:name":"Malzhagen",
    "gn:population":0,
    "gn:timezone":"Europe/Berlin",
    "iso:country":"DE",
    "wof:name":"Malzhagen",
    "wof:placetype":"neighbourhood"
},
  "geometry": {"coordinates":[7.57629,50.90137],"type":"Point"}
}