{
  "type": "Feature",
  "properties": {
    "gn:admin1_code":"9",
    "gn:admin2_code":"0.0",
    "gn:admin3_code":"10046.0",
    "gn:admin4_code":"10046113.0",
    "gn:asciiname":"Furschweiler",
    "gn:country_code":"DE",
    "gn:dem":357,
    "gn:feature_class":"P",
    "gn:feature_code":"PPL",
    "gn:name":"Furschweiler",
    "gn:population":0,
    "gn:timezone":"Europe/Berlin",
    "iso:country":"DE",
    "wof:name":"Furschweiler",
    "wof:placetype":"neighbourhood"
},
  "geometry": {"coordinates":[7.17888,49.51568],"type":"Point"}
}