{
  "type": "Feature",
  "properties": {
    "gn:admin1_code":"12.0",
    "gn:admin2_code":"00",
    "gn:admin3_code":"13072.0",
    "gn:admin4_code":"13072014.0",
    "gn:asciiname":"Wischuer",
    "gn:country_code":"DE",
    "gn:dem":51,
    "gn:feature_class":"P",
    "gn:feature_code":"PPL",
    "gn:name":"Wischuer",
    "gn:population":0,
    "gn:timezone":"Europe/Berlin",
    "iso:country":"DE",
    "wof:name":"Wischuer",
    "wof:placetype":"neighbourhood"
},
  "geometry": {"coordinates":[11.69469,54.09291999999999],"type":"Point"}
}