{
  "type": "Feature",
  "properties": {
    "gn:admin1_code":"6.0",
    "gn:admin2_code":"0.0",
    "gn:admin3_code":"3256.0",
    "gn:admin4_code":"3256003.0",
    "gn:asciiname":"Altenbuecken",
    "gn:country_code":"DE",
    "gn:dem":20,
    "gn:feature_class":"P",
    "gn:feature_code":"PPL",
    "gn:name":"Altenb\u00fccken",
    "gn:population":0,
    "gn:timezone":"Europe/Berlin",
    "iso:country":"DE",
    "wof:name":"Altenbuecken",
    "wof:placetype":"neighbourhood"
},
  "geometry": {"coordinates":[9.14645,52.77832],"type":"Point"}
}