{
  "type": "Feature",
  "properties": {
    "gn:admin1_code":"7",
    "gn:admin2_code":"51.0",
    "gn:admin3_code":"5166.0",
    "gn:admin4_code":"5166016.0",
    "gn:asciiname":"Dyck",
    "gn:country_code":"DE",
    "gn:dem":47,
    "gn:feature_class":"P",
    "gn:feature_code":"PPL",
    "gn:name":"Dyck",
    "gn:population":0,
    "gn:timezone":"Europe/Berlin",
    "iso:country":"DE",
    "name:und_x_variant":[
        "Dyk",
        "Dyck"
    ],
    "wof:name":"Dyck",
    "wof:placetype":"neighbourhood"
},
  "geometry": {"coordinates":[6.28862,51.28551],"type":"Point"}
}