{
  "type": "Feature",
  "properties": {
    "gn:admin1_code":"13",
    "gn:admin2_code":"0.0",
    "gn:admin3_code":"14521.0",
    "gn:admin4_code":"14521590.0",
    "gn:asciiname":"Raum",
    "gn:country_code":"DE",
    "gn:dem":481,
    "gn:feature_class":"P",
    "gn:feature_code":"PPL",
    "gn:name":"Raum",
    "gn:population":0,
    "gn:timezone":"Europe/Berlin",
    "iso:country":"DE",
    "name:fra_x_preferred":[
        "Raum"
    ],
    "name:hrv_x_preferred":[
        "Raum"
    ],
    "name:jpn_x_preferred":[
        "\u30e9\u30a6\u30e0"
    ],
    "name:pol_x_preferred":[
        "Raum"
    ],
    "name:por_x_preferred":[
        "Raum"
    ],
    "name:spa_x_preferred":[
        "Raum"
    ],
    "wof:name":"Raum",
    "wof:placetype":"neighbourhood"
},
  "geometry": {"coordinates":[12.7032,50.65876],"type":"Point"}
}