{
  "type": "Feature",
  "properties": {
    "gn:admin1_code":"11.0",
    "gn:admin2_code":"0.0",
    "gn:admin3_code":"12073.0",
    "gn:admin4_code":"12073069.0",
    "gn:asciiname":"Berkholz",
    "gn:country_code":"DE",
    "gn:dem":74,
    "gn:feature_class":"P",
    "gn:feature_code":"PPL",
    "gn:name":"Berkholz",
    "gn:population":0,
    "gn:timezone":"Europe/Berlin",
    "iso:country":"DE",
    "wof:name":"Berkholz",
    "wof:placetype":"neighbourhood"
},
  "geometry": {"coordinates":[13.66136,53.28308000000001],"type":"Point"}
}