{
  "type": "Feature",
  "properties": {
    "gn:admin1_code":"2.0",
    "gn:admin2_code":"93.0",
    "gn:admin3_code":"9373.0",
    "gn:admin4_code":"9373167.0",
    "gn:asciiname":"Albertshofen",
    "gn:country_code":"DE",
    "gn:dem":496,
    "gn:feature_class":"P",
    "gn:feature_code":"PPL",
    "gn:name":"Albertshofen",
    "gn:population":0,
    "gn:timezone":"Europe/Berlin",
    "iso:country":"DE",
    "name:ceb_x_preferred":[
        "Albertshofen"
    ],
    "name:dan_x_preferred":[
        "Albertshofen"
    ],
    "name:deu_x_preferred":[
        "Albertshofen"
    ],
    "name:epo_x_preferred":[
        "Albertshofen"
    ],
    "name:eus_x_preferred":[
        "Albertshofen"
    ],
    "name:fas_x_preferred":[
        "\u0627\u0644\u0628\u0631\u062a\u0634\u0627\u0641\u0646"
    ],
    "name:fra_x_preferred":[
        "Albertshofen"
    ],
    "name:hun_x_preferred":[
        "Albertshofen"
    ],
    "name:hye_x_preferred":[
        "\u0531\u056c\u0562\u0565\u0580\u0569\u057d\u0570\u0578\u0586\u0565\u0576"
    ],
    "name:ind_x_preferred":[
        "Albertshofen"
    ],
    "name:ita_x_preferred":[
        "Albertshofen"
    ],
    "name:lat_x_preferred":[
        "Albertshofen"
    ],
    "name:lmo_x_preferred":[
        "Albertshofen"
    ],
    "name:msa_x_preferred":[
        "Albertshofen"
    ],
    "name:nld_x_preferred":[
        "Albertshofen"
    ],
    "name:pol_x_preferred":[
        "Albertshofen"
    ],
    "name:por_x_preferred":[
        "Albertshofen"
    ],
    "name:ron_x_preferred":[
        "Albertshofen"
    ],
    "name:rus_x_preferred":[
        "\u0410\u043b\u044c\u0431\u0435\u0440\u0442\u0441\u0445\u043e\u0444\u0435\u043d"
    ],
    "name:spa_x_preferred":[
        "Albertshofen"
    ],
    "name:srp_x_preferred":[
        "\u0410\u043b\u0431\u0435\u0440\u0442\u0441\u0445\u043e\u0444\u0435\u043d"
    ],
    "name:ukr_x_preferred":[
        "\u0410\u043b\u044c\u0431\u0435\u0440\u0442\u0441\u0433\u043e\u0444\u0435\u043d"
    ],
    "name:uzb_x_preferred":[
        "Albertshofen"
    ],
    "name:vie_x_preferred":[
        "Albertshofen"
    ],
    "name:vol_x_preferred":[
        "Albertshofen"
    ],
    "name:war_x_preferred":[
        "Albertshofen"
    ],
    "name:zho_x_preferred":[
        "\u963f\u5c14\u8d1d\u5c14\u8328\u970d\u82ac"
    ],
    "wof:name":"Albertshofen",
    "wof:placetype":"neighbourhood"
},
  "geometry": {"coordinates":[11.68705,49.29955],"type":"Point"}
}