{
  "type": "Feature",
  "properties": {
    "gn:admin1_code":"2.0",
    "gn:admin2_code":"93.0",
    "gn:admin3_code":"9373.0",
    "gn:admin4_code":"9373167.0",
    "gn:asciiname":"Albertshofen",
    "gn:country_code":"DE",
    "gn:dem":496,
    "gn:feature_class":"P",
    "gn:feature_code":"PPL",
    "gn:name":"Albertshofen",
    "gn:population":0,
    "gn:timezone":"Europe/Berlin",
    "iso:country":"DE",
    "wof:name":"Albertshofen",
    "wof:placetype":"neighbourhood"
},
  "geometry": {"coordinates":[11.68705,49.29955],"type":"Point"}
}