{
  "type": "Feature",
  "properties": {
    "gn:admin1_code":"2",
    "gn:admin2_code":"95.0",
    "gn:admin3_code":"9575.0",
    "gn:admin4_code":"9575133.0",
    "gn:asciiname":"Urfersheim",
    "gn:country_code":"DE",
    "gn:dem":328,
    "gn:feature_class":"P",
    "gn:feature_code":"PPL",
    "gn:name":"Urfersheim",
    "gn:population":0,
    "gn:timezone":"Europe/Berlin",
    "iso:country":"DE",
    "wof:name":"Urfersheim",
    "wof:placetype":"neighbourhood"
},
  "geometry": {"coordinates":[10.39519,49.47121],"type":"Point"}
}