{
  "type": "Feature",
  "properties": {
    "gn:admin1_code":"2",
    "gn:admin2_code":"91.0",
    "gn:admin3_code":"9187.0",
    "gn:admin4_code":"9187176.0",
    "gn:asciiname":"Reiching",
    "gn:country_code":"DE",
    "gn:dem":481,
    "gn:feature_class":"P",
    "gn:feature_code":"PPL",
    "gn:name":"Reiching",
    "gn:population":0,
    "gn:timezone":"Europe/Berlin",
    "iso:country":"DE",
    "wof:name":"Reiching",
    "wof:placetype":"neighbourhood"
},
  "geometry": {"coordinates":[12.21319,48.12259],"type":"Point"}
}