{
  "type": "Feature",
  "properties": {
    "gn:admin1_code":"11",
    "gn:admin2_code":"0.0",
    "gn:admin3_code":"12064.0",
    "gn:admin4_code":"12064029.0",
    "gn:asciiname":"Seeberg",
    "gn:country_code":"DE",
    "gn:dem":57,
    "gn:feature_class":"P",
    "gn:feature_code":"PPL",
    "gn:name":"Seeberg",
    "gn:population":0,
    "gn:timezone":"Europe/Berlin",
    "iso:country":"DE",
    "name:als_x_preferred":[
        "Seeberg"
    ],
    "name:ceb_x_preferred":[
        "Seeberg"
    ],
    "name:deu_x_preferred":[
        "Seeberg"
    ],
    "name:epo_x_preferred":[
        "Seeberg"
    ],
    "name:eus_x_preferred":[
        "Seeberg"
    ],
    "name:fra_x_preferred":[
        "Seeberg"
    ],
    "name:ita_x_preferred":[
        "Seeberg"
    ],
    "name:kaz_x_preferred":[
        "\u0417\u0435\u0435\u0431\u0435\u0440\u0433"
    ],
    "name:lmo_x_preferred":[
        "Seeberg"
    ],
    "name:msa_x_preferred":[
        "Seeberg"
    ],
    "name:nld_x_preferred":[
        "Seeberg"
    ],
    "name:nno_x_preferred":[
        "Seeberg"
    ],
    "name:rus_x_preferred":[
        "\u0417\u0435\u0431\u0435\u0440\u0433"
    ],
    "name:spa_x_preferred":[
        "Seeberg"
    ],
    "name:sqi_x_preferred":[
        "Seeberg"
    ],
    "name:swe_x_preferred":[
        "Seeberg"
    ],
    "name:vol_x_preferred":[
        "Seeberg"
    ],
    "name:war_x_preferred":[
        "Seeberg"
    ],
    "name:zho_x_preferred":[
        "\u585e\u8c9d\u683c"
    ],
    "wof:name":"Seeberg",
    "wof:placetype":"neighbourhood"
},
  "geometry": {"coordinates":[13.68581,52.54921],"type":"Point"}
}