{
  "type": "Feature",
  "properties": {
    "gn:admin1_code":"12",
    "gn:admin2_code":"0.0",
    "gn:admin3_code":"13072.0",
    "gn:admin4_code":"13072082.0",
    "gn:asciiname":"Klein Buetzin",
    "gn:country_code":"DE",
    "gn:dem":45,
    "gn:feature_class":"P",
    "gn:feature_code":"PPL",
    "gn:name":"Klein B\u00fctzin",
    "gn:population":0,
    "gn:timezone":"Europe/Berlin",
    "iso:country":"DE",
    "wof:name":"Klein Buetzin",
    "wof:placetype":"neighbourhood"
},
  "geometry": {"coordinates":[12.45388,53.88746999999999],"type":"Point"}
}