{
  "type": "Feature",
  "properties": {
    "gn:admin1_code":"11",
    "gn:admin2_code":"0.0",
    "gn:admin3_code":"12062.0",
    "gn:admin4_code":"12062500.0",
    "gn:asciiname":"Grube Louise",
    "gn:country_code":"DE",
    "gn:dem":107,
    "gn:feature_class":"P",
    "gn:feature_code":"PPL",
    "gn:name":"Grube Louise",
    "gn:population":0,
    "gn:timezone":"Europe/Berlin",
    "iso:country":"DE",
    "wof:name":"Grube Louise",
    "wof:placetype":"neighbourhood"
},
  "geometry": {"coordinates":[13.41667,51.58333],"type":"Point"}
}