{
  "type": "Feature",
  "properties": {
    "gn:admin1_code":"1.0",
    "gn:admin2_code":"83.0",
    "gn:admin3_code":"8337.0",
    "gn:admin4_code":"8337128.0",
    "gn:asciiname":"Brenden",
    "gn:country_code":"DE",
    "gn:dem":895,
    "gn:feature_class":"P",
    "gn:feature_code":"PPL",
    "gn:name":"Brenden",
    "gn:population":0,
    "gn:timezone":"Europe/Berlin",
    "iso:country":"DE",
    "wof:name":"Brenden",
    "wof:placetype":"neighbourhood"
},
  "geometry": {"coordinates":[8.22517,47.72787],"type":"Point"}
}