{
  "type": "Feature",
  "properties": {
    "gn:country":"DE",
    "gn:fcode":"PPL",
    "gn:population":546,
    "iso:country":"DE",
    "name:bak_x_preferred":[
        "\u0412\u0430\u043d\u0433\u0435\u043d"
    ],
    "name:ceb_x_preferred":[
        "Wangen"
    ],
    "name:che_x_preferred":[
        "\u0412\u0430\u043d\u0433\u0435\u043d"
    ],
    "name:deu_x_preferred":[
        "Wangen"
    ],
    "name:eng_x_preferred":[
        "Wangen"
    ],
    "name:epo_x_preferred":[
        "Wangen"
    ],
    "name:fas_x_preferred":[
        "\u0648\u0627\u0646\u06af\u0646"
    ],
    "name:fra_x_preferred":[
        "Wangen"
    ],
    "name:kaz_x_preferred":[
        "\u0412\u0430\u043d\u0433\u0435\u043d"
    ],
    "name:kir_x_preferred":[
        "\u0412\u0430\u043d\u0433\u0435\u043d"
    ],
    "name:nld_x_preferred":[
        "Wangen"
    ],
    "name:por_x_preferred":[
        "Wangen"
    ],
    "name:ron_x_preferred":[
        "Wangen"
    ],
    "name:rus_x_preferred":[
        "\u0412\u0430\u043d\u0433\u0435\u043d"
    ],
    "name:spa_x_preferred":[
        "Wangen"
    ],
    "name:tat_x_preferred":[
        "\u0412\u0430\u043d\u0433\u0435\u043d"
    ],
    "name:und_x_variant":[
        "Gro\u00dfwangen"
    ],
    "name:uzb_x_preferred":[
        "Wangen"
    ],
    "name:vol_x_preferred":[
        "Wangen"
    ],
    "qs_pg:aaroncc":"DE",
    "qs_pg:gn_country":"DE",
    "qs_pg:gn_fcode":"PPL",
    "qs_pg:gn_pop":546,
    "qs_pg:name":"Wangen",
    "qs_pg:name_adm0":"Deutschland",
    "qs_pg:name_adm1":"Sachsen-Anhalt",
    "qs_pg:photos_9r":0,
    "qs_pg:photos_sr":0,
    "qs_pg:pop_sr":2,
    "qs_pg:qs_pg_placetype":"locality",
    "qs_pg:qs_pg_placetype_gp":"Town",
    "qs_pg:woe_adm0":23424829,
    "woe:adm0_id":23424829,
    "woe:name_adm0":"Deutschland",
    "woe:name_adm1":"Sachsen-Anhalt",
    "woe:placetype":"Town",
    "wof:name":"Wangen",
    "wof:placetype":"neighbourhood",
    "wof:population":546
},
  "geometry": {"coordinates":[11.54593,51.2695],"type":"Point"}
}