{
  "type": "Feature",
  "properties": {
    "gn:admin1_code":"2",
    "gn:admin2_code":"97.0",
    "gn:admin3_code":"9771.0",
    "gn:admin4_code":"9771129.0",
    "gn:asciiname":"Hergertswiesen",
    "gn:country_code":"DE",
    "gn:dem":535,
    "gn:feature_class":"P",
    "gn:feature_code":"PPL",
    "gn:name":"Hergertswiesen",
    "gn:population":0,
    "gn:timezone":"Europe/Berlin",
    "iso:country":"DE",
    "wof:name":"Hergertswiesen",
    "wof:placetype":"neighbourhood"
},
  "geometry": {"coordinates":[11.11502,48.33049000000001],"type":"Point"}
}