{
  "type": "Feature",
  "properties": {
    "gn:admin1_code":"10",
    "gn:admin2_code":"0.0",
    "gn:admin3_code":"1061.0",
    "gn:admin4_code":"1061023.0",
    "gn:asciiname":"Hochfeld",
    "gn:cc2":"DE",
    "gn:country_code":"DE",
    "gn:dem":-2,
    "gn:feature_class":"P",
    "gn:feature_code":"PPL",
    "gn:name":"Hochfeld",
    "gn:population":0,
    "gn:timezone":"Europe/Berlin",
    "iso:country":"DE",
    "name:ceb_x_preferred":[
        "Hochfeld"
    ],
    "name:deu_x_preferred":[
        "Hochfeld"
    ],
    "name:swe_x_preferred":[
        "Hochfeld"
    ],
    "name:und_x_variant":[
        "Hochfeldt"
    ],
    "wof:name":"Hochfeld",
    "wof:placetype":"neighbourhood"
},
  "geometry": {"coordinates":[9.37389,53.89319],"type":"Point"}
}