{
  "type": "Feature",
  "properties": {
    "gn:admin1_code":"10",
    "gn:admin2_code":"0.0",
    "gn:admin3_code":"1059.0",
    "gn:admin4_code":"1059164.0",
    "gn:asciiname":"Habernis",
    "gn:country_code":"DE",
    "gn:dem":13,
    "gn:feature_class":"P",
    "gn:feature_code":"PPL",
    "gn:name":"Habernis",
    "gn:population":0,
    "gn:timezone":"Europe/Berlin",
    "iso:country":"DE",
    "wof:name":"Habernis",
    "wof:placetype":"neighbourhood"
},
  "geometry": {"coordinates":[9.78824,54.79499000000001],"type":"Point"}
}