{
  "type": "Feature",
  "properties": {
    "gn:admin1_code":"8",
    "gn:admin2_code":"0.0",
    "gn:admin3_code":"7143.0",
    "gn:admin4_code":"7143267.0",
    "gn:asciiname":"Hanwerth",
    "gn:country_code":"DE",
    "gn:dem":273,
    "gn:feature_class":"P",
    "gn:feature_code":"PPL",
    "gn:name":"Hanwerth",
    "gn:population":0,
    "gn:timezone":"Europe/Berlin",
    "iso:country":"DE",
    "wof:name":"Hanwerth",
    "wof:placetype":"neighbourhood"
},
  "geometry": {"coordinates":[7.73834,50.65776],"type":"Point"}
}