{
  "type": "Feature",
  "properties": {
    "gn:admin1_code":"2",
    "gn:admin2_code":"95.0",
    "gn:admin3_code":"9571.0",
    "gn:admin4_code":"9571205.0",
    "gn:asciiname":"Reichelshofen",
    "gn:country_code":"DE",
    "gn:dem":420,
    "gn:feature_class":"P",
    "gn:feature_code":"PPL",
    "gn:name":"Reichelshofen",
    "gn:population":0,
    "gn:timezone":"Europe/Berlin",
    "iso:country":"DE",
    "wof:name":"Reichelshofen",
    "wof:placetype":"neighbourhood"
},
  "geometry": {"coordinates":[10.20902,49.43978],"type":"Point"}
}