{
  "type": "Feature",
  "properties": {
    "gn:admin1_code":"5",
    "gn:admin2_code":"66.0",
    "gn:admin3_code":"6631.0",
    "gn:admin4_code":"6631023.0",
    "gn:asciiname":"Schwarzenborn",
    "gn:country_code":"DE",
    "gn:dem":543,
    "gn:feature_class":"P",
    "gn:feature_code":"PPL",
    "gn:name":"Schwarzenborn",
    "gn:population":0,
    "gn:timezone":"Europe/Berlin",
    "iso:country":"DE",
    "name:ceb_x_preferred":[
        "Schwarzenborn"
    ],
    "name:deu_x_preferred":[
        "Schwarzenborn"
    ],
    "name:epo_x_preferred":[
        "Schwarzenborn"
    ],
    "name:eus_x_preferred":[
        "Schwarzenborn"
    ],
    "name:fas_x_preferred":[
        "\u0634\u0648\u0627\u0631\u062a\u0633\u0646\u0628\u0648\u0631\u0646"
    ],
    "name:fra_x_preferred":[
        "Schwarzenborn"
    ],
    "name:hun_x_preferred":[
        "Schwarzenborn"
    ],
    "name:ita_x_preferred":[
        "Schwarzenborn"
    ],
    "name:msa_x_preferred":[
        "Schwarzenborn"
    ],
    "name:nld_x_preferred":[
        "Schwarzenborn"
    ],
    "name:pol_x_preferred":[
        "Schwarzenborn"
    ],
    "name:por_x_preferred":[
        "Schwarzenborn"
    ],
    "name:ron_x_preferred":[
        "Schwarzenborn"
    ],
    "name:rus_x_preferred":[
        "\u0428\u0432\u0430\u0440\u0446\u0435\u043d\u0431\u043e\u0440\u043d"
    ],
    "name:spa_x_preferred":[
        "Schwarzenborn"
    ],
    "name:srp_x_preferred":[
        "\u0428\u0432\u0430\u0440\u0446\u0435\u043d\u0431\u043e\u0440\u043d"
    ],
    "name:ukr_x_preferred":[
        "\u0428\u0432\u0430\u0440\u0446\u0435\u043d\u0431\u043e\u0440\u043d"
    ],
    "name:uzb_x_preferred":[
        "Schwarzenborn"
    ],
    "name:vie_x_preferred":[
        "Schwarzenborn"
    ],
    "name:vol_x_preferred":[
        "Schwarzenborn"
    ],
    "name:war_x_preferred":[
        "Schwarzenborn"
    ],
    "name:zho_x_preferred":[
        "\u65bd\u74e6\u5c91\u535a\u6069"
    ],
    "wof:name":"Schwarzenborn",
    "wof:placetype":"neighbourhood"
},
  "geometry": {"coordinates":[9.96366,50.62093],"type":"Point"}
}