{
  "type": "Feature",
  "properties": {
    "gn:admin1_code":"5",
    "gn:admin2_code":"66.0",
    "gn:admin3_code":"6631.0",
    "gn:admin4_code":"6631023.0",
    "gn:asciiname":"Schwarzenborn",
    "gn:country_code":"DE",
    "gn:dem":543,
    "gn:feature_class":"P",
    "gn:feature_code":"PPL",
    "gn:name":"Schwarzenborn",
    "gn:population":0,
    "gn:timezone":"Europe/Berlin",
    "iso:country":"DE",
    "wof:name":"Schwarzenborn",
    "wof:placetype":"neighbourhood"
},
  "geometry": {"coordinates":[9.96366,50.62093],"type":"Point"}
}