{
  "type": "Feature",
  "properties": {
    "gn:admin1_code":"1.0",
    "gn:admin2_code":"83.0",
    "gn:admin3_code":"8317.0",
    "gn:admin4_code":"8317093.0",
    "gn:asciiname":"Allmend",
    "gn:country_code":"DE",
    "gn:dem":288,
    "gn:feature_class":"P",
    "gn:feature_code":"PPLL",
    "gn:name":"Allmend",
    "gn:population":0,
    "gn:timezone":"Europe/Berlin",
    "iso:country":"DE",
    "wof:name":"Allmend",
    "wof:placetype":"neighbourhood"
},
  "geometry": {"coordinates":[8.21667,48.31667],"type":"Point"}
}