{
  "type": "Feature",
  "properties": {
    "iso:country":"DE",
    "oa:elevation_ft":"1598",
    "oa:type":"small_airport",
    "woe:hierarchy":{
        "country_id":23424829,
        "county_id":12596809,
        "localadmin_id":12634396,
        "planet_id":1,
        "state_id":2345482
    },
    "wof:name":"Segelflugplatz Dinkelsb\u00fchl-sinbronn",
    "wof:placetype":"campus"
},
  "geometry": {"coordinates":[10.401,49.065],"type":"Point"}
}