{
  "type": "Feature",
  "properties": {
    "iso:country":"DE",
    "name:deu_x_preferred":[
        "Flugplatz Dinkelsb\u00fchl-Sinbronn"
    ],
    "name:eng_x_preferred":[
        "Dinkelsbuhl-Sinbronn Airport"
    ],
    "name:eng_x_variant":[
        "EDND",
        "Dinkelsb\u00fchl-Sinbronn airfield"
    ],
    "name:ind_x_preferred":[
        "Bandar Udara Dinkelsbuhl-Sinbronn"
    ],
    "name:msa_x_preferred":[
        "Lapangan Terbang Dinkelsbuhl-Sinbronn"
    ],
    "name:ron_x_preferred":[
        "Aeroportul Dinkelsbuhl-Sinbronn"
    ],
    "oa:elevation_ft":"1598",
    "oa:type":"small_airport",
    "woe:hierarchy":{
        "country_id":23424829,
        "county_id":12596809,
        "localadmin_id":12634396,
        "planet_id":1,
        "state_id":2345482
    },
    "wof:name":"Segelflugplatz Dinkelsb\u00fchl-sinbronn",
    "wof:placetype":"campus"
},
  "geometry": {"coordinates":[10.401,49.065],"type":"Point"}
}