{
  "type": "Feature",
  "properties": {
    "gn:admin1_code":"12.0",
    "gn:admin2_code":"00",
    "gn:admin3_code":"13075.0",
    "gn:admin4_code":"13075055.0",
    "gn:asciiname":"Wilhelmsthal",
    "gn:country_code":"DE",
    "gn:dem":14,
    "gn:feature_class":"P",
    "gn:feature_code":"PPL",
    "gn:name":"Wilhelmsthal",
    "gn:population":0,
    "gn:timezone":"Europe/Berlin",
    "iso:country":"DE",
    "name:ara_x_preferred":[
        "\u0641\u064a\u0644\u0647\u0644\u0645\u0633\u062a\u0622\u0644"
    ],
    "name:bar_x_preferred":[
        "Wilhelmsthal"
    ],
    "name:ceb_x_preferred":[
        "Wilhelmsthal"
    ],
    "name:dan_x_preferred":[
        "Wilhelmsthal"
    ],
    "name:deu_x_preferred":[
        "Wilhelmsthal"
    ],
    "name:epo_x_preferred":[
        "Wilhelmsthal"
    ],
    "name:eus_x_preferred":[
        "Wilhelmsthal"
    ],
    "name:fas_x_preferred":[
        "\u0648\u06cc\u0644\u0647\u0644\u0645\u0634\u062a\u0627\u0644"
    ],
    "name:fra_x_preferred":[
        "Wilhelmsthal"
    ],
    "name:hun_x_preferred":[
        "Wilhelmsthal"
    ],
    "name:hye_x_preferred":[
        "\u054e\u056b\u056c\u0570\u0565\u056c\u0574\u057d\u0569\u0561\u056c"
    ],
    "name:ita_x_preferred":[
        "Wilhelmsthal"
    ],
    "name:jpn_x_preferred":[
        "\u30f4\u30a3\u30eb\u30d8\u30eb\u30e0\u30b9\u30bf\u30fc\u30eb"
    ],
    "name:kaz_x_preferred":[
        "\u0412\u0438\u043b\u044c\u0433\u0435\u043b\u044c\u043c\u0441\u0442\u0430\u043b\u044c"
    ],
    "name:lmo_x_preferred":[
        "Wilhelmsthal"
    ],
    "name:msa_x_preferred":[
        "Wilhelmsthal"
    ],
    "name:nld_x_preferred":[
        "Wilhelmsthal"
    ],
    "name:pol_x_preferred":[
        "Wilhelmsthal"
    ],
    "name:por_x_preferred":[
        "Wilhelmsthal"
    ],
    "name:ron_x_preferred":[
        "Wilhelmsthal"
    ],
    "name:rus_x_preferred":[
        "\u0412\u0438\u043b\u044c\u0433\u0435\u043b\u044c\u043c\u0441\u0442\u0430\u043b\u044c"
    ],
    "name:spa_x_preferred":[
        "Wilhelmsthal"
    ],
    "name:srp_x_preferred":[
        "\u0412\u0438\u043b\u0445\u0435\u043b\u043c\u0441\u0442\u0430\u043b"
    ],
    "name:ukr_x_preferred":[
        "\u0412\u0456\u043b\u044c\u0433\u0435\u043b\u044c\u043c\u0441\u0442\u0430\u043b\u044c"
    ],
    "name:uzb_x_preferred":[
        "Wilhelmsthal"
    ],
    "name:vie_x_preferred":[
        "Wilhelmsthal"
    ],
    "name:vol_x_preferred":[
        "Wilhelmsthal"
    ],
    "name:war_x_preferred":[
        "Wilhelmsthal"
    ],
    "name:zho_x_preferred":[
        "\u5a01\u5ec9\u65af\u5854\u5c14"
    ],
    "wof:name":"Wilhelmsthal",
    "wof:placetype":"neighbourhood"
},
  "geometry": {"coordinates":[13.96414,53.56344],"type":"Point"}
}