{
  "type": "Feature",
  "properties": {
    "gn:admin1_code":"12.0",
    "gn:admin2_code":"00",
    "gn:admin3_code":"13075.0",
    "gn:admin4_code":"13075055.0",
    "gn:asciiname":"Wilhelmsthal",
    "gn:country_code":"DE",
    "gn:dem":14,
    "gn:feature_class":"P",
    "gn:feature_code":"PPL",
    "gn:name":"Wilhelmsthal",
    "gn:population":0,
    "gn:timezone":"Europe/Berlin",
    "iso:country":"DE",
    "wof:name":"Wilhelmsthal",
    "wof:placetype":"neighbourhood"
},
  "geometry": {"coordinates":[13.96414,53.56344],"type":"Point"}
}