{
  "type": "Feature",
  "properties": {
    "gn:admin1_code":"12",
    "gn:admin2_code":"0.0",
    "gn:admin3_code":"13073.0",
    "gn:admin4_code":"13073014.0",
    "gn:asciiname":"Stedar",
    "gn:country_code":"DE",
    "gn:dem":1,
    "gn:feature_class":"P",
    "gn:feature_code":"PPL",
    "gn:name":"Stedar",
    "gn:population":0,
    "gn:timezone":"Europe/Berlin",
    "iso:country":"DE",
    "wof:name":"Stedar",
    "wof:placetype":"neighbourhood"
},
  "geometry": {"coordinates":[13.48059,54.44521],"type":"Point"}
}