{
  "type": "Feature",
  "properties": {
    "gn:admin1_code":"7",
    "gn:admin2_code":"53.0",
    "gn:admin3_code":"5358.0",
    "gn:admin4_code":"5358024.0",
    "gn:asciiname":"Mariawald",
    "gn:country_code":"DE",
    "gn:dem":104,
    "gn:feature_class":"P",
    "gn:feature_code":"PPL",
    "gn:name":"Mariawald",
    "gn:population":0,
    "gn:timezone":"Europe/Berlin",
    "iso:country":"DE",
    "name:und_x_variant":[
        "Haus Mariawald",
        "Mariawald"
    ],
    "wof:name":"Mariawald",
    "wof:placetype":"neighbourhood"
},
  "geometry": {"coordinates":[6.38461,50.93326],"type":"Point"}
}