{
  "type": "Feature",
  "properties": {
    "iso:country":"DE",
    "name:deu_x_preferred":[
        "Flugplatz Osnabr\u00fcck-Atterheide"
    ],
    "name:eng_x_preferred":[
        "Osnabr\u00fcck-Atterheide Airport"
    ],
    "name:eng_x_variant":[
        "EDWO",
        "Osnabr\u00fcck-Atterheide airfield"
    ],
    "name:msa_x_preferred":[
        "Lapangan Terbang Atterheide"
    ],
    "oa:elevation_ft":"287",
    "oa:type":"small_airport",
    "woe:hierarchy":{
        "country_id":23424829,
        "county_id":20071102,
        "localadmin_id":12629824,
        "planet_id":1,
        "state_id":2345486
    },
    "wof:name":"Osnabruck-Atterheide Airport",
    "wof:placetype":"campus"
},
  "geometry": {"coordinates":[7.96982,52.2866],"type":"Point"}
}