{
  "type": "Feature",
  "properties": {
    "gn:admin1_code":"7",
    "gn:admin2_code":"53.0",
    "gn:admin3_code":"5374.0",
    "gn:admin4_code":"5374040.0",
    "gn:asciiname":"Eichholz",
    "gn:country_code":"DE",
    "gn:dem":340,
    "gn:feature_class":"P",
    "gn:feature_code":"PPLL",
    "gn:name":"Eichholz",
    "gn:population":0,
    "gn:timezone":"Europe/Berlin",
    "iso:country":"DE",
    "wof:name":"Eichholz",
    "wof:placetype":"neighbourhood"
},
  "geometry": {"coordinates":[7.64639,50.94469],"type":"Point"}
}