{
  "type": "Feature",
  "properties": {
    "gn:admin1_code":"6",
    "gn:admin2_code":"0.0",
    "gn:admin3_code":"3257.0",
    "gn:admin4_code":"3257036.0",
    "gn:asciiname":"Kreuzriehe",
    "gn:country_code":"DE",
    "gn:dem":58,
    "gn:feature_class":"P",
    "gn:feature_code":"PPL",
    "gn:name":"Kreuzriehe",
    "gn:population":0,
    "gn:timezone":"Europe/Berlin",
    "iso:country":"DE",
    "wof:name":"Kreuzriehe",
    "wof:placetype":"neighbourhood"
},
  "geometry": {"coordinates":[9.38678,52.3565],"type":"Point"}
}