{
  "type": "Feature",
  "properties": {
    "gn:admin1_code":"2",
    "gn:admin2_code":"93.0",
    "gn:admin3_code":"9377.0",
    "gn:admin4_code":"9377116.0",
    "gn:asciiname":"Paterlhutte",
    "gn:country_code":"DE",
    "gn:dem":557,
    "gn:feature_class":"P",
    "gn:feature_code":"PPL",
    "gn:name":"Paterlh\u00fctte",
    "gn:population":0,
    "gn:timezone":"Europe/Berlin",
    "iso:country":"DE",
    "wof:name":"Paterlhutte",
    "wof:placetype":"neighbourhood"
},
  "geometry": {"coordinates":[12.02,49.83399],"type":"Point"}
}