{
  "type": "Feature",
  "properties": {
    "gn:admin1_code":"10",
    "gn:admin2_code":"0.0",
    "gn:admin3_code":"1059.0",
    "gn:admin4_code":"1059142.0",
    "gn:asciiname":"Oehe",
    "gn:country_code":"DE",
    "gn:dem":8,
    "gn:feature_class":"P",
    "gn:feature_code":"PPL",
    "gn:name":"Oehe",
    "gn:population":0,
    "gn:timezone":"Europe/Berlin",
    "iso:country":"DE",
    "name:und_x_variant":[
        "\u00d6he",
        "Oehe"
    ],
    "wof:name":"Oehe",
    "wof:placetype":"neighbourhood"
},
  "geometry": {"coordinates":[10.00408,54.70704],"type":"Point"}
}