{
  "type": "Feature",
  "properties": {
    "gn:admin1_code":"2.0",
    "gn:admin2_code":"91.0",
    "gn:admin3_code":"9183.0",
    "gn:admin4_code":"9183139.0",
    "gn:asciiname":"Kling",
    "gn:country_code":"DE",
    "gn:dem":547,
    "gn:feature_class":"P",
    "gn:feature_code":"PPLF",
    "gn:name":"Kling",
    "gn:population":0,
    "gn:timezone":"Europe/Berlin",
    "iso:country":"DE",
    "wof:name":"Kling",
    "wof:placetype":"neighbourhood"
},
  "geometry": {"coordinates":[12.14676,48.14267],"type":"Point"}
}