{
  "type": "Feature",
  "properties": {
    "gn:admin1_code":"8",
    "gn:admin2_code":"0.0",
    "gn:admin3_code":"7131.0",
    "gn:admin4_code":"7131044.0",
    "gn:asciiname":"Leimbach",
    "gn:country_code":"DE",
    "gn:dem":271,
    "gn:feature_class":"P",
    "gn:feature_code":"PPLA4",
    "gn:name":"Leimbach",
    "gn:population":0,
    "gn:timezone":"Europe/Berlin",
    "iso:country":"DE",
    "wof:name":"Leimbach",
    "wof:placetype":"locality"
},
  "geometry": {"coordinates":[6.92774,50.40392],"type":"Point"}
}