{
  "type": "Feature",
  "properties": {
    "gn:admin1_code":"2",
    "gn:admin2_code":"97.0",
    "gn:admin3_code":"9778.0",
    "gn:admin4_code":"9778177.0",
    "gn:asciiname":"Otterwald",
    "gn:country_code":"DE",
    "gn:dem":618,
    "gn:feature_class":"P",
    "gn:feature_code":"PPL",
    "gn:name":"Otterwald",
    "gn:population":0,
    "gn:timezone":"Europe/Berlin",
    "iso:country":"DE",
    "wof:name":"Otterwald",
    "wof:placetype":"neighbourhood"
},
  "geometry": {"coordinates":[10.23376,48.06683],"type":"Point"}
}