{
  "type": "Feature",
  "properties": {
    "gn:admin1_code":"9",
    "gn:admin2_code":"0.0",
    "gn:admin3_code":"10046.0",
    "gn:admin4_code":"10046118.0",
    "gn:asciiname":"Hasborn-Dautweiler",
    "gn:country_code":"DE",
    "gn:dem":349,
    "gn:feature_class":"P",
    "gn:feature_code":"PPL",
    "gn:name":"Hasborn-Dautweiler",
    "gn:population":0,
    "gn:timezone":"Europe/Berlin",
    "iso:country":"DE",
    "name:ceb_x_preferred":[
        "Hasborn-Dautweiler"
    ],
    "name:deu_x_preferred":[
        "Hasborn-Dautweiler"
    ],
    "name:fas_x_preferred":[
        "\u0647\u0627\u0633\u0628\u0648\u0631\u0646-\u062f\u0627\u0648\u062a\u0648\u0627\u06cc\u0644\u0631"
    ],
    "name:por_x_preferred":[
        "Hasborn-Dautweiler"
    ],
    "wof:name":"Hasborn-Dautweiler",
    "wof:placetype":"neighbourhood"
},
  "geometry": {"coordinates":[6.97826,49.493],"type":"Point"}
}