{
  "type": "Feature",
  "properties": {
    "gn:country":"DE",
    "gn:fcode":"PPL",
    "gn:population":3995,
    "iso:country":"DE",
    "name:ceb_x_preferred":[
        "Fredeburg"
    ],
    "name:dan_x_preferred":[
        "Fredeburg"
    ],
    "name:deu_x_preferred":[
        "Fredeburg"
    ],
    "name:epo_x_preferred":[
        "Fredeburg"
    ],
    "name:eus_x_preferred":[
        "Fredeburg"
    ],
    "name:fas_x_preferred":[
        "\u0641\u0631\u062f\u0628\u0648\u0631\u06af"
    ],
    "name:fra_x_preferred":[
        "Fredeburg"
    ],
    "name:hun_x_preferred":[
        "Fredeburg"
    ],
    "name:ita_x_preferred":[
        "Fredeburg"
    ],
    "name:kaz_x_preferred":[
        "\u0424\u0440\u0435\u0434\u0435\u0431\u0443\u0440\u0433"
    ],
    "name:kir_x_preferred":[
        "\u0424\u0440\u0435\u0434\u0435\u0431\u0443\u0440\u0433"
    ],
    "name:mkd_x_preferred":[
        "\u0424\u0440\u0435\u0434\u0435\u0431\u0443\u0440\u0433"
    ],
    "name:msa_x_preferred":[
        "Fredeburg"
    ],
    "name:nld_x_preferred":[
        "Fredeburg"
    ],
    "name:nor_x_preferred":[
        "Fredeburg"
    ],
    "name:pol_x_preferred":[
        "Fredeburg"
    ],
    "name:por_x_preferred":[
        "Fredeburg"
    ],
    "name:ron_x_preferred":[
        "Fredeburg"
    ],
    "name:rus_x_preferred":[
        "\u0424\u0440\u0435\u0434\u0435\u0431\u0443\u0440\u0433"
    ],
    "name:spa_x_preferred":[
        "Fredeburgo"
    ],
    "name:srp_x_preferred":[
        "\u0424\u0440\u0435\u0434\u0435\u0431\u0443\u0440\u0433"
    ],
    "name:tur_x_preferred":[
        "Fredeburg"
    ],
    "name:ukr_x_preferred":[
        "\u0424\u0440\u0435\u0434\u0435\u0431\u0443\u0440\u0433"
    ],
    "name:uzb_x_preferred":[
        "Fredeburg"
    ],
    "name:vie_x_preferred":[
        "Fredeburg"
    ],
    "name:vol_x_preferred":[
        "Fredeburg"
    ],
    "name:war_x_preferred":[
        "Fredeburg"
    ],
    "name:zho_x_preferred":[
        "\u5f17\u96f7\u5fb7\u5821"
    ],
    "qs_pg:aaroncc":"DE",
    "qs_pg:gn_country":"DE",
    "qs_pg:gn_fcode":"PPL",
    "qs_pg:gn_pop":3995,
    "qs_pg:name":"Fredeburg",
    "qs_pg:name_adm0":"Deutschland",
    "qs_pg:name_adm1":"Nordrhein-Westfalen",
    "qs_pg:photos_9k":1,
    "qs_pg:photos_9r":1,
    "qs_pg:photos_all":17,
    "qs_pg:photos_sr":0,
    "qs_pg:pop_sr":4,
    "qs_pg:qs_pg_placetype":"locality",
    "qs_pg:qs_pg_placetype_gp":"Town",
    "qs_pg:woe_adm0":23424829,
    "woe:adm0_id":23424829,
    "woe:name_adm0":"Deutschland",
    "woe:name_adm1":"Nordrhein-Westfalen",
    "woe:placetype":"Town",
    "wof:name":"Fredeburg",
    "wof:placetype":"neighbourhood",
    "wof:population":3995
},
  "geometry": {"coordinates":[8.30978,51.1893],"type":"Point"}
}