{
  "type": "Feature",
  "properties": {
    "gn:admin1_code":"2",
    "gn:admin2_code":"92.0",
    "gn:admin3_code":"9277.0",
    "gn:admin4_code":"9277152.0",
    "gn:asciiname":"Holzen",
    "gn:country_code":"DE",
    "gn:dem":482,
    "gn:feature_class":"P",
    "gn:feature_code":"PPL",
    "gn:name":"Holzen",
    "gn:population":0,
    "gn:timezone":"Europe/Berlin",
    "iso:country":"DE",
    "name:ceb_x_preferred":[
        "Holzen"
    ],
    "name:dan_x_preferred":[
        "Holzen"
    ],
    "name:deu_x_preferred":[
        "Holzen"
    ],
    "name:epo_x_preferred":[
        "Holzen"
    ],
    "name:est_x_preferred":[
        "Holzen"
    ],
    "name:eus_x_preferred":[
        "Holzen"
    ],
    "name:fas_x_preferred":[
        "\u0647\u0648\u0644\u062a\u0633\u0646"
    ],
    "name:fra_x_preferred":[
        "Holzen"
    ],
    "name:hun_x_preferred":[
        "Holzen"
    ],
    "name:ita_x_preferred":[
        "Holzen"
    ],
    "name:jpn_x_preferred":[
        "\u30db\u30eb\u30c4\u30a7\u30f3"
    ],
    "name:kaz_x_preferred":[
        "\u0425\u043e\u043b\u044c\u0446\u0435\u043d"
    ],
    "name:kir_x_preferred":[
        "\u0425\u043e\u043b\u044c\u0446\u0435\u043d"
    ],
    "name:lat_x_preferred":[
        "Holzen"
    ],
    "name:mkd_x_preferred":[
        "\u0425\u043e\u043b\u0446\u0435\u043d"
    ],
    "name:msa_x_preferred":[
        "Holzen"
    ],
    "name:nld_x_preferred":[
        "Holzen"
    ],
    "name:pol_x_preferred":[
        "Holzen"
    ],
    "name:por_x_preferred":[
        "Holzen"
    ],
    "name:ron_x_preferred":[
        "Holzen"
    ],
    "name:rus_x_preferred":[
        "\u0425\u043e\u043b\u044c\u0446\u0435\u043d"
    ],
    "name:spa_x_preferred":[
        "Holzen"
    ],
    "name:srp_x_preferred":[
        "\u0425\u043e\u043b\u0446\u0435\u043d"
    ],
    "name:ukr_x_preferred":[
        "\u0413\u043e\u043b\u044c\u0446\u0435\u043d"
    ],
    "name:uzb_x_preferred":[
        "Holzen"
    ],
    "name:vie_x_preferred":[
        "Holzen"
    ],
    "name:vol_x_preferred":[
        "Holzen"
    ],
    "name:war_x_preferred":[
        "Holzen"
    ],
    "name:zho_x_preferred":[
        "\u970d\u5c14\u5c91"
    ],
    "wof:name":"Holzen",
    "wof:placetype":"neighbourhood"
},
  "geometry": {"coordinates":[12.9898,48.33424],"type":"Point"}
}