{
  "type": "Feature",
  "properties": {
    "gn:admin1_code":"8",
    "gn:admin2_code":"0.0",
    "gn:admin3_code":"7318.0",
    "gn:admin4_code":"7318000.0",
    "gn:asciiname":"Rinkenbergerhof",
    "gn:country_code":"DE",
    "gn:dem":106,
    "gn:feature_class":"P",
    "gn:feature_code":"PPL",
    "gn:name":"Rinkenbergerhof",
    "gn:population":0,
    "gn:timezone":"Europe/Berlin",
    "iso:country":"DE",
    "wof:name":"Rinkenbergerhof",
    "wof:placetype":"neighbourhood"
},
  "geometry": {"coordinates":[8.41667,49.35],"type":"Point"}
}