{
  "type": "Feature",
  "properties": {
    "gn:admin1_code":"2.0",
    "gn:admin2_code":"91.0",
    "gn:admin3_code":"9175.0",
    "gn:admin4_code":"9175122.0",
    "gn:asciiname":"Grafing Bahnhof",
    "gn:country_code":"DE",
    "gn:dem":542,
    "gn:feature_class":"P",
    "gn:feature_code":"PPL",
    "gn:name":"Grafing Bahnhof",
    "gn:population":0,
    "gn:timezone":"Europe/Berlin",
    "iso:country":"DE",
    "wof:name":"Grafing Bahnhof",
    "wof:placetype":"neighbourhood"
},
  "geometry": {"coordinates":[11.94197,48.04378],"type":"Point"}
}