{
  "type": "Feature",
  "properties": {
    "gn:admin1_code":"2.0",
    "gn:admin2_code":"91.0",
    "gn:admin3_code":"9178.0",
    "gn:admin4_code":"9178144.0",
    "gn:asciiname":"Baumgarten",
    "gn:country_code":"DE",
    "gn:dem":503,
    "gn:feature_class":"P",
    "gn:feature_code":"PPL",
    "gn:name":"Baumgarten",
    "gn:population":0,
    "gn:timezone":"Europe/Berlin",
    "iso:country":"DE",
    "wof:name":"Baumgarten",
    "wof:placetype":"neighbourhood"
},
  "geometry": {"coordinates":[11.82532,48.52727],"type":"Point"}
}