{
  "type": "Feature",
  "properties": {
    "gn:admin1_code":"2.0",
    "gn:admin2_code":"91.0",
    "gn:admin3_code":"9178.0",
    "gn:admin4_code":"9178144.0",
    "gn:asciiname":"Baumgarten",
    "gn:country_code":"DE",
    "gn:dem":503,
    "gn:feature_class":"P",
    "gn:feature_code":"PPL",
    "gn:name":"Baumgarten",
    "gn:population":0,
    "gn:timezone":"Europe/Berlin",
    "iso:country":"DE",
    "name:bel_x_preferred":[
        "\u0411\u0430\u045e\u043c\u0433\u0430\u0440\u0442\u044d\u043d"
    ],
    "name:ceb_x_preferred":[
        "Baumgarten"
    ],
    "name:ces_x_preferred":[
        "Baumgarten"
    ],
    "name:deu_x_preferred":[
        "Baumgarten"
    ],
    "name:epo_x_preferred":[
        "Baumgarten"
    ],
    "name:fra_x_preferred":[
        "Baumgarten"
    ],
    "name:heb_x_preferred":[
        "\u05d1\u05d0\u05d5\u05de\u05d2\u05e8\u05d8\u05df"
    ],
    "name:hun_x_preferred":[
        "Baumgarten"
    ],
    "name:ita_x_preferred":[
        "Baumgarten"
    ],
    "name:kat_x_preferred":[
        "\u10d1\u10d0\u10e3\u10db\u10d2\u10d0\u10e0\u10e2\u10d4\u10dc\u10d8"
    ],
    "name:mkd_x_preferred":[
        "\u0411\u0430\u0443\u043c\u0433\u0430\u0440\u0442\u0435\u043d"
    ],
    "name:nds_x_preferred":[
        "Baumgarten"
    ],
    "name:nld_x_preferred":[
        "Baumgarten"
    ],
    "name:pol_x_preferred":[
        "Baumgarten"
    ],
    "name:ron_x_preferred":[
        "Baumgarten"
    ],
    "name:rus_x_preferred":[
        "\u0411\u0430\u0443\u043c\u0433\u0430\u0440\u0442\u0435\u043d"
    ],
    "name:swe_x_preferred":[
        "Baumgarten"
    ],
    "name:vol_x_preferred":[
        "Baumgarten"
    ],
    "wof:name":"Baumgarten",
    "wof:placetype":"neighbourhood"
},
  "geometry": {"coordinates":[11.82532,48.52727],"type":"Point"}
}