{
  "type": "Feature",
  "properties": {
    "gn:admin1_code":"1",
    "gn:admin2_code":"84.0",
    "gn:admin3_code":"8435.0",
    "gn:admin4_code":"8435052.0",
    "gn:asciiname":"Rickenbach",
    "gn:country_code":"DE",
    "gn:dem":456,
    "gn:feature_class":"P",
    "gn:feature_code":"PPL",
    "gn:name":"Rickenbach",
    "gn:population":0,
    "gn:timezone":"Europe/Berlin",
    "iso:country":"DE",
    "name:als_x_preferred":[
        "Rickenbach"
    ],
    "name:ceb_x_preferred":[
        "Rickenbach"
    ],
    "name:deu_x_preferred":[
        "Rickenbach"
    ],
    "name:epo_x_preferred":[
        "Rickenbach"
    ],
    "name:eus_x_preferred":[
        "Rickenbach"
    ],
    "name:fra_x_preferred":[
        "Rickenbach"
    ],
    "name:ita_x_preferred":[
        "Rickenbach"
    ],
    "name:lmo_x_preferred":[
        "Rickenbach"
    ],
    "name:nld_x_preferred":[
        "Rickenbach"
    ],
    "name:pol_x_preferred":[
        "Rickenbach"
    ],
    "name:por_x_preferred":[
        "Rickenbach"
    ],
    "name:rus_x_preferred":[
        "\u0420\u0438\u043a\u043a\u0435\u043d\u0431\u0430\u0445"
    ],
    "name:spa_x_preferred":[
        "Rickenbach"
    ],
    "name:swe_x_preferred":[
        "Rickenbach"
    ],
    "name:vol_x_preferred":[
        "Rickenbach"
    ],
    "wof:name":"Rickenbach",
    "wof:placetype":"neighbourhood"
},
  "geometry": {"coordinates":[9.26025,47.79474],"type":"Point"}
}