{
  "type": "Feature",
  "properties": {
    "gn:admin1_code":"12",
    "gn:admin2_code":"0.0",
    "gn:admin3_code":"13073.0",
    "gn:admin4_code":"13073017.0",
    "gn:asciiname":"Hof Koerkwitz",
    "gn:country_code":"DE",
    "gn:dem":1,
    "gn:feature_class":"P",
    "gn:feature_code":"PPL",
    "gn:name":"Hof K\u00f6rkwitz",
    "gn:population":0,
    "gn:timezone":"Europe/Berlin",
    "iso:country":"DE",
    "name:und_x_variant":[
        "K\u00f6rkwitz-Hof",
        "Hof K\u00f6rkwitz"
    ],
    "wof:name":"Hof Koerkwitz",
    "wof:placetype":"neighbourhood"
},
  "geometry": {"coordinates":[12.35397,54.26053],"type":"Point"}
}