{
  "type": "Feature",
  "properties": {
    "gn:country":"DE",
    "gn:fcode":"PPL",
    "gn:population":0,
    "iso:country":"DE",
    "name:ceb_x_preferred":[
        "Wenden"
    ],
    "name:deu_x_preferred":[
        "Wenden"
    ],
    "name:epo_x_preferred":[
        "Wenden"
    ],
    "name:ita_x_preferred":[
        "Wenden"
    ],
    "name:nld_x_preferred":[
        "Wenden"
    ],
    "name:pol_x_preferred":[
        "Wenden"
    ],
    "name:por_x_preferred":[
        "Wenden"
    ],
    "name:srp_x_preferred":[
        "\u0412\u0435\u043d\u0434\u0438"
    ],
    "name:ukr_x_preferred":[
        "\u0412\u0435\u043d\u0434\u0435\u043d"
    ],
    "name:vol_x_preferred":[
        "Wenden"
    ],
    "qs_pg:aaroncc":"DE",
    "qs_pg:gn_country":"DE",
    "qs_pg:gn_fcode":"PPL",
    "qs_pg:gn_pop":0,
    "qs_pg:name":"Wenden",
    "qs_pg:name_adm0":"Deutschland",
    "qs_pg:name_adm1":"Niedersachsen",
    "qs_pg:photos_9r":0,
    "qs_pg:photos_sr":0,
    "qs_pg:pop_sr":0,
    "qs_pg:qs_pg_placetype":"neighbourhood",
    "qs_pg:qs_pg_placetype_gp":"Suburb",
    "qs_pg:woe_adm0":23424829,
    "woe:adm0_id":23424829,
    "woe:name_adm0":"Deutschland",
    "woe:name_adm1":"Niedersachsen",
    "woe:placetype":"Suburb",
    "wof:name":"Wenden",
    "wof:placetype":"neighbourhood"
},
  "geometry": {"coordinates":[10.51392,52.32401],"type":"Point"}
}