{
  "type": "Feature",
  "properties": {
    "gn:admin1_code":"14",
    "gn:admin2_code":"0.0",
    "gn:admin3_code":"15084.0",
    "gn:admin4_code":"15084442.0",
    "gn:asciiname":"Hohenkirchen",
    "gn:country_code":"DE",
    "gn:dem":265,
    "gn:feature_class":"P",
    "gn:feature_code":"PPL",
    "gn:name":"Hohenkirchen",
    "gn:population":0,
    "gn:timezone":"Europe/Berlin",
    "iso:country":"DE",
    "name:ceb_x_preferred":[
        "Hohenkirchen"
    ],
    "name:deu_x_preferred":[
        "Hohenkirchen"
    ],
    "name:epo_x_preferred":[
        "Hohenkirchen"
    ],
    "name:fas_x_preferred":[
        "\u0647\u0648\u0647\u0646\u06a9\u06cc\u0631\u0634\u0646"
    ],
    "name:fra_x_preferred":[
        "Hohenkirchen"
    ],
    "name:hun_x_preferred":[
        "Hohenkirchen"
    ],
    "name:ita_x_preferred":[
        "Hohenkirchen"
    ],
    "name:kaz_x_preferred":[
        "\u0425\u043e\u044d\u043d\u043a\u0438\u0440\u0445\u0435\u043d"
    ],
    "name:kir_x_preferred":[
        "\u0425\u043e\u044d\u043d\u043a\u0438\u0440\u0445\u0435\u043d"
    ],
    "name:mkd_x_preferred":[
        "\u0425\u043e\u0435\u043d\u043a\u0438\u0440\u0445\u0435\u043d"
    ],
    "name:msa_x_preferred":[
        "Hohenkirchen"
    ],
    "name:nld_x_preferred":[
        "Hohenkirchen"
    ],
    "name:pol_x_preferred":[
        "Hohenkirchen"
    ],
    "name:por_x_preferred":[
        "Hohenkirchen"
    ],
    "name:ron_x_preferred":[
        "Hohenkirchen"
    ],
    "name:rus_x_preferred":[
        "\u0425\u043e\u044d\u043d\u043a\u0438\u0440\u0445\u0435\u043d"
    ],
    "name:spa_x_preferred":[
        "Hohenkirchen"
    ],
    "name:srp_x_preferred":[
        "\u0425\u043e\u0435\u043d\u043a\u0438\u0440\u0445\u0435\u043d"
    ],
    "name:ukr_x_preferred":[
        "\u0413\u043e\u0435\u043d\u043a\u0456\u0440\u0445\u0435\u043d"
    ],
    "name:uzb_x_preferred":[
        "Hohenkirchen"
    ],
    "name:vie_x_preferred":[
        "Hohenkirchen"
    ],
    "name:vol_x_preferred":[
        "Hohenkirchen"
    ],
    "name:war_x_preferred":[
        "Hohenkirchen"
    ],
    "name:zho_x_preferred":[
        "\u970d\u6069\u57fa\u5174"
    ],
    "wof:name":"Hohenkirchen",
    "wof:placetype":"neighbourhood"
},
  "geometry": {"coordinates":[12.21976,50.94859],"type":"Point"}
}