{
  "type": "Feature",
  "properties": {
    "gn:admin1_code":"14",
    "gn:admin2_code":"0.0",
    "gn:admin3_code":"15084.0",
    "gn:admin4_code":"15084442.0",
    "gn:asciiname":"Hohenkirchen",
    "gn:country_code":"DE",
    "gn:dem":265,
    "gn:feature_class":"P",
    "gn:feature_code":"PPL",
    "gn:name":"Hohenkirchen",
    "gn:population":0,
    "gn:timezone":"Europe/Berlin",
    "iso:country":"DE",
    "wof:name":"Hohenkirchen",
    "wof:placetype":"neighbourhood"
},
  "geometry": {"coordinates":[12.21976,50.94859],"type":"Point"}
}