{
  "type": "Feature",
  "properties": {
    "gn:admin1_code":"14",
    "gn:admin2_code":"0.0",
    "gn:admin3_code":"15084.0",
    "gn:admin4_code":"15084275.0",
    "gn:asciiname":"Groitzschen",
    "gn:country_code":"DE",
    "gn:dem":176,
    "gn:feature_class":"P",
    "gn:feature_code":"PPL",
    "gn:name":"Groitzschen",
    "gn:population":0,
    "gn:timezone":"Europe/Berlin",
    "iso:country":"DE",
    "wof:name":"Groitzschen",
    "wof:placetype":"neighbourhood"
},
  "geometry": {"coordinates":[12.08241,51.06447],"type":"Point"}
}