{
  "type": "Feature",
  "properties": {
    "gn:admin1_code":"10",
    "gn:admin2_code":"0.0",
    "gn:admin3_code":"1051.0",
    "gn:admin4_code":"1051107.0",
    "gn:asciiname":"Dollenburen",
    "gn:country_code":"DE",
    "gn:dem":0,
    "gn:feature_class":"P",
    "gn:feature_code":"PPL",
    "gn:name":"Dollenburen",
    "gn:population":0,
    "gn:timezone":"Europe/Berlin",
    "iso:country":"DE",
    "wof:name":"Dollenburen",
    "wof:placetype":"neighbourhood"
},
  "geometry": {"coordinates":[9.06667,54.25],"type":"Point"}
}