{
  "type": "Feature",
  "properties": {
    "gn:admin1_code":"1",
    "gn:admin2_code":"81.0",
    "gn:admin3_code":"8127.0",
    "gn:admin4_code":"8127046.0",
    "gn:asciiname":"Gaggstatt",
    "gn:country_code":"DE",
    "gn:dem":390,
    "gn:feature_class":"P",
    "gn:feature_code":"PPL",
    "gn:name":"Gaggstatt",
    "gn:population":0,
    "gn:timezone":"Europe/Berlin",
    "iso:country":"DE",
    "wof:name":"Gaggstatt",
    "wof:placetype":"neighbourhood"
},
  "geometry": {"coordinates":[10.00636,49.2188],"type":"Point"}
}