{
  "type": "Feature",
  "properties": {
    "gn:admin1_code":"7",
    "gn:admin2_code":"53.0",
    "gn:admin3_code":"5374.0",
    "gn:admin4_code":"5374048.0",
    "gn:asciiname":"Dreisbach",
    "gn:country_code":"DE",
    "gn:dem":217,
    "gn:feature_class":"P",
    "gn:feature_code":"PPL",
    "gn:name":"Dreisbach",
    "gn:population":0,
    "gn:timezone":"Europe/Berlin",
    "iso:country":"DE",
    "name:ceb_x_preferred":[
        "Dreisbach"
    ],
    "name:deu_x_preferred":[
        "Dreisbach"
    ],
    "name:pol_x_preferred":[
        "Dreisbach"
    ],
    "name:rus_x_preferred":[
        "\u0414\u0440\u0430\u0439\u0441\u0431\u0430\u0445"
    ],
    "name:swe_x_preferred":[
        "Dreisbach"
    ],
    "wof:name":"Dreisbach",
    "wof:placetype":"neighbourhood"
},
  "geometry": {"coordinates":[7.59331,50.95272],"type":"Point"}
}