{
  "type": "Feature",
  "properties": {
    "gn:admin1_code":"7.0",
    "gn:admin2_code":"51.0",
    "gn:admin3_code":"5162.0",
    "gn:admin4_code":"5162008.0",
    "gn:asciiname":"Huelchrath",
    "gn:country_code":"DE",
    "gn:dem":45,
    "gn:feature_class":"P",
    "gn:feature_code":"PPL",
    "gn:name":"H\u00fclchrath",
    "gn:population":0,
    "gn:timezone":"Europe/Berlin",
    "iso:country":"DE",
    "name:deu_x_preferred":[
        "Stadt H\u00fclchrath"
    ],
    "name:epo_x_preferred":[
        "H\u00fclchrath"
    ],
    "name:nld_x_preferred":[
        "H\u00fclchrath"
    ],
    "wof:name":"Huelchrath",
    "wof:placetype":"neighbourhood"
},
  "geometry": {"coordinates":[6.66132,51.12551],"type":"Point"}
}