{
  "type": "Feature",
  "properties": {
    "gn:admin1_code":"2",
    "gn:admin2_code":"91.0",
    "gn:admin3_code":"9180.0",
    "gn:admin4_code":"9180132.0",
    "gn:asciiname":"Riedhausen",
    "gn:country_code":"DE",
    "gn:dem":696,
    "gn:feature_class":"P",
    "gn:feature_code":"PPL",
    "gn:name":"Riedhausen",
    "gn:population":0,
    "gn:timezone":"Europe/Berlin",
    "iso:country":"DE",
    "name:als_x_preferred":[
        "Riedhausen"
    ],
    "name:ceb_x_preferred":[
        "Riedhausen"
    ],
    "name:deu_x_preferred":[
        "Riedhausen"
    ],
    "name:epo_x_preferred":[
        "Riedhausen"
    ],
    "name:eus_x_preferred":[
        "Riedhausen"
    ],
    "name:fas_x_preferred":[
        "\u0631\u06cc\u062f\u0647\u0627\u0648\u0632\u0646"
    ],
    "name:fra_x_preferred":[
        "Riedhausen"
    ],
    "name:hun_x_preferred":[
        "Riedhausen"
    ],
    "name:ita_x_preferred":[
        "Riedhausen"
    ],
    "name:lat_x_preferred":[
        "Riedhausen"
    ],
    "name:lmo_x_preferred":[
        "Riedhausen"
    ],
    "name:nld_x_preferred":[
        "Riedhausen"
    ],
    "name:pol_x_preferred":[
        "Riedhausen"
    ],
    "name:por_x_preferred":[
        "Riedhausen"
    ],
    "name:ron_x_preferred":[
        "Riedhausen"
    ],
    "name:rus_x_preferred":[
        "\u0420\u0438\u0434\u0445\u0430\u0443\u0437\u0435\u043d"
    ],
    "name:spa_x_preferred":[
        "Riedhausen"
    ],
    "name:srp_x_preferred":[
        "\u0420\u0438\u0434\u0445\u0430\u0443\u0437\u0435\u043d"
    ],
    "name:ukr_x_preferred":[
        "\u0420\u0456\u0434\u0433\u0430\u0443\u0437\u0435\u043d"
    ],
    "name:uzb_x_preferred":[
        "Riedhausen"
    ],
    "name:vie_x_preferred":[
        "Riedhausen"
    ],
    "name:vol_x_preferred":[
        "Riedhausen"
    ],
    "name:war_x_preferred":[
        "Riedhausen"
    ],
    "name:zho_x_preferred":[
        "\u91cc\u5fb7\u8c6a\u68ee"
    ],
    "wof:name":"Riedhausen",
    "wof:placetype":"neighbourhood"
},
  "geometry": {"coordinates":[11.1955,47.68821],"type":"Point"}
}