{
  "type": "Feature",
  "properties": {
    "iso:country":"DE",
    "name:deu_x_colloquial":[
        "Woelfnitz",
        "Wolfnitz"
    ],
    "name:deu_x_preferred":[
        "W\u00f6lfnitz"
    ],
    "name:eng_x_preferred":[
        "W\u00f6lfnitz"
    ],
    "name:unk_x_variant":[
        "W\u00f6lfnitz"
    ],
    "qs:gn_fcode":"PPL",
    "qs:gn_local":0,
    "qs:gn_namadm1":"13",
    "qs:gn_name":"W\u00f6lfnitz",
    "qs:local_max":13108,
    "qs:local_sum":52556,
    "qs:localhoods":61,
    "qs:name":"W\u00f6lfnitz",
    "qs:name_adm0":"Deutschland",
    "qs:name_adm1":"Sachsen",
    "qs:name_adm2":"Kreisfreie Stadt Dresden",
    "qs:name_lau":"Gorbitz-Ost",
    "qs:name_local":"Dresden",
    "qs:photo_max":5,
    "qs:photo_sum":9,
    "qs:placetype":"Suburb",
    "qs:quad_count":2,
    "qs:woe_adm0":23424829,
    "qs:woe_adm1":2345493,
    "qs:woe_adm2":12596943,
    "qs:woe_lau":26822136,
    "qs:woe_local":645686,
    "qs:woe_ver":"7.10.0",
    "wof:lang":[
        "ger"
    ],
    "wof:name":"Woelfnitz",
    "wof:placetype":"neighbourhood"
},
  "geometry": {"coordinates":[13.67836,51.040519],"type":"Point"}
}