{
  "type": "Feature",
  "properties": {
    "gn:admin1_code":"2",
    "gn:admin2_code":"92.0",
    "gn:admin3_code":"9273.0",
    "gn:admin4_code":"9273152.0",
    "gn:asciiname":"Schwaig",
    "gn:country_code":"DE",
    "gn:dem":354,
    "gn:feature_class":"P",
    "gn:feature_code":"PPL",
    "gn:name":"Schwaig",
    "gn:population":0,
    "gn:timezone":"Europe/Berlin",
    "iso:country":"DE",
    "name:ceb_x_preferred":[
        "Schwaig b.N\u00fcrnberg"
    ],
    "name:eus_x_preferred":[
        "Schwaig"
    ],
    "name:hye_x_preferred":[
        "\u0547\u057e\u0561\u0575\u0563 \u0546\u0575\u0578\u0582\u0580\u0576\u0562\u0565\u0580\u0563"
    ],
    "name:ind_x_preferred":[
        "Schwaig"
    ],
    "name:kaz_x_preferred":[
        "\u0428\u0432\u0430\u0439\u0433-\u041d\u044e\u0440\u043d\u0431\u0435\u0440\u0433"
    ],
    "name:kir_x_preferred":[
        "\u0428\u0432\u0430\u0439\u0433-\u041d\u044e\u0440\u043d\u0431\u0435\u0440\u0433"
    ],
    "name:msa_x_preferred":[
        "Schwaig"
    ],
    "name:por_x_preferred":[
        "Schwaig"
    ],
    "name:rus_x_preferred":[
        "\u0428\u0432\u0430\u0439\u0433-\u0431\u0430\u0439-\u041d\u044e\u0440\u043d\u0431\u0435\u0440\u0433"
    ],
    "name:spa_x_preferred":[
        "Schwaig"
    ],
    "name:ukr_x_preferred":[
        "\u0428\u0432\u0430\u0439\u0433"
    ],
    "name:vie_x_preferred":[
        "Schwaig"
    ],
    "name:war_x_preferred":[
        "Schwaig"
    ],
    "name:zho_x_preferred":[
        "\u7ebd\u4f26\u5821\u9644\u8fd1\u65bd\u9b4f\u683c"
    ],
    "wof:name":"Schwaig",
    "wof:placetype":"neighbourhood"
},
  "geometry": {"coordinates":[11.70387,48.7695],"type":"Point"}
}