{
  "type": "Feature",
  "properties": {
    "gn:admin1_code":"7",
    "gn:admin2_code":"53.0",
    "gn:admin3_code":"5358.0",
    "gn:admin4_code":"5358044.0",
    "gn:asciiname":"Kommerscheidt",
    "gn:country_code":"DE",
    "gn:dem":437,
    "gn:feature_class":"P",
    "gn:feature_code":"PPL",
    "gn:name":"Kommerscheidt",
    "gn:population":0,
    "gn:timezone":"Europe/Berlin",
    "iso:country":"DE",
    "name:und_x_variant":[
        "Commerscheid",
        "Kemmerscheid",
        "Homerscheidt",
        "Kommerscheid",
        "Komerscheidt",
        "Kommerscheidt"
    ],
    "wof:name":"Kommerscheidt",
    "wof:placetype":"neighbourhood"
},
  "geometry": {"coordinates":[6.39853,50.66633],"type":"Point"}
}