{
  "type": "Feature",
  "properties": {
    "gn:admin1_code":"6.0",
    "gn:admin2_code":"0.0",
    "gn:admin3_code":"3241.0",
    "gn:admin4_code":"3241005.0",
    "gn:asciiname":"Berenbostel",
    "gn:country_code":"DE",
    "gn:dem":56,
    "gn:feature_class":"P",
    "gn:feature_code":"PPL",
    "gn:name":"Berenbostel",
    "gn:population":0,
    "gn:timezone":"Europe/Berlin",
    "iso:country":"DE",
    "name:nds_x_preferred":[
        "Bi'ernbossel"
    ],
    "name:nds_x_variant":[
        "Biernbossel"
    ],
    "wof:name":"Berenbostel",
    "wof:placetype":"neighbourhood"
},
  "geometry": {"coordinates":[9.60798,52.44116],"type":"Point"}
}