{
  "type": "Feature",
  "properties": {
    "gn:admin1_code":"2",
    "gn:admin2_code":"93.0",
    "gn:admin3_code":"9371.0",
    "gn:admin4_code":"9371144.0",
    "gn:asciiname":"Trasslberg",
    "gn:country_code":"DE",
    "gn:dem":387,
    "gn:feature_class":"P",
    "gn:feature_code":"PPL",
    "gn:name":"Tra\u00dflberg",
    "gn:population":0,
    "gn:timezone":"Europe/Berlin",
    "iso:country":"DE",
    "wof:name":"Trasslberg",
    "wof:placetype":"neighbourhood"
},
  "geometry": {"coordinates":[11.82678,49.47855],"type":"Point"}
}