{
  "type": "Feature",
  "properties": {
    "gn:country":"DE",
    "gn:fcode":"PPL",
    "gn:population":941,
    "iso:country":"DE",
    "name:bak_x_preferred":[
        "\u041a\u0430\u043a\u0435\u0440\u0431\u0435\u043a"
    ],
    "name:cat_x_preferred":[
        "Kakerbeck"
    ],
    "name:ceb_x_preferred":[
        "Kakerbeck"
    ],
    "name:che_x_preferred":[
        "\u041a\u0430\u043a\u0435\u0440\u0431\u0435\u043a"
    ],
    "name:deu_x_preferred":[
        "Kakerbeck"
    ],
    "name:eng_x_preferred":[
        "Kakerbeck"
    ],
    "name:epo_x_preferred":[
        "Kakerbeck"
    ],
    "name:fas_x_preferred":[
        "\u06a9\u0627\u06a9\u0631\u0628\u06a9"
    ],
    "name:fra_x_preferred":[
        "Kakerbeck"
    ],
    "name:gle_x_preferred":[
        "Kakerbeck"
    ],
    "name:ita_x_preferred":[
        "Kakerbeck"
    ],
    "name:kaz_x_preferred":[
        "\u041a\u0430\u043a\u0435\u0440\u0431\u0435\u043a"
    ],
    "name:kir_x_preferred":[
        "\u041a\u0430\u043a\u0435\u0440\u0431\u0435\u043a"
    ],
    "name:nld_x_preferred":[
        "Kakerbeck"
    ],
    "name:nob_x_preferred":[
        "Kakerbeck"
    ],
    "name:ron_x_preferred":[
        "Kakerbeck"
    ],
    "name:rus_x_preferred":[
        "\u041a\u0430\u043a\u0435\u0440\u0431\u0435\u043a"
    ],
    "name:tat_x_preferred":[
        "\u041a\u0430\u043a\u0435\u0440\u0431\u0435\u043a"
    ],
    "name:uzb_x_preferred":[
        "Kakerbeck"
    ],
    "name:vie_x_preferred":[
        "Kakerbeck"
    ],
    "name:vol_x_preferred":[
        "Kakerbeck"
    ],
    "qs_pg:aaroncc":"DE",
    "qs_pg:gn_country":"DE",
    "qs_pg:gn_fcode":"PPL",
    "qs_pg:gn_pop":941,
    "qs_pg:name":"Kakerbeck",
    "qs_pg:name_adm0":"Deutschland",
    "qs_pg:name_adm1":"Sachsen-Anhalt",
    "qs_pg:photos_9k":1,
    "qs_pg:photos_9r":1,
    "qs_pg:photos_all":1,
    "qs_pg:photos_sr":0,
    "qs_pg:pop_sr":2,
    "qs_pg:qs_pg_placetype":"locality",
    "qs_pg:qs_pg_placetype_gp":"Town",
    "qs_pg:woe_adm0":23424829,
    "woe:adm0_id":23424829,
    "woe:name_adm0":"Deutschland",
    "woe:name_adm1":"Sachsen-Anhalt",
    "woe:placetype":"Town",
    "wof:name":"Kakerbeck",
    "wof:placetype":"neighbourhood",
    "wof:population":941
},
  "geometry": {"coordinates":[11.27849,52.66924],"type":"Point"}
}