{
  "type": "Feature",
  "properties": {
    "gn:gn_country":"DE",
    "gn:gn_fcode":"PPLA4",
    "gn:gn_pop":543,
    "gn:population":543,
    "iso:country":"DE",
    "name:baq_x_preferred":[
        "Talkau"
    ],
    "name:chi_x_preferred":[
        "\u5854\u5c14\u8003"
    ],
    "name:dan_x_preferred":[
        "Talkau"
    ],
    "name:dut_x_preferred":[
        "Talkau"
    ],
    "name:eng_x_preferred":[
        "Talkau"
    ],
    "name:epo_x_preferred":[
        "Talkau"
    ],
    "name:fre_x_preferred":[
        "Talkau"
    ],
    "name:ger_x_preferred":[
        "Talkau"
    ],
    "name:hun_x_preferred":[
        "Talkau"
    ],
    "name:ita_x_preferred":[
        "Talkau"
    ],
    "name:mac_x_preferred":[
        "\u0422\u0430\u043b\u043a\u0430\u0443"
    ],
    "name:may_x_preferred":[
        "Talkau"
    ],
    "name:per_x_preferred":[
        "\u062a\u0627\u0644\u06a9\u0627\u0648"
    ],
    "name:pol_x_preferred":[
        "Talkau"
    ],
    "name:por_x_preferred":[
        "Talkau"
    ],
    "name:rum_x_preferred":[
        "Talkau"
    ],
    "name:rus_x_preferred":[
        "\u0422\u0430\u043b\u044c\u043a\u0430\u0443"
    ],
    "name:srp_x_preferred":[
        "\u0422\u0430\u043b\u043a\u0430\u0443"
    ],
    "name:tur_x_preferred":[
        "Talkau"
    ],
    "name:ukr_x_preferred":[
        "\u0422\u0430\u043b\u044c\u043a\u0430\u0443"
    ],
    "name:uzb_x_preferred":[
        "Talkau"
    ],
    "name:vie_x_preferred":[
        "Talkau"
    ],
    "name:vol_x_preferred":[
        "Talkau"
    ],
    "name:war_x_preferred":[
        "Talkau"
    ],
    "qs_pg:aaroncc":"DE",
    "qs_pg:gn_country":"DE",
    "qs_pg:gn_fcode":"PPLA4",
    "qs_pg:gn_pop":543,
    "qs_pg:name":"Talkau",
    "qs_pg:photos_9r":0,
    "qs_pg:photos_sr":0,
    "qs_pg:pop_sr":2,
    "qs_pg:qs_pg_placetype":"locality",
    "wof:name":"Talkau",
    "wof:placetype":"locality",
    "wof:population":543
},
  "geometry": {"coordinates":[10.56667,53.56667],"type":"Point"}
}