{
  "type": "Feature",
  "properties": {
    "gn:admin1_code":"2",
    "gn:admin2_code":"92.0",
    "gn:admin3_code":"9275.0",
    "gn:admin4_code":"9275150.0",
    "gn:asciiname":"Buchsee",
    "gn:country_code":"DE",
    "gn:dem":443,
    "gn:feature_class":"P",
    "gn:feature_code":"PPL",
    "gn:name":"Buchsee",
    "gn:population":0,
    "gn:timezone":"Europe/Berlin",
    "iso:country":"DE",
    "name:ceb_x_preferred":[
        "Buchsee"
    ],
    "name:deu_x_preferred":[
        "Buchsee"
    ],
    "name:spa_x_preferred":[
        "Lago Buch"
    ],
    "wof:name":"Buchsee",
    "wof:placetype":"neighbourhood"
},
  "geometry": {"coordinates":[13.54234,48.58888],"type":"Point"}
}