{
  "type": "Feature",
  "properties": {
    "gn:admin1_code":"8",
    "gn:admin2_code":"0.0",
    "gn:admin3_code":"7138.0",
    "gn:admin4_code":"7138007.0",
    "gn:asciiname":"Frorath",
    "gn:country_code":"DE",
    "gn:dem":220,
    "gn:feature_class":"P",
    "gn:feature_code":"PPL",
    "gn:name":"Frorath",
    "gn:population":0,
    "gn:timezone":"Europe/Berlin",
    "iso:country":"DE",
    "wof:name":"Frorath",
    "wof:placetype":"neighbourhood"
},
  "geometry": {"coordinates":[7.39306,50.53912],"type":"Point"}
}