{
  "type": "Feature",
  "properties": {
    "gn:gn_country":"DE",
    "gn:gn_fcode":"PPLA4",
    "gn:gn_pop":582,
    "gn:population":582,
    "iso:country":"DE",
    "name:baq_x_preferred":[
        "Vollmersbach"
    ],
    "name:chi_x_preferred":[
        "\u798f\u5c14\u6885\u5c14\u65af\u5df4\u8d6b"
    ],
    "name:dut_x_preferred":[
        "Vollmersbach"
    ],
    "name:eng_x_preferred":[
        "Vollmersbach"
    ],
    "name:epo_x_preferred":[
        "Vollmersbach"
    ],
    "name:fre_x_preferred":[
        "Vollmersbach"
    ],
    "name:ger_x_preferred":[
        "Vollmersbach"
    ],
    "name:hun_x_preferred":[
        "Vollmersbach"
    ],
    "name:ita_x_preferred":[
        "Vollmersbach"
    ],
    "name:jpn_x_preferred":[
        "\u30d5\u30a9\u30eb\u30e1\u30fc\u30b9\u30d0\u30c3\u30cf"
    ],
    "name:kaz_x_preferred":[
        "\u0424\u043e\u043b\u044c\u043c\u0435\u0440\u0441\u0431\u0430\u0445"
    ],
    "name:kir_x_preferred":[
        "\u0424\u043e\u043b\u044c\u043c\u0435\u0440\u0441\u0431\u0430\u0445"
    ],
    "name:may_x_preferred":[
        "Vollmersbach"
    ],
    "name:per_x_preferred":[
        "\u0641\u0648\u0644\u0645\u0631\u0633\u0628\u0627\u062e"
    ],
    "name:pol_x_preferred":[
        "Vollmersbach"
    ],
    "name:por_x_preferred":[
        "Vollmersbach"
    ],
    "name:rum_x_preferred":[
        "Vollmersbach"
    ],
    "name:rus_x_preferred":[
        "\u0424\u043e\u043b\u044c\u043c\u0435\u0440\u0441\u0431\u0430\u0445"
    ],
    "name:srp_x_preferred":[
        "\u0424\u043e\u043b\u043c\u0435\u0440\u0441\u0431\u0430\u0445"
    ],
    "name:ukr_x_preferred":[
        "\u0424\u043e\u043b\u044c\u043c\u0435\u0440\u0441\u0431\u0430\u0445"
    ],
    "name:uzb_x_preferred":[
        "Vollmersbach"
    ],
    "name:vie_x_preferred":[
        "Vollmersbach"
    ],
    "name:vol_x_preferred":[
        "Vollmersbach"
    ],
    "name:war_x_preferred":[
        "Vollmersbach"
    ],
    "qs_pg:aaroncc":"DE",
    "qs_pg:gn_country":"DE",
    "qs_pg:gn_fcode":"PPLA4",
    "qs_pg:gn_pop":582,
    "qs_pg:name":"Vollmersbach",
    "qs_pg:photos_9r":0,
    "qs_pg:photos_sr":0,
    "qs_pg:pop_sr":2,
    "qs_pg:qs_pg_placetype":"locality",
    "wof:name":"Vollmersbach",
    "wof:placetype":"locality",
    "wof:population":582
},
  "geometry": {"coordinates":[7.31667,49.73333],"type":"Point"}
}