{
  "type": "Feature",
  "properties": {
    "gn:admin1_code":"15",
    "gn:admin2_code":"0.0",
    "gn:admin3_code":"16065.0",
    "gn:admin4_code":"16065002.0",
    "gn:asciiname":"Kachstedt",
    "gn:country_code":"DE",
    "gn:dem":134,
    "gn:feature_class":"P",
    "gn:feature_code":"PPL",
    "gn:name":"Kachstedt",
    "gn:population":0,
    "gn:timezone":"Europe/Berlin",
    "iso:country":"DE",
    "wof:name":"Kachstedt",
    "wof:placetype":"neighbourhood"
},
  "geometry": {"coordinates":[11.26091,51.39057],"type":"Point"}
}