{
  "type": "Feature",
  "properties": {
    "gn:admin1_code":"5",
    "gn:admin2_code":"66.0",
    "gn:admin3_code":"6631.0",
    "gn:admin4_code":"6631004.0",
    "gn:asciiname":"Halsbach",
    "gn:country_code":"DE",
    "gn:dem":360,
    "gn:feature_class":"P",
    "gn:feature_code":"PPL",
    "gn:name":"Halsbach",
    "gn:population":0,
    "gn:timezone":"Europe/Berlin",
    "iso:country":"DE",
    "name:ara_x_preferred":[
        "\u0647\u0627\u0644\u0633\u0628\u0627\u062e"
    ],
    "name:bar_x_preferred":[
        "Halsbach"
    ],
    "name:ceb_x_preferred":[
        "Halsbach"
    ],
    "name:deu_x_preferred":[
        "Halsbach"
    ],
    "name:epo_x_preferred":[
        "Halsbach"
    ],
    "name:eus_x_preferred":[
        "Halsbach"
    ],
    "name:fas_x_preferred":[
        "\u0647\u0627\u0644\u0633\u0628\u0627\u062e"
    ],
    "name:fra_x_preferred":[
        "Halsbach"
    ],
    "name:hun_x_preferred":[
        "Halsbach"
    ],
    "name:hye_x_preferred":[
        "\u0540\u0561\u056c\u057d\u0562\u0561\u056d"
    ],
    "name:ilo_x_preferred":[
        "Halsbach"
    ],
    "name:ind_x_preferred":[
        "Halsbach"
    ],
    "name:ita_x_preferred":[
        "Halsbach"
    ],
    "name:kaz_x_preferred":[
        "\u0425\u0430\u043b\u044c\u0441\u0431\u0430\u0445"
    ],
    "name:kir_x_preferred":[
        "\u0425\u0430\u043b\u044c\u0441\u0431\u0430\u0445"
    ],
    "name:lmo_x_preferred":[
        "Halsbach"
    ],
    "name:msa_x_preferred":[
        "Halsbach"
    ],
    "name:nld_x_preferred":[
        "Halsbach"
    ],
    "name:pol_x_preferred":[
        "Halsbach"
    ],
    "name:por_x_preferred":[
        "Halsbach"
    ],
    "name:ron_x_preferred":[
        "Halsbach"
    ],
    "name:rus_x_preferred":[
        "\u0425\u0430\u043b\u044c\u0441\u0431\u0430\u0445"
    ],
    "name:spa_x_preferred":[
        "Halsbach"
    ],
    "name:srp_x_preferred":[
        "\u0425\u0430\u043b\u0441\u0431\u0430\u0445"
    ],
    "name:ukr_x_preferred":[
        "\u0413\u0430\u043b\u044c\u0441\u0431\u0430\u0445"
    ],
    "name:uzb_x_preferred":[
        "Halsbach"
    ],
    "name:vie_x_preferred":[
        "Halsbach"
    ],
    "name:vol_x_preferred":[
        "Halsbach"
    ],
    "name:war_x_preferred":[
        "Halsbach"
    ],
    "name:zho_x_preferred":[
        "\u54c8\u5c14\u65af\u5df4\u8d6b"
    ],
    "wof:name":"Halsbach",
    "wof:placetype":"neighbourhood"
},
  "geometry": {"coordinates":[9.7703,50.48875],"type":"Point"}
}