{
  "type": "Feature",
  "properties": {
    "gn:admin1_code":"8",
    "gn:admin2_code":"0.0",
    "gn:admin3_code":"7340.0",
    "gn:admin4_code":"7340028.0",
    "gn:asciiname":"Langmuehle",
    "gn:country_code":"DE",
    "gn:dem":281,
    "gn:feature_class":"P",
    "gn:feature_code":"PPL",
    "gn:name":"Langm\u00fchle",
    "gn:population":0,
    "gn:timezone":"Europe/Berlin",
    "iso:country":"DE",
    "wof:name":"Langmuehle",
    "wof:placetype":"neighbourhood"
},
  "geometry": {"coordinates":[7.67249,49.16108],"type":"Point"}
}