{
  "type": "Feature",
  "properties": {
    "gn:admin1_code":"7.0",
    "gn:admin2_code":"53.0",
    "gn:admin3_code":"5370.0",
    "gn:admin4_code":"5370016.0",
    "gn:asciiname":"Brehm",
    "gn:country_code":"DE",
    "gn:dem":35,
    "gn:feature_class":"P",
    "gn:feature_code":"PPL",
    "gn:name":"Brehm",
    "gn:population":0,
    "gn:timezone":"Europe/Berlin",
    "iso:country":"DE",
    "name:deu_x_preferred":[
        "Brehm"
    ],
    "name:fra_x_preferred":[
        "Brehm"
    ],
    "name:hun_x_preferred":[
        "Brehm"
    ],
    "name:ita_x_preferred":[
        "Brehm"
    ],
    "name:nld_x_preferred":[
        "Brehm"
    ],
    "name:pol_x_preferred":[
        "Brehm"
    ],
    "name:por_x_preferred":[
        "Brehm"
    ],
    "name:rus_x_preferred":[
        "\u0411\u0440\u0435\u043c"
    ],
    "name:srp_x_preferred":[
        "\u0411\u0440\u0435\u043c"
    ],
    "name:ukr_x_preferred":[
        "\u0411\u0440\u0435\u043c"
    ],
    "wof:name":"Brehm",
    "wof:placetype":"neighbourhood"
},
  "geometry": {"coordinates":[6.12362,51.08832],"type":"Point"}
}