{
  "type": "Feature",
  "properties": {
    "gn:admin1_code":"11.0",
    "gn:admin2_code":"0.0",
    "gn:admin3_code":"12069.0",
    "gn:admin4_code":"12069017.0",
    "gn:asciiname":"Birkhorst",
    "gn:country_code":"DE",
    "gn:dem":41,
    "gn:feature_class":"P",
    "gn:feature_code":"PPL",
    "gn:name":"Birkhorst",
    "gn:population":0,
    "gn:timezone":"Europe/Berlin",
    "iso:country":"DE",
    "wof:name":"Birkhorst",
    "wof:placetype":"neighbourhood"
},
  "geometry": {"coordinates":[12.90487,52.18831],"type":"Point"}
}