{
  "type": "Feature",
  "properties": {
    "gn:admin1_code":"13",
    "gn:admin2_code":"0.0",
    "gn:admin3_code":"14523.0",
    "gn:admin4_code":"14523280.0",
    "gn:asciiname":"Reuth",
    "gn:country_code":"DE",
    "gn:dem":372,
    "gn:feature_class":"P",
    "gn:feature_code":"PPL",
    "gn:name":"Reuth",
    "gn:population":0,
    "gn:timezone":"Europe/Berlin",
    "iso:country":"DE",
    "name:ceb_x_preferred":[
        "Reuth"
    ],
    "name:deu_x_preferred":[
        "Reuth"
    ],
    "name:epo_x_preferred":[
        "Reuth"
    ],
    "name:fra_x_preferred":[
        "Reuth"
    ],
    "name:ita_x_preferred":[
        "Reuth"
    ],
    "name:nld_x_preferred":[
        "Reuth"
    ],
    "name:pol_x_preferred":[
        "Reuth"
    ],
    "name:srp_x_preferred":[
        "\u0420\u043e\u0458\u0442"
    ],
    "name:swe_x_preferred":[
        "Reuth"
    ],
    "name:vol_x_preferred":[
        "Reuth"
    ],
    "wof:name":"Reuth",
    "wof:placetype":"neighbourhood"
},
  "geometry": {"coordinates":[12.32208,50.67148],"type":"Point"}
}