{
  "type": "Feature",
  "properties": {
    "gn:admin1_code":"2",
    "gn:admin2_code":"93.0",
    "gn:admin3_code":"9371.0",
    "gn:admin4_code":"9371128.0",
    "gn:asciiname":"Buchhof",
    "gn:country_code":"DE",
    "gn:dem":513,
    "gn:feature_class":"P",
    "gn:feature_code":"PPL",
    "gn:name":"Buchhof",
    "gn:population":0,
    "gn:timezone":"Europe/Berlin",
    "iso:country":"DE",
    "name:bar_x_preferred":[
        "Buchhof"
    ],
    "name:deu_x_preferred":[
        "Buchhof"
    ],
    "wof:name":"Buchhof",
    "wof:placetype":"neighbourhood"
},
  "geometry": {"coordinates":[11.59563,49.55723],"type":"Point"}
}