{
  "type": "Feature",
  "properties": {
    "gn:admin1_code":"6",
    "gn:admin2_code":"0.0",
    "gn:admin3_code":"3459.0",
    "gn:admin4_code":"3459027.0",
    "gn:asciiname":"Rothertshausen",
    "gn:country_code":"DE",
    "gn:dem":47,
    "gn:feature_class":"P",
    "gn:feature_code":"PPL",
    "gn:name":"Rothertshausen",
    "gn:population":0,
    "gn:timezone":"Europe/Berlin",
    "iso:country":"DE",
    "wof:name":"Rothertshausen",
    "wof:placetype":"neighbourhood"
},
  "geometry": {"coordinates":[7.77335,52.38918],"type":"Point"}
}