{
  "type": "Feature",
  "properties": {
    "gn:admin1_code":"7",
    "gn:admin2_code":"51.0",
    "gn:admin3_code":"5154.0",
    "gn:admin4_code":"5154044.0",
    "gn:asciiname":"Grietherbusch",
    "gn:country_code":"DE",
    "gn:dem":14,
    "gn:feature_class":"P",
    "gn:feature_code":"PPL",
    "gn:name":"Grietherbusch",
    "gn:population":0,
    "gn:timezone":"Europe/Berlin",
    "iso:country":"DE",
    "wof:name":"Grietherbusch",
    "wof:placetype":"neighbourhood"
},
  "geometry": {"coordinates":[6.35132,51.80353],"type":"Point"}
}