{
  "type": "Feature",
  "properties": {
    "gn:admin1_code":"15",
    "gn:admin2_code":"0.0",
    "gn:admin3_code":"16075.0",
    "gn:admin4_code":"16075098.0",
    "gn:asciiname":"Droeswein",
    "gn:country_code":"DE",
    "gn:dem":480,
    "gn:feature_class":"P",
    "gn:feature_code":"PPL",
    "gn:name":"Dr\u00f6swein",
    "gn:population":0,
    "gn:timezone":"Europe/Berlin",
    "iso:country":"DE",
    "wof:name":"Droeswein",
    "wof:placetype":"neighbourhood"
},
  "geometry": {"coordinates":[11.92389,50.58909],"type":"Point"}
}