{
  "type": "Feature",
  "properties": {
    "gn:admin1_code":"7",
    "gn:admin2_code":"57.0",
    "gn:admin3_code":"5766.0",
    "gn:admin4_code":"5766020.0",
    "gn:asciiname":"Leistrup",
    "gn:country_code":"DE",
    "gn:dem":206,
    "gn:feature_class":"P",
    "gn:feature_code":"PPL",
    "gn:name":"Leistrup",
    "gn:population":0,
    "gn:timezone":"Europe/Berlin",
    "iso:country":"DE",
    "wof:name":"Leistrup",
    "wof:placetype":"neighbourhood"
},
  "geometry": {"coordinates":[8.94502,51.9294],"type":"Point"}
}