{
  "type": "Feature",
  "properties": {
    "gn:admin1_code":"11",
    "gn:admin2_code":"0.0",
    "gn:admin3_code":"12052.0",
    "gn:admin4_code":"12052000.0",
    "gn:asciiname":"Sandow",
    "gn:country_code":"DE",
    "gn:dem":74,
    "gn:feature_class":"P",
    "gn:feature_code":"PPL",
    "gn:name":"Sandow",
    "gn:population":0,
    "gn:timezone":"Europe/Berlin",
    "iso:country":"DE",
    "name:deu_x_preferred":[
        "Sandow"
    ],
    "name:fra_x_preferred":[
        "Sandow"
    ],
    "name:ita_x_preferred":[
        "Sandow"
    ],
    "name:pol_x_preferred":[
        "Sandow"
    ],
    "wof:name":"Sandow",
    "wof:placetype":"neighbourhood"
},
  "geometry": {"coordinates":[14.35085,51.76102],"type":"Point"}
}