{
  "type": "Feature",
  "properties": {
    "gn:admin1_code":"2",
    "gn:admin2_code":"97.0",
    "gn:admin3_code":"9776.0",
    "gn:admin4_code":"9776113.0",
    "gn:asciiname":"Motzgatzried",
    "gn:country_code":"DE",
    "gn:dem":814,
    "gn:feature_class":"P",
    "gn:feature_code":"PPL",
    "gn:name":"Motzgatzried",
    "gn:population":0,
    "gn:timezone":"Europe/Berlin",
    "iso:country":"DE",
    "wof:name":"Motzgatzried",
    "wof:placetype":"neighbourhood"
},
  "geometry": {"coordinates":[10.03238,47.6266],"type":"Point"}
}