{
  "type": "Feature",
  "properties": {
    "gn:admin1_code":"15",
    "gn:admin2_code":"0.0",
    "gn:admin3_code":"16075.0",
    "gn:admin4_code":"16075049.0",
    "gn:asciiname":"Posen",
    "gn:country_code":"DE",
    "gn:dem":444,
    "gn:feature_class":"P",
    "gn:feature_code":"PPL",
    "gn:name":"Posen",
    "gn:population":0,
    "gn:timezone":"Europe/Berlin",
    "iso:country":"DE",
    "name:ceb_x_preferred":[
        "Posen"
    ],
    "name:deu_x_preferred":[
        "Posen"
    ],
    "name:fas_x_preferred":[
        "\u067e\u0648\u0632\u0646"
    ],
    "name:fra_x_preferred":[
        "Posen"
    ],
    "name:ind_x_preferred":[
        "Posen"
    ],
    "name:ita_x_preferred":[
        "Posen"
    ],
    "name:pol_x_preferred":[
        "Posen"
    ],
    "name:rus_x_preferred":[
        "\u041f\u043e\u0437\u0435\u043d"
    ],
    "name:srp_x_preferred":[
        "\u041f\u043e\u0441\u0435\u043d"
    ],
    "name:swe_x_preferred":[
        "Posen"
    ],
    "name:vol_x_preferred":[
        "Posen"
    ],
    "wof:name":"Posen",
    "wof:placetype":"neighbourhood"
},
  "geometry": {"coordinates":[11.69031,50.6426],"type":"Point"}
}