{
  "type": "Feature",
  "properties": {
    "gn:admin1_code":"2.0",
    "gn:admin2_code":"094",
    "gn:admin3_code":"9472.0",
    "gn:admin4_code":"9472139.0",
    "gn:asciiname":"Zettlitz",
    "gn:country_code":"DE",
    "gn:dem":540,
    "gn:feature_class":"P",
    "gn:feature_code":"PPL",
    "gn:name":"Zettlitz",
    "gn:population":0,
    "gn:timezone":"Europe/Berlin",
    "iso:country":"DE",
    "wof:name":"Zettlitz",
    "wof:placetype":"neighbourhood"
},
  "geometry": {"coordinates":[11.76876,50.1156],"type":"Point"}
}