{
  "type": "Feature",
  "properties": {
    "gn:admin1_code":"7",
    "gn:admin2_code":"55.0",
    "gn:admin3_code":"5562.0",
    "gn:admin4_code":"5562036.0",
    "gn:asciiname":"Leveringhausen",
    "gn:country_code":"DE",
    "gn:dem":67,
    "gn:feature_class":"P",
    "gn:feature_code":"PPL",
    "gn:name":"Leveringhausen",
    "gn:population":0,
    "gn:timezone":"Europe/Berlin",
    "iso:country":"DE",
    "wof:name":"Leveringhausen",
    "wof:placetype":"neighbourhood"
},
  "geometry": {"coordinates":[7.37763,51.60096],"type":"Point"}
}