{
  "type": "Feature",
  "properties": {
    "gn:admin1_code":"6",
    "gn:admin2_code":"0.0",
    "gn:admin3_code":"3453.0",
    "gn:admin4_code":"3453013.0",
    "gn:asciiname":"Scharrel",
    "gn:country_code":"DE",
    "gn:dem":5,
    "gn:feature_class":"P",
    "gn:feature_code":"PPL",
    "gn:name":"Scharrel",
    "gn:population":0,
    "gn:timezone":"Europe/Berlin",
    "iso:country":"DE",
    "name:frs_x_preferred":[
        "Sch\u00e4ddel"
    ],
    "wof:name":"Scharrel",
    "wof:placetype":"neighbourhood"
},
  "geometry": {"coordinates":[7.70399,53.07169],"type":"Point"}
}