{
  "type": "Feature",
  "properties": {
    "gn:admin1_code":"12",
    "gn:admin2_code":"0.0",
    "gn:admin3_code":"13076.0",
    "gn:admin4_code":"13076068.0",
    "gn:asciiname":"Neu Herzfeld",
    "gn:country_code":"DE",
    "gn:dem":51,
    "gn:feature_class":"P",
    "gn:feature_code":"PPL",
    "gn:name":"Neu Herzfeld",
    "gn:population":0,
    "gn:timezone":"Europe/Berlin",
    "iso:country":"DE",
    "wof:name":"Neu Herzfeld",
    "wof:placetype":"neighbourhood"
},
  "geometry": {"coordinates":[11.78357,53.32911],"type":"Point"}
}