{
  "type": "Feature",
  "properties": {
    "gn:admin1_code":"7",
    "gn:admin2_code":"59.0",
    "gn:admin3_code":"5958.0",
    "gn:admin4_code":"5958040.0",
    "gn:asciiname":"Oberhenneborn",
    "gn:country_code":"DE",
    "gn:dem":441,
    "gn:feature_class":"P",
    "gn:feature_code":"PPL",
    "gn:name":"Oberhenneborn",
    "gn:population":0,
    "gn:timezone":"Europe/Berlin",
    "iso:country":"DE",
    "name:deu_x_preferred":[
        "Oberhenneborn"
    ],
    "name:fas_x_preferred":[
        "\u0627\u0628\u0631\u0647\u0646\u0647 \u0628\u0631\u0646"
    ],
    "name:nld_x_preferred":[
        "Oberhenneborn"
    ],
    "wof:name":"Oberhenneborn",
    "wof:placetype":"neighbourhood"
},
  "geometry": {"coordinates":[8.29793,51.2328],"type":"Point"}
}