{
  "type": "Feature",
  "properties": {
    "gn:admin1_code":"8",
    "gn:admin2_code":"0.0",
    "gn:admin3_code":"7336.0",
    "gn:admin4_code":"7336037.0",
    "gn:asciiname":"Haschbach an der Glan",
    "gn:country_code":"DE",
    "gn:dem":240,
    "gn:feature_class":"P",
    "gn:feature_code":"PPL",
    "gn:name":"Haschbach an der Glan",
    "gn:population":0,
    "gn:timezone":"Europe/Berlin",
    "iso:country":"DE",
    "name:und_x_variant":[
        "Haschbach",
        "Haschbach an der Glan"
    ],
    "wof:name":"Haschbach an der Glan",
    "wof:placetype":"neighbourhood"
},
  "geometry": {"coordinates":[7.41261,49.46651],"type":"Point"}
}