{
  "type": "Feature",
  "properties": {
    "gn:admin1_code":"2.0",
    "gn:admin2_code":"093",
    "gn:admin3_code":"9375.0",
    "gn:admin4_code":"9375190.0",
    "gn:asciiname":"Wohrhof",
    "gn:country_code":"DE",
    "gn:dem":337,
    "gn:feature_class":"P",
    "gn:feature_code":"PPL",
    "gn:name":"W\u00f6hrhof",
    "gn:population":0,
    "gn:timezone":"Europe/Berlin",
    "iso:country":"DE",
    "wof:name":"Wohrhof",
    "wof:placetype":"neighbourhood"
},
  "geometry": {"coordinates":[12.13879,49.13669],"type":"Point"}
}