{
  "type": "Feature",
  "properties": {
    "gn:admin1_code":"8.0",
    "gn:admin2_code":"0.0",
    "gn:admin3_code":"7141.0",
    "gn:admin4_code":"7141085.0",
    "gn:asciiname":"Aftholderbach",
    "gn:country_code":"DE",
    "gn:dem":304,
    "gn:feature_class":"P",
    "gn:feature_code":"PPL",
    "gn:name":"Aftholderbach",
    "gn:population":0,
    "gn:timezone":"Europe/Berlin",
    "iso:country":"DE",
    "wof:name":"Aftholderbach",
    "wof:placetype":"neighbourhood"
},
  "geometry": {"coordinates":[7.86085,50.21165],"type":"Point"}
}