{
  "type": "Feature",
  "properties": {
    "gn:admin1_code":"1",
    "gn:admin2_code":"81.0",
    "gn:admin3_code":"8125.0",
    "gn:admin4_code":"8125007.0",
    "gn:asciiname":"Hohenstadt",
    "gn:country_code":"DE",
    "gn:dem":217,
    "gn:feature_class":"P",
    "gn:feature_code":"PPL",
    "gn:name":"Hohenstadt",
    "gn:population":0,
    "gn:timezone":"Europe/Berlin",
    "iso:country":"DE",
    "name:als_x_preferred":[
        "Hohenstadt"
    ],
    "name:ceb_x_preferred":[
        "Hohenstadt"
    ],
    "name:deu_x_preferred":[
        "Hohenstadt"
    ],
    "name:epo_x_preferred":[
        "Hohenstadt"
    ],
    "name:eus_x_preferred":[
        "Hohenstadt"
    ],
    "name:fas_x_preferred":[
        "\u0647\u0648\u0647\u0646\u0634\u062a\u0627\u062f\u062a"
    ],
    "name:fra_x_preferred":[
        "Hohenstadt"
    ],
    "name:hun_x_preferred":[
        "Hohenstadt"
    ],
    "name:ita_x_preferred":[
        "Hohenstadt"
    ],
    "name:kaz_x_preferred":[
        "\u0425\u043e\u044d\u043d\u0448\u0442\u0430\u0434\u0442"
    ],
    "name:kir_x_preferred":[
        "\u0425\u043e\u044d\u043d\u0448\u0442\u0430\u0434\u0442"
    ],
    "name:lat_x_preferred":[
        "Hohenstadt"
    ],
    "name:lmo_x_preferred":[
        "Hohenstadt"
    ],
    "name:msa_x_preferred":[
        "Hohenstadt"
    ],
    "name:nld_x_preferred":[
        "Hohenstadt"
    ],
    "name:pol_x_preferred":[
        "Hohenstadt"
    ],
    "name:por_x_preferred":[
        "Hohenstadt"
    ],
    "name:ron_x_preferred":[
        "Hohenstadt"
    ],
    "name:rus_x_preferred":[
        "\u0425\u043e\u044d\u043d\u0448\u0442\u0430\u0434\u0442"
    ],
    "name:srp_x_preferred":[
        "\u0425\u043e\u0435\u043d\u0448\u0442\u0430\u0442"
    ],
    "name:ukr_x_preferred":[
        "\u0413\u043e\u0435\u043d\u0448\u0442\u0430\u0434\u0442"
    ],
    "name:uzb_x_preferred":[
        "Hohenstadt"
    ],
    "name:vie_x_preferred":[
        "Hohenstadt"
    ],
    "name:vol_x_preferred":[
        "Hohenstadt"
    ],
    "name:war_x_preferred":[
        "Hohenstadt"
    ],
    "name:zho_x_preferred":[
        "\u970d\u6069\u65bd\u5854\u7279"
    ],
    "wof:name":"Hohenstadt",
    "wof:placetype":"neighbourhood"
},
  "geometry": {"coordinates":[9.13781,49.24278],"type":"Point"}
}