{
  "type": "Feature",
  "properties": {
    "gn:admin1_code":"2",
    "gn:admin2_code":"91.0",
    "gn:admin3_code":"9181.0",
    "gn:admin4_code":"9181122.0",
    "gn:asciiname":"Durnast",
    "gn:country_code":"DE",
    "gn:dem":581,
    "gn:feature_class":"P",
    "gn:feature_code":"PPL",
    "gn:name":"D\u00fcrnast",
    "gn:population":0,
    "gn:timezone":"Europe/Berlin",
    "iso:country":"DE",
    "wof:name":"Durnast",
    "wof:placetype":"neighbourhood"
},
  "geometry": {"coordinates":[11.00419,48.11909],"type":"Point"}
}