{
  "type": "Feature",
  "properties": {
    "gn:admin1_code":"13",
    "gn:admin2_code":"0.0",
    "gn:admin3_code":"14522.0",
    "gn:admin4_code":"14522300.0",
    "gn:asciiname":"Hoefchen",
    "gn:country_code":"DE",
    "gn:dem":274,
    "gn:feature_class":"P",
    "gn:feature_code":"PPL",
    "gn:name":"H\u00f6fchen",
    "gn:population":0,
    "gn:timezone":"Europe/Berlin",
    "iso:country":"DE",
    "wof:name":"Hoefchen",
    "wof:placetype":"neighbourhood"
},
  "geometry": {"coordinates":[12.98942,51.03398],"type":"Point"}
}