{
  "type": "Feature",
  "properties": {
    "gn:admin1_code":"7",
    "gn:admin2_code":"55.0",
    "gn:admin3_code":"5562.0",
    "gn:admin4_code":"5562004.0",
    "gn:asciiname":"Frohlinde",
    "gn:country_code":"DE",
    "gn:dem":108,
    "gn:feature_class":"P",
    "gn:feature_code":"PPL",
    "gn:name":"Frohlinde",
    "gn:population":0,
    "gn:timezone":"Europe/Berlin",
    "iso:country":"DE",
    "wof:name":"Frohlinde",
    "wof:placetype":"neighbourhood"
},
  "geometry": {"coordinates":[7.34958,51.53163],"type":"Point"}
}