{
  "type": "Feature",
  "properties": {
    "gn:admin1_code":"2.0",
    "gn:admin2_code":"093",
    "gn:admin3_code":"9371.0",
    "gn:admin4_code":"9371113.0",
    "gn:asciiname":"Welluck",
    "gn:country_code":"DE",
    "gn:dem":451,
    "gn:feature_class":"P",
    "gn:feature_code":"PPL",
    "gn:name":"Welluck",
    "gn:population":0,
    "gn:timezone":"Europe/Berlin",
    "iso:country":"DE",
    "wof:name":"Welluck",
    "wof:placetype":"neighbourhood"
},
  "geometry": {"coordinates":[11.63928,49.68194],"type":"Point"}
}