{
  "type": "Feature",
  "properties": {
    "gn:admin1_code":"7",
    "gn:admin2_code":"55.0",
    "gn:admin3_code":"5558.0",
    "gn:admin4_code":"5558040.0",
    "gn:asciiname":"Hegerort",
    "gn:country_code":"DE",
    "gn:dem":76,
    "gn:feature_class":"P",
    "gn:feature_code":"PPL",
    "gn:name":"Hegerort",
    "gn:population":0,
    "gn:timezone":"Europe/Berlin",
    "iso:country":"DE",
    "wof:name":"Hegerort",
    "wof:placetype":"neighbourhood"
},
  "geometry": {"coordinates":[7.0901,52.00213],"type":"Point"}
}