{
  "type": "Feature",
  "properties": {
    "gn:admin1_code":"12.0",
    "gn:admin2_code":"0.0",
    "gn:admin3_code":"13073.0",
    "gn:admin4_code":"13073075.0",
    "gn:asciiname":"Borg",
    "gn:country_code":"DE",
    "gn:dem":11,
    "gn:feature_class":"P",
    "gn:feature_code":"PPL",
    "gn:name":"Borg",
    "gn:population":0,
    "gn:timezone":"Europe/Berlin",
    "iso:country":"DE",
    "name:bos_x_preferred":[
        "Borg"
    ],
    "name:bul_x_preferred":[
        "\u0411\u043e\u0440\u0433\u0438"
    ],
    "name:cat_x_preferred":[
        "Borg"
    ],
    "name:ces_x_preferred":[
        "Borgov\u00e9"
    ],
    "name:epo_x_preferred":[
        "Borg"
    ],
    "name:eus_x_preferred":[
        "Borg"
    ],
    "name:fas_x_preferred":[
        "\u0628\u0648\u0631\u06af"
    ],
    "name:fin_x_preferred":[
        "Borgit"
    ],
    "name:fra_x_preferred":[
        "Borg"
    ],
    "name:heb_x_preferred":[
        "\u05d1\u05d5\u05e8\u05d2"
    ],
    "name:hrv_x_preferred":[
        "Borg"
    ],
    "name:hun_x_preferred":[
        "Borg"
    ],
    "name:ind_x_preferred":[
        "Borg"
    ],
    "name:ita_x_preferred":[
        "Borg"
    ],
    "name:jpn_x_preferred":[
        "\u30dc\u30fc\u30b0"
    ],
    "name:kor_x_preferred":[
        "\ubcf4\uadf8"
    ],
    "name:lat_x_preferred":[
        "Borg"
    ],
    "name:mar_x_preferred":[
        "\u0913\u0915\u093e\u0902\u092a\u093e"
    ],
    "name:nld_x_preferred":[
        "Borg"
    ],
    "name:nor_x_preferred":[
        "Borg"
    ],
    "name:pol_x_preferred":[
        "Borg"
    ],
    "name:por_x_preferred":[
        "Borg"
    ],
    "name:ron_x_preferred":[
        "Borg"
    ],
    "name:rus_x_preferred":[
        "\u0411\u043e\u0440\u0433"
    ],
    "name:slk_x_preferred":[
        "Borgovia"
    ],
    "name:spa_x_preferred":[
        "Borg"
    ],
    "name:srp_x_preferred":[
        "Borg"
    ],
    "name:ukr_x_preferred":[
        "\u0411\u043e\u0440\u0491"
    ],
    "name:zho_x_preferred":[
        "\u535a\u683c"
    ],
    "wof:name":"Borg",
    "wof:placetype":"neighbourhood"
},
  "geometry": {"coordinates":[12.38777,54.23353],"type":"Point"}
}