{
  "type": "Feature",
  "properties": {
    "gn:admin1_code":"2.0",
    "gn:admin2_code":"94.0",
    "gn:admin3_code":"9475.0",
    "gn:admin4_code":"9475156.0",
    "gn:asciiname":"Modelsmuehle",
    "gn:country_code":"DE",
    "gn:dem":500,
    "gn:feature_class":"P",
    "gn:feature_code":"PPL",
    "gn:name":"Modelsm\u00fchle",
    "gn:population":0,
    "gn:timezone":"Europe/Berlin",
    "iso:country":"DE",
    "wof:name":"Modelsmuehle",
    "wof:placetype":"neighbourhood"
},
  "geometry": {"coordinates":[11.68879,50.35862],"type":"Point"}
}