{
  "type": "Feature",
  "properties": {
    "gn:admin1_code":"7",
    "gn:admin2_code":"53.0",
    "gn:admin3_code":"5378.0",
    "gn:admin4_code":"5378028.0",
    "gn:asciiname":"Grosshecken",
    "gn:country_code":"DE",
    "gn:dem":166,
    "gn:feature_class":"P",
    "gn:feature_code":"PPL",
    "gn:name":"Gro\u00dfhecken",
    "gn:population":0,
    "gn:timezone":"Europe/Berlin",
    "iso:country":"DE",
    "wof:name":"Grosshecken",
    "wof:placetype":"neighbourhood"
},
  "geometry": {"coordinates":[7.21802,50.89862],"type":"Point"}
}