{
  "type": "Feature",
  "properties": {
    "gn:admin1_code":"7",
    "gn:admin2_code":"51.0",
    "gn:admin3_code":"5158.0",
    "gn:admin4_code":"5158028.0",
    "gn:asciiname":"Eggerscheidt",
    "gn:country_code":"DE",
    "gn:dem":119,
    "gn:feature_class":"P",
    "gn:feature_code":"PPL",
    "gn:name":"Eggerscheidt",
    "gn:population":0,
    "gn:timezone":"Europe/Berlin",
    "iso:country":"DE",
    "name:und_x_variant":[
        "Eggersheid",
        "Eggerscheidt"
    ],
    "wof:name":"Eggerscheidt",
    "wof:placetype":"neighbourhood"
},
  "geometry": {"coordinates":[6.88733,51.31711],"type":"Point"}
}