{
  "type": "Feature",
  "properties": {
    "gn:admin1_code":"2",
    "gn:admin2_code":"97.0",
    "gn:admin3_code":"9777.0",
    "gn:admin4_code":"9777166.0",
    "gn:asciiname":"Langenwald",
    "gn:country_code":"DE",
    "gn:dem":800,
    "gn:feature_class":"P",
    "gn:feature_code":"PPL",
    "gn:name":"Langenwald",
    "gn:population":0,
    "gn:timezone":"Europe/Berlin",
    "iso:country":"DE",
    "wof:name":"Langenwald",
    "wof:placetype":"neighbourhood"
},
  "geometry": {"coordinates":[10.74088,47.67917],"type":"Point"}
}