{
  "type": "Feature",
  "properties": {
    "gn:admin1_code":"14",
    "gn:admin2_code":"0.0",
    "gn:admin3_code":"15090.0",
    "gn:admin4_code":"15090500.0",
    "gn:asciiname":"Hohengoehrener Damm",
    "gn:country_code":"DE",
    "gn:dem":35,
    "gn:feature_class":"P",
    "gn:feature_code":"PPL",
    "gn:name":"Hoheng\u00f6hrener Damm",
    "gn:population":0,
    "gn:timezone":"Europe/Berlin",
    "iso:country":"DE",
    "wof:name":"Hohengoehrener Damm",
    "wof:placetype":"neighbourhood"
},
  "geometry": {"coordinates":[12.09765,52.61935],"type":"Point"}
}