{
  "type": "Feature",
  "properties": {
    "gn:admin1_code":"14",
    "gn:admin2_code":"0.0",
    "gn:admin3_code":"15084.0",
    "gn:admin4_code":"15084490.0",
    "gn:asciiname":"Kostplatz",
    "gn:country_code":"DE",
    "gn:dem":203,
    "gn:feature_class":"P",
    "gn:feature_code":"PPL",
    "gn:name":"Kostplatz",
    "gn:population":0,
    "gn:timezone":"Europe/Berlin",
    "iso:country":"DE",
    "wof:name":"Kostplatz",
    "wof:placetype":"neighbourhood"
},
  "geometry": {"coordinates":[11.97078,51.11633],"type":"Point"}
}