{
  "type": "Feature",
  "properties": {
    "gn:population":1171,
    "iso:country":"DE",
    "name:als_x_preferred":[
        "Aichen"
    ],
    "name:arm_x_preferred":[
        "\u0531\u0575\u056d\u0565\u0576"
    ],
    "name:baq_x_preferred":[
        "Aichen"
    ],
    "name:bar_x_preferred":[
        "Aichen"
    ],
    "name:dan_x_preferred":[
        "Aichen"
    ],
    "name:deu_x_preferred":[
        "Aichen"
    ],
    "name:deu_x_variant":[
        "Gemeinde Aichen"
    ],
    "name:dut_x_preferred":[
        "Aichen"
    ],
    "name:eng_x_preferred":[
        "Aichen"
    ],
    "name:epo_x_preferred":[
        "Aichen"
    ],
    "name:eus_x_preferred":[
        "Aichen"
    ],
    "name:fas_x_preferred":[
        "\u0627\u06cc\u0686\u0646"
    ],
    "name:fra_x_preferred":[
        "Aichen"
    ],
    "name:fre_x_preferred":[
        "Aichen"
    ],
    "name:ger_x_preferred":[
        "Aichen"
    ],
    "name:gsw_x_preferred":[
        "Aichen"
    ],
    "name:hbs_x_preferred":[
        "Aichen"
    ],
    "name:hun_x_preferred":[
        "Aichen"
    ],
    "name:hye_x_preferred":[
        "\u0531\u0575\u056d\u0565\u0576"
    ],
    "name:ind_x_preferred":[
        "Aichen"
    ],
    "name:ita_x_preferred":[
        "Aichen"
    ],
    "name:lat_x_preferred":[
        "Aichen"
    ],
    "name:lmo_x_preferred":[
        "Aichen"
    ],
    "name:may_x_preferred":[
        "Aichen"
    ],
    "name:msa_x_preferred":[
        "Aichen"
    ],
    "name:nan_x_preferred":[
        "Aichen"
    ],
    "name:nld_x_preferred":[
        "Aichen"
    ],
    "name:per_x_preferred":[
        "\u0627\u06cc\u0686\u0646"
    ],
    "name:pol_x_preferred":[
        "Aichen"
    ],
    "name:por_x_preferred":[
        "Aichen"
    ],
    "name:ron_x_preferred":[
        "Aichen"
    ],
    "name:rum_x_preferred":[
        "Aichen"
    ],
    "name:rus_x_preferred":[
        "\u0410\u0439\u0445\u0435\u043d"
    ],
    "name:srp_x_preferred":[
        "\u0410\u0458\u0445\u0435\u043d"
    ],
    "name:ukr_x_preferred":[
        "\u0410\u0439\u0445\u0435\u043d"
    ],
    "name:uzb_x_preferred":[
        "Aichen"
    ],
    "name:vie_x_preferred":[
        "Aichen"
    ],
    "name:vol_x_preferred":[
        "Aichen"
    ],
    "name:war_x_preferred":[
        "Aichen"
    ],
    "name:zho_min_nan_x_preferred":[
        "Aichen"
    ],
    "qs:a0":"Bundesrepublik Deutschland",
    "qs:a1":"*Bayern",
    "qs:a1r":"0",
    "qs:a2":"G\u00fcnzburg",
    "qs:adm0":"Bundesrepublik Deutschland",
    "qs:la_lc":"*",
    "qs:level":"locality",
    "qs:loc":"Aichen",
    "qs:loc_alt":"Aichen",
    "qs:pop":0,
    "qs:type":"buffered point",
    "wd:wordcount":26,
    "wof:lang":[
        "ger"
    ],
    "wof:name":"Aichen",
    "wof:placetype":"locality",
    "wof:population":1171
},
  "geometry": {"coordinates":[10.539088,48.229353],"type":"Point"}
}