{
  "type": "Feature",
  "properties": {
    "gn:admin1_code":"14",
    "gn:admin2_code":"0.0",
    "gn:admin3_code":"15082.0",
    "gn:admin4_code":"15082377.0",
    "gn:asciiname":"Naundorf",
    "gn:country_code":"DE",
    "gn:dem":78,
    "gn:feature_class":"P",
    "gn:feature_code":"PPL",
    "gn:name":"Naundorf",
    "gn:population":185,
    "gn:timezone":"Europe/Berlin",
    "iso:country":"DE",
    "name:und_x_variant":[
        "Naundorf vor der Heide",
        "Naundorf"
    ],
    "wof:name":"Naundorf",
    "wof:placetype":"neighbourhood",
    "wof:population":185
},
  "geometry": {"coordinates":[12.101,51.75321],"type":"Point"}
}