{
  "type": "Feature",
  "properties": {
    "gn:admin1_code":"6.0",
    "gn:admin2_code":"0.0",
    "gn:admin3_code":"3351.0",
    "gn:admin4_code":"3351025.0",
    "gn:asciiname":"Habighorster Hoehe",
    "gn:country_code":"DE",
    "gn:dem":68,
    "gn:feature_class":"P",
    "gn:feature_code":"PPL",
    "gn:name":"Habighorster H\u00f6he",
    "gn:population":0,
    "gn:timezone":"Europe/Berlin",
    "iso:country":"DE",
    "wof:name":"Habighorster Hoehe",
    "wof:placetype":"neighbourhood"
},
  "geometry": {"coordinates":[10.23494,52.69902],"type":"Point"}
}