{
  "type": "Feature",
  "properties": {
    "gn:admin1_code":"2.0",
    "gn:admin2_code":"95.0",
    "gn:admin3_code":"9576.0",
    "gn:admin4_code":"9576113.0",
    "gn:asciiname":"Appelhof",
    "gn:country_code":"DE",
    "gn:dem":384,
    "gn:feature_class":"P",
    "gn:feature_code":"PPL",
    "gn:name":"Appelhof",
    "gn:population":0,
    "gn:timezone":"Europe/Berlin",
    "iso:country":"DE",
    "wof:name":"Appelhof",
    "wof:placetype":"neighbourhood"
},
  "geometry": {"coordinates":[11.21281,49.24367],"type":"Point"}
}