{
  "type": "Feature",
  "properties": {
    "iso:country":"DE",
    "name:ceb_x_preferred":[
        "H\u00f6fen"
    ],
    "name:deu_x_colloquial":[
        "Hoefen",
        "Hofen"
    ],
    "name:deu_x_preferred":[
        "H\u00f6fen"
    ],
    "name:epo_x_preferred":[
        "H\u00f6fen"
    ],
    "name:fra_x_preferred":[
        "H\u00f6fen"
    ],
    "name:ita_x_preferred":[
        "H\u00f6fen"
    ],
    "name:lmo_x_preferred":[
        "H\u00f6fen"
    ],
    "name:nld_x_preferred":[
        "H\u00f6fen"
    ],
    "name:pol_x_preferred":[
        "H\u00f6fen"
    ],
    "name:rus_x_preferred":[
        "\u0425\u0451\u0444\u0435\u043d"
    ],
    "name:swe_x_preferred":[
        "H\u00f6fen"
    ],
    "name:unk_x_variant":[
        "H\u00f6fen"
    ],
    "qs:gn_fcode":"PPL",
    "qs:gn_local":0,
    "qs:gn_namadm1":"02",
    "qs:gn_name":"H\u00f6fen",
    "qs:local_max":1488,
    "qs:local_sum":4358,
    "qs:localhoods":13,
    "qs:name":"H\u00f6fen",
    "qs:name_adm0":"Deutschland",
    "qs:name_adm1":"Bayern",
    "qs:name_adm2":"Stadtkreis F\u00fcrth",
    "qs:name_lau":"Stadtteil F\u00fcrth",
    "qs:name_local":"Stadtteil F\u00fcrth",
    "qs:photo_max":141,
    "qs:photo_sum":575,
    "qs:placetype":"Suburb",
    "qs:quad_count":21,
    "qs:woe_adm0":23424829,
    "qs:woe_adm1":2345482,
    "qs:woe_adm2":20071091,
    "qs:woe_lau":28350201,
    "qs:woe_local":28350201,
    "qs:woe_ver":"7.10.0",
    "wd:wordcount":90,
    "wof:lang":[
        "ger"
    ],
    "wof:name":"H\u00f6fen",
    "wof:placetype":"neighbourhood"
},
  "geometry": {"coordinates":[11.011236,49.449554],"type":"Point"}
}