{
  "type": "Feature",
  "properties": {
    "gn:admin1_code":"1",
    "gn:admin2_code":"82.0",
    "gn:admin3_code":"8237.0",
    "gn:admin4_code":"8237004.0",
    "gn:asciiname":"Mittellangenbach",
    "gn:country_code":"DE",
    "gn:dem":636,
    "gn:feature_class":"P",
    "gn:feature_code":"PPLL",
    "gn:name":"Mittellangenbach",
    "gn:population":0,
    "gn:timezone":"Europe/Berlin",
    "iso:country":"DE",
    "wof:name":"Mittellangenbach",
    "wof:placetype":"neighbourhood"
},
  "geometry": {"coordinates":[8.28055,48.58683],"type":"Point"}
}