{
  "type": "Feature",
  "properties": {
    "gn:gn_country":"DE",
    "gn:gn_fcode":"PPLA4",
    "gn:gn_pop":260,
    "gn:population":260,
    "iso:country":"DE",
    "name:baq_x_preferred":[
        "R\u00f6hrig"
    ],
    "name:chi_x_preferred":[
        "\u52d2\u8d6b\u91cc\u5e0c"
    ],
    "name:dut_x_preferred":[
        "R\u00f6hrig"
    ],
    "name:eng_x_preferred":[
        "R\u00f6hrig"
    ],
    "name:epo_x_preferred":[
        "R\u00f6hrig"
    ],
    "name:fre_x_preferred":[
        "R\u00f6hrig"
    ],
    "name:ger_x_preferred":[
        "R\u00f6hrig"
    ],
    "name:hun_x_preferred":[
        "R\u00f6hrig"
    ],
    "name:ita_x_preferred":[
        "R\u00f6hrig"
    ],
    "name:kaz_x_preferred":[
        "\u0420\u0451\u0440\u0438\u0433"
    ],
    "name:kir_x_preferred":[
        "\u0420\u04e9\u0440\u0438\u0433"
    ],
    "name:mac_x_preferred":[
        "\u0420\u0435\u0440\u0438\u0433"
    ],
    "name:may_x_preferred":[
        "R\u00f6hrig"
    ],
    "name:per_x_preferred":[
        "\u0631\u0648\u0647\u0631\u06cc\u06af"
    ],
    "name:pol_x_preferred":[
        "R\u00f6hrig"
    ],
    "name:por_x_preferred":[
        "R\u00f6hrig"
    ],
    "name:rum_x_preferred":[
        "R\u00f6hrig"
    ],
    "name:rus_x_preferred":[
        "\u0420\u0451\u0440\u0438\u0433"
    ],
    "name:srp_x_preferred":[
        "\u0420\u0435\u0440\u0438\u0433"
    ],
    "name:ukr_x_preferred":[
        "\u0420\u0435\u0440\u0456\u0433"
    ],
    "name:uzb_x_preferred":[
        "R\u00f6hrig"
    ],
    "name:vie_x_preferred":[
        "R\u00f6hrig"
    ],
    "name:vol_x_preferred":[
        "R\u00f6hrig"
    ],
    "name:war_x_preferred":[
        "R\u00f6hrig"
    ],
    "qs_pg:aaroncc":"DE",
    "qs_pg:gn_country":"DE",
    "qs_pg:gn_fcode":"PPLA4",
    "qs_pg:gn_pop":260,
    "qs_pg:name":"R\u00f6hrig",
    "qs_pg:photos_9r":0,
    "qs_pg:photos_sr":0,
    "qs_pg:pop_sr":2,
    "qs_pg:qs_pg_placetype":"locality",
    "wof:name":"R\u00f6hrig",
    "wof:placetype":"locality",
    "wof:population":260
},
  "geometry": {"coordinates":[10.03333,51.33333],"type":"Point"}
}