{
  "type": "Feature",
  "properties": {
    "gn:admin1_code":"6",
    "gn:admin2_code":"0.0",
    "gn:admin3_code":"3462.0",
    "gn:admin4_code":"3462019.0",
    "gn:asciiname":"Kloster",
    "gn:country_code":"DE",
    "gn:dem":4,
    "gn:feature_class":"P",
    "gn:feature_code":"PPL",
    "gn:name":"Kloster",
    "gn:population":0,
    "gn:timezone":"Europe/Berlin",
    "iso:country":"DE",
    "name:ceb_x_preferred":[
        "Kloster"
    ],
    "name:dan_x_preferred":[
        "Kloster"
    ],
    "name:deu_x_preferred":[
        "Kloster"
    ],
    "name:ita_x_preferred":[
        "Kloster"
    ],
    "name:nld_x_preferred":[
        "Kloster"
    ],
    "name:pol_x_preferred":[
        "Kloster"
    ],
    "name:swe_x_preferred":[
        "Kloster"
    ],
    "wof:name":"Kloster",
    "wof:placetype":"neighbourhood"
},
  "geometry": {"coordinates":[7.76666,53.53178000000001],"type":"Point"}
}