{
  "type": "Feature",
  "properties": {
    "gn:admin1_code":"1.0",
    "gn:admin2_code":"84.0",
    "gn:admin3_code":"8415.0",
    "gn:admin4_code":"8415093.0",
    "gn:asciiname":"Bleichstetten",
    "gn:country_code":"DE",
    "gn:dem":768,
    "gn:feature_class":"P",
    "gn:feature_code":"PPL",
    "gn:name":"Bleichstetten",
    "gn:population":0,
    "gn:timezone":"Europe/Berlin",
    "iso:country":"DE",
    "wof:name":"Bleichstetten",
    "wof:placetype":"neighbourhood"
},
  "geometry": {"coordinates":[9.35656,48.46193],"type":"Point"}
}