{
  "type": "Feature",
  "properties": {
    "gn:admin1_code":"2.0",
    "gn:admin2_code":"97.0",
    "gn:admin3_code":"9779.0",
    "gn:admin4_code":"9779131.0",
    "gn:asciiname":"Auchsesheim",
    "gn:country_code":"DE",
    "gn:dem":404,
    "gn:feature_class":"P",
    "gn:feature_code":"PPL",
    "gn:name":"Auchsesheim",
    "gn:population":0,
    "gn:timezone":"Europe/Berlin",
    "iso:country":"DE",
    "wof:name":"Auchsesheim",
    "wof:placetype":"neighbourhood"
},
  "geometry": {"coordinates":[10.78194,48.68945],"type":"Point"}
}