{
  "type": "Feature",
  "properties": {
    "gn:admin1_code":"2",
    "gn:admin2_code":"91.0",
    "gn:admin3_code":"9189.0",
    "gn:admin4_code":"9189152.0",
    "gn:asciiname":"Lanzing",
    "gn:country_code":"DE",
    "gn:dem":462,
    "gn:feature_class":"P",
    "gn:feature_code":"PPL",
    "gn:name":"Lanzing",
    "gn:population":0,
    "gn:timezone":"Europe/Berlin",
    "iso:country":"DE",
    "name:deu_x_preferred":[
        "Lanzing"
    ],
    "wof:name":"Lanzing",
    "wof:placetype":"neighbourhood"
},
  "geometry": {"coordinates":[12.72804,48.05411],"type":"Point"}
}