{
  "type": "Feature",
  "properties": {
    "gn:admin1_code":"6.0",
    "gn:admin2_code":"0.0",
    "gn:admin3_code":"3358.0",
    "gn:admin4_code":"3358004.0",
    "gn:asciiname":"Bommelsen",
    "gn:country_code":"DE",
    "gn:dem":70,
    "gn:feature_class":"P",
    "gn:feature_code":"PPL",
    "gn:name":"Bommelsen",
    "gn:population":0,
    "gn:timezone":"Europe/Berlin",
    "iso:country":"DE",
    "name:deu_x_preferred":[
        "Bommelsen"
    ],
    "wof:name":"Bommelsen",
    "wof:placetype":"neighbourhood"
},
  "geometry": {"coordinates":[9.69028,52.94553000000001],"type":"Point"}
}