{
  "type": "Feature",
  "properties": {
    "gn:admin1_code":"11",
    "gn:admin2_code":"0.0",
    "gn:admin3_code":"12068.0",
    "gn:admin4_code":"12068468.0",
    "gn:asciiname":"Goldbeck",
    "gn:country_code":"DE",
    "gn:dem":57,
    "gn:feature_class":"P",
    "gn:feature_code":"PPL",
    "gn:name":"Goldbeck",
    "gn:population":0,
    "gn:timezone":"Europe/Berlin",
    "iso:country":"DE",
    "name:bak_x_preferred":[
        "\u0413\u043e\u043b\u044c\u0434\u0431\u0435\u043a"
    ],
    "name:ceb_x_preferred":[
        "Goldbeck"
    ],
    "name:deu_x_preferred":[
        "Goldbeck"
    ],
    "name:epo_x_preferred":[
        "Goldbeck"
    ],
    "name:fas_x_preferred":[
        "\u06af\u0648\u0644\u062f\u0628\u06a9"
    ],
    "name:fra_x_preferred":[
        "Goldbeck"
    ],
    "name:hun_x_preferred":[
        "Goldbeck"
    ],
    "name:ita_x_preferred":[
        "Goldbeck"
    ],
    "name:kaz_x_preferred":[
        "\u0413\u043e\u043b\u044c\u0434\u0431\u0435\u043a"
    ],
    "name:kir_x_preferred":[
        "\u0413\u043e\u043b\u044c\u0434\u0431\u0435\u043a"
    ],
    "name:mkd_x_preferred":[
        "\u0413\u043e\u043b\u0434\u0431\u0435\u043a"
    ],
    "name:msa_x_preferred":[
        "Goldbeck"
    ],
    "name:nld_x_preferred":[
        "Goldbeck"
    ],
    "name:pol_x_preferred":[
        "Goldbeck"
    ],
    "name:ron_x_preferred":[
        "Goldbeck"
    ],
    "name:rus_x_preferred":[
        "\u0413\u043e\u043b\u044c\u0434\u0431\u0435\u043a"
    ],
    "name:spa_x_preferred":[
        "Goldbeck"
    ],
    "name:srp_x_preferred":[
        "\u0413\u043e\u043b\u0434\u0431\u0435\u043a"
    ],
    "name:ukr_x_preferred":[
        "\u0413\u043e\u043b\u044c\u0434\u0431\u0435\u043a"
    ],
    "name:uzb_x_preferred":[
        "Goldbeck"
    ],
    "name:vie_x_preferred":[
        "Goldbeck"
    ],
    "name:vol_x_preferred":[
        "Goldbeck"
    ],
    "name:war_x_preferred":[
        "Goldbeck"
    ],
    "wof:name":"Goldbeck",
    "wof:placetype":"neighbourhood"
},
  "geometry": {"coordinates":[12.51549,53.13391],"type":"Point"}
}