{
  "type": "Feature",
  "properties": {
    "gn:admin1_code":"2",
    "gn:admin2_code":"91.0",
    "gn:admin3_code":"9187.0",
    "gn:admin4_code":"9187139.0",
    "gn:asciiname":"Hangendobl",
    "gn:country_code":"DE",
    "gn:dem":557,
    "gn:feature_class":"P",
    "gn:feature_code":"PPL",
    "gn:name":"Hangendobl",
    "gn:population":0,
    "gn:timezone":"Europe/Berlin",
    "iso:country":"DE",
    "wof:name":"Hangendobl",
    "wof:placetype":"neighbourhood"
},
  "geometry": {"coordinates":[12.29522,47.96329],"type":"Point"}
}