{
  "type": "Feature",
  "properties": {
    "gn:admin1_code":"2",
    "gn:admin2_code":"97.0",
    "gn:admin3_code":"9771.0",
    "gn:admin4_code":"9771112.0",
    "gn:asciiname":"Haunswies",
    "gn:country_code":"DE",
    "gn:dem":479,
    "gn:feature_class":"P",
    "gn:feature_code":"PPL",
    "gn:name":"Haunswies",
    "gn:population":0,
    "gn:timezone":"Europe/Berlin",
    "iso:country":"DE",
    "wof:name":"Haunswies",
    "wof:placetype":"neighbourhood"
},
  "geometry": {"coordinates":[11.00427,48.45515],"type":"Point"}
}