{
  "type": "Feature",
  "properties": {
    "gn:country":"DE",
    "gn:fcode":"PPL",
    "gn:population":0,
    "iso:country":"DE",
    "name:ceb_x_preferred":[
        "Muggendorf"
    ],
    "name:ces_x_preferred":[
        "Muggendorf"
    ],
    "name:deu_x_preferred":[
        "Muggendorf"
    ],
    "name:epo_x_preferred":[
        "Muggendorf"
    ],
    "name:fas_x_preferred":[
        "\u0645\u0648\u06af\u0646\u062f\u0648\u0631\u0641"
    ],
    "name:fra_x_preferred":[
        "Muggendorf"
    ],
    "name:hun_x_preferred":[
        "Muggendorf"
    ],
    "name:ita_x_preferred":[
        "Muggendorf"
    ],
    "name:kaz_x_preferred":[
        "\u041c\u0443\u0433\u0433\u0435\u043d\u0434\u043e\u0440\u0444"
    ],
    "name:nld_x_preferred":[
        "Muggendorf"
    ],
    "name:pol_x_preferred":[
        "Muggendorf"
    ],
    "name:por_x_preferred":[
        "Muggendorf"
    ],
    "name:rus_x_preferred":[
        "\u041c\u0443\u0433\u0433\u0435\u043d\u0434\u043e\u0440\u0444"
    ],
    "name:slk_x_preferred":[
        "Muggendorf"
    ],
    "name:spa_x_preferred":[
        "Muggendorf"
    ],
    "name:swe_x_preferred":[
        "Muggendorf"
    ],
    "name:uzb_x_preferred":[
        "Muggendorf"
    ],
    "name:vie_x_preferred":[
        "Muggendorf"
    ],
    "name:vol_x_preferred":[
        "Muggendorf"
    ],
    "name:war_x_preferred":[
        "Muggendorf"
    ],
    "name:zho_x_preferred":[
        "\u7a46\u6839\u591a\u592b"
    ],
    "qs_pg:aaroncc":"DE",
    "qs_pg:gn_country":"DE",
    "qs_pg:gn_fcode":"PPL",
    "qs_pg:gn_pop":0,
    "qs_pg:name":"Muggendorf",
    "qs_pg:name_adm0":"Deutschland",
    "qs_pg:name_adm1":"Bayern",
    "qs_pg:photos_9k":1,
    "qs_pg:photos_9r":1,
    "qs_pg:photos_all":6,
    "qs_pg:photos_sr":0,
    "qs_pg:pop_sr":0,
    "qs_pg:qs_pg_placetype":"locality",
    "qs_pg:qs_pg_placetype_gp":"Town",
    "qs_pg:woe_adm0":23424829,
    "woe:adm0_id":23424829,
    "woe:name_adm0":"Deutschland",
    "woe:name_adm1":"Bayern",
    "woe:placetype":"Town",
    "wof:name":"Muggendorf",
    "wof:placetype":"neighbourhood"
},
  "geometry": {"coordinates":[11.26164,49.80306],"type":"Point"}
}