{
  "type": "Feature",
  "properties": {
    "gn:admin1_code":"2",
    "gn:admin2_code":"93.0",
    "gn:admin3_code":"9374.0",
    "gn:admin4_code":"9374137.0",
    "gn:asciiname":"Gebhardsreuth",
    "gn:country_code":"DE",
    "gn:dem":502,
    "gn:feature_class":"P",
    "gn:feature_code":"PPL",
    "gn:name":"Gebhardsreuth",
    "gn:population":0,
    "gn:timezone":"Europe/Berlin",
    "iso:country":"DE",
    "wof:name":"Gebhardsreuth",
    "wof:placetype":"neighbourhood"
},
  "geometry": {"coordinates":[12.4297,49.60048],"type":"Point"}
}