{
  "type": "Feature",
  "properties": {
    "gn:country":"DE",
    "gn:fcode":"PPL",
    "gn:population":0,
    "iso:country":"DE",
    "qs_pg:aaroncc":"DE",
    "qs_pg:gn_country":"DE",
    "qs_pg:gn_fcode":"PPL",
    "qs_pg:gn_pop":0,
    "qs_pg:name":"M\u00f6ltenort",
    "qs_pg:name_adm0":"Deutschland",
    "qs_pg:name_adm1":"Schleswig-Holstein",
    "qs_pg:photos":134,
    "qs_pg:photos_1k":27,
    "qs_pg:photos_9k":1,
    "qs_pg:photos_9r":3,
    "qs_pg:photos_all":134,
    "qs_pg:photos_sr":3,
    "qs_pg:pop_sr":0,
    "qs_pg:qs_pg_placetype":"locality",
    "qs_pg:qs_pg_placetype_gp":"Town",
    "qs_pg:woe_adm0":23424829,
    "woe:adm0_id":23424829,
    "woe:name_adm0":"Deutschland",
    "woe:name_adm1":"Schleswig-Holstein",
    "woe:placetype":"Town",
    "wof:name":"M\u00f6ltenort",
    "wof:placetype":"neighbourhood"
},
  "geometry": {"coordinates":[10.20345,54.37607],"type":"Point"}
}