{
  "type": "Feature",
  "properties": {
    "iso:country":"DE",
    "qs_pg:aaroncc":"DE",
    "qs_pg:name":"Bosen",
    "qs_pg:name_adm0":"Deutschland",
    "qs_pg:name_adm1":"Saarland",
    "qs_pg:photos":45,
    "qs_pg:photos_1k":9,
    "qs_pg:photos_9k":1,
    "qs_pg:photos_9r":2,
    "qs_pg:photos_all":45,
    "qs_pg:photos_sr":2,
    "qs_pg:pop_sr":0,
    "qs_pg:qs_pg_placetype":"locality",
    "qs_pg:qs_pg_placetype_gp":"Town",
    "qs_pg:woe_adm0":23424829,
    "woe:adm0_id":23424829,
    "woe:name_adm0":"Deutschland",
    "woe:name_adm1":"Saarland",
    "woe:placetype":"Town",
    "wof:name":"Bosen",
    "wof:placetype":"neighbourhood"
},
  "geometry": {"coordinates":[7.064895,49.567532],"type":"Point"}
}