{
  "type": "Feature",
  "properties": {
    "gn:admin1_code":"2",
    "gn:admin2_code":"93.0",
    "gn:admin3_code":"9373.0",
    "gn:admin4_code":"9373160.0",
    "gn:asciiname":"Freihausen",
    "gn:country_code":"DE",
    "gn:dem":491,
    "gn:feature_class":"P",
    "gn:feature_code":"PPL",
    "gn:name":"Freihausen",
    "gn:population":0,
    "gn:timezone":"Europe/Berlin",
    "iso:country":"DE",
    "name:deu_x_preferred":[
        "Freihausen"
    ],
    "name:fas_x_preferred":[
        "\u0641\u0631\u0627\u06cc\u0647\u0627\u0648\u0632\u0646"
    ],
    "name:fra_x_preferred":[
        "Freihausen"
    ],
    "wof:name":"Freihausen",
    "wof:placetype":"neighbourhood"
},
  "geometry": {"coordinates":[11.55908,49.14595],"type":"Point"}
}