{
  "type": "Feature",
  "properties": {
    "gn:country":"DE",
    "gn:fcode":"PPL",
    "gn:population":0,
    "iso:country":"DE",
    "name:ceb_x_preferred":[
        "Hohenzell"
    ],
    "name:deu_x_preferred":[
        "Hohenzell"
    ],
    "name:fas_x_preferred":[
        "\u0647\u0648\u0647\u0646\u062a\u0633\u0644"
    ],
    "name:fra_x_preferred":[
        "Hohenzell"
    ],
    "name:hun_x_preferred":[
        "Hohenzell"
    ],
    "name:ita_x_preferred":[
        "Hohenzell"
    ],
    "name:kaz_x_preferred":[
        "\u0425\u043e\u044d\u043d\u0446\u0435\u043b\u043b\u044c"
    ],
    "name:nld_x_preferred":[
        "Hohenzell"
    ],
    "name:pol_x_preferred":[
        "Hohenzell"
    ],
    "name:por_x_preferred":[
        "Hohenzell"
    ],
    "name:rus_x_preferred":[
        "\u0425\u043e\u044d\u043d\u0446\u0435\u043b\u043b\u044c"
    ],
    "name:slk_x_preferred":[
        "Hohenzell"
    ],
    "name:spa_x_preferred":[
        "Hohenzell"
    ],
    "name:swe_x_preferred":[
        "Hohenzell"
    ],
    "name:uzb_x_preferred":[
        "Hohenzell"
    ],
    "name:vie_x_preferred":[
        "Hohenzell"
    ],
    "name:vol_x_preferred":[
        "Hohenzell"
    ],
    "name:war_x_preferred":[
        "Hohenzell"
    ],
    "name:zho_x_preferred":[
        "\u970d\u6069\u91c7\u5c14"
    ],
    "qs_pg:aaroncc":"DE",
    "qs_pg:gn_country":"DE",
    "qs_pg:gn_fcode":"PPL",
    "qs_pg:gn_pop":0,
    "qs_pg:name":"Hohenzell",
    "qs_pg:name_adm0":"Deutschland",
    "qs_pg:name_adm1":"Bayern",
    "qs_pg:photos_9r":0,
    "qs_pg:photos_sr":0,
    "qs_pg:pop_sr":0,
    "qs_pg:qs_pg_placetype":"locality",
    "qs_pg:qs_pg_placetype_gp":"Town",
    "qs_pg:woe_adm0":23424829,
    "woe:adm0_id":23424829,
    "woe:name_adm0":"Deutschland",
    "woe:name_adm1":"Bayern",
    "woe:placetype":"Town",
    "wof:name":"Hohenzell",
    "wof:placetype":"neighbourhood"
},
  "geometry": {"coordinates":[11.18537,48.34972],"type":"Point"}
}