{
  "type": "Feature",
  "properties": {
    "gn:admin1_code":"6",
    "gn:admin2_code":"0.0",
    "gn:admin3_code":"3354.0",
    "gn:admin4_code":"3354027.0",
    "gn:asciiname":"Timmeitz",
    "gn:country_code":"DE",
    "gn:dem":94,
    "gn:feature_class":"P",
    "gn:feature_code":"PPL",
    "gn:name":"Timmeitz",
    "gn:population":0,
    "gn:timezone":"Europe/Berlin",
    "iso:country":"DE",
    "wof:name":"Timmeitz",
    "wof:placetype":"neighbourhood"
},
  "geometry": {"coordinates":[10.86883,53.06149],"type":"Point"}
}