{
  "type": "Feature",
  "properties": {
    "gn:admin1_code":"14",
    "gn:admin2_code":"0.0",
    "gn:admin3_code":"15083.0",
    "gn:admin4_code":"15083415.0",
    "gn:asciiname":"Gross Germersleben",
    "gn:country_code":"DE",
    "gn:dem":82,
    "gn:feature_class":"P",
    "gn:feature_code":"PPL",
    "gn:name":"Gro\u00df Germersleben",
    "gn:population":0,
    "gn:timezone":"Europe/Berlin",
    "iso:country":"DE",
    "name:nds_x_preferred":[
        "Groten Garmsl\u00e4"
    ],
    "name:osx_x_preferred":[
        "Germisleve"
    ],
    "name:und_x_variant":[
        "Gro\u00df Germersleben"
    ],
    "wof:name":"Gross Germersleben",
    "wof:placetype":"neighbourhood"
},
  "geometry": {"coordinates":[11.36393,52.00424],"type":"Point"}
}