{
  "type": "Feature",
  "properties": {
    "gn:admin1_code":"7",
    "gn:admin2_code":"51.0",
    "gn:admin3_code":"5162.0",
    "gn:admin4_code":"5162012.0",
    "gn:asciiname":"Hackhausen",
    "gn:country_code":"DE",
    "gn:dem":91,
    "gn:feature_class":"P",
    "gn:feature_code":"PPL",
    "gn:name":"Hackhausen",
    "gn:population":0,
    "gn:timezone":"Europe/Berlin",
    "iso:country":"DE",
    "wof:name":"Hackhausen",
    "wof:placetype":"neighbourhood"
},
  "geometry": {"coordinates":[6.47204,51.1043],"type":"Point"}
}