{
  "type": "Feature",
  "properties": {
    "gn:admin1_code":"7",
    "gn:admin2_code":"53.0",
    "gn:admin3_code":"5374.0",
    "gn:admin4_code":"5374012.0",
    "gn:asciiname":"Niedergelpe",
    "gn:country_code":"DE",
    "gn:dem":231,
    "gn:feature_class":"P",
    "gn:feature_code":"PPL",
    "gn:name":"Niedergelpe",
    "gn:population":0,
    "gn:timezone":"Europe/Berlin",
    "iso:country":"DE",
    "wof:name":"Niedergelpe",
    "wof:placetype":"neighbourhood"
},
  "geometry": {"coordinates":[7.48183,51.03469000000001],"type":"Point"}
}