{
  "type": "Feature",
  "properties": {
    "gn:admin1_code":"2",
    "gn:admin2_code":"93.0",
    "gn:admin3_code":"9372.0",
    "gn:admin4_code":"9372144.0",
    "gn:asciiname":"Kager",
    "gn:country_code":"DE",
    "gn:dem":653,
    "gn:feature_class":"P",
    "gn:feature_code":"PPLL",
    "gn:name":"Kager",
    "gn:population":0,
    "gn:timezone":"Europe/Berlin",
    "iso:country":"DE",
    "wof:name":"Kager",
    "wof:placetype":"neighbourhood"
},
  "geometry": {"coordinates":[12.97747,49.23334000000001],"type":"Point"}
}