{
  "type": "Feature",
  "properties": {
    "iso:country":"DE",
    "name:deu_x_preferred":[
        "Kirchfeldsiedlung"
    ],
    "name:unk_x_variant":[
        "Kirchfeldsiedlung"
    ],
    "qs:gn_adm0_cc":"DE",
    "qs:gn_local":2892794,
    "qs:local_max":5751,
    "qs:local_sum":18066,
    "qs:localhoods":10,
    "qs:name":"Kirchfeldsiedlung",
    "qs:name_adm0":"Deutschland",
    "qs:name_adm1":"Baden-W\u00fcrttemberg",
    "qs:name_adm2":"Stadtkreis Karlsruhe",
    "qs:name_lau":"Stadtteil Neureut",
    "qs:name_local":"Karlsruhe",
    "qs:photo_max":554,
    "qs:photo_sum":648,
    "qs:placetype":"Suburb",
    "qs:quad_count":24,
    "qs:woe_adm0":23424829,
    "qs:woe_adm1":2345481,
    "qs:woe_adm2":20071085,
    "qs:woe_lau":26822682,
    "qs:woe_local":664942,
    "qs:woe_ver":"7.10.0",
    "wof:lang":[
        "ger"
    ],
    "wof:name":"Kirchfeldsiedlung",
    "wof:placetype":"neighbourhood"
},
  "geometry": {"coordinates":[8.395568,49.042571],"type":"Point"}
}