{
  "type": "Feature",
  "properties": {
    "gn:admin1_code":"8",
    "gn:admin2_code":"0.0",
    "gn:admin3_code":"7232.0",
    "gn:admin4_code":"7232226.0",
    "gn:asciiname":"Gondelsheim",
    "gn:country_code":"DE",
    "gn:dem":546,
    "gn:feature_class":"P",
    "gn:feature_code":"PPL",
    "gn:name":"Gondelsheim",
    "gn:population":0,
    "gn:timezone":"Europe/Berlin",
    "iso:country":"DE",
    "name:als_x_preferred":[
        "Gondelsheim"
    ],
    "name:ceb_x_preferred":[
        "Gondelsheim"
    ],
    "name:deu_x_preferred":[
        "Gondelsheim"
    ],
    "name:epo_x_preferred":[
        "Gondelsheim"
    ],
    "name:eus_x_preferred":[
        "Gondelsheim"
    ],
    "name:fas_x_preferred":[
        "\u06af\u0648\u0646\u062f\u0644\u0633\u0647\u0627\u06cc\u0645"
    ],
    "name:fra_x_preferred":[
        "Gondelsheim"
    ],
    "name:hrv_x_preferred":[
        "Gondelsheim"
    ],
    "name:hun_x_preferred":[
        "Gondelsheim"
    ],
    "name:ita_x_preferred":[
        "Gondelsheim"
    ],
    "name:kaz_x_preferred":[
        "\u0413\u043e\u043d\u0434\u0435\u043b\u044c\u0441\u0445\u0430\u0439\u043c"
    ],
    "name:kir_x_preferred":[
        "\u0413\u043e\u043d\u0434\u0435\u043b\u044c\u0441\u0445\u0430\u0439\u043c"
    ],
    "name:lat_x_preferred":[
        "Gondelsheim"
    ],
    "name:lmo_x_preferred":[
        "Gondelsheim"
    ],
    "name:msa_x_preferred":[
        "Gondelsheim"
    ],
    "name:nld_x_preferred":[
        "Gondelsheim"
    ],
    "name:pol_x_preferred":[
        "Gondelsheim"
    ],
    "name:por_x_preferred":[
        "Gondelsheim"
    ],
    "name:ron_x_preferred":[
        "Gondelsheim"
    ],
    "name:rus_x_preferred":[
        "\u0413\u043e\u043d\u0434\u0435\u043b\u044c\u0441\u0445\u0430\u0439\u043c"
    ],
    "name:spa_x_preferred":[
        "Gondelsheim"
    ],
    "name:srp_x_preferred":[
        "\u0413\u043e\u043d\u0434\u0435\u043b\u0441\u0445\u0430\u0458\u043c"
    ],
    "name:ukr_x_preferred":[
        "\u0413\u043e\u043d\u0434\u0435\u043b\u044c\u0441\u0433\u0430\u0439\u043c"
    ],
    "name:uzb_x_preferred":[
        "Gondelsheim"
    ],
    "name:vie_x_preferred":[
        "Gondelsheim"
    ],
    "name:vol_x_preferred":[
        "Gondelsheim"
    ],
    "name:war_x_preferred":[
        "Gondelsheim"
    ],
    "wof:name":"Gondelsheim",
    "wof:placetype":"neighbourhood"
},
  "geometry": {"coordinates":[6.50208,50.23401],"type":"Point"}
}