{
  "type": "Feature",
  "properties": {
    "gn:admin1_code":"2",
    "gn:admin2_code":"97.0",
    "gn:admin3_code":"9778.0",
    "gn:admin4_code":"9778137.0",
    "gn:asciiname":"Traunried",
    "gn:country_code":"DE",
    "gn:dem":588,
    "gn:feature_class":"P",
    "gn:feature_code":"PPL",
    "gn:name":"Traunried",
    "gn:population":0,
    "gn:timezone":"Europe/Berlin",
    "iso:country":"DE",
    "name:und_x_variant":[
        "Traumried",
        "Traunried"
    ],
    "wof:name":"Traunried",
    "wof:placetype":"neighbourhood"
},
  "geometry": {"coordinates":[10.66396,48.1604],"type":"Point"}
}