{
  "type": "Feature",
  "properties": {
    "gn:admin1_code":"13",
    "gn:admin2_code":"0.0",
    "gn:admin3_code":"14524.0",
    "gn:admin4_code":"14524120.0",
    "gn:asciiname":"Corba",
    "gn:country_code":"DE",
    "gn:dem":449,
    "gn:feature_class":"P",
    "gn:feature_code":"PPL",
    "gn:name":"Corba",
    "gn:population":0,
    "gn:timezone":"Europe/Berlin",
    "iso:country":"DE",
    "wof:name":"Corba",
    "wof:placetype":"neighbourhood"
},
  "geometry": {"coordinates":[12.75,50.81667],"type":"Point"}
}