{
  "type": "Feature",
  "properties": {
    "gn:admin1_code":"6",
    "gn:admin2_code":"0.0",
    "gn:admin3_code":"3355.0",
    "gn:admin4_code":"3355049.0",
    "gn:asciiname":"Gross Banratz",
    "gn:cc2":"DE",
    "gn:country_code":"DE",
    "gn:dem":10,
    "gn:feature_class":"P",
    "gn:feature_code":"PPL",
    "gn:name":"Gro\u00df Banratz",
    "gn:population":0,
    "gn:timezone":"Europe/Berlin",
    "iso:country":"DE",
    "name:und_x_variant":[
        "Gro\u00df Banrutz",
        "Gro\u00df Banratz"
    ],
    "wof:name":"Gross Banratz",
    "wof:placetype":"neighbourhood"
},
  "geometry": {"coordinates":[10.93905,53.24119],"type":"Point"}
}