{
  "type": "Feature",
  "properties": {
    "gn:admin1_code":"6.0",
    "gn:admin2_code":"0.0",
    "gn:admin3_code":"3459.0",
    "gn:admin4_code":"3459020.0",
    "gn:asciiname":"Altenhagen",
    "gn:country_code":"DE",
    "gn:dem":124,
    "gn:feature_class":"P",
    "gn:feature_code":"PPL",
    "gn:name":"Altenhagen",
    "gn:population":0,
    "gn:timezone":"Europe/Berlin",
    "iso:country":"DE",
    "name:deu_x_preferred":[
        "Altenhagen (Hagen am Teuteburger Wald)"
    ],
    "name:osx_x_preferred":[
        "Hagen [a. 1097]"
    ],
    "wof:name":"Altenhagen",
    "wof:placetype":"neighbourhood"
},
  "geometry": {"coordinates":[7.98646,52.20172],"type":"Point"}
}