{
  "type": "Feature",
  "properties": {
    "gn:admin1_code":"6.0",
    "gn:admin2_code":"0.0",
    "gn:admin3_code":"3459.0",
    "gn:admin4_code":"3459020.0",
    "gn:asciiname":"Altenhagen",
    "gn:country_code":"DE",
    "gn:dem":124,
    "gn:feature_class":"P",
    "gn:feature_code":"PPL",
    "gn:name":"Altenhagen",
    "gn:population":0,
    "gn:timezone":"Europe/Berlin",
    "iso:country":"DE",
    "name:ceb_x_preferred":[
        "Altenhagen"
    ],
    "name:deu_x_preferred":[
        "Altenhagen (Hagen am Teuteburger Wald)"
    ],
    "name:deu_x_variant":[
        "Altenhagen"
    ],
    "name:epo_x_preferred":[
        "Altenhagen"
    ],
    "name:fas_x_preferred":[
        "\u0627\u0644\u062a\u0646\u0647\u0627\u06af\u0646"
    ],
    "name:fra_x_preferred":[
        "Altenhagen"
    ],
    "name:hun_x_preferred":[
        "Altenhagen"
    ],
    "name:ita_x_preferred":[
        "Altenhagen"
    ],
    "name:kaz_x_preferred":[
        "\u0410\u043b\u044c\u0442\u0435\u043d\u0445\u0430\u0433\u0435\u043d"
    ],
    "name:kir_x_preferred":[
        "\u0410\u043b\u044c\u0442\u0435\u043d\u0445\u0430\u0433\u0435\u043d"
    ],
    "name:mkd_x_preferred":[
        "\u0410\u043b\u0442\u0435\u043d\u0445\u0430\u0433\u0435\u043d"
    ],
    "name:msa_x_preferred":[
        "Altenhagen"
    ],
    "name:nld_x_preferred":[
        "Altenhagen"
    ],
    "name:osx_x_preferred":[
        "Hagen [a. 1097]"
    ],
    "name:pol_x_preferred":[
        "Altenhagen"
    ],
    "name:ron_x_preferred":[
        "Altenhagen"
    ],
    "name:rus_x_preferred":[
        "\u0410\u043b\u044c\u0442\u0435\u043d\u0445\u0430\u0433\u0435\u043d"
    ],
    "name:spa_x_preferred":[
        "Altenhagen"
    ],
    "name:srp_x_preferred":[
        "\u0410\u043b\u0442\u0435\u043d\u0445\u0430\u0433\u0435\u043d"
    ],
    "name:ukr_x_preferred":[
        "\u0410\u043b\u044c\u0442\u0435\u043d\u0433\u0430\u0433\u0435\u043d"
    ],
    "name:uzb_x_preferred":[
        "Altenhagen"
    ],
    "name:vol_x_preferred":[
        "Altenhagen"
    ],
    "name:war_x_preferred":[
        "Altenhagen"
    ],
    "name:zho_x_preferred":[
        "\u963f\u5c14\u6ed5\u54c8\u6839"
    ],
    "wof:name":"Altenhagen",
    "wof:placetype":"neighbourhood"
},
  "geometry": {"coordinates":[7.98646,52.20172],"type":"Point"}
}