{
  "type": "Feature",
  "properties": {
    "gn:admin1_code":"10",
    "gn:admin2_code":"0.0",
    "gn:admin3_code":"1061.0",
    "gn:admin4_code":"1061044.0",
    "gn:asciiname":"Horstheide",
    "gn:country_code":"DE",
    "gn:dem":6,
    "gn:feature_class":"P",
    "gn:feature_code":"PPL",
    "gn:name":"Horstheide",
    "gn:population":0,
    "gn:timezone":"Europe/Berlin",
    "iso:country":"DE",
    "wof:name":"Horstheide",
    "wof:placetype":"neighbourhood"
},
  "geometry": {"coordinates":[9.65303,53.80293],"type":"Point"}
}