{
  "type": "Feature",
  "properties": {
    "gn:admin1_code":"5",
    "gn:admin2_code":"66.0",
    "gn:admin3_code":"6632.0",
    "gn:admin4_code":"6632002.0",
    "gn:asciiname":"Sorga",
    "gn:country_code":"DE",
    "gn:dem":226,
    "gn:feature_class":"P",
    "gn:feature_code":"PPL",
    "gn:name":"Sorga",
    "gn:population":0,
    "gn:timezone":"Europe/Berlin",
    "iso:country":"DE",
    "wof:name":"Sorga",
    "wof:placetype":"neighbourhood"
},
  "geometry": {"coordinates":[9.7606,50.86857],"type":"Point"}
}