{
  "type": "Feature",
  "properties": {
    "gn:admin1_code":"1",
    "gn:admin2_code":"84.0",
    "gn:admin3_code":"8436.0",
    "gn:admin4_code":"8436011.0",
    "gn:asciiname":"Butzenberg",
    "gn:country_code":"DE",
    "gn:dem":607,
    "gn:feature_class":"P",
    "gn:feature_code":"PPL",
    "gn:name":"Butzenberg",
    "gn:population":0,
    "gn:timezone":"Europe/Berlin",
    "iso:country":"DE",
    "wof:name":"Butzenberg",
    "wof:placetype":"neighbourhood"
},
  "geometry": {"coordinates":[9.67959,47.81367],"type":"Point"}
}