{
  "type": "Feature",
  "properties": {
    "gn:country":"DE",
    "gn:fcode":"PPL",
    "gn:population":0,
    "iso:country":"DE",
    "name:deu_x_preferred":[
        "Hoffeld"
    ],
    "name:epo_x_preferred":[
        "Hoffeld"
    ],
    "name:eus_x_preferred":[
        "Hoffeld"
    ],
    "name:fas_x_preferred":[
        "\u0647\u0648\u0641\u0644\u062f"
    ],
    "name:fra_x_preferred":[
        "Hoffeld"
    ],
    "name:hun_x_preferred":[
        "Hoffeld"
    ],
    "name:ita_x_preferred":[
        "Hoffeld"
    ],
    "name:kaz_x_preferred":[
        "\u0425\u043e\u0444\u0444\u0435\u043b\u044c\u0434"
    ],
    "name:kir_x_preferred":[
        "\u0425\u043e\u0444\u0444\u0435\u043b\u044c\u0434"
    ],
    "name:msa_x_preferred":[
        "Hoffeld"
    ],
    "name:nld_x_preferred":[
        "Hoffeld"
    ],
    "name:pol_x_preferred":[
        "Hoffeld"
    ],
    "name:por_x_preferred":[
        "Hoffeld"
    ],
    "name:ron_x_preferred":[
        "Hoffeld"
    ],
    "name:rus_x_preferred":[
        "\u0425\u043e\u0444\u0444\u0435\u043b\u044c\u0434"
    ],
    "name:spa_x_preferred":[
        "Hoffeld"
    ],
    "name:srp_x_preferred":[
        "\u0425\u043e\u0444\u0435\u043b\u0434"
    ],
    "name:ukr_x_preferred":[
        "\u0413\u043e\u0444\u0444\u0435\u043b\u044c\u0434"
    ],
    "name:uzb_x_preferred":[
        "Hoffeld"
    ],
    "name:vie_x_preferred":[
        "Hoffeld"
    ],
    "name:vol_x_preferred":[
        "Hoffeld"
    ],
    "name:war_x_preferred":[
        "Hoffeld"
    ],
    "name:zho_x_preferred":[
        "\u970d\u8d39\u5c14\u5fb7"
    ],
    "qs_pg:aaroncc":"DE",
    "qs_pg:gn_country":"DE",
    "qs_pg:gn_fcode":"PPL",
    "qs_pg:gn_pop":0,
    "qs_pg:name":"Hoffeld",
    "qs_pg:name_adm0":"Deutschland",
    "qs_pg:name_adm1":"Rheinland-Pfalz",
    "qs_pg:photos_9r":0,
    "qs_pg:photos_sr":0,
    "qs_pg:pop_sr":0,
    "qs_pg:qs_pg_placetype":"locality",
    "qs_pg:qs_pg_placetype_gp":"Town",
    "qs_pg:woe_adm0":23424829,
    "woe:adm0_id":23424829,
    "woe:name_adm0":"Deutschland",
    "woe:name_adm1":"Rheinland-Pfalz",
    "woe:placetype":"Town",
    "wof:name":"Hoffeld",
    "wof:placetype":"neighbourhood"
},
  "geometry": {"coordinates":[7.15306,49.51038],"type":"Point"}
}