{
  "type": "Feature",
  "properties": {
    "gn:admin1_code":"12",
    "gn:admin2_code":"0.0",
    "gn:admin3_code":"13071.0",
    "gn:admin4_code":"13071032.0",
    "gn:asciiname":"Liepener Teerofen",
    "gn:cc2":"DE",
    "gn:country_code":"DE",
    "gn:dem":61,
    "gn:feature_class":"P",
    "gn:feature_code":"PPL",
    "gn:name":"Liepener Teerofen",
    "gn:population":0,
    "gn:timezone":"Europe/Berlin",
    "iso:country":"DE",
    "name:und_x_variant":[
        "Liepener Theerofen",
        "Liepener Teerofen"
    ],
    "wof:name":"Liepener Teerofen",
    "wof:placetype":"neighbourhood"
},
  "geometry": {"coordinates":[12.76667,53.66667],"type":"Point"}
}