{
  "type": "Feature",
  "properties": {
    "gn:admin1_code":"1",
    "gn:admin2_code":"83.0",
    "gn:admin3_code":"8317.0",
    "gn:admin4_code":"8317102.0",
    "gn:asciiname":"Furschenbach",
    "gn:country_code":"DE",
    "gn:dem":258,
    "gn:feature_class":"P",
    "gn:feature_code":"PPL",
    "gn:name":"Furschenbach",
    "gn:population":0,
    "gn:timezone":"Europe/Berlin",
    "iso:country":"DE",
    "wof:name":"Furschenbach",
    "wof:placetype":"neighbourhood"
},
  "geometry": {"coordinates":[8.13679,48.57641],"type":"Point"}
}