{
  "type": "Feature",
  "properties": {
    "gn:admin1_code":"11",
    "gn:admin2_code":"0.0",
    "gn:admin3_code":"12064.0",
    "gn:admin4_code":"12064222.0",
    "gn:asciiname":"Sternkrug",
    "gn:country_code":"DE",
    "gn:dem":144,
    "gn:feature_class":"P",
    "gn:feature_code":"PPL",
    "gn:name":"Sternkrug",
    "gn:population":0,
    "gn:timezone":"Europe/Berlin",
    "iso:country":"DE",
    "wof:name":"Sternkrug",
    "wof:placetype":"neighbourhood"
},
  "geometry": {"coordinates":[13.96036,52.7405],"type":"Point"}
}