{
  "type": "Feature",
  "properties": {
    "gn:admin1_code":"2",
    "gn:admin2_code":"95.0",
    "gn:admin3_code":"9574.0",
    "gn:admin4_code":"9574112.0",
    "gn:asciiname":"Sturzelhof",
    "gn:country_code":"DE",
    "gn:dem":446,
    "gn:feature_class":"P",
    "gn:feature_code":"PPL",
    "gn:name":"St\u00fcrzelhof",
    "gn:population":0,
    "gn:timezone":"Europe/Berlin",
    "iso:country":"DE",
    "wof:name":"Sturzelhof",
    "wof:placetype":"neighbourhood"
},
  "geometry": {"coordinates":[11.33035,49.38073],"type":"Point"}
}