{
  "type": "Feature",
  "properties": {
    "gn:country":"DE",
    "gn:fcode":"PPLA4",
    "gn:population":2566,
    "iso:country":"DE",
    "name:ara_x_preferred":[
        "\u0645\u0627\u0648\u062a"
    ],
    "name:cat_x_preferred":[
        "Mauth"
    ],
    "name:ceb_x_preferred":[
        "Mauth"
    ],
    "name:ces_x_preferred":[
        "Mauth"
    ],
    "name:che_x_preferred":[
        "\u041c\u0430\u0443\u0442"
    ],
    "name:dan_x_preferred":[
        "Mauth"
    ],
    "name:deu_x_preferred":[
        "Mauth"
    ],
    "name:eng_x_preferred":[
        "Mauth"
    ],
    "name:epo_x_preferred":[
        "Mauth"
    ],
    "name:eus_x_preferred":[
        "Mauth"
    ],
    "name:fas_x_preferred":[
        "\u0645\u0627\u0648\u062a"
    ],
    "name:fra_x_preferred":[
        "Mauth"
    ],
    "name:hun_x_preferred":[
        "Mauth"
    ],
    "name:hye_x_preferred":[
        "\u0544\u0561\u0578\u0582\u0569"
    ],
    "name:ind_x_preferred":[
        "Mauth"
    ],
    "name:ita_x_preferred":[
        "Mauth"
    ],
    "name:kaz_x_preferred":[
        "\u041c\u0430\u0443\u0442"
    ],
    "name:kir_x_preferred":[
        "\u041c\u0430\u0443\u0442"
    ],
    "name:kur_x_preferred":[
        "Mauth"
    ],
    "name:lld_x_preferred":[
        "Mauth"
    ],
    "name:lmo_x_preferred":[
        "Mauth"
    ],
    "name:msa_x_preferred":[
        "Mauth"
    ],
    "name:nan_x_preferred":[
        "Mauth"
    ],
    "name:nld_x_preferred":[
        "Mauth"
    ],
    "name:nob_x_preferred":[
        "Mauth"
    ],
    "name:pol_x_preferred":[
        "Mauth"
    ],
    "name:por_x_preferred":[
        "Mauth"
    ],
    "name:ron_x_preferred":[
        "Mauth"
    ],
    "name:rus_x_preferred":[
        "\u041c\u0430\u0443\u0442"
    ],
    "name:spa_x_preferred":[
        "Mauth"
    ],
    "name:srp_x_preferred":[
        "\u041c\u0430\u0443\u0442"
    ],
    "name:swe_x_preferred":[
        "Mauth"
    ],
    "name:tat_x_preferred":[
        "\u041c\u0430\u0443\u0442"
    ],
    "name:ukr_x_preferred":[
        "\u041c\u0430\u0443\u0442"
    ],
    "name:uzb_x_preferred":[
        "Mauth"
    ],
    "name:vie_x_preferred":[
        "Mauth"
    ],
    "name:vol_x_preferred":[
        "Mauth"
    ],
    "name:war_x_preferred":[
        "Mauth"
    ],
    "name:zho_x_preferred":[
        "\u6bdb\u7279"
    ],
    "qs_pg:aaroncc":"DE",
    "qs_pg:gn_country":"DE",
    "qs_pg:gn_fcode":"PPLA4",
    "qs_pg:gn_pop":2566,
    "qs_pg:name":"Muth",
    "qs_pg:name_adm0":"Deutschland",
    "qs_pg:name_adm1":"Bayern",
    "qs_pg:photos_9r":0,
    "qs_pg:photos_sr":0,
    "qs_pg:pop_sr":4,
    "qs_pg:qs_pg_placetype":"locality",
    "qs_pg:qs_pg_placetype_gp":"Town",
    "qs_pg:woe_adm0":23424829,
    "woe:adm0_id":23424829,
    "woe:name_adm0":"Deutschland",
    "woe:name_adm1":"Bayern",
    "woe:placetype":"Town",
    "wof:name":"Muth",
    "wof:placetype":"neighbourhood",
    "wof:population":2566
},
  "geometry": {"coordinates":[13.58459,48.88972],"type":"Point"}
}