{
  "type": "Feature",
  "properties": {
    "gn:admin1_code":"1.0",
    "gn:admin2_code":"81.0",
    "gn:admin3_code":"8126.0",
    "gn:admin4_code":"8126046.0",
    "gn:asciiname":"Amrichshausen",
    "gn:country_code":"DE",
    "gn:dem":400,
    "gn:feature_class":"P",
    "gn:feature_code":"PPL",
    "gn:name":"Amrichshausen",
    "gn:population":0,
    "gn:timezone":"Europe/Berlin",
    "iso:country":"DE",
    "wof:name":"Amrichshausen",
    "wof:placetype":"neighbourhood"
},
  "geometry": {"coordinates":[9.73982,49.28278],"type":"Point"}
}