{
  "type": "Feature",
  "properties": {
    "gn:admin1_code":"1",
    "gn:admin2_code":"83.0",
    "gn:admin3_code":"8317.0",
    "gn:admin4_code":"8317065.0",
    "gn:asciiname":"Langenhard",
    "gn:country_code":"DE",
    "gn:dem":386,
    "gn:feature_class":"P",
    "gn:feature_code":"PPLL",
    "gn:name":"Langenhard",
    "gn:population":0,
    "gn:timezone":"Europe/Berlin",
    "iso:country":"DE",
    "wof:name":"Langenhard",
    "wof:placetype":"neighbourhood"
},
  "geometry": {"coordinates":[7.90207,48.31372],"type":"Point"}
}