{
  "type": "Feature",
  "properties": {
    "gn:admin1_code":"7",
    "gn:admin2_code":"55.0",
    "gn:admin3_code":"5566.0",
    "gn:admin4_code":"5566096.0",
    "gn:asciiname":"Maxhafen",
    "gn:country_code":"DE",
    "gn:dem":45,
    "gn:feature_class":"P",
    "gn:feature_code":"PPLL",
    "gn:name":"Maxhafen",
    "gn:population":0,
    "gn:timezone":"Europe/Berlin",
    "iso:country":"DE",
    "wof:name":"Maxhafen",
    "wof:placetype":"neighbourhood"
},
  "geometry": {"coordinates":[7.3447,52.22286],"type":"Point"}
}