{
  "type": "Feature",
  "properties": {
    "gn:admin1_code":"13",
    "gn:admin2_code":"0.0",
    "gn:admin3_code":"14627.0",
    "gn:admin4_code":"14627220.0",
    "gn:asciiname":"Grossdittmannsdorf",
    "gn:country_code":"DE",
    "gn:dem":157,
    "gn:feature_class":"P",
    "gn:feature_code":"PPL",
    "gn:name":"Gro\u00dfdittmannsdorf",
    "gn:population":0,
    "gn:timezone":"Europe/Berlin",
    "iso:country":"DE",
    "wof:name":"Grossdittmannsdorf",
    "wof:placetype":"neighbourhood"
},
  "geometry": {"coordinates":[13.77145,51.19726],"type":"Point"}
}