{
  "type": "Feature",
  "properties": {
    "gn:admin1_code":"13",
    "gn:admin2_code":"0.0",
    "gn:admin3_code":"14521.0",
    "gn:admin4_code":"14521550.0",
    "gn:asciiname":"Vorderhenneberg",
    "gn:country_code":"DE",
    "gn:dem":432,
    "gn:feature_class":"P",
    "gn:feature_code":"PPL",
    "gn:name":"Vorderhenneberg",
    "gn:population":0,
    "gn:timezone":"Europe/Berlin",
    "iso:country":"DE",
    "wof:name":"Vorderhenneberg",
    "wof:placetype":"neighbourhood"
},
  "geometry": {"coordinates":[12.76667,50.55],"type":"Point"}
}