{
  "type": "Feature",
  "properties": {
    "gn:admin1_code":"5",
    "gn:admin2_code":"65.0",
    "gn:admin3_code":"6535.0",
    "gn:admin4_code":"6535015.0",
    "gn:asciiname":"Karlshof",
    "gn:country_code":"DE",
    "gn:dem":261,
    "gn:feature_class":"P",
    "gn:feature_code":"PPL",
    "gn:name":"Karlshof",
    "gn:population":0,
    "gn:timezone":"Europe/Berlin",
    "iso:country":"DE",
    "wof:name":"Karlshof",
    "wof:placetype":"neighbourhood"
},
  "geometry": {"coordinates":[9.53739,50.67295],"type":"Point"}
}