{
  "type": "Feature",
  "properties": {
    "gn:admin1_code":"6",
    "gn:admin2_code":"0.0",
    "gn:admin3_code":"3360.0",
    "gn:admin4_code":"3360030.0",
    "gn:asciiname":"Esterholz",
    "gn:country_code":"DE",
    "gn:dem":54,
    "gn:feature_class":"P",
    "gn:feature_code":"PPL",
    "gn:name":"Esterholz",
    "gn:population":0,
    "gn:timezone":"Europe/Berlin",
    "iso:country":"DE",
    "wof:name":"Esterholz",
    "wof:placetype":"neighbourhood"
},
  "geometry": {"coordinates":[10.61718,52.91802],"type":"Point"}
}