{
  "type": "Feature",
  "properties": {
    "gn:admin1_code":"2",
    "gn:admin2_code":"93.0",
    "gn:admin3_code":"9373.0",
    "gn:admin4_code":"9373153.0",
    "gn:asciiname":"Niederhofen",
    "gn:country_code":"DE",
    "gn:dem":487,
    "gn:feature_class":"P",
    "gn:feature_code":"PPL",
    "gn:name":"Niederhofen",
    "gn:population":0,
    "gn:timezone":"Europe/Berlin",
    "iso:country":"DE",
    "name:ceb_x_preferred":[
        "Niederhofen"
    ],
    "name:deu_x_preferred":[
        "Niederhofen"
    ],
    "name:epo_x_preferred":[
        "Niederhofen"
    ],
    "name:eus_x_preferred":[
        "Niederhofen"
    ],
    "name:fas_x_preferred":[
        "\u0646\u06cc\u062f\u0631\u0647\u0648\u0641\u0646"
    ],
    "name:fra_x_preferred":[
        "Niederhofen"
    ],
    "name:hun_x_preferred":[
        "Niederhofen"
    ],
    "name:ita_x_preferred":[
        "Niederhofen"
    ],
    "name:kaz_x_preferred":[
        "\u041d\u0438\u0434\u0435\u0440\u0445\u043e\u0444\u0435\u043d"
    ],
    "name:kir_x_preferred":[
        "\u041d\u0438\u0434\u0435\u0440\u0445\u043e\u0444\u0435\u043d"
    ],
    "name:msa_x_preferred":[
        "Niederhofen"
    ],
    "name:nld_x_preferred":[
        "Niederhofen"
    ],
    "name:pol_x_preferred":[
        "Niederhofen"
    ],
    "name:por_x_preferred":[
        "Niederhofen"
    ],
    "name:ron_x_preferred":[
        "Niederhofen"
    ],
    "name:rus_x_preferred":[
        "\u041d\u0438\u0434\u0435\u0440\u0445\u043e\u0444\u0435\u043d"
    ],
    "name:spa_x_preferred":[
        "Niederhofen"
    ],
    "name:srp_x_preferred":[
        "\u041d\u0438\u0434\u0435\u0440\u0445\u043e\u0444\u0435\u043d"
    ],
    "name:ukr_x_preferred":[
        "\u041d\u0456\u0434\u0435\u0440\u0433\u043e\u0444\u0435\u043d"
    ],
    "name:uzb_x_preferred":[
        "Niederhofen"
    ],
    "name:vie_x_preferred":[
        "Niederhofen"
    ],
    "name:vol_x_preferred":[
        "Niederhofen"
    ],
    "name:war_x_preferred":[
        "Niederhofen"
    ],
    "name:zho_x_preferred":[
        "\u5c3c\u5fb7\u970d\u82ac"
    ],
    "wof:name":"Niederhofen",
    "wof:placetype":"neighbourhood"
},
  "geometry": {"coordinates":[11.57453,49.29339],"type":"Point"}
}