{
  "type": "Feature",
  "properties": {
    "gn:admin1_code":"1",
    "gn:admin2_code":"83.0",
    "gn:admin3_code":"8317.0",
    "gn:admin4_code":"8317057.0",
    "gn:asciiname":"Kork",
    "gn:country_code":"DE",
    "gn:dem":139,
    "gn:feature_class":"P",
    "gn:feature_code":"PPL",
    "gn:name":"Kork",
    "gn:population":0,
    "gn:timezone":"Europe/Berlin",
    "iso:country":"DE",
    "name:ceb_x_preferred":[
        "Kork"
    ],
    "name:deu_x_preferred":[
        "Kork"
    ],
    "name:swe_x_preferred":[
        "Kork"
    ],
    "wof:name":"Kork",
    "wof:placetype":"neighbourhood"
},
  "geometry": {"coordinates":[7.87039,48.56773],"type":"Point"}
}