{
  "type": "Feature",
  "properties": {
    "iso:country":"DE",
    "name:und_x_variant":[
        "Niederholtdorf"
    ],
    "wof:name":"Niederholtorf",
    "wof:placetype":"neighbourhood"
},
  "geometry": {"coordinates":[7.18338179022989,50.73080334517027],"type":"Point"}
}