{
  "type": "Feature",
  "properties": {
    "gn:admin1_code":"14",
    "gn:admin2_code":"0.0",
    "gn:admin3_code":"15084.0",
    "gn:admin4_code":"15084015.0",
    "gn:asciiname":"Krawinkel",
    "gn:country_code":"DE",
    "gn:dem":268,
    "gn:feature_class":"P",
    "gn:feature_code":"PPL",
    "gn:name":"Krawinkel",
    "gn:population":0,
    "gn:timezone":"Europe/Berlin",
    "iso:country":"DE",
    "wof:name":"Krawinkel",
    "wof:placetype":"neighbourhood"
},
  "geometry": {"coordinates":[11.62392,51.20255],"type":"Point"}
}