{
  "type": "Feature",
  "properties": {
    "gn:admin1_code":"2",
    "gn:admin2_code":"97.0",
    "gn:admin3_code":"9778.0",
    "gn:admin4_code":"9778119.0",
    "gn:asciiname":"Huners",
    "gn:country_code":"DE",
    "gn:dem":765,
    "gn:feature_class":"P",
    "gn:feature_code":"PPL",
    "gn:name":"H\u00fcners",
    "gn:population":0,
    "gn:timezone":"Europe/Berlin",
    "iso:country":"DE",
    "wof:name":"Huners",
    "wof:placetype":"neighbourhood"
},
  "geometry": {"coordinates":[10.28698,47.89958],"type":"Point"}
}