{
  "type": "Feature",
  "properties": {
    "gn:admin1_code":"1",
    "gn:admin2_code":"84.0",
    "gn:admin3_code":"8416.0",
    "gn:admin4_code":"8416041.0",
    "gn:asciiname":"Kilchberg",
    "gn:country_code":"DE",
    "gn:dem":333,
    "gn:feature_class":"P",
    "gn:feature_code":"PPL",
    "gn:name":"Kilchberg",
    "gn:population":0,
    "gn:timezone":"Europe/Berlin",
    "iso:country":"DE",
    "name:ces_x_preferred":[
        "Kilchberg"
    ],
    "name:deu_x_preferred":[
        "Kilchberg"
    ],
    "name:msa_x_preferred":[
        "Kilchberg"
    ],
    "name:nld_x_preferred":[
        "Kilchberg"
    ],
    "wof:name":"Kilchberg",
    "wof:placetype":"neighbourhood"
},
  "geometry": {"coordinates":[9.01754,48.48953],"type":"Point"}
}