{
  "type": "Feature",
  "properties": {
    "gn:admin1_code":"11",
    "gn:admin2_code":"0.0",
    "gn:admin3_code":"12064.0",
    "gn:admin4_code":"12064512.0",
    "gn:asciiname":"Thoeringswerder",
    "gn:country_code":"DE",
    "gn:dem":3,
    "gn:feature_class":"P",
    "gn:feature_code":"PPL",
    "gn:name":"Th\u00f6ringswerder",
    "gn:population":0,
    "gn:timezone":"Europe/Berlin",
    "iso:country":"DE",
    "wof:name":"Thoeringswerder",
    "wof:placetype":"neighbourhood"
},
  "geometry": {"coordinates":[14.20944,52.71384000000001],"type":"Point"}
}