{
  "type": "Feature",
  "properties": {
    "gn:admin1_code":"2",
    "gn:admin2_code":"93.0",
    "gn:admin3_code":"9373.0",
    "gn:admin4_code":"9373112.0",
    "gn:asciiname":"Thannbrunn",
    "gn:country_code":"DE",
    "gn:dem":530,
    "gn:feature_class":"P",
    "gn:feature_code":"PPL",
    "gn:name":"Thannbrunn",
    "gn:population":0,
    "gn:timezone":"Europe/Berlin",
    "iso:country":"DE",
    "wof:name":"Thannbrunn",
    "wof:placetype":"neighbourhood"
},
  "geometry": {"coordinates":[11.5202,49.15089],"type":"Point"}
}