{
  "type": "Feature",
  "properties": {
    "gn:admin1_code":"14",
    "gn:admin2_code":"0.0",
    "gn:admin3_code":"15091.0",
    "gn:admin4_code":"15091375.0",
    "gn:asciiname":"Kienberge",
    "gn:country_code":"DE",
    "gn:dem":69,
    "gn:feature_class":"P",
    "gn:feature_code":"PPL",
    "gn:name":"Kienberge",
    "gn:population":0,
    "gn:timezone":"Europe/Berlin",
    "iso:country":"DE",
    "wof:name":"Kienberge",
    "wof:placetype":"neighbourhood"
},
  "geometry": {"coordinates":[12.62497,51.84584],"type":"Point"}
}