{
  "type": "Feature",
  "properties": {
    "gn:admin1_code":"7",
    "gn:admin2_code":"55.0",
    "gn:admin3_code":"5515.0",
    "gn:admin4_code":"5515000.0",
    "gn:asciiname":"Herrenburg",
    "gn:country_code":"DE",
    "gn:dem":58,
    "gn:feature_class":"P",
    "gn:feature_code":"PPL",
    "gn:name":"Herrenburg",
    "gn:population":0,
    "gn:timezone":"Europe/Berlin",
    "iso:country":"DE",
    "wof:name":"Herrenburg",
    "wof:placetype":"neighbourhood"
},
  "geometry": {"coordinates":[7.63333,51.88333],"type":"Point"}
}