{
  "type": "Feature",
  "properties": {
    "gn:admin1_code":"5",
    "gn:admin2_code":"64.0",
    "gn:admin3_code":"6440.0",
    "gn:admin4_code":"6440012.0",
    "gn:asciiname":"Klein-Karben",
    "gn:country_code":"DE",
    "gn:dem":124,
    "gn:feature_class":"P",
    "gn:feature_code":"PPL",
    "gn:name":"Klein-Karben",
    "gn:population":0,
    "gn:timezone":"Europe/Berlin",
    "iso:country":"DE",
    "wof:name":"Klein-Karben",
    "wof:placetype":"neighbourhood"
},
  "geometry": {"coordinates":[8.77391,50.22717],"type":"Point"}
}