{
  "type": "Feature",
  "properties": {
    "gn:admin1_code":"7",
    "gn:admin2_code":"57.0",
    "gn:admin3_code":"5766.0",
    "gn:admin4_code":"5766004.0",
    "gn:asciiname":"Heimathof",
    "gn:country_code":"DE",
    "gn:dem":174,
    "gn:feature_class":"P",
    "gn:feature_code":"PPL",
    "gn:name":"Heimathof",
    "gn:population":0,
    "gn:timezone":"Europe/Berlin",
    "iso:country":"DE",
    "wof:name":"Heimathof",
    "wof:placetype":"neighbourhood"
},
  "geometry": {"coordinates":[8.74479,51.86999],"type":"Point"}
}