{
  "type": "Feature",
  "properties": {
    "iso:country":"DE",
    "name:deu_x_preferred":[
        "Neudorf-S\u00fcd"
    ],
    "wof:name":"Neudorf-Sued",
    "wof:placetype":"neighbourhood"
},
  "geometry": {"coordinates":[6.78884017606824,51.41242624936469],"type":"Point"}
}