{
  "type": "Feature",
  "properties": {
    "gn:admin1_code":"6.0",
    "gn:admin2_code":"00",
    "gn:admin3_code":"3158.0",
    "gn:admin4_code":"3158004.0",
    "gn:asciiname":"Westerlinde",
    "gn:country_code":"DE",
    "gn:dem":103,
    "gn:feature_class":"P",
    "gn:feature_code":"PPL",
    "gn:name":"Westerlinde",
    "gn:population":0,
    "gn:timezone":"Europe/Berlin",
    "iso:country":"DE",
    "wof:name":"Westerlinde",
    "wof:placetype":"neighbourhood"
},
  "geometry": {"coordinates":[10.22449,52.12253],"type":"Point"}
}