{
  "type": "Feature",
  "properties": {
    "gn:admin1_code":"2",
    "gn:admin2_code":"91.0",
    "gn:admin3_code":"9178.0",
    "gn:admin4_code":"9178116.0",
    "gn:asciiname":"Osseltshausen",
    "gn:country_code":"DE",
    "gn:dem":487,
    "gn:feature_class":"P",
    "gn:feature_code":"PPL",
    "gn:name":"Osseltshausen",
    "gn:population":0,
    "gn:timezone":"Europe/Berlin",
    "iso:country":"DE",
    "wof:name":"Osseltshausen",
    "wof:placetype":"neighbourhood"
},
  "geometry": {"coordinates":[11.68132,48.5609],"type":"Point"}
}