{
  "type": "Feature",
  "properties": {
    "gn:admin1_code":"2.0",
    "gn:admin2_code":"097",
    "gn:admin3_code":"9771.0",
    "gn:admin4_code":"9771162.0",
    "gn:asciiname":"Wundersdorf",
    "gn:country_code":"DE",
    "gn:dem":521,
    "gn:feature_class":"P",
    "gn:feature_code":"PPL",
    "gn:name":"Wundersdorf",
    "gn:population":0,
    "gn:timezone":"Europe/Berlin",
    "iso:country":"DE",
    "wof:name":"Wundersdorf",
    "wof:placetype":"neighbourhood"
},
  "geometry": {"coordinates":[11.2868,48.46278],"type":"Point"}
}