{
  "type": "Feature",
  "properties": {
    "gn:admin1_code":"2",
    "gn:admin2_code":"95.0",
    "gn:admin3_code":"9572.0",
    "gn:admin4_code":"9572121.0",
    "gn:asciiname":"Eckenhaid",
    "gn:country_code":"DE",
    "gn:dem":352,
    "gn:feature_class":"P",
    "gn:feature_code":"PPL",
    "gn:name":"Eckenhaid",
    "gn:population":0,
    "gn:timezone":"Europe/Berlin",
    "iso:country":"DE",
    "wof:name":"Eckenhaid",
    "wof:placetype":"neighbourhood"
},
  "geometry": {"coordinates":[11.2206,49.57443],"type":"Point"}
}