{
  "type": "Feature",
  "properties": {
    "gn:admin1_code":"2",
    "gn:admin2_code":"94.0",
    "gn:admin3_code":"9471.0",
    "gn:admin4_code":"9471120.0",
    "gn:asciiname":"Vollmannsdorf",
    "gn:country_code":"DE",
    "gn:dem":272,
    "gn:feature_class":"P",
    "gn:feature_code":"PPL",
    "gn:name":"Vollmannsdorf",
    "gn:population":0,
    "gn:timezone":"Europe/Berlin",
    "iso:country":"DE",
    "wof:name":"Vollmannsdorf",
    "wof:placetype":"neighbourhood"
},
  "geometry": {"coordinates":[10.70486,49.82598],"type":"Point"}
}