{
  "type": "Feature",
  "properties": {
    "gn:admin1_code":"7",
    "gn:admin2_code":"59.0",
    "gn:admin3_code":"5970.0",
    "gn:admin4_code":"5970028.0",
    "gn:asciiname":"Wahlbachsmuehle",
    "gn:country_code":"DE",
    "gn:dem":380,
    "gn:feature_class":"P",
    "gn:feature_code":"PPL",
    "gn:name":"Wahlbachsm\u00fchle",
    "gn:population":0,
    "gn:timezone":"Europe/Berlin",
    "iso:country":"DE",
    "wof:name":"Wahlbachsmuehle",
    "wof:placetype":"neighbourhood"
},
  "geometry": {"coordinates":[8.35862,50.94784],"type":"Point"}
}