{
  "type": "Feature",
  "properties": {
    "gn:admin1_code":"7.0",
    "gn:admin2_code":"059",
    "gn:admin3_code":"5974.0",
    "gn:admin4_code":"5974008.0",
    "gn:asciiname":"Weslarn",
    "gn:country_code":"DE",
    "gn:dem":85,
    "gn:feature_class":"P",
    "gn:feature_code":"PPL",
    "gn:name":"Weslarn",
    "gn:population":0,
    "gn:timezone":"Europe/Berlin",
    "iso:country":"DE",
    "wof:name":"Weslarn",
    "wof:placetype":"neighbourhood"
},
  "geometry": {"coordinates":[8.16526,51.61985],"type":"Point"}
}