{
  "type": "Feature",
  "properties": {
    "gn:admin1_code":"6",
    "gn:admin2_code":"0.0",
    "gn:admin3_code":"3101.0",
    "gn:admin4_code":"3101000.0",
    "gn:asciiname":"Mascherode",
    "gn:country_code":"DE",
    "gn:dem":86,
    "gn:feature_class":"P",
    "gn:feature_code":"PPL",
    "gn:name":"Mascherode",
    "gn:population":0,
    "gn:timezone":"Europe/Berlin",
    "iso:country":"DE",
    "wof:name":"Mascherode",
    "wof:placetype":"neighbourhood"
},
  "geometry": {"coordinates":[10.56653,52.22338],"type":"Point"}
}