{
  "type": "Feature",
  "properties": {
    "gn:admin1_code":"2",
    "gn:admin2_code":"93.0",
    "gn:admin3_code":"9375.0",
    "gn:admin4_code":"9375114.0",
    "gn:asciiname":"Unterlichtenwald",
    "gn:country_code":"DE",
    "gn:dem":351,
    "gn:feature_class":"P",
    "gn:feature_code":"PPL",
    "gn:name":"Unterlichtenwald",
    "gn:population":0,
    "gn:timezone":"Europe/Berlin",
    "iso:country":"DE",
    "wof:name":"Unterlichtenwald",
    "wof:placetype":"neighbourhood"
},
  "geometry": {"coordinates":[12.26065,49.05003],"type":"Point"}
}