{
  "type": "Feature",
  "properties": {
    "gn:gn_country":"DE",
    "gn:gn_fcode":"PPLA4",
    "gn:gn_pop":212,
    "gn:population":212,
    "iso:country":"DE",
    "name:chi_x_preferred":[
        "\u5927\u514b\u62c9\u59c6\u65af"
    ],
    "name:dut_x_preferred":[
        "Gro\u00df Krams"
    ],
    "name:eng_x_preferred":[
        "Gro\u00df Krams"
    ],
    "name:epo_x_preferred":[
        "Gro\u00df Krams"
    ],
    "name:fre_x_preferred":[
        "Gro\u00df Krams"
    ],
    "name:ger_x_preferred":[
        "Gro\u00df Krams"
    ],
    "name:hun_x_preferred":[
        "Gro\u00df Krams"
    ],
    "name:ita_x_preferred":[
        "Gro\u00df Krams"
    ],
    "name:kaz_x_preferred":[
        "\u0413\u0440\u043e\u0441-\u041a\u0440\u0430\u043c\u0441"
    ],
    "name:kir_x_preferred":[
        "\u0413\u0440\u043e\u0441-\u041a\u0440\u0430\u043c\u0441"
    ],
    "name:mac_x_preferred":[
        "\u0413\u0440\u043e\u0441 \u041a\u0440\u0430\u043c\u0441"
    ],
    "name:may_x_preferred":[
        "Gro\u00df Krams"
    ],
    "name:per_x_preferred":[
        "\u06af\u0631\u0648\u0633 \u06a9\u0631\u0627\u0645\u0633"
    ],
    "name:pol_x_preferred":[
        "Gro\u00df Krams"
    ],
    "name:rum_x_preferred":[
        "Gro\u00df Krams"
    ],
    "name:rus_x_preferred":[
        "\u0413\u0440\u043e\u0441-\u041a\u0440\u0430\u043c\u0441"
    ],
    "name:srp_x_preferred":[
        "\u0413\u0440\u043e\u0441 \u041a\u0440\u0430\u043c\u0441"
    ],
    "name:ukr_x_preferred":[
        "\u0413\u0440\u043e\u0441-\u041a\u0440\u0430\u043c\u0441"
    ],
    "name:uzb_x_preferred":[
        "Gro\u00df Krams"
    ],
    "name:vie_x_preferred":[
        "Gro\u00df Krams"
    ],
    "name:vol_x_preferred":[
        "Gro\u00df Krams"
    ],
    "name:war_x_preferred":[
        "Gro\u00df Krams"
    ],
    "qs_pg:aaroncc":"DE",
    "qs_pg:gn_country":"DE",
    "qs_pg:gn_fcode":"PPLA4",
    "qs_pg:gn_pop":212,
    "qs_pg:name":"Gro\u00df Krams",
    "qs_pg:photos_9r":0,
    "qs_pg:photos_sr":0,
    "qs_pg:pop_sr":2,
    "qs_pg:qs_pg_placetype":"locality",
    "wof:name":"Gro\u00df Krams",
    "wof:placetype":"locality",
    "wof:population":212
},
  "geometry": {"coordinates":[11.26667,53.33333],"type":"Point"}
}