{
  "type": "Feature",
  "properties": {
    "gn:admin1_code":"2",
    "gn:admin2_code":"91.0",
    "gn:admin3_code":"9173.0",
    "gn:admin4_code":"9173118.0",
    "gn:asciiname":"Tattenkofen",
    "gn:country_code":"DE",
    "gn:dem":620,
    "gn:feature_class":"P",
    "gn:feature_code":"PPL",
    "gn:name":"Tattenkofen",
    "gn:population":0,
    "gn:timezone":"Europe/Berlin",
    "iso:country":"DE",
    "wof:name":"Tattenkofen",
    "wof:placetype":"neighbourhood"
},
  "geometry": {"coordinates":[11.5153,47.86322],"type":"Point"}
}