{
  "type": "Feature",
  "properties": {
    "gn:admin1_code":"13",
    "gn:admin2_code":"0.0",
    "gn:admin3_code":"14625.0",
    "gn:admin4_code":"14625340.0",
    "gn:asciiname":"Ruhethal",
    "gn:country_code":"DE",
    "gn:dem":145,
    "gn:feature_class":"P",
    "gn:feature_code":"PPL",
    "gn:name":"Ruhethal",
    "gn:population":0,
    "gn:timezone":"Europe/Berlin",
    "iso:country":"DE",
    "name:hsb_x_preferred":[
        "Wotpo\u010dink"
    ],
    "wof:name":"Ruhethal",
    "wof:placetype":"neighbourhood"
},
  "geometry": {"coordinates":[14.54303,51.3313],"type":"Point"}
}