{
  "type": "Feature",
  "properties": {
    "gn:admin1_code":"15",
    "gn:admin2_code":"0.0",
    "gn:admin3_code":"16073.0",
    "gn:admin4_code":"16073105.0",
    "gn:asciiname":"Geitersdorf",
    "gn:country_code":"DE",
    "gn:dem":289,
    "gn:feature_class":"P",
    "gn:feature_code":"PPL",
    "gn:name":"Geitersdorf",
    "gn:population":0,
    "gn:timezone":"Europe/Berlin",
    "iso:country":"DE",
    "wof:name":"Geitersdorf",
    "wof:placetype":"neighbourhood"
},
  "geometry": {"coordinates":[11.30381,50.74402],"type":"Point"}
}