{
  "type": "Feature",
  "properties": {
    "gn:admin1_code":"9.0",
    "gn:admin2_code":"0.0",
    "gn:admin3_code":"10046.0",
    "gn:admin4_code":"10046114.0",
    "gn:asciiname":"Bosen-Eckelhausen",
    "gn:country_code":"DE",
    "gn:dem":441,
    "gn:feature_class":"P",
    "gn:feature_code":"PPL",
    "gn:name":"Bosen-Eckelhausen",
    "gn:population":0,
    "gn:timezone":"Europe/Berlin",
    "iso:country":"DE",
    "wof:name":"Bosen-Eckelhausen",
    "wof:placetype":"neighbourhood"
},
  "geometry": {"coordinates":[7.05,49.56667],"type":"Point"}
}