{
  "type": "Feature",
  "properties": {
    "gn:admin1_code":"7.0",
    "gn:admin2_code":"053",
    "gn:admin3_code":"5366.0",
    "gn:admin4_code":"5366028.0",
    "gn:asciiname":"Wielpuetz",
    "gn:country_code":"DE",
    "gn:dem":361,
    "gn:feature_class":"P",
    "gn:feature_code":"PPL",
    "gn:name":"Wielp\u00fctz",
    "gn:population":0,
    "gn:timezone":"Europe/Berlin",
    "iso:country":"DE",
    "wof:name":"Wielpuetz",
    "wof:placetype":"neighbourhood"
},
  "geometry": {"coordinates":[6.56477,50.58045],"type":"Point"}
}