{
  "type": "Feature",
  "properties": {
    "iso:country":"DE",
    "wof:name":"Worringen",
    "wof:placetype":"neighbourhood"
},
  "geometry": {"coordinates":[6.85605777254913,51.06274913574932],"type":"Point"}
}