{
  "type": "Feature",
  "properties": {
    "iso:country":"DE",
    "name:cat_x_preferred":[
        "Worringen"
    ],
    "name:deu_x_preferred":[
        "Worringen"
    ],
    "name:fra_x_preferred":[
        "Worringen"
    ],
    "name:ksh_x_preferred":[
        "Worringe"
    ],
    "name:lat_x_preferred":[
        "Wuringensis civitas"
    ],
    "name:nld_x_preferred":[
        "K\u00f6ln-Worringen"
    ],
    "name:pol_x_preferred":[
        "Worringen"
    ],
    "name:ron_x_preferred":[
        "Worringen"
    ],
    "wof:name":"Worringen",
    "wof:placetype":"neighbourhood"
},
  "geometry": {"coordinates":[6.85605777254913,51.06274913574932],"type":"Point"}
}