{
  "type": "Feature",
  "properties": {
    "gn:admin1_code":"6.0",
    "gn:admin2_code":"00",
    "gn:admin3_code":"3451.0",
    "gn:admin4_code":"3451004.0",
    "gn:asciiname":"Westerscheps",
    "gn:country_code":"DE",
    "gn:dem":6,
    "gn:feature_class":"P",
    "gn:feature_code":"PPL",
    "gn:name":"Westerscheps",
    "gn:population":0,
    "gn:timezone":"Europe/Berlin",
    "iso:country":"DE",
    "wof:name":"Westerscheps",
    "wof:placetype":"neighbourhood"
},
  "geometry": {"coordinates":[7.901,53.12801999999999],"type":"Point"}
}