{
  "type": "Feature",
  "properties": {
    "gn:admin1_code":"1",
    "gn:admin2_code":"82.0",
    "gn:admin3_code":"8235.0",
    "gn:admin4_code":"8235025.0",
    "gn:asciiname":"Gompelscheuer",
    "gn:country_code":"DE",
    "gn:dem":673,
    "gn:feature_class":"P",
    "gn:feature_code":"PPL",
    "gn:name":"Gompelscheuer",
    "gn:population":0,
    "gn:timezone":"Europe/Berlin",
    "iso:country":"DE",
    "wof:name":"Gompelscheuer",
    "wof:placetype":"neighbourhood"
},
  "geometry": {"coordinates":[8.44766,48.635],"type":"Point"}
}