{
  "type": "Feature",
  "properties": {
    "gn:admin1_code":"15.0",
    "gn:admin2_code":"00",
    "gn:admin3_code":"16074.0",
    "gn:admin4_code":"16074112.0",
    "gn:asciiname":"Wuerchhausen",
    "gn:country_code":"DE",
    "gn:dem":138,
    "gn:feature_class":"P",
    "gn:feature_code":"PPL",
    "gn:name":"W\u00fcrchhausen",
    "gn:population":0,
    "gn:timezone":"Europe/Berlin",
    "iso:country":"DE",
    "wof:name":"Wuerchhausen",
    "wof:placetype":"neighbourhood"
},
  "geometry": {"coordinates":[11.68525,51.0303],"type":"Point"}
}