{
  "type": "Feature",
  "properties": {
    "gn:admin1_code":"2.0",
    "gn:admin2_code":"95.0",
    "gn:admin3_code":"9564.0",
    "gn:admin4_code":"9564000.0",
    "gn:asciiname":"Hauptmarkt",
    "gn:country_code":"DE",
    "gn:dem":300,
    "gn:feature_class":"P",
    "gn:feature_code":"PPL",
    "gn:name":"Hauptmarkt",
    "gn:population":0,
    "gn:timezone":"Europe/Berlin",
    "iso:country":"DE",
    "wof:name":"Hauptmarkt",
    "wof:placetype":"neighbourhood"
},
  "geometry": {"coordinates":[11.07709,49.45378],"type":"Point"}
}