{
  "type": "Feature",
  "properties": {
    "gn:admin1_code":"11",
    "gn:admin2_code":"0.0",
    "gn:admin3_code":"12066.0",
    "gn:admin4_code":"12066226.0",
    "gn:asciiname":"Leeskow",
    "gn:country_code":"DE",
    "gn:dem":112,
    "gn:feature_class":"P",
    "gn:feature_code":"PPL",
    "gn:name":"Leeskow",
    "gn:population":0,
    "gn:timezone":"Europe/Berlin",
    "iso:country":"DE",
    "wof:name":"Leeskow",
    "wof:placetype":"neighbourhood"
},
  "geometry": {"coordinates":[14.09304,51.60692],"type":"Point"}
}