{
  "type": "Feature",
  "properties": {
    "gn:admin1_code":"13.0",
    "gn:admin2_code":"00",
    "gn:admin3_code":"14730.0",
    "gn:admin4_code":"14730200.0",
    "gn:asciiname":"Wetitz",
    "gn:country_code":"DE",
    "gn:dem":145,
    "gn:feature_class":"P",
    "gn:feature_code":"PPL",
    "gn:name":"Wetitz",
    "gn:population":0,
    "gn:timezone":"Europe/Berlin",
    "iso:country":"DE",
    "wof:name":"Wetitz",
    "wof:placetype":"neighbourhood"
},
  "geometry": {"coordinates":[13.06531,51.24231],"type":"Point"}
}