{
  "type": "Feature",
  "properties": {
    "gn:admin1_code":"2.0",
    "gn:admin2_code":"93.0",
    "gn:admin3_code":"9373.0",
    "gn:admin4_code":"9373160.0",
    "gn:asciiname":"Batzhausen",
    "gn:country_code":"DE",
    "gn:dem":508,
    "gn:feature_class":"P",
    "gn:feature_code":"PPL",
    "gn:name":"Batzhausen",
    "gn:population":0,
    "gn:timezone":"Europe/Berlin",
    "iso:country":"DE",
    "wof:name":"Batzhausen",
    "wof:placetype":"neighbourhood"
},
  "geometry": {"coordinates":[11.60276,49.18827],"type":"Point"}
}