{
  "type": "Feature",
  "properties": {
    "gn:admin1_code":"2",
    "gn:admin2_code":"95.0",
    "gn:admin3_code":"9571.0",
    "gn:admin4_code":"9571145.0",
    "gn:asciiname":"Vorderbreitenthann",
    "gn:country_code":"DE",
    "gn:dem":501,
    "gn:feature_class":"P",
    "gn:feature_code":"PPL",
    "gn:name":"Vorderbreitenthann",
    "gn:population":0,
    "gn:timezone":"Europe/Berlin",
    "iso:country":"DE",
    "wof:name":"Vorderbreitenthann",
    "wof:placetype":"neighbourhood"
},
  "geometry": {"coordinates":[10.35212,49.20846],"type":"Point"}
}