{
  "type": "Feature",
  "properties": {
    "gn:country":"DE",
    "gn:fcode":"PPLX",
    "gn:population":750,
    "iso:country":"DE",
    "qs_pg:aaroncc":"DE",
    "qs_pg:gn_country":"DE",
    "qs_pg:gn_fcode":"PPLX",
    "qs_pg:gn_pop":750,
    "qs_pg:name":"Holzbronn",
    "qs_pg:photos_9r":0,
    "qs_pg:photos_sr":0,
    "qs_pg:pop_sr":2,
    "qs_pg:qs_pg_placetype":"neighbourhood",
    "wof:name":"Holzbronn",
    "wof:placetype":"neighbourhood",
    "wof:population":750
},
  "geometry": {"coordinates":[8.74443,48.65951],"type":"Point"}
}