{
  "type": "Feature",
  "properties": {
    "gn:admin1_code":"2",
    "gn:admin2_code":"93.0",
    "gn:admin3_code":"9373.0",
    "gn:admin4_code":"9373126.0",
    "gn:asciiname":"Frettenshofen",
    "gn:country_code":"DE",
    "gn:dem":429,
    "gn:feature_class":"P",
    "gn:feature_code":"PPL",
    "gn:name":"Frettenshofen",
    "gn:population":0,
    "gn:timezone":"Europe/Berlin",
    "iso:country":"DE",
    "wof:name":"Frettenshofen",
    "wof:placetype":"neighbourhood"
},
  "geometry": {"coordinates":[11.37136,49.21031],"type":"Point"}
}