{
  "type": "Feature",
  "properties": {
    "gn:admin1_code":"2",
    "gn:admin2_code":"91.0",
    "gn:admin3_code":"9186.0",
    "gn:admin4_code":"9186143.0",
    "gn:asciiname":"Gittenbach",
    "gn:country_code":"DE",
    "gn:dem":450,
    "gn:feature_class":"P",
    "gn:feature_code":"PPL",
    "gn:name":"Gittenbach",
    "gn:population":0,
    "gn:timezone":"Europe/Berlin",
    "iso:country":"DE",
    "wof:name":"Gittenbach",
    "wof:placetype":"neighbourhood"
},
  "geometry": {"coordinates":[11.47732,48.56583],"type":"Point"}
}