{
  "type": "Feature",
  "properties": {
    "gn:country":"DE",
    "gn:fcode":"PPL",
    "gn:population":0,
    "iso:country":"DE",
    "name:ceb_x_preferred":[
        "Wolfsbach"
    ],
    "name:deu_x_preferred":[
        "Wolfsbach"
    ],
    "name:ita_x_preferred":[
        "Wolfsbach"
    ],
    "name:kaz_x_preferred":[
        "\u0412\u043e\u043b\u044c\u0444\u0441\u0431\u0430\u0445"
    ],
    "name:pol_x_preferred":[
        "Wolfsbach"
    ],
    "name:rus_x_preferred":[
        "\u0412\u043e\u043b\u044c\u0444\u0441\u0431\u0430\u0445"
    ],
    "name:swe_x_preferred":[
        "Wolfsbach"
    ],
    "qs_pg:aaroncc":"DE",
    "qs_pg:gn_country":"DE",
    "qs_pg:gn_fcode":"PPL",
    "qs_pg:gn_pop":0,
    "qs_pg:name":"Wolfsbach",
    "qs_pg:name_adm0":"Deutschland",
    "qs_pg:name_adm1":"Bayern",
    "qs_pg:photos":2,
    "qs_pg:photos_1k":1,
    "qs_pg:photos_9k":1,
    "qs_pg:photos_9r":1,
    "qs_pg:photos_all":2,
    "qs_pg:photos_sr":1,
    "qs_pg:pop_sr":0,
    "qs_pg:qs_pg_placetype":"locality",
    "qs_pg:qs_pg_placetype_gp":"Town",
    "qs_pg:woe_adm0":23424829,
    "woe:adm0_id":23424829,
    "woe:name_adm0":"Deutschland",
    "woe:name_adm1":"Bayern",
    "woe:placetype":"Town",
    "wof:name":"Wolfsbach",
    "wof:placetype":"neighbourhood"
},
  "geometry": {"coordinates":[11.60941,49.90564],"type":"Point"}
}