{
  "type": "Feature",
  "properties": {
    "gn:admin1_code":"7",
    "gn:admin2_code":"53.0",
    "gn:admin3_code":"5374.0",
    "gn:admin4_code":"5374032.0",
    "gn:asciiname":"Heddinghausen",
    "gn:country_code":"DE",
    "gn:dem":245,
    "gn:feature_class":"P",
    "gn:feature_code":"PPL",
    "gn:name":"Heddinghausen",
    "gn:population":0,
    "gn:timezone":"Europe/Berlin",
    "iso:country":"DE",
    "wof:name":"Heddinghausen",
    "wof:placetype":"neighbourhood"
},
  "geometry": {"coordinates":[7.5109,50.90248],"type":"Point"}
}