{
  "type": "Feature",
  "properties": {
    "gn:admin1_code":"2.0",
    "gn:admin2_code":"097",
    "gn:admin3_code":"9763.0",
    "gn:admin4_code":"9763000.0",
    "gn:asciiname":"Wettmannsberg",
    "gn:country_code":"DE",
    "gn:dem":736,
    "gn:feature_class":"P",
    "gn:feature_code":"PPL",
    "gn:name":"Wettmannsberg",
    "gn:population":0,
    "gn:timezone":"Europe/Berlin",
    "iso:country":"DE",
    "wof:name":"Wettmannsberg",
    "wof:placetype":"neighbourhood"
},
  "geometry": {"coordinates":[10.34612,47.74575],"type":"Point"}
}