{
  "type": "Feature",
  "properties": {
    "gn:admin1_code":"2",
    "gn:admin2_code":"93.0",
    "gn:admin3_code":"9371.0",
    "gn:admin4_code":"9371127.0",
    "gn:asciiname":"Kindlas",
    "gn:country_code":"DE",
    "gn:dem":482,
    "gn:feature_class":"P",
    "gn:feature_code":"PPL",
    "gn:name":"Kindlas",
    "gn:population":0,
    "gn:timezone":"Europe/Berlin",
    "iso:country":"DE",
    "wof:name":"Kindlas",
    "wof:placetype":"neighbourhood"
},
  "geometry": {"coordinates":[11.9787,49.57432],"type":"Point"}
}