{
  "type": "Feature",
  "properties": {
    "gn:country":"DE",
    "gn:fcode":"PPL",
    "gn:population":0,
    "iso:country":"DE",
    "name:bre_x_preferred":[
        "Herberhausen"
    ],
    "name:cat_x_preferred":[
        "Herberhausen"
    ],
    "name:cos_x_preferred":[
        "Herberhausen"
    ],
    "name:dan_x_preferred":[
        "Herberhausen"
    ],
    "name:deu_x_preferred":[
        "Herberhausen"
    ],
    "name:eng_x_preferred":[
        "Herberhausen"
    ],
    "name:fra_x_preferred":[
        "Herberhausen"
    ],
    "name:ind_x_preferred":[
        "Herberhausen"
    ],
    "name:ita_x_preferred":[
        "Herberhausen"
    ],
    "name:lld_x_preferred":[
        "Herberhausen"
    ],
    "name:nds_x_preferred":[
        "Helpershusen"
    ],
    "name:nld_x_preferred":[
        "Herberhausen"
    ],
    "name:nob_x_preferred":[
        "Herberhausen"
    ],
    "name:por_x_preferred":[
        "Herberhausen"
    ],
    "name:ron_x_preferred":[
        "Herberhausen"
    ],
    "name:spa_x_preferred":[
        "Herberhausen"
    ],
    "name:swe_x_preferred":[
        "Herberhausen"
    ],
    "name:tah_x_preferred":[
        "Herberhausen"
    ],
    "qs_pg:aaroncc":"DE",
    "qs_pg:gn_country":"DE",
    "qs_pg:gn_fcode":"PPL",
    "qs_pg:gn_pop":0,
    "qs_pg:name":"Herberhausen",
    "qs_pg:name_adm0":"Deutschland",
    "qs_pg:name_adm1":"Niedersachsen",
    "qs_pg:photos":9,
    "qs_pg:photos_1k":2,
    "qs_pg:photos_9k":1,
    "qs_pg:photos_9r":1,
    "qs_pg:photos_all":9,
    "qs_pg:photos_sr":1,
    "qs_pg:pop_sr":0,
    "qs_pg:qs_pg_placetype":"locality",
    "qs_pg:qs_pg_placetype_gp":"Town",
    "qs_pg:woe_adm0":23424829,
    "woe:adm0_id":23424829,
    "woe:name_adm0":"Deutschland",
    "woe:name_adm1":"Niedersachsen",
    "woe:placetype":"Town",
    "wof:name":"Herberhausen",
    "wof:placetype":"neighbourhood"
},
  "geometry": {"coordinates":[9.98548,51.53992],"type":"Point"}
}