{
  "type": "Feature",
  "properties": {
    "gn:admin1_code":"6.0",
    "gn:admin2_code":"0.0",
    "gn:admin3_code":"3462.0",
    "gn:admin4_code":"3462019.0",
    "gn:asciiname":"Abens",
    "gn:country_code":"DE",
    "gn:dem":2,
    "gn:feature_class":"P",
    "gn:feature_code":"PPL",
    "gn:name":"Abens",
    "gn:population":0,
    "gn:timezone":"Europe/Berlin",
    "iso:country":"DE",
    "name:ceb_x_preferred":[
        "Abens"
    ],
    "name:dan_x_preferred":[
        "Abens"
    ],
    "name:deu_x_preferred":[
        "Abens"
    ],
    "name:ell_x_preferred":[
        "\u0386\u03bc\u03c0\u03b5\u03bd\u03c2"
    ],
    "name:fas_x_preferred":[
        "\u0622\u0628\u0646\u0633"
    ],
    "name:fra_x_preferred":[
        "Abens"
    ],
    "name:mkd_x_preferred":[
        "\u0410\u0431\u0435\u043d\u0441"
    ],
    "name:nno_x_preferred":[
        "Abens"
    ],
    "name:nor_x_preferred":[
        "Abens"
    ],
    "name:pnb_x_preferred":[
        "\u0627\u06cc\u0628\u0646\u0632"
    ],
    "name:pol_x_preferred":[
        "Abens"
    ],
    "name:rus_x_preferred":[
        "\u0410\u0431\u0435\u043d\u0441"
    ],
    "name:zho_x_preferred":[
        "\u963f\u672c\u65af\u6cb3"
    ],
    "wof:name":"Abens",
    "wof:placetype":"neighbourhood"
},
  "geometry": {"coordinates":[7.72612,53.5966],"type":"Point"}
}