{
  "type": "Feature",
  "properties": {
    "gn:admin1_code":"10",
    "gn:admin2_code":"0.0",
    "gn:admin3_code":"1004.0",
    "gn:admin4_code":"1004000.0",
    "gn:asciiname":"Einfeld",
    "gn:country_code":"DE",
    "gn:dem":31,
    "gn:feature_class":"P",
    "gn:feature_code":"PPL",
    "gn:name":"Einfeld",
    "gn:population":0,
    "gn:timezone":"Europe/Berlin",
    "iso:country":"DE",
    "wof:name":"Einfeld",
    "wof:placetype":"neighbourhood"
},
  "geometry": {"coordinates":[9.99192,54.12369],"type":"Point"}
}