{
  "type": "Feature",
  "properties": {
    "gn:admin1_code":"6",
    "gn:admin2_code":"0.0",
    "gn:admin3_code":"3360.0",
    "gn:admin4_code":"3360014.0",
    "gn:asciiname":"Hohenbunstorf",
    "gn:country_code":"DE",
    "gn:dem":94,
    "gn:feature_class":"P",
    "gn:feature_code":"PPL",
    "gn:name":"Hohenb\u00fcnstorf",
    "gn:population":0,
    "gn:timezone":"Europe/Berlin",
    "iso:country":"DE",
    "wof:name":"Hohenbunstorf",
    "wof:placetype":"neighbourhood"
},
  "geometry": {"coordinates":[10.48478,53.05594],"type":"Point"}
}