{
  "type": "Feature",
  "properties": {
    "gn:admin1_code":"8",
    "gn:admin2_code":"0.0",
    "gn:admin3_code":"7131.0",
    "gn:admin4_code":"7131077.0",
    "gn:asciiname":"Franken",
    "gn:country_code":"DE",
    "gn:dem":193,
    "gn:feature_class":"P",
    "gn:feature_code":"PPL",
    "gn:name":"Franken",
    "gn:population":0,
    "gn:timezone":"Europe/Berlin",
    "iso:country":"DE",
    "name:als_x_preferred":[
        "Franken"
    ],
    "name:deu_x_preferred":[
        "Franken"
    ],
    "name:ell_x_preferred":[
        "\u03a6\u03c1\u03ac\u03b3\u03ba\u03bf\u03b9"
    ],
    "name:fra_x_preferred":[
        "Franken"
    ],
    "name:frr_x_preferred":[
        "Franken"
    ],
    "name:jpn_x_preferred":[
        "\u30d5\u30e9\u30f3\u30b1\u30f3"
    ],
    "name:nds_x_preferred":[
        "Franken"
    ],
    "name:nld_x_preferred":[
        "Franken"
    ],
    "name:pol_x_preferred":[
        "Franken"
    ],
    "name:rus_x_preferred":[
        "\u0424\u0440\u0430\u043d\u043a\u0435\u043d"
    ],
    "name:swe_x_preferred":[
        "Franken"
    ],
    "name:ukr_x_preferred":[
        "\u0424\u0440\u0430\u043d\u043a\u0435\u043d"
    ],
    "wof:name":"Franken",
    "wof:placetype":"neighbourhood"
},
  "geometry": {"coordinates":[7.23461,50.50124],"type":"Point"}
}