{
  "type": "Feature",
  "properties": {
    "gn:admin1_code":"11.0",
    "gn:admin2_code":"00",
    "gn:admin3_code":"12070.0",
    "gn:admin4_code":"12070302.0",
    "gn:asciiname":"Zernikow",
    "gn:country_code":"DE",
    "gn:dem":51,
    "gn:feature_class":"P",
    "gn:feature_code":"PPL",
    "gn:name":"Zernikow",
    "gn:population":0,
    "gn:timezone":"Europe/Berlin",
    "iso:country":"DE",
    "name:deu_x_preferred":[
        "Zernikow"
    ],
    "name:ita_x_preferred":[
        "Zernikow"
    ],
    "wof:name":"Zernikow",
    "wof:placetype":"neighbourhood"
},
  "geometry": {"coordinates":[12.07689,52.9656],"type":"Point"}
}