{
  "type": "Feature",
  "properties": {
    "gn:admin1_code":"15",
    "gn:admin2_code":"0.0",
    "gn:admin3_code":"16063.0",
    "gn:admin4_code":"16063076.0",
    "gn:asciiname":"Grossburschla",
    "gn:country_code":"DE",
    "gn:dem":181,
    "gn:feature_class":"P",
    "gn:feature_code":"PPL",
    "gn:name":"Gro\u00dfburschla",
    "gn:population":0,
    "gn:timezone":"Europe/Berlin",
    "iso:country":"DE",
    "wof:name":"Grossburschla",
    "wof:placetype":"neighbourhood"
},
  "geometry": {"coordinates":[10.17277,51.1369],"type":"Point"}
}