{
  "type": "Feature",
  "properties": {
    "gn:admin1_code":"2",
    "gn:admin2_code":"91.0",
    "gn:admin3_code":"9177.0",
    "gn:admin4_code":"9177115.0",
    "gn:asciiname":"Kirnham",
    "gn:country_code":"DE",
    "gn:dem":467,
    "gn:feature_class":"P",
    "gn:feature_code":"PPL",
    "gn:name":"Kirnham",
    "gn:population":0,
    "gn:timezone":"Europe/Berlin",
    "iso:country":"DE",
    "wof:name":"Kirnham",
    "wof:placetype":"neighbourhood"
},
  "geometry": {"coordinates":[12.15385,48.29604000000001],"type":"Point"}
}