{
  "type": "Feature",
  "properties": {
    "gn:admin1_code":"2",
    "gn:admin2_code":"93.0",
    "gn:admin3_code":"9374.0",
    "gn:admin4_code":"9374132.0",
    "gn:asciiname":"Kleinpoppenhof",
    "gn:country_code":"DE",
    "gn:dem":492,
    "gn:feature_class":"P",
    "gn:feature_code":"PPL",
    "gn:name":"Kleinpoppenhof",
    "gn:population":0,
    "gn:timezone":"Europe/Berlin",
    "iso:country":"DE",
    "wof:name":"Kleinpoppenhof",
    "wof:placetype":"neighbourhood"
},
  "geometry": {"coordinates":[12.25666,49.61009],"type":"Point"}
}