{
  "type": "Feature",
  "properties": {
    "gn:admin1_code":"15",
    "gn:admin2_code":"0.0",
    "gn:admin3_code":"16056.0",
    "gn:admin4_code":"16056000.0",
    "gn:asciiname":"Rothenhof",
    "gn:country_code":"DE",
    "gn:dem":227,
    "gn:feature_class":"P",
    "gn:feature_code":"PPL",
    "gn:name":"Rothenhof",
    "gn:population":0,
    "gn:timezone":"Europe/Berlin",
    "iso:country":"DE",
    "wof:name":"Rothenhof",
    "wof:placetype":"neighbourhood"
},
  "geometry": {"coordinates":[10.36377,50.96408],"type":"Point"}
}