{
  "type": "Feature",
  "properties": {
    "gn:admin1_code":"8",
    "gn:admin2_code":"0.0",
    "gn:admin3_code":"7235.0",
    "gn:admin4_code":"7235501.0",
    "gn:asciiname":"Kyll",
    "gn:country_code":"DE",
    "gn:dem":165,
    "gn:feature_class":"P",
    "gn:feature_code":"PPL",
    "gn:name":"Kyll",
    "gn:population":0,
    "gn:timezone":"Europe/Berlin",
    "iso:country":"DE",
    "name:ceb_x_preferred":[
        "Kyll"
    ],
    "name:ces_x_preferred":[
        "Kyll"
    ],
    "name:chv_x_preferred":[
        "\u041a\u0438\u043b\u043b\u044c"
    ],
    "name:dan_x_preferred":[
        "Kyll"
    ],
    "name:deu_x_preferred":[
        "Kyll"
    ],
    "name:epo_x_preferred":[
        "Kyll"
    ],
    "name:fra_x_preferred":[
        "Kyll"
    ],
    "name:nld_x_preferred":[
        "Kyll"
    ],
    "name:nno_x_preferred":[
        "Kyll"
    ],
    "name:nor_x_preferred":[
        "Kyll"
    ],
    "name:pol_x_preferred":[
        "Kyll"
    ],
    "name:ron_x_preferred":[
        "Kyll"
    ],
    "name:rus_x_preferred":[
        "\u041a\u0438\u043b\u043b\u044c"
    ],
    "name:zho_x_preferred":[
        "\u57fa\u723e\u6cb3"
    ],
    "wof:name":"Kyll",
    "wof:placetype":"neighbourhood"
},
  "geometry": {"coordinates":[6.60452,49.87797],"type":"Point"}
}