{
  "type": "Feature",
  "properties": {
    "gn:admin1_code":"8",
    "gn:admin2_code":"0.0",
    "gn:admin3_code":"7235.0",
    "gn:admin4_code":"7235501.0",
    "gn:asciiname":"Kyll",
    "gn:country_code":"DE",
    "gn:dem":165,
    "gn:feature_class":"P",
    "gn:feature_code":"PPL",
    "gn:name":"Kyll",
    "gn:population":0,
    "gn:timezone":"Europe/Berlin",
    "iso:country":"DE",
    "wof:name":"Kyll",
    "wof:placetype":"neighbourhood"
},
  "geometry": {"coordinates":[6.60452,49.87797],"type":"Point"}
}