{
  "type": "Feature",
  "properties": {
    "gn:admin1_code":"2",
    "gn:admin2_code":"91.0",
    "gn:admin3_code":"9174.0",
    "gn:admin4_code":"9174147.0",
    "gn:asciiname":"Buxberg",
    "gn:country_code":"DE",
    "gn:dem":511,
    "gn:feature_class":"P",
    "gn:feature_code":"PPL",
    "gn:name":"Buxberg",
    "gn:population":0,
    "gn:timezone":"Europe/Berlin",
    "iso:country":"DE",
    "wof:name":"Buxberg",
    "wof:placetype":"neighbourhood"
},
  "geometry": {"coordinates":[11.26482,48.4427],"type":"Point"}
}