{
  "type": "Feature",
  "properties": {
    "gn:admin1_code":"2",
    "gn:admin2_code":"92.0",
    "gn:admin3_code":"9279.0",
    "gn:admin4_code":"9279134.0",
    "gn:asciiname":"Thann",
    "gn:country_code":"DE",
    "gn:dem":458,
    "gn:feature_class":"P",
    "gn:feature_code":"PPL",
    "gn:name":"Thann",
    "gn:population":0,
    "gn:timezone":"Europe/Berlin",
    "iso:country":"DE",
    "name:ceb_x_preferred":[
        "Thann"
    ],
    "name:deu_x_preferred":[
        "Thann"
    ],
    "name:fra_x_preferred":[
        "Thann"
    ],
    "name:pol_x_preferred":[
        "Thann"
    ],
    "name:slk_x_preferred":[
        "Thann"
    ],
    "wof:name":"Thann",
    "wof:placetype":"neighbourhood"
},
  "geometry": {"coordinates":[12.64171,48.53162],"type":"Point"}
}