{
  "type": "Feature",
  "properties": {
    "gn:country":"DE",
    "gn:fcode":"PPL",
    "gn:population":0,
    "iso:country":"DE",
    "name:bul_x_preferred":[
        "\u0412\u0430\u043b\u0435"
    ],
    "name:gml_x_preferred":[
        "Wolde [a. 1369]"
    ],
    "name:lat_x_preferred":[
        "Maior Woeledhe [a. 1258]"
    ],
    "name:osx_x_preferred":[
        "Walede [a. 1141]"
    ],
    "name:osx_x_variant":[
        "Welethe [a. 1181]"
    ],
    "name:rus_x_preferred":[
        "\u0412\u0430\u043b\u0435"
    ],
    "qs_pg:aaroncc":"DE",
    "qs_pg:gn_country":"DE",
    "qs_pg:gn_fcode":"PPL",
    "qs_pg:gn_pop":0,
    "qs_pg:name":"Wahle",
    "qs_pg:name_adm0":"Deutschland",
    "qs_pg:name_adm1":"Niedersachsen",
    "qs_pg:photos":29,
    "qs_pg:photos_1k":6,
    "qs_pg:photos_9k":1,
    "qs_pg:photos_9r":2,
    "qs_pg:photos_all":29,
    "qs_pg:photos_sr":2,
    "qs_pg:pop_sr":0,
    "qs_pg:qs_pg_placetype":"locality",
    "qs_pg:qs_pg_placetype_gp":"Town",
    "qs_pg:woe_adm0":23424829,
    "woe:adm0_id":23424829,
    "woe:name_adm0":"Deutschland",
    "woe:name_adm1":"Niedersachsen",
    "woe:placetype":"Town",
    "wof:name":"Wahle",
    "wof:placetype":"neighbourhood"
},
  "geometry": {"coordinates":[10.36182,52.27089],"type":"Point"}
}