{
  "type": "Feature",
  "properties": {
    "gn:admin1_code":"11.0",
    "gn:admin2_code":"0.0",
    "gn:admin3_code":"12063.0",
    "gn:admin4_code":"12063142.0",
    "gn:asciiname":"Bernhardinenhof",
    "gn:country_code":"DE",
    "gn:dem":50,
    "gn:feature_class":"P",
    "gn:feature_code":"PPL",
    "gn:name":"Bernhardinenhof",
    "gn:population":0,
    "gn:timezone":"Europe/Berlin",
    "iso:country":"DE",
    "wof:name":"Bernhardinenhof",
    "wof:placetype":"neighbourhood"
},
  "geometry": {"coordinates":[12.63762,52.68944000000001],"type":"Point"}
}