{
  "type": "Feature",
  "properties": {
    "gn:admin1_code":"8",
    "gn:admin2_code":"0.0",
    "gn:admin3_code":"7335.0",
    "gn:admin4_code":"7335010.0",
    "gn:asciiname":"Frankenstein",
    "gn:country_code":"DE",
    "gn:dem":283,
    "gn:feature_class":"P",
    "gn:feature_code":"PPLA4",
    "gn:name":"Frankenstein",
    "gn:population":1108,
    "gn:timezone":"Europe/Berlin",
    "iso:country":"DE",
    "wof:name":"Frankenstein",
    "wof:placetype":"locality",
    "wof:population":1108
},
  "geometry": {"coordinates":[7.97744,49.44015],"type":"Point"}
}