{
  "type": "Feature",
  "properties": {
    "gn:admin1_code":"8",
    "gn:admin2_code":"0.0",
    "gn:admin3_code":"7332.0",
    "gn:admin4_code":"7332016.0",
    "gn:asciiname":"Erfenstein",
    "gn:country_code":"DE",
    "gn:dem":199,
    "gn:feature_class":"P",
    "gn:feature_code":"PPL",
    "gn:name":"Erfenstein",
    "gn:population":0,
    "gn:timezone":"Europe/Berlin",
    "iso:country":"DE",
    "name:und_x_variant":[
        "Erfensteinerhof",
        "Erfenstein Hof",
        "Erfenstein"
    ],
    "wof:name":"Erfenstein",
    "wof:placetype":"neighbourhood"
},
  "geometry": {"coordinates":[8.01775,49.35378],"type":"Point"}
}