{
  "type": "Feature",
  "properties": {
    "gn:admin1_code":"13.0",
    "gn:admin2_code":"0.0",
    "gn:admin3_code":"14521.0",
    "gn:admin4_code":"14521700.0",
    "gn:asciiname":"Albernau",
    "gn:country_code":"DE",
    "gn:dem":559,
    "gn:feature_class":"P",
    "gn:feature_code":"PPL",
    "gn:name":"Albernau",
    "gn:population":0,
    "gn:timezone":"Europe/Berlin",
    "iso:country":"DE",
    "wof:name":"Albernau",
    "wof:placetype":"neighbourhood"
},
  "geometry": {"coordinates":[12.6531,50.54898],"type":"Point"}
}