{
  "type": "Feature",
  "properties": {
    "iso:country":"DE",
    "name:deu_x_preferred":[
        "Leutewitz"
    ],
    "qs:gn_fcode":"PPLX",
    "qs:gn_local":0,
    "qs:gn_namadm1":"13",
    "qs:gn_name":"Leutewitz",
    "qs:local_max":13108,
    "qs:local_sum":52556,
    "qs:localhoods":61,
    "qs:name":"Leutewitz",
    "qs:name_adm0":"Deutschland",
    "qs:name_adm1":"Sachsen",
    "qs:name_adm2":"Kreisfreie Stadt Dresden",
    "qs:name_lau":"Gorbitz-Ost",
    "qs:name_local":"Dresden",
    "qs:photo_max":20,
    "qs:photo_sum":80,
    "qs:placetype":"Suburb",
    "qs:quad_count":18,
    "qs:woe_adm0":23424829,
    "qs:woe_adm1":2345493,
    "qs:woe_adm2":12596943,
    "qs:woe_lau":26822136,
    "qs:woe_local":645686,
    "qs:woe_ver":"7.10.0",
    "wof:lang":[
        "ger"
    ],
    "wof:name":"Leutewitz",
    "wof:placetype":"neighbourhood"
},
  "geometry": {"coordinates":[13.671039,51.056411],"type":"Point"}
}