{
  "type": "Feature",
  "properties": {
    "gn:admin1_code":"10.0",
    "gn:admin2_code":"00",
    "gn:admin3_code":"1056.0",
    "gn:admin4_code":"1056005.0",
    "gn:asciiname":"Winzeldorf",
    "gn:country_code":"DE",
    "gn:dem":11,
    "gn:feature_class":"P",
    "gn:feature_code":"PPL",
    "gn:name":"Winzeldorf",
    "gn:population":0,
    "gn:timezone":"Europe/Berlin",
    "iso:country":"DE",
    "wof:name":"Winzeldorf",
    "wof:placetype":"neighbourhood"
},
  "geometry": {"coordinates":[9.89837,53.67641],"type":"Point"}
}