{
  "type": "Feature",
  "properties": {
    "gn:admin1_code":"5",
    "gn:admin2_code":"64.0",
    "gn:admin3_code":"6435.0",
    "gn:admin4_code":"6435020.0",
    "gn:asciiname":"Ruedigheim",
    "gn:country_code":"DE",
    "gn:dem":131,
    "gn:feature_class":"P",
    "gn:feature_code":"PPL",
    "gn:name":"R\u00fcdigheim",
    "gn:population":0,
    "gn:timezone":"Europe/Berlin",
    "iso:country":"DE",
    "wof:name":"Ruedigheim",
    "wof:placetype":"neighbourhood"
},
  "geometry": {"coordinates":[8.97652,50.2024],"type":"Point"}
}