{
  "type": "Feature",
  "properties": {
    "gn:admin1_code":"2.0",
    "gn:admin2_code":"093",
    "gn:admin3_code":"9372.0",
    "gn:admin4_code":"9372169.0",
    "gn:asciiname":"Woppmannsdorf",
    "gn:country_code":"DE",
    "gn:dem":512,
    "gn:feature_class":"P",
    "gn:feature_code":"PPL",
    "gn:name":"Woppmannsdorf",
    "gn:population":0,
    "gn:timezone":"Europe/Berlin",
    "iso:country":"DE",
    "wof:name":"Woppmannsdorf",
    "wof:placetype":"neighbourhood"
},
  "geometry": {"coordinates":[12.35296,49.12385],"type":"Point"}
}