{
  "type": "Feature",
  "properties": {
    "gn:admin1_code":"6",
    "gn:admin2_code":"0.0",
    "gn:admin3_code":"3356.0",
    "gn:admin4_code":"3356007.0",
    "gn:asciiname":"Lilkendey",
    "gn:country_code":"DE",
    "gn:dem":39,
    "gn:feature_class":"P",
    "gn:feature_code":"PPL",
    "gn:name":"Lilkendey",
    "gn:population":0,
    "gn:timezone":"Europe/Berlin",
    "iso:country":"DE",
    "wof:name":"Lilkendey",
    "wof:placetype":"neighbourhood"
},
  "geometry": {"coordinates":[8.70217,53.2388],"type":"Point"}
}