{
  "type": "Feature",
  "properties": {
    "gn:admin1_code":"2",
    "gn:admin2_code":"91.0",
    "gn:admin3_code":"9187.0",
    "gn:admin4_code":"9187137.0",
    "gn:asciiname":"Ried",
    "gn:country_code":"DE",
    "gn:dem":473,
    "gn:feature_class":"P",
    "gn:feature_code":"PPL",
    "gn:name":"Ried",
    "gn:population":0,
    "gn:timezone":"Europe/Berlin",
    "iso:country":"DE",
    "name:bar_x_preferred":[
        "Ried"
    ],
    "name:ceb_x_preferred":[
        "Ried"
    ],
    "name:ces_x_preferred":[
        "Ried"
    ],
    "name:deu_x_preferred":[
        "Ried"
    ],
    "name:epo_x_preferred":[
        "Ried"
    ],
    "name:fra_x_preferred":[
        "Ried"
    ],
    "name:ita_x_preferred":[
        "Ried"
    ],
    "name:nld_x_preferred":[
        "Ried"
    ],
    "name:pol_x_preferred":[
        "Ried"
    ],
    "name:ron_x_preferred":[
        "Ried"
    ],
    "name:swe_x_preferred":[
        "Ried"
    ],
    "wof:name":"Ried",
    "wof:placetype":"neighbourhood"
},
  "geometry": {"coordinates":[12.06775,47.91364],"type":"Point"}
}