{
  "type": "Feature",
  "properties": {
    "gn:admin1_code":"13",
    "gn:admin2_code":"0.0",
    "gn:admin3_code":"14523.0",
    "gn:admin4_code":"14523245.0",
    "gn:asciiname":"Rissbruecke",
    "gn:country_code":"DE",
    "gn:dem":696,
    "gn:feature_class":"P",
    "gn:feature_code":"PPL",
    "gn:name":"Ri\u00dfbr\u00fccke",
    "gn:population":0,
    "gn:timezone":"Europe/Berlin",
    "iso:country":"DE",
    "wof:name":"Rissbruecke",
    "wof:placetype":"neighbourhood"
},
  "geometry": {"coordinates":[12.40006,50.43703],"type":"Point"}
}