{
  "type": "Feature",
  "properties": {
    "gn:admin1_code":"11.0",
    "gn:admin2_code":"00",
    "gn:admin3_code":"12062.0",
    "gn:admin4_code":"12062024.0",
    "gn:asciiname":"Ziegelscheune",
    "gn:country_code":"DE",
    "gn:dem":94,
    "gn:feature_class":"P",
    "gn:feature_code":"PPL",
    "gn:name":"Ziegelscheune",
    "gn:population":0,
    "gn:timezone":"Europe/Berlin",
    "iso:country":"DE",
    "wof:name":"Ziegelscheune",
    "wof:placetype":"neighbourhood"
},
  "geometry": {"coordinates":[13.48745,51.55204000000001],"type":"Point"}
}