{
  "type": "Feature",
  "properties": {
    "gn:admin1_code":"15",
    "gn:admin2_code":"0.0",
    "gn:admin3_code":"16075.0",
    "gn:admin4_code":"16075102.0",
    "gn:asciiname":"Schondorf",
    "gn:country_code":"DE",
    "gn:dem":444,
    "gn:feature_class":"P",
    "gn:feature_code":"PPLA4",
    "gn:name":"Sch\u00f6ndorf",
    "gn:population":0,
    "gn:timezone":"Europe/Berlin",
    "iso:country":"DE",
    "name:ara_x_preferred":[
        "\u0634\u0648\u0646\u062f\u0648\u0631\u0641"
    ],
    "name:eus_x_preferred":[
        "Schondorf"
    ],
    "name:fas_x_preferred":[
        "\u0634\u0648\u0646\u062f\u0648\u0631\u0641"
    ],
    "name:hye_x_preferred":[
        "\u0531\u0574\u0565\u0580\u0566\u0565\u056b \u0547\u0578\u0576\u0564\u0578\u0580\u0586"
    ],
    "name:jpn_x_preferred":[
        "\u30b7\u30e7\u30fc\u30f3\u30c9\u30eb\u30d5\u30fb\u30a2\u30e0\u30fb\u30a2\u30f3\u30de\u30fc\u30bc\u30fc"
    ],
    "name:kaz_x_preferred":[
        "\u0428\u043e\u043d\u0434\u043e\u0440\u0444-\u0430\u043c-\u0410\u043c\u043c\u0435\u0440\u0437\u0435\u0435"
    ],
    "name:kir_x_preferred":[
        "\u0428\u043e\u043d\u0434\u043e\u0440\u0444-\u0430\u043c-\u0410\u043c\u043c\u0435\u0440\u0437\u0435\u0435"
    ],
    "name:msa_x_preferred":[
        "Schondorf"
    ],
    "name:por_x_preferred":[
        "Schondorf"
    ],
    "name:rus_x_preferred":[
        "\u0428\u043e\u043d\u0434\u043e\u0440\u0444-\u0430\u043c-\u0410\u043c\u043c\u0435\u0440\u0437\u0435"
    ],
    "name:spa_x_preferred":[
        "Schondorf"
    ],
    "name:ukr_x_preferred":[
        "\u0428\u043e\u043d\u0434\u043e\u0440\u0444"
    ],
    "name:vie_x_preferred":[
        "Schondorf"
    ],
    "name:war_x_preferred":[
        "Schondorf"
    ],
    "name:zho_x_preferred":[
        "\u963f\u9ed8\u6e56\u7554\u96c4\u591a\u592b"
    ],
    "wof:name":"Schondorf",
    "wof:placetype":"neighbourhood"
},
  "geometry": {"coordinates":[11.69477,50.61745],"type":"Point"}
}