{
  "type": "Feature",
  "properties": {
    "gn:country":"DE",
    "gn:fcode":"PPL",
    "gn:population":0,
    "iso:country":"DE",
    "name:bul_x_preferred":[
        "\u0425\u0430\u0431\u043a\u0438\u0440\u0445\u0435\u043d"
    ],
    "name:deu_x_preferred":[
        "Habkirchen"
    ],
    "name:fas_x_preferred":[
        "\u0647\u0627\u0628\u06a9\u06cc\u0631\u0634\u0646"
    ],
    "name:fra_x_preferred":[
        "Habkirchen"
    ],
    "name:nld_x_preferred":[
        "Habkirchen"
    ],
    "qs_pg:aaroncc":"DE",
    "qs_pg:gn_country":"DE",
    "qs_pg:gn_fcode":"PPL",
    "qs_pg:gn_pop":0,
    "qs_pg:name":"Habkirchen",
    "qs_pg:name_adm0":"Deutschland",
    "qs_pg:name_adm1":"Saarland",
    "qs_pg:photos":30,
    "qs_pg:photos_1k":6,
    "qs_pg:photos_9k":1,
    "qs_pg:photos_9r":2,
    "qs_pg:photos_all":30,
    "qs_pg:photos_sr":2,
    "qs_pg:pop_sr":0,
    "qs_pg:qs_pg_placetype":"locality",
    "qs_pg:qs_pg_placetype_gp":"Town",
    "qs_pg:woe_adm0":23424829,
    "woe:adm0_id":23424829,
    "woe:name_adm0":"Deutschland",
    "woe:name_adm1":"Saarland",
    "woe:placetype":"Town",
    "wof:name":"Habkirchen",
    "wof:placetype":"neighbourhood"
},
  "geometry": {"coordinates":[7.13665,49.13373],"type":"Point"}
}