{
  "type": "Feature",
  "properties": {
    "gn:admin1_code":"13",
    "gn:admin2_code":"0.0",
    "gn:admin3_code":"14730.0",
    "gn:admin4_code":"14730150.0",
    "gn:asciiname":"Niederossig",
    "gn:cc2":"DE",
    "gn:country_code":"DE",
    "gn:dem":108,
    "gn:feature_class":"P",
    "gn:feature_code":"PPL",
    "gn:name":"Niederossig",
    "gn:population":0,
    "gn:timezone":"Europe/Berlin",
    "iso:country":"DE",
    "name:und_x_variant":[
        "Krensitz-Nieder Ossig",
        "Niederossig"
    ],
    "wof:name":"Niederossig",
    "wof:placetype":"neighbourhood"
},
  "geometry": {"coordinates":[12.47309,51.48267],"type":"Point"}
}