{
  "type": "Feature",
  "properties": {
    "gn:country":"DE",
    "gn:fcode":"PPL",
    "gn:population":572,
    "iso:country":"DE",
    "name:arz_x_preferred":[
        "\u0645\u0648\u062a\u0634\u0627\u0648"
    ],
    "name:bak_x_preferred":[
        "\u041c\u043e\u0445\u0430\u0443"
    ],
    "name:ceb_x_preferred":[
        "Mochau"
    ],
    "name:che_x_preferred":[
        "\u041c\u043e\u0445\u0430\u0443"
    ],
    "name:deu_x_preferred":[
        "Mochau"
    ],
    "name:eng_x_preferred":[
        "Mochau"
    ],
    "name:fas_x_preferred":[
        "\u0645\u0648\u0634\u0627\u0648"
    ],
    "name:gle_x_preferred":[
        "Mochau"
    ],
    "name:kaz_x_preferred":[
        "\u041c\u043e\u0445\u0430\u0443"
    ],
    "name:kir_x_preferred":[
        "\u041c\u043e\u0445\u0430\u0443"
    ],
    "name:mkd_x_preferred":[
        "\u041c\u043e\u0445\u0430\u0443"
    ],
    "name:nld_x_preferred":[
        "Mochau"
    ],
    "name:rus_x_preferred":[
        "\u041c\u043e\u0445\u0430\u0443"
    ],
    "name:tat_x_preferred":[
        "\u041c\u043e\u0445\u0430\u0443"
    ],
    "name:uzb_x_preferred":[
        "Mochau"
    ],
    "name:vol_x_preferred":[
        "Mochau"
    ],
    "qs_pg:aaroncc":"DE",
    "qs_pg:gn_country":"DE",
    "qs_pg:gn_fcode":"PPL",
    "qs_pg:gn_pop":572,
    "qs_pg:name":"Mochau",
    "qs_pg:name_adm0":"Deutschland",
    "qs_pg:name_adm1":"Sachsen-Anhalt",
    "qs_pg:photos_9r":0,
    "qs_pg:photos_sr":0,
    "qs_pg:pop_sr":2,
    "qs_pg:qs_pg_placetype":"locality",
    "qs_pg:qs_pg_placetype_gp":"Town",
    "qs_pg:woe_adm0":23424829,
    "woe:adm0_id":23424829,
    "woe:name_adm0":"Deutschland",
    "woe:name_adm1":"Sachsen-Anhalt",
    "woe:placetype":"Town",
    "wof:name":"Mochau",
    "wof:placetype":"neighbourhood",
    "wof:population":572
},
  "geometry": {"coordinates":[12.67953,51.93103],"type":"Point"}
}