{
  "type": "Feature",
  "properties": {
    "gn:admin1_code":"1.0",
    "gn:admin2_code":"083",
    "gn:admin3_code":"8325.0",
    "gn:admin4_code":"8325050.0",
    "gn:asciiname":"Winterhalden",
    "gn:country_code":"DE",
    "gn:dem":396,
    "gn:feature_class":"P",
    "gn:feature_code":"PPL",
    "gn:name":"Winterhalden",
    "gn:population":0,
    "gn:timezone":"Europe/Berlin",
    "iso:country":"DE",
    "wof:name":"Winterhalden",
    "wof:placetype":"neighbourhood"
},
  "geometry": {"coordinates":[8.37166,48.30198],"type":"Point"}
}