{
  "type": "Feature",
  "properties": {
    "gn:admin1_code":"15",
    "gn:admin2_code":"0.0",
    "gn:admin3_code":"16071.0",
    "gn:admin4_code":"16071012.0",
    "gn:asciiname":"Daasdorf am Berge",
    "gn:country_code":"DE",
    "gn:dem":280,
    "gn:feature_class":"P",
    "gn:feature_code":"PPL",
    "gn:name":"Daasdorf am Berge",
    "gn:population":0,
    "gn:timezone":"Europe/Berlin",
    "iso:country":"DE",
    "name:bak_x_preferred":[
        "\u0414\u0430\u0441\u0434\u043e\u0440\u0444-\u0430\u043c-\u0411\u0435\u0440\u0433"
    ],
    "name:ceb_x_preferred":[
        "Daasdorf a. Berge"
    ],
    "name:deu_x_preferred":[
        "Daasdorf a. Berge"
    ],
    "name:epo_x_preferred":[
        "Daasdorf am Berge"
    ],
    "name:eus_x_preferred":[
        "Daasdorf am Berge"
    ],
    "name:fas_x_preferred":[
        "\u062f\u0627\u0633\u062f\u0648\u0631\u0641 \u0627\u0645 \u0628\u0631\u06af\u0647"
    ],
    "name:fra_x_preferred":[
        "Daasdorf am Berge"
    ],
    "name:hun_x_preferred":[
        "Daasdorf a. Berge"
    ],
    "name:ita_x_preferred":[
        "Daasdorf a. Berge"
    ],
    "name:kaz_x_preferred":[
        "\u0414\u0430\u0441\u0434\u043e\u0440\u0444-\u043d\u0430-\u0411\u0435\u0440\u0433\u0435"
    ],
    "name:mkd_x_preferred":[
        "\u0414\u0430\u0441\u0434\u043e\u0440\u0444 \u043d\u0430 \u0411\u0435\u0440\u0433\u0435"
    ],
    "name:msa_x_preferred":[
        "Daasdorf am Berge"
    ],
    "name:nld_x_preferred":[
        "Daasdorf a. Berge"
    ],
    "name:pol_x_preferred":[
        "Daasdorf a. Berge"
    ],
    "name:ron_x_preferred":[
        "Daasdorf a. Berge"
    ],
    "name:rus_x_preferred":[
        "\u0414\u0430\u0441\u0434\u043e\u0440\u0444-\u043d\u0430-\u0411\u0435\u0440\u0433\u0435"
    ],
    "name:spa_x_preferred":[
        "Daasdorf am Berge"
    ],
    "name:srp_x_preferred":[
        "\u0414\u0430\u0441\u0434\u043e\u0440\u0444 \u0430\u043c \u0411\u0435\u0440\u0433\u0435"
    ],
    "name:ukr_x_preferred":[
        "\u0414\u0430\u0430\u0441\u0434\u043e\u0440\u0444-\u0430\u043c-\u0411\u0435\u0440\u0433\u0435"
    ],
    "name:und_x_variant":[
        "Daasdorf"
    ],
    "name:uzb_x_preferred":[
        "Daasdorf a. Berge"
    ],
    "name:vie_x_preferred":[
        "Daasdorf am Berge"
    ],
    "name:vol_x_preferred":[
        "Daasdorf a. Berge"
    ],
    "name:war_x_preferred":[
        "Daasdorf am Berge"
    ],
    "name:zho_x_preferred":[
        "\u5c71\u533a\u8fbe\u65af\u591a\u592b"
    ],
    "wof:name":"Daasdorf am Berge",
    "wof:placetype":"neighbourhood"
},
  "geometry": {"coordinates":[11.26164,50.99549],"type":"Point"}
}