{
  "type": "Feature",
  "properties": {
    "gn:admin1_code":"12",
    "gn:admin2_code":"0.0",
    "gn:admin3_code":"13072.0",
    "gn:admin4_code":"13072029.0",
    "gn:asciiname":"Goeldenitz",
    "gn:country_code":"DE",
    "gn:dem":42,
    "gn:feature_class":"P",
    "gn:feature_code":"PPL",
    "gn:name":"G\u00f6ldenitz",
    "gn:population":0,
    "gn:timezone":"Europe/Berlin",
    "iso:country":"DE",
    "wof:name":"Goeldenitz",
    "wof:placetype":"neighbourhood"
},
  "geometry": {"coordinates":[12.29473,54.00726],"type":"Point"}
}