{
  "type": "Feature",
  "properties": {
    "gn:admin1_code":"13",
    "gn:admin2_code":"0.0",
    "gn:admin3_code":"14729.0",
    "gn:admin4_code":"14729160.0",
    "gn:asciiname":"Poehsig",
    "gn:country_code":"DE",
    "gn:dem":197,
    "gn:feature_class":"P",
    "gn:feature_code":"PPL",
    "gn:name":"P\u00f6hsig",
    "gn:population":0,
    "gn:timezone":"Europe/Berlin",
    "iso:country":"DE",
    "wof:name":"Poehsig",
    "wof:placetype":"neighbourhood"
},
  "geometry": {"coordinates":[12.83485,51.22913],"type":"Point"}
}