{
  "type": "Feature",
  "properties": {
    "gn:country":"DE",
    "gn:fcode":"PPL",
    "gn:population":0,
    "iso:country":"DE",
    "name:ceb_x_preferred":[
        "Seebronn"
    ],
    "name:deu_x_preferred":[
        "Seebronn"
    ],
    "name:fas_x_preferred":[
        "\u0632\u0628\u0631\u0648\u0646"
    ],
    "name:fra_x_preferred":[
        "Seebronn"
    ],
    "name:nld_x_preferred":[
        "Seebronn"
    ],
    "qs_pg:aaroncc":"DE",
    "qs_pg:gn_country":"DE",
    "qs_pg:gn_fcode":"PPL",
    "qs_pg:gn_pop":0,
    "qs_pg:name":"Seebronn",
    "qs_pg:name_adm0":"Deutschland",
    "qs_pg:name_adm1":"Baden-W\u00fcrttemberg",
    "qs_pg:photos":2196,
    "qs_pg:photos_1k":445,
    "qs_pg:photos_9k":10,
    "qs_pg:photos_9r":9,
    "qs_pg:photos_all":2196,
    "qs_pg:photos_sr":16,
    "qs_pg:pop_sr":0,
    "qs_pg:qs_pg_placetype":"locality",
    "qs_pg:qs_pg_placetype_gp":"Town",
    "qs_pg:woe_adm0":23424829,
    "woe:adm0_id":23424829,
    "woe:name_adm0":"Deutschland",
    "woe:name_adm1":"Baden-W\u00fcrttemberg",
    "woe:placetype":"Town",
    "wof:name":"Seebronn",
    "wof:placetype":"neighbourhood"
},
  "geometry": {"coordinates":[8.87386,48.50745],"type":"Point"}
}