{
  "type": "Feature",
  "properties": {
    "gn:admin1_code":"2.0",
    "gn:admin2_code":"094",
    "gn:admin3_code":"9471.0",
    "gn:admin4_code":"9471186.0",
    "gn:asciiname":"Zettmannsdorf",
    "gn:country_code":"DE",
    "gn:dem":287,
    "gn:feature_class":"P",
    "gn:feature_code":"PPL",
    "gn:name":"Zettmannsdorf",
    "gn:population":0,
    "gn:timezone":"Europe/Berlin",
    "iso:country":"DE",
    "wof:name":"Zettmannsdorf",
    "wof:placetype":"neighbourhood"
},
  "geometry": {"coordinates":[10.6556,49.86665],"type":"Point"}
}