{
  "type": "Feature",
  "properties": {
    "gn:admin1_code":"5",
    "gn:admin2_code":"66.0",
    "gn:admin3_code":"6634.0",
    "gn:admin4_code":"6634011.0",
    "gn:asciiname":"Oberappenfeld",
    "gn:country_code":"DE",
    "gn:dem":360,
    "gn:feature_class":"P",
    "gn:feature_code":"PPL",
    "gn:name":"Oberappenfeld",
    "gn:population":0,
    "gn:timezone":"Europe/Berlin",
    "iso:country":"DE",
    "wof:name":"Oberappenfeld",
    "wof:placetype":"neighbourhood"
},
  "geometry": {"coordinates":[9.48333,50.93333],"type":"Point"}
}