{
  "type": "Feature",
  "properties": {
    "iso:country":"DE",
    "name:deu_x_colloquial":[
        "Moenkehof",
        "Monkehof"
    ],
    "name:deu_x_preferred":[
        "M\u00f6nkehof"
    ],
    "name:unk_x_variant":[
        "M\u00f6nkehof"
    ],
    "qs:gn_adm0_cc":"DE",
    "qs:gn_local":2949186,
    "qs:local_max":3834,
    "qs:local_sum":10586,
    "qs:localhoods":26,
    "qs:name":"M\u00f6nkehof",
    "qs:name_adm0":"Deutschland",
    "qs:name_adm1":"Nordrhein-Westfalen",
    "qs:name_adm2":"Stadtkreis Bielefeld",
    "qs:name_lau":"Stadtteil Gadderbaum",
    "qs:name_local":"Bielefeld",
    "qs:photo_max":28,
    "qs:photo_sum":76,
    "qs:placetype":"Suburb",
    "qs:quad_count":16,
    "qs:woe_adm0":23424829,
    "qs:woe_adm1":2345487,
    "qs:woe_adm2":12596866,
    "qs:woe_lau":26821925,
    "qs:woe_local":638806,
    "qs:woe_ver":"7.10.0",
    "wof:lang":[
        "ger"
    ],
    "wof:name":"M\u00f6nkehof",
    "wof:placetype":"neighbourhood"
},
  "geometry": {"coordinates":[8.466321,52.014327],"type":"Point"}
}