{
  "type": "Feature",
  "properties": {
    "gn:admin1_code":"7",
    "gn:admin2_code":"55.0",
    "gn:admin3_code":"5558.0",
    "gn:admin4_code":"5558040.0",
    "gn:asciiname":"Geitendorf",
    "gn:country_code":"DE",
    "gn:dem":87,
    "gn:feature_class":"P",
    "gn:feature_code":"PPL",
    "gn:name":"Geitendorf",
    "gn:population":0,
    "gn:timezone":"Europe/Berlin",
    "iso:country":"DE",
    "wof:name":"Geitendorf",
    "wof:placetype":"neighbourhood"
},
  "geometry": {"coordinates":[7.24228,52.04129],"type":"Point"}
}