{
  "type": "Feature",
  "properties": {
    "gn:admin1_code":"5",
    "gn:admin2_code":"66.0",
    "gn:admin3_code":"6636.0",
    "gn:admin4_code":"6636010.0",
    "gn:asciiname":"Grandenborn",
    "gn:country_code":"DE",
    "gn:dem":409,
    "gn:feature_class":"P",
    "gn:feature_code":"PPL",
    "gn:name":"Grandenborn",
    "gn:population":0,
    "gn:timezone":"Europe/Berlin",
    "iso:country":"DE",
    "wof:name":"Grandenborn",
    "wof:placetype":"neighbourhood"
},
  "geometry": {"coordinates":[10.03678,51.08205],"type":"Point"}
}