{
  "type": "Feature",
  "properties": {
    "gn:admin1_code":"2.0",
    "gn:admin2_code":"097",
    "gn:admin3_code":"9778.0",
    "gn:admin4_code":"9778144.0",
    "gn:asciiname":"Zell",
    "gn:country_code":"DE",
    "gn:dem":651,
    "gn:feature_class":"P",
    "gn:feature_code":"PPL",
    "gn:name":"Zell",
    "gn:population":0,
    "gn:timezone":"Europe/Berlin",
    "iso:country":"DE",
    "name:als_x_preferred":[
        "Zell"
    ],
    "name:bar_x_preferred":[
        "Zell"
    ],
    "name:ceb_x_preferred":[
        "Zell"
    ],
    "name:deu_x_preferred":[
        "Zell"
    ],
    "name:epo_x_preferred":[
        "Zell"
    ],
    "name:eus_x_preferred":[
        "Zell"
    ],
    "name:fra_x_preferred":[
        "Zell"
    ],
    "name:hun_x_preferred":[
        "Zell"
    ],
    "name:hye_x_preferred":[
        "\u0551\u0565\u056c"
    ],
    "name:ita_x_preferred":[
        "Zell"
    ],
    "name:jpn_x_preferred":[
        "\u30c4\u30a7\u30eb"
    ],
    "name:kaz_x_preferred":[
        "\u0426\u0435\u043b\u043b\u044c"
    ],
    "name:lmo_x_preferred":[
        "Zell"
    ],
    "name:nld_x_preferred":[
        "Zell"
    ],
    "name:pol_x_preferred":[
        "Zell"
    ],
    "name:por_x_preferred":[
        "Zell"
    ],
    "name:ron_x_preferred":[
        "Zell"
    ],
    "name:rus_x_preferred":[
        "\u0426\u0435\u043b\u043b\u044c"
    ],
    "name:spa_x_preferred":[
        "Zell"
    ],
    "name:sqi_x_preferred":[
        "Zell"
    ],
    "name:swe_x_preferred":[
        "Zell"
    ],
    "name:vol_x_preferred":[
        "Zell"
    ],
    "wof:name":"Zell",
    "wof:placetype":"neighbourhood"
},
  "geometry": {"coordinates":[10.2063,47.89965],"type":"Point"}
}