{
  "type": "Feature",
  "properties": {
    "gn:admin1_code":"2.0",
    "gn:admin2_code":"097",
    "gn:admin3_code":"9778.0",
    "gn:admin4_code":"9778144.0",
    "gn:asciiname":"Zell",
    "gn:country_code":"DE",
    "gn:dem":651,
    "gn:feature_class":"P",
    "gn:feature_code":"PPL",
    "gn:name":"Zell",
    "gn:population":0,
    "gn:timezone":"Europe/Berlin",
    "iso:country":"DE",
    "wof:name":"Zell",
    "wof:placetype":"neighbourhood"
},
  "geometry": {"coordinates":[10.2063,47.89965],"type":"Point"}
}