{
  "type": "Feature",
  "properties": {
    "gn:admin1_code":"12",
    "gn:admin2_code":"0.0",
    "gn:admin3_code":"13072.0",
    "gn:admin4_code":"13072084.0",
    "gn:asciiname":"Rum Kogel",
    "gn:country_code":"DE",
    "gn:dem":63,
    "gn:feature_class":"P",
    "gn:feature_code":"PPL",
    "gn:name":"Rum Kogel",
    "gn:population":0,
    "gn:timezone":"Europe/Berlin",
    "iso:country":"DE",
    "wof:name":"Rum Kogel",
    "wof:placetype":"neighbourhood"
},
  "geometry": {"coordinates":[12.18401,53.65821999999999],"type":"Point"}
}