{
  "type": "Feature",
  "properties": {
    "gn:admin1_code":"2.0",
    "gn:admin2_code":"97.0",
    "gn:admin3_code":"9774.0",
    "gn:admin4_code":"9774150.0",
    "gn:asciiname":"Edenhausen",
    "gn:country_code":"DE",
    "gn:dem":529,
    "gn:feature_class":"P",
    "gn:feature_code":"PPL",
    "gn:name":"Edenhausen",
    "gn:population":0,
    "gn:timezone":"Europe/Berlin",
    "iso:country":"DE",
    "wof:name":"Edenhausen",
    "wof:placetype":"neighbourhood"
},
  "geometry": {"coordinates":[10.41768,48.24707],"type":"Point"}
}