{
  "type": "Feature",
  "properties": {
    "gn:admin1_code":"11",
    "gn:admin2_code":"0.0",
    "gn:admin3_code":"12071.0",
    "gn:admin4_code":"12071160.0",
    "gn:asciiname":"Kaltenborn",
    "gn:country_code":"DE",
    "gn:dem":48,
    "gn:feature_class":"P",
    "gn:feature_code":"PPL",
    "gn:name":"Kaltenborn",
    "gn:population":0,
    "gn:timezone":"Europe/Berlin",
    "iso:country":"DE",
    "name:ceb_x_preferred":[
        "Kaltenborn"
    ],
    "name:deu_x_preferred":[
        "Kaltenborn"
    ],
    "name:epo_x_preferred":[
        "Kaltenborn"
    ],
    "name:eus_x_preferred":[
        "Kaltenborn"
    ],
    "name:fas_x_preferred":[
        "\u06a9\u0627\u0644\u062a\u0646\u0628\u0648\u0631\u0646"
    ],
    "name:fra_x_preferred":[
        "Kaltenborn"
    ],
    "name:hun_x_preferred":[
        "Kaltenborn"
    ],
    "name:ita_x_preferred":[
        "Kaltenborn"
    ],
    "name:kaz_x_preferred":[
        "\u041a\u0430\u043b\u044c\u0442\u0435\u043d\u0431\u043e\u0440\u043d"
    ],
    "name:kir_x_preferred":[
        "\u041a\u0430\u043b\u044c\u0442\u0435\u043d\u0431\u043e\u0440\u043d"
    ],
    "name:msa_x_preferred":[
        "Kaltenborn"
    ],
    "name:nld_x_preferred":[
        "Kaltenborn"
    ],
    "name:pol_x_preferred":[
        "Kaltenborn"
    ],
    "name:por_x_preferred":[
        "Kaltenborn"
    ],
    "name:ron_x_preferred":[
        "Kaltenborn"
    ],
    "name:rus_x_preferred":[
        "\u041a\u0430\u043b\u044c\u0442\u0435\u043d\u0431\u043e\u0440\u043d"
    ],
    "name:spa_x_preferred":[
        "Kaltenborn"
    ],
    "name:srp_x_preferred":[
        "\u041a\u0430\u043b\u0442\u0435\u043d\u0431\u043e\u0440\u043d"
    ],
    "name:ukr_x_preferred":[
        "\u041a\u0430\u043b\u044c\u0442\u0435\u043d\u0431\u043e\u0440\u043d"
    ],
    "name:uzb_x_preferred":[
        "Kaltenborn"
    ],
    "name:vie_x_preferred":[
        "Kaltenborn"
    ],
    "name:vol_x_preferred":[
        "Kaltenborn"
    ],
    "name:war_x_preferred":[
        "Kaltenborn"
    ],
    "name:zho_x_preferred":[
        "\u5361\u5c14\u6ed5\u535a\u6069"
    ],
    "wof:name":"Kaltenborn",
    "wof:placetype":"neighbourhood"
},
  "geometry": {"coordinates":[14.67581,51.93382],"type":"Point"}
}