{
  "type": "Feature",
  "properties": {
    "gn:admin1_code":"10",
    "gn:admin2_code":"0.0",
    "gn:admin3_code":"1057.0",
    "gn:admin4_code":"1057028.0",
    "gn:asciiname":"Goedersdorf",
    "gn:country_code":"DE",
    "gn:dem":40,
    "gn:feature_class":"P",
    "gn:feature_code":"PPL",
    "gn:name":"G\u00f6dersdorf",
    "gn:population":0,
    "gn:timezone":"Europe/Berlin",
    "iso:country":"DE",
    "wof:name":"Goedersdorf",
    "wof:placetype":"neighbourhood"
},
  "geometry": {"coordinates":[10.36882,54.36231],"type":"Point"}
}