{
  "type": "Feature",
  "properties": {
    "gn:admin1_code":"6",
    "gn:admin2_code":"0.0",
    "gn:admin3_code":"3452.0",
    "gn:admin4_code":"3452025.0",
    "gn:asciiname":"Marcardsmoor",
    "gn:country_code":"DE",
    "gn:dem":11,
    "gn:feature_class":"P",
    "gn:feature_code":"PPL",
    "gn:name":"Marcardsmoor",
    "gn:population":0,
    "gn:timezone":"Europe/Berlin",
    "iso:country":"DE",
    "wof:name":"Marcardsmoor",
    "wof:placetype":"neighbourhood"
},
  "geometry": {"coordinates":[7.71587,53.46175],"type":"Point"}
}