{
  "type": "Feature",
  "properties": {
    "gn:admin1_code":"8",
    "gn:admin2_code":"0.0",
    "gn:admin3_code":"7138.0",
    "gn:admin4_code":"7138044.0",
    "gn:asciiname":"Hombach",
    "gn:country_code":"DE",
    "gn:dem":317,
    "gn:feature_class":"P",
    "gn:feature_code":"PPL",
    "gn:name":"Hombach",
    "gn:population":0,
    "gn:timezone":"Europe/Berlin",
    "iso:country":"DE",
    "name:deu_x_preferred":[
        "Hombach"
    ],
    "wof:name":"Hombach",
    "wof:placetype":"neighbourhood"
},
  "geometry": {"coordinates":[7.46584,50.58745],"type":"Point"}
}