{
  "type": "Feature",
  "properties": {
    "gn:admin1_code":"2",
    "gn:admin2_code":"91.0",
    "gn:admin3_code":"9179.0",
    "gn:admin4_code":"9179142.0",
    "gn:asciiname":"Grasslfing",
    "gn:country_code":"DE",
    "gn:dem":498,
    "gn:feature_class":"P",
    "gn:feature_code":"PPL",
    "gn:name":"Gra\u00dflfing",
    "gn:population":0,
    "gn:timezone":"Europe/Berlin",
    "iso:country":"DE",
    "wof:name":"Grasslfing",
    "wof:placetype":"neighbourhood"
},
  "geometry": {"coordinates":[11.37078,48.22081],"type":"Point"}
}