{
  "type": "Feature",
  "properties": {
    "gn:admin1_code":"7.0",
    "gn:admin2_code":"059",
    "gn:admin3_code":"5958.0",
    "gn:admin4_code":"5958004.0",
    "gn:asciiname":"Wettmarsen",
    "gn:country_code":"DE",
    "gn:dem":298,
    "gn:feature_class":"P",
    "gn:feature_code":"PPL",
    "gn:name":"Wettmarsen",
    "gn:population":0,
    "gn:timezone":"Europe/Berlin",
    "iso:country":"DE",
    "wof:name":"Wettmarsen",
    "wof:placetype":"neighbourhood"
},
  "geometry": {"coordinates":[7.91521,51.38285],"type":"Point"}
}