{
  "type": "Feature",
  "properties": {
    "gn:admin1_code":"1",
    "gn:admin2_code":"84.0",
    "gn:admin3_code":"8415.0",
    "gn:admin4_code":"8415053.0",
    "gn:asciiname":"Dottingen",
    "gn:country_code":"DE",
    "gn:dem":741,
    "gn:feature_class":"P",
    "gn:feature_code":"PPL",
    "gn:name":"Dottingen",
    "gn:population":0,
    "gn:timezone":"Europe/Berlin",
    "iso:country":"DE",
    "wof:name":"Dottingen",
    "wof:placetype":"neighbourhood"
},
  "geometry": {"coordinates":[9.43442,48.42359],"type":"Point"}
}