{
  "type": "Feature",
  "properties": {
    "gn:gn_country":"DE",
    "gn:gn_fcode":"PPLA4",
    "gn:gn_pop":152,
    "gn:population":152,
    "iso:country":"DE",
    "name:baq_x_preferred":[
        "Dintesheim"
    ],
    "name:chi_x_preferred":[
        "\u4e01\u7279\u65af\u6d77\u59c6"
    ],
    "name:dut_x_preferred":[
        "Dintesheim"
    ],
    "name:eng_x_preferred":[
        "Dintesheim"
    ],
    "name:epo_x_preferred":[
        "Dintesheim"
    ],
    "name:fre_x_preferred":[
        "Dintesheim"
    ],
    "name:ger_x_preferred":[
        "Dintesheim"
    ],
    "name:hun_x_preferred":[
        "Dintesheim"
    ],
    "name:ita_x_preferred":[
        "Dintesheim"
    ],
    "name:jpn_x_preferred":[
        "\u30c7\u30a3\u30f3\u30c6\u30b9\u30cf\u30a4\u30e0"
    ],
    "name:kaz_x_preferred":[
        "\u0414\u0438\u043d\u0442\u0435\u0441\u0445\u0430\u0439\u043c"
    ],
    "name:kir_x_preferred":[
        "\u0414\u0438\u043d\u0442\u0435\u0441\u0445\u0430\u0439\u043c"
    ],
    "name:may_x_preferred":[
        "Dintesheim"
    ],
    "name:per_x_preferred":[
        "\u062f\u06cc\u0646\u062a\u0633\u0647\u0627\u06cc\u0645"
    ],
    "name:pol_x_preferred":[
        "Dintesheim"
    ],
    "name:por_x_preferred":[
        "Dintesheim"
    ],
    "name:rum_x_preferred":[
        "Dintesheim"
    ],
    "name:rus_x_preferred":[
        "\u0414\u0438\u043d\u0442\u0435\u0441\u0445\u0430\u0439\u043c"
    ],
    "name:spa_x_preferred":[
        "Dintesheim"
    ],
    "name:srp_x_preferred":[
        "\u0414\u0438\u043d\u0442\u0435\u0441\u0445\u0430\u0458\u043c"
    ],
    "name:ukr_x_preferred":[
        "\u0414\u0456\u043d\u0442\u0435\u0441\u0433\u0430\u0439\u043c"
    ],
    "name:uzb_x_preferred":[
        "Dintesheim"
    ],
    "name:vie_x_preferred":[
        "Dintesheim"
    ],
    "name:vol_x_preferred":[
        "Dintesheim"
    ],
    "name:war_x_preferred":[
        "Dintesheim"
    ],
    "qs_pg:aaroncc":"DE",
    "qs_pg:gn_country":"DE",
    "qs_pg:gn_fcode":"PPLA4",
    "qs_pg:gn_pop":152,
    "qs_pg:name":"Dintesheim",
    "qs_pg:photos_9r":0,
    "qs_pg:photos_sr":0,
    "qs_pg:pop_sr":1,
    "qs_pg:qs_pg_placetype":"locality",
    "wof:name":"Dintesheim",
    "wof:placetype":"locality",
    "wof:population":152
},
  "geometry": {"coordinates":[8.14333,49.7075],"type":"Point"}
}