{
  "type": "Feature",
  "properties": {
    "gn:admin1_code":"2",
    "gn:admin2_code":"91.0",
    "gn:admin3_code":"9178.0",
    "gn:admin4_code":"9178145.0",
    "gn:asciiname":"Furholzen",
    "gn:country_code":"DE",
    "gn:dem":465,
    "gn:feature_class":"P",
    "gn:feature_code":"PPL",
    "gn:name":"F\u00fcrholzen",
    "gn:population":0,
    "gn:timezone":"Europe/Berlin",
    "iso:country":"DE",
    "wof:name":"Furholzen",
    "wof:placetype":"neighbourhood"
},
  "geometry": {"coordinates":[11.61864,48.33149],"type":"Point"}
}