{
  "type": "Feature",
  "properties": {
    "gn:admin1_code":"2",
    "gn:admin2_code":"91.0",
    "gn:admin3_code":"9187.0",
    "gn:admin4_code":"9187174.0",
    "gn:asciiname":"Haid",
    "gn:country_code":"DE",
    "gn:dem":498,
    "gn:feature_class":"P",
    "gn:feature_code":"PPL",
    "gn:name":"Haid",
    "gn:population":0,
    "gn:timezone":"Europe/Berlin",
    "iso:country":"DE",
    "name:deu_x_preferred":[
        "Haid"
    ],
    "wof:name":"Haid",
    "wof:placetype":"neighbourhood"
},
  "geometry": {"coordinates":[12.23207,47.93958],"type":"Point"}
}