{
  "type": "Feature",
  "properties": {
    "gn:admin1_code":"13",
    "gn:admin2_code":"0.0",
    "gn:admin3_code":"14729.0",
    "gn:admin4_code":"14729140.0",
    "gn:asciiname":"Oberfrankenhain",
    "gn:country_code":"DE",
    "gn:dem":205,
    "gn:feature_class":"P",
    "gn:feature_code":"PPL",
    "gn:name":"Oberfrankenhain",
    "gn:population":0,
    "gn:timezone":"Europe/Berlin",
    "iso:country":"DE",
    "name:und_x_variant":[
        "Frankenhain-Oberfrankenhain",
        "Oberfrankenhain"
    ],
    "wof:name":"Oberfrankenhain",
    "wof:placetype":"neighbourhood"
},
  "geometry": {"coordinates":[12.65722,51.08046],"type":"Point"}
}