{
  "type": "Feature",
  "properties": {
    "gn:admin1_code":"2",
    "gn:admin2_code":"94.0",
    "gn:admin3_code":"9471.0",
    "gn:admin4_code":"9471172.0",
    "gn:asciiname":"Unterkost",
    "gn:country_code":"DE",
    "gn:dem":281,
    "gn:feature_class":"P",
    "gn:feature_code":"PPL",
    "gn:name":"Unterk\u00f6st",
    "gn:population":0,
    "gn:timezone":"Europe/Berlin",
    "iso:country":"DE",
    "wof:name":"Unterkost",
    "wof:placetype":"neighbourhood"
},
  "geometry": {"coordinates":[10.78403,49.7821],"type":"Point"}
}