{
  "type": "Feature",
  "properties": {
    "gn:admin1_code":"13",
    "gn:admin2_code":"0.0",
    "gn:admin3_code":"14523.0",
    "gn:admin4_code":"14523365.0",
    "gn:asciiname":"Schoenberg",
    "gn:country_code":"DE",
    "gn:dem":515,
    "gn:feature_class":"P",
    "gn:feature_code":"PPL",
    "gn:name":"Sch\u00f6nberg",
    "gn:population":0,
    "gn:timezone":"Europe/Berlin",
    "iso:country":"DE",
    "name:nld_x_preferred":[
        "Sch\u00f6nberg"
    ],
    "wof:name":"Schoenberg",
    "wof:placetype":"neighbourhood"
},
  "geometry": {"coordinates":[11.96684,50.52931],"type":"Point"}
}