{
  "type": "Feature",
  "properties": {
    "gn:admin1_code":"13.0",
    "gn:admin2_code":"00",
    "gn:admin3_code":"14522.0",
    "gn:admin4_code":"14522510.0",
    "gn:asciiname":"Wetterwitz",
    "gn:country_code":"DE",
    "gn:dem":285,
    "gn:feature_class":"P",
    "gn:feature_code":"PPL",
    "gn:name":"Wetterwitz",
    "gn:population":0,
    "gn:timezone":"Europe/Berlin",
    "iso:country":"DE",
    "wof:name":"Wetterwitz",
    "wof:placetype":"neighbourhood"
},
  "geometry": {"coordinates":[13.22996,51.08695],"type":"Point"}
}