{
  "type": "Feature",
  "properties": {
    "gn:admin1_code":"10",
    "gn:admin2_code":"0.0",
    "gn:admin3_code":"1059.0",
    "gn:admin4_code":"1059020.0",
    "gn:asciiname":"Dorpstedt",
    "gn:country_code":"DE",
    "gn:dem":5,
    "gn:feature_class":"P",
    "gn:feature_code":"PPLA4",
    "gn:name":"D\u00f6rpstedt",
    "gn:population":0,
    "gn:timezone":"Europe/Berlin",
    "iso:country":"DE",
    "wof:name":"Dorpstedt",
    "wof:placetype":"neighbourhood"
},
  "geometry": {"coordinates":[9.36667,54.43333000000001],"type":"Point"}
}