{
  "type": "Feature",
  "properties": {
    "iso:country":"DE",
    "name:deu_x_preferred":[
        "Geist"
    ],
    "name:eng_x_preferred":[
        "Geist"
    ],
    "name:kor_x_preferred":[
        "\uac00\uc774\uc2a4\ud2b8"
    ],
    "name:unk_x_variant":[
        "Geist"
    ],
    "qs:gn_fcode":"PPL",
    "qs:gn_local":0,
    "qs:gn_namadm1":"06",
    "qs:gn_name":"Geest",
    "qs:local_max":4321,
    "qs:local_sum":13562,
    "qs:localhoods":28,
    "qs:name":"Geist",
    "qs:name_adm0":"Deutschland",
    "qs:name_adm1":"Nordrhein-Westfalen",
    "qs:name_adm2":"Stadtkreis M\u00fcnster",
    "qs:name_lau":"Mitte-S\u00fcd",
    "qs:name_local":"M\u00fcnster",
    "qs:photo_max":136,
    "qs:photo_sum":573,
    "qs:placetype":"Suburb",
    "qs:quad_count":55,
    "qs:woe_adm0":23424829,
    "qs:woe_adm1":2345487,
    "qs:woe_adm2":12596927,
    "qs:woe_lau":26823098,
    "qs:woe_local":676864,
    "qs:woe_ver":"7.10.0",
    "wd:wordcount":762,
    "wof:lang":[
        "ger"
    ],
    "wof:name":"Geist",
    "wof:placetype":"neighbourhood"
},
  "geometry": {"coordinates":[7.626151,51.936454],"type":"Point"}
}