{
  "type": "Feature",
  "properties": {
    "gn:admin1_code":"5",
    "gn:admin2_code":"66.0",
    "gn:admin3_code":"6633.0",
    "gn:admin4_code":"6633029.0",
    "gn:asciiname":"Friedrichsaue",
    "gn:cc2":"DE",
    "gn:country_code":"DE",
    "gn:dem":282,
    "gn:feature_class":"P",
    "gn:feature_code":"PPL",
    "gn:name":"Friedrichsaue",
    "gn:population":0,
    "gn:timezone":"Europe/Berlin",
    "iso:country":"DE",
    "name:bak_x_preferred":[
        "\u0424\u0440\u0438\u0434\u0440\u0438\u043a\u0441\u0430\u0443\u044d"
    ],
    "name:ceb_x_preferred":[
        "Friedrichsaue"
    ],
    "name:deu_x_preferred":[
        "Friedrichsaue"
    ],
    "name:epo_x_preferred":[
        "Friedrichsaue"
    ],
    "name:fas_x_preferred":[
        "\u0641\u0631\u06cc\u062f\u0631\u0627\u06cc\u0634\u0633\u0627\u0648\u0647"
    ],
    "name:ita_x_preferred":[
        "Friedrichsaue"
    ],
    "name:kaz_x_preferred":[
        "\u0424\u0440\u0438\u0434\u0440\u0438\u043a\u0441\u0430\u0443\u044d"
    ],
    "name:kir_x_preferred":[
        "\u0424\u0440\u0438\u0434\u0440\u0438\u043a\u0441\u0430\u0443\u044d"
    ],
    "name:mkd_x_preferred":[
        "\u0424\u0440\u0438\u0434\u0440\u0438\u043a\u0441\u0430\u0443\u0435"
    ],
    "name:nld_x_preferred":[
        "Friedrichsaue"
    ],
    "name:ron_x_preferred":[
        "Friedrichsaue"
    ],
    "name:rus_x_preferred":[
        "\u0424\u0440\u0438\u0434\u0440\u0438\u0445\u0441\u0430\u0443\u044d"
    ],
    "name:und_x_variant":[
        "Friedrichsau"
    ],
    "name:uzb_x_preferred":[
        "Friedrichsaue"
    ],
    "name:vol_x_preferred":[
        "Friedrichsaue"
    ],
    "wof:name":"Friedrichsaue",
    "wof:placetype":"neighbourhood"
},
  "geometry": {"coordinates":[9.27649,51.38008],"type":"Point"}
}