{
  "type": "Feature",
  "properties": {
    "gn:admin1_code":"7",
    "gn:admin2_code":"55.0",
    "gn:admin3_code":"5570.0",
    "gn:admin4_code":"5570004.0",
    "gn:asciiname":"Guissen",
    "gn:country_code":"DE",
    "gn:dem":82,
    "gn:feature_class":"P",
    "gn:feature_code":"PPLL",
    "gn:name":"Guissen",
    "gn:population":0,
    "gn:timezone":"Europe/Berlin",
    "iso:country":"DE",
    "name:osx_x_preferred":[
        "Gusnun"
    ],
    "wof:name":"Guissen",
    "wof:placetype":"neighbourhood"
},
  "geometry": {"coordinates":[7.93839,51.73245],"type":"Point"}
}