{
  "type": "Feature",
  "properties": {
    "gn:gn_country":"DE",
    "gn:gn_fcode":"PPLA4",
    "gn:gn_pop":223,
    "gn:population":223,
    "iso:country":"DE",
    "name:baq_x_preferred":[
        "Eulgem"
    ],
    "name:chi_x_preferred":[
        "\u5965\u4f0a\u5c14\u683c\u59c6"
    ],
    "name:dut_x_preferred":[
        "Eulgem"
    ],
    "name:eng_x_preferred":[
        "Eulgem"
    ],
    "name:epo_x_preferred":[
        "Eulgem"
    ],
    "name:fre_x_preferred":[
        "Eulgem"
    ],
    "name:ger_x_preferred":[
        "Eulgem"
    ],
    "name:hun_x_preferred":[
        "Eulgem"
    ],
    "name:ita_x_preferred":[
        "Eulgem"
    ],
    "name:jpn_x_preferred":[
        "\u30aa\u30a4\u30eb\u30b2\u30e0"
    ],
    "name:kaz_x_preferred":[
        "\u041e\u0439\u043b\u044c\u0433\u0435\u043c"
    ],
    "name:kir_x_preferred":[
        "\u041e\u0439\u043b\u044c\u0433\u0435\u043c"
    ],
    "name:may_x_preferred":[
        "Eulgem"
    ],
    "name:per_x_preferred":[
        "\u0627\u0648\u06cc\u0644\u06af\u0645"
    ],
    "name:pol_x_preferred":[
        "Eulgem"
    ],
    "name:por_x_preferred":[
        "Eulgem"
    ],
    "name:rum_x_preferred":[
        "Eulgem"
    ],
    "name:rus_x_preferred":[
        "\u041e\u0439\u043b\u044c\u0433\u0435\u043c"
    ],
    "name:spa_x_preferred":[
        "Eulgem"
    ],
    "name:srp_x_preferred":[
        "\u041e\u0458\u043b\u0433\u0435\u043c"
    ],
    "name:ukr_x_preferred":[
        "\u041e\u0439\u043b\u044c\u0433\u0435\u043c"
    ],
    "name:uzb_x_preferred":[
        "Eulgem"
    ],
    "name:vie_x_preferred":[
        "Eulgem"
    ],
    "name:vol_x_preferred":[
        "Eulgem"
    ],
    "name:war_x_preferred":[
        "Eulgem"
    ],
    "qs_pg:aaroncc":"DE",
    "qs_pg:gn_country":"DE",
    "qs_pg:gn_fcode":"PPLA4",
    "qs_pg:gn_pop":223,
    "qs_pg:name":"Eulgem",
    "qs_pg:photos_9r":0,
    "qs_pg:photos_sr":0,
    "qs_pg:pop_sr":2,
    "qs_pg:qs_pg_placetype":"locality",
    "wof:name":"Eulgem",
    "wof:placetype":"locality",
    "wof:population":223
},
  "geometry": {"coordinates":[7.16667,50.23333],"type":"Point"}
}