{
  "type": "Feature",
  "properties": {
    "gn:admin1_code":"2",
    "gn:admin2_code":"92.0",
    "gn:admin3_code":"9275.0",
    "gn:admin4_code":"9275114.0",
    "gn:asciiname":"Schwaig",
    "gn:country_code":"DE",
    "gn:dem":345,
    "gn:feature_class":"P",
    "gn:feature_code":"PPLL",
    "gn:name":"Schwaig",
    "gn:population":0,
    "gn:timezone":"Europe/Berlin",
    "iso:country":"DE",
    "wof:name":"Schwaig",
    "wof:placetype":"neighbourhood"
},
  "geometry": {"coordinates":[13.07139,48.5875],"type":"Point"}
}