{
  "type": "Feature",
  "properties": {
    "gn:admin1_code":"2",
    "gn:admin2_code":"93.0",
    "gn:admin3_code":"9372.0",
    "gn:admin4_code":"9372126.0",
    "gn:asciiname":"Klopfelsberg",
    "gn:country_code":"DE",
    "gn:dem":424,
    "gn:feature_class":"P",
    "gn:feature_code":"PPLL",
    "gn:name":"Kl\u00f6pfelsberg",
    "gn:population":0,
    "gn:timezone":"Europe/Berlin",
    "iso:country":"DE",
    "wof:name":"Klopfelsberg",
    "wof:placetype":"neighbourhood"
},
  "geometry": {"coordinates":[12.88173,49.31897],"type":"Point"}
}