{
  "type": "Feature",
  "properties": {
    "gn:admin1_code":"1",
    "gn:admin2_code":"82.0",
    "gn:admin3_code":"8235.0",
    "gn:admin4_code":"8235006.0",
    "gn:asciiname":"Hornberg",
    "gn:country_code":"DE",
    "gn:dem":677,
    "gn:feature_class":"P",
    "gn:feature_code":"PPL",
    "gn:name":"Hornberg",
    "gn:population":0,
    "gn:timezone":"Europe/Berlin",
    "iso:country":"DE",
    "name:als_x_preferred":[
        "Hornberg"
    ],
    "name:ara_x_preferred":[
        "\u0647\u0648\u0631\u0646\u0628\u0631\u063a"
    ],
    "name:azb_x_preferred":[
        "\u0647\u0648\u0631\u0646\u0628\u0631\u0642"
    ],
    "name:ceb_x_preferred":[
        "Hornberg"
    ],
    "name:deu_x_preferred":[
        "Hornberg"
    ],
    "name:epo_x_preferred":[
        "Hornberg"
    ],
    "name:fas_x_preferred":[
        "\u0647\u0648\u0631\u0646\u0628\u0631\u06af"
    ],
    "name:fra_x_preferred":[
        "Hornberg"
    ],
    "name:hun_x_preferred":[
        "Hornberg"
    ],
    "name:ita_x_preferred":[
        "Hornberg"
    ],
    "name:kaz_x_preferred":[
        "\u0425\u043e\u0440\u043d\u0431\u0435\u0440\u0433"
    ],
    "name:kir_x_preferred":[
        "\u0425\u043e\u0440\u043d\u0431\u0435\u0440\u0433"
    ],
    "name:lat_x_preferred":[
        "Hornberg"
    ],
    "name:lmo_x_preferred":[
        "Hornberg"
    ],
    "name:msa_x_preferred":[
        "Hornberg"
    ],
    "name:nld_x_preferred":[
        "Hornberg"
    ],
    "name:pol_x_preferred":[
        "Hornberg"
    ],
    "name:por_x_preferred":[
        "Hornberg"
    ],
    "name:ron_x_preferred":[
        "Hornberg"
    ],
    "name:rus_x_preferred":[
        "\u0425\u043e\u0440\u043d\u0431\u0435\u0440\u0433"
    ],
    "name:spa_x_preferred":[
        "Hornberg"
    ],
    "name:srp_x_preferred":[
        "\u0425\u043e\u0440\u043d\u0431\u0435\u0440\u0433"
    ],
    "name:swe_x_preferred":[
        "Hornberg"
    ],
    "name:tur_x_preferred":[
        "Hornberg"
    ],
    "name:ukr_x_preferred":[
        "\u0413\u043e\u0440\u043d\u0431\u0435\u0440\u0433"
    ],
    "name:uzb_x_preferred":[
        "Hornberg"
    ],
    "name:vol_x_preferred":[
        "Hornberg"
    ],
    "name:war_x_preferred":[
        "Hornberg"
    ],
    "name:zho_x_preferred":[
        "\u970d\u6069\u8d1d\u683c"
    ],
    "wof:name":"Hornberg",
    "wof:placetype":"neighbourhood"
},
  "geometry": {"coordinates":[8.57334,48.62098],"type":"Point"}
}