{
  "type": "Feature",
  "properties": {
    "gn:admin1_code":"14",
    "gn:admin2_code":"0.0",
    "gn:admin3_code":"15088.0",
    "gn:admin4_code":"15088216.0",
    "gn:asciiname":"Dalena",
    "gn:country_code":"DE",
    "gn:dem":116,
    "gn:feature_class":"P",
    "gn:feature_code":"PPL",
    "gn:name":"Dalena",
    "gn:population":0,
    "gn:timezone":"Europe/Berlin",
    "iso:country":"DE",
    "wof:name":"Dalena",
    "wof:placetype":"neighbourhood"
},
  "geometry": {"coordinates":[11.84114,51.64707],"type":"Point"}
}