{
  "type": "Feature",
  "properties": {
    "gn:admin1_code":"13",
    "gn:admin2_code":"0.0",
    "gn:admin3_code":"14523.0",
    "gn:admin4_code":"14523260.0",
    "gn:asciiname":"Dungersgruen",
    "gn:country_code":"DE",
    "gn:dem":382,
    "gn:feature_class":"P",
    "gn:feature_code":"PPL",
    "gn:name":"Dungersgr\u00fcn",
    "gn:population":0,
    "gn:timezone":"Europe/Berlin",
    "iso:country":"DE",
    "wof:name":"Dungersgruen",
    "wof:placetype":"neighbourhood"
},
  "geometry": {"coordinates":[12.23709,50.60995],"type":"Point"}
}