{
  "type": "Feature",
  "properties": {
    "gn:admin1_code":"8",
    "gn:admin2_code":"0.0",
    "gn:admin3_code":"7235.0",
    "gn:admin4_code":"7235083.0",
    "gn:asciiname":"Loersch",
    "gn:country_code":"DE",
    "gn:dem":143,
    "gn:feature_class":"P",
    "gn:feature_code":"PPL",
    "gn:name":"L\u00f6rsch",
    "gn:population":0,
    "gn:timezone":"Europe/Berlin",
    "iso:country":"DE",
    "wof:name":"Loersch",
    "wof:placetype":"neighbourhood"
},
  "geometry": {"coordinates":[6.8007,49.80077],"type":"Point"}
}