{
  "type": "Feature",
  "properties": {
    "gn:admin1_code":"2",
    "gn:admin2_code":"91.0",
    "gn:admin3_code":"9186.0",
    "gn:admin4_code":"9186162.0",
    "gn:asciiname":"Lehen",
    "gn:country_code":"DE",
    "gn:dem":394,
    "gn:feature_class":"P",
    "gn:feature_code":"PPL",
    "gn:name":"Lehen",
    "gn:population":0,
    "gn:timezone":"Europe/Berlin",
    "iso:country":"DE",
    "name:bar_x_preferred":[
        "Lehen"
    ],
    "name:deu_x_preferred":[
        "Lehen"
    ],
    "wof:name":"Lehen",
    "wof:placetype":"neighbourhood"
},
  "geometry": {"coordinates":[11.62493,48.64542],"type":"Point"}
}