{
  "type": "Feature",
  "properties": {
    "gn:admin1_code":"2",
    "gn:admin2_code":"96.0",
    "gn:admin3_code":"9678.0",
    "gn:admin4_code":"9678193.0",
    "gn:asciiname":"Vasbuhl",
    "gn:country_code":"DE",
    "gn:dem":312,
    "gn:feature_class":"P",
    "gn:feature_code":"PPL",
    "gn:name":"Vasb\u00fchl",
    "gn:population":0,
    "gn:timezone":"Europe/Berlin",
    "iso:country":"DE",
    "wof:name":"Vasbuhl",
    "wof:placetype":"neighbourhood"
},
  "geometry": {"coordinates":[10.05163,50.0223],"type":"Point"}
}