{
  "type": "Feature",
  "properties": {
    "gn:admin1_code":"2.0",
    "gn:admin2_code":"096",
    "gn:admin3_code":"9672.0",
    "gn:admin4_code":"9672135.0",
    "gn:asciiname":"Wermerichshausen",
    "gn:country_code":"DE",
    "gn:dem":325,
    "gn:feature_class":"P",
    "gn:feature_code":"PPL",
    "gn:name":"Wermerichshausen",
    "gn:population":0,
    "gn:timezone":"Europe/Berlin",
    "iso:country":"DE",
    "wof:name":"Wermerichshausen",
    "wof:placetype":"neighbourhood"
},
  "geometry": {"coordinates":[10.27288,50.2394],"type":"Point"}
}