{
  "type": "Feature",
  "properties": {
    "gn:gn_country":"DE",
    "gn:gn_fcode":"PPLA4",
    "gn:gn_pop":122,
    "gn:population":122,
    "iso:country":"DE",
    "name:bak_x_preferred":[
        "\u0422\u0430\u0439\u0445\u0432\u0438\u0446"
    ],
    "name:baq_x_preferred":[
        "Teichwitz"
    ],
    "name:chi_x_preferred":[
        "\u6cf0\u5e0c\u7ef4\u8328"
    ],
    "name:dut_x_preferred":[
        "Teichwitz"
    ],
    "name:eng_x_preferred":[
        "Teichwitz"
    ],
    "name:epo_x_preferred":[
        "Teichwitz"
    ],
    "name:fre_x_preferred":[
        "Teichwitz"
    ],
    "name:ger_x_preferred":[
        "Teichwitz"
    ],
    "name:hun_x_preferred":[
        "Teichwitz"
    ],
    "name:ita_x_preferred":[
        "Teichwitz"
    ],
    "name:kaz_x_preferred":[
        "\u0422\u0430\u0439\u0445\u0432\u0438\u0446"
    ],
    "name:kir_x_preferred":[
        "\u0422\u0430\u0439\u0445\u0432\u0438\u0446"
    ],
    "name:mac_x_preferred":[
        "\u0422\u0430\u0458\u0445\u0432\u0438\u0446"
    ],
    "name:may_x_preferred":[
        "Teichwitz"
    ],
    "name:per_x_preferred":[
        "\u062a\u0627\u06cc\u0634\u0648\u06cc\u062a\u0633"
    ],
    "name:pol_x_preferred":[
        "Teichwitz"
    ],
    "name:por_x_preferred":[
        "Teichwitz"
    ],
    "name:rum_x_preferred":[
        "Teichwitz"
    ],
    "name:rus_x_preferred":[
        "\u0422\u0430\u0439\u0445\u0432\u0438\u0446"
    ],
    "name:srp_x_preferred":[
        "\u0422\u0430\u0458\u0445\u0432\u0438\u0446"
    ],
    "name:ukr_x_preferred":[
        "\u0422\u0430\u0439\u0445\u0432\u0456\u0446"
    ],
    "name:uzb_x_preferred":[
        "Teichwitz"
    ],
    "name:vie_x_preferred":[
        "Teichwitz"
    ],
    "name:vol_x_preferred":[
        "Teichwitz"
    ],
    "name:war_x_preferred":[
        "Teichwitz"
    ],
    "qs_pg:aaroncc":"DE",
    "qs_pg:gn_country":"DE",
    "qs_pg:gn_fcode":"PPLA4",
    "qs_pg:gn_pop":122,
    "qs_pg:name":"Teichwitz",
    "qs_pg:photos_9r":0,
    "qs_pg:photos_sr":0,
    "qs_pg:pop_sr":1,
    "qs_pg:qs_pg_placetype":"locality",
    "wof:name":"Teichwitz",
    "wof:placetype":"locality",
    "wof:population":122
},
  "geometry": {"coordinates":[12.08333,50.75],"type":"Point"}
}