{
  "type": "Feature",
  "properties": {
    "gn:admin1_code":"6",
    "gn:admin2_code":"0.0",
    "gn:admin3_code":"3251.0",
    "gn:admin4_code":"3251041.0",
    "gn:asciiname":"Schorlingkamp",
    "gn:country_code":"DE",
    "gn:dem":54,
    "gn:feature_class":"P",
    "gn:feature_code":"PPL",
    "gn:name":"Schorlingkamp",
    "gn:population":0,
    "gn:timezone":"Europe/Berlin",
    "iso:country":"DE",
    "wof:name":"Schorlingkamp",
    "wof:placetype":"neighbourhood"
},
  "geometry": {"coordinates":[8.77948,52.91867],"type":"Point"}
}