{
  "type": "Feature",
  "properties": {
    "gn:admin1_code":"15",
    "gn:admin2_code":"0.0",
    "gn:admin3_code":"16072.0",
    "gn:admin4_code":"16072018.0",
    "gn:asciiname":"Koeppelsdorf",
    "gn:country_code":"DE",
    "gn:dem":399,
    "gn:feature_class":"P",
    "gn:feature_code":"PPL",
    "gn:name":"K\u00f6ppelsdorf",
    "gn:population":0,
    "gn:timezone":"Europe/Berlin",
    "iso:country":"DE",
    "name:und_x_variant":[
        "K\u00f6ppelsdorf"
    ],
    "wof:name":"Koeppelsdorf",
    "wof:placetype":"neighbourhood"
},
  "geometry": {"coordinates":[11.20892,50.35828],"type":"Point"}
}