{
  "type": "Feature",
  "properties": {
    "gn:admin1_code":"2",
    "gn:admin2_code":"96.0",
    "gn:admin3_code":"9673.0",
    "gn:admin4_code":"9673123.0",
    "gn:asciiname":"Sands",
    "gn:country_code":"DE",
    "gn:dem":411,
    "gn:feature_class":"P",
    "gn:feature_code":"PPL",
    "gn:name":"Sands",
    "gn:population":0,
    "gn:timezone":"Europe/Berlin",
    "iso:country":"DE",
    "name:deu_x_preferred":[
        "Sands"
    ],
    "name:fra_x_preferred":[
        "Sands"
    ],
    "name:heb_x_preferred":[
        "\u05e1\u05e0\u05d3\u05e1"
    ],
    "name:ita_x_preferred":[
        "Sands"
    ],
    "name:jpn_x_preferred":[
        "\u30b5\u30f3\u30ba"
    ],
    "wof:name":"Sands",
    "wof:placetype":"neighbourhood"
},
  "geometry": {"coordinates":[10.18662,50.52315],"type":"Point"}
}