{
  "type": "Feature",
  "properties": {
    "gn:admin1_code":"13",
    "gn:admin2_code":"0.0",
    "gn:admin3_code":"14522.0",
    "gn:admin4_code":"14522440.0",
    "gn:asciiname":"Hetzdorf",
    "gn:country_code":"DE",
    "gn:dem":325,
    "gn:feature_class":"P",
    "gn:feature_code":"PPL",
    "gn:name":"Hetzdorf",
    "gn:population":0,
    "gn:timezone":"Europe/Berlin",
    "iso:country":"DE",
    "wof:name":"Hetzdorf",
    "wof:placetype":"neighbourhood"
},
  "geometry": {"coordinates":[13.14502,50.84562],"type":"Point"}
}