{
  "type": "Feature",
  "properties": {
    "gn:admin1_code":"5",
    "gn:admin2_code":"64.0",
    "gn:admin3_code":"6439.0",
    "gn:admin4_code":"6439015.0",
    "gn:asciiname":"Orlen",
    "gn:country_code":"DE",
    "gn:dem":417,
    "gn:feature_class":"P",
    "gn:feature_code":"PPL",
    "gn:name":"Orlen",
    "gn:population":0,
    "gn:timezone":"Europe/Berlin",
    "iso:country":"DE",
    "wof:name":"Orlen",
    "wof:placetype":"neighbourhood"
},
  "geometry": {"coordinates":[8.1868,50.18163],"type":"Point"}
}