{
  "type": "Feature",
  "properties": {
    "gn:admin1_code":"15",
    "gn:admin2_code":"0.0",
    "gn:admin3_code":"16072.0",
    "gn:admin4_code":"16072009.0",
    "gn:asciiname":"Neuenbau",
    "gn:country_code":"DE",
    "gn:dem":716,
    "gn:feature_class":"P",
    "gn:feature_code":"PPL",
    "gn:name":"Neuenbau",
    "gn:population":0,
    "gn:timezone":"Europe/Berlin",
    "iso:country":"DE",
    "wof:name":"Neuenbau",
    "wof:placetype":"neighbourhood"
},
  "geometry": {"coordinates":[11.23999,50.43706],"type":"Point"}
}