{
  "type": "Feature",
  "properties": {
    "gn:admin1_code":"5.0",
    "gn:admin2_code":"066",
    "gn:admin3_code":"6633.0",
    "gn:admin4_code":"6633005.0",
    "gn:asciiname":"Westuffeln",
    "gn:country_code":"DE",
    "gn:dem":198,
    "gn:feature_class":"P",
    "gn:feature_code":"PPL",
    "gn:name":"Westuffeln",
    "gn:population":0,
    "gn:timezone":"Europe/Berlin",
    "iso:country":"DE",
    "wof:name":"Westuffeln",
    "wof:placetype":"neighbourhood"
},
  "geometry": {"coordinates":[9.32583,51.43412],"type":"Point"}
}