{
  "type": "Feature",
  "properties": {
    "gn:admin1_code":"7",
    "gn:admin2_code":"53.0",
    "gn:admin3_code":"5358.0",
    "gn:admin4_code":"5358008.0",
    "gn:asciiname":"Guerzenich",
    "gn:country_code":"DE",
    "gn:dem":135,
    "gn:feature_class":"P",
    "gn:feature_code":"PPL",
    "gn:name":"G\u00fcrzenich",
    "gn:population":0,
    "gn:timezone":"Europe/Berlin",
    "iso:country":"DE",
    "wof:name":"Guerzenich",
    "wof:placetype":"neighbourhood"
},
  "geometry": {"coordinates":[6.44338,50.79173],"type":"Point"}
}