{
  "type": "Feature",
  "properties": {
    "gn:admin1_code":"2",
    "gn:admin2_code":"92.0",
    "gn:admin3_code":"9271.0",
    "gn:admin4_code":"9271123.0",
    "gn:asciiname":"Maging",
    "gn:country_code":"DE",
    "gn:dem":395,
    "gn:feature_class":"P",
    "gn:feature_code":"PPLL",
    "gn:name":"Maging",
    "gn:population":0,
    "gn:timezone":"Europe/Berlin",
    "iso:country":"DE",
    "wof:name":"Maging",
    "wof:placetype":"neighbourhood"
},
  "geometry": {"coordinates":[13.11986,48.79807],"type":"Point"}
}