{
  "type": "Feature",
  "properties": {
    "gn:admin1_code":"2",
    "gn:admin2_code":"93.0",
    "gn:admin3_code":"9374.0",
    "gn:admin4_code":"9374111.0",
    "gn:asciiname":"Sussenlohe",
    "gn:country_code":"DE",
    "gn:dem":418,
    "gn:feature_class":"P",
    "gn:feature_code":"PPL",
    "gn:name":"S\u00fc\u00dfenlohe",
    "gn:population":0,
    "gn:timezone":"Europe/Berlin",
    "iso:country":"DE",
    "wof:name":"Sussenlohe",
    "wof:placetype":"neighbourhood"
},
  "geometry": {"coordinates":[12.14078,49.72725],"type":"Point"}
}