{
  "type": "Feature",
  "properties": {
    "gn:admin1_code":"5.0",
    "gn:admin2_code":"065",
    "gn:admin3_code":"6535.0",
    "gn:admin4_code":"6535011.0",
    "gn:asciiname":"Wernges",
    "gn:country_code":"DE",
    "gn:dem":371,
    "gn:feature_class":"P",
    "gn:feature_code":"PPL",
    "gn:name":"Wernges",
    "gn:population":0,
    "gn:timezone":"Europe/Berlin",
    "iso:country":"DE",
    "wof:name":"Wernges",
    "wof:placetype":"neighbourhood"
},
  "geometry": {"coordinates":[9.42077,50.67701],"type":"Point"}
}