{
  "type": "Feature",
  "properties": {
    "gn:admin1_code":"7",
    "gn:admin2_code":"57.0",
    "gn:admin3_code":"5758.0",
    "gn:admin4_code":"5758036.0",
    "gn:asciiname":"Exter",
    "gn:country_code":"DE",
    "gn:dem":115,
    "gn:feature_class":"P",
    "gn:feature_code":"PPL",
    "gn:name":"Exter",
    "gn:population":0,
    "gn:timezone":"Europe/Berlin",
    "iso:country":"DE",
    "name:deu_x_preferred":[
        "Exter"
    ],
    "name:fas_x_preferred":[
        "\u0627\u06a9\u0633\u062a\u0631"
    ],
    "name:nld_x_preferred":[
        "Exter"
    ],
    "wof:name":"Exter",
    "wof:placetype":"neighbourhood"
},
  "geometry": {"coordinates":[8.77888,52.13703],"type":"Point"}
}