{
  "type": "Feature",
  "properties": {
    "gn:country":"DE",
    "gn:fcode":"PPL",
    "gn:population":0,
    "iso:country":"DE",
    "name:bar_x_preferred":[
        "Schambach"
    ],
    "name:deu_x_preferred":[
        "Schambach"
    ],
    "name:eng_x_preferred":[
        "Schambach"
    ],
    "name:fra_x_preferred":[
        "Schambach"
    ],
    "name:gle_x_preferred":[
        "Schambach"
    ],
    "name:nld_x_preferred":[
        "Schambach"
    ],
    "qs_pg:aaroncc":"DE",
    "qs_pg:gn_country":"DE",
    "qs_pg:gn_fcode":"PPL",
    "qs_pg:gn_pop":0,
    "qs_pg:name":"Schambach",
    "qs_pg:name_adm0":"Deutschland",
    "qs_pg:name_adm1":"Bayern",
    "qs_pg:photos_9k":1,
    "qs_pg:photos_9r":1,
    "qs_pg:photos_all":5,
    "qs_pg:photos_sr":0,
    "qs_pg:pop_sr":0,
    "qs_pg:qs_pg_placetype":"locality",
    "qs_pg:qs_pg_placetype_gp":"Town",
    "qs_pg:woe_adm0":23424829,
    "woe:adm0_id":23424829,
    "woe:name_adm0":"Deutschland",
    "woe:name_adm1":"Bayern",
    "woe:placetype":"Town",
    "wof:name":"Schambach",
    "wof:placetype":"neighbourhood"
},
  "geometry": {"coordinates":[12.68884,48.85258],"type":"Point"}
}