{
  "type": "Feature",
  "properties": {
    "gn:admin1_code":"10.0",
    "gn:admin2_code":"0.0",
    "gn:admin3_code":"1055.0",
    "gn:admin4_code":"1055037.0",
    "gn:asciiname":"Bliesdorf",
    "gn:country_code":"DE",
    "gn:dem":37,
    "gn:feature_class":"P",
    "gn:feature_code":"PPL",
    "gn:name":"Bliesdorf",
    "gn:population":0,
    "gn:timezone":"Europe/Berlin",
    "iso:country":"DE",
    "name:ceb_x_preferred":[
        "Bliesdorf"
    ],
    "name:deu_x_preferred":[
        "Bliesdorf"
    ],
    "name:epo_x_preferred":[
        "Bliesdorf"
    ],
    "name:eus_x_preferred":[
        "Bliesdorf"
    ],
    "name:fas_x_preferred":[
        "\u0628\u0644\u06cc\u0633\u062f\u0648\u0631\u0641"
    ],
    "name:fra_x_preferred":[
        "Bliesdorf"
    ],
    "name:hun_x_preferred":[
        "Bliesdorf"
    ],
    "name:hye_x_preferred":[
        "\u0532\u056c\u056b\u057d\u0564\u0578\u0580\u0586"
    ],
    "name:ile_x_preferred":[
        "Bliesdorf"
    ],
    "name:ita_x_preferred":[
        "Bliesdorf"
    ],
    "name:mkd_x_preferred":[
        "\u0411\u043b\u0438\u0441\u0434\u043e\u0440\u0444"
    ],
    "name:msa_x_preferred":[
        "Bliesdorf"
    ],
    "name:nld_x_preferred":[
        "Bliesdorf"
    ],
    "name:pol_x_preferred":[
        "Bliesdorf"
    ],
    "name:ron_x_preferred":[
        "Bliesdorf"
    ],
    "name:rus_x_preferred":[
        "\u0411\u043b\u0438\u0441\u0434\u043e\u0440\u0444"
    ],
    "name:spa_x_preferred":[
        "Bliesdorf"
    ],
    "name:srp_x_preferred":[
        "\u0411\u043b\u0438\u0441\u0434\u043e\u0440\u0444"
    ],
    "name:ukr_x_preferred":[
        "\u0411\u043b\u0456\u0441\u0434\u043e\u0440\u0444"
    ],
    "name:uzb_x_preferred":[
        "Bliesdorf"
    ],
    "name:vie_x_preferred":[
        "Bliesdorf"
    ],
    "name:vol_x_preferred":[
        "Bliesdorf"
    ],
    "name:war_x_preferred":[
        "Bliesdorf"
    ],
    "name:zho_x_preferred":[
        "\u5e03\u5229\u65af\u591a\u592b"
    ],
    "wof:name":"Bliesdorf",
    "wof:placetype":"neighbourhood"
},
  "geometry": {"coordinates":[10.90964,54.1304],"type":"Point"}
}