{
  "type": "Feature",
  "properties": {
    "gn:admin1_code":"13",
    "gn:admin2_code":"0.0",
    "gn:admin3_code":"14730.0",
    "gn:admin4_code":"14730150.0",
    "gn:asciiname":"Hohenossig",
    "gn:country_code":"DE",
    "gn:dem":128,
    "gn:feature_class":"P",
    "gn:feature_code":"PPL",
    "gn:name":"Hohenossig",
    "gn:population":0,
    "gn:timezone":"Europe/Berlin",
    "iso:country":"DE",
    "wof:name":"Hohenossig",
    "wof:placetype":"neighbourhood"
},
  "geometry": {"coordinates":[12.41996,51.44411],"type":"Point"}
}