{
  "type": "Feature",
  "properties": {
    "gn:admin1_code":"7",
    "gn:admin2_code":"59.0",
    "gn:admin3_code":"5962.0",
    "gn:admin4_code":"5962020.0",
    "gn:asciiname":"Verse",
    "gn:country_code":"DE",
    "gn:dem":327,
    "gn:feature_class":"P",
    "gn:feature_code":"PPL",
    "gn:name":"Verse",
    "gn:population":0,
    "gn:timezone":"Europe/Berlin",
    "iso:country":"DE",
    "name:aze_x_preferred":[
        "Ekspromt"
    ],
    "name:ceb_x_preferred":[
        "Verse"
    ],
    "name:deu_x_preferred":[
        "Verse"
    ],
    "name:fra_x_preferred":[
        "Verse"
    ],
    "name:swe_x_preferred":[
        "Verse"
    ],
    "wof:name":"Verse",
    "wof:placetype":"neighbourhood"
},
  "geometry": {"coordinates":[7.71883,51.19789],"type":"Point"}
}