{
  "type": "Feature",
  "properties": {
    "gn:admin1_code":"2",
    "gn:admin2_code":"93.0",
    "gn:admin3_code":"9374.0",
    "gn:admin4_code":"9374117.0",
    "gn:asciiname":"Stegenthumbach",
    "gn:country_code":"DE",
    "gn:dem":439,
    "gn:feature_class":"P",
    "gn:feature_code":"PPL",
    "gn:name":"Stegenthumbach",
    "gn:population":0,
    "gn:timezone":"Europe/Berlin",
    "iso:country":"DE",
    "wof:name":"Stegenthumbach",
    "wof:placetype":"neighbourhood"
},
  "geometry": {"coordinates":[11.82035,49.73742],"type":"Point"}
}