{
  "type": "Feature",
  "properties": {
    "gn:admin1_code":"7",
    "gn:admin2_code":"55.0",
    "gn:admin3_code":"5566.0",
    "gn:admin4_code":"5566032.0",
    "gn:asciiname":"Overbeck",
    "gn:country_code":"DE",
    "gn:dem":55,
    "gn:feature_class":"P",
    "gn:feature_code":"PPLL",
    "gn:name":"Overbeck",
    "gn:population":0,
    "gn:timezone":"Europe/Berlin",
    "iso:country":"DE",
    "name:deu_x_preferred":[
        "Overbeck"
    ],
    "name:swe_x_preferred":[
        "Overbeck"
    ],
    "wof:name":"Overbeck",
    "wof:placetype":"neighbourhood"
},
  "geometry": {"coordinates":[7.73661,52.15308],"type":"Point"}
}