{
  "type": "Feature",
  "properties": {
    "gn:admin1_code":"12",
    "gn:admin2_code":"0.0",
    "gn:admin3_code":"13072.0",
    "gn:admin4_code":"13072093.0",
    "gn:asciiname":"Radegast",
    "gn:country_code":"DE",
    "gn:dem":61,
    "gn:feature_class":"P",
    "gn:feature_code":"PPL",
    "gn:name":"Radegast",
    "gn:population":0,
    "gn:timezone":"Europe/Berlin",
    "iso:country":"DE",
    "wof:name":"Radegast",
    "wof:placetype":"neighbourhood"
},
  "geometry": {"coordinates":[11.85291,53.96632],"type":"Point"}
}