{
  "type": "Feature",
  "properties": {
    "gn:admin1_code":"12",
    "gn:admin2_code":"0.0",
    "gn:admin3_code":"13072.0",
    "gn:admin4_code":"13072093.0",
    "gn:asciiname":"Radegast",
    "gn:country_code":"DE",
    "gn:dem":61,
    "gn:feature_class":"P",
    "gn:feature_code":"PPL",
    "gn:name":"Radegast",
    "gn:population":0,
    "gn:timezone":"Europe/Berlin",
    "iso:country":"DE",
    "name:bak_x_preferred":[
        "\u0420\u0430\u0434\u0435\u0433\u0430\u0441\u0442"
    ],
    "name:ceb_x_preferred":[
        "Radegast"
    ],
    "name:deu_x_preferred":[
        "Stadt Radegast"
    ],
    "name:epo_x_preferred":[
        "Radegast"
    ],
    "name:fas_x_preferred":[
        "\u0631\u0627\u062f\u06af\u0627\u0634\u062a"
    ],
    "name:fra_x_preferred":[
        "Radegast"
    ],
    "name:ita_x_preferred":[
        "Radegast"
    ],
    "name:kaz_x_preferred":[
        "\u0420\u0430\u0434\u0435\u0433\u0430\u0441\u0442"
    ],
    "name:kir_x_preferred":[
        "\u0420\u0430\u0434\u0435\u0433\u0430\u0441\u0442"
    ],
    "name:mkd_x_preferred":[
        "\u0420\u0430\u0434\u0435\u0433\u0430\u0441\u0442"
    ],
    "name:nld_x_preferred":[
        "Radegast"
    ],
    "name:pol_x_preferred":[
        "Radegast"
    ],
    "name:ron_x_preferred":[
        "Radegast"
    ],
    "name:rus_x_preferred":[
        "\u0420\u0430\u0434\u0435\u0433\u0430\u0441\u0442"
    ],
    "name:uzb_x_preferred":[
        "Radegast"
    ],
    "name:vie_x_preferred":[
        "Radegast"
    ],
    "name:vol_x_preferred":[
        "Radegast"
    ],
    "name:zho_x_preferred":[
        "\u62c9\u5fb7\u52a0\u65af\u7279"
    ],
    "wof:name":"Radegast",
    "wof:placetype":"neighbourhood"
},
  "geometry": {"coordinates":[11.85291,53.96632],"type":"Point"}
}