{
  "type": "Feature",
  "properties": {
    "gn:admin1_code":"13.0",
    "gn:admin2_code":"0.0",
    "gn:admin3_code":"14628.0",
    "gn:admin4_code":"14628360.0",
    "gn:asciiname":"Kirnitzsch",
    "gn:country_code":"DE",
    "gn:dem":151,
    "gn:feature_class":"P",
    "gn:feature_code":"PPL",
    "gn:name":"Kirnitzsch",
    "gn:population":0,
    "gn:timezone":"Europe/Berlin",
    "iso:country":"DE",
    "name:ceb_x_preferred":[
        "Kirnitzsch"
    ],
    "name:ces_x_preferred":[
        "K\u0159inice"
    ],
    "name:deu_x_preferred":[
        "Kirnitzsch"
    ],
    "name:fas_x_preferred":[
        "\u06a9\u06cc\u0631\u0646\u06cc\u062a\u0686"
    ],
    "name:hsb_x_preferred":[
        "Kirnitzsch"
    ],
    "name:nld_x_preferred":[
        "Kirnitzsch"
    ],
    "name:pol_x_preferred":[
        "K\u0159inice"
    ],
    "name:rus_x_preferred":[
        "\u041a\u0438\u0440\u043d\u0438\u0447"
    ],
    "wof:name":"Kirnitzsch",
    "wof:placetype":"neighbourhood"
},
  "geometry": {"coordinates":[14.19419,50.92933],"type":"Point"}
}