{
  "type": "Feature",
  "properties": {
    "gn:admin1_code":"13",
    "gn:admin2_code":"0.0",
    "gn:admin3_code":"14626.0",
    "gn:admin4_code":"14626250.0",
    "gn:asciiname":"Podrosche",
    "gn:cc2":"DE",
    "gn:country_code":"DE",
    "gn:dem":128,
    "gn:feature_class":"P",
    "gn:feature_code":"PPL",
    "gn:name":"Podrosche",
    "gn:population":0,
    "gn:timezone":"Europe/Berlin",
    "iso:country":"DE",
    "name:hsb_x_preferred":[
        "Podro\u017ed\u017a"
    ],
    "name:und_x_variant":[
        "Grenzkirch",
        "Podrosche"
    ],
    "wof:name":"Podrosche",
    "wof:placetype":"neighbourhood"
},
  "geometry": {"coordinates":[14.94561,51.47005],"type":"Point"}
}