{
  "type": "Feature",
  "properties": {
    "gn:gn_country":"DE",
    "gn:gn_fcode":"PPLA4",
    "gn:gn_pop":979,
    "gn:population":979,
    "iso:country":"DE",
    "name:baq_x_preferred":[
        "Neidenfels"
    ],
    "name:chi_x_preferred":[
        "\u5948\u767b\u8d39\u5c14\u65af"
    ],
    "name:dut_x_preferred":[
        "Neidenfels"
    ],
    "name:eng_x_preferred":[
        "Neidenfels"
    ],
    "name:epo_x_preferred":[
        "Neidenfels"
    ],
    "name:fre_x_preferred":[
        "Neidenfels"
    ],
    "name:ger_x_preferred":[
        "Neidenfels"
    ],
    "name:hun_x_preferred":[
        "Neidenfels"
    ],
    "name:ita_x_preferred":[
        "Neidenfels"
    ],
    "name:jpn_x_preferred":[
        "\u30ca\u30a4\u30c7\u30f3\u30d5\u30a7\u30eb\u30b9"
    ],
    "name:kaz_x_preferred":[
        "\u041d\u0430\u0439\u0434\u0435\u043d\u0444\u0435\u043b\u044c\u0441"
    ],
    "name:kir_x_preferred":[
        "\u041d\u0430\u0439\u0434\u0435\u043d\u0444\u0435\u043b\u044c\u0441"
    ],
    "name:may_x_preferred":[
        "Neidenfels"
    ],
    "name:per_x_preferred":[
        "\u0646\u0627\u06cc\u062f\u0646\u0641\u0644\u0633"
    ],
    "name:pol_x_preferred":[
        "Neidenfels"
    ],
    "name:por_x_preferred":[
        "Neidenfels"
    ],
    "name:rum_x_preferred":[
        "Neidenfels"
    ],
    "name:rus_x_preferred":[
        "\u041d\u0430\u0439\u0434\u0435\u043d\u0444\u0435\u043b\u044c\u0441"
    ],
    "name:srp_x_preferred":[
        "\u041d\u0430\u0458\u0434\u0435\u043d\u0444\u0435\u043b\u0441"
    ],
    "name:ukr_x_preferred":[
        "\u041d\u0430\u0439\u0434\u0435\u043d\u0444\u0435\u043b\u044c\u0441"
    ],
    "name:uzb_x_preferred":[
        "Neidenfels"
    ],
    "name:vol_x_preferred":[
        "Neidenfels"
    ],
    "name:war_x_preferred":[
        "Neidenfels"
    ],
    "qs_pg:aaroncc":"DE",
    "qs_pg:gn_country":"DE",
    "qs_pg:gn_fcode":"PPLA4",
    "qs_pg:gn_pop":979,
    "qs_pg:name":"Neidenfels",
    "qs_pg:photos_9r":0,
    "qs_pg:photos_sr":0,
    "qs_pg:pop_sr":2,
    "qs_pg:qs_pg_placetype":"locality",
    "wof:name":"Neidenfels",
    "wof:placetype":"locality",
    "wof:population":979
},
  "geometry": {"coordinates":[8.04639,49.38889],"type":"Point"}
}