{
  "type": "Feature",
  "properties": {
    "gn:admin1_code":"15",
    "gn:admin2_code":"0.0",
    "gn:admin3_code":"16064.0",
    "gn:admin4_code":"16064071.0",
    "gn:asciiname":"Reiser",
    "gn:country_code":"DE",
    "gn:dem":235,
    "gn:feature_class":"P",
    "gn:feature_code":"PPL",
    "gn:name":"Reiser",
    "gn:population":0,
    "gn:timezone":"Europe/Berlin",
    "iso:country":"DE",
    "name:ces_x_preferred":[
        "Reiser"
    ],
    "name:deu_x_preferred":[
        "Reiser"
    ],
    "name:fra_x_preferred":[
        "Reiser"
    ],
    "name:heb_x_preferred":[
        "\u05e8\u05d9\u05d9\u05d6\u05e8"
    ],
    "name:rus_x_preferred":[
        "\u0420\u0430\u0439\u0437\u0435\u0440"
    ],
    "name:spa_x_preferred":[
        "Reiser"
    ],
    "wof:name":"Reiser",
    "wof:placetype":"neighbourhood"
},
  "geometry": {"coordinates":[10.46958,51.25218],"type":"Point"}
}