{
  "type": "Feature",
  "properties": {
    "gn:admin1_code":"14",
    "gn:admin2_code":"0.0",
    "gn:admin3_code":"15084.0",
    "gn:admin4_code":"15084565.0",
    "gn:asciiname":"Gossra",
    "gn:country_code":"DE",
    "gn:dem":244,
    "gn:feature_class":"P",
    "gn:feature_code":"PPL",
    "gn:name":"Go\u00dfra",
    "gn:population":0,
    "gn:timezone":"Europe/Berlin",
    "iso:country":"DE",
    "wof:name":"Gossra",
    "wof:placetype":"neighbourhood"
},
  "geometry": {"coordinates":[12.06571,51.01222],"type":"Point"}
}