{
  "type": "Feature",
  "properties": {
    "gn:admin1_code":"6",
    "gn:admin2_code":"0.0",
    "gn:admin3_code":"3256.0",
    "gn:admin4_code":"3256034.0",
    "gn:asciiname":"Brueninghorstedt",
    "gn:country_code":"DE",
    "gn:dem":51,
    "gn:feature_class":"P",
    "gn:feature_code":"PPL",
    "gn:name":"Br\u00fcninghorstedt",
    "gn:population":0,
    "gn:timezone":"Europe/Berlin",
    "iso:country":"DE",
    "wof:name":"Brueninghorstedt",
    "wof:placetype":"neighbourhood"
},
  "geometry": {"coordinates":[8.88398,52.41072],"type":"Point"}
}