{
  "type": "Feature",
  "properties": {
    "gn:admin1_code":"6.0",
    "gn:admin2_code":"0.0",
    "gn:admin3_code":"3453.0",
    "gn:admin4_code":"3453010.0",
    "gn:asciiname":"Auen",
    "gn:country_code":"DE",
    "gn:dem":39,
    "gn:feature_class":"P",
    "gn:feature_code":"PPL",
    "gn:name":"Auen",
    "gn:population":0,
    "gn:timezone":"Europe/Berlin",
    "iso:country":"DE",
    "name:ceb_x_preferred":[
        "Auen"
    ],
    "name:deu_x_preferred":[
        "Auen"
    ],
    "name:epo_x_preferred":[
        "Auen"
    ],
    "name:pol_x_preferred":[
        "Auen"
    ],
    "name:swe_x_preferred":[
        "Auen"
    ],
    "wof:name":"Auen",
    "wof:placetype":"neighbourhood"
},
  "geometry": {"coordinates":[7.73093,52.84385],"type":"Point"}
}