{
  "type": "Feature",
  "properties": {
    "gn:admin1_code":"6.0",
    "gn:admin2_code":"0.0",
    "gn:admin3_code":"3360.0",
    "gn:admin4_code":"3360023.0",
    "gn:asciiname":"Boddenstedt",
    "gn:country_code":"DE",
    "gn:dem":68,
    "gn:feature_class":"P",
    "gn:feature_code":"PPL",
    "gn:name":"B\u00f6ddenstedt",
    "gn:population":0,
    "gn:timezone":"Europe/Berlin",
    "iso:country":"DE",
    "name:deu_x_preferred":[
        "B\u00f6ddenstedt (Suderburg)"
    ],
    "name:nds_x_preferred":[
        "B\u00f6enst\u00e4e"
    ],
    "name:nds_x_variant":[
        "B\u022b\u0259nst\u01df\u0259",
        "b\u00f8\u02d0\u0259nst\u025b\u02d0\u0259"
    ],
    "wof:name":"Boddenstedt",
    "wof:placetype":"neighbourhood"
},
  "geometry": {"coordinates":[10.44233,52.93095],"type":"Point"}
}