{
  "type": "Feature",
  "properties": {
    "gn:admin1_code":"11.0",
    "gn:admin2_code":"0.0",
    "gn:admin3_code":"12063.0",
    "gn:admin4_code":"12063208.0",
    "gn:asciiname":"Am Weinberg",
    "gn:country_code":"DE",
    "gn:dem":27,
    "gn:feature_class":"P",
    "gn:feature_code":"PPL",
    "gn:name":"Am Weinberg",
    "gn:population":0,
    "gn:timezone":"Europe/Berlin",
    "iso:country":"DE",
    "wof:name":"Am Weinberg",
    "wof:placetype":"neighbourhood"
},
  "geometry": {"coordinates":[12.88851,52.62754],"type":"Point"}
}