{
  "type": "Feature",
  "properties": {
    "gn:admin1_code":"1",
    "gn:admin2_code":"81.0",
    "gn:admin3_code":"8117.0",
    "gn:admin4_code":"8117061.0",
    "gn:asciiname":"Nenningen",
    "gn:country_code":"DE",
    "gn:dem":470,
    "gn:feature_class":"P",
    "gn:feature_code":"PPL",
    "gn:name":"Nenningen",
    "gn:population":0,
    "gn:timezone":"Europe/Berlin",
    "iso:country":"DE",
    "wof:name":"Nenningen",
    "wof:placetype":"neighbourhood"
},
  "geometry": {"coordinates":[9.86229,48.71039],"type":"Point"}
}