{
  "type": "Feature",
  "properties": {
    "gn:admin1_code":"8.0",
    "gn:admin2_code":"0.0",
    "gn:admin3_code":"7313.0",
    "gn:admin4_code":"7313000.0",
    "gn:asciiname":"Arzheim",
    "gn:country_code":"DE",
    "gn:dem":204,
    "gn:feature_class":"P",
    "gn:feature_code":"PPL",
    "gn:name":"Arzheim",
    "gn:population":0,
    "gn:timezone":"Europe/Berlin",
    "iso:country":"DE",
    "wof:name":"Arzheim",
    "wof:placetype":"neighbourhood"
},
  "geometry": {"coordinates":[8.06916,49.19354000000001],"type":"Point"}
}