{
  "type": "Feature",
  "properties": {
    "gn:admin1_code":"6",
    "gn:admin2_code":"0.0",
    "gn:admin3_code":"3251.0",
    "gn:admin4_code":"3251013.0",
    "gn:asciiname":"Jakobidrebber",
    "gn:country_code":"DE",
    "gn:dem":39,
    "gn:feature_class":"P",
    "gn:feature_code":"PPL",
    "gn:name":"Jakobidrebber",
    "gn:population":0,
    "gn:timezone":"Europe/Berlin",
    "iso:country":"DE",
    "wof:name":"Jakobidrebber",
    "wof:placetype":"neighbourhood"
},
  "geometry": {"coordinates":[8.42487,52.64973000000001],"type":"Point"}
}