{
  "type": "Feature",
  "properties": {
    "gn:admin1_code":"7",
    "gn:admin2_code":"59.0",
    "gn:admin3_code":"5914.0",
    "gn:admin4_code":"5914000.0",
    "gn:asciiname":"Henkhausen",
    "gn:country_code":"DE",
    "gn:dem":146,
    "gn:feature_class":"P",
    "gn:feature_code":"PPL",
    "gn:name":"Henkhausen",
    "gn:population":0,
    "gn:timezone":"Europe/Berlin",
    "iso:country":"DE",
    "wof:name":"Henkhausen",
    "wof:placetype":"neighbourhood"
},
  "geometry": {"coordinates":[7.56027,51.36858],"type":"Point"}
}