{
  "type": "Feature",
  "properties": {
    "gn:admin1_code":"2.0",
    "gn:admin2_code":"93.0",
    "gn:admin3_code":"9372.0",
    "gn:admin4_code":"9372177.0",
    "gn:asciiname":"Bierwinkl",
    "gn:country_code":"DE",
    "gn:dem":504,
    "gn:feature_class":"P",
    "gn:feature_code":"PPL",
    "gn:name":"Bierwinkl",
    "gn:population":0,
    "gn:timezone":"Europe/Berlin",
    "iso:country":"DE",
    "wof:name":"Bierwinkl",
    "wof:placetype":"neighbourhood"
},
  "geometry": {"coordinates":[12.70342,49.14653],"type":"Point"}
}