{
  "type": "Feature",
  "properties": {
    "gn:country":"DE",
    "gn:fcode":"PPL",
    "gn:population":79,
    "iso:country":"DE",
    "name:ara_x_preferred":[
        "\u0628\u064a\u0644\u064a\u062a\u0633"
    ],
    "name:azb_x_preferred":[
        "\u0628\u0644\u06cc\u062a\u0632"
    ],
    "name:ceb_x_preferred":[
        "Beelitz"
    ],
    "name:dan_x_preferred":[
        "Beelitz"
    ],
    "name:deu_x_preferred":[
        "Beelitz"
    ],
    "name:epo_x_preferred":[
        "Beelitz"
    ],
    "name:fas_x_preferred":[
        "\u0628\u0644\u06cc\u062a\u0632"
    ],
    "name:fra_x_preferred":[
        "Beelitz"
    ],
    "name:hun_x_preferred":[
        "Beelitz"
    ],
    "name:hye_x_preferred":[
        "\u0532\u0565\u056c\u056b\u0581"
    ],
    "name:ita_x_preferred":[
        "Beelitz"
    ],
    "name:lav_x_preferred":[
        "B\u0113lica"
    ],
    "name:mkd_x_preferred":[
        "\u0411\u0435\u043b\u0438\u0446"
    ],
    "name:msa_x_preferred":[
        "Beelitz"
    ],
    "name:nld_x_preferred":[
        "Beelitz"
    ],
    "name:nor_x_preferred":[
        "Beelitz"
    ],
    "name:pol_x_preferred":[
        "Beelitz"
    ],
    "name:ron_x_preferred":[
        "Beelitz"
    ],
    "name:rus_x_preferred":[
        "\u0411\u0435\u043b\u0438\u0446"
    ],
    "name:spa_x_preferred":[
        "Beelitz"
    ],
    "name:srp_x_preferred":[
        "\u0411\u0435\u043b\u0438\u0446"
    ],
    "name:swe_x_preferred":[
        "Beelitz"
    ],
    "name:tur_x_preferred":[
        "Beelitz"
    ],
    "name:ukr_x_preferred":[
        "\u0411\u0435\u043b\u0456\u0446"
    ],
    "name:uzb_x_preferred":[
        "Beelitz"
    ],
    "name:vie_x_preferred":[
        "Beelitz"
    ],
    "name:vol_x_preferred":[
        "Beelitz"
    ],
    "name:war_x_preferred":[
        "Beelitz"
    ],
    "name:zho_x_preferred":[
        "\u8d1d\u5229\u8328"
    ],
    "qs_pg:aaroncc":"DE",
    "qs_pg:gn_country":"DE",
    "qs_pg:gn_fcode":"PPL",
    "qs_pg:gn_pop":79,
    "qs_pg:name":"Beelitz",
    "qs_pg:name_adm0":"Deutschland",
    "qs_pg:name_adm1":"Sachsen-Anhalt",
    "qs_pg:photos_9k":1,
    "qs_pg:photos_9r":1,
    "qs_pg:photos_all":2,
    "qs_pg:photos_sr":0,
    "qs_pg:pop_sr":1,
    "qs_pg:qs_pg_placetype":"locality",
    "qs_pg:qs_pg_placetype_gp":"Town",
    "qs_pg:woe_adm0":23424829,
    "woe:adm0_id":23424829,
    "woe:name_adm0":"Deutschland",
    "woe:name_adm1":"Sachsen-Anhalt",
    "woe:placetype":"Town",
    "wof:name":"Beelitz",
    "wof:placetype":"neighbourhood",
    "wof:population":79
},
  "geometry": {"coordinates":[11.95364,52.68835],"type":"Point"}
}