{
  "type": "Feature",
  "properties": {
    "gn:admin1_code":"13",
    "gn:admin2_code":"0.0",
    "gn:admin3_code":"14627.0",
    "gn:admin4_code":"14627190.0",
    "gn:asciiname":"Goltzscha",
    "gn:country_code":"DE",
    "gn:dem":119,
    "gn:feature_class":"P",
    "gn:feature_code":"PPL",
    "gn:name":"Goltzscha",
    "gn:population":0,
    "gn:timezone":"Europe/Berlin",
    "iso:country":"DE",
    "wof:name":"Goltzscha",
    "wof:placetype":"neighbourhood"
},
  "geometry": {"coordinates":[13.4358,51.27119],"type":"Point"}
}