{
  "type": "Feature",
  "properties": {
    "gn:admin1_code":"6",
    "gn:admin2_code":"0.0",
    "gn:admin3_code":"3459.0",
    "gn:admin4_code":"3459029.0",
    "gn:asciiname":"Hitz-Joestinghausen",
    "gn:country_code":"DE",
    "gn:dem":77,
    "gn:feature_class":"P",
    "gn:feature_code":"PPL",
    "gn:name":"Hitz-J\u00f6stinghausen",
    "gn:population":0,
    "gn:timezone":"Europe/Berlin",
    "iso:country":"DE",
    "wof:name":"Hitz-Joestinghausen",
    "wof:placetype":"neighbourhood"
},
  "geometry": {"coordinates":[8.26667,52.33333],"type":"Point"}
}