{
  "type": "Feature",
  "properties": {
    "iso:country":"DE",
    "name:cat_x_preferred":[
        "S\u00fclldorf"
    ],
    "name:deu_x_preferred":[
        "S\u00fclldorf"
    ],
    "name:eng_x_preferred":[
        "S\u00fclldorf"
    ],
    "name:fas_x_preferred":[
        "\u0633\u0648\u0644\u062f\u0648\u0631\u0641"
    ],
    "name:fra_x_preferred":[
        "Hamburg-S\u00fclldorf"
    ],
    "name:hun_x_preferred":[
        "S\u00fclldorf"
    ],
    "name:ita_x_preferred":[
        "S\u00fclldorf"
    ],
    "name:jpn_x_preferred":[
        "\u30cf\u30f3\u30d6\u30eb\u30af\uff1d\u30b8\u30e5\u30eb\u30c9\u30eb\u30d5"
    ],
    "name:lat_x_preferred":[
        "Hamburg-S\u00fclldorf"
    ],
    "name:nds_x_preferred":[
        "S\u00fclld\u00f6rp"
    ],
    "name:nld_x_preferred":[
        "S\u00fclldorf"
    ],
    "name:oci_x_preferred":[
        "S\u00fclldorf"
    ],
    "name:pol_x_preferred":[
        "S\u00fclldorf"
    ],
    "name:rus_x_preferred":[
        "\u0417\u044e\u043b\u044c\u0434\u043e\u0440\u0444"
    ],
    "name:spa_x_preferred":[
        "S\u00fclldorf"
    ],
    "wof:name":"S\u00fclldorf",
    "wof:placetype":"neighbourhood"
},
  "geometry": {"coordinates":[9.7976515065097,53.5816298881995],"type":"Point"}
}