{
  "type": "Feature",
  "properties": {
    "iso:country":"DE",
    "wof:name":"Theegarten",
    "wof:placetype":"neighbourhood"
},
  "geometry": {"coordinates":[7.11113974013669,51.17611692007517],"type":"Point"}
}