{
  "type": "Feature",
  "properties": {
    "gn:admin1_code":"7",
    "gn:admin2_code":"59.0",
    "gn:admin3_code":"5958.0",
    "gn:admin4_code":"5958040.0",
    "gn:asciiname":"Lenne",
    "gn:country_code":"DE",
    "gn:dem":354,
    "gn:feature_class":"P",
    "gn:feature_code":"PPLL",
    "gn:name":"Lenne",
    "gn:population":0,
    "gn:timezone":"Europe/Berlin",
    "iso:country":"DE",
    "name:cat_x_preferred":[
        "Lenne"
    ],
    "name:ceb_x_preferred":[
        "Lenne"
    ],
    "name:chv_x_preferred":[
        "\u041b\u0435\u043d\u043d\u0435"
    ],
    "name:dan_x_preferred":[
        "Lenne"
    ],
    "name:deu_x_preferred":[
        "Lenne"
    ],
    "name:ell_x_preferred":[
        "\u039b\u03ad\u03bd\u03bd\u03b5"
    ],
    "name:epo_x_preferred":[
        "Lenne"
    ],
    "name:eus_x_preferred":[
        "Lenne"
    ],
    "name:nld_x_preferred":[
        "Lenne"
    ],
    "name:nno_x_preferred":[
        "Lenne"
    ],
    "name:nor_x_preferred":[
        "Lenne"
    ],
    "name:pol_x_preferred":[
        "Lenne"
    ],
    "name:ron_x_preferred":[
        "Lenne"
    ],
    "name:rus_x_preferred":[
        "\u041b\u0435\u043d\u043d\u0435"
    ],
    "wof:name":"Lenne",
    "wof:placetype":"neighbourhood"
},
  "geometry": {"coordinates":[8.22473,51.13095],"type":"Point"}
}