{
  "type": "Feature",
  "properties": {
    "gn:admin1_code":"13.0",
    "gn:admin2_code":"00",
    "gn:admin3_code":"14729.0",
    "gn:admin4_code":"14729245.0",
    "gn:asciiname":"Zschorna",
    "gn:cc2":"DE",
    "gn:country_code":"DE",
    "gn:dem":141,
    "gn:feature_class":"P",
    "gn:feature_code":"PPL",
    "gn:name":"Zschorna",
    "gn:population":0,
    "gn:timezone":"Europe/Berlin",
    "iso:country":"DE",
    "name:und_x_variant":[
        "L\u00fcptitz-Zschorna"
    ],
    "wof:name":"Zschorna",
    "wof:placetype":"neighbourhood"
},
  "geometry": {"coordinates":[12.80491,51.39171],"type":"Point"}
}