{
  "type": "Feature",
  "properties": {
    "gn:admin1_code":"12.0",
    "gn:admin2_code":"00",
    "gn:admin3_code":"13071.0",
    "gn:admin4_code":"13071033.0",
    "gn:asciiname":"Weitendorf",
    "gn:country_code":"DE",
    "gn:dem":106,
    "gn:feature_class":"P",
    "gn:feature_code":"PPL",
    "gn:name":"Weitendorf",
    "gn:population":0,
    "gn:timezone":"Europe/Berlin",
    "iso:country":"DE",
    "name:deu_x_preferred":[
        "Weitendorf"
    ],
    "name:epo_x_preferred":[
        "Weitendorf"
    ],
    "name:fas_x_preferred":[
        "\u0648\u0627\u06cc\u062a\u0646\u062f\u0648\u0631\u0641"
    ],
    "name:fra_x_preferred":[
        "Weitendorf"
    ],
    "name:hun_x_preferred":[
        "Weitendorf"
    ],
    "name:ita_x_preferred":[
        "Weitendorf"
    ],
    "name:mkd_x_preferred":[
        "\u0412\u0430\u0458\u0442\u0435\u043d\u0434\u043e\u0440\u0444"
    ],
    "name:msa_x_preferred":[
        "Weitendorf"
    ],
    "name:nld_x_preferred":[
        "Weitendorf"
    ],
    "name:pol_x_preferred":[
        "Weitendorf"
    ],
    "name:por_x_preferred":[
        "Weitendorf"
    ],
    "name:ron_x_preferred":[
        "Weitendorf"
    ],
    "name:rus_x_preferred":[
        "\u0412\u0430\u0439\u0442\u0435\u043d\u0434\u043e\u0440\u0444"
    ],
    "name:spa_x_preferred":[
        "Weitendorf"
    ],
    "name:srp_x_preferred":[
        "\u0412\u0430\u0458\u0442\u0435\u043d\u0434\u043e\u0440\u0444"
    ],
    "name:tgl_x_preferred":[
        "Weitendorf"
    ],
    "name:ukr_x_preferred":[
        "\u0412\u0430\u0439\u0442\u0435\u043d\u0434\u043e\u0440\u0444"
    ],
    "name:uzb_x_preferred":[
        "Weitendorf"
    ],
    "name:vie_x_preferred":[
        "Weitendorf"
    ],
    "name:vol_x_preferred":[
        "Weitendorf"
    ],
    "name:war_x_preferred":[
        "Weitendorf"
    ],
    "name:zho_x_preferred":[
        "\u9b4f\u6ed5\u591a\u592b"
    ],
    "wof:name":"Weitendorf",
    "wof:placetype":"neighbourhood"
},
  "geometry": {"coordinates":[13.39022,53.35825],"type":"Point"}
}