{
  "type": "Feature",
  "properties": {
    "gn:admin1_code":"2",
    "gn:admin2_code":"92.0",
    "gn:admin3_code":"9275.0",
    "gn:admin4_code":"9275153.0",
    "gn:asciiname":"Endsfelden",
    "gn:country_code":"DE",
    "gn:dem":509,
    "gn:feature_class":"P",
    "gn:feature_code":"PPL",
    "gn:name":"Endsfelden",
    "gn:population":0,
    "gn:timezone":"Europe/Berlin",
    "iso:country":"DE",
    "wof:name":"Endsfelden",
    "wof:placetype":"neighbourhood"
},
  "geometry": {"coordinates":[13.68201,48.53769000000001],"type":"Point"}
}