{
  "type": "Feature",
  "properties": {
    "gn:admin1_code":"5.0",
    "gn:admin2_code":"064",
    "gn:admin3_code":"6432.0",
    "gn:admin4_code":"6432010.0",
    "gn:asciiname":"Wiebelsbach",
    "gn:country_code":"DE",
    "gn:dem":219,
    "gn:feature_class":"P",
    "gn:feature_code":"PPL",
    "gn:name":"Wiebelsbach",
    "gn:population":0,
    "gn:timezone":"Europe/Berlin",
    "iso:country":"DE",
    "wof:name":"Wiebelsbach",
    "wof:placetype":"neighbourhood"
},
  "geometry": {"coordinates":[8.9428,49.82327],"type":"Point"}
}