{
  "type": "Feature",
  "properties": {
    "gn:admin1_code":"15",
    "gn:admin2_code":"0.0",
    "gn:admin3_code":"16063.0",
    "gn:admin4_code":"16063011.0",
    "gn:asciiname":"Mieswarz",
    "gn:country_code":"DE",
    "gn:dem":361,
    "gn:feature_class":"P",
    "gn:feature_code":"PPL",
    "gn:name":"Mieswarz",
    "gn:population":0,
    "gn:timezone":"Europe/Berlin",
    "iso:country":"DE",
    "wof:name":"Mieswarz",
    "wof:placetype":"neighbourhood"
},
  "geometry": {"coordinates":[10.02368,50.75648],"type":"Point"}
}