{
  "type": "Feature",
  "properties": {
    "gn:admin1_code":"2.0",
    "gn:admin2_code":"093",
    "gn:admin3_code":"9376.0",
    "gn:admin4_code":"9376162.0",
    "gn:asciiname":"Wolsendorf",
    "gn:country_code":"DE",
    "gn:dem":370,
    "gn:feature_class":"P",
    "gn:feature_code":"PPL",
    "gn:name":"W\u00f6lsendorf",
    "gn:population":0,
    "gn:timezone":"Europe/Berlin",
    "iso:country":"DE",
    "wof:name":"Wolsendorf",
    "wof:placetype":"neighbourhood"
},
  "geometry": {"coordinates":[12.16809,49.40969000000001],"type":"Point"}
}