{
  "type": "Feature",
  "properties": {
    "gn:admin1_code":"6.0",
    "gn:admin2_code":"0.0",
    "gn:admin3_code":"3254.0",
    "gn:admin4_code":"3254044.0",
    "gn:asciiname":"Ammenhausen",
    "gn:country_code":"DE",
    "gn:dem":207,
    "gn:feature_class":"P",
    "gn:feature_code":"PPL",
    "gn:name":"Ammenhausen",
    "gn:population":0,
    "gn:timezone":"Europe/Berlin",
    "iso:country":"DE",
    "wof:name":"Ammenhausen",
    "wof:placetype":"neighbourhood"
},
  "geometry": {"coordinates":[10.06536,51.97304000000001],"type":"Point"}
}