{
  "type": "Feature",
  "properties": {
    "gn:admin1_code":"8",
    "gn:admin2_code":"0.0",
    "gn:admin3_code":"7231.0",
    "gn:admin4_code":"7231133.0",
    "gn:asciiname":"Kasholz",
    "gn:country_code":"DE",
    "gn:dem":411,
    "gn:feature_class":"P",
    "gn:feature_code":"PPL",
    "gn:name":"Kasholz",
    "gn:population":0,
    "gn:timezone":"Europe/Berlin",
    "iso:country":"DE",
    "wof:name":"Kasholz",
    "wof:placetype":"neighbourhood"
},
  "geometry": {"coordinates":[6.97564,49.85739],"type":"Point"}
}