{
  "type": "Feature",
  "properties": {
    "iso:country":"DE",
    "name:deu_x_preferred":[
        "Holthausen"
    ],
    "name:nld_x_preferred":[
        "Holthausen"
    ],
    "name:pol_x_preferred":[
        "Holthausen"
    ],
    "qs:gn_fcode":"PPLX",
    "qs:gn_local":0,
    "qs:gn_namadm1":"07",
    "qs:gn_name":"Holthausen",
    "qs:local_max":1301,
    "qs:local_sum":5213,
    "qs:localhoods":14,
    "qs:name":"Holthausen",
    "qs:name_adm0":"Deutschland",
    "qs:name_adm1":"Nordrhein-Westfalen",
    "qs:name_adm2":"Stadtkreis Bottrop",
    "qs:name_lau":"Bottrop",
    "qs:name_local":"Bottrop",
    "qs:photo_max":391,
    "qs:photo_sum":1301,
    "qs:placetype":"Suburb",
    "qs:quad_count":25,
    "qs:woe_adm0":23424829,
    "qs:woe_adm1":2345487,
    "qs:woe_adm2":12597076,
    "qs:woe_lau":28350220,
    "qs:woe_local":28350220,
    "qs:woe_ver":"7.10.0",
    "wd:wordcount":125,
    "wof:lang":[
        "ger"
    ],
    "wof:name":"Holthausen",
    "wof:placetype":"neighbourhood"
},
  "geometry": {"coordinates":[6.901828,51.582954],"type":"Point"}
}