{
  "type": "Feature",
  "properties": {
    "gn:admin1_code":"2",
    "gn:admin2_code":"92.0",
    "gn:admin3_code":"9276.0",
    "gn:admin4_code":"9276135.0",
    "gn:asciiname":"Ruhmannsdorf",
    "gn:country_code":"DE",
    "gn:dem":488,
    "gn:feature_class":"P",
    "gn:feature_code":"PPL",
    "gn:name":"Ruhmannsdorf",
    "gn:population":0,
    "gn:timezone":"Europe/Berlin",
    "iso:country":"DE",
    "wof:name":"Ruhmannsdorf",
    "wof:placetype":"neighbourhood"
},
  "geometry": {"coordinates":[12.85042,49.1152],"type":"Point"}
}