{
  "type": "Feature",
  "properties": {
    "gn:admin1_code":"2",
    "gn:admin2_code":"91.0",
    "gn:admin3_code":"9187.0",
    "gn:admin4_code":"9187122.0",
    "gn:asciiname":"Oberstaudhausen",
    "gn:country_code":"DE",
    "gn:dem":499,
    "gn:feature_class":"P",
    "gn:feature_code":"PPL",
    "gn:name":"Oberstaudhausen",
    "gn:population":0,
    "gn:timezone":"Europe/Berlin",
    "iso:country":"DE",
    "wof:name":"Oberstaudhausen",
    "wof:placetype":"neighbourhood"
},
  "geometry": {"coordinates":[11.95132,47.8549],"type":"Point"}
}