{
  "type": "Feature",
  "properties": {
    "gn:admin1_code":"2",
    "gn:admin2_code":"93.0",
    "gn:admin3_code":"9371.0",
    "gn:admin4_code":"9371120.0",
    "gn:asciiname":"Hirschwald",
    "gn:country_code":"DE",
    "gn:dem":492,
    "gn:feature_class":"P",
    "gn:feature_code":"PPL",
    "gn:name":"Hirschwald",
    "gn:population":0,
    "gn:timezone":"Europe/Berlin",
    "iso:country":"DE",
    "wof:name":"Hirschwald",
    "wof:placetype":"neighbourhood"
},
  "geometry": {"coordinates":[11.87072,49.3533],"type":"Point"}
}