{
  "type": "Feature",
  "properties": {
    "gn:admin1_code":"2",
    "gn:admin2_code":"92.0",
    "gn:admin3_code":"9278.0",
    "gn:admin4_code":"9278129.0",
    "gn:asciiname":"Vornwald",
    "gn:country_code":"DE",
    "gn:dem":628,
    "gn:feature_class":"P",
    "gn:feature_code":"PPL",
    "gn:name":"Vornwald",
    "gn:population":0,
    "gn:timezone":"Europe/Berlin",
    "iso:country":"DE",
    "wof:name":"Vornwald",
    "wof:placetype":"neighbourhood"
},
  "geometry": {"coordinates":[12.77,49.00642],"type":"Point"}
}