{
  "type": "Feature",
  "properties": {
    "gn:admin1_code":"2",
    "gn:admin2_code":"91.0",
    "gn:admin3_code":"9171.0",
    "gn:admin4_code":"9171112.0",
    "gn:asciiname":"Laimgruben",
    "gn:country_code":"DE",
    "gn:dem":433,
    "gn:feature_class":"P",
    "gn:feature_code":"PPL",
    "gn:name":"Laimgruben",
    "gn:population":0,
    "gn:timezone":"Europe/Berlin",
    "iso:country":"DE",
    "wof:name":"Laimgruben",
    "wof:placetype":"neighbourhood"
},
  "geometry": {"coordinates":[12.80085,48.15112],"type":"Point"}
}