{
  "type": "Feature",
  "properties": {
    "gn:admin1_code":"8",
    "gn:admin2_code":"0.0",
    "gn:admin3_code":"7312.0",
    "gn:admin4_code":"7312000.0",
    "gn:asciiname":"Erlenbach",
    "gn:country_code":"DE",
    "gn:dem":293,
    "gn:feature_class":"P",
    "gn:feature_code":"PPL",
    "gn:name":"Erlenbach",
    "gn:population":0,
    "gn:timezone":"Europe/Berlin",
    "iso:country":"DE",
    "name:als_x_preferred":[
        "Erlenbach"
    ],
    "name:ceb_x_preferred":[
        "Erlenbach"
    ],
    "name:deu_x_preferred":[
        "Erlenbach"
    ],
    "name:epo_x_preferred":[
        "Erlenbach"
    ],
    "name:eus_x_preferred":[
        "Erlenbach"
    ],
    "name:fra_x_preferred":[
        "Erlenbach"
    ],
    "name:hun_x_preferred":[
        "Erlenbach"
    ],
    "name:ita_x_preferred":[
        "Erlenbach"
    ],
    "name:jpn_x_preferred":[
        "\u30a8\u30a2\u30ec\u30f3\u30d0\u30c3\u30cf"
    ],
    "name:lmo_x_preferred":[
        "Erlenbach"
    ],
    "name:nld_x_preferred":[
        "Erlenbach"
    ],
    "name:pol_x_preferred":[
        "Erlenbach"
    ],
    "name:rus_x_preferred":[
        "\u042d\u0440\u043b\u0435\u043d\u0431\u0430\u0445"
    ],
    "name:swe_x_preferred":[
        "Erlenbach"
    ],
    "name:vol_x_preferred":[
        "Erlenbach"
    ],
    "wof:name":"Erlenbach",
    "wof:placetype":"neighbourhood"
},
  "geometry": {"coordinates":[7.77487,49.47892],"type":"Point"}
}