{
  "type": "Feature",
  "properties": {
    "iso:country":"DE",
    "wof:name":"Gaulnhofen",
    "wof:placetype":"neighbourhood"
},
  "geometry": {"coordinates":[11.07164668076084,49.36779316591927],"type":"Point"}
}