{
  "type": "Feature",
  "properties": {
    "gn:admin1_code":"12.0",
    "gn:admin2_code":"00",
    "gn:admin3_code":"13076.0",
    "gn:admin4_code":"13076011.0",
    "gn:asciiname":"Wipersdorf",
    "gn:country_code":"DE",
    "gn:dem":28,
    "gn:feature_class":"P",
    "gn:feature_code":"PPL",
    "gn:name":"Wipersdorf",
    "gn:population":0,
    "gn:timezone":"Europe/Berlin",
    "iso:country":"DE",
    "wof:name":"Wipersdorf",
    "wof:placetype":"neighbourhood"
},
  "geometry": {"coordinates":[11.72769,53.76211],"type":"Point"}
}