{
  "type": "Feature",
  "properties": {
    "gn:admin1_code":"2.0",
    "gn:admin2_code":"097",
    "gn:admin3_code":"9780.0",
    "gn:admin4_code":"9780117.0",
    "gn:asciiname":"Wirlings",
    "gn:country_code":"DE",
    "gn:dem":756,
    "gn:feature_class":"P",
    "gn:feature_code":"PPL",
    "gn:name":"Wirlings",
    "gn:population":0,
    "gn:timezone":"Europe/Berlin",
    "iso:country":"DE",
    "wof:name":"Wirlings",
    "wof:placetype":"neighbourhood"
},
  "geometry": {"coordinates":[10.27223,47.69089],"type":"Point"}
}