{
  "type": "Feature",
  "properties": {
    "gn:admin1_code":"8",
    "gn:admin2_code":"0.0",
    "gn:admin3_code":"7340.0",
    "gn:admin4_code":"7340225.0",
    "gn:asciiname":"Oberhausen",
    "gn:country_code":"DE",
    "gn:dem":271,
    "gn:feature_class":"P",
    "gn:feature_code":"PPL",
    "gn:name":"Oberhausen",
    "gn:population":0,
    "gn:timezone":"Europe/Berlin",
    "iso:country":"DE",
    "wof:name":"Oberhausen",
    "wof:placetype":"neighbourhood"
},
  "geometry": {"coordinates":[7.51782,49.31646],"type":"Point"}
}