{
  "type": "Feature",
  "properties": {
    "gn:admin1_code":"2.0",
    "gn:admin2_code":"95.0",
    "gn:admin3_code":"9575.0",
    "gn:admin4_code":"9575121.0",
    "gn:asciiname":"Bottenbach",
    "gn:country_code":"DE",
    "gn:dem":363,
    "gn:feature_class":"P",
    "gn:feature_code":"PPL",
    "gn:name":"Bottenbach",
    "gn:population":0,
    "gn:timezone":"Europe/Berlin",
    "iso:country":"DE",
    "wof:name":"Bottenbach",
    "wof:placetype":"neighbourhood"
},
  "geometry": {"coordinates":[10.67322,49.5549],"type":"Point"}
}