{
  "type": "Feature",
  "properties": {
    "gn:admin1_code":"2.0",
    "gn:admin2_code":"95.0",
    "gn:admin3_code":"9575.0",
    "gn:admin4_code":"9575121.0",
    "gn:asciiname":"Bottenbach",
    "gn:country_code":"DE",
    "gn:dem":363,
    "gn:feature_class":"P",
    "gn:feature_code":"PPL",
    "gn:name":"Bottenbach",
    "gn:population":0,
    "gn:timezone":"Europe/Berlin",
    "iso:country":"DE",
    "name:ceb_x_preferred":[
        "Bottenbach"
    ],
    "name:deu_x_preferred":[
        "Bottenbach"
    ],
    "name:epo_x_preferred":[
        "Bottenbach"
    ],
    "name:eus_x_preferred":[
        "Bottenbach"
    ],
    "name:fas_x_preferred":[
        "\u0628\u0648\u062a\u0646\u0628\u0627\u062e"
    ],
    "name:fra_x_preferred":[
        "Bottenbach"
    ],
    "name:hun_x_preferred":[
        "Bottenbach"
    ],
    "name:ita_x_preferred":[
        "Bottenbach"
    ],
    "name:kaz_x_preferred":[
        "\u0411\u043e\u0442\u0442\u0435\u043d\u0431\u0430\u0445"
    ],
    "name:kir_x_preferred":[
        "\u0411\u043e\u0442\u0442\u0435\u043d\u0431\u0430\u0445"
    ],
    "name:msa_x_preferred":[
        "Bottenbach"
    ],
    "name:nld_x_preferred":[
        "Bottenbach"
    ],
    "name:pol_x_preferred":[
        "Bottenbach"
    ],
    "name:por_x_preferred":[
        "Bottenbach"
    ],
    "name:ron_x_preferred":[
        "Bottenbach"
    ],
    "name:rus_x_preferred":[
        "\u0411\u043e\u0442\u0442\u0435\u043d\u0431\u0430\u0445"
    ],
    "name:srp_x_preferred":[
        "\u0411\u043e\u0442\u0435\u043d\u0431\u0430\u0445"
    ],
    "name:ukr_x_preferred":[
        "\u0411\u043e\u0442\u0442\u0435\u043d\u0431\u0430\u0445"
    ],
    "name:uzb_x_preferred":[
        "Bottenbach"
    ],
    "name:vie_x_preferred":[
        "Bottenbach"
    ],
    "name:vol_x_preferred":[
        "Bottenbach"
    ],
    "name:war_x_preferred":[
        "Bottenbach"
    ],
    "name:zho_x_preferred":[
        "\u535a\u6ed5\u5df4\u8d6b"
    ],
    "wof:name":"Bottenbach",
    "wof:placetype":"neighbourhood"
},
  "geometry": {"coordinates":[10.67322,49.5549],"type":"Point"}
}