{
  "type": "Feature",
  "properties": {
    "gn:admin1_code":"7",
    "gn:admin2_code":"57.0",
    "gn:admin3_code":"5766.0",
    "gn:admin4_code":"5766032.0",
    "gn:asciiname":"Wehren",
    "gn:country_code":"DE",
    "gn:dem":236,
    "gn:feature_class":"P",
    "gn:feature_code":"PPL",
    "gn:name":"Wehren",
    "gn:population":0,
    "gn:timezone":"Europe/Berlin",
    "iso:country":"DE",
    "wof:name":"Wehren",
    "wof:placetype":"neighbourhood"
},
  "geometry": {"coordinates":[8.99883,51.90833],"type":"Point"}
}