{
  "type": "Feature",
  "properties": {
    "gn:admin1_code":"12",
    "gn:admin2_code":"0.0",
    "gn:admin3_code":"13074.0",
    "gn:admin4_code":"13074065.0",
    "gn:asciiname":"Toerberhals",
    "gn:country_code":"DE",
    "gn:dem":16,
    "gn:feature_class":"P",
    "gn:feature_code":"PPL",
    "gn:name":"T\u00f6rberhals",
    "gn:population":0,
    "gn:timezone":"Europe/Berlin",
    "iso:country":"DE",
    "wof:name":"Toerberhals",
    "wof:placetype":"neighbourhood"
},
  "geometry": {"coordinates":[11.03745,53.82194000000001],"type":"Point"}
}