{
  "type": "Feature",
  "properties": {
    "gn:admin1_code":"6",
    "gn:admin2_code":"0.0",
    "gn:admin3_code":"3351.0",
    "gn:admin4_code":"3351022.0",
    "gn:asciiname":"Offensen",
    "gn:country_code":"DE",
    "gn:dem":43,
    "gn:feature_class":"P",
    "gn:feature_code":"PPL",
    "gn:name":"Offensen",
    "gn:population":0,
    "gn:timezone":"Europe/Berlin",
    "iso:country":"DE",
    "name:gml_x_preferred":[
        "Uffenhusen [a. 1255]"
    ],
    "wof:name":"Offensen",
    "wof:placetype":"neighbourhood"
},
  "geometry": {"coordinates":[10.2281,52.57844],"type":"Point"}
}