{
  "type": "Feature",
  "properties": {
    "gn:admin1_code":"2.0",
    "gn:admin2_code":"097",
    "gn:admin3_code":"9772.0",
    "gn:admin4_code":"9772115.0",
    "gn:asciiname":"Zusamzell",
    "gn:country_code":"DE",
    "gn:dem":435,
    "gn:feature_class":"P",
    "gn:feature_code":"PPL",
    "gn:name":"Zusamzell",
    "gn:population":0,
    "gn:timezone":"Europe/Berlin",
    "iso:country":"DE",
    "wof:name":"Zusamzell",
    "wof:placetype":"neighbourhood"
},
  "geometry": {"coordinates":[10.60528,48.4825],"type":"Point"}
}