{
  "type": "Feature",
  "properties": {
    "gn:admin1_code":"11.0",
    "gn:admin2_code":"00",
    "gn:admin3_code":"12072.0",
    "gn:admin4_code":"12072426.0",
    "gn:asciiname":"Wiesenhagen",
    "gn:country_code":"DE",
    "gn:dem":40,
    "gn:feature_class":"P",
    "gn:feature_code":"PPL",
    "gn:name":"Wiesenhagen",
    "gn:population":0,
    "gn:timezone":"Europe/Berlin",
    "iso:country":"DE",
    "wof:name":"Wiesenhagen",
    "wof:placetype":"neighbourhood"
},
  "geometry": {"coordinates":[13.23775,52.17518],"type":"Point"}
}