{
  "type": "Feature",
  "properties": {
    "gn:admin1_code":"15",
    "gn:admin2_code":"0.0",
    "gn:admin3_code":"16073.0",
    "gn:admin4_code":"16073112.0",
    "gn:asciiname":"Garsitz",
    "gn:country_code":"DE",
    "gn:dem":414,
    "gn:feature_class":"P",
    "gn:feature_code":"PPL",
    "gn:name":"Garsitz",
    "gn:population":0,
    "gn:timezone":"Europe/Berlin",
    "iso:country":"DE",
    "wof:name":"Garsitz",
    "wof:placetype":"neighbourhood"
},
  "geometry": {"coordinates":[11.07781,50.65151],"type":"Point"}
}