{
  "type": "Feature",
  "properties": {
    "gn:admin1_code":"1",
    "gn:admin2_code":"84.0",
    "gn:admin3_code":"8417.0",
    "gn:admin4_code":"8417008.0",
    "gn:asciiname":"Julienhutte",
    "gn:country_code":"DE",
    "gn:dem":566,
    "gn:feature_class":"P",
    "gn:feature_code":"PPL",
    "gn:name":"Julienh\u00fctte",
    "gn:population":0,
    "gn:timezone":"Europe/Berlin",
    "iso:country":"DE",
    "wof:name":"Julienhutte",
    "wof:placetype":"neighbourhood"
},
  "geometry": {"coordinates":[8.91667,48.31667],"type":"Point"}
}