{
  "type": "Feature",
  "properties": {
    "gn:admin1_code":"2",
    "gn:admin2_code":"92.0",
    "gn:admin3_code":"9274.0",
    "gn:admin4_code":"9274145.0",
    "gn:asciiname":"Hermannsreit",
    "gn:country_code":"DE",
    "gn:dem":477,
    "gn:feature_class":"P",
    "gn:feature_code":"PPL",
    "gn:name":"Hermannsreit",
    "gn:population":0,
    "gn:timezone":"Europe/Berlin",
    "iso:country":"DE",
    "wof:name":"Hermannsreit",
    "wof:placetype":"neighbourhood"
},
  "geometry": {"coordinates":[12.38279,48.5108],"type":"Point"}
}