{
  "type": "Feature",
  "properties": {
    "gn:admin1_code":"8.0",
    "gn:admin2_code":"0.0",
    "gn:admin3_code":"7138.0",
    "gn:admin4_code":"7138059.0",
    "gn:asciiname":"Hedwigsthal",
    "gn:country_code":"DE",
    "gn:dem":222,
    "gn:feature_class":"P",
    "gn:feature_code":"PPL",
    "gn:name":"Hedwigsthal",
    "gn:population":0,
    "gn:timezone":"Europe/Berlin",
    "iso:country":"DE",
    "wof:name":"Hedwigsthal",
    "wof:placetype":"neighbourhood"
},
  "geometry": {"coordinates":[7.62392,50.58406],"type":"Point"}
}