{
  "type": "Feature",
  "properties": {
    "gn:admin1_code":"1",
    "gn:admin2_code":"83.0",
    "gn:admin3_code":"8317.0",
    "gn:admin4_code":"8317021.0",
    "gn:asciiname":"Gebirg",
    "gn:country_code":"DE",
    "gn:dem":318,
    "gn:feature_class":"P",
    "gn:feature_code":"PPLL",
    "gn:name":"Gebirg",
    "gn:population":0,
    "gn:timezone":"Europe/Berlin",
    "iso:country":"DE",
    "wof:name":"Gebirg",
    "wof:placetype":"neighbourhood"
},
  "geometry": {"coordinates":[8.05569,48.46712],"type":"Point"}
}