{
  "type": "Feature",
  "properties": {
    "gn:admin1_code":"1",
    "gn:admin2_code":"81.0",
    "gn:admin3_code":"8125.0",
    "gn:admin4_code":"8125068.0",
    "gn:asciiname":"Siglingen",
    "gn:country_code":"DE",
    "gn:dem":176,
    "gn:feature_class":"P",
    "gn:feature_code":"PPL",
    "gn:name":"Siglingen",
    "gn:population":0,
    "gn:timezone":"Europe/Berlin",
    "iso:country":"DE",
    "wof:name":"Siglingen",
    "wof:placetype":"neighbourhood"
},
  "geometry": {"coordinates":[9.30694,49.29907],"type":"Point"}
}