{
  "type": "Feature",
  "properties": {
    "gn:admin1_code":"1.0",
    "gn:admin2_code":"84.0",
    "gn:admin3_code":"8436.0",
    "gn:admin4_code":"8436094.0",
    "gn:asciiname":"Berfallen",
    "gn:country_code":"DE",
    "gn:dem":672,
    "gn:feature_class":"P",
    "gn:feature_code":"PPL",
    "gn:name":"Berfallen",
    "gn:population":0,
    "gn:timezone":"Europe/Berlin",
    "iso:country":"DE",
    "wof:name":"Berfallen",
    "wof:placetype":"neighbourhood"
},
  "geometry": {"coordinates":[9.91667,47.73333],"type":"Point"}
}