{
  "type": "Feature",
  "properties": {
    "gn:admin1_code":"1",
    "gn:admin2_code":"81.0",
    "gn:admin3_code":"8119.0",
    "gn:admin4_code":"8119024.0",
    "gn:asciiname":"Morbach",
    "gn:country_code":"DE",
    "gn:dem":486,
    "gn:feature_class":"P",
    "gn:feature_code":"PPL",
    "gn:name":"Morbach",
    "gn:population":0,
    "gn:timezone":"Europe/Berlin",
    "iso:country":"DE",
    "name:bul_x_preferred":[
        "\u041c\u043e\u0440\u0431\u0430\u0445"
    ],
    "name:ceb_x_preferred":[
        "Morbach"
    ],
    "name:deu_x_preferred":[
        "Morbach"
    ],
    "name:epo_x_preferred":[
        "Morbach"
    ],
    "name:eus_x_preferred":[
        "Morbach"
    ],
    "name:fas_x_preferred":[
        "\u0645\u0648\u0631\u0628\u0627\u062e"
    ],
    "name:fra_x_preferred":[
        "Morbach"
    ],
    "name:hun_x_preferred":[
        "Morbach"
    ],
    "name:ita_x_preferred":[
        "Morbach"
    ],
    "name:jpn_x_preferred":[
        "\u30e2\u30fc\u30eb\u30d0\u30c3\u30cf"
    ],
    "name:msa_x_preferred":[
        "Morbach"
    ],
    "name:nld_x_preferred":[
        "Morbach"
    ],
    "name:pol_x_preferred":[
        "Morbach"
    ],
    "name:por_x_preferred":[
        "Morbach"
    ],
    "name:ron_x_preferred":[
        "Morbach"
    ],
    "name:rus_x_preferred":[
        "\u041c\u043e\u0440\u0431\u0430\u0445"
    ],
    "name:srp_x_preferred":[
        "\u041c\u043e\u0440\u0431\u0430\u0445"
    ],
    "name:swe_x_preferred":[
        "Morbach"
    ],
    "name:ukr_x_preferred":[
        "\u041c\u043e\u0440\u0431\u0430\u0445"
    ],
    "name:uzb_x_preferred":[
        "Morbach"
    ],
    "name:vie_x_preferred":[
        "Morbach"
    ],
    "name:vol_x_preferred":[
        "Morbach"
    ],
    "name:war_x_preferred":[
        "Morbach"
    ],
    "name:zho_x_preferred":[
        "\u83ab\u5c14\u5df4\u8d6b"
    ],
    "wof:name":"Morbach",
    "wof:placetype":"neighbourhood"
},
  "geometry": {"coordinates":[9.59407,49.03214000000001],"type":"Point"}
}