{
  "type": "Feature",
  "properties": {
    "iso:country":"DE",
    "wof:name":"Solingen Mitte",
    "wof:placetype":"neighbourhood"
},
  "geometry": {"coordinates":[7.0858339957481,51.17115717718139],"type":"Point"}
}