{
  "type": "Feature",
  "properties": {
    "gn:admin1_code":"14",
    "gn:admin2_code":"0.0",
    "gn:admin3_code":"15081.0",
    "gn:admin4_code":"15081030.0",
    "gn:asciiname":"Kraatz",
    "gn:country_code":"DE",
    "gn:dem":28,
    "gn:feature_class":"P",
    "gn:feature_code":"PPL",
    "gn:name":"Kraatz",
    "gn:population":0,
    "gn:timezone":"Europe/Berlin",
    "iso:country":"DE",
    "wof:name":"Kraatz",
    "wof:placetype":"neighbourhood"
},
  "geometry": {"coordinates":[11.42438,52.85421],"type":"Point"}
}