{
  "type": "Feature",
  "properties": {
    "gn:admin1_code":"7.0",
    "gn:admin2_code":"59.0",
    "gn:admin3_code":"5974.0",
    "gn:admin4_code":"5974004.0",
    "gn:asciiname":"Altenmellrich",
    "gn:country_code":"DE",
    "gn:dem":216,
    "gn:feature_class":"P",
    "gn:feature_code":"PPL",
    "gn:name":"Altenmellrich",
    "gn:population":0,
    "gn:timezone":"Europe/Berlin",
    "iso:country":"DE",
    "wof:name":"Altenmellrich",
    "wof:placetype":"neighbourhood"
},
  "geometry": {"coordinates":[8.26477,51.53313],"type":"Point"}
}