{
  "type": "Feature",
  "properties": {
    "gn:admin1_code":"7",
    "gn:admin2_code":"53.0",
    "gn:admin3_code":"5370.0",
    "gn:admin4_code":"5370004.0",
    "gn:asciiname":"Holzweiler",
    "gn:country_code":"DE",
    "gn:dem":96,
    "gn:feature_class":"P",
    "gn:feature_code":"PPL",
    "gn:name":"Holzweiler",
    "gn:population":0,
    "gn:timezone":"Europe/Berlin",
    "iso:country":"DE",
    "name:nor_x_preferred":[
        "Holzweiler"
    ],
    "wof:name":"Holzweiler",
    "wof:placetype":"neighbourhood"
},
  "geometry": {"coordinates":[6.40569,51.04809],"type":"Point"}
}