{
  "type": "Feature",
  "properties": {
    "gn:admin1_code":"6",
    "gn:admin2_code":"0.0",
    "gn:admin3_code":"3355.0",
    "gn:admin4_code":"3355012.0",
    "gn:asciiname":"Koestorf",
    "gn:country_code":"DE",
    "gn:dem":64,
    "gn:feature_class":"P",
    "gn:feature_code":"PPL",
    "gn:name":"K\u00f6storf",
    "gn:population":0,
    "gn:timezone":"Europe/Berlin",
    "iso:country":"DE",
    "wof:name":"Koestorf",
    "wof:placetype":"neighbourhood"
},
  "geometry": {"coordinates":[10.7535,53.22924],"type":"Point"}
}