{
  "type": "Feature",
  "properties": {
    "gn:admin1_code":"2",
    "gn:admin2_code":"91.0",
    "gn:admin3_code":"9190.0",
    "gn:admin4_code":"9190157.0",
    "gn:asciiname":"Lichtenau",
    "gn:country_code":"DE",
    "gn:dem":605,
    "gn:feature_class":"P",
    "gn:feature_code":"PPL",
    "gn:name":"Lichtenau",
    "gn:population":0,
    "gn:timezone":"Europe/Berlin",
    "iso:country":"DE",
    "name:bak_x_preferred":[
        "\u041b\u0438\u0445\u0442\u0435\u043d\u0430\u0443"
    ],
    "name:ceb_x_preferred":[
        "Lichtenau"
    ],
    "name:deu_x_preferred":[
        "Lichtenau"
    ],
    "name:epo_x_preferred":[
        "Lichtenau"
    ],
    "name:fra_x_preferred":[
        "Lichtenau"
    ],
    "name:hun_x_preferred":[
        "Lichtenau"
    ],
    "name:ita_x_preferred":[
        "Lichtenau"
    ],
    "name:jpn_x_preferred":[
        "\u30ea\u30d2\u30c6\u30ca\u30a6"
    ],
    "name:lmo_x_preferred":[
        "Lichtenau"
    ],
    "name:mkd_x_preferred":[
        "\u041b\u0438\u0445\u0442\u0435\u043d\u0430\u0443"
    ],
    "name:nld_x_preferred":[
        "Lichtenau"
    ],
    "name:pol_x_preferred":[
        "Lichtenau"
    ],
    "name:por_x_preferred":[
        "Lichtenau"
    ],
    "name:rus_x_preferred":[
        "\u041b\u0438\u0445\u0442\u0435\u043d\u0430\u0443"
    ],
    "name:spa_x_preferred":[
        "Lichtenau"
    ],
    "name:swe_x_preferred":[
        "Lichtenau"
    ],
    "name:vol_x_preferred":[
        "Lichtenau"
    ],
    "wof:name":"Lichtenau",
    "wof:placetype":"neighbourhood"
},
  "geometry": {"coordinates":[11.0791,47.87154],"type":"Point"}
}