{
  "type": "Feature",
  "properties": {
    "gn:admin1_code":"1.0",
    "gn:admin2_code":"81.0",
    "gn:admin3_code":"8111.0",
    "gn:admin4_code":"8111000.0",
    "gn:asciiname":"Muehlhausen",
    "gn:country_code":"DE",
    "gn:dem":215,
    "gn:feature_class":"P",
    "gn:feature_code":"PPL",
    "gn:name":"M\u00fchlhausen",
    "gn:population":0,
    "gn:timezone":"Europe/Berlin",
    "iso:country":"DE",
    "name:und_x_variant":[
        "M\u00fchlhausen"
    ],
    "wof:name":"Muehlhausen",
    "wof:placetype":"neighbourhood"
},
  "geometry": {"coordinates":[9.22251,48.84006],"type":"Point"}
}