{
  "type": "Feature",
  "properties": {
    "iso:country":"DE",
    "name:deu_x_colloquial":[
        "Diessem"
    ],
    "name:deu_x_preferred":[
        "Die\u00dfem"
    ],
    "name:eng_x_preferred":[
        "Die\u00dfem"
    ],
    "name:unk_x_variant":[
        "Die\u00dfem"
    ],
    "qs:gn_adm0_cc":"DE",
    "qs:gn_fcode":"PPLX",
    "qs:gn_local":2884509,
    "qs:gn_nam_loc":"krefeld",
    "qs:gn_namadm1":"07",
    "qs:gn_name":"Die\u00dfem",
    "qs:local_max":3369,
    "qs:local_sum":5777,
    "qs:localhoods":16,
    "qs:name":"Die\u00dfem",
    "qs:name_adm0":"Deutschland",
    "qs:name_adm1":"Nordrhein-Westfalen",
    "qs:name_adm2":"Stadtkreis Krefeld",
    "qs:name_lau":"Die\u00dfem/Lehmheide",
    "qs:name_local":"Krefeld",
    "qs:photo_max":67,
    "qs:photo_sum":342,
    "qs:placetype":"Suburb",
    "qs:quad_count":30,
    "qs:woe_adm0":23424829,
    "qs:woe_adm1":2345487,
    "qs:woe_adm2":12597091,
    "qs:woe_lau":26822852,
    "qs:woe_local":668736,
    "qs:woe_ver":"7.10.0",
    "wof:lang":[
        "ger"
    ],
    "wof:name":"Diessem",
    "wof:placetype":"neighbourhood"
},
  "geometry": {"coordinates":[6.584844,51.324307],"type":"Point"}
}