{
  "type": "Feature",
  "properties": {
    "gn:admin1_code":"11.0",
    "gn:admin2_code":"0.0",
    "gn:admin3_code":"12064.0",
    "gn:admin4_code":"12064371.0",
    "gn:asciiname":"Bienenwerder",
    "gn:country_code":"DE",
    "gn:dem":2,
    "gn:feature_class":"P",
    "gn:feature_code":"PPL",
    "gn:name":"Bienenwerder",
    "gn:population":0,
    "gn:timezone":"Europe/Berlin",
    "iso:country":"DE",
    "wof:name":"Bienenwerder",
    "wof:placetype":"neighbourhood"
},
  "geometry": {"coordinates":[14.20695,52.801],"type":"Point"}
}