{
  "type": "Feature",
  "properties": {
    "gn:country":"DE",
    "gn:fcode":"PPL",
    "gn:population":0,
    "iso:country":"DE",
    "name:ara_x_preferred":[
        "\u0623\u0648\u0643\u0627\u0631"
    ],
    "name:bul_x_preferred":[
        "\u041e\u043a\u0435\u0440"
    ],
    "name:ceb_x_preferred":[
        "Oker"
    ],
    "name:chv_x_preferred":[
        "\u041e\u043a\u0435\u0440"
    ],
    "name:dan_x_preferred":[
        "Oker"
    ],
    "name:deu_x_preferred":[
        "Oker"
    ],
    "name:est_x_preferred":[
        "Oker"
    ],
    "name:eus_x_preferred":[
        "Oker"
    ],
    "name:fra_x_preferred":[
        "Oker"
    ],
    "name:fry_x_preferred":[
        "Oker"
    ],
    "name:jpn_x_preferred":[
        "\u30aa\u30fc\u30ab\u30fc\u5ddd"
    ],
    "name:mkd_x_preferred":[
        "\u041e\u043a\u0435\u0440"
    ],
    "name:nld_x_preferred":[
        "Oker"
    ],
    "name:nno_x_preferred":[
        "Elva Oker"
    ],
    "name:nor_x_preferred":[
        "Oker"
    ],
    "name:pol_x_preferred":[
        "Oker"
    ],
    "name:rus_x_preferred":[
        "\u041e\u043a\u0435\u0440"
    ],
    "name:swe_x_preferred":[
        "Ocker"
    ],
    "name:vep_x_preferred":[
        "Oker"
    ],
    "name:zho_x_preferred":[
        "\u5967\u514b\u6cb3"
    ],
    "qs_pg:aaroncc":"DE",
    "qs_pg:gn_country":"DE",
    "qs_pg:gn_fcode":"PPL",
    "qs_pg:gn_pop":0,
    "qs_pg:name":"Oker",
    "qs_pg:name_adm0":"Deutschland",
    "qs_pg:name_adm1":"Niedersachsen",
    "qs_pg:photos":16,
    "qs_pg:photos_1k":3,
    "qs_pg:photos_9k":1,
    "qs_pg:photos_9r":1,
    "qs_pg:photos_all":16,
    "qs_pg:photos_sr":1,
    "qs_pg:pop_sr":0,
    "qs_pg:qs_pg_placetype":"locality",
    "qs_pg:qs_pg_placetype_gp":"Town",
    "qs_pg:woe_adm0":23424829,
    "woe:adm0_id":23424829,
    "woe:name_adm0":"Deutschland",
    "woe:name_adm1":"Niedersachsen",
    "woe:placetype":"Town",
    "wof:name":"Oker",
    "wof:placetype":"neighbourhood"
},
  "geometry": {"coordinates":[10.48191,51.90508],"type":"Point"}
}