{
  "type": "Feature",
  "properties": {
    "gn:admin1_code":"2.0",
    "gn:admin2_code":"91.0",
    "gn:admin3_code":"9178.0",
    "gn:admin4_code":"9178137.0",
    "gn:asciiname":"Ampertshausen",
    "gn:country_code":"DE",
    "gn:dem":506,
    "gn:feature_class":"P",
    "gn:feature_code":"PPL",
    "gn:name":"Ampertshausen",
    "gn:population":0,
    "gn:timezone":"Europe/Berlin",
    "iso:country":"DE",
    "wof:name":"Ampertshausen",
    "wof:placetype":"neighbourhood"
},
  "geometry": {"coordinates":[11.67561,48.42333],"type":"Point"}
}