{
  "type": "Feature",
  "properties": {
    "gn:admin1_code":"6",
    "gn:admin2_code":"0.0",
    "gn:admin3_code":"3254.0",
    "gn:admin4_code":"3254043.0",
    "gn:asciiname":"Haus Escherde",
    "gn:country_code":"DE",
    "gn:dem":139,
    "gn:feature_class":"P",
    "gn:feature_code":"PPL",
    "gn:name":"Haus Escherde",
    "gn:population":0,
    "gn:timezone":"Europe/Berlin",
    "iso:country":"DE",
    "wof:name":"Haus Escherde",
    "wof:placetype":"neighbourhood"
},
  "geometry": {"coordinates":[9.81886,52.11589],"type":"Point"}
}