{
  "type": "Feature",
  "properties": {
    "gn:admin1_code":"10",
    "gn:admin2_code":"0.0",
    "gn:admin3_code":"1055.0",
    "gn:admin4_code":"1055028.0",
    "gn:asciiname":"Malente-Gremsmuehlen",
    "gn:country_code":"DE",
    "gn:dem":35,
    "gn:feature_class":"P",
    "gn:feature_code":"PPL",
    "gn:name":"Malente-Gremsm\u00fchlen",
    "gn:population":0,
    "gn:timezone":"Europe/Berlin",
    "iso:country":"DE",
    "wof:name":"Malente-Gremsmuehlen",
    "wof:placetype":"neighbourhood"
},
  "geometry": {"coordinates":[10.56667,54.18333000000001],"type":"Point"}
}