{
  "type": "Feature",
  "properties": {
    "gn:admin1_code":"13",
    "gn:admin2_code":"0.0",
    "gn:admin3_code":"14625.0",
    "gn:admin4_code":"14625390.0",
    "gn:asciiname":"Lehn",
    "gn:country_code":"DE",
    "gn:dem":248,
    "gn:feature_class":"P",
    "gn:feature_code":"PPL",
    "gn:name":"Lehn",
    "gn:population":0,
    "gn:timezone":"Europe/Berlin",
    "iso:country":"DE",
    "name:hsb_x_preferred":[
        "Lejno"
    ],
    "wof:name":"Lehn",
    "wof:placetype":"neighbourhood"
},
  "geometry": {"coordinates":[14.42092,51.12282],"type":"Point"}
}