{
  "type": "Feature",
  "properties": {
    "gn:admin1_code":"2",
    "gn:admin2_code":"95.0",
    "gn:admin3_code":"9577.0",
    "gn:admin4_code":"9577161.0",
    "gn:asciiname":"Erlingsdorf",
    "gn:country_code":"DE",
    "gn:dem":479,
    "gn:feature_class":"P",
    "gn:feature_code":"PPL",
    "gn:name":"Erlingsdorf",
    "gn:population":0,
    "gn:timezone":"Europe/Berlin",
    "iso:country":"DE",
    "wof:name":"Erlingsdorf",
    "wof:placetype":"neighbourhood"
},
  "geometry": {"coordinates":[10.95792,49.14483],"type":"Point"}
}