{
  "type": "Feature",
  "properties": {
    "gn:admin1_code":"5",
    "gn:admin2_code":"66.0",
    "gn:admin3_code":"6632.0",
    "gn:admin4_code":"6632003.0",
    "gn:asciiname":"Gilfershausen",
    "gn:country_code":"DE",
    "gn:dem":235,
    "gn:feature_class":"P",
    "gn:feature_code":"PPL",
    "gn:name":"Gilfershausen",
    "gn:population":0,
    "gn:timezone":"Europe/Berlin",
    "iso:country":"DE",
    "name:und_x_variant":[
        "Gilsershausen",
        "Gilfershausen"
    ],
    "wof:name":"Gilfershausen",
    "wof:placetype":"neighbourhood"
},
  "geometry": {"coordinates":[9.83277,50.9887],"type":"Point"}
}