{
  "type": "Feature",
  "properties": {
    "gn:admin1_code":"2",
    "gn:admin2_code":"97.0",
    "gn:admin3_code":"9771.0",
    "gn:admin4_code":"9771165.0",
    "gn:asciiname":"Unterschroetenloh",
    "gn:country_code":"DE",
    "gn:dem":521,
    "gn:feature_class":"P",
    "gn:feature_code":"PPL",
    "gn:name":"Unterschr\u00f6tenloh",
    "gn:population":0,
    "gn:timezone":"Europe/Berlin",
    "iso:country":"DE",
    "wof:name":"Unterschroetenloh",
    "wof:placetype":"neighbourhood"
},
  "geometry": {"coordinates":[11.19209,48.38063],"type":"Point"}
}