{
  "type": "Feature",
  "properties": {
    "gn:admin1_code":"2",
    "gn:admin2_code":"91.0",
    "gn:admin3_code":"9189.0",
    "gn:admin4_code":"9189142.0",
    "gn:asciiname":"Fachendorf",
    "gn:country_code":"DE",
    "gn:dem":587,
    "gn:feature_class":"P",
    "gn:feature_code":"PPL",
    "gn:name":"Fachendorf",
    "gn:population":0,
    "gn:timezone":"Europe/Berlin",
    "iso:country":"DE",
    "wof:name":"Fachendorf",
    "wof:placetype":"neighbourhood"
},
  "geometry": {"coordinates":[12.38875,48.05649],"type":"Point"}
}