{
  "type": "Feature",
  "properties": {
    "gn:admin1_code":"1",
    "gn:admin2_code":"81.0",
    "gn:admin3_code":"8128.0",
    "gn:admin4_code":"8128115.0",
    "gn:asciiname":"Dienstadt",
    "gn:country_code":"DE",
    "gn:dem":275,
    "gn:feature_class":"P",
    "gn:feature_code":"PPL",
    "gn:name":"Dienstadt",
    "gn:population":0,
    "gn:timezone":"Europe/Berlin",
    "iso:country":"DE",
    "name:deu_x_preferred":[
        "Dienstadt"
    ],
    "name:spa_x_preferred":[
        "Dienstadt"
    ],
    "wof:name":"Dienstadt",
    "wof:placetype":"neighbourhood"
},
  "geometry": {"coordinates":[9.61254,49.63311],"type":"Point"}
}