{
  "type": "Feature",
  "properties": {
    "gn:admin1_code":"1.0",
    "gn:admin2_code":"81.0",
    "gn:admin3_code":"8136.0",
    "gn:admin4_code":"8136027.0",
    "gn:asciiname":"Altersberg",
    "gn:country_code":"DE",
    "gn:dem":562,
    "gn:feature_class":"P",
    "gn:feature_code":"PPL",
    "gn:name":"Altersberg",
    "gn:population":0,
    "gn:timezone":"Europe/Berlin",
    "iso:country":"DE",
    "wof:name":"Altersberg",
    "wof:placetype":"neighbourhood"
},
  "geometry": {"coordinates":[9.69076,48.94156],"type":"Point"}
}