{
  "type": "Feature",
  "properties": {
    "iso:country":"DE",
    "name:deu_x_preferred":[
        "Beckrath"
    ],
    "wof:name":"Beckrath",
    "wof:placetype":"neighbourhood"
},
  "geometry": {"coordinates":[6.38434972383178,51.10963690838869],"type":"Point"}
}