{
  "type": "Feature",
  "properties": {
    "gn:gn_country":"DE",
    "gn:gn_fcode":"PPLA4",
    "gn:gn_pop":227,
    "gn:population":227,
    "iso:country":"DE",
    "name:bak_x_preferred":[
        "\u0422\u0440\u043e\u0439\u0448\u0442\u0435\u0434\u0442"
    ],
    "name:baq_x_preferred":[
        "Troistedt"
    ],
    "name:chi_x_preferred":[
        "\u7279\u7f57\u4f0a\u65af\u7279"
    ],
    "name:dut_x_preferred":[
        "Troistedt"
    ],
    "name:eng_x_preferred":[
        "Troistedt"
    ],
    "name:epo_x_preferred":[
        "Troistedt"
    ],
    "name:fre_x_preferred":[
        "Troistedt"
    ],
    "name:ger_x_preferred":[
        "Troistedt"
    ],
    "name:hun_x_preferred":[
        "Troistedt"
    ],
    "name:ita_x_preferred":[
        "Troistedt"
    ],
    "name:kaz_x_preferred":[
        "\u0422\u0440\u043e\u0439\u0448\u0442\u0435\u0434\u0442"
    ],
    "name:kir_x_preferred":[
        "\u0422\u0440\u043e\u0439\u0448\u0442\u0435\u0434\u0442"
    ],
    "name:mac_x_preferred":[
        "\u0422\u0440\u043e\u0458\u0448\u0442\u0435\u0442"
    ],
    "name:may_x_preferred":[
        "Troistedt"
    ],
    "name:per_x_preferred":[
        "\u062a\u0631\u0648\u06cc\u0634\u062a\u062f\u062a"
    ],
    "name:pol_x_preferred":[
        "Troistedt"
    ],
    "name:rum_x_preferred":[
        "Troistedt"
    ],
    "name:rus_x_preferred":[
        "\u0422\u0440\u043e\u0439\u0448\u0442\u0435\u0434\u0442"
    ],
    "name:spa_x_preferred":[
        "Troistedt"
    ],
    "name:srp_x_preferred":[
        "\u0422\u0440\u043e\u0438\u0448\u0442\u0435\u0442"
    ],
    "name:ukr_x_preferred":[
        "\u0422\u0440\u043e\u0439\u0448\u0442\u0435\u0434\u0442"
    ],
    "name:uzb_x_preferred":[
        "Troistedt"
    ],
    "name:vie_x_preferred":[
        "Troistedt"
    ],
    "name:vol_x_preferred":[
        "Troistedt"
    ],
    "name:war_x_preferred":[
        "Troistedt"
    ],
    "qs_pg:aaroncc":"DE",
    "qs_pg:gn_country":"DE",
    "qs_pg:gn_fcode":"PPLA4",
    "qs_pg:gn_pop":227,
    "qs_pg:name":"Troistedt",
    "qs_pg:photos_9r":0,
    "qs_pg:photos_sr":0,
    "qs_pg:pop_sr":2,
    "qs_pg:qs_pg_placetype":"locality",
    "wof:name":"Troistedt",
    "wof:placetype":"locality",
    "wof:population":227
},
  "geometry": {"coordinates":[11.25,50.93333],"type":"Point"}
}