{
  "type": "Feature",
  "properties": {
    "gn:admin1_code":"1.0",
    "gn:admin2_code":"81.0",
    "gn:admin3_code":"8125.0",
    "gn:admin4_code":"8125008.0",
    "gn:asciiname":"Billensbach",
    "gn:country_code":"DE",
    "gn:dem":367,
    "gn:feature_class":"P",
    "gn:feature_code":"PPL",
    "gn:name":"Billensbach",
    "gn:population":0,
    "gn:timezone":"Europe/Berlin",
    "iso:country":"DE",
    "wof:name":"Billensbach",
    "wof:placetype":"neighbourhood"
},
  "geometry": {"coordinates":[9.36702,49.06207],"type":"Point"}
}