{
  "type": "Feature",
  "properties": {
    "gn:country":"DE",
    "gn:fcode":"PPL",
    "gn:population":341,
    "iso:country":"DE",
    "name:bak_x_preferred":[
        "\u041f\u043b\u0451\u0446"
    ],
    "name:ceb_x_preferred":[
        "Pl\u00f6tz"
    ],
    "name:deu_x_preferred":[
        "Pl\u00f6tz"
    ],
    "name:epo_x_preferred":[
        "Pl\u00f6tz"
    ],
    "name:fas_x_preferred":[
        "\u067e\u0644\u0648\u062a\u0633"
    ],
    "name:ita_x_preferred":[
        "Pl\u00f6tz"
    ],
    "name:kaz_x_preferred":[
        "\u041f\u043b\u0451\u0446"
    ],
    "name:kir_x_preferred":[
        "\u041f\u043b\u04e9\u0446"
    ],
    "name:mkd_x_preferred":[
        "\u041f\u043b\u0435\u0446"
    ],
    "name:nld_x_preferred":[
        "Pl\u00f6tz"
    ],
    "name:ron_x_preferred":[
        "Pl\u00f6tz"
    ],
    "name:rus_x_preferred":[
        "\u041f\u043b\u0451\u0446"
    ],
    "name:srp_x_preferred":[
        "\u041f\u043b\u0435\u0446"
    ],
    "name:uzb_x_preferred":[
        "Pl\u00f6tz"
    ],
    "name:vie_x_preferred":[
        "Pl\u00f6tz"
    ],
    "name:vol_x_preferred":[
        "Pl\u00f6tz"
    ],
    "name:war_x_preferred":[
        "Pl\u00f6tz"
    ],
    "qs_pg:aaroncc":"DE",
    "qs_pg:gn_country":"DE",
    "qs_pg:gn_fcode":"PPL",
    "qs_pg:gn_pop":341,
    "qs_pg:name":"Pl\u00f6tz",
    "qs_pg:name_adm0":"Deutschland",
    "qs_pg:name_adm1":"Mecklenburg-Vorpommern",
    "qs_pg:photos_9r":0,
    "qs_pg:photos_sr":0,
    "qs_pg:pop_sr":2,
    "qs_pg:qs_pg_placetype":"locality",
    "qs_pg:qs_pg_placetype_gp":"Town",
    "qs_pg:woe_adm0":23424829,
    "woe:adm0_id":23424829,
    "woe:name_adm0":"Deutschland",
    "woe:name_adm1":"Mecklenburg-Vorpommern",
    "woe:placetype":"Town",
    "wof:name":"Pl\u00f6tz",
    "wof:placetype":"neighbourhood",
    "wof:population":341
},
  "geometry": {"coordinates":[13.29221,53.87338],"type":"Point"}
}