{
  "type": "Feature",
  "properties": {
    "gn:admin1_code":"2",
    "gn:admin2_code":"97.0",
    "gn:admin3_code":"9778.0",
    "gn:admin4_code":"9778218.0",
    "gn:asciiname":"Dietratried",
    "gn:country_code":"DE",
    "gn:dem":650,
    "gn:feature_class":"P",
    "gn:feature_code":"PPL",
    "gn:name":"Dietratried",
    "gn:population":0,
    "gn:timezone":"Europe/Berlin",
    "iso:country":"DE",
    "name:und_x_variant":[
        "Dietradsried",
        "Dietratried"
    ],
    "wof:name":"Dietratried",
    "wof:placetype":"neighbourhood"
},
  "geometry": {"coordinates":[10.24951,47.91921],"type":"Point"}
}