{
  "type": "Feature",
  "properties": {
    "gn:admin1_code":"12",
    "gn:admin2_code":"0.0",
    "gn:admin3_code":"13073.0",
    "gn:admin4_code":"13073016.0",
    "gn:asciiname":"Faesekow",
    "gn:country_code":"DE",
    "gn:dem":9,
    "gn:feature_class":"P",
    "gn:feature_code":"PPL",
    "gn:name":"F\u00e4sekow",
    "gn:population":0,
    "gn:timezone":"Europe/Berlin",
    "iso:country":"DE",
    "wof:name":"Faesekow",
    "wof:placetype":"neighbourhood"
},
  "geometry": {"coordinates":[12.79667,54.0473],"type":"Point"}
}