{
  "type": "Feature",
  "properties": {
    "gn:admin1_code":"14",
    "gn:admin2_code":"0.0",
    "gn:admin3_code":"15081.0",
    "gn:admin4_code":"15081135.0",
    "gn:asciiname":"Polvitz-Neuemuehle",
    "gn:country_code":"DE",
    "gn:dem":69,
    "gn:feature_class":"P",
    "gn:feature_code":"PPL",
    "gn:name":"Polvitz-Neuem\u00fchle",
    "gn:population":0,
    "gn:timezone":"Europe/Berlin",
    "iso:country":"DE",
    "wof:name":"Polvitz-Neuemuehle",
    "wof:placetype":"neighbourhood"
},
  "geometry": {"coordinates":[11.41667,52.48333],"type":"Point"}
}