{
  "type": "Feature",
  "properties": {
    "gn:admin1_code":"2",
    "gn:admin2_code":"92.0",
    "gn:admin3_code":"9277.0",
    "gn:admin4_code":"9277145.0",
    "gn:asciiname":"Kirchberg am Inn",
    "gn:country_code":"DE",
    "gn:dem":419,
    "gn:feature_class":"P",
    "gn:feature_code":"PPL",
    "gn:name":"Kirchberg am Inn",
    "gn:population":0,
    "gn:timezone":"Europe/Berlin",
    "iso:country":"DE",
    "name:und_x_variant":[
        "Kirchberg",
        "Kirchberg am Inn"
    ],
    "wof:name":"Kirchberg am Inn",
    "wof:placetype":"neighbourhood"
},
  "geometry": {"coordinates":[13.01686,48.28585],"type":"Point"}
}