{
  "type": "Feature",
  "properties": {
    "gn:admin1_code":"2",
    "gn:admin2_code":"97.0",
    "gn:admin3_code":"9773.0",
    "gn:admin4_code":"9773117.0",
    "gn:asciiname":"Hochstein",
    "gn:country_code":"DE",
    "gn:dem":477,
    "gn:feature_class":"P",
    "gn:feature_code":"PPL",
    "gn:name":"Hochstein",
    "gn:population":0,
    "gn:timezone":"Europe/Berlin",
    "iso:country":"DE",
    "wof:name":"Hochstein",
    "wof:placetype":"neighbourhood"
},
  "geometry": {"coordinates":[10.59417,48.71662],"type":"Point"}
}