{
  "type": "Feature",
  "properties": {
    "gn:admin1_code":"7",
    "gn:admin2_code":"55.0",
    "gn:admin3_code":"5562.0",
    "gn:admin4_code":"5562008.0",
    "gn:asciiname":"Emscher-Lippe",
    "gn:cc2":"DE",
    "gn:country_code":"DE",
    "gn:dem":62,
    "gn:feature_class":"P",
    "gn:feature_code":"PPL",
    "gn:name":"Emscher-Lippe",
    "gn:population":0,
    "gn:timezone":"Europe/Berlin",
    "iso:country":"DE",
    "name:und_x_variant":[
        "Lippe",
        "Emscher-Lippe"
    ],
    "wof:name":"Emscher-Lippe",
    "wof:placetype":"neighbourhood"
},
  "geometry": {"coordinates":[7.33333,51.63333],"type":"Point"}
}