{
  "type": "Feature",
  "properties": {
    "gn:admin1_code":"6",
    "gn:admin2_code":"0.0",
    "gn:admin3_code":"3461.0",
    "gn:admin4_code":"3461005.0",
    "gn:asciiname":"Suederschweiburg",
    "gn:country_code":"DE",
    "gn:dem":0,
    "gn:feature_class":"P",
    "gn:feature_code":"PPLL",
    "gn:name":"S\u00fcderschweiburg",
    "gn:population":0,
    "gn:timezone":"Europe/Berlin",
    "iso:country":"DE",
    "wof:name":"Suederschweiburg",
    "wof:placetype":"neighbourhood"
},
  "geometry": {"coordinates":[8.27455,53.38774],"type":"Point"}
}