{
  "type": "Feature",
  "properties": {
    "gn:admin1_code":"2",
    "gn:admin2_code":"91.0",
    "gn:admin3_code":"9187.0",
    "gn:admin4_code":"9187172.0",
    "gn:asciiname":"Dorfen",
    "gn:country_code":"DE",
    "gn:dem":790,
    "gn:feature_class":"P",
    "gn:feature_code":"PPL",
    "gn:name":"Dorfen",
    "gn:population":0,
    "gn:timezone":"Europe/Berlin",
    "iso:country":"DE",
    "name:ara_x_preferred":[
        "\u062f\u0648\u0631\u0641\u0646"
    ],
    "name:azb_x_preferred":[
        "\u062f\u0648\u0631\u0641\u0646"
    ],
    "name:bar_x_preferred":[
        "Dorfen"
    ],
    "name:ceb_x_preferred":[
        "Dorfen"
    ],
    "name:dan_x_preferred":[
        "Dorfen"
    ],
    "name:deu_x_preferred":[
        "Dorfen"
    ],
    "name:epo_x_preferred":[
        "Dorfen"
    ],
    "name:fas_x_preferred":[
        "\u062f\u0648\u0631\u0641\u0646"
    ],
    "name:fra_x_preferred":[
        "Dorfen"
    ],
    "name:hun_x_preferred":[
        "Dorfen"
    ],
    "name:ind_x_preferred":[
        "Dorfen"
    ],
    "name:ita_x_preferred":[
        "Dorfen"
    ],
    "name:kaz_x_preferred":[
        "\u0414\u043e\u0440\u0444\u0435\u043d"
    ],
    "name:kir_x_preferred":[
        "\u0414\u043e\u0440\u0444\u0435\u043d"
    ],
    "name:lmo_x_preferred":[
        "Dorfen"
    ],
    "name:msa_x_preferred":[
        "Dorfen"
    ],
    "name:nld_x_preferred":[
        "Dorfen"
    ],
    "name:pnb_x_preferred":[
        "\u0688\u0648\u0631\u0641\u0646"
    ],
    "name:pol_x_preferred":[
        "Dorfen"
    ],
    "name:por_x_preferred":[
        "Dorfen"
    ],
    "name:ron_x_preferred":[
        "Dorfen"
    ],
    "name:rus_x_preferred":[
        "\u0414\u043e\u0440\u0444\u0435\u043d"
    ],
    "name:spa_x_preferred":[
        "Dorfen"
    ],
    "name:srp_x_preferred":[
        "\u0414\u043e\u0440\u0444\u0435\u043d"
    ],
    "name:swe_x_preferred":[
        "Dorfen"
    ],
    "name:tur_x_preferred":[
        "Dorfen"
    ],
    "name:ukr_x_preferred":[
        "\u0414\u043e\u0440\u0444\u0435\u043d"
    ],
    "name:uzb_x_preferred":[
        "Dorfen"
    ],
    "name:vol_x_preferred":[
        "Dorfen"
    ],
    "name:war_x_preferred":[
        "Dorfen"
    ],
    "name:zho_x_preferred":[
        "\u591a\u5c14\u82ac"
    ],
    "wof:name":"Dorfen",
    "wof:placetype":"neighbourhood"
},
  "geometry": {"coordinates":[12.1907,47.77389],"type":"Point"}
}