{
  "type": "Feature",
  "properties": {
    "gn:admin1_code":"15.0",
    "gn:admin2_code":"0.0",
    "gn:admin3_code":"16071.0",
    "gn:admin4_code":"16071022.0",
    "gn:asciiname":"Unterneusulza",
    "gn:country_code":"DE",
    "gn:dem":148,
    "gn:feature_class":"P",
    "gn:feature_code":"PPL",
    "gn:name":"Unterneusulza",
    "gn:population":0,
    "gn:timezone":"Europe/Berlin",
    "iso:country":"DE",
    "wof:name":"Unterneusulza",
    "wof:placetype":"neighbourhood"
},
  "geometry": {"coordinates":[11.66014,51.10799],"type":"Point"}
}