{
  "type": "Feature",
  "properties": {
    "gn:admin1_code":"12",
    "gn:admin2_code":"0.0",
    "gn:admin3_code":"13073.0",
    "gn:admin4_code":"13073018.0",
    "gn:asciiname":"Gaethkenhagen",
    "gn:cc2":"DE",
    "gn:country_code":"DE",
    "gn:dem":5,
    "gn:feature_class":"P",
    "gn:feature_code":"PPL",
    "gn:name":"G\u00e4thkenhagen",
    "gn:population":0,
    "gn:timezone":"Europe/Berlin",
    "iso:country":"DE",
    "name:und_x_variant":[
        "G\u00e4thkenhagen"
    ],
    "wof:name":"Gaethkenhagen",
    "wof:placetype":"neighbourhood"
},
  "geometry": {"coordinates":[12.63132,54.32796],"type":"Point"}
}