{
  "type": "Feature",
  "properties": {
    "gn:admin1_code":"2",
    "gn:admin2_code":"97.0",
    "gn:admin3_code":"9777.0",
    "gn:admin4_code":"9777125.0",
    "gn:asciiname":"Unterdolden",
    "gn:country_code":"DE",
    "gn:dem":815,
    "gn:feature_class":"P",
    "gn:feature_code":"PPL",
    "gn:name":"Unterdolden",
    "gn:population":0,
    "gn:timezone":"Europe/Berlin",
    "iso:country":"DE",
    "wof:name":"Unterdolden",
    "wof:placetype":"neighbourhood"
},
  "geometry": {"coordinates":[10.61228,47.6035],"type":"Point"}
}