{
  "type": "Feature",
  "properties": {
    "gn:admin1_code":"5.0",
    "gn:admin2_code":"64.0",
    "gn:admin3_code":"6436.0",
    "gn:admin4_code":"6436001.0",
    "gn:asciiname":"Altenhain",
    "gn:country_code":"DE",
    "gn:dem":254,
    "gn:feature_class":"P",
    "gn:feature_code":"PPL",
    "gn:name":"Altenhain",
    "gn:population":0,
    "gn:timezone":"Europe/Berlin",
    "iso:country":"DE",
    "wof:name":"Altenhain",
    "wof:placetype":"neighbourhood"
},
  "geometry": {"coordinates":[8.47023,50.15687],"type":"Point"}
}