{
  "type": "Feature",
  "properties": {
    "gn:admin1_code":"2",
    "gn:admin2_code":"96.0",
    "gn:admin3_code":"9671.0",
    "gn:admin4_code":"9671126.0",
    "gn:asciiname":"Jakobsthal",
    "gn:country_code":"DE",
    "gn:dem":395,
    "gn:feature_class":"P",
    "gn:feature_code":"PPL",
    "gn:name":"Jakobsthal",
    "gn:population":0,
    "gn:timezone":"Europe/Berlin",
    "iso:country":"DE",
    "wof:name":"Jakobsthal",
    "wof:placetype":"neighbourhood"
},
  "geometry": {"coordinates":[9.32186,50.05137],"type":"Point"}
}