{
  "type": "Feature",
  "properties": {
    "gn:admin1_code":"7",
    "gn:admin2_code":"53.0",
    "gn:admin3_code":"5358.0",
    "gn:admin4_code":"5358024.0",
    "gn:asciiname":"Merscherhoehe",
    "gn:country_code":"DE",
    "gn:dem":106,
    "gn:feature_class":"P",
    "gn:feature_code":"PPL",
    "gn:name":"Merscherh\u00f6he",
    "gn:population":0,
    "gn:timezone":"Europe/Berlin",
    "iso:country":"DE",
    "wof:name":"Merscherhoehe",
    "wof:placetype":"neighbourhood"
},
  "geometry": {"coordinates":[6.36819,50.93769],"type":"Point"}
}