{
  "type": "Feature",
  "properties": {
    "gn:admin1_code":"2",
    "gn:admin2_code":"92.0",
    "gn:admin3_code":"9274.0",
    "gn:admin4_code":"9274184.0",
    "gn:asciiname":"Geratspoint",
    "gn:country_code":"DE",
    "gn:dem":436,
    "gn:feature_class":"P",
    "gn:feature_code":"PPL",
    "gn:name":"Geratspoint",
    "gn:population":0,
    "gn:timezone":"Europe/Berlin",
    "iso:country":"DE",
    "wof:name":"Geratspoint",
    "wof:placetype":"neighbourhood"
},
  "geometry": {"coordinates":[12.38019,48.46865],"type":"Point"}
}