{
  "type": "Feature",
  "properties": {
    "gn:admin1_code":"1",
    "gn:admin2_code":"82.0",
    "gn:admin3_code":"8215.0",
    "gn:admin4_code":"8215108.0",
    "gn:asciiname":"Forchheim",
    "gn:country_code":"DE",
    "gn:dem":115,
    "gn:feature_class":"P",
    "gn:feature_code":"PPL",
    "gn:name":"Forchheim",
    "gn:population":0,
    "gn:timezone":"Europe/Berlin",
    "iso:country":"DE",
    "name:ara_x_preferred":[
        "\u0641\u0648\u0631\u0634\u0647\u0627\u064a\u0645"
    ],
    "name:ces_x_preferred":[
        "Forchheim"
    ],
    "name:dan_x_preferred":[
        "Forchheim"
    ],
    "name:deu_x_preferred":[
        "Forchheim"
    ],
    "name:epo_x_preferred":[
        "Forchheim"
    ],
    "name:fas_x_preferred":[
        "\u0641\u0631\u0634\u0647\u0627\u06cc\u0645"
    ],
    "name:fra_x_preferred":[
        "Forchheim"
    ],
    "name:heb_x_preferred":[
        "\u05e4\u05d5\u05e8\u05e9\u05d4\u05d9\u05d9\u05dd"
    ],
    "name:hun_x_preferred":[
        "Forchheim"
    ],
    "name:hye_x_preferred":[
        "\u0556\u0578\u0580\u056d\u0570\u0561\u0575\u0574"
    ],
    "name:ind_x_preferred":[
        "Forchheim"
    ],
    "name:ita_x_preferred":[
        "Forchheim"
    ],
    "name:jpn_x_preferred":[
        "\u30d5\u30a9\u30eb\u30d2\u30cf\u30a4\u30e0"
    ],
    "name:kaz_x_preferred":[
        "\u0424\u043e\u0440\u0445\u0445\u0430\u0439\u043c"
    ],
    "name:kir_x_preferred":[
        "\u0424\u043e\u0440\u0445\u0445\u0430\u0439\u043c"
    ],
    "name:lit_x_preferred":[
        "Forchheimas"
    ],
    "name:lmo_x_preferred":[
        "Forchheim"
    ],
    "name:msa_x_preferred":[
        "Forchheim"
    ],
    "name:nds_x_preferred":[
        "Forchheim"
    ],
    "name:nld_x_preferred":[
        "Forchheim"
    ],
    "name:nor_x_preferred":[
        "Forchheim"
    ],
    "name:pnb_x_preferred":[
        "\u0641\u0648\u0631\u0686\u06c1\u0627\u06cc\u0645"
    ],
    "name:pol_x_preferred":[
        "Forchheim"
    ],
    "name:por_x_preferred":[
        "Forchheim"
    ],
    "name:ron_x_preferred":[
        "Forchheim"
    ],
    "name:rus_x_preferred":[
        "\u0424\u043e\u0440\u0445\u0445\u0430\u0439\u043c"
    ],
    "name:sco_x_preferred":[
        "Forchheim"
    ],
    "name:slk_x_preferred":[
        "Forchheim"
    ],
    "name:spa_x_preferred":[
        "Forchheim"
    ],
    "name:srp_x_preferred":[
        "\u0424\u043e\u0440\u0445\u0445\u0430\u0458\u043c"
    ],
    "name:swe_x_preferred":[
        "Forchheim"
    ],
    "name:tur_x_preferred":[
        "Forchheim"
    ],
    "name:ukr_x_preferred":[
        "\u0424\u043e\u0440\u0445\u0433\u0430\u0439\u043c"
    ],
    "name:uzb_x_preferred":[
        "Forchheim"
    ],
    "name:vie_x_preferred":[
        "Forchheim"
    ],
    "name:vol_x_preferred":[
        "Forchheim"
    ],
    "name:war_x_preferred":[
        "Forchheim"
    ],
    "name:zho_x_preferred":[
        "\u798f\u5e0c\u6d77\u59c6"
    ],
    "wof:name":"Forchheim",
    "wof:placetype":"neighbourhood"
},
  "geometry": {"coordinates":[8.3145,48.97667],"type":"Point"}
}