{
  "type": "Feature",
  "properties": {
    "gn:admin1_code":"10",
    "gn:admin2_code":"0.0",
    "gn:admin3_code":"1062.0",
    "gn:admin4_code":"1062025.0",
    "gn:asciiname":"Hansfelde",
    "gn:country_code":"DE",
    "gn:dem":12,
    "gn:feature_class":"P",
    "gn:feature_code":"PPL",
    "gn:name":"Hansfelde",
    "gn:population":0,
    "gn:timezone":"Europe/Berlin",
    "iso:country":"DE",
    "wof:name":"Hansfelde",
    "wof:placetype":"neighbourhood"
},
  "geometry": {"coordinates":[10.59528,53.84175],"type":"Point"}
}