{
  "type": "Feature",
  "properties": {
    "gn:admin1_code":"6.0",
    "gn:admin2_code":"0.0",
    "gn:admin3_code":"3459.0",
    "gn:admin4_code":"3459031.0",
    "gn:asciiname":"Burlager Ort",
    "gn:country_code":"DE",
    "gn:dem":39,
    "gn:feature_class":"P",
    "gn:feature_code":"PPL",
    "gn:name":"Burlager Ort",
    "gn:population":0,
    "gn:timezone":"Europe/Berlin",
    "iso:country":"DE",
    "wof:name":"Burlager Ort",
    "wof:placetype":"neighbourhood"
},
  "geometry": {"coordinates":[7.99519,52.4742],"type":"Point"}
}