{
  "type": "Feature",
  "properties": {
    "gn:admin1_code":"12",
    "gn:admin2_code":"0.0",
    "gn:admin3_code":"13071.0",
    "gn:admin4_code":"13071044.0",
    "gn:asciiname":"Tueckhude",
    "gn:country_code":"DE",
    "gn:dem":6,
    "gn:feature_class":"P",
    "gn:feature_code":"PPL",
    "gn:name":"T\u00fcckhude",
    "gn:population":0,
    "gn:timezone":"Europe/Berlin",
    "iso:country":"DE",
    "name:und_x_variant":[
        "Kolonie T\u00fcckhude",
        "T\u00fcckhude"
    ],
    "wof:name":"Tueckhude",
    "wof:placetype":"neighbourhood"
},
  "geometry": {"coordinates":[13.26559,53.81746999999999],"type":"Point"}
}