{
  "type": "Feature",
  "properties": {
    "gn:admin1_code":"10",
    "gn:admin2_code":"0.0",
    "gn:admin3_code":"1059.0",
    "gn:admin4_code":"1059090.0",
    "gn:asciiname":"Tolkschuby",
    "gn:country_code":"DE",
    "gn:dem":27,
    "gn:feature_class":"P",
    "gn:feature_code":"PPL",
    "gn:name":"Tolkschuby",
    "gn:population":0,
    "gn:timezone":"Europe/Berlin",
    "iso:country":"DE",
    "wof:name":"Tolkschuby",
    "wof:placetype":"neighbourhood"
},
  "geometry": {"coordinates":[9.64684,54.59749],"type":"Point"}
}