{
  "type": "Feature",
  "properties": {
    "gn:admin1_code":"12",
    "gn:admin2_code":"0.0",
    "gn:admin3_code":"13072.0",
    "gn:admin4_code":"13072058.0",
    "gn:asciiname":"Diedrichshagen",
    "gn:country_code":"DE",
    "gn:dem":103,
    "gn:feature_class":"P",
    "gn:feature_code":"PPL",
    "gn:name":"Diedrichshagen",
    "gn:population":0,
    "gn:timezone":"Europe/Berlin",
    "iso:country":"DE",
    "name:dan_x_preferred":[
        "Diedrichshagen"
    ],
    "name:deu_x_preferred":[
        "Diedrichshagen"
    ],
    "name:epo_x_preferred":[
        "Diedrichshagen"
    ],
    "name:fas_x_preferred":[
        "\u062f\u06cc\u062f\u0631\u0627\u06cc\u0634\u0633\u0647\u0627\u06af\u0646"
    ],
    "name:fra_x_preferred":[
        "Diedrichshagen"
    ],
    "name:hun_x_preferred":[
        "Diedrichshagen"
    ],
    "name:ita_x_preferred":[
        "Diedrichshagen"
    ],
    "name:kaz_x_preferred":[
        "\u0414\u0438\u0434\u0440\u0438\u0445\u0441\u0445\u0430\u0433\u0435\u043d"
    ],
    "name:kir_x_preferred":[
        "\u0414\u0438\u0434\u0440\u0438\u0445\u0441\u0445\u0430\u0433\u0435\u043d"
    ],
    "name:mkd_x_preferred":[
        "\u0414\u0438\u0434\u0440\u0438\u0445\u0441\u0445\u0430\u0433\u0435\u043d"
    ],
    "name:msa_x_preferred":[
        "Diedrichshagen"
    ],
    "name:nld_x_preferred":[
        "Diedrichshagen"
    ],
    "name:pol_x_preferred":[
        "Diedrichshagen"
    ],
    "name:por_x_preferred":[
        "Diedrichshagen"
    ],
    "name:ron_x_preferred":[
        "Diedrichshagen"
    ],
    "name:rus_x_preferred":[
        "\u0414\u0438\u0434\u0440\u0438\u0445\u0441\u0445\u0430\u0433\u0435\u043d"
    ],
    "name:spa_x_preferred":[
        "Diedrichshagen"
    ],
    "name:srp_x_preferred":[
        "\u0414\u0438\u0434\u0440\u0438\u0445\u0441\u0445\u0430\u0433\u0435\u043d"
    ],
    "name:ukr_x_preferred":[
        "\u0414\u0456\u0434\u0440\u0456\u0445\u0441\u0433\u0430\u0433\u0435\u043d"
    ],
    "name:uzb_x_preferred":[
        "Diedrichshagen"
    ],
    "name:vie_x_preferred":[
        "Diedrichshagen"
    ],
    "name:vol_x_preferred":[
        "Diedrichshagen"
    ],
    "name:war_x_preferred":[
        "Diedrichshagen"
    ],
    "name:zho_x_preferred":[
        "\u8fea\u5fb7\u91cc\u5e0c\u65af\u54c8\u6839"
    ],
    "wof:name":"Diedrichshagen",
    "wof:placetype":"neighbourhood"
},
  "geometry": {"coordinates":[11.76346,54.10039],"type":"Point"}
}