{
  "type": "Feature",
  "properties": {
    "gn:admin1_code":"2",
    "gn:admin2_code":"97.0",
    "gn:admin3_code":"9778.0",
    "gn:admin4_code":"9778163.0",
    "gn:asciiname":"Lauberhart",
    "gn:country_code":"DE",
    "gn:dem":627,
    "gn:feature_class":"P",
    "gn:feature_code":"PPL",
    "gn:name":"Lauberhart",
    "gn:population":0,
    "gn:timezone":"Europe/Berlin",
    "iso:country":"DE",
    "wof:name":"Lauberhart",
    "wof:placetype":"neighbourhood"
},
  "geometry": {"coordinates":[10.24137,48.0457],"type":"Point"}
}