{
  "type": "Feature",
  "properties": {
    "gn:admin1_code":"2",
    "gn:admin2_code":"95.0",
    "gn:admin3_code":"9571.0",
    "gn:admin4_code":"9571141.0",
    "gn:asciiname":"Lentersheim",
    "gn:country_code":"DE",
    "gn:dem":449,
    "gn:feature_class":"P",
    "gn:feature_code":"PPL",
    "gn:name":"Lentersheim",
    "gn:population":0,
    "gn:timezone":"Europe/Berlin",
    "iso:country":"DE",
    "wof:name":"Lentersheim",
    "wof:placetype":"neighbourhood"
},
  "geometry": {"coordinates":[10.57924,49.07999],"type":"Point"}
}