{
  "type": "Feature",
  "properties": {
    "gn:admin1_code":"2",
    "gn:admin2_code":"91.0",
    "gn:admin3_code":"9173.0",
    "gn:admin4_code":"9173118.0",
    "gn:asciiname":"Foggenbeuern",
    "gn:country_code":"DE",
    "gn:dem":712,
    "gn:feature_class":"P",
    "gn:feature_code":"PPL",
    "gn:name":"F\u00f6ggenbeuern",
    "gn:population":0,
    "gn:timezone":"Europe/Berlin",
    "iso:country":"DE",
    "wof:name":"Foggenbeuern",
    "wof:placetype":"neighbourhood"
},
  "geometry": {"coordinates":[11.56354,47.87427],"type":"Point"}
}