{
  "type": "Feature",
  "properties": {
    "gn:admin1_code":"1",
    "gn:admin2_code":"84.0",
    "gn:admin3_code":"8435.0",
    "gn:admin4_code":"8435057.0",
    "gn:asciiname":"Untereisenbach",
    "gn:country_code":"DE",
    "gn:dem":484,
    "gn:feature_class":"P",
    "gn:feature_code":"PPL",
    "gn:name":"Untereisenbach",
    "gn:population":0,
    "gn:timezone":"Europe/Berlin",
    "iso:country":"DE",
    "name:bar_x_preferred":[
        "Untereisenbach"
    ],
    "name:cat_x_preferred":[
        "Untereisenbach"
    ],
    "name:deu_x_preferred":[
        "Untereisenbach"
    ],
    "name:fra_x_preferred":[
        "Untereisenbach"
    ],
    "name:ltz_x_preferred":[
        "\u00cbnnereesbech"
    ],
    "name:msa_x_preferred":[
        "Untereisenbach"
    ],
    "name:nld_x_preferred":[
        "Untereisenbach"
    ],
    "name:pol_x_preferred":[
        "Untereisenbach"
    ],
    "wof:name":"Untereisenbach",
    "wof:placetype":"neighbourhood"
},
  "geometry": {"coordinates":[9.63333,47.66667],"type":"Point"}
}