{
  "type": "Feature",
  "properties": {
    "gn:admin1_code":"2",
    "gn:admin2_code":"94.0",
    "gn:admin3_code":"9471.0",
    "gn:admin4_code":"9471131.0",
    "gn:asciiname":"Ellersdorf",
    "gn:country_code":"DE",
    "gn:dem":261,
    "gn:feature_class":"P",
    "gn:feature_code":"PPL",
    "gn:name":"Ellersdorf",
    "gn:population":0,
    "gn:timezone":"Europe/Berlin",
    "iso:country":"DE",
    "wof:name":"Ellersdorf",
    "wof:placetype":"neighbourhood"
},
  "geometry": {"coordinates":[10.87724,49.78537],"type":"Point"}
}