{
  "type": "Feature",
  "properties": {
    "gn:admin1_code":"15.0",
    "gn:admin2_code":"00",
    "gn:admin3_code":"16054.0",
    "gn:admin4_code":"16054000.0",
    "gn:asciiname":"Wichtshausen",
    "gn:country_code":"DE",
    "gn:dem":362,
    "gn:feature_class":"P",
    "gn:feature_code":"PPL",
    "gn:name":"Wichtshausen",
    "gn:population":0,
    "gn:timezone":"Europe/Berlin",
    "iso:country":"DE",
    "wof:name":"Wichtshausen",
    "wof:placetype":"neighbourhood"
},
  "geometry": {"coordinates":[10.57369,50.60103],"type":"Point"}
}