{
  "type": "Feature",
  "properties": {
    "gn:admin1_code":"6",
    "gn:admin2_code":"0.0",
    "gn:admin3_code":"3404.0",
    "gn:admin4_code":"3404000.0",
    "gn:asciiname":"Hellern",
    "gn:country_code":"DE",
    "gn:dem":70,
    "gn:feature_class":"P",
    "gn:feature_code":"PPL",
    "gn:name":"Hellern",
    "gn:population":0,
    "gn:timezone":"Europe/Berlin",
    "iso:country":"DE",
    "name:deu_x_preferred":[
        "Hellern"
    ],
    "name:pol_x_preferred":[
        "Hellern"
    ],
    "wof:name":"Hellern",
    "wof:placetype":"neighbourhood"
},
  "geometry": {"coordinates":[7.99,52.25942],"type":"Point"}
}