{
  "type": "Feature",
  "properties": {
    "gn:admin1_code":"13",
    "gn:admin2_code":"0.0",
    "gn:admin3_code":"14625.0",
    "gn:admin4_code":"14625640.0",
    "gn:asciiname":"Hoske",
    "gn:cc2":"DE",
    "gn:country_code":"DE",
    "gn:dem":130,
    "gn:feature_class":"P",
    "gn:feature_code":"PPL",
    "gn:name":"Hoske",
    "gn:population":0,
    "gn:timezone":"Europe/Berlin",
    "iso:country":"DE",
    "name:hsb_x_preferred":[
        "H\u00f3zk"
    ],
    "name:und_x_variant":[
        "Elsterode",
        "Hoske"
    ],
    "wof:name":"Hoske",
    "wof:placetype":"neighbourhood"
},
  "geometry": {"coordinates":[14.26455,51.36524],"type":"Point"}
}