{
  "type": "Feature",
  "properties": {
    "gn:admin1_code":"6",
    "gn:admin2_code":"0.0",
    "gn:admin3_code":"3252.0",
    "gn:admin4_code":"3252002.0",
    "gn:asciiname":"Egestorf",
    "gn:country_code":"DE",
    "gn:dem":133,
    "gn:feature_class":"P",
    "gn:feature_code":"PPL",
    "gn:name":"Egestorf",
    "gn:population":0,
    "gn:timezone":"Europe/Berlin",
    "iso:country":"DE",
    "name:ceb_x_preferred":[
        "Egestorf"
    ],
    "name:deu_x_preferred":[
        "Egestorf"
    ],
    "name:epo_x_preferred":[
        "Egestorf"
    ],
    "name:est_x_preferred":[
        "Egestorf"
    ],
    "name:eus_x_preferred":[
        "Egestorf"
    ],
    "name:fas_x_preferred":[
        "\u0627\u06af\u0634\u062a\u0648\u0631\u0641"
    ],
    "name:fra_x_preferred":[
        "Egestorf"
    ],
    "name:hun_x_preferred":[
        "Egestorf"
    ],
    "name:ita_x_preferred":[
        "Egestorf"
    ],
    "name:kaz_x_preferred":[
        "\u042d\u0433\u0435\u0441\u0442\u043e\u0440\u0444"
    ],
    "name:kir_x_preferred":[
        "\u042d\u0433\u0435\u0441\u0442\u043e\u0440\u0444"
    ],
    "name:lat_x_preferred":[
        "Egestorf"
    ],
    "name:msa_x_preferred":[
        "Egestorf"
    ],
    "name:nds_x_preferred":[
        "Gemeen \u00c4\u00e4st\u00f6rp"
    ],
    "name:nld_x_preferred":[
        "Egestorf"
    ],
    "name:pol_x_preferred":[
        "Egestorf"
    ],
    "name:por_x_preferred":[
        "Egestorf"
    ],
    "name:ron_x_preferred":[
        "Egestorf"
    ],
    "name:rus_x_preferred":[
        "\u042d\u0433\u0435\u0441\u0442\u043e\u0440\u0444"
    ],
    "name:spa_x_preferred":[
        "Egestorf"
    ],
    "name:srp_x_preferred":[
        "\u0415\u0433\u0435\u0441\u0442\u043e\u0440\u0444"
    ],
    "name:ukr_x_preferred":[
        "\u0415\u0433\u0435\u0441\u0442\u043e\u0440\u0444"
    ],
    "name:uzb_x_preferred":[
        "Egestorf"
    ],
    "name:vie_x_preferred":[
        "Egestorf"
    ],
    "name:vol_x_preferred":[
        "Egestorf"
    ],
    "name:war_x_preferred":[
        "Egestorf"
    ],
    "name:zho_x_preferred":[
        "\u57c3\u683c\u65af\u6258\u592b"
    ],
    "wof:name":"Egestorf",
    "wof:placetype":"neighbourhood"
},
  "geometry": {"coordinates":[9.40069,52.21912],"type":"Point"}
}