{
  "type": "Feature",
  "properties": {
    "gn:admin1_code":"5.0",
    "gn:admin2_code":"64.0",
    "gn:admin3_code":"6435.0",
    "gn:admin4_code":"6435018.0",
    "gn:asciiname":"Altenhasslau",
    "gn:country_code":"DE",
    "gn:dem":142,
    "gn:feature_class":"P",
    "gn:feature_code":"PPL",
    "gn:name":"Altenha\u00dflau",
    "gn:population":0,
    "gn:timezone":"Europe/Berlin",
    "iso:country":"DE",
    "wof:name":"Altenhasslau",
    "wof:placetype":"neighbourhood"
},
  "geometry": {"coordinates":[9.19736,50.18983],"type":"Point"}
}