{
  "type": "Feature",
  "properties": {
    "gn:admin1_code":"6",
    "gn:admin2_code":"0.0",
    "gn:admin3_code":"3454.0",
    "gn:admin4_code":"3454019.0",
    "gn:asciiname":"Wehlage",
    "gn:country_code":"DE",
    "gn:dem":18,
    "gn:feature_class":"P",
    "gn:feature_code":"PPL",
    "gn:name":"Wehlage",
    "gn:population":0,
    "gn:timezone":"Europe/Berlin",
    "iso:country":"DE",
    "wof:name":"Wehlage",
    "wof:placetype":"neighbourhood"
},
  "geometry": {"coordinates":[7.53333,52.68333000000001],"type":"Point"}
}