{
  "type": "Feature",
  "properties": {
    "iso:country":"DE",
    "wof:name":"Cunnersdorf",
    "wof:placetype":"neighbourhood"
},
  "geometry": {"coordinates":[13.8783391061965,51.04276088788334],"type":"Point"}
}