{
  "type": "Feature",
  "properties": {
    "gn:admin1_code":"13",
    "gn:admin2_code":"0.0",
    "gn:admin3_code":"14612.0",
    "gn:admin4_code":"14612000.0",
    "gn:asciiname":"Cunnersdorf",
    "gn:country_code":"DE",
    "gn:dem":279,
    "gn:feature_class":"P",
    "gn:feature_code":"PPL",
    "gn:name":"Cunnersdorf",
    "gn:population":0,
    "gn:timezone":"Europe/Berlin",
    "iso:country":"DE",
    "wof:name":"Cunnersdorf",
    "wof:placetype":"neighbourhood"
},
  "geometry": {"coordinates":[13.878339,51.042761],"type":"Point"}
}