{
  "type": "Feature",
  "properties": {
    "gn:admin1_code":"11",
    "gn:admin2_code":"0.0",
    "gn:admin3_code":"12070.0",
    "gn:admin4_code":"12070173.0",
    "gn:asciiname":"Garlin",
    "gn:country_code":"DE",
    "gn:dem":43,
    "gn:feature_class":"P",
    "gn:feature_code":"PPL",
    "gn:name":"Garlin",
    "gn:population":0,
    "gn:timezone":"Europe/Berlin",
    "iso:country":"DE",
    "name:arg_x_preferred":[
        "Garlin"
    ],
    "name:cat_x_preferred":[
        "Garlin"
    ],
    "name:ceb_x_preferred":[
        "Garlin"
    ],
    "name:deu_x_preferred":[
        "Garlin"
    ],
    "name:eus_x_preferred":[
        "Garlin"
    ],
    "name:fra_x_preferred":[
        "Garlin"
    ],
    "name:hun_x_preferred":[
        "Garlin"
    ],
    "name:ita_x_preferred":[
        "Garlin"
    ],
    "name:kaz_x_preferred":[
        "\u0413\u0430\u0440\u043b\u0435\u043d"
    ],
    "name:lat_x_preferred":[
        "Garlin"
    ],
    "name:mlg_x_preferred":[
        "Garlin"
    ],
    "name:msa_x_preferred":[
        "Garlin"
    ],
    "name:nld_x_preferred":[
        "Garlin"
    ],
    "name:oci_x_preferred":[
        "Garlin"
    ],
    "name:pms_x_preferred":[
        "Garlin"
    ],
    "name:pol_x_preferred":[
        "Garlin"
    ],
    "name:por_x_preferred":[
        "Garlin"
    ],
    "name:ron_x_preferred":[
        "Garlin"
    ],
    "name:rus_x_preferred":[
        "\u0413\u0430\u0440\u043b\u0435\u043d"
    ],
    "name:slk_x_preferred":[
        "Garlin"
    ],
    "name:spa_x_preferred":[
        "Garlin"
    ],
    "name:swe_x_preferred":[
        "Garlin"
    ],
    "name:ukr_x_preferred":[
        "\u0413\u0430\u0440\u043b\u0435\u043d"
    ],
    "name:uzb_x_preferred":[
        "Garlin"
    ],
    "name:vie_x_preferred":[
        "Garlin"
    ],
    "name:vol_x_preferred":[
        "Garlin"
    ],
    "name:war_x_preferred":[
        "Garlin"
    ],
    "name:zho_x_preferred":[
        "\u52a0\u5c14\u5170"
    ],
    "wof:name":"Garlin",
    "wof:placetype":"neighbourhood"
},
  "geometry": {"coordinates":[11.67883,53.18427],"type":"Point"}
}