{
  "type": "Feature",
  "properties": {
    "gn:admin1_code":"1",
    "gn:admin2_code":"84.0",
    "gn:admin3_code":"8425.0",
    "gn:admin4_code":"8425014.0",
    "gn:asciiname":"Hagen",
    "gn:country_code":"DE",
    "gn:dem":588,
    "gn:feature_class":"P",
    "gn:feature_code":"PPL",
    "gn:name":"Hagen",
    "gn:population":0,
    "gn:timezone":"Europe/Berlin",
    "iso:country":"DE",
    "wof:name":"Hagen",
    "wof:placetype":"neighbourhood"
},
  "geometry": {"coordinates":[9.99249,48.46942],"type":"Point"}
}