{
  "type": "Feature",
  "properties": {
    "gn:admin1_code":"6.0",
    "gn:admin2_code":"00",
    "gn:admin3_code":"3352.0",
    "gn:admin4_code":"3352022.0",
    "gn:asciiname":"Westersode",
    "gn:country_code":"DE",
    "gn:dem":16,
    "gn:feature_class":"P",
    "gn:feature_code":"PPL",
    "gn:name":"Westersode",
    "gn:population":0,
    "gn:timezone":"Europe/Berlin",
    "iso:country":"DE",
    "wof:name":"Westersode",
    "wof:placetype":"neighbourhood"
},
  "geometry": {"coordinates":[9.11069,53.69975],"type":"Point"}
}