{
  "type": "Feature",
  "properties": {
    "gn:admin1_code":"2",
    "gn:admin2_code":"91.0",
    "gn:admin3_code":"9172.0",
    "gn:admin4_code":"9172132.0",
    "gn:asciiname":"Oberschonau Zwei",
    "gn:country_code":"DE",
    "gn:dem":596,
    "gn:feature_class":"P",
    "gn:feature_code":"PPLL",
    "gn:name":"Obersch\u00f6nau Zwei",
    "gn:population":0,
    "gn:timezone":"Europe/Berlin",
    "iso:country":"DE",
    "wof:name":"Oberschonau Zwei",
    "wof:placetype":"neighbourhood"
},
  "geometry": {"coordinates":[12.96667,47.61667],"type":"Point"}
}