{
  "type": "Feature",
  "properties": {
    "gn:admin1_code":"7",
    "gn:admin2_code":"59.0",
    "gn:admin3_code":"5970.0",
    "gn:admin4_code":"5970020.0",
    "gn:asciiname":"Haarhausen",
    "gn:country_code":"DE",
    "gn:dem":347,
    "gn:feature_class":"P",
    "gn:feature_code":"PPL",
    "gn:name":"Haarhausen",
    "gn:population":0,
    "gn:timezone":"Europe/Berlin",
    "iso:country":"DE",
    "wof:name":"Haarhausen",
    "wof:placetype":"neighbourhood"
},
  "geometry": {"coordinates":[8.10253,50.98373],"type":"Point"}
}