{
  "type": "Feature",
  "properties": {
    "gn:admin1_code":"1",
    "gn:admin2_code":"81.0",
    "gn:admin3_code":"8126.0",
    "gn:admin4_code":"8126072.0",
    "gn:asciiname":"Rossach",
    "gn:country_code":"DE",
    "gn:dem":322,
    "gn:feature_class":"P",
    "gn:feature_code":"PPL",
    "gn:name":"Rossach",
    "gn:population":0,
    "gn:timezone":"Europe/Berlin",
    "iso:country":"DE",
    "wof:name":"Rossach",
    "wof:placetype":"neighbourhood"
},
  "geometry": {"coordinates":[9.48345,49.35154],"type":"Point"}
}