{
  "type": "Feature",
  "properties": {
    "gn:admin1_code":"2",
    "gn:admin2_code":"97.0",
    "gn:admin3_code":"9777.0",
    "gn:admin4_code":"9777166.0",
    "gn:asciiname":"Fischhaus",
    "gn:country_code":"DE",
    "gn:dem":804,
    "gn:feature_class":"P",
    "gn:feature_code":"PPL",
    "gn:name":"Fischhaus",
    "gn:population":0,
    "gn:timezone":"Europe/Berlin",
    "iso:country":"DE",
    "wof:name":"Fischhaus",
    "wof:placetype":"neighbourhood"
},
  "geometry": {"coordinates":[10.72066,47.66379000000001],"type":"Point"}
}