{
  "type": "Feature",
  "properties": {
    "gn:admin1_code":"12",
    "gn:admin2_code":"0.0",
    "gn:admin3_code":"13073.0",
    "gn:admin4_code":"13073089.0",
    "gn:asciiname":"Pruetzmannshagen",
    "gn:country_code":"DE",
    "gn:dem":7,
    "gn:feature_class":"P",
    "gn:feature_code":"PPL",
    "gn:name":"Pr\u00fctzmannshagen",
    "gn:population":0,
    "gn:timezone":"Europe/Berlin",
    "iso:country":"DE",
    "wof:name":"Pruetzmannshagen",
    "wof:placetype":"neighbourhood"
},
  "geometry": {"coordinates":[13.1345,54.10058000000001],"type":"Point"}
}