{
  "type": "Feature",
  "properties": {
    "gn:admin1_code":"1.0",
    "gn:admin2_code":"83.0",
    "gn:admin3_code":"8315.0",
    "gn:admin4_code":"8315125.0",
    "gn:asciiname":"Biezighofen",
    "gn:country_code":"DE",
    "gn:dem":404,
    "gn:feature_class":"P",
    "gn:feature_code":"PPL",
    "gn:name":"Biezighofen",
    "gn:population":0,
    "gn:timezone":"Europe/Berlin",
    "iso:country":"DE",
    "wof:name":"Biezighofen",
    "wof:placetype":"neighbourhood"
},
  "geometry": {"coordinates":[7.81781,47.94012],"type":"Point"}
}