{
  "type": "Feature",
  "properties": {
    "gn:admin1_code":"8.0",
    "gn:admin2_code":"00",
    "gn:admin3_code":"7132.0",
    "gn:admin4_code":"7132094.0",
    "gn:asciiname":"Witthecke",
    "gn:country_code":"DE",
    "gn:dem":296,
    "gn:feature_class":"P",
    "gn:feature_code":"PPL",
    "gn:name":"Witthecke",
    "gn:population":0,
    "gn:timezone":"Europe/Berlin",
    "iso:country":"DE",
    "wof:name":"Witthecke",
    "wof:placetype":"neighbourhood"
},
  "geometry": {"coordinates":[7.51806,50.70801],"type":"Point"}
}