{
  "type": "Feature",
  "properties": {
    "gn:admin1_code":"2",
    "gn:admin2_code":"96.0",
    "gn:admin3_code":"9672.0",
    "gn:admin4_code":"9672140.0",
    "gn:asciiname":"Ebenhausen",
    "gn:country_code":"DE",
    "gn:dem":315,
    "gn:feature_class":"P",
    "gn:feature_code":"PPL",
    "gn:name":"Ebenhausen",
    "gn:population":0,
    "gn:timezone":"Europe/Berlin",
    "iso:country":"DE",
    "wof:name":"Ebenhausen",
    "wof:placetype":"neighbourhood"
},
  "geometry": {"coordinates":[10.13139,50.1285],"type":"Point"}
}