{
  "type": "Feature",
  "properties": {
    "gn:admin1_code":"11",
    "gn:admin2_code":"0.0",
    "gn:admin3_code":"12066.0",
    "gn:admin4_code":"12066176.0",
    "gn:asciiname":"Grube Alwine",
    "gn:country_code":"DE",
    "gn:dem":90,
    "gn:feature_class":"P",
    "gn:feature_code":"PPL",
    "gn:name":"Grube Alwine",
    "gn:population":0,
    "gn:timezone":"Europe/Berlin",
    "iso:country":"DE",
    "wof:name":"Grube Alwine",
    "wof:placetype":"neighbourhood"
},
  "geometry": {"coordinates":[13.85,51.53333],"type":"Point"}
}