{
  "type": "Feature",
  "properties": {
    "gn:admin1_code":"13",
    "gn:admin2_code":"0.0",
    "gn:admin3_code":"14521.0",
    "gn:admin4_code":"14521180.0",
    "gn:asciiname":"Burgstaedtel",
    "gn:country_code":"DE",
    "gn:dem":604,
    "gn:feature_class":"P",
    "gn:feature_code":"PPL",
    "gn:name":"Burgst\u00e4dtel",
    "gn:population":0,
    "gn:timezone":"Europe/Berlin",
    "iso:country":"DE",
    "wof:name":"Burgstaedtel",
    "wof:placetype":"neighbourhood"
},
  "geometry": {"coordinates":[12.83988,50.61014],"type":"Point"}
}