{
  "type": "Feature",
  "properties": {
    "gn:admin1_code":"1",
    "gn:admin2_code":"82.0",
    "gn:admin3_code":"8237.0",
    "gn:admin4_code":"8237054.0",
    "gn:asciiname":"Neunuifra",
    "gn:country_code":"DE",
    "gn:dem":600,
    "gn:feature_class":"P",
    "gn:feature_code":"PPL",
    "gn:name":"Neunuifra",
    "gn:population":0,
    "gn:timezone":"Europe/Berlin",
    "iso:country":"DE",
    "wof:name":"Neunuifra",
    "wof:placetype":"neighbourhood"
},
  "geometry": {"coordinates":[8.59375,48.51383],"type":"Point"}
}