{
  "type": "Feature",
  "properties": {
    "gn:admin1_code":"1",
    "gn:admin2_code":"81.0",
    "gn:admin3_code":"8128.0",
    "gn:admin4_code":"8128058.0",
    "gn:asciiname":"Harthausen",
    "gn:country_code":"DE",
    "gn:dem":324,
    "gn:feature_class":"P",
    "gn:feature_code":"PPL",
    "gn:name":"Harthausen",
    "gn:population":0,
    "gn:timezone":"Europe/Berlin",
    "iso:country":"DE",
    "name:ceb_x_preferred":[
        "Harthausen"
    ],
    "name:deu_x_preferred":[
        "Harthausen"
    ],
    "name:epo_x_preferred":[
        "Harthausen"
    ],
    "name:eus_x_preferred":[
        "Harthausen"
    ],
    "name:fas_x_preferred":[
        "\u0647\u0627\u0631\u062a\u0627\u0648\u0632\u0646"
    ],
    "name:fra_x_preferred":[
        "Harthausen"
    ],
    "name:hun_x_preferred":[
        "Harthausen"
    ],
    "name:ita_x_preferred":[
        "Harthausen"
    ],
    "name:kaz_x_preferred":[
        "\u0425\u0430\u0440\u0442\u0430\u0443\u0437\u0435\u043d"
    ],
    "name:kir_x_preferred":[
        "\u0425\u0430\u0440\u0442\u0430\u0443\u0437\u0435\u043d"
    ],
    "name:msa_x_preferred":[
        "Harthausen"
    ],
    "name:nld_x_preferred":[
        "Harthausen"
    ],
    "name:pol_x_preferred":[
        "Harthausen"
    ],
    "name:por_x_preferred":[
        "Harthausen"
    ],
    "name:ron_x_preferred":[
        "Harthausen"
    ],
    "name:rus_x_preferred":[
        "\u0425\u0430\u0440\u0442\u0445\u0430\u0443\u0437\u0435\u043d"
    ],
    "name:spa_x_preferred":[
        "Harthausen"
    ],
    "name:srp_x_preferred":[
        "\u0425\u0430\u0440\u0442\u0430\u0443\u0437\u0435\u043d"
    ],
    "name:ukr_x_preferred":[
        "\u0413\u0430\u0440\u0442\u0433\u0430\u0443\u0437\u0435\u043d"
    ],
    "name:uzb_x_preferred":[
        "Harthausen"
    ],
    "name:vie_x_preferred":[
        "Harthausen"
    ],
    "name:vol_x_preferred":[
        "Harthausen"
    ],
    "name:war_x_preferred":[
        "Harthausen"
    ],
    "name:zho_x_preferred":[
        "\u54c8\u7279\u8c6a\u68ee"
    ],
    "wof:name":"Harthausen",
    "wof:placetype":"neighbourhood"
},
  "geometry": {"coordinates":[9.84753,49.53221],"type":"Point"}
}