{
  "type": "Feature",
  "properties": {
    "gn:admin1_code":"6.0",
    "gn:admin2_code":"0.0",
    "gn:admin3_code":"3356.0",
    "gn:admin4_code":"3356007.0",
    "gn:asciiname":"Auf dem Raden",
    "gn:country_code":"DE",
    "gn:dem":35,
    "gn:feature_class":"P",
    "gn:feature_code":"PPL",
    "gn:name":"Auf dem Raden",
    "gn:population":0,
    "gn:timezone":"Europe/Berlin",
    "iso:country":"DE",
    "wof:name":"Auf dem Raden",
    "wof:placetype":"neighbourhood"
},
  "geometry": {"coordinates":[8.72559,53.27194],"type":"Point"}
}