{
  "type": "Feature",
  "properties": {
    "gn:admin1_code":"13",
    "gn:admin2_code":"0.0",
    "gn:admin3_code":"14521.0",
    "gn:admin4_code":"14521310.0",
    "gn:asciiname":"Leukersdorf",
    "gn:country_code":"DE",
    "gn:dem":373,
    "gn:feature_class":"P",
    "gn:feature_code":"PPL",
    "gn:name":"Leukersdorf",
    "gn:population":0,
    "gn:timezone":"Europe/Berlin",
    "iso:country":"DE",
    "name:und_x_variant":[
        "Leukersdorf/Erzgebirge",
        "Leukersdorf"
    ],
    "wof:name":"Leukersdorf",
    "wof:placetype":"neighbourhood"
},
  "geometry": {"coordinates":[12.82504,50.76659],"type":"Point"}
}