{
  "type": "Feature",
  "properties": {
    "gn:admin1_code":"6",
    "gn:admin2_code":"0.0",
    "gn:admin3_code":"3154.0",
    "gn:admin4_code":"3154027.0",
    "gn:asciiname":"Dobbeln",
    "gn:country_code":"DE",
    "gn:dem":102,
    "gn:feature_class":"P",
    "gn:feature_code":"PPL",
    "gn:name":"Dobbeln",
    "gn:population":0,
    "gn:timezone":"Europe/Berlin",
    "iso:country":"DE",
    "wof:name":"Dobbeln",
    "wof:placetype":"neighbourhood"
},
  "geometry": {"coordinates":[10.90256,52.10303],"type":"Point"}
}