{
  "type": "Feature",
  "properties": {
    "gn:admin1_code":"7",
    "gn:admin2_code":"55.0",
    "gn:admin3_code":"5566.0",
    "gn:admin4_code":"5566040.0",
    "gn:asciiname":"Niederlengerich",
    "gn:country_code":"DE",
    "gn:dem":64,
    "gn:feature_class":"P",
    "gn:feature_code":"PPLL",
    "gn:name":"Niederlengerich",
    "gn:population":0,
    "gn:timezone":"Europe/Berlin",
    "iso:country":"DE",
    "wof:name":"Niederlengerich",
    "wof:placetype":"neighbourhood"
},
  "geometry": {"coordinates":[7.83246,52.16901],"type":"Point"}
}