{
  "type": "Feature",
  "properties": {
    "iso:country":"DE",
    "wof:name":"Zollstock",
    "wof:placetype":"neighbourhood"
},
  "geometry": {"coordinates":[6.94076932340337,50.91046302517557],"type":"Point"}
}