{
  "type": "Feature",
  "properties": {
    "gn:admin1_code":"2",
    "gn:admin2_code":"92.0",
    "gn:admin3_code":"9271.0",
    "gn:admin4_code":"9271140.0",
    "gn:asciiname":"Buchberg",
    "gn:country_code":"DE",
    "gn:dem":395,
    "gn:feature_class":"P",
    "gn:feature_code":"PPL",
    "gn:name":"Buchberg",
    "gn:population":0,
    "gn:timezone":"Europe/Berlin",
    "iso:country":"DE",
    "name:als_x_preferred":[
        "Buchberg"
    ],
    "name:ceb_x_preferred":[
        "Buchberg"
    ],
    "name:deu_x_preferred":[
        "Buchberg"
    ],
    "name:epo_x_preferred":[
        "Buchberg"
    ],
    "name:fra_x_preferred":[
        "Buchberg"
    ],
    "name:ita_x_preferred":[
        "Buchberg"
    ],
    "name:mkd_x_preferred":[
        "\u0411\u0443\u0445\u0431\u0435\u0440\u0433"
    ],
    "name:nld_x_preferred":[
        "Buchberg"
    ],
    "name:pol_x_preferred":[
        "Buchberg"
    ],
    "name:swe_x_preferred":[
        "Buchberg"
    ],
    "name:vol_x_preferred":[
        "Buchberg"
    ],
    "wof:name":"Buchberg",
    "wof:placetype":"neighbourhood"
},
  "geometry": {"coordinates":[12.88945,48.88254000000001],"type":"Point"}
}