{
  "type": "Feature",
  "properties": {
    "iso:country":"DE",
    "wof:name":"Volkeskotten",
    "wof:placetype":"neighbourhood"
},
  "geometry": {"coordinates":[6.9869758134882,51.39891640280868],"type":"Point"}
}