{
  "type": "Feature",
  "properties": {
    "gn:admin1_code":"13",
    "gn:admin2_code":"0.0",
    "gn:admin3_code":"14625.0",
    "gn:admin4_code":"14625420.0",
    "gn:asciiname":"Liebegast",
    "gn:country_code":"DE",
    "gn:dem":144,
    "gn:feature_class":"P",
    "gn:feature_code":"PPL",
    "gn:name":"Liebegast",
    "gn:population":0,
    "gn:timezone":"Europe/Berlin",
    "iso:country":"DE",
    "name:hsb_x_preferred":[
        "Lubhozd\u017a"
    ],
    "wof:name":"Liebegast",
    "wof:placetype":"neighbourhood"
},
  "geometry": {"coordinates":[14.19674,51.36208],"type":"Point"}
}