{
  "type": "Feature",
  "properties": {
    "gn:admin1_code":"2",
    "gn:admin2_code":"95.0",
    "gn:admin3_code":"9576.0",
    "gn:admin4_code":"9576143.0",
    "gn:asciiname":"Haimpfarrich",
    "gn:country_code":"DE",
    "gn:dem":361,
    "gn:feature_class":"P",
    "gn:feature_code":"PPL",
    "gn:name":"Haimpfarrich",
    "gn:population":0,
    "gn:timezone":"Europe/Berlin",
    "iso:country":"DE",
    "wof:name":"Haimpfarrich",
    "wof:placetype":"neighbourhood"
},
  "geometry": {"coordinates":[11.17009,49.21255],"type":"Point"}
}