{
  "type": "Feature",
  "properties": {
    "gn:admin1_code":"2",
    "gn:admin2_code":"97.0",
    "gn:admin3_code":"9780.0",
    "gn:admin4_code":"9780117.0",
    "gn:asciiname":"Masers",
    "gn:country_code":"DE",
    "gn:dem":881,
    "gn:feature_class":"P",
    "gn:feature_code":"PPL",
    "gn:name":"Masers",
    "gn:population":0,
    "gn:timezone":"Europe/Berlin",
    "iso:country":"DE",
    "wof:name":"Masers",
    "wof:placetype":"neighbourhood"
},
  "geometry": {"coordinates":[10.22987,47.72119],"type":"Point"}
}