{
  "type": "Feature",
  "properties": {
    "gn:admin1_code":"2.0",
    "gn:admin2_code":"095",
    "gn:admin3_code":"9575.0",
    "gn:admin4_code":"9575144.0",
    "gn:asciiname":"Ziegenbach",
    "gn:country_code":"DE",
    "gn:dem":326,
    "gn:feature_class":"P",
    "gn:feature_code":"PPL",
    "gn:name":"Ziegenbach",
    "gn:population":0,
    "gn:timezone":"Europe/Berlin",
    "iso:country":"DE",
    "wof:name":"Ziegenbach",
    "wof:placetype":"neighbourhood"
},
  "geometry": {"coordinates":[10.3643,49.69823],"type":"Point"}
}