{
  "type": "Feature",
  "properties": {
    "gn:admin1_code":"6",
    "gn:admin2_code":"0.0",
    "gn:admin3_code":"3453.0",
    "gn:admin4_code":"3453006.0",
    "gn:asciiname":"Stadtsholte",
    "gn:country_code":"DE",
    "gn:dem":37,
    "gn:feature_class":"P",
    "gn:feature_code":"PPL",
    "gn:name":"Stadtsholte",
    "gn:population":0,
    "gn:timezone":"Europe/Berlin",
    "iso:country":"DE",
    "wof:name":"Stadtsholte",
    "wof:placetype":"neighbourhood"
},
  "geometry": {"coordinates":[8.04838,52.73388000000001],"type":"Point"}
}