{
  "type": "Feature",
  "properties": {
    "gn:admin1_code":"14",
    "gn:admin2_code":"0.0",
    "gn:admin3_code":"15083.0",
    "gn:admin4_code":"15083298.0",
    "gn:asciiname":"Klein Santersleben",
    "gn:country_code":"DE",
    "gn:dem":97,
    "gn:feature_class":"P",
    "gn:feature_code":"PPL",
    "gn:name":"Klein Santersleben",
    "gn:population":0,
    "gn:timezone":"Europe/Berlin",
    "iso:country":"DE",
    "wof:name":"Klein Santersleben",
    "wof:placetype":"neighbourhood"
},
  "geometry": {"coordinates":[11.42115,52.20319],"type":"Point"}
}