{
  "type": "Feature",
  "properties": {
    "gn:admin1_code":"11",
    "gn:admin2_code":"0.0",
    "gn:admin3_code":"12052.0",
    "gn:admin4_code":"12052000.0",
    "gn:asciiname":"Nutzberg",
    "gn:country_code":"DE",
    "gn:dem":77,
    "gn:feature_class":"P",
    "gn:feature_code":"PPL",
    "gn:name":"Nutzberg",
    "gn:population":0,
    "gn:timezone":"Europe/Berlin",
    "iso:country":"DE",
    "name:und_x_variant":[
        "Kolonie Nutzberg",
        "Nutzberg"
    ],
    "wof:name":"Nutzberg",
    "wof:placetype":"neighbourhood"
},
  "geometry": {"coordinates":[14.39773,51.73526],"type":"Point"}
}