{
  "type": "Feature",
  "properties": {
    "gn:admin1_code":"1.0",
    "gn:admin2_code":"083",
    "gn:admin3_code":"8316.0",
    "gn:admin4_code":"8316020.0",
    "gn:asciiname":"Wonnental",
    "gn:country_code":"DE",
    "gn:dem":174,
    "gn:feature_class":"P",
    "gn:feature_code":"PPL",
    "gn:name":"Wonnental",
    "gn:population":0,
    "gn:timezone":"Europe/Berlin",
    "iso:country":"DE",
    "wof:name":"Wonnental",
    "wof:placetype":"neighbourhood"
},
  "geometry": {"coordinates":[7.76673,48.18541],"type":"Point"}
}