{
  "type": "Feature",
  "properties": {
    "gn:gn_country":"DE",
    "gn:gn_fcode":"PPLA4",
    "gn:gn_pop":124,
    "gn:population":124,
    "iso:country":"DE",
    "name:baq_x_preferred":[
        "Bereborn"
    ],
    "name:chi_x_preferred":[
        "\u8d1d\u96f7\u535a\u5c14\u6069"
    ],
    "name:dut_x_preferred":[
        "Bereborn"
    ],
    "name:eng_x_preferred":[
        "Bereborn"
    ],
    "name:epo_x_preferred":[
        "Bereborn"
    ],
    "name:fre_x_preferred":[
        "Bereborn"
    ],
    "name:ger_x_preferred":[
        "Bereborn"
    ],
    "name:hun_x_preferred":[
        "Bereborn"
    ],
    "name:ita_x_preferred":[
        "Bereborn"
    ],
    "name:jpn_x_preferred":[
        "\u30d9\u30ec\u30fc\u30dc\u30eb\u30f3"
    ],
    "name:kaz_x_preferred":[
        "\u0411\u0435\u0440\u0435\u0431\u043e\u0440\u043d"
    ],
    "name:kir_x_preferred":[
        "\u0411\u0435\u0440\u0435\u0431\u043e\u0440\u043d"
    ],
    "name:may_x_preferred":[
        "Bereborn"
    ],
    "name:per_x_preferred":[
        "\u0628\u0631\u0628\u0648\u0631\u0646"
    ],
    "name:pol_x_preferred":[
        "Bereborn"
    ],
    "name:por_x_preferred":[
        "Bereborn"
    ],
    "name:rum_x_preferred":[
        "Bereborn"
    ],
    "name:rus_x_preferred":[
        "\u0411\u0435\u0440\u0435\u0431\u043e\u0440\u043d"
    ],
    "name:spa_x_preferred":[
        "Bereborn"
    ],
    "name:srp_x_preferred":[
        "\u0411\u0435\u0440\u0435\u0431\u043e\u0440\u043d"
    ],
    "name:ukr_x_preferred":[
        "\u0411\u0435\u0440\u0435\u0431\u043e\u0440\u043d"
    ],
    "name:uzb_x_preferred":[
        "Bereborn"
    ],
    "name:vie_x_preferred":[
        "Bereborn"
    ],
    "name:vol_x_preferred":[
        "Bereborn"
    ],
    "name:war_x_preferred":[
        "Bereborn"
    ],
    "qs_pg:aaroncc":"DE",
    "qs_pg:gn_country":"DE",
    "qs_pg:gn_fcode":"PPLA4",
    "qs_pg:gn_pop":124,
    "qs_pg:name":"Bereborn",
    "qs_pg:photos_9r":0,
    "qs_pg:photos_sr":0,
    "qs_pg:pop_sr":1,
    "qs_pg:qs_pg_placetype":"locality",
    "wof:name":"Bereborn",
    "wof:placetype":"locality",
    "wof:population":124
},
  "geometry": {"coordinates":[6.96667,50.28333],"type":"Point"}
}