{
  "type": "Feature",
  "properties": {
    "gn:admin1_code":"13",
    "gn:admin2_code":"0.0",
    "gn:admin3_code":"14627.0",
    "gn:admin4_code":"14627100.0",
    "gn:asciiname":"Burkhardswalde",
    "gn:country_code":"DE",
    "gn:dem":239,
    "gn:feature_class":"P",
    "gn:feature_code":"PPL",
    "gn:name":"Burkhardswalde",
    "gn:population":0,
    "gn:timezone":"Europe/Berlin",
    "iso:country":"DE",
    "name:und_x_variant":[
        "Burkhardtswalde",
        "Burkhardswalde"
    ],
    "wof:name":"Burkhardswalde",
    "wof:placetype":"neighbourhood"
},
  "geometry": {"coordinates":[13.43191,51.07304],"type":"Point"}
}