{
  "type": "Feature",
  "properties": {
    "gn:admin1_code":"10",
    "gn:admin2_code":"0.0",
    "gn:admin3_code":"1054.0",
    "gn:admin4_code":"1054074.0",
    "gn:asciiname":"Hunnenswarf",
    "gn:cc2":"DE",
    "gn:country_code":"DE",
    "gn:dem":1,
    "gn:feature_class":"P",
    "gn:feature_code":"PPL",
    "gn:name":"Hunnenswarf",
    "gn:population":0,
    "gn:timezone":"Europe/Berlin",
    "iso:country":"DE",
    "wof:name":"Hunnenswarf",
    "wof:placetype":"neighbourhood"
},
  "geometry": {"coordinates":[8.63956,54.64919],"type":"Point"}
}