{
  "type": "Feature",
  "properties": {
    "gn:admin1_code":"2.0",
    "gn:admin2_code":"92.0",
    "gn:admin3_code":"9276.0",
    "gn:admin4_code":"9276144.0",
    "gn:asciiname":"Barndorf",
    "gn:country_code":"DE",
    "gn:dem":601,
    "gn:feature_class":"P",
    "gn:feature_code":"PPL",
    "gn:name":"B\u00e4rndorf",
    "gn:population":0,
    "gn:timezone":"Europe/Berlin",
    "iso:country":"DE",
    "wof:name":"Barndorf",
    "wof:placetype":"neighbourhood"
},
  "geometry": {"coordinates":[12.92859,49.08792],"type":"Point"}
}