{
  "type": "Feature",
  "properties": {
    "gn:admin1_code":"2",
    "gn:admin2_code":"91.0",
    "gn:admin3_code":"9187.0",
    "gn:admin4_code":"9187138.0",
    "gn:asciiname":"Preinersdorf",
    "gn:country_code":"DE",
    "gn:dem":544,
    "gn:feature_class":"P",
    "gn:feature_code":"PPL",
    "gn:name":"Preinersdorf",
    "gn:population":0,
    "gn:timezone":"Europe/Berlin",
    "iso:country":"DE",
    "wof:name":"Preinersdorf",
    "wof:placetype":"neighbourhood"
},
  "geometry": {"coordinates":[12.40262,47.91122],"type":"Point"}
}