{
  "type": "Feature",
  "properties": {
    "gn:admin1_code":"13.0",
    "gn:admin2_code":"0.0",
    "gn:admin3_code":"14511.0",
    "gn:admin4_code":"14511000.0",
    "gn:asciiname":"Reichenbrand",
    "gn:country_code":"DE",
    "gn:dem":328,
    "gn:feature_class":"P",
    "gn:feature_code":"PPL",
    "gn:name":"Reichenbrand",
    "gn:population":0,
    "gn:timezone":"Europe/Berlin",
    "iso:country":"DE",
    "wof:name":"Reichenbrand",
    "wof:placetype":"neighbourhood"
},
  "geometry": {"coordinates":[12.82946,50.81206],"type":"Point"}
}