{
  "type": "Feature",
  "properties": {
    "gn:admin1_code":"2",
    "gn:admin2_code":"96.0",
    "gn:admin3_code":"9672.0",
    "gn:admin4_code":"9672138.0",
    "gn:asciiname":"Dreistelzhof",
    "gn:country_code":"DE",
    "gn:dem":512,
    "gn:feature_class":"P",
    "gn:feature_code":"PPL",
    "gn:name":"Dreistelzhof",
    "gn:population":0,
    "gn:timezone":"Europe/Berlin",
    "iso:country":"DE",
    "name:und_x_variant":[
        "Dreistelz",
        "Dreistelzhof"
    ],
    "wof:name":"Dreistelzhof",
    "wof:placetype":"neighbourhood"
},
  "geometry": {"coordinates":[9.77877,50.27988],"type":"Point"}
}