{
  "type": "Feature",
  "properties": {
    "gn:admin1_code":"8",
    "gn:admin2_code":"0.0",
    "gn:admin3_code":"7133.0",
    "gn:admin4_code":"7133058.0",
    "gn:asciiname":"Neudorferhof",
    "gn:country_code":"DE",
    "gn:dem":364,
    "gn:feature_class":"P",
    "gn:feature_code":"PPL",
    "gn:name":"Neudorferhof",
    "gn:population":0,
    "gn:timezone":"Europe/Berlin",
    "iso:country":"DE",
    "wof:name":"Neudorferhof",
    "wof:placetype":"neighbourhood"
},
  "geometry": {"coordinates":[7.75657,49.74209000000001],"type":"Point"}
}