{
  "type": "Feature",
  "properties": {
    "iso:country":"DE",
    "wof:name":"Flittard",
    "wof:placetype":"neighbourhood"
},
  "geometry": {"coordinates":[6.97776236874987,51.00172660957694],"type":"Point"}
}