{
  "type": "Feature",
  "properties": {
    "gn:admin1_code":"2",
    "gn:admin2_code":"94.0",
    "gn:admin3_code":"9478.0",
    "gn:admin4_code":"9478176.0",
    "gn:asciiname":"Niesten",
    "gn:country_code":"DE",
    "gn:dem":405,
    "gn:feature_class":"P",
    "gn:feature_code":"PPL",
    "gn:name":"Niesten",
    "gn:population":0,
    "gn:timezone":"Europe/Berlin",
    "iso:country":"DE",
    "wof:name":"Niesten",
    "wof:placetype":"neighbourhood"
},
  "geometry": {"coordinates":[11.26223,50.07136],"type":"Point"}
}