{
  "type": "Feature",
  "properties": {
    "gn:admin1_code":"8",
    "gn:admin2_code":"0.0",
    "gn:admin3_code":"7333.0",
    "gn:admin4_code":"7333503.0",
    "gn:asciiname":"Langmeil",
    "gn:country_code":"DE",
    "gn:dem":251,
    "gn:feature_class":"P",
    "gn:feature_code":"PPL",
    "gn:name":"Langmeil",
    "gn:population":0,
    "gn:timezone":"Europe/Berlin",
    "iso:country":"DE",
    "wof:name":"Langmeil",
    "wof:placetype":"neighbourhood"
},
  "geometry": {"coordinates":[7.88394,49.56719],"type":"Point"}
}