{
  "type": "Feature",
  "properties": {
    "gn:admin1_code":"12",
    "gn:admin2_code":"0.0",
    "gn:admin3_code":"13075.0",
    "gn:admin4_code":"13075120.0",
    "gn:asciiname":"Nonnendorf",
    "gn:country_code":"DE",
    "gn:dem":13,
    "gn:feature_class":"P",
    "gn:feature_code":"PPL",
    "gn:name":"Nonnendorf",
    "gn:population":0,
    "gn:timezone":"Europe/Berlin",
    "iso:country":"DE",
    "wof:name":"Nonnendorf",
    "wof:placetype":"neighbourhood"
},
  "geometry": {"coordinates":[13.69475,54.11897],"type":"Point"}
}