{
  "type": "Feature",
  "properties": {
    "gn:admin1_code":"10",
    "gn:admin2_code":"0.0",
    "gn:admin3_code":"1003.0",
    "gn:admin4_code":"1003000.0",
    "gn:asciiname":"Moisling",
    "gn:country_code":"DE",
    "gn:dem":13,
    "gn:feature_class":"P",
    "gn:feature_code":"PPL",
    "gn:name":"Moisling",
    "gn:population":0,
    "gn:timezone":"Europe/Berlin",
    "iso:country":"DE",
    "wof:name":"Moisling",
    "wof:placetype":"neighbourhood"
},
  "geometry": {"coordinates":[10.62959,53.84508],"type":"Point"}
}