{
  "type": "Feature",
  "properties": {
    "gn:admin1_code":"7.0",
    "gn:admin2_code":"59.0",
    "gn:admin3_code":"5974.0",
    "gn:admin4_code":"5974048.0",
    "gn:asciiname":"Borgeler Linde",
    "gn:country_code":"DE",
    "gn:dem":96,
    "gn:feature_class":"P",
    "gn:feature_code":"PPL",
    "gn:name":"Borgeler Linde",
    "gn:population":0,
    "gn:timezone":"Europe/Berlin",
    "iso:country":"DE",
    "wof:name":"Borgeler Linde",
    "wof:placetype":"neighbourhood"
},
  "geometry": {"coordinates":[8.04705,51.60457],"type":"Point"}
}