{
  "type": "Feature",
  "properties": {
    "gn:admin1_code":"5",
    "gn:admin2_code":"65.0",
    "gn:admin3_code":"6534.0",
    "gn:admin4_code":"6534010.0",
    "gn:asciiname":"Roemershausen",
    "gn:country_code":"DE",
    "gn:dem":320,
    "gn:feature_class":"P",
    "gn:feature_code":"PPL",
    "gn:name":"R\u00f6mershausen",
    "gn:population":0,
    "gn:timezone":"Europe/Berlin",
    "iso:country":"DE",
    "wof:name":"Roemershausen",
    "wof:placetype":"neighbourhood"
},
  "geometry": {"coordinates":[8.53323,50.77537],"type":"Point"}
}