{
  "type": "Feature",
  "properties": {
    "gn:admin1_code":"5",
    "gn:admin2_code":"66.0",
    "gn:admin3_code":"6634.0",
    "gn:admin4_code":"6634026.0",
    "gn:asciiname":"Merzhausen",
    "gn:country_code":"DE",
    "gn:dem":232,
    "gn:feature_class":"P",
    "gn:feature_code":"PPL",
    "gn:name":"Merzhausen",
    "gn:population":0,
    "gn:timezone":"Europe/Berlin",
    "iso:country":"DE",
    "name:als_x_preferred":[
        "Merzhausen"
    ],
    "name:ceb_x_preferred":[
        "Merzhausen"
    ],
    "name:deu_x_preferred":[
        "Merzhausen"
    ],
    "name:epo_x_preferred":[
        "Merzhausen"
    ],
    "name:eus_x_preferred":[
        "Merzhausen"
    ],
    "name:fas_x_preferred":[
        "\u0645\u0631\u062a\u0633\u0647\u0627\u0648\u0632\u0646"
    ],
    "name:fra_x_preferred":[
        "Merzhausen"
    ],
    "name:hun_x_preferred":[
        "Merzhausen"
    ],
    "name:hye_x_preferred":[
        "\u0544\u0565\u0580\u0581\u0570\u0561\u0578\u0582\u0566\u0565\u0576"
    ],
    "name:ita_x_preferred":[
        "Merzhausen"
    ],
    "name:lat_x_preferred":[
        "Merzhausen"
    ],
    "name:lmo_x_preferred":[
        "Merzhausen"
    ],
    "name:msa_x_preferred":[
        "Merzhausen"
    ],
    "name:nld_x_preferred":[
        "Merzhausen"
    ],
    "name:pol_x_preferred":[
        "Merzhausen"
    ],
    "name:por_x_preferred":[
        "Merzhausen"
    ],
    "name:ron_x_preferred":[
        "Merzhausen"
    ],
    "name:rus_x_preferred":[
        "\u041c\u0435\u0440\u0446\u0445\u0430\u0443\u0437\u0435\u043d"
    ],
    "name:spa_x_preferred":[
        "Merzhausen"
    ],
    "name:srp_x_preferred":[
        "\u041c\u0435\u0440\u0446\u0445\u0430\u0443\u0437\u0435\u043d"
    ],
    "name:ukr_x_preferred":[
        "\u041c\u0435\u0440\u0446\u0433\u0430\u0443\u0437\u0435\u043d"
    ],
    "name:uzb_x_preferred":[
        "Merzhausen"
    ],
    "name:vie_x_preferred":[
        "Merzhausen"
    ],
    "name:vol_x_preferred":[
        "Merzhausen"
    ],
    "name:war_x_preferred":[
        "Merzhausen"
    ],
    "name:zho_x_preferred":[
        "\u6885\u5c14\u8328\u8c6a\u68ee"
    ],
    "wof:name":"Merzhausen",
    "wof:placetype":"neighbourhood"
},
  "geometry": {"coordinates":[9.22054,50.85091],"type":"Point"}
}