{
  "type": "Feature",
  "properties": {
    "gn:admin1_code":"2",
    "gn:admin2_code":"94.0",
    "gn:admin3_code":"9475.0",
    "gn:admin4_code":"9475154.0",
    "gn:asciiname":"Schodlas",
    "gn:country_code":"DE",
    "gn:dem":597,
    "gn:feature_class":"P",
    "gn:feature_code":"PPL",
    "gn:name":"Sch\u00f6dlas",
    "gn:population":0,
    "gn:timezone":"Europe/Berlin",
    "iso:country":"DE",
    "wof:name":"Schodlas",
    "wof:placetype":"neighbourhood"
},
  "geometry": {"coordinates":[11.714,50.18463],"type":"Point"}
}