{
  "type": "Feature",
  "properties": {
    "gn:admin1_code":"2",
    "gn:admin2_code":"97.0",
    "gn:admin3_code":"9772.0",
    "gn:admin4_code":"9772170.0",
    "gn:asciiname":"Schwabmuhlhausen",
    "gn:country_code":"DE",
    "gn:dem":580,
    "gn:feature_class":"P",
    "gn:feature_code":"PPL",
    "gn:name":"Schwabm\u00fchlhausen",
    "gn:population":0,
    "gn:timezone":"Europe/Berlin",
    "iso:country":"DE",
    "wof:name":"Schwabmuhlhausen",
    "wof:placetype":"neighbourhood"
},
  "geometry": {"coordinates":[10.77209,48.10548],"type":"Point"}
}