{
  "type": "Feature",
  "properties": {
    "gn:admin1_code":"12",
    "gn:admin2_code":"0.0",
    "gn:admin3_code":"13071.0",
    "gn:admin4_code":"13071034.0",
    "gn:asciiname":"Knueppeldamm",
    "gn:country_code":"DE",
    "gn:dem":80,
    "gn:feature_class":"P",
    "gn:feature_code":"PPL",
    "gn:name":"Kn\u00fcppeldamm",
    "gn:population":0,
    "gn:timezone":"Europe/Berlin",
    "iso:country":"DE",
    "wof:name":"Knueppeldamm",
    "wof:placetype":"neighbourhood"
},
  "geometry": {"coordinates":[12.40219,53.33886999999999],"type":"Point"}
}