{
  "type": "Feature",
  "properties": {
    "gn:gn_country":"DE",
    "gn:gn_fcode":"PPLA4",
    "gn:gn_pop":305,
    "gn:population":305,
    "iso:country":"DE",
    "name:baq_x_preferred":[
        "Grevenkrug"
    ],
    "name:chi_x_preferred":[
        "\u683c\u96f7\u82ac\u514b\u9c81\u683c"
    ],
    "name:dan_x_preferred":[
        "Grevenkrug"
    ],
    "name:dut_x_preferred":[
        "Grevenkrug"
    ],
    "name:eng_x_preferred":[
        "Grevenkrug"
    ],
    "name:epo_x_preferred":[
        "Grevenkrug"
    ],
    "name:fre_x_preferred":[
        "Grevenkrug"
    ],
    "name:ger_x_preferred":[
        "Grevenkrug"
    ],
    "name:hun_x_preferred":[
        "Grevenkrug"
    ],
    "name:ita_x_preferred":[
        "Grevenkrug"
    ],
    "name:mac_x_preferred":[
        "\u0413\u0440\u0435\u0444\u0435\u043d\u043a\u0440\u0443\u0433"
    ],
    "name:may_x_preferred":[
        "Grevenkrug"
    ],
    "name:per_x_preferred":[
        "\u06af\u0631\u0641\u0646\u06a9\u0631\u0648\u06af"
    ],
    "name:pol_x_preferred":[
        "Grevenkrug"
    ],
    "name:por_x_preferred":[
        "Grevenkrug"
    ],
    "name:rum_x_preferred":[
        "Grevenkrug"
    ],
    "name:rus_x_preferred":[
        "\u0413\u0440\u0435\u0444\u0435\u043d\u043a\u0440\u0443\u0433"
    ],
    "name:spa_x_preferred":[
        "Grevenkrug"
    ],
    "name:srp_x_preferred":[
        "\u0413\u0440\u0435\u0432\u0435\u043d\u043a\u0440\u0443\u0433"
    ],
    "name:tur_x_preferred":[
        "Grevenkrug"
    ],
    "name:ukr_x_preferred":[
        "\u0413\u0440\u0435\u0444\u0435\u043d\u043a\u0440\u0443\u0433"
    ],
    "name:uzb_x_preferred":[
        "Grevenkrug"
    ],
    "name:vie_x_preferred":[
        "Grevenkrug"
    ],
    "name:vol_x_preferred":[
        "Grevenkrug"
    ],
    "name:war_x_preferred":[
        "Grevenkrug"
    ],
    "qs_pg:aaroncc":"DE",
    "qs_pg:gn_country":"DE",
    "qs_pg:gn_fcode":"PPLA4",
    "qs_pg:gn_pop":305,
    "qs_pg:name":"Grevenkrug",
    "qs_pg:photos_9r":0,
    "qs_pg:photos_sr":0,
    "qs_pg:pop_sr":2,
    "qs_pg:qs_pg_placetype":"locality",
    "wof:name":"Grevenkrug",
    "wof:placetype":"locality",
    "wof:population":305
},
  "geometry": {"coordinates":[10.01667,54.21667],"type":"Point"}
}