{
  "type": "Feature",
  "properties": {
    "gn:admin1_code":"1.0",
    "gn:admin2_code":"083",
    "gn:admin3_code":"8336.0",
    "gn:admin4_code":"8336045.0",
    "gn:asciiname":"Wollbach",
    "gn:country_code":"DE",
    "gn:dem":323,
    "gn:feature_class":"P",
    "gn:feature_code":"PPL",
    "gn:name":"Wollbach",
    "gn:population":0,
    "gn:timezone":"Europe/Berlin",
    "iso:country":"DE",
    "wof:name":"Wollbach",
    "wof:placetype":"neighbourhood"
},
  "geometry": {"coordinates":[7.65451,47.67137],"type":"Point"}
}