{
  "type": "Feature",
  "properties": {
    "gn:admin1_code":"10",
    "gn:admin2_code":"0.0",
    "gn:admin3_code":"1055.0",
    "gn:admin4_code":"1055007.0",
    "gn:asciiname":"Klein Neudorf",
    "gn:country_code":"DE",
    "gn:dem":41,
    "gn:feature_class":"P",
    "gn:feature_code":"PPL",
    "gn:name":"Klein Neudorf",
    "gn:population":0,
    "gn:timezone":"Europe/Berlin",
    "iso:country":"DE",
    "wof:name":"Klein Neudorf",
    "wof:placetype":"neighbourhood"
},
  "geometry": {"coordinates":[10.44479,54.10916],"type":"Point"}
}