{
  "type": "Feature",
  "properties": {
    "gn:admin1_code":"1",
    "gn:admin2_code":"82.0",
    "gn:admin3_code":"8225.0",
    "gn:admin4_code":"8225118.0",
    "gn:asciiname":"Mulben",
    "gn:country_code":"DE",
    "gn:dem":503,
    "gn:feature_class":"P",
    "gn:feature_code":"PPL",
    "gn:name":"M\u00fclben",
    "gn:population":0,
    "gn:timezone":"Europe/Berlin",
    "iso:country":"DE",
    "name:ces_x_preferred":[
        "Mulben"
    ],
    "name:deu_x_preferred":[
        "Mulben"
    ],
    "name:eus_x_preferred":[
        "Mulben"
    ],
    "wof:name":"Mulben",
    "wof:placetype":"neighbourhood"
},
  "geometry": {"coordinates":[9.09989,49.46445],"type":"Point"}
}