{
  "type": "Feature",
  "properties": {
    "gn:admin1_code":"2",
    "gn:admin2_code":"93.0",
    "gn:admin3_code":"9372.0",
    "gn:admin4_code":"9372137.0",
    "gn:asciiname":"Ramsried",
    "gn:country_code":"DE",
    "gn:dem":513,
    "gn:feature_class":"P",
    "gn:feature_code":"PPL",
    "gn:name":"Ramsried",
    "gn:population":0,
    "gn:timezone":"Europe/Berlin",
    "iso:country":"DE",
    "wof:name":"Ramsried",
    "wof:placetype":"neighbourhood"
},
  "geometry": {"coordinates":[12.84287,49.21198],"type":"Point"}
}