{
  "type": "Feature",
  "properties": {
    "gn:gn_country":"DE",
    "gn:gn_fcode":"PPLA4",
    "gn:gn_pop":265,
    "gn:population":265,
    "iso:country":"DE",
    "name:chi_x_preferred":[
        "\u514b\u9c81\u660e"
    ],
    "name:dut_x_preferred":[
        "Krummin"
    ],
    "name:eng_x_preferred":[
        "Krummin"
    ],
    "name:epo_x_preferred":[
        "Krummin"
    ],
    "name:fre_x_preferred":[
        "Krummin"
    ],
    "name:ger_x_preferred":[
        "Krummin"
    ],
    "name:hun_x_preferred":[
        "Krummin"
    ],
    "name:ita_x_preferred":[
        "Krummin"
    ],
    "name:kaz_x_preferred":[
        "\u041a\u0440\u0443\u043c\u043c\u0438\u043d"
    ],
    "name:kir_x_preferred":[
        "\u041a\u0440\u0443\u043c\u043c\u0438\u043d"
    ],
    "name:mac_x_preferred":[
        "\u041a\u0440\u0443\u043c\u0438\u043d"
    ],
    "name:may_x_preferred":[
        "Krummin"
    ],
    "name:per_x_preferred":[
        "\u06a9\u0631\u0648\u0645\u06cc\u0646"
    ],
    "name:pol_x_preferred":[
        "Krummin"
    ],
    "name:por_x_preferred":[
        "Krummin"
    ],
    "name:rum_x_preferred":[
        "Krummin"
    ],
    "name:rus_x_preferred":[
        "\u041a\u0440\u0443\u043c\u043c\u0438\u043d"
    ],
    "name:srp_x_preferred":[
        "\u041a\u0440\u0443\u043c\u0438\u043d"
    ],
    "name:ukr_x_preferred":[
        "\u041a\u0440\u0443\u043c\u043c\u0456\u043d"
    ],
    "name:uzb_x_preferred":[
        "Krummin"
    ],
    "name:vie_x_preferred":[
        "Krummin"
    ],
    "name:vol_x_preferred":[
        "Krummin"
    ],
    "name:war_x_preferred":[
        "Krummin"
    ],
    "qs_pg:aaroncc":"DE",
    "qs_pg:gn_country":"DE",
    "qs_pg:gn_fcode":"PPLA4",
    "qs_pg:gn_pop":265,
    "qs_pg:name":"Krummin",
    "qs_pg:name_adm0":"Deutschland",
    "qs_pg:name_adm1":"Mecklenburg-Vorpommern",
    "qs_pg:photos":18,
    "qs_pg:photos_1k":4,
    "qs_pg:photos_9k":1,
    "qs_pg:photos_9r":0,
    "qs_pg:photos_all":18,
    "qs_pg:photos_sr":0,
    "qs_pg:pop_sr":2,
    "qs_pg:qs_pg_placetype":"locality",
    "qs_pg:qs_pg_placetype_gp":"Town",
    "qs_pg:woe_adm0":23424829,
    "wof:name":"Krummin",
    "wof:placetype":"locality",
    "wof:population":265
},
  "geometry": {"coordinates":[13.85,54.05],"type":"Point"}
}