{
  "type": "Feature",
  "properties": {
    "gn:admin1_code":"2",
    "gn:admin2_code":"97.0",
    "gn:admin3_code":"9776.0",
    "gn:admin4_code":"9776117.0",
    "gn:asciiname":"Ratzenberg",
    "gn:country_code":"DE",
    "gn:dem":758,
    "gn:feature_class":"P",
    "gn:feature_code":"PPL",
    "gn:name":"Ratzenberg",
    "gn:population":0,
    "gn:timezone":"Europe/Berlin",
    "iso:country":"DE",
    "wof:name":"Ratzenberg",
    "wof:placetype":"neighbourhood"
},
  "geometry": {"coordinates":[9.86667,47.61667],"type":"Point"}
}