{
  "type": "Feature",
  "properties": {
    "gn:admin1_code":"7",
    "gn:admin2_code":"57.0",
    "gn:admin3_code":"5770.0",
    "gn:admin4_code":"5770016.0",
    "gn:asciiname":"Hongsen",
    "gn:country_code":"DE",
    "gn:dem":124,
    "gn:feature_class":"P",
    "gn:feature_code":"PPL",
    "gn:name":"Hongsen",
    "gn:population":0,
    "gn:timezone":"Europe/Berlin",
    "iso:country":"DE",
    "wof:name":"Hongsen",
    "wof:placetype":"neighbourhood"
},
  "geometry": {"coordinates":[8.64516,52.2711],"type":"Point"}
}