{
  "type": "Feature",
  "properties": {
    "gn:admin1_code":"2",
    "gn:admin2_code":"93.0",
    "gn:admin3_code":"9374.0",
    "gn:admin4_code":"9374149.0",
    "gn:asciiname":"Pfaffenreuth",
    "gn:country_code":"DE",
    "gn:dem":487,
    "gn:feature_class":"P",
    "gn:feature_code":"PPL",
    "gn:name":"Pfaffenreuth",
    "gn:population":0,
    "gn:timezone":"Europe/Berlin",
    "iso:country":"DE",
    "wof:name":"Pfaffenreuth",
    "wof:placetype":"neighbourhood"
},
  "geometry": {"coordinates":[12.0101,49.75328],"type":"Point"}
}