{
  "type": "Feature",
  "properties": {
    "gn:admin1_code":"6",
    "gn:admin2_code":"0.0",
    "gn:admin3_code":"3157.0",
    "gn:admin4_code":"3157007.0",
    "gn:asciiname":"Sonnenberg",
    "gn:country_code":"DE",
    "gn:dem":78,
    "gn:feature_class":"P",
    "gn:feature_code":"PPL",
    "gn:name":"Sonnenberg",
    "gn:population":0,
    "gn:timezone":"Europe/Berlin",
    "iso:country":"DE",
    "name:ceb_x_preferred":[
        "Sonnenberg"
    ],
    "name:deu_x_preferred":[
        "Sonnenberg"
    ],
    "name:epo_x_preferred":[
        "Sonnenberg"
    ],
    "name:eus_x_preferred":[
        "Sonnenberg"
    ],
    "name:fas_x_preferred":[
        "\u0633\u0648\u0646\u0646\u0628\u0631\u06af"
    ],
    "name:fra_x_preferred":[
        "Sonnenberg"
    ],
    "name:gml_x_preferred":[
        "Sunnenberch [a. 1318]"
    ],
    "name:gml_x_variant":[
        "Sunnenberg [a. 1574]"
    ],
    "name:hun_x_preferred":[
        "Sonnenberg"
    ],
    "name:hye_x_preferred":[
        "\u054d\u0578\u0576\u0565\u0576\u0562\u0565\u0580\u0563"
    ],
    "name:ita_x_preferred":[
        "Sonnenberg"
    ],
    "name:mkd_x_preferred":[
        "\u0417\u043e\u043d\u0435\u043d\u0431\u0435\u0440\u0433"
    ],
    "name:msa_x_preferred":[
        "Sonnenberg"
    ],
    "name:nds_x_preferred":[
        "Sunnbarre"
    ],
    "name:nds_x_variant":[
        "Sumbarre"
    ],
    "name:nld_x_preferred":[
        "Sonnenberg"
    ],
    "name:osx_x_preferred":[
        "Sunnenbore [a. 780]"
    ],
    "name:pol_x_preferred":[
        "Sonnenberg"
    ],
    "name:ron_x_preferred":[
        "Sonnenberg"
    ],
    "name:rus_x_preferred":[
        "\u0417\u043e\u043d\u043d\u0435\u043d\u0431\u0435\u0440\u0433"
    ],
    "name:spa_x_preferred":[
        "Sonnenberg"
    ],
    "name:srp_x_preferred":[
        "\u0417\u043e\u043d\u0435\u043d\u0431\u0435\u0440\u0433"
    ],
    "name:ukr_x_preferred":[
        "\u0417\u043e\u043d\u043d\u0435\u043d\u0431\u0435\u0440\u0433"
    ],
    "name:uzb_x_preferred":[
        "Sonnenberg"
    ],
    "name:vol_x_preferred":[
        "Sonnenberg"
    ],
    "name:war_x_preferred":[
        "Sonnenberg"
    ],
    "name:zho_x_preferred":[
        "\u7d22\u5ae9\u8d1d\u683c"
    ],
    "wof:name":"Sonnenberg",
    "wof:placetype":"neighbourhood"
},
  "geometry": {"coordinates":[10.40697,52.23779],"type":"Point"}
}