{
  "type": "Feature",
  "properties": {
    "gn:admin1_code":"6",
    "gn:admin2_code":"0.0",
    "gn:admin3_code":"3157.0",
    "gn:admin4_code":"3157007.0",
    "gn:asciiname":"Sonnenberg",
    "gn:country_code":"DE",
    "gn:dem":78,
    "gn:feature_class":"P",
    "gn:feature_code":"PPL",
    "gn:name":"Sonnenberg",
    "gn:population":0,
    "gn:timezone":"Europe/Berlin",
    "iso:country":"DE",
    "name:gml_x_preferred":[
        "Sunnenberch [a. 1318]"
    ],
    "name:gml_x_variant":[
        "Sunnenberg [a. 1574]"
    ],
    "name:nds_x_preferred":[
        "Sunnbarre"
    ],
    "name:nds_x_variant":[
        "Sumbarre"
    ],
    "name:osx_x_preferred":[
        "Sunnenbore [a. 780]"
    ],
    "wof:name":"Sonnenberg",
    "wof:placetype":"neighbourhood"
},
  "geometry": {"coordinates":[10.40697,52.23779],"type":"Point"}
}