{
  "type": "Feature",
  "properties": {
    "gn:admin1_code":"7",
    "gn:admin2_code":"53.0",
    "gn:admin3_code":"5366.0",
    "gn:admin4_code":"5366016.0",
    "gn:asciiname":"Stotzheim",
    "gn:country_code":"DE",
    "gn:dem":194,
    "gn:feature_class":"P",
    "gn:feature_code":"PPL",
    "gn:name":"Stotzheim",
    "gn:population":0,
    "gn:timezone":"Europe/Berlin",
    "iso:country":"DE",
    "wof:name":"Stotzheim",
    "wof:placetype":"neighbourhood"
},
  "geometry": {"coordinates":[6.81234,50.62808],"type":"Point"}
}