{
  "type": "Feature",
  "properties": {
    "gn:admin1_code":"11",
    "gn:admin2_code":"0.0",
    "gn:admin3_code":"12071.0",
    "gn:admin4_code":"12071386.0",
    "gn:asciiname":"Neuendorf",
    "gn:country_code":"DE",
    "gn:dem":64,
    "gn:feature_class":"P",
    "gn:feature_code":"PPL",
    "gn:name":"Neuendorf",
    "gn:population":0,
    "gn:timezone":"Europe/Berlin",
    "iso:country":"DE",
    "wof:name":"Neuendorf",
    "wof:placetype":"neighbourhood"
},
  "geometry": {"coordinates":[14.4241,51.81249],"type":"Point"}
}