{
  "type": "Feature",
  "properties": {
    "gn:admin1_code":"11",
    "gn:admin2_code":"0.0",
    "gn:admin3_code":"12071.0",
    "gn:admin4_code":"12071386.0",
    "gn:asciiname":"Neuendorf",
    "gn:country_code":"DE",
    "gn:dem":64,
    "gn:feature_class":"P",
    "gn:feature_code":"PPL",
    "gn:name":"Neuendorf",
    "gn:population":0,
    "gn:timezone":"Europe/Berlin",
    "iso:country":"DE",
    "name:cat_x_preferred":[
        "Neuendorf"
    ],
    "name:ceb_x_preferred":[
        "Neuendorf"
    ],
    "name:deu_x_preferred":[
        "Neuendorf"
    ],
    "name:epo_x_preferred":[
        "Neuendorf"
    ],
    "name:eus_x_preferred":[
        "Neuendorf"
    ],
    "name:fra_x_preferred":[
        "Neuendorf"
    ],
    "name:ita_x_preferred":[
        "Neuendorf"
    ],
    "name:nld_x_preferred":[
        "Neuendorf"
    ],
    "name:pol_x_preferred":[
        "Neuendorf"
    ],
    "name:rus_x_preferred":[
        "\u041d\u043e\u0439\u0435\u043d\u0434\u043e\u0440\u0444"
    ],
    "name:spa_x_preferred":[
        "Neuendorf"
    ],
    "name:swe_x_preferred":[
        "Neuendorf"
    ],
    "name:vol_x_preferred":[
        "Neuendorf"
    ],
    "name:zho_x_preferred":[
        "\u8bfa\u4f0a\u6069\u591a\u592b"
    ],
    "wof:name":"Neuendorf",
    "wof:placetype":"neighbourhood"
},
  "geometry": {"coordinates":[14.4241,51.81249],"type":"Point"}
}