{
  "type": "Feature",
  "properties": {
    "gn:admin1_code":"2",
    "gn:admin2_code":"96.0",
    "gn:admin3_code":"9678.0",
    "gn:admin4_code":"9678164.0",
    "gn:asciiname":"Mutzenroth",
    "gn:country_code":"DE",
    "gn:dem":296,
    "gn:feature_class":"P",
    "gn:feature_code":"PPL",
    "gn:name":"Mutzenroth",
    "gn:population":0,
    "gn:timezone":"Europe/Berlin",
    "iso:country":"DE",
    "wof:name":"Mutzenroth",
    "wof:placetype":"neighbourhood"
},
  "geometry": {"coordinates":[10.40178,49.87427],"type":"Point"}
}