{
  "type": "Feature",
  "properties": {
    "gn:admin1_code":"7",
    "gn:admin2_code":"53.0",
    "gn:admin3_code":"5334.0",
    "gn:admin4_code":"5334004.0",
    "gn:asciiname":"Ottenfeld",
    "gn:country_code":"DE",
    "gn:dem":206,
    "gn:feature_class":"P",
    "gn:feature_code":"PPL",
    "gn:name":"Ottenfeld",
    "gn:population":0,
    "gn:timezone":"Europe/Berlin",
    "iso:country":"DE",
    "wof:name":"Ottenfeld",
    "wof:placetype":"neighbourhood"
},
  "geometry": {"coordinates":[6.15,50.86667],"type":"Point"}
}