{
  "type": "Feature",
  "properties": {
    "gn:country":"DE",
    "gn:fcode":"PPL",
    "gn:population":0,
    "iso:country":"DE",
    "name:als_x_preferred":[
        "Rimbach"
    ],
    "name:ceb_x_preferred":[
        "Rimbach"
    ],
    "name:deu_x_preferred":[
        "Rimbach"
    ],
    "name:epo_x_preferred":[
        "Rimbach"
    ],
    "name:fra_x_preferred":[
        "Rimbach"
    ],
    "name:hye_x_preferred":[
        "\u054c\u056b\u0574\u0562\u0561\u056d"
    ],
    "name:ita_x_preferred":[
        "Rimbach"
    ],
    "name:nld_x_preferred":[
        "Rimbach"
    ],
    "name:pol_x_preferred":[
        "Rimbach"
    ],
    "name:rus_x_preferred":[
        "\u0420\u0438\u043c\u0431\u0430\u0445"
    ],
    "name:spa_x_preferred":[
        "Rimbach"
    ],
    "name:srp_x_preferred":[
        "\u0420\u0438\u043c\u0431\u0430\u0445"
    ],
    "name:swe_x_preferred":[
        "Rimbach"
    ],
    "name:vol_x_preferred":[
        "Rimbach"
    ],
    "qs_pg:aaroncc":"DE",
    "qs_pg:gn_country":"DE",
    "qs_pg:gn_fcode":"PPL",
    "qs_pg:gn_pop":0,
    "qs_pg:name":"Rimbach",
    "qs_pg:name_adm0":"Deutschland",
    "qs_pg:name_adm1":"Th\u00fcringen",
    "qs_pg:photos":1463,
    "qs_pg:photos_1k":296,
    "qs_pg:photos_9k":6,
    "qs_pg:photos_9r":7,
    "qs_pg:photos_all":1463,
    "qs_pg:photos_sr":12,
    "qs_pg:pop_sr":0,
    "qs_pg:qs_pg_placetype":"locality",
    "qs_pg:qs_pg_placetype_gp":"Town",
    "qs_pg:woe_adm0":23424829,
    "woe:adm0_id":23424829,
    "woe:name_adm0":"Deutschland",
    "woe:name_adm1":"Th\u00fcringen",
    "woe:placetype":"Town",
    "wof:name":"Rimbach",
    "wof:placetype":"neighbourhood"
},
  "geometry": {"coordinates":[9.94196,51.33851],"type":"Point"}
}