{
  "type": "Feature",
  "properties": {
    "gn:admin1_code":"13",
    "gn:admin2_code":"0.0",
    "gn:admin3_code":"14625.0",
    "gn:admin4_code":"14625100.0",
    "gn:asciiname":"Stacha",
    "gn:country_code":"DE",
    "gn:dem":287,
    "gn:feature_class":"P",
    "gn:feature_code":"PPL",
    "gn:name":"Stacha",
    "gn:population":0,
    "gn:timezone":"Europe/Berlin",
    "iso:country":"DE",
    "name:hsb_x_preferred":[
        "Stachow"
    ],
    "wof:name":"Stacha",
    "wof:placetype":"neighbourhood"
},
  "geometry": {"coordinates":[14.23337,51.16714],"type":"Point"}
}