{
  "type": "Feature",
  "properties": {
    "gn:admin1_code":"8",
    "gn:admin2_code":"0.0",
    "gn:admin3_code":"7232.0",
    "gn:admin4_code":"7232102.0",
    "gn:asciiname":"Russdorf",
    "gn:country_code":"DE",
    "gn:dem":338,
    "gn:feature_class":"P",
    "gn:feature_code":"PPL",
    "gn:name":"Ru\u00dfdorf",
    "gn:population":0,
    "gn:timezone":"Europe/Berlin",
    "iso:country":"DE",
    "wof:name":"Russdorf",
    "wof:placetype":"neighbourhood"
},
  "geometry": {"coordinates":[6.36585,49.99062],"type":"Point"}
}