{
  "type": "Feature",
  "properties": {
    "gn:admin1_code":"7",
    "gn:admin2_code":"53.0",
    "gn:admin3_code":"5382.0",
    "gn:admin4_code":"5382076.0",
    "gn:asciiname":"Stromberg",
    "gn:country_code":"DE",
    "gn:dem":98,
    "gn:feature_class":"P",
    "gn:feature_code":"PPL",
    "gn:name":"Stromberg",
    "gn:population":0,
    "gn:timezone":"Europe/Berlin",
    "iso:country":"DE",
    "name:ceb_x_preferred":[
        "Stromberg"
    ],
    "name:deu_x_preferred":[
        "Stromberg"
    ],
    "name:fra_x_preferred":[
        "Stromberg"
    ],
    "name:ita_x_preferred":[
        "Stromberg"
    ],
    "name:nld_x_preferred":[
        "Stromberg"
    ],
    "name:pol_x_preferred":[
        "Stromberg"
    ],
    "name:rus_x_preferred":[
        "\u0421\u0442\u0440\u043e\u043c\u0431\u0435\u0440\u0433"
    ],
    "wof:name":"Stromberg",
    "wof:placetype":"neighbourhood"
},
  "geometry": {"coordinates":[7.51749,50.75952],"type":"Point"}
}