{
  "type": "Feature",
  "properties": {
    "gn:admin1_code":"1",
    "gn:admin2_code":"84.0",
    "gn:admin3_code":"8437.0",
    "gn:admin4_code":"8437124.0",
    "gn:asciiname":"Oberndorf",
    "gn:country_code":"DE",
    "gn:dem":695,
    "gn:feature_class":"P",
    "gn:feature_code":"PPL",
    "gn:name":"Oberndorf",
    "gn:population":0,
    "gn:timezone":"Europe/Berlin",
    "iso:country":"DE",
    "wof:name":"Oberndorf",
    "wof:placetype":"neighbourhood"
},
  "geometry": {"coordinates":[9.14402,47.86111],"type":"Point"}
}