{
  "type": "Feature",
  "properties": {
    "gn:admin1_code":"2",
    "gn:admin2_code":"95.0",
    "gn:admin3_code":"9575.0",
    "gn:admin4_code":"9575156.0",
    "gn:asciiname":"Egenhausen",
    "gn:country_code":"DE",
    "gn:dem":418,
    "gn:feature_class":"P",
    "gn:feature_code":"PPL",
    "gn:name":"Egenhausen",
    "gn:population":0,
    "gn:timezone":"Europe/Berlin",
    "iso:country":"DE",
    "name:als_x_preferred":[
        "Egenhausen"
    ],
    "name:ceb_x_preferred":[
        "Egenhausen"
    ],
    "name:deu_x_preferred":[
        "Egenhausen"
    ],
    "name:epo_x_preferred":[
        "Egenhausen"
    ],
    "name:eus_x_preferred":[
        "Egenhausen"
    ],
    "name:fas_x_preferred":[
        "\u0627\u06af\u0646\u0647\u0627\u0648\u0632\u0646"
    ],
    "name:fra_x_preferred":[
        "Egenhausen"
    ],
    "name:hun_x_preferred":[
        "Egenhausen"
    ],
    "name:hye_x_preferred":[
        "\u0537\u0563\u0565\u0576\u0570\u0561\u0578\u0582\u0566\u0565\u0576"
    ],
    "name:ita_x_preferred":[
        "Egenhausen"
    ],
    "name:kaz_x_preferred":[
        "\u042d\u0433\u0435\u043d\u0445\u0430\u0443\u0437\u0435\u043d"
    ],
    "name:kir_x_preferred":[
        "\u042d\u0433\u0435\u043d\u0445\u0430\u0443\u0437\u0435\u043d"
    ],
    "name:lat_x_preferred":[
        "Egenhausen"
    ],
    "name:lmo_x_preferred":[
        "Egenhausen"
    ],
    "name:msa_x_preferred":[
        "Egenhausen"
    ],
    "name:nld_x_preferred":[
        "Egenhausen"
    ],
    "name:pol_x_preferred":[
        "Egenhausen"
    ],
    "name:por_x_preferred":[
        "Egenhausen"
    ],
    "name:ron_x_preferred":[
        "Egenhausen"
    ],
    "name:rus_x_preferred":[
        "\u042d\u0433\u0435\u043d\u0445\u0430\u0443\u0437\u0435\u043d"
    ],
    "name:spa_x_preferred":[
        "Egenhausen"
    ],
    "name:srp_x_preferred":[
        "\u0415\u0433\u0435\u043d\u0445\u0430\u0443\u0437\u0435\u043d"
    ],
    "name:ukr_x_preferred":[
        "\u0415\u0433\u0435\u043d\u0433\u0430\u0443\u0437\u0435\u043d"
    ],
    "name:uzb_x_preferred":[
        "Egenhausen"
    ],
    "name:vie_x_preferred":[
        "Egenhausen"
    ],
    "name:vol_x_preferred":[
        "Egenhausen"
    ],
    "name:war_x_preferred":[
        "Egenhausen"
    ],
    "name:zho_x_preferred":[
        "\u57c3\u6839\u8c6a\u68ee"
    ],
    "wof:name":"Egenhausen",
    "wof:placetype":"neighbourhood"
},
  "geometry": {"coordinates":[10.47181,49.4339],"type":"Point"}
}