{
  "type": "Feature",
  "properties": {
    "gn:admin1_code":"7",
    "gn:admin2_code":"51.0",
    "gn:admin3_code":"5111.0",
    "gn:admin4_code":"5111000.0",
    "gn:asciiname":"Kleinbroich",
    "gn:country_code":"DE",
    "gn:dem":43,
    "gn:feature_class":"P",
    "gn:feature_code":"PPL",
    "gn:name":"Kleinbroich",
    "gn:population":0,
    "gn:timezone":"Europe/Berlin",
    "iso:country":"DE",
    "wof:name":"Kleinbroich",
    "wof:placetype":"neighbourhood"
},
  "geometry": {"coordinates":[6.88333,51.15],"type":"Point"}
}