{
  "type": "Feature",
  "properties": {
    "gn:admin1_code":"2",
    "gn:admin2_code":"97.0",
    "gn:admin3_code":"9764.0",
    "gn:admin4_code":"9764000.0",
    "gn:asciiname":"Grunenfurt",
    "gn:country_code":"DE",
    "gn:dem":586,
    "gn:feature_class":"P",
    "gn:feature_code":"PPL",
    "gn:name":"Gr\u00fcnenfurt",
    "gn:population":0,
    "gn:timezone":"Europe/Berlin",
    "iso:country":"DE",
    "wof:name":"Grunenfurt",
    "wof:placetype":"neighbourhood"
},
  "geometry": {"coordinates":[10.19016,48.0114],"type":"Point"}
}