{
  "type": "Feature",
  "properties": {
    "iso:country":"DE",
    "name:deu_x_preferred":[
        "D\u00fcnnwald"
    ],
    "wof:name":"Duennwald",
    "wof:placetype":"neighbourhood"
},
  "geometry": {"coordinates":[7.04345148871554,50.99974608992412],"type":"Point"}
}