{
  "type": "Feature",
  "properties": {
    "gn:admin1_code":"2",
    "gn:admin2_code":"93.0",
    "gn:admin3_code":"9375.0",
    "gn:admin4_code":"9375183.0",
    "gn:asciiname":"Griesau",
    "gn:country_code":"DE",
    "gn:dem":326,
    "gn:feature_class":"P",
    "gn:feature_code":"PPL",
    "gn:name":"Griesau",
    "gn:population":0,
    "gn:timezone":"Europe/Berlin",
    "iso:country":"DE",
    "wof:name":"Griesau",
    "wof:placetype":"neighbourhood"
},
  "geometry": {"coordinates":[12.41316,48.94843],"type":"Point"}
}