{
  "type": "Feature",
  "properties": {
    "iso:country":"DE",
    "name:cat_x_preferred":[
        "Hummelsb\u00fcttel"
    ],
    "name:deu_x_preferred":[
        "Hummelsb\u00fcttel"
    ],
    "name:eng_x_preferred":[
        "Hummelsb\u00fcttel"
    ],
    "name:fra_x_preferred":[
        "Hamburg-Hummelsb\u00fcttel"
    ],
    "name:hun_x_preferred":[
        "Hummelsb\u00fcttel"
    ],
    "name:ita_x_preferred":[
        "Hummelsb\u00fcttel"
    ],
    "name:lat_x_preferred":[
        "Hamburg-Hummelsb\u00fcttel"
    ],
    "name:pol_x_preferred":[
        "Hummelsb\u00fcttel"
    ],
    "name:rus_x_preferred":[
        "\u0425\u0443\u043c\u043c\u0435\u043b\u044c\u0441\u0431\u044e\u0442\u0442\u0435\u043b\u044c"
    ],
    "name:spa_x_preferred":[
        "Hummelsb\u00fcttel"
    ],
    "wof:name":"Hummelsbuettel",
    "wof:placetype":"neighbourhood"
},
  "geometry": {"coordinates":[10.04530177759905,53.64926613645849],"type":"Point"}
}