{
  "type": "Feature",
  "properties": {
    "gn:gn_country":"DE",
    "gn:gn_fcode":"PPLA4",
    "gn:gn_pop":254,
    "gn:population":254,
    "iso:country":"DE",
    "name:baq_x_preferred":[
        "Niederscheidweiler"
    ],
    "name:chi_x_preferred":[
        "\u4e0b\u6c99\u4f0a\u5fb7\u9b4f\u83b1\u5c14"
    ],
    "name:dut_x_preferred":[
        "Niederscheidweiler"
    ],
    "name:eng_x_preferred":[
        "Niederscheidweiler"
    ],
    "name:epo_x_preferred":[
        "Niederscheidweiler"
    ],
    "name:fre_x_preferred":[
        "Niederscheidweiler"
    ],
    "name:ger_x_preferred":[
        "Niederscheidweiler"
    ],
    "name:hun_x_preferred":[
        "Niederscheidweiler"
    ],
    "name:ita_x_preferred":[
        "Niederscheidweiler"
    ],
    "name:jpn_x_preferred":[
        "\u30cb\u30fc\u30c0\u30fc\u30b7\u30e3\u30a4\u30c8\u30f4\u30a1\u30a4\u30e9\u30fc"
    ],
    "name:kaz_x_preferred":[
        "\u041d\u0438\u0434\u0435\u0440\u0448\u0430\u0439\u0434\u0432\u0430\u0439\u043b\u0435\u0440"
    ],
    "name:kir_x_preferred":[
        "\u041d\u0438\u0434\u0435\u0440\u0448\u0430\u0439\u0434\u0432\u0430\u0439\u043b\u0435\u0440"
    ],
    "name:may_x_preferred":[
        "Niederscheidweiler"
    ],
    "name:per_x_preferred":[
        "\u0646\u06cc\u062f\u0631\u0634\u0627\u06cc\u062f\u0648\u0627\u06cc\u0644\u0631"
    ],
    "name:pol_x_preferred":[
        "Niederscheidweiler"
    ],
    "name:por_x_preferred":[
        "Niederscheidweiler"
    ],
    "name:rum_x_preferred":[
        "Niederscheidweiler"
    ],
    "name:rus_x_preferred":[
        "\u041d\u0438\u0434\u0435\u0440\u0448\u0430\u0439\u0434\u0432\u0430\u0439\u043b\u0435\u0440"
    ],
    "name:srp_x_preferred":[
        "\u041d\u0438\u0434\u0435\u0440\u0448\u0430\u0458\u0434\u0432\u0430\u0458\u043b\u0435\u0440"
    ],
    "name:ukr_x_preferred":[
        "\u041d\u0456\u0434\u0435\u0440\u0448\u0430\u0439\u0434\u0432\u0430\u0439\u043b\u0435\u0440"
    ],
    "name:uzb_x_preferred":[
        "Niederscheidweiler"
    ],
    "name:vie_x_preferred":[
        "Niederscheidweiler"
    ],
    "name:vol_x_preferred":[
        "Niederscheidweiler"
    ],
    "name:war_x_preferred":[
        "Niederscheidweiler"
    ],
    "qs_pg:aaroncc":"DE",
    "qs_pg:gn_country":"DE",
    "qs_pg:gn_fcode":"PPLA4",
    "qs_pg:gn_pop":254,
    "qs_pg:name":"Niederscheidweiler",
    "qs_pg:photos_9r":0,
    "qs_pg:photos_sr":0,
    "qs_pg:pop_sr":2,
    "qs_pg:qs_pg_placetype":"locality",
    "wof:name":"Niederscheidweiler",
    "wof:placetype":"locality",
    "wof:population":254
},
  "geometry": {"coordinates":[6.95,50.06667],"type":"Point"}
}