{
  "type": "Feature",
  "properties": {
    "gn:admin1_code":"7.0",
    "gn:admin2_code":"59.0",
    "gn:admin3_code":"5978.0",
    "gn:admin4_code":"5978036.0",
    "gn:asciiname":"Bimberghot",
    "gn:country_code":"DE",
    "gn:dem":129,
    "gn:feature_class":"P",
    "gn:feature_code":"PPL",
    "gn:name":"Bimberghot",
    "gn:population":0,
    "gn:timezone":"Europe/Berlin",
    "iso:country":"DE",
    "wof:name":"Bimberghot",
    "wof:placetype":"neighbourhood"
},
  "geometry": {"coordinates":[7.74316,51.53144],"type":"Point"}
}