{
  "type": "Feature",
  "properties": {
    "gn:admin1_code":"14",
    "gn:admin2_code":"0.0",
    "gn:admin3_code":"15088.0",
    "gn:admin4_code":"15088020.0",
    "gn:asciiname":"Kirchfaehrendorf",
    "gn:country_code":"DE",
    "gn:dem":90,
    "gn:feature_class":"P",
    "gn:feature_code":"PPL",
    "gn:name":"Kirchf\u00e4hrendorf",
    "gn:population":0,
    "gn:timezone":"Europe/Berlin",
    "iso:country":"DE",
    "wof:name":"Kirchfaehrendorf",
    "wof:placetype":"neighbourhood"
},
  "geometry": {"coordinates":[12.05603,51.29455],"type":"Point"}
}