{
  "type": "Feature",
  "properties": {
    "gn:admin1_code":"6",
    "gn:admin2_code":"0.0",
    "gn:admin3_code":"3461.0",
    "gn:admin4_code":"3461004.0",
    "gn:asciiname":"Lienen",
    "gn:country_code":"DE",
    "gn:dem":1,
    "gn:feature_class":"P",
    "gn:feature_code":"PPL",
    "gn:name":"Lienen",
    "gn:population":0,
    "gn:timezone":"Europe/Berlin",
    "iso:country":"DE",
    "name:ceb_x_preferred":[
        "Lienen"
    ],
    "name:deu_x_preferred":[
        "Lienen"
    ],
    "name:epo_x_preferred":[
        "Lienen"
    ],
    "name:eus_x_preferred":[
        "Lienen"
    ],
    "name:fas_x_preferred":[
        "\u0644\u06cc\u0646\u0646"
    ],
    "name:fra_x_preferred":[
        "Lienen"
    ],
    "name:hun_x_preferred":[
        "Lienen"
    ],
    "name:ita_x_preferred":[
        "Lienen"
    ],
    "name:jpn_x_preferred":[
        "\u30ea\u30fc\u30cd\u30f3"
    ],
    "name:lim_x_preferred":[
        "Lienen"
    ],
    "name:lit_x_preferred":[
        "Lynenas"
    ],
    "name:msa_x_preferred":[
        "Lienen"
    ],
    "name:nld_x_preferred":[
        "Lienen"
    ],
    "name:pol_x_preferred":[
        "Lienen"
    ],
    "name:por_x_preferred":[
        "Lienen"
    ],
    "name:ron_x_preferred":[
        "Lienen"
    ],
    "name:rus_x_preferred":[
        "\u041b\u0438\u043d\u0435\u043d"
    ],
    "name:spa_x_preferred":[
        "Lienen"
    ],
    "name:srp_x_preferred":[
        "\u041b\u0438\u043d\u0435\u043d"
    ],
    "name:swe_x_preferred":[
        "Lienen"
    ],
    "name:ukr_x_preferred":[
        "\u041b\u0456\u043d\u0435\u043d"
    ],
    "name:uzb_x_preferred":[
        "Lienen"
    ],
    "name:vie_x_preferred":[
        "Lienen"
    ],
    "name:vol_x_preferred":[
        "Lienen"
    ],
    "name:war_x_preferred":[
        "Lienen"
    ],
    "wof:name":"Lienen",
    "wof:placetype":"neighbourhood"
},
  "geometry": {"coordinates":[8.4679,53.25532],"type":"Point"}
}