{
  "type": "Feature",
  "properties": {
    "gn:admin1_code":"10",
    "gn:admin2_code":"0.0",
    "gn:admin3_code":"1055.0",
    "gn:admin4_code":"1055020.0",
    "gn:asciiname":"Einhaus",
    "gn:country_code":"DE",
    "gn:dem":20,
    "gn:feature_class":"P",
    "gn:feature_code":"PPL",
    "gn:name":"Einhaus",
    "gn:population":0,
    "gn:timezone":"Europe/Berlin",
    "iso:country":"DE",
    "name:ceb_x_preferred":[
        "Einhaus"
    ],
    "name:dan_x_preferred":[
        "Einhaus"
    ],
    "name:deu_x_preferred":[
        "Einhaus"
    ],
    "name:epo_x_preferred":[
        "Einhaus"
    ],
    "name:eus_x_preferred":[
        "Einhaus"
    ],
    "name:fas_x_preferred":[
        "\u0622\u06cc\u0646\u0647\u0627\u0648\u0633"
    ],
    "name:fra_x_preferred":[
        "Einhaus"
    ],
    "name:hun_x_preferred":[
        "Einhaus"
    ],
    "name:ita_x_preferred":[
        "Einhaus"
    ],
    "name:kaz_x_preferred":[
        "\u0410\u0439\u043d\u0445\u0430\u0443\u0441"
    ],
    "name:kir_x_preferred":[
        "\u0410\u0439\u043d\u0445\u0430\u0443\u0441"
    ],
    "name:mkd_x_preferred":[
        "\u0410\u0458\u043d\u0445\u0430\u0443\u0441"
    ],
    "name:msa_x_preferred":[
        "Einhaus"
    ],
    "name:nld_x_preferred":[
        "Einhaus"
    ],
    "name:pol_x_preferred":[
        "Einhaus"
    ],
    "name:por_x_preferred":[
        "Einhaus"
    ],
    "name:ron_x_preferred":[
        "Einhaus"
    ],
    "name:rus_x_preferred":[
        "\u0410\u0439\u043d\u0445\u0430\u0443\u0441"
    ],
    "name:spa_x_preferred":[
        "Einhaus"
    ],
    "name:srp_x_preferred":[
        "\u0410\u0458\u043d\u0445\u0430\u0443\u0441"
    ],
    "name:tur_x_preferred":[
        "Einhaus"
    ],
    "name:ukr_x_preferred":[
        "\u0410\u0439\u043d\u0433\u0430\u0443\u0441"
    ],
    "name:uzb_x_preferred":[
        "Einhaus"
    ],
    "name:vie_x_preferred":[
        "Einhaus"
    ],
    "name:vol_x_preferred":[
        "Einhaus"
    ],
    "name:war_x_preferred":[
        "Einhaus"
    ],
    "name:zho_x_preferred":[
        "\u827e\u6069\u8c6a\u65af"
    ],
    "wof:name":"Einhaus",
    "wof:placetype":"neighbourhood"
},
  "geometry": {"coordinates":[10.83903,54.255],"type":"Point"}
}