{
  "type": "Feature",
  "properties": {
    "gn:admin1_code":"6",
    "gn:admin2_code":"0.0",
    "gn:admin3_code":"3456.0",
    "gn:admin4_code":"3456023.0",
    "gn:asciiname":"Lemke",
    "gn:country_code":"DE",
    "gn:dem":32,
    "gn:feature_class":"P",
    "gn:feature_code":"PPL",
    "gn:name":"Lemke",
    "gn:population":0,
    "gn:timezone":"Europe/Berlin",
    "iso:country":"DE",
    "name:deu_x_preferred":[
        "Lemke"
    ],
    "name:fra_x_preferred":[
        "Lemke"
    ],
    "name:nld_x_preferred":[
        "Lemke"
    ],
    "name:pol_x_preferred":[
        "Lemke"
    ],
    "name:rus_x_preferred":[
        "\u041b\u0435\u043c\u043a\u0435"
    ],
    "name:ukr_x_preferred":[
        "\u041b\u0435\u043c\u043a\u0435"
    ],
    "wof:name":"Lemke",
    "wof:placetype":"neighbourhood"
},
  "geometry": {"coordinates":[6.91238,52.4941],"type":"Point"}
}