{
  "type": "Feature",
  "properties": {
    "gn:admin1_code":"2",
    "gn:admin2_code":"93.0",
    "gn:admin3_code":"9372.0",
    "gn:admin4_code":"9372144.0",
    "gn:asciiname":"Kolmstein",
    "gn:country_code":"DE",
    "gn:dem":609,
    "gn:feature_class":"P",
    "gn:feature_code":"PPL",
    "gn:name":"Kolmstein",
    "gn:population":0,
    "gn:timezone":"Europe/Berlin",
    "iso:country":"DE",
    "wof:name":"Kolmstein",
    "wof:placetype":"neighbourhood"
},
  "geometry": {"coordinates":[12.99123,49.22924],"type":"Point"}
}