{
  "type": "Feature",
  "properties": {
    "gn:admin1_code":"2",
    "gn:admin2_code":"95.0",
    "gn:admin3_code":"9577.0",
    "gn:admin4_code":"9577115.0",
    "gn:asciiname":"Thalmannsfeld",
    "gn:country_code":"DE",
    "gn:dem":540,
    "gn:feature_class":"P",
    "gn:feature_code":"PPL",
    "gn:name":"Thalmannsfeld",
    "gn:population":0,
    "gn:timezone":"Europe/Berlin",
    "iso:country":"DE",
    "wof:name":"Thalmannsfeld",
    "wof:placetype":"neighbourhood"
},
  "geometry": {"coordinates":[11.15105,49.06909],"type":"Point"}
}