{
  "type": "Feature",
  "properties": {
    "gn:admin1_code":"8.0",
    "gn:admin2_code":"00",
    "gn:admin3_code":"7138.0",
    "gn:admin4_code":"7138003.0",
    "gn:asciiname":"Wilsberg",
    "gn:country_code":"DE",
    "gn:dem":262,
    "gn:feature_class":"P",
    "gn:feature_code":"PPL",
    "gn:name":"Wilsberg",
    "gn:population":0,
    "gn:timezone":"Europe/Berlin",
    "iso:country":"DE",
    "name:deu_x_preferred":[
        "Wilsberg"
    ],
    "wof:name":"Wilsberg",
    "wof:placetype":"neighbourhood"
},
  "geometry": {"coordinates":[7.42473,50.65023],"type":"Point"}
}