{
  "type": "Feature",
  "properties": {
    "gn:admin1_code":"2",
    "gn:admin2_code":"92.0",
    "gn:admin3_code":"9277.0",
    "gn:admin4_code":"9277113.0",
    "gn:asciiname":"Steina",
    "gn:country_code":"DE",
    "gn:dem":390,
    "gn:feature_class":"P",
    "gn:feature_code":"PPL",
    "gn:name":"Steina",
    "gn:population":0,
    "gn:timezone":"Europe/Berlin",
    "iso:country":"DE",
    "name:bak_x_preferred":[
        "\u0428\u0442\u0430\u0439\u043d\u0430"
    ],
    "name:cat_x_preferred":[
        "Steina"
    ],
    "name:deu_x_preferred":[
        "Steina"
    ],
    "name:epo_x_preferred":[
        "Steina"
    ],
    "name:est_x_preferred":[
        "Steina vald"
    ],
    "name:eus_x_preferred":[
        "Steina"
    ],
    "name:fas_x_preferred":[
        "\u0634\u062a\u0627\u06cc\u0646\u0627"
    ],
    "name:fra_x_preferred":[
        "Steina"
    ],
    "name:hsb_x_preferred":[
        "S\u0107enjow"
    ],
    "name:hun_x_preferred":[
        "Steina"
    ],
    "name:ita_x_preferred":[
        "Steina"
    ],
    "name:mkd_x_preferred":[
        "\u0428\u0442\u0430\u0458\u043d\u0430"
    ],
    "name:msa_x_preferred":[
        "Steina"
    ],
    "name:nld_x_preferred":[
        "Steina"
    ],
    "name:pol_x_preferred":[
        "Steina"
    ],
    "name:por_x_preferred":[
        "Steina"
    ],
    "name:ron_x_preferred":[
        "Steina"
    ],
    "name:rus_x_preferred":[
        "\u0428\u0442\u0430\u0439\u043d\u0430"
    ],
    "name:spa_x_preferred":[
        "Steina"
    ],
    "name:srp_x_preferred":[
        "\u0428\u0442\u0430\u0458\u043d\u0430"
    ],
    "name:ukr_x_preferred":[
        "\u0428\u0442\u0430\u0439\u043d\u0430"
    ],
    "name:uzb_x_preferred":[
        "Steina"
    ],
    "name:vie_x_preferred":[
        "Steina"
    ],
    "name:vol_x_preferred":[
        "Steina"
    ],
    "name:war_x_preferred":[
        "Steina"
    ],
    "wof:name":"Steina",
    "wof:placetype":"neighbourhood"
},
  "geometry": {"coordinates":[13.06447,48.41932],"type":"Point"}
}