{
  "type": "Feature",
  "properties": {
    "gn:admin1_code":"2",
    "gn:admin2_code":"92.0",
    "gn:admin3_code":"9276.0",
    "gn:admin4_code":"9276126.0",
    "gn:asciiname":"Kaltenbrunn",
    "gn:country_code":"DE",
    "gn:dem":673,
    "gn:feature_class":"P",
    "gn:feature_code":"PPL",
    "gn:name":"Kaltenbrunn",
    "gn:population":0,
    "gn:timezone":"Europe/Berlin",
    "iso:country":"DE",
    "wof:name":"Kaltenbrunn",
    "wof:placetype":"neighbourhood"
},
  "geometry": {"coordinates":[13.24007,48.86878],"type":"Point"}
}