{
  "type": "Feature",
  "properties": {
    "gn:admin1_code":"2",
    "gn:admin2_code":"92.0",
    "gn:admin3_code":"9272.0",
    "gn:admin4_code":"9272118.0",
    "gn:asciiname":"Oberndorf",
    "gn:country_code":"DE",
    "gn:dem":695,
    "gn:feature_class":"P",
    "gn:feature_code":"PPL",
    "gn:name":"Oberndorf",
    "gn:population":0,
    "gn:timezone":"Europe/Berlin",
    "iso:country":"DE",
    "wof:name":"Oberndorf",
    "wof:placetype":"neighbourhood"
},
  "geometry": {"coordinates":[13.55808,48.8096],"type":"Point"}
}