{
  "type": "Feature",
  "properties": {
    "gn:admin1_code":"12.0",
    "gn:admin2_code":"00",
    "gn:admin3_code":"13073.0",
    "gn:admin4_code":"13073092.0",
    "gn:asciiname":"Zaase",
    "gn:country_code":"DE",
    "gn:dem":2,
    "gn:feature_class":"P",
    "gn:feature_code":"PPL",
    "gn:name":"Zaase",
    "gn:population":0,
    "gn:timezone":"Europe/Berlin",
    "iso:country":"DE",
    "wof:name":"Zaase",
    "wof:placetype":"neighbourhood"
},
  "geometry": {"coordinates":[13.2449,54.52199],"type":"Point"}
}