{
  "type": "Feature",
  "properties": {
    "gn:admin1_code":"2",
    "gn:admin2_code":"92.0",
    "gn:admin3_code":"9272.0",
    "gn:admin4_code":"9272147.0",
    "gn:asciiname":"Pummerhof",
    "gn:country_code":"DE",
    "gn:dem":546,
    "gn:feature_class":"P",
    "gn:feature_code":"PPL",
    "gn:name":"Pummerhof",
    "gn:population":0,
    "gn:timezone":"Europe/Berlin",
    "iso:country":"DE",
    "wof:name":"Pummerhof",
    "wof:placetype":"neighbourhood"
},
  "geometry": {"coordinates":[13.31582,48.85557],"type":"Point"}
}