{
  "type": "Feature",
  "properties": {
    "gn:admin1_code":"2",
    "gn:admin2_code":"94.0",
    "gn:admin3_code":"9476.0",
    "gn:admin4_code":"9476177.0",
    "gn:asciiname":"Neufang",
    "gn:country_code":"DE",
    "gn:dem":587,
    "gn:feature_class":"P",
    "gn:feature_code":"PPL",
    "gn:name":"Neufang",
    "gn:population":0,
    "gn:timezone":"Europe/Berlin",
    "iso:country":"DE",
    "wof:name":"Neufang",
    "wof:placetype":"neighbourhood"
},
  "geometry": {"coordinates":[11.42603,50.31333],"type":"Point"}
}