{
  "type": "Feature",
  "properties": {
    "gn:admin1_code":"2",
    "gn:admin2_code":"97.0",
    "gn:admin3_code":"9778.0",
    "gn:admin4_code":"9778183.0",
    "gn:asciiname":"Spitzisbui",
    "gn:country_code":"DE",
    "gn:dem":651,
    "gn:feature_class":"P",
    "gn:feature_code":"PPL",
    "gn:name":"Spitzisbui",
    "gn:population":0,
    "gn:timezone":"Europe/Berlin",
    "iso:country":"DE",
    "wof:name":"Spitzisbui",
    "wof:placetype":"neighbourhood"
},
  "geometry": {"coordinates":[10.38333,48.08333],"type":"Point"}
}