{
  "type": "Feature",
  "properties": {
    "gn:admin1_code":"7",
    "gn:admin2_code":"55.0",
    "gn:admin3_code":"5558.0",
    "gn:admin4_code":"5558016.0",
    "gn:asciiname":"Hanrorup",
    "gn:country_code":"DE",
    "gn:dem":117,
    "gn:feature_class":"P",
    "gn:feature_code":"PPLL",
    "gn:name":"Hanrorup",
    "gn:population":0,
    "gn:timezone":"Europe/Berlin",
    "iso:country":"DE",
    "wof:name":"Hanrorup",
    "wof:placetype":"neighbourhood"
},
  "geometry": {"coordinates":[7.26139,51.91279],"type":"Point"}
}