{
  "type": "Feature",
  "properties": {
    "gn:admin1_code":"2",
    "gn:admin2_code":"95.0",
    "gn:admin3_code":"9574.0",
    "gn:admin4_code":"9574147.0",
    "gn:asciiname":"Hofstetten",
    "gn:country_code":"DE",
    "gn:dem":543,
    "gn:feature_class":"P",
    "gn:feature_code":"PPL",
    "gn:name":"Hofstetten",
    "gn:population":0,
    "gn:timezone":"Europe/Berlin",
    "iso:country":"DE",
    "name:als_x_preferred":[
        "Hofstetten"
    ],
    "name:ceb_x_preferred":[
        "Hofstetten"
    ],
    "name:deu_x_preferred":[
        "Hofstetten"
    ],
    "name:epo_x_preferred":[
        "Hofstetten"
    ],
    "name:eus_x_preferred":[
        "Hofstetten"
    ],
    "name:fra_x_preferred":[
        "Hofstetten"
    ],
    "name:hun_x_preferred":[
        "Hofstetten"
    ],
    "name:ita_x_preferred":[
        "Hofstetten"
    ],
    "name:jpn_x_preferred":[
        "\u30db\u30fc\u30d5\u30b7\u30e5\u30c6\u30c3\u30c6\u30f3"
    ],
    "name:lmo_x_preferred":[
        "Hofstetten"
    ],
    "name:nld_x_preferred":[
        "Hofstetten"
    ],
    "name:pol_x_preferred":[
        "Hofstetten"
    ],
    "name:rus_x_preferred":[
        "\u0425\u043e\u0444\u0448\u0442\u0435\u0442\u0442\u0435\u043d"
    ],
    "name:spa_x_preferred":[
        "Hofstetten"
    ],
    "name:srp_x_preferred":[
        "\u0425\u043e\u0444\u0448\u0442\u0435\u0442\u0435\u043d"
    ],
    "name:swe_x_preferred":[
        "Hofstetten"
    ],
    "name:vol_x_preferred":[
        "Hofstetten"
    ],
    "wof:name":"Hofstetten",
    "wof:placetype":"neighbourhood"
},
  "geometry": {"coordinates":[11.57298,49.4563],"type":"Point"}
}