{
  "type": "Feature",
  "properties": {
    "gn:admin1_code":"7.0",
    "gn:admin2_code":"53.0",
    "gn:admin3_code":"5366.0",
    "gn:admin4_code":"5366016.0",
    "gn:asciiname":"Billig",
    "gn:country_code":"DE",
    "gn:dem":206,
    "gn:feature_class":"P",
    "gn:feature_code":"PPL",
    "gn:name":"Billig",
    "gn:population":0,
    "gn:timezone":"Europe/Berlin",
    "iso:country":"DE",
    "wof:name":"Billig",
    "wof:placetype":"neighbourhood"
},
  "geometry": {"coordinates":[6.77769,50.63057],"type":"Point"}
}