{
  "type": "Feature",
  "properties": {
    "gn:country":"DE",
    "gn:fcode":"PPL",
    "gn:population":0,
    "iso:country":"DE",
    "name:ara_x_preferred":[
        "\u0644\u0646\u063a\u0646\u0641\u0644\u062f"
    ],
    "name:azb_x_preferred":[
        "\u0644\u0646\u0642\u0646\u0641\u0644\u062f"
    ],
    "name:bak_x_preferred":[
        "\u041b\u0435\u043d\u0433\u0435\u043d\u0444\u0435\u043b\u044c\u0434"
    ],
    "name:deu_x_preferred":[
        "Lengenfeld"
    ],
    "name:epo_x_preferred":[
        "Lengenfeld"
    ],
    "name:fas_x_preferred":[
        "\u0644\u0646\u06af\u0646\u0641\u0644\u062f"
    ],
    "name:fra_x_preferred":[
        "Lengenfeld"
    ],
    "name:hsb_x_preferred":[
        "Lengenfeld"
    ],
    "name:hun_x_preferred":[
        "Lengenfeld"
    ],
    "name:ita_x_preferred":[
        "Lengenfeld"
    ],
    "name:lav_x_preferred":[
        "Lengenfelde"
    ],
    "name:mkd_x_preferred":[
        "\u041b\u0435\u043d\u0433\u0435\u043d\u0444\u0435\u043b\u0434"
    ],
    "name:msa_x_preferred":[
        "Lengenfeld"
    ],
    "name:nld_x_preferred":[
        "Lengenfeld"
    ],
    "name:pol_x_preferred":[
        "Lengenfeld"
    ],
    "name:ron_x_preferred":[
        "Lengenfeld"
    ],
    "name:rus_x_preferred":[
        "\u041b\u0435\u043d\u0433\u0435\u043d\u0444\u0435\u043b\u044c\u0434"
    ],
    "name:srp_x_preferred":[
        "\u041b\u0435\u043d\u0433\u0435\u043d\u0444\u0435\u043b\u0434"
    ],
    "name:swe_x_preferred":[
        "Lengenfeld"
    ],
    "name:ukr_x_preferred":[
        "\u041b\u0435\u043d\u0433\u0435\u043d\u0444\u0435\u043b\u044c\u0434"
    ],
    "name:uzb_x_preferred":[
        "Lengenfeld"
    ],
    "name:vol_x_preferred":[
        "Lengenfeld"
    ],
    "name:war_x_preferred":[
        "Lengenfeld"
    ],
    "name:zho_x_preferred":[
        "\u4f26\u6839\u8d39\u5c14\u5fb7"
    ],
    "qs_pg:aaroncc":"DE",
    "qs_pg:gn_country":"DE",
    "qs_pg:gn_fcode":"PPL",
    "qs_pg:gn_pop":0,
    "qs_pg:name":"Lengenfeld",
    "qs_pg:name_adm0":"Deutschland",
    "qs_pg:name_adm1":"Bayern",
    "qs_pg:photos_9k":1,
    "qs_pg:photos_9r":1,
    "qs_pg:photos_all":10,
    "qs_pg:photos_sr":0,
    "qs_pg:pop_sr":0,
    "qs_pg:qs_pg_placetype":"locality",
    "qs_pg:qs_pg_placetype_gp":"Town",
    "qs_pg:woe_adm0":23424829,
    "woe:adm0_id":23424829,
    "woe:name_adm0":"Deutschland",
    "woe:name_adm1":"Bayern",
    "woe:placetype":"Town",
    "wof:name":"Lengenfeld",
    "wof:placetype":"neighbourhood"
},
  "geometry": {"coordinates":[11.63006,49.2389],"type":"Point"}
}