{
  "type": "Feature",
  "properties": {
    "gn:admin1_code":"14",
    "gn:admin2_code":"0.0",
    "gn:admin3_code":"15090.0",
    "gn:admin4_code":"15090070.0",
    "gn:asciiname":"Friedrichsfleiss",
    "gn:country_code":"DE",
    "gn:dem":55,
    "gn:feature_class":"P",
    "gn:feature_code":"PPL",
    "gn:name":"Friedrichsflei\u00df",
    "gn:population":0,
    "gn:timezone":"Europe/Berlin",
    "iso:country":"DE",
    "wof:name":"Friedrichsfleiss",
    "wof:placetype":"neighbourhood"
},
  "geometry": {"coordinates":[11.63416,52.67256999999999],"type":"Point"}
}