{
  "type": "Feature",
  "properties": {
    "gn:admin1_code":"6.0",
    "gn:admin2_code":"0.0",
    "gn:admin3_code":"3153.0",
    "gn:admin4_code":"3153002.0",
    "gn:asciiname":"Bettingerode",
    "gn:country_code":"DE",
    "gn:dem":178,
    "gn:feature_class":"P",
    "gn:feature_code":"PPL",
    "gn:name":"Bettingerode",
    "gn:population":0,
    "gn:timezone":"Europe/Berlin",
    "iso:country":"DE",
    "name:deu_x_preferred":[
        "Bettingerode"
    ],
    "wof:name":"Bettingerode",
    "wof:placetype":"neighbourhood"
},
  "geometry": {"coordinates":[10.57125,51.91261],"type":"Point"}
}