{
  "type": "Feature",
  "properties": {
    "gn:admin1_code":"2",
    "gn:admin2_code":"97.0",
    "gn:admin3_code":"9780.0",
    "gn:admin4_code":"9780119.0",
    "gn:asciiname":"Kasers",
    "gn:country_code":"DE",
    "gn:dem":708,
    "gn:feature_class":"P",
    "gn:feature_code":"PPL",
    "gn:name":"K\u00e4sers",
    "gn:population":0,
    "gn:timezone":"Europe/Berlin",
    "iso:country":"DE",
    "wof:name":"Kasers",
    "wof:placetype":"neighbourhood"
},
  "geometry": {"coordinates":[10.27235,47.83134],"type":"Point"}
}