{
  "type": "Feature",
  "properties": {
    "gn:admin1_code":"2.0",
    "gn:admin2_code":"093",
    "gn:admin3_code":"9376.0",
    "gn:admin4_code":"9376119.0",
    "gn:asciiname":"Witzlarn",
    "gn:country_code":"DE",
    "gn:dem":461,
    "gn:feature_class":"P",
    "gn:feature_code":"PPL",
    "gn:name":"Witzlarn",
    "gn:population":0,
    "gn:timezone":"Europe/Berlin",
    "iso:country":"DE",
    "wof:name":"Witzlarn",
    "wof:placetype":"neighbourhood"
},
  "geometry": {"coordinates":[12.01223,49.27886],"type":"Point"}
}