{
  "type": "Feature",
  "properties": {
    "iso:country":"DE",
    "name:ara_x_preferred":[
        "\u0645\u064a\u062a\u0647"
    ],
    "name:aze_x_preferred":[
        "Mitte"
    ],
    "name:bre_x_preferred":[
        "Mitte"
    ],
    "name:cym_x_preferred":[
        "Mitte"
    ],
    "name:dan_x_preferred":[
        "Berlin Mitte"
    ],
    "name:deu_x_preferred":[
        "Bezirk Mitte"
    ],
    "name:ell_x_preferred":[
        "\u039c\u03af\u03c4\u03b5"
    ],
    "name:epo_x_preferred":[
        "Berlin-Mitte"
    ],
    "name:est_x_preferred":[
        "Mitte rajoon"
    ],
    "name:fas_x_preferred":[
        "\u0645\u06cc\u062a\u0647"
    ],
    "name:fin_x_preferred":[
        "Mitte"
    ],
    "name:heb_x_preferred":[
        "\u05de\u05d9\u05d8\u05d4"
    ],
    "name:ile_x_preferred":[
        "Berlin-Mitte"
    ],
    "name:ind_x_preferred":[
        "Mitte"
    ],
    "name:jpn_x_preferred":[
        "\u30df\u30c3\u30c6\u533a"
    ],
    "name:lat_x_preferred":[
        "Bezirk Mitte"
    ],
    "name:mkd_x_preferred":[
        "\u041c\u0438\u0442\u0435"
    ],
    "name:nld_x_preferred":[
        "Mitte"
    ],
    "name:nor_x_preferred":[
        "Mitte"
    ],
    "name:pol_x_preferred":[
        "Mitte"
    ],
    "name:ron_x_preferred":[
        "Sectorul Centru"
    ],
    "name:rus_x_preferred":[
        "\u041c\u0438\u0442\u0442\u0435"
    ],
    "name:sco_x_preferred":[
        "Mitte"
    ],
    "name:spa_x_preferred":[
        "Berl\u00edn-Mitte"
    ],
    "name:srp_x_preferred":[
        "\u041c\u0438\u0442\u0435"
    ],
    "name:swe_x_preferred":[
        "Mitte"
    ],
    "name:tur_x_preferred":[
        "Mitte"
    ],
    "name:ukr_x_preferred":[
        "\u041c\u0456\u0442\u0442\u0435"
    ],
    "name:zho_x_preferred":[
        "\u7c73\u7279\u533a"
    ],
    "wof:name":"Mitte",
    "wof:placetype":"neighbourhood"
},
  "geometry": {"coordinates":[9.17910748468828,48.77940132874947],"type":"Point"}
}