{
  "type": "Feature",
  "properties": {
    "iso:country":"DE",
    "wof:name":"Mitte",
    "wof:placetype":"neighbourhood"
},
  "geometry": {"coordinates":[9.17910748468828,48.77940132874947],"type":"Point"}
}