{
  "type": "Feature",
  "properties": {
    "gn:admin1_code":"1",
    "gn:admin2_code":"81.0",
    "gn:admin3_code":"8126.0",
    "gn:admin4_code":"8126069.0",
    "gn:asciiname":"Oberhofen",
    "gn:country_code":"DE",
    "gn:dem":254,
    "gn:feature_class":"P",
    "gn:feature_code":"PPL",
    "gn:name":"Oberh\u00f6fen",
    "gn:population":0,
    "gn:timezone":"Europe/Berlin",
    "iso:country":"DE",
    "name:als_x_preferred":[
        "Oberhofen"
    ],
    "name:ceb_x_preferred":[
        "Oberhofen"
    ],
    "name:deu_x_preferred":[
        "Oberhofen"
    ],
    "name:epo_x_preferred":[
        "Oberhofen"
    ],
    "name:fra_x_preferred":[
        "Oberhofen"
    ],
    "name:ita_x_preferred":[
        "Oberhofen"
    ],
    "name:nld_x_preferred":[
        "Oberhofen"
    ],
    "name:pol_x_preferred":[
        "Oberhofen"
    ],
    "name:swe_x_preferred":[
        "Oberhofen"
    ],
    "wof:name":"Oberhofen",
    "wof:placetype":"neighbourhood"
},
  "geometry": {"coordinates":[9.53748,49.16066],"type":"Point"}
}