{
  "type": "Feature",
  "properties": {
    "gn:admin1_code":"14",
    "gn:admin2_code":"0.0",
    "gn:admin3_code":"15088.0",
    "gn:admin4_code":"15088205.0",
    "gn:asciiname":"Goehren",
    "gn:country_code":"DE",
    "gn:dem":98,
    "gn:feature_class":"P",
    "gn:feature_code":"PPL",
    "gn:name":"G\u00f6hren",
    "gn:population":0,
    "gn:timezone":"Europe/Berlin",
    "iso:country":"DE",
    "wof:name":"Goehren",
    "wof:placetype":"neighbourhood"
},
  "geometry": {"coordinates":[12.13645,51.35406],"type":"Point"}
}