{
  "type": "Feature",
  "properties": {
    "gn:admin1_code":"14",
    "gn:admin2_code":"0.0",
    "gn:admin3_code":"15084.0",
    "gn:admin4_code":"15084341.0",
    "gn:asciiname":"Sieglitz",
    "gn:country_code":"DE",
    "gn:dem":243,
    "gn:feature_class":"P",
    "gn:feature_code":"PPL",
    "gn:name":"Sieglitz",
    "gn:population":0,
    "gn:timezone":"Europe/Berlin",
    "iso:country":"DE",
    "name:deu_x_preferred":[
        "Sieglitz"
    ],
    "wof:name":"Sieglitz",
    "wof:placetype":"neighbourhood"
},
  "geometry": {"coordinates":[11.75647,51.0649],"type":"Point"}
}