{
  "type": "Feature",
  "properties": {
    "gn:country":"DE",
    "gn:fcode":"PPL",
    "gn:population":0,
    "iso:country":"DE",
    "name:ceb_x_preferred":[
        "Ziegenhain"
    ],
    "name:deu_x_preferred":[
        "Ziegenhain"
    ],
    "name:epo_x_preferred":[
        "Ziegenhain"
    ],
    "name:eus_x_preferred":[
        "Ziegenhain"
    ],
    "name:fas_x_preferred":[
        "\u062a\u0633\u06cc\u06af\u0646\u0647\u0627\u06cc\u0646"
    ],
    "name:fra_x_preferred":[
        "Ziegenhain"
    ],
    "name:hun_x_preferred":[
        "Ziegenhain"
    ],
    "name:ita_x_preferred":[
        "Ziegenhain"
    ],
    "name:msa_x_preferred":[
        "Ziegenhain"
    ],
    "name:nld_x_preferred":[
        "Ziegenhain"
    ],
    "name:pol_x_preferred":[
        "Ziegenhain"
    ],
    "name:por_x_preferred":[
        "Ziegenhain"
    ],
    "name:ron_x_preferred":[
        "Ziegenhain"
    ],
    "name:rus_x_preferred":[
        "\u0426\u0438\u0433\u0435\u043d\u0445\u0430\u0439\u043d"
    ],
    "name:spa_x_preferred":[
        "Ziegenhain"
    ],
    "name:srp_x_preferred":[
        "\u0426\u0438\u0433\u0435\u043d\u0445\u0430\u0458\u043d"
    ],
    "name:ukr_x_preferred":[
        "\u0426\u0438\u0433\u0435\u043d\u0433\u0430\u0439\u043d"
    ],
    "name:uzb_x_preferred":[
        "Ziegenhain"
    ],
    "name:vie_x_preferred":[
        "Ziegenhain"
    ],
    "name:vol_x_preferred":[
        "Ziegenhain"
    ],
    "name:war_x_preferred":[
        "Ziegenhain"
    ],
    "name:zho_x_preferred":[
        "\u9f50\u6839\u6d77\u6069"
    ],
    "qs_pg:aaroncc":"DE",
    "qs_pg:gn_country":"DE",
    "qs_pg:gn_fcode":"PPL",
    "qs_pg:gn_pop":0,
    "qs_pg:name":"Ziegenhain",
    "qs_pg:name_adm0":"Deutschland",
    "qs_pg:name_adm1":"Th\u00fcringen",
    "qs_pg:photos":535,
    "qs_pg:photos_1k":108,
    "qs_pg:photos_9k":2,
    "qs_pg:photos_9r":5,
    "qs_pg:photos_all":535,
    "qs_pg:photos_sr":7,
    "qs_pg:pop_sr":0,
    "qs_pg:qs_pg_placetype":"locality",
    "qs_pg:qs_pg_placetype_gp":"Town",
    "qs_pg:woe_adm0":23424829,
    "woe:adm0_id":23424829,
    "woe:name_adm0":"Deutschland",
    "woe:name_adm1":"Th\u00fcringen",
    "woe:placetype":"Town",
    "wof:name":"Ziegenhain",
    "wof:placetype":"neighbourhood"
},
  "geometry": {"coordinates":[11.62495,50.91961],"type":"Point"}
}