{
  "type": "Feature",
  "properties": {
    "gn:country":"DE",
    "gn:fcode":"PPL",
    "gn:population":0,
    "iso:country":"DE",
    "qs_pg:aaroncc":"DE",
    "qs_pg:gn_country":"DE",
    "qs_pg:gn_fcode":"PPL",
    "qs_pg:gn_pop":0,
    "qs_pg:name":"Walddrehna",
    "qs_pg:name_adm0":"Deutschland",
    "qs_pg:name_adm1":"Bundesland Brandenburg",
    "qs_pg:photos":45,
    "qs_pg:photos_1k":9,
    "qs_pg:photos_9k":1,
    "qs_pg:photos_9r":2,
    "qs_pg:photos_all":45,
    "qs_pg:photos_sr":2,
    "qs_pg:pop_sr":0,
    "qs_pg:qs_pg_placetype":"locality",
    "qs_pg:qs_pg_placetype_gp":"Town",
    "qs_pg:woe_adm0":23424829,
    "woe:adm0_id":23424829,
    "woe:name_adm0":"Deutschland",
    "woe:name_adm1":"Bundesland Brandenburg",
    "woe:placetype":"Town",
    "wof:name":"Walddrehna",
    "wof:placetype":"neighbourhood"
},
  "geometry": {"coordinates":[13.62693,51.77783],"type":"Point"}
}