{
  "type": "Feature",
  "properties": {
    "gn:admin1_code":"2",
    "gn:admin2_code":"91.0",
    "gn:admin3_code":"9190.0",
    "gn:admin4_code":"9190113.0",
    "gn:asciiname":"Neuried",
    "gn:country_code":"DE",
    "gn:dem":665,
    "gn:feature_class":"P",
    "gn:feature_code":"PPL",
    "gn:name":"Neuried",
    "gn:population":0,
    "gn:timezone":"Europe/Berlin",
    "iso:country":"DE",
    "name:als_x_preferred":[
        "Neuried"
    ],
    "name:ceb_x_preferred":[
        "Neuried"
    ],
    "name:deu_x_preferred":[
        "Neuried"
    ],
    "name:epo_x_preferred":[
        "Neuried"
    ],
    "name:eus_x_preferred":[
        "Neuried"
    ],
    "name:fas_x_preferred":[
        "\u0646\u0627\u0648\u06cc\u0631\u0627\u06cc\u062f"
    ],
    "name:fra_x_preferred":[
        "Neuried"
    ],
    "name:hun_x_preferred":[
        "Neuried"
    ],
    "name:ita_x_preferred":[
        "Neuried"
    ],
    "name:lat_x_preferred":[
        "Neuried"
    ],
    "name:lmo_x_preferred":[
        "Neuried"
    ],
    "name:msa_x_preferred":[
        "Neuried"
    ],
    "name:nld_x_preferred":[
        "Neuried"
    ],
    "name:pol_x_preferred":[
        "Neuried"
    ],
    "name:por_x_preferred":[
        "Neuried"
    ],
    "name:ron_x_preferred":[
        "Neuried"
    ],
    "name:rus_x_preferred":[
        "\u041d\u043e\u0439\u0440\u0438\u0434"
    ],
    "name:spa_x_preferred":[
        "Neuried"
    ],
    "name:srp_x_preferred":[
        "\u041d\u043e\u0458\u0440\u0438\u0434"
    ],
    "name:swe_x_preferred":[
        "Neuried"
    ],
    "name:ukr_x_preferred":[
        "\u041d\u043e\u0439\u0440\u0456\u0434"
    ],
    "name:uzb_x_preferred":[
        "Neuried"
    ],
    "name:vie_x_preferred":[
        "Neuried"
    ],
    "name:vol_x_preferred":[
        "Neuried"
    ],
    "name:war_x_preferred":[
        "Neuried"
    ],
    "name:zho_x_preferred":[
        "\u8bfa\u4f0a\u91cc\u5fb7"
    ],
    "wof:name":"Neuried",
    "wof:placetype":"neighbourhood"
},
  "geometry": {"coordinates":[11.27636,47.7782],"type":"Point"}
}