{
  "type": "Feature",
  "properties": {
    "iso:country":"DE",
    "name:als_x_preferred":[
        "Urbach"
    ],
    "name:ceb_x_preferred":[
        "Urbach"
    ],
    "name:deu_x_preferred":[
        "Urbach"
    ],
    "name:epo_x_preferred":[
        "Urbach"
    ],
    "name:fra_x_preferred":[
        "Urbach"
    ],
    "name:heb_x_preferred":[
        "\u05d0\u05d5\u05e8\u05d1\u05da"
    ],
    "name:ita_x_preferred":[
        "Urbach"
    ],
    "name:jpn_x_preferred":[
        "\u30a6\u30eb\u30d0\u30c3\u30cf"
    ],
    "name:nld_x_preferred":[
        "Urbach"
    ],
    "name:pol_x_preferred":[
        "Urbach"
    ],
    "name:por_x_preferred":[
        "Urbach"
    ],
    "name:rus_x_preferred":[
        "\u0423\u0440\u0431\u0430\u0445"
    ],
    "name:swe_x_preferred":[
        "Urbach"
    ],
    "name:vol_x_preferred":[
        "Urbach"
    ],
    "wof:name":"Urbach",
    "wof:placetype":"neighbourhood"
},
  "geometry": {"coordinates":[7.08217305247784,50.88127543139036],"type":"Point"}
}