{
  "type": "Feature",
  "properties": {
    "gn:admin1_code":"12.0",
    "gn:admin2_code":"0.0",
    "gn:admin3_code":"13073.0",
    "gn:admin4_code":"13073073.0",
    "gn:asciiname":"Bessin",
    "gn:country_code":"DE",
    "gn:dem":8,
    "gn:feature_class":"P",
    "gn:feature_code":"PPL",
    "gn:name":"Bessin",
    "gn:population":0,
    "gn:timezone":"Europe/Berlin",
    "iso:country":"DE",
    "name:bar_x_preferred":[
        "Bessin"
    ],
    "name:bre_x_preferred":[
        "Bessin"
    ],
    "name:deu_x_preferred":[
        "Bessin"
    ],
    "name:fra_x_preferred":[
        "Bessin"
    ],
    "name:nld_x_preferred":[
        "Bessin"
    ],
    "name:nor_x_preferred":[
        "Bessin"
    ],
    "name:pol_x_preferred":[
        "Bessin"
    ],
    "name:rus_x_preferred":[
        "\u0411\u0435\u0441\u0441\u0435\u043d"
    ],
    "name:spa_x_preferred":[
        "Bessin"
    ],
    "wof:name":"Bessin",
    "wof:placetype":"neighbourhood"
},
  "geometry": {"coordinates":[13.14824,54.36351],"type":"Point"}
}