{
  "type": "Feature",
  "properties": {
    "gn:admin1_code":"13",
    "gn:admin2_code":"0.0",
    "gn:admin3_code":"14521.0",
    "gn:admin4_code":"14521560.0",
    "gn:asciiname":"Siebensaeure",
    "gn:country_code":"DE",
    "gn:dem":824,
    "gn:feature_class":"P",
    "gn:feature_code":"PPL",
    "gn:name":"Siebens\u00e4ure",
    "gn:population":0,
    "gn:timezone":"Europe/Berlin",
    "iso:country":"DE",
    "wof:name":"Siebensaeure",
    "wof:placetype":"neighbourhood"
},
  "geometry": {"coordinates":[12.94884,50.47527],"type":"Point"}
}