{
  "type": "Feature",
  "properties": {
    "gn:admin1_code":"7",
    "gn:admin2_code":"53.0",
    "gn:admin3_code":"5378.0",
    "gn:admin4_code":"5378012.0",
    "gn:asciiname":"Keller",
    "gn:country_code":"DE",
    "gn:dem":171,
    "gn:feature_class":"P",
    "gn:feature_code":"PPL",
    "gn:name":"Keller",
    "gn:population":0,
    "gn:timezone":"Europe/Berlin",
    "iso:country":"DE",
    "name:bre_x_preferred":[
        "Keller"
    ],
    "name:cat_x_preferred":[
        "Keller"
    ],
    "name:ceb_x_preferred":[
        "Keller"
    ],
    "name:ces_x_preferred":[
        "Keller"
    ],
    "name:deu_x_preferred":[
        "Keller"
    ],
    "name:epo_x_preferred":[
        "Keller"
    ],
    "name:fin_x_preferred":[
        "Keller"
    ],
    "name:fra_x_preferred":[
        "Keller"
    ],
    "name:heb_x_preferred":[
        "\u05e7\u05dc\u05e8"
    ],
    "name:hun_x_preferred":[
        "Keller"
    ],
    "name:ita_x_preferred":[
        "Keller"
    ],
    "name:jpn_x_preferred":[
        "\u30b1\u30e9\u30fc"
    ],
    "name:nld_x_preferred":[
        "Keller"
    ],
    "name:pol_x_preferred":[
        "Keller"
    ],
    "name:por_x_preferred":[
        "Keller"
    ],
    "name:rus_x_preferred":[
        "\u041a\u0435\u043b\u043b\u0435\u0440"
    ],
    "name:slk_x_preferred":[
        "Keller"
    ],
    "name:spa_x_preferred":[
        "Keller"
    ],
    "name:swe_x_preferred":[
        "Keller"
    ],
    "name:ukr_x_preferred":[
        "\u041a\u0435\u043b\u043b\u0435\u0440"
    ],
    "name:vol_x_preferred":[
        "Keller"
    ],
    "wof:name":"Keller",
    "wof:placetype":"neighbourhood"
},
  "geometry": {"coordinates":[7.2156,51.0034],"type":"Point"}
}