{
  "type": "Feature",
  "properties": {
    "gn:admin1_code":"8.0",
    "gn:admin2_code":"00",
    "gn:admin3_code":"7138.0",
    "gn:admin4_code":"7138044.0",
    "gn:asciiname":"Woelsreeg",
    "gn:country_code":"DE",
    "gn:dem":174,
    "gn:feature_class":"P",
    "gn:feature_code":"PPL",
    "gn:name":"W\u00f6lsreeg",
    "gn:population":0,
    "gn:timezone":"Europe/Berlin",
    "iso:country":"DE",
    "wof:name":"Woelsreeg",
    "wof:placetype":"neighbourhood"
},
  "geometry": {"coordinates":[7.39611,50.62079],"type":"Point"}
}