{
  "type": "Feature",
  "properties": {
    "gn:country":"DE",
    "gn:fcode":"PPL",
    "gn:population":868,
    "iso:country":"DE",
    "name:deu_x_preferred":[
        "Wust"
    ],
    "name:nds_x_preferred":[
        "Wust"
    ],
    "name:nld_x_preferred":[
        "Wust"
    ],
    "name:pol_x_preferred":[
        "Wust"
    ],
    "qs_pg:aaroncc":"DE",
    "qs_pg:gn_country":"DE",
    "qs_pg:gn_fcode":"PPL",
    "qs_pg:gn_pop":868,
    "qs_pg:name":"Wust",
    "qs_pg:name_adm0":"Deutschland",
    "qs_pg:name_adm1":"Sachsen-Anhalt",
    "qs_pg:photos_9k":1,
    "qs_pg:photos_9r":1,
    "qs_pg:photos_all":5,
    "qs_pg:photos_sr":0,
    "qs_pg:pop_sr":2,
    "qs_pg:qs_pg_placetype":"locality",
    "qs_pg:qs_pg_placetype_gp":"Town",
    "qs_pg:woe_adm0":23424829,
    "woe:adm0_id":23424829,
    "woe:name_adm0":"Deutschland",
    "woe:name_adm1":"Sachsen-Anhalt",
    "woe:placetype":"Town",
    "wof:name":"Wust",
    "wof:placetype":"neighbourhood",
    "wof:population":868
},
  "geometry": {"coordinates":[12.11421,52.55153],"type":"Point"}
}