{
  "type": "Feature",
  "properties": {
    "gn:admin1_code":"7",
    "gn:admin2_code":"55.0",
    "gn:admin3_code":"5554.0",
    "gn:admin4_code":"5554056.0",
    "gn:asciiname":"Hengeler-Wendfeld",
    "gn:country_code":"DE",
    "gn:dem":56,
    "gn:feature_class":"P",
    "gn:feature_code":"PPL",
    "gn:name":"Hengeler-Wendfeld",
    "gn:population":0,
    "gn:timezone":"Europe/Berlin",
    "iso:country":"DE",
    "wof:name":"Hengeler-Wendfeld",
    "wof:placetype":"neighbourhood"
},
  "geometry": {"coordinates":[6.91667,52.01667],"type":"Point"}
}