{
  "type": "Feature",
  "properties": {
    "gn:admin1_code":"11.0",
    "gn:admin2_code":"0.0",
    "gn:admin3_code":"12064.0",
    "gn:admin4_code":"12064393.0",
    "gn:asciiname":"Biesow",
    "gn:country_code":"DE",
    "gn:dem":107,
    "gn:feature_class":"P",
    "gn:feature_code":"PPL",
    "gn:name":"Biesow",
    "gn:population":0,
    "gn:timezone":"Europe/Berlin",
    "iso:country":"DE",
    "wof:name":"Biesow",
    "wof:placetype":"neighbourhood"
},
  "geometry": {"coordinates":[13.92781,52.68056],"type":"Point"}
}