{
  "type": "Feature",
  "properties": {
    "gn:admin1_code":"13",
    "gn:asciiname":"Quingenberg",
    "gn:country_code":"DE",
    "gn:dem":367,
    "gn:feature_class":"P",
    "gn:feature_code":"PPL",
    "gn:name":"Quingenberg",
    "gn:population":0,
    "gn:timezone":"Europe/Berlin",
    "iso:country":"DE",
    "wof:name":"Quingenberg",
    "wof:placetype":"neighbourhood"
},
  "geometry": {"coordinates":[11.96793,50.6664],"type":"Point"}
}