{
  "type": "Feature",
  "properties": {
    "gn:admin1_code":"6",
    "gn:admin2_code":"0.0",
    "gn:admin3_code":"3256.0",
    "gn:admin4_code":"3256026.0",
    "gn:asciiname":"Neudorf",
    "gn:country_code":"DE",
    "gn:dem":26,
    "gn:feature_class":"P",
    "gn:feature_code":"PPL",
    "gn:name":"Neudorf",
    "gn:population":0,
    "gn:timezone":"Europe/Berlin",
    "iso:country":"DE",
    "name:als_x_preferred":[
        "Neudorf"
    ],
    "name:ceb_x_preferred":[
        "Neudorf"
    ],
    "name:ces_x_preferred":[
        "Neudorf"
    ],
    "name:deu_x_preferred":[
        "Neudorf"
    ],
    "name:epo_x_preferred":[
        "Neudorf"
    ],
    "name:fra_x_preferred":[
        "Neudorf"
    ],
    "name:ita_x_preferred":[
        "Neudorf"
    ],
    "name:nld_x_preferred":[
        "Neudorf"
    ],
    "name:pol_x_preferred":[
        "Neudorf"
    ],
    "name:ron_x_preferred":[
        "Neudorf"
    ],
    "name:rus_x_preferred":[
        "\u041d\u043e\u0439\u0434\u043e\u0440\u0444"
    ],
    "name:slk_x_preferred":[
        "Neudorf"
    ],
    "name:swe_x_preferred":[
        "Neudorf"
    ],
    "name:ukr_x_preferred":[
        "\u041d\u043e\u0439\u0434\u043e\u0440\u0444"
    ],
    "name:vol_x_preferred":[
        "Neudorf"
    ],
    "wof:name":"Neudorf",
    "wof:placetype":"neighbourhood"
},
  "geometry": {"coordinates":[9.48566,52.69657],"type":"Point"}
}