{
  "type": "Feature",
  "properties": {
    "iso:country":"DE",
    "wof:name":"Schwarzrheindorf-Vilich-Rheindorf",
    "wof:placetype":"neighbourhood"
},
  "geometry": {"coordinates":[7.11281462368141,50.75154292781701],"type":"Point"}
}