{
  "type": "Feature",
  "properties": {
    "gn:admin1_code":"2",
    "gn:admin2_code":"93.0",
    "gn:admin3_code":"9372.0",
    "gn:admin4_code":"9372137.0",
    "gn:asciiname":"Harras",
    "gn:country_code":"DE",
    "gn:dem":397,
    "gn:feature_class":"P",
    "gn:feature_code":"PPL",
    "gn:name":"Harras",
    "gn:population":0,
    "gn:timezone":"Europe/Berlin",
    "iso:country":"DE",
    "name:fra_x_preferred":[
        "Harras"
    ],
    "wof:name":"Harras",
    "wof:placetype":"neighbourhood"
},
  "geometry": {"coordinates":[12.83778,49.17256],"type":"Point"}
}