{
  "type": "Feature",
  "properties": {
    "iso:country":"DE",
    "name:deu_x_preferred":[
        "Dreik\u00f6nigenviertel"
    ],
    "wof:name":"Dreikoenigenviertel",
    "wof:placetype":"neighbourhood"
},
  "geometry": {"coordinates":[6.68954950050044,51.18925854210572],"type":"Point"}
}