{
  "type": "Feature",
  "properties": {
    "gn:admin1_code":"2",
    "gn:admin2_code":"91.0",
    "gn:admin3_code":"9177.0",
    "gn:admin4_code":"9177137.0",
    "gn:asciiname":"Schonfleck",
    "gn:country_code":"DE",
    "gn:dem":568,
    "gn:feature_class":"P",
    "gn:feature_code":"PPL",
    "gn:name":"Sch\u00f6nfleck",
    "gn:population":0,
    "gn:timezone":"Europe/Berlin",
    "iso:country":"DE",
    "wof:name":"Schonfleck",
    "wof:placetype":"neighbourhood"
},
  "geometry": {"coordinates":[12.12398,48.22711],"type":"Point"}
}