{
  "type": "Feature",
  "properties": {
    "gn:admin1_code":"1",
    "gn:admin2_code":"84.0",
    "gn:admin3_code":"8436.0",
    "gn:admin4_code":"8436010.0",
    "gn:asciiname":"Oberschwarzach",
    "gn:country_code":"DE",
    "gn:dem":736,
    "gn:feature_class":"P",
    "gn:feature_code":"PPL",
    "gn:name":"Oberschwarzach",
    "gn:population":0,
    "gn:timezone":"Europe/Berlin",
    "iso:country":"DE",
    "name:ceb_x_preferred":[
        "Oberschwarzach"
    ],
    "name:deu_x_preferred":[
        "Oberschwarzach"
    ],
    "name:epo_x_preferred":[
        "Oberschwarzach"
    ],
    "name:eus_x_preferred":[
        "Oberschwarzach"
    ],
    "name:fas_x_preferred":[
        "\u0627\u0648\u0628\u0631\u0634\u0648\u0627\u0631\u062a\u0633\u0627\u062e"
    ],
    "name:fra_x_preferred":[
        "Oberschwarzach"
    ],
    "name:hun_x_preferred":[
        "Oberschwarzach"
    ],
    "name:hye_x_preferred":[
        "\u0555\u0562\u0565\u0580\u0577\u057e\u0561\u0580\u0581\u0561\u056d"
    ],
    "name:ita_x_preferred":[
        "Oberschwarzach"
    ],
    "name:kaz_x_preferred":[
        "\u041e\u0431\u0435\u0440\u0448\u0432\u0430\u0440\u0446\u0430\u0445"
    ],
    "name:kir_x_preferred":[
        "\u041e\u0431\u0435\u0440\u0448\u0432\u0430\u0440\u0446\u0430\u0445"
    ],
    "name:lmo_x_preferred":[
        "Oberschwarzach"
    ],
    "name:msa_x_preferred":[
        "Oberschwarzach"
    ],
    "name:nld_x_preferred":[
        "Oberschwarzach"
    ],
    "name:pol_x_preferred":[
        "Oberschwarzach"
    ],
    "name:ron_x_preferred":[
        "Oberschwarzach"
    ],
    "name:rus_x_preferred":[
        "\u041e\u0431\u0435\u0440\u0448\u0432\u0430\u0440\u0446\u0430\u0445"
    ],
    "name:spa_x_preferred":[
        "Oberschwarzach"
    ],
    "name:srp_x_preferred":[
        "\u041e\u0431\u0435\u0440\u0448\u0432\u0430\u0440\u0446\u0430\u0445"
    ],
    "name:ukr_x_preferred":[
        "\u041e\u0431\u0435\u0440\u0448\u0432\u0430\u0440\u0446\u0430\u0445"
    ],
    "name:uzb_x_preferred":[
        "Oberschwarzach"
    ],
    "name:vie_x_preferred":[
        "Oberschwarzach"
    ],
    "name:vol_x_preferred":[
        "Oberschwarzach"
    ],
    "name:war_x_preferred":[
        "Oberschwarzach"
    ],
    "name:zho_x_preferred":[
        "\u4e0a\u65bd\u74e6\u5c14\u5bdf\u8d6b"
    ],
    "wof:name":"Oberschwarzach",
    "wof:placetype":"neighbourhood"
},
  "geometry": {"coordinates":[9.88972,47.9598],"type":"Point"}
}