{
  "type": "Feature",
  "properties": {
    "gn:admin1_code":"7",
    "gn:admin2_code":"57.0",
    "gn:admin3_code":"5754.0",
    "gn:admin4_code":"5754048.0",
    "gn:asciiname":"Stockheim",
    "gn:country_code":"DE",
    "gn:dem":74,
    "gn:feature_class":"P",
    "gn:feature_code":"PPLL",
    "gn:name":"Stockheim",
    "gn:population":0,
    "gn:timezone":"Europe/Berlin",
    "iso:country":"DE",
    "name:ara_x_preferred":[
        "\u0634\u062a\u0648\u0643\u0647\u0622\u064a\u0645"
    ],
    "name:dan_x_preferred":[
        "Stockheim"
    ],
    "name:deu_x_preferred":[
        "Stockheim"
    ],
    "name:epo_x_preferred":[
        "Stockheim"
    ],
    "name:eus_x_preferred":[
        "Stockheim"
    ],
    "name:fas_x_preferred":[
        "\u0634\u062a\u0648\u06a9\u0647\u0627\u06cc\u0645"
    ],
    "name:fra_x_preferred":[
        "Stockheim"
    ],
    "name:hun_x_preferred":[
        "Stockheim"
    ],
    "name:hye_x_preferred":[
        "\u0547\u0569\u0578\u056f\u0570\u0561\u0575\u0574"
    ],
    "name:ita_x_preferred":[
        "Stockheim"
    ],
    "name:jpn_x_preferred":[
        "\u30b7\u30e5\u30c8\u30c3\u30af\u30cf\u30a4\u30e0"
    ],
    "name:kaz_x_preferred":[
        "\u0428\u0442\u043e\u043a\u0445\u0430\u0439\u043c"
    ],
    "name:lmo_x_preferred":[
        "Stockheim"
    ],
    "name:msa_x_preferred":[
        "Stockheim"
    ],
    "name:nld_x_preferred":[
        "Stockheim"
    ],
    "name:pol_x_preferred":[
        "Stockheim"
    ],
    "name:por_x_preferred":[
        "Stockheim"
    ],
    "name:ron_x_preferred":[
        "Stockheim"
    ],
    "name:rus_x_preferred":[
        "\u0428\u0442\u043e\u043a\u043a\u0445\u0430\u0439\u043c"
    ],
    "name:spa_x_preferred":[
        "Stockheim"
    ],
    "name:srp_x_preferred":[
        "\u0428\u0442\u043e\u043a\u0445\u0430\u0458\u043c"
    ],
    "name:tur_x_preferred":[
        "Stockheim"
    ],
    "name:ukr_x_preferred":[
        "\u0428\u0442\u043e\u043a\u0433\u0430\u0439\u043c"
    ],
    "name:uzb_x_preferred":[
        "Stockheim"
    ],
    "name:vie_x_preferred":[
        "Stockheim"
    ],
    "name:war_x_preferred":[
        "Stockheim"
    ],
    "name:zho_x_preferred":[
        "\u65bd\u6258\u514b\u6d77\u59c6"
    ],
    "wof:name":"Stockheim",
    "wof:placetype":"neighbourhood"
},
  "geometry": {"coordinates":[8.18421,52.06153],"type":"Point"}
}