{
  "type": "Feature",
  "properties": {
    "gn:admin1_code":"13",
    "gn:admin2_code":"0.0",
    "gn:admin3_code":"14625.0",
    "gn:admin4_code":"14625430.0",
    "gn:asciiname":"Gruenberg",
    "gn:country_code":"DE",
    "gn:dem":180,
    "gn:feature_class":"P",
    "gn:feature_code":"PPL",
    "gn:name":"Gr\u00fcnberg",
    "gn:population":0,
    "gn:timezone":"Europe/Berlin",
    "iso:country":"DE",
    "wof:name":"Gruenberg",
    "wof:placetype":"neighbourhood"
},
  "geometry": {"coordinates":[13.84285,51.16408],"type":"Point"}
}