{
  "type": "Feature",
  "properties": {
    "iso:country":"DE",
    "wof:name":"Zschachwitz",
    "wof:placetype":"neighbourhood"
},
  "geometry": {"coordinates":[13.84598092035975,51.00624802298259],"type":"Point"}
}