{
  "type": "Feature",
  "properties": {
    "gn:country":"DE",
    "gn:fcode":"PPL",
    "gn:population":0,
    "iso:country":"DE",
    "name:ceb_x_preferred":[
        "L\u00fcerdissen"
    ],
    "name:dan_x_preferred":[
        "L\u00fcerdissen"
    ],
    "name:deu_x_preferred":[
        "L\u00fcerdissen"
    ],
    "name:epo_x_preferred":[
        "L\u00fcerdissen"
    ],
    "name:est_x_preferred":[
        "L\u00fcerdissen"
    ],
    "name:eus_x_preferred":[
        "L\u00fcerdissen"
    ],
    "name:fas_x_preferred":[
        "\u0644\u0648\u0631\u062f\u06cc\u0633\u0646"
    ],
    "name:fra_x_preferred":[
        "L\u00fcerdissen"
    ],
    "name:hun_x_preferred":[
        "L\u00fcerdissen"
    ],
    "name:ita_x_preferred":[
        "L\u00fcerdissen"
    ],
    "name:jpn_x_preferred":[
        "\u30ea\u30e5\u30fc\u30a2\u30fc\u30c7\u30a3\u30c3\u30bb\u30f3"
    ],
    "name:kaz_x_preferred":[
        "\u041b\u044e\u044d\u0440\u0434\u0438\u0441\u0441\u0435\u043d"
    ],
    "name:kir_x_preferred":[
        "\u041b\u044e\u044d\u0440\u0434\u0438\u0441\u0441\u0435\u043d"
    ],
    "name:lat_x_preferred":[
        "L\u00fcerdissen"
    ],
    "name:mkd_x_preferred":[
        "\u041b\u0438\u0440\u0434\u0438\u0441\u0435\u043d"
    ],
    "name:msa_x_preferred":[
        "L\u00fcerdissen"
    ],
    "name:nld_x_preferred":[
        "L\u00fcerdissen"
    ],
    "name:pol_x_preferred":[
        "L\u00fcerdissen"
    ],
    "name:por_x_preferred":[
        "L\u00fcerdissen"
    ],
    "name:ron_x_preferred":[
        "L\u00fcerdissen"
    ],
    "name:rus_x_preferred":[
        "\u041b\u044e\u044d\u0440\u0434\u0438\u0441\u0441\u0435\u043d"
    ],
    "name:spa_x_preferred":[
        "L\u00fcerdissen"
    ],
    "name:srp_x_preferred":[
        "\u041b\u0438\u0440\u0434\u0438\u0441\u0435\u043d"
    ],
    "name:ukr_x_preferred":[
        "\u041b\u044e\u0435\u0440\u0434\u0456\u0441\u0441\u0435\u043d"
    ],
    "name:uzb_x_preferred":[
        "L\u00fcerdissen"
    ],
    "name:vie_x_preferred":[
        "L\u00fcerdissen"
    ],
    "name:vol_x_preferred":[
        "L\u00fcerdissen"
    ],
    "name:war_x_preferred":[
        "L\u00fcerdissen"
    ],
    "name:zho_x_preferred":[
        "\u5415\u5c14\u8fea\u68ee"
    ],
    "qs_pg:aaroncc":"DE",
    "qs_pg:gn_country":"DE",
    "qs_pg:gn_fcode":"PPL",
    "qs_pg:gn_pop":0,
    "qs_pg:name":"L\u00fcerdissen",
    "qs_pg:name_adm0":"Deutschland",
    "qs_pg:name_adm1":"Nordrhein-Westfalen",
    "qs_pg:photos_9r":0,
    "qs_pg:photos_sr":0,
    "qs_pg:pop_sr":0,
    "qs_pg:qs_pg_placetype":"locality",
    "qs_pg:qs_pg_placetype_gp":"Town",
    "qs_pg:woe_adm0":23424829,
    "woe:adm0_id":23424829,
    "woe:name_adm0":"Deutschland",
    "woe:name_adm1":"Nordrhein-Westfalen",
    "woe:placetype":"Town",
    "wof:name":"L\u00fcerdissen",
    "wof:placetype":"neighbourhood"
},
  "geometry": {"coordinates":[8.93051,52.06125],"type":"Point"}
}