{
  "type": "Feature",
  "properties": {
    "gn:admin1_code":"15",
    "gn:admin2_code":"0.0",
    "gn:admin3_code":"16062.0",
    "gn:admin4_code":"16062041.0",
    "gn:asciiname":"Gumpe",
    "gn:country_code":"DE",
    "gn:dem":193,
    "gn:feature_class":"P",
    "gn:feature_code":"PPL",
    "gn:name":"Gumpe",
    "gn:population":0,
    "gn:timezone":"Europe/Berlin",
    "iso:country":"DE",
    "wof:name":"Gumpe",
    "wof:placetype":"neighbourhood"
},
  "geometry": {"coordinates":[10.78333,51.51667],"type":"Point"}
}