{
  "type": "Feature",
  "properties": {
    "gn:admin1_code":"2",
    "gn:admin2_code":"97.0",
    "gn:admin3_code":"9773.0",
    "gn:admin4_code":"9773144.0",
    "gn:asciiname":"Frauenriedhausen",
    "gn:country_code":"DE",
    "gn:dem":442,
    "gn:feature_class":"P",
    "gn:feature_code":"PPL",
    "gn:name":"Frauenriedhausen",
    "gn:population":0,
    "gn:timezone":"Europe/Berlin",
    "iso:country":"DE",
    "wof:name":"Frauenriedhausen",
    "wof:placetype":"neighbourhood"
},
  "geometry": {"coordinates":[10.40302,48.59705],"type":"Point"}
}