{
  "type": "Feature",
  "properties": {
    "gn:admin1_code":"1.0",
    "gn:admin2_code":"83.0",
    "gn:admin3_code":"8317.0",
    "gn:admin4_code":"8317093.0",
    "gn:asciiname":"Walke",
    "gn:country_code":"DE",
    "gn:dem":316,
    "gn:feature_class":"P",
    "gn:feature_code":"PPL",
    "gn:name":"Walke",
    "gn:population":0,
    "gn:timezone":"Europe/Berlin",
    "iso:country":"DE",
    "name:deu_x_preferred":[
        "Walke"
    ],
    "name:rus_x_preferred":[
        "\u0412\u0430\u043b\u044c\u043a\u0435"
    ],
    "wof:name":"Walke",
    "wof:placetype":"neighbourhood"
},
  "geometry": {"coordinates":[8.22609,48.34429],"type":"Point"}
}