{
  "type": "Feature",
  "properties": {
    "gn:admin1_code":"13",
    "gn:admin2_code":"0.0",
    "gn:admin3_code":"14628.0",
    "gn:admin4_code":"14628250.0",
    "gn:asciiname":"Haeselich",
    "gn:country_code":"DE",
    "gn:dem":223,
    "gn:feature_class":"P",
    "gn:feature_code":"PPL",
    "gn:name":"H\u00e4selich",
    "gn:population":0,
    "gn:timezone":"Europe/Berlin",
    "iso:country":"DE",
    "wof:name":"Haeselich",
    "wof:placetype":"neighbourhood"
},
  "geometry": {"coordinates":[13.81941,50.91259],"type":"Point"}
}