{
  "type": "Feature",
  "properties": {
    "gn:admin1_code":"2.0",
    "gn:admin2_code":"92.0",
    "gn:admin3_code":"9274.0",
    "gn:admin4_code":"9274156.0",
    "gn:asciiname":"Bergham",
    "gn:country_code":"DE",
    "gn:dem":484,
    "gn:feature_class":"P",
    "gn:feature_code":"PPLL",
    "gn:name":"Bergham",
    "gn:population":0,
    "gn:timezone":"Europe/Berlin",
    "iso:country":"DE",
    "wof:name":"Bergham",
    "wof:placetype":"neighbourhood"
},
  "geometry": {"coordinates":[12.34366,48.58762],"type":"Point"}
}