{
  "type": "Feature",
  "properties": {
    "gn:admin1_code":"15",
    "gn:admin2_code":"0.0",
    "gn:admin3_code":"16066.0",
    "gn:admin4_code":"16066093.0",
    "gn:asciiname":"Thurmgut",
    "gn:country_code":"DE",
    "gn:dem":353,
    "gn:feature_class":"P",
    "gn:feature_code":"PPL",
    "gn:name":"Thurmgut",
    "gn:population":0,
    "gn:timezone":"Europe/Berlin",
    "iso:country":"DE",
    "wof:name":"Thurmgut",
    "wof:placetype":"neighbourhood"
},
  "geometry": {"coordinates":[10.31886,50.51236],"type":"Point"}
}