{
  "type": "Feature",
  "properties": {
    "gn:admin1_code":"12",
    "gn:admin2_code":"0.0",
    "gn:admin3_code":"13074.0",
    "gn:admin4_code":"13074010.0",
    "gn:asciiname":"Tarnewitzer Kamp",
    "gn:country_code":"DE",
    "gn:dem":13,
    "gn:feature_class":"P",
    "gn:feature_code":"PPL",
    "gn:name":"Tarnewitzer Kamp",
    "gn:population":0,
    "gn:timezone":"Europe/Berlin",
    "iso:country":"DE",
    "wof:name":"Tarnewitzer Kamp",
    "wof:placetype":"neighbourhood"
},
  "geometry": {"coordinates":[11.23809,53.95576],"type":"Point"}
}