{
  "type": "Feature",
  "properties": {
    "gn:admin1_code":"15.0",
    "gn:admin2_code":"00",
    "gn:admin3_code":"16073.0",
    "gn:admin4_code":"16073036.0",
    "gn:asciiname":"Zollhaus",
    "gn:country_code":"DE",
    "gn:dem":371,
    "gn:feature_class":"P",
    "gn:feature_code":"PPL",
    "gn:name":"Zollhaus",
    "gn:population":0,
    "gn:timezone":"Europe/Berlin",
    "iso:country":"DE",
    "wof:name":"Zollhaus",
    "wof:placetype":"neighbourhood"
},
  "geometry": {"coordinates":[11.46364,50.64318],"type":"Point"}
}