{
  "type": "Feature",
  "properties": {
    "gn:admin1_code":"2",
    "gn:admin2_code":"92.0",
    "gn:admin3_code":"9277.0",
    "gn:admin4_code":"9277116.0",
    "gn:asciiname":"Niederndorf",
    "gn:country_code":"DE",
    "gn:dem":413,
    "gn:feature_class":"P",
    "gn:feature_code":"PPL",
    "gn:name":"Niederndorf",
    "gn:population":0,
    "gn:timezone":"Europe/Berlin",
    "iso:country":"DE",
    "name:deu_x_preferred":[
        "Niederndorf"
    ],
    "name:hun_x_preferred":[
        "Niederndorf"
    ],
    "name:ind_x_preferred":[
        "Niederndorf"
    ],
    "name:ita_x_preferred":[
        "Niederndorf"
    ],
    "name:pol_x_preferred":[
        "Niederndorf"
    ],
    "wof:name":"Niederndorf",
    "wof:placetype":"neighbourhood"
},
  "geometry": {"coordinates":[12.76121,48.38635],"type":"Point"}
}