{
  "type": "Feature",
  "properties": {
    "iso:country":"DE",
    "wof:name":"Philosophenviertel",
    "wof:placetype":"neighbourhood"
},
  "geometry": {"coordinates":[9.79502019584856,52.37005871524946],"type":"Point"}
}