{
  "type": "Feature",
  "properties": {
    "gn:admin1_code":"15",
    "gn:admin2_code":"0.0",
    "gn:admin3_code":"16073.0",
    "gn:admin4_code":"16073068.0",
    "gn:asciiname":"Goesselsdorf",
    "gn:country_code":"DE",
    "gn:dem":613,
    "gn:feature_class":"P",
    "gn:feature_code":"PPL",
    "gn:name":"G\u00f6sselsdorf",
    "gn:population":0,
    "gn:timezone":"Europe/Berlin",
    "iso:country":"DE",
    "wof:name":"Goesselsdorf",
    "wof:placetype":"neighbourhood"
},
  "geometry": {"coordinates":[11.28964,50.54423],"type":"Point"}
}