{
  "type": "Feature",
  "properties": {
    "gn:admin1_code":"15.0",
    "gn:admin2_code":"00",
    "gn:admin3_code":"16072.0",
    "gn:admin4_code":"16072023.0",
    "gn:asciiname":"Welchendorf",
    "gn:country_code":"DE",
    "gn:dem":403,
    "gn:feature_class":"P",
    "gn:feature_code":"PPL",
    "gn:name":"Welchendorf",
    "gn:population":0,
    "gn:timezone":"Europe/Berlin",
    "iso:country":"DE",
    "wof:name":"Welchendorf",
    "wof:placetype":"neighbourhood"
},
  "geometry": {"coordinates":[11.0538,50.38663],"type":"Point"}
}