{
  "type": "Feature",
  "properties": {
    "gn:admin1_code":"7",
    "gn:admin2_code":"51.0",
    "gn:admin3_code":"5166.0",
    "gn:admin4_code":"5166032.0",
    "gn:asciiname":"Waldnielerstrasse",
    "gn:country_code":"DE",
    "gn:dem":64,
    "gn:feature_class":"P",
    "gn:feature_code":"PPL",
    "gn:name":"Waldnielerstra\u00dfe",
    "gn:population":0,
    "gn:timezone":"Europe/Berlin",
    "iso:country":"DE",
    "wof:name":"Waldnielerstrasse",
    "wof:placetype":"neighbourhood"
},
  "geometry": {"coordinates":[6.31853,51.23807],"type":"Point"}
}