{
  "type": "Feature",
  "properties": {
    "gn:admin1_code":"6",
    "gn:admin2_code":"0.0",
    "gn:admin3_code":"3459.0",
    "gn:admin4_code":"3459003.0",
    "gn:asciiname":"Buescherheide",
    "gn:country_code":"DE",
    "gn:dem":182,
    "gn:feature_class":"P",
    "gn:feature_code":"PPL",
    "gn:name":"B\u00fcscherheide",
    "gn:population":0,
    "gn:timezone":"Europe/Berlin",
    "iso:country":"DE",
    "wof:name":"Buescherheide",
    "wof:placetype":"neighbourhood"
},
  "geometry": {"coordinates":[8.45692,52.27999000000001],"type":"Point"}
}