{
  "type": "Feature",
  "properties": {
    "gn:admin1_code":"2",
    "gn:admin2_code":"92.0",
    "gn:admin3_code":"9271.0",
    "gn:admin4_code":"9271141.0",
    "gn:asciiname":"Kirchdorf bei Osterhofen",
    "gn:country_code":"DE",
    "gn:dem":333,
    "gn:feature_class":"P",
    "gn:feature_code":"PPL",
    "gn:name":"Kirchdorf bei Osterhofen",
    "gn:population":0,
    "gn:timezone":"Europe/Berlin",
    "iso:country":"DE",
    "name:und_x_variant":[
        "Kirchdorf",
        "Kirchdorf bei Osterhofen"
    ],
    "wof:name":"Kirchdorf bei Osterhofen",
    "wof:placetype":"neighbourhood"
},
  "geometry": {"coordinates":[12.94638,48.68775],"type":"Point"}
}