{
  "type": "Feature",
  "properties": {
    "gn:admin1_code":"1.0",
    "gn:admin2_code":"84.0",
    "gn:admin3_code":"8417.0",
    "gn:admin4_code":"8417031.0",
    "gn:asciiname":"Beuren",
    "gn:country_code":"DE",
    "gn:dem":681,
    "gn:feature_class":"P",
    "gn:feature_code":"PPL",
    "gn:name":"Beuren",
    "gn:population":0,
    "gn:timezone":"Europe/Berlin",
    "iso:country":"DE",
    "name:ceb_x_preferred":[
        "Beuren"
    ],
    "name:deu_x_preferred":[
        "Beuren"
    ],
    "name:epo_x_preferred":[
        "Beuren"
    ],
    "name:eus_x_preferred":[
        "Beuren"
    ],
    "name:fra_x_preferred":[
        "Beuren"
    ],
    "name:ita_x_preferred":[
        "Beuren"
    ],
    "name:nld_x_preferred":[
        "Beuren"
    ],
    "name:pol_x_preferred":[
        "Beuren"
    ],
    "name:rus_x_preferred":[
        "\u0411\u043e\u0439\u0440\u0435\u043d"
    ],
    "name:swe_x_preferred":[
        "Beuren"
    ],
    "name:vol_x_preferred":[
        "Beuren"
    ],
    "wof:name":"Beuren",
    "wof:placetype":"neighbourhood"
},
  "geometry": {"coordinates":[9.03008,48.36329],"type":"Point"}
}