{
  "type": "Feature",
  "properties": {
    "gn:admin1_code":"15",
    "gn:admin2_code":"0.0",
    "gn:admin3_code":"16069.0",
    "gn:admin4_code":"16069012.0",
    "gn:asciiname":"Heid",
    "gn:country_code":"DE",
    "gn:dem":465,
    "gn:feature_class":"P",
    "gn:feature_code":"PPL",
    "gn:name":"Heid",
    "gn:population":0,
    "gn:timezone":"Europe/Berlin",
    "iso:country":"DE",
    "name:deu_x_preferred":[
        "Heid"
    ],
    "name:fra_x_preferred":[
        "Heid"
    ],
    "name:nds_x_preferred":[
        "Heid"
    ],
    "wof:name":"Heid",
    "wof:placetype":"neighbourhood"
},
  "geometry": {"coordinates":[10.94099,50.40008],"type":"Point"}
}