{
  "type": "Feature",
  "properties": {
    "iso:country":"DE",
    "name:deu_x_preferred":[
        "Lehndorf"
    ],
    "name:unk_x_variant":[
        "Lehndorf"
    ],
    "qs:gn_adm0_cc":"DE",
    "qs:gn_fcode":"PPLX",
    "qs:gn_local":2945024,
    "qs:gn_namadm1":"06",
    "qs:gn_name":"Lehndorf",
    "qs:local_max":1853,
    "qs:local_sum":10764,
    "qs:localhoods":34,
    "qs:name":"Lehndorf",
    "qs:name_adm0":"Deutschland",
    "qs:name_adm1":"Niedersachsen",
    "qs:name_adm2":"Stadtkreis Braunschweig",
    "qs:name_lau":"Stadtteil Westliches Ringgebiet",
    "qs:name_local":"Braunschweig",
    "qs:photo_max":13,
    "qs:photo_sum":32,
    "qs:placetype":"Suburb",
    "qs:quad_count":9,
    "qs:woe_adm0":23424829,
    "qs:woe_adm1":2345486,
    "qs:woe_adm2":12596719,
    "qs:woe_lau":26822024,
    "qs:woe_local":640831,
    "qs:woe_ver":"7.10.0",
    "wof:lang":[
        "ger"
    ],
    "wof:name":"Lehndorf",
    "wof:placetype":"neighbourhood"
},
  "geometry": {"coordinates":[10.483875,52.274462],"type":"Point"}
}