{
  "type": "Feature",
  "properties": {
    "gn:admin1_code":"2",
    "gn:admin2_code":"93.0",
    "gn:admin3_code":"9372.0",
    "gn:admin4_code":"9372150.0",
    "gn:asciiname":"Ebersroith",
    "gn:country_code":"DE",
    "gn:dem":608,
    "gn:feature_class":"P",
    "gn:feature_code":"PPL",
    "gn:name":"Ebersroith",
    "gn:population":0,
    "gn:timezone":"Europe/Berlin",
    "iso:country":"DE",
    "wof:name":"Ebersroith",
    "wof:placetype":"neighbourhood"
},
  "geometry": {"coordinates":[12.48494,49.06891],"type":"Point"}
}