{
  "type": "Feature",
  "properties": {
    "gn:admin1_code":"14.0",
    "gn:admin2_code":"00",
    "gn:admin3_code":"15084.0",
    "gn:admin4_code":"15084015.0",
    "gn:asciiname":"Wippach",
    "gn:country_code":"DE",
    "gn:dem":211,
    "gn:feature_class":"P",
    "gn:feature_code":"PPL",
    "gn:name":"Wippach",
    "gn:population":0,
    "gn:timezone":"Europe/Berlin",
    "iso:country":"DE",
    "wof:name":"Wippach",
    "wof:placetype":"neighbourhood"
},
  "geometry": {"coordinates":[11.56194,51.25165],"type":"Point"}
}