{
  "type": "Feature",
  "properties": {
    "gn:admin1_code":"8.0",
    "gn:admin2_code":"0.0",
    "gn:admin3_code":"7138.0",
    "gn:admin4_code":"7138070.0",
    "gn:asciiname":"Alberthofen",
    "gn:country_code":"DE",
    "gn:dem":230,
    "gn:feature_class":"P",
    "gn:feature_code":"PPL",
    "gn:name":"Alberthofen",
    "gn:population":0,
    "gn:timezone":"Europe/Berlin",
    "iso:country":"DE",
    "wof:name":"Alberthofen",
    "wof:placetype":"neighbourhood"
},
  "geometry": {"coordinates":[7.60644,50.62863],"type":"Point"}
}