{
  "type": "Feature",
  "properties": {
    "gn:admin1_code":"5",
    "gn:admin2_code":"64.0",
    "gn:admin3_code":"6435.0",
    "gn:admin4_code":"6435019.0",
    "gn:asciiname":"Eichenheege",
    "gn:country_code":"DE",
    "gn:dem":110,
    "gn:feature_class":"P",
    "gn:feature_code":"PPL",
    "gn:name":"Eichenheege",
    "gn:population":0,
    "gn:timezone":"Europe/Berlin",
    "iso:country":"DE",
    "wof:name":"Eichenheege",
    "wof:placetype":"neighbourhood"
},
  "geometry": {"coordinates":[8.85,50.15],"type":"Point"}
}