{
  "type": "Feature",
  "properties": {
    "gn:admin1_code":"10",
    "gn:admin2_code":"0.0",
    "gn:admin3_code":"1060.0",
    "gn:admin4_code":"1060075.0",
    "gn:asciiname":"Kuhlenbrook",
    "gn:country_code":"DE",
    "gn:dem":32,
    "gn:feature_class":"P",
    "gn:feature_code":"PPL",
    "gn:name":"Kuhlenbrook",
    "gn:population":0,
    "gn:timezone":"Europe/Berlin",
    "iso:country":"DE",
    "name:und_x_variant":[
        "Kuhlenbrok",
        "Kuhlenbrook"
    ],
    "wof:name":"Kuhlenbrook",
    "wof:placetype":"neighbourhood"
},
  "geometry": {"coordinates":[10.42595,54.06007],"type":"Point"}
}