{
  "type": "Feature",
  "properties": {
    "gn:admin1_code":"1",
    "gn:admin2_code":"83.0",
    "gn:admin3_code":"8317.0",
    "gn:admin4_code":"8317078.0",
    "gn:asciiname":"Fannis",
    "gn:country_code":"DE",
    "gn:dem":335,
    "gn:feature_class":"P",
    "gn:feature_code":"PPLL",
    "gn:name":"Fannis",
    "gn:population":0,
    "gn:timezone":"Europe/Berlin",
    "iso:country":"DE",
    "wof:name":"Fannis",
    "wof:placetype":"neighbourhood"
},
  "geometry": {"coordinates":[8.10064,48.23358],"type":"Point"}
}