{
  "type": "Feature",
  "properties": {
    "iso:country":"DE",
    "wof:name":"Postsiedlung",
    "wof:placetype":"neighbourhood"
},
  "geometry": {"coordinates":[8.62001277178033,50.11867044606322],"type":"Point"}
}