{
  "type": "Feature",
  "properties": {
    "gn:admin1_code":"2",
    "gn:admin2_code":"91.0",
    "gn:admin3_code":"9176.0",
    "gn:admin4_code":"9176112.0",
    "gn:asciiname":"Megmannsdorf",
    "gn:country_code":"DE",
    "gn:dem":516,
    "gn:feature_class":"P",
    "gn:feature_code":"PPL",
    "gn:name":"Megmannsdorf",
    "gn:population":0,
    "gn:timezone":"Europe/Berlin",
    "iso:country":"DE",
    "wof:name":"Megmannsdorf",
    "wof:placetype":"neighbourhood"
},
  "geometry": {"coordinates":[11.54706,48.93158],"type":"Point"}
}