{
  "type": "Feature",
  "properties": {
    "gn:admin1_code":"1",
    "gn:admin2_code":"81.0",
    "gn:admin3_code":"8136.0",
    "gn:admin4_code":"8136061.0",
    "gn:asciiname":"Steinenbach",
    "gn:country_code":"DE",
    "gn:dem":514,
    "gn:feature_class":"P",
    "gn:feature_code":"PPL",
    "gn:name":"Steinenbach",
    "gn:population":0,
    "gn:timezone":"Europe/Berlin",
    "iso:country":"DE",
    "wof:name":"Steinenbach",
    "wof:placetype":"neighbourhood"
},
  "geometry": {"coordinates":[9.82403,48.89692],"type":"Point"}
}