{
  "type": "Feature",
  "properties": {
    "gn:admin1_code":"7",
    "gn:admin2_code":"57.0",
    "gn:admin3_code":"5766.0",
    "gn:admin4_code":"5766024.0",
    "gn:asciiname":"Goettentrup",
    "gn:country_code":"DE",
    "gn:dem":173,
    "gn:feature_class":"P",
    "gn:feature_code":"PPL",
    "gn:name":"G\u00f6ttentrup",
    "gn:population":0,
    "gn:timezone":"Europe/Berlin",
    "iso:country":"DE",
    "wof:name":"Goettentrup",
    "wof:placetype":"neighbourhood"
},
  "geometry": {"coordinates":[9.0148,52.04489],"type":"Point"}
}