{
  "type": "Feature",
  "properties": {
    "gn:admin1_code":"13",
    "gn:admin2_code":"0.0",
    "gn:admin3_code":"14729.0",
    "gn:admin4_code":"14729160.0",
    "gn:asciiname":"Roda",
    "gn:country_code":"DE",
    "gn:dem":165,
    "gn:feature_class":"P",
    "gn:feature_code":"PPL",
    "gn:name":"Roda",
    "gn:population":0,
    "gn:timezone":"Europe/Berlin",
    "iso:country":"DE",
    "name:cat_x_preferred":[
        "Roda"
    ],
    "name:ceb_x_preferred":[
        "Roda"
    ],
    "name:deu_x_preferred":[
        "Roda"
    ],
    "name:heb_x_preferred":[
        "\u05e8\u05d5\u05d3\u05d4"
    ],
    "name:ita_x_preferred":[
        "Roda"
    ],
    "name:nld_x_preferred":[
        "Roda"
    ],
    "name:pol_x_preferred":[
        "Roda"
    ],
    "name:por_x_preferred":[
        "Roda"
    ],
    "name:rus_x_preferred":[
        "\u0420\u043e\u0434\u0430"
    ],
    "name:spa_x_preferred":[
        "Roda"
    ],
    "name:swe_x_preferred":[
        "Roda"
    ],
    "wof:name":"Roda",
    "wof:placetype":"neighbourhood"
},
  "geometry": {"coordinates":[12.87855,51.27437000000001],"type":"Point"}
}