{
  "type": "Feature",
  "properties": {
    "gn:admin1_code":"2",
    "gn:admin2_code":"91.0",
    "gn:admin3_code":"9183.0",
    "gn:admin4_code":"9183128.0",
    "gn:asciiname":"Ecksberg",
    "gn:country_code":"DE",
    "gn:dem":418,
    "gn:feature_class":"P",
    "gn:feature_code":"PPL",
    "gn:name":"Ecksberg",
    "gn:population":0,
    "gn:timezone":"Europe/Berlin",
    "iso:country":"DE",
    "wof:name":"Ecksberg",
    "wof:placetype":"neighbourhood"
},
  "geometry": {"coordinates":[12.47864,48.2443],"type":"Point"}
}