{
  "type": "Feature",
  "properties": {
    "gn:admin1_code":"2",
    "gn:admin2_code":"95.0",
    "gn:admin3_code":"9571.0",
    "gn:admin4_code":"9571174.0",
    "gn:asciiname":"Hinterholz",
    "gn:country_code":"DE",
    "gn:dem":502,
    "gn:feature_class":"P",
    "gn:feature_code":"PPL",
    "gn:name":"Hinterholz",
    "gn:population":0,
    "gn:timezone":"Europe/Berlin",
    "iso:country":"DE",
    "wof:name":"Hinterholz",
    "wof:placetype":"neighbourhood"
},
  "geometry": {"coordinates":[10.46524,49.32688],"type":"Point"}
}