{
  "type": "Feature",
  "properties": {
    "gn:admin1_code":"7",
    "gn:admin2_code":"55.0",
    "gn:admin3_code":"5570.0",
    "gn:admin4_code":"5570016.0",
    "gn:asciiname":"Rieth",
    "gn:country_code":"DE",
    "gn:dem":65,
    "gn:feature_class":"P",
    "gn:feature_code":"PPLL",
    "gn:name":"Rieth",
    "gn:population":0,
    "gn:timezone":"Europe/Berlin",
    "iso:country":"DE",
    "name:deu_x_preferred":[
        "Rieth"
    ],
    "name:pol_x_preferred":[
        "Rieth"
    ],
    "wof:name":"Rieth",
    "wof:placetype":"neighbourhood"
},
  "geometry": {"coordinates":[7.71662,51.78824],"type":"Point"}
}