{
  "type": "Feature",
  "properties": {
    "gn:admin1_code":"15.0",
    "gn:admin2_code":"0.0",
    "gn:admin3_code":"16070.0",
    "gn:admin4_code":"16070053.0",
    "gn:asciiname":"Branchewinda",
    "gn:country_code":"DE",
    "gn:dem":384,
    "gn:feature_class":"P",
    "gn:feature_code":"PPL",
    "gn:name":"Branchewinda",
    "gn:population":0,
    "gn:timezone":"Europe/Berlin",
    "iso:country":"DE",
    "wof:name":"Branchewinda",
    "wof:placetype":"neighbourhood"
},
  "geometry": {"coordinates":[10.99358,50.78644],"type":"Point"}
}