{
  "type": "Feature",
  "properties": {
    "gn:admin1_code":"13",
    "gn:admin2_code":"0.0",
    "gn:admin3_code":"14522.0",
    "gn:admin4_code":"14522450.0",
    "gn:asciiname":"Noschkowitz",
    "gn:country_code":"DE",
    "gn:dem":154,
    "gn:feature_class":"P",
    "gn:feature_code":"PPL",
    "gn:name":"Noschkowitz",
    "gn:population":0,
    "gn:timezone":"Europe/Berlin",
    "iso:country":"DE",
    "name:deu_x_preferred":[
        "Noschkowitz"
    ],
    "wof:name":"Noschkowitz",
    "wof:placetype":"neighbourhood"
},
  "geometry": {"coordinates":[13.13987,51.18935],"type":"Point"}
}