{
  "type": "Feature",
  "properties": {
    "gn:admin1_code":"7.0",
    "gn:admin2_code":"53.0",
    "gn:admin3_code":"5382.0",
    "gn:admin4_code":"5382024.0",
    "gn:asciiname":"Thomasberg",
    "gn:country_code":"DE",
    "gn:dem":221,
    "gn:feature_class":"P",
    "gn:feature_code":"PPL",
    "gn:name":"Thomasberg",
    "gn:population":0,
    "gn:timezone":"Europe/Berlin",
    "iso:country":"DE",
    "name:ceb_x_preferred":[
        "Thomasberg"
    ],
    "name:deu_x_preferred":[
        "Thomasberg"
    ],
    "name:epo_x_preferred":[
        "Thomasberg"
    ],
    "name:fas_x_preferred":[
        "\u062a\u0648\u0645\u0627\u0633\u0628\u0631\u06af"
    ],
    "name:fra_x_preferred":[
        "Thomasberg"
    ],
    "name:hun_x_preferred":[
        "Thomasberg"
    ],
    "name:ita_x_preferred":[
        "Thomasberg"
    ],
    "name:kaz_x_preferred":[
        "\u0422\u043e\u043c\u0430\u0441\u0431\u0435\u0440\u0433"
    ],
    "name:nld_x_preferred":[
        "Thomasberg"
    ],
    "name:nor_x_preferred":[
        "Thomasberg"
    ],
    "name:pol_x_preferred":[
        "Thomasberg"
    ],
    "name:por_x_preferred":[
        "Thomasberg"
    ],
    "name:rus_x_preferred":[
        "\u0422\u043e\u043c\u0430\u0441\u0431\u0435\u0440\u0433"
    ],
    "name:slk_x_preferred":[
        "Thomasberg"
    ],
    "name:spa_x_preferred":[
        "Thomasberg"
    ],
    "name:swe_x_preferred":[
        "Thomasberg"
    ],
    "name:uzb_x_preferred":[
        "Thomasberg"
    ],
    "name:vie_x_preferred":[
        "Thomasberg"
    ],
    "name:vol_x_preferred":[
        "Thomasberg"
    ],
    "name:war_x_preferred":[
        "Thomasberg"
    ],
    "name:zho_x_preferred":[
        "\u6258\u9a6c\u65af\u8d1d\u683c"
    ],
    "wof:name":"Thomasberg",
    "wof:placetype":"neighbourhood"
},
  "geometry": {"coordinates":[7.24411,50.69676],"type":"Point"}
}