{
  "type": "Feature",
  "properties": {
    "gn:admin1_code":"12",
    "gn:admin2_code":"0.0",
    "gn:admin3_code":"13076.0",
    "gn:admin4_code":"13076087.0",
    "gn:asciiname":"Neu Lueblow",
    "gn:country_code":"DE",
    "gn:dem":31,
    "gn:feature_class":"P",
    "gn:feature_code":"PPL",
    "gn:name":"Neu L\u00fcblow",
    "gn:population":0,
    "gn:timezone":"Europe/Berlin",
    "iso:country":"DE",
    "wof:name":"Neu Lueblow",
    "wof:placetype":"neighbourhood"
},
  "geometry": {"coordinates":[11.45658,53.3836],"type":"Point"}
}