{
  "type": "Feature",
  "properties": {
    "gn:admin1_code":"7",
    "gn:admin2_code":"59.0",
    "gn:admin3_code":"5915.0",
    "gn:admin4_code":"5915000.0",
    "gn:asciiname":"Oberallen",
    "gn:country_code":"DE",
    "gn:dem":88,
    "gn:feature_class":"P",
    "gn:feature_code":"PPLL",
    "gn:name":"Oberallen",
    "gn:population":0,
    "gn:timezone":"Europe/Berlin",
    "iso:country":"DE",
    "wof:name":"Oberallen",
    "wof:placetype":"neighbourhood"
},
  "geometry": {"coordinates":[7.86475,51.6178],"type":"Point"}
}