{
  "type": "Feature",
  "properties": {
    "gn:admin1_code":"2",
    "gn:admin2_code":"97.0",
    "gn:admin3_code":"9779.0",
    "gn:admin4_code":"9779181.0",
    "gn:asciiname":"Druisheim",
    "gn:country_code":"DE",
    "gn:dem":432,
    "gn:feature_class":"P",
    "gn:feature_code":"PPL",
    "gn:name":"Druisheim",
    "gn:population":0,
    "gn:timezone":"Europe/Berlin",
    "iso:country":"DE",
    "wof:name":"Druisheim",
    "wof:placetype":"neighbourhood"
},
  "geometry": {"coordinates":[10.81528,48.63444000000001],"type":"Point"}
}