{
  "type": "Feature",
  "properties": {
    "gn:admin1_code":"1",
    "gn:admin2_code":"84.0",
    "gn:admin3_code":"8435.0",
    "gn:admin4_code":"8435034.0",
    "gn:asciiname":"Stadel",
    "gn:country_code":"DE",
    "gn:dem":489,
    "gn:feature_class":"P",
    "gn:feature_code":"PPL",
    "gn:name":"Stadel",
    "gn:population":0,
    "gn:timezone":"Europe/Berlin",
    "iso:country":"DE",
    "name:ceb_x_preferred":[
        "Stadel"
    ],
    "name:deu_x_preferred":[
        "Stadel"
    ],
    "name:fra_x_preferred":[
        "Stadel"
    ],
    "name:ita_x_preferred":[
        "Stadel"
    ],
    "name:swe_x_preferred":[
        "Stadel"
    ],
    "wof:name":"Stadel",
    "wof:placetype":"neighbourhood"
},
  "geometry": {"coordinates":[9.44592,47.72948],"type":"Point"}
}