{
  "type": "Feature",
  "properties": {
    "gn:admin1_code":"10",
    "gn:admin2_code":"0.0",
    "gn:admin3_code":"1053.0",
    "gn:admin4_code":"1053097.0",
    "gn:asciiname":"Mannhagen",
    "gn:country_code":"DE",
    "gn:dem":47,
    "gn:feature_class":"P",
    "gn:feature_code":"PPL",
    "gn:name":"Mannhagen",
    "gn:population":0,
    "gn:timezone":"Europe/Berlin",
    "iso:country":"DE",
    "wof:name":"Mannhagen",
    "wof:placetype":"neighbourhood"
},
  "geometry": {"coordinates":[10.6136,53.64372],"type":"Point"}
}