{
  "type": "Feature",
  "properties": {
    "gn:admin1_code":"13",
    "gn:admin2_code":"0.0",
    "gn:admin3_code":"14522.0",
    "gn:admin4_code":"14522220.0",
    "gn:asciiname":"Mockritz",
    "gn:country_code":"DE",
    "gn:dem":219,
    "gn:feature_class":"P",
    "gn:feature_code":"PPL",
    "gn:name":"Mockritz",
    "gn:population":0,
    "gn:timezone":"Europe/Berlin",
    "iso:country":"DE",
    "wof:name":"Mockritz",
    "wof:placetype":"neighbourhood"
},
  "geometry": {"coordinates":[13.07644,51.16472],"type":"Point"}
}