{
  "type": "Feature",
  "properties": {
    "gn:admin1_code":"7.0",
    "gn:admin2_code":"55.0",
    "gn:admin3_code":"5513.0",
    "gn:admin4_code":"5513000.0",
    "gn:asciiname":"Feldmark",
    "gn:country_code":"DE",
    "gn:dem":44,
    "gn:feature_class":"P",
    "gn:feature_code":"PPL",
    "gn:name":"Feldmark",
    "gn:population":0,
    "gn:timezone":"Europe/Berlin",
    "iso:country":"DE",
    "wof:name":"Feldmark",
    "wof:placetype":"locality"
},
  "geometry": {"coordinates":[7.07421,51.50829],"type":"Point"}
}