{
  "type": "Feature",
  "properties": {
    "gn:admin1_code":"12",
    "gn:admin2_code":"0.0",
    "gn:admin3_code":"13076.0",
    "gn:admin4_code":"13076089.0",
    "gn:asciiname":"Riederfelde",
    "gn:cc2":"DE",
    "gn:country_code":"DE",
    "gn:dem":92,
    "gn:feature_class":"P",
    "gn:feature_code":"PPL",
    "gn:name":"Riederfelde",
    "gn:population":0,
    "gn:timezone":"Europe/Berlin",
    "iso:country":"DE",
    "name:und_x_variant":[
        "Bauhof Riederfelde"
    ],
    "wof:name":"Riederfelde",
    "wof:placetype":"neighbourhood"
},
  "geometry": {"coordinates":[12.07415,53.4668],"type":"Point"}
}