{
  "type": "Feature",
  "properties": {
    "gn:admin1_code":"6",
    "gn:admin2_code":"0.0",
    "gn:admin3_code":"3461.0",
    "gn:admin4_code":"3461005.0",
    "gn:asciiname":"Nordmentzhausen",
    "gn:country_code":"DE",
    "gn:dem":1,
    "gn:feature_class":"P",
    "gn:feature_code":"PPLL",
    "gn:name":"Nordmentzhausen",
    "gn:population":0,
    "gn:timezone":"Europe/Berlin",
    "iso:country":"DE",
    "wof:name":"Nordmentzhausen",
    "wof:placetype":"neighbourhood"
},
  "geometry": {"coordinates":[8.29834,53.33675],"type":"Point"}
}