{
  "type": "Feature",
  "properties": {
    "gn:admin1_code":"14",
    "gn:admin2_code":"0.0",
    "gn:admin3_code":"15090.0",
    "gn:admin4_code":"15090535.0",
    "gn:asciiname":"Lindenhof",
    "gn:country_code":"DE",
    "gn:dem":32,
    "gn:feature_class":"P",
    "gn:feature_code":"PPL",
    "gn:name":"Lindenhof",
    "gn:population":0,
    "gn:timezone":"Europe/Berlin",
    "iso:country":"DE",
    "name:deu_x_preferred":[
        "Lindenhof"
    ],
    "name:lat_x_preferred":[
        "Lindenhof"
    ],
    "name:pol_x_preferred":[
        "Lindenhof"
    ],
    "name:rus_x_preferred":[
        "\u041b\u0438\u043d\u0434\u0435\u043d\u0445\u043e\u0444"
    ],
    "name:tur_x_preferred":[
        "Lindenhof"
    ],
    "wof:name":"Lindenhof",
    "wof:placetype":"neighbourhood"
},
  "geometry": {"coordinates":[11.87073,52.56952],"type":"Point"}
}