{
  "type": "Feature",
  "properties": {
    "gn:admin1_code":"13",
    "gn:admin2_code":"0.0",
    "gn:admin3_code":"14729.0",
    "gn:admin4_code":"14729140.0",
    "gn:asciiname":"Priessnitz",
    "gn:country_code":"DE",
    "gn:dem":169,
    "gn:feature_class":"P",
    "gn:feature_code":"PPL",
    "gn:name":"Prie\u00dfnitz",
    "gn:population":0,
    "gn:timezone":"Europe/Berlin",
    "iso:country":"DE",
    "name:ceb_x_preferred":[
        "Prie\u00dfnitz"
    ],
    "name:ces_x_preferred":[
        "Priessnitz"
    ],
    "name:deu_x_preferred":[
        "Prie\u00dfnitz"
    ],
    "name:ita_x_preferred":[
        "Priessnitz"
    ],
    "name:nld_x_preferred":[
        "Prie\u00dfnitz"
    ],
    "name:swe_x_preferred":[
        "Prie\u00dfnitz"
    ],
    "wof:name":"Priessnitz",
    "wof:placetype":"neighbourhood"
},
  "geometry": {"coordinates":[12.60856,51.10538],"type":"Point"}
}