{
  "type": "Feature",
  "properties": {
    "gn:admin1_code":"10.0",
    "gn:admin2_code":"00",
    "gn:admin3_code":"1062.0",
    "gn:admin4_code":"1062076.0",
    "gn:asciiname":"Wulksfelde",
    "gn:country_code":"DE",
    "gn:dem":22,
    "gn:feature_class":"P",
    "gn:feature_code":"PPL",
    "gn:name":"Wulksfelde",
    "gn:population":0,
    "gn:timezone":"Europe/Berlin",
    "iso:country":"DE",
    "wof:name":"Wulksfelde",
    "wof:placetype":"neighbourhood"
},
  "geometry": {"coordinates":[10.11096,53.71832],"type":"Point"}
}