{
  "type": "Feature",
  "properties": {
    "gn:admin1_code":"2",
    "gn:admin2_code":"91.0",
    "gn:admin3_code":"9185.0",
    "gn:admin4_code":"9185150.0",
    "gn:asciiname":"Unterhausen",
    "gn:country_code":"DE",
    "gn:dem":410,
    "gn:feature_class":"P",
    "gn:feature_code":"PPL",
    "gn:name":"Unterhausen",
    "gn:population":0,
    "gn:timezone":"Europe/Berlin",
    "iso:country":"DE",
    "name:deu_x_preferred":[
        "Unterhausen"
    ],
    "wof:name":"Unterhausen",
    "wof:placetype":"neighbourhood"
},
  "geometry": {"coordinates":[11.0926,48.71915],"type":"Point"}
}