{
  "type": "Feature",
  "properties": {
    "gn:admin1_code":"12",
    "gn:admin2_code":"0.0",
    "gn:admin3_code":"13074.0",
    "gn:admin4_code":"13074002.0",
    "gn:asciiname":"Hoppenrade",
    "gn:country_code":"DE",
    "gn:dem":55,
    "gn:feature_class":"P",
    "gn:feature_code":"PPL",
    "gn:name":"Hoppenrade",
    "gn:population":0,
    "gn:timezone":"Europe/Berlin",
    "iso:country":"DE",
    "name:ceb_x_preferred":[
        "Hoppenrade"
    ],
    "name:deu_x_preferred":[
        "Hoppenrade"
    ],
    "name:epo_x_preferred":[
        "Hoppenrade"
    ],
    "name:fas_x_preferred":[
        "\u0647\u0648\u067e\u0646\u0631\u0627\u062f\u0647"
    ],
    "name:fra_x_preferred":[
        "Hoppenrade"
    ],
    "name:hun_x_preferred":[
        "Hoppenrade"
    ],
    "name:ita_x_preferred":[
        "Hoppenrade"
    ],
    "name:kaz_x_preferred":[
        "\u0425\u043e\u043f\u043f\u0435\u043d\u0440\u0430\u0434\u0435"
    ],
    "name:kir_x_preferred":[
        "\u0425\u043e\u043f\u043f\u0435\u043d\u0440\u0430\u0434\u0435"
    ],
    "name:mkd_x_preferred":[
        "\u0425\u043e\u043f\u0435\u043d\u0440\u0430\u0434\u0435"
    ],
    "name:msa_x_preferred":[
        "Hoppenrade"
    ],
    "name:nld_x_preferred":[
        "Hoppenrade"
    ],
    "name:pol_x_preferred":[
        "Hoppenrade"
    ],
    "name:ron_x_preferred":[
        "Hoppenrade"
    ],
    "name:rus_x_preferred":[
        "\u0425\u043e\u043f\u043f\u0435\u043d\u0440\u0430\u0434\u0435"
    ],
    "name:spa_x_preferred":[
        "Hoppenrade"
    ],
    "name:srp_x_preferred":[
        "\u0425\u043e\u043f\u0435\u043d\u0440\u0430\u0434\u0435"
    ],
    "name:ukr_x_preferred":[
        "\u0413\u043e\u043f\u043f\u0435\u043d\u0440\u0430\u0434\u0435"
    ],
    "name:uzb_x_preferred":[
        "Hoppenrade"
    ],
    "name:vie_x_preferred":[
        "Hoppenrade"
    ],
    "name:vol_x_preferred":[
        "Hoppenrade"
    ],
    "name:war_x_preferred":[
        "Hoppenrade"
    ],
    "name:zho_x_preferred":[
        "\u970d\u5f6d\u62c9\u5fb7"
    ],
    "wof:name":"Hoppenrade",
    "wof:placetype":"neighbourhood"
},
  "geometry": {"coordinates":[11.44842,53.78635],"type":"Point"}
}