{
  "type": "Feature",
  "properties": {
    "gn:admin1_code":"2",
    "gn:admin2_code":"91.0",
    "gn:admin3_code":"9178.0",
    "gn:admin4_code":"9178124.0",
    "gn:asciiname":"Pallhausen",
    "gn:country_code":"DE",
    "gn:dem":458,
    "gn:feature_class":"P",
    "gn:feature_code":"PPL",
    "gn:name":"Pallhausen",
    "gn:population":0,
    "gn:timezone":"Europe/Berlin",
    "iso:country":"DE",
    "wof:name":"Pallhausen",
    "wof:placetype":"neighbourhood"
},
  "geometry": {"coordinates":[11.66057,48.37487],"type":"Point"}
}