{
  "type": "Feature",
  "properties": {
    "gn:admin1_code":"7",
    "gn:admin2_code":"59.0",
    "gn:admin3_code":"5962.0",
    "gn:admin4_code":"5962056.0",
    "gn:asciiname":"Everinghausen",
    "gn:country_code":"DE",
    "gn:dem":377,
    "gn:feature_class":"P",
    "gn:feature_code":"PPL",
    "gn:name":"Everinghausen",
    "gn:population":0,
    "gn:timezone":"Europe/Berlin",
    "iso:country":"DE",
    "wof:name":"Everinghausen",
    "wof:placetype":"neighbourhood"
},
  "geometry": {"coordinates":[7.55721,51.26903],"type":"Point"}
}