{
  "type": "Feature",
  "properties": {
    "gn:admin1_code":"8",
    "gn:admin2_code":"0.0",
    "gn:admin3_code":"7138.0",
    "gn:admin4_code":"7138003.0",
    "gn:asciiname":"Dinspel",
    "gn:country_code":"DE",
    "gn:dem":208,
    "gn:feature_class":"P",
    "gn:feature_code":"PPL",
    "gn:name":"Dinspel",
    "gn:population":0,
    "gn:timezone":"Europe/Berlin",
    "iso:country":"DE",
    "wof:name":"Dinspel",
    "wof:placetype":"neighbourhood"
},
  "geometry": {"coordinates":[7.43389,50.64301],"type":"Point"}
}