{
  "type": "Feature",
  "properties": {
    "gn:admin1_code":"1",
    "gn:admin2_code":"84.0",
    "gn:admin3_code":"8436.0",
    "gn:admin4_code":"8436055.0",
    "gn:asciiname":"Ubendorf",
    "gn:country_code":"DE",
    "gn:dem":659,
    "gn:feature_class":"P",
    "gn:feature_code":"PPL",
    "gn:name":"\u00dcbendorf",
    "gn:population":0,
    "gn:timezone":"Europe/Berlin",
    "iso:country":"DE",
    "wof:name":"Ubendorf",
    "wof:placetype":"neighbourhood"
},
  "geometry": {"coordinates":[9.91436,47.83504],"type":"Point"}
}