{
  "type": "Feature",
  "properties": {
    "gn:admin1_code":"14",
    "gn:admin2_code":"0.0",
    "gn:admin3_code":"15082.0",
    "gn:admin4_code":"15082430.0",
    "gn:asciiname":"Ronney",
    "gn:country_code":"DE",
    "gn:dem":52,
    "gn:feature_class":"P",
    "gn:feature_code":"PPL",
    "gn:name":"Ronney",
    "gn:population":0,
    "gn:timezone":"Europe/Berlin",
    "iso:country":"DE",
    "wof:name":"Ronney",
    "wof:placetype":"neighbourhood"
},
  "geometry": {"coordinates":[11.91418,51.96182],"type":"Point"}
}