{
  "type": "Feature",
  "properties": {
    "gn:admin1_code":"5",
    "gn:admin2_code":"66.0",
    "gn:admin3_code":"6633.0",
    "gn:admin4_code":"6633023.0",
    "gn:asciiname":"Hoof",
    "gn:country_code":"DE",
    "gn:dem":379,
    "gn:feature_class":"P",
    "gn:feature_code":"PPL",
    "gn:name":"Hoof",
    "gn:population":0,
    "gn:timezone":"Europe/Berlin",
    "iso:country":"DE",
    "wof:name":"Hoof",
    "wof:placetype":"neighbourhood"
},
  "geometry": {"coordinates":[9.34052,51.28302],"type":"Point"}
}