{
  "type": "Feature",
  "properties": {
    "gn:admin1_code":"1",
    "gn:admin2_code":"82.0",
    "gn:admin3_code":"8235.0",
    "gn:admin4_code":"8235055.0",
    "gn:asciiname":"Siehdichfur",
    "gn:country_code":"DE",
    "gn:dem":668,
    "gn:feature_class":"P",
    "gn:feature_code":"PPL",
    "gn:name":"Siehdichf\u00fcr",
    "gn:population":0,
    "gn:timezone":"Europe/Berlin",
    "iso:country":"DE",
    "wof:name":"Siehdichfur",
    "wof:placetype":"neighbourhood"
},
  "geometry": {"coordinates":[8.66161,48.7432],"type":"Point"}
}