{
  "type": "Feature",
  "properties": {
    "gn:admin1_code":"10",
    "gn:admin2_code":"0.0",
    "gn:admin3_code":"1057.0",
    "gn:admin4_code":"1057009.0",
    "gn:asciiname":"Oberkleveez",
    "gn:country_code":"DE",
    "gn:dem":48,
    "gn:feature_class":"P",
    "gn:feature_code":"PPL",
    "gn:name":"Oberkleveez",
    "gn:population":0,
    "gn:timezone":"Europe/Berlin",
    "iso:country":"DE",
    "wof:name":"Oberkleveez",
    "wof:placetype":"neighbourhood"
},
  "geometry": {"coordinates":[10.50159,54.15055],"type":"Point"}
}