{
  "type": "Feature",
  "properties": {
    "gn:admin1_code":"13",
    "gn:admin2_code":"0.0",
    "gn:admin3_code":"14729.0",
    "gn:admin4_code":"14729160.0",
    "gn:asciiname":"Koellmichen",
    "gn:country_code":"DE",
    "gn:dem":204,
    "gn:feature_class":"P",
    "gn:feature_code":"PPL",
    "gn:name":"K\u00f6llmichen",
    "gn:population":0,
    "gn:timezone":"Europe/Berlin",
    "iso:country":"DE",
    "wof:name":"Koellmichen",
    "wof:placetype":"neighbourhood"
},
  "geometry": {"coordinates":[12.8907,51.24042],"type":"Point"}
}