{
  "type": "Feature",
  "properties": {
    "gn:admin1_code":"2.0",
    "gn:admin2_code":"94.0",
    "gn:admin3_code":"9464.0",
    "gn:admin4_code":"9464000.0",
    "gn:asciiname":"Alsenberg",
    "gn:country_code":"DE",
    "gn:dem":504,
    "gn:feature_class":"P",
    "gn:feature_code":"PPL",
    "gn:name":"Alsenberg",
    "gn:population":0,
    "gn:timezone":"Europe/Berlin",
    "iso:country":"DE",
    "wof:name":"Alsenberg",
    "wof:placetype":"neighbourhood"
},
  "geometry": {"coordinates":[11.92856,50.30181],"type":"Point"}
}