{
  "type": "Feature",
  "properties": {
    "gn:gn_country":"DE",
    "gn:gn_fcode":"PPL",
    "gn:gn_pop":1702,
    "gn:population":1702,
    "iso:country":"DE",
    "name:ara_x_preferred":[
        "\u0634\u062a\u0627\u062a\u0628\u0631\u0648\u062a\u0633\u0644\u062a\u0646"
    ],
    "name:fas_x_preferred":[
        "\u0627\u0634\u062a\u0627\u062a\u200c\u067e\u0631\u062a\u0633\u0644\u062a\u0646"
    ],
    "name:hye_x_preferred":[
        "\u0547\u0569\u0561\u0569\u057a\u0580\u0578\u0581\u0565\u056c\u057f\u0565\u0576"
    ],
    "name:jpn_x_preferred":[
        "\u30b7\u30e5\u30bf\u30c3\u30c8\u30d7\u30ed\u30c4\u30a7\u30eb\u30c6\u30f3"
    ],
    "name:kaz_x_preferred":[
        "\u0428\u0442\u0430\u0434\u0442\u043f\u0440\u043e\u0446\u0435\u043b\u044c\u0442\u0435\u043d"
    ],
    "name:rus_x_preferred":[
        "\u0428\u0442\u0430\u0434\u0442\u043f\u0440\u043e\u0446\u0435\u043b\u044c\u0442\u0435\u043d"
    ],
    "name:srp_x_preferred":[
        "\u0428\u0442\u0430\u0442\u043f\u0440\u043e\u0446\u0435\u043b\u0442\u0435\u043d"
    ],
    "name:ukr_x_preferred":[
        "\u0428\u0442\u0430\u0434\u0442\u043f\u0440\u043e\u0446\u0435\u043b\u044c\u0442\u0435\u043d"
    ],
    "name:zho_x_preferred":[
        "\u65bd\u5854\u7279\u666e\u7f57\u7b56\u5c14\u6ed5"
    ],
    "qs_pg:aaroncc":"DE",
    "qs_pg:gn_country":"DE",
    "qs_pg:gn_fcode":"PPL",
    "qs_pg:gn_pop":1702,
    "qs_pg:name":"Stadtprozelten",
    "qs_pg:name_adm0":"Deutschland",
    "qs_pg:name_adm1":"Bayern",
    "qs_pg:photos_9k":1,
    "qs_pg:photos_9r":2,
    "qs_pg:photos_all":52,
    "qs_pg:photos_sr":0,
    "qs_pg:pop_sr":3,
    "qs_pg:qs_pg_placetype":"locality",
    "qs_pg:qs_pg_placetype_gp":"Town",
    "qs_pg:woe_adm0":23424829,
    "woe:adm0_id":23424829,
    "woe:name_adm0":"Deutschland",
    "woe:name_adm1":"Bayern",
    "woe:placetype":"Town",
    "wof:name":"Stadtprozelten",
    "wof:placetype":"locality",
    "wof:population":1702
},
  "geometry": {"coordinates":[9.41184,49.78466],"type":"Point"}
}