{
  "type": "Feature",
  "properties": {
    "gn:admin1_code":"2",
    "gn:admin2_code":"94.0",
    "gn:admin3_code":"9475.0",
    "gn:admin4_code":"9475127.0",
    "gn:asciiname":"Neuenreuth",
    "gn:country_code":"DE",
    "gn:dem":562,
    "gn:feature_class":"P",
    "gn:feature_code":"PPL",
    "gn:name":"Neuenreuth",
    "gn:population":0,
    "gn:timezone":"Europe/Berlin",
    "iso:country":"DE",
    "wof:name":"Neuenreuth",
    "wof:placetype":"neighbourhood"
},
  "geometry": {"coordinates":[11.98864,50.33123],"type":"Point"}
}