{
  "type": "Feature",
  "properties": {
    "gn:admin1_code":"1",
    "gn:admin2_code":"83.0",
    "gn:admin3_code":"8317.0",
    "gn:admin4_code":"8317068.0",
    "gn:asciiname":"Matzenhofe",
    "gn:country_code":"DE",
    "gn:dem":288,
    "gn:feature_class":"P",
    "gn:feature_code":"PPLL",
    "gn:name":"Matzenh\u00f6fe",
    "gn:population":0,
    "gn:timezone":"Europe/Berlin",
    "iso:country":"DE",
    "name:und_x_variant":[
        "Matzenh\u00f6f",
        "Matzenh\u00f6fe"
    ],
    "wof:name":"Matzenhofe",
    "wof:placetype":"neighbourhood"
},
  "geometry": {"coordinates":[8.14168,48.6402],"type":"Point"}
}