{
  "type": "Feature",
  "properties": {
    "gn:country":"DE",
    "gn:fcode":"PPL",
    "gn:population":0,
    "iso:country":"DE",
    "name:bel_x_preferred":[
        "\u041e\u0431\u0435\u0440\u043b\u0430\u045e\u0434\u0430"
    ],
    "name:ces_x_preferred":[
        "Oberlauda"
    ],
    "name:dan_x_preferred":[
        "Oberlauda"
    ],
    "name:deu_x_preferred":[
        "Oberlauda"
    ],
    "name:eng_x_preferred":[
        "Oberlauda"
    ],
    "name:epo_x_preferred":[
        "Oberlauda"
    ],
    "name:fra_x_preferred":[
        "Oberlauda"
    ],
    "name:gle_x_preferred":[
        "Oberlauda"
    ],
    "name:hun_x_preferred":[
        "Oberlauda"
    ],
    "name:nld_x_preferred":[
        "Oberlauda"
    ],
    "name:pol_x_preferred":[
        "Oberlauda"
    ],
    "name:rus_x_preferred":[
        "\u041e\u0431\u0435\u0440\u043b\u0430\u0443\u0434\u0430"
    ],
    "name:vol_x_preferred":[
        "Oberlauda"
    ],
    "qs_pg:aaroncc":"DE",
    "qs_pg:gn_country":"DE",
    "qs_pg:gn_fcode":"PPL",
    "qs_pg:gn_pop":0,
    "qs_pg:name":"Oberlauda",
    "qs_pg:name_adm0":"Deutschland",
    "qs_pg:name_adm1":"Baden-W\u00fcrttemberg",
    "qs_pg:photos":24,
    "qs_pg:photos_1k":5,
    "qs_pg:photos_9k":1,
    "qs_pg:photos_9r":1,
    "qs_pg:photos_all":24,
    "qs_pg:photos_sr":1,
    "qs_pg:pop_sr":0,
    "qs_pg:qs_pg_placetype":"locality",
    "qs_pg:qs_pg_placetype_gp":"Town",
    "qs_pg:woe_adm0":23424829,
    "woe:adm0_id":23424829,
    "woe:name_adm0":"Deutschland",
    "woe:name_adm1":"Baden-W\u00fcrttemberg",
    "woe:placetype":"Town",
    "wof:name":"Oberlauda",
    "wof:placetype":"neighbourhood"
},
  "geometry": {"coordinates":[9.67644,49.56963],"type":"Point"}
}