{
  "type": "Feature",
  "properties": {
    "gn:admin1_code":"1",
    "gn:admin2_code":"83.0",
    "gn:admin3_code":"8315.0",
    "gn:admin4_code":"8315113.0",
    "gn:asciiname":"Unterschwarzenbach",
    "gn:country_code":"DE",
    "gn:dem":917,
    "gn:feature_class":"P",
    "gn:feature_code":"PPLL",
    "gn:name":"Unterschw\u00e4rzenbach",
    "gn:population":0,
    "gn:timezone":"Europe/Berlin",
    "iso:country":"DE",
    "wof:name":"Unterschwarzenbach",
    "wof:placetype":"neighbourhood"
},
  "geometry": {"coordinates":[8.21854,47.94466],"type":"Point"}
}