{
  "type": "Feature",
  "properties": {
    "gn:admin1_code":"5.0",
    "gn:admin2_code":"65.0",
    "gn:admin3_code":"6533.0",
    "gn:admin4_code":"6533017.0",
    "gn:asciiname":"Bermbach",
    "gn:country_code":"DE",
    "gn:dem":293,
    "gn:feature_class":"P",
    "gn:feature_code":"PPL",
    "gn:name":"Bermbach",
    "gn:population":0,
    "gn:timezone":"Europe/Berlin",
    "iso:country":"DE",
    "name:bak_x_preferred":[
        "\u0411\u0435\u0440\u043c\u0431\u0430\u0445"
    ],
    "name:ceb_x_preferred":[
        "Bermbach"
    ],
    "name:deu_x_preferred":[
        "Bermbach"
    ],
    "name:epo_x_preferred":[
        "Bermbach"
    ],
    "name:eus_x_preferred":[
        "Bermbach"
    ],
    "name:fas_x_preferred":[
        "\u0628\u0631\u0645\u0628\u0627\u062e"
    ],
    "name:fra_x_preferred":[
        "Bermbach"
    ],
    "name:hun_x_preferred":[
        "Bermbach"
    ],
    "name:ita_x_preferred":[
        "Bermbach"
    ],
    "name:kaz_x_preferred":[
        "\u0411\u0435\u0440\u043c\u0431\u0430\u0445"
    ],
    "name:kir_x_preferred":[
        "\u0411\u0435\u0440\u043c\u0431\u0430\u0445"
    ],
    "name:mkd_x_preferred":[
        "\u0411\u0435\u0440\u043c\u0431\u0430\u0445"
    ],
    "name:msa_x_preferred":[
        "Bermbach"
    ],
    "name:nld_x_preferred":[
        "Bermbach"
    ],
    "name:pol_x_preferred":[
        "Bermbach"
    ],
    "name:por_x_preferred":[
        "Bermbach"
    ],
    "name:ron_x_preferred":[
        "Bermbach"
    ],
    "name:rus_x_preferred":[
        "\u0411\u0435\u0440\u043c\u0431\u0430\u0445"
    ],
    "name:spa_x_preferred":[
        "Bermbach"
    ],
    "name:srp_x_preferred":[
        "\u0411\u0435\u0440\u043c\u0431\u0430\u0445"
    ],
    "name:ukr_x_preferred":[
        "\u0411\u0435\u0440\u043c\u0431\u0430\u0445"
    ],
    "name:uzb_x_preferred":[
        "Bermbach"
    ],
    "name:vie_x_preferred":[
        "Bermbach"
    ],
    "name:vol_x_preferred":[
        "Bermbach"
    ],
    "name:war_x_preferred":[
        "Bermbach"
    ],
    "name:zho_x_preferred":[
        "\u8d1d\u5c14\u6069\u5df4\u8d6b"
    ],
    "wof:name":"Bermbach",
    "wof:placetype":"neighbourhood"
},
  "geometry": {"coordinates":[8.35811,50.48192],"type":"Point"}
}