{
  "type": "Feature",
  "properties": {
    "gn:admin1_code":"2",
    "gn:admin2_code":"94.0",
    "gn:admin3_code":"9471.0",
    "gn:admin4_code":"9471122.0",
    "gn:asciiname":"Ober Steinach",
    "gn:country_code":"DE",
    "gn:dem":346,
    "gn:feature_class":"P",
    "gn:feature_code":"PPL",
    "gn:name":"Ober Steinach",
    "gn:population":0,
    "gn:timezone":"Europe/Berlin",
    "iso:country":"DE",
    "wof:name":"Ober Steinach",
    "wof:placetype":"neighbourhood"
},
  "geometry": {"coordinates":[10.52952,49.81038],"type":"Point"}
}