{
  "type": "Feature",
  "properties": {
    "gn:admin1_code":"14",
    "gn:admin2_code":"0.0",
    "gn:admin3_code":"15087.0",
    "gn:admin4_code":"15087130.0",
    "gn:asciiname":"Kleinosterhausen",
    "gn:country_code":"DE",
    "gn:dem":163,
    "gn:feature_class":"P",
    "gn:feature_code":"PPL",
    "gn:name":"Kleinosterhausen",
    "gn:population":0,
    "gn:timezone":"Europe/Berlin",
    "iso:country":"DE",
    "wof:name":"Kleinosterhausen",
    "wof:placetype":"neighbourhood"
},
  "geometry": {"coordinates":[11.51937,51.44758],"type":"Point"}
}