{
  "type": "Feature",
  "properties": {
    "gn:admin1_code":"1",
    "gn:admin2_code":"83.0",
    "gn:admin3_code":"8336.0",
    "gn:admin4_code":"8336104.0",
    "gn:asciiname":"Lutschenbach",
    "gn:country_code":"DE",
    "gn:dem":586,
    "gn:feature_class":"P",
    "gn:feature_code":"PPL",
    "gn:name":"L\u00fctschenbach",
    "gn:population":0,
    "gn:timezone":"Europe/Berlin",
    "iso:country":"DE",
    "wof:name":"Lutschenbach",
    "wof:placetype":"neighbourhood"
},
  "geometry": {"coordinates":[7.7136,47.74544],"type":"Point"}
}