{
  "type": "Feature",
  "properties": {
    "gn:admin1_code":"6",
    "gn:admin2_code":"0.0",
    "gn:admin3_code":"3155.0",
    "gn:admin4_code":"3155009.0",
    "gn:asciiname":"Grossenrode",
    "gn:country_code":"DE",
    "gn:dem":171,
    "gn:feature_class":"P",
    "gn:feature_code":"PPL",
    "gn:name":"Gro\u00dfenrode",
    "gn:population":0,
    "gn:timezone":"Europe/Berlin",
    "iso:country":"DE",
    "name:deu_x_preferred":[
        "Gro\u00dfenrode"
    ],
    "name:fas_x_preferred":[
        "\u06af\u0631\u0648\u0633\u0646\u0631\u0648\u062f"
    ],
    "wof:name":"Grossenrode",
    "wof:placetype":"neighbourhood"
},
  "geometry": {"coordinates":[9.90623,51.66867],"type":"Point"}
}