{
  "type": "Feature",
  "properties": {
    "gn:admin1_code":"13",
    "gn:admin2_code":"0.0",
    "gn:admin3_code":"14625.0",
    "gn:admin4_code":"14625490.0",
    "gn:asciiname":"Luttowitz",
    "gn:country_code":"DE",
    "gn:dem":177,
    "gn:feature_class":"P",
    "gn:feature_code":"PPL",
    "gn:name":"Luttowitz",
    "gn:population":0,
    "gn:timezone":"Europe/Berlin",
    "iso:country":"DE",
    "name:hsb_x_preferred":[
        "Lutob\u010d"
    ],
    "wof:name":"Luttowitz",
    "wof:placetype":"neighbourhood"
},
  "geometry": {"coordinates":[14.42342,51.24091],"type":"Point"}
}