{
  "type": "Feature",
  "properties": {
    "gn:admin1_code":"7",
    "gn:admin2_code":"53.0",
    "gn:admin3_code":"5358.0",
    "gn:admin4_code":"5358020.0",
    "gn:asciiname":"Pier",
    "gn:country_code":"DE",
    "gn:dem":107,
    "gn:feature_class":"P",
    "gn:feature_code":"PPL",
    "gn:name":"Pier",
    "gn:population":0,
    "gn:timezone":"Europe/Berlin",
    "iso:country":"DE",
    "name:ara_x_preferred":[
        "\u0631\u0635\u064a\u0641 \u0628\u062d\u0631\u064a"
    ],
    "name:bul_x_preferred":[
        "\u041a\u0435\u0439"
    ],
    "name:ces_x_preferred":[
        "Molo"
    ],
    "name:cym_x_preferred":[
        "Pier"
    ],
    "name:deu_x_preferred":[
        "Seebr\u00fccke"
    ],
    "name:epo_x_preferred":[
        "Piero"
    ],
    "name:fas_x_preferred":[
        "\u06a9\u0648\u062a\u0627\u0647\u200c\u0627\u0633\u06a9\u0644\u0647"
    ],
    "name:fin_x_preferred":[
        "Laituri"
    ],
    "name:fra_x_preferred":[
        "Estacade"
    ],
    "name:fry_x_preferred":[
        "Pier"
    ],
    "name:gle_x_preferred":[
        "Caladh"
    ],
    "name:glg_x_preferred":[
        "Embarcadoiro"
    ],
    "name:heb_x_preferred":[
        "\u05de\u05d6\u05d7"
    ],
    "name:ido_x_preferred":[
        "Estakado"
    ],
    "name:isl_x_preferred":[
        "Bryggja"
    ],
    "name:ita_x_preferred":[
        "Pontile"
    ],
    "name:kor_x_preferred":[
        "\ub3cc\uc81c\ubd80\ub450"
    ],
    "name:lit_x_preferred":[
        "Pirsas"
    ],
    "name:nld_x_preferred":[
        "Pier"
    ],
    "name:nor_x_preferred":[
        "Pir"
    ],
    "name:pol_x_preferred":[
        "Molo"
    ],
    "name:por_x_preferred":[
        "P\u00eder"
    ],
    "name:rue_x_preferred":[
        "\u041c\u043e\u043b\u043e"
    ],
    "name:rus_x_preferred":[
        "\u041f\u0438\u0440\u0441"
    ],
    "name:sco_x_preferred":[
        "Pier"
    ],
    "name:slk_x_preferred":[
        "M\u00f3lo"
    ],
    "name:slv_x_preferred":[
        "Pomol"
    ],
    "name:tgl_x_preferred":[
        "Piyer"
    ],
    "name:tha_x_preferred":[
        "\u0e17\u0e48\u0e32\u0e19\u0e49\u0e33"
    ],
    "name:tur_x_preferred":[
        "\u0130skele"
    ],
    "name:ukr_x_preferred":[
        "\u041f\u0456\u0440\u0441"
    ],
    "name:vls_x_preferred":[
        "Piere"
    ],
    "wof:name":"Pier",
    "wof:placetype":"neighbourhood"
},
  "geometry": {"coordinates":[6.3972,50.86207],"type":"Point"}
}