{
  "type": "Feature",
  "properties": {
    "gn:admin1_code":"2",
    "gn:admin2_code":"95.0",
    "gn:admin3_code":"9574.0",
    "gn:admin4_code":"9574139.0",
    "gn:asciiname":"Scheerau",
    "gn:country_code":"DE",
    "gn:dem":372,
    "gn:feature_class":"P",
    "gn:feature_code":"PPL",
    "gn:name":"Scheerau",
    "gn:population":0,
    "gn:timezone":"Europe/Berlin",
    "iso:country":"DE",
    "wof:name":"Scheerau",
    "wof:placetype":"neighbourhood"
},
  "geometry": {"coordinates":[11.2902,49.4515],"type":"Point"}
}