{
  "type": "Feature",
  "properties": {
    "gn:admin1_code":"2",
    "gn:admin2_code":"94.0",
    "gn:admin3_code":"9477.0",
    "gn:admin4_code":"9477124.0",
    "gn:asciiname":"Unterneuhuttendorf",
    "gn:country_code":"DE",
    "gn:dem":376,
    "gn:feature_class":"P",
    "gn:feature_code":"PPL",
    "gn:name":"Unterneuh\u00fcttendorf",
    "gn:population":0,
    "gn:timezone":"Europe/Berlin",
    "iso:country":"DE",
    "wof:name":"Unterneuhuttendorf",
    "wof:placetype":"neighbourhood"
},
  "geometry": {"coordinates":[11.36667,50.05],"type":"Point"}
}