{
  "type": "Feature",
  "properties": {
    "gn:admin1_code":"6",
    "gn:admin2_code":"0.0",
    "gn:admin3_code":"3254.0",
    "gn:admin4_code":"3254021.0",
    "gn:asciiname":"Einum",
    "gn:country_code":"DE",
    "gn:dem":97,
    "gn:feature_class":"P",
    "gn:feature_code":"PPL",
    "gn:name":"Einum",
    "gn:population":0,
    "gn:timezone":"Europe/Berlin",
    "iso:country":"DE",
    "wof:name":"Einum",
    "wof:placetype":"neighbourhood"
},
  "geometry": {"coordinates":[10.01284,52.16235],"type":"Point"}
}