{
  "type": "Feature",
  "properties": {
    "gn:admin1_code":"2",
    "gn:admin2_code":"91.0",
    "gn:admin3_code":"9183.0",
    "gn:admin4_code":"9183147.0",
    "gn:asciiname":"Dirnberg",
    "gn:country_code":"DE",
    "gn:dem":523,
    "gn:feature_class":"P",
    "gn:feature_code":"PPL",
    "gn:name":"Dirnberg",
    "gn:population":0,
    "gn:timezone":"Europe/Berlin",
    "iso:country":"DE",
    "wof:name":"Dirnberg",
    "wof:placetype":"neighbourhood"
},
  "geometry": {"coordinates":[12.2844,48.11978],"type":"Point"}
}