{
  "type": "Feature",
  "properties": {
    "gn:gn_country":"DE",
    "gn:gn_fcode":"PPLA4",
    "gn:gn_pop":302,
    "gn:population":302,
    "iso:country":"DE",
    "name:baq_x_preferred":[
        "Hirz-Maulsbach"
    ],
    "name:chi_x_preferred":[
        "\u5e0c\u5c14\u8328-\u6bdb\u5c14\u65af\u5df4\u8d6b"
    ],
    "name:dut_x_preferred":[
        "Hirz-Maulsbach"
    ],
    "name:eng_x_preferred":[
        "Hirz-Maulsbach"
    ],
    "name:epo_x_preferred":[
        "Hirz-Maulsbach"
    ],
    "name:fre_x_preferred":[
        "Hirz-Maulsbach"
    ],
    "name:ger_x_preferred":[
        "Hirz-Maulsbach"
    ],
    "name:hun_x_preferred":[
        "Hirz-Maulsbach"
    ],
    "name:ita_x_preferred":[
        "Hirz-Maulsbach"
    ],
    "name:jpn_x_preferred":[
        "\u30d2\u30eb\u30c4\uff1d\u30de\u30a6\u30eb\u30b9\u30d0\u30c3\u30cf"
    ],
    "name:kaz_x_preferred":[
        "\u0425\u0438\u0440\u0446-\u041c\u0430\u0443\u043b\u044c\u0441\u0431\u0430\u0445"
    ],
    "name:kir_x_preferred":[
        "\u0425\u0438\u0440\u0446-\u041c\u0430\u0443\u043b\u044c\u0441\u0431\u0430\u0445"
    ],
    "name:may_x_preferred":[
        "Hirz-Maulsbach"
    ],
    "name:per_x_preferred":[
        "\u0647\u06cc\u0631\u0632-\u0645\u0627\u0644\u0633\u0628\u0627\u062e"
    ],
    "name:pol_x_preferred":[
        "Hirz-Maulsbach"
    ],
    "name:por_x_preferred":[
        "Hirz-Maulsbach"
    ],
    "name:rum_x_preferred":[
        "Hirz-Maulsbach"
    ],
    "name:rus_x_preferred":[
        "\u0425\u0438\u0440\u0446-\u041c\u0430\u0443\u043b\u044c\u0441\u0431\u0430\u0445"
    ],
    "name:srp_x_preferred":[
        "\u0425\u0438\u0440\u0446-\u041c\u0430\u0443\u043b\u0441\u0431\u0430\u0445"
    ],
    "name:ukr_x_preferred":[
        "\u0413\u0456\u0440\u0446-\u041c\u0430\u0443\u043b\u044c\u0441\u0431\u0430\u0445"
    ],
    "name:uzb_x_preferred":[
        "Hirz-Maulsbach"
    ],
    "name:vie_x_preferred":[
        "Hirz-Maulsbach"
    ],
    "name:vol_x_preferred":[
        "Hirz-Maulsbach"
    ],
    "name:war_x_preferred":[
        "Hirz-Maulsbach"
    ],
    "qs_pg:aaroncc":"DE",
    "qs_pg:gn_country":"DE",
    "qs_pg:gn_fcode":"PPLA4",
    "qs_pg:gn_pop":302,
    "qs_pg:name":"Hirz-Maulsbach",
    "qs_pg:photos_9r":0,
    "qs_pg:photos_sr":0,
    "qs_pg:pop_sr":2,
    "qs_pg:qs_pg_placetype":"locality",
    "wof:name":"Hirz-Maulsbach",
    "wof:placetype":"locality",
    "wof:population":302
},
  "geometry": {"coordinates":[7.48333,50.68333],"type":"Point"}
}