{
  "type": "Feature",
  "properties": {
    "gn:admin1_code":"14",
    "gn:admin2_code":"0.0",
    "gn:admin3_code":"15091.0",
    "gn:admin4_code":"15091391.0",
    "gn:asciiname":"Kuelso",
    "gn:country_code":"DE",
    "gn:dem":76,
    "gn:feature_class":"P",
    "gn:feature_code":"PPL",
    "gn:name":"K\u00fclso",
    "gn:population":0,
    "gn:timezone":"Europe/Berlin",
    "iso:country":"DE",
    "wof:name":"Kuelso",
    "wof:placetype":"neighbourhood"
},
  "geometry": {"coordinates":[12.7823,51.86722],"type":"Point"}
}