{
  "type": "Feature",
  "properties": {
    "gn:admin1_code":"1",
    "gn:admin2_code":"81.0",
    "gn:admin3_code":"8126.0",
    "gn:admin4_code":"8126066.0",
    "gn:asciiname":"Buchhof",
    "gn:country_code":"DE",
    "gn:dem":273,
    "gn:feature_class":"P",
    "gn:feature_code":"PPL",
    "gn:name":"Buchhof",
    "gn:population":0,
    "gn:timezone":"Europe/Berlin",
    "iso:country":"DE",
    "name:bar_x_preferred":[
        "Buchhof"
    ],
    "name:deu_x_preferred":[
        "Buchhof"
    ],
    "wof:name":"Buchhof",
    "wof:placetype":"neighbourhood"
},
  "geometry": {"coordinates":[9.44125,49.27632],"type":"Point"}
}