{
  "type": "Feature",
  "properties": {
    "gn:admin1_code":"7",
    "gn:admin2_code":"57.0",
    "gn:admin3_code":"5766.0",
    "gn:admin4_code":"5766044.0",
    "gn:asciiname":"Wahmbeck",
    "gn:country_code":"DE",
    "gn:dem":180,
    "gn:feature_class":"P",
    "gn:feature_code":"PPL",
    "gn:name":"Wahmbeck",
    "gn:population":0,
    "gn:timezone":"Europe/Berlin",
    "iso:country":"DE",
    "wof:name":"Wahmbeck",
    "wof:placetype":"neighbourhood"
},
  "geometry": {"coordinates":[8.9027,51.99381],"type":"Point"}
}