{
  "type": "Feature",
  "properties": {
    "gn:country":"DE",
    "gn:fcode":"PPLA4",
    "gn:population":68,
    "iso:country":"DE",
    "name:cat_x_preferred":[
        "Scharfbillig"
    ],
    "name:ceb_x_preferred":[
        "Scharfbillig"
    ],
    "name:che_x_preferred":[
        "\u0428\u0430\u0440\u0444\u0431\u0438\u043b\u043b\u0438\u0433"
    ],
    "name:deu_x_preferred":[
        "Scharfbillig"
    ],
    "name:eng_x_preferred":[
        "Scharfbillig"
    ],
    "name:epo_x_preferred":[
        "Scharfbillig"
    ],
    "name:eus_x_preferred":[
        "Scharfbillig"
    ],
    "name:fas_x_preferred":[
        "\u0634\u0627\u0631\u0641\u0628\u06cc\u0644\u06cc\u06af"
    ],
    "name:fra_x_preferred":[
        "Scharfbillig"
    ],
    "name:hun_x_preferred":[
        "Scharfbillig"
    ],
    "name:ita_x_preferred":[
        "Scharfbillig"
    ],
    "name:jpn_x_preferred":[
        "\u30b7\u30e3\u30eb\u30d5\u30d3\u30ea\u30d2"
    ],
    "name:kur_x_preferred":[
        "Scharfbillig"
    ],
    "name:msa_x_preferred":[
        "Scharfbillig"
    ],
    "name:nan_x_preferred":[
        "Scharfbillig"
    ],
    "name:nld_x_preferred":[
        "Scharfbillig"
    ],
    "name:nob_x_preferred":[
        "Scharfbillig"
    ],
    "name:pol_x_preferred":[
        "Scharfbillig"
    ],
    "name:por_x_preferred":[
        "Scharfbillig"
    ],
    "name:ron_x_preferred":[
        "Scharfbillig"
    ],
    "name:rus_x_preferred":[
        "\u0428\u0430\u0440\u0444\u0431\u0438\u043b\u043b\u0438\u0433"
    ],
    "name:spa_x_preferred":[
        "Scharfbillig"
    ],
    "name:srp_x_preferred":[
        "\u0428\u0430\u0440\u0444\u0431\u0438\u043b\u0438\u0433"
    ],
    "name:swe_x_preferred":[
        "Scharfbillig"
    ],
    "name:tat_x_preferred":[
        "\u0428\u0430\u0440\u0444\u0431\u0438\u043b\u043b\u0438\u0433"
    ],
    "name:ukr_x_preferred":[
        "\u0428\u0430\u0440\u0444\u0431\u0456\u043b\u043b\u0456\u0433"
    ],
    "name:uzb_x_preferred":[
        "Scharfbillig"
    ],
    "name:vie_x_preferred":[
        "Scharfbillig"
    ],
    "name:vol_x_preferred":[
        "Scharfbillig"
    ],
    "name:war_x_preferred":[
        "Scharfbillig"
    ],
    "name:zho_x_preferred":[
        "\u6c99\u5c14\u592b\u6bd4\u5229\u5e0c"
    ],
    "qs_pg:aaroncc":"DE",
    "qs_pg:gn_country":"DE",
    "qs_pg:gn_fcode":"PPLA4",
    "qs_pg:gn_pop":68,
    "qs_pg:name":"Scharfbillig",
    "qs_pg:name_adm0":"Deutschland",
    "qs_pg:name_adm1":"Rheinland-Pfalz",
    "qs_pg:photos":881,
    "qs_pg:photos_1k":179,
    "qs_pg:photos_9k":4,
    "qs_pg:photos_9r":0,
    "qs_pg:photos_all":881,
    "qs_pg:photos_sr":0,
    "qs_pg:pop_sr":1,
    "qs_pg:qs_pg_placetype":"locality",
    "qs_pg:qs_pg_placetype_gp":"Town",
    "qs_pg:woe_adm0":23424829,
    "wof:name":"Scharfbillig",
    "wof:placetype":"neighbourhood",
    "wof:population":68
},
  "geometry": {"coordinates":[6.55523,49.93233],"type":"Point"}
}