{
  "type": "Feature",
  "properties": {
    "gn:admin1_code":"11",
    "gn:admin2_code":"0.0",
    "gn:admin3_code":"12069.0",
    "gn:admin4_code":"12069665.0",
    "gn:asciiname":"Setzsteig",
    "gn:country_code":"DE",
    "gn:dem":146,
    "gn:feature_class":"P",
    "gn:feature_code":"PPL",
    "gn:name":"Setzsteig",
    "gn:population":0,
    "gn:timezone":"Europe/Berlin",
    "iso:country":"DE",
    "wof:name":"Setzsteig",
    "wof:placetype":"neighbourhood"
},
  "geometry": {"coordinates":[12.44157,52.0287],"type":"Point"}
}