{
  "type": "Feature",
  "properties": {
    "gn:admin1_code":"11.0",
    "gn:admin2_code":"00",
    "gn:admin3_code":"12062.0",
    "gn:admin4_code":"12062024.0",
    "gn:asciiname":"Zobersdorf",
    "gn:country_code":"DE",
    "gn:dem":90,
    "gn:feature_class":"P",
    "gn:feature_code":"PPL",
    "gn:name":"Zobersdorf",
    "gn:population":0,
    "gn:timezone":"Europe/Berlin",
    "iso:country":"DE",
    "wof:name":"Zobersdorf",
    "wof:placetype":"neighbourhood"
},
  "geometry": {"coordinates":[13.40574,51.49442],"type":"Point"}
}