{
  "type": "Feature",
  "properties": {
    "gn:admin1_code":"1",
    "gn:admin2_code":"84.0",
    "gn:admin3_code":"8437.0",
    "gn:admin4_code":"8437124.0",
    "gn:asciiname":"Ebratsweiler",
    "gn:country_code":"DE",
    "gn:dem":643,
    "gn:feature_class":"P",
    "gn:feature_code":"PPL",
    "gn:name":"Ebratsweiler",
    "gn:population":0,
    "gn:timezone":"Europe/Berlin",
    "iso:country":"DE",
    "wof:name":"Ebratsweiler",
    "wof:placetype":"neighbourhood"
},
  "geometry": {"coordinates":[9.17362,47.87498],"type":"Point"}
}