{
  "type": "Feature",
  "properties": {
    "gn:admin1_code":"12",
    "gn:admin2_code":"0.0",
    "gn:admin3_code":"13072.0",
    "gn:admin4_code":"13072013.0",
    "gn:asciiname":"Moisall",
    "gn:country_code":"DE",
    "gn:dem":83,
    "gn:feature_class":"P",
    "gn:feature_code":"PPL",
    "gn:name":"Moisall",
    "gn:population":0,
    "gn:timezone":"Europe/Berlin",
    "iso:country":"DE",
    "wof:name":"Moisall",
    "wof:placetype":"neighbourhood"
},
  "geometry": {"coordinates":[11.83945,53.8828],"type":"Point"}
}