{
  "type": "Feature",
  "properties": {
    "gn:admin1_code":"2",
    "gn:admin2_code":"92.0",
    "gn:admin3_code":"9279.0",
    "gn:admin4_code":"9279127.0",
    "gn:asciiname":"Untersalhof",
    "gn:country_code":"DE",
    "gn:dem":406,
    "gn:feature_class":"P",
    "gn:feature_code":"PPLL",
    "gn:name":"Untersalhof",
    "gn:population":0,
    "gn:timezone":"Europe/Berlin",
    "iso:country":"DE",
    "wof:name":"Untersalhof",
    "wof:placetype":"neighbourhood"
},
  "geometry": {"coordinates":[12.42414,48.73991],"type":"Point"}
}