{
  "type": "Feature",
  "properties": {
    "gn:admin1_code":"2",
    "gn:admin2_code":"94.0",
    "gn:admin3_code":"9479.0",
    "gn:admin4_code":"9479166.0",
    "gn:asciiname":"Weiherhofen",
    "gn:country_code":"DE",
    "gn:dem":622,
    "gn:feature_class":"P",
    "gn:feature_code":"PPL",
    "gn:name":"Weiherh\u00f6fen",
    "gn:population":0,
    "gn:timezone":"Europe/Berlin",
    "iso:country":"DE",
    "wof:name":"Weiherhofen",
    "wof:placetype":"neighbourhood"
},
  "geometry": {"coordinates":[11.86578,50.10031],"type":"Point"}
}