{
  "type": "Feature",
  "properties": {
    "gn:admin1_code":"12",
    "gn:admin2_code":"0.0",
    "gn:admin3_code":"13073.0",
    "gn:admin4_code":"13073074.0",
    "gn:asciiname":"Luessmitz",
    "gn:country_code":"DE",
    "gn:dem":5,
    "gn:feature_class":"P",
    "gn:feature_code":"PPL",
    "gn:name":"L\u00fc\u00dfmitz",
    "gn:population":0,
    "gn:timezone":"Europe/Berlin",
    "iso:country":"DE",
    "wof:name":"Luessmitz",
    "wof:placetype":"neighbourhood"
},
  "geometry": {"coordinates":[13.40734,54.48862],"type":"Point"}
}