{
  "type": "Feature",
  "properties": {
    "gn:admin1_code":"2",
    "gn:admin2_code":"91.0",
    "gn:admin3_code":"9177.0",
    "gn:admin4_code":"9177115.0",
    "gn:asciiname":"Scheideck",
    "gn:country_code":"DE",
    "gn:dem":476,
    "gn:feature_class":"P",
    "gn:feature_code":"PPL",
    "gn:name":"Scheideck",
    "gn:population":0,
    "gn:timezone":"Europe/Berlin",
    "iso:country":"DE",
    "wof:name":"Scheideck",
    "wof:placetype":"neighbourhood"
},
  "geometry": {"coordinates":[12.13092,48.28892000000001],"type":"Point"}
}