{
  "type": "Feature",
  "properties": {
    "gn:admin1_code":"2.0",
    "gn:admin2_code":"093",
    "gn:admin3_code":"9372.0",
    "gn:admin4_code":"9372175.0",
    "gn:asciiname":"Zifling",
    "gn:country_code":"DE",
    "gn:dem":395,
    "gn:feature_class":"P",
    "gn:feature_code":"PPL",
    "gn:name":"Zifling",
    "gn:population":0,
    "gn:timezone":"Europe/Berlin",
    "iso:country":"DE",
    "wof:name":"Zifling",
    "wof:placetype":"neighbourhood"
},
  "geometry": {"coordinates":[12.67909,49.23713],"type":"Point"}
}