{
  "type": "Feature",
  "properties": {
    "gn:admin1_code":"13.0",
    "gn:admin2_code":"0.0",
    "gn:admin3_code":"14628.0",
    "gn:admin4_code":"14628080.0",
    "gn:asciiname":"Meusegast",
    "gn:country_code":"DE",
    "gn:dem":243,
    "gn:feature_class":"P",
    "gn:feature_code":"PPL",
    "gn:name":"Meusegast",
    "gn:population":0,
    "gn:timezone":"Europe/Berlin",
    "iso:country":"DE",
    "wof:name":"Meusegast",
    "wof:placetype":"neighbourhood"
},
  "geometry": {"coordinates":[13.87973,50.93083],"type":"Point"}
}