{
  "type": "Feature",
  "properties": {
    "gn:admin1_code":"14",
    "gn:admin2_code":"0.0",
    "gn:admin3_code":"15091.0",
    "gn:admin4_code":"15091020.0",
    "gn:asciiname":"Sackwitz",
    "gn:country_code":"DE",
    "gn:dem":121,
    "gn:feature_class":"P",
    "gn:feature_code":"PPL",
    "gn:name":"Sackwitz",
    "gn:population":0,
    "gn:timezone":"Europe/Berlin",
    "iso:country":"DE",
    "wof:name":"Sackwitz",
    "wof:placetype":"neighbourhood"
},
  "geometry": {"coordinates":[12.67566,51.72152],"type":"Point"}
}