{
  "type": "Feature",
  "properties": {
    "gn:admin1_code":"15",
    "gn:admin2_code":"0.0",
    "gn:admin3_code":"16077.0",
    "gn:admin4_code":"16077001.0",
    "gn:asciiname":"Drescha",
    "gn:country_code":"DE",
    "gn:dem":186,
    "gn:feature_class":"P",
    "gn:feature_code":"PPL",
    "gn:name":"Drescha",
    "gn:population":0,
    "gn:timezone":"Europe/Berlin",
    "iso:country":"DE",
    "name:und_x_variant":[
        "Altenburg Drescha",
        "Drescha"
    ],
    "wof:name":"Drescha",
    "wof:placetype":"neighbourhood"
},
  "geometry": {"coordinates":[12.4114,50.98895],"type":"Point"}
}