{
  "type": "Feature",
  "properties": {
    "iso:country":"DE",
    "wof:name":"Neuehrendfeld",
    "wof:placetype":"neighbourhood"
},
  "geometry": {"coordinates":[6.92512290129352,50.95578479982428],"type":"Point"}
}