{
  "type": "Feature",
  "properties": {
    "gn:admin1_code":"2",
    "gn:admin2_code":"94.0",
    "gn:admin3_code":"9479.0",
    "gn:admin4_code":"9479126.0",
    "gn:asciiname":"Rugersgrun",
    "gn:country_code":"DE",
    "gn:dem":570,
    "gn:feature_class":"P",
    "gn:feature_code":"PPL",
    "gn:name":"R\u00fcgersgr\u00fcn",
    "gn:population":0,
    "gn:timezone":"Europe/Berlin",
    "iso:country":"DE",
    "wof:name":"Rugersgrun",
    "wof:placetype":"neighbourhood"
},
  "geometry": {"coordinates":[12.05706,50.09463],"type":"Point"}
}