{
  "type": "Feature",
  "properties": {
    "gn:admin1_code":"2.0",
    "gn:admin2_code":"091",
    "gn:admin3_code":"9189.0",
    "gn:admin4_code":"9189140.0",
    "gn:asciiname":"Wiesen",
    "gn:country_code":"DE",
    "gn:dem":645,
    "gn:feature_class":"P",
    "gn:feature_code":"PPL",
    "gn:name":"Wiesen",
    "gn:population":0,
    "gn:timezone":"Europe/Berlin",
    "iso:country":"DE",
    "name:ceb_x_preferred":[
        "Wiesen"
    ],
    "name:deu_x_preferred":[
        "Wiesen"
    ],
    "name:epo_x_preferred":[
        "Wiesen"
    ],
    "name:fra_x_preferred":[
        "Wiesen"
    ],
    "name:ita_x_preferred":[
        "Wiesen"
    ],
    "name:lmo_x_preferred":[
        "Wiesen"
    ],
    "name:nld_x_preferred":[
        "Wiesen"
    ],
    "name:pol_x_preferred":[
        "Wiesen"
    ],
    "name:rus_x_preferred":[
        "\u0412\u0438\u0437\u0435\u043d"
    ],
    "name:spa_x_preferred":[
        "Wiesen"
    ],
    "name:swe_x_preferred":[
        "Wiesen"
    ],
    "name:ukr_x_preferred":[
        "\u0412\u0456\u0437\u0435\u043d"
    ],
    "name:vol_x_preferred":[
        "Wiesen"
    ],
    "wof:name":"Wiesen",
    "wof:placetype":"neighbourhood"
},
  "geometry": {"coordinates":[12.64663,47.76927],"type":"Point"}
}