{
  "type": "Feature",
  "properties": {
    "gn:admin1_code":"13",
    "gn:admin2_code":"0.0",
    "gn:admin3_code":"14625.0",
    "gn:admin4_code":"14625500.0",
    "gn:asciiname":"Schmerlitz",
    "gn:country_code":"DE",
    "gn:dem":142,
    "gn:feature_class":"P",
    "gn:feature_code":"PPL",
    "gn:name":"Schmerlitz",
    "gn:population":0,
    "gn:timezone":"Europe/Berlin",
    "iso:country":"DE",
    "name:hsb_x_preferred":[
        "Smjerd\u017aaca"
    ],
    "wof:name":"Schmerlitz",
    "wof:placetype":"neighbourhood"
},
  "geometry": {"coordinates":[14.21447,51.30256],"type":"Point"}
}