{
  "type": "Feature",
  "properties": {
    "gn:admin1_code":"13",
    "gn:admin2_code":"0.0",
    "gn:admin3_code":"14522.0",
    "gn:admin4_code":"14522460.0",
    "gn:asciiname":"Markersdorf",
    "gn:country_code":"DE",
    "gn:dem":261,
    "gn:feature_class":"P",
    "gn:feature_code":"PPL",
    "gn:name":"Markersdorf",
    "gn:population":0,
    "gn:timezone":"Europe/Berlin",
    "iso:country":"DE",
    "name:bak_x_preferred":[
        "\u041c\u0430\u0440\u043a\u0435\u0440\u0441\u0434\u043e\u0440\u0444"
    ],
    "name:cat_x_preferred":[
        "Markersdorf"
    ],
    "name:ceb_x_preferred":[
        "Markersdorf"
    ],
    "name:ces_x_preferred":[
        "Markersdorf"
    ],
    "name:deu_x_preferred":[
        "Markersdorf"
    ],
    "name:epo_x_preferred":[
        "Markersdorf"
    ],
    "name:est_x_preferred":[
        "Markersdorf"
    ],
    "name:eus_x_preferred":[
        "Markersdorf"
    ],
    "name:fas_x_preferred":[
        "\u0645\u0627\u0631\u06a9\u0631\u0633\u062f\u0648\u0631\u0641"
    ],
    "name:fra_x_preferred":[
        "Markersdorf"
    ],
    "name:hsb_x_preferred":[
        "Marko\u0107icy"
    ],
    "name:hun_x_preferred":[
        "Markersdorf"
    ],
    "name:ita_x_preferred":[
        "Markersdorf"
    ],
    "name:mkd_x_preferred":[
        "\u041c\u0430\u0440\u043a\u0435\u0440\u0441\u0434\u043e\u0440\u0444"
    ],
    "name:msa_x_preferred":[
        "Markersdorf"
    ],
    "name:nld_x_preferred":[
        "Markersdorf"
    ],
    "name:nor_x_preferred":[
        "Markersdorf"
    ],
    "name:pol_x_preferred":[
        "Markersdorf"
    ],
    "name:por_x_preferred":[
        "Markersdorf"
    ],
    "name:ron_x_preferred":[
        "Markersdorf"
    ],
    "name:rus_x_preferred":[
        "\u041c\u0430\u0440\u043a\u0435\u0440\u0441\u0434\u043e\u0440\u0444"
    ],
    "name:spa_x_preferred":[
        "Markersdorf"
    ],
    "name:srp_x_preferred":[
        "\u041c\u0430\u0440\u043a\u0435\u0440\u0441\u0434\u043e\u0440\u0444"
    ],
    "name:ukr_x_preferred":[
        "\u041c\u0430\u0440\u043a\u0435\u0440\u0441\u0434\u043e\u0440\u0444"
    ],
    "name:uzb_x_preferred":[
        "Markersdorf"
    ],
    "name:vie_x_preferred":[
        "Markersdorf"
    ],
    "name:vol_x_preferred":[
        "Markersdorf"
    ],
    "name:war_x_preferred":[
        "Markersdorf"
    ],
    "name:zho_x_preferred":[
        "\u9a6c\u5c14\u514b\u5c14\u65af\u591a\u592b"
    ],
    "wof:name":"Markersdorf",
    "wof:placetype":"neighbourhood"
},
  "geometry": {"coordinates":[12.66819,50.93003],"type":"Point"}
}