{
  "type": "Feature",
  "properties": {
    "gn:admin1_code":"13",
    "gn:admin2_code":"0.0",
    "gn:admin3_code":"14522.0",
    "gn:admin4_code":"14522460.0",
    "gn:asciiname":"Markersdorf",
    "gn:country_code":"DE",
    "gn:dem":261,
    "gn:feature_class":"P",
    "gn:feature_code":"PPL",
    "gn:name":"Markersdorf",
    "gn:population":0,
    "gn:timezone":"Europe/Berlin",
    "iso:country":"DE",
    "wof:name":"Markersdorf",
    "wof:placetype":"neighbourhood"
},
  "geometry": {"coordinates":[12.66819,50.93003],"type":"Point"}
}