{
  "type": "Feature",
  "properties": {
    "gn:admin1_code":"6",
    "gn:admin2_code":"0.0",
    "gn:admin3_code":"3354.0",
    "gn:admin4_code":"3354006.0",
    "gn:asciiname":"Metzingen",
    "gn:country_code":"DE",
    "gn:dem":36,
    "gn:feature_class":"P",
    "gn:feature_code":"PPL",
    "gn:name":"Metzingen",
    "gn:population":0,
    "gn:timezone":"Europe/Berlin",
    "iso:country":"DE",
    "name:als_x_preferred":[
        "Metzingen"
    ],
    "name:ara_x_preferred":[
        "\u0645\u062a\u0632\u0646\u062c\u0646"
    ],
    "name:azb_x_preferred":[
        "\u0645\u062a\u0633\u06cc\u0646\u0642\u0646"
    ],
    "name:aze_x_preferred":[
        "Metzingen"
    ],
    "name:bel_x_preferred":[
        "\u041c\u0435\u0446\u044b\u043d\u0433\u0435\u043d"
    ],
    "name:ceb_x_preferred":[
        "Metzingen"
    ],
    "name:cym_x_preferred":[
        "Metzingen"
    ],
    "name:deu_x_preferred":[
        "Metzingen"
    ],
    "name:ell_x_preferred":[
        "\u039c\u03ad\u03c4\u03c3\u03b9\u03bd\u03b3\u03ba\u03b5\u03bd"
    ],
    "name:epo_x_preferred":[
        "Metzingen"
    ],
    "name:fas_x_preferred":[
        "\u0645\u062a\u0633\u06cc\u0646\u06af\u0646"
    ],
    "name:fra_x_preferred":[
        "Metzingen"
    ],
    "name:hun_x_preferred":[
        "Metzingen"
    ],
    "name:ita_x_preferred":[
        "Metzingen"
    ],
    "name:lat_x_preferred":[
        "Metzingen"
    ],
    "name:lav_x_preferred":[
        "Mecingene"
    ],
    "name:lmo_x_preferred":[
        "Metzingen"
    ],
    "name:msa_x_preferred":[
        "Metzingen"
    ],
    "name:nld_x_preferred":[
        "Metzingen"
    ],
    "name:pol_x_preferred":[
        "Metzingen"
    ],
    "name:por_x_preferred":[
        "Metzingen"
    ],
    "name:ron_x_preferred":[
        "Metzingen"
    ],
    "name:rus_x_preferred":[
        "\u041c\u0435\u0442\u0446\u0438\u043d\u0433\u0435\u043d"
    ],
    "name:spa_x_preferred":[
        "Metzingen"
    ],
    "name:srp_x_preferred":[
        "\u041c\u0435\u0446\u0438\u043d\u0433\u0435\u043d"
    ],
    "name:swe_x_preferred":[
        "Metzingen"
    ],
    "name:szl_x_preferred":[
        "Metzingen"
    ],
    "name:tur_x_preferred":[
        "Metzingen"
    ],
    "name:ukr_x_preferred":[
        "\u041c\u0435\u0442\u0446\u0438\u043d\u0433\u0435\u043d"
    ],
    "name:uzb_x_preferred":[
        "Metzingen"
    ],
    "name:vie_x_preferred":[
        "Metzingen"
    ],
    "name:vol_x_preferred":[
        "Metzingen"
    ],
    "name:war_x_preferred":[
        "Metzingen"
    ],
    "name:zho_x_preferred":[
        "\u6885\u9752\u6839"
    ],
    "wof:name":"Metzingen",
    "wof:placetype":"neighbourhood"
},
  "geometry": {"coordinates":[10.96272,53.13004],"type":"Point"}
}