{
  "type": "Feature",
  "properties": {
    "gn:admin1_code":"2",
    "gn:admin2_code":"91.0",
    "gn:admin3_code":"9183.0",
    "gn:admin4_code":"9183143.0",
    "gn:asciiname":"Unterweinbach",
    "gn:country_code":"DE",
    "gn:dem":485,
    "gn:feature_class":"P",
    "gn:feature_code":"PPL",
    "gn:name":"Unterweinbach",
    "gn:population":0,
    "gn:timezone":"Europe/Berlin",
    "iso:country":"DE",
    "wof:name":"Unterweinbach",
    "wof:placetype":"neighbourhood"
},
  "geometry": {"coordinates":[12.4292,48.36145],"type":"Point"}
}