{
  "type": "Feature",
  "properties": {
    "gn:admin1_code":"13",
    "gn:admin2_code":"0.0",
    "gn:admin3_code":"14625.0",
    "gn:admin4_code":"14625490.0",
    "gn:asciiname":"Luppedubrau",
    "gn:cc2":"DE",
    "gn:country_code":"DE",
    "gn:dem":163,
    "gn:feature_class":"P",
    "gn:feature_code":"PPL",
    "gn:name":"Luppedubrau",
    "gn:population":0,
    "gn:timezone":"Europe/Berlin",
    "iso:country":"DE",
    "name:hsb_x_preferred":[
        "\u0141upjanska Dubrawka"
    ],
    "name:und_x_variant":[
        "Luppa-Dubrau",
        "Luppedubrau"
    ],
    "wof:name":"Luppedubrau",
    "wof:placetype":"neighbourhood"
},
  "geometry": {"coordinates":[14.38574,51.27513],"type":"Point"}
}