{
  "type": "Feature",
  "properties": {
    "gn:admin1_code":"1.0",
    "gn:admin2_code":"84.0",
    "gn:admin3_code":"8435.0",
    "gn:admin4_code":"8435045.0",
    "gn:asciiname":"Bitzenhofen",
    "gn:country_code":"DE",
    "gn:dem":458,
    "gn:feature_class":"P",
    "gn:feature_code":"PPL",
    "gn:name":"Bitzenhofen",
    "gn:population":0,
    "gn:timezone":"Europe/Berlin",
    "iso:country":"DE",
    "wof:name":"Bitzenhofen",
    "wof:placetype":"neighbourhood"
},
  "geometry": {"coordinates":[9.46331,47.73519],"type":"Point"}
}