{
  "type": "Feature",
  "properties": {
    "gn:admin1_code":"2.0",
    "gn:admin2_code":"93.0",
    "gn:admin3_code":"9373.0",
    "gn:admin4_code":"9373121.0",
    "gn:asciiname":"Arnsdorf",
    "gn:country_code":"DE",
    "gn:dem":515,
    "gn:feature_class":"P",
    "gn:feature_code":"PPL",
    "gn:name":"Arnsdorf",
    "gn:population":0,
    "gn:timezone":"Europe/Berlin",
    "iso:country":"DE",
    "name:bak_x_preferred":[
        "\u0410\u0440\u043d\u0441\u0434\u043e\u0440\u0444"
    ],
    "name:cat_x_preferred":[
        "Arnsdorf"
    ],
    "name:deu_x_preferred":[
        "Arnsdorf"
    ],
    "name:epo_x_preferred":[
        "Arnsdorf"
    ],
    "name:est_x_preferred":[
        "Arnsdorfi vald"
    ],
    "name:eus_x_preferred":[
        "Arnsdorf"
    ],
    "name:fas_x_preferred":[
        "\u0622\u0631\u0646\u0633\u062f\u0648\u0631\u0641"
    ],
    "name:fra_x_preferred":[
        "Arnsdorf"
    ],
    "name:hsb_x_preferred":[
        "Warno\u0107icy"
    ],
    "name:hun_x_preferred":[
        "Arnsdorf"
    ],
    "name:ita_x_preferred":[
        "Arnsdorf"
    ],
    "name:kaz_x_preferred":[
        "\u0410\u0440\u043d\u0441\u0434\u043e\u0440\u0444"
    ],
    "name:kir_x_preferred":[
        "\u0410\u0440\u043d\u0441\u0434\u043e\u0440\u0444"
    ],
    "name:mkd_x_preferred":[
        "\u0410\u0440\u043d\u0441\u0434\u043e\u0440\u0444"
    ],
    "name:msa_x_preferred":[
        "Arnsdorf"
    ],
    "name:nld_x_preferred":[
        "Arnsdorf"
    ],
    "name:pol_x_preferred":[
        "Arnsdorf"
    ],
    "name:por_x_preferred":[
        "Arnsdorf"
    ],
    "name:ron_x_preferred":[
        "Arnsdorf"
    ],
    "name:rus_x_preferred":[
        "\u0410\u0440\u043d\u0441\u0434\u043e\u0440\u0444"
    ],
    "name:spa_x_preferred":[
        "Arnsdorf"
    ],
    "name:srp_x_preferred":[
        "\u0410\u0440\u043d\u0441\u0434\u043e\u0440\u0444"
    ],
    "name:ukr_x_preferred":[
        "\u0410\u0440\u043d\u0441\u0434\u043e\u0440\u0444"
    ],
    "name:und_x_variant":[
        "Arnstorf"
    ],
    "name:uzb_x_preferred":[
        "Arnsdorf"
    ],
    "name:vie_x_preferred":[
        "Arnsdorf"
    ],
    "name:vol_x_preferred":[
        "Arnsdorf"
    ],
    "name:war_x_preferred":[
        "Arnsdorf"
    ],
    "name:zho_x_preferred":[
        "\u963f\u5c14\u6069\u65af\u591a\u592b"
    ],
    "wof:name":"Arnsdorf",
    "wof:placetype":"neighbourhood"
},
  "geometry": {"coordinates":[11.59083,49.00202],"type":"Point"}
}