{
  "type": "Feature",
  "properties": {
    "gn:admin1_code":"2.0",
    "gn:admin2_code":"93.0",
    "gn:admin3_code":"9373.0",
    "gn:admin4_code":"9373121.0",
    "gn:asciiname":"Arnsdorf",
    "gn:country_code":"DE",
    "gn:dem":515,
    "gn:feature_class":"P",
    "gn:feature_code":"PPL",
    "gn:name":"Arnsdorf",
    "gn:population":0,
    "gn:timezone":"Europe/Berlin",
    "iso:country":"DE",
    "name:und_x_variant":[
        "Arnstorf",
        "Arnsdorf"
    ],
    "wof:name":"Arnsdorf",
    "wof:placetype":"neighbourhood"
},
  "geometry": {"coordinates":[11.59083,49.00202],"type":"Point"}
}