{
  "type": "Feature",
  "properties": {
    "gn:admin1_code":"6.0",
    "gn:admin2_code":"0.0",
    "gn:admin3_code":"3351.0",
    "gn:admin4_code":"3351004.0",
    "gn:asciiname":"Bleckmar",
    "gn:country_code":"DE",
    "gn:dem":68,
    "gn:feature_class":"P",
    "gn:feature_code":"PPL",
    "gn:name":"Bleckmar",
    "gn:population":0,
    "gn:timezone":"Europe/Berlin",
    "iso:country":"DE",
    "name:ceb_x_preferred":[
        "Bleckmar"
    ],
    "name:deu_x_preferred":[
        "Bleckmar"
    ],
    "name:fas_x_preferred":[
        "\u0628\u0644\u06a9\u0645\u0627\u0631"
    ],
    "name:hun_x_preferred":[
        "Bleckmar"
    ],
    "wof:name":"Bleckmar",
    "wof:placetype":"neighbourhood"
},
  "geometry": {"coordinates":[9.93387,52.82621],"type":"Point"}
}