{
  "type": "Feature",
  "properties": {
    "gn:admin1_code":"6",
    "gn:admin2_code":"0.0",
    "gn:admin3_code":"3357.0",
    "gn:admin4_code":"3357051.0",
    "gn:asciiname":"Schwitschen",
    "gn:country_code":"DE",
    "gn:dem":57,
    "gn:feature_class":"P",
    "gn:feature_code":"PPL",
    "gn:name":"Schwitschen",
    "gn:population":0,
    "gn:timezone":"Europe/Berlin",
    "iso:country":"DE",
    "wof:name":"Schwitschen",
    "wof:placetype":"neighbourhood"
},
  "geometry": {"coordinates":[9.60198,52.99985],"type":"Point"}
}