{
  "type": "Feature",
  "properties": {
    "gn:admin1_code":"13",
    "gn:admin2_code":"0.0",
    "gn:admin3_code":"14626.0",
    "gn:admin4_code":"14626250.0",
    "gn:asciiname":"Skerbersdorf",
    "gn:country_code":"DE",
    "gn:dem":127,
    "gn:feature_class":"P",
    "gn:feature_code":"PPL",
    "gn:name":"Skerbersdorf",
    "gn:population":0,
    "gn:timezone":"Europe/Berlin",
    "iso:country":"DE",
    "name:hsb_x_preferred":[
        "Skarbi\u0161ecy"
    ],
    "wof:name":"Skerbersdorf",
    "wof:placetype":"neighbourhood"
},
  "geometry": {"coordinates":[14.81153,51.50158],"type":"Point"}
}