{
  "type": "Feature",
  "properties": {
    "gn:admin1_code":"2",
    "gn:admin2_code":"91.0",
    "gn:admin3_code":"9187.0",
    "gn:admin4_code":"9187179.0",
    "gn:asciiname":"Harrain",
    "gn:country_code":"DE",
    "gn:dem":515,
    "gn:feature_class":"P",
    "gn:feature_code":"PPL",
    "gn:name":"Harrain",
    "gn:population":0,
    "gn:timezone":"Europe/Berlin",
    "iso:country":"DE",
    "wof:name":"Harrain",
    "wof:placetype":"neighbourhood"
},
  "geometry": {"coordinates":[12.04407,47.94328],"type":"Point"}
}