{
  "type": "Feature",
  "properties": {
    "gn:admin1_code":"2",
    "gn:admin2_code":"91.0",
    "gn:admin3_code":"9187.0",
    "gn:admin4_code":"9187163.0",
    "gn:asciiname":"Haidham",
    "gn:country_code":"DE",
    "gn:dem":505,
    "gn:feature_class":"P",
    "gn:feature_code":"PPL",
    "gn:name":"Haidham",
    "gn:population":0,
    "gn:timezone":"Europe/Berlin",
    "iso:country":"DE",
    "wof:name":"Haidham",
    "wof:placetype":"neighbourhood"
},
  "geometry": {"coordinates":[12.21439,47.88465],"type":"Point"}
}