{
  "type": "Feature",
  "properties": {
    "gn:admin1_code":"15",
    "gn:admin2_code":"0.0",
    "gn:admin3_code":"16077.0",
    "gn:admin4_code":"16077005.0",
    "gn:asciiname":"Kleintreben",
    "gn:country_code":"DE",
    "gn:dem":161,
    "gn:feature_class":"P",
    "gn:feature_code":"PPL",
    "gn:name":"Kleintreben",
    "gn:population":0,
    "gn:timezone":"Europe/Berlin",
    "iso:country":"DE",
    "wof:name":"Kleintreben",
    "wof:placetype":"neighbourhood"
},
  "geometry": {"coordinates":[12.45884,51.05269000000001],"type":"Point"}
}