{
  "type": "Feature",
  "properties": {
    "gn:admin1_code":"6",
    "gn:admin2_code":"0.0",
    "gn:admin3_code":"3353.0",
    "gn:admin4_code":"3353028.0",
    "gn:asciiname":"Rahmstorf",
    "gn:country_code":"DE",
    "gn:dem":35,
    "gn:feature_class":"P",
    "gn:feature_code":"PPL",
    "gn:name":"Rahmstorf",
    "gn:population":0,
    "gn:timezone":"Europe/Berlin",
    "iso:country":"DE",
    "wof:name":"Rahmstorf",
    "wof:placetype":"neighbourhood"
},
  "geometry": {"coordinates":[9.65957,53.40196],"type":"Point"}
}