{
  "type": "Feature",
  "properties": {
    "gn:admin1_code":"2",
    "gn:admin2_code":"92.0",
    "gn:admin3_code":"9277.0",
    "gn:admin4_code":"9277153.0",
    "gn:asciiname":"Schachten",
    "gn:country_code":"DE",
    "gn:dem":472,
    "gn:feature_class":"P",
    "gn:feature_code":"PPL",
    "gn:name":"Schachten",
    "gn:population":0,
    "gn:timezone":"Europe/Berlin",
    "iso:country":"DE",
    "name:bar_x_preferred":[
        "Schachtn"
    ],
    "name:ces_x_preferred":[
        "Schachten"
    ],
    "name:deu_x_preferred":[
        "Schachten"
    ],
    "wof:name":"Schachten",
    "wof:placetype":"neighbourhood"
},
  "geometry": {"coordinates":[12.80801,48.37369],"type":"Point"}
}