{
  "type": "Feature",
  "properties": {
    "gn:admin1_code":"7",
    "gn:admin2_code":"57.0",
    "gn:admin3_code":"5770.0",
    "gn:admin4_code":"5770040.0",
    "gn:asciiname":"OErtlingerhausen",
    "gn:country_code":"DE",
    "gn:dem":40,
    "gn:feature_class":"P",
    "gn:feature_code":"PPL",
    "gn:name":"\u00d6rtlingerhausen",
    "gn:population":0,
    "gn:timezone":"Europe/Berlin",
    "iso:country":"DE",
    "wof:name":"OErtlingerhausen",
    "wof:placetype":"neighbourhood"
},
  "geometry": {"coordinates":[8.62609,52.44752],"type":"Point"}
}