{
  "type": "Feature",
  "properties": {
    "gn:admin1_code":"2",
    "gn:admin2_code":"91.0",
    "gn:admin3_code":"9171.0",
    "gn:admin4_code":"9171126.0",
    "gn:asciiname":"Steinbach",
    "gn:country_code":"DE",
    "gn:dem":387,
    "gn:feature_class":"P",
    "gn:feature_code":"PPL",
    "gn:name":"Steinbach",
    "gn:population":0,
    "gn:timezone":"Europe/Berlin",
    "iso:country":"DE",
    "name:als_x_preferred":[
        "Steinbach"
    ],
    "name:bre_x_preferred":[
        "Steinbach"
    ],
    "name:ceb_x_preferred":[
        "Steinbach"
    ],
    "name:ces_x_preferred":[
        "Steinbach"
    ],
    "name:deu_x_preferred":[
        "Steinbach"
    ],
    "name:epo_x_preferred":[
        "Steinbach"
    ],
    "name:fra_x_preferred":[
        "Steinbach"
    ],
    "name:heb_x_preferred":[
        "\u05e1\u05d8\u05d9\u05d9\u05d1\u05d0\u05da"
    ],
    "name:hun_x_preferred":[
        "Steinbach"
    ],
    "name:ita_x_preferred":[
        "Steinbach"
    ],
    "name:jpn_x_preferred":[
        "\u30b7\u30e5\u30bf\u30a4\u30f3\u30d0\u30c3\u30cf"
    ],
    "name:nld_x_preferred":[
        "Steinbach"
    ],
    "name:pol_x_preferred":[
        "Steinbach"
    ],
    "name:ron_x_preferred":[
        "Steinbach"
    ],
    "name:rus_x_preferred":[
        "\u0428\u0442\u0430\u0439\u043d\u0431\u0430\u0445"
    ],
    "name:spa_x_preferred":[
        "Steinbach"
    ],
    "name:swe_x_preferred":[
        "Steinbach"
    ],
    "name:vol_x_preferred":[
        "Steinbach"
    ],
    "wof:name":"Steinbach",
    "wof:placetype":"neighbourhood"
},
  "geometry": {"coordinates":[12.77612,48.26718],"type":"Point"}
}