{
  "type": "Feature",
  "properties": {
    "gn:admin1_code":"14.0",
    "gn:admin2_code":"0.0",
    "gn:admin3_code":"15085.0",
    "gn:admin4_code":"15085185.0",
    "gn:asciiname":"Aderstedt",
    "gn:country_code":"DE",
    "gn:dem":95,
    "gn:feature_class":"P",
    "gn:feature_code":"PPL",
    "gn:name":"Aderstedt",
    "gn:population":0,
    "gn:timezone":"Europe/Berlin",
    "iso:country":"DE",
    "wof:name":"Aderstedt",
    "wof:placetype":"neighbourhood"
},
  "geometry": {"coordinates":[10.99731,52.03085],"type":"Point"}
}