{
  "type": "Feature",
  "properties": {
    "gn:admin1_code":"11",
    "gn:admin2_code":"0.0",
    "gn:admin3_code":"12067.0",
    "gn:admin4_code":"12067357.0",
    "gn:asciiname":"Moebiskruge",
    "gn:country_code":"DE",
    "gn:dem":84,
    "gn:feature_class":"P",
    "gn:feature_code":"PPL",
    "gn:name":"M\u00f6biskruge",
    "gn:population":0,
    "gn:timezone":"Europe/Berlin",
    "iso:country":"DE",
    "wof:name":"Moebiskruge",
    "wof:placetype":"neighbourhood"
},
  "geometry": {"coordinates":[14.59168,52.10116],"type":"Point"}
}