{
  "type": "Feature",
  "properties": {
    "gn:admin1_code":"1",
    "gn:admin2_code":"83.0",
    "gn:admin3_code":"8336.0",
    "gn:admin4_code":"8336079.0",
    "gn:asciiname":"Ruttehof",
    "gn:country_code":"DE",
    "gn:dem":835,
    "gn:feature_class":"P",
    "gn:feature_code":"PPL",
    "gn:name":"R\u00fcttehof",
    "gn:population":0,
    "gn:timezone":"Europe/Berlin",
    "iso:country":"DE",
    "wof:name":"Ruttehof",
    "wof:placetype":"neighbourhood"
},
  "geometry": {"coordinates":[7.96123,47.80353],"type":"Point"}
}