{
  "type": "Feature",
  "properties": {
    "gn:admin1_code":"1",
    "gn:admin2_code":"84.0",
    "gn:admin3_code":"8435.0",
    "gn:admin4_code":"8435045.0",
    "gn:asciiname":"Rammetshofen",
    "gn:country_code":"DE",
    "gn:dem":453,
    "gn:feature_class":"P",
    "gn:feature_code":"PPL",
    "gn:name":"Rammetshofen",
    "gn:population":0,
    "gn:timezone":"Europe/Berlin",
    "iso:country":"DE",
    "name:deu_x_preferred":[
        "Rammetshofen"
    ],
    "wof:name":"Rammetshofen",
    "wof:placetype":"neighbourhood"
},
  "geometry": {"coordinates":[9.46806,47.71636],"type":"Point"}
}