{
  "type": "Feature",
  "properties": {
    "gn:admin1_code":"2",
    "gn:admin2_code":"95.0",
    "gn:admin3_code":"9572.0",
    "gn:admin4_code":"9572137.0",
    "gn:asciiname":"Kaswasser",
    "gn:country_code":"DE",
    "gn:dem":419,
    "gn:feature_class":"P",
    "gn:feature_code":"PPL",
    "gn:name":"K\u00e4swasser",
    "gn:population":0,
    "gn:timezone":"Europe/Berlin",
    "iso:country":"DE",
    "wof:name":"Kaswasser",
    "wof:placetype":"neighbourhood"
},
  "geometry": {"coordinates":[11.15107,49.5582],"type":"Point"}
}