{
  "type": "Feature",
  "properties": {
    "gn:admin1_code":"2",
    "gn:admin2_code":"92.0",
    "gn:admin3_code":"9275.0",
    "gn:admin4_code":"9275151.0",
    "gn:asciiname":"Schnelling",
    "gn:country_code":"DE",
    "gn:dem":331,
    "gn:feature_class":"P",
    "gn:feature_code":"PPL",
    "gn:name":"Schnelling",
    "gn:population":0,
    "gn:timezone":"Europe/Berlin",
    "iso:country":"DE",
    "wof:name":"Schnelling",
    "wof:placetype":"neighbourhood"
},
  "geometry": {"coordinates":[13.34074,48.6546],"type":"Point"}
}