{
  "type": "Feature",
  "properties": {
    "gn:admin1_code":"7.0",
    "gn:admin2_code":"59.0",
    "gn:admin3_code":"5974.0",
    "gn:admin4_code":"5974016.0",
    "gn:asciiname":"Boeckum",
    "gn:country_code":"DE",
    "gn:dem":84,
    "gn:feature_class":"P",
    "gn:feature_code":"PPL",
    "gn:name":"B\u00f6ckum",
    "gn:population":0,
    "gn:timezone":"Europe/Berlin",
    "iso:country":"DE",
    "wof:name":"Boeckum",
    "wof:placetype":"neighbourhood"
},
  "geometry": {"coordinates":[8.25725,51.63415],"type":"Point"}
}