{
  "type": "Feature",
  "properties": {
    "gn:admin1_code":"12",
    "gn:admin2_code":"0.0",
    "gn:admin3_code":"13072.0",
    "gn:admin4_code":"13072029.0",
    "gn:asciiname":"Waldeck",
    "gn:country_code":"DE",
    "gn:dem":45,
    "gn:feature_class":"P",
    "gn:feature_code":"PPL",
    "gn:name":"Waldeck",
    "gn:population":0,
    "gn:timezone":"Europe/Berlin",
    "iso:country":"DE",
    "name:bre_x_preferred":[
        "Waldeck"
    ],
    "name:bul_x_preferred":[
        "\u0412\u0430\u043b\u0434\u0435\u043a"
    ],
    "name:ceb_x_preferred":[
        "Waldeck"
    ],
    "name:ces_x_preferred":[
        "Waldeck"
    ],
    "name:deu_x_preferred":[
        "Waldeck"
    ],
    "name:epo_x_preferred":[
        "Waldeck"
    ],
    "name:fra_x_preferred":[
        "Waldeck"
    ],
    "name:hun_x_preferred":[
        "Waldeck"
    ],
    "name:jpn_x_preferred":[
        "\u30ef\u30eb\u30c7\u30c3\u30af"
    ],
    "name:nld_x_preferred":[
        "Waldeck"
    ],
    "name:nor_x_preferred":[
        "Waldeck"
    ],
    "name:pol_x_preferred":[
        "Waldeck"
    ],
    "name:por_x_preferred":[
        "Waldeck"
    ],
    "name:rus_x_preferred":[
        "\u0412\u0430\u043b\u044c\u0434\u0435\u043a"
    ],
    "name:spa_x_preferred":[
        "Waldeck"
    ],
    "name:swe_x_preferred":[
        "Waldeck"
    ],
    "name:vol_x_preferred":[
        "Waldeck"
    ],
    "wof:name":"Waldeck",
    "wof:placetype":"neighbourhood"
},
  "geometry": {"coordinates":[12.21394,54.03555],"type":"Point"}
}