{
  "type": "Feature",
  "properties": {
    "gn:admin1_code":"6",
    "gn:admin2_code":"0.0",
    "gn:admin3_code":"3252.0",
    "gn:admin4_code":"3252005.0",
    "gn:asciiname":"Hagenohsen",
    "gn:country_code":"DE",
    "gn:dem":73,
    "gn:feature_class":"P",
    "gn:feature_code":"PPL",
    "gn:name":"Hagenohsen",
    "gn:population":0,
    "gn:timezone":"Europe/Berlin",
    "iso:country":"DE",
    "wof:name":"Hagenohsen",
    "wof:placetype":"neighbourhood"
},
  "geometry": {"coordinates":[9.39657,52.05281],"type":"Point"}
}