{
  "type": "Feature",
  "properties": {
    "iso:country":"DE",
    "name:ceb_x_preferred":[
        "Isle Martin"
    ],
    "name:deu_x_preferred":[
        "Berliner Vorstadt"
    ],
    "name:fra_x_preferred":[
        "Martin"
    ],
    "name:gla_x_preferred":[
        "Eilean Mh\u00e0rtainn"
    ],
    "name:gle_x_preferred":[
        "Eilean Mh\u00e1rtainn"
    ],
    "name:nno_x_preferred":[
        "Isle Martin"
    ],
    "name:swe_x_preferred":[
        "Isle Martin"
    ],
    "name:zho_x_preferred":[
        "\u99ac\u4e01\u5cf6"
    ],
    "qs:gn_adm0_cc":"DE",
    "qs:gn_fcode":"PPL",
    "qs:gn_local":2852458,
    "qs:gn_namadm1":"11",
    "qs:gn_name":"Berliner Vorstadt",
    "qs:local_max":6891,
    "qs:local_sum":26199,
    "qs:localhoods":32,
    "qs:name":"Berliner Vorstadt",
    "qs:name_adm0":"Deutschland",
    "qs:name_adm1":"Bundesland Brandenburg",
    "qs:name_adm2":"Stadtkreis Potsdam",
    "qs:name_lau":"Gemeinde Potsdam",
    "qs:name_local":"Potsdam",
    "qs:photo_max":315,
    "qs:photo_sum":1427,
    "qs:placetype":"Suburb",
    "qs:quad_count":48,
    "qs:woe_adm0":23424829,
    "qs:woe_adm1":2345491,
    "qs:woe_adm2":12597070,
    "qs:woe_lau":12632873,
    "qs:woe_local":685783,
    "qs:woe_ver":"7.10.0",
    "wof:lang":[
        "ger"
    ],
    "wof:name":"Berliner Vorstadt",
    "wof:placetype":"neighbourhood"
},
  "geometry": {"coordinates":[13.079391,52.411931],"type":"Point"}
}