{
  "type": "Feature",
  "properties": {
    "gn:admin1_code":"2",
    "gn:admin2_code":"97.0",
    "gn:admin3_code":"9778.0",
    "gn:admin4_code":"9778144.0",
    "gn:asciiname":"Kornhofen",
    "gn:country_code":"DE",
    "gn:dem":754,
    "gn:feature_class":"P",
    "gn:feature_code":"PPL",
    "gn:name":"Kornhofen",
    "gn:population":0,
    "gn:timezone":"Europe/Berlin",
    "iso:country":"DE",
    "wof:name":"Kornhofen",
    "wof:placetype":"neighbourhood"
},
  "geometry": {"coordinates":[10.23061,47.85401],"type":"Point"}
}