{
  "type": "Feature",
  "properties": {
    "gn:admin1_code":"1",
    "gn:admin2_code":"83.0",
    "gn:admin3_code":"8326.0",
    "gn:admin4_code":"8326075.0",
    "gn:asciiname":"Uberauchen",
    "gn:country_code":"DE",
    "gn:dem":695,
    "gn:feature_class":"P",
    "gn:feature_code":"PPL",
    "gn:name":"\u00dcberauchen",
    "gn:population":0,
    "gn:timezone":"Europe/Berlin",
    "iso:country":"DE",
    "wof:name":"Uberauchen",
    "wof:placetype":"neighbourhood"
},
  "geometry": {"coordinates":[8.45398,48.01186],"type":"Point"}
}