{
  "type": "Feature",
  "properties": {
    "gn:admin1_code":"1",
    "gn:admin2_code":"82.0",
    "gn:admin3_code":"8236.0",
    "gn:admin4_code":"8236040.0",
    "gn:asciiname":"Muhlhausen an der Enz",
    "gn:country_code":"DE",
    "gn:dem":217,
    "gn:feature_class":"P",
    "gn:feature_code":"PPL",
    "gn:name":"M\u00fchlhausen an der Enz",
    "gn:population":0,
    "gn:timezone":"Europe/Berlin",
    "iso:country":"DE",
    "name:und_x_variant":[
        "M\u00fchlhausen",
        "M\u00fchlhausen an der Enz"
    ],
    "wof:name":"Muhlhausen an der Enz",
    "wof:placetype":"neighbourhood"
},
  "geometry": {"coordinates":[8.89151,48.93993],"type":"Point"}
}