{
  "type": "Feature",
  "properties": {
    "gn:admin1_code":"13.0",
    "gn:admin2_code":"00",
    "gn:admin3_code":"14729.0",
    "gn:admin4_code":"14729050.0",
    "gn:asciiname":"Wyhra",
    "gn:country_code":"DE",
    "gn:dem":154,
    "gn:feature_class":"P",
    "gn:feature_code":"PPL",
    "gn:name":"Wyhra",
    "gn:population":0,
    "gn:timezone":"Europe/Berlin",
    "iso:country":"DE",
    "name:ceb_x_preferred":[
        "Wyhra"
    ],
    "name:chv_x_preferred":[
        "\u0412\u0438\u0440\u0430"
    ],
    "name:deu_x_preferred":[
        "Wyhra"
    ],
    "name:mkd_x_preferred":[
        "\u0412\u0438\u0440\u0430"
    ],
    "name:rus_x_preferred":[
        "\u0412\u0438\u0440\u0430"
    ],
    "name:und_x_variant":[
        "Neukirchen-Wyhra"
    ],
    "wof:name":"Wyhra",
    "wof:placetype":"neighbourhood"
},
  "geometry": {"coordinates":[12.51396,51.0792],"type":"Point"}
}