{
  "type": "Feature",
  "properties": {
    "gn:admin1_code":"2",
    "gn:admin2_code":"93.0",
    "gn:admin3_code":"9371.0",
    "gn:admin4_code":"9371131.0",
    "gn:asciiname":"Hermannsberg",
    "gn:country_code":"DE",
    "gn:dem":488,
    "gn:feature_class":"P",
    "gn:feature_code":"PPL",
    "gn:name":"Hermannsberg",
    "gn:population":0,
    "gn:timezone":"Europe/Berlin",
    "iso:country":"DE",
    "name:ceb_x_preferred":[
        "Hermannsberg"
    ],
    "name:deu_x_preferred":[
        "Hermannsberg"
    ],
    "name:epo_x_preferred":[
        "Hermannsberg"
    ],
    "name:swe_x_preferred":[
        "Hermannsberg"
    ],
    "wof:name":"Hermannsberg",
    "wof:placetype":"neighbourhood"
},
  "geometry": {"coordinates":[11.7419,49.43855],"type":"Point"}
}