{
  "type": "Feature",
  "properties": {
    "gn:admin1_code":"6",
    "gn:admin2_code":"0.0",
    "gn:admin3_code":"3155.0",
    "gn:admin4_code":"3155011.0",
    "gn:asciiname":"Levershausen",
    "gn:country_code":"DE",
    "gn:dem":263,
    "gn:feature_class":"P",
    "gn:feature_code":"PPL",
    "gn:name":"Levershausen",
    "gn:population":0,
    "gn:timezone":"Europe/Berlin",
    "iso:country":"DE",
    "wof:name":"Levershausen",
    "wof:placetype":"neighbourhood"
},
  "geometry": {"coordinates":[10.01067,51.66382],"type":"Point"}
}