{
  "type": "Feature",
  "properties": {
    "gn:admin1_code":"7.0",
    "gn:admin2_code":"057",
    "gn:admin3_code":"5766.0",
    "gn:admin4_code":"5766036.0",
    "gn:asciiname":"Westorf",
    "gn:country_code":"DE",
    "gn:dem":205,
    "gn:feature_class":"P",
    "gn:feature_code":"PPL",
    "gn:name":"Westorf",
    "gn:population":0,
    "gn:timezone":"Europe/Berlin",
    "iso:country":"DE",
    "wof:name":"Westorf",
    "wof:placetype":"neighbourhood"
},
  "geometry": {"coordinates":[8.9197,52.10608],"type":"Point"}
}