{
  "type": "Feature",
  "properties": {
    "gn:admin1_code":"1",
    "gn:admin2_code":"83.0",
    "gn:admin3_code":"8335.0",
    "gn:admin4_code":"8335025.0",
    "gn:asciiname":"Hornstaad",
    "gn:country_code":"DE",
    "gn:dem":417,
    "gn:feature_class":"P",
    "gn:feature_code":"PPL",
    "gn:name":"Hornstaad",
    "gn:population":0,
    "gn:timezone":"Europe/Berlin",
    "iso:country":"DE",
    "wof:name":"Hornstaad",
    "wof:placetype":"neighbourhood"
},
  "geometry": {"coordinates":[8.99669,47.69251],"type":"Point"}
}