{
  "type": "Feature",
  "properties": {
    "gn:admin1_code":"2",
    "gn:admin2_code":"96.0",
    "gn:admin3_code":"9675.0",
    "gn:admin4_code":"9675178.0",
    "gn:asciiname":"Reupelsdorf",
    "gn:country_code":"DE",
    "gn:dem":213,
    "gn:feature_class":"P",
    "gn:feature_code":"PPL",
    "gn:name":"Reupelsdorf",
    "gn:population":0,
    "gn:timezone":"Europe/Berlin",
    "iso:country":"DE",
    "wof:name":"Reupelsdorf",
    "wof:placetype":"neighbourhood"
},
  "geometry": {"coordinates":[10.29148,49.81367],"type":"Point"}
}