{
  "type": "Feature",
  "properties": {
    "gn:admin1_code":"2",
    "gn:admin2_code":"97.0",
    "gn:admin3_code":"9774.0",
    "gn:admin4_code":"9774189.0",
    "gn:asciiname":"Sausenthal",
    "gn:country_code":"DE",
    "gn:dem":504,
    "gn:feature_class":"P",
    "gn:feature_code":"PPL",
    "gn:name":"Sausenthal",
    "gn:population":0,
    "gn:timezone":"Europe/Berlin",
    "iso:country":"DE",
    "wof:name":"Sausenthal",
    "wof:placetype":"neighbourhood"
},
  "geometry": {"coordinates":[10.31667,48.31667],"type":"Point"}
}