{
  "type": "Feature",
  "properties": {
    "gn:admin1_code":"7",
    "gn:admin2_code":"57.0",
    "gn:admin3_code":"5770.0",
    "gn:admin4_code":"5770028.0",
    "gn:asciiname":"Heimsen",
    "gn:country_code":"DE",
    "gn:dem":38,
    "gn:feature_class":"P",
    "gn:feature_code":"PPL",
    "gn:name":"Heimsen",
    "gn:population":0,
    "gn:timezone":"Europe/Berlin",
    "iso:country":"DE",
    "wof:name":"Heimsen",
    "wof:placetype":"neighbourhood"
},
  "geometry": {"coordinates":[9.05559,52.46648],"type":"Point"}
}