{
  "type": "Feature",
  "properties": {
    "gn:admin1_code":"2.0",
    "gn:admin2_code":"91.0",
    "gn:admin3_code":"9189.0",
    "gn:admin4_code":"9189140.0",
    "gn:asciiname":"Zell",
    "gn:country_code":"DE",
    "gn:dem":665,
    "gn:feature_class":"P",
    "gn:feature_code":"PPL",
    "gn:name":"Zell",
    "gn:population":0,
    "gn:timezone":"Europe/Berlin",
    "iso:country":"DE",
    "wof:name":"Zell",
    "wof:placetype":"neighbourhood"
},
  "geometry": {"coordinates":[12.66569,47.7568],"type":"Point"}
}