{
  "type": "Feature",
  "properties": {
    "gn:admin1_code":"2",
    "gn:admin2_code":"91.0",
    "gn:admin3_code":"9188.0",
    "gn:admin4_code":"9188145.0",
    "gn:asciiname":"Schluifeld",
    "gn:country_code":"DE",
    "gn:dem":580,
    "gn:feature_class":"P",
    "gn:feature_code":"PPLL",
    "gn:name":"Schluifeld",
    "gn:population":0,
    "gn:timezone":"Europe/Berlin",
    "iso:country":"DE",
    "wof:name":"Schluifeld",
    "wof:placetype":"neighbourhood"
},
  "geometry": {"coordinates":[11.21914,48.08258],"type":"Point"}
}