{
  "type": "Feature",
  "properties": {
    "gn:country":"DE",
    "gn:fcode":"PPL",
    "gn:population":170,
    "iso:country":"DE",
    "name:bak_x_preferred":[
        "\u0411\u0440\u0435\u0437\u0435\u043d"
    ],
    "name:ceb_x_preferred":[
        "Br\u00e4sen"
    ],
    "name:deu_x_preferred":[
        "Br\u00e4sen"
    ],
    "name:epo_x_preferred":[
        "Br\u00e4sen"
    ],
    "name:fas_x_preferred":[
        "\u0628\u0631\u0632\u0646"
    ],
    "name:kir_x_preferred":[
        "\u0411\u0440\u0435\u0437\u0435\u043d"
    ],
    "name:mkd_x_preferred":[
        "\u0411\u0440\u0435\u0437\u0435\u043d"
    ],
    "name:nld_x_preferred":[
        "Br\u00e4sen"
    ],
    "name:por_x_preferred":[
        "Br\u00e4sen"
    ],
    "name:ron_x_preferred":[
        "Br\u00e4sen"
    ],
    "name:rus_x_preferred":[
        "\u0411\u0440\u0435\u0437\u0435\u043d"
    ],
    "name:uzb_x_preferred":[
        "Br\u00e4sen"
    ],
    "name:vie_x_preferred":[
        "Br\u00e4sen"
    ],
    "name:vol_x_preferred":[
        "Br\u00e4sen"
    ],
    "qs_pg:aaroncc":"DE",
    "qs_pg:gn_country":"DE",
    "qs_pg:gn_fcode":"PPL",
    "qs_pg:gn_pop":170,
    "qs_pg:name":"Br\u00e4sen",
    "qs_pg:name_adm0":"Deutschland",
    "qs_pg:name_adm1":"Sachsen-Anhalt",
    "qs_pg:photos_9r":0,
    "qs_pg:photos_sr":0,
    "qs_pg:pop_sr":1,
    "qs_pg:qs_pg_placetype":"locality",
    "qs_pg:qs_pg_placetype_gp":"Town",
    "qs_pg:woe_adm0":23424829,
    "woe:adm0_id":23424829,
    "woe:name_adm0":"Deutschland",
    "woe:name_adm1":"Sachsen-Anhalt",
    "woe:placetype":"Town",
    "wof:name":"Br\u00e4sen",
    "wof:placetype":"neighbourhood",
    "wof:population":170
},
  "geometry": {"coordinates":[12.37638,51.9646],"type":"Point"}
}