{
  "type": "Feature",
  "properties": {
    "gn:admin1_code":"2",
    "gn:admin2_code":"91.0",
    "gn:admin3_code":"9189.0",
    "gn:admin4_code":"9189137.0",
    "gn:asciiname":"Hinzing",
    "gn:country_code":"DE",
    "gn:dem":565,
    "gn:feature_class":"P",
    "gn:feature_code":"PPL",
    "gn:name":"Hinzing",
    "gn:population":0,
    "gn:timezone":"Europe/Berlin",
    "iso:country":"DE",
    "wof:name":"Hinzing",
    "wof:placetype":"neighbourhood"
},
  "geometry": {"coordinates":[12.37381,47.96882],"type":"Point"}
}