{
  "type": "Feature",
  "properties": {
    "gn:admin1_code":"8",
    "gn:admin2_code":"0.0",
    "gn:admin3_code":"7340.0",
    "gn:admin4_code":"7340206.0",
    "gn:asciiname":"Stambach",
    "gn:country_code":"DE",
    "gn:dem":240,
    "gn:feature_class":"P",
    "gn:feature_code":"PPL",
    "gn:name":"Stambach",
    "gn:population":0,
    "gn:timezone":"Europe/Berlin",
    "iso:country":"DE",
    "name:deu_x_preferred":[
        "Stambach"
    ],
    "name:fra_x_preferred":[
        "Stambach"
    ],
    "name:ita_x_preferred":[
        "Stambach"
    ],
    "name:nld_x_preferred":[
        "Stambach"
    ],
    "name:slk_x_preferred":[
        "Stambach"
    ],
    "name:vie_x_preferred":[
        "Stambach"
    ],
    "name:vol_x_preferred":[
        "Stambach"
    ],
    "name:war_x_preferred":[
        "Stambach"
    ],
    "name:zho_x_preferred":[
        "\u65bd\u5766\u5df4\u8d6b"
    ],
    "wof:name":"Stambach",
    "wof:placetype":"neighbourhood"
},
  "geometry": {"coordinates":[7.45539,49.24454],"type":"Point"}
}