{
  "type": "Feature",
  "properties": {
    "gn:admin1_code":"8",
    "gn:admin2_code":"0.0",
    "gn:admin3_code":"7335.0",
    "gn:admin4_code":"7335017.0",
    "gn:asciiname":"Kuehboerncheshof",
    "gn:country_code":"DE",
    "gn:dem":267,
    "gn:feature_class":"P",
    "gn:feature_code":"PPL",
    "gn:name":"K\u00fchb\u00f6rncheshof",
    "gn:population":0,
    "gn:timezone":"Europe/Berlin",
    "iso:country":"DE",
    "wof:name":"Kuehboerncheshof",
    "wof:placetype":"neighbourhood"
},
  "geometry": {"coordinates":[7.67384,49.49983],"type":"Point"}
}