{
  "type": "Feature",
  "properties": {
    "gn:admin1_code":"11",
    "gn:admin2_code":"0.0",
    "gn:admin3_code":"12072.0",
    "gn:admin4_code":"12072297.0",
    "gn:asciiname":"Kurzlipsdorf",
    "gn:country_code":"DE",
    "gn:dem":113,
    "gn:feature_class":"P",
    "gn:feature_code":"PPL",
    "gn:name":"Kurzlipsdorf",
    "gn:population":0,
    "gn:timezone":"Europe/Berlin",
    "iso:country":"DE",
    "wof:name":"Kurzlipsdorf",
    "wof:placetype":"neighbourhood"
},
  "geometry": {"coordinates":[12.86266,51.96919000000001],"type":"Point"}
}