{
  "type": "Feature",
  "properties": {
    "gn:admin1_code":"13.0",
    "gn:admin2_code":"0.0",
    "gn:admin3_code":"14730.0",
    "gn:admin4_code":"14730060.0",
    "gn:asciiname":"Am Bahnhof",
    "gn:country_code":"DE",
    "gn:dem":153,
    "gn:feature_class":"P",
    "gn:feature_code":"PPL",
    "gn:name":"Am Bahnhof",
    "gn:population":0,
    "gn:timezone":"Europe/Berlin",
    "iso:country":"DE",
    "wof:name":"Am Bahnhof",
    "wof:placetype":"neighbourhood"
},
  "geometry": {"coordinates":[12.98445,51.35183],"type":"Point"}
}