{
  "type": "Feature",
  "properties": {
    "gn:admin1_code":"1",
    "gn:admin2_code":"81.0",
    "gn:admin3_code":"8115.0",
    "gn:admin4_code":"8115021.0",
    "gn:asciiname":"Monchberg",
    "gn:country_code":"DE",
    "gn:dem":473,
    "gn:feature_class":"P",
    "gn:feature_code":"PPL",
    "gn:name":"M\u00f6nchberg",
    "gn:population":0,
    "gn:timezone":"Europe/Berlin",
    "iso:country":"DE",
    "wof:name":"Monchberg",
    "wof:placetype":"neighbourhood"
},
  "geometry": {"coordinates":[8.91575,48.58155],"type":"Point"}
}