{
  "type": "Feature",
  "properties": {
    "gn:admin1_code":"13",
    "gn:admin2_code":"0.0",
    "gn:admin3_code":"14627.0",
    "gn:admin4_code":"14627180.0",
    "gn:asciiname":"Schaenitz",
    "gn:country_code":"DE",
    "gn:dem":204,
    "gn:feature_class":"P",
    "gn:feature_code":"PPL",
    "gn:name":"Sch\u00e4nitz",
    "gn:population":0,
    "gn:timezone":"Europe/Berlin",
    "iso:country":"DE",
    "wof:name":"Schaenitz",
    "wof:placetype":"neighbourhood"
},
  "geometry": {"coordinates":[13.34099,51.12789],"type":"Point"}
}