{
  "type": "Feature",
  "properties": {
    "iso:country":"DE",
    "name:deu_x_preferred":[
        "Rockershausen"
    ],
    "name:unk_x_variant":[
        "Rockershausen"
    ],
    "qs:gn_fcode":"PPL",
    "qs:gn_local":0,
    "qs:gn_namadm1":"09",
    "qs:gn_name":"Rockershausen",
    "qs:local_max":4137,
    "qs:local_sum":6400,
    "qs:localhoods":13,
    "qs:name":"Rockershausen",
    "qs:name_adm0":"Deutschland",
    "qs:name_adm1":"Saarland",
    "qs:name_adm2":"Landkreis Saarbr\u00fccken",
    "qs:name_lau":"Stadtteil Altenkessel",
    "qs:name_local":"Saarbr\u00fccken",
    "qs:photo_max":50,
    "qs:photo_sum":99,
    "qs:placetype":"Suburb",
    "qs:quad_count":13,
    "qs:woe_adm0":23424829,
    "qs:woe_adm1":2345489,
    "qs:woe_adm2":12597017,
    "qs:woe_lau":26823192,
    "qs:woe_local":690631,
    "qs:woe_ver":"7.10.0",
    "wof:lang":[
        "ger"
    ],
    "wof:name":"Rockershausen",
    "wof:placetype":"neighbourhood"
},
  "geometry": {"coordinates":[6.892017,49.252008],"type":"Point"}
}