{
  "type": "Feature",
  "properties": {
    "gn:admin1_code":"2",
    "gn:admin2_code":"94.0",
    "gn:admin3_code":"9472.0",
    "gn:admin4_code":"9472175.0",
    "gn:asciiname":"Lobensteig",
    "gn:country_code":"DE",
    "gn:dem":500,
    "gn:feature_class":"P",
    "gn:feature_code":"PPL",
    "gn:name":"Lobensteig",
    "gn:population":0,
    "gn:timezone":"Europe/Berlin",
    "iso:country":"DE",
    "wof:name":"Lobensteig",
    "wof:placetype":"neighbourhood"
},
  "geometry": {"coordinates":[11.58787,49.74704000000001],"type":"Point"}
}