{
  "type": "Feature",
  "properties": {
    "gn:admin1_code":"2",
    "gn:admin2_code":"95.0",
    "gn:admin3_code":"9575.0",
    "gn:admin4_code":"9575130.0",
    "gn:asciiname":"Pfahlenheim",
    "gn:country_code":"DE",
    "gn:dem":302,
    "gn:feature_class":"P",
    "gn:feature_code":"PPL",
    "gn:name":"Pfahlenheim",
    "gn:population":0,
    "gn:timezone":"Europe/Berlin",
    "iso:country":"DE",
    "wof:name":"Pfahlenheim",
    "wof:placetype":"neighbourhood"
},
  "geometry": {"coordinates":[10.1251,49.55885],"type":"Point"}
}