{
  "type": "Feature",
  "properties": {
    "gn:admin1_code":"11",
    "gn:admin2_code":"0.0",
    "gn:admin3_code":"12063.0",
    "gn:admin4_code":"12063088.0",
    "gn:asciiname":"Briesener Zootzen",
    "gn:country_code":"DE",
    "gn:dem":32,
    "gn:feature_class":"P",
    "gn:feature_code":"PPL",
    "gn:name":"Briesener Zootzen",
    "gn:population":0,
    "gn:timezone":"Europe/Berlin",
    "iso:country":"DE",
    "wof:name":"Briesener Zootzen",
    "wof:placetype":"neighbourhood"
},
  "geometry": {"coordinates":[12.67367,52.75842],"type":"Point"}
}