{
  "type": "Feature",
  "properties": {
    "gn:admin1_code":"13.0",
    "gn:admin2_code":"00",
    "gn:admin3_code":"14522.0",
    "gn:admin4_code":"14522090.0",
    "gn:asciiname":"Wolfsgrund",
    "gn:country_code":"DE",
    "gn:dem":528,
    "gn:feature_class":"P",
    "gn:feature_code":"PPL",
    "gn:name":"Wolfsgrund",
    "gn:population":0,
    "gn:timezone":"Europe/Berlin",
    "iso:country":"DE",
    "wof:name":"Wolfsgrund",
    "wof:placetype":"neighbourhood"
},
  "geometry": {"coordinates":[13.41133,50.77043],"type":"Point"}
}