{
  "type": "Feature",
  "properties": {
    "gn:admin1_code":"2",
    "gn:admin2_code":"92.0",
    "gn:admin3_code":"9275.0",
    "gn:admin4_code":"9275148.0",
    "gn:asciiname":"Bruckleiten",
    "gn:country_code":"DE",
    "gn:dem":802,
    "gn:feature_class":"P",
    "gn:feature_code":"PPL",
    "gn:name":"Bruckleiten",
    "gn:population":0,
    "gn:timezone":"Europe/Berlin",
    "iso:country":"DE",
    "wof:name":"Bruckleiten",
    "wof:placetype":"neighbourhood"
},
  "geometry": {"coordinates":[13.72919,48.68655],"type":"Point"}
}