{
  "type": "Feature",
  "properties": {
    "iso:country":"DE",
    "wof:name":"Holzheim",
    "wof:placetype":"neighbourhood"
},
  "geometry": {"coordinates":[11.02157875396314,49.37423907516406],"type":"Point"}
}