{
  "type": "Feature",
  "properties": {
    "gn:admin1_code":"11",
    "gn:admin2_code":"0.0",
    "gn:admin3_code":"12063.0",
    "gn:admin4_code":"12063189.0",
    "gn:asciiname":"Kleine Buensche",
    "gn:country_code":"DE",
    "gn:dem":45,
    "gn:feature_class":"P",
    "gn:feature_code":"PPL",
    "gn:name":"Kleine B\u00fcnsche",
    "gn:population":0,
    "gn:timezone":"Europe/Berlin",
    "iso:country":"DE",
    "wof:name":"Kleine Buensche",
    "wof:placetype":"neighbourhood"
},
  "geometry": {"coordinates":[12.21667,52.56667],"type":"Point"}
}