{
  "type": "Feature",
  "properties": {
    "gn:admin1_code":"12",
    "gn:admin2_code":"0.0",
    "gn:admin3_code":"13076.0",
    "gn:admin4_code":"13076152.0",
    "gn:asciiname":"Klein Wolde",
    "gn:country_code":"DE",
    "gn:dem":59,
    "gn:feature_class":"P",
    "gn:feature_code":"PPL",
    "gn:name":"Klein Wolde",
    "gn:population":0,
    "gn:timezone":"Europe/Berlin",
    "iso:country":"DE",
    "wof:name":"Klein Wolde",
    "wof:placetype":"neighbourhood"
},
  "geometry": {"coordinates":[11.12089,53.47456999999999],"type":"Point"}
}