{
  "type": "Feature",
  "properties": {
    "gn:admin1_code":"7",
    "gn:admin2_code":"59.0",
    "gn:admin3_code":"5958.0",
    "gn:admin4_code":"5958016.0",
    "gn:asciiname":"Obermarpe",
    "gn:country_code":"DE",
    "gn:dem":464,
    "gn:feature_class":"P",
    "gn:feature_code":"PPLL",
    "gn:name":"Obermarpe",
    "gn:population":0,
    "gn:timezone":"Europe/Berlin",
    "iso:country":"DE",
    "wof:name":"Obermarpe",
    "wof:placetype":"neighbourhood"
},
  "geometry": {"coordinates":[8.12658,51.20009],"type":"Point"}
}