{
  "type": "Feature",
  "properties": {
    "gn:admin1_code":"1",
    "gn:admin2_code":"83.0",
    "gn:admin3_code":"8337.0",
    "gn:admin4_code":"8337013.0",
    "gn:asciiname":"Innerlehen",
    "gn:country_code":"DE",
    "gn:dem":925,
    "gn:feature_class":"P",
    "gn:feature_code":"PPL",
    "gn:name":"Innerlehen",
    "gn:population":0,
    "gn:timezone":"Europe/Berlin",
    "iso:country":"DE",
    "name:und_x_variant":[
        "Bernau-Innerlehen",
        "Innerlehen"
    ],
    "wof:name":"Innerlehen",
    "wof:placetype":"neighbourhood"
},
  "geometry": {"coordinates":[8.03281,47.80387],"type":"Point"}
}