{
  "type": "Feature",
  "properties": {
    "gn:admin1_code":"14.0",
    "gn:admin2_code":"0.0",
    "gn:admin3_code":"15085.0",
    "gn:admin4_code":"15085145.0",
    "gn:asciiname":"Baerenrode",
    "gn:country_code":"DE",
    "gn:dem":446,
    "gn:feature_class":"P",
    "gn:feature_code":"PPL",
    "gn:name":"B\u00e4renrode",
    "gn:population":0,
    "gn:timezone":"Europe/Berlin",
    "iso:country":"DE",
    "wof:name":"Baerenrode",
    "wof:placetype":"neighbourhood"
},
  "geometry": {"coordinates":[10.99622,51.66396],"type":"Point"}
}