{
  "type": "Feature",
  "properties": {
    "gn:admin1_code":"7",
    "gn:admin2_code":"59.0",
    "gn:admin3_code":"5970.0",
    "gn:admin4_code":"5970036.0",
    "gn:asciiname":"Salchendorf",
    "gn:country_code":"DE",
    "gn:dem":318,
    "gn:feature_class":"P",
    "gn:feature_code":"PPL",
    "gn:name":"Salchendorf",
    "gn:population":0,
    "gn:timezone":"Europe/Berlin",
    "iso:country":"DE",
    "wof:name":"Salchendorf",
    "wof:placetype":"neighbourhood"
},
  "geometry": {"coordinates":[8.01498,50.79747],"type":"Point"}
}