{
  "type": "Feature",
  "properties": {
    "gn:admin1_code":"13",
    "gn:admin2_code":"0.0",
    "gn:admin3_code":"14522.0",
    "gn:admin4_code":"14522050.0",
    "gn:asciiname":"Sankt Michaelis",
    "gn:country_code":"DE",
    "gn:dem":414,
    "gn:feature_class":"P",
    "gn:feature_code":"PPL",
    "gn:name":"Sankt Michaelis",
    "gn:population":0,
    "gn:timezone":"Europe/Berlin",
    "iso:country":"DE",
    "wof:name":"Sankt Michaelis",
    "wof:placetype":"neighbourhood"
},
  "geometry": {"coordinates":[13.29458,50.87152],"type":"Point"}
}