{
  "type": "Feature",
  "properties": {
    "gn:admin1_code":"2",
    "gn:admin2_code":"97.0",
    "gn:admin3_code":"9777.0",
    "gn:admin4_code":"9777131.0",
    "gn:asciiname":"Hasenmahd",
    "gn:country_code":"DE",
    "gn:dem":828,
    "gn:feature_class":"P",
    "gn:feature_code":"PPL",
    "gn:name":"Hasenmahd",
    "gn:population":0,
    "gn:timezone":"Europe/Berlin",
    "iso:country":"DE",
    "wof:name":"Hasenmahd",
    "wof:placetype":"neighbourhood"
},
  "geometry": {"coordinates":[10.48917,47.70349],"type":"Point"}
}