{
  "type": "Feature",
  "properties": {
    "gn:admin1_code":"8",
    "gn:admin2_code":"0.0",
    "gn:admin3_code":"7135.0",
    "gn:admin4_code":"7135016.0",
    "gn:asciiname":"Brohl",
    "gn:country_code":"DE",
    "gn:dem":249,
    "gn:feature_class":"P",
    "gn:feature_code":"PPLA4",
    "gn:name":"Brohl",
    "gn:population":0,
    "gn:timezone":"Europe/Berlin",
    "iso:country":"DE",
    "wof:name":"Brohl",
    "wof:placetype":"locality"
},
  "geometry": {"coordinates":[7.27947,50.21909],"type":"Point"}
}