{
  "type": "Feature",
  "properties": {
    "gn:admin1_code":"8.0",
    "gn:admin2_code":"0.0",
    "gn:admin3_code":"7233.0",
    "gn:admin4_code":"7233010.0",
    "gn:asciiname":"Boxberg",
    "gn:country_code":"DE",
    "gn:dem":490,
    "gn:feature_class":"P",
    "gn:feature_code":"PPLA4",
    "gn:name":"Boxberg",
    "gn:population":190,
    "gn:timezone":"Europe/Berlin",
    "iso:country":"DE",
    "wof:name":"Boxberg",
    "wof:placetype":"locality",
    "wof:population":190
},
  "geometry": {"coordinates":[6.88333,50.26667],"type":"Point"}
}