{
  "type": "Feature",
  "properties": {
    "gn:admin1_code":"2",
    "gn:admin2_code":"95.0",
    "gn:admin3_code":"9574.0",
    "gn:admin4_code":"9574128.0",
    "gn:asciiname":"See",
    "gn:country_code":"DE",
    "gn:dem":532,
    "gn:feature_class":"P",
    "gn:feature_code":"PPL",
    "gn:name":"See",
    "gn:population":0,
    "gn:timezone":"Europe/Berlin",
    "iso:country":"DE",
    "name:ceb_x_preferred":[
        "See"
    ],
    "name:deu_x_preferred":[
        "See"
    ],
    "name:fra_x_preferred":[
        "See"
    ],
    "name:nds_x_preferred":[
        "See"
    ],
    "name:nld_x_preferred":[
        "See"
    ],
    "name:pol_x_preferred":[
        "See"
    ],
    "name:por_x_preferred":[
        "See"
    ],
    "name:swe_x_preferred":[
        "See"
    ],
    "wof:name":"See",
    "wof:placetype":"neighbourhood"
},
  "geometry": {"coordinates":[11.52122,49.45964],"type":"Point"}
}