{
  "type": "Feature",
  "properties": {
    "gn:admin1_code":"2.0",
    "gn:admin2_code":"91.0",
    "gn:admin3_code":"9180.0",
    "gn:admin4_code":"9180128.0",
    "gn:asciiname":"Aidling",
    "gn:country_code":"DE",
    "gn:dem":720,
    "gn:feature_class":"P",
    "gn:feature_code":"PPL",
    "gn:name":"Aidling",
    "gn:population":0,
    "gn:timezone":"Europe/Berlin",
    "iso:country":"DE",
    "wof:name":"Aidling",
    "wof:placetype":"neighbourhood"
},
  "geometry": {"coordinates":[11.24773,47.71319],"type":"Point"}
}