{
  "type": "Feature",
  "properties": {
    "gn:admin1_code":"1",
    "gn:admin2_code":"82.0",
    "gn:admin3_code":"8235.0",
    "gn:admin4_code":"8235033.0",
    "gn:asciiname":"Kullenmuhle",
    "gn:country_code":"DE",
    "gn:dem":346,
    "gn:feature_class":"P",
    "gn:feature_code":"PPL",
    "gn:name":"Kullenm\u00fchle",
    "gn:population":0,
    "gn:timezone":"Europe/Berlin",
    "iso:country":"DE",
    "wof:name":"Kullenmuhle",
    "wof:placetype":"neighbourhood"
},
  "geometry": {"coordinates":[8.44239,48.81122],"type":"Point"}
}