{
  "type": "Feature",
  "properties": {
    "gn:admin1_code":"13",
    "gn:admin2_code":"0.0",
    "gn:admin3_code":"14729.0",
    "gn:admin4_code":"14729245.0",
    "gn:asciiname":"Watzschwitz",
    "gn:country_code":"DE",
    "gn:dem":129,
    "gn:feature_class":"P",
    "gn:feature_code":"PPL",
    "gn:name":"Watzschwitz",
    "gn:population":0,
    "gn:timezone":"Europe/Berlin",
    "iso:country":"DE",
    "name:und_x_variant":[
        "Hohburg-Watzschwitz",
        "Watzschwitz"
    ],
    "wof:name":"Watzschwitz",
    "wof:placetype":"neighbourhood"
},
  "geometry": {"coordinates":[12.81951,51.3993],"type":"Point"}
}