{
  "type": "Feature",
  "properties": {
    "gn:admin1_code":"6",
    "gn:admin2_code":"0.0",
    "gn:admin3_code":"3462.0",
    "gn:admin4_code":"3462005.0",
    "gn:asciiname":"Dose",
    "gn:country_code":"DE",
    "gn:dem":3,
    "gn:feature_class":"P",
    "gn:feature_code":"PPL",
    "gn:name":"Dose",
    "gn:population":0,
    "gn:timezone":"Europe/Berlin",
    "iso:country":"DE",
    "name:ceb_x_preferred":[
        "Dose"
    ],
    "name:deu_x_preferred":[
        "Dose"
    ],
    "name:fas_x_preferred":[
        "\u062f\u0648\u0632"
    ],
    "name:fra_x_preferred":[
        "Dose"
    ],
    "name:hun_x_preferred":[
        "D\u00f3zis"
    ],
    "name:ita_x_preferred":[
        "Dose"
    ],
    "name:jpn_x_preferred":[
        "\u30c9\u30fc\u30b9"
    ],
    "name:nld_x_preferred":[
        "Dose"
    ],
    "name:rus_x_preferred":[
        "\u0414\u043e\u0437\u0430"
    ],
    "name:swe_x_preferred":[
        "Dose"
    ],
    "name:uzb_x_preferred":[
        "Doza"
    ],
    "wof:name":"Dose",
    "wof:placetype":"neighbourhood"
},
  "geometry": {"coordinates":[7.8903,53.50238],"type":"Point"}
}