{
  "type": "Feature",
  "properties": {
    "gn:admin1_code":"7",
    "gn:admin2_code":"55.0",
    "gn:admin3_code":"5566.0",
    "gn:admin4_code":"5566088.0",
    "gn:asciiname":"Leeden",
    "gn:country_code":"DE",
    "gn:dem":92,
    "gn:feature_class":"P",
    "gn:feature_code":"PPL",
    "gn:name":"Leeden",
    "gn:population":0,
    "gn:timezone":"Europe/Berlin",
    "iso:country":"DE",
    "wof:name":"Leeden",
    "wof:placetype":"neighbourhood"
},
  "geometry": {"coordinates":[7.89034,52.21564],"type":"Point"}
}