{
  "type": "Feature",
  "properties": {
    "gn:admin1_code":"7.0",
    "gn:admin2_code":"57.0",
    "gn:admin3_code":"5762.0",
    "gn:admin4_code":"5762020.0",
    "gn:asciiname":"Albaxen",
    "gn:country_code":"DE",
    "gn:dem":105,
    "gn:feature_class":"P",
    "gn:feature_code":"PPL",
    "gn:name":"Albaxen",
    "gn:population":0,
    "gn:timezone":"Europe/Berlin",
    "iso:country":"DE",
    "wof:name":"Albaxen",
    "wof:placetype":"neighbourhood"
},
  "geometry": {"coordinates":[9.40751,51.82218],"type":"Point"}
}