{
  "type": "Feature",
  "properties": {
    "gn:admin1_code":"2",
    "gn:admin2_code":"96.0",
    "gn:admin3_code":"9672.0",
    "gn:admin4_code":"9672139.0",
    "gn:asciiname":"Thulba",
    "gn:country_code":"DE",
    "gn:dem":234,
    "gn:feature_class":"P",
    "gn:feature_code":"PPL",
    "gn:name":"Thulba",
    "gn:population":0,
    "gn:timezone":"Europe/Berlin",
    "iso:country":"DE",
    "name:ceb_x_preferred":[
        "Thulba"
    ],
    "name:chv_x_preferred":[
        "\u0422\u0443\u043b\u044c\u0431\u0430"
    ],
    "name:deu_x_preferred":[
        "Thulba"
    ],
    "name:rus_x_preferred":[
        "\u0422\u0443\u043b\u044c\u0431\u0430"
    ],
    "wof:name":"Thulba",
    "wof:placetype":"neighbourhood"
},
  "geometry": {"coordinates":[9.91943,50.1792],"type":"Point"}
}