{
  "type": "Feature",
  "properties": {
    "gn:admin1_code":"10.0",
    "gn:admin2_code":"00",
    "gn:admin3_code":"1062.0",
    "gn:admin4_code":"1062059.0",
    "gn:asciiname":"Willendorf",
    "gn:country_code":"DE",
    "gn:dem":51,
    "gn:feature_class":"P",
    "gn:feature_code":"PPL",
    "gn:name":"Willendorf",
    "gn:population":0,
    "gn:timezone":"Europe/Berlin",
    "iso:country":"DE",
    "name:bre_x_preferred":[
        "Willendorf"
    ],
    "name:ceb_x_preferred":[
        "Willendorf"
    ],
    "name:deu_x_preferred":[
        "Willendorf"
    ],
    "name:epo_x_preferred":[
        "Willendorf"
    ],
    "name:fas_x_preferred":[
        "\u0648\u06cc\u0644\u0646\u062f\u0648\u0631\u0641"
    ],
    "name:fra_x_preferred":[
        "Willendorf"
    ],
    "name:fry_x_preferred":[
        "Willendorf"
    ],
    "name:hun_x_preferred":[
        "Willendorf"
    ],
    "name:ita_x_preferred":[
        "Willendorf"
    ],
    "name:kaz_x_preferred":[
        "\u0412\u0438\u043b\u043b\u0435\u043d\u0434\u043e\u0440\u0444"
    ],
    "name:nld_x_preferred":[
        "Willendorf"
    ],
    "name:nno_x_preferred":[
        "Willendorf"
    ],
    "name:pol_x_preferred":[
        "Willendorf"
    ],
    "name:por_x_preferred":[
        "Willendorf"
    ],
    "name:rus_x_preferred":[
        "\u0412\u0438\u043b\u043b\u0435\u043d\u0434\u043e\u0440\u0444"
    ],
    "name:scn_x_preferred":[
        "Willendorf"
    ],
    "name:slk_x_preferred":[
        "Willendorf"
    ],
    "name:spa_x_preferred":[
        "Willendorf"
    ],
    "name:srp_x_preferred":[
        "\u0412\u0438\u043b\u0435\u043d\u0434\u043e\u0440\u0444"
    ],
    "name:swe_x_preferred":[
        "Willendorf"
    ],
    "name:uzb_x_preferred":[
        "Willendorf"
    ],
    "name:vie_x_preferred":[
        "Willendorf"
    ],
    "name:vol_x_preferred":[
        "Willendorf"
    ],
    "name:war_x_preferred":[
        "Willendorf"
    ],
    "name:zho_x_preferred":[
        "\u7ef4\u4f26\u591a\u592b"
    ],
    "wof:name":"Willendorf",
    "wof:placetype":"neighbourhood"
},
  "geometry": {"coordinates":[10.44873,53.89542],"type":"Point"}
}