{
  "type": "Feature",
  "properties": {
    "gn:admin1_code":"10.0",
    "gn:admin2_code":"00",
    "gn:admin3_code":"1062.0",
    "gn:admin4_code":"1062059.0",
    "gn:asciiname":"Willendorf",
    "gn:country_code":"DE",
    "gn:dem":51,
    "gn:feature_class":"P",
    "gn:feature_code":"PPL",
    "gn:name":"Willendorf",
    "gn:population":0,
    "gn:timezone":"Europe/Berlin",
    "iso:country":"DE",
    "wof:name":"Willendorf",
    "wof:placetype":"neighbourhood"
},
  "geometry": {"coordinates":[10.44873,53.89542],"type":"Point"}
}