{
  "type": "Feature",
  "properties": {
    "gn:admin1_code":"9.0",
    "gn:admin2_code":"0.0",
    "gn:admin3_code":"10042.0",
    "gn:admin4_code":"10042115.0",
    "gn:asciiname":"Berg",
    "gn:country_code":"DE",
    "gn:dem":174,
    "gn:feature_class":"P",
    "gn:feature_code":"PPL",
    "gn:name":"Berg",
    "gn:population":0,
    "gn:timezone":"Europe/Berlin",
    "iso:country":"DE",
    "wof:name":"Berg",
    "wof:placetype":"neighbourhood"
},
  "geometry": {"coordinates":[6.3868,49.53484],"type":"Point"}
}