{
  "type": "Feature",
  "properties": {
    "gn:admin1_code":"1",
    "gn:admin2_code":"83.0",
    "gn:admin3_code":"8335.0",
    "gn:admin4_code":"8335035.0",
    "gn:asciiname":"Duchtlingen",
    "gn:country_code":"DE",
    "gn:dem":528,
    "gn:feature_class":"P",
    "gn:feature_code":"PPL",
    "gn:name":"Duchtlingen",
    "gn:population":0,
    "gn:timezone":"Europe/Berlin",
    "iso:country":"DE",
    "wof:name":"Duchtlingen",
    "wof:placetype":"neighbourhood"
},
  "geometry": {"coordinates":[8.79129,47.79125],"type":"Point"}
}