{
  "type": "Feature",
  "properties": {
    "gn:admin1_code":"11.0",
    "gn:admin2_code":"0.0",
    "gn:admin3_code":"12073.0",
    "gn:admin4_code":"12073569.0",
    "gn:asciiname":"Ahlimbswalde",
    "gn:country_code":"DE",
    "gn:dem":65,
    "gn:feature_class":"P",
    "gn:feature_code":"PPL",
    "gn:name":"Ahlimbswalde",
    "gn:population":0,
    "gn:timezone":"Europe/Berlin",
    "iso:country":"DE",
    "wof:name":"Ahlimbswalde",
    "wof:placetype":"neighbourhood"
},
  "geometry": {"coordinates":[13.72416,53.04663000000001],"type":"Point"}
}