{
  "type": "Feature",
  "properties": {
    "gn:admin1_code":"8.0",
    "gn:admin2_code":"0.0",
    "gn:admin3_code":"7143.0",
    "gn:admin4_code":"7143235.0",
    "gn:asciiname":"Oberhattert",
    "gn:country_code":"DE",
    "gn:dem":300,
    "gn:feature_class":"P",
    "gn:feature_code":"PPL",
    "gn:name":"Oberhattert",
    "gn:population":0,
    "gn:timezone":"Europe/Berlin",
    "iso:country":"DE",
    "wof:name":"Oberhattert",
    "wof:placetype":"neighbourhood"
},
  "geometry": {"coordinates":[7.77711,50.66655],"type":"Point"}
}