{
  "type": "Feature",
  "properties": {
    "gn:admin1_code":"2",
    "gn:admin2_code":"94.0",
    "gn:admin3_code":"9479.0",
    "gn:admin4_code":"9479112.0",
    "gn:asciiname":"Sandmuhle",
    "gn:country_code":"DE",
    "gn:dem":498,
    "gn:feature_class":"P",
    "gn:feature_code":"PPL",
    "gn:name":"Sandm\u00fchle",
    "gn:population":0,
    "gn:timezone":"Europe/Berlin",
    "iso:country":"DE",
    "wof:name":"Sandmuhle",
    "wof:placetype":"neighbourhood"
},
  "geometry": {"coordinates":[12.16609,50.06909],"type":"Point"}
}