{
  "type": "Feature",
  "properties": {
    "gn:admin1_code":"2",
    "gn:admin2_code":"93.0",
    "gn:admin3_code":"9375.0",
    "gn:admin4_code":"9375171.0",
    "gn:asciiname":"Schonach",
    "gn:country_code":"DE",
    "gn:dem":331,
    "gn:feature_class":"P",
    "gn:feature_code":"PPL",
    "gn:name":"Sch\u00f6nach",
    "gn:population":0,
    "gn:timezone":"Europe/Berlin",
    "iso:country":"DE",
    "name:ceb_x_preferred":[
        "Schonach"
    ],
    "name:deu_x_preferred":[
        "Schonach"
    ],
    "name:nld_x_preferred":[
        "Schonach"
    ],
    "name:pol_x_preferred":[
        "Schonach"
    ],
    "name:swe_x_preferred":[
        "Schonach"
    ],
    "wof:name":"Schonach",
    "wof:placetype":"neighbourhood"
},
  "geometry": {"coordinates":[12.42312,48.91165],"type":"Point"}
}