{
  "type": "Feature",
  "properties": {
    "gn:admin1_code":"5.0",
    "gn:admin2_code":"66.0",
    "gn:admin3_code":"6631.0",
    "gn:admin4_code":"6631013.0",
    "gn:asciiname":"Allmus",
    "gn:country_code":"DE",
    "gn:dem":344,
    "gn:feature_class":"P",
    "gn:feature_code":"PPL",
    "gn:name":"Allmus",
    "gn:population":0,
    "gn:timezone":"Europe/Berlin",
    "iso:country":"DE",
    "wof:name":"Allmus",
    "wof:placetype":"neighbourhood"
},
  "geometry": {"coordinates":[9.81422,50.59561],"type":"Point"}
}