{
  "type": "Feature",
  "properties": {
    "gn:admin1_code":"13",
    "gn:admin2_code":"0.0",
    "gn:admin3_code":"14730.0",
    "gn:admin4_code":"14730320.0",
    "gn:asciiname":"Dahlenberg",
    "gn:country_code":"DE",
    "gn:dem":109,
    "gn:feature_class":"P",
    "gn:feature_code":"PPL",
    "gn:name":"Dahlenberg",
    "gn:population":0,
    "gn:timezone":"Europe/Berlin",
    "iso:country":"DE",
    "wof:name":"Dahlenberg",
    "wof:placetype":"neighbourhood"
},
  "geometry": {"coordinates":[12.78611,51.63903],"type":"Point"}
}