{
  "type": "Feature",
  "properties": {
    "gn:admin1_code":"10",
    "gn:admin2_code":"0.0",
    "gn:admin3_code":"1056.0",
    "gn:admin4_code":"1056045.0",
    "gn:asciiname":"Esch",
    "gn:country_code":"DE",
    "gn:dem":1,
    "gn:feature_class":"P",
    "gn:feature_code":"PPL",
    "gn:name":"Esch",
    "gn:population":0,
    "gn:timezone":"Europe/Berlin",
    "iso:country":"DE",
    "name:ceb_x_preferred":[
        "Esch"
    ],
    "name:deu_x_preferred":[
        "Esch"
    ],
    "name:epo_x_preferred":[
        "Esch"
    ],
    "name:fra_x_preferred":[
        "Esch"
    ],
    "name:ita_x_preferred":[
        "Esch"
    ],
    "name:lav_x_preferred":[
        "E\u0161s"
    ],
    "name:ltz_x_preferred":[
        "Esch"
    ],
    "name:nds_x_preferred":[
        "Esch"
    ],
    "name:nld_x_preferred":[
        "Esch"
    ],
    "name:pol_x_preferred":[
        "Esch"
    ],
    "name:ron_x_preferred":[
        "Esch"
    ],
    "name:swe_x_preferred":[
        "Esch"
    ],
    "name:und_x_variant":[
        "Im Esch"
    ],
    "wof:name":"Esch",
    "wof:placetype":"neighbourhood"
},
  "geometry": {"coordinates":[9.56347,53.68578],"type":"Point"}
}