{
  "type": "Feature",
  "properties": {
    "gn:admin1_code":"9.0",
    "gn:admin2_code":"0.0",
    "gn:admin3_code":"10042.0",
    "gn:admin4_code":"10042116.0",
    "gn:asciiname":"Roth",
    "gn:country_code":"DE",
    "gn:dem":278,
    "gn:feature_class":"P",
    "gn:feature_code":"PPL",
    "gn:name":"Roth",
    "gn:population":0,
    "gn:timezone":"Europe/Berlin",
    "iso:country":"DE",
    "name:ceb_x_preferred":[
        "Roth"
    ],
    "name:dan_x_preferred":[
        "Roth"
    ],
    "name:deu_x_preferred":[
        "Roth"
    ],
    "name:epo_x_preferred":[
        "Roth"
    ],
    "name:est_x_preferred":[
        "Roth"
    ],
    "name:fra_x_preferred":[
        "Roth"
    ],
    "name:hye_x_preferred":[
        "\u054c\u0578\u0569"
    ],
    "name:ita_x_preferred":[
        "Roth"
    ],
    "name:jpn_x_preferred":[
        "\u30ed\u30fc\u30c8"
    ],
    "name:nld_x_preferred":[
        "Roth"
    ],
    "name:pol_x_preferred":[
        "Roth"
    ],
    "name:por_x_preferred":[
        "Roth"
    ],
    "name:slk_x_preferred":[
        "Roth"
    ],
    "name:spa_x_preferred":[
        "Roth"
    ],
    "name:swe_x_preferred":[
        "Roth"
    ],
    "name:vol_x_preferred":[
        "Roth"
    ],
    "wof:name":"Roth",
    "wof:placetype":"neighbourhood"
},
  "geometry": {"coordinates":[6.8624,49.52462],"type":"Point"}
}