{
  "type": "Feature",
  "properties": {
    "gn:admin1_code":"15",
    "gn:admin2_code":"0.0",
    "gn:admin3_code":"16063.0",
    "gn:admin4_code":"16063099.0",
    "gn:asciiname":"Gluecksbrunn",
    "gn:country_code":"DE",
    "gn:dem":328,
    "gn:feature_class":"P",
    "gn:feature_code":"PPL",
    "gn:name":"Gl\u00fccksbrunn",
    "gn:population":0,
    "gn:timezone":"Europe/Berlin",
    "iso:country":"DE",
    "wof:name":"Gluecksbrunn",
    "wof:placetype":"neighbourhood"
},
  "geometry": {"coordinates":[10.34203,50.83099],"type":"Point"}
}