{
  "type": "Feature",
  "properties": {
    "gn:admin1_code":"1",
    "gn:admin2_code":"82.0",
    "gn:admin3_code":"8226.0",
    "gn:admin4_code":"8226013.0",
    "gn:asciiname":"Brombach",
    "gn:country_code":"DE",
    "gn:dem":353,
    "gn:feature_class":"P",
    "gn:feature_code":"PPL",
    "gn:name":"Brombach",
    "gn:population":0,
    "gn:timezone":"Europe/Berlin",
    "iso:country":"DE",
    "name:deu_x_preferred":[
        "Brombach"
    ],
    "wof:name":"Brombach",
    "wof:placetype":"neighbourhood"
},
  "geometry": {"coordinates":[8.86886,49.48944],"type":"Point"}
}