{
  "type": "Feature",
  "properties": {
    "gn:admin1_code":"7",
    "gn:admin2_code":"59.0",
    "gn:admin3_code":"5962.0",
    "gn:admin4_code":"5962056.0",
    "gn:asciiname":"Twiestroemen",
    "gn:country_code":"DE",
    "gn:dem":221,
    "gn:feature_class":"P",
    "gn:feature_code":"PPL",
    "gn:name":"Twiestr\u00f6men",
    "gn:population":0,
    "gn:timezone":"Europe/Berlin",
    "iso:country":"DE",
    "wof:name":"Twiestroemen",
    "wof:placetype":"neighbourhood"
},
  "geometry": {"coordinates":[7.51667,51.25],"type":"Point"}
}