{
  "type": "Feature",
  "properties": {
    "gn:admin1_code":"2",
    "gn:admin2_code":"97.0",
    "gn:admin3_code":"9779.0",
    "gn:admin4_code":"9779226.0",
    "gn:asciiname":"Speckbrodi",
    "gn:country_code":"DE",
    "gn:dem":410,
    "gn:feature_class":"P",
    "gn:feature_code":"PPL",
    "gn:name":"Speckbrodi",
    "gn:population":0,
    "gn:timezone":"Europe/Berlin",
    "iso:country":"DE",
    "wof:name":"Speckbrodi",
    "wof:placetype":"neighbourhood"
},
  "geometry": {"coordinates":[10.6351,48.87982],"type":"Point"}
}