{
  "type": "Feature",
  "properties": {
    "gn:admin1_code":"2",
    "gn:admin2_code":"93.0",
    "gn:admin3_code":"9375.0",
    "gn:admin4_code":"9375148.0",
    "gn:asciiname":"Eichlberg",
    "gn:country_code":"DE",
    "gn:dem":583,
    "gn:feature_class":"P",
    "gn:feature_code":"PPL",
    "gn:name":"Eichlberg",
    "gn:population":0,
    "gn:timezone":"Europe/Berlin",
    "iso:country":"DE",
    "wof:name":"Eichlberg",
    "wof:placetype":"neighbourhood"
},
  "geometry": {"coordinates":[11.71366,49.08438],"type":"Point"}
}