{
  "type": "Feature",
  "properties": {
    "gn:admin1_code":"6",
    "gn:admin2_code":"0.0",
    "gn:admin3_code":"3452.0",
    "gn:admin4_code":"3452001.0",
    "gn:asciiname":"Wallerlange AEcker",
    "gn:country_code":"DE",
    "gn:dem":5,
    "gn:feature_class":"P",
    "gn:feature_code":"PPLL",
    "gn:name":"Wallerlange \u00c4cker",
    "gn:population":0,
    "gn:timezone":"Europe/Berlin",
    "iso:country":"DE",
    "wof:name":"Wallerlange AEcker",
    "wof:placetype":"neighbourhood"
},
  "geometry": {"coordinates":[7.45868,53.48652],"type":"Point"}
}