{
  "type": "Feature",
  "properties": {
    "iso:country":"DE",
    "name:ceb_x_preferred":[
        "K\u00f6nigstuhl"
    ],
    "name:deu_x_preferred":[
        "K\u00f6nigstuhl"
    ],
    "name:pol_x_preferred":[
        "K\u00f6nigstuhl"
    ],
    "name:ron_x_preferred":[
        "K\u00f6nigstuhl"
    ],
    "name:swe_x_preferred":[
        "K\u00f6nigstuhl"
    ],
    "qs_pg:aaroncc":"DE",
    "qs_pg:name":"K\u00f6nigstuhl",
    "qs_pg:name_adm0":"Deutschland",
    "qs_pg:name_adm1":"Baden-W\u00fcrttemberg",
    "qs_pg:photos":103,
    "qs_pg:photos_1k":21,
    "qs_pg:photos_9k":1,
    "qs_pg:photos_9r":3,
    "qs_pg:photos_all":103,
    "qs_pg:photos_sr":3,
    "qs_pg:pop_sr":0,
    "qs_pg:qs_pg_placetype":"locality",
    "qs_pg:qs_pg_placetype_gp":"Town",
    "qs_pg:woe_adm0":23424829,
    "woe:adm0_id":23424829,
    "woe:name_adm0":"Deutschland",
    "woe:name_adm1":"Baden-W\u00fcrttemberg",
    "woe:placetype":"Town",
    "wof:name":"K\u00f6nigstuhl",
    "wof:placetype":"neighbourhood"
},
  "geometry": {"coordinates":[8.724989,49.396507],"type":"Point"}
}