{
  "type": "Feature",
  "properties": {
    "gn:admin1_code":"2",
    "gn:admin2_code":"92.0",
    "gn:admin3_code":"9271.0",
    "gn:admin4_code":"9271149.0",
    "gn:asciiname":"Rieden",
    "gn:country_code":"DE",
    "gn:dem":390,
    "gn:feature_class":"P",
    "gn:feature_code":"PPLL",
    "gn:name":"Rieden",
    "gn:population":0,
    "gn:timezone":"Europe/Berlin",
    "iso:country":"DE",
    "name:ceb_x_preferred":[
        "Rieden"
    ],
    "name:deu_x_preferred":[
        "Rieden"
    ],
    "name:epo_x_preferred":[
        "Rieden"
    ],
    "name:fas_x_preferred":[
        "\u0631\u06cc\u062f\u0646"
    ],
    "name:fra_x_preferred":[
        "Rieden"
    ],
    "name:hye_x_preferred":[
        "\u054c\u056b\u0564\u0565\u0576"
    ],
    "name:ita_x_preferred":[
        "Rieden"
    ],
    "name:jpn_x_preferred":[
        "\u30ea\u30fc\u30c7\u30f3"
    ],
    "name:lmo_x_preferred":[
        "Rieden"
    ],
    "name:nld_x_preferred":[
        "Rieden"
    ],
    "name:pol_x_preferred":[
        "Rieden"
    ],
    "name:por_x_preferred":[
        "Rieden"
    ],
    "name:rus_x_preferred":[
        "\u0420\u0438\u0434\u0435\u043d"
    ],
    "name:spa_x_preferred":[
        "Rieden"
    ],
    "name:srp_x_preferred":[
        "\u0420\u0438\u0434\u0435\u043d"
    ],
    "name:swe_x_preferred":[
        "Rieden"
    ],
    "name:vol_x_preferred":[
        "Rieden"
    ],
    "wof:name":"Rieden",
    "wof:placetype":"neighbourhood"
},
  "geometry": {"coordinates":[13.15779,48.7614],"type":"Point"}
}