{
  "type": "Feature",
  "properties": {
    "gn:admin1_code":"5.0",
    "gn:admin2_code":"65.0",
    "gn:admin3_code":"6532.0",
    "gn:admin4_code":"6532017.0",
    "gn:asciiname":"Bicken",
    "gn:country_code":"DE",
    "gn:dem":256,
    "gn:feature_class":"P",
    "gn:feature_code":"PPL",
    "gn:name":"Bicken",
    "gn:population":0,
    "gn:timezone":"Europe/Berlin",
    "iso:country":"DE",
    "wof:name":"Bicken",
    "wof:placetype":"neighbourhood"
},
  "geometry": {"coordinates":[8.37782,50.69261],"type":"Point"}
}