{
  "type": "Feature",
  "properties": {
    "gn:admin1_code":"5",
    "gn:admin2_code":"64.0",
    "gn:admin3_code":"6440.0",
    "gn:admin4_code":"6440009.0",
    "gn:asciiname":"Niederseemen",
    "gn:country_code":"DE",
    "gn:dem":326,
    "gn:feature_class":"P",
    "gn:feature_code":"PPL",
    "gn:name":"Niederseemen",
    "gn:population":0,
    "gn:timezone":"Europe/Berlin",
    "iso:country":"DE",
    "wof:name":"Niederseemen",
    "wof:placetype":"neighbourhood"
},
  "geometry": {"coordinates":[9.24509,50.38725],"type":"Point"}
}