{
  "type": "Feature",
  "properties": {
    "gn:country":"DE",
    "gn:fcode":"PPL",
    "gn:population":0,
    "iso:country":"DE",
    "name:ceb_x_preferred":[
        "Glewitz"
    ],
    "name:deu_x_preferred":[
        "Glewitz"
    ],
    "name:epo_x_preferred":[
        "Glewitz"
    ],
    "name:fas_x_preferred":[
        "\u06af\u0644\u0648\u06cc\u062a\u0633"
    ],
    "name:fra_x_preferred":[
        "Glewitz"
    ],
    "name:hun_x_preferred":[
        "Glewitz"
    ],
    "name:ita_x_preferred":[
        "Glewitz"
    ],
    "name:kaz_x_preferred":[
        "\u0413\u043b\u0435\u0432\u0438\u0446"
    ],
    "name:kir_x_preferred":[
        "\u0413\u043b\u0435\u0432\u0438\u0446"
    ],
    "name:mkd_x_preferred":[
        "\u0413\u043b\u0435\u0432\u0438\u0446"
    ],
    "name:msa_x_preferred":[
        "Glewitz"
    ],
    "name:nld_x_preferred":[
        "Glewitz"
    ],
    "name:pol_x_preferred":[
        "Glewitz"
    ],
    "name:por_x_preferred":[
        "Glewitz"
    ],
    "name:ron_x_preferred":[
        "Glewitz"
    ],
    "name:rus_x_preferred":[
        "\u0413\u043b\u0435\u0432\u0438\u0446"
    ],
    "name:spa_x_preferred":[
        "Glewitz"
    ],
    "name:srp_x_preferred":[
        "\u0413\u043b\u0435\u0432\u0438\u0446"
    ],
    "name:ukr_x_preferred":[
        "\u0413\u043b\u0435\u0432\u0456\u0446"
    ],
    "name:uzb_x_preferred":[
        "Glewitz"
    ],
    "name:vie_x_preferred":[
        "Glewitz"
    ],
    "name:vol_x_preferred":[
        "Glewitz"
    ],
    "name:war_x_preferred":[
        "Glewitz"
    ],
    "name:zho_x_preferred":[
        "\u683c\u83b1\u7ef4\u8328"
    ],
    "qs_pg:aaroncc":"DE",
    "qs_pg:gn_country":"DE",
    "qs_pg:gn_fcode":"PPL",
    "qs_pg:gn_pop":0,
    "qs_pg:name":"Glewitz",
    "qs_pg:name_adm0":"Deutschland",
    "qs_pg:name_adm1":"Mecklenburg-Vorpommern",
    "qs_pg:photos":25,
    "qs_pg:photos_1k":5,
    "qs_pg:photos_9k":1,
    "qs_pg:photos_9r":1,
    "qs_pg:photos_all":25,
    "qs_pg:photos_sr":1,
    "qs_pg:pop_sr":0,
    "qs_pg:qs_pg_placetype":"locality",
    "qs_pg:qs_pg_placetype_gp":"Town",
    "qs_pg:woe_adm0":23424829,
    "woe:adm0_id":23424829,
    "woe:name_adm0":"Deutschland",
    "woe:name_adm1":"Mecklenburg-Vorpommern",
    "woe:placetype":"Town",
    "wof:name":"Glewitz",
    "wof:placetype":"neighbourhood"
},
  "geometry": {"coordinates":[13.31835,54.24266],"type":"Point"}
}