{
  "type": "Feature",
  "properties": {
    "gn:admin1_code":"7.0",
    "gn:admin2_code":"53.0",
    "gn:admin3_code":"5358.0",
    "gn:admin4_code":"5358056.0",
    "gn:asciiname":"Ameln",
    "gn:country_code":"DE",
    "gn:dem":98,
    "gn:feature_class":"P",
    "gn:feature_code":"PPL",
    "gn:name":"Ameln",
    "gn:population":0,
    "gn:timezone":"Europe/Berlin",
    "iso:country":"DE",
    "name:deu_x_preferred":[
        "Ameln"
    ],
    "wof:name":"Ameln",
    "wof:placetype":"neighbourhood"
},
  "geometry": {"coordinates":[6.43485,50.98605],"type":"Point"}
}