{
  "type": "Feature",
  "properties": {
    "gn:admin1_code":"2",
    "gn:admin2_code":"92.0",
    "gn:admin3_code":"9272.0",
    "gn:admin4_code":"9272121.0",
    "gn:asciiname":"Unterseilberg",
    "gn:country_code":"DE",
    "gn:dem":663,
    "gn:feature_class":"P",
    "gn:feature_code":"PPL",
    "gn:name":"Unterseilberg",
    "gn:population":0,
    "gn:timezone":"Europe/Berlin",
    "iso:country":"DE",
    "wof:name":"Unterseilberg",
    "wof:placetype":"neighbourhood"
},
  "geometry": {"coordinates":[13.62796,48.80151],"type":"Point"}
}