{
  "type": "Feature",
  "properties": {
    "gn:admin1_code":"6",
    "gn:admin2_code":"0.0",
    "gn:admin3_code":"3354.0",
    "gn:admin4_code":"3354022.0",
    "gn:asciiname":"Harpe",
    "gn:country_code":"DE",
    "gn:dem":37,
    "gn:feature_class":"P",
    "gn:feature_code":"PPL",
    "gn:name":"Harpe",
    "gn:population":0,
    "gn:timezone":"Europe/Berlin",
    "iso:country":"DE",
    "name:deu_x_preferred":[
        "Harpe"
    ],
    "name:ita_x_preferred":[
        "Harpe"
    ],
    "name:jpn_x_preferred":[
        "\u30cf\u30eb\u30d1\u30fc"
    ],
    "name:pol_x_preferred":[
        "Harpe"
    ],
    "name:por_x_preferred":[
        "Harpe"
    ],
    "wof:name":"Harpe",
    "wof:placetype":"neighbourhood"
},
  "geometry": {"coordinates":[10.88426,52.85168],"type":"Point"}
}