{
  "type": "Feature",
  "properties": {
    "gn:admin1_code":"13",
    "gn:admin2_code":"0.0",
    "gn:admin3_code":"14627.0",
    "gn:admin4_code":"14627100.0",
    "gn:asciiname":"Semmelsberg",
    "gn:country_code":"DE",
    "gn:dem":156,
    "gn:feature_class":"P",
    "gn:feature_code":"PPL",
    "gn:name":"Semmelsberg",
    "gn:population":0,
    "gn:timezone":"Europe/Berlin",
    "iso:country":"DE",
    "wof:name":"Semmelsberg",
    "wof:placetype":"neighbourhood"
},
  "geometry": {"coordinates":[13.43276,51.125],"type":"Point"}
}