{
  "type": "Feature",
  "properties": {
    "gn:admin1_code":"5.0",
    "gn:admin2_code":"65.0",
    "gn:admin3_code":"6534.0",
    "gn:admin4_code":"6534008.0",
    "gn:asciiname":"Beltershausen",
    "gn:country_code":"DE",
    "gn:dem":259,
    "gn:feature_class":"P",
    "gn:feature_code":"PPL",
    "gn:name":"Beltershausen",
    "gn:population":0,
    "gn:timezone":"Europe/Berlin",
    "iso:country":"DE",
    "wof:name":"Beltershausen",
    "wof:placetype":"neighbourhood"
},
  "geometry": {"coordinates":[8.81304,50.75803],"type":"Point"}
}