{
  "type": "Feature",
  "properties": {
    "gn:admin1_code":"1.0",
    "gn:admin2_code":"081",
    "gn:admin3_code":"8119.0",
    "gn:admin4_code":"8119075.0",
    "gn:asciiname":"Zwerenberg",
    "gn:country_code":"DE",
    "gn:dem":438,
    "gn:feature_class":"P",
    "gn:feature_code":"PPL",
    "gn:name":"Zwerenberg",
    "gn:population":0,
    "gn:timezone":"Europe/Berlin",
    "iso:country":"DE",
    "wof:name":"Zwerenberg",
    "wof:placetype":"neighbourhood"
},
  "geometry": {"coordinates":[9.5453,49.0119],"type":"Point"}
}