{
  "type": "Feature",
  "properties": {
    "iso:country":"DE",
    "wof:name":"Gompitz",
    "wof:placetype":"neighbourhood"
},
  "geometry": {"coordinates":[13.63755529363942,51.04360633604283],"type":"Point"}
}