{
  "type": "Feature",
  "properties": {
    "gn:admin1_code":"1.0",
    "gn:admin2_code":"84.0",
    "gn:admin3_code":"8436.0",
    "gn:admin4_code":"8436055.0",
    "gn:asciiname":"Bimmlings",
    "gn:country_code":"DE",
    "gn:dem":692,
    "gn:feature_class":"P",
    "gn:feature_code":"PPL",
    "gn:name":"Bimmlings",
    "gn:population":0,
    "gn:timezone":"Europe/Berlin",
    "iso:country":"DE",
    "wof:name":"Bimmlings",
    "wof:placetype":"neighbourhood"
},
  "geometry": {"coordinates":[10.08676,47.84618],"type":"Point"}
}