{
  "type": "Feature",
  "properties": {
    "gn:admin1_code":"13",
    "gn:admin2_code":"0.0",
    "gn:admin3_code":"14522.0",
    "gn:admin4_code":"14522360.0",
    "gn:asciiname":"Frankenau",
    "gn:country_code":"DE",
    "gn:dem":266,
    "gn:feature_class":"P",
    "gn:feature_code":"PPL",
    "gn:name":"Frankenau",
    "gn:population":0,
    "gn:timezone":"Europe/Berlin",
    "iso:country":"DE",
    "name:ara_x_preferred":[
        "\u0641\u0631\u0627\u0646\u0643\u0646\u0627\u0648"
    ],
    "name:azb_x_preferred":[
        "\u0641\u0631\u0627\u0646\u06a9\u0646\u0627\u0648"
    ],
    "name:ceb_x_preferred":[
        "Frankenau"
    ],
    "name:deu_x_preferred":[
        "Frankenau"
    ],
    "name:epo_x_preferred":[
        "Frankenau"
    ],
    "name:fas_x_preferred":[
        "\u0641\u0631\u0627\u0646\u06a9\u0646\u0627\u0648"
    ],
    "name:fra_x_preferred":[
        "Frankenau"
    ],
    "name:hrv_x_preferred":[
        "Frakanava"
    ],
    "name:hun_x_preferred":[
        "Frankenau"
    ],
    "name:ita_x_preferred":[
        "Frankenau"
    ],
    "name:jpn_x_preferred":[
        "\u30d5\u30e9\u30f3\u30b1\u30ca\u30a6"
    ],
    "name:msa_x_preferred":[
        "Frankenau"
    ],
    "name:nld_x_preferred":[
        "Frankenau"
    ],
    "name:pol_x_preferred":[
        "Frankenau"
    ],
    "name:ron_x_preferred":[
        "Frankenau"
    ],
    "name:rus_x_preferred":[
        "\u0424\u0440\u0430\u043d\u043a\u0435\u043d\u0430\u0443"
    ],
    "name:spa_x_preferred":[
        "Frankenau"
    ],
    "name:srp_x_preferred":[
        "\u0424\u0440\u0430\u043d\u043a\u0435\u043d\u0430\u0443"
    ],
    "name:tur_x_preferred":[
        "Frankenau"
    ],
    "name:ukr_x_preferred":[
        "\u0424\u0440\u0430\u043d\u043a\u0435\u043d\u0430\u0443"
    ],
    "name:uzb_x_preferred":[
        "Frankenau"
    ],
    "name:vol_x_preferred":[
        "Frankenau"
    ],
    "name:war_x_preferred":[
        "Frankenau"
    ],
    "name:zho_x_preferred":[
        "\u5f17\u5170\u514b\u7459"
    ],
    "wof:name":"Frankenau",
    "wof:placetype":"neighbourhood"
},
  "geometry": {"coordinates":[12.9233,50.9892],"type":"Point"}
}