{
  "type": "Feature",
  "properties": {
    "gn:admin1_code":"14",
    "gn:admin2_code":"0.0",
    "gn:admin3_code":"15083.0",
    "gn:admin4_code":"15083490.0",
    "gn:asciiname":"Suelldorf",
    "gn:country_code":"DE",
    "gn:dem":67,
    "gn:feature_class":"P",
    "gn:feature_code":"PPL",
    "gn:name":"S\u00fclldorf",
    "gn:population":0,
    "gn:timezone":"Europe/Berlin",
    "iso:country":"DE",
    "name:nds_x_preferred":[
        "S\u00fclldarp"
    ],
    "name:osx_x_preferred":[
        "Suldorp"
    ],
    "wof:name":"Suelldorf",
    "wof:placetype":"neighbourhood"
},
  "geometry": {"coordinates":[11.565,52.02514],"type":"Point"}
}