{
  "type": "Feature",
  "properties": {
    "gn:admin1_code":"13",
    "gn:admin2_code":"0.0",
    "gn:admin3_code":"14730.0",
    "gn:admin4_code":"14730030.0",
    "gn:asciiname":"Doehlen",
    "gn:country_code":"DE",
    "gn:dem":82,
    "gn:feature_class":"P",
    "gn:feature_code":"PPL",
    "gn:name":"D\u00f6hlen",
    "gn:population":0,
    "gn:timezone":"Europe/Berlin",
    "iso:country":"DE",
    "wof:name":"Doehlen",
    "wof:placetype":"neighbourhood"
},
  "geometry": {"coordinates":[13.02532,51.60608],"type":"Point"}
}