{
  "type": "Feature",
  "properties": {
    "gn:admin1_code":"2",
    "gn:admin2_code":"91.0",
    "gn:admin3_code":"9175.0",
    "gn:admin4_code":"9175137.0",
    "gn:asciiname":"Niederaltmannsberg",
    "gn:country_code":"DE",
    "gn:dem":552,
    "gn:feature_class":"P",
    "gn:feature_code":"PPL",
    "gn:name":"Niederaltmannsberg",
    "gn:population":0,
    "gn:timezone":"Europe/Berlin",
    "iso:country":"DE",
    "wof:name":"Niederaltmannsberg",
    "wof:placetype":"neighbourhood"
},
  "geometry": {"coordinates":[12.03746,48.11226],"type":"Point"}
}