{
  "type": "Feature",
  "properties": {
    "gn:admin1_code":"5",
    "gn:admin2_code":"66.0",
    "gn:admin3_code":"6635.0",
    "gn:admin4_code":"6635022.0",
    "gn:asciiname":"Rattlar",
    "gn:country_code":"DE",
    "gn:dem":581,
    "gn:feature_class":"P",
    "gn:feature_code":"PPL",
    "gn:name":"Rattlar",
    "gn:population":0,
    "gn:timezone":"Europe/Berlin",
    "iso:country":"DE",
    "wof:name":"Rattlar",
    "wof:placetype":"neighbourhood"
},
  "geometry": {"coordinates":[8.64705,51.31100000000001],"type":"Point"}
}