{
  "type": "Feature",
  "properties": {
    "gn:admin1_code":"15",
    "gn:admin2_code":"0.0",
    "gn:admin3_code":"16076.0",
    "gn:admin4_code":"16076022.0",
    "gn:asciiname":"Irchwitz",
    "gn:country_code":"DE",
    "gn:dem":384,
    "gn:feature_class":"P",
    "gn:feature_code":"PPL",
    "gn:name":"Irchwitz",
    "gn:population":0,
    "gn:timezone":"Europe/Berlin",
    "iso:country":"DE",
    "name:und_x_variant":[
        "Greiz-Irchwitz",
        "Irchwitz"
    ],
    "wof:name":"Irchwitz",
    "wof:placetype":"neighbourhood"
},
  "geometry": {"coordinates":[12.21775,50.64574],"type":"Point"}
}