{
  "type": "Feature",
  "properties": {
    "gn:admin1_code":"6",
    "gn:admin2_code":"0.0",
    "gn:admin3_code":"3354.0",
    "gn:admin4_code":"3354018.0",
    "gn:asciiname":"Luesen",
    "gn:country_code":"DE",
    "gn:dem":17,
    "gn:feature_class":"P",
    "gn:feature_code":"PPL",
    "gn:name":"L\u00fcsen",
    "gn:population":0,
    "gn:timezone":"Europe/Berlin",
    "iso:country":"DE",
    "wof:name":"Luesen",
    "wof:placetype":"neighbourhood"
},
  "geometry": {"coordinates":[11.1213,52.9932],"type":"Point"}
}