{
  "type": "Feature",
  "properties": {
    "gn:admin1_code":"15",
    "gn:admin2_code":"0.0",
    "gn:admin3_code":"16065.0",
    "gn:admin4_code":"16065074.0",
    "gn:asciiname":"Obertopfstedt",
    "gn:country_code":"DE",
    "gn:dem":190,
    "gn:feature_class":"P",
    "gn:feature_code":"PPL",
    "gn:name":"Obertopfstedt",
    "gn:population":0,
    "gn:timezone":"Europe/Berlin",
    "iso:country":"DE",
    "wof:name":"Obertopfstedt",
    "wof:placetype":"neighbourhood"
},
  "geometry": {"coordinates":[10.94893,51.2492],"type":"Point"}
}