{
  "type": "Feature",
  "properties": {
    "gn:admin1_code":"5",
    "gn:admin2_code":"66.0",
    "gn:admin3_code":"6634.0",
    "gn:admin4_code":"6634009.0",
    "gn:asciiname":"Luetzelwig",
    "gn:country_code":"DE",
    "gn:dem":203,
    "gn:feature_class":"P",
    "gn:feature_code":"PPL",
    "gn:name":"L\u00fctzelwig",
    "gn:population":0,
    "gn:timezone":"Europe/Berlin",
    "iso:country":"DE",
    "wof:name":"Luetzelwig",
    "wof:placetype":"neighbourhood"
},
  "geometry": {"coordinates":[9.36789,51.00728],"type":"Point"}
}