{
  "type": "Feature",
  "properties": {
    "gn:admin1_code":"11",
    "gn:admin2_code":"0.0",
    "gn:admin3_code":"12067.0",
    "gn:admin4_code":"12067473.0",
    "gn:asciiname":"Hasenfelde",
    "gn:country_code":"DE",
    "gn:dem":66,
    "gn:feature_class":"P",
    "gn:feature_code":"PPL",
    "gn:name":"Hasenfelde",
    "gn:population":0,
    "gn:timezone":"Europe/Berlin",
    "iso:country":"DE",
    "wof:name":"Hasenfelde",
    "wof:placetype":"neighbourhood"
},
  "geometry": {"coordinates":[14.20742,52.43008],"type":"Point"}
}