{
  "type": "Feature",
  "properties": {
    "gn:admin1_code":"2",
    "gn:admin2_code":"93.0",
    "gn:admin3_code":"9377.0",
    "gn:admin4_code":"9377157.0",
    "gn:asciiname":"Hard",
    "gn:country_code":"DE",
    "gn:dem":675,
    "gn:feature_class":"P",
    "gn:feature_code":"PPL",
    "gn:name":"Hard",
    "gn:population":0,
    "gn:timezone":"Europe/Berlin",
    "iso:country":"DE",
    "wof:name":"Hard",
    "wof:placetype":"neighbourhood"
},
  "geometry": {"coordinates":[12.08577,49.94172],"type":"Point"}
}