{
  "type": "Feature",
  "properties": {
    "gn:admin1_code":"15",
    "gn:admin2_code":"0.0",
    "gn:admin3_code":"16073.0",
    "gn:admin4_code":"16073005.0",
    "gn:asciiname":"Watzdorf",
    "gn:country_code":"DE",
    "gn:dem":242,
    "gn:feature_class":"P",
    "gn:feature_code":"PPL",
    "gn:name":"Watzdorf",
    "gn:population":0,
    "gn:timezone":"Europe/Berlin",
    "iso:country":"DE",
    "wof:name":"Watzdorf",
    "wof:placetype":"neighbourhood"
},
  "geometry": {"coordinates":[11.23631,50.69078],"type":"Point"}
}