{
  "type": "Feature",
  "properties": {
    "gn:admin1_code":"1",
    "gn:admin2_code":"83.0",
    "gn:admin3_code":"8336.0",
    "gn:admin4_code":"8336050.0",
    "gn:asciiname":"Hasenloch",
    "gn:country_code":"DE",
    "gn:dem":312,
    "gn:feature_class":"P",
    "gn:feature_code":"PPL",
    "gn:name":"Hasenloch",
    "gn:population":0,
    "gn:timezone":"Europe/Berlin",
    "iso:country":"DE",
    "wof:name":"Hasenloch",
    "wof:placetype":"neighbourhood"
},
  "geometry": {"coordinates":[7.66667,47.63333],"type":"Point"}
}