{
  "type": "Feature",
  "properties": {
    "gn:admin1_code":"2.0",
    "gn:admin2_code":"91.0",
    "gn:admin3_code":"9189.0",
    "gn:admin4_code":"9189139.0",
    "gn:asciiname":"Blindau",
    "gn:country_code":"DE",
    "gn:dem":713,
    "gn:feature_class":"P",
    "gn:feature_code":"PPL",
    "gn:name":"Blindau",
    "gn:population":0,
    "gn:timezone":"Europe/Berlin",
    "iso:country":"DE",
    "wof:name":"Blindau",
    "wof:placetype":"neighbourhood"
},
  "geometry": {"coordinates":[12.47721,47.66308],"type":"Point"}
}