{
  "type": "Feature",
  "properties": {
    "gn:admin1_code":"2",
    "gn:admin2_code":"94.0",
    "gn:admin3_code":"9471.0",
    "gn:admin4_code":"9471131.0",
    "gn:asciiname":"Schlusselau",
    "gn:country_code":"DE",
    "gn:dem":261,
    "gn:feature_class":"P",
    "gn:feature_code":"PPL",
    "gn:name":"Schl\u00fcsselau",
    "gn:population":0,
    "gn:timezone":"Europe/Berlin",
    "iso:country":"DE",
    "wof:name":"Schlusselau",
    "wof:placetype":"neighbourhood"
},
  "geometry": {"coordinates":[10.91088,49.7898],"type":"Point"}
}