{
  "type": "Feature",
  "properties": {
    "gn:admin1_code":"2.0",
    "gn:admin2_code":"91.0",
    "gn:admin3_code":"9189.0",
    "gn:admin4_code":"9189157.0",
    "gn:asciiname":"Aspertsham",
    "gn:country_code":"DE",
    "gn:dem":540,
    "gn:feature_class":"P",
    "gn:feature_code":"PPL",
    "gn:name":"Aspertsham",
    "gn:population":0,
    "gn:timezone":"Europe/Berlin",
    "iso:country":"DE",
    "wof:name":"Aspertsham",
    "wof:placetype":"neighbourhood"
},
  "geometry": {"coordinates":[12.57634,48.01226],"type":"Point"}
}