{
  "type": "Feature",
  "properties": {
    "gn:admin1_code":"2",
    "gn:admin2_code":"91.0",
    "gn:admin3_code":"9178.0",
    "gn:admin4_code":"9178156.0",
    "gn:asciiname":"Thonhausen",
    "gn:country_code":"DE",
    "gn:dem":485,
    "gn:feature_class":"P",
    "gn:feature_code":"PPL",
    "gn:name":"Thonhausen",
    "gn:population":0,
    "gn:timezone":"Europe/Berlin",
    "iso:country":"DE",
    "name:bak_x_preferred":[
        "\u0422\u043e\u043d\u0445\u0430\u0443\u0437\u0435\u043d"
    ],
    "name:ceb_x_preferred":[
        "Thonhausen"
    ],
    "name:deu_x_preferred":[
        "Thonhausen"
    ],
    "name:epo_x_preferred":[
        "Thonhausen"
    ],
    "name:eus_x_preferred":[
        "Thonhausen"
    ],
    "name:fas_x_preferred":[
        "\u062a\u0648\u0646\u0647\u0627\u0648\u0632\u0646"
    ],
    "name:fra_x_preferred":[
        "Thonhausen"
    ],
    "name:hun_x_preferred":[
        "Thonhausen"
    ],
    "name:ita_x_preferred":[
        "Thonhausen"
    ],
    "name:kaz_x_preferred":[
        "\u0422\u043e\u043d\u0445\u0430\u0443\u0437\u0435\u043d"
    ],
    "name:kir_x_preferred":[
        "\u0422\u043e\u043d\u0445\u0430\u0443\u0437\u0435\u043d"
    ],
    "name:mkd_x_preferred":[
        "\u0422\u043e\u043d\u0445\u0430\u0443\u0437\u0435\u043d"
    ],
    "name:msa_x_preferred":[
        "Thonhausen"
    ],
    "name:nld_x_preferred":[
        "Thonhausen"
    ],
    "name:pol_x_preferred":[
        "Thonhausen"
    ],
    "name:por_x_preferred":[
        "Thonhausen"
    ],
    "name:ron_x_preferred":[
        "Thonhausen"
    ],
    "name:rus_x_preferred":[
        "\u0422\u043e\u043d\u0445\u0430\u0443\u0437\u0435\u043d"
    ],
    "name:spa_x_preferred":[
        "Thonhausen"
    ],
    "name:srp_x_preferred":[
        "\u0422\u043e\u043d\u0445\u0430\u0443\u0437\u0435\u043d"
    ],
    "name:ukr_x_preferred":[
        "\u0422\u043e\u043d\u0433\u0430\u0443\u0437\u0435\u043d"
    ],
    "name:uzb_x_preferred":[
        "Thonhausen"
    ],
    "name:vie_x_preferred":[
        "Thonhausen"
    ],
    "name:vol_x_preferred":[
        "Thonhausen"
    ],
    "name:war_x_preferred":[
        "Thonhausen"
    ],
    "name:zho_x_preferred":[
        "\u901a\u8c6a\u68ee"
    ],
    "wof:name":"Thonhausen",
    "wof:placetype":"neighbourhood"
},
  "geometry": {"coordinates":[11.74036,48.47854],"type":"Point"}
}