{
  "type": "Feature",
  "properties": {
    "gn:admin1_code":"14",
    "gn:admin2_code":"0.0",
    "gn:admin3_code":"15088.0",
    "gn:admin4_code":"15088319.0",
    "gn:asciiname":"Schwittersdorf",
    "gn:country_code":"DE",
    "gn:dem":184,
    "gn:feature_class":"P",
    "gn:feature_code":"PPL",
    "gn:name":"Schwittersdorf",
    "gn:population":0,
    "gn:timezone":"Europe/Berlin",
    "iso:country":"DE",
    "name:gml_x_preferred":[
        "Swithardestorp [a. 1180]"
    ],
    "wof:name":"Schwittersdorf",
    "wof:placetype":"neighbourhood"
},
  "geometry": {"coordinates":[11.70959,51.56233],"type":"Point"}
}