{
  "type": "Feature",
  "properties": {
    "iso:country":"DE",
    "name:ceb_x_preferred":[
        "Gruna"
    ],
    "name:ces_x_preferred":[
        "Gruna"
    ],
    "name:deu_x_preferred":[
        "Gruna"
    ],
    "name:swe_x_preferred":[
        "Gruna"
    ],
    "wof:name":"Gruna",
    "wof:placetype":"neighbourhood"
},
  "geometry": {"coordinates":[13.7882740584387,51.03448547982678],"type":"Point"}
}