{
  "type": "Feature",
  "properties": {
    "gn:admin1_code":"2",
    "gn:admin2_code":"94.0",
    "gn:admin3_code":"9474.0",
    "gn:admin4_code":"9474132.0",
    "gn:asciiname":"Lilling",
    "gn:country_code":"DE",
    "gn:dem":520,
    "gn:feature_class":"P",
    "gn:feature_code":"PPL",
    "gn:name":"Lilling",
    "gn:population":0,
    "gn:timezone":"Europe/Berlin",
    "iso:country":"DE",
    "wof:name":"Lilling",
    "wof:placetype":"neighbourhood"
},
  "geometry": {"coordinates":[11.29034,49.6359],"type":"Point"}
}