{
  "type": "Feature",
  "properties": {
    "gn:admin1_code":"1",
    "gn:admin2_code":"81.0",
    "gn:admin3_code":"8127.0",
    "gn:admin4_code":"8127073.0",
    "gn:asciiname":"Sattelweiler",
    "gn:country_code":"DE",
    "gn:dem":443,
    "gn:feature_class":"P",
    "gn:feature_code":"PPL",
    "gn:name":"Sattelweiler",
    "gn:population":0,
    "gn:timezone":"Europe/Berlin",
    "iso:country":"DE",
    "wof:name":"Sattelweiler",
    "wof:placetype":"neighbourhood"
},
  "geometry": {"coordinates":[10.07614,49.16961],"type":"Point"}
}