{
  "type": "Feature",
  "properties": {
    "iso:country":"DE",
    "name:aze_x_preferred":[
        "Ernest Telman"
    ],
    "name:bel_x_preferred":[
        "\u042d\u0440\u043d\u0441\u0442 \u0422\u044d\u043b\u044c\u043c\u0430\u043d"
    ],
    "name:bel_x_variant":[
        "\u042d\u0440\u043d\u0441\u0442 \u0422\u044d\u043b\u044c\u043c\u0430\u043d"
    ],
    "name:bre_x_preferred":[
        "Ernst Th\u00e4lmann"
    ],
    "name:bul_x_preferred":[
        "\u0415\u0440\u043d\u0441\u0442 \u0422\u0435\u043b\u043c\u0430\u043d"
    ],
    "name:cat_x_preferred":[
        "Ernst Th\u00e4lmann"
    ],
    "name:ces_x_preferred":[
        "Ernst Th\u00e4lmann"
    ],
    "name:chv_x_preferred":[
        "\u042d\u0440\u043d\u0441\u0442 \u0422\u0435\u043b\u044c\u043c\u0430\u043d"
    ],
    "name:dan_x_preferred":[
        "Ernst Th\u00e4lmann"
    ],
    "name:deu_x_preferred":[
        "Ernst Th\u00e4lmann"
    ],
    "name:deu_x_variant":[
        "Hummelsheim"
    ],
    "qs:gn_adm0_cc":"DE",
    "qs:gn_local":2886242,
    "qs:gn_nam_loc":"Koeln",
    "qs:gn_namadm1":"07",
    "qs:local_max":29601,
    "qs:local_sum":50930,
    "qs:localhoods":35,
    "qs:name":"Hummelsheim",
    "qs:name_adm0":"Deutschland",
    "qs:name_adm1":"Nordrhein-Westfalen",
    "qs:name_adm2":"Stadtkreis K\u00f6ln",
    "qs:name_lau":"Stadtteil D\u00fcnnwald",
    "qs:name_local":"K\u00f6ln",
    "qs:photo_max":21,
    "qs:photo_sum":23,
    "qs:placetype":"Suburb",
    "qs:quad_count":2,
    "qs:woe_adm0":23424829,
    "qs:woe_adm1":2345487,
    "qs:woe_adm2":12597059,
    "qs:woe_lau":26822820,
    "qs:woe_local":667931,
    "qs:woe_ver":"7.10.0",
    "wof:lang":[
        "ger"
    ],
    "wof:name":"Hummelsheim",
    "wof:placetype":"neighbourhood"
},
  "geometry": {"coordinates":[7.082957,51.015482],"type":"Point"}
}