{
  "type": "Feature",
  "properties": {
    "gn:admin1_code":"2.0",
    "gn:admin2_code":"91.0",
    "gn:admin3_code":"9182.0",
    "gn:admin4_code":"9182136.0",
    "gn:asciiname":"Allerheiligen",
    "gn:country_code":"DE",
    "gn:dem":746,
    "gn:feature_class":"P",
    "gn:feature_code":"PPL",
    "gn:name":"Allerheiligen",
    "gn:population":0,
    "gn:timezone":"Europe/Berlin",
    "iso:country":"DE",
    "name:als_x_preferred":[
        "Allerheiligen"
    ],
    "name:bar_x_preferred":[
        "Allerheiligen"
    ],
    "name:deu_x_preferred":[
        "Allerheiligen"
    ],
    "name:fra_x_preferred":[
        "Allerheiligen"
    ],
    "name:ita_x_preferred":[
        "Allerheiligen"
    ],
    "name:pol_x_preferred":[
        "Allerheiligen"
    ],
    "wof:name":"Allerheiligen",
    "wof:placetype":"neighbourhood"
},
  "geometry": {"coordinates":[11.72104,47.82261],"type":"Point"}
}