{
  "type": "Feature",
  "properties": {
    "gn:country":"DE",
    "gn:fcode":"PPL",
    "gn:population":0,
    "iso:country":"DE",
    "name:als_x_preferred":[
        "Homberg"
    ],
    "name:ceb_x_preferred":[
        "Homberg"
    ],
    "name:deu_x_preferred":[
        "Homberg"
    ],
    "name:epo_x_preferred":[
        "Homberg"
    ],
    "name:eus_x_preferred":[
        "Homberg"
    ],
    "name:fas_x_preferred":[
        "\u0647\u0648\u0645\u0628\u0631\u06af"
    ],
    "name:fra_x_preferred":[
        "Homberg"
    ],
    "name:ita_x_preferred":[
        "Homberg"
    ],
    "name:jpn_x_preferred":[
        "\u30db\u30e0\u30d9\u30eb\u30af"
    ],
    "name:nld_x_preferred":[
        "Homberg"
    ],
    "name:pol_x_preferred":[
        "Homberg"
    ],
    "name:por_x_preferred":[
        "Homberg"
    ],
    "name:ron_x_preferred":[
        "Homberg"
    ],
    "name:rus_x_preferred":[
        "\u0425\u043e\u043c\u0431\u0435\u0440\u0433"
    ],
    "name:srp_x_preferred":[
        "\u0425\u043e\u043c\u0431\u0435\u0440\u0433"
    ],
    "name:swe_x_preferred":[
        "Homberg"
    ],
    "name:und_x_variant":[
        "Homberg-Meiersberg"
    ],
    "name:vol_x_preferred":[
        "Homberg"
    ],
    "qs_pg:aaroncc":"DE",
    "qs_pg:gn_country":"DE",
    "qs_pg:gn_fcode":"PPL",
    "qs_pg:gn_pop":0,
    "qs_pg:name":"Homberg",
    "qs_pg:name_adm0":"Deutschland",
    "qs_pg:name_adm1":"Nordrhein-Westfalen",
    "qs_pg:photos":7,
    "qs_pg:photos_1k":1,
    "qs_pg:photos_9k":1,
    "qs_pg:photos_9r":1,
    "qs_pg:photos_all":7,
    "qs_pg:photos_sr":1,
    "qs_pg:pop_sr":0,
    "qs_pg:qs_pg_placetype":"locality",
    "qs_pg:qs_pg_placetype_gp":"Town",
    "qs_pg:woe_adm0":23424829,
    "woe:adm0_id":23424829,
    "woe:name_adm0":"Deutschland",
    "woe:name_adm1":"Nordrhein-Westfalen",
    "woe:placetype":"Town",
    "wof:name":"Homberg",
    "wof:placetype":"neighbourhood"
},
  "geometry": {"coordinates":[6.92615,51.29238],"type":"Point"}
}