{
  "type": "Feature",
  "properties": {
    "gn:admin1_code":"1.0",
    "gn:admin2_code":"083",
    "gn:admin3_code":"8326.0",
    "gn:admin4_code":"8326005.0",
    "gn:asciiname":"Zollhaus",
    "gn:country_code":"DE",
    "gn:dem":702,
    "gn:feature_class":"P",
    "gn:feature_code":"PPL",
    "gn:name":"Zollhaus",
    "gn:population":0,
    "gn:timezone":"Europe/Berlin",
    "iso:country":"DE",
    "wof:name":"Zollhaus",
    "wof:placetype":"neighbourhood"
},
  "geometry": {"coordinates":[8.55487,47.83713],"type":"Point"}
}