{
  "type": "Feature",
  "properties": {
    "gn:admin1_code":"2",
    "gn:admin2_code":"91.0",
    "gn:admin3_code":"9171.0",
    "gn:admin4_code":"9171127.0",
    "gn:asciiname":"Moosbuch",
    "gn:country_code":"DE",
    "gn:dem":483,
    "gn:feature_class":"P",
    "gn:feature_code":"PPL",
    "gn:name":"Moosbuch",
    "gn:population":0,
    "gn:timezone":"Europe/Berlin",
    "iso:country":"DE",
    "wof:name":"Moosbuch",
    "wof:placetype":"neighbourhood"
},
  "geometry": {"coordinates":[12.60516,48.34169],"type":"Point"}
}