{
  "type": "Feature",
  "properties": {
    "gn:admin1_code":"1.0",
    "gn:admin2_code":"84.0",
    "gn:admin3_code":"8426.0",
    "gn:admin4_code":"8426038.0",
    "gn:asciiname":"Bebenhaus",
    "gn:country_code":"DE",
    "gn:dem":666,
    "gn:feature_class":"P",
    "gn:feature_code":"PPL",
    "gn:name":"Bebenhaus",
    "gn:population":0,
    "gn:timezone":"Europe/Berlin",
    "iso:country":"DE",
    "wof:name":"Bebenhaus",
    "wof:placetype":"neighbourhood"
},
  "geometry": {"coordinates":[9.88333,48.01667],"type":"Point"}
}