{
  "type": "Feature",
  "properties": {
    "gn:country":"DE",
    "gn:fcode":"PPL",
    "gn:population":0,
    "iso:country":"DE",
    "name:deu_x_preferred":[
        "Gr\u00fcnenthal"
    ],
    "name:fas_x_preferred":[
        "\u06af\u0631\u0648\u0646\u0646\u062a\u0627\u0644"
    ],
    "name:jpn_x_preferred":[
        "\u30b0\u30ea\u30e5\u30fc\u30cd\u30f3\u30bf\u30fc\u30eb"
    ],
    "name:kor_x_preferred":[
        "\uadf8\ub93c\ub128\ud0c8"
    ],
    "name:ksh_x_preferred":[
        "Chemie Jr\u00f6nedaahl"
    ],
    "name:nor_x_preferred":[
        "Gr\u00fcnenthal"
    ],
    "name:spa_x_preferred":[
        "Gr\u00fcnenthal GmbH"
    ],
    "name:swe_x_preferred":[
        "Gr\u00fcnenthal"
    ],
    "name:und_x_variant":[
        "Gr\u00fcneutal"
    ],
    "name:zho_x_preferred":[
        "\u683c\u862d\u6cf0"
    ],
    "qs_pg:aaroncc":"DE",
    "qs_pg:gn_country":"DE",
    "qs_pg:gn_fcode":"PPL",
    "qs_pg:gn_pop":0,
    "qs_pg:name":"Gr\u00fcnenthal",
    "qs_pg:name_adm0":"Deutschland",
    "qs_pg:name_adm1":"Nordrhein-Westfalen",
    "qs_pg:photos":5,
    "qs_pg:photos_1k":1,
    "qs_pg:photos_9k":1,
    "qs_pg:photos_9r":1,
    "qs_pg:photos_all":5,
    "qs_pg:photos_sr":1,
    "qs_pg:pop_sr":0,
    "qs_pg:qs_pg_placetype":"neighbourhood",
    "qs_pg:qs_pg_placetype_gp":"Suburb",
    "qs_pg:woe_adm0":23424829,
    "woe:adm0_id":23424829,
    "woe:name_adm0":"Deutschland",
    "woe:name_adm1":"Nordrhein-Westfalen",
    "woe:placetype":"Suburb",
    "wof:name":"Gr\u00fcnenthal",
    "wof:placetype":"neighbourhood"
},
  "geometry": {"coordinates":[6.04916,50.81135],"type":"Point"}
}