{
  "type": "Feature",
  "properties": {
    "gn:gn_country":"DE",
    "gn:gn_fcode":"PPLA4",
    "gn:gn_pop":325,
    "gn:population":325,
    "iso:country":"DE",
    "name:baq_x_preferred":[
        "K\u00f6werich"
    ],
    "name:chi_x_preferred":[
        "\u514b\u97e6\u91cc\u5e0c"
    ],
    "name:dut_x_preferred":[
        "K\u00f6werich"
    ],
    "name:eng_x_preferred":[
        "K\u00f6werich"
    ],
    "name:epo_x_preferred":[
        "K\u00f6werich"
    ],
    "name:fre_x_preferred":[
        "K\u00f6werich"
    ],
    "name:ger_x_preferred":[
        "K\u00f6werich"
    ],
    "name:hun_x_preferred":[
        "K\u00f6werich"
    ],
    "name:ita_x_preferred":[
        "K\u00f6werich"
    ],
    "name:jpn_x_preferred":[
        "\u30b1\u30fc\u30f4\u30a7\u30ea\u30d2"
    ],
    "name:may_x_preferred":[
        "K\u00f6werich"
    ],
    "name:per_x_preferred":[
        "\u06a9\u0648\u0648\u0631\u0627\u06cc\u0634"
    ],
    "name:pol_x_preferred":[
        "K\u00f6werich"
    ],
    "name:por_x_preferred":[
        "K\u00f6werich"
    ],
    "name:rum_x_preferred":[
        "K\u00f6werich"
    ],
    "name:rus_x_preferred":[
        "\u041a\u0451\u0432\u0435\u0440\u0438\u0445"
    ],
    "name:srp_x_preferred":[
        "\u041a\u0435\u0432\u0435\u0440\u0438\u0445"
    ],
    "name:ukr_x_preferred":[
        "\u041a\u0435\u0432\u0435\u0440\u0456\u0445"
    ],
    "name:uzb_x_preferred":[
        "K\u00f6werich"
    ],
    "name:vie_x_preferred":[
        "K\u00f6werich"
    ],
    "name:vol_x_preferred":[
        "K\u00f6werich"
    ],
    "name:war_x_preferred":[
        "K\u00f6werich"
    ],
    "qs_pg:aaroncc":"DE",
    "qs_pg:gn_country":"DE",
    "qs_pg:gn_fcode":"PPLA4",
    "qs_pg:gn_pop":325,
    "qs_pg:name":"K\u00f6werich",
    "qs_pg:photos_9r":0,
    "qs_pg:photos_sr":0,
    "qs_pg:pop_sr":2,
    "qs_pg:qs_pg_placetype":"locality",
    "wof:name":"K\u00f6werich",
    "wof:placetype":"locality",
    "wof:population":325
},
  "geometry": {"coordinates":[6.88333,49.83333],"type":"Point"}
}