{
  "type": "Feature",
  "properties": {
    "abrv:eng_x_preferred":[
        "Twk"
    ],
    "iso:country":"DE",
    "name:deu_x_preferred":[
        "Toitenwinkel"
    ],
    "name:unk_x_variant":[
        "Toitenwinkel"
    ],
    "qs:gn_adm0_cc":"DE",
    "qs:gn_fcode":"PPL",
    "qs:gn_local":2844588,
    "qs:gn_nam_loc":"rostock",
    "qs:gn_namadm1":"12",
    "qs:gn_name":"Toitenwinkel",
    "qs:local_max":6613,
    "qs:local_sum":19240,
    "qs:localhoods":23,
    "qs:name":"Toitenwinkel",
    "qs:name_adm0":"Deutschland",
    "qs:name_adm1":"Mecklenburg-Vorpommern",
    "qs:name_adm2":"Stadtkreis Rostock",
    "qs:name_lau":"Dierkow (Neu)",
    "qs:name_local":"Rostock",
    "qs:photo_max":12,
    "qs:photo_sum":40,
    "qs:placetype":"Suburb",
    "qs:quad_count":10,
    "qs:woe_adm0":23424829,
    "qs:woe_adm1":2345492,
    "qs:woe_adm2":12597074,
    "qs:woe_lau":26823185,
    "qs:woe_local":689776,
    "qs:woe_ver":"7.10.0",
    "wof:lang":[
        "ger"
    ],
    "wof:name":"Toitenwinkel",
    "wof:placetype":"neighbourhood",
    "wof:shortcode":"TWK"
},
  "geometry": {"coordinates":[12.146759,54.118508],"type":"Point"}
}