{
  "type": "Feature",
  "properties": {
    "gn:admin1_code":"2.0",
    "gn:admin2_code":"94.0",
    "gn:admin3_code":"9475.0",
    "gn:admin4_code":"9475112.0",
    "gn:asciiname":"Thierbacher Muehle",
    "gn:country_code":"DE",
    "gn:dem":508,
    "gn:feature_class":"P",
    "gn:feature_code":"PPL",
    "gn:name":"Thierbacher M\u00fchle",
    "gn:population":0,
    "gn:timezone":"Europe/Berlin",
    "iso:country":"DE",
    "wof:name":"Thierbacher Muehle",
    "wof:placetype":"neighbourhood"
},
  "geometry": {"coordinates":[11.66877,50.35169000000001],"type":"Point"}
}