{
  "type": "Feature",
  "properties": {
    "gn:admin1_code":"5",
    "gn:admin2_code":"65.0",
    "gn:admin3_code":"6535.0",
    "gn:admin4_code":"6535004.0",
    "gn:asciiname":"Salz",
    "gn:country_code":"DE",
    "gn:dem":387,
    "gn:feature_class":"P",
    "gn:feature_code":"PPL",
    "gn:name":"Salz",
    "gn:population":0,
    "gn:timezone":"Europe/Berlin",
    "iso:country":"DE",
    "name:als_x_preferred":[
        "Salz"
    ],
    "name:arg_x_preferred":[
        "Salz"
    ],
    "name:ceb_x_preferred":[
        "Salz"
    ],
    "name:deu_x_preferred":[
        "Salz"
    ],
    "name:epo_x_preferred":[
        "Salz"
    ],
    "name:fra_x_preferred":[
        "Salz"
    ],
    "name:frr_x_preferred":[
        "Saalt"
    ],
    "name:hat_x_preferred":[
        "S\u00e8l"
    ],
    "name:heb_x_preferred":[
        "\u05d6\u05dc\u05e5"
    ],
    "name:ita_x_preferred":[
        "Salz"
    ],
    "name:nld_x_preferred":[
        "Salz"
    ],
    "name:pol_x_preferred":[
        "Salz"
    ],
    "name:srp_x_preferred":[
        "\u0417\u0430\u043b\u0446"
    ],
    "name:swe_x_preferred":[
        "Salz"
    ],
    "name:vol_x_preferred":[
        "Salz"
    ],
    "wof:name":"Salz",
    "wof:placetype":"neighbourhood"
},
  "geometry": {"coordinates":[9.36651,50.42698],"type":"Point"}
}