{
  "type": "Feature",
  "properties": {
    "gn:admin1_code":"2",
    "gn:admin2_code":"94.0",
    "gn:admin3_code":"9472.0",
    "gn:admin4_code":"9472179.0",
    "gn:asciiname":"Pullendorf",
    "gn:country_code":"DE",
    "gn:dem":495,
    "gn:feature_class":"P",
    "gn:feature_code":"PPL",
    "gn:name":"Pullendorf",
    "gn:population":0,
    "gn:timezone":"Europe/Berlin",
    "iso:country":"DE",
    "wof:name":"Pullendorf",
    "wof:placetype":"neighbourhood"
},
  "geometry": {"coordinates":[11.46077,49.81367],"type":"Point"}
}