{
  "type": "Feature",
  "properties": {
    "gn:admin1_code":"2",
    "gn:admin2_code":"91.0",
    "gn:admin3_code":"9172.0",
    "gn:admin4_code":"9172122.0",
    "gn:asciiname":"Froschham",
    "gn:country_code":"DE",
    "gn:dem":438,
    "gn:feature_class":"P",
    "gn:feature_code":"PPL",
    "gn:name":"Froschham",
    "gn:population":0,
    "gn:timezone":"Europe/Berlin",
    "iso:country":"DE",
    "wof:name":"Froschham",
    "wof:placetype":"neighbourhood"
},
  "geometry": {"coordinates":[12.91112,47.92776],"type":"Point"}
}