{
  "type": "Feature",
  "properties": {
    "gn:admin1_code":"13",
    "gn:admin2_code":"0.0",
    "gn:admin3_code":"14522.0",
    "gn:admin4_code":"14522220.0",
    "gn:asciiname":"Eichardt",
    "gn:country_code":"DE",
    "gn:dem":242,
    "gn:feature_class":"P",
    "gn:feature_code":"PPL",
    "gn:name":"Eichardt",
    "gn:population":0,
    "gn:timezone":"Europe/Berlin",
    "iso:country":"DE",
    "wof:name":"Eichardt",
    "wof:placetype":"neighbourhood"
},
  "geometry": {"coordinates":[13.02004,51.17469000000001],"type":"Point"}
}