{
  "type": "Feature",
  "properties": {
    "gn:admin1_code":"6",
    "gn:admin2_code":"0.0",
    "gn:admin3_code":"3458.0",
    "gn:admin4_code":"3458005.0",
    "gn:asciiname":"Steenhafe",
    "gn:country_code":"DE",
    "gn:dem":29,
    "gn:feature_class":"P",
    "gn:feature_code":"PPL",
    "gn:name":"Steenhafe",
    "gn:population":0,
    "gn:timezone":"Europe/Berlin",
    "iso:country":"DE",
    "wof:name":"Steenhafe",
    "wof:placetype":"neighbourhood"
},
  "geometry": {"coordinates":[8.5665,53.06926],"type":"Point"}
}