{
  "type": "Feature",
  "properties": {
    "gn:admin1_code":"2",
    "gn:admin2_code":"92.0",
    "gn:admin3_code":"9271.0",
    "gn:admin4_code":"9271141.0",
    "gn:asciiname":"Holzhauser",
    "gn:country_code":"DE",
    "gn:dem":405,
    "gn:feature_class":"P",
    "gn:feature_code":"PPLL",
    "gn:name":"Holzh\u00e4user",
    "gn:population":0,
    "gn:timezone":"Europe/Berlin",
    "iso:country":"DE",
    "wof:name":"Holzhauser",
    "wof:placetype":"neighbourhood"
},
  "geometry": {"coordinates":[12.95244,48.6448],"type":"Point"}
}