{
  "type": "Feature",
  "properties": {
    "gn:admin1_code":"6",
    "gn:admin2_code":"0.0",
    "gn:admin3_code":"3358.0",
    "gn:admin4_code":"3358019.0",
    "gn:asciiname":"Langeloh",
    "gn:country_code":"DE",
    "gn:dem":96,
    "gn:feature_class":"P",
    "gn:feature_code":"PPL",
    "gn:name":"Langeloh",
    "gn:population":0,
    "gn:timezone":"Europe/Berlin",
    "iso:country":"DE",
    "name:ceb_x_preferred":[
        "Langeloh"
    ],
    "name:deu_x_preferred":[
        "Langeloh"
    ],
    "name:fas_x_preferred":[
        "\u0644\u0627\u0646\u06af\u0644\u0648\u0647"
    ],
    "name:nds_x_preferred":[
        "Langloh"
    ],
    "wof:name":"Langeloh",
    "wof:placetype":"neighbourhood"
},
  "geometry": {"coordinates":[9.78623,53.06208],"type":"Point"}
}