{
  "type": "Feature",
  "properties": {
    "gn:admin1_code":"14",
    "gn:admin2_code":"0.0",
    "gn:admin3_code":"15085.0",
    "gn:admin4_code":"15085235.0",
    "gn:asciiname":"Gersdorfer Burg",
    "gn:country_code":"DE",
    "gn:dem":152,
    "gn:feature_class":"P",
    "gn:feature_code":"PPL",
    "gn:name":"Gersdorfer Burg",
    "gn:population":0,
    "gn:timezone":"Europe/Berlin",
    "iso:country":"DE",
    "wof:name":"Gersdorfer Burg",
    "wof:placetype":"neighbourhood"
},
  "geometry": {"coordinates":[11.21153,51.76408],"type":"Point"}
}