{
  "type": "Feature",
  "properties": {
    "gn:admin1_code":"7",
    "gn:admin2_code":"53.0",
    "gn:admin3_code":"5378.0",
    "gn:admin4_code":"5378032.0",
    "gn:asciiname":"Doellersweg",
    "gn:cc2":"DE",
    "gn:country_code":"DE",
    "gn:dem":276,
    "gn:feature_class":"P",
    "gn:feature_code":"PPL",
    "gn:name":"D\u00f6llersweg",
    "gn:population":0,
    "gn:timezone":"Europe/Berlin",
    "iso:country":"DE",
    "name:und_x_variant":[
        "Dollernweg",
        "D\u00f6llersweg"
    ],
    "wof:name":"Doellersweg",
    "wof:placetype":"neighbourhood"
},
  "geometry": {"coordinates":[7.19002,51.12385],"type":"Point"}
}