{
  "type": "Feature",
  "properties": {
    "gn:admin1_code":"6.0",
    "gn:admin2_code":"0.0",
    "gn:admin3_code":"3402.0",
    "gn:admin4_code":"3402000.0",
    "gn:asciiname":"Knock",
    "gn:country_code":"DE",
    "gn:dem":-2,
    "gn:feature_class":"P",
    "gn:feature_code":"PPL",
    "gn:name":"Knock",
    "gn:population":0,
    "gn:timezone":"Europe/Berlin",
    "iso:country":"DE",
    "name:ceb_x_preferred":[
        "Knock"
    ],
    "name:deu_x_preferred":[
        "Knock"
    ],
    "name:fra_x_preferred":[
        "Knock"
    ],
    "name:ido_x_preferred":[
        "Knock"
    ],
    "name:ita_x_preferred":[
        "Knock"
    ],
    "name:jpn_x_preferred":[
        "\u30ce\u30c3\u30af"
    ],
    "name:nld_x_preferred":[
        "Knock"
    ],
    "name:pol_x_preferred":[
        "Knock"
    ],
    "name:swe_x_preferred":[
        "Knock"
    ],
    "wof:name":"Knock",
    "wof:placetype":"neighbourhood"
},
  "geometry": {"coordinates":[7.04536,53.34153000000001],"type":"Point"}
}