{
  "type": "Feature",
  "properties": {
    "gn:admin1_code":"12.0",
    "gn:admin2_code":"00",
    "gn:admin3_code":"13074.0",
    "gn:admin4_code":"13074066.0",
    "gn:asciiname":"Wendorf",
    "gn:country_code":"DE",
    "gn:dem":66,
    "gn:feature_class":"P",
    "gn:feature_code":"PPL",
    "gn:name":"Wendorf",
    "gn:population":0,
    "gn:timezone":"Europe/Berlin",
    "iso:country":"DE",
    "name:ceb_x_preferred":[
        "Wendorf"
    ],
    "name:deu_x_preferred":[
        "Wendorf"
    ],
    "name:nld_x_preferred":[
        "Wendorf"
    ],
    "name:pol_x_preferred":[
        "Wendorf"
    ],
    "name:swe_x_preferred":[
        "Wendorf"
    ],
    "wof:name":"Wendorf",
    "wof:placetype":"neighbourhood"
},
  "geometry": {"coordinates":[10.84419,53.78361999999999],"type":"Point"}
}