{
  "type": "Feature",
  "properties": {
    "iso:country":"DE",
    "wof:name":"Vohwinkel-Mitte",
    "wof:placetype":"neighbourhood"
},
  "geometry": {"coordinates":[7.07283777613236,51.23198687075845],"type":"Point"}
}