{
  "type": "Feature",
  "properties": {
    "gn:admin1_code":"2",
    "gn:admin2_code":"93.0",
    "gn:admin3_code":"9373.0",
    "gn:admin4_code":"9373155.0",
    "gn:asciiname":"Pavelsbach",
    "gn:country_code":"DE",
    "gn:dem":432,
    "gn:feature_class":"P",
    "gn:feature_code":"PPL",
    "gn:name":"Pavelsbach",
    "gn:population":0,
    "gn:timezone":"Europe/Berlin",
    "iso:country":"DE",
    "wof:name":"Pavelsbach",
    "wof:placetype":"neighbourhood"
},
  "geometry": {"coordinates":[11.34381,49.26439],"type":"Point"}
}