{
  "type": "Feature",
  "properties": {
    "gn:admin1_code":"2.0",
    "gn:admin2_code":"97.0",
    "gn:admin3_code":"9777.0",
    "gn:admin4_code":"9777173.0",
    "gn:asciiname":"Birnbaum",
    "gn:country_code":"DE",
    "gn:dem":835,
    "gn:feature_class":"P",
    "gn:feature_code":"PPL",
    "gn:name":"Birnbaum",
    "gn:population":0,
    "gn:timezone":"Europe/Berlin",
    "iso:country":"DE",
    "name:ces_x_preferred":[
        "Birnbaum"
    ],
    "name:deu_x_preferred":[
        "Birnbaum"
    ],
    "name:fin_x_preferred":[
        "Birnbaum"
    ],
    "name:fra_x_preferred":[
        "Birnbaum"
    ],
    "name:hun_x_preferred":[
        "Birnbaum"
    ],
    "name:ita_x_preferred":[
        "Birnbaum"
    ],
    "name:nld_x_preferred":[
        "Birnbaum"
    ],
    "name:pol_x_preferred":[
        "Birnbaum"
    ],
    "name:por_x_preferred":[
        "Birnbaum"
    ],
    "name:rus_x_preferred":[
        "\u0411\u0438\u0440\u043d\u0431\u0430\u0443\u043c"
    ],
    "name:swe_x_preferred":[
        "Birnbaum"
    ],
    "wof:name":"Birnbaum",
    "wof:placetype":"locality"
},
  "geometry": {"coordinates":[10.8383,47.65386],"type":"Point"}
}