{
  "type": "Feature",
  "properties": {
    "gn:admin1_code":"7",
    "gn:admin2_code":"53.0",
    "gn:admin3_code":"5370.0",
    "gn:admin4_code":"5370008.0",
    "gn:asciiname":"Buscherheide",
    "gn:cc2":"DE",
    "gn:country_code":"DE",
    "gn:dem":64,
    "gn:feature_class":"P",
    "gn:feature_code":"PPL",
    "gn:name":"Buscherheide",
    "gn:population":0,
    "gn:timezone":"Europe/Berlin",
    "iso:country":"DE",
    "name:und_x_variant":[
        "Buschesheide"
    ],
    "wof:name":"Buscherheide",
    "wof:placetype":"neighbourhood"
},
  "geometry": {"coordinates":[5.98748,51.02181],"type":"Point"}
}