{
  "type": "Feature",
  "properties": {
    "gn:admin1_code":"7",
    "gn:admin2_code":"59.0",
    "gn:admin3_code":"5954.0",
    "gn:admin4_code":"5954028.0",
    "gn:asciiname":"Scheideweg",
    "gn:country_code":"DE",
    "gn:dem":190,
    "gn:feature_class":"P",
    "gn:feature_code":"PPL",
    "gn:name":"Scheideweg",
    "gn:population":0,
    "gn:timezone":"Europe/Berlin",
    "iso:country":"DE",
    "wof:name":"Scheideweg",
    "wof:placetype":"neighbourhood"
},
  "geometry": {"coordinates":[7.28333,51.36667],"type":"Point"}
}