{
  "type": "Feature",
  "properties": {
    "gn:admin1_code":"7",
    "gn:admin2_code":"51.0",
    "gn:admin3_code":"5162.0",
    "gn:admin4_code":"5162022.0",
    "gn:asciiname":"Langst-Kierst",
    "gn:country_code":"DE",
    "gn:dem":37,
    "gn:feature_class":"P",
    "gn:feature_code":"PPL",
    "gn:name":"Langst-Kierst",
    "gn:population":0,
    "gn:timezone":"Europe/Berlin",
    "iso:country":"DE",
    "wof:name":"Langst-Kierst",
    "wof:placetype":"neighbourhood"
},
  "geometry": {"coordinates":[6.71096,51.29868],"type":"Point"}
}