{
  "type": "Feature",
  "properties": {
    "gn:admin1_code":"2",
    "gn:admin2_code":"92.0",
    "gn:admin3_code":"9271.0",
    "gn:admin4_code":"9271140.0",
    "gn:asciiname":"Unterried",
    "gn:country_code":"DE",
    "gn:dem":326,
    "gn:feature_class":"P",
    "gn:feature_code":"PPL",
    "gn:name":"Unterried",
    "gn:population":0,
    "gn:timezone":"Europe/Berlin",
    "iso:country":"DE",
    "wof:name":"Unterried",
    "wof:placetype":"neighbourhood"
},
  "geometry": {"coordinates":[12.88728,48.86585],"type":"Point"}
}