{
  "type": "Feature",
  "properties": {
    "gn:admin1_code":"1.0",
    "gn:admin2_code":"084",
    "gn:admin3_code":"8417.0",
    "gn:admin4_code":"8417008.0",
    "gn:asciiname":"Zimmern",
    "gn:country_code":"DE",
    "gn:dem":547,
    "gn:feature_class":"P",
    "gn:feature_code":"PPL",
    "gn:name":"Zimmern",
    "gn:population":471,
    "gn:timezone":"Europe/Berlin",
    "iso:country":"DE",
    "name:ceb_x_preferred":[
        "Zimmern"
    ],
    "name:deu_x_preferred":[
        "Zimmern"
    ],
    "name:fra_x_preferred":[
        "Zimmern"
    ],
    "name:ita_x_preferred":[
        "Zimmern"
    ],
    "name:nld_x_preferred":[
        "Zimmern"
    ],
    "name:pol_x_preferred":[
        "Zimmern"
    ],
    "name:rus_x_preferred":[
        "\u0426\u0438\u043c\u043c\u0435\u0440\u043d"
    ],
    "name:srp_x_preferred":[
        "\u0426\u0438\u043c\u0435\u0440\u043d"
    ],
    "name:swe_x_preferred":[
        "Zimmern"
    ],
    "wof:name":"Zimmern",
    "wof:placetype":"neighbourhood",
    "wof:population":471
},
  "geometry": {"coordinates":[8.94596,48.32133],"type":"Point"}
}