{
  "type": "Feature",
  "properties": {
    "gn:admin1_code":"12",
    "gn:admin2_code":"0.0",
    "gn:admin3_code":"13074.0",
    "gn:admin4_code":"13074001.0",
    "gn:asciiname":"Rothefloete",
    "gn:country_code":"DE",
    "gn:dem":50,
    "gn:feature_class":"P",
    "gn:feature_code":"PPL",
    "gn:name":"Rothefl\u00f6te",
    "gn:population":0,
    "gn:timezone":"Europe/Berlin",
    "iso:country":"DE",
    "wof:name":"Rothefloete",
    "wof:placetype":"neighbourhood"
},
  "geometry": {"coordinates":[11.36482,53.74633000000001],"type":"Point"}
}