{
  "type": "Feature",
  "properties": {
    "gn:admin1_code":"13",
    "gn:admin2_code":"0.0",
    "gn:admin3_code":"14625.0",
    "gn:admin4_code":"14625340.0",
    "gn:asciiname":"Neudoerfel",
    "gn:country_code":"DE",
    "gn:dem":148,
    "gn:feature_class":"P",
    "gn:feature_code":"PPL",
    "gn:name":"Neud\u00f6rfel",
    "gn:population":0,
    "gn:timezone":"Europe/Berlin",
    "iso:country":"DE",
    "wof:name":"Neudoerfel",
    "wof:placetype":"neighbourhood"
},
  "geometry": {"coordinates":[14.59131,51.2539],"type":"Point"}
}