{
  "type": "Feature",
  "properties": {
    "gn:admin1_code":"12",
    "gn:admin2_code":"0.0",
    "gn:admin3_code":"13076.0",
    "gn:admin4_code":"13076114.0",
    "gn:asciiname":"Reppentin",
    "gn:country_code":"DE",
    "gn:dem":75,
    "gn:feature_class":"P",
    "gn:feature_code":"PPL",
    "gn:name":"Reppentin",
    "gn:population":0,
    "gn:timezone":"Europe/Berlin",
    "iso:country":"DE",
    "wof:name":"Reppentin",
    "wof:placetype":"neighbourhood"
},
  "geometry": {"coordinates":[12.22864,53.43306],"type":"Point"}
}