{
  "type": "Feature",
  "properties": {
    "gn:admin1_code":"8",
    "gn:admin2_code":"0.0",
    "gn:admin3_code":"7138.0",
    "gn:admin4_code":"7138045.0",
    "gn:asciiname":"Engers",
    "gn:country_code":"DE",
    "gn:dem":73,
    "gn:feature_class":"P",
    "gn:feature_code":"PPL",
    "gn:name":"Engers",
    "gn:population":0,
    "gn:timezone":"Europe/Berlin",
    "iso:country":"DE",
    "name:deu_x_preferred":[
        "Engers"
    ],
    "wof:name":"Engers",
    "wof:placetype":"neighbourhood"
},
  "geometry": {"coordinates":[7.54415,50.43106],"type":"Point"}
}