{
  "type": "Feature",
  "properties": {
    "gn:admin1_code":"5",
    "gn:admin2_code":"66.0",
    "gn:admin3_code":"6635.0",
    "gn:admin4_code":"6635016.0",
    "gn:asciiname":"Goddelsheim",
    "gn:country_code":"DE",
    "gn:dem":389,
    "gn:feature_class":"P",
    "gn:feature_code":"PPL",
    "gn:name":"Goddelsheim",
    "gn:population":0,
    "gn:timezone":"Europe/Berlin",
    "iso:country":"DE",
    "wof:name":"Goddelsheim",
    "wof:placetype":"neighbourhood"
},
  "geometry": {"coordinates":[8.80657,51.20038],"type":"Point"}
}