{
  "type": "Feature",
  "properties": {
    "iso:country":"DE",
    "qs_pg:aaroncc":"DE",
    "qs_pg:name":"Edertal Siedlung Rehbach",
    "qs_pg:name_adm0":"Deutschland",
    "qs_pg:name_adm1":"Hessen",
    "qs_pg:photos":146,
    "qs_pg:photos_1k":30,
    "qs_pg:photos_9k":1,
    "qs_pg:photos_9r":3,
    "qs_pg:photos_all":146,
    "qs_pg:photos_sr":3,
    "qs_pg:pop_sr":0,
    "qs_pg:qs_pg_placetype":"locality",
    "qs_pg:qs_pg_placetype_gp":"Town",
    "qs_pg:woe_adm0":23424829,
    "woe:adm0_id":23424829,
    "woe:name_adm0":"Deutschland",
    "woe:name_adm1":"Hessen",
    "woe:placetype":"Town",
    "wof:name":"Edertal Siedlung Rehbach",
    "wof:placetype":"neighbourhood"
},
  "geometry": {"coordinates":[9.020477,51.190011],"type":"Point"}
}