{
  "type": "Feature",
  "properties": {
    "gn:admin1_code":"1",
    "gn:admin2_code":"84.0",
    "gn:admin3_code":"8435.0",
    "gn:admin4_code":"8435013.0",
    "gn:asciiname":"Schlatt",
    "gn:country_code":"DE",
    "gn:dem":401,
    "gn:feature_class":"P",
    "gn:feature_code":"PPL",
    "gn:name":"Schlatt",
    "gn:population":0,
    "gn:timezone":"Europe/Berlin",
    "iso:country":"DE",
    "name:als_x_preferred":[
        "Schlatt"
    ],
    "name:ceb_x_preferred":[
        "Schlatt"
    ],
    "name:deu_x_preferred":[
        "Schlatt"
    ],
    "name:epo_x_preferred":[
        "Schlatt"
    ],
    "name:eus_x_preferred":[
        "Schlatt"
    ],
    "name:fra_x_preferred":[
        "Schlatt"
    ],
    "name:ita_x_preferred":[
        "Schlatt"
    ],
    "name:lmo_x_preferred":[
        "Schlatt"
    ],
    "name:nld_x_preferred":[
        "Schlatt"
    ],
    "name:pol_x_preferred":[
        "Schlatt"
    ],
    "name:rus_x_preferred":[
        "\u0428\u043b\u0430\u0442"
    ],
    "name:spa_x_preferred":[
        "Schlatt"
    ],
    "name:swe_x_preferred":[
        "Schlatt"
    ],
    "name:vol_x_preferred":[
        "Schlatt"
    ],
    "wof:name":"Schlatt",
    "wof:placetype":"neighbourhood"
},
  "geometry": {"coordinates":[9.53986,47.62369],"type":"Point"}
}