{
  "type": "Feature",
  "properties": {
    "gn:admin1_code":"1",
    "gn:admin2_code":"84.0",
    "gn:admin3_code":"8435.0",
    "gn:admin4_code":"8435013.0",
    "gn:asciiname":"Schlatt",
    "gn:country_code":"DE",
    "gn:dem":401,
    "gn:feature_class":"P",
    "gn:feature_code":"PPL",
    "gn:name":"Schlatt",
    "gn:population":0,
    "gn:timezone":"Europe/Berlin",
    "iso:country":"DE",
    "wof:name":"Schlatt",
    "wof:placetype":"neighbourhood"
},
  "geometry": {"coordinates":[9.53986,47.62369],"type":"Point"}
}