{
  "type": "Feature",
  "properties": {
    "gn:admin1_code":"15",
    "gn:admin2_code":"0.0",
    "gn:admin3_code":"16074.0",
    "gn:admin4_code":"16074053.0",
    "gn:asciiname":"Erdmannsdorf",
    "gn:country_code":"DE",
    "gn:dem":225,
    "gn:feature_class":"P",
    "gn:feature_code":"PPL",
    "gn:name":"Erdmannsdorf",
    "gn:population":0,
    "gn:timezone":"Europe/Berlin",
    "iso:country":"DE",
    "name:deu_x_preferred":[
        "Erdmannsdorf"
    ],
    "name:pol_x_preferred":[
        "Erdmannsdorf"
    ],
    "name:rus_x_preferred":[
        "\u042d\u0440\u0434\u043c\u0430\u043d\u0441\u0434\u043e\u0440\u0444"
    ],
    "wof:name":"Erdmannsdorf",
    "wof:placetype":"neighbourhood"
},
  "geometry": {"coordinates":[11.77844,50.83068],"type":"Point"}
}