{
  "type": "Feature",
  "properties": {
    "gn:admin1_code":"10",
    "gn:admin2_code":"0.0",
    "gn:admin3_code":"1051.0",
    "gn:admin4_code":"1051087.0",
    "gn:asciiname":"Kringelkrug",
    "gn:country_code":"DE",
    "gn:dem":8,
    "gn:feature_class":"P",
    "gn:feature_code":"PPL",
    "gn:name":"Kringelkrug",
    "gn:population":0,
    "gn:timezone":"Europe/Berlin",
    "iso:country":"DE",
    "wof:name":"Kringelkrug",
    "wof:placetype":"neighbourhood"
},
  "geometry": {"coordinates":[9.12693,54.21658000000001],"type":"Point"}
}