{
  "type": "Feature",
  "properties": {
    "gn:admin1_code":"10",
    "gn:admin2_code":"0.0",
    "gn:admin3_code":"1057.0",
    "gn:admin4_code":"1057011.0",
    "gn:asciiname":"Kleinbuchwald",
    "gn:country_code":"DE",
    "gn:dem":36,
    "gn:feature_class":"P",
    "gn:feature_code":"PPL",
    "gn:name":"Kleinbuchwald",
    "gn:population":0,
    "gn:timezone":"Europe/Berlin",
    "iso:country":"DE",
    "wof:name":"Kleinbuchwald",
    "wof:placetype":"neighbourhood"
},
  "geometry": {"coordinates":[10.1275,54.15508000000001],"type":"Point"}
}