{
  "type": "Feature",
  "properties": {
    "gn:admin1_code":"7",
    "gn:admin2_code":"59.0",
    "gn:admin3_code":"5970.0",
    "gn:admin4_code":"5970040.0",
    "gn:asciiname":"Niederschelden",
    "gn:country_code":"DE",
    "gn:dem":226,
    "gn:feature_class":"P",
    "gn:feature_code":"PPL",
    "gn:name":"Niederschelden",
    "gn:population":0,
    "gn:timezone":"Europe/Berlin",
    "iso:country":"DE",
    "wof:name":"Niederschelden",
    "wof:placetype":"neighbourhood"
},
  "geometry": {"coordinates":[7.97441,50.84525],"type":"Point"}
}