{
  "type": "Feature",
  "properties": {
    "gn:admin1_code":"12",
    "gn:admin2_code":"0.0",
    "gn:admin3_code":"13076.0",
    "gn:admin4_code":"13076009.0",
    "gn:asciiname":"Gross Bengerstorf",
    "gn:cc2":"DE",
    "gn:country_code":"DE",
    "gn:dem":32,
    "gn:feature_class":"P",
    "gn:feature_code":"PPL",
    "gn:name":"Gro\u00df Bengerstorf",
    "gn:population":0,
    "gn:timezone":"Europe/Berlin",
    "iso:country":"DE",
    "name:und_x_variant":[
        "Gro\u00df Bengersdorf"
    ],
    "wof:name":"Gross Bengerstorf",
    "wof:placetype":"neighbourhood"
},
  "geometry": {"coordinates":[10.84076,53.42621],"type":"Point"}
}