{
  "type": "Feature",
  "properties": {
    "gn:admin1_code":"7",
    "gn:admin2_code":"51.0",
    "gn:admin3_code":"5154.0",
    "gn:admin4_code":"5154044.0",
    "gn:asciiname":"Helderloh",
    "gn:country_code":"DE",
    "gn:dem":22,
    "gn:feature_class":"P",
    "gn:feature_code":"PPL",
    "gn:name":"Helderloh",
    "gn:population":0,
    "gn:timezone":"Europe/Berlin",
    "iso:country":"DE",
    "wof:name":"Helderloh",
    "wof:placetype":"neighbourhood"
},
  "geometry": {"coordinates":[6.47997,51.77714],"type":"Point"}
}