{
  "type": "Feature",
  "properties": {
    "gn:admin1_code":"7",
    "gn:admin2_code":"51.0",
    "gn:admin3_code":"5124.0",
    "gn:admin4_code":"5124000.0",
    "gn:asciiname":"Nieder-Sondern",
    "gn:country_code":"DE",
    "gn:dem":280,
    "gn:feature_class":"P",
    "gn:feature_code":"PPL",
    "gn:name":"Nieder-Sondern",
    "gn:population":0,
    "gn:timezone":"Europe/Berlin",
    "iso:country":"DE",
    "wof:name":"Nieder-Sondern",
    "wof:placetype":"neighbourhood"
},
  "geometry": {"coordinates":[7.28626,51.23483],"type":"Point"}
}