{
  "type": "Feature",
  "properties": {
    "gn:admin1_code":"2",
    "gn:admin2_code":"91.0",
    "gn:admin3_code":"9177.0",
    "gn:admin4_code":"9177135.0",
    "gn:asciiname":"Poigenberg",
    "gn:country_code":"DE",
    "gn:dem":507,
    "gn:feature_class":"P",
    "gn:feature_code":"PPL",
    "gn:name":"Poigenberg",
    "gn:population":0,
    "gn:timezone":"Europe/Berlin",
    "iso:country":"DE",
    "wof:name":"Poigenberg",
    "wof:placetype":"neighbourhood"
},
  "geometry": {"coordinates":[11.93673,48.21272],"type":"Point"}
}