{
  "type": "Feature",
  "properties": {
    "gn:admin1_code":"2",
    "gn:admin2_code":"92.0",
    "gn:admin3_code":"9274.0",
    "gn:admin4_code":"9274120.0",
    "gn:asciiname":"Geratsfurt",
    "gn:country_code":"DE",
    "gn:dem":461,
    "gn:feature_class":"P",
    "gn:feature_code":"PPL",
    "gn:name":"Geratsfurt",
    "gn:population":0,
    "gn:timezone":"Europe/Berlin",
    "iso:country":"DE",
    "wof:name":"Geratsfurt",
    "wof:placetype":"neighbourhood"
},
  "geometry": {"coordinates":[12.47456,48.44317],"type":"Point"}
}