{
  "type": "Feature",
  "properties": {
    "iso:country":"DE",
    "name:deu_x_preferred":[
        "Plau\u00dfig"
    ],
    "wof:name":"Plaussig",
    "wof:placetype":"neighbourhood"
},
  "geometry": {"coordinates":[12.45560884977581,51.3927107062227],"type":"Point"}
}