{
  "type": "Feature",
  "properties": {
    "gn:admin1_code":"7",
    "gn:admin2_code":"57.0",
    "gn:admin3_code":"5766.0",
    "gn:admin4_code":"5766024.0",
    "gn:asciiname":"Spork",
    "gn:country_code":"DE",
    "gn:dem":133,
    "gn:feature_class":"P",
    "gn:feature_code":"PPL",
    "gn:name":"Spork",
    "gn:population":0,
    "gn:timezone":"Europe/Berlin",
    "iso:country":"DE",
    "name:ara_x_preferred":[
        "\u0645\u0644\u0639\u0643\u0629"
    ],
    "name:ast_x_preferred":[
        "Tenedor-cuyar"
    ],
    "name:aze_x_preferred":[
        "Spork"
    ],
    "name:dan_x_preferred":[
        "Spork"
    ],
    "name:deu_x_preferred":[
        "G\u00f6ffel"
    ],
    "name:fas_x_preferred":[
        "\u0642\u0627\u0634\u200c\u0686\u0646\u06af"
    ],
    "name:fra_x_preferred":[
        "Cuill\u00e8re-fourchette"
    ],
    "name:ind_x_preferred":[
        "Sendok garpu"
    ],
    "name:isl_x_preferred":[
        "Skaffall"
    ],
    "name:jpn_x_preferred":[
        "\u5148\u5272\u308c\u30b9\u30d7\u30fc\u30f3"
    ],
    "name:kor_x_preferred":[
        "\uc2a4\ud3ec\ud06c"
    ],
    "name:pol_x_preferred":[
        "\u0141y\u017ckowidelec"
    ],
    "name:ron_x_preferred":[
        "Furculingur\u0103"
    ],
    "name:rus_x_preferred":[
        "\u041b\u043e\u0436\u043a\u0430-\u0432\u0438\u043b\u043a\u0430"
    ],
    "name:scn_x_preferred":[
        "Burcicchiaru"
    ],
    "name:spa_x_preferred":[
        "Tenedor-cuchara"
    ],
    "name:srp_x_preferred":[
        "\u0421\u043f\u043e\u0440\u043a"
    ],
    "name:swe_x_preferred":[
        "Skaffel"
    ],
    "wof:name":"Spork",
    "wof:placetype":"neighbourhood"
},
  "geometry": {"coordinates":[9.00673,52.02683],"type":"Point"}
}