{
  "type": "Feature",
  "properties": {
    "gn:admin1_code":"2",
    "gn:admin2_code":"96.0",
    "gn:admin3_code":"9672.0",
    "gn:admin4_code":"9672138.0",
    "gn:asciiname":"Buchrasen",
    "gn:country_code":"DE",
    "gn:dem":433,
    "gn:feature_class":"P",
    "gn:feature_code":"PPL",
    "gn:name":"Buchrasen",
    "gn:population":0,
    "gn:timezone":"Europe/Berlin",
    "iso:country":"DE",
    "wof:name":"Buchrasen",
    "wof:placetype":"neighbourhood"
},
  "geometry": {"coordinates":[9.78729,50.28725],"type":"Point"}
}