{
  "type": "Feature",
  "properties": {
    "gn:admin1_code":"2",
    "gn:admin2_code":"96.0",
    "gn:admin3_code":"9678.0",
    "gn:admin4_code":"9678153.0",
    "gn:asciiname":"Schallfeld",
    "gn:country_code":"DE",
    "gn:dem":256,
    "gn:feature_class":"P",
    "gn:feature_code":"PPL",
    "gn:name":"Schallfeld",
    "gn:population":0,
    "gn:timezone":"Europe/Berlin",
    "iso:country":"DE",
    "wof:name":"Schallfeld",
    "wof:placetype":"neighbourhood"
},
  "geometry": {"coordinates":[10.35725,49.87364],"type":"Point"}
}