{
  "type": "Feature",
  "properties": {
    "iso:country":"DE",
    "wof:name":"Weiler",
    "wof:placetype":"neighbourhood"
},
  "geometry": {"coordinates":[6.88112034619456,51.02238297516255],"type":"Point"}
}