{
  "type": "Feature",
  "properties": {
    "iso:country":"DE",
    "name:als_x_preferred":[
        "Weiler"
    ],
    "name:bar_x_preferred":[
        "Weiler"
    ],
    "name:ceb_x_preferred":[
        "Weiler"
    ],
    "name:deu_x_preferred":[
        "Weiler"
    ],
    "name:epo_x_preferred":[
        "Weiler"
    ],
    "name:fra_x_preferred":[
        "Weiler"
    ],
    "name:hun_x_preferred":[
        "Weiler"
    ],
    "name:ita_x_preferred":[
        "Weiler"
    ],
    "name:ltz_x_preferred":[
        "Weiler"
    ],
    "name:nld_x_preferred":[
        "Weiler"
    ],
    "name:pol_x_preferred":[
        "Weiler"
    ],
    "name:por_x_preferred":[
        "Weiler"
    ],
    "name:rus_x_preferred":[
        "\u0412\u0430\u0439\u043b\u0435\u0440"
    ],
    "name:srp_x_preferred":[
        "\u0412\u0430\u0458\u043b\u0435\u0440"
    ],
    "name:swe_x_preferred":[
        "Weiler"
    ],
    "name:ukr_x_preferred":[
        "\u0412\u0430\u0439\u043b\u0435\u0440"
    ],
    "name:vol_x_preferred":[
        "Weiler"
    ],
    "wof:name":"Weiler",
    "wof:placetype":"neighbourhood"
},
  "geometry": {"coordinates":[6.88112034619456,51.02238297516255],"type":"Point"}
}