{
  "type": "Feature",
  "properties": {
    "gn:admin1_code":"2.0",
    "gn:admin2_code":"92.0",
    "gn:admin3_code":"9275.0",
    "gn:admin4_code":"9275114.0",
    "gn:asciiname":"Adenberg",
    "gn:country_code":"DE",
    "gn:dem":365,
    "gn:feature_class":"P",
    "gn:feature_code":"PPL",
    "gn:name":"Adenberg",
    "gn:population":0,
    "gn:timezone":"Europe/Berlin",
    "iso:country":"DE",
    "wof:name":"Adenberg",
    "wof:placetype":"neighbourhood"
},
  "geometry": {"coordinates":[13.12083,48.58555],"type":"Point"}
}