{
  "type": "Feature",
  "properties": {
    "iso:country":"DE",
    "name:deu_x_preferred":[
        "Sachsenhausen-S\u00fcd"
    ],
    "wof:name":"Sachsenhausen-Sued",
    "wof:placetype":"neighbourhood"
},
  "geometry": {"coordinates":[8.68922095174411,50.09110851130528],"type":"Point"}
}