{
  "type": "Feature",
  "properties": {
    "gn:admin1_code":"2",
    "gn:admin2_code":"92.0",
    "gn:admin3_code":"9277.0",
    "gn:admin4_code":"9277126.0",
    "gn:asciiname":"Schwaigerod",
    "gn:country_code":"DE",
    "gn:dem":401,
    "gn:feature_class":"P",
    "gn:feature_code":"PPL",
    "gn:name":"Schwaiger\u00f6d",
    "gn:population":0,
    "gn:timezone":"Europe/Berlin",
    "iso:country":"DE",
    "wof:name":"Schwaigerod",
    "wof:placetype":"neighbourhood"
},
  "geometry": {"coordinates":[12.955,48.52368],"type":"Point"}
}