{
  "type": "Feature",
  "properties": {
    "gn:admin1_code":"5",
    "gn:admin2_code":"66.0",
    "gn:admin3_code":"6633.0",
    "gn:admin4_code":"6633026.0",
    "gn:asciiname":"Obervellmar",
    "gn:country_code":"DE",
    "gn:dem":206,
    "gn:feature_class":"P",
    "gn:feature_code":"PPL",
    "gn:name":"Obervellmar",
    "gn:population":0,
    "gn:timezone":"Europe/Berlin",
    "iso:country":"DE",
    "wof:name":"Obervellmar",
    "wof:placetype":"neighbourhood"
},
  "geometry": {"coordinates":[9.46343,51.36867],"type":"Point"}
}