{
  "type": "Feature",
  "properties": {
    "gn:admin1_code":"13",
    "gn:admin2_code":"0.0",
    "gn:admin3_code":"14522.0",
    "gn:admin4_code":"14522590.0",
    "gn:asciiname":"Neuberthelsdorf",
    "gn:country_code":"DE",
    "gn:dem":369,
    "gn:feature_class":"P",
    "gn:feature_code":"PPL",
    "gn:name":"Neuberthelsdorf",
    "gn:population":0,
    "gn:timezone":"Europe/Berlin",
    "iso:country":"DE",
    "wof:name":"Neuberthelsdorf",
    "wof:placetype":"neighbourhood"
},
  "geometry": {"coordinates":[13.3962,50.87852],"type":"Point"}
}