{
  "type": "Feature",
  "properties": {
    "gn:admin1_code":"2",
    "gn:admin2_code":"96.0",
    "gn:admin3_code":"9673.0",
    "gn:admin4_code":"9673116.0",
    "gn:asciiname":"Unterwaldbehrungen",
    "gn:country_code":"DE",
    "gn:dem":337,
    "gn:feature_class":"P",
    "gn:feature_code":"PPL",
    "gn:name":"Unterwaldbehrungen",
    "gn:population":0,
    "gn:timezone":"Europe/Berlin",
    "iso:country":"DE",
    "wof:name":"Unterwaldbehrungen",
    "wof:placetype":"neighbourhood"
},
  "geometry": {"coordinates":[10.18232,50.42582],"type":"Point"}
}