{
  "type": "Feature",
  "properties": {
    "gn:admin1_code":"13",
    "gn:admin2_code":"0.0",
    "gn:admin3_code":"14522.0",
    "gn:admin4_code":"14522300.0",
    "gn:asciiname":"Erlebach",
    "gn:country_code":"DE",
    "gn:dem":260,
    "gn:feature_class":"P",
    "gn:feature_code":"PPL",
    "gn:name":"Erlebach",
    "gn:population":0,
    "gn:timezone":"Europe/Berlin",
    "iso:country":"DE",
    "name:deu_x_preferred":[
        "Erlebach"
    ],
    "wof:name":"Erlebach",
    "wof:placetype":"neighbourhood"
},
  "geometry": {"coordinates":[13.0275,51.02256],"type":"Point"}
}