{
  "type": "Feature",
  "properties": {
    "gn:admin1_code":"10",
    "gn:admin2_code":"0.0",
    "gn:admin3_code":"1058.0",
    "gn:admin4_code":"1058078.0",
    "gn:asciiname":"Julianenebene",
    "gn:country_code":"DE",
    "gn:dem":1,
    "gn:feature_class":"P",
    "gn:feature_code":"PPLL",
    "gn:name":"Julianenebene",
    "gn:population":0,
    "gn:timezone":"Europe/Berlin",
    "iso:country":"DE",
    "wof:name":"Julianenebene",
    "wof:placetype":"neighbourhood"
},
  "geometry": {"coordinates":[9.50136,54.31633000000001],"type":"Point"}
}