{
  "type": "Feature",
  "properties": {
    "gn:admin1_code":"2",
    "gn:admin2_code":"93.0",
    "gn:admin3_code":"9372.0",
    "gn:admin4_code":"9372164.0",
    "gn:asciiname":"Hagendorf",
    "gn:country_code":"DE",
    "gn:dem":446,
    "gn:feature_class":"P",
    "gn:feature_code":"PPL",
    "gn:name":"Hagendorf",
    "gn:population":0,
    "gn:timezone":"Europe/Berlin",
    "iso:country":"DE",
    "name:deu_x_preferred":[
        "Hagendorf"
    ],
    "wof:name":"Hagendorf",
    "wof:placetype":"neighbourhood"
},
  "geometry": {"coordinates":[12.66059,49.11789],"type":"Point"}
}