{
  "type": "Feature",
  "properties": {
    "gn:admin1_code":"2",
    "gn:admin2_code":"93.0",
    "gn:admin3_code":"9372.0",
    "gn:admin4_code":"9372171.0",
    "gn:asciiname":"Moosdorf",
    "gn:country_code":"DE",
    "gn:dem":514,
    "gn:feature_class":"P",
    "gn:feature_code":"PPL",
    "gn:name":"Moosdorf",
    "gn:population":0,
    "gn:timezone":"Europe/Berlin",
    "iso:country":"DE",
    "name:ceb_x_preferred":[
        "Moosdorf"
    ],
    "name:deu_x_preferred":[
        "Moosdorf"
    ],
    "name:fas_x_preferred":[
        "\u0645\u0648\u0633\u062f\u0648\u0631\u0641"
    ],
    "name:fra_x_preferred":[
        "Moosdorf"
    ],
    "name:fur_x_preferred":[
        "Moosdorf"
    ],
    "name:hun_x_preferred":[
        "Moosdorf"
    ],
    "name:ita_x_preferred":[
        "Moosdorf"
    ],
    "name:kaz_x_preferred":[
        "\u041c\u043e\u0441\u0434\u043e\u0440\u0444"
    ],
    "name:nld_x_preferred":[
        "Moosdorf"
    ],
    "name:pol_x_preferred":[
        "Moosdorf"
    ],
    "name:por_x_preferred":[
        "Moosdorf"
    ],
    "name:rus_x_preferred":[
        "\u041c\u043e\u0441\u0434\u043e\u0440\u0444"
    ],
    "name:slk_x_preferred":[
        "Moosdorf"
    ],
    "name:spa_x_preferred":[
        "Moosdorf"
    ],
    "name:swe_x_preferred":[
        "Moosdorf"
    ],
    "name:uzb_x_preferred":[
        "Moosdorf"
    ],
    "name:vie_x_preferred":[
        "Moosdorf"
    ],
    "name:vol_x_preferred":[
        "Moosdorf"
    ],
    "name:war_x_preferred":[
        "Moosdorf"
    ],
    "name:zho_x_preferred":[
        "\u83ab\u65af\u591a\u592b"
    ],
    "wof:name":"Moosdorf",
    "wof:placetype":"neighbourhood"
},
  "geometry": {"coordinates":[12.7007,49.35719],"type":"Point"}
}