{
  "type": "Feature",
  "properties": {
    "gn:gn_country":"DE",
    "gn:gn_fcode":"PPLA4",
    "gn:gn_pop":36,
    "gn:population":36,
    "iso:country":"DE",
    "name:baq_x_preferred":[
        "Kollmoor"
    ],
    "name:chi_x_preferred":[
        "\u79d1\u5c14\u83ab\u5c14"
    ],
    "name:dan_x_preferred":[
        "Kollmoor"
    ],
    "name:dut_x_preferred":[
        "Kollmoor"
    ],
    "name:eng_x_preferred":[
        "Kollmoor"
    ],
    "name:epo_x_preferred":[
        "Kollmoor"
    ],
    "name:fre_x_preferred":[
        "Kollmoor"
    ],
    "name:ger_x_preferred":[
        "Kollmoor"
    ],
    "name:hun_x_preferred":[
        "Kollmoor"
    ],
    "name:ita_x_preferred":[
        "Kollmoor"
    ],
    "name:kaz_x_preferred":[
        "\u041a\u043e\u043b\u044c\u043c\u043e\u0440"
    ],
    "name:kir_x_preferred":[
        "\u041a\u043e\u043b\u044c\u043c\u043e\u0440"
    ],
    "name:mac_x_preferred":[
        "\u041a\u043e\u043b\u043c\u043e\u0440"
    ],
    "name:may_x_preferred":[
        "Kollmoor"
    ],
    "name:per_x_preferred":[
        "\u06a9\u0648\u0644\u0645\u0648\u0648\u0631"
    ],
    "name:pol_x_preferred":[
        "Kollmoor"
    ],
    "name:por_x_preferred":[
        "Kollmoor"
    ],
    "name:rum_x_preferred":[
        "Kollmoor"
    ],
    "name:rus_x_preferred":[
        "\u041a\u043e\u043b\u044c\u043c\u043e\u0440"
    ],
    "name:spa_x_preferred":[
        "Kollmoor"
    ],
    "name:srp_x_preferred":[
        "\u041a\u043e\u043b\u043c\u043e\u0440"
    ],
    "name:tur_x_preferred":[
        "Kollmoor"
    ],
    "name:ukr_x_preferred":[
        "\u041a\u043e\u043b\u044c\u043c\u043e\u0440"
    ],
    "name:uzb_x_preferred":[
        "Kollmoor"
    ],
    "name:vie_x_preferred":[
        "Kollmoor"
    ],
    "name:vol_x_preferred":[
        "Kollmoor"
    ],
    "name:war_x_preferred":[
        "Kollmoor"
    ],
    "qs_pg:aaroncc":"DE",
    "qs_pg:gn_country":"DE",
    "qs_pg:gn_fcode":"PPLA4",
    "qs_pg:gn_pop":36,
    "qs_pg:name":"Kollmoor",
    "qs_pg:photos_9r":0,
    "qs_pg:photos_sr":0,
    "qs_pg:pop_sr":1,
    "qs_pg:qs_pg_placetype":"locality",
    "wof:name":"Kollmoor",
    "wof:placetype":"locality",
    "wof:population":36
},
  "geometry": {"coordinates":[9.59411,53.92023],"type":"Point"}
}