{
  "type": "Feature",
  "properties": {
    "gn:admin1_code":"2",
    "gn:admin2_code":"91.0",
    "gn:admin3_code":"9173.0",
    "gn:admin4_code":"9173134.0",
    "gn:asciiname":"Osterhofen",
    "gn:country_code":"DE",
    "gn:dem":646,
    "gn:feature_class":"P",
    "gn:feature_code":"PPL",
    "gn:name":"Osterhofen",
    "gn:population":0,
    "gn:timezone":"Europe/Berlin",
    "iso:country":"DE",
    "name:ara_x_preferred":[
        "\u0623\u0648\u0633\u062a\u0631\u0647\u0648\u0641\u0646"
    ],
    "name:azb_x_preferred":[
        "\u0627\u0633\u062a\u0631\u0647\u0648\u0641\u0646"
    ],
    "name:ceb_x_preferred":[
        "Osterhofen"
    ],
    "name:ces_x_preferred":[
        "Osterhofen"
    ],
    "name:dan_x_preferred":[
        "Osterhofen"
    ],
    "name:deu_x_preferred":[
        "Osterhofen"
    ],
    "name:epo_x_preferred":[
        "Osterhofen"
    ],
    "name:fas_x_preferred":[
        "\u0627\u0633\u062a\u0631\u0647\u0648\u0641\u0646"
    ],
    "name:fra_x_preferred":[
        "Osterhofen"
    ],
    "name:hun_x_preferred":[
        "Osterhofen"
    ],
    "name:hye_x_preferred":[
        "\u0555\u057d\u0569\u0565\u0580\u0570\u0578\u0586\u0565\u0576"
    ],
    "name:ind_x_preferred":[
        "Osterhofen"
    ],
    "name:ita_x_preferred":[
        "Osterhofen"
    ],
    "name:kaz_x_preferred":[
        "\u041e\u0441\u0442\u0435\u0440\u0445\u043e\u0444\u0435\u043d"
    ],
    "name:kir_x_preferred":[
        "\u041e\u0441\u0442\u0435\u0440\u0445\u043e\u0444\u0435\u043d"
    ],
    "name:lmo_x_preferred":[
        "Osterhofen"
    ],
    "name:msa_x_preferred":[
        "Osterhofen"
    ],
    "name:nld_x_preferred":[
        "Osterhofen"
    ],
    "name:pol_x_preferred":[
        "Osterhofen"
    ],
    "name:por_x_preferred":[
        "Osterhofen"
    ],
    "name:ron_x_preferred":[
        "Osterhofen"
    ],
    "name:rus_x_preferred":[
        "\u041e\u0441\u0442\u0435\u0440\u0445\u043e\u0444\u0435\u043d"
    ],
    "name:spa_x_preferred":[
        "Osterhofen"
    ],
    "name:srp_x_preferred":[
        "\u041e\u0441\u0442\u0435\u0440\u0445\u043e\u0444\u0435\u043d"
    ],
    "name:swe_x_preferred":[
        "Osterhofen"
    ],
    "name:tur_x_preferred":[
        "Osterhofen"
    ],
    "name:ukr_x_preferred":[
        "\u041e\u0441\u0442\u0435\u0440\u0433\u043e\u0444\u0435\u043d"
    ],
    "name:uzb_x_preferred":[
        "Osterhofen"
    ],
    "name:vie_x_preferred":[
        "Osterhofen"
    ],
    "name:vol_x_preferred":[
        "Osterhofen"
    ],
    "name:war_x_preferred":[
        "Osterhofen"
    ],
    "name:zho_x_preferred":[
        "\u5965\u65af\u7279\u970d\u82ac"
    ],
    "wof:name":"Osterhofen",
    "wof:placetype":"neighbourhood"
},
  "geometry": {"coordinates":[11.49445,47.82088],"type":"Point"}
}