{
  "type": "Feature",
  "properties": {
    "gn:admin1_code":"2",
    "gn:admin2_code":"91.0",
    "gn:admin3_code":"9173.0",
    "gn:admin4_code":"9173134.0",
    "gn:asciiname":"Osterhofen",
    "gn:country_code":"DE",
    "gn:dem":646,
    "gn:feature_class":"P",
    "gn:feature_code":"PPL",
    "gn:name":"Osterhofen",
    "gn:population":0,
    "gn:timezone":"Europe/Berlin",
    "iso:country":"DE",
    "wof:name":"Osterhofen",
    "wof:placetype":"neighbourhood"
},
  "geometry": {"coordinates":[11.49445,47.82088],"type":"Point"}
}