{
  "type": "Feature",
  "properties": {
    "gn:admin1_code":"7",
    "gn:admin2_code":"57.0",
    "gn:admin3_code":"5770.0",
    "gn:admin4_code":"5770044.0",
    "gn:asciiname":"Hammoor",
    "gn:country_code":"DE",
    "gn:dem":43,
    "gn:feature_class":"P",
    "gn:feature_code":"PPLL",
    "gn:name":"Hammoor",
    "gn:population":0,
    "gn:timezone":"Europe/Berlin",
    "iso:country":"DE",
    "name:ceb_x_preferred":[
        "Hammoor"
    ],
    "name:dan_x_preferred":[
        "Hammoor"
    ],
    "name:deu_x_preferred":[
        "Hammoor"
    ],
    "name:epo_x_preferred":[
        "Hammoor"
    ],
    "name:eus_x_preferred":[
        "Hammoor"
    ],
    "name:fas_x_preferred":[
        "\u0647\u0627\u0645\u0648\u0648\u0631"
    ],
    "name:fra_x_preferred":[
        "Hammoor"
    ],
    "name:hun_x_preferred":[
        "Hammoor"
    ],
    "name:ita_x_preferred":[
        "Hammoor"
    ],
    "name:mkd_x_preferred":[
        "\u0425\u0430\u043c\u043e\u0440"
    ],
    "name:msa_x_preferred":[
        "Hammoor"
    ],
    "name:nld_x_preferred":[
        "Hammoor"
    ],
    "name:pol_x_preferred":[
        "Hammoor"
    ],
    "name:por_x_preferred":[
        "Hammoor"
    ],
    "name:ron_x_preferred":[
        "Hammoor"
    ],
    "name:rus_x_preferred":[
        "\u0425\u0430\u043c\u043c\u043e\u0440"
    ],
    "name:spa_x_preferred":[
        "Hammoor"
    ],
    "name:srp_x_preferred":[
        "\u0425\u0430\u043c\u043e\u0440"
    ],
    "name:tur_x_preferred":[
        "Hammoor"
    ],
    "name:ukr_x_preferred":[
        "\u0413\u0430\u043c\u043c\u043e\u0440"
    ],
    "name:uzb_x_preferred":[
        "Hammoor"
    ],
    "name:vie_x_preferred":[
        "Hammoor"
    ],
    "name:vol_x_preferred":[
        "Hammoor"
    ],
    "name:war_x_preferred":[
        "Hammoor"
    ],
    "name:zho_x_preferred":[
        "\u54c8\u83ab\u5c14"
    ],
    "wof:name":"Hammoor",
    "wof:placetype":"neighbourhood"
},
  "geometry": {"coordinates":[8.54301,52.46515],"type":"Point"}
}