{
  "type": "Feature",
  "properties": {
    "gn:admin1_code":"2",
    "gn:admin2_code":"97.0",
    "gn:admin3_code":"9775.0",
    "gn:admin4_code":"9775118.0",
    "gn:asciiname":"Friesenhofen",
    "gn:country_code":"DE",
    "gn:dem":536,
    "gn:feature_class":"P",
    "gn:feature_code":"PPL",
    "gn:name":"Friesenhofen",
    "gn:population":0,
    "gn:timezone":"Europe/Berlin",
    "iso:country":"DE",
    "wof:name":"Friesenhofen",
    "wof:placetype":"neighbourhood"
},
  "geometry": {"coordinates":[10.22827,48.23519],"type":"Point"}
}