{
  "type": "Feature",
  "properties": {
    "gn:admin1_code":"2",
    "gn:admin2_code":"94.0",
    "gn:admin3_code":"9478.0",
    "gn:admin4_code":"9478116.0",
    "gn:asciiname":"Hainweiher",
    "gn:country_code":"DE",
    "gn:dem":410,
    "gn:feature_class":"P",
    "gn:feature_code":"PPL",
    "gn:name":"Hainweiher",
    "gn:population":0,
    "gn:timezone":"Europe/Berlin",
    "iso:country":"DE",
    "wof:name":"Hainweiher",
    "wof:placetype":"neighbourhood"
},
  "geometry": {"coordinates":[11.26648,50.15628],"type":"Point"}
}