{
  "type": "Feature",
  "properties": {
    "gn:admin1_code":"2",
    "gn:admin2_code":"91.0",
    "gn:admin3_code":"9173.0",
    "gn:admin4_code":"9173115.0",
    "gn:asciiname":"Vormholz",
    "gn:country_code":"DE",
    "gn:dem":680,
    "gn:feature_class":"P",
    "gn:feature_code":"PPL",
    "gn:name":"Vormholz",
    "gn:population":0,
    "gn:timezone":"Europe/Berlin",
    "iso:country":"DE",
    "wof:name":"Vormholz",
    "wof:placetype":"neighbourhood"
},
  "geometry": {"coordinates":[11.43333,47.71667],"type":"Point"}
}