{
  "type": "Feature",
  "properties": {
    "gn:admin1_code":"2",
    "gn:admin2_code":"97.0",
    "gn:admin3_code":"9778.0",
    "gn:admin4_code":"9778151.0",
    "gn:asciiname":"Unterholzgunz",
    "gn:country_code":"DE",
    "gn:dem":609,
    "gn:feature_class":"P",
    "gn:feature_code":"PPL",
    "gn:name":"Unterholzg\u00fcnz",
    "gn:population":0,
    "gn:timezone":"Europe/Berlin",
    "iso:country":"DE",
    "wof:name":"Unterholzgunz",
    "wof:placetype":"neighbourhood"
},
  "geometry": {"coordinates":[10.25903,48.02788],"type":"Point"}
}