{
  "type": "Feature",
  "properties": {
    "gn:country":"DE",
    "gn:fcode":"PPL",
    "gn:population":0,
    "iso:country":"DE",
    "name:deu_x_preferred":[
        "Nordenau"
    ],
    "name:epo_x_preferred":[
        "Nordenau"
    ],
    "name:fas_x_preferred":[
        "\u0646\u0631\u062f\u0646\u0627\u0648"
    ],
    "qs_pg:aaroncc":"DE",
    "qs_pg:gn_country":"DE",
    "qs_pg:gn_fcode":"PPL",
    "qs_pg:gn_pop":0,
    "qs_pg:name":"Nordenau",
    "qs_pg:name_adm0":"Deutschland",
    "qs_pg:name_adm1":"Nordrhein-Westfalen",
    "qs_pg:photos_9k":1,
    "qs_pg:photos_9r":1,
    "qs_pg:photos_all":2,
    "qs_pg:photos_sr":0,
    "qs_pg:pop_sr":0,
    "qs_pg:qs_pg_placetype":"locality",
    "qs_pg:qs_pg_placetype_gp":"Town",
    "qs_pg:woe_adm0":23424829,
    "woe:adm0_id":23424829,
    "woe:name_adm0":"Deutschland",
    "woe:name_adm1":"Nordrhein-Westfalen",
    "woe:placetype":"Town",
    "wof:name":"Nordenau",
    "wof:placetype":"neighbourhood"
},
  "geometry": {"coordinates":[8.42445,51.17574],"type":"Point"}
}