{
  "type": "Feature",
  "properties": {
    "gn:admin1_code":"2.0",
    "gn:admin2_code":"095",
    "gn:admin3_code":"9572.0",
    "gn:admin4_code":"9572130.0",
    "gn:asciiname":"Zeckern",
    "gn:country_code":"DE",
    "gn:dem":310,
    "gn:feature_class":"P",
    "gn:feature_code":"PPL",
    "gn:name":"Zeckern",
    "gn:population":0,
    "gn:timezone":"Europe/Berlin",
    "iso:country":"DE",
    "wof:name":"Zeckern",
    "wof:placetype":"neighbourhood"
},
  "geometry": {"coordinates":[10.93637,49.69395],"type":"Point"}
}