{
  "type": "Feature",
  "properties": {
    "gn:admin1_code":"11",
    "gn:admin2_code":"0.0",
    "gn:admin3_code":"12067.0",
    "gn:admin4_code":"12067481.0",
    "gn:asciiname":"Goersdorf",
    "gn:country_code":"DE",
    "gn:dem":35,
    "gn:feature_class":"P",
    "gn:feature_code":"PPL",
    "gn:name":"G\u00f6rsdorf",
    "gn:population":0,
    "gn:timezone":"Europe/Berlin",
    "iso:country":"DE",
    "name:und_x_variant":[
        "G\u00f6rsdorf bei Stork\u00f6w",
        "G\u00f6rsdorf"
    ],
    "wof:name":"Goersdorf",
    "wof:placetype":"neighbourhood"
},
  "geometry": {"coordinates":[13.837,52.23976],"type":"Point"}
}