{
  "type": "Feature",
  "properties": {
    "gn:admin1_code":"5",
    "gn:admin2_code":"64.0",
    "gn:admin3_code":"6431.0",
    "gn:admin4_code":"6431014.0",
    "gn:asciiname":"Staffel",
    "gn:country_code":"DE",
    "gn:dem":417,
    "gn:feature_class":"P",
    "gn:feature_code":"PPL",
    "gn:name":"Staffel",
    "gn:population":0,
    "gn:timezone":"Europe/Berlin",
    "iso:country":"DE",
    "name:deu_x_preferred":[
        "Staffel"
    ],
    "name:nld_x_preferred":[
        "Staffel"
    ],
    "wof:name":"Staffel",
    "wof:placetype":"neighbourhood"
},
  "geometry": {"coordinates":[8.68297,49.74029],"type":"Point"}
}