{
  "type": "Feature",
  "properties": {
    "gn:admin1_code":"6",
    "gn:admin2_code":"0.0",
    "gn:admin3_code":"3351.0",
    "gn:admin4_code":"3351023.0",
    "gn:asciiname":"Kolonie Steinfoerde",
    "gn:country_code":"DE",
    "gn:dem":41,
    "gn:feature_class":"P",
    "gn:feature_code":"PPL",
    "gn:name":"Kolonie Steinf\u00f6rde",
    "gn:population":0,
    "gn:timezone":"Europe/Berlin",
    "iso:country":"DE",
    "wof:name":"Kolonie Steinfoerde",
    "wof:placetype":"neighbourhood"
},
  "geometry": {"coordinates":[9.86667,52.65],"type":"Point"}
}