{
  "type": "Feature",
  "properties": {
    "gn:admin1_code":"2",
    "gn:admin2_code":"91.0",
    "gn:admin3_code":"9183.0",
    "gn:admin4_code":"9183129.0",
    "gn:asciiname":"Sagmuhle",
    "gn:country_code":"DE",
    "gn:dem":435,
    "gn:feature_class":"P",
    "gn:feature_code":"PPL",
    "gn:name":"S\u00e4gm\u00fchle",
    "gn:population":0,
    "gn:timezone":"Europe/Berlin",
    "iso:country":"DE",
    "wof:name":"Sagmuhle",
    "wof:placetype":"neighbourhood"
},
  "geometry": {"coordinates":[12.53689,48.37788],"type":"Point"}
}