{
  "type": "Feature",
  "properties": {
    "gn:admin1_code":"2",
    "gn:admin2_code":"92.0",
    "gn:admin3_code":"9275.0",
    "gn:admin4_code":"9275122.0",
    "gn:asciiname":"Pfalsau",
    "gn:country_code":"DE",
    "gn:dem":370,
    "gn:feature_class":"P",
    "gn:feature_code":"PPL",
    "gn:name":"Pfalsau",
    "gn:population":0,
    "gn:timezone":"Europe/Berlin",
    "iso:country":"DE",
    "wof:name":"Pfalsau",
    "wof:placetype":"neighbourhood"
},
  "geometry": {"coordinates":[13.28359,48.52197],"type":"Point"}
}