{
  "type": "Feature",
  "properties": {
    "gn:admin1_code":"2",
    "gn:admin2_code":"92.0",
    "gn:admin3_code":"9272.0",
    "gn:admin4_code":"9272146.0",
    "gn:asciiname":"Schonanger",
    "gn:country_code":"DE",
    "gn:dem":666,
    "gn:feature_class":"P",
    "gn:feature_code":"PPL",
    "gn:name":"Sch\u00f6nanger",
    "gn:population":0,
    "gn:timezone":"Europe/Berlin",
    "iso:country":"DE",
    "wof:name":"Schonanger",
    "wof:placetype":"neighbourhood"
},
  "geometry": {"coordinates":[13.45975,48.86991],"type":"Point"}
}