{
  "type": "Feature",
  "properties": {
    "gn:admin1_code":"11",
    "gn:admin2_code":"0.0",
    "gn:admin3_code":"12065.0",
    "gn:admin4_code":"12065117.0",
    "gn:asciiname":"Kehlkendorf",
    "gn:cc2":"DE",
    "gn:country_code":"DE",
    "gn:dem":76,
    "gn:feature_class":"P",
    "gn:feature_code":"PPL",
    "gn:name":"Kehlkendorf",
    "gn:population":0,
    "gn:timezone":"Europe/Berlin",
    "iso:country":"DE",
    "name:und_x_variant":[
        "Kelkendorf"
    ],
    "wof:name":"Kehlkendorf",
    "wof:placetype":"neighbourhood"
},
  "geometry": {"coordinates":[13.09785,53.08686],"type":"Point"}
}