{
  "type": "Feature",
  "properties": {
    "gn:admin1_code":"13",
    "gn:admin2_code":"0.0",
    "gn:admin3_code":"14521.0",
    "gn:admin4_code":"14521320.0",
    "gn:asciiname":"Neuoberhaus",
    "gn:country_code":"DE",
    "gn:dem":788,
    "gn:feature_class":"P",
    "gn:feature_code":"PPL",
    "gn:name":"Neuoberhaus",
    "gn:population":0,
    "gn:timezone":"Europe/Berlin",
    "iso:country":"DE",
    "wof:name":"Neuoberhaus",
    "wof:placetype":"neighbourhood"
},
  "geometry": {"coordinates":[12.7366,50.44288],"type":"Point"}
}