{
  "type": "Feature",
  "properties": {
    "gn:admin1_code":"2",
    "gn:asciiname":"Haidhauser",
    "gn:country_code":"DE",
    "gn:dem":825,
    "gn:feature_class":"P",
    "gn:feature_code":"PPL",
    "gn:name":"Haidha\u00fcser",
    "gn:population":0,
    "gn:timezone":"Europe/Berlin",
    "iso:country":"DE",
    "wof:name":"Haidhauser",
    "wof:placetype":"neighbourhood"
},
  "geometry": {"coordinates":[13.78333,48.83333],"type":"Point"}
}