{
  "type": "Feature",
  "properties": {
    "gn:admin1_code":"7",
    "gn:admin2_code":"59.0",
    "gn:admin3_code":"5958.0",
    "gn:admin4_code":"5958044.0",
    "gn:asciiname":"Estinghausen",
    "gn:country_code":"DE",
    "gn:dem":293,
    "gn:feature_class":"P",
    "gn:feature_code":"PPL",
    "gn:name":"Estinghausen",
    "gn:population":0,
    "gn:timezone":"Europe/Berlin",
    "iso:country":"DE",
    "wof:name":"Estinghausen",
    "wof:placetype":"neighbourhood"
},
  "geometry": {"coordinates":[7.94364,51.3743],"type":"Point"}
}