{
  "type": "Feature",
  "properties": {
    "gn:admin1_code":"2",
    "gn:admin2_code":"96.0",
    "gn:admin3_code":"9674.0",
    "gn:admin4_code":"9674130.0",
    "gn:asciiname":"Vorbach",
    "gn:country_code":"DE",
    "gn:dem":315,
    "gn:feature_class":"P",
    "gn:feature_code":"PPL",
    "gn:name":"Vorbach",
    "gn:population":0,
    "gn:timezone":"Europe/Berlin",
    "iso:country":"DE",
    "name:ceb_x_preferred":[
        "Vorbach"
    ],
    "name:dan_x_preferred":[
        "Vorbach"
    ],
    "name:deu_x_preferred":[
        "Vorbach"
    ],
    "name:epo_x_preferred":[
        "Vorbach"
    ],
    "name:eus_x_preferred":[
        "Vorbach"
    ],
    "name:fas_x_preferred":[
        "\u0641\u0648\u0631\u0628\u0627\u062e"
    ],
    "name:fra_x_preferred":[
        "Vorbach"
    ],
    "name:hun_x_preferred":[
        "Vorbach"
    ],
    "name:hye_x_preferred":[
        "\u0556\u0578\u0580\u0562\u0561\u056d"
    ],
    "name:ind_x_preferred":[
        "Vorbach"
    ],
    "name:ita_x_preferred":[
        "Vorbach"
    ],
    "name:lmo_x_preferred":[
        "Vorbach"
    ],
    "name:msa_x_preferred":[
        "Vorbach"
    ],
    "name:nld_x_preferred":[
        "Vorbach"
    ],
    "name:pol_x_preferred":[
        "Vorbach"
    ],
    "name:por_x_preferred":[
        "Vorbach"
    ],
    "name:ron_x_preferred":[
        "Vorbach"
    ],
    "name:rus_x_preferred":[
        "\u0424\u043e\u0440\u0431\u0430\u0445"
    ],
    "name:spa_x_preferred":[
        "Vorbach"
    ],
    "name:srp_x_preferred":[
        "\u0424\u043e\u0440\u0431\u0430\u0445"
    ],
    "name:ukr_x_preferred":[
        "\u0424\u043e\u0440\u0431\u0430\u0445"
    ],
    "name:uzb_x_preferred":[
        "Vorbach"
    ],
    "name:vie_x_preferred":[
        "Vorbach"
    ],
    "name:vol_x_preferred":[
        "Vorbach"
    ],
    "name:war_x_preferred":[
        "Vorbach"
    ],
    "wof:name":"Vorbach",
    "wof:placetype":"neighbourhood"
},
  "geometry": {"coordinates":[10.73096,50.1012],"type":"Point"}
}