{
  "type": "Feature",
  "properties": {
    "gn:admin1_code":"2",
    "gn:admin2_code":"92.0",
    "gn:admin3_code":"9274.0",
    "gn:admin4_code":"9274176.0",
    "gn:asciiname":"Oberotterbach",
    "gn:country_code":"DE",
    "gn:dem":464,
    "gn:feature_class":"P",
    "gn:feature_code":"PPL",
    "gn:name":"Oberotterbach",
    "gn:population":0,
    "gn:timezone":"Europe/Berlin",
    "iso:country":"DE",
    "name:ceb_x_preferred":[
        "Oberotterbach"
    ],
    "name:deu_x_preferred":[
        "Oberotterbach"
    ],
    "name:epo_x_preferred":[
        "Oberotterbach"
    ],
    "name:eus_x_preferred":[
        "Oberotterbach"
    ],
    "name:fas_x_preferred":[
        "\u0627\u0648\u0628\u0631\u0648\u062a\u0631\u0628\u0627\u062e"
    ],
    "name:fra_x_preferred":[
        "Oberotterbach"
    ],
    "name:hun_x_preferred":[
        "Oberotterbach"
    ],
    "name:ita_x_preferred":[
        "Oberotterbach"
    ],
    "name:msa_x_preferred":[
        "Oberotterbach"
    ],
    "name:nld_x_preferred":[
        "Oberotterbach"
    ],
    "name:pol_x_preferred":[
        "Oberotterbach"
    ],
    "name:por_x_preferred":[
        "Oberotterbach"
    ],
    "name:ron_x_preferred":[
        "Oberotterbach"
    ],
    "name:rus_x_preferred":[
        "\u041e\u0431\u0435\u0440\u043e\u0442\u0442\u0435\u0440\u0431\u0430\u0445"
    ],
    "name:spa_x_preferred":[
        "Oberotterbach"
    ],
    "name:srp_x_preferred":[
        "\u041e\u0431\u0435\u0440\u043e\u0442\u0435\u0440\u0431\u0430\u0445"
    ],
    "name:ukr_x_preferred":[
        "\u041e\u0431\u0435\u0440\u043e\u0442\u0442\u0435\u0440\u0431\u0430\u0445"
    ],
    "name:uzb_x_preferred":[
        "Oberotterbach"
    ],
    "name:vie_x_preferred":[
        "Oberotterbach"
    ],
    "name:vol_x_preferred":[
        "Oberotterbach"
    ],
    "name:war_x_preferred":[
        "Oberotterbach"
    ],
    "name:zho_x_preferred":[
        "\u4e0a\u5965\u7279\u5df4\u8d6b"
    ],
    "wof:name":"Oberotterbach",
    "wof:placetype":"neighbourhood"
},
  "geometry": {"coordinates":[12.04475,48.69712],"type":"Point"}
}