{
  "type": "Feature",
  "properties": {
    "gn:admin1_code":"8.0",
    "gn:admin2_code":"0.0",
    "gn:admin3_code":"7132.0",
    "gn:admin4_code":"7132109.0",
    "gn:asciiname":"Breibacherhof",
    "gn:country_code":"DE",
    "gn:dem":266,
    "gn:feature_class":"P",
    "gn:feature_code":"PPL",
    "gn:name":"Breibacherhof",
    "gn:population":0,
    "gn:timezone":"Europe/Berlin",
    "iso:country":"DE",
    "wof:name":"Breibacherhof",
    "wof:placetype":"neighbourhood"
},
  "geometry": {"coordinates":[7.5975,50.65079],"type":"Point"}
}