{
  "type": "Feature",
  "properties": {
    "gn:admin1_code":"7.0",
    "gn:admin2_code":"051",
    "gn:admin3_code":"5170.0",
    "gn:admin4_code":"5170048.0",
    "gn:asciiname":"Winkeling",
    "gn:country_code":"DE",
    "gn:dem":20,
    "gn:feature_class":"P",
    "gn:feature_code":"PPL",
    "gn:name":"Winkeling",
    "gn:population":0,
    "gn:timezone":"Europe/Berlin",
    "iso:country":"DE",
    "wof:name":"Winkeling",
    "wof:placetype":"neighbourhood"
},
  "geometry": {"coordinates":[6.57375,51.62484],"type":"Point"}
}