{
  "type": "Feature",
  "properties": {
    "gn:admin1_code":"7",
    "gn:admin2_code":"59.0",
    "gn:admin3_code":"5962.0",
    "gn:admin4_code":"5962004.0",
    "gn:asciiname":"Grossendrescheid",
    "gn:country_code":"DE",
    "gn:dem":449,
    "gn:feature_class":"P",
    "gn:feature_code":"PPL",
    "gn:name":"Gro\u00dfendrescheid",
    "gn:population":0,
    "gn:timezone":"Europe/Berlin",
    "iso:country":"DE",
    "name:und_x_variant":[
        "Gro\u00dfendrehscheid",
        "Gro\u00dfendrescheid"
    ],
    "wof:name":"Grossendrescheid",
    "wof:placetype":"neighbourhood"
},
  "geometry": {"coordinates":[7.64539,51.27154],"type":"Point"}
}