{
  "type": "Feature",
  "properties": {
    "gn:admin1_code":"5",
    "gn:admin2_code":"66.0",
    "gn:admin3_code":"6635.0",
    "gn:admin4_code":"6635014.0",
    "gn:asciiname":"Lindenhof",
    "gn:country_code":"DE",
    "gn:dem":409,
    "gn:feature_class":"P",
    "gn:feature_code":"PPL",
    "gn:name":"Lindenhof",
    "gn:population":0,
    "gn:timezone":"Europe/Berlin",
    "iso:country":"DE",
    "name:deu_x_preferred":[
        "Lindenhof"
    ],
    "name:lat_x_preferred":[
        "Lindenhof"
    ],
    "name:pol_x_preferred":[
        "Lindenhof"
    ],
    "name:rus_x_preferred":[
        "\u041b\u0438\u043d\u0434\u0435\u043d\u0445\u043e\u0444"
    ],
    "name:tur_x_preferred":[
        "Lindenhof"
    ],
    "wof:name":"Lindenhof",
    "wof:placetype":"neighbourhood"
},
  "geometry": {"coordinates":[8.51699,50.97355],"type":"Point"}
}