{
  "type": "Feature",
  "properties": {
    "gn:country":"DE",
    "gn:fcode":"PPL",
    "gn:population":523,
    "iso:country":"DE",
    "name:bak_x_preferred":[
        "\u0411\u043e\u0439\u0441\u0442\u0435\u0440"
    ],
    "name:cat_x_preferred":[
        "Beuster"
    ],
    "name:ceb_x_preferred":[
        "Beuster"
    ],
    "name:che_x_preferred":[
        "\u0411\u043e\u0439\u0441\u0442\u0435\u0440"
    ],
    "name:deu_x_preferred":[
        "Beuster"
    ],
    "name:eng_x_preferred":[
        "Beuster"
    ],
    "name:epo_x_preferred":[
        "Beuster"
    ],
    "name:fas_x_preferred":[
        "\u0628\u0648\u06cc\u0633\u062a\u0631"
    ],
    "name:fra_x_preferred":[
        "Beuster"
    ],
    "name:gle_x_preferred":[
        "Beuster"
    ],
    "name:ita_x_preferred":[
        "Beuster"
    ],
    "name:kaz_x_preferred":[
        "\u0411\u043e\u0439\u0441\u0442\u0435\u0440"
    ],
    "name:kir_x_preferred":[
        "\u0411\u043e\u0439\u0441\u0442\u0435\u0440"
    ],
    "name:mkd_x_preferred":[
        "\u0411\u043e\u0458\u0441\u0442\u0435\u0440"
    ],
    "name:nld_x_preferred":[
        "Beuster"
    ],
    "name:nob_x_preferred":[
        "Beuster"
    ],
    "name:ron_x_preferred":[
        "Beuster"
    ],
    "name:rus_x_preferred":[
        "\u0411\u043e\u0439\u0441\u0442\u0435\u0440"
    ],
    "name:tat_x_preferred":[
        "\u0411\u043e\u0439\u0441\u0442\u0435\u0440"
    ],
    "name:uzb_x_preferred":[
        "Beuster"
    ],
    "name:vie_x_preferred":[
        "Beuster"
    ],
    "name:vol_x_preferred":[
        "Beuster"
    ],
    "qs_pg:aaroncc":"DE",
    "qs_pg:gn_country":"DE",
    "qs_pg:gn_fcode":"PPL",
    "qs_pg:gn_pop":523,
    "qs_pg:name":"Beuster",
    "qs_pg:name_adm0":"Deutschland",
    "qs_pg:name_adm1":"Sachsen-Anhalt",
    "qs_pg:photos_9k":1,
    "qs_pg:photos_9r":1,
    "qs_pg:photos_all":2,
    "qs_pg:photos_sr":0,
    "qs_pg:pop_sr":2,
    "qs_pg:qs_pg_placetype":"locality",
    "qs_pg:qs_pg_placetype_gp":"Town",
    "qs_pg:woe_adm0":23424829,
    "woe:adm0_id":23424829,
    "woe:name_adm0":"Deutschland",
    "woe:name_adm1":"Sachsen-Anhalt",
    "woe:placetype":"Town",
    "wof:name":"Beuster",
    "wof:placetype":"neighbourhood",
    "wof:population":523
},
  "geometry": {"coordinates":[11.78593,52.93964],"type":"Point"}
}