{
  "type": "Feature",
  "properties": {
    "gn:gn_country":"DE",
    "gn:gn_fcode":"PPLA4",
    "gn:gn_pop":642,
    "gn:population":642,
    "iso:country":"DE",
    "name:baq_x_preferred":[
        "Dockweiler"
    ],
    "name:chi_x_preferred":[
        "\u591a\u514b\u9b4f\u83b1\u5c14"
    ],
    "name:dut_x_preferred":[
        "Dockweiler"
    ],
    "name:eng_x_preferred":[
        "Dockweiler"
    ],
    "name:epo_x_preferred":[
        "Dockweiler"
    ],
    "name:fre_x_preferred":[
        "Dockweiler"
    ],
    "name:ger_x_preferred":[
        "Dockweiler"
    ],
    "name:hun_x_preferred":[
        "Dockweiler"
    ],
    "name:ita_x_preferred":[
        "Dockweiler"
    ],
    "name:jpn_x_preferred":[
        "\u30c9\u30c3\u30af\u30f4\u30a1\u30a4\u30e9\u30fc"
    ],
    "name:kaz_x_preferred":[
        "\u0414\u043e\u043a\u0432\u0430\u0439\u043b\u0435\u0440"
    ],
    "name:kir_x_preferred":[
        "\u0414\u043e\u043a\u0432\u0430\u0439\u043b\u0435\u0440"
    ],
    "name:may_x_preferred":[
        "Dockweiler"
    ],
    "name:per_x_preferred":[
        "\u062f\u0648\u06a9\u0648\u0627\u06cc\u0644\u0631"
    ],
    "name:pol_x_preferred":[
        "Dockweiler"
    ],
    "name:por_x_preferred":[
        "Dockweiler"
    ],
    "name:rum_x_preferred":[
        "Dockweiler"
    ],
    "name:rus_x_preferred":[
        "\u0414\u043e\u043a\u0432\u0430\u0439\u043b\u0435\u0440"
    ],
    "name:spa_x_preferred":[
        "Dockweiler"
    ],
    "name:srp_x_preferred":[
        "\u0414\u043e\u043a\u0432\u0430\u0458\u043b\u0435\u0440"
    ],
    "name:ukr_x_preferred":[
        "\u0414\u043e\u043a\u0432\u0430\u0439\u043b\u0435\u0440"
    ],
    "name:uzb_x_preferred":[
        "Dockweiler"
    ],
    "name:vie_x_preferred":[
        "Dockweiler"
    ],
    "name:vol_x_preferred":[
        "Dockweiler"
    ],
    "name:war_x_preferred":[
        "Dockweiler"
    ],
    "name:zho_x_preferred":[
        "\u591a\u514b\u97e6\u52d2"
    ],
    "qs_pg:aaroncc":"DE",
    "qs_pg:gn_country":"DE",
    "qs_pg:gn_fcode":"PPLA4",
    "qs_pg:gn_pop":642,
    "qs_pg:name":"Dockweiler",
    "qs_pg:photos_9r":0,
    "qs_pg:photos_sr":0,
    "qs_pg:pop_sr":2,
    "qs_pg:qs_pg_placetype":"locality",
    "wof:name":"Dockweiler",
    "wof:placetype":"locality",
    "wof:population":642
},
  "geometry": {"coordinates":[6.78333,50.25],"type":"Point"}
}