{
  "type": "Feature",
  "properties": {
    "gn:admin1_code":"13",
    "gn:admin2_code":"0.0",
    "gn:admin3_code":"14627.0",
    "gn:admin4_code":"14627270.0",
    "gn:asciiname":"Unterreussen",
    "gn:country_code":"DE",
    "gn:dem":98,
    "gn:feature_class":"P",
    "gn:feature_code":"PPL",
    "gn:name":"Unterreu\u00dfen",
    "gn:population":0,
    "gn:timezone":"Europe/Berlin",
    "iso:country":"DE",
    "wof:name":"Unterreussen",
    "wof:placetype":"neighbourhood"
},
  "geometry": {"coordinates":[13.2523,51.33303],"type":"Point"}
}