{
  "type": "Feature",
  "properties": {
    "gn:admin1_code":"6",
    "gn:admin2_code":"0.0",
    "gn:admin3_code":"3256.0",
    "gn:admin4_code":"3256013.0",
    "gn:asciiname":"Dahlhausen",
    "gn:country_code":"DE",
    "gn:dem":14,
    "gn:feature_class":"P",
    "gn:feature_code":"PPL",
    "gn:name":"Dahlhausen",
    "gn:population":0,
    "gn:timezone":"Europe/Berlin",
    "iso:country":"DE",
    "name:deu_x_preferred":[
        "Dahlhausen"
    ],
    "name:tur_x_preferred":[
        "Bochum-Dahlhausen"
    ],
    "wof:name":"Dahlhausen",
    "wof:placetype":"neighbourhood"
},
  "geometry": {"coordinates":[9.17089,52.88744000000001],"type":"Point"}
}