{
  "type": "Feature",
  "properties": {
    "gn:admin1_code":"2",
    "gn:admin2_code":"95.0",
    "gn:admin3_code":"9574.0",
    "gn:admin4_code":"9574152.0",
    "gn:asciiname":"Schnackenhof",
    "gn:country_code":"DE",
    "gn:dem":335,
    "gn:feature_class":"P",
    "gn:feature_code":"PPL",
    "gn:name":"Schnackenhof",
    "gn:population":0,
    "gn:timezone":"Europe/Berlin",
    "iso:country":"DE",
    "wof:name":"Schnackenhof",
    "wof:placetype":"neighbourhood"
},
  "geometry": {"coordinates":[11.23333,49.48333],"type":"Point"}
}