{
  "type": "Feature",
  "properties": {
    "gn:admin1_code":"6",
    "gn:admin2_code":"0.0",
    "gn:admin3_code":"3461.0",
    "gn:admin4_code":"3461007.0",
    "gn:asciiname":"Sarve",
    "gn:country_code":"DE",
    "gn:dem":-1,
    "gn:feature_class":"P",
    "gn:feature_code":"PPL",
    "gn:name":"Sarve",
    "gn:population":0,
    "gn:timezone":"Europe/Berlin",
    "iso:country":"DE",
    "name:deu_x_preferred":[
        "Sarve"
    ],
    "name:est_x_preferred":[
        "Sarve"
    ],
    "name:hye_x_preferred":[
        "\u054d\u0561\u057c\u057e\u0565"
    ],
    "name:pol_x_preferred":[
        "Sarve"
    ],
    "name:spa_x_preferred":[
        "Sarve"
    ],
    "name:vol_x_preferred":[
        "Sarve"
    ],
    "wof:name":"Sarve",
    "wof:placetype":"neighbourhood"
},
  "geometry": {"coordinates":[8.44139,53.50571],"type":"Point"}
}