{
  "type": "Feature",
  "properties": {
    "gn:admin1_code":"5.0",
    "gn:admin2_code":"66.0",
    "gn:admin3_code":"6636.0",
    "gn:admin4_code":"6636016.0",
    "gn:asciiname":"Albshausen",
    "gn:country_code":"DE",
    "gn:dem":214,
    "gn:feature_class":"P",
    "gn:feature_code":"PPL",
    "gn:name":"Albshausen",
    "gn:population":0,
    "gn:timezone":"Europe/Berlin",
    "iso:country":"DE",
    "wof:name":"Albshausen",
    "wof:placetype":"neighbourhood"
},
  "geometry": {"coordinates":[9.83783,51.37607],"type":"Point"}
}