{
  "type": "Feature",
  "properties": {
    "gn:admin1_code":"13",
    "gn:admin2_code":"0.0",
    "gn:admin3_code":"14626.0",
    "gn:admin4_code":"14626470.0",
    "gn:asciiname":"Scharfsoeders",
    "gn:country_code":"DE",
    "gn:dem":294,
    "gn:feature_class":"P",
    "gn:feature_code":"PPL",
    "gn:name":"Scharfs\u00f6ders",
    "gn:population":0,
    "gn:timezone":"Europe/Berlin",
    "iso:country":"DE",
    "wof:name":"Scharfsoeders",
    "wof:placetype":"neighbourhood"
},
  "geometry": {"coordinates":[14.71861,51.08374],"type":"Point"}
}