{
  "type": "Feature",
  "properties": {
    "gn:admin1_code":"1.0",
    "gn:admin2_code":"81.0",
    "gn:admin3_code":"8128.0",
    "gn:admin4_code":"8128039.0",
    "gn:asciiname":"Ebenheid",
    "gn:country_code":"DE",
    "gn:dem":383,
    "gn:feature_class":"P",
    "gn:feature_code":"PPL",
    "gn:name":"Ebenheid",
    "gn:population":0,
    "gn:timezone":"Europe/Berlin",
    "iso:country":"DE",
    "wof:name":"Ebenheid",
    "wof:placetype":"neighbourhood"
},
  "geometry": {"coordinates":[9.3616,49.71611],"type":"Point"}
}