{
  "type": "Feature",
  "properties": {
    "gn:admin1_code":"14",
    "gn:admin2_code":"0.0",
    "gn:admin3_code":"15082.0",
    "gn:admin4_code":"15082340.0",
    "gn:asciiname":"Deutsches Haus",
    "gn:country_code":"DE",
    "gn:dem":91,
    "gn:feature_class":"P",
    "gn:feature_code":"PPL",
    "gn:name":"Deutsches Haus",
    "gn:population":0,
    "gn:timezone":"Europe/Berlin",
    "iso:country":"DE",
    "wof:name":"Deutsches Haus",
    "wof:placetype":"neighbourhood"
},
  "geometry": {"coordinates":[12.25,51.58333],"type":"Point"}
}