{
  "type": "Feature",
  "properties": {
    "gn:admin1_code":"2",
    "gn:admin2_code":"91.0",
    "gn:admin3_code":"9189.0",
    "gn:admin4_code":"9189133.0",
    "gn:asciiname":"Kleinornach",
    "gn:country_code":"DE",
    "gn:dem":572,
    "gn:feature_class":"P",
    "gn:feature_code":"PPL",
    "gn:name":"Kleinornach",
    "gn:population":0,
    "gn:timezone":"Europe/Berlin",
    "iso:country":"DE",
    "wof:name":"Kleinornach",
    "wof:placetype":"neighbourhood"
},
  "geometry": {"coordinates":[12.438,48.00769],"type":"Point"}
}