{
  "type": "Feature",
  "properties": {
    "gn:admin1_code":"5",
    "gn:admin2_code":"64.0",
    "gn:admin3_code":"6432.0",
    "gn:admin4_code":"6432021.0",
    "gn:asciiname":"Mosbach",
    "gn:country_code":"DE",
    "gn:dem":162,
    "gn:feature_class":"P",
    "gn:feature_code":"PPL",
    "gn:name":"Mosbach",
    "gn:population":0,
    "gn:timezone":"Europe/Berlin",
    "iso:country":"DE",
    "name:als_x_preferred":[
        "Mosbach"
    ],
    "name:ara_x_preferred":[
        "\u0645\u0648\u0633\u0628\u0627\u062e"
    ],
    "name:azb_x_preferred":[
        "\u0645\u0633\u0628\u0627\u062e"
    ],
    "name:bul_x_preferred":[
        "\u041c\u043e\u0437\u0431\u0430\u0445"
    ],
    "name:ceb_x_preferred":[
        "Mosbach"
    ],
    "name:ces_x_preferred":[
        "Mosbach"
    ],
    "name:deu_x_preferred":[
        "Mosbach"
    ],
    "name:epo_x_preferred":[
        "Mosbach"
    ],
    "name:fas_x_preferred":[
        "\u0645\u0633\u0628\u0627\u062e"
    ],
    "name:fra_x_preferred":[
        "Mosbach"
    ],
    "name:frr_x_preferred":[
        "Mosbach"
    ],
    "name:hrv_x_preferred":[
        "Mosbach"
    ],
    "name:hun_x_preferred":[
        "Mosbach"
    ],
    "name:ile_x_preferred":[
        "Mosbach"
    ],
    "name:ita_x_preferred":[
        "Mosbach"
    ],
    "name:jpn_x_preferred":[
        "\u30e2\u30fc\u30b9\u30d0\u30c3\u30cf"
    ],
    "name:lat_x_preferred":[
        "Mosbach"
    ],
    "name:lmo_x_preferred":[
        "Mosbach"
    ],
    "name:msa_x_preferred":[
        "Mosbach"
    ],
    "name:nld_x_preferred":[
        "Mosbach"
    ],
    "name:pfl_x_preferred":[
        "Mosbach"
    ],
    "name:pol_x_preferred":[
        "Mosbach"
    ],
    "name:por_x_preferred":[
        "Mosbach"
    ],
    "name:ron_x_preferred":[
        "Mosbach"
    ],
    "name:rus_x_preferred":[
        "\u041c\u043e\u0441\u0431\u0430\u0445"
    ],
    "name:spa_x_preferred":[
        "Mosbach"
    ],
    "name:srp_x_preferred":[
        "\u041c\u043e\u0441\u0431\u0430\u0445"
    ],
    "name:ukr_x_preferred":[
        "\u041c\u043e\u0441\u0431\u0430\u0445"
    ],
    "name:uzb_x_preferred":[
        "Mosbach"
    ],
    "name:vol_x_preferred":[
        "Mosbach"
    ],
    "name:war_x_preferred":[
        "Mosbach"
    ],
    "name:zho_x_preferred":[
        "\u83ab\u65af\u5df4\u8d6b"
    ],
    "wof:name":"Mosbach",
    "wof:placetype":"neighbourhood"
},
  "geometry": {"coordinates":[9.02748,49.89208],"type":"Point"}
}