{
  "type": "Feature",
  "properties": {
    "gn:admin1_code":"2.0",
    "gn:admin2_code":"97.0",
    "gn:admin3_code":"9771.0",
    "gn:admin4_code":"9771122.0",
    "gn:asciiname":"Bitzenhofen",
    "gn:country_code":"DE",
    "gn:dem":477,
    "gn:feature_class":"P",
    "gn:feature_code":"PPL",
    "gn:name":"Bitzenhofen",
    "gn:population":0,
    "gn:timezone":"Europe/Berlin",
    "iso:country":"DE",
    "wof:name":"Bitzenhofen",
    "wof:placetype":"neighbourhood"
},
  "geometry": {"coordinates":[11.038,48.40385],"type":"Point"}
}