{
  "type": "Feature",
  "properties": {
    "gn:admin1_code":"2",
    "gn:admin2_code":"93.0",
    "gn:admin3_code":"9373.0",
    "gn:admin4_code":"9373121.0",
    "gn:asciiname":"Stettenhof",
    "gn:country_code":"DE",
    "gn:dem":497,
    "gn:feature_class":"P",
    "gn:feature_code":"PPL",
    "gn:name":"Stettenhof",
    "gn:population":0,
    "gn:timezone":"Europe/Berlin",
    "iso:country":"DE",
    "wof:name":"Stettenhof",
    "wof:placetype":"neighbourhood"
},
  "geometry": {"coordinates":[11.55642,49.05671],"type":"Point"}
}