{
  "type": "Feature",
  "properties": {
    "gn:admin1_code":"1",
    "gn:admin2_code":"84.0",
    "gn:admin3_code":"8437.0",
    "gn:admin4_code":"8437078.0",
    "gn:asciiname":"Menningen",
    "gn:country_code":"DE",
    "gn:dem":604,
    "gn:feature_class":"P",
    "gn:feature_code":"PPL",
    "gn:name":"Menningen",
    "gn:population":0,
    "gn:timezone":"Europe/Berlin",
    "iso:country":"DE",
    "name:ceb_x_preferred":[
        "Menningen"
    ],
    "name:deu_x_preferred":[
        "Menningen"
    ],
    "name:epo_x_preferred":[
        "Menningen"
    ],
    "name:eus_x_preferred":[
        "Menningen"
    ],
    "name:fas_x_preferred":[
        "\u0645\u0646\u06cc\u0646\u06af\u0646"
    ],
    "name:fra_x_preferred":[
        "Menningen"
    ],
    "name:hun_x_preferred":[
        "Menningen"
    ],
    "name:ita_x_preferred":[
        "Menningen"
    ],
    "name:msa_x_preferred":[
        "Menningen"
    ],
    "name:nld_x_preferred":[
        "Menningen"
    ],
    "name:pol_x_preferred":[
        "Menningen"
    ],
    "name:por_x_preferred":[
        "Menningen"
    ],
    "name:ron_x_preferred":[
        "Menningen"
    ],
    "name:rus_x_preferred":[
        "\u041c\u0435\u043d\u043d\u0438\u043d\u0433\u0435\u043d"
    ],
    "name:spa_x_preferred":[
        "Menningen"
    ],
    "name:srp_x_preferred":[
        "\u041c\u0435\u043d\u0438\u043d\u0433\u0435\u043d"
    ],
    "name:ukr_x_preferred":[
        "\u041c\u0435\u043d\u043d\u0456\u043d\u0433\u0435\u043d"
    ],
    "name:uzb_x_preferred":[
        "Menningen"
    ],
    "name:vie_x_preferred":[
        "Menningen"
    ],
    "name:vol_x_preferred":[
        "Menningen"
    ],
    "name:war_x_preferred":[
        "Menningen"
    ],
    "name:zho_x_preferred":[
        "\u95e8\u5b81\u6839"
    ],
    "wof:name":"Menningen",
    "wof:placetype":"neighbourhood"
},
  "geometry": {"coordinates":[9.16018,48.00848],"type":"Point"}
}