{
  "type": "Feature",
  "properties": {
    "gn:admin1_code":"13",
    "gn:admin2_code":"0.0",
    "gn:admin3_code":"14625.0",
    "gn:admin4_code":"14625360.0",
    "gn:asciiname":"Luga",
    "gn:country_code":"DE",
    "gn:dem":158,
    "gn:feature_class":"P",
    "gn:feature_code":"PPL",
    "gn:name":"Luga",
    "gn:population":0,
    "gn:timezone":"Europe/Berlin",
    "iso:country":"DE",
    "name:bel_x_preferred":[
        "\u041b\u0443\u0433\u0430"
    ],
    "name:ceb_x_preferred":[
        "Luga"
    ],
    "name:chu_x_preferred":[
        "\u041b\u043e\u0443\u0433\u0430"
    ],
    "name:deu_x_preferred":[
        "Luga"
    ],
    "name:epo_x_preferred":[
        "Luga"
    ],
    "name:fin_x_preferred":[
        "Luga"
    ],
    "name:hsb_x_preferred":[
        "Luga"
    ],
    "name:ita_x_preferred":[
        "Luga"
    ],
    "name:jpn_x_preferred":[
        "\u30eb\u30fc\u30ac"
    ],
    "name:kor_x_preferred":[
        "\ub8e8\uac00"
    ],
    "name:lit_x_preferred":[
        "Luga"
    ],
    "name:ltz_x_preferred":[
        "Luga"
    ],
    "name:nld_x_preferred":[
        "Loega"
    ],
    "name:nor_x_preferred":[
        "Luga"
    ],
    "name:por_x_preferred":[
        "Luga"
    ],
    "name:ron_x_preferred":[
        "Luga"
    ],
    "name:rus_x_preferred":[
        "\u041b\u0443\u0433\u0430"
    ],
    "name:sco_x_preferred":[
        "Luga"
    ],
    "name:slk_x_preferred":[
        "Luga"
    ],
    "name:srp_x_preferred":[
        "\u041b\u0443\u0433\u0430"
    ],
    "name:swe_x_preferred":[
        "Luga"
    ],
    "name:ukr_x_preferred":[
        "\u041b\u0443\u0433\u0430"
    ],
    "wof:name":"Luga",
    "wof:placetype":"neighbourhood"
},
  "geometry": {"coordinates":[14.345,51.2459],"type":"Point"}
}