{
  "type": "Feature",
  "properties": {
    "gn:admin1_code":"13",
    "gn:admin2_code":"0.0",
    "gn:admin3_code":"14625.0",
    "gn:admin4_code":"14625360.0",
    "gn:asciiname":"Luga",
    "gn:country_code":"DE",
    "gn:dem":158,
    "gn:feature_class":"P",
    "gn:feature_code":"PPL",
    "gn:name":"Luga",
    "gn:population":0,
    "gn:timezone":"Europe/Berlin",
    "iso:country":"DE",
    "wof:name":"Luga",
    "wof:placetype":"neighbourhood"
},
  "geometry": {"coordinates":[14.345,51.2459],"type":"Point"}
}