{
  "type": "Feature",
  "properties": {
    "gn:admin1_code":"7.0",
    "gn:admin2_code":"57.0",
    "gn:admin3_code":"5754.0",
    "gn:admin4_code":"5754052.0",
    "gn:asciiname":"Arrode",
    "gn:cc2":"DE",
    "gn:country_code":"DE",
    "gn:dem":128,
    "gn:feature_class":"P",
    "gn:feature_code":"PPL",
    "gn:name":"Arrode",
    "gn:population":0,
    "gn:timezone":"Europe/Berlin",
    "iso:country":"DE",
    "name:und_x_variant":[
        "Arrode-Werther"
    ],
    "wof:name":"Arrode",
    "wof:placetype":"neighbourhood"
},
  "geometry": {"coordinates":[8.42857,52.07486],"type":"Point"}
}