{
  "type": "Feature",
  "properties": {
    "gn:admin1_code":"2",
    "gn:admin2_code":"92.0",
    "gn:admin3_code":"9274.0",
    "gn:admin4_code":"9274165.0",
    "gn:asciiname":"Haslau",
    "gn:country_code":"DE",
    "gn:dem":479,
    "gn:feature_class":"P",
    "gn:feature_code":"PPL",
    "gn:name":"Haslau",
    "gn:population":0,
    "gn:timezone":"Europe/Berlin",
    "iso:country":"DE",
    "wof:name":"Haslau",
    "wof:placetype":"neighbourhood"
},
  "geometry": {"coordinates":[11.93196,48.59641],"type":"Point"}
}