{
  "type": "Feature",
  "properties": {
    "gn:admin1_code":"6.0",
    "gn:admin2_code":"00",
    "gn:admin3_code":"3358.0",
    "gn:admin4_code":"3358019.0",
    "gn:asciiname":"Zahrensen",
    "gn:country_code":"DE",
    "gn:dem":70,
    "gn:feature_class":"P",
    "gn:feature_code":"PPL",
    "gn:name":"Zahrensen",
    "gn:population":0,
    "gn:timezone":"Europe/Berlin",
    "iso:country":"DE",
    "wof:name":"Zahrensen",
    "wof:placetype":"neighbourhood"
},
  "geometry": {"coordinates":[9.76208,53.11352],"type":"Point"}
}