{
  "type": "Feature",
  "properties": {
    "gn:admin1_code":"7",
    "gn:admin2_code":"57.0",
    "gn:admin3_code":"5766.0",
    "gn:admin4_code":"5766040.0",
    "gn:asciiname":"Hedderhagen",
    "gn:country_code":"DE",
    "gn:dem":188,
    "gn:feature_class":"P",
    "gn:feature_code":"PPL",
    "gn:name":"Hedderhagen",
    "gn:population":0,
    "gn:timezone":"Europe/Berlin",
    "iso:country":"DE",
    "wof:name":"Hedderhagen",
    "wof:placetype":"neighbourhood"
},
  "geometry": {"coordinates":[8.86302,51.97626],"type":"Point"}
}