{
  "type": "Feature",
  "properties": {
    "gn:admin1_code":"5",
    "gn:admin2_code":"65.0",
    "gn:admin3_code":"6533.0",
    "gn:admin4_code":"6533018.0",
    "gn:asciiname":"Laubuseschbach",
    "gn:country_code":"DE",
    "gn:dem":294,
    "gn:feature_class":"P",
    "gn:feature_code":"PPL",
    "gn:name":"Laubuseschbach",
    "gn:population":0,
    "gn:timezone":"Europe/Berlin",
    "iso:country":"DE",
    "wof:name":"Laubuseschbach",
    "wof:placetype":"neighbourhood"
},
  "geometry": {"coordinates":[8.33709,50.39764],"type":"Point"}
}