{
  "type": "Feature",
  "properties": {
    "gn:admin1_code":"6",
    "gn:admin2_code":"0.0",
    "gn:admin3_code":"3159.0",
    "gn:admin4_code":"3159015.0",
    "gn:asciiname":"Etzenborn",
    "gn:country_code":"DE",
    "gn:dem":220,
    "gn:feature_class":"P",
    "gn:feature_code":"PPL",
    "gn:name":"Etzenborn",
    "gn:population":0,
    "gn:timezone":"Europe/Berlin",
    "iso:country":"DE",
    "name:deu_x_preferred":[
        "Etzenborn"
    ],
    "name:fas_x_preferred":[
        "\u0627\u062a\u0633\u0646\u0628\u0648\u0631\u0646"
    ],
    "wof:name":"Etzenborn",
    "wof:placetype":"neighbourhood"
},
  "geometry": {"coordinates":[10.16459,51.46171],"type":"Point"}
}