{
  "type": "Feature",
  "properties": {
    "gn:admin1_code":"2",
    "gn:admin2_code":"95.0",
    "gn:admin3_code":"9576.0",
    "gn:admin4_code":"9576151.0",
    "gn:asciiname":"Raubersried",
    "gn:country_code":"DE",
    "gn:dem":347,
    "gn:feature_class":"P",
    "gn:feature_code":"PPL",
    "gn:name":"Raubersried",
    "gn:population":0,
    "gn:timezone":"Europe/Berlin",
    "iso:country":"DE",
    "wof:name":"Raubersried",
    "wof:placetype":"neighbourhood"
},
  "geometry": {"coordinates":[11.14675,49.34263],"type":"Point"}
}