{
  "type": "Feature",
  "properties": {
    "gn:admin1_code":"2",
    "gn:admin2_code":"94.0",
    "gn:admin3_code":"9471.0",
    "gn:admin4_code":"9471185.0",
    "gn:asciiname":"Stubig",
    "gn:country_code":"DE",
    "gn:dem":349,
    "gn:feature_class":"P",
    "gn:feature_code":"PPL",
    "gn:name":"St\u00fcbig",
    "gn:population":0,
    "gn:timezone":"Europe/Berlin",
    "iso:country":"DE",
    "wof:name":"Stubig",
    "wof:placetype":"neighbourhood"
},
  "geometry": {"coordinates":[11.07336,50.01105],"type":"Point"}
}