{
  "type": "Feature",
  "properties": {
    "iso:country":"DE",
    "wof:name":"Leipziger Vorstadt",
    "wof:placetype":"neighbourhood"
},
  "geometry": {"coordinates":[13.74284099114537,51.07322323484664],"type":"Point"}
}