{
  "type": "Feature",
  "properties": {
    "gn:admin1_code":"1",
    "gn:admin2_code":"81.0",
    "gn:admin3_code":"8117.0",
    "gn:admin4_code":"8117014.0",
    "gn:asciiname":"Reichenbach im Tale",
    "gn:country_code":"DE",
    "gn:dem":491,
    "gn:feature_class":"P",
    "gn:feature_code":"PPL",
    "gn:name":"Reichenbach im T\u00e4le",
    "gn:population":0,
    "gn:timezone":"Europe/Berlin",
    "iso:country":"DE",
    "name:und_x_variant":[
        "Reichenbach"
    ],
    "wof:name":"Reichenbach im Tale",
    "wof:placetype":"neighbourhood"
},
  "geometry": {"coordinates":[9.73612,48.61566],"type":"Point"}
}