{
  "type": "Feature",
  "properties": {
    "gn:admin1_code":"5.0",
    "gn:admin2_code":"66.0",
    "gn:admin3_code":"6631.0",
    "gn:admin4_code":"6631003.0",
    "gn:asciiname":"Birkenhof",
    "gn:country_code":"DE",
    "gn:dem":433,
    "gn:feature_class":"P",
    "gn:feature_code":"PPL",
    "gn:name":"Birkenhof",
    "gn:population":0,
    "gn:timezone":"Europe/Berlin",
    "iso:country":"DE",
    "wof:name":"Birkenhof",
    "wof:placetype":"neighbourhood"
},
  "geometry": {"coordinates":[9.83478,50.54273],"type":"Point"}
}