{
  "type": "Feature",
  "properties": {
    "gn:admin1_code":"13.0",
    "gn:admin2_code":"0.0",
    "gn:admin3_code":"14521.0",
    "gn:admin4_code":"14521390.0",
    "gn:asciiname":"Auf der Heide",
    "gn:country_code":"DE",
    "gn:dem":625,
    "gn:feature_class":"P",
    "gn:feature_code":"PPL",
    "gn:name":"Auf der Heide",
    "gn:population":0,
    "gn:timezone":"Europe/Berlin",
    "iso:country":"DE",
    "wof:name":"Auf der Heide",
    "wof:placetype":"neighbourhood"
},
  "geometry": {"coordinates":[13.25541,50.65363],"type":"Point"}
}