{
  "type": "Feature",
  "properties": {
    "gn:admin1_code":"5",
    "gn:admin2_code":"65.0",
    "gn:admin3_code":"6534.0",
    "gn:admin4_code":"6534002.0",
    "gn:asciiname":"Frechenhausen",
    "gn:country_code":"DE",
    "gn:dem":426,
    "gn:feature_class":"P",
    "gn:feature_code":"PPL",
    "gn:name":"Frechenhausen",
    "gn:population":0,
    "gn:timezone":"Europe/Berlin",
    "iso:country":"DE",
    "wof:name":"Frechenhausen",
    "wof:placetype":"neighbourhood"
},
  "geometry": {"coordinates":[8.4332,50.81105],"type":"Point"}
}