{
  "type": "Feature",
  "properties": {
    "gn:admin1_code":"2",
    "gn:admin2_code":"96.0",
    "gn:admin3_code":"9678.0",
    "gn:admin4_code":"9678157.0",
    "gn:asciiname":"Heinachshof",
    "gn:country_code":"DE",
    "gn:dem":387,
    "gn:feature_class":"P",
    "gn:feature_code":"PPL",
    "gn:name":"Heinachshof",
    "gn:population":0,
    "gn:timezone":"Europe/Berlin",
    "iso:country":"DE",
    "wof:name":"Heinachshof",
    "wof:placetype":"neighbourhood"
},
  "geometry": {"coordinates":[10.45379,49.92819],"type":"Point"}
}