{
  "type": "Feature",
  "properties": {
    "gn:admin1_code":"1",
    "gn:admin2_code":"84.0",
    "gn:admin3_code":"8436.0",
    "gn:admin4_code":"8436049.0",
    "gn:asciiname":"Hedrazhofen",
    "gn:country_code":"DE",
    "gn:dem":723,
    "gn:feature_class":"P",
    "gn:feature_code":"PPL",
    "gn:name":"Hedrazhofen",
    "gn:population":0,
    "gn:timezone":"Europe/Berlin",
    "iso:country":"DE",
    "wof:name":"Hedrazhofen",
    "wof:placetype":"neighbourhood"
},
  "geometry": {"coordinates":[10.01596,47.74511],"type":"Point"}
}