{
  "type": "Feature",
  "properties": {
    "gn:admin1_code":"14",
    "gn:admin2_code":"0.0",
    "gn:admin3_code":"15090.0",
    "gn:admin4_code":"15090546.0",
    "gn:asciiname":"Kleinschwarzlosen",
    "gn:country_code":"DE",
    "gn:dem":46,
    "gn:feature_class":"P",
    "gn:feature_code":"PPL",
    "gn:name":"Kleinschwarzlosen",
    "gn:population":0,
    "gn:timezone":"Europe/Berlin",
    "iso:country":"DE",
    "wof:name":"Kleinschwarzlosen",
    "wof:placetype":"neighbourhood"
},
  "geometry": {"coordinates":[11.79039,52.49344],"type":"Point"}
}