{
  "type": "Feature",
  "properties": {
    "gn:gn_country":"DE",
    "gn:gn_fcode":"PPLA4",
    "gn:gn_pop":546,
    "gn:population":546,
    "iso:country":"DE",
    "name:baq_x_preferred":[
        "Echternacherbr\u00fcck"
    ],
    "name:chi_x_preferred":[
        "\u57c3\u5e0c\u7279\u5c14\u7eb3\u9ed1\u5c14\u5e03\u5415\u514b"
    ],
    "name:dut_x_preferred":[
        "Echternacherbr\u00fcck"
    ],
    "name:eng_x_preferred":[
        "Echternacherbr\u00fcck"
    ],
    "name:epo_x_preferred":[
        "Echternacherbr\u00fcck"
    ],
    "name:fre_x_preferred":[
        "Echternacherbr\u00fcck"
    ],
    "name:ger_x_preferred":[
        "Echternacherbr\u00fcck"
    ],
    "name:hun_x_preferred":[
        "Echternacherbr\u00fcck"
    ],
    "name:ita_x_preferred":[
        "Echternacherbr\u00fcck"
    ],
    "name:jpn_x_preferred":[
        "\u30a8\u30d2\u30bf\u30fc\u30ca\u30c3\u30cf\u30fc\u30d7\u30ea\u30e5\u30c3\u30af"
    ],
    "name:kaz_x_preferred":[
        "\u042d\u0445\u0442\u0435\u0440\u043d\u0430\u0445\u0435\u0440\u0431\u0440\u044e\u043a"
    ],
    "name:kir_x_preferred":[
        "\u042d\u0445\u0442\u0435\u0440\u043d\u0430\u0445\u0435\u0440\u0431\u0440\u04af\u043a"
    ],
    "name:ltz_x_preferred":[
        "Iechternacherbr\u00e9ck"
    ],
    "name:may_x_preferred":[
        "Echternacherbr\u00fcck"
    ],
    "name:per_x_preferred":[
        "\u0627\u0634\u062a\u0631\u0646\u0627\u062e\u0631\u0628\u0631\u0648\u06a9"
    ],
    "name:pol_x_preferred":[
        "Echternacherbr\u00fcck"
    ],
    "name:por_x_preferred":[
        "Echternacherbr\u00fcck"
    ],
    "name:rum_x_preferred":[
        "Echternacherbr\u00fcck"
    ],
    "name:rus_x_preferred":[
        "\u042d\u0445\u0442\u0435\u0440\u043d\u0430\u0445\u0435\u0440\u0431\u0440\u044e\u043a"
    ],
    "name:spa_x_preferred":[
        "Echternacherbr\u00fcck"
    ],
    "name:srp_x_preferred":[
        "\u0415\u0445\u0442\u0435\u0440\u043d\u0430\u0445\u0435\u0440\u0431\u0440\u0438\u043a"
    ],
    "name:ukr_x_preferred":[
        "\u0415\u0445\u0442\u0435\u0440\u043d\u0430\u0445\u0435\u0440\u0431\u0440\u044e\u043a"
    ],
    "name:uzb_x_preferred":[
        "Echternacherbr\u00fcck"
    ],
    "name:vie_x_preferred":[
        "Echternacherbr\u00fcck"
    ],
    "name:vol_x_preferred":[
        "Echternacherbr\u00fcck"
    ],
    "name:war_x_preferred":[
        "Echternacherbr\u00fcck"
    ],
    "qs_pg:aaroncc":"DE",
    "qs_pg:gn_country":"DE",
    "qs_pg:gn_fcode":"PPLA4",
    "qs_pg:gn_pop":546,
    "qs_pg:name":"Echternacherbr\u00fcck",
    "qs_pg:photos_9r":0,
    "qs_pg:photos_sr":0,
    "qs_pg:pop_sr":2,
    "qs_pg:qs_pg_placetype":"locality",
    "wof:name":"Echternacherbr\u00fcck",
    "wof:placetype":"locality",
    "wof:population":546
},
  "geometry": {"coordinates":[6.43333,49.81667],"type":"Point"}
}