{
  "type": "Feature",
  "properties": {
    "gn:admin1_code":"13.0",
    "gn:admin2_code":"0.0",
    "gn:admin3_code":"14625.0",
    "gn:admin4_code":"14625580.0",
    "gn:asciiname":"Niedersteina",
    "gn:country_code":"DE",
    "gn:dem":250,
    "gn:feature_class":"P",
    "gn:feature_code":"PPL",
    "gn:name":"Niedersteina",
    "gn:population":0,
    "gn:timezone":"Europe/Berlin",
    "iso:country":"DE",
    "wof:name":"Niedersteina",
    "wof:placetype":"neighbourhood"
},
  "geometry": {"coordinates":[14.03456,51.21218],"type":"Point"}
}