{
  "type": "Feature",
  "properties": {
    "gn:admin1_code":"12",
    "gn:admin2_code":"0.0",
    "gn:admin3_code":"13073.0",
    "gn:admin4_code":"13073090.0",
    "gn:asciiname":"Hof Reinberg",
    "gn:country_code":"DE",
    "gn:dem":11,
    "gn:feature_class":"P",
    "gn:feature_code":"PPL",
    "gn:name":"Hof Reinberg",
    "gn:population":0,
    "gn:timezone":"Europe/Berlin",
    "iso:country":"DE",
    "wof:name":"Hof Reinberg",
    "wof:placetype":"neighbourhood"
},
  "geometry": {"coordinates":[13.25,54.21666999999999],"type":"Point"}
}