{
  "type": "Feature",
  "properties": {
    "gn:admin1_code":"1",
    "gn:admin2_code":"81.0",
    "gn:admin3_code":"8136.0",
    "gn:admin4_code":"8136060.0",
    "gn:asciiname":"Geiselrot",
    "gn:country_code":"DE",
    "gn:dem":505,
    "gn:feature_class":"P",
    "gn:feature_code":"PPL",
    "gn:name":"Geiselrot",
    "gn:population":0,
    "gn:timezone":"Europe/Berlin",
    "iso:country":"DE",
    "wof:name":"Geiselrot",
    "wof:placetype":"neighbourhood"
},
  "geometry": {"coordinates":[10.01938,49.02438],"type":"Point"}
}