{
  "type": "Feature",
  "properties": {
    "gn:admin1_code":"2",
    "gn:admin2_code":"95.0",
    "gn:admin3_code":"9571.0",
    "gn:admin4_code":"9571196.0",
    "gn:asciiname":"Steinhof",
    "gn:country_code":"DE",
    "gn:dem":463,
    "gn:feature_class":"P",
    "gn:feature_code":"PPL",
    "gn:name":"Steinhof",
    "gn:population":0,
    "gn:timezone":"Europe/Berlin",
    "iso:country":"DE",
    "name:ara_x_preferred":[
        "\u0633\u062a\u0627\u064a\u0646 \u0647\u0648\u0641"
    ],
    "name:cat_x_preferred":[
        "Steinhof"
    ],
    "name:ceb_x_preferred":[
        "Steinhof"
    ],
    "name:deu_x_preferred":[
        "Steinhof"
    ],
    "name:epo_x_preferred":[
        "Steinhof"
    ],
    "name:fin_x_preferred":[
        "Steinhof"
    ],
    "name:fra_x_preferred":[
        "Steinhof"
    ],
    "name:ita_x_preferred":[
        "Steinhof"
    ],
    "name:kaz_x_preferred":[
        "\u0428\u0442\u0430\u0439\u043d\u0445\u043e\u0444"
    ],
    "name:lmo_x_preferred":[
        "Steinhof"
    ],
    "name:msa_x_preferred":[
        "Steinhof"
    ],
    "name:nld_x_preferred":[
        "Steinhof"
    ],
    "name:rus_x_preferred":[
        "\u0428\u0442\u0430\u0439\u043d\u0445\u043e\u0444"
    ],
    "name:spa_x_preferred":[
        "Steinhof"
    ],
    "name:sqi_x_preferred":[
        "Steinhof"
    ],
    "name:swe_x_preferred":[
        "Steinhof"
    ],
    "name:uzb_x_preferred":[
        "Steinhof"
    ],
    "name:vie_x_preferred":[
        "Steinhof"
    ],
    "name:vol_x_preferred":[
        "Steinhof"
    ],
    "name:war_x_preferred":[
        "Steinhof"
    ],
    "name:zho_x_preferred":[
        "\u65af\u6cf0\u56e0\u970d\u592b"
    ],
    "wof:name":"Steinhof",
    "wof:placetype":"neighbourhood"
},
  "geometry": {"coordinates":[10.65512,49.25958],"type":"Point"}
}