{
  "type": "Feature",
  "properties": {
    "gn:admin1_code":"14",
    "gn:admin2_code":"0.0",
    "gn:admin3_code":"15081.0",
    "gn:admin4_code":"15081455.0",
    "gn:asciiname":"Klein Chueden",
    "gn:country_code":"DE",
    "gn:dem":23,
    "gn:feature_class":"P",
    "gn:feature_code":"PPL",
    "gn:name":"Klein Ch\u00fcden",
    "gn:population":0,
    "gn:timezone":"Europe/Berlin",
    "iso:country":"DE",
    "wof:name":"Klein Chueden",
    "wof:placetype":"neighbourhood"
},
  "geometry": {"coordinates":[11.21867,52.87457],"type":"Point"}
}