{
  "type": "Feature",
  "properties": {
    "gn:admin1_code":"13.0",
    "gn:admin2_code":"0.0",
    "gn:admin3_code":"14523.0",
    "gn:admin4_code":"14523170.0",
    "gn:asciiname":"Abhorn",
    "gn:country_code":"DE",
    "gn:dem":416,
    "gn:feature_class":"P",
    "gn:feature_code":"PPL",
    "gn:name":"Abhorn",
    "gn:population":0,
    "gn:timezone":"Europe/Berlin",
    "iso:country":"DE",
    "wof:name":"Abhorn",
    "wof:placetype":"neighbourhood"
},
  "geometry": {"coordinates":[12.39753,50.56011],"type":"Point"}
}