{
  "type": "Feature",
  "properties": {
    "gn:admin1_code":"6",
    "gn:admin2_code":"0.0",
    "gn:admin3_code":"3455.0",
    "gn:admin4_code":"3455007.0",
    "gn:asciiname":"Sandeler Moens",
    "gn:country_code":"DE",
    "gn:dem":4,
    "gn:feature_class":"P",
    "gn:feature_code":"PPL",
    "gn:name":"Sandeler M\u00f6ns",
    "gn:population":0,
    "gn:timezone":"Europe/Berlin",
    "iso:country":"DE",
    "name:und_x_variant":[
        "M\u00f6ns",
        "Sandeler M\u00f6ns"
    ],
    "wof:name":"Sandeler Moens",
    "wof:placetype":"neighbourhood"
},
  "geometry": {"coordinates":[7.845,53.52246],"type":"Point"}
}