{
  "type": "Feature",
  "properties": {
    "gn:admin1_code":"2",
    "gn:admin2_code":"97.0",
    "gn:admin3_code":"9778.0",
    "gn:admin4_code":"9778136.0",
    "gn:asciiname":"Moosmuhle",
    "gn:country_code":"DE",
    "gn:dem":582,
    "gn:feature_class":"P",
    "gn:feature_code":"PPL",
    "gn:name":"Moosm\u00fchle",
    "gn:population":0,
    "gn:timezone":"Europe/Berlin",
    "iso:country":"DE",
    "wof:name":"Moosmuhle",
    "wof:placetype":"neighbourhood"
},
  "geometry": {"coordinates":[10.30986,48.05895],"type":"Point"}
}