{
  "type": "Feature",
  "properties": {
    "gn:gn_country":"DE",
    "gn:gn_fcode":"PPLA4",
    "gn:gn_pop":312,
    "gn:population":312,
    "iso:country":"DE",
    "name:baq_x_preferred":[
        "Hilgenroth"
    ],
    "name:chi_x_preferred":[
        "\u5e0c\u5c14\u6839\u7f57\u7279"
    ],
    "name:dut_x_preferred":[
        "Hilgenroth"
    ],
    "name:eng_x_preferred":[
        "Hilgenroth"
    ],
    "name:epo_x_preferred":[
        "Hilgenroth"
    ],
    "name:fas_x_preferred":[
        "\u0647\u06cc\u0644\u06af\u0646\u0631\u0627\u062a"
    ],
    "name:fre_x_preferred":[
        "Hilgenroth"
    ],
    "name:ger_x_preferred":[
        "Hilgenroth"
    ],
    "name:hun_x_preferred":[
        "Hilgenroth"
    ],
    "name:ita_x_preferred":[
        "Hilgenroth"
    ],
    "name:jpn_x_preferred":[
        "\u30d2\u30eb\u30b2\u30f3\u30ed\u30fc\u30c8"
    ],
    "name:kaz_x_preferred":[
        "\u0425\u0438\u043b\u044c\u0433\u0435\u043d\u0440\u043e\u0442"
    ],
    "name:kir_x_preferred":[
        "\u0425\u0438\u043b\u044c\u0433\u0435\u043d\u0440\u043e\u0442"
    ],
    "name:may_x_preferred":[
        "Hilgenroth"
    ],
    "name:per_x_preferred":[
        "\u0647\u06cc\u0644\u06af\u0646\u0631\u0627\u062a"
    ],
    "name:pol_x_preferred":[
        "Hilgenroth"
    ],
    "name:por_x_preferred":[
        "Hilgenroth"
    ],
    "name:rum_x_preferred":[
        "Hilgenroth"
    ],
    "name:rus_x_preferred":[
        "\u0425\u0438\u043b\u044c\u0433\u0435\u043d\u0440\u043e\u0442"
    ],
    "name:srp_x_preferred":[
        "\u0425\u0438\u043b\u0433\u0435\u043d\u0440\u043e\u0442"
    ],
    "name:ukr_x_preferred":[
        "\u0413\u0456\u043b\u044c\u0433\u0435\u043d\u0440\u043e\u0442"
    ],
    "name:uzb_x_preferred":[
        "Hilgenroth"
    ],
    "name:vie_x_preferred":[
        "Hilgenroth"
    ],
    "name:vol_x_preferred":[
        "Hilgenroth"
    ],
    "name:war_x_preferred":[
        "Hilgenroth"
    ],
    "name:zho_x_preferred":[
        "\u5e0c\u5c14\u6839\u7f57\u7279"
    ],
    "qs_pg:aaroncc":"DE",
    "qs_pg:gn_country":"DE",
    "qs_pg:gn_fcode":"PPLA4",
    "qs_pg:gn_pop":312,
    "qs_pg:name":"Hilgenroth",
    "qs_pg:photos_9r":0,
    "qs_pg:photos_sr":0,
    "qs_pg:pop_sr":2,
    "qs_pg:qs_pg_placetype":"locality",
    "wof:name":"Hilgenroth",
    "wof:placetype":"locality",
    "wof:population":312
},
  "geometry": {"coordinates":[7.65,50.73333],"type":"Point"}
}