{
  "type": "Feature",
  "properties": {
    "gn:admin1_code":"6",
    "gn:admin2_code":"0.0",
    "gn:admin3_code":"3454.0",
    "gn:admin4_code":"3454007.0",
    "gn:asciiname":"Neudersum",
    "gn:country_code":"DE",
    "gn:dem":7,
    "gn:feature_class":"P",
    "gn:feature_code":"PPL",
    "gn:name":"Neudersum",
    "gn:population":0,
    "gn:timezone":"Europe/Berlin",
    "iso:country":"DE",
    "wof:name":"Neudersum",
    "wof:placetype":"neighbourhood"
},
  "geometry": {"coordinates":[7.23332,52.97081],"type":"Point"}
}