{
  "type": "Feature",
  "properties": {
    "gn:admin1_code":"1",
    "gn:admin2_code":"83.0",
    "gn:admin3_code":"8326.0",
    "gn:admin4_code":"8326052.0",
    "gn:asciiname":"Sinsenbach",
    "gn:country_code":"DE",
    "gn:dem":899,
    "gn:feature_class":"P",
    "gn:feature_code":"PPLL",
    "gn:name":"Sinsenbach",
    "gn:population":0,
    "gn:timezone":"Europe/Berlin",
    "iso:country":"DE",
    "wof:name":"Sinsenbach",
    "wof:placetype":"neighbourhood"
},
  "geometry": {"coordinates":[8.31481,48.08459000000001],"type":"Point"}
}