{
  "type": "Feature",
  "properties": {
    "gn:admin1_code":"7.0",
    "gn:admin2_code":"053",
    "gn:admin3_code":"5362.0",
    "gn:admin4_code":"5362008.0",
    "gn:asciiname":"Zieverich",
    "gn:country_code":"DE",
    "gn:dem":65,
    "gn:feature_class":"P",
    "gn:feature_code":"PPL",
    "gn:name":"Zieverich",
    "gn:population":0,
    "gn:timezone":"Europe/Berlin",
    "iso:country":"DE",
    "wof:name":"Zieverich",
    "wof:placetype":"neighbourhood"
},
  "geometry": {"coordinates":[6.62446,50.95107],"type":"Point"}
}