{
  "type": "Feature",
  "properties": {
    "gn:admin1_code":"2.0",
    "gn:admin2_code":"94.0",
    "gn:admin3_code":"9477.0",
    "gn:admin4_code":"9477136.0",
    "gn:asciiname":"Bechtelsreuth",
    "gn:country_code":"DE",
    "gn:dem":376,
    "gn:feature_class":"P",
    "gn:feature_code":"PPL",
    "gn:name":"Bechtelsreuth",
    "gn:population":0,
    "gn:timezone":"Europe/Berlin",
    "iso:country":"DE",
    "wof:name":"Bechtelsreuth",
    "wof:placetype":"neighbourhood"
},
  "geometry": {"coordinates":[11.3532,50.07972],"type":"Point"}
}