{
  "type": "Feature",
  "properties": {
    "gn:admin1_code":"5",
    "gn:admin2_code":"64.0",
    "gn:admin3_code":"6439.0",
    "gn:admin4_code":"6439001.0",
    "gn:asciiname":"Hausen ueber Aar",
    "gn:country_code":"DE",
    "gn:dem":184,
    "gn:feature_class":"P",
    "gn:feature_code":"PPL",
    "gn:name":"Hausen \u00fcber Aar",
    "gn:population":0,
    "gn:timezone":"Europe/Berlin",
    "iso:country":"DE",
    "name:und_x_variant":[
        "Hausen",
        "Hausen \u00fcber Aar"
    ],
    "wof:name":"Hausen ueber Aar",
    "wof:placetype":"neighbourhood"
},
  "geometry": {"coordinates":[8.06053,50.25216],"type":"Point"}
}