{
  "type": "Feature",
  "properties": {
    "gn:admin1_code":"7",
    "gn:admin2_code":"59.0",
    "gn:admin3_code":"5915.0",
    "gn:admin4_code":"5915000.0",
    "gn:asciiname":"Rhynern",
    "gn:country_code":"DE",
    "gn:dem":93,
    "gn:feature_class":"P",
    "gn:feature_code":"PPL",
    "gn:name":"Rhynern",
    "gn:population":0,
    "gn:timezone":"Europe/Berlin",
    "iso:country":"DE",
    "name:ceb_x_preferred":[
        "Rhynern"
    ],
    "name:deu_x_preferred":[
        "Hamm-Rhynern"
    ],
    "name:fas_x_preferred":[
        "\u0631\u0647\u0648\u0646\u0631\u0646"
    ],
    "wof:name":"Rhynern",
    "wof:placetype":"neighbourhood"
},
  "geometry": {"coordinates":[7.85591,51.63022],"type":"Point"}
}