{
  "type": "Feature",
  "properties": {
    "gn:admin1_code":"1",
    "gn:admin2_code":"82.0",
    "gn:admin3_code":"8237.0",
    "gn:admin4_code":"8237045.0",
    "gn:asciiname":"Rossbach",
    "gn:country_code":"DE",
    "gn:dem":568,
    "gn:feature_class":"P",
    "gn:feature_code":"PPL",
    "gn:name":"Ro\u00dfbach",
    "gn:population":0,
    "gn:timezone":"Europe/Berlin",
    "iso:country":"DE",
    "name:ceb_x_preferred":[
        "Rossbach"
    ],
    "name:kaz_x_preferred":[
        "\u0420\u043e\u0441\u0431\u0430\u0445"
    ],
    "name:kir_x_preferred":[
        "\u0420\u043e\u0441\u0431\u0430\u0445"
    ],
    "name:rus_x_preferred":[
        "\u0420\u043e\u0441\u0431\u0430\u0445"
    ],
    "name:srp_x_preferred":[
        "\u0420\u043e\u0441\u0431\u0430\u0445"
    ],
    "name:swe_x_preferred":[
        "Rossbach"
    ],
    "wof:name":"Rossbach",
    "wof:placetype":"neighbourhood"
},
  "geometry": {"coordinates":[8.46853,48.37761],"type":"Point"}
}