{
  "type": "Feature",
  "properties": {
    "gn:admin1_code":"14.0",
    "gn:admin2_code":"0.0",
    "gn:admin3_code":"15088.0",
    "gn:admin4_code":"15088319.0",
    "gn:asciiname":"Boltzenhoehe",
    "gn:country_code":"DE",
    "gn:dem":176,
    "gn:feature_class":"P",
    "gn:feature_code":"PPL",
    "gn:name":"Boltzenh\u00f6he",
    "gn:population":0,
    "gn:timezone":"Europe/Berlin",
    "iso:country":"DE",
    "name:und_x_variant":[
        "Boltzenh\u00f6h",
        "Boltzenh\u00f6he"
    ],
    "wof:name":"Boltzenhoehe",
    "wof:placetype":"neighbourhood"
},
  "geometry": {"coordinates":[11.74916,51.52072],"type":"Point"}
}