{
  "type": "Feature",
  "properties": {
    "gn:admin1_code":"5",
    "gn:admin2_code":"66.0",
    "gn:admin3_code":"6631.0",
    "gn:admin4_code":"6631018.0",
    "gn:asciiname":"Dorfborn",
    "gn:country_code":"DE",
    "gn:dem":288,
    "gn:feature_class":"P",
    "gn:feature_code":"PPL",
    "gn:name":"Dorfborn",
    "gn:population":0,
    "gn:timezone":"Europe/Berlin",
    "iso:country":"DE",
    "wof:name":"Dorfborn",
    "wof:placetype":"neighbourhood"
},
  "geometry": {"coordinates":[9.62874,50.46597],"type":"Point"}
}