{
  "type": "Feature",
  "properties": {
    "gn:country":"DE",
    "gn:fcode":"PPL",
    "gn:population":971,
    "iso:country":"DE",
    "name:bak_x_preferred":[
        "\u0425\u0430\u0439\u043c\u0431\u0443\u0440\u0433"
    ],
    "name:bul_x_preferred":[
        "\u0425\u0430\u0439\u043c\u0431\u0443\u0440\u0433"
    ],
    "name:ceb_x_preferred":[
        "Heimburg"
    ],
    "name:deu_x_preferred":[
        "Heimburg"
    ],
    "name:epo_x_preferred":[
        "Heimburg"
    ],
    "name:fas_x_preferred":[
        "\u0647\u0627\u06cc\u0645\u0628\u0648\u0631\u06af"
    ],
    "name:ita_x_preferred":[
        "Heimburg"
    ],
    "name:kaz_x_preferred":[
        "\u0425\u0430\u0439\u043c\u0431\u0443\u0440\u0433"
    ],
    "name:kir_x_preferred":[
        "\u0425\u0430\u0439\u043c\u0431\u0443\u0440\u0433"
    ],
    "name:mkd_x_preferred":[
        "\u0425\u0430\u0458\u043c\u0431\u0443\u0440\u0433"
    ],
    "name:nld_x_preferred":[
        "Heimburg"
    ],
    "name:ron_x_preferred":[
        "Heimburg"
    ],
    "name:rus_x_preferred":[
        "\u0425\u0430\u0439\u043c\u0431\u0443\u0440\u0433"
    ],
    "name:uzb_x_preferred":[
        "Heimburg"
    ],
    "name:vie_x_preferred":[
        "Heimburg"
    ],
    "name:vol_x_preferred":[
        "Heimburg"
    ],
    "qs_pg:aaroncc":"DE",
    "qs_pg:gn_country":"DE",
    "qs_pg:gn_fcode":"PPL",
    "qs_pg:gn_pop":971,
    "qs_pg:name":"Heimburg",
    "qs_pg:name_adm0":"Deutschland",
    "qs_pg:name_adm1":"Sachsen-Anhalt",
    "qs_pg:photos_9k":1,
    "qs_pg:photos_9r":4,
    "qs_pg:photos_all":184,
    "qs_pg:photos_sr":0,
    "qs_pg:pop_sr":2,
    "qs_pg:qs_pg_placetype":"locality",
    "qs_pg:qs_pg_placetype_gp":"Town",
    "qs_pg:woe_adm0":23424829,
    "woe:adm0_id":23424829,
    "woe:name_adm0":"Deutschland",
    "woe:name_adm1":"Sachsen-Anhalt",
    "woe:placetype":"Town",
    "wof:name":"Heimburg",
    "wof:placetype":"neighbourhood",
    "wof:population":971
},
  "geometry": {"coordinates":[10.9114,51.82326],"type":"Point"}
}