{
  "type": "Feature",
  "properties": {
    "gn:admin1_code":"10",
    "gn:admin2_code":"0.0",
    "gn:admin3_code":"1054.0",
    "gn:admin4_code":"1054150.0",
    "gn:asciiname":"Steinhuetten",
    "gn:country_code":"DE",
    "gn:dem":-1,
    "gn:feature_class":"P",
    "gn:feature_code":"PPL",
    "gn:name":"Steinh\u00fctten",
    "gn:population":0,
    "gn:timezone":"Europe/Berlin",
    "iso:country":"DE",
    "wof:name":"Steinhuetten",
    "wof:placetype":"neighbourhood"
},
  "geometry": {"coordinates":[8.70051,54.38141],"type":"Point"}
}