{
  "type": "Feature",
  "properties": {
    "iso:country":"DE",
    "wof:name":"Dransdorf",
    "wof:placetype":"neighbourhood"
},
  "geometry": {"coordinates":[7.05080192005528,50.73800122925164],"type":"Point"}
}