{
  "type": "Feature",
  "properties": {
    "gn:admin1_code":"12.0",
    "gn:admin2_code":"0.0",
    "gn:admin3_code":"13073.0",
    "gn:admin4_code":"13073022.0",
    "gn:asciiname":"Eixen Forsthaus",
    "gn:country_code":"DE",
    "gn:dem":22,
    "gn:feature_class":"P",
    "gn:feature_code":"PPL",
    "gn:name":"Eixen Forsthaus",
    "gn:population":0,
    "gn:timezone":"Europe/Berlin",
    "iso:country":"DE",
    "wof:name":"Eixen Forsthaus",
    "wof:placetype":"neighbourhood"
},
  "geometry": {"coordinates":[12.73878,54.17635],"type":"Point"}
}