{
  "type": "Feature",
  "properties": {
    "gn:admin1_code":"13.0",
    "gn:admin2_code":"0.0",
    "gn:admin3_code":"14730.0",
    "gn:admin4_code":"14730250.0",
    "gn:asciiname":"Biesen",
    "gn:country_code":"DE",
    "gn:dem":107,
    "gn:feature_class":"P",
    "gn:feature_code":"PPL",
    "gn:name":"Biesen",
    "gn:population":0,
    "gn:timezone":"Europe/Berlin",
    "iso:country":"DE",
    "wof:name":"Biesen",
    "wof:placetype":"neighbourhood"
},
  "geometry": {"coordinates":[12.37141,51.47231],"type":"Point"}
}