{
  "type": "Feature",
  "properties": {
    "gn:admin1_code":"6",
    "gn:admin2_code":"0.0",
    "gn:admin3_code":"3360.0",
    "gn:admin4_code":"3360025.0",
    "gn:asciiname":"Holdenstedt",
    "gn:country_code":"DE",
    "gn:dem":47,
    "gn:feature_class":"P",
    "gn:feature_code":"PPL",
    "gn:name":"Holdenstedt",
    "gn:population":0,
    "gn:timezone":"Europe/Berlin",
    "iso:country":"DE",
    "name:bak_x_preferred":[
        "\u0425\u043e\u043b\u044c\u0434\u0435\u043d\u0448\u0442\u0435\u0434\u0442"
    ],
    "name:ceb_x_preferred":[
        "Holdenstedt"
    ],
    "name:deu_x_preferred":[
        "Holdenstedt"
    ],
    "name:epo_x_preferred":[
        "Holdenstedt"
    ],
    "name:fas_x_preferred":[
        "\u0647\u0648\u0644\u062f\u0646\u0634\u062a\u062f\u062a"
    ],
    "name:ita_x_preferred":[
        "Holdenstedt"
    ],
    "name:kaz_x_preferred":[
        "\u0425\u043e\u043b\u044c\u0434\u0435\u043d\u0448\u0442\u0435\u0434\u0442"
    ],
    "name:kir_x_preferred":[
        "\u0425\u043e\u043b\u044c\u0434\u0435\u043d\u0448\u0442\u0435\u0434\u0442"
    ],
    "name:mkd_x_preferred":[
        "\u0425\u043e\u043b\u0434\u0435\u043d\u0448\u0442\u0435\u0442"
    ],
    "name:nld_x_preferred":[
        "Holdenstedt"
    ],
    "name:ron_x_preferred":[
        "Holdenstedt"
    ],
    "name:rus_x_preferred":[
        "\u0425\u043e\u043b\u044c\u0434\u0435\u043d\u0448\u0442\u0435\u0434\u0442"
    ],
    "name:uzb_x_preferred":[
        "Holdenstedt"
    ],
    "name:vie_x_preferred":[
        "Holdenstedt"
    ],
    "name:vol_x_preferred":[
        "Holdenstedt"
    ],
    "wof:name":"Holdenstedt",
    "wof:placetype":"neighbourhood"
},
  "geometry": {"coordinates":[10.52748,52.92567],"type":"Point"}
}