{
  "type": "Feature",
  "properties": {
    "gn:admin1_code":"2",
    "gn:admin2_code":"91.0",
    "gn:admin3_code":"9183.0",
    "gn:admin4_code":"9183128.0",
    "gn:asciiname":"Oberaham",
    "gn:country_code":"DE",
    "gn:dem":407,
    "gn:feature_class":"P",
    "gn:feature_code":"PPL",
    "gn:name":"Oberaham",
    "gn:population":0,
    "gn:timezone":"Europe/Berlin",
    "iso:country":"DE",
    "wof:name":"Oberaham",
    "wof:placetype":"neighbourhood"
},
  "geometry": {"coordinates":[12.53333,48.25],"type":"Point"}
}