{
  "type": "Feature",
  "properties": {
    "gn:admin1_code":"1",
    "gn:admin2_code":"84.0",
    "gn:admin3_code":"8436.0",
    "gn:admin4_code":"8436004.0",
    "gn:asciiname":"Schmiddis",
    "gn:country_code":"DE",
    "gn:dem":677,
    "gn:feature_class":"P",
    "gn:feature_code":"PPL",
    "gn:name":"Schmiddis",
    "gn:population":0,
    "gn:timezone":"Europe/Berlin",
    "iso:country":"DE",
    "name:chv_x_preferred":[
        "\u0428\u043c\u0438\u0434\u0434\u0438\u0441"
    ],
    "name:deu_x_preferred":[
        "Schmiddis"
    ],
    "wof:name":"Schmiddis",
    "wof:placetype":"neighbourhood"
},
  "geometry": {"coordinates":[10.04999,47.94404],"type":"Point"}
}