{
  "type": "Feature",
  "properties": {
    "gn:admin1_code":"1",
    "gn:admin2_code":"83.0",
    "gn:admin3_code":"8325.0",
    "gn:admin4_code":"8325051.0",
    "gn:asciiname":"Ober-Staigenbach",
    "gn:country_code":"DE",
    "gn:dem":616,
    "gn:feature_class":"P",
    "gn:feature_code":"PPL",
    "gn:name":"Ober-Staigenbach",
    "gn:population":0,
    "gn:timezone":"Europe/Berlin",
    "iso:country":"DE",
    "name:und_x_variant":[
        "Ober Steigenbach"
    ],
    "wof:name":"Ober-Staigenbach",
    "wof:placetype":"neighbourhood"
},
  "geometry": {"coordinates":[8.35074,48.24989],"type":"Point"}
}