{
  "type": "Feature",
  "properties": {
    "gn:admin1_code":"1",
    "gn:admin2_code":"82.0",
    "gn:admin3_code":"8225.0",
    "gn:admin4_code":"8225114.0",
    "gn:asciiname":"Oberwittstadt",
    "gn:country_code":"DE",
    "gn:dem":311,
    "gn:feature_class":"P",
    "gn:feature_code":"PPL",
    "gn:name":"Oberwittstadt",
    "gn:population":0,
    "gn:timezone":"Europe/Berlin",
    "iso:country":"DE",
    "wof:name":"Oberwittstadt",
    "wof:placetype":"neighbourhood"
},
  "geometry": {"coordinates":[9.55888,49.42985],"type":"Point"}
}