{
  "type": "Feature",
  "properties": {
    "gn:admin1_code":"5",
    "gn:admin2_code":"65.0",
    "gn:admin3_code":"6534.0",
    "gn:admin4_code":"6534005.0",
    "gn:asciiname":"Oberdieten",
    "gn:country_code":"DE",
    "gn:dem":357,
    "gn:feature_class":"P",
    "gn:feature_code":"PPL",
    "gn:name":"Oberdieten",
    "gn:population":0,
    "gn:timezone":"Europe/Berlin",
    "iso:country":"DE",
    "wof:name":"Oberdieten",
    "wof:placetype":"neighbourhood"
},
  "geometry": {"coordinates":[8.415,50.8576],"type":"Point"}
}