{
  "type": "Feature",
  "properties": {
    "gn:admin1_code":"5",
    "gn:admin2_code":"66.0",
    "gn:admin3_code":"6635.0",
    "gn:admin4_code":"6635013.0",
    "gn:asciiname":"Roemershausen",
    "gn:country_code":"DE",
    "gn:dem":331,
    "gn:feature_class":"P",
    "gn:feature_code":"PPL",
    "gn:name":"R\u00f6mershausen",
    "gn:population":0,
    "gn:timezone":"Europe/Berlin",
    "iso:country":"DE",
    "wof:name":"Roemershausen",
    "wof:placetype":"neighbourhood"
},
  "geometry": {"coordinates":[8.8999,51.03508],"type":"Point"}
}