{
  "type": "Feature",
  "properties": {
    "gn:admin1_code":"1",
    "gn:admin2_code":"84.0",
    "gn:admin3_code":"8436.0",
    "gn:admin4_code":"8436085.0",
    "gn:asciiname":"Maierhof",
    "gn:country_code":"DE",
    "gn:dem":627,
    "gn:feature_class":"P",
    "gn:feature_code":"PPL",
    "gn:name":"Maierhof",
    "gn:population":0,
    "gn:timezone":"Europe/Berlin",
    "iso:country":"DE",
    "wof:name":"Maierhof",
    "wof:placetype":"neighbourhood"
},
  "geometry": {"coordinates":[9.78575,47.80895],"type":"Point"}
}