{
  "type": "Feature",
  "properties": {
    "iso:country":"DE",
    "name:deu_x_preferred":[
        "Niedergorbitz"
    ],
    "name:unk_x_variant":[
        "Niedergorbitz"
    ],
    "qs:gn_fcode":"PPLX",
    "qs:gn_local":0,
    "qs:gn_namadm1":"13",
    "qs:gn_name":"Niedergorbitz",
    "qs:local_max":13108,
    "qs:local_sum":52556,
    "qs:localhoods":61,
    "qs:name":"Niedergorbitz",
    "qs:name_adm0":"Deutschland",
    "qs:name_adm1":"Sachsen",
    "qs:name_adm2":"Kreisfreie Stadt Dresden",
    "qs:name_lau":"Wilsdruffer Vorstadt/Seevorstadt-West",
    "qs:name_local":"Dresden",
    "qs:photo_max":1436,
    "qs:photo_sum":6567,
    "qs:placetype":"Suburb",
    "qs:quad_count":75,
    "qs:woe_adm0":23424829,
    "qs:woe_adm1":2345493,
    "qs:woe_adm2":12596943,
    "qs:woe_lau":26822148,
    "qs:woe_local":645686,
    "qs:woe_ver":"7.10.0",
    "wof:lang":[
        "ger"
    ],
    "wof:name":"Niedergorbitz",
    "wof:placetype":"neighbourhood"
},
  "geometry": {"coordinates":[13.678366,51.043986],"type":"Point"}
}