{
  "type": "Feature",
  "properties": {
    "gn:admin1_code":"12",
    "gn:admin2_code":"0.0",
    "gn:admin3_code":"13075.0",
    "gn:admin4_code":"13075067.0",
    "gn:asciiname":"Kyritz",
    "gn:country_code":"DE",
    "gn:dem":28,
    "gn:feature_class":"P",
    "gn:feature_code":"PPL",
    "gn:name":"Kyritz",
    "gn:population":0,
    "gn:timezone":"Europe/Berlin",
    "iso:country":"DE",
    "name:ara_x_preferred":[
        "\u0643\u0648\u0631\u064a\u062a\u0633"
    ],
    "name:azb_x_preferred":[
        "\u06a9\u06cc\u0631\u06cc\u062a\u0632"
    ],
    "name:ceb_x_preferred":[
        "Kyritz"
    ],
    "name:dan_x_preferred":[
        "Kyritz"
    ],
    "name:deu_x_preferred":[
        "Kyritz"
    ],
    "name:epo_x_preferred":[
        "Kyritz"
    ],
    "name:fas_x_preferred":[
        "\u06a9\u06cc\u0631\u06cc\u062a\u0632"
    ],
    "name:fra_x_preferred":[
        "Kyritz"
    ],
    "name:hun_x_preferred":[
        "Kyritz"
    ],
    "name:hye_x_preferred":[
        "\u053f\u056b\u0580\u056b\u0581"
    ],
    "name:ita_x_preferred":[
        "Kyritz"
    ],
    "name:lav_x_preferred":[
        "K\u012brica"
    ],
    "name:mkd_x_preferred":[
        "\u041a\u0438\u0440\u0438\u0446"
    ],
    "name:msa_x_preferred":[
        "Kyritz"
    ],
    "name:nds_x_preferred":[
        "Kyritz"
    ],
    "name:nld_x_preferred":[
        "Kyritz"
    ],
    "name:pol_x_preferred":[
        "Kyritz"
    ],
    "name:ron_x_preferred":[
        "Kyritz"
    ],
    "name:rus_x_preferred":[
        "\u041a\u0438\u0440\u0438\u0446"
    ],
    "name:spa_x_preferred":[
        "Kyritz"
    ],
    "name:srp_x_preferred":[
        "\u041a\u0438\u0440\u0438\u0446"
    ],
    "name:swe_x_preferred":[
        "Kyritz"
    ],
    "name:tur_x_preferred":[
        "Kyritz"
    ],
    "name:ukr_x_preferred":[
        "\u041a\u0438\u0440\u0456\u0446"
    ],
    "name:uzb_x_preferred":[
        "Kyritz"
    ],
    "name:vie_x_preferred":[
        "Kyritz"
    ],
    "name:vol_x_preferred":[
        "Kyritz"
    ],
    "name:war_x_preferred":[
        "Kyritz"
    ],
    "name:zho_x_preferred":[
        "\u57fa\u91cc\u8328"
    ],
    "wof:name":"Kyritz",
    "wof:placetype":"neighbourhood"
},
  "geometry": {"coordinates":[14.34187,53.36524],"type":"Point"}
}