{
  "type": "Feature",
  "properties": {
    "gn:admin1_code":"2",
    "gn:admin2_code":"97.0",
    "gn:admin3_code":"9778.0",
    "gn:admin4_code":"9778137.0",
    "gn:asciiname":"Hofen",
    "gn:country_code":"DE",
    "gn:dem":560,
    "gn:feature_class":"P",
    "gn:feature_code":"PPL",
    "gn:name":"H\u00f6fen",
    "gn:population":0,
    "gn:timezone":"Europe/Berlin",
    "iso:country":"DE",
    "name:deu_x_preferred":[
        "Hofen"
    ],
    "name:epo_x_preferred":[
        "Hofen"
    ],
    "name:ita_x_preferred":[
        "Hofen"
    ],
    "name:pol_x_preferred":[
        "Hofen"
    ],
    "wof:name":"Hofen",
    "wof:placetype":"neighbourhood"
},
  "geometry": {"coordinates":[10.6885,48.16162],"type":"Point"}
}