{
  "type": "Feature",
  "properties": {
    "gn:gn_country":"DE",
    "gn:gn_fcode":"PPLA4",
    "gn:gn_pop":584,
    "gn:population":584,
    "iso:country":"DE",
    "name:baq_x_preferred":[
        "Seesbach"
    ],
    "name:chi_x_preferred":[
        "\u585e\u65af\u5df4\u8d6b"
    ],
    "name:dut_x_preferred":[
        "Seesbach"
    ],
    "name:eng_x_preferred":[
        "Seesbach"
    ],
    "name:epo_x_preferred":[
        "Seesbach"
    ],
    "name:fre_x_preferred":[
        "Seesbach"
    ],
    "name:ger_x_preferred":[
        "Seesbach"
    ],
    "name:hun_x_preferred":[
        "Seesbach"
    ],
    "name:ita_x_preferred":[
        "Seesbach"
    ],
    "name:jpn_x_preferred":[
        "\u30bc\u30fc\u30b9\u30d0\u30c3\u30cf"
    ],
    "name:may_x_preferred":[
        "Seesbach"
    ],
    "name:per_x_preferred":[
        "\u0632\u0633\u0628\u0627\u062e"
    ],
    "name:pol_x_preferred":[
        "Seesbach"
    ],
    "name:por_x_preferred":[
        "Seesbach"
    ],
    "name:rum_x_preferred":[
        "Seesbach"
    ],
    "name:rus_x_preferred":[
        "\u0417\u0435\u0435\u0441\u0431\u0430\u0445"
    ],
    "name:srp_x_preferred":[
        "\u0417\u0435\u0441\u0431\u0430\u0445"
    ],
    "name:ukr_x_preferred":[
        "\u0417\u0435\u0441\u0431\u0430\u0445"
    ],
    "name:uzb_x_preferred":[
        "Seesbach"
    ],
    "name:vie_x_preferred":[
        "Seesbach"
    ],
    "name:vol_x_preferred":[
        "Seesbach"
    ],
    "name:war_x_preferred":[
        "Seesbach"
    ],
    "qs_pg:aaroncc":"DE",
    "qs_pg:gn_country":"DE",
    "qs_pg:gn_fcode":"PPLA4",
    "qs_pg:gn_pop":584,
    "qs_pg:name":"Seesbach",
    "qs_pg:photos_9r":0,
    "qs_pg:photos_sr":0,
    "qs_pg:pop_sr":2,
    "qs_pg:qs_pg_placetype":"locality",
    "wof:name":"Seesbach",
    "wof:placetype":"locality",
    "wof:population":584
},
  "geometry": {"coordinates":[7.55,49.85],"type":"Point"}
}