{
  "type": "Feature",
  "properties": {
    "gn:admin1_code":"2",
    "gn:admin2_code":"92.0",
    "gn:admin3_code":"9275.0",
    "gn:admin4_code":"9275125.0",
    "gn:asciiname":"Holzhauser",
    "gn:country_code":"DE",
    "gn:dem":458,
    "gn:feature_class":"P",
    "gn:feature_code":"PPL",
    "gn:name":"Holzh\u00e4user",
    "gn:population":0,
    "gn:timezone":"Europe/Berlin",
    "iso:country":"DE",
    "wof:name":"Holzhauser",
    "wof:placetype":"neighbourhood"
},
  "geometry": {"coordinates":[13.11667,48.48333],"type":"Point"}
}