{
  "type": "Feature",
  "properties": {
    "gn:admin1_code":"13.0",
    "gn:admin2_code":"00",
    "gn:admin3_code":"14522.0",
    "gn:admin4_code":"14522450.0",
    "gn:asciiname":"Wutzschwitz",
    "gn:country_code":"DE",
    "gn:dem":145,
    "gn:feature_class":"P",
    "gn:feature_code":"PPL",
    "gn:name":"Wutzschwitz",
    "gn:population":0,
    "gn:timezone":"Europe/Berlin",
    "iso:country":"DE",
    "wof:name":"Wutzschwitz",
    "wof:placetype":"neighbourhood"
},
  "geometry": {"coordinates":[13.14982,51.19744],"type":"Point"}
}