{
  "type": "Feature",
  "properties": {
    "gn:admin1_code":"2",
    "gn:admin2_code":"93.0",
    "gn:admin3_code":"9375.0",
    "gn:admin4_code":"9375211.0",
    "gn:asciiname":"Sillen",
    "gn:country_code":"DE",
    "gn:dem":443,
    "gn:feature_class":"P",
    "gn:feature_code":"PPL",
    "gn:name":"Sillen",
    "gn:population":0,
    "gn:timezone":"Europe/Berlin",
    "iso:country":"DE",
    "name:fin_x_preferred":[
        "Sillen"
    ],
    "name:nno_x_preferred":[
        "Sillen"
    ],
    "name:nor_x_preferred":[
        "Sillen"
    ],
    "name:swe_x_preferred":[
        "Sillen"
    ],
    "wof:name":"Sillen",
    "wof:placetype":"neighbourhood"
},
  "geometry": {"coordinates":[11.96703,49.1086],"type":"Point"}
}