{
  "type": "Feature",
  "properties": {
    "gn:admin1_code":"2",
    "gn:admin2_code":"91.0",
    "gn:admin3_code":"9182.0",
    "gn:admin4_code":"9182137.0",
    "gn:asciiname":"Holzolling",
    "gn:country_code":"DE",
    "gn:dem":586,
    "gn:feature_class":"P",
    "gn:feature_code":"PPL",
    "gn:name":"Holzolling",
    "gn:population":0,
    "gn:timezone":"Europe/Berlin",
    "iso:country":"DE",
    "wof:name":"Holzolling",
    "wof:placetype":"neighbourhood"
},
  "geometry": {"coordinates":[11.8273,47.87082],"type":"Point"}
}