{
  "type": "Feature",
  "properties": {
    "gn:admin1_code":"1",
    "gn:admin2_code":"81.0",
    "gn:admin3_code":"8125.0",
    "gn:admin4_code":"8125039.0",
    "gn:asciiname":"Dornbach",
    "gn:country_code":"DE",
    "gn:dem":298,
    "gn:feature_class":"P",
    "gn:feature_code":"PPL",
    "gn:name":"Dornbach",
    "gn:population":0,
    "gn:timezone":"Europe/Berlin",
    "iso:country":"DE",
    "name:ceb_x_preferred":[
        "Dornbach"
    ],
    "name:deu_x_preferred":[
        "Dornbach"
    ],
    "name:swe_x_preferred":[
        "Dornbach"
    ],
    "wof:name":"Dornbach",
    "wof:placetype":"neighbourhood"
},
  "geometry": {"coordinates":[9.17356,49.30802],"type":"Point"}
}