{
  "type": "Feature",
  "properties": {
    "gn:admin1_code":"8",
    "gn:admin2_code":"0.0",
    "gn:admin3_code":"7336.0",
    "gn:admin4_code":"7336003.0",
    "gn:asciiname":"Muehlbach an der Glan",
    "gn:country_code":"DE",
    "gn:dem":209,
    "gn:feature_class":"P",
    "gn:feature_code":"PPL",
    "gn:name":"M\u00fchlbach an der Glan",
    "gn:population":0,
    "gn:timezone":"Europe/Berlin",
    "iso:country":"DE",
    "name:und_x_variant":[
        "M\u00fchlbach",
        "M\u00fchlbach an der Glan"
    ],
    "wof:name":"Muehlbach an der Glan",
    "wof:placetype":"neighbourhood"
},
  "geometry": {"coordinates":[7.46612,49.54251],"type":"Point"}
}