{
  "type": "Feature",
  "properties": {
    "gn:admin1_code":"1",
    "gn:admin2_code":"83.0",
    "gn:admin3_code":"8315.0",
    "gn:admin4_code":"8315056.0",
    "gn:asciiname":"Katzental",
    "gn:country_code":"DE",
    "gn:dem":486,
    "gn:feature_class":"P",
    "gn:feature_code":"PPLL",
    "gn:name":"Katzental",
    "gn:population":0,
    "gn:timezone":"Europe/Berlin",
    "iso:country":"DE",
    "wof:name":"Katzental",
    "wof:placetype":"neighbourhood"
},
  "geometry": {"coordinates":[7.84386,47.9375],"type":"Point"}
}