{
  "type": "Feature",
  "properties": {
    "gn:admin1_code":"2",
    "gn:admin2_code":"91.0",
    "gn:admin3_code":"9187.0",
    "gn:admin4_code":"9187125.0",
    "gn:asciiname":"Meisham",
    "gn:country_code":"DE",
    "gn:dem":534,
    "gn:feature_class":"P",
    "gn:feature_code":"PPL",
    "gn:name":"Meisham",
    "gn:population":0,
    "gn:timezone":"Europe/Berlin",
    "iso:country":"DE",
    "wof:name":"Meisham",
    "wof:placetype":"neighbourhood"
},
  "geometry": {"coordinates":[12.3761,47.94251],"type":"Point"}
}