{
  "type": "Feature",
  "properties": {
    "gn:admin1_code":"1",
    "gn:admin2_code":"84.0",
    "gn:admin3_code":"8436.0",
    "gn:admin4_code":"8436069.0",
    "gn:asciiname":"Hintermoos",
    "gn:country_code":"DE",
    "gn:dem":633,
    "gn:feature_class":"P",
    "gn:feature_code":"PPL",
    "gn:name":"Hintermoos",
    "gn:population":0,
    "gn:timezone":"Europe/Berlin",
    "iso:country":"DE",
    "wof:name":"Hintermoos",
    "wof:placetype":"neighbourhood"
},
  "geometry": {"coordinates":[9.70959,47.80022],"type":"Point"}
}