{
  "type": "Feature",
  "properties": {
    "gn:country":"DE",
    "gn:fcode":"PPLX",
    "gn:population":0,
    "iso:country":"DE",
    "name:deu_x_preferred":[
        "Scharhof"
    ],
    "name:eng_x_preferred":[
        "Scharhof"
    ],
    "qs_pg:aaroncc":"DE",
    "qs_pg:gn_country":"DE",
    "qs_pg:gn_fcode":"PPLX",
    "qs_pg:gn_pop":0,
    "qs_pg:name":"Scharhof",
    "qs_pg:name_adm0":"Deutschland",
    "qs_pg:name_adm1":"Baden-W\u00fcrttemberg",
    "qs_pg:photos":19,
    "qs_pg:photos_1k":4,
    "qs_pg:photos_9k":1,
    "qs_pg:photos_9r":1,
    "qs_pg:photos_all":19,
    "qs_pg:photos_sr":1,
    "qs_pg:pop_sr":0,
    "qs_pg:qs_pg_placetype":"neighbourhood",
    "qs_pg:qs_pg_placetype_gp":"Suburb",
    "qs_pg:woe_adm0":23424829,
    "woe:adm0_id":23424829,
    "woe:name_adm0":"Deutschland",
    "woe:name_adm1":"Baden-W\u00fcrttemberg",
    "woe:placetype":"Suburb",
    "wof:name":"Scharhof",
    "wof:placetype":"neighbourhood"
},
  "geometry": {"coordinates":[8.44918,49.56028],"type":"Point"}
}