{
  "type": "Feature",
  "properties": {
    "gn:admin1_code":"2",
    "gn:admin2_code":"91.0",
    "gn:admin3_code":"9187.0",
    "gn:admin4_code":"9187131.0",
    "gn:asciiname":"Oberflintsbach",
    "gn:country_code":"DE",
    "gn:dem":490,
    "gn:feature_class":"P",
    "gn:feature_code":"PPL",
    "gn:name":"Oberflintsbach",
    "gn:population":0,
    "gn:timezone":"Europe/Berlin",
    "iso:country":"DE",
    "wof:name":"Oberflintsbach",
    "wof:placetype":"neighbourhood"
},
  "geometry": {"coordinates":[12.13333,47.71667],"type":"Point"}
}