{
  "type": "Feature",
  "properties": {
    "gn:admin1_code":"12",
    "gn:admin2_code":"0.0",
    "gn:admin3_code":"13073.0",
    "gn:admin4_code":"13073030.0",
    "gn:asciiname":"Ruschvitz",
    "gn:country_code":"DE",
    "gn:dem":12,
    "gn:feature_class":"P",
    "gn:feature_code":"PPL",
    "gn:name":"Ruschvitz",
    "gn:population":0,
    "gn:timezone":"Europe/Berlin",
    "iso:country":"DE",
    "wof:name":"Ruschvitz",
    "wof:placetype":"neighbourhood"
},
  "geometry": {"coordinates":[13.51164,54.56936999999999],"type":"Point"}
}