{
  "type": "Feature",
  "properties": {
    "gn:admin1_code":"8.0",
    "gn:admin2_code":"00",
    "gn:admin3_code":"7235.0",
    "gn:admin4_code":"7235146.0",
    "gn:asciiname":"Wellen",
    "gn:country_code":"DE",
    "gn:dem":172,
    "gn:feature_class":"P",
    "gn:feature_code":"PPLA4",
    "gn:name":"Wellen",
    "gn:population":762,
    "gn:timezone":"Europe/Berlin",
    "iso:country":"DE",
    "wof:name":"Wellen",
    "wof:placetype":"locality",
    "wof:population":762
},
  "geometry": {"coordinates":[6.43333,49.66667],"type":"Point"}
}