{
  "type": "Feature",
  "properties": {
    "gn:admin1_code":"2.0",
    "gn:admin2_code":"97.0",
    "gn:admin3_code":"9777.0",
    "gn:admin4_code":"9777124.0",
    "gn:asciiname":"Beschaunen",
    "gn:country_code":"DE",
    "gn:dem":815,
    "gn:feature_class":"P",
    "gn:feature_code":"PPL",
    "gn:name":"Beschaunen",
    "gn:population":0,
    "gn:timezone":"Europe/Berlin",
    "iso:country":"DE",
    "wof:name":"Beschaunen",
    "wof:placetype":"neighbourhood"
},
  "geometry": {"coordinates":[10.46377,47.8975],"type":"Point"}
}