{
  "type": "Feature",
  "properties": {
    "gn:admin1_code":"1",
    "gn:admin2_code":"83.0",
    "gn:admin3_code":"8326.0",
    "gn:admin4_code":"8326054.0",
    "gn:asciiname":"Schonbachle",
    "gn:country_code":"DE",
    "gn:dem":994,
    "gn:feature_class":"P",
    "gn:feature_code":"PPLL",
    "gn:name":"Sch\u00f6nb\u00e4chle",
    "gn:population":0,
    "gn:timezone":"Europe/Berlin",
    "iso:country":"DE",
    "wof:name":"Schonbachle",
    "wof:placetype":"neighbourhood"
},
  "geometry": {"coordinates":[8.21987,48.08665],"type":"Point"}
}