{
  "type": "Feature",
  "properties": {
    "gn:admin1_code":"2",
    "gn:admin2_code":"95.0",
    "gn:admin3_code":"9561.0",
    "gn:admin4_code":"9561000.0",
    "gn:asciiname":"Wallersdorf",
    "gn:country_code":"DE",
    "gn:dem":432,
    "gn:feature_class":"P",
    "gn:feature_code":"PPL",
    "gn:name":"Wallersdorf",
    "gn:population":0,
    "gn:timezone":"Europe/Berlin",
    "iso:country":"DE",
    "name:ara_x_preferred":[
        "\u0641\u0627\u0644\u0627\u0631\u0633\u062f\u0648\u0631\u0641"
    ],
    "name:ceb_x_preferred":[
        "Wallersdorf"
    ],
    "name:dan_x_preferred":[
        "Wallersdorf"
    ],
    "name:deu_x_preferred":[
        "Wallersdorf"
    ],
    "name:epo_x_preferred":[
        "Wallersdorf"
    ],
    "name:eus_x_preferred":[
        "Wallersdorf"
    ],
    "name:fas_x_preferred":[
        "\u0648\u0627\u0644\u0631\u0633\u062f\u0648\u0631\u0641"
    ],
    "name:fra_x_preferred":[
        "Wallersdorf"
    ],
    "name:hun_x_preferred":[
        "Wallersdorf"
    ],
    "name:hye_x_preferred":[
        "\u054e\u0561\u056c\u0565\u0580\u057d\u0564\u0578\u0580\u0586"
    ],
    "name:ita_x_preferred":[
        "Wallersdorf"
    ],
    "name:lmo_x_preferred":[
        "Wallersdorf"
    ],
    "name:msa_x_preferred":[
        "Wallersdorf"
    ],
    "name:nld_x_preferred":[
        "Wallersdorf"
    ],
    "name:pol_x_preferred":[
        "Wallersdorf"
    ],
    "name:por_x_preferred":[
        "Wallersdorf"
    ],
    "name:ron_x_preferred":[
        "Wallersdorf"
    ],
    "name:rus_x_preferred":[
        "\u0412\u0430\u043b\u043b\u0435\u0440\u0441\u0434\u043e\u0440\u0444"
    ],
    "name:spa_x_preferred":[
        "Wallersdorf"
    ],
    "name:srp_x_preferred":[
        "\u0412\u0430\u043b\u0435\u0440\u0441\u0434\u043e\u0440\u0444"
    ],
    "name:ukr_x_preferred":[
        "\u0412\u0430\u043b\u043b\u0435\u0440\u0441\u0434\u043e\u0440\u0444"
    ],
    "name:uzb_x_preferred":[
        "Wallersdorf"
    ],
    "name:vol_x_preferred":[
        "Wallersdorf"
    ],
    "name:war_x_preferred":[
        "Wallersdorf"
    ],
    "name:zho_x_preferred":[
        "\u74e6\u52d2\u65af\u591a\u592b"
    ],
    "wof:name":"Wallersdorf",
    "wof:placetype":"neighbourhood"
},
  "geometry": {"coordinates":[10.61653,49.27003],"type":"Point"}
}