{
  "type": "Feature",
  "properties": {
    "gn:admin1_code":"13",
    "gn:admin2_code":"0.0",
    "gn:admin3_code":"14625.0",
    "gn:admin4_code":"14625640.0",
    "gn:asciiname":"Rachlau",
    "gn:country_code":"DE",
    "gn:dem":129,
    "gn:feature_class":"P",
    "gn:feature_code":"PPL",
    "gn:name":"Rachlau",
    "gn:population":0,
    "gn:timezone":"Europe/Berlin",
    "iso:country":"DE",
    "name:hsb_x_preferred":[
        "Rachlow"
    ],
    "name:und_x_variant":[
        "Hoske-Rachlau",
        "Rachlau"
    ],
    "wof:name":"Rachlau",
    "wof:placetype":"neighbourhood"
},
  "geometry": {"coordinates":[14.27952,51.35523],"type":"Point"}
}