{
  "type": "Feature",
  "properties": {
    "gn:admin1_code":"6",
    "gn:admin2_code":"0.0",
    "gn:admin3_code":"3257.0",
    "gn:admin4_code":"3257003.0",
    "gn:asciiname":"Raden",
    "gn:country_code":"DE",
    "gn:dem":263,
    "gn:feature_class":"P",
    "gn:feature_code":"PPL",
    "gn:name":"Raden",
    "gn:population":0,
    "gn:timezone":"Europe/Berlin",
    "iso:country":"DE",
    "name:kor_x_preferred":[
        "\ub098\uc804\uce60\uae30"
    ],
    "name:rus_x_preferred":[
        "\u0420\u0430\u0434\u044d\u043d"
    ],
    "wof:name":"Raden",
    "wof:placetype":"neighbourhood"
},
  "geometry": {"coordinates":[9.30782,52.2299],"type":"Point"}
}