{
  "type": "Feature",
  "properties": {
    "gn:admin1_code":"2",
    "gn:admin2_code":"91.0",
    "gn:admin3_code":"9187.0",
    "gn:admin4_code":"9187168.0",
    "gn:asciiname":"Hotzelsberg",
    "gn:country_code":"DE",
    "gn:dem":636,
    "gn:feature_class":"P",
    "gn:feature_code":"PPL",
    "gn:name":"H\u00f6tzelsberg",
    "gn:population":0,
    "gn:timezone":"Europe/Berlin",
    "iso:country":"DE",
    "wof:name":"Hotzelsberg",
    "wof:placetype":"neighbourhood"
},
  "geometry": {"coordinates":[12.31438,47.88299],"type":"Point"}
}