{
  "type": "Feature",
  "properties": {
    "gn:admin1_code":"2",
    "gn:admin2_code":"95.0",
    "gn:admin3_code":"9572.0",
    "gn:admin4_code":"9572111.0",
    "gn:asciiname":"Heppstadt",
    "gn:country_code":"DE",
    "gn:dem":292,
    "gn:feature_class":"P",
    "gn:feature_code":"PPL",
    "gn:name":"Heppst\u00e4dt",
    "gn:population":0,
    "gn:timezone":"Europe/Berlin",
    "iso:country":"DE",
    "wof:name":"Heppstadt",
    "wof:placetype":"neighbourhood"
},
  "geometry": {"coordinates":[10.90831,49.6924],"type":"Point"}
}