{
  "type": "Feature",
  "properties": {
    "gn:admin1_code":"2",
    "gn:admin2_code":"96.0",
    "gn:admin3_code":"9674.0",
    "gn:admin4_code":"9674171.0",
    "gn:asciiname":"Durrenried",
    "gn:country_code":"DE",
    "gn:dem":311,
    "gn:feature_class":"P",
    "gn:feature_code":"PPL",
    "gn:name":"D\u00fcrrenried",
    "gn:population":0,
    "gn:timezone":"Europe/Berlin",
    "iso:country":"DE",
    "wof:name":"Durrenried",
    "wof:placetype":"neighbourhood"
},
  "geometry": {"coordinates":[10.74324,50.21809],"type":"Point"}
}