{
  "type": "Feature",
  "properties": {
    "gn:gn_country":"DE",
    "gn:gn_fcode":"ADM4",
    "gn:gn_pop":272,
    "gn:population":267,
    "iso:country":"DE",
    "name:baq_x_preferred":[
        "Berschweiler bei Kirn"
    ],
    "name:chi_x_preferred":[
        "\u57fa\u5c14\u6069\u9644\u8fd1\u8d1d\u5c14\u65bd\u9b4f\u83b1\u5c14"
    ],
    "name:dut_x_preferred":[
        "Berschweiler bei Kirn"
    ],
    "name:eng_x_preferred":[
        "Berschweiler bei Kirn"
    ],
    "name:epo_x_preferred":[
        "Berschweiler bei Kirn"
    ],
    "name:fre_x_preferred":[
        "Berschweiler bei Kirn"
    ],
    "name:ger_x_preferred":[
        "Berschweiler bei Kirn"
    ],
    "name:hun_x_preferred":[
        "Berschweiler bei Kirn"
    ],
    "name:ita_x_preferred":[
        "Berschweiler bei Kirn"
    ],
    "name:jpn_x_preferred":[
        "\u30d0\u30b7\u30e5\u30f4\u30a1\u30a4\u30e9\u30fc\u30fb\u30d0\u30a4\u30fb\u30ad\u30eb\u30f3"
    ],
    "name:kaz_x_preferred":[
        "\u0411\u0435\u0440\u0448\u0432\u0430\u0439\u043b\u0435\u0440-\u041a\u0438\u0440\u043d"
    ],
    "name:kir_x_preferred":[
        "\u0411\u0435\u0440\u0448\u0432\u0430\u0439\u043b\u0435\u0440-\u041a\u0438\u0440\u043d"
    ],
    "name:may_x_preferred":[
        "Berschweiler bei Kirn"
    ],
    "name:pol_x_preferred":[
        "Berschweiler bei Kirn"
    ],
    "name:por_x_preferred":[
        "Berschweiler bei Kirn"
    ],
    "name:rum_x_preferred":[
        "Berschweiler bei Kirn"
    ],
    "name:rus_x_preferred":[
        "\u0411\u0435\u0440\u0448\u0432\u0430\u0439\u043b\u0435\u0440-\u041a\u0438\u0440\u043d"
    ],
    "name:spa_x_preferred":[
        "Berschweiler bei Kirn"
    ],
    "name:srp_x_preferred":[
        "\u0411\u0435\u0440\u0448\u0432\u0430\u0458\u043b\u0435\u0440 \u0431\u0430\u0458 \u041a\u0438\u0440\u043d"
    ],
    "name:ukr_x_preferred":[
        "\u0411\u0435\u0440\u0448\u0432\u0430\u0439\u043b\u0435\u0440-\u0431\u0430\u0439-\u041a\u0456\u0440\u043d"
    ],
    "name:uzb_x_preferred":[
        "Berschweiler bei Kirn"
    ],
    "name:vie_x_preferred":[
        "Berschweiler bei Kirn"
    ],
    "name:vol_x_preferred":[
        "Berschweiler bei Kirn"
    ],
    "name:war_x_preferred":[
        "Berschweiler bei Kirn"
    ],
    "qs_pg:aaroncc":"DE",
    "qs_pg:gn_country":"DE",
    "qs_pg:gn_fcode":"ADM4",
    "qs_pg:gn_pop":272,
    "qs_pg:name":"Berschweiler bei Kirn",
    "qs_pg:name_adm0":"Deutschland",
    "qs_pg:name_adm1":"Rheinland-Pfalz",
    "qs_pg:photos_9r":0,
    "qs_pg:photos_sr":0,
    "qs_pg:pop_sr":2,
    "qs_pg:qs_pg_placetype":"locality",
    "qs_pg:qs_pg_placetype_gp":"Town",
    "qs_pg:woe_adm0":23424829,
    "woe:adm0_id":23424829,
    "woe:name_adm0":"Deutschland",
    "woe:name_adm1":"Rheinland-Pfalz",
    "woe:placetype":"Town",
    "wof:name":"Berschweiler bei Kirn",
    "wof:placetype":"locality",
    "wof:population":267
},
  "geometry": {"coordinates":[7.38333,49.7667],"type":"Point"}
}