{
  "type": "Feature",
  "properties": {
    "gn:admin1_code":"2",
    "gn:admin2_code":"97.0",
    "gn:admin3_code":"9780.0",
    "gn:admin4_code":"9780139.0",
    "gn:asciiname":"Hochweiler",
    "gn:country_code":"DE",
    "gn:dem":923,
    "gn:feature_class":"P",
    "gn:feature_code":"PPL",
    "gn:name":"Hochweiler",
    "gn:population":0,
    "gn:timezone":"Europe/Berlin",
    "iso:country":"DE",
    "wof:name":"Hochweiler",
    "wof:placetype":"neighbourhood"
},
  "geometry": {"coordinates":[10.30008,47.48092000000001],"type":"Point"}
}