{
  "type": "Feature",
  "properties": {
    "gn:admin1_code":"1.0",
    "gn:admin2_code":"81.0",
    "gn:admin3_code":"8128.0",
    "gn:admin4_code":"8128061.0",
    "gn:asciiname":"Birkenfeld",
    "gn:country_code":"DE",
    "gn:dem":346,
    "gn:feature_class":"P",
    "gn:feature_code":"PPL",
    "gn:name":"Birkenfeld",
    "gn:population":0,
    "gn:timezone":"Europe/Berlin",
    "iso:country":"DE",
    "name:ara_x_preferred":[
        "\u0628\u064a\u0631\u0643\u0646\u0641\u0644\u062f"
    ],
    "name:azb_x_preferred":[
        "\u0628\u06cc\u0631\u06a9\u0646\u0641\u0644\u062f"
    ],
    "name:bul_x_preferred":[
        "\u0411\u0438\u0440\u043a\u0435\u043d\u0444\u0435\u043b\u0434"
    ],
    "name:dan_x_preferred":[
        "Birkenfeld"
    ],
    "name:deu_x_preferred":[
        "Birkenfeld"
    ],
    "name:epo_x_preferred":[
        "Birkenfeld"
    ],
    "name:eus_x_preferred":[
        "Birkenfeld"
    ],
    "name:fas_x_preferred":[
        "\u0628\u06cc\u0631\u06a9\u0646\u0641\u0644\u062f"
    ],
    "name:fra_x_preferred":[
        "Birkenfeld"
    ],
    "name:hun_x_preferred":[
        "Birkenfeld"
    ],
    "name:ita_x_preferred":[
        "Birkenfeld"
    ],
    "name:jpn_x_preferred":[
        "\u30d3\u30eb\u30b1\u30f3\u30d5\u30a7\u30eb\u30c8"
    ],
    "name:kat_x_preferred":[
        "\u10d1\u10d8\u10e0\u10d9\u10d4\u10dc\u10e4\u10d4\u10da\u10d3\u10d8"
    ],
    "name:kaz_x_preferred":[
        "\u0411\u0438\u0440\u043a\u0435\u043d\u0444\u0435\u043b\u044c\u0434"
    ],
    "name:kir_x_preferred":[
        "\u0411\u0438\u0440\u043a\u0435\u043d\u0444\u0435\u043b\u044c\u0434"
    ],
    "name:msa_x_preferred":[
        "Birkenfeld"
    ],
    "name:nld_x_preferred":[
        "Birkenfeld"
    ],
    "name:pol_x_preferred":[
        "Birkenfeld"
    ],
    "name:por_x_preferred":[
        "Birkenfeld"
    ],
    "name:ron_x_preferred":[
        "Birkenfeld"
    ],
    "name:rus_x_preferred":[
        "\u0411\u0438\u0440\u043a\u0435\u043d\u0444\u0435\u043b\u044c\u0434"
    ],
    "name:spa_x_preferred":[
        "Birkenfeld"
    ],
    "name:srp_x_preferred":[
        "\u0411\u0438\u0440\u043a\u0435\u043d\u0444\u0435\u043b\u0434"
    ],
    "name:swe_x_preferred":[
        "Birkenfeld"
    ],
    "name:tur_x_preferred":[
        "Birkenfeld"
    ],
    "name:ukr_x_preferred":[
        "\u0411\u0456\u0440\u043a\u0435\u043d\u0444\u0435\u043b\u044c\u0434"
    ],
    "name:uzb_x_preferred":[
        "Birkenfeld"
    ],
    "name:vie_x_preferred":[
        "Birkenfeld"
    ],
    "name:vol_x_preferred":[
        "Birkenfeld"
    ],
    "name:war_x_preferred":[
        "Birkenfeld"
    ],
    "name:zho_x_preferred":[
        "\u6bd4\u80af\u8d39\u5c14\u5fb7"
    ],
    "wof:name":"Birkenfeld",
    "wof:placetype":"neighbourhood"
},
  "geometry": {"coordinates":[9.55758,49.58363],"type":"Point"}
}