{
  "type": "Feature",
  "properties": {
    "iso:country":"DE",
    "wof:name":"Wahnheide",
    "wof:placetype":"neighbourhood"
},
  "geometry": {"coordinates":[7.10403127880789,50.86271526314922],"type":"Point"}
}