{
  "type": "Feature",
  "properties": {
    "gn:admin1_code":"2",
    "gn:admin2_code":"95.0",
    "gn:admin3_code":"9577.0",
    "gn:admin4_code":"9577177.0",
    "gn:asciiname":"Schmalwiesen",
    "gn:country_code":"DE",
    "gn:dem":431,
    "gn:feature_class":"P",
    "gn:feature_code":"PPL",
    "gn:name":"Schmalwiesen",
    "gn:population":0,
    "gn:timezone":"Europe/Berlin",
    "iso:country":"DE",
    "wof:name":"Schmalwiesen",
    "wof:placetype":"neighbourhood"
},
  "geometry": {"coordinates":[10.95182,49.0458],"type":"Point"}
}