{
  "type": "Feature",
  "properties": {
    "gn:admin1_code":"2.0",
    "gn:admin2_code":"091",
    "gn:admin3_code":"9175.0",
    "gn:admin4_code":"9175121.0",
    "gn:asciiname":"Zinneberg",
    "gn:country_code":"DE",
    "gn:dem":610,
    "gn:feature_class":"P",
    "gn:feature_code":"PPL",
    "gn:name":"Zinneberg",
    "gn:population":0,
    "gn:timezone":"Europe/Berlin",
    "iso:country":"DE",
    "wof:name":"Zinneberg",
    "wof:placetype":"neighbourhood"
},
  "geometry": {"coordinates":[11.8818,47.99366],"type":"Point"}
}