{
  "type": "Feature",
  "properties": {
    "gn:admin1_code":"1",
    "gn:admin2_code":"83.0",
    "gn:admin3_code":"8325.0",
    "gn:admin4_code":"8325015.0",
    "gn:asciiname":"Harthausen",
    "gn:country_code":"DE",
    "gn:dem":565,
    "gn:feature_class":"P",
    "gn:feature_code":"PPL",
    "gn:name":"Harthausen",
    "gn:population":0,
    "gn:timezone":"Europe/Berlin",
    "iso:country":"DE",
    "wof:name":"Harthausen",
    "wof:placetype":"neighbourhood"
},
  "geometry": {"coordinates":[8.62963,48.26183],"type":"Point"}
}