{
  "type": "Feature",
  "properties": {
    "gn:admin1_code":"2",
    "gn:admin2_code":"91.0",
    "gn:admin3_code":"9187.0",
    "gn:admin4_code":"9187148.0",
    "gn:asciiname":"Kurz",
    "gn:country_code":"DE",
    "gn:dem":523,
    "gn:feature_class":"P",
    "gn:feature_code":"PPL",
    "gn:name":"Kurz",
    "gn:population":0,
    "gn:timezone":"Europe/Berlin",
    "iso:country":"DE",
    "wof:name":"Kurz",
    "wof:placetype":"neighbourhood"
},
  "geometry": {"coordinates":[12.15972,47.61583],"type":"Point"}
}