{
  "type": "Feature",
  "properties": {
    "gn:admin1_code":"12",
    "gn:admin2_code":"0.0",
    "gn:admin3_code":"13076.0",
    "gn:admin4_code":"13076164.0",
    "gn:asciiname":"Lenschow",
    "gn:country_code":"DE",
    "gn:dem":65,
    "gn:feature_class":"P",
    "gn:feature_code":"PPL",
    "gn:name":"Lenschow",
    "gn:population":0,
    "gn:timezone":"Europe/Berlin",
    "iso:country":"DE",
    "wof:name":"Lenschow",
    "wof:placetype":"neighbourhood"
},
  "geometry": {"coordinates":[11.92034,53.54622],"type":"Point"}
}