{
  "type": "Feature",
  "properties": {
    "gn:admin1_code":"2",
    "gn:admin2_code":"93.0",
    "gn:admin3_code":"9373.0",
    "gn:admin4_code":"9373146.0",
    "gn:asciiname":"Kerkhofen",
    "gn:country_code":"DE",
    "gn:dem":437,
    "gn:feature_class":"P",
    "gn:feature_code":"PPL",
    "gn:name":"Kerkhofen",
    "gn:population":0,
    "gn:timezone":"Europe/Berlin",
    "iso:country":"DE",
    "wof:name":"Kerkhofen",
    "wof:placetype":"neighbourhood"
},
  "geometry": {"coordinates":[11.39531,49.17132],"type":"Point"}
}