{
  "type": "Feature",
  "properties": {
    "gn:country":"DE",
    "gn:fcode":"PPL",
    "gn:population":1124,
    "iso:country":"DE",
    "name:als_x_preferred":[
        "Lochau"
    ],
    "name:bul_x_preferred":[
        "\u041b\u043e\u0445\u0430\u0443"
    ],
    "name:cat_x_preferred":[
        "Lochau"
    ],
    "name:ceb_x_preferred":[
        "Lochau"
    ],
    "name:deu_x_preferred":[
        "Lochau"
    ],
    "name:fas_x_preferred":[
        "\u0644\u062e\u0648"
    ],
    "name:fra_x_preferred":[
        "Lochau"
    ],
    "name:fur_x_preferred":[
        "Lochau"
    ],
    "name:hun_x_preferred":[
        "Lochau"
    ],
    "name:ita_x_preferred":[
        "Lochau"
    ],
    "name:lmo_x_preferred":[
        "Lochau"
    ],
    "name:nld_x_preferred":[
        "Lochau"
    ],
    "name:nno_x_preferred":[
        "Lochau"
    ],
    "name:pol_x_preferred":[
        "Lochau"
    ],
    "name:ron_x_preferred":[
        "Lochau"
    ],
    "name:rus_x_preferred":[
        "\u041b\u043e\u0445\u0430\u0443"
    ],
    "name:slk_x_preferred":[
        "Lochau"
    ],
    "name:spa_x_preferred":[
        "Lochau"
    ],
    "name:swe_x_preferred":[
        "Lochau"
    ],
    "name:tur_x_preferred":[
        "Lochau"
    ],
    "name:ukr_x_preferred":[
        "\u041b\u043e\u0445\u0430\u0443"
    ],
    "name:uzb_x_preferred":[
        "Lochau"
    ],
    "name:vol_x_preferred":[
        "Lochau"
    ],
    "name:war_x_preferred":[
        "Lochau"
    ],
    "qs_pg:aaroncc":"DE",
    "qs_pg:gn_country":"DE",
    "qs_pg:gn_fcode":"PPL",
    "qs_pg:gn_pop":1124,
    "qs_pg:name":"Lochau",
    "qs_pg:name_adm0":"Deutschland",
    "qs_pg:name_adm1":"Sachsen-Anhalt",
    "qs_pg:photos_9k":1,
    "qs_pg:photos_9r":1,
    "qs_pg:photos_all":1,
    "qs_pg:photos_sr":0,
    "qs_pg:pop_sr":3,
    "qs_pg:qs_pg_placetype":"locality",
    "qs_pg:qs_pg_placetype_gp":"Town",
    "qs_pg:woe_adm0":23424829,
    "woe:adm0_id":23424829,
    "woe:name_adm0":"Deutschland",
    "woe:name_adm1":"Sachsen-Anhalt",
    "woe:placetype":"Town",
    "wof:name":"Lochau",
    "wof:placetype":"neighbourhood",
    "wof:population":1124
},
  "geometry": {"coordinates":[12.05303,51.39738],"type":"Point"}
}