{
  "type": "Feature",
  "properties": {
    "gn:admin1_code":"2.0",
    "gn:admin2_code":"92.0",
    "gn:admin3_code":"9279.0",
    "gn:admin4_code":"9279134.0",
    "gn:asciiname":"Breitenloh",
    "gn:country_code":"DE",
    "gn:dem":465,
    "gn:feature_class":"P",
    "gn:feature_code":"PPL",
    "gn:name":"Breitenloh",
    "gn:population":0,
    "gn:timezone":"Europe/Berlin",
    "iso:country":"DE",
    "wof:name":"Breitenloh",
    "wof:placetype":"neighbourhood"
},
  "geometry": {"coordinates":[12.6288,48.5158],"type":"Point"}
}