{
  "type": "Feature",
  "properties": {
    "gn:admin1_code":"2",
    "gn:admin2_code":"92.0",
    "gn:admin3_code":"9276.0",
    "gn:admin4_code":"9276138.0",
    "gn:asciiname":"Reinhartsmais",
    "gn:country_code":"DE",
    "gn:dem":554,
    "gn:feature_class":"P",
    "gn:feature_code":"PPL",
    "gn:name":"Reinhartsmais",
    "gn:population":0,
    "gn:timezone":"Europe/Berlin",
    "iso:country":"DE",
    "wof:name":"Reinhartsmais",
    "wof:placetype":"neighbourhood"
},
  "geometry": {"coordinates":[13.10029,48.94865],"type":"Point"}
}