{
  "type": "Feature",
  "properties": {
    "gn:admin1_code":"15",
    "gn:admin2_code":"0.0",
    "gn:admin3_code":"16076.0",
    "gn:admin4_code":"16076003.0",
    "gn:asciiname":"Pohlitz",
    "gn:country_code":"DE",
    "gn:dem":184,
    "gn:feature_class":"P",
    "gn:feature_code":"PPL",
    "gn:name":"Pohlitz",
    "gn:population":0,
    "gn:timezone":"Europe/Berlin",
    "iso:country":"DE",
    "wof:name":"Pohlitz",
    "wof:placetype":"neighbourhood"
},
  "geometry": {"coordinates":[12.02525,50.93905],"type":"Point"}
}