{
  "type": "Feature",
  "properties": {
    "gn:admin1_code":"13",
    "gn:admin2_code":"0.0",
    "gn:admin3_code":"14627.0",
    "gn:admin4_code":"14627250.0",
    "gn:asciiname":"Linz",
    "gn:country_code":"DE",
    "gn:dem":148,
    "gn:feature_class":"P",
    "gn:feature_code":"PPL",
    "gn:name":"Linz",
    "gn:population":0,
    "gn:timezone":"Europe/Berlin",
    "iso:country":"DE",
    "wof:name":"Linz",
    "wof:placetype":"neighbourhood"
},
  "geometry": {"coordinates":[13.7342,51.34252],"type":"Point"}
}