{
  "type": "Feature",
  "properties": {
    "gn:admin1_code":"6",
    "gn:admin2_code":"0.0",
    "gn:admin3_code":"3256.0",
    "gn:admin4_code":"3256023.0",
    "gn:asciiname":"Sudholz",
    "gn:country_code":"DE",
    "gn:dem":58,
    "gn:feature_class":"P",
    "gn:feature_code":"PPL",
    "gn:name":"Sudholz",
    "gn:population":0,
    "gn:timezone":"Europe/Berlin",
    "iso:country":"DE",
    "wof:name":"Sudholz",
    "wof:placetype":"neighbourhood"
},
  "geometry": {"coordinates":[9.00055,52.64463000000001],"type":"Point"}
}