{
  "type": "Feature",
  "properties": {
    "gn:admin1_code":"2",
    "gn:admin2_code":"93.0",
    "gn:admin3_code":"9372.0",
    "gn:admin4_code":"9372164.0",
    "gn:asciiname":"Tragenschwand",
    "gn:country_code":"DE",
    "gn:dem":473,
    "gn:feature_class":"P",
    "gn:feature_code":"PPL",
    "gn:name":"Tragenschwand",
    "gn:population":0,
    "gn:timezone":"Europe/Berlin",
    "iso:country":"DE",
    "wof:name":"Tragenschwand",
    "wof:placetype":"neighbourhood"
},
  "geometry": {"coordinates":[12.67554,49.11062],"type":"Point"}
}