{
  "type": "Feature",
  "properties": {
    "gn:admin1_code":"12.0",
    "gn:admin2_code":"0.0",
    "gn:admin3_code":"13071.0",
    "gn:admin4_code":"13071164.0",
    "gn:asciiname":"Bredenfelde",
    "gn:country_code":"DE",
    "gn:dem":100,
    "gn:feature_class":"P",
    "gn:feature_code":"PPL",
    "gn:name":"Bredenfelde",
    "gn:population":0,
    "gn:timezone":"Europe/Berlin",
    "iso:country":"DE",
    "name:deu_x_preferred":[
        "Bredenfelde"
    ],
    "name:epo_x_preferred":[
        "Bredenfelde"
    ],
    "name:fas_x_preferred":[
        "\u0628\u0631\u062f\u0646\u0641\u0644\u062f\u0647"
    ],
    "name:fra_x_preferred":[
        "Bredenfelde"
    ],
    "name:hun_x_preferred":[
        "Bredenfelde"
    ],
    "name:ita_x_preferred":[
        "Bredenfelde"
    ],
    "name:mkd_x_preferred":[
        "\u0411\u0440\u0435\u0434\u0435\u043d\u0444\u0435\u043b\u0434\u0435"
    ],
    "name:msa_x_preferred":[
        "Bredenfelde"
    ],
    "name:nld_x_preferred":[
        "Bredenfelde"
    ],
    "name:pol_x_preferred":[
        "Bredenfelde"
    ],
    "name:ron_x_preferred":[
        "Bredenfelde"
    ],
    "name:rus_x_preferred":[
        "\u0411\u0440\u0435\u0434\u0435\u043d\u0444\u0435\u043b\u044c\u0434\u0435"
    ],
    "name:spa_x_preferred":[
        "Bredenfelde"
    ],
    "name:srp_x_preferred":[
        "\u0411\u0440\u0435\u0434\u0435\u043d\u0444\u0435\u043b\u0434\u0435"
    ],
    "name:ukr_x_preferred":[
        "\u0411\u0440\u0435\u0434\u0435\u043d\u0444\u0435\u043b\u044c\u0434\u0435"
    ],
    "name:uzb_x_preferred":[
        "Bredenfelde"
    ],
    "name:vie_x_preferred":[
        "Bredenfelde"
    ],
    "name:vol_x_preferred":[
        "Bredenfelde"
    ],
    "name:war_x_preferred":[
        "Bredenfelde"
    ],
    "name:zho_x_preferred":[
        "\u5e03\u96f7\u767b\u8d39\u5c14\u5fb7"
    ],
    "wof:name":"Bredenfelde",
    "wof:placetype":"neighbourhood"
},
  "geometry": {"coordinates":[13.42887,53.42018],"type":"Point"}
}