{
  "type": "Feature",
  "properties": {
    "gn:admin1_code":"6.0",
    "gn:admin2_code":"0.0",
    "gn:admin3_code":"3159.0",
    "gn:admin4_code":"3159017.0",
    "gn:asciiname":"Bonaforth",
    "gn:cc2":"DE",
    "gn:country_code":"DE",
    "gn:dem":142,
    "gn:feature_class":"P",
    "gn:feature_code":"PPL",
    "gn:name":"Bonaforth",
    "gn:population":0,
    "gn:timezone":"Europe/Berlin",
    "iso:country":"DE",
    "name:und_x_variant":[
        "Bonafort"
    ],
    "wof:name":"Bonaforth",
    "wof:placetype":"neighbourhood"
},
  "geometry": {"coordinates":[9.6266,51.40038],"type":"Point"}
}