{
  "type": "Feature",
  "properties": {
    "gn:admin1_code":"12.0",
    "gn:admin2_code":"0.0",
    "gn:admin3_code":"13075.0",
    "gn:admin4_code":"13075131.0",
    "gn:asciiname":"Hoelkebaum",
    "gn:country_code":"DE",
    "gn:dem":13,
    "gn:feature_class":"P",
    "gn:feature_code":"PPL",
    "gn:name":"H\u00f6lkebaum",
    "gn:population":0,
    "gn:timezone":"Europe/Berlin",
    "iso:country":"DE",
    "wof:name":"Hoelkebaum",
    "wof:placetype":"neighbourhood"
},
  "geometry": {"coordinates":[14.08333,53.61666999999999],"type":"Point"}
}