{
  "type": "Feature",
  "properties": {
    "gn:admin1_code":"2",
    "gn:admin2_code":"93.0",
    "gn:admin3_code":"9374.0",
    "gn:admin4_code":"9374129.0",
    "gn:asciiname":"Oberlenkenreuth",
    "gn:country_code":"DE",
    "gn:dem":532,
    "gn:feature_class":"P",
    "gn:feature_code":"PPL",
    "gn:name":"Oberlenkenreuth",
    "gn:population":0,
    "gn:timezone":"Europe/Berlin",
    "iso:country":"DE",
    "wof:name":"Oberlenkenreuth",
    "wof:placetype":"neighbourhood"
},
  "geometry": {"coordinates":[11.65149,49.80014],"type":"Point"}
}