{
  "type": "Feature",
  "properties": {
    "gn:admin1_code":"7",
    "gn:admin2_code":"53.0",
    "gn:admin3_code":"5378.0",
    "gn:admin4_code":"5378012.0",
    "gn:asciiname":"Viersbach",
    "gn:country_code":"DE",
    "gn:dem":213,
    "gn:feature_class":"P",
    "gn:feature_code":"PPL",
    "gn:name":"Viersbach",
    "gn:population":0,
    "gn:timezone":"Europe/Berlin",
    "iso:country":"DE",
    "wof:name":"Viersbach",
    "wof:placetype":"neighbourhood"
},
  "geometry": {"coordinates":[7.21232,51.0644],"type":"Point"}
}