{
  "type": "Feature",
  "properties": {
    "gn:admin1_code":"2",
    "gn:admin2_code":"91.0",
    "gn:admin3_code":"9178.0",
    "gn:admin4_code":"9178115.0",
    "gn:asciiname":"Haarland",
    "gn:country_code":"DE",
    "gn:dem":468,
    "gn:feature_class":"P",
    "gn:feature_code":"PPL",
    "gn:name":"Haarland",
    "gn:population":0,
    "gn:timezone":"Europe/Berlin",
    "iso:country":"DE",
    "wof:name":"Haarland",
    "wof:placetype":"neighbourhood"
},
  "geometry": {"coordinates":[11.76043,48.48465],"type":"Point"}
}