{
  "type": "Feature",
  "properties": {
    "gn:admin1_code":"1.0",
    "gn:admin2_code":"81.0",
    "gn:admin3_code":"8127.0",
    "gn:admin4_code":"8127071.0",
    "gn:asciiname":"Brettenfeld",
    "gn:country_code":"DE",
    "gn:dem":416,
    "gn:feature_class":"P",
    "gn:feature_code":"PPL",
    "gn:name":"Brettenfeld",
    "gn:population":0,
    "gn:timezone":"Europe/Berlin",
    "iso:country":"DE",
    "wof:name":"Brettenfeld",
    "wof:placetype":"neighbourhood"
},
  "geometry": {"coordinates":[10.01999,49.25801],"type":"Point"}
}