{
  "type": "Feature",
  "properties": {
    "gn:admin1_code":"11",
    "gn:admin2_code":"0.0",
    "gn:admin3_code":"12072.0",
    "gn:admin4_code":"12072297.0",
    "gn:asciiname":"Lindow",
    "gn:country_code":"DE",
    "gn:dem":90,
    "gn:feature_class":"P",
    "gn:feature_code":"PPL",
    "gn:name":"Lindow",
    "gn:population":0,
    "gn:timezone":"Europe/Berlin",
    "iso:country":"DE",
    "name:ceb_x_preferred":[
        "Lindow"
    ],
    "name:deu_x_preferred":[
        "Lindow"
    ],
    "name:fra_x_preferred":[
        "Lindow"
    ],
    "name:ita_x_preferred":[
        "Lindow"
    ],
    "name:pol_x_preferred":[
        "Lindow"
    ],
    "wof:name":"Lindow",
    "wof:placetype":"neighbourhood"
},
  "geometry": {"coordinates":[12.92278,52.01211],"type":"Point"}
}