{
  "type": "Feature",
  "properties": {
    "iso:country":"DE",
    "name:deu_x_colloquial":[
        "Sudholz",
        "Suedholz"
    ],
    "name:deu_x_preferred":[
        "S\u00fcdholz"
    ],
    "qs:gn_fcode":"PPL",
    "qs:gn_local":0,
    "qs:gn_namadm1":"07",
    "qs:gn_name":"Sudholz",
    "qs:local_max":1333,
    "qs:local_sum":7580,
    "qs:localhoods":22,
    "qs:name":"S\u00fcdholz",
    "qs:name_adm0":"Deutschland",
    "qs:name_adm1":"Nordrhein-Westfalen",
    "qs:name_adm2":"Stadtkreis Bochum",
    "qs:name_lau":"Stadtteil H\u00f6ntrop",
    "qs:name_local":"Bochum",
    "qs:photo_max":20,
    "qs:photo_sum":110,
    "qs:placetype":"Suburb",
    "qs:quad_count":20,
    "qs:woe_adm0":23424829,
    "qs:woe_adm1":2345487,
    "qs:woe_adm2":12597004,
    "qs:woe_lau":26821960,
    "qs:woe_local":639679,
    "qs:woe_ver":"7.10.0",
    "wof:lang":[
        "ger"
    ],
    "wof:name":"S\u00fcdholz",
    "wof:placetype":"neighbourhood"
},
  "geometry": {"coordinates":[7.16798,51.462968],"type":"Point"}
}