{
  "type": "Feature",
  "properties": {
    "gn:country":"DE",
    "gn:fcode":"PPL",
    "gn:population":0,
    "iso:country":"DE",
    "name:ceb_x_preferred":[
        "Bruchhausen"
    ],
    "name:deu_x_preferred":[
        "Bruchhausen"
    ],
    "name:epo_x_preferred":[
        "Bruchhausen"
    ],
    "name:eus_x_preferred":[
        "Bruchhausen"
    ],
    "name:fas_x_preferred":[
        "\u0628\u0631\u0648\u062e\u0647\u0627\u0648\u0632\u0646"
    ],
    "name:fra_x_preferred":[
        "Bruchhausen"
    ],
    "name:hun_x_preferred":[
        "Bruchhausen"
    ],
    "name:ita_x_preferred":[
        "Bruchhausen"
    ],
    "name:kaz_x_preferred":[
        "\u0411\u0440\u0443\u0445\u0433\u0430\u0443\u0437\u0435\u043d"
    ],
    "name:kir_x_preferred":[
        "\u0411\u0440\u0443\u0445\u0433\u0430\u0443\u0437\u0435\u043d"
    ],
    "name:msa_x_preferred":[
        "Bruchhausen"
    ],
    "name:nld_x_preferred":[
        "Bruchhausen"
    ],
    "name:pol_x_preferred":[
        "Bruchhausen"
    ],
    "name:por_x_preferred":[
        "Bruchhausen"
    ],
    "name:ron_x_preferred":[
        "Bruchhausen"
    ],
    "name:rus_x_preferred":[
        "\u0411\u0440\u0443\u0445\u0445\u0430\u0443\u0437\u0435\u043d"
    ],
    "name:spa_x_preferred":[
        "Bruchhausen"
    ],
    "name:srp_x_preferred":[
        "\u0411\u0440\u0443\u0445\u0430\u0443\u0437\u0435\u043d"
    ],
    "name:ukr_x_preferred":[
        "\u0411\u0440\u0443\u0445\u0433\u0430\u0443\u0437\u0435\u043d"
    ],
    "name:uzb_x_preferred":[
        "Bruchhausen"
    ],
    "name:vie_x_preferred":[
        "Bruchhausen"
    ],
    "name:vol_x_preferred":[
        "Bruchhausen"
    ],
    "name:war_x_preferred":[
        "Bruchhausen"
    ],
    "name:zho_x_preferred":[
        "\u5e03\u9c81\u8d6b\u8c6a\u68ee"
    ],
    "qs_pg:aaroncc":"DE",
    "qs_pg:gn_country":"DE",
    "qs_pg:gn_fcode":"PPL",
    "qs_pg:gn_pop":0,
    "qs_pg:name":"Bruchhausen",
    "qs_pg:name_adm0":"Deutschland",
    "qs_pg:name_adm1":"Nordrhein-Westfalen",
    "qs_pg:photos":116,
    "qs_pg:photos_1k":24,
    "qs_pg:photos_9k":1,
    "qs_pg:photos_9r":3,
    "qs_pg:photos_all":116,
    "qs_pg:photos_sr":3,
    "qs_pg:pop_sr":0,
    "qs_pg:qs_pg_placetype":"locality",
    "qs_pg:qs_pg_placetype_gp":"Town",
    "qs_pg:woe_adm0":23424829,
    "woe:adm0_id":23424829,
    "woe:name_adm0":"Deutschland",
    "woe:name_adm1":"Nordrhein-Westfalen",
    "woe:placetype":"Town",
    "wof:name":"Bruchhausen",
    "wof:placetype":"neighbourhood"
},
  "geometry": {"coordinates":[8.53176,51.3181],"type":"Point"}
}