{
  "type": "Feature",
  "properties": {
    "gn:admin1_code":"7",
    "gn:admin2_code":"51.0",
    "gn:admin3_code":"5154.0",
    "gn:admin4_code":"5154012.0",
    "gn:asciiname":"Schmalkuhl",
    "gn:country_code":"DE",
    "gn:dem":30,
    "gn:feature_class":"P",
    "gn:feature_code":"PPLL",
    "gn:name":"Schmalkuhl",
    "gn:population":0,
    "gn:timezone":"Europe/Berlin",
    "iso:country":"DE",
    "wof:name":"Schmalkuhl",
    "wof:placetype":"neighbourhood"
},
  "geometry": {"coordinates":[6.25422,51.50859000000001],"type":"Point"}
}