{
  "type": "Feature",
  "properties": {
    "gn:admin1_code":"6",
    "gn:admin2_code":"0.0",
    "gn:admin3_code":"3360.0",
    "gn:admin4_code":"3360024.0",
    "gn:asciiname":"Rassau",
    "gn:country_code":"DE",
    "gn:dem":64,
    "gn:feature_class":"P",
    "gn:feature_code":"PPL",
    "gn:name":"Rassau",
    "gn:population":0,
    "gn:timezone":"Europe/Berlin",
    "iso:country":"DE",
    "name:ceb_x_preferred":[
        "Rassau"
    ],
    "name:cor_x_preferred":[
        "Rasa"
    ],
    "name:cym_x_preferred":[
        "Rasa"
    ],
    "name:eus_x_preferred":[
        "Rassau"
    ],
    "name:fas_x_preferred":[
        "\u0631\u0633\u0627"
    ],
    "name:gla_x_preferred":[
        "Rasa"
    ],
    "name:gle_x_preferred":[
        "Rasa"
    ],
    "name:swe_x_preferred":[
        "Rassau"
    ],
    "wof:name":"Rassau",
    "wof:placetype":"neighbourhood"
},
  "geometry": {"coordinates":[10.69004,52.95717],"type":"Point"}
}