{
  "type": "Feature",
  "properties": {
    "gn:admin1_code":"2",
    "gn:admin2_code":"91.0",
    "gn:admin3_code":"9185.0",
    "gn:admin4_code":"9185123.0",
    "gn:asciiname":"Honighausen",
    "gn:country_code":"DE",
    "gn:dem":395,
    "gn:feature_class":"P",
    "gn:feature_code":"PPL",
    "gn:name":"H\u00f6nighausen",
    "gn:population":0,
    "gn:timezone":"Europe/Berlin",
    "iso:country":"DE",
    "wof:name":"Honighausen",
    "wof:placetype":"neighbourhood"
},
  "geometry": {"coordinates":[11.35029,48.6468],"type":"Point"}
}