{
  "type": "Feature",
  "properties": {
    "gn:admin1_code":"2",
    "gn:admin2_code":"92.0",
    "gn:admin3_code":"9271.0",
    "gn:admin4_code":"9271125.0",
    "gn:asciiname":"Schwanenkirchen",
    "gn:country_code":"DE",
    "gn:dem":380,
    "gn:feature_class":"P",
    "gn:feature_code":"PPL",
    "gn:name":"Schwanenkirchen",
    "gn:population":0,
    "gn:timezone":"Europe/Berlin",
    "iso:country":"DE",
    "wof:name":"Schwanenkirchen",
    "wof:placetype":"neighbourhood"
},
  "geometry": {"coordinates":[13.10399,48.74849],"type":"Point"}
}