{
  "type": "Feature",
  "properties": {
    "gn:admin1_code":"15",
    "gn:admin2_code":"0.0",
    "gn:admin3_code":"16066.0",
    "gn:admin4_code":"16066063.0",
    "gn:asciiname":"Reichenbach",
    "gn:country_code":"DE",
    "gn:dem":350,
    "gn:feature_class":"P",
    "gn:feature_code":"PPL",
    "gn:name":"Reichenbach",
    "gn:population":0,
    "gn:timezone":"Europe/Berlin",
    "iso:country":"DE",
    "wof:name":"Reichenbach",
    "wof:placetype":"neighbourhood"
},
  "geometry": {"coordinates":[10.4662,50.75387],"type":"Point"}
}