{
  "type": "Feature",
  "properties": {
    "gn:admin1_code":"6.0",
    "gn:admin2_code":"0.0",
    "gn:admin3_code":"3359.0",
    "gn:admin4_code":"3359035.0",
    "gn:asciiname":"Landesbrueck",
    "gn:country_code":"DE",
    "gn:dem":0,
    "gn:feature_class":"P",
    "gn:feature_code":"PPL",
    "gn:name":"Landesbr\u00fcck",
    "gn:population":0,
    "gn:timezone":"Europe/Berlin",
    "iso:country":"DE",
    "wof:name":"Landesbrueck",
    "wof:placetype":"neighbourhood"
},
  "geometry": {"coordinates":[9.26864,53.80558000000001],"type":"Point"}
}