{
  "type": "Feature",
  "properties": {
    "gn:admin1_code":"2",
    "gn:admin2_code":"91.0",
    "gn:admin3_code":"9190.0",
    "gn:admin4_code":"9190114.0",
    "gn:asciiname":"Gruiwang",
    "gn:country_code":"DE",
    "gn:dem":760,
    "gn:feature_class":"P",
    "gn:feature_code":"PPL",
    "gn:name":"Gruiwang",
    "gn:population":0,
    "gn:timezone":"Europe/Berlin",
    "iso:country":"DE",
    "name:deu_x_preferred":[
        "Greuwang"
    ],
    "wof:name":"Gruiwang",
    "wof:placetype":"neighbourhood"
},
  "geometry": {"coordinates":[10.80682,47.73978],"type":"Point"}
}