{
  "type": "Feature",
  "properties": {
    "gn:admin1_code":"1",
    "gn:admin2_code":"84.0",
    "gn:admin3_code":"8436.0",
    "gn:admin4_code":"8436055.0",
    "gn:asciiname":"Raggen",
    "gn:country_code":"DE",
    "gn:dem":707,
    "gn:feature_class":"P",
    "gn:feature_code":"PPL",
    "gn:name":"Raggen",
    "gn:population":0,
    "gn:timezone":"Europe/Berlin",
    "iso:country":"DE",
    "wof:name":"Raggen",
    "wof:placetype":"neighbourhood"
},
  "geometry": {"coordinates":[10.12317,47.81829000000001],"type":"Point"}
}