{
  "type": "Feature",
  "properties": {
    "gn:admin1_code":"1",
    "gn:admin2_code":"81.0",
    "gn:admin3_code":"8119.0",
    "gn:admin4_code":"8119024.0",
    "gn:asciiname":"Schonbronn",
    "gn:country_code":"DE",
    "gn:dem":487,
    "gn:feature_class":"P",
    "gn:feature_code":"PPL",
    "gn:name":"Sch\u00f6nbronn",
    "gn:population":0,
    "gn:timezone":"Europe/Berlin",
    "iso:country":"DE",
    "wof:name":"Schonbronn",
    "wof:placetype":"neighbourhood"
},
  "geometry": {"coordinates":[9.58572,49.04625],"type":"Point"}
}