{
  "type": "Feature",
  "properties": {
    "gn:admin1_code":"2",
    "gn:admin2_code":"96.0",
    "gn:admin3_code":"9675.0",
    "gn:admin4_code":"9675117.0",
    "gn:asciiname":"Schnepfenbach",
    "gn:country_code":"DE",
    "gn:dem":235,
    "gn:feature_class":"P",
    "gn:feature_code":"PPL",
    "gn:name":"Schnepfenbach",
    "gn:population":0,
    "gn:timezone":"Europe/Berlin",
    "iso:country":"DE",
    "name:deu_x_preferred":[
        "Schnepfenbach"
    ],
    "wof:name":"Schnepfenbach",
    "wof:placetype":"neighbourhood"
},
  "geometry": {"coordinates":[10.14934,49.83273],"type":"Point"}
}