{
  "type": "Feature",
  "properties": {
    "gn:admin1_code":"13",
    "gn:admin2_code":"0.0",
    "gn:admin3_code":"14522.0",
    "gn:admin4_code":"14522080.0",
    "gn:asciiname":"Schallhausen",
    "gn:country_code":"DE",
    "gn:dem":225,
    "gn:feature_class":"P",
    "gn:feature_code":"PPL",
    "gn:name":"Schallhausen",
    "gn:population":0,
    "gn:timezone":"Europe/Berlin",
    "iso:country":"DE",
    "wof:name":"Schallhausen",
    "wof:placetype":"neighbourhood"
},
  "geometry": {"coordinates":[13.18602,51.14655],"type":"Point"}
}