{
  "type": "Feature",
  "properties": {
    "gn:admin1_code":"2.0",
    "gn:admin2_code":"095",
    "gn:admin3_code":"9574.0",
    "gn:admin4_code":"9574139.0",
    "gn:asciiname":"Winn",
    "gn:country_code":"DE",
    "gn:dem":398,
    "gn:feature_class":"P",
    "gn:feature_code":"PPL",
    "gn:name":"Winn",
    "gn:population":0,
    "gn:timezone":"Europe/Berlin",
    "iso:country":"DE",
    "name:deu_x_preferred":[
        "Winn"
    ],
    "name:ita_x_preferred":[
        "Winn"
    ],
    "name:pol_x_preferred":[
        "Winn"
    ],
    "wof:name":"Winn",
    "wof:placetype":"neighbourhood"
},
  "geometry": {"coordinates":[11.34192,49.43972],"type":"Point"}
}