{
  "type": "Feature",
  "properties": {
    "gn:admin1_code":"7",
    "gn:admin2_code":"53.0",
    "gn:admin3_code":"5366.0",
    "gn:admin4_code":"5366032.0",
    "gn:asciiname":"Holzmuelheim",
    "gn:country_code":"DE",
    "gn:dem":418,
    "gn:feature_class":"P",
    "gn:feature_code":"PPL",
    "gn:name":"Holzm\u00fclheim",
    "gn:population":0,
    "gn:timezone":"Europe/Berlin",
    "iso:country":"DE",
    "wof:name":"Holzmuelheim",
    "wof:placetype":"neighbourhood"
},
  "geometry": {"coordinates":[6.73572,50.50022],"type":"Point"}
}