{
  "type": "Feature",
  "properties": {
    "gn:admin1_code":"6",
    "gn:admin2_code":"0.0",
    "gn:admin3_code":"3158.0",
    "gn:admin4_code":"3158040.0",
    "gn:asciiname":"Gross Biewende",
    "gn:country_code":"DE",
    "gn:dem":99,
    "gn:feature_class":"P",
    "gn:feature_code":"PPL",
    "gn:name":"Gro\u00df Biewende",
    "gn:population":0,
    "gn:timezone":"Europe/Berlin",
    "iso:country":"DE",
    "wof:name":"Gross Biewende",
    "wof:placetype":"neighbourhood"
},
  "geometry": {"coordinates":[10.62687,52.0987],"type":"Point"}
}