{
  "type": "Feature",
  "properties": {
    "gn:admin1_code":"2",
    "gn:admin2_code":"94.0",
    "gn:admin3_code":"9471.0",
    "gn:admin4_code":"9471191.0",
    "gn:asciiname":"Seehoflein",
    "gn:country_code":"DE",
    "gn:dem":271,
    "gn:feature_class":"P",
    "gn:feature_code":"PPL",
    "gn:name":"Seeh\u00f6flein",
    "gn:population":0,
    "gn:timezone":"Europe/Berlin",
    "iso:country":"DE",
    "wof:name":"Seehoflein",
    "wof:placetype":"neighbourhood"
},
  "geometry": {"coordinates":[10.8357,49.87052],"type":"Point"}
}