{
  "type": "Feature",
  "properties": {
    "gn:admin1_code":"11",
    "gn:admin2_code":"0.0",
    "gn:admin3_code":"12073.0",
    "gn:admin4_code":"12073572.0",
    "gn:asciiname":"Gandenitz",
    "gn:cc2":"DE",
    "gn:country_code":"DE",
    "gn:dem":64,
    "gn:feature_class":"P",
    "gn:feature_code":"PPL",
    "gn:name":"Gandenitz",
    "gn:population":0,
    "gn:timezone":"Europe/Berlin",
    "iso:country":"DE",
    "name:und_x_variant":[
        "Gradenitz"
    ],
    "wof:name":"Gandenitz",
    "wof:placetype":"neighbourhood"
},
  "geometry": {"coordinates":[13.44091,53.17353000000001],"type":"Point"}
}