{
  "type": "Feature",
  "properties": {
    "gn:gn_country":"DE",
    "gn:gn_fcode":"PPLA4",
    "gn:gn_pop":295,
    "gn:population":295,
    "iso:country":"DE",
    "name:baq_x_preferred":[
        "Christiansholm"
    ],
    "name:chi_x_preferred":[
        "\u5e0c\u91cc\u65af\u8482\u5b89\u65af\u970d\u5c14\u59c6"
    ],
    "name:dan_x_preferred":[
        "Christiansholm"
    ],
    "name:dut_x_preferred":[
        "Christiansholm"
    ],
    "name:eng_x_preferred":[
        "Christiansholm"
    ],
    "name:epo_x_preferred":[
        "Christiansholm"
    ],
    "name:fre_x_preferred":[
        "Christiansholm"
    ],
    "name:ger_x_preferred":[
        "Christiansholm"
    ],
    "name:hun_x_preferred":[
        "Christiansholm"
    ],
    "name:ita_x_preferred":[
        "Christiansholm"
    ],
    "name:mac_x_preferred":[
        "\u041a\u0440\u0438\u0441\u0442\u0438\u0458\u0430\u043d\u0441\u0445\u043e\u043b\u043c"
    ],
    "name:may_x_preferred":[
        "Christiansholm"
    ],
    "name:nds_x_preferred":[
        "Chrischansholm"
    ],
    "name:pol_x_preferred":[
        "Christiansholm"
    ],
    "name:por_x_preferred":[
        "Christiansholm"
    ],
    "name:rum_x_preferred":[
        "Christiansholm"
    ],
    "name:rus_x_preferred":[
        "\u0425\u0440\u0438\u0441\u0442\u0438\u0430\u043d\u0441\u0445\u043e\u043b\u044c\u043c"
    ],
    "name:spa_x_preferred":[
        "Christiansholm"
    ],
    "name:srp_x_preferred":[
        "\u041a\u0440\u0438\u0441\u0442\u0438\u0430\u043d\u0441\u0445\u043e\u043b\u043c"
    ],
    "name:tur_x_preferred":[
        "Christiansholm"
    ],
    "name:ukr_x_preferred":[
        "\u041a\u0440\u0456\u0441\u0442\u0456\u0430\u043d\u0441\u0433\u043e\u043b\u044c\u043c"
    ],
    "name:uzb_x_preferred":[
        "Christiansholm"
    ],
    "name:vie_x_preferred":[
        "Christiansholm"
    ],
    "name:vol_x_preferred":[
        "Christiansholm"
    ],
    "name:war_x_preferred":[
        "Christiansholm"
    ],
    "qs_pg:aaroncc":"DE",
    "qs_pg:gn_country":"DE",
    "qs_pg:gn_fcode":"PPLA4",
    "qs_pg:gn_pop":295,
    "qs_pg:name":"Christiansholm",
    "qs_pg:photos_9r":0,
    "qs_pg:photos_sr":0,
    "qs_pg:pop_sr":2,
    "qs_pg:qs_pg_placetype":"locality",
    "wof:name":"Christiansholm",
    "wof:placetype":"locality",
    "wof:population":295
},
  "geometry": {"coordinates":[9.41667,54.31667],"type":"Point"}
}