{
  "type": "Feature",
  "properties": {
    "gn:admin1_code":"8",
    "gn:admin2_code":"0.0",
    "gn:admin3_code":"7132.0",
    "gn:admin4_code":"7132109.0",
    "gn:asciiname":"Mahlert",
    "gn:country_code":"DE",
    "gn:dem":279,
    "gn:feature_class":"P",
    "gn:feature_code":"PPL",
    "gn:name":"Mahlert",
    "gn:population":0,
    "gn:timezone":"Europe/Berlin",
    "iso:country":"DE",
    "wof:name":"Mahlert",
    "wof:placetype":"neighbourhood"
},
  "geometry": {"coordinates":[7.62358,50.65462],"type":"Point"}
}