{
  "type": "Feature",
  "properties": {
    "gn:admin1_code":"7",
    "gn:admin2_code":"55.0",
    "gn:admin3_code":"5566.0",
    "gn:admin4_code":"5566048.0",
    "gn:asciiname":"Halen",
    "gn:country_code":"DE",
    "gn:dem":57,
    "gn:feature_class":"P",
    "gn:feature_code":"PPL",
    "gn:name":"Halen",
    "gn:population":0,
    "gn:timezone":"Europe/Berlin",
    "iso:country":"DE",
    "name:afr_x_preferred":[
        "Halen"
    ],
    "name:bre_x_preferred":[
        "Halen"
    ],
    "name:bul_x_preferred":[
        "\u0425\u0430\u043b\u0435\u043d"
    ],
    "name:cat_x_preferred":[
        "Halen"
    ],
    "name:ceb_x_preferred":[
        "Halen"
    ],
    "name:deu_x_preferred":[
        "Halen"
    ],
    "name:ell_x_preferred":[
        "\u03a7\u03ac\u03bb\u03b5\u03bd"
    ],
    "name:epo_x_preferred":[
        "Halen"
    ],
    "name:eus_x_preferred":[
        "Halen"
    ],
    "name:fas_x_preferred":[
        "\u0627\u0644\u0627\u0646"
    ],
    "name:fra_x_preferred":[
        "Halen"
    ],
    "name:hye_x_preferred":[
        "\u0540\u0561\u056c\u0565\u0576"
    ],
    "name:ita_x_preferred":[
        "Halen"
    ],
    "name:lim_x_preferred":[
        "H\u00f4le"
    ],
    "name:nld_x_preferred":[
        "Halen"
    ],
    "name:nor_x_preferred":[
        "Halen"
    ],
    "name:oci_x_preferred":[
        "Halen"
    ],
    "name:pol_x_preferred":[
        "Halen"
    ],
    "name:por_x_preferred":[
        "Halen"
    ],
    "name:ron_x_preferred":[
        "Halen"
    ],
    "name:rus_x_preferred":[
        "\u0425\u0430\u043b\u0435\u043d"
    ],
    "name:slk_x_preferred":[
        "Halen"
    ],
    "name:spa_x_preferred":[
        "Halen"
    ],
    "name:swe_x_preferred":[
        "Halen"
    ],
    "name:tha_x_preferred":[
        "\u0e2e\u0e32\u0e40\u0e25\u0e34\u0e19"
    ],
    "name:tur_x_preferred":[
        "Halen"
    ],
    "name:vie_x_preferred":[
        "Halen"
    ],
    "name:vol_x_preferred":[
        "Halen"
    ],
    "name:war_x_preferred":[
        "Halen"
    ],
    "wof:name":"Halen",
    "wof:placetype":"neighbourhood"
},
  "geometry": {"coordinates":[7.93688,52.34041],"type":"Point"}
}