{
  "type": "Feature",
  "properties": {
    "gn:admin1_code":"7",
    "gn:admin2_code":"55.0",
    "gn:admin3_code":"5566.0",
    "gn:admin4_code":"5566048.0",
    "gn:asciiname":"Halen",
    "gn:country_code":"DE",
    "gn:dem":57,
    "gn:feature_class":"P",
    "gn:feature_code":"PPL",
    "gn:name":"Halen",
    "gn:population":0,
    "gn:timezone":"Europe/Berlin",
    "iso:country":"DE",
    "wof:name":"Halen",
    "wof:placetype":"neighbourhood"
},
  "geometry": {"coordinates":[7.93688,52.34041],"type":"Point"}
}