{
  "type": "Feature",
  "properties": {
    "gn:admin1_code":"5",
    "gn:admin2_code":"64.0",
    "gn:admin3_code":"6414.0",
    "gn:admin4_code":"6414000.0",
    "gn:asciiname":"Klarenthal",
    "gn:country_code":"DE",
    "gn:dem":191,
    "gn:feature_class":"P",
    "gn:feature_code":"PPL",
    "gn:name":"Klarenthal",
    "gn:population":0,
    "gn:timezone":"Europe/Berlin",
    "iso:country":"DE",
    "name:ceb_x_preferred":[
        "Klarenthal"
    ],
    "name:deu_x_preferred":[
        "Wiesbaden-Klarenthal"
    ],
    "name:fas_x_preferred":[
        "\u06a9\u0644\u0627\u0631\u0646\u062a\u0627\u0644"
    ],
    "name:fra_x_preferred":[
        "Klarenthal"
    ],
    "name:ltz_x_preferred":[
        "Wiesbaden-Klarenthal"
    ],
    "name:nld_x_preferred":[
        "Klarenthal"
    ],
    "name:nor_x_preferred":[
        "Wiesbaden-Klarenthal"
    ],
    "wof:name":"Klarenthal",
    "wof:placetype":"neighbourhood"
},
  "geometry": {"coordinates":[8.202,50.08826],"type":"Point"}
}