{
  "type": "Feature",
  "properties": {
    "gn:admin1_code":"12",
    "gn:admin2_code":"0.0",
    "gn:admin3_code":"13071.0",
    "gn:admin4_code":"13071008.0",
    "gn:asciiname":"Klippstein",
    "gn:cc2":"DE",
    "gn:country_code":"DE",
    "gn:dem":41,
    "gn:feature_class":"P",
    "gn:feature_code":"PPL",
    "gn:name":"Klippstein",
    "gn:population":0,
    "gn:timezone":"Europe/Berlin",
    "iso:country":"DE",
    "name:und_x_variant":[
        "Klipstein",
        "Klippstein"
    ],
    "wof:name":"Klippstein",
    "wof:placetype":"neighbourhood"
},
  "geometry": {"coordinates":[13.03333,53.81667],"type":"Point"}
}