{
  "type": "Feature",
  "properties": {
    "gn:admin1_code":"13",
    "gn:admin2_code":"0.0",
    "gn:admin3_code":"14523.0",
    "gn:admin4_code":"14523100.0",
    "gn:asciiname":"Losa",
    "gn:country_code":"DE",
    "gn:dem":385,
    "gn:feature_class":"P",
    "gn:feature_code":"PPL",
    "gn:name":"Losa",
    "gn:population":0,
    "gn:timezone":"Europe/Berlin",
    "iso:country":"DE",
    "wof:name":"Losa",
    "wof:placetype":"neighbourhood"
},
  "geometry": {"coordinates":[12.18873,50.59664],"type":"Point"}
}