{
  "type": "Feature",
  "properties": {
    "gn:admin1_code":"13",
    "gn:admin2_code":"0.0",
    "gn:admin3_code":"14730.0",
    "gn:admin4_code":"14730080.0",
    "gn:asciiname":"Bunitz",
    "gn:country_code":"DE",
    "gn:dem":127,
    "gn:feature_class":"P",
    "gn:feature_code":"PPL",
    "gn:name":"Bunitz",
    "gn:population":0,
    "gn:timezone":"Europe/Berlin",
    "iso:country":"DE",
    "wof:name":"Bunitz",
    "wof:placetype":"neighbourhood"
},
  "geometry": {"coordinates":[12.69608,51.45764000000001],"type":"Point"}
}