{
  "type": "Feature",
  "properties": {
    "gn:country":"DE",
    "gn:fcode":"PPL",
    "gn:population":0,
    "iso:country":"DE",
    "qs_pg:aaroncc":"DE",
    "qs_pg:gn_country":"DE",
    "qs_pg:gn_fcode":"PPL",
    "qs_pg:gn_pop":0,
    "qs_pg:name":"H\u00f6rlitz",
    "qs_pg:name_adm0":"Deutschland",
    "qs_pg:name_adm1":"Bundesland Brandenburg",
    "qs_pg:photos":214,
    "qs_pg:photos_1k":43,
    "qs_pg:photos_9k":1,
    "qs_pg:photos_9r":4,
    "qs_pg:photos_all":214,
    "qs_pg:photos_sr":4,
    "qs_pg:pop_sr":0,
    "qs_pg:qs_pg_placetype":"locality",
    "qs_pg:qs_pg_placetype_gp":"Town",
    "qs_pg:woe_adm0":23424829,
    "woe:adm0_id":23424829,
    "woe:name_adm0":"Deutschland",
    "woe:name_adm1":"Bundesland Brandenburg",
    "woe:placetype":"Town",
    "wof:name":"H\u00f6rlitz",
    "wof:placetype":"neighbourhood"
},
  "geometry": {"coordinates":[13.94655,51.52661],"type":"Point"}
}