{
  "type": "Feature",
  "properties": {
    "gn:admin1_code":"13",
    "gn:admin2_code":"0.0",
    "gn:admin3_code":"14524.0",
    "gn:admin4_code":"14524200.0",
    "gn:asciiname":"Thurm",
    "gn:country_code":"DE",
    "gn:dem":280,
    "gn:feature_class":"P",
    "gn:feature_code":"PPL",
    "gn:name":"Thurm",
    "gn:population":0,
    "gn:timezone":"Europe/Berlin",
    "iso:country":"DE",
    "wof:name":"Thurm",
    "wof:placetype":"neighbourhood"
},
  "geometry": {"coordinates":[12.55159,50.76675],"type":"Point"}
}