{
  "type": "Feature",
  "properties": {
    "iso:country":"DE",
    "wof:name":"Kohlfurth",
    "wof:placetype":"neighbourhood"
},
  "geometry": {"coordinates":[7.1095089562351,51.18928049061115],"type":"Point"}
}