{
  "type": "Feature",
  "properties": {
    "gn:admin1_code":"2",
    "gn:admin2_code":"93.0",
    "gn:admin3_code":"9376.0",
    "gn:admin4_code":"9376151.0",
    "gn:asciiname":"Pirkhof",
    "gn:country_code":"DE",
    "gn:dem":564,
    "gn:feature_class":"P",
    "gn:feature_code":"PPL",
    "gn:name":"Pirkhof",
    "gn:population":0,
    "gn:timezone":"Europe/Berlin",
    "iso:country":"DE",
    "wof:name":"Pirkhof",
    "wof:placetype":"neighbourhood"
},
  "geometry": {"coordinates":[12.45886,49.48782],"type":"Point"}
}