{
  "type": "Feature",
  "properties": {
    "gn:admin1_code":"15.0",
    "gn:admin2_code":"0.0",
    "gn:admin3_code":"16065.0",
    "gn:admin4_code":"16065067.0",
    "gn:asciiname":"Berka",
    "gn:country_code":"DE",
    "gn:dem":186,
    "gn:feature_class":"P",
    "gn:feature_code":"PPL",
    "gn:name":"Berka",
    "gn:population":0,
    "gn:timezone":"Europe/Berlin",
    "iso:country":"DE",
    "name:ces_x_preferred":[
        "Berka"
    ],
    "name:deu_x_preferred":[
        "Berka"
    ],
    "name:epo_x_preferred":[
        "Berka"
    ],
    "name:fra_x_preferred":[
        "Berka"
    ],
    "name:ita_x_preferred":[
        "Berka"
    ],
    "name:jpn_x_preferred":[
        "\u30d9\u30eb\u30ab"
    ],
    "name:pol_x_preferred":[
        "Berka"
    ],
    "name:srp_x_preferred":[
        "\u0411\u0435\u0440\u043a\u0430"
    ],
    "wof:name":"Berka",
    "wof:placetype":"neighbourhood"
},
  "geometry": {"coordinates":[10.93002,51.3475],"type":"Point"}
}