{
  "type": "Feature",
  "properties": {
    "gn:admin1_code":"2",
    "gn:admin2_code":"91.0",
    "gn:admin3_code":"9185.0",
    "gn:admin4_code":"9185131.0",
    "gn:asciiname":"Weilach",
    "gn:country_code":"DE",
    "gn:dem":444,
    "gn:feature_class":"P",
    "gn:feature_code":"PPL",
    "gn:name":"Weilach",
    "gn:population":0,
    "gn:timezone":"Europe/Berlin",
    "iso:country":"DE",
    "name:ceb_x_preferred":[
        "Weilach"
    ],
    "name:chv_x_preferred":[
        "\u0412\u0430\u0439\u043b\u044f\u0445"
    ],
    "name:deu_x_preferred":[
        "Weilach"
    ],
    "name:rus_x_preferred":[
        "\u0412\u0430\u0439\u043b\u0430\u0445"
    ],
    "wof:name":"Weilach",
    "wof:placetype":"neighbourhood"
},
  "geometry": {"coordinates":[11.26459,48.48743],"type":"Point"}
}