{
  "type": "Feature",
  "properties": {
    "gn:admin1_code":"2",
    "gn:admin2_code":"93.0",
    "gn:admin3_code":"9362.0",
    "gn:admin4_code":"9362000.0",
    "gn:asciiname":"Gallingkofen",
    "gn:country_code":"DE",
    "gn:dem":336,
    "gn:feature_class":"P",
    "gn:feature_code":"PPL",
    "gn:name":"Gallingkofen",
    "gn:population":0,
    "gn:timezone":"Europe/Berlin",
    "iso:country":"DE",
    "wof:name":"Gallingkofen",
    "wof:placetype":"neighbourhood"
},
  "geometry": {"coordinates":[12.10191,49.04706],"type":"Point"}
}