{
  "type": "Feature",
  "properties": {
    "gn:admin1_code":"6",
    "gn:admin2_code":"0.0",
    "gn:admin3_code":"3358.0",
    "gn:admin4_code":"3358021.0",
    "gn:asciiname":"Frielingen",
    "gn:cc2":"DE",
    "gn:country_code":"DE",
    "gn:dem":72,
    "gn:feature_class":"P",
    "gn:feature_code":"PPL",
    "gn:name":"Frielingen",
    "gn:population":0,
    "gn:timezone":"Europe/Berlin",
    "iso:country":"DE",
    "name:und_x_variant":[
        "Dreifrielingen",
        "Frielingen"
    ],
    "wof:name":"Frielingen",
    "wof:placetype":"neighbourhood"
},
  "geometry": {"coordinates":[9.72153,52.97656],"type":"Point"}
}