{
  "type": "Feature",
  "properties": {
    "gn:gn_country":"DE",
    "gn:gn_fcode":"PPLA4",
    "gn:gn_pop":353,
    "gn:population":353,
    "iso:country":"DE",
    "name:bak_x_preferred":[
        "\u0424\u0440\u0438\u0434\u0435\u043b\u044c\u0441\u0445\u0430\u0443\u0437\u0435\u043d"
    ],
    "name:baq_x_preferred":[
        "Friedelshausen"
    ],
    "name:chi_x_preferred":[
        "\u5f17\u91cc\u5fb7\u5c14\u65af\u8c6a\u68ee"
    ],
    "name:dut_x_preferred":[
        "Friedelshausen"
    ],
    "name:eng_x_preferred":[
        "Friedelshausen"
    ],
    "name:epo_x_preferred":[
        "Friedelshausen"
    ],
    "name:fre_x_preferred":[
        "Friedelshausen"
    ],
    "name:ger_x_preferred":[
        "Friedelshausen"
    ],
    "name:hun_x_preferred":[
        "Friedelshausen"
    ],
    "name:ita_x_preferred":[
        "Friedelshausen"
    ],
    "name:mac_x_preferred":[
        "\u0424\u0440\u0438\u0434\u0435\u043b\u0441\u0445\u0430\u0443\u0437\u0435\u043d"
    ],
    "name:may_x_preferred":[
        "Friedelshausen"
    ],
    "name:per_x_preferred":[
        "\u0641\u0631\u06cc\u062f\u0644\u0633\u0647\u0627\u0648\u0632\u0646"
    ],
    "name:pol_x_preferred":[
        "Friedelshausen"
    ],
    "name:por_x_preferred":[
        "Friedelshausen"
    ],
    "name:rum_x_preferred":[
        "Friedelshausen"
    ],
    "name:rus_x_preferred":[
        "\u0424\u0440\u0438\u0434\u0435\u043b\u044c\u0441\u0445\u0430\u0443\u0437\u0435\u043d"
    ],
    "name:spa_x_preferred":[
        "Friedelshausen"
    ],
    "name:srp_x_preferred":[
        "\u0424\u0440\u0438\u0434\u0435\u043b\u0441\u0445\u0430\u0443\u0437\u0435\u043d"
    ],
    "name:ukr_x_preferred":[
        "\u0424\u0440\u0456\u0434\u0435\u043b\u044c\u0441\u0433\u0430\u0443\u0437\u0435\u043d"
    ],
    "name:uzb_x_preferred":[
        "Friedelshausen"
    ],
    "name:vie_x_preferred":[
        "Friedelshausen"
    ],
    "name:vol_x_preferred":[
        "Friedelshausen"
    ],
    "name:war_x_preferred":[
        "Friedelshausen"
    ],
    "qs_pg:aaroncc":"DE",
    "qs_pg:gn_country":"DE",
    "qs_pg:gn_fcode":"PPLA4",
    "qs_pg:gn_pop":353,
    "qs_pg:name":"Friedelshausen",
    "qs_pg:photos_9r":0,
    "qs_pg:photos_sr":0,
    "qs_pg:pop_sr":2,
    "qs_pg:qs_pg_placetype":"locality",
    "wof:name":"Friedelshausen",
    "wof:placetype":"locality",
    "wof:population":353
},
  "geometry": {"coordinates":[10.23333,50.66667],"type":"Point"}
}