{
  "type": "Feature",
  "properties": {
    "gn:admin1_code":"13",
    "gn:admin2_code":"0.0",
    "gn:admin3_code":"14523.0",
    "gn:admin4_code":"14523320.0",
    "gn:asciiname":"Haselbrunn",
    "gn:country_code":"DE",
    "gn:dem":409,
    "gn:feature_class":"P",
    "gn:feature_code":"PPL",
    "gn:name":"Haselbrunn",
    "gn:population":0,
    "gn:timezone":"Europe/Berlin",
    "iso:country":"DE",
    "wof:name":"Haselbrunn",
    "wof:placetype":"neighbourhood"
},
  "geometry": {"coordinates":[12.12754,50.51402],"type":"Point"}
}