{
  "type": "Feature",
  "properties": {
    "gn:admin1_code":"7",
    "gn:admin2_code":"57.0",
    "gn:admin3_code":"5774.0",
    "gn:admin4_code":"5774032.0",
    "gn:asciiname":"Nesthausen",
    "gn:country_code":"DE",
    "gn:dem":100,
    "gn:feature_class":"P",
    "gn:feature_code":"PPLL",
    "gn:name":"Nesthausen",
    "gn:population":0,
    "gn:timezone":"Europe/Berlin",
    "iso:country":"DE",
    "wof:name":"Nesthausen",
    "wof:placetype":"neighbourhood"
},
  "geometry": {"coordinates":[8.68852,51.75087],"type":"Point"}
}