{
  "type": "Feature",
  "properties": {
    "gn:admin1_code":"2.0",
    "gn:admin2_code":"97.0",
    "gn:admin3_code":"9773.0",
    "gn:admin4_code":"9773170.0",
    "gn:asciiname":"Ballhausen",
    "gn:country_code":"DE",
    "gn:dem":486,
    "gn:feature_class":"P",
    "gn:feature_code":"PPL",
    "gn:name":"Ballhausen",
    "gn:population":0,
    "gn:timezone":"Europe/Berlin",
    "iso:country":"DE",
    "name:bak_x_preferred":[
        "\u0411\u0430\u043b\u044c\u0445\u0430\u0443\u0437\u0435\u043d"
    ],
    "name:ceb_x_preferred":[
        "Ballhausen"
    ],
    "name:deu_x_preferred":[
        "Ballhausen"
    ],
    "name:epo_x_preferred":[
        "Ballhausen"
    ],
    "name:eus_x_preferred":[
        "Ballhausen"
    ],
    "name:fas_x_preferred":[
        "\u0628\u0627\u0644\u0647\u0627\u0648\u0632\u0646"
    ],
    "name:fra_x_preferred":[
        "Ballhausen"
    ],
    "name:hun_x_preferred":[
        "Ballhausen"
    ],
    "name:ita_x_preferred":[
        "Ballhausen"
    ],
    "name:kaz_x_preferred":[
        "\u0411\u0430\u043b\u044c\u0445\u0430\u0443\u0437\u0435\u043d"
    ],
    "name:kir_x_preferred":[
        "\u0411\u0430\u043b\u044c\u0445\u0430\u0443\u0437\u0435\u043d"
    ],
    "name:mkd_x_preferred":[
        "\u0411\u0430\u043b\u0445\u0430\u0443\u0437\u0435\u043d"
    ],
    "name:msa_x_preferred":[
        "Ballhausen"
    ],
    "name:nld_x_preferred":[
        "Ballhausen"
    ],
    "name:pol_x_preferred":[
        "Ballhausen"
    ],
    "name:ron_x_preferred":[
        "Ballhausen"
    ],
    "name:rus_x_preferred":[
        "\u0411\u0430\u043b\u044c\u0445\u0430\u0443\u0437\u0435\u043d"
    ],
    "name:spa_x_preferred":[
        "Ballhausen"
    ],
    "name:srp_x_preferred":[
        "\u0411\u0430\u043b\u0445\u0430\u0443\u0437\u0435\u043d"
    ],
    "name:ukr_x_preferred":[
        "\u0411\u0430\u043b\u043b\u044c\u0433\u0430\u0443\u0437\u0435\u043d"
    ],
    "name:uzb_x_preferred":[
        "Ballhausen"
    ],
    "name:vol_x_preferred":[
        "Ballhausen"
    ],
    "name:war_x_preferred":[
        "Ballhausen"
    ],
    "name:zho_x_preferred":[
        "\u5df4\u5c14\u8c6a\u68ee"
    ],
    "wof:name":"Ballhausen",
    "wof:placetype":"neighbourhood"
},
  "geometry": {"coordinates":[10.30111,48.65097],"type":"Point"}
}