{
  "type": "Feature",
  "properties": {
    "gn:admin1_code":"2",
    "gn:admin2_code":"95.0",
    "gn:admin3_code":"9571.0",
    "gn:admin4_code":"9571115.0",
    "gn:asciiname":"Rottenbach",
    "gn:country_code":"DE",
    "gn:dem":433,
    "gn:feature_class":"P",
    "gn:feature_code":"PPL",
    "gn:name":"R\u00f6ttenbach",
    "gn:population":0,
    "gn:timezone":"Europe/Berlin",
    "iso:country":"DE",
    "name:ceb_x_preferred":[
        "Rottenbach"
    ],
    "name:deu_x_preferred":[
        "Rottenbach"
    ],
    "name:epo_x_preferred":[
        "Rottenbach"
    ],
    "name:ita_x_preferred":[
        "Rottenbach"
    ],
    "name:kaz_x_preferred":[
        "\u0420\u043e\u0442\u0442\u0435\u043d\u0431\u0430\u0445"
    ],
    "name:kir_x_preferred":[
        "\u0420\u043e\u0442\u0442\u0435\u043d\u0431\u0430\u0445"
    ],
    "name:nld_x_preferred":[
        "Rottenbach"
    ],
    "name:pol_x_preferred":[
        "Rottenbach"
    ],
    "name:rus_x_preferred":[
        "\u0420\u043e\u0442\u0442\u0435\u043d\u0431\u0430\u0445"
    ],
    "name:swe_x_preferred":[
        "Rottenbach"
    ],
    "name:vol_x_preferred":[
        "Rottenbach"
    ],
    "wof:name":"Rottenbach",
    "wof:placetype":"neighbourhood"
},
  "geometry": {"coordinates":[10.57804,49.13779],"type":"Point"}
}