{
  "type": "Feature",
  "properties": {
    "gn:country":"DE",
    "gn:fcode":"PPL",
    "gn:population":248,
    "iso:country":"DE",
    "name:bak_x_preferred":[
        "\u0412\u0435\u0441\u043f\u0435\u043d"
    ],
    "name:ceb_x_preferred":[
        "Wespen"
    ],
    "name:deu_x_preferred":[
        "Wespen"
    ],
    "name:epo_x_preferred":[
        "Wespen"
    ],
    "name:fas_x_preferred":[
        "\u0648\u0634\u067e\u0646"
    ],
    "name:ita_x_preferred":[
        "Wespen"
    ],
    "name:kaz_x_preferred":[
        "\u0412\u0435\u0441\u043f\u0435\u043d"
    ],
    "name:kir_x_preferred":[
        "\u0412\u0435\u0441\u043f\u0435\u043d"
    ],
    "name:mkd_x_preferred":[
        "\u0412\u0435\u0441\u043f\u0435\u043d"
    ],
    "name:nld_x_preferred":[
        "Wespen"
    ],
    "name:pol_x_preferred":[
        "Wespen"
    ],
    "name:ron_x_preferred":[
        "Wespen"
    ],
    "name:rus_x_preferred":[
        "\u0412\u0435\u0441\u043f\u0435\u043d"
    ],
    "name:uzb_x_preferred":[
        "Wespen"
    ],
    "name:vie_x_preferred":[
        "Wespen"
    ],
    "name:vol_x_preferred":[
        "Wespen"
    ],
    "qs_pg:aaroncc":"DE",
    "qs_pg:gn_country":"DE",
    "qs_pg:gn_fcode":"PPL",
    "qs_pg:gn_pop":248,
    "qs_pg:name":"Wespen",
    "qs_pg:name_adm0":"Deutschland",
    "qs_pg:name_adm1":"Sachsen-Anhalt",
    "qs_pg:photos_9r":0,
    "qs_pg:photos_sr":0,
    "qs_pg:pop_sr":2,
    "qs_pg:qs_pg_placetype":"locality",
    "qs_pg:qs_pg_placetype_gp":"Town",
    "qs_pg:woe_adm0":23424829,
    "woe:adm0_id":23424829,
    "woe:name_adm0":"Deutschland",
    "woe:name_adm1":"Sachsen-Anhalt",
    "woe:placetype":"Town",
    "wof:name":"Wespen",
    "wof:placetype":"neighbourhood",
    "wof:population":248
},
  "geometry": {"coordinates":[11.82797,51.95901],"type":"Point"}
}