{
  "type": "Feature",
  "properties": {
    "gn:admin1_code":"1",
    "gn:admin2_code":"84.0",
    "gn:admin3_code":"8437.0",
    "gn:admin4_code":"8437107.0",
    "gn:asciiname":"Nusplingen",
    "gn:country_code":"DE",
    "gn:dem":801,
    "gn:feature_class":"P",
    "gn:feature_code":"PPL",
    "gn:name":"Nusplingen",
    "gn:population":0,
    "gn:timezone":"Europe/Berlin",
    "iso:country":"DE",
    "name:als_x_preferred":[
        "Nusplingen"
    ],
    "name:ceb_x_preferred":[
        "Nusplingen"
    ],
    "name:deu_x_preferred":[
        "Nusplingen"
    ],
    "name:epo_x_preferred":[
        "Nusplingen"
    ],
    "name:eus_x_preferred":[
        "Nusplingen"
    ],
    "name:fas_x_preferred":[
        "\u0646\u0648\u0634\u067e\u0644\u06cc\u0646\u06af\u0646"
    ],
    "name:fra_x_preferred":[
        "Nusplingen"
    ],
    "name:hun_x_preferred":[
        "Nusplingen"
    ],
    "name:ita_x_preferred":[
        "Nusplingen"
    ],
    "name:lat_x_preferred":[
        "Nusplingen"
    ],
    "name:lmo_x_preferred":[
        "Nusplingen"
    ],
    "name:msa_x_preferred":[
        "Nusplingen"
    ],
    "name:nld_x_preferred":[
        "Nusplingen"
    ],
    "name:pol_x_preferred":[
        "Nusplingen"
    ],
    "name:por_x_preferred":[
        "Nusplingen"
    ],
    "name:ron_x_preferred":[
        "Nusplingen"
    ],
    "name:rus_x_preferred":[
        "\u041d\u0443\u0441\u043f\u043b\u0438\u043d\u0433\u0435\u043d"
    ],
    "name:spa_x_preferred":[
        "Nusplingen"
    ],
    "name:srp_x_preferred":[
        "\u041d\u0443\u0441\u043f\u043b\u0438\u043d\u0433\u0435\u043d"
    ],
    "name:ukr_x_preferred":[
        "\u041d\u0443\u0441\u043f\u043b\u0456\u043d\u0433\u0435\u043d"
    ],
    "name:uzb_x_preferred":[
        "Nusplingen"
    ],
    "name:vol_x_preferred":[
        "Nusplingen"
    ],
    "name:war_x_preferred":[
        "Nusplingen"
    ],
    "name:zho_x_preferred":[
        "\u52aa\u65af\u666e\u6797\u6839"
    ],
    "wof:name":"Nusplingen",
    "wof:placetype":"neighbourhood"
},
  "geometry": {"coordinates":[9.10161,48.11818],"type":"Point"}
}