{
  "type": "Feature",
  "properties": {
    "gn:admin1_code":"13",
    "gn:admin2_code":"0.0",
    "gn:admin3_code":"14521.0",
    "gn:admin4_code":"14521060.0",
    "gn:asciiname":"Niederschlag",
    "gn:country_code":"DE",
    "gn:dem":738,
    "gn:feature_class":"P",
    "gn:feature_code":"PPL",
    "gn:name":"Niederschlag",
    "gn:population":0,
    "gn:timezone":"Europe/Berlin",
    "iso:country":"DE",
    "name:und_x_variant":[
        "Hammerunterwiesenthal-Niederschlag",
        "Niederschlag"
    ],
    "wof:name":"Niederschlag",
    "wof:placetype":"neighbourhood"
},
  "geometry": {"coordinates":[13.01902,50.47175],"type":"Point"}
}