{
  "type": "Feature",
  "properties": {
    "gn:admin1_code":"2.0",
    "gn:admin2_code":"093",
    "gn:admin3_code":"9376.0",
    "gn:admin4_code":"9376112.0",
    "gn:asciiname":"Willhof",
    "gn:country_code":"DE",
    "gn:dem":378,
    "gn:feature_class":"P",
    "gn:feature_code":"PPL",
    "gn:name":"Willhof",
    "gn:population":0,
    "gn:timezone":"Europe/Berlin",
    "iso:country":"DE",
    "wof:name":"Willhof",
    "wof:placetype":"neighbourhood"
},
  "geometry": {"coordinates":[12.25851,49.41767],"type":"Point"}
}