{
  "type": "Feature",
  "properties": {
    "gn:admin1_code":"2",
    "gn:admin2_code":"91.0",
    "gn:admin3_code":"9181.0",
    "gn:admin4_code":"9181135.0",
    "gn:asciiname":"Gimmenhausen",
    "gn:country_code":"DE",
    "gn:dem":711,
    "gn:feature_class":"P",
    "gn:feature_code":"PPL",
    "gn:name":"Gimmenhausen",
    "gn:population":0,
    "gn:timezone":"Europe/Berlin",
    "iso:country":"DE",
    "wof:name":"Gimmenhausen",
    "wof:placetype":"neighbourhood"
},
  "geometry": {"coordinates":[10.96977,47.94085],"type":"Point"}
}