{
  "type": "Feature",
  "properties": {
    "gn:admin1_code":"2.0",
    "gn:admin2_code":"91.0",
    "gn:admin3_code":"9190.0",
    "gn:admin4_code":"9190130.0",
    "gn:asciiname":"Bergbau",
    "gn:country_code":"DE",
    "gn:dem":787,
    "gn:feature_class":"P",
    "gn:feature_code":"PPL",
    "gn:name":"Bergbau",
    "gn:population":0,
    "gn:timezone":"Europe/Berlin",
    "iso:country":"DE",
    "wof:name":"Bergbau",
    "wof:placetype":"neighbourhood"
},
  "geometry": {"coordinates":[11.0173,47.79366],"type":"Point"}
}