{
  "type": "Feature",
  "properties": {
    "gn:admin1_code":"1.0",
    "gn:admin2_code":"083",
    "gn:admin3_code":"8335.0",
    "gn:admin4_code":"8335043.0",
    "gn:asciiname":"Wollmatingen",
    "gn:country_code":"DE",
    "gn:dem":416,
    "gn:feature_class":"P",
    "gn:feature_code":"PPL",
    "gn:name":"Wollmatingen",
    "gn:population":0,
    "gn:timezone":"Europe/Berlin",
    "iso:country":"DE",
    "wof:name":"Wollmatingen",
    "wof:placetype":"locality"
},
  "geometry": {"coordinates":[9.14595,47.69226],"type":"Point"}
}