{
  "type": "Feature",
  "properties": {
    "gn:admin1_code":"12",
    "gn:admin2_code":"0.0",
    "gn:admin3_code":"13074.0",
    "gn:admin4_code":"13074090.0",
    "gn:asciiname":"Fahren",
    "gn:country_code":"DE",
    "gn:dem":58,
    "gn:feature_class":"P",
    "gn:feature_code":"PPL",
    "gn:name":"Fahren",
    "gn:population":0,
    "gn:timezone":"Europe/Berlin",
    "iso:country":"DE",
    "wof:name":"Fahren",
    "wof:placetype":"neighbourhood"
},
  "geometry": {"coordinates":[11.6022,53.84761999999999],"type":"Point"}
}