{
  "type": "Feature",
  "properties": {
    "gn:admin1_code":"12",
    "gn:admin2_code":"0.0",
    "gn:admin3_code":"13074.0",
    "gn:admin4_code":"13074090.0",
    "gn:asciiname":"Fahren",
    "gn:country_code":"DE",
    "gn:dem":58,
    "gn:feature_class":"P",
    "gn:feature_code":"PPL",
    "gn:name":"Fahren",
    "gn:population":0,
    "gn:timezone":"Europe/Berlin",
    "iso:country":"DE",
    "name:ceb_x_preferred":[
        "Fahren"
    ],
    "name:dan_x_preferred":[
        "Fahren"
    ],
    "name:deu_x_preferred":[
        "Fahren"
    ],
    "name:epo_x_preferred":[
        "Fahren"
    ],
    "name:eus_x_preferred":[
        "Fahren"
    ],
    "name:fas_x_preferred":[
        "\u0641\u0627\u0631\u0646"
    ],
    "name:fra_x_preferred":[
        "Fahren"
    ],
    "name:hun_x_preferred":[
        "Fahren"
    ],
    "name:ita_x_preferred":[
        "Fahren"
    ],
    "name:kir_x_preferred":[
        "\u0424\u0430\u0440\u0435\u043d"
    ],
    "name:mkd_x_preferred":[
        "\u0424\u0430\u0440\u0435\u043d"
    ],
    "name:msa_x_preferred":[
        "Fahren"
    ],
    "name:nld_x_preferred":[
        "Fahren"
    ],
    "name:pol_x_preferred":[
        "Fahren"
    ],
    "name:por_x_preferred":[
        "Fahren"
    ],
    "name:ron_x_preferred":[
        "Fahren"
    ],
    "name:rus_x_preferred":[
        "\u0424\u0430\u0440\u0435\u043d"
    ],
    "name:spa_x_preferred":[
        "Fahren"
    ],
    "name:srp_x_preferred":[
        "\u0424\u0430\u0440\u0435\u043d"
    ],
    "name:tur_x_preferred":[
        "Fahren"
    ],
    "name:ukr_x_preferred":[
        "\u0424\u0430\u0440\u0435\u043d"
    ],
    "name:urd_x_preferred":[
        "\u0641\u0627\u06c1\u0631\u06cc\u0646"
    ],
    "name:uzb_x_preferred":[
        "Fahren"
    ],
    "name:vie_x_preferred":[
        "Fahren"
    ],
    "name:vol_x_preferred":[
        "Fahren"
    ],
    "name:war_x_preferred":[
        "Fahren"
    ],
    "wof:name":"Fahren",
    "wof:placetype":"neighbourhood"
},
  "geometry": {"coordinates":[11.6022,53.84761999999999],"type":"Point"}
}