{
  "type": "Feature",
  "properties": {
    "iso:country":"DE",
    "name:deu_x_preferred":[
        "S\u00fcdstadt"
    ],
    "wof:name":"Suedstadt",
    "wof:placetype":"neighbourhood"
},
  "geometry": {"coordinates":[9.75323493465088,52.36133246503497],"type":"Point"}
}