{
  "type": "Feature",
  "properties": {
    "gn:admin1_code":"2",
    "gn:admin2_code":"92.0",
    "gn:admin3_code":"9279.0",
    "gn:admin4_code":"9279116.0",
    "gn:asciiname":"Frichlkofen",
    "gn:country_code":"DE",
    "gn:dem":391,
    "gn:feature_class":"P",
    "gn:feature_code":"PPL",
    "gn:name":"Frichlkofen",
    "gn:population":0,
    "gn:timezone":"Europe/Berlin",
    "iso:country":"DE",
    "wof:name":"Frichlkofen",
    "wof:placetype":"neighbourhood"
},
  "geometry": {"coordinates":[12.52451,48.62053],"type":"Point"}
}