{
  "type": "Feature",
  "properties": {
    "gn:admin1_code":"14",
    "gn:admin2_code":"0.0",
    "gn:admin3_code":"15084.0",
    "gn:admin4_code":"15084315.0",
    "gn:asciiname":"Michlitz",
    "gn:country_code":"DE",
    "gn:dem":121,
    "gn:feature_class":"P",
    "gn:feature_code":"PPL",
    "gn:name":"Michlitz",
    "gn:population":0,
    "gn:timezone":"Europe/Berlin",
    "iso:country":"DE",
    "wof:name":"Michlitz",
    "wof:placetype":"neighbourhood"
},
  "geometry": {"coordinates":[12.11668,51.24735],"type":"Point"}
}