{
  "type": "Feature",
  "properties": {
    "gn:admin1_code":"15",
    "gn:admin2_code":"0.0",
    "gn:admin3_code":"16074.0",
    "gn:admin4_code":"16074085.0",
    "gn:asciiname":"Trockhausen",
    "gn:country_code":"DE",
    "gn:dem":268,
    "gn:feature_class":"P",
    "gn:feature_code":"PPL",
    "gn:name":"Trockhausen",
    "gn:population":0,
    "gn:timezone":"Europe/Berlin",
    "iso:country":"DE",
    "wof:name":"Trockhausen",
    "wof:placetype":"neighbourhood"
},
  "geometry": {"coordinates":[11.70722,50.89605],"type":"Point"}
}