{
  "type": "Feature",
  "properties": {
    "gn:admin1_code":"1",
    "gn:admin2_code":"84.0",
    "gn:admin3_code":"8425.0",
    "gn:admin4_code":"8425108.0",
    "gn:asciiname":"Schmiechen",
    "gn:country_code":"DE",
    "gn:dem":547,
    "gn:feature_class":"P",
    "gn:feature_code":"PPL",
    "gn:name":"Schmiechen",
    "gn:population":0,
    "gn:timezone":"Europe/Berlin",
    "iso:country":"DE",
    "name:als_x_preferred":[
        "Schmiechen"
    ],
    "name:ara_x_preferred":[
        "\u0634\u0645\u064a\u0634\u064a\u0646"
    ],
    "name:ceb_x_preferred":[
        "Schmiechen"
    ],
    "name:ces_x_preferred":[
        "Schmiechen"
    ],
    "name:deu_x_preferred":[
        "Schmiechen"
    ],
    "name:epo_x_preferred":[
        "Schmiechen"
    ],
    "name:eus_x_preferred":[
        "Schmiechen"
    ],
    "name:fas_x_preferred":[
        "\u0634\u0645\u06cc\u0634\u0646"
    ],
    "name:fra_x_preferred":[
        "Schmiechen"
    ],
    "name:hun_x_preferred":[
        "Schmiechen"
    ],
    "name:hye_x_preferred":[
        "\u0547\u0574\u056b\u056d\u0565\u0576"
    ],
    "name:ind_x_preferred":[
        "Schmiechen"
    ],
    "name:ita_x_preferred":[
        "Schmiechen"
    ],
    "name:jpn_x_preferred":[
        "\u30b7\u30e5\u30df\u30fc\u30d2\u30a7\u30f3"
    ],
    "name:kaz_x_preferred":[
        "\u0428\u043c\u0438\u0445\u0435\u043d"
    ],
    "name:kir_x_preferred":[
        "\u0428\u043c\u0438\u0445\u0435\u043d"
    ],
    "name:lmo_x_preferred":[
        "Schmiechen"
    ],
    "name:msa_x_preferred":[
        "Schmiechen"
    ],
    "name:nld_x_preferred":[
        "Schmiechen"
    ],
    "name:pol_x_preferred":[
        "Schmiechen"
    ],
    "name:por_x_preferred":[
        "Schmiechen"
    ],
    "name:ron_x_preferred":[
        "Schmiechen"
    ],
    "name:rus_x_preferred":[
        "\u0428\u043c\u0438\u0445\u0435\u043d"
    ],
    "name:spa_x_preferred":[
        "Schmiechen"
    ],
    "name:srp_x_preferred":[
        "\u0428\u043c\u0438\u0445\u0435\u043d"
    ],
    "name:ukr_x_preferred":[
        "\u0428\u043c\u0456\u0445\u0435\u043d"
    ],
    "name:uzb_x_preferred":[
        "Schmiechen"
    ],
    "name:vie_x_preferred":[
        "Schmiechen"
    ],
    "name:vol_x_preferred":[
        "Schmiechen"
    ],
    "name:war_x_preferred":[
        "Schmiechen"
    ],
    "name:zho_x_preferred":[
        "\u65bd\u7c73\u5174"
    ],
    "wof:name":"Schmiechen",
    "wof:placetype":"neighbourhood"
},
  "geometry": {"coordinates":[9.71483,48.3642],"type":"Point"}
}