{
  "type": "Feature",
  "properties": {
    "gn:admin1_code":"2.0",
    "gn:admin2_code":"92.0",
    "gn:admin3_code":"9273.0",
    "gn:admin4_code":"9273127.0",
    "gn:asciiname":"Altbach",
    "gn:country_code":"DE",
    "gn:dem":418,
    "gn:feature_class":"P",
    "gn:feature_code":"PPL",
    "gn:name":"Altbach",
    "gn:population":0,
    "gn:timezone":"Europe/Berlin",
    "iso:country":"DE",
    "wof:name":"Altbach",
    "wof:placetype":"neighbourhood"
},
  "geometry": {"coordinates":[12.04562,48.76716],"type":"Point"}
}