{
  "type": "Feature",
  "properties": {
    "gn:admin1_code":"2.0",
    "gn:admin2_code":"92.0",
    "gn:admin3_code":"9273.0",
    "gn:admin4_code":"9273127.0",
    "gn:asciiname":"Altbach",
    "gn:country_code":"DE",
    "gn:dem":418,
    "gn:feature_class":"P",
    "gn:feature_code":"PPL",
    "gn:name":"Altbach",
    "gn:population":0,
    "gn:timezone":"Europe/Berlin",
    "iso:country":"DE",
    "name:als_x_preferred":[
        "Altbach"
    ],
    "name:ceb_x_preferred":[
        "Altbach"
    ],
    "name:deu_x_preferred":[
        "Altbach"
    ],
    "name:epo_x_preferred":[
        "Altbach"
    ],
    "name:eus_x_preferred":[
        "Altbach"
    ],
    "name:fas_x_preferred":[
        "\u0627\u0644\u062a\u0628\u0627\u062e"
    ],
    "name:fra_x_preferred":[
        "Altbach"
    ],
    "name:hun_x_preferred":[
        "Altbach"
    ],
    "name:hye_x_preferred":[
        "\u0531\u056c\u057f\u0562\u0561\u056d"
    ],
    "name:ita_x_preferred":[
        "Altbach"
    ],
    "name:kaz_x_preferred":[
        "\u0410\u043b\u044c\u0442\u0431\u0430\u0445"
    ],
    "name:kir_x_preferred":[
        "\u0410\u043b\u044c\u0442\u0431\u0430\u0445"
    ],
    "name:lat_x_preferred":[
        "Altbach"
    ],
    "name:lmo_x_preferred":[
        "Altbach"
    ],
    "name:msa_x_preferred":[
        "Altbach"
    ],
    "name:nld_x_preferred":[
        "Altbach"
    ],
    "name:pol_x_preferred":[
        "Altbach"
    ],
    "name:por_x_preferred":[
        "Altbach"
    ],
    "name:ron_x_preferred":[
        "Altbach"
    ],
    "name:rus_x_preferred":[
        "\u0410\u043b\u044c\u0442\u0431\u0430\u0445"
    ],
    "name:spa_x_preferred":[
        "Altbach"
    ],
    "name:srp_x_preferred":[
        "\u0410\u043b\u0442\u0431\u0430\u0445"
    ],
    "name:ukr_x_preferred":[
        "\u0410\u043b\u044c\u0442\u0431\u0430\u0445"
    ],
    "name:uzb_x_preferred":[
        "Altbach"
    ],
    "name:vie_x_preferred":[
        "Altbach"
    ],
    "name:vol_x_preferred":[
        "Altbach"
    ],
    "name:war_x_preferred":[
        "Altbach"
    ],
    "name:zho_x_preferred":[
        "\u963f\u5c14\u7279\u5df4\u8d6b"
    ],
    "wof:name":"Altbach",
    "wof:placetype":"neighbourhood"
},
  "geometry": {"coordinates":[12.04562,48.76716],"type":"Point"}
}