{
  "type": "Feature",
  "properties": {
    "gn:admin1_code":"14",
    "gn:admin2_code":"0.0",
    "gn:admin3_code":"15081.0",
    "gn:admin4_code":"15081030.0",
    "gn:asciiname":"Lohne",
    "gn:country_code":"DE",
    "gn:dem":37,
    "gn:feature_class":"P",
    "gn:feature_code":"PPL",
    "gn:name":"Lohne",
    "gn:population":0,
    "gn:timezone":"Europe/Berlin",
    "iso:country":"DE",
    "name:ceb_x_preferred":[
        "Lohne"
    ],
    "name:deu_x_preferred":[
        "Lohne"
    ],
    "name:fra_x_preferred":[
        "Lohne"
    ],
    "name:nld_x_preferred":[
        "Lohne"
    ],
    "name:pol_x_preferred":[
        "Lohne"
    ],
    "wof:name":"Lohne",
    "wof:placetype":"neighbourhood"
},
  "geometry": {"coordinates":[11.47928,52.78392],"type":"Point"}
}