{
  "type": "Feature",
  "properties": {
    "gn:admin1_code":"5",
    "gn:admin2_code":"64.0",
    "gn:admin3_code":"6438.0",
    "gn:admin4_code":"6438002.0",
    "gn:asciiname":"Offenthal",
    "gn:country_code":"DE",
    "gn:dem":184,
    "gn:feature_class":"P",
    "gn:feature_code":"PPL",
    "gn:name":"Offenthal",
    "gn:population":0,
    "gn:timezone":"Europe/Berlin",
    "iso:country":"DE",
    "wof:name":"Offenthal",
    "wof:placetype":"neighbourhood"
},
  "geometry": {"coordinates":[8.74583,49.98113],"type":"Point"}
}