{
  "type": "Feature",
  "properties": {
    "gn:admin1_code":"2",
    "gn:admin2_code":"91.0",
    "gn:admin3_code":"9180.0",
    "gn:admin4_code":"9180118.0",
    "gn:asciiname":"Schmolz",
    "gn:country_code":"DE",
    "gn:dem":742,
    "gn:feature_class":"P",
    "gn:feature_code":"PPL",
    "gn:name":"Schm\u00f6lz",
    "gn:population":0,
    "gn:timezone":"Europe/Berlin",
    "iso:country":"DE",
    "wof:name":"Schmolz",
    "wof:placetype":"neighbourhood"
},
  "geometry": {"coordinates":[11.04837,47.47896],"type":"Point"}
}