{
  "type": "Feature",
  "properties": {
    "gn:admin1_code":"2",
    "gn:admin2_code":"97.0",
    "gn:admin3_code":"9775.0",
    "gn:admin4_code":"9775164.0",
    "gn:asciiname":"Hegelhofen",
    "gn:country_code":"DE",
    "gn:dem":496,
    "gn:feature_class":"P",
    "gn:feature_code":"PPL",
    "gn:name":"Hegelhofen",
    "gn:population":0,
    "gn:timezone":"Europe/Berlin",
    "iso:country":"DE",
    "wof:name":"Hegelhofen",
    "wof:placetype":"neighbourhood"
},
  "geometry": {"coordinates":[10.15635,48.31323],"type":"Point"}
}