{
  "type": "Feature",
  "properties": {
    "gn:admin1_code":"6",
    "gn:admin2_code":"0.0",
    "gn:admin3_code":"3451.0",
    "gn:admin4_code":"3451002.0",
    "gn:asciiname":"Querenstede",
    "gn:country_code":"DE",
    "gn:dem":6,
    "gn:feature_class":"P",
    "gn:feature_code":"PPL",
    "gn:name":"Querenstede",
    "gn:population":0,
    "gn:timezone":"Europe/Berlin",
    "iso:country":"DE",
    "wof:name":"Querenstede",
    "wof:placetype":"neighbourhood"
},
  "geometry": {"coordinates":[7.9593,53.15756],"type":"Point"}
}