{
  "type": "Feature",
  "properties": {
    "gn:admin1_code":"11",
    "gn:admin2_code":"0.0",
    "gn:admin3_code":"12067.0",
    "gn:admin4_code":"12067137.0",
    "gn:asciiname":"Reudnitz",
    "gn:country_code":"DE",
    "gn:dem":57,
    "gn:feature_class":"P",
    "gn:feature_code":"PPL",
    "gn:name":"Reudnitz",
    "gn:population":0,
    "gn:timezone":"Europe/Berlin",
    "iso:country":"DE",
    "name:deu_x_preferred":[
        "Reudnitz"
    ],
    "wof:name":"Reudnitz",
    "wof:placetype":"neighbourhood"
},
  "geometry": {"coordinates":[14.32551,52.13128],"type":"Point"}
}