{
  "type": "Feature",
  "properties": {
    "gn:admin1_code":"12",
    "gn:admin2_code":"0.0",
    "gn:admin3_code":"13076.0",
    "gn:admin4_code":"13076078.0",
    "gn:asciiname":"Gustaevel",
    "gn:country_code":"DE",
    "gn:dem":24,
    "gn:feature_class":"P",
    "gn:feature_code":"PPL",
    "gn:name":"Gust\u00e4vel",
    "gn:population":0,
    "gn:timezone":"Europe/Berlin",
    "iso:country":"DE",
    "name:deu_x_preferred":[
        "Gust\u00e4vel"
    ],
    "wof:name":"Gustaevel",
    "wof:placetype":"neighbourhood"
},
  "geometry": {"coordinates":[11.6525,53.69884],"type":"Point"}
}