{
  "type": "Feature",
  "properties": {
    "gn:country":"DE",
    "gn:fcode":"PPL",
    "gn:population":101,
    "iso:country":"DE",
    "name:bak_x_preferred":[
        "\u0422\u0440\u0435\u0437\u0435\u0431\u0443\u0440\u0433"
    ],
    "name:ceb_x_preferred":[
        "Treseburg"
    ],
    "name:deu_x_preferred":[
        "Treseburg"
    ],
    "name:epo_x_preferred":[
        "Treseburg"
    ],
    "name:fas_x_preferred":[
        "\u062a\u0631\u0632\u0628\u0648\u0631\u06af"
    ],
    "name:kaz_x_preferred":[
        "\u0422\u0440\u0435\u0437\u0435\u0431\u0443\u0440\u0433"
    ],
    "name:kir_x_preferred":[
        "\u0422\u0440\u0435\u0437\u0435\u0431\u0443\u0440\u0433"
    ],
    "name:mkd_x_preferred":[
        "\u0422\u0440\u0435\u0437\u0435\u0431\u0443\u0440\u0433"
    ],
    "name:nld_x_preferred":[
        "Treseburg"
    ],
    "name:por_x_preferred":[
        "Treseburg"
    ],
    "name:ron_x_preferred":[
        "Treseburg"
    ],
    "name:rus_x_preferred":[
        "\u0422\u0440\u0435\u0437\u0435\u0431\u0443\u0440\u0433"
    ],
    "name:uzb_x_preferred":[
        "Treseburg"
    ],
    "name:vol_x_preferred":[
        "Treseburg"
    ],
    "qs_pg:aaroncc":"DE",
    "qs_pg:gn_country":"DE",
    "qs_pg:gn_fcode":"PPL",
    "qs_pg:gn_pop":101,
    "qs_pg:name":"Treseburg",
    "qs_pg:name_adm0":"Deutschland",
    "qs_pg:name_adm1":"Sachsen-Anhalt",
    "qs_pg:photos":57,
    "qs_pg:photos_1k":12,
    "qs_pg:photos_9k":1,
    "qs_pg:photos_9r":2,
    "qs_pg:photos_all":57,
    "qs_pg:photos_sr":2,
    "qs_pg:pop_sr":1,
    "qs_pg:qs_pg_placetype":"locality",
    "qs_pg:qs_pg_placetype_gp":"Town",
    "qs_pg:woe_adm0":23424829,
    "woe:adm0_id":23424829,
    "woe:name_adm0":"Deutschland",
    "woe:name_adm1":"Sachsen-Anhalt",
    "woe:placetype":"Town",
    "wof:name":"Treseburg",
    "wof:placetype":"neighbourhood",
    "wof:population":101
},
  "geometry": {"coordinates":[10.97121,51.71608],"type":"Point"}
}