{
  "type": "Feature",
  "properties": {
    "gn:gn_country":"DE",
    "gn:gn_fcode":"PPLA4",
    "gn:gn_pop":521,
    "gn:population":521,
    "iso:country":"DE",
    "name:baq_x_preferred":[
        "Minheim"
    ],
    "name:chi_x_preferred":[
        "\u660e\u6d77\u59c6"
    ],
    "name:dut_x_preferred":[
        "Minheim"
    ],
    "name:eng_x_preferred":[
        "Minheim"
    ],
    "name:epo_x_preferred":[
        "Minheim"
    ],
    "name:fre_x_preferred":[
        "Minheim"
    ],
    "name:ger_x_preferred":[
        "Minheim"
    ],
    "name:hun_x_preferred":[
        "Minheim"
    ],
    "name:ita_x_preferred":[
        "Minheim"
    ],
    "name:jpn_x_preferred":[
        "\u30df\u30f3\u30cf\u30a4\u30e0"
    ],
    "name:may_x_preferred":[
        "Minheim"
    ],
    "name:per_x_preferred":[
        "\u0645\u06cc\u0646\u0647\u0627\u06cc\u0645"
    ],
    "name:pol_x_preferred":[
        "Minheim"
    ],
    "name:por_x_preferred":[
        "Minheim"
    ],
    "name:rum_x_preferred":[
        "Minheim"
    ],
    "name:rus_x_preferred":[
        "\u041c\u0438\u043d\u0445\u0430\u0439\u043c"
    ],
    "name:srp_x_preferred":[
        "\u041c\u0438\u043d\u0445\u0430\u0458\u043c"
    ],
    "name:ukr_x_preferred":[
        "\u041c\u0456\u043d\u0433\u0430\u0439\u043c"
    ],
    "name:uzb_x_preferred":[
        "Minheim"
    ],
    "name:vie_x_preferred":[
        "Minheim"
    ],
    "name:vol_x_preferred":[
        "Minheim"
    ],
    "name:war_x_preferred":[
        "Minheim"
    ],
    "qs_pg:aaroncc":"DE",
    "qs_pg:gn_country":"DE",
    "qs_pg:gn_fcode":"PPLA4",
    "qs_pg:gn_pop":521,
    "qs_pg:name":"Minheim",
    "qs_pg:photos_9r":0,
    "qs_pg:photos_sr":0,
    "qs_pg:pop_sr":2,
    "qs_pg:qs_pg_placetype":"locality",
    "wof:name":"Minheim",
    "wof:placetype":"locality",
    "wof:population":521
},
  "geometry": {"coordinates":[6.93692,49.86493],"type":"Point"}
}