{
  "type": "Feature",
  "properties": {
    "gn:admin1_code":"7",
    "gn:admin2_code":"55.0",
    "gn:admin3_code":"5570.0",
    "gn:admin4_code":"5570040.0",
    "gn:asciiname":"Hardt",
    "gn:country_code":"DE",
    "gn:dem":65,
    "gn:feature_class":"P",
    "gn:feature_code":"PPLL",
    "gn:name":"Hardt",
    "gn:population":0,
    "gn:timezone":"Europe/Berlin",
    "iso:country":"DE",
    "name:ceb_x_preferred":[
        "Hardt"
    ],
    "name:deu_x_preferred":[
        "Hardt"
    ],
    "name:epo_x_preferred":[
        "Hardt"
    ],
    "name:fra_x_preferred":[
        "Hardt"
    ],
    "name:hun_x_preferred":[
        "Hardt"
    ],
    "name:ita_x_preferred":[
        "Hardt"
    ],
    "name:nld_x_preferred":[
        "Hardt"
    ],
    "name:pol_x_preferred":[
        "Hardt"
    ],
    "name:por_x_preferred":[
        "Hardt"
    ],
    "name:ron_x_preferred":[
        "Hardt"
    ],
    "name:rus_x_preferred":[
        "\u0425\u0430\u0440\u0434\u0442"
    ],
    "name:srp_x_preferred":[
        "\u0425\u0430\u0440\u0434\u0442"
    ],
    "name:swe_x_preferred":[
        "Hardt"
    ],
    "name:vol_x_preferred":[
        "Hardt"
    ],
    "wof:name":"Hardt",
    "wof:placetype":"neighbourhood"
},
  "geometry": {"coordinates":[7.87865,51.83064],"type":"Point"}
}