{
  "type": "Feature",
  "properties": {
    "gn:admin1_code":"2.0",
    "gn:admin2_code":"094",
    "gn:admin3_code":"9475.0",
    "gn:admin4_code":"9475184.0",
    "gn:asciiname":"Wulmersreuth",
    "gn:country_code":"DE",
    "gn:dem":548,
    "gn:feature_class":"P",
    "gn:feature_code":"PPL",
    "gn:name":"Wulmersreuth",
    "gn:population":0,
    "gn:timezone":"Europe/Berlin",
    "iso:country":"DE",
    "wof:name":"Wulmersreuth",
    "wof:placetype":"neighbourhood"
},
  "geometry": {"coordinates":[11.83134,50.19014],"type":"Point"}
}