{
  "type": "Feature",
  "properties": {
    "gn:admin1_code":"14.0",
    "gn:admin2_code":"0.0",
    "gn:admin3_code":"15081.0",
    "gn:admin4_code":"15081455.0",
    "gn:asciiname":"Andorf",
    "gn:country_code":"DE",
    "gn:dem":29,
    "gn:feature_class":"P",
    "gn:feature_code":"PPL",
    "gn:name":"Andorf",
    "gn:population":0,
    "gn:timezone":"Europe/Berlin",
    "iso:country":"DE",
    "name:ceb_x_preferred":[
        "Andorf"
    ],
    "name:ces_x_preferred":[
        "Andorf"
    ],
    "name:deu_x_preferred":[
        "Andorf"
    ],
    "name:epo_x_preferred":[
        "Andorf"
    ],
    "name:fas_x_preferred":[
        "\u0622\u0646\u062f\u0648\u0631\u0641"
    ],
    "name:fra_x_preferred":[
        "Andorf"
    ],
    "name:hun_x_preferred":[
        "Andorf"
    ],
    "name:ita_x_preferred":[
        "Andorf"
    ],
    "name:kaz_x_preferred":[
        "\u0410\u043d\u0434\u043e\u0440\u0444"
    ],
    "name:nld_x_preferred":[
        "Andorf"
    ],
    "name:nno_x_preferred":[
        "Andorf"
    ],
    "name:pol_x_preferred":[
        "Andorf"
    ],
    "name:por_x_preferred":[
        "Andorf"
    ],
    "name:rus_x_preferred":[
        "\u0410\u043d\u0434\u043e\u0440\u0444"
    ],
    "name:slk_x_preferred":[
        "Andorf"
    ],
    "name:spa_x_preferred":[
        "Andorf"
    ],
    "name:swe_x_preferred":[
        "Andorf"
    ],
    "name:uzb_x_preferred":[
        "Andorf"
    ],
    "name:vie_x_preferred":[
        "Andorf"
    ],
    "name:vol_x_preferred":[
        "Andorf"
    ],
    "name:war_x_preferred":[
        "Andorf"
    ],
    "name:zho_x_preferred":[
        "\u5b89\u591a\u592b"
    ],
    "wof:name":"Andorf",
    "wof:placetype":"neighbourhood"
},
  "geometry": {"coordinates":[10.99433,52.85663],"type":"Point"}
}