{
  "type": "Feature",
  "properties": {
    "gn:admin1_code":"14.0",
    "gn:admin2_code":"0.0",
    "gn:admin3_code":"15081.0",
    "gn:admin4_code":"15081455.0",
    "gn:asciiname":"Andorf",
    "gn:country_code":"DE",
    "gn:dem":29,
    "gn:feature_class":"P",
    "gn:feature_code":"PPL",
    "gn:name":"Andorf",
    "gn:population":0,
    "gn:timezone":"Europe/Berlin",
    "iso:country":"DE",
    "wof:name":"Andorf",
    "wof:placetype":"neighbourhood"
},
  "geometry": {"coordinates":[10.99433,52.85663],"type":"Point"}
}