{
  "type": "Feature",
  "properties": {
    "gn:admin1_code":"5.0",
    "gn:admin2_code":"065",
    "gn:admin3_code":"6534.0",
    "gn:admin4_code":"6534013.0",
    "gn:asciiname":"Weipoltshausen",
    "gn:country_code":"DE",
    "gn:dem":222,
    "gn:feature_class":"P",
    "gn:feature_code":"PPL",
    "gn:name":"Weipoltshausen",
    "gn:population":0,
    "gn:timezone":"Europe/Berlin",
    "iso:country":"DE",
    "wof:name":"Weipoltshausen",
    "wof:placetype":"neighbourhood"
},
  "geometry": {"coordinates":[8.60281,50.69985],"type":"Point"}
}