{
  "type": "Feature",
  "properties": {
    "gn:admin1_code":"12",
    "gn:admin2_code":"0.0",
    "gn:admin3_code":"13074.0",
    "gn:admin4_code":"13074038.0",
    "gn:asciiname":"Gross Trebbow",
    "gn:country_code":"DE",
    "gn:dem":56,
    "gn:feature_class":"P",
    "gn:feature_code":"PPL",
    "gn:name":"Gro\u00df Trebbow",
    "gn:population":0,
    "gn:timezone":"Europe/Berlin",
    "iso:country":"DE",
    "wof:name":"Gross Trebbow",
    "wof:placetype":"neighbourhood"
},
  "geometry": {"coordinates":[11.35951,53.70871999999999],"type":"Point"}
}