{
  "type": "Feature",
  "properties": {
    "gn:admin1_code":"2",
    "gn:admin2_code":"92.0",
    "gn:admin3_code":"9275.0",
    "gn:admin4_code":"9275145.0",
    "gn:asciiname":"Horgertsham",
    "gn:country_code":"DE",
    "gn:dem":362,
    "gn:feature_class":"P",
    "gn:feature_code":"PPL",
    "gn:name":"H\u00f6rgertsham",
    "gn:population":0,
    "gn:timezone":"Europe/Berlin",
    "iso:country":"DE",
    "wof:name":"Horgertsham",
    "wof:placetype":"neighbourhood"
},
  "geometry": {"coordinates":[13.28526,48.48167],"type":"Point"}
}