{
  "type": "Feature",
  "properties": {
    "gn:country":"DE",
    "gn:fcode":"PPL",
    "gn:population":0,
    "iso:country":"DE",
    "name:als_x_preferred":[
        "Eberstadt"
    ],
    "name:ceb_x_preferred":[
        "Eberstadt"
    ],
    "name:ces_x_preferred":[
        "Eberstadt"
    ],
    "name:dan_x_preferred":[
        "Eberstadt"
    ],
    "name:deu_x_preferred":[
        "Eberstadt"
    ],
    "name:epo_x_preferred":[
        "Eberstadt"
    ],
    "name:eus_x_preferred":[
        "Eberstadt"
    ],
    "name:fas_x_preferred":[
        "\u0627\u0628\u0631\u0634\u062a\u0627\u062a"
    ],
    "name:fra_x_preferred":[
        "Eberstadt"
    ],
    "name:hun_x_preferred":[
        "Eberstadt"
    ],
    "name:ita_x_preferred":[
        "Eberstadt"
    ],
    "name:jpn_x_preferred":[
        "\u30a8\u30fc\u30d0\u30fc\u30b7\u30e5\u30bf\u30c3\u30c8"
    ],
    "name:kaz_x_preferred":[
        "\u042d\u0431\u0435\u0440\u0448\u0442\u0430\u0434\u0442"
    ],
    "name:kir_x_preferred":[
        "\u042d\u0431\u0435\u0440\u0448\u0442\u0430\u0434\u0442"
    ],
    "name:lat_x_preferred":[
        "Eberstadt"
    ],
    "name:lmo_x_preferred":[
        "Eberstadt"
    ],
    "name:msa_x_preferred":[
        "Eberstadt"
    ],
    "name:nld_x_preferred":[
        "Eberstadt"
    ],
    "name:nor_x_preferred":[
        "Eberstadt"
    ],
    "name:pol_x_preferred":[
        "Eberstadt"
    ],
    "name:por_x_preferred":[
        "Eberstadt"
    ],
    "name:ron_x_preferred":[
        "Eberstadt"
    ],
    "name:rus_x_preferred":[
        "\u042d\u0431\u0435\u0440\u0448\u0442\u0430\u0434\u0442"
    ],
    "name:srp_x_preferred":[
        "\u0415\u0431\u0435\u0440\u0448\u0442\u0430\u0442"
    ],
    "name:ukr_x_preferred":[
        "\u0415\u0431\u0435\u0440\u0448\u0442\u0430\u0434\u0442"
    ],
    "name:uzb_x_preferred":[
        "Eberstadt"
    ],
    "name:vol_x_preferred":[
        "Eberstadt"
    ],
    "name:war_x_preferred":[
        "Eberstadt"
    ],
    "name:zho_x_preferred":[
        "\u57c3\u4f2f\u65bd\u5854\u7279"
    ],
    "qs_pg:aaroncc":"DE",
    "qs_pg:gn_country":"DE",
    "qs_pg:gn_fcode":"PPL",
    "qs_pg:gn_pop":0,
    "qs_pg:name":"Eberstadt",
    "qs_pg:name_adm0":"Deutschland",
    "qs_pg:name_adm1":"Hessen",
    "qs_pg:photos_9k":1,
    "qs_pg:photos_9r":1,
    "qs_pg:photos_all":1,
    "qs_pg:photos_sr":0,
    "qs_pg:pop_sr":0,
    "qs_pg:qs_pg_placetype":"locality",
    "qs_pg:qs_pg_placetype_gp":"Town",
    "qs_pg:woe_adm0":23424829,
    "woe:adm0_id":23424829,
    "woe:name_adm0":"Deutschland",
    "woe:name_adm1":"Hessen",
    "woe:placetype":"Town",
    "wof:name":"Eberstadt",
    "wof:placetype":"neighbourhood"
},
  "geometry": {"coordinates":[8.75954,50.48034],"type":"Point"}
}