{
  "type": "Feature",
  "properties": {
    "gn:admin1_code":"10",
    "gn:admin2_code":"0.0",
    "gn:admin3_code":"1003.0",
    "gn:admin4_code":"1003000.0",
    "gn:asciiname":"Reecke",
    "gn:country_code":"DE",
    "gn:dem":14,
    "gn:feature_class":"P",
    "gn:feature_code":"PPL",
    "gn:name":"Reecke",
    "gn:population":0,
    "gn:timezone":"Europe/Berlin",
    "iso:country":"DE",
    "wof:name":"Reecke",
    "wof:placetype":"neighbourhood"
},
  "geometry": {"coordinates":[10.57314,53.83318000000001],"type":"Point"}
}