{
  "type": "Feature",
  "properties": {
    "gn:admin1_code":"7",
    "gn:admin2_code":"53.0",
    "gn:admin3_code":"5358.0",
    "gn:admin4_code":"5358008.0",
    "gn:asciiname":"Hoven",
    "gn:country_code":"DE",
    "gn:dem":113,
    "gn:feature_class":"P",
    "gn:feature_code":"PPL",
    "gn:name":"Hoven",
    "gn:population":0,
    "gn:timezone":"Europe/Berlin",
    "iso:country":"DE",
    "name:ceb_x_preferred":[
        "Hoven"
    ],
    "name:dan_x_preferred":[
        "Hoven"
    ],
    "name:deu_x_preferred":[
        "Hoven"
    ],
    "name:fra_x_preferred":[
        "Hoven"
    ],
    "name:ita_x_preferred":[
        "Hoven"
    ],
    "name:lav_x_preferred":[
        "Hovens"
    ],
    "name:nld_x_preferred":[
        "Hoven"
    ],
    "name:pol_x_preferred":[
        "Hoven"
    ],
    "wof:name":"Hoven",
    "wof:placetype":"neighbourhood"
},
  "geometry": {"coordinates":[6.43853,50.83132],"type":"Point"}
}