{
  "type": "Feature",
  "properties": {
    "gn:admin1_code":"2",
    "gn:admin2_code":"93.0",
    "gn:admin3_code":"9377.0",
    "gn:admin4_code":"9377157.0",
    "gn:asciiname":"Schafbruck",
    "gn:country_code":"DE",
    "gn:dem":674,
    "gn:feature_class":"P",
    "gn:feature_code":"PPL",
    "gn:name":"Schafbruck",
    "gn:population":0,
    "gn:timezone":"Europe/Berlin",
    "iso:country":"DE",
    "wof:name":"Schafbruck",
    "wof:placetype":"neighbourhood"
},
  "geometry": {"coordinates":[12.10496,49.94233],"type":"Point"}
}