{
  "type": "Feature",
  "properties": {
    "gn:country":"DE",
    "gn:fcode":"PPL",
    "gn:population":0,
    "iso:country":"DE",
    "name:ceb_x_preferred":[
        "Hofgarten"
    ],
    "name:deu_x_preferred":[
        "Hofgarten"
    ],
    "name:ind_x_preferred":[
        "Hofgarten"
    ],
    "name:ita_x_preferred":[
        "Hofgarten"
    ],
    "name:rus_x_preferred":[
        "\u0425\u043e\u0444\u0433\u0430\u0440\u0442\u0435\u043d"
    ],
    "name:swe_x_preferred":[
        "Hofgarten"
    ],
    "qs_pg:aaroncc":"DE",
    "qs_pg:gn_country":"DE",
    "qs_pg:gn_fcode":"PPL",
    "qs_pg:gn_pop":0,
    "qs_pg:name":"Hofgarten",
    "qs_pg:name_adm0":"Deutschland",
    "qs_pg:name_adm1":"Bayern",
    "qs_pg:photos_9k":1,
    "qs_pg:photos_9r":1,
    "qs_pg:photos_all":2,
    "qs_pg:photos_sr":0,
    "qs_pg:pop_sr":0,
    "qs_pg:qs_pg_placetype":"locality",
    "qs_pg:qs_pg_placetype_gp":"Town",
    "qs_pg:woe_adm0":23424829,
    "woe:adm0_id":23424829,
    "woe:name_adm0":"Deutschland",
    "woe:name_adm1":"Bayern",
    "woe:placetype":"Town",
    "wof:name":"Hofgarten",
    "wof:placetype":"neighbourhood"
},
  "geometry": {"coordinates":[11.06024,48.44005],"type":"Point"}
}