{
  "type": "Feature",
  "properties": {
    "gn:admin1_code":"5",
    "gn:admin2_code":"66.0",
    "gn:admin3_code":"6634.0",
    "gn:admin4_code":"6634003.0",
    "gn:asciiname":"Hesslar",
    "gn:country_code":"DE",
    "gn:dem":261,
    "gn:feature_class":"P",
    "gn:feature_code":"PPL",
    "gn:name":"He\u00dflar",
    "gn:population":0,
    "gn:timezone":"Europe/Berlin",
    "iso:country":"DE",
    "wof:name":"Hesslar",
    "wof:placetype":"neighbourhood"
},
  "geometry": {"coordinates":[9.48367,51.1337],"type":"Point"}
}