{
  "type": "Feature",
  "properties": {
    "gn:admin1_code":"7",
    "gn:admin2_code":"59.0",
    "gn:admin3_code":"5962.0",
    "gn:admin4_code":"5962012.0",
    "gn:asciiname":"Nieder Buschhausen",
    "gn:country_code":"DE",
    "gn:dem":362,
    "gn:feature_class":"P",
    "gn:feature_code":"PPL",
    "gn:name":"Nieder Buschhausen",
    "gn:population":0,
    "gn:timezone":"Europe/Berlin",
    "iso:country":"DE",
    "wof:name":"Nieder Buschhausen",
    "wof:placetype":"neighbourhood"
},
  "geometry": {"coordinates":[7.45273,51.21371],"type":"Point"}
}