{
  "type": "Feature",
  "properties": {
    "gn:admin1_code":"13",
    "gn:admin2_code":"0.0",
    "gn:admin3_code":"14627.0",
    "gn:admin4_code":"14627180.0",
    "gn:asciiname":"Loesten",
    "gn:country_code":"DE",
    "gn:dem":196,
    "gn:feature_class":"P",
    "gn:feature_code":"PPL",
    "gn:name":"L\u00f6sten",
    "gn:population":0,
    "gn:timezone":"Europe/Berlin",
    "iso:country":"DE",
    "wof:name":"Loesten",
    "wof:placetype":"neighbourhood"
},
  "geometry": {"coordinates":[13.32787,51.12848],"type":"Point"}
}