{
  "type": "Feature",
  "properties": {
    "gn:admin1_code":"13.0",
    "gn:admin2_code":"00",
    "gn:admin3_code":"14524.0",
    "gn:admin4_code":"14524200.0",
    "gn:asciiname":"Wulm",
    "gn:country_code":"DE",
    "gn:dem":251,
    "gn:feature_class":"P",
    "gn:feature_code":"PPL",
    "gn:name":"Wulm",
    "gn:population":0,
    "gn:timezone":"Europe/Berlin",
    "iso:country":"DE",
    "wof:name":"Wulm",
    "wof:placetype":"neighbourhood"
},
  "geometry": {"coordinates":[12.49901,50.77855],"type":"Point"}
}