{
  "type": "Feature",
  "properties": {
    "gn:admin1_code":"7.0",
    "gn:admin2_code":"51.0",
    "gn:admin3_code":"5170.0",
    "gn:admin4_code":"5170032.0",
    "gn:asciiname":"Annaberg",
    "gn:country_code":"DE",
    "gn:dem":23,
    "gn:feature_class":"P",
    "gn:feature_code":"PPL",
    "gn:name":"Annaberg",
    "gn:population":0,
    "gn:timezone":"Europe/Berlin",
    "iso:country":"DE",
    "name:ceb_x_preferred":[
        "Annaberg"
    ],
    "name:ces_x_preferred":[
        "Annaberg"
    ],
    "name:deu_x_preferred":[
        "Annaberg"
    ],
    "name:est_x_preferred":[
        "Annaberg"
    ],
    "name:fra_x_preferred":[
        "Annaberg"
    ],
    "name:hun_x_preferred":[
        "Annaberg"
    ],
    "name:ita_x_preferred":[
        "Annaberg"
    ],
    "name:mkd_x_preferred":[
        "\u0410\u043d\u0430\u0431\u0435\u0440\u0433"
    ],
    "name:nld_x_preferred":[
        "Annaberg"
    ],
    "name:pol_x_preferred":[
        "Annaberg"
    ],
    "name:rus_x_preferred":[
        "\u0410\u043d\u043d\u0430\u0431\u0435\u0440\u0433"
    ],
    "name:swe_x_preferred":[
        "Annaberg"
    ],
    "name:ukr_x_preferred":[
        "\u0410\u043d\u043d\u0430\u0431\u0435\u0440\u0433"
    ],
    "wof:name":"Annaberg",
    "wof:placetype":"neighbourhood"
},
  "geometry": {"coordinates":[6.58712,51.54715],"type":"Point"}
}