{
  "type": "Feature",
  "properties": {
    "gn:admin1_code":"1",
    "gn:admin2_code":"84.0",
    "gn:admin3_code":"8436.0",
    "gn:admin4_code":"8436008.0",
    "gn:asciiname":"Geiger",
    "gn:country_code":"DE",
    "gn:dem":563,
    "gn:feature_class":"P",
    "gn:feature_code":"PPL",
    "gn:name":"Geiger",
    "gn:population":0,
    "gn:timezone":"Europe/Berlin",
    "iso:country":"DE",
    "name:ceb_x_preferred":[
        "Geiger"
    ],
    "name:ces_x_preferred":[
        "Geiger"
    ],
    "name:dan_x_preferred":[
        "Geiger"
    ],
    "name:deu_x_preferred":[
        "Geiger"
    ],
    "name:fas_x_preferred":[
        "\u06af\u0627\u06cc\u06af\u0631"
    ],
    "name:fin_x_preferred":[
        "Geiger"
    ],
    "name:fra_x_preferred":[
        "Geiger"
    ],
    "name:heb_x_preferred":[
        "\u05d2\u05d9\u05d9\u05d2\u05e8"
    ],
    "name:ita_x_preferred":[
        "Geiger"
    ],
    "name:nld_x_preferred":[
        "Geiger"
    ],
    "name:pol_x_preferred":[
        "Geiger"
    ],
    "name:por_x_preferred":[
        "Geiger"
    ],
    "name:rus_x_preferred":[
        "\u0413\u0435\u0439\u0433\u0435\u0440"
    ],
    "name:swe_x_preferred":[
        "Geiger"
    ],
    "name:ukr_x_preferred":[
        "\u0413\u0435\u0439\u0433\u0435\u0440"
    ],
    "wof:name":"Geiger",
    "wof:placetype":"neighbourhood"
},
  "geometry": {"coordinates":[9.64431,47.9158],"type":"Point"}
}