{
  "type": "Feature",
  "properties": {
    "gn:admin1_code":"13",
    "gn:admin2_code":"0.0",
    "gn:admin3_code":"14523.0",
    "gn:admin4_code":"14523080.0",
    "gn:asciiname":"Pabstleithen",
    "gn:country_code":"DE",
    "gn:dem":588,
    "gn:feature_class":"P",
    "gn:feature_code":"PPL",
    "gn:name":"Pabstleithen",
    "gn:population":0,
    "gn:timezone":"Europe/Berlin",
    "iso:country":"DE",
    "wof:name":"Pabstleithen",
    "wof:placetype":"neighbourhood"
},
  "geometry": {"coordinates":[12.1253,50.32026],"type":"Point"}
}