{
  "type": "Feature",
  "properties": {
    "gn:admin1_code":"7.0",
    "gn:admin2_code":"59.0",
    "gn:admin3_code":"5958.0",
    "gn:admin4_code":"5958012.0",
    "gn:asciiname":"Altenbueren",
    "gn:country_code":"DE",
    "gn:dem":467,
    "gn:elevation":"464.0",
    "gn:feature_class":"P",
    "gn:feature_code":"PPL",
    "gn:name":"Altenb\u00fcren",
    "gn:population":1321,
    "gn:timezone":"Europe/Berlin",
    "iso:country":"DE",
    "wof:name":"Altenbueren",
    "wof:placetype":"neighbourhood",
    "wof:population":1321
},
  "geometry": {"coordinates":[8.50584,51.38634],"type":"Point"}
}