{
  "type": "Feature",
  "properties": {
    "gn:admin1_code":"1",
    "gn:admin2_code":"81.0",
    "gn:admin3_code":"8128.0",
    "gn:admin4_code":"8128131.0",
    "gn:asciiname":"Schafhof",
    "gn:country_code":"DE",
    "gn:dem":247,
    "gn:feature_class":"P",
    "gn:feature_code":"PPL",
    "gn:name":"Schafhof",
    "gn:population":0,
    "gn:timezone":"Europe/Berlin",
    "iso:country":"DE",
    "wof:name":"Schafhof",
    "wof:placetype":"neighbourhood"
},
  "geometry": {"coordinates":[9.55921,49.71804],"type":"Point"}
}