{
  "type": "Feature",
  "properties": {
    "gn:admin1_code":"7",
    "gn:admin2_code":"57.0",
    "gn:admin3_code":"5770.0",
    "gn:admin4_code":"5770044.0",
    "gn:asciiname":"Osterheide",
    "gn:country_code":"DE",
    "gn:dem":50,
    "gn:feature_class":"P",
    "gn:feature_code":"PPLL",
    "gn:name":"Osterheide",
    "gn:population":0,
    "gn:timezone":"Europe/Berlin",
    "iso:country":"DE",
    "name:deu_x_preferred":[
        "Osterheide"
    ],
    "name:est_x_preferred":[
        "Osterheide"
    ],
    "name:fas_x_preferred":[
        "\u0627\u0648\u0634\u062a\u0631\u0647\u0627\u06cc\u062f\u0647"
    ],
    "name:ita_x_preferred":[
        "Osterheide"
    ],
    "name:msa_x_preferred":[
        "Osterheide"
    ],
    "name:nld_x_preferred":[
        "Osterheide"
    ],
    "name:pol_x_preferred":[
        "Osterheide"
    ],
    "name:por_x_preferred":[
        "Osterheide"
    ],
    "name:ron_x_preferred":[
        "Osterheide"
    ],
    "name:ukr_x_preferred":[
        "\u041e\u0441\u0442\u0435\u0440\u0433\u0430\u0439\u0434\u0435"
    ],
    "name:war_x_preferred":[
        "Osterheide"
    ],
    "name:zho_x_preferred":[
        "\u5965\u65af\u7279\u8d56\u5fb7"
    ],
    "wof:name":"Osterheide",
    "wof:placetype":"neighbourhood"
},
  "geometry": {"coordinates":[8.5054,52.3729],"type":"Point"}
}