{
  "type": "Feature",
  "properties": {
    "gn:gn_country":"DE",
    "gn:gn_fcode":"PPL",
    "gn:gn_pop":0,
    "iso:country":"DE",
    "qs_pg:aaroncc":"DE",
    "qs_pg:gn_country":"DE",
    "qs_pg:gn_fcode":"PPL",
    "qs_pg:gn_pop":0,
    "qs_pg:name":"Breitenbach",
    "qs_pg:name_adm0":"Deutschland",
    "qs_pg:name_adm1":"Th\u00fcringen",
    "qs_pg:photos_9r":0,
    "qs_pg:photos_sr":0,
    "qs_pg:pop_sr":0,
    "qs_pg:qs_pg_placetype":"locality",
    "qs_pg:qs_pg_placetype_gp":"Town",
    "qs_pg:woe_adm0":23424829,
    "woe:adm0_id":23424829,
    "woe:name_adm0":"Deutschland",
    "woe:name_adm1":"Th\u00fcringen",
    "woe:placetype":"Town",
    "wof:name":"Breitenbach",
    "wof:placetype":"neighbourhood"
},
  "geometry": {"coordinates":[10.77737,50.53846],"type":"Point"}
}