{
  "type": "Feature",
  "properties": {
    "gn:country":"DE",
    "gn:fcode":"PPL",
    "gn:population":0,
    "iso:country":"DE",
    "name:als_x_preferred":[
        "Breitenbach"
    ],
    "name:cat_x_preferred":[
        "Breitenbach"
    ],
    "name:ceb_x_preferred":[
        "Breitenbach"
    ],
    "name:deu_x_preferred":[
        "Breitenbach"
    ],
    "name:epo_x_preferred":[
        "Breitenbach"
    ],
    "name:eus_x_preferred":[
        "Breitenbach"
    ],
    "name:fra_x_preferred":[
        "Breitenbach"
    ],
    "name:ita_x_preferred":[
        "Breitenbach"
    ],
    "name:jpn_x_preferred":[
        "\u30d6\u30e9\u30a4\u30c6\u30f3\u30d0\u30c3\u30cf"
    ],
    "name:kor_x_preferred":[
        "\ube0c\ub77c\uc774\ud150\ubc14\ud750"
    ],
    "name:nld_x_preferred":[
        "Breitenbach"
    ],
    "name:pol_x_preferred":[
        "Breitenbach"
    ],
    "name:por_x_preferred":[
        "Breitenbach"
    ],
    "name:rus_x_preferred":[
        "\u0411\u0440\u0430\u0439\u0442\u0435\u043d\u0431\u0430\u0445"
    ],
    "name:spa_x_preferred":[
        "Breitenbach"
    ],
    "name:srp_x_preferred":[
        "\u0411\u0440\u0430\u0458\u0442\u0435\u043d\u0431\u0430\u0445"
    ],
    "name:swe_x_preferred":[
        "Breitenbach"
    ],
    "name:vol_x_preferred":[
        "Breitenbach"
    ],
    "qs_pg:aaroncc":"DE",
    "qs_pg:gn_country":"DE",
    "qs_pg:gn_fcode":"PPL",
    "qs_pg:gn_pop":0,
    "qs_pg:name":"Breitenbach",
    "qs_pg:name_adm0":"Deutschland",
    "qs_pg:name_adm1":"Th\u00fcringen",
    "qs_pg:photos_9r":0,
    "qs_pg:photos_sr":0,
    "qs_pg:pop_sr":0,
    "qs_pg:qs_pg_placetype":"locality",
    "qs_pg:qs_pg_placetype_gp":"Town",
    "qs_pg:woe_adm0":23424829,
    "woe:adm0_id":23424829,
    "woe:name_adm0":"Deutschland",
    "woe:name_adm1":"Th\u00fcringen",
    "woe:placetype":"Town",
    "wof:name":"Breitenbach",
    "wof:placetype":"neighbourhood"
},
  "geometry": {"coordinates":[10.77737,50.53846],"type":"Point"}
}