{
  "type": "Feature",
  "properties": {
    "iso:country":"DE",
    "name:deu_x_preferred":[
        "Grumme"
    ],
    "name:tur_x_preferred":[
        "Bochum-Grumme"
    ],
    "wof:name":"Grumme",
    "wof:placetype":"neighbourhood"
},
  "geometry": {"coordinates":[7.23245885357334,51.49879202877701],"type":"Point"}
}