{
  "type": "Feature",
  "properties": {
    "gn:admin1_code":"1",
    "gn:admin2_code":"84.0",
    "gn:admin3_code":"8435.0",
    "gn:admin4_code":"8435052.0",
    "gn:asciiname":"Buggensegel",
    "gn:country_code":"DE",
    "gn:dem":433,
    "gn:feature_class":"P",
    "gn:feature_code":"PPL",
    "gn:name":"Buggensegel",
    "gn:population":0,
    "gn:timezone":"Europe/Berlin",
    "iso:country":"DE",
    "wof:name":"Buggensegel",
    "wof:placetype":"neighbourhood"
},
  "geometry": {"coordinates":[9.30236,47.74469000000001],"type":"Point"}
}