{
  "type": "Feature",
  "properties": {
    "gn:admin1_code":"1",
    "gn:admin2_code":"84.0",
    "gn:admin3_code":"8435.0",
    "gn:admin4_code":"8435035.0",
    "gn:asciiname":"Kehlen",
    "gn:country_code":"DE",
    "gn:dem":411,
    "gn:feature_class":"P",
    "gn:feature_code":"PPL",
    "gn:name":"Kehlen",
    "gn:population":0,
    "gn:timezone":"Europe/Berlin",
    "iso:country":"DE",
    "name:als_x_preferred":[
        "Kielen"
    ],
    "name:bel_x_preferred":[
        "\u041a\u0435\u043b\u0435\u043d"
    ],
    "name:cat_x_preferred":[
        "Kehlen"
    ],
    "name:ceb_x_preferred":[
        "Kehlen"
    ],
    "name:dan_x_preferred":[
        "Kehlen"
    ],
    "name:deu_x_preferred":[
        "Kehlen"
    ],
    "name:fas_x_preferred":[
        "\u06a9\u0647\u0644\u0646"
    ],
    "name:fra_x_preferred":[
        "Kehlen"
    ],
    "name:ita_x_preferred":[
        "Kehlen"
    ],
    "name:ltz_x_preferred":[
        "Gemeng Kielen"
    ],
    "name:msa_x_preferred":[
        "Kehlen"
    ],
    "name:nds_x_preferred":[
        "Gemeen Kehlen"
    ],
    "name:nld_x_preferred":[
        "Kehlen"
    ],
    "name:nor_x_preferred":[
        "Kehlen"
    ],
    "name:pol_x_preferred":[
        "Kehlen"
    ],
    "name:por_x_preferred":[
        "Kehlen"
    ],
    "name:rus_x_preferred":[
        "\u041a\u0435\u043b\u0435\u043d"
    ],
    "name:slk_x_preferred":[
        "Kehlen"
    ],
    "name:swe_x_preferred":[
        "Kehlen"
    ],
    "name:ukr_x_preferred":[
        "\u041a\u0435\u043b\u0435\u043d"
    ],
    "wof:name":"Kehlen",
    "wof:placetype":"neighbourhood"
},
  "geometry": {"coordinates":[9.55504,47.68505],"type":"Point"}
}