{
  "type": "Feature",
  "properties": {
    "gn:admin1_code":"2",
    "gn:admin2_code":"91.0",
    "gn:admin3_code":"9190.0",
    "gn:admin4_code":"9190121.0",
    "gn:asciiname":"Obereglfing",
    "gn:country_code":"DE",
    "gn:dem":658,
    "gn:feature_class":"P",
    "gn:feature_code":"PPL",
    "gn:name":"Obereglfing",
    "gn:population":0,
    "gn:timezone":"Europe/Berlin",
    "iso:country":"DE",
    "wof:name":"Obereglfing",
    "wof:placetype":"neighbourhood"
},
  "geometry": {"coordinates":[11.17748,47.73511],"type":"Point"}
}