{
  "type": "Feature",
  "properties": {
    "iso:country":"DE",
    "wof:name":"Giesenkirchen-Mitte",
    "wof:placetype":"neighbourhood"
},
  "geometry": {"coordinates":[6.48550124109564,51.15463781386675],"type":"Point"}
}