{
  "type": "Feature",
  "properties": {
    "gn:admin1_code":"2",
    "gn:admin2_code":"96.0",
    "gn:admin3_code":"9674.0",
    "gn:admin4_code":"9674187.0",
    "gn:asciiname":"Furnbach",
    "gn:country_code":"DE",
    "gn:dem":321,
    "gn:feature_class":"P",
    "gn:feature_code":"PPL",
    "gn:name":"F\u00fcrnbach",
    "gn:population":0,
    "gn:timezone":"Europe/Berlin",
    "iso:country":"DE",
    "wof:name":"Furnbach",
    "wof:placetype":"neighbourhood"
},
  "geometry": {"coordinates":[10.63425,49.89216],"type":"Point"}
}