{
  "type": "Feature",
  "properties": {
    "iso:country":"DE",
    "wof:name":"Ellinghausen",
    "wof:placetype":"neighbourhood"
},
  "geometry": {"coordinates":[7.43020571179295,51.55486203065969],"type":"Point"}
}