{
  "type": "Feature",
  "properties": {
    "gn:admin1_code":"6",
    "gn:admin2_code":"0.0",
    "gn:admin3_code":"3405.0",
    "gn:admin4_code":"3405000.0",
    "gn:asciiname":"Wehlens",
    "gn:country_code":"DE",
    "gn:dem":1,
    "gn:feature_class":"P",
    "gn:feature_code":"PPL",
    "gn:name":"Wehlens",
    "gn:population":0,
    "gn:timezone":"Europe/Berlin",
    "iso:country":"DE",
    "wof:name":"Wehlens",
    "wof:placetype":"neighbourhood"
},
  "geometry": {"coordinates":[8.03532,53.59004],"type":"Point"}
}