{
  "type": "Feature",
  "properties": {
    "gn:admin1_code":"15",
    "gn:admin2_code":"0.0",
    "gn:admin3_code":"16076.0",
    "gn:admin4_code":"16076004.0",
    "gn:asciiname":"Eula",
    "gn:country_code":"DE",
    "gn:dem":323,
    "gn:feature_class":"P",
    "gn:feature_code":"PPL",
    "gn:name":"Eula",
    "gn:population":0,
    "gn:timezone":"Europe/Berlin",
    "iso:country":"DE",
    "name:deu_x_preferred":[
        "Eula"
    ],
    "wof:name":"Eula",
    "wof:placetype":"neighbourhood"
},
  "geometry": {"coordinates":[12.16091,50.72962],"type":"Point"}
}