{
  "type": "Feature",
  "properties": {
    "gn:admin1_code":"13",
    "gn:admin2_code":"0.0",
    "gn:admin3_code":"14524.0",
    "gn:admin4_code":"14524140.0",
    "gn:asciiname":"Walddorf",
    "gn:country_code":"DE",
    "gn:dem":347,
    "gn:feature_class":"P",
    "gn:feature_code":"PPL",
    "gn:name":"Walddorf",
    "gn:population":0,
    "gn:timezone":"Europe/Berlin",
    "iso:country":"DE",
    "wof:name":"Walddorf",
    "wof:placetype":"neighbourhood"
},
  "geometry": {"coordinates":[12.2526,50.74636],"type":"Point"}
}