{
  "type": "Feature",
  "properties": {
    "gn:admin1_code":"2",
    "gn:admin2_code":"95.0",
    "gn:admin3_code":"9573.0",
    "gn:admin4_code":"9573120.0",
    "gn:asciiname":"Klaushof",
    "gn:country_code":"DE",
    "gn:dem":340,
    "gn:feature_class":"P",
    "gn:feature_code":"PPL",
    "gn:name":"Klaushof",
    "gn:population":0,
    "gn:timezone":"Europe/Berlin",
    "iso:country":"DE",
    "wof:name":"Klaushof",
    "wof:placetype":"neighbourhood"
},
  "geometry": {"coordinates":[10.79925,49.46791],"type":"Point"}
}