{
  "type": "Feature",
  "properties": {
    "gn:country":"DE",
    "gn:fcode":"PPL",
    "gn:population":0,
    "iso:country":"DE",
    "name:ara_x_preferred":[
        "\u0643\u064a\u0631\u062e\u0628\u0631\u063a \u0641\u064a \u062a\u064a\u0631\u0648\u0644"
    ],
    "name:ceb_x_preferred":[
        "Kirchberg in Tirol"
    ],
    "name:ces_x_preferred":[
        "Kirchberg in Tirol"
    ],
    "name:deu_x_preferred":[
        "Kirchberg in Tirol"
    ],
    "name:est_x_preferred":[
        "Kirchberg in Tirol"
    ],
    "name:fas_x_preferred":[
        "\u06a9\u06cc\u0631\u0634\u0628\u0631\u06af \u06cc\u0646 \u062a\u06cc\u0631\u0648\u0644"
    ],
    "name:fra_x_preferred":[
        "Kirchberg in Tirol"
    ],
    "name:hun_x_preferred":[
        "Kirchberg in Tirol"
    ],
    "name:ita_x_preferred":[
        "Kirchberg in Tirol"
    ],
    "name:kaz_x_preferred":[
        "\u041a\u0438\u0440\u0445\u0431\u0435\u0440\u0433"
    ],
    "name:lmo_x_preferred":[
        "Kirchberg in Tirol"
    ],
    "name:nld_x_preferred":[
        "Kirchberg in Tirol"
    ],
    "name:nno_x_preferred":[
        "Kirchberg in Tirol"
    ],
    "name:pnb_x_preferred":[
        "\u06a9\u0631\u062e\u0628\u0631\u06af \u0627\u0646 \u0679\u06cc\u0631\u0648\u0644"
    ],
    "name:pol_x_preferred":[
        "Kirchberg in Tirol"
    ],
    "name:por_x_preferred":[
        "Kirchberg in Tirol"
    ],
    "name:rus_x_preferred":[
        "\u041a\u0438\u0440\u0445\u0431\u0435\u0440\u0433"
    ],
    "name:slk_x_preferred":[
        "Kirchberg in Tirol"
    ],
    "name:spa_x_preferred":[
        "Kirchberg in Tirol"
    ],
    "name:swe_x_preferred":[
        "Kirchberg in Tirol"
    ],
    "name:ukr_x_preferred":[
        "\u041a\u0456\u0440\u0445\u0431\u0435\u0440\u0433"
    ],
    "name:uzb_x_preferred":[
        "Kirchberg in Tirol"
    ],
    "name:vol_x_preferred":[
        "Kirchberg in Tirol"
    ],
    "name:war_x_preferred":[
        "Kirchberg in Tirol"
    ],
    "name:zho_x_preferred":[
        "\u8482\u7f57\u5c14\u5dde\u57fa\u5e0c\u8d1d\u683c"
    ],
    "qs_pg:aaroncc":"DE",
    "qs_pg:gn_country":"DE",
    "qs_pg:gn_fcode":"PPL",
    "qs_pg:gn_pop":0,
    "qs_pg:name":"Kirchberg in Tirol",
    "qs_pg:name_adm0":"\u00d6sterreich",
    "qs_pg:name_adm1":"Tirol",
    "qs_pg:photos":1060,
    "qs_pg:photos_1k":215,
    "qs_pg:photos_9k":5,
    "qs_pg:photos_9r":7,
    "qs_pg:photos_all":1060,
    "qs_pg:photos_sr":11,
    "qs_pg:pop_sr":0,
    "qs_pg:qs_pg_placetype":"locality",
    "qs_pg:qs_pg_placetype_gp":"Town",
    "qs_pg:woe_adm0":23424750,
    "woe:adm0_id":23424750,
    "woe:name_adm0":"\u00d6sterreich",
    "woe:name_adm1":"Tirol",
    "woe:placetype":"Town",
    "wof:name":"Kirchberg in Tirol",
    "wof:placetype":"neighbourhood"
},
  "geometry": {"coordinates":[12.51427,48.00906],"type":"Point"}
}