{
  "type": "Feature",
  "properties": {
    "gn:admin1_code":"11",
    "gn:admin2_code":"0.0",
    "gn:admin3_code":"12073.0",
    "gn:admin4_code":"12073261.0",
    "gn:asciiname":"Grunow",
    "gn:country_code":"DE",
    "gn:dem":61,
    "gn:feature_class":"P",
    "gn:feature_code":"PPLA4",
    "gn:name":"Gr\u00fcnow",
    "gn:population":0,
    "gn:timezone":"Europe/Berlin",
    "iso:country":"DE",
    "wof:name":"Grunow",
    "wof:placetype":"neighbourhood"
},
  "geometry": {"coordinates":[13.95,53.31667],"type":"Point"}
}