{
  "type": "Feature",
  "properties": {
    "gn:admin1_code":"1",
    "gn:admin2_code":"83.0",
    "gn:admin3_code":"8326.0",
    "gn:admin4_code":"8326017.0",
    "gn:asciiname":"Neukirch",
    "gn:country_code":"DE",
    "gn:dem":969,
    "gn:feature_class":"P",
    "gn:feature_code":"PPL",
    "gn:name":"Neukirch",
    "gn:population":0,
    "gn:timezone":"Europe/Berlin",
    "iso:country":"DE",
    "name:ceb_x_preferred":[
        "Neukirch"
    ],
    "name:deu_x_preferred":[
        "Neukirch"
    ],
    "name:epo_x_preferred":[
        "Neukirch"
    ],
    "name:est_x_preferred":[
        "Neukirch"
    ],
    "name:fra_x_preferred":[
        "Neukirch"
    ],
    "name:ita_x_preferred":[
        "Neukirch"
    ],
    "name:mkd_x_preferred":[
        "\u041d\u043e\u0458\u043a\u0438\u0440\u0445"
    ],
    "name:nld_x_preferred":[
        "Neukirch"
    ],
    "name:pol_x_preferred":[
        "Neukirch"
    ],
    "name:rus_x_preferred":[
        "\u041d\u0435\u0439\u043a\u0438\u0440\u0445"
    ],
    "name:srp_x_preferred":[
        "\u041d\u043e\u0458\u043a\u0438\u0440\u0445"
    ],
    "name:swe_x_preferred":[
        "Neukirch"
    ],
    "name:vol_x_preferred":[
        "Neukirch"
    ],
    "wof:name":"Neukirch",
    "wof:placetype":"neighbourhood"
},
  "geometry": {"coordinates":[8.17421,48.02486],"type":"Point"}
}