{
  "type": "Feature",
  "properties": {
    "gn:admin1_code":"12",
    "gn:admin2_code":"0.0",
    "gn:admin3_code":"13072.0",
    "gn:admin4_code":"13072103.0",
    "gn:asciiname":"Pohnstorf",
    "gn:country_code":"DE",
    "gn:dem":29,
    "gn:feature_class":"P",
    "gn:feature_code":"PPL",
    "gn:name":"Pohnstorf",
    "gn:population":0,
    "gn:timezone":"Europe/Berlin",
    "iso:country":"DE",
    "wof:name":"Pohnstorf",
    "wof:placetype":"neighbourhood"
},
  "geometry": {"coordinates":[12.57782,53.86751999999999],"type":"Point"}
}