{
  "type": "Feature",
  "properties": {
    "gn:admin1_code":"2.0",
    "gn:admin2_code":"094",
    "gn:admin3_code":"9477.0",
    "gn:admin4_code":"9477128.0",
    "gn:asciiname":"Wickenreuth",
    "gn:country_code":"DE",
    "gn:dem":319,
    "gn:feature_class":"P",
    "gn:feature_code":"PPL",
    "gn:name":"Wickenreuth",
    "gn:population":0,
    "gn:timezone":"Europe/Berlin",
    "iso:country":"DE",
    "wof:name":"Wickenreuth",
    "wof:placetype":"neighbourhood"
},
  "geometry": {"coordinates":[11.44504,50.07928],"type":"Point"}
}