{
  "type": "Feature",
  "properties": {
    "gn:admin1_code":"2.0",
    "gn:admin2_code":"093",
    "gn:admin3_code":"9376.0",
    "gn:admin4_code":"9376150.0",
    "gn:asciiname":"Wohlsbach",
    "gn:country_code":"DE",
    "gn:dem":380,
    "gn:feature_class":"P",
    "gn:feature_code":"PPL",
    "gn:name":"Wohlsbach",
    "gn:population":0,
    "gn:timezone":"Europe/Berlin",
    "iso:country":"DE",
    "wof:name":"Wohlsbach",
    "wof:placetype":"neighbourhood"
},
  "geometry": {"coordinates":[12.16433,49.53579000000001],"type":"Point"}
}