{
  "type": "Feature",
  "properties": {
    "gn:admin1_code":"2",
    "gn:admin2_code":"91.0",
    "gn:admin3_code":"9172.0",
    "gn:admin4_code":"9172132.0",
    "gn:asciiname":"Hinterschonau",
    "gn:country_code":"DE",
    "gn:dem":694,
    "gn:feature_class":"P",
    "gn:feature_code":"PPLL",
    "gn:name":"Hintersch\u00f6nau",
    "gn:population":0,
    "gn:timezone":"Europe/Berlin",
    "iso:country":"DE",
    "wof:name":"Hinterschonau",
    "wof:placetype":"neighbourhood"
},
  "geometry": {"coordinates":[12.94913,47.60768],"type":"Point"}
}