{
  "type": "Feature",
  "properties": {
    "gn:admin1_code":"11",
    "gn:admin2_code":"0.0",
    "gn:admin3_code":"12071.0",
    "gn:admin4_code":"12071160.0",
    "gn:asciiname":"Deulowitz",
    "gn:country_code":"DE",
    "gn:dem":55,
    "gn:feature_class":"P",
    "gn:feature_code":"PPL",
    "gn:name":"Deulowitz",
    "gn:population":0,
    "gn:timezone":"Europe/Berlin",
    "iso:country":"DE",
    "wof:name":"Deulowitz",
    "wof:placetype":"neighbourhood"
},
  "geometry": {"coordinates":[14.65369,51.94808],"type":"Point"}
}