{
  "type": "Feature",
  "properties": {
    "gn:admin1_code":"7",
    "gn:admin2_code":"57.0",
    "gn:admin3_code":"5774.0",
    "gn:admin4_code":"5774040.0",
    "gn:asciiname":"Tindeln",
    "gn:country_code":"DE",
    "gn:dem":334,
    "gn:feature_class":"P",
    "gn:feature_code":"PPL",
    "gn:name":"Tindeln",
    "gn:population":0,
    "gn:timezone":"Europe/Berlin",
    "iso:country":"DE",
    "wof:name":"Tindeln",
    "wof:placetype":"neighbourhood"
},
  "geometry": {"coordinates":[8.7074,51.57079],"type":"Point"}
}