{
  "type": "Feature",
  "properties": {
    "gn:admin1_code":"1",
    "gn:admin2_code":"84.0",
    "gn:admin3_code":"8425.0",
    "gn:admin4_code":"8425002.0",
    "gn:asciiname":"Ennahofen",
    "gn:country_code":"DE",
    "gn:dem":734,
    "gn:feature_class":"P",
    "gn:feature_code":"PPL",
    "gn:name":"Ennahofen",
    "gn:population":0,
    "gn:timezone":"Europe/Berlin",
    "iso:country":"DE",
    "wof:name":"Ennahofen",
    "wof:placetype":"neighbourhood"
},
  "geometry": {"coordinates":[9.65981,48.35097],"type":"Point"}
}