{
  "type": "Feature",
  "properties": {
    "gn:gn_country":"DE",
    "gn:gn_fcode":"PPLA4",
    "gn:gn_pop":151,
    "gn:population":151,
    "iso:country":"DE",
    "name:baq_x_preferred":[
        "Heuzert"
    ],
    "name:chi_x_preferred":[
        "\u970d\u4f0a\u7b56\u5c14\u7279"
    ],
    "name:dut_x_preferred":[
        "Heuzert"
    ],
    "name:eng_x_preferred":[
        "Heuzert"
    ],
    "name:epo_x_preferred":[
        "Heuzert"
    ],
    "name:fre_x_preferred":[
        "Heuzert"
    ],
    "name:ger_x_preferred":[
        "Heuzert"
    ],
    "name:hun_x_preferred":[
        "Heuzert"
    ],
    "name:ita_x_preferred":[
        "Heuzert"
    ],
    "name:jpn_x_preferred":[
        "\u30db\u30a4\u30c4\u30a1\u30fc\u30c8"
    ],
    "name:kaz_x_preferred":[
        "\u0425\u043e\u0439\u0446\u0435\u0440\u0442"
    ],
    "name:kir_x_preferred":[
        "\u0425\u043e\u0439\u0446\u0435\u0440\u0442"
    ],
    "name:may_x_preferred":[
        "Heuzert"
    ],
    "name:per_x_preferred":[
        "\u0647\u0648\u06cc\u062a\u0633\u0631\u062a"
    ],
    "name:pol_x_preferred":[
        "Heuzert"
    ],
    "name:por_x_preferred":[
        "Heuzert"
    ],
    "name:rum_x_preferred":[
        "Heuzert"
    ],
    "name:rus_x_preferred":[
        "\u0425\u043e\u0439\u0446\u0435\u0440\u0442"
    ],
    "name:srp_x_preferred":[
        "\u0425\u043e\u0458\u0446\u0435\u0440\u0442"
    ],
    "name:ukr_x_preferred":[
        "\u0413\u043e\u0439\u0446\u0435\u0440\u0442"
    ],
    "name:uzb_x_preferred":[
        "Heuzert"
    ],
    "name:vol_x_preferred":[
        "Heuzert"
    ],
    "name:war_x_preferred":[
        "Heuzert"
    ],
    "qs_pg:aaroncc":"DE",
    "qs_pg:gn_country":"DE",
    "qs_pg:gn_fcode":"PPLA4",
    "qs_pg:gn_pop":151,
    "qs_pg:name":"Heuzert",
    "qs_pg:photos_9r":0,
    "qs_pg:photos_sr":0,
    "qs_pg:pop_sr":1,
    "qs_pg:qs_pg_placetype":"locality",
    "wof:name":"Heuzert",
    "wof:placetype":"locality",
    "wof:population":151
},
  "geometry": {"coordinates":[7.75978,50.69912],"type":"Point"}
}