{
  "type": "Feature",
  "properties": {
    "gn:admin1_code":"7",
    "gn:admin2_code":"59.0",
    "gn:admin3_code":"5966.0",
    "gn:admin4_code":"5966028.0",
    "gn:asciiname":"Doernscheid",
    "gn:country_code":"DE",
    "gn:dem":397,
    "gn:feature_class":"P",
    "gn:feature_code":"PPL",
    "gn:name":"D\u00f6rnscheid",
    "gn:population":0,
    "gn:timezone":"Europe/Berlin",
    "iso:country":"DE",
    "wof:name":"Doernscheid",
    "wof:placetype":"neighbourhood"
},
  "geometry": {"coordinates":[7.84971,50.93969],"type":"Point"}
}