{
  "type": "Feature",
  "properties": {
    "gn:admin1_code":"7",
    "gn:admin2_code":"57.0",
    "gn:admin3_code":"5770.0",
    "gn:admin4_code":"5770012.0",
    "gn:asciiname":"Eickhorst",
    "gn:country_code":"DE",
    "gn:dem":57,
    "gn:feature_class":"P",
    "gn:feature_code":"PPL",
    "gn:name":"Eickhorst",
    "gn:population":0,
    "gn:timezone":"Europe/Berlin",
    "iso:country":"DE",
    "wof:name":"Eickhorst",
    "wof:placetype":"neighbourhood"
},
  "geometry": {"coordinates":[8.7351,52.30321],"type":"Point"}
}