{
  "type": "Feature",
  "properties": {
    "gn:admin1_code":"13",
    "gn:admin2_code":"0.0",
    "gn:admin3_code":"14628.0",
    "gn:admin4_code":"14628010.0",
    "gn:asciiname":"Fuerstenau",
    "gn:country_code":"DE",
    "gn:dem":725,
    "gn:feature_class":"P",
    "gn:feature_code":"PPL",
    "gn:name":"F\u00fcrstenau",
    "gn:population":0,
    "gn:timezone":"Europe/Berlin",
    "iso:country":"DE",
    "name:und_x_variant":[
        "F\u00fcrstenau"
    ],
    "wof:name":"Fuerstenau",
    "wof:placetype":"neighbourhood"
},
  "geometry": {"coordinates":[13.8314,50.73904],"type":"Point"}
}