{
  "type": "Feature",
  "properties": {
    "gn:admin1_code":"1",
    "gn:admin2_code":"81.0",
    "gn:admin3_code":"8128.0",
    "gn:admin4_code":"8128126.0",
    "gn:asciiname":"Queckbronn",
    "gn:country_code":"DE",
    "gn:dem":348,
    "gn:feature_class":"P",
    "gn:feature_code":"PPL",
    "gn:name":"Queckbronn",
    "gn:population":0,
    "gn:timezone":"Europe/Berlin",
    "iso:country":"DE",
    "wof:name":"Queckbronn",
    "wof:placetype":"neighbourhood"
},
  "geometry": {"coordinates":[9.94981,49.47297],"type":"Point"}
}