{
  "type": "Feature",
  "properties": {
    "gn:admin1_code":"5",
    "gn:admin2_code":"64.0",
    "gn:admin3_code":"6439.0",
    "gn:admin4_code":"6439003.0",
    "gn:asciiname":"Wachholderhof",
    "gn:country_code":"DE",
    "gn:dem":173,
    "gn:feature_class":"P",
    "gn:feature_code":"PPL",
    "gn:name":"Wachholderhof",
    "gn:population":0,
    "gn:timezone":"Europe/Berlin",
    "iso:country":"DE",
    "wof:name":"Wachholderhof",
    "wof:placetype":"neighbourhood"
},
  "geometry": {"coordinates":[8.06276,50.03485],"type":"Point"}
}