{
  "type": "Feature",
  "properties": {
    "gn:admin1_code":"13.0",
    "gn:admin2_code":"0.0",
    "gn:admin3_code":"14521.0",
    "gn:admin4_code":"14521340.0",
    "gn:asciiname":"Brettmuehle",
    "gn:country_code":"DE",
    "gn:dem":595,
    "gn:feature_class":"P",
    "gn:feature_code":"PPL",
    "gn:name":"Brettm\u00fchle",
    "gn:population":0,
    "gn:timezone":"Europe/Berlin",
    "iso:country":"DE",
    "wof:name":"Brettmuehle",
    "wof:placetype":"neighbourhood"
},
  "geometry": {"coordinates":[13.0566,50.52813],"type":"Point"}
}