{
  "type": "Feature",
  "properties": {
    "gn:admin1_code":"7",
    "gn:admin2_code":"55.0",
    "gn:admin3_code":"5554.0",
    "gn:admin4_code":"5554044.0",
    "gn:asciiname":"Gross Reken",
    "gn:country_code":"DE",
    "gn:dem":98,
    "gn:feature_class":"P",
    "gn:feature_code":"PPL",
    "gn:name":"Gro\u00df Reken",
    "gn:population":0,
    "gn:timezone":"Europe/Berlin",
    "iso:country":"DE",
    "name:und_x_variant":[
        "Reken",
        "Gro\u00df Reken"
    ],
    "wof:name":"Gross Reken",
    "wof:placetype":"neighbourhood"
},
  "geometry": {"coordinates":[7.04544,51.83042],"type":"Point"}
}