{
  "type": "Feature",
  "properties": {
    "gn:admin1_code":"13",
    "gn:admin2_code":"0.0",
    "gn:admin3_code":"14521.0",
    "gn:admin4_code":"14521110.0",
    "gn:asciiname":"Hammerleithe",
    "gn:country_code":"DE",
    "gn:dem":612,
    "gn:feature_class":"P",
    "gn:feature_code":"PPL",
    "gn:name":"Hammerleithe",
    "gn:population":0,
    "gn:timezone":"Europe/Berlin",
    "iso:country":"DE",
    "wof:name":"Hammerleithe",
    "wof:placetype":"neighbourhood"
},
  "geometry": {"coordinates":[12.75035,50.47689],"type":"Point"}
}