{
  "type": "Feature",
  "properties": {
    "gn:admin1_code":"6",
    "gn:admin2_code":"0.0",
    "gn:admin3_code":"3353.0",
    "gn:admin4_code":"3353040.0",
    "gn:asciiname":"Lassroenne",
    "gn:country_code":"DE",
    "gn:dem":4,
    "gn:feature_class":"P",
    "gn:feature_code":"PPL",
    "gn:name":"La\u00dfr\u00f6nne",
    "gn:population":0,
    "gn:timezone":"Europe/Berlin",
    "iso:country":"DE",
    "wof:name":"Lassroenne",
    "wof:placetype":"neighbourhood"
},
  "geometry": {"coordinates":[10.22713,53.39092],"type":"Point"}
}