{
  "type": "Feature",
  "properties": {
    "gn:admin1_code":"1",
    "gn:admin2_code":"83.0",
    "gn:admin3_code":"8317.0",
    "gn:admin4_code":"8317088.0",
    "gn:asciiname":"Langhardle",
    "gn:country_code":"DE",
    "gn:dem":493,
    "gn:feature_class":"P",
    "gn:feature_code":"PPLL",
    "gn:name":"Langh\u00e4rdle",
    "gn:population":0,
    "gn:timezone":"Europe/Berlin",
    "iso:country":"DE",
    "wof:name":"Langhardle",
    "wof:placetype":"neighbourhood"
},
  "geometry": {"coordinates":[8.15794,48.40887],"type":"Point"}
}