{
  "type": "Feature",
  "properties": {
    "gn:admin1_code":"1",
    "gn:admin2_code":"81.0",
    "gn:admin3_code":"8125.0",
    "gn:admin4_code":"8125111.0",
    "gn:asciiname":"Lampoldshausen",
    "gn:country_code":"DE",
    "gn:dem":245,
    "gn:feature_class":"P",
    "gn:feature_code":"PPL",
    "gn:name":"Lampoldshausen",
    "gn:population":0,
    "gn:timezone":"Europe/Berlin",
    "iso:country":"DE",
    "name:deu_x_preferred":[
        "Lampoldshausen"
    ],
    "wof:name":"Lampoldshausen",
    "wof:placetype":"neighbourhood"
},
  "geometry": {"coordinates":[9.4007,49.26438],"type":"Point"}
}