{
  "type": "Feature",
  "properties": {
    "gn:admin1_code":"14",
    "gn:admin2_code":"0.0",
    "gn:admin3_code":"15087.0",
    "gn:admin4_code":"15087130.0",
    "gn:asciiname":"Neckendorf",
    "gn:country_code":"DE",
    "gn:dem":197,
    "gn:feature_class":"P",
    "gn:feature_code":"PPL",
    "gn:name":"Neckendorf",
    "gn:population":0,
    "gn:timezone":"Europe/Berlin",
    "iso:country":"DE",
    "wof:name":"Neckendorf",
    "wof:placetype":"neighbourhood"
},
  "geometry": {"coordinates":[11.53618,51.50098],"type":"Point"}
}