{
  "type": "Feature",
  "properties": {
    "gn:admin1_code":"2",
    "gn:admin2_code":"94.0",
    "gn:admin3_code":"9472.0",
    "gn:admin4_code":"9472188.0",
    "gn:asciiname":"Wallenbrunn",
    "gn:country_code":"DE",
    "gn:dem":412,
    "gn:feature_class":"P",
    "gn:feature_code":"PPL",
    "gn:name":"Wallenbrunn",
    "gn:population":0,
    "gn:timezone":"Europe/Berlin",
    "iso:country":"DE",
    "wof:name":"Wallenbrunn",
    "wof:placetype":"neighbourhood"
},
  "geometry": {"coordinates":[11.72029,49.88227],"type":"Point"}
}