{
  "type": "Feature",
  "properties": {
    "iso:country":"DE",
    "wof:name":"Alt-Rahlstedt",
    "wof:placetype":"microhood"
},
  "geometry": {"coordinates":[10.159092,53.5928],"type":"Point"}
}