{
  "type": "Feature",
  "properties": {
    "gn:admin1_code":"14",
    "gn:admin2_code":"0.0",
    "gn:admin3_code":"15084.0",
    "gn:admin4_code":"15084550.0",
    "gn:asciiname":"Untergreisslau",
    "gn:country_code":"DE",
    "gn:dem":154,
    "gn:feature_class":"P",
    "gn:feature_code":"PPL",
    "gn:name":"Untergrei\u00dflau",
    "gn:population":0,
    "gn:timezone":"Europe/Berlin",
    "iso:country":"DE",
    "wof:name":"Untergreisslau",
    "wof:placetype":"neighbourhood"
},
  "geometry": {"coordinates":[11.96067,51.17514],"type":"Point"}
}