{
  "type": "Feature",
  "properties": {
    "gn:admin1_code":"6",
    "gn:admin2_code":"0.0",
    "gn:admin3_code":"3255.0",
    "gn:admin4_code":"3255018.0",
    "gn:asciiname":"Merxhausen",
    "gn:country_code":"DE",
    "gn:dem":225,
    "gn:feature_class":"P",
    "gn:feature_code":"PPL",
    "gn:name":"Merxhausen",
    "gn:population":0,
    "gn:timezone":"Europe/Berlin",
    "iso:country":"DE",
    "wof:name":"Merxhausen",
    "wof:placetype":"neighbourhood"
},
  "geometry": {"coordinates":[9.64042,51.82283],"type":"Point"}
}