{
  "type": "Feature",
  "properties": {
    "gn:admin1_code":"14",
    "gn:admin2_code":"0.0",
    "gn:admin3_code":"15081.0",
    "gn:admin4_code":"15081045.0",
    "gn:asciiname":"Klein Gischau",
    "gn:country_code":"DE",
    "gn:dem":36,
    "gn:feature_class":"P",
    "gn:feature_code":"PPL",
    "gn:name":"Klein Gischau",
    "gn:population":0,
    "gn:timezone":"Europe/Berlin",
    "iso:country":"DE",
    "wof:name":"Klein Gischau",
    "wof:placetype":"neighbourhood"
},
  "geometry": {"coordinates":[11.12912,52.74218000000001],"type":"Point"}
}