{
  "type": "Feature",
  "properties": {
    "gn:admin1_code":"2",
    "gn:admin2_code":"93.0",
    "gn:admin3_code":"9373.0",
    "gn:admin4_code":"9373113.0",
    "gn:asciiname":"Unterrohrenstadt",
    "gn:country_code":"DE",
    "gn:dem":419,
    "gn:feature_class":"P",
    "gn:feature_code":"PPL",
    "gn:name":"Unterrohrenstadt",
    "gn:population":0,
    "gn:timezone":"Europe/Berlin",
    "iso:country":"DE",
    "wof:name":"Unterrohrenstadt",
    "wof:placetype":"neighbourhood"
},
  "geometry": {"coordinates":[11.43969,49.37511],"type":"Point"}
}