{
  "type": "Feature",
  "properties": {
    "gn:admin1_code":"1",
    "gn:admin2_code":"84.0",
    "gn:admin3_code":"8436.0",
    "gn:admin4_code":"8436009.0",
    "gn:asciiname":"Ehrensberg",
    "gn:country_code":"DE",
    "gn:dem":719,
    "gn:feature_class":"P",
    "gn:feature_code":"PPL",
    "gn:name":"Ehrensberg",
    "gn:population":0,
    "gn:timezone":"Europe/Berlin",
    "iso:country":"DE",
    "wof:name":"Ehrensberg",
    "wof:placetype":"neighbourhood"
},
  "geometry": {"coordinates":[9.80885,47.90171],"type":"Point"}
}