{
  "type": "Feature",
  "properties": {
    "gn:admin1_code":"2",
    "gn:admin2_code":"91.0",
    "gn:admin3_code":"9178.0",
    "gn:admin4_code":"9178137.0",
    "gn:asciiname":"Kuhnhausen",
    "gn:country_code":"DE",
    "gn:dem":488,
    "gn:feature_class":"P",
    "gn:feature_code":"PPL",
    "gn:name":"K\u00fchnhausen",
    "gn:population":0,
    "gn:timezone":"Europe/Berlin",
    "iso:country":"DE",
    "wof:name":"Kuhnhausen",
    "wof:placetype":"neighbourhood"
},
  "geometry": {"coordinates":[11.63342,48.41551],"type":"Point"}
}