{
  "type": "Feature",
  "properties": {
    "gn:country":"DE",
    "gn:fcode":"PPL",
    "gn:population":0,
    "iso:country":"DE",
    "name:ceb_x_preferred":[
        "D\u00f6se"
    ],
    "name:dan_x_preferred":[
        "D\u00f6se"
    ],
    "name:deu_x_historical":[
        "Steinmarne"
    ],
    "name:deu_x_preferred":[
        "Steinmarne"
    ],
    "name:deu_x_variant":[
        "D\u00f6se"
    ],
    "name:fas_x_preferred":[
        "\u062f\u0648\u0633\u0647"
    ],
    "name:fra_x_preferred":[
        "D\u00f6se"
    ],
    "name:nds_x_preferred":[
        "D\u00f6\u00f6s"
    ],
    "name:nld_x_preferred":[
        "D\u00f6se"
    ],
    "qs_pg:aaroncc":"DE",
    "qs_pg:gn_country":"DE",
    "qs_pg:gn_fcode":"PPL",
    "qs_pg:gn_pop":0,
    "qs_pg:name":"D\u00f6se",
    "qs_pg:name_adm0":"Deutschland",
    "qs_pg:name_adm1":"Niedersachsen",
    "qs_pg:photos":253,
    "qs_pg:photos_1k":51,
    "qs_pg:photos_9k":1,
    "qs_pg:photos_9r":4,
    "qs_pg:photos_all":253,
    "qs_pg:photos_sr":5,
    "qs_pg:pop_sr":0,
    "qs_pg:qs_pg_placetype":"locality",
    "qs_pg:qs_pg_placetype_gp":"Town",
    "qs_pg:woe_adm0":23424829,
    "woe:adm0_id":23424829,
    "woe:name_adm0":"Deutschland",
    "woe:name_adm1":"Niedersachsen",
    "woe:placetype":"Town",
    "wof:name":"D\u00f6se",
    "wof:placetype":"neighbourhood"
},
  "geometry": {"coordinates":[8.67356,53.88316],"type":"Point"}
}