{
  "type": "Feature",
  "properties": {
    "gn:admin1_code":"13.0",
    "gn:admin2_code":"00",
    "gn:admin3_code":"14730.0",
    "gn:admin4_code":"14730200.0",
    "gn:asciiname":"Zschannewitz",
    "gn:country_code":"DE",
    "gn:dem":215,
    "gn:feature_class":"P",
    "gn:feature_code":"PPL",
    "gn:name":"Zschannewitz",
    "gn:population":0,
    "gn:timezone":"Europe/Berlin",
    "iso:country":"DE",
    "wof:name":"Zschannewitz",
    "wof:placetype":"neighbourhood"
},
  "geometry": {"coordinates":[12.95,51.23333],"type":"Point"}
}