{
  "type": "Feature",
  "properties": {
    "gn:admin1_code":"13",
    "gn:admin2_code":"0.0",
    "gn:admin3_code":"14522.0",
    "gn:admin4_code":"14522350.0",
    "gn:asciiname":"Elsdorf",
    "gn:country_code":"DE",
    "gn:dem":238,
    "gn:feature_class":"P",
    "gn:feature_code":"PPL",
    "gn:name":"Elsdorf",
    "gn:population":0,
    "gn:timezone":"Europe/Berlin",
    "iso:country":"DE",
    "name:ara_x_preferred":[
        "\u0625\u0644\u0633\u062f\u0648\u0631\u0641"
    ],
    "name:azb_x_preferred":[
        "\u0627\u0644\u0632\u062f\u0648\u0631\u0641"
    ],
    "name:dan_x_preferred":[
        "Elsdorf"
    ],
    "name:deu_x_preferred":[
        "Elsdorf"
    ],
    "name:epo_x_preferred":[
        "Elsdorf"
    ],
    "name:eus_x_preferred":[
        "Elsdorf"
    ],
    "name:fas_x_preferred":[
        "\u0627\u0644\u0632\u062f\u0648\u0631\u0641"
    ],
    "name:fra_x_preferred":[
        "Elsdorf"
    ],
    "name:hun_x_preferred":[
        "Elsdorf"
    ],
    "name:ita_x_preferred":[
        "Elsdorf"
    ],
    "name:kaz_x_preferred":[
        "\u042d\u043b\u044c\u0441\u0434\u043e\u0440\u0444"
    ],
    "name:kir_x_preferred":[
        "\u042d\u043b\u044c\u0441\u0434\u043e\u0440\u0444"
    ],
    "name:lim_x_preferred":[
        "Elsdorf"
    ],
    "name:msa_x_preferred":[
        "Elsdorf"
    ],
    "name:nld_x_preferred":[
        "Elsdorf"
    ],
    "name:pol_x_preferred":[
        "Elsdorf"
    ],
    "name:por_x_preferred":[
        "Elsdorf"
    ],
    "name:ron_x_preferred":[
        "Elsdorf"
    ],
    "name:rus_x_preferred":[
        "\u042d\u043b\u044c\u0441\u0434\u043e\u0440\u0444"
    ],
    "name:spa_x_preferred":[
        "Elsdorf"
    ],
    "name:srp_x_preferred":[
        "\u0415\u043b\u0441\u0434\u043e\u0440\u0444"
    ],
    "name:swe_x_preferred":[
        "Elsdorf"
    ],
    "name:ukr_x_preferred":[
        "\u0415\u043b\u044c\u0441\u0434\u043e\u0440\u0444"
    ],
    "name:uzb_x_preferred":[
        "Elsdorf"
    ],
    "name:vie_x_preferred":[
        "Elsdorf"
    ],
    "name:vol_x_preferred":[
        "Elsdorf"
    ],
    "name:war_x_preferred":[
        "Elsdorf"
    ],
    "name:zho_x_preferred":[
        "\u57c3\u5c14\u65af\u591a\u592b"
    ],
    "wof:name":"Elsdorf",
    "wof:placetype":"neighbourhood"
},
  "geometry": {"coordinates":[12.71667,50.96667],"type":"Point"}
}