{
  "type": "Feature",
  "properties": {
    "gn:admin1_code":"2",
    "gn:admin2_code":"92.0",
    "gn:admin3_code":"9275.0",
    "gn:admin4_code":"9275135.0",
    "gn:asciiname":"Pilling",
    "gn:country_code":"DE",
    "gn:dem":415,
    "gn:feature_class":"P",
    "gn:feature_code":"PPL",
    "gn:name":"Pilling",
    "gn:population":0,
    "gn:timezone":"Europe/Berlin",
    "iso:country":"DE",
    "name:ceb_x_preferred":[
        "Pilling"
    ],
    "name:cym_x_preferred":[
        "Pilling"
    ],
    "name:fas_x_preferred":[
        "\u067e\u06cc\u0644\u06cc\u0646\u06af"
    ],
    "name:ita_x_preferred":[
        "Pilling"
    ],
    "name:nld_x_preferred":[
        "Pilling"
    ],
    "name:pol_x_preferred":[
        "Pilling"
    ],
    "name:spa_x_preferred":[
        "Pilling"
    ],
    "name:swe_x_preferred":[
        "Pilling"
    ],
    "wof:name":"Pilling",
    "wof:placetype":"neighbourhood"
},
  "geometry": {"coordinates":[13.37083,48.68235],"type":"Point"}
}