{
  "type": "Feature",
  "properties": {
    "gn:admin1_code":"2",
    "gn:admin2_code":"92.0",
    "gn:admin3_code":"9277.0",
    "gn:admin4_code":"9277111.0",
    "gn:asciiname":"Thanning",
    "gn:country_code":"DE",
    "gn:dem":438,
    "gn:feature_class":"P",
    "gn:feature_code":"PPL",
    "gn:name":"Thanning",
    "gn:population":0,
    "gn:timezone":"Europe/Berlin",
    "iso:country":"DE",
    "wof:name":"Thanning",
    "wof:placetype":"neighbourhood"
},
  "geometry": {"coordinates":[12.75959,48.51402],"type":"Point"}
}