{
  "type": "Feature",
  "properties": {
    "gn:admin1_code":"12",
    "gn:admin2_code":"0.0",
    "gn:admin3_code":"13073.0",
    "gn:admin4_code":"13073066.0",
    "gn:asciiname":"Kroennewitz",
    "gn:cc2":"DE",
    "gn:country_code":"DE",
    "gn:dem":12,
    "gn:feature_class":"P",
    "gn:feature_code":"PPL",
    "gn:name":"Kr\u00f6nnewitz",
    "gn:population":0,
    "gn:timezone":"Europe/Berlin",
    "iso:country":"DE",
    "name:deu_x_preferred":[
        "Kr\u00f6nnewitz"
    ],
    "wof:name":"Kroennewitz",
    "wof:placetype":"neighbourhood"
},
  "geometry": {"coordinates":[12.97125,54.33224000000001],"type":"Point"}
}