{
  "type": "Feature",
  "properties": {
    "gn:admin1_code":"7.0",
    "gn:admin2_code":"053",
    "gn:admin3_code":"5358.0",
    "gn:admin4_code":"5358044.0",
    "gn:asciiname":"Wollersheim",
    "gn:country_code":"DE",
    "gn:dem":241,
    "gn:feature_class":"P",
    "gn:feature_code":"PPL",
    "gn:name":"Wollersheim",
    "gn:population":0,
    "gn:timezone":"Europe/Berlin",
    "iso:country":"DE",
    "name:deu_x_preferred":[
        "Wollersheim"
    ],
    "name:fas_x_preferred":[
        "\u0648\u0644\u0631\u0634\u0627\u06cc\u0645"
    ],
    "name:nld_x_preferred":[
        "Wollersheim"
    ],
    "wof:name":"Wollersheim",
    "wof:placetype":"neighbourhood"
},
  "geometry": {"coordinates":[6.56517,50.67159],"type":"Point"}
}