{
  "type": "Feature",
  "properties": {
    "gn:admin1_code":"6.0",
    "gn:admin2_code":"0.0",
    "gn:admin3_code":"3251.0",
    "gn:admin4_code":"3251040.0",
    "gn:asciiname":"Barrien",
    "gn:country_code":"DE",
    "gn:dem":44,
    "gn:feature_class":"P",
    "gn:feature_code":"PPL",
    "gn:name":"Barrien",
    "gn:population":0,
    "gn:timezone":"Europe/Berlin",
    "iso:country":"DE",
    "wof:name":"Barrien",
    "wof:placetype":"neighbourhood"
},
  "geometry": {"coordinates":[8.71899,52.66735],"type":"Point"}
}