{
  "type": "Feature",
  "properties": {
    "gn:admin1_code":"14.0",
    "gn:admin2_code":"0.0",
    "gn:admin3_code":"15091.0",
    "gn:admin4_code":"15091375.0",
    "gn:asciiname":"Berkau",
    "gn:country_code":"DE",
    "gn:dem":160,
    "gn:feature_class":"P",
    "gn:feature_code":"PPL",
    "gn:name":"Berkau",
    "gn:population":0,
    "gn:timezone":"Europe/Berlin",
    "iso:country":"DE",
    "name:bak_x_preferred":[
        "\u0411\u0435\u0440\u043a\u0430\u0443"
    ],
    "name:ceb_x_preferred":[
        "Berkau"
    ],
    "name:deu_x_preferred":[
        "Berkau"
    ],
    "name:epo_x_preferred":[
        "Berkau"
    ],
    "name:fas_x_preferred":[
        "\u0628\u0631\u06a9\u0627\u0648"
    ],
    "name:ita_x_preferred":[
        "Berkau"
    ],
    "name:kaz_x_preferred":[
        "\u0411\u0435\u0440\u043a\u0430\u0443"
    ],
    "name:kir_x_preferred":[
        "\u0411\u0435\u0440\u043a\u0430\u0443"
    ],
    "name:mkd_x_preferred":[
        "\u0411\u0435\u0440\u043a\u0430\u0443"
    ],
    "name:nld_x_preferred":[
        "Berkau"
    ],
    "name:ron_x_preferred":[
        "Berkau"
    ],
    "name:rus_x_preferred":[
        "\u0411\u0435\u0440\u043a\u0430\u0443"
    ],
    "name:uzb_x_preferred":[
        "Berkau"
    ],
    "name:vie_x_preferred":[
        "Berkau"
    ],
    "name:vol_x_preferred":[
        "Berkau"
    ],
    "wof:name":"Berkau",
    "wof:placetype":"neighbourhood"
},
  "geometry": {"coordinates":[12.64093,51.96861],"type":"Point"}
}