{
  "type": "Feature",
  "properties": {
    "gn:admin1_code":"14",
    "gn:admin2_code":"0.0",
    "gn:admin3_code":"15089.0",
    "gn:admin4_code":"15089175.0",
    "gn:asciiname":"Gaensefurth",
    "gn:country_code":"DE",
    "gn:dem":67,
    "gn:feature_class":"P",
    "gn:feature_code":"PPL",
    "gn:name":"G\u00e4nsefurth",
    "gn:population":0,
    "gn:timezone":"Europe/Berlin",
    "iso:country":"DE",
    "wof:name":"Gaensefurth",
    "wof:placetype":"neighbourhood"
},
  "geometry": {"coordinates":[11.53473,51.86442],"type":"Point"}
}