{
  "type": "Feature",
  "properties": {
    "gn:admin1_code":"2",
    "gn:admin2_code":"97.0",
    "gn:admin3_code":"9780.0",
    "gn:admin4_code":"9780120.0",
    "gn:asciiname":"Miesenbach",
    "gn:country_code":"DE",
    "gn:dem":714,
    "gn:feature_class":"P",
    "gn:feature_code":"PPL",
    "gn:name":"Miesenbach",
    "gn:population":0,
    "gn:timezone":"Europe/Berlin",
    "iso:country":"DE",
    "name:ceb_x_preferred":[
        "Miesenbach"
    ],
    "name:ces_x_preferred":[
        "Miesenbach"
    ],
    "name:deu_x_preferred":[
        "Miesenbach"
    ],
    "name:fra_x_preferred":[
        "Miesenbach"
    ],
    "name:ita_x_preferred":[
        "Miesenbach"
    ],
    "name:pol_x_preferred":[
        "Miesenbach"
    ],
    "name:swe_x_preferred":[
        "Miesenbach"
    ],
    "wof:name":"Miesenbach",
    "wof:placetype":"neighbourhood"
},
  "geometry": {"coordinates":[10.34004,47.69998],"type":"Point"}
}