{
  "type": "Feature",
  "properties": {
    "gn:admin1_code":"2",
    "gn:admin2_code":"91.0",
    "gn:admin3_code":"9171.0",
    "gn:admin4_code":"9171114.0",
    "gn:asciiname":"Seng",
    "gn:country_code":"DE",
    "gn:dem":389,
    "gn:feature_class":"P",
    "gn:feature_code":"PPL",
    "gn:name":"Seng",
    "gn:population":0,
    "gn:timezone":"Europe/Berlin",
    "iso:country":"DE",
    "wof:name":"Seng",
    "wof:placetype":"neighbourhood"
},
  "geometry": {"coordinates":[12.76096,48.1946],"type":"Point"}
}