{
  "type": "Feature",
  "properties": {
    "gn:admin1_code":"8",
    "gn:admin2_code":"0.0",
    "gn:admin3_code":"7319.0",
    "gn:admin4_code":"7319000.0",
    "gn:asciiname":"Heppenheim an der Wiese",
    "gn:country_code":"DE",
    "gn:dem":113,
    "gn:feature_class":"P",
    "gn:feature_code":"PPL",
    "gn:name":"Heppenheim an der Wiese",
    "gn:population":0,
    "gn:timezone":"Europe/Berlin",
    "iso:country":"DE",
    "name:und_x_variant":[
        "Heppenheim",
        "Heppenheim an der Wiese"
    ],
    "wof:name":"Heppenheim an der Wiese",
    "wof:placetype":"neighbourhood"
},
  "geometry": {"coordinates":[8.26781,49.60557],"type":"Point"}
}