{
  "type": "Feature",
  "properties": {
    "gn:admin1_code":"11",
    "gn:admin2_code":"0.0",
    "gn:admin3_code":"12062.0",
    "gn:admin4_code":"12062289.0",
    "gn:asciiname":"Koerba",
    "gn:country_code":"DE",
    "gn:dem":94,
    "gn:feature_class":"P",
    "gn:feature_code":"PPL",
    "gn:name":"K\u00f6rba",
    "gn:population":0,
    "gn:timezone":"Europe/Berlin",
    "iso:country":"DE",
    "wof:name":"Koerba",
    "wof:placetype":"neighbourhood"
},
  "geometry": {"coordinates":[13.38774,51.80471],"type":"Point"}
}