{
  "type": "Feature",
  "properties": {
    "gn:admin1_code":"6.0",
    "gn:admin2_code":"0.0",
    "gn:admin3_code":"3351.0",
    "gn:admin4_code":"3351001.0",
    "gn:asciiname":"Grossmoor",
    "gn:country_code":"DE",
    "gn:dem":40,
    "gn:feature_class":"P",
    "gn:feature_code":"PPL",
    "gn:name":"Gro\u00dfmoor",
    "gn:population":0,
    "gn:timezone":"Europe/Berlin",
    "iso:country":"DE",
    "name:deu_x_preferred":[
        "Gro\u00dfmoor"
    ],
    "name:nds_x_preferred":[
        "Grootmoor"
    ],
    "wof:name":"Grossmoor",
    "wof:placetype":"neighbourhood"
},
  "geometry": {"coordinates":[10.0185,52.55172],"type":"Point"}
}