{
  "type": "Feature",
  "properties": {
    "gn:admin1_code":"2.0",
    "gn:admin2_code":"93.0",
    "gn:admin3_code":"9371.0",
    "gn:admin4_code":"9371132.0",
    "gn:asciiname":"Aicha",
    "gn:country_code":"DE",
    "gn:dem":517,
    "gn:feature_class":"P",
    "gn:feature_code":"PPL",
    "gn:name":"Aicha",
    "gn:population":0,
    "gn:timezone":"Europe/Berlin",
    "iso:country":"DE",
    "wof:name":"Aicha",
    "wof:placetype":"neighbourhood"
},
  "geometry": {"coordinates":[11.73151,49.35431],"type":"Point"}
}