{
  "type": "Feature",
  "properties": {
    "gn:admin1_code":"2",
    "gn:admin2_code":"92.0",
    "gn:admin3_code":"9275.0",
    "gn:admin4_code":"9275127.0",
    "gn:asciiname":"Grubhof",
    "gn:country_code":"DE",
    "gn:dem":326,
    "gn:feature_class":"P",
    "gn:feature_code":"PPL",
    "gn:name":"Grubhof",
    "gn:population":0,
    "gn:timezone":"Europe/Berlin",
    "iso:country":"DE",
    "wof:name":"Grubhof",
    "wof:placetype":"neighbourhood"
},
  "geometry": {"coordinates":[13.14778,48.69],"type":"Point"}
}