{
  "type": "Feature",
  "properties": {
    "gn:admin1_code":"2",
    "gn:admin2_code":"94.0",
    "gn:admin3_code":"9472.0",
    "gn:admin4_code":"9472133.0",
    "gn:asciiname":"Hauendorf",
    "gn:country_code":"DE",
    "gn:dem":395,
    "gn:feature_class":"P",
    "gn:feature_code":"PPL",
    "gn:name":"Hauendorf",
    "gn:population":0,
    "gn:timezone":"Europe/Berlin",
    "iso:country":"DE",
    "wof:name":"Hauendorf",
    "wof:placetype":"neighbourhood"
},
  "geometry": {"coordinates":[11.66258,49.88703],"type":"Point"}
}