{
  "type": "Feature",
  "properties": {
    "gn:admin1_code":"13",
    "gn:admin2_code":"0.0",
    "gn:admin3_code":"14628.0",
    "gn:admin4_code":"14628080.0",
    "gn:asciiname":"Gamig",
    "gn:cc2":"DE",
    "gn:country_code":"DE",
    "gn:dem":195,
    "gn:feature_class":"P",
    "gn:feature_code":"PPL",
    "gn:name":"Gamig",
    "gn:population":0,
    "gn:timezone":"Europe/Berlin",
    "iso:country":"DE",
    "name:und_x_variant":[
        "Gut Gamig"
    ],
    "wof:name":"Gamig",
    "wof:placetype":"neighbourhood"
},
  "geometry": {"coordinates":[13.84174,50.96172],"type":"Point"}
}