{
  "type": "Feature",
  "properties": {
    "gn:admin1_code":"8",
    "gn:admin2_code":"0.0",
    "gn:admin3_code":"7138.0",
    "gn:admin4_code":"7138003.0",
    "gn:asciiname":"Thelenberg",
    "gn:country_code":"DE",
    "gn:dem":259,
    "gn:feature_class":"P",
    "gn:feature_code":"PPL",
    "gn:name":"Thelenberg",
    "gn:population":0,
    "gn:timezone":"Europe/Berlin",
    "iso:country":"DE",
    "name:deu_x_preferred":[
        "Thelenberg"
    ],
    "name:fas_x_preferred":[
        "\u062a\u0647\u0644\u0646\u0628\u0631\u06af"
    ],
    "wof:name":"Thelenberg",
    "wof:placetype":"neighbourhood"
},
  "geometry": {"coordinates":[7.40639,50.65634],"type":"Point"}
}