{
  "type": "Feature",
  "properties": {
    "gn:admin1_code":"6.0",
    "gn:admin2_code":"0.0",
    "gn:admin3_code":"3151.0",
    "gn:admin4_code":"3151015.0",
    "gn:asciiname":"Bahnhof Leiferde",
    "gn:country_code":"DE",
    "gn:dem":55,
    "gn:feature_class":"P",
    "gn:feature_code":"PPL",
    "gn:name":"Bahnhof Leiferde",
    "gn:population":0,
    "gn:timezone":"Europe/Berlin",
    "iso:country":"DE",
    "wof:name":"Bahnhof Leiferde",
    "wof:placetype":"neighbourhood"
},
  "geometry": {"coordinates":[10.43186,52.45496],"type":"Point"}
}