{
  "type": "Feature",
  "properties": {
    "gn:admin1_code":"6",
    "gn:admin2_code":"0.0",
    "gn:admin3_code":"3257.0",
    "gn:admin4_code":"3257009.0",
    "gn:asciiname":"Petzen",
    "gn:country_code":"DE",
    "gn:dem":53,
    "gn:feature_class":"P",
    "gn:feature_code":"PPL",
    "gn:name":"Petzen",
    "gn:population":0,
    "gn:timezone":"Europe/Berlin",
    "iso:country":"DE",
    "name:ceb_x_preferred":[
        "Peca"
    ],
    "name:deu_x_preferred":[
        "Petzen"
    ],
    "name:fra_x_preferred":[
        "Petzen"
    ],
    "name:ita_x_preferred":[
        "Petzen"
    ],
    "name:lit_x_preferred":[
        "Peca"
    ],
    "name:nno_x_preferred":[
        "Peca"
    ],
    "name:pol_x_preferred":[
        "Petzen"
    ],
    "name:slk_x_preferred":[
        "Peca"
    ],
    "name:slv_x_preferred":[
        "Peca"
    ],
    "name:swe_x_preferred":[
        "Peca"
    ],
    "name:ukr_x_preferred":[
        "\u041f\u0435\u0446\u0430"
    ],
    "wof:name":"Petzen",
    "wof:placetype":"neighbourhood"
},
  "geometry": {"coordinates":[9.00364,52.27152],"type":"Point"}
}