{
  "type": "Feature",
  "properties": {
    "gn:admin1_code":"13",
    "gn:admin2_code":"0.0",
    "gn:admin3_code":"14730.0",
    "gn:admin4_code":"14730150.0",
    "gn:asciiname":"Proettitz",
    "gn:country_code":"DE",
    "gn:dem":124,
    "gn:feature_class":"P",
    "gn:feature_code":"PPL",
    "gn:name":"Pr\u00f6ttitz",
    "gn:population":0,
    "gn:timezone":"Europe/Berlin",
    "iso:country":"DE",
    "wof:name":"Proettitz",
    "wof:placetype":"neighbourhood"
},
  "geometry": {"coordinates":[12.4324,51.4555],"type":"Point"}
}