{
  "type": "Feature",
  "properties": {
    "gn:admin1_code":"11",
    "gn:admin2_code":"0.0",
    "gn:admin3_code":"12062.0",
    "gn:admin4_code":"12062461.0",
    "gn:asciiname":"Hohenkuhnsdorf",
    "gn:country_code":"DE",
    "gn:dem":84,
    "gn:feature_class":"P",
    "gn:feature_code":"PPL",
    "gn:name":"Hohenkuhnsdorf",
    "gn:population":0,
    "gn:timezone":"Europe/Berlin",
    "iso:country":"DE",
    "wof:name":"Hohenkuhnsdorf",
    "wof:placetype":"neighbourhood"
},
  "geometry": {"coordinates":[13.21359,51.86111],"type":"Point"}
}