{
  "type": "Feature",
  "properties": {
    "gn:admin1_code":"11",
    "gn:admin2_code":"0.0",
    "gn:admin3_code":"12063.0",
    "gn:admin4_code":"12063134.0",
    "gn:asciiname":"Parey",
    "gn:country_code":"DE",
    "gn:dem":29,
    "gn:feature_class":"P",
    "gn:feature_code":"PPL",
    "gn:name":"Parey",
    "gn:population":0,
    "gn:timezone":"Europe/Berlin",
    "iso:country":"DE",
    "name:ceb_x_preferred":[
        "Parey"
    ],
    "name:deu_x_preferred":[
        "Parey"
    ],
    "name:ita_x_preferred":[
        "Parey"
    ],
    "name:swe_x_preferred":[
        "Parey"
    ],
    "wof:name":"Parey",
    "wof:placetype":"neighbourhood"
},
  "geometry": {"coordinates":[12.24486,52.67841],"type":"Point"}
}