{
  "type": "Feature",
  "properties": {
    "gn:admin1_code":"2",
    "gn:admin2_code":"94.0",
    "gn:admin3_code":"9472.0",
    "gn:admin4_code":"9472175.0",
    "gn:asciiname":"Hollenberg",
    "gn:country_code":"DE",
    "gn:dem":504,
    "gn:feature_class":"P",
    "gn:feature_code":"PPL",
    "gn:name":"Hollenberg",
    "gn:population":0,
    "gn:timezone":"Europe/Berlin",
    "iso:country":"DE",
    "name:deu_x_preferred":[
        "Hollenberg"
    ],
    "name:nld_x_preferred":[
        "Hollenberg"
    ],
    "wof:name":"Hollenberg",
    "wof:placetype":"neighbourhood"
},
  "geometry": {"coordinates":[11.48224,49.76575],"type":"Point"}
}