{
  "type": "Feature",
  "properties": {
    "gn:admin1_code":"15",
    "gn:admin2_code":"0.0",
    "gn:admin3_code":"16073.0",
    "gn:admin4_code":"16073112.0",
    "gn:asciiname":"Thaelendorf",
    "gn:country_code":"DE",
    "gn:dem":319,
    "gn:feature_class":"P",
    "gn:feature_code":"PPL",
    "gn:name":"Th\u00e4lendorf",
    "gn:population":0,
    "gn:timezone":"Europe/Berlin",
    "iso:country":"DE",
    "wof:name":"Thaelendorf",
    "wof:placetype":"neighbourhood"
},
  "geometry": {"coordinates":[11.19823,50.71703],"type":"Point"}
}