{
  "type": "Feature",
  "properties": {
    "gn:admin1_code":"2",
    "gn:admin2_code":"96.0",
    "gn:admin3_code":"9673.0",
    "gn:admin4_code":"9673162.0",
    "gn:asciiname":"Waldberg",
    "gn:country_code":"DE",
    "gn:dem":435,
    "gn:feature_class":"P",
    "gn:feature_code":"PPL",
    "gn:name":"Waldberg",
    "gn:population":0,
    "gn:timezone":"Europe/Berlin",
    "iso:country":"DE",
    "wof:name":"Waldberg",
    "wof:placetype":"neighbourhood"
},
  "geometry": {"coordinates":[9.99957,50.33706],"type":"Point"}
}