{
  "type": "Feature",
  "properties": {
    "gn:admin1_code":"15.0",
    "gn:admin2_code":"0.0",
    "gn:admin3_code":"16066.0",
    "gn:admin4_code":"16066053.0",
    "gn:asciiname":"Amoenenhof",
    "gn:country_code":"DE",
    "gn:dem":617,
    "gn:feature_class":"P",
    "gn:feature_code":"PPL",
    "gn:name":"Am\u00f6nenhof",
    "gn:population":0,
    "gn:timezone":"Europe/Berlin",
    "iso:country":"DE",
    "wof:name":"Amoenenhof",
    "wof:placetype":"neighbourhood"
},
  "geometry": {"coordinates":[10.22736,50.6289],"type":"Point"}
}