{
  "type": "Feature",
  "properties": {
    "gn:admin1_code":"10",
    "gn:admin2_code":"0.0",
    "gn:admin3_code":"1057.0",
    "gn:admin4_code":"1057004.0",
    "gn:asciiname":"Waterneverstorf",
    "gn:country_code":"DE",
    "gn:dem":4,
    "gn:feature_class":"P",
    "gn:feature_code":"PPL",
    "gn:name":"Waterneverstorf",
    "gn:population":0,
    "gn:timezone":"Europe/Berlin",
    "iso:country":"DE",
    "wof:name":"Waterneverstorf",
    "wof:placetype":"neighbourhood"
},
  "geometry": {"coordinates":[10.60644,54.33439],"type":"Point"}
}