{
  "type": "Feature",
  "properties": {
    "gn:admin1_code":"2",
    "gn:admin2_code":"92.0",
    "gn:admin3_code":"9277.0",
    "gn:admin4_code":"9277112.0",
    "gn:asciiname":"Kindlbach",
    "gn:country_code":"DE",
    "gn:dem":344,
    "gn:feature_class":"P",
    "gn:feature_code":"PPL",
    "gn:name":"Kindlbach",
    "gn:population":0,
    "gn:timezone":"Europe/Berlin",
    "iso:country":"DE",
    "wof:name":"Kindlbach",
    "wof:placetype":"neighbourhood"
},
  "geometry": {"coordinates":[13.15883,48.42353],"type":"Point"}
}