{
  "type": "Feature",
  "properties": {
    "gn:admin1_code":"2",
    "gn:admin2_code":"91.0",
    "gn:admin3_code":"9178.0",
    "gn:admin4_code":"9178125.0",
    "gn:asciiname":"Priel",
    "gn:country_code":"DE",
    "gn:dem":466,
    "gn:feature_class":"P",
    "gn:feature_code":"PPL",
    "gn:name":"Priel",
    "gn:population":0,
    "gn:timezone":"Europe/Berlin",
    "iso:country":"DE",
    "wof:name":"Priel",
    "wof:placetype":"neighbourhood"
},
  "geometry": {"coordinates":[11.91527,48.55043],"type":"Point"}
}