{
  "type": "Feature",
  "properties": {
    "gn:admin1_code":"2",
    "gn:admin2_code":"91.0",
    "gn:admin3_code":"9173.0",
    "gn:admin4_code":"9173118.0",
    "gn:asciiname":"Osten",
    "gn:country_code":"DE",
    "gn:dem":734,
    "gn:feature_class":"P",
    "gn:feature_code":"PPL",
    "gn:name":"Osten",
    "gn:population":0,
    "gn:timezone":"Europe/Berlin",
    "iso:country":"DE",
    "name:ceb_x_preferred":[
        "Osten"
    ],
    "name:deu_x_preferred":[
        "Osten"
    ],
    "name:epo_x_preferred":[
        "Osten"
    ],
    "name:est_x_preferred":[
        "Osten"
    ],
    "name:eus_x_preferred":[
        "Osten"
    ],
    "name:fas_x_preferred":[
        "\u0627\u0648\u0634\u062a\u0646"
    ],
    "name:fra_x_preferred":[
        "Osten"
    ],
    "name:hun_x_preferred":[
        "Osten"
    ],
    "name:ita_x_preferred":[
        "Osten"
    ],
    "name:kaz_x_preferred":[
        "\u041e\u0441\u0442\u0435\u043d"
    ],
    "name:kir_x_preferred":[
        "\u041e\u0441\u0442\u0435\u043d"
    ],
    "name:msa_x_preferred":[
        "Osten"
    ],
    "name:nds_x_preferred":[
        "Gemeen Oosten"
    ],
    "name:nld_x_preferred":[
        "Osten"
    ],
    "name:pol_x_preferred":[
        "Osten"
    ],
    "name:por_x_preferred":[
        "Osten"
    ],
    "name:ron_x_preferred":[
        "Osten"
    ],
    "name:rus_x_preferred":[
        "\u041e\u0441\u0442\u0435\u043d"
    ],
    "name:spa_x_preferred":[
        "Osten"
    ],
    "name:srp_x_preferred":[
        "\u041e\u0441\u0442\u0435\u043d"
    ],
    "name:uzb_x_preferred":[
        "Osten"
    ],
    "name:vie_x_preferred":[
        "Osten"
    ],
    "name:vol_x_preferred":[
        "Osten"
    ],
    "name:war_x_preferred":[
        "Osten"
    ],
    "name:zho_x_preferred":[
        "\u5965\u65af\u6ed5"
    ],
    "wof:name":"Osten",
    "wof:placetype":"neighbourhood"
},
  "geometry": {"coordinates":[11.60903,47.85735],"type":"Point"}
}