{
  "type": "Feature",
  "properties": {
    "gn:admin1_code":"2.0",
    "gn:admin2_code":"93.0",
    "gn:admin3_code":"9375.0",
    "gn:admin4_code":"9375120.0",
    "gn:asciiname":"Bibersbach",
    "gn:country_code":"DE",
    "gn:dem":544,
    "gn:feature_class":"P",
    "gn:feature_code":"PPL",
    "gn:name":"Bibersbach",
    "gn:population":0,
    "gn:timezone":"Europe/Berlin",
    "iso:country":"DE",
    "wof:name":"Bibersbach",
    "wof:placetype":"neighbourhood"
},
  "geometry": {"coordinates":[12.35105,49.07754],"type":"Point"}
}