{
  "type": "Feature",
  "properties": {
    "gn:admin1_code":"1",
    "gn:admin2_code":"81.0",
    "gn:admin3_code":"8127.0",
    "gn:admin4_code":"8127099.0",
    "gn:asciiname":"Rudelsdorf",
    "gn:country_code":"DE",
    "gn:dem":431,
    "gn:feature_class":"P",
    "gn:feature_code":"PPL",
    "gn:name":"Rudelsdorf",
    "gn:population":0,
    "gn:timezone":"Europe/Berlin",
    "iso:country":"DE",
    "wof:name":"Rudelsdorf",
    "wof:placetype":"neighbourhood"
},
  "geometry": {"coordinates":[9.87502,49.16773],"type":"Point"}
}