{
  "type": "Feature",
  "properties": {
    "gn:admin1_code":"2",
    "gn:admin2_code":"93.0",
    "gn:admin3_code":"9373.0",
    "gn:admin4_code":"9373167.0",
    "gn:asciiname":"Sankt Wolfgang",
    "gn:country_code":"DE",
    "gn:dem":534,
    "gn:feature_class":"P",
    "gn:feature_code":"PPL",
    "gn:name":"Sankt Wolfgang",
    "gn:population":0,
    "gn:timezone":"Europe/Berlin",
    "iso:country":"DE",
    "name:ara_x_preferred":[
        "\u0632\u0622\u0646\u0643\u062a \u0641\u0648\u0644\u0641\u063a\u0622\u0646\u063a"
    ],
    "name:ceb_x_preferred":[
        "Sankt Wolfgang"
    ],
    "name:dan_x_preferred":[
        "Sankt Wolfgang"
    ],
    "name:deu_x_preferred":[
        "Sankt Wolfgang"
    ],
    "name:epo_x_preferred":[
        "Sankt Wolfgang"
    ],
    "name:eus_x_preferred":[
        "Sankt Wolfgang"
    ],
    "name:fas_x_preferred":[
        "\u0633\u0627\u0646\u06a9\u062a \u0648\u0644\u0641\u06af\u0627\u0646\u06af"
    ],
    "name:fra_x_preferred":[
        "Sankt Wolfgang"
    ],
    "name:hun_x_preferred":[
        "Sankt Wolfgang"
    ],
    "name:ind_x_preferred":[
        "Sankt Wolfgang"
    ],
    "name:ita_x_preferred":[
        "Sankt Wolfgang"
    ],
    "name:kaz_x_preferred":[
        "\u0421\u0430\u043d\u043a\u0442-\u0412\u043e\u043b\u044c\u0444\u0433\u0430\u043d\u0433"
    ],
    "name:kir_x_preferred":[
        "\u0421\u0430\u043d\u043a\u0442-\u0412\u043e\u043b\u044c\u0444\u0433\u0430\u043d\u0433"
    ],
    "name:lmo_x_preferred":[
        "Sankt Wolfgang"
    ],
    "name:msa_x_preferred":[
        "Sankt Wolfgang"
    ],
    "name:nld_x_preferred":[
        "Sankt Wolfgang"
    ],
    "name:pol_x_preferred":[
        "Sankt Wolfgang"
    ],
    "name:por_x_preferred":[
        "Sankt Wolfgang"
    ],
    "name:ron_x_preferred":[
        "Sankt Wolfgang"
    ],
    "name:rus_x_preferred":[
        "\u0421\u0430\u043d\u043a\u0442-\u0412\u043e\u043b\u044c\u0444\u0433\u0430\u043d\u0433"
    ],
    "name:spa_x_preferred":[
        "Sankt Wolfgang"
    ],
    "name:srp_x_preferred":[
        "\u0421\u0430\u043d\u043a\u0442 \u0412\u043e\u043b\u0444\u0433\u0430\u043d\u0433"
    ],
    "name:ukr_x_preferred":[
        "\u0417\u0430\u043d\u043a\u0442-\u0412\u043e\u043b\u044c\u0444\u0433\u0430\u043d\u0433"
    ],
    "name:uzb_x_preferred":[
        "Sankt Wolfgang"
    ],
    "name:vol_x_preferred":[
        "Sankt Wolfgang"
    ],
    "name:war_x_preferred":[
        "Sankt Wolfgang"
    ],
    "name:zho_x_preferred":[
        "\u5723\u6c83\u5c14\u592b\u5188"
    ],
    "wof:name":"Sankt Wolfgang",
    "wof:placetype":"neighbourhood"
},
  "geometry": {"coordinates":[11.68868,49.23738],"type":"Point"}
}