{
  "type": "Feature",
  "properties": {
    "gn:admin1_code":"2",
    "gn:admin2_code":"91.0",
    "gn:admin3_code":"9183.0",
    "gn:admin4_code":"9183129.0",
    "gn:asciiname":"Imming",
    "gn:country_code":"DE",
    "gn:dem":434,
    "gn:feature_class":"P",
    "gn:feature_code":"PPL",
    "gn:name":"Imming",
    "gn:population":0,
    "gn:timezone":"Europe/Berlin",
    "iso:country":"DE",
    "wof:name":"Imming",
    "wof:placetype":"neighbourhood"
},
  "geometry": {"coordinates":[12.5595,48.38432],"type":"Point"}
}