{
  "type": "Feature",
  "properties": {
    "gn:admin1_code":"2",
    "gn:admin2_code":"96.0",
    "gn:admin3_code":"9675.0",
    "gn:admin4_code":"9675141.0",
    "gn:asciiname":"Hoheim",
    "gn:country_code":"DE",
    "gn:dem":211,
    "gn:feature_class":"P",
    "gn:feature_code":"PPL",
    "gn:name":"Hoheim",
    "gn:population":0,
    "gn:timezone":"Europe/Berlin",
    "iso:country":"DE",
    "wof:name":"Hoheim",
    "wof:placetype":"neighbourhood"
},
  "geometry": {"coordinates":[10.20355,49.72859],"type":"Point"}
}