{
  "type": "Feature",
  "properties": {
    "gn:admin1_code":"2",
    "gn:admin2_code":"92.0",
    "gn:admin3_code":"9279.0",
    "gn:admin4_code":"9279127.0",
    "gn:asciiname":"Rauhleiten",
    "gn:country_code":"DE",
    "gn:dem":423,
    "gn:feature_class":"P",
    "gn:feature_code":"PPL",
    "gn:name":"Rauhleiten",
    "gn:population":0,
    "gn:timezone":"Europe/Berlin",
    "iso:country":"DE",
    "wof:name":"Rauhleiten",
    "wof:placetype":"neighbourhood"
},
  "geometry": {"coordinates":[12.3947,48.73786],"type":"Point"}
}