{
  "type": "Feature",
  "properties": {
    "gn:admin1_code":"7",
    "gn:admin2_code":"53.0",
    "gn:admin3_code":"5358.0",
    "gn:admin4_code":"5358012.0",
    "gn:asciiname":"Hergarten",
    "gn:country_code":"DE",
    "gn:dem":339,
    "gn:feature_class":"P",
    "gn:feature_code":"PPL",
    "gn:name":"Hergarten",
    "gn:population":0,
    "gn:timezone":"Europe/Berlin",
    "iso:country":"DE",
    "wof:name":"Hergarten",
    "wof:placetype":"neighbourhood"
},
  "geometry": {"coordinates":[6.54456,50.62128],"type":"Point"}
}