{
  "type": "Feature",
  "properties": {
    "iso:country":"DE",
    "wof:name":"Wiemelhausen",
    "wof:placetype":"neighbourhood"
},
  "geometry": {"coordinates":[7.21683766041077,51.46098190788727],"type":"Point"}
}