{
  "type": "Feature",
  "properties": {
    "gn:admin1_code":"15",
    "gn:admin2_code":"0.0",
    "gn:admin3_code":"16073.0",
    "gn:admin4_code":"16073107.0",
    "gn:asciiname":"Neidenberga",
    "gn:country_code":"DE",
    "gn:dem":394,
    "gn:feature_class":"P",
    "gn:feature_code":"PPL",
    "gn:name":"Neidenberga",
    "gn:population":0,
    "gn:timezone":"Europe/Berlin",
    "iso:country":"DE",
    "wof:name":"Neidenberga",
    "wof:placetype":"neighbourhood"
},
  "geometry": {"coordinates":[11.52311,50.60991],"type":"Point"}
}