{
  "type": "Feature",
  "properties": {
    "gn:admin1_code":"15",
    "gn:admin2_code":"0.0",
    "gn:admin3_code":"16061.0",
    "gn:admin4_code":"16061115.0",
    "gn:asciiname":"Kirchohmfeld",
    "gn:country_code":"DE",
    "gn:dem":424,
    "gn:feature_class":"P",
    "gn:feature_code":"PPL",
    "gn:name":"Kirchohmfeld",
    "gn:population":0,
    "gn:timezone":"Europe/Berlin",
    "iso:country":"DE",
    "wof:name":"Kirchohmfeld",
    "wof:placetype":"neighbourhood"
},
  "geometry": {"coordinates":[10.35891,51.44267],"type":"Point"}
}