{
  "type": "Feature",
  "properties": {
    "iso:country":"DE",
    "name:deu_x_preferred":[
        "Diepeschrath"
    ],
    "name:ind_x_preferred":[
        "Beruas"
    ],
    "name:msa_x_preferred":[
        "Pekan Beruas"
    ],
    "name:unk_x_variant":[
        "Diepeschrath"
    ],
    "qs:gn_adm0_cc":"DE",
    "qs:gn_fcode":"PPL",
    "qs:gn_local":2886242,
    "qs:gn_nam_loc":"Koeln",
    "qs:gn_namadm1":"07",
    "qs:gn_name":"Diepeschrath",
    "qs:local_max":29601,
    "qs:local_sum":50930,
    "qs:localhoods":35,
    "qs:name":"Diepeschrath",
    "qs:name_adm0":"Deutschland",
    "qs:name_adm1":"Nordrhein-Westfalen",
    "qs:name_adm2":"Stadtkreis K\u00f6ln",
    "qs:name_lau":"Stadtteil Dellbr\u00fcck",
    "qs:name_local":"K\u00f6ln",
    "qs:photo_max":916,
    "qs:photo_sum":1677,
    "qs:placetype":"Suburb",
    "qs:quad_count":43,
    "qs:woe_adm0":23424829,
    "qs:woe_adm1":2345487,
    "qs:woe_adm2":12597059,
    "qs:woe_lau":26822833,
    "qs:woe_local":667931,
    "qs:woe_ver":"7.10.0",
    "wof:lang":[
        "ger"
    ],
    "wof:name":"Diepeschrath",
    "wof:placetype":"neighbourhood"
},
  "geometry": {"coordinates":[7.054243,50.968423],"type":"Point"}
}