{
  "type": "Feature",
  "properties": {
    "gn:admin1_code":"11",
    "gn:admin2_code":"0.0",
    "gn:admin3_code":"12070.0",
    "gn:admin4_code":"12070416.0",
    "gn:asciiname":"Schilde",
    "gn:country_code":"DE",
    "gn:dem":25,
    "gn:feature_class":"P",
    "gn:feature_code":"PPL",
    "gn:name":"Schilde",
    "gn:population":0,
    "gn:timezone":"Europe/Berlin",
    "iso:country":"DE",
    "name:bre_x_preferred":[
        "Schilde"
    ],
    "name:bul_x_preferred":[
        "\u0421\u0445\u0438\u043b\u0434\u0435"
    ],
    "name:cat_x_preferred":[
        "Schilde"
    ],
    "name:ceb_x_preferred":[
        "Schilde"
    ],
    "name:deu_x_preferred":[
        "Schilde"
    ],
    "name:epo_x_preferred":[
        "Schilde"
    ],
    "name:fas_x_preferred":[
        "\u0634\u06cc\u0644\u062f"
    ],
    "name:fra_x_preferred":[
        "Schilde"
    ],
    "name:ita_x_preferred":[
        "Schilde"
    ],
    "name:nld_x_preferred":[
        "Schilde"
    ],
    "name:nor_x_preferred":[
        "Schilde"
    ],
    "name:oci_x_preferred":[
        "Schilde"
    ],
    "name:pol_x_preferred":[
        "Schilde"
    ],
    "name:por_x_preferred":[
        "Schilde"
    ],
    "name:ron_x_preferred":[
        "Schilde"
    ],
    "name:slk_x_preferred":[
        "Schilde"
    ],
    "name:spa_x_preferred":[
        "Schilde"
    ],
    "name:srp_x_preferred":[
        "\u0421\u0445\u0438\u043b\u0434\u0435"
    ],
    "name:swe_x_preferred":[
        "Schilde"
    ],
    "name:vol_x_preferred":[
        "Schilde"
    ],
    "name:war_x_preferred":[
        "Schilde"
    ],
    "name:zho_x_preferred":[
        "\u5e0c\u5c14\u5fb7"
    ],
    "wof:name":"Schilde",
    "wof:placetype":"neighbourhood"
},
  "geometry": {"coordinates":[11.77185,53.0521],"type":"Point"}
}