{
  "type": "Feature",
  "properties": {
    "gn:country":"DE",
    "gn:fcode":"PPL",
    "gn:population":0,
    "iso:country":"DE",
    "name:als_x_preferred":[
        "F\u00fcrstenberg"
    ],
    "name:ceb_x_preferred":[
        "F\u00fcrstenberg"
    ],
    "name:deu_x_preferred":[
        "F\u00fcrstenberg"
    ],
    "name:epo_x_preferred":[
        "F\u00fcrstenberg"
    ],
    "name:est_x_preferred":[
        "F\u00fcrstenberg"
    ],
    "name:fra_x_preferred":[
        "F\u00fcrstenberg"
    ],
    "name:heb_x_preferred":[
        "\u05e4\u05d9\u05e8\u05e1\u05d8\u05e0\u05d1\u05e8\u05d2"
    ],
    "name:ita_x_preferred":[
        "F\u00fcrstenberg"
    ],
    "name:jpn_x_preferred":[
        "\u30d5\u30e5\u30eb\u30b9\u30c6\u30f3\u30d9\u30eb\u30af"
    ],
    "name:kor_x_preferred":[
        "\ud4cc\ub974\uc2a4\ud150\ubca0\ub974\ud06c"
    ],
    "name:lav_x_preferred":[
        "Fon Firstenbergs"
    ],
    "name:mkd_x_preferred":[
        "\u0424\u0438\u0440\u0441\u0442\u0435\u043d\u0431\u0435\u0440\u0433"
    ],
    "name:nld_x_preferred":[
        "F\u00fcrstenberg"
    ],
    "name:pol_x_preferred":[
        "F\u00fcrstenberg"
    ],
    "name:rus_x_preferred":[
        "\u0424\u044e\u0440\u0441\u0442\u0435\u043d\u0431\u0435\u0440\u0433"
    ],
    "name:swe_x_preferred":[
        "F\u00fcrstenberg"
    ],
    "qs_pg:aaroncc":"DE",
    "qs_pg:gn_country":"DE",
    "qs_pg:gn_fcode":"PPL",
    "qs_pg:gn_pop":0,
    "qs_pg:name":"F\u00fcrstenberg",
    "qs_pg:name_adm0":"Deutschland",
    "qs_pg:name_adm1":"Nordrhein-Westfalen",
    "qs_pg:photos_9r":0,
    "qs_pg:photos_sr":0,
    "qs_pg:pop_sr":0,
    "qs_pg:qs_pg_placetype":"locality",
    "qs_pg:qs_pg_placetype_gp":"Town",
    "qs_pg:woe_adm0":23424829,
    "woe:adm0_id":23424829,
    "woe:name_adm0":"Deutschland",
    "woe:name_adm1":"Nordrhein-Westfalen",
    "woe:placetype":"Town",
    "wof:name":"F\u00fcrstenberg",
    "wof:placetype":"neighbourhood"
},
  "geometry": {"coordinates":[8.74181,51.51581],"type":"Point"}
}