{
  "type": "Feature",
  "properties": {
    "gn:admin1_code":"10",
    "gn:admin2_code":"0.0",
    "gn:admin3_code":"1062.0",
    "gn:admin4_code":"1062004.0",
    "gn:asciiname":"Rethwischhof",
    "gn:country_code":"DE",
    "gn:dem":19,
    "gn:feature_class":"P",
    "gn:feature_code":"PPL",
    "gn:name":"Rethwischhof",
    "gn:population":0,
    "gn:timezone":"Europe/Berlin",
    "iso:country":"DE",
    "wof:name":"Rethwischhof",
    "wof:placetype":"neighbourhood"
},
  "geometry": {"coordinates":[10.40368,53.79509],"type":"Point"}
}