{
  "type": "Feature",
  "properties": {
    "gn:admin1_code":"6",
    "gn:admin2_code":"0.0",
    "gn:admin3_code":"3241.0",
    "gn:admin4_code":"3241002.0",
    "gn:asciiname":"Nordgoltern",
    "gn:country_code":"DE",
    "gn:dem":58,
    "gn:feature_class":"P",
    "gn:feature_code":"PPL",
    "gn:name":"Nordgoltern",
    "gn:population":0,
    "gn:timezone":"Europe/Berlin",
    "iso:country":"DE",
    "wof:name":"Nordgoltern",
    "wof:placetype":"neighbourhood"
},
  "geometry": {"coordinates":[9.49511,52.33817],"type":"Point"}
}