{
  "type": "Feature",
  "properties": {
    "gn:admin1_code":"7.0",
    "gn:admin2_code":"055",
    "gn:admin3_code":"5570.0",
    "gn:admin4_code":"5570020.0",
    "gn:asciiname":"Wessenhorst",
    "gn:country_code":"DE",
    "gn:dem":67,
    "gn:feature_class":"P",
    "gn:feature_code":"PPLL",
    "gn:name":"Wessenhorst",
    "gn:population":0,
    "gn:timezone":"Europe/Berlin",
    "iso:country":"DE",
    "wof:name":"Wessenhorst",
    "wof:placetype":"neighbourhood"
},
  "geometry": {"coordinates":[7.89582,51.84994],"type":"Point"}
}