{
  "type": "Feature",
  "properties": {
    "gn:admin1_code":"2",
    "gn:admin2_code":"96.0",
    "gn:admin3_code":"9677.0",
    "gn:admin4_code":"9677146.0",
    "gn:asciiname":"Haghof",
    "gn:country_code":"DE",
    "gn:dem":288,
    "gn:feature_class":"P",
    "gn:feature_code":"PPL",
    "gn:name":"Haghof",
    "gn:population":0,
    "gn:timezone":"Europe/Berlin",
    "iso:country":"DE",
    "wof:name":"Haghof",
    "wof:placetype":"neighbourhood"
},
  "geometry": {"coordinates":[9.65,49.85],"type":"Point"}
}