{
  "type": "Feature",
  "properties": {
    "gn:admin1_code":"13",
    "gn:admin2_code":"0.0",
    "gn:admin3_code":"14625.0",
    "gn:admin4_code":"14625500.0",
    "gn:asciiname":"Ralbitz",
    "gn:country_code":"DE",
    "gn:dem":143,
    "gn:feature_class":"P",
    "gn:feature_code":"PPL",
    "gn:name":"Ralbitz",
    "gn:population":0,
    "gn:timezone":"Europe/Berlin",
    "iso:country":"DE",
    "name:hsb_x_preferred":[
        "Ralbicy"
    ],
    "wof:name":"Ralbitz",
    "wof:placetype":"neighbourhood"
},
  "geometry": {"coordinates":[14.24802,51.30124],"type":"Point"}
}