{
  "type": "Feature",
  "properties": {
    "gn:admin1_code":"2",
    "gn:admin2_code":"93.0",
    "gn:admin3_code":"9377.0",
    "gn:admin4_code":"9377113.0",
    "gn:asciiname":"Oberolbuhl",
    "gn:country_code":"DE",
    "gn:dem":630,
    "gn:feature_class":"P",
    "gn:feature_code":"PPL",
    "gn:name":"Ober\u00f6lb\u00fchl",
    "gn:population":0,
    "gn:timezone":"Europe/Berlin",
    "iso:country":"DE",
    "wof:name":"Oberolbuhl",
    "wof:placetype":"neighbourhood"
},
  "geometry": {"coordinates":[11.90693,49.97075],"type":"Point"}
}