{
  "type": "Feature",
  "properties": {
    "gn:admin1_code":"7",
    "gn:admin2_code":"55.0",
    "gn:admin3_code":"5558.0",
    "gn:admin4_code":"5558016.0",
    "gn:asciiname":"Karthaus",
    "gn:country_code":"DE",
    "gn:dem":76,
    "gn:feature_class":"P",
    "gn:feature_code":"PPL",
    "gn:name":"Karthaus",
    "gn:population":0,
    "gn:timezone":"Europe/Berlin",
    "iso:country":"DE",
    "name:deu_x_preferred":[
        "Karthaus"
    ],
    "name:pol_x_preferred":[
        "Karthaus"
    ],
    "wof:name":"Karthaus",
    "wof:placetype":"neighbourhood"
},
  "geometry": {"coordinates":[7.31108,51.87279],"type":"Point"}
}