{
  "type": "Feature",
  "properties": {
    "gn:gn_country":"DE",
    "gn:gn_fcode":"PPLA4",
    "gn:gn_pop":2005,
    "gn:population":2005,
    "iso:country":"DE",
    "name:baq_x_preferred":[
        "Helpsen"
    ],
    "name:chi_x_preferred":[
        "\u9ed1\u5c14\u666e\u68ee"
    ],
    "name:dan_x_preferred":[
        "Helpsen"
    ],
    "name:dut_x_preferred":[
        "Helpsen"
    ],
    "name:eng_x_preferred":[
        "Helpsen"
    ],
    "name:epo_x_preferred":[
        "Helpsen"
    ],
    "name:fre_x_preferred":[
        "Helpsen"
    ],
    "name:ger_x_preferred":[
        "Helpsen"
    ],
    "name:hun_x_preferred":[
        "Helpsen"
    ],
    "name:ita_x_preferred":[
        "Helpsen"
    ],
    "name:jpn_x_preferred":[
        "\u30d8\u30eb\u30d7\u30bc\u30f3"
    ],
    "name:kaz_x_preferred":[
        "\u0425\u0435\u043b\u044c\u043f\u0437\u0435\u043d"
    ],
    "name:kir_x_preferred":[
        "\u0425\u0435\u043b\u044c\u043f\u0437\u0435\u043d"
    ],
    "name:may_x_preferred":[
        "Helpsen"
    ],
    "name:nan_x_preferred":[
        "Helpsen"
    ],
    "name:per_x_preferred":[
        "\u0647\u0644\u067e\u0632\u0646"
    ],
    "name:pol_x_preferred":[
        "Helpsen"
    ],
    "name:por_x_preferred":[
        "Helpsen"
    ],
    "name:rum_x_preferred":[
        "Helpsen"
    ],
    "name:rus_x_preferred":[
        "\u0425\u0435\u043b\u044c\u043f\u0437\u0435\u043d"
    ],
    "name:srp_x_preferred":[
        "\u0425\u0435\u043b\u043f\u0441\u0435\u043d"
    ],
    "name:ukr_x_preferred":[
        "\u0413\u0435\u043b\u044c\u043f\u0437\u0435\u043d"
    ],
    "name:uzb_x_preferred":[
        "Helpsen"
    ],
    "name:vol_x_preferred":[
        "Helpsen"
    ],
    "name:war_x_preferred":[
        "Helpsen"
    ],
    "name:zho_x_preferred":[
        "\u9ed1\u5c14\u666e\u68ee"
    ],
    "qs_pg:aaroncc":"DE",
    "qs_pg:gn_country":"DE",
    "qs_pg:gn_fcode":"PPLA4",
    "qs_pg:gn_pop":2005,
    "qs_pg:name":"Helpsen",
    "qs_pg:photos_9r":0,
    "qs_pg:photos_sr":0,
    "qs_pg:pop_sr":4,
    "qs_pg:qs_pg_placetype":"locality",
    "wof:name":"Helpsen",
    "wof:placetype":"locality",
    "wof:population":2005
},
  "geometry": {"coordinates":[9.11676,52.31131],"type":"Point"}
}