{
  "type": "Feature",
  "properties": {
    "gn:admin1_code":"1",
    "gn:admin2_code":"84.0",
    "gn:admin3_code":"8436.0",
    "gn:admin4_code":"8436052.0",
    "gn:asciiname":"Pfaffenweiler",
    "gn:country_code":"DE",
    "gn:dem":676,
    "gn:feature_class":"P",
    "gn:feature_code":"PPL",
    "gn:name":"Pfaffenweiler",
    "gn:population":0,
    "gn:timezone":"Europe/Berlin",
    "iso:country":"DE",
    "name:als_x_preferred":[
        "Pfaffenweiler"
    ],
    "name:ceb_x_preferred":[
        "Pfaffenweiler"
    ],
    "name:ces_x_preferred":[
        "Pfaffenweiler"
    ],
    "name:deu_x_preferred":[
        "Pfaffenweiler"
    ],
    "name:epo_x_preferred":[
        "Pfaffenweiler"
    ],
    "name:eus_x_preferred":[
        "Pfaffenweiler"
    ],
    "name:fas_x_preferred":[
        "\u067e\u0641\u0627\u0641\u0646\u0648\u0627\u06cc\u0644\u0631"
    ],
    "name:fra_x_preferred":[
        "Pfaffenweiler"
    ],
    "name:hun_x_preferred":[
        "Pfaffenweiler"
    ],
    "name:hye_x_preferred":[
        "\u054a\u0586\u0561\u0586\u0565\u0576\u057e\u0561\u0575\u056c\u0565\u0580"
    ],
    "name:ita_x_preferred":[
        "Pfaffenweiler"
    ],
    "name:lat_x_preferred":[
        "Pfaffenweiler"
    ],
    "name:lmo_x_preferred":[
        "Pfaffenweiler"
    ],
    "name:msa_x_preferred":[
        "Pfaffenweiler"
    ],
    "name:nld_x_preferred":[
        "Pfaffenweiler"
    ],
    "name:pol_x_preferred":[
        "Pfaffenweiler"
    ],
    "name:por_x_preferred":[
        "Pfaffenweiler"
    ],
    "name:ron_x_preferred":[
        "Pfaffenweiler"
    ],
    "name:rus_x_preferred":[
        "\u041f\u0444\u0430\u0444\u0444\u0435\u043d\u0432\u0430\u0439\u043b\u0435\u0440"
    ],
    "name:spa_x_preferred":[
        "Pfaffenweiler"
    ],
    "name:srp_x_preferred":[
        "\u041f\u0444\u0430\u0444\u0435\u043d\u0432\u0430\u0458\u043b\u0435\u0440"
    ],
    "name:ukr_x_preferred":[
        "\u041f\u0444\u0430\u0444\u0444\u0435\u043d\u0432\u0430\u0439\u043b\u0435\u0440"
    ],
    "name:uzb_x_preferred":[
        "Pfaffenweiler"
    ],
    "name:vie_x_preferred":[
        "Pfaffenweiler"
    ],
    "name:vol_x_preferred":[
        "Pfaffenweiler"
    ],
    "name:war_x_preferred":[
        "Pfaffenweiler"
    ],
    "name:zho_x_preferred":[
        "\u666e\u6cd5\u82ac\u97e6\u52d2"
    ],
    "wof:name":"Pfaffenweiler",
    "wof:placetype":"neighbourhood"
},
  "geometry": {"coordinates":[9.86667,47.78333],"type":"Point"}
}