{
  "type": "Feature",
  "properties": {
    "gn:admin1_code":"1",
    "gn:admin2_code":"84.0",
    "gn:admin3_code":"8436.0",
    "gn:admin4_code":"8436052.0",
    "gn:asciiname":"Pfaffenweiler",
    "gn:country_code":"DE",
    "gn:dem":676,
    "gn:feature_class":"P",
    "gn:feature_code":"PPL",
    "gn:name":"Pfaffenweiler",
    "gn:population":0,
    "gn:timezone":"Europe/Berlin",
    "iso:country":"DE",
    "wof:name":"Pfaffenweiler",
    "wof:placetype":"neighbourhood"
},
  "geometry": {"coordinates":[9.86667,47.78333],"type":"Point"}
}