{
  "type": "Feature",
  "properties": {
    "gn:admin1_code":"1",
    "gn:admin2_code":"84.0",
    "gn:admin3_code":"8416.0",
    "gn:admin4_code":"8416048.0",
    "gn:asciiname":"Poltringen",
    "gn:country_code":"DE",
    "gn:dem":359,
    "gn:feature_class":"P",
    "gn:feature_code":"PPL",
    "gn:name":"Poltringen",
    "gn:population":0,
    "gn:timezone":"Europe/Berlin",
    "iso:country":"DE",
    "name:deu_x_preferred":[
        "Poltringen"
    ],
    "name:nld_x_preferred":[
        "Poltringen"
    ],
    "wof:name":"Poltringen",
    "wof:placetype":"neighbourhood"
},
  "geometry": {"coordinates":[8.94639,48.53602],"type":"Point"}
}