{
  "type": "Feature",
  "properties": {
    "gn:admin1_code":"6",
    "gn:admin2_code":"0.0",
    "gn:admin3_code":"3354.0",
    "gn:admin4_code":"3354013.0",
    "gn:asciiname":"Guehlitz",
    "gn:country_code":"DE",
    "gn:dem":23,
    "gn:feature_class":"P",
    "gn:feature_code":"PPL",
    "gn:name":"G\u00fchlitz",
    "gn:population":0,
    "gn:timezone":"Europe/Berlin",
    "iso:country":"DE",
    "wof:name":"Guehlitz",
    "wof:placetype":"neighbourhood"
},
  "geometry": {"coordinates":[11.0804,52.96645],"type":"Point"}
}