{
  "type": "Feature",
  "properties": {
    "gn:admin1_code":"6",
    "gn:admin2_code":"0.0",
    "gn:admin3_code":"3254.0",
    "gn:admin4_code":"3254026.0",
    "gn:asciiname":"Burgstemmen",
    "gn:country_code":"DE",
    "gn:dem":82,
    "gn:feature_class":"P",
    "gn:feature_code":"PPL",
    "gn:name":"Burgstemmen",
    "gn:population":0,
    "gn:timezone":"Europe/Berlin",
    "iso:country":"DE",
    "wof:name":"Burgstemmen",
    "wof:placetype":"neighbourhood"
},
  "geometry": {"coordinates":[9.77562,52.14493],"type":"Point"}
}