{
  "type": "Feature",
  "properties": {
    "gn:admin1_code":"1",
    "gn:admin2_code":"81.0",
    "gn:admin3_code":"8128.0",
    "gn:admin4_code":"8128082.0",
    "gn:asciiname":"Eichhof",
    "gn:country_code":"DE",
    "gn:dem":417,
    "gn:feature_class":"P",
    "gn:feature_code":"PPL",
    "gn:name":"Eichhof",
    "gn:population":0,
    "gn:timezone":"Europe/Berlin",
    "iso:country":"DE",
    "wof:name":"Eichhof",
    "wof:placetype":"neighbourhood"
},
  "geometry": {"coordinates":[9.88485,49.39361],"type":"Point"}
}