{
  "type": "Feature",
  "properties": {
    "gn:admin1_code":"15",
    "gn:admin2_code":"0.0",
    "gn:admin3_code":"16077.0",
    "gn:admin4_code":"16077048.0",
    "gn:asciiname":"Trebanz",
    "gn:country_code":"DE",
    "gn:dem":162,
    "gn:feature_class":"P",
    "gn:feature_code":"PPL",
    "gn:name":"Trebanz",
    "gn:population":0,
    "gn:timezone":"Europe/Berlin",
    "iso:country":"DE",
    "wof:name":"Trebanz",
    "wof:placetype":"neighbourhood"
},
  "geometry": {"coordinates":[12.4341,51.04028],"type":"Point"}
}