{
  "type": "Feature",
  "properties": {
    "gn:admin1_code":"13.0",
    "gn:admin2_code":"00",
    "gn:admin3_code":"14522.0",
    "gn:admin4_code":"14522450.0",
    "gn:asciiname":"Zschochau",
    "gn:country_code":"DE",
    "gn:dem":182,
    "gn:feature_class":"P",
    "gn:feature_code":"PPL",
    "gn:name":"Zschochau",
    "gn:population":0,
    "gn:timezone":"Europe/Berlin",
    "iso:country":"DE",
    "wof:name":"Zschochau",
    "wof:placetype":"neighbourhood"
},
  "geometry": {"coordinates":[13.19685,51.19727],"type":"Point"}
}