{
  "type": "Feature",
  "properties": {
    "gn:admin1_code":"15",
    "gn:admin2_code":"0.0",
    "gn:admin3_code":"16076.0",
    "gn:admin4_code":"16076022.0",
    "gn:asciiname":"Untergrochlitz",
    "gn:country_code":"DE",
    "gn:dem":343,
    "gn:feature_class":"P",
    "gn:feature_code":"PPL",
    "gn:name":"Untergrochlitz",
    "gn:population":0,
    "gn:timezone":"Europe/Berlin",
    "iso:country":"DE",
    "name:und_x_variant":[
        "Greiz-Untergrochlitz",
        "Untergrochlitz"
    ],
    "wof:name":"Untergrochlitz",
    "wof:placetype":"neighbourhood"
},
  "geometry": {"coordinates":[12.16217,50.64462],"type":"Point"}
}