{
  "type": "Feature",
  "properties": {
    "gn:admin1_code":"14",
    "gn:asciiname":"Sonnendorf",
    "gn:country_code":"DE",
    "gn:dem":202,
    "gn:feature_class":"P",
    "gn:feature_code":"PPL",
    "gn:name":"Sonnendorf",
    "gn:population":0,
    "gn:timezone":"Europe/Berlin",
    "iso:country":"DE",
    "wof:name":"Sonnendorf",
    "wof:placetype":"neighbourhood"
},
  "geometry": {"coordinates":[11.6387,51.10818],"type":"Point"}
}