{
  "type": "Feature",
  "properties": {
    "gn:admin1_code":"15.0",
    "gn:admin2_code":"0.0",
    "gn:admin3_code":"16068.0",
    "gn:admin4_code":"16068036.0",
    "gn:asciiname":"Bachstedt",
    "gn:country_code":"DE",
    "gn:dem":194,
    "gn:feature_class":"P",
    "gn:feature_code":"PPL",
    "gn:name":"Bachstedt",
    "gn:population":0,
    "gn:timezone":"Europe/Berlin",
    "iso:country":"DE",
    "name:gml_x_preferred":[
        "Bacsteden [a. 1144]"
    ],
    "name:gml_x_variant":[
        "Baksteti"
    ],
    "wof:name":"Bachstedt",
    "wof:placetype":"neighbourhood"
},
  "geometry": {"coordinates":[11.19025,51.0641],"type":"Point"}
}