{
  "type": "Feature",
  "properties": {
    "gn:admin1_code":"7",
    "gn:admin2_code":"53.0",
    "gn:admin3_code":"5374.0",
    "gn:admin4_code":"5374052.0",
    "gn:asciiname":"Muente",
    "gn:country_code":"DE",
    "gn:dem":340,
    "gn:feature_class":"P",
    "gn:feature_code":"PPL",
    "gn:name":"M\u00fcnte",
    "gn:population":0,
    "gn:timezone":"Europe/Berlin",
    "iso:country":"DE",
    "wof:name":"Muente",
    "wof:placetype":"neighbourhood"
},
  "geometry": {"coordinates":[7.39176,51.10665],"type":"Point"}
}