{
  "type": "Feature",
  "properties": {
    "gn:admin1_code":"14",
    "gn:admin2_code":"0.0",
    "gn:admin3_code":"15085.0",
    "gn:admin4_code":"15085227.0",
    "gn:asciiname":"Neue Turmwarte",
    "gn:country_code":"DE",
    "gn:dem":205,
    "gn:feature_class":"P",
    "gn:feature_code":"PPL",
    "gn:name":"Neue Turmwarte",
    "gn:population":0,
    "gn:timezone":"Europe/Berlin",
    "iso:country":"DE",
    "wof:name":"Neue Turmwarte",
    "wof:placetype":"neighbourhood"
},
  "geometry": {"coordinates":[10.75,51.88333],"type":"Point"}
}