{
  "type": "Feature",
  "properties": {
    "gn:admin1_code":"2",
    "gn:admin2_code":"94.0",
    "gn:admin3_code":"9471.0",
    "gn:admin4_code":"9471123.0",
    "gn:asciiname":"Tiefenhochstadt",
    "gn:country_code":"DE",
    "gn:dem":465,
    "gn:feature_class":"P",
    "gn:feature_code":"PPL",
    "gn:name":"Tiefenh\u00f6chstadt",
    "gn:population":0,
    "gn:timezone":"Europe/Berlin",
    "iso:country":"DE",
    "name:deu_x_preferred":[
        "Tiefenh\u00f6chstadt"
    ],
    "wof:name":"Tiefenhochstadt",
    "wof:placetype":"neighbourhood"
},
  "geometry": {"coordinates":[11.07748,49.85016],"type":"Point"}
}