{
  "type": "Feature",
  "properties": {
    "gn:admin1_code":"1",
    "gn:admin2_code":"81.0",
    "gn:admin3_code":"8127.0",
    "gn:admin4_code":"8127076.0",
    "gn:asciiname":"Weckrieden",
    "gn:country_code":"DE",
    "gn:dem":392,
    "gn:feature_class":"P",
    "gn:feature_code":"PPL",
    "gn:name":"Weckrieden",
    "gn:population":0,
    "gn:timezone":"Europe/Berlin",
    "iso:country":"DE",
    "wof:name":"Weckrieden",
    "wof:placetype":"neighbourhood"
},
  "geometry": {"coordinates":[9.7529,49.12385],"type":"Point"}
}