{
  "type": "Feature",
  "properties": {
    "gn:admin1_code":"7",
    "gn:admin2_code":"53.0",
    "gn:admin3_code":"5378.0",
    "gn:admin4_code":"5378032.0",
    "gn:asciiname":"Roelscheide",
    "gn:country_code":"DE",
    "gn:dem":258,
    "gn:feature_class":"P",
    "gn:feature_code":"PPL",
    "gn:name":"R\u00f6lscheide",
    "gn:population":0,
    "gn:timezone":"Europe/Berlin",
    "iso:country":"DE",
    "wof:name":"Roelscheide",
    "wof:placetype":"neighbourhood"
},
  "geometry": {"coordinates":[7.21515,51.09046],"type":"Point"}
}