{
  "type": "Feature",
  "properties": {
    "gn:admin1_code":"2",
    "gn:admin2_code":"91.0",
    "gn:admin3_code":"9183.0",
    "gn:admin4_code":"9183130.0",
    "gn:asciiname":"Sarling",
    "gn:country_code":"DE",
    "gn:dem":448,
    "gn:feature_class":"P",
    "gn:feature_code":"PPL",
    "gn:name":"Sarling",
    "gn:population":0,
    "gn:timezone":"Europe/Berlin",
    "iso:country":"DE",
    "wof:name":"Sarling",
    "wof:placetype":"neighbourhood"
},
  "geometry": {"coordinates":[12.50785,48.3256],"type":"Point"}
}