{
  "type": "Feature",
  "properties": {
    "gn:admin1_code":"2",
    "gn:admin2_code":"97.0",
    "gn:admin3_code":"9780.0",
    "gn:admin4_code":"9780143.0",
    "gn:asciiname":"Veits",
    "gn:country_code":"DE",
    "gn:dem":698,
    "gn:feature_class":"P",
    "gn:feature_code":"PPL",
    "gn:name":"Veits",
    "gn:population":0,
    "gn:timezone":"Europe/Berlin",
    "iso:country":"DE",
    "wof:name":"Veits",
    "wof:placetype":"neighbourhood"
},
  "geometry": {"coordinates":[10.31737,47.68077],"type":"Point"}
}