{
  "type": "Feature",
  "properties": {
    "iso:country":"DE",
    "wof:name":"Bilk",
    "wof:placetype":"neighbourhood"
},
  "geometry": {"coordinates":[6.77530433603335,51.20323378568799],"type":"Point"}
}