{
  "type": "Feature",
  "properties": {
    "iso:country":"DE",
    "name:deu_x_preferred":[
        "Bilk"
    ],
    "name:ita_x_preferred":[
        "Bilk"
    ],
    "name:pol_x_preferred":[
        "Bilk"
    ],
    "name:rus_x_preferred":[
        "\u0414\u044e\u0441\u0441\u0435\u043b\u044c\u0434\u043e\u0440\u0444-\u0411\u0438\u043b\u044c\u043a"
    ],
    "wof:name":"Bilk",
    "wof:placetype":"neighbourhood"
},
  "geometry": {"coordinates":[6.77530433603335,51.20323378568799],"type":"Point"}
}