{
  "type": "Feature",
  "properties": {
    "gn:admin1_code":"15.0",
    "gn:admin2_code":"00",
    "gn:admin3_code":"16075.0",
    "gn:admin4_code":"16075103.0",
    "gn:asciiname":"Woehlsdorf",
    "gn:country_code":"DE",
    "gn:dem":352,
    "gn:feature_class":"P",
    "gn:feature_code":"PPL",
    "gn:name":"W\u00f6hlsdorf",
    "gn:population":0,
    "gn:timezone":"Europe/Berlin",
    "iso:country":"DE",
    "wof:name":"Woehlsdorf",
    "wof:placetype":"neighbourhood"
},
  "geometry": {"coordinates":[11.54423,50.65229],"type":"Point"}
}