{
  "type": "Feature",
  "properties": {
    "gn:admin1_code":"15",
    "gn:admin2_code":"0.0",
    "gn:admin3_code":"16069.0",
    "gn:admin4_code":"16069009.0",
    "gn:asciiname":"Ehrenberg",
    "gn:country_code":"DE",
    "gn:dem":399,
    "gn:feature_class":"P",
    "gn:feature_code":"PPLA4",
    "gn:name":"Ehrenberg",
    "gn:population":0,
    "gn:timezone":"Europe/Berlin",
    "iso:country":"DE",
    "wof:name":"Ehrenberg",
    "wof:placetype":"locality"
},
  "geometry": {"coordinates":[10.65,50.48333],"type":"Point"}
}