{
  "type": "Feature",
  "properties": {
    "gn:admin1_code":"13",
    "gn:admin2_code":"0.0",
    "gn:admin3_code":"14522.0",
    "gn:admin4_code":"14522540.0",
    "gn:asciiname":"Kaltofen",
    "gn:country_code":"DE",
    "gn:dem":320,
    "gn:feature_class":"P",
    "gn:feature_code":"PPL",
    "gn:name":"Kaltofen",
    "gn:population":0,
    "gn:timezone":"Europe/Berlin",
    "iso:country":"DE",
    "wof:name":"Kaltofen",
    "wof:placetype":"neighbourhood"
},
  "geometry": {"coordinates":[13.15423,50.99073],"type":"Point"}
}