{
  "type": "Feature",
  "properties": {
    "gn:admin1_code":"6",
    "gn:admin2_code":"0.0",
    "gn:admin3_code":"3458.0",
    "gn:admin4_code":"3458014.0",
    "gn:asciiname":"Garmhausen",
    "gn:country_code":"DE",
    "gn:dem":27,
    "gn:feature_class":"P",
    "gn:feature_code":"PPL",
    "gn:name":"Garmhausen",
    "gn:population":0,
    "gn:timezone":"Europe/Berlin",
    "iso:country":"DE",
    "wof:name":"Garmhausen",
    "wof:placetype":"neighbourhood"
},
  "geometry": {"coordinates":[8.46543,52.82981],"type":"Point"}
}