{
  "type": "Feature",
  "properties": {
    "gn:admin1_code":"13",
    "gn:admin2_code":"0.0",
    "gn:admin3_code":"14627.0",
    "gn:admin4_code":"14627290.0",
    "gn:asciiname":"Sacka",
    "gn:country_code":"DE",
    "gn:dem":168,
    "gn:feature_class":"P",
    "gn:feature_code":"PPL",
    "gn:name":"Sacka",
    "gn:population":0,
    "gn:timezone":"Europe/Berlin",
    "iso:country":"DE",
    "wof:name":"Sacka",
    "wof:placetype":"neighbourhood"
},
  "geometry": {"coordinates":[13.79158,51.28402],"type":"Point"}
}