{
  "type": "Feature",
  "properties": {
    "gn:admin1_code":"2",
    "gn:admin2_code":"97.0",
    "gn:admin3_code":"9778.0",
    "gn:admin4_code":"9778165.0",
    "gn:asciiname":"Hummels",
    "gn:country_code":"DE",
    "gn:dem":675,
    "gn:feature_class":"P",
    "gn:feature_code":"PPL",
    "gn:name":"Hummels",
    "gn:population":0,
    "gn:timezone":"Europe/Berlin",
    "iso:country":"DE",
    "wof:name":"Hummels",
    "wof:placetype":"neighbourhood"
},
  "geometry": {"coordinates":[10.13196,47.8701],"type":"Point"}
}