{
  "type": "Feature",
  "properties": {
    "gn:country":"DE",
    "gn:fcode":"PPL",
    "gn:population":0,
    "iso:country":"DE",
    "name:ceb_x_preferred":[
        "Besse"
    ],
    "name:deu_x_preferred":[
        "Besse"
    ],
    "name:fra_x_preferred":[
        "Besse"
    ],
    "name:ita_x_preferred":[
        "Besse"
    ],
    "name:ltz_x_preferred":[
        "Besse"
    ],
    "name:nds_x_preferred":[
        "Besse"
    ],
    "name:nld_x_preferred":[
        "Besse"
    ],
    "name:pms_x_preferred":[
        "Besse"
    ],
    "name:pol_x_preferred":[
        "Besse"
    ],
    "name:por_x_preferred":[
        "Besse"
    ],
    "name:scn_x_preferred":[
        "Besse"
    ],
    "name:slk_x_preferred":[
        "Besse"
    ],
    "name:spa_x_preferred":[
        "Besse"
    ],
    "name:srp_x_preferred":[
        "\u0411\u0435\u0441\u0435"
    ],
    "name:swe_x_preferred":[
        "Besse"
    ],
    "qs_pg:aaroncc":"DE",
    "qs_pg:gn_country":"DE",
    "qs_pg:gn_fcode":"PPL",
    "qs_pg:gn_pop":0,
    "qs_pg:name":"Besse",
    "qs_pg:name_adm0":"Deutschland",
    "qs_pg:name_adm1":"Hessen",
    "qs_pg:photos_9k":1,
    "qs_pg:photos_9r":1,
    "qs_pg:photos_all":1,
    "qs_pg:photos_sr":0,
    "qs_pg:pop_sr":0,
    "qs_pg:qs_pg_placetype":"locality",
    "qs_pg:qs_pg_placetype_gp":"Town",
    "qs_pg:woe_adm0":23424829,
    "woe:adm0_id":23424829,
    "woe:name_adm0":"Deutschland",
    "woe:name_adm1":"Hessen",
    "woe:placetype":"Town",
    "wof:name":"Besse",
    "wof:placetype":"neighbourhood"
},
  "geometry": {"coordinates":[9.39032,51.22094],"type":"Point"}
}