{
  "type": "Feature",
  "properties": {
    "gn:admin1_code":"2",
    "gn:admin2_code":"95.0",
    "gn:admin3_code":"9571.0",
    "gn:admin4_code":"9571113.0",
    "gn:asciiname":"Goldbuhl",
    "gn:country_code":"DE",
    "gn:dem":466,
    "gn:feature_class":"P",
    "gn:feature_code":"PPL",
    "gn:name":"Goldb\u00fchl",
    "gn:population":0,
    "gn:timezone":"Europe/Berlin",
    "iso:country":"DE",
    "wof:name":"Goldbuhl",
    "wof:placetype":"neighbourhood"
},
  "geometry": {"coordinates":[10.6412,49.12777],"type":"Point"}
}