{
  "type": "Feature",
  "properties": {
    "gn:admin1_code":"1",
    "gn:admin2_code":"84.0",
    "gn:admin3_code":"8436.0",
    "gn:admin4_code":"8436081.0",
    "gn:asciiname":"Deuchelried",
    "gn:country_code":"DE",
    "gn:dem":592,
    "gn:feature_class":"P",
    "gn:feature_code":"PPL",
    "gn:name":"Deuchelried",
    "gn:population":0,
    "gn:timezone":"Europe/Berlin",
    "iso:country":"DE",
    "wof:name":"Deuchelried",
    "wof:placetype":"neighbourhood"
},
  "geometry": {"coordinates":[9.85091,47.69441],"type":"Point"}
}