{
  "type": "Feature",
  "properties": {
    "gn:admin1_code":"2",
    "gn:admin2_code":"91.0",
    "gn:admin3_code":"9175.0",
    "gn:admin4_code":"9175121.0",
    "gn:asciiname":"Doblberg",
    "gn:country_code":"DE",
    "gn:dem":566,
    "gn:feature_class":"P",
    "gn:feature_code":"PPL",
    "gn:name":"Doblberg",
    "gn:population":0,
    "gn:timezone":"Europe/Berlin",
    "iso:country":"DE",
    "wof:name":"Doblberg",
    "wof:placetype":"neighbourhood"
},
  "geometry": {"coordinates":[11.87279,48.01077],"type":"Point"}
}