{
  "type": "Feature",
  "properties": {
    "gn:admin1_code":"8",
    "gn:admin2_code":"0.0",
    "gn:admin3_code":"7336.0",
    "gn:admin4_code":"7336095.0",
    "gn:asciiname":"Eschenau",
    "gn:country_code":"DE",
    "gn:dem":200,
    "gn:feature_class":"P",
    "gn:feature_code":"PPL",
    "gn:name":"Eschenau",
    "gn:population":0,
    "gn:timezone":"Europe/Berlin",
    "iso:country":"DE",
    "wof:name":"Eschenau",
    "wof:placetype":"neighbourhood"
},
  "geometry": {"coordinates":[7.48813,49.60068],"type":"Point"}
}