{
  "type": "Feature",
  "properties": {
    "gn:admin1_code":"8",
    "gn:admin2_code":"0.0",
    "gn:admin3_code":"7336.0",
    "gn:admin4_code":"7336095.0",
    "gn:asciiname":"Eschenau",
    "gn:country_code":"DE",
    "gn:dem":200,
    "gn:feature_class":"P",
    "gn:feature_code":"PPL",
    "gn:name":"Eschenau",
    "gn:population":0,
    "gn:timezone":"Europe/Berlin",
    "iso:country":"DE",
    "name:ceb_x_preferred":[
        "Eschenau"
    ],
    "name:deu_x_preferred":[
        "Eschenau"
    ],
    "name:epo_x_preferred":[
        "Eschenau"
    ],
    "name:fas_x_preferred":[
        "\u0627\u0634\u0646\u0648"
    ],
    "name:fra_x_preferred":[
        "Eschenau"
    ],
    "name:hun_x_preferred":[
        "Eschenau"
    ],
    "name:ita_x_preferred":[
        "Eschenau"
    ],
    "name:kaz_x_preferred":[
        "\u0412\u0435\u0440\u0430\u0431\u0430\u0445"
    ],
    "name:nld_x_preferred":[
        "Eschenau"
    ],
    "name:pol_x_preferred":[
        "Eschenau"
    ],
    "name:por_x_preferred":[
        "Eschenau"
    ],
    "name:rus_x_preferred":[
        "\u042d\u0448\u0435\u043d\u0430\u0443"
    ],
    "name:slk_x_preferred":[
        "Eschenau"
    ],
    "name:spa_x_preferred":[
        "Eschenau"
    ],
    "name:swe_x_preferred":[
        "Eschenau"
    ],
    "name:uzb_x_preferred":[
        "Eschenau"
    ],
    "name:vie_x_preferred":[
        "Eschenau"
    ],
    "name:vol_x_preferred":[
        "Eschenau"
    ],
    "name:war_x_preferred":[
        "Eschenau"
    ],
    "name:zho_x_preferred":[
        "\u57c3\u820d\u7459"
    ],
    "wof:name":"Eschenau",
    "wof:placetype":"neighbourhood"
},
  "geometry": {"coordinates":[7.48813,49.60068],"type":"Point"}
}