{
  "type": "Feature",
  "properties": {
    "gn:admin1_code":"6",
    "gn:admin2_code":"0.0",
    "gn:admin3_code":"3154.0",
    "gn:admin4_code":"3154013.0",
    "gn:asciiname":"Uhry",
    "gn:country_code":"DE",
    "gn:dem":100,
    "gn:feature_class":"P",
    "gn:feature_code":"PPL",
    "gn:name":"Uhry",
    "gn:population":0,
    "gn:timezone":"Europe/Berlin",
    "iso:country":"DE",
    "name:ceb_x_preferred":[
        "Uhry"
    ],
    "name:deu_x_preferred":[
        "Uhry"
    ],
    "name:fas_x_preferred":[
        "\u0627\u0648\u0631\u06cc"
    ],
    "name:nds_x_preferred":[
        "Uhry"
    ],
    "name:nld_x_preferred":[
        "Uhry"
    ],
    "wof:name":"Uhry",
    "wof:placetype":"neighbourhood"
},
  "geometry": {"coordinates":[10.85758,52.29693],"type":"Point"}
}