{
  "type": "Feature",
  "properties": {
    "gn:admin1_code":"2",
    "gn:admin2_code":"92.0",
    "gn:admin3_code":"9275.0",
    "gn:admin4_code":"9275148.0",
    "gn:asciiname":"Holzgattern",
    "gn:country_code":"DE",
    "gn:dem":862,
    "gn:feature_class":"P",
    "gn:feature_code":"PPL",
    "gn:name":"Holzgattern",
    "gn:population":0,
    "gn:timezone":"Europe/Berlin",
    "iso:country":"DE",
    "wof:name":"Holzgattern",
    "wof:placetype":"neighbourhood"
},
  "geometry": {"coordinates":[13.72693,48.67224],"type":"Point"}
}