{
  "type": "Feature",
  "properties": {
    "gn:admin1_code":"6",
    "gn:admin2_code":"0.0",
    "gn:admin3_code":"3457.0",
    "gn:admin4_code":"3457014.0",
    "gn:asciiname":"Warsingsfehn",
    "gn:country_code":"DE",
    "gn:dem":2,
    "gn:feature_class":"P",
    "gn:feature_code":"PPL",
    "gn:name":"Warsingsfehn",
    "gn:population":0,
    "gn:timezone":"Europe/Berlin",
    "iso:country":"DE",
    "wof:name":"Warsingsfehn",
    "wof:placetype":"neighbourhood"
},
  "geometry": {"coordinates":[7.48756,53.31108],"type":"Point"}
}