{
  "type": "Feature",
  "properties": {
    "gn:gn_country":"DE",
    "gn:gn_fcode":"PPLA4",
    "gn:gn_pop":971,
    "gn:population":971,
    "iso:country":"DE",
    "name:bak_x_preferred":[
        "\u041d\u0435\u043c\u0441\u0434\u043e\u0440\u0444-\u0413\u0451\u0440\u0435\u043d\u0434\u043e\u0440\u0444"
    ],
    "name:chi_x_preferred":[
        "\u5185\u59c6\u65af\u591a\u592b-\u683c\u8d6b\u4f26\u591a\u592b"
    ],
    "name:dut_x_preferred":[
        "Nemsdorf-G\u00f6hrendorf"
    ],
    "name:eng_x_preferred":[
        "Nemsdorf-G\u00f6hrendorf"
    ],
    "name:epo_x_preferred":[
        "Nemsdorf-G\u00f6hrendorf"
    ],
    "name:fre_x_preferred":[
        "Nemsdorf-G\u00f6hrendorf"
    ],
    "name:ger_x_preferred":[
        "Nemsdorf-G\u00f6hrendorf"
    ],
    "name:hun_x_preferred":[
        "Nemsdorf-G\u00f6hrendorf"
    ],
    "name:ita_x_preferred":[
        "Nemsdorf-G\u00f6hrendorf"
    ],
    "name:kaz_x_preferred":[
        "\u041d\u0435\u043c\u0441\u0434\u043e\u0440\u0444-\u0413\u0451\u0440\u0435\u043d\u0434\u043e\u0440\u0444"
    ],
    "name:kir_x_preferred":[
        "\u041d\u0435\u043c\u0441\u0434\u043e\u0440\u0444-\u0413\u04e9\u0440\u0435\u043d\u0434\u043e\u0440\u0444"
    ],
    "name:mac_x_preferred":[
        "\u041d\u0435\u043c\u0441\u0434\u043e\u0440\u0444-\u0413\u0435\u0440\u0435\u043d\u0434\u043e\u0440\u0444"
    ],
    "name:may_x_preferred":[
        "Nemsdorf-G\u00f6hrendorf"
    ],
    "name:per_x_preferred":[
        "\u0646\u0645\u0633\u062f\u0648\u0631\u0641-\u06af\u0648\u0647\u0631\u0646\u062f\u0648\u0631\u0641"
    ],
    "name:pol_x_preferred":[
        "Nemsdorf-G\u00f6hrendorf"
    ],
    "name:rum_x_preferred":[
        "Nemsdorf-G\u00f6hrendorf"
    ],
    "name:rus_x_preferred":[
        "\u041d\u0435\u043c\u0441\u0434\u043e\u0440\u0444-\u0413\u0451\u0440\u0435\u043d\u0434\u043e\u0440\u0444"
    ],
    "name:srp_x_preferred":[
        "\u041d\u0435\u043c\u0441\u0434\u043e\u0440\u0444-\u0413\u0435\u0440\u0435\u043d\u0434\u043e\u0440\u0444"
    ],
    "name:ukr_x_preferred":[
        "\u041d\u0435\u043c\u0441\u0434\u043e\u0440\u0444-\u0413\u0435\u0440\u0435\u043d\u0434\u043e\u0440\u0444"
    ],
    "name:uzb_x_preferred":[
        "Nemsdorf-G\u00f6hrendorf"
    ],
    "name:vie_x_preferred":[
        "Nemsdorf-G\u00f6hrendorf"
    ],
    "name:vol_x_preferred":[
        "Nemsdorf-G\u00f6hrendorf"
    ],
    "name:war_x_preferred":[
        "Nemsdorf-G\u00f6hrendorf"
    ],
    "qs_pg:aaroncc":"DE",
    "qs_pg:gn_country":"DE",
    "qs_pg:gn_fcode":"PPLA4",
    "qs_pg:gn_pop":971,
    "qs_pg:name":"Nemsdorf-G\u00f6hrendorf",
    "qs_pg:photos_9r":0,
    "qs_pg:photos_sr":0,
    "qs_pg:pop_sr":2,
    "qs_pg:qs_pg_placetype":"locality",
    "wof:name":"Nemsdorf-G\u00f6hrendorf",
    "wof:placetype":"locality",
    "wof:population":971
},
  "geometry": {"coordinates":[11.65,51.35],"type":"Point"}
}