{
  "type": "Feature",
  "properties": {
    "gn:admin1_code":"7",
    "gn:admin2_code":"59.0",
    "gn:admin3_code":"5958.0",
    "gn:admin4_code":"5958044.0",
    "gn:asciiname":"Doernholthausen",
    "gn:country_code":"DE",
    "gn:dem":354,
    "gn:feature_class":"P",
    "gn:feature_code":"PPL",
    "gn:name":"D\u00f6rnholthausen",
    "gn:population":0,
    "gn:timezone":"Europe/Berlin",
    "iso:country":"DE",
    "wof:name":"Doernholthausen",
    "wof:placetype":"neighbourhood"
},
  "geometry": {"coordinates":[7.98977,51.28466],"type":"Point"}
}