{
  "type": "Feature",
  "properties": {
    "gn:admin1_code":"10",
    "gn:admin2_code":"0.0",
    "gn:admin3_code":"1054.0",
    "gn:admin4_code":"1054168.0",
    "gn:asciiname":"Osterwall",
    "gn:country_code":"DE",
    "gn:dem":2,
    "gn:feature_class":"P",
    "gn:feature_code":"PPL",
    "gn:name":"Osterwall",
    "gn:population":0,
    "gn:timezone":"Europe/Berlin",
    "iso:country":"DE",
    "wof:name":"Osterwall",
    "wof:placetype":"neighbourhood"
},
  "geometry": {"coordinates":[8.42171,54.86149],"type":"Point"}
}