{
  "type": "Feature",
  "properties": {
    "gn:country":"DE",
    "gn:fcode":"PPL",
    "gn:population":0,
    "iso:country":"DE",
    "name:deu_x_preferred":[
        "Isernhagen-Niederh\u00e4gener Bauernschaft"
    ],
    "name:deu_x_variant":[
        "Isernhagen NB"
    ],
    "name:nds_x_preferred":[
        "up\u2019n Niernhagen"
    ],
    "name:und_x_variant":[
        "Niederh\u00e4gener Bauerschaft"
    ],
    "qs_pg:aaroncc":"DE",
    "qs_pg:gn_country":"DE",
    "qs_pg:gn_fcode":"PPL",
    "qs_pg:gn_pop":0,
    "qs_pg:name":"Isernhagen Niederh\u00e4gener Bauerschaf",
    "qs_pg:name_adm0":"Deutschland",
    "qs_pg:name_adm1":"Niedersachsen",
    "qs_pg:photos_9r":0,
    "qs_pg:photos_sr":0,
    "qs_pg:pop_sr":0,
    "qs_pg:qs_pg_placetype":"locality",
    "qs_pg:qs_pg_placetype_gp":"Town",
    "qs_pg:woe_adm0":23424829,
    "woe:adm0_id":23424829,
    "woe:name_adm0":"Deutschland",
    "woe:name_adm1":"Niedersachsen",
    "woe:placetype":"Town",
    "wof:name":"Isernhagen Niederh\u00e4gener Bauerschaf",
    "wof:placetype":"neighbourhood"
},
  "geometry": {"coordinates":[9.79182,52.4558],"type":"Point"}
}