{
  "type": "Feature",
  "properties": {
    "gn:admin1_code":"2.0",
    "gn:admin2_code":"095",
    "gn:admin3_code":"9561.0",
    "gn:admin4_code":"9561000.0",
    "gn:asciiname":"Wengenstadt",
    "gn:country_code":"DE",
    "gn:dem":463,
    "gn:feature_class":"P",
    "gn:feature_code":"PPL",
    "gn:name":"Wengenstadt",
    "gn:population":0,
    "gn:timezone":"Europe/Berlin",
    "iso:country":"DE",
    "wof:name":"Wengenstadt",
    "wof:placetype":"neighbourhood"
},
  "geometry": {"coordinates":[10.60205,49.32598],"type":"Point"}
}