{
  "type": "Feature",
  "properties": {
    "gn:admin1_code":"13.0",
    "gn:admin2_code":"0.0",
    "gn:admin3_code":"14729.0",
    "gn:admin4_code":"14729050.0",
    "gn:asciiname":"Berghaeuser",
    "gn:country_code":"DE",
    "gn:dem":163,
    "gn:feature_class":"P",
    "gn:feature_code":"PPL",
    "gn:name":"Bergh\u00e4user",
    "gn:population":0,
    "gn:timezone":"Europe/Berlin",
    "iso:country":"DE",
    "wof:name":"Berghaeuser",
    "wof:placetype":"neighbourhood"
},
  "geometry": {"coordinates":[12.51247,51.15753],"type":"Point"}
}