{
  "type": "Feature",
  "properties": {
    "gn:admin1_code":"2",
    "gn:admin2_code":"91.0",
    "gn:admin3_code":"9180.0",
    "gn:admin4_code":"9180112.0",
    "gn:asciiname":"Sonnen",
    "gn:country_code":"DE",
    "gn:dem":946,
    "gn:feature_class":"P",
    "gn:feature_code":"PPL",
    "gn:name":"Sonnen",
    "gn:population":0,
    "gn:timezone":"Europe/Berlin",
    "iso:country":"DE",
    "wof:name":"Sonnen",
    "wof:placetype":"neighbourhood"
},
  "geometry": {"coordinates":[11.04322,47.65911],"type":"Point"}
}