{
  "type": "Feature",
  "properties": {
    "gn:country":"DE",
    "gn:fcode":"PPL",
    "gn:population":0,
    "iso:country":"DE",
    "name:und_x_variant":[
        "K\u00f6venich"
    ],
    "qs_pg:aaroncc":"DE",
    "qs_pg:gn_country":"DE",
    "qs_pg:gn_fcode":"PPL",
    "qs_pg:gn_pop":0,
    "qs_pg:name":"K\u00f6venig",
    "qs_pg:name_adm0":"Deutschland",
    "qs_pg:name_adm1":"Rheinland-Pfalz",
    "qs_pg:photos_9k":1,
    "qs_pg:photos_9r":1,
    "qs_pg:photos_all":6,
    "qs_pg:photos_sr":0,
    "qs_pg:pop_sr":0,
    "qs_pg:qs_pg_placetype":"locality",
    "qs_pg:qs_pg_placetype_gp":"Town",
    "qs_pg:woe_adm0":23424829,
    "woe:adm0_id":23424829,
    "woe:name_adm0":"Deutschland",
    "woe:name_adm1":"Rheinland-Pfalz",
    "woe:placetype":"Town",
    "wof:name":"K\u00f6venig",
    "wof:placetype":"neighbourhood"
},
  "geometry": {"coordinates":[7.11716,49.98129],"type":"Point"}
}