{
  "type": "Feature",
  "properties": {
    "gn:admin1_code":"2",
    "gn:admin2_code":"96.0",
    "gn:admin3_code":"9671.0",
    "gn:admin4_code":"9671152.0",
    "gn:asciiname":"Hofstadten",
    "gn:country_code":"DE",
    "gn:dem":248,
    "gn:feature_class":"P",
    "gn:feature_code":"PPL",
    "gn:name":"Hofst\u00e4dten",
    "gn:population":0,
    "gn:timezone":"Europe/Berlin",
    "iso:country":"DE",
    "wof:name":"Hofstadten",
    "wof:placetype":"neighbourhood"
},
  "geometry": {"coordinates":[9.21694,50.10822],"type":"Point"}
}