{
  "type": "Feature",
  "properties": {
    "gn:admin1_code":"2",
    "gn:admin2_code":"91.0",
    "gn:admin3_code":"9187.0",
    "gn:admin4_code":"9187167.0",
    "gn:asciiname":"Patting",
    "gn:country_code":"DE",
    "gn:dem":596,
    "gn:feature_class":"P",
    "gn:feature_code":"PPL",
    "gn:name":"Patting",
    "gn:population":0,
    "gn:timezone":"Europe/Berlin",
    "iso:country":"DE",
    "wof:name":"Patting",
    "wof:placetype":"neighbourhood"
},
  "geometry": {"coordinates":[12.23628,47.81903],"type":"Point"}
}