{
  "type": "Feature",
  "properties": {
    "gn:admin1_code":"6",
    "gn:admin2_code":"0.0",
    "gn:admin3_code":"3351.0",
    "gn:admin4_code":"3351025.0",
    "gn:asciiname":"Endeholz",
    "gn:country_code":"DE",
    "gn:dem":79,
    "gn:feature_class":"P",
    "gn:feature_code":"PPL",
    "gn:name":"Endeholz",
    "gn:population":0,
    "gn:timezone":"Europe/Berlin",
    "iso:country":"DE",
    "wof:name":"Endeholz",
    "wof:placetype":"neighbourhood"
},
  "geometry": {"coordinates":[10.31503,52.7182],"type":"Point"}
}