{
  "type": "Feature",
  "properties": {
    "gn:admin1_code":"11",
    "gn:admin2_code":"0.0",
    "gn:admin3_code":"12073.0",
    "gn:admin4_code":"12073097.0",
    "gn:asciiname":"Petershagen",
    "gn:country_code":"DE",
    "gn:dem":22,
    "gn:feature_class":"P",
    "gn:feature_code":"PPL",
    "gn:name":"Petershagen",
    "gn:population":0,
    "gn:timezone":"Europe/Berlin",
    "iso:country":"DE",
    "wof:name":"Petershagen",
    "wof:placetype":"neighbourhood"
},
  "geometry": {"coordinates":[14.25244,53.24462],"type":"Point"}
}