{
  "type": "Feature",
  "properties": {
    "gn:admin1_code":"11",
    "gn:admin2_code":"0.0",
    "gn:admin3_code":"12073.0",
    "gn:admin4_code":"12073097.0",
    "gn:asciiname":"Petershagen",
    "gn:country_code":"DE",
    "gn:dem":22,
    "gn:feature_class":"P",
    "gn:feature_code":"PPL",
    "gn:name":"Petershagen",
    "gn:population":0,
    "gn:timezone":"Europe/Berlin",
    "iso:country":"DE",
    "name:ara_x_preferred":[
        "\u0628\u062a\u0631\u0633\u0647\u0627\u063a\u0646"
    ],
    "name:azb_x_preferred":[
        "\u067e\u062a\u0631\u0633\u0647\u0627\u0642\u0646"
    ],
    "name:deu_x_preferred":[
        "Petershagen"
    ],
    "name:epo_x_preferred":[
        "Petershagen"
    ],
    "name:eus_x_preferred":[
        "Petershagen"
    ],
    "name:fas_x_preferred":[
        "\u067e\u062a\u0631\u0633\u0647\u0627\u06af\u0646"
    ],
    "name:fra_x_preferred":[
        "Petershagen"
    ],
    "name:heb_x_preferred":[
        "\u05e4\u05d8\u05e8\u05e1\u05d4\u05d0\u05d2\u05df"
    ],
    "name:hun_x_preferred":[
        "Petershagen"
    ],
    "name:ita_x_preferred":[
        "Petershagen"
    ],
    "name:jpn_x_preferred":[
        "\u30da\u30fc\u30bf\u30fc\u30b9\u30cf\u30fc\u30b2\u30f3"
    ],
    "name:kaz_x_preferred":[
        "\u041f\u0435\u0442\u0435\u0440\u0441\u0445\u0430\u0433\u0435\u043d"
    ],
    "name:kir_x_preferred":[
        "\u041f\u0435\u0442\u0435\u0440\u0441\u0445\u0430\u0433\u0435\u043d"
    ],
    "name:msa_x_preferred":[
        "Petershagen"
    ],
    "name:nld_x_preferred":[
        "Petershagen"
    ],
    "name:pol_x_preferred":[
        "Petershagen"
    ],
    "name:por_x_preferred":[
        "Petershagen"
    ],
    "name:ron_x_preferred":[
        "Petershagen"
    ],
    "name:rus_x_preferred":[
        "\u041f\u0435\u0442\u0435\u0440\u0441\u0445\u0430\u0433\u0435\u043d"
    ],
    "name:spa_x_preferred":[
        "Petershagen"
    ],
    "name:srp_x_preferred":[
        "\u041f\u0435\u0442\u0435\u0440\u0441\u0445\u0430\u0433\u0435\u043d"
    ],
    "name:swe_x_preferred":[
        "Petershagen"
    ],
    "name:tur_x_preferred":[
        "Petershagen"
    ],
    "name:ukr_x_preferred":[
        "\u041f\u0435\u0442\u0435\u0440\u0441\u0433\u0430\u0433\u0435\u043d"
    ],
    "name:uzb_x_preferred":[
        "Petershagen"
    ],
    "name:vie_x_preferred":[
        "Petershagen"
    ],
    "name:vol_x_preferred":[
        "Petershagen"
    ],
    "name:war_x_preferred":[
        "Petershagen"
    ],
    "name:zho_x_preferred":[
        "\u5f7c\u5f97\u65af\u54c8\u6839"
    ],
    "wof:name":"Petershagen",
    "wof:placetype":"neighbourhood"
},
  "geometry": {"coordinates":[14.25244,53.24462],"type":"Point"}
}