{
  "type": "Feature",
  "properties": {
    "gn:admin1_code":"12.0",
    "gn:admin2_code":"00",
    "gn:admin3_code":"13074.0",
    "gn:admin4_code":"13074070.0",
    "gn:asciiname":"Woldhof",
    "gn:country_code":"DE",
    "gn:dem":53,
    "gn:feature_class":"P",
    "gn:feature_code":"PPL",
    "gn:name":"Woldhof",
    "gn:population":0,
    "gn:timezone":"Europe/Berlin",
    "iso:country":"DE",
    "wof:name":"Woldhof",
    "wof:placetype":"neighbourhood"
},
  "geometry": {"coordinates":[11.01554,53.63006],"type":"Point"}
}