{
  "type": "Feature",
  "properties": {
    "gn:admin1_code":"8",
    "gn:admin2_code":"0.0",
    "gn:admin3_code":"7313.0",
    "gn:admin4_code":"7313000.0",
    "gn:asciiname":"Moerlheim",
    "gn:country_code":"DE",
    "gn:dem":136,
    "gn:feature_class":"P",
    "gn:feature_code":"PPL",
    "gn:name":"M\u00f6rlheim",
    "gn:population":0,
    "gn:timezone":"Europe/Berlin",
    "iso:country":"DE",
    "wof:name":"Moerlheim",
    "wof:placetype":"neighbourhood"
},
  "geometry": {"coordinates":[8.16438,49.18993],"type":"Point"}
}