{
  "type": "Feature",
  "properties": {
    "iso:country":"DE",
    "name:ceb_x_preferred":[
        "Zentrum"
    ],
    "name:deu_x_preferred":[
        "Zentrum"
    ],
    "name:nld_x_preferred":[
        "Zentrum"
    ],
    "name:pol_x_preferred":[
        "Zentrum"
    ],
    "qs_pg:aaroncc":"DE",
    "qs_pg:name":"Zentrum",
    "qs_pg:name_adm0":"Deutschland",
    "qs_pg:name_adm1":"Nordrhein-Westfalen",
    "qs_pg:photos":79,
    "qs_pg:photos_1k":16,
    "qs_pg:photos_9k":1,
    "qs_pg:photos_9r":3,
    "qs_pg:photos_all":79,
    "qs_pg:photos_sr":3,
    "qs_pg:pop_sr":0,
    "qs_pg:qs_pg_placetype":"locality",
    "qs_pg:qs_pg_placetype_gp":"Town",
    "qs_pg:woe_adm0":23424829,
    "woe:adm0_id":23424829,
    "woe:name_adm0":"Deutschland",
    "woe:name_adm1":"Nordrhein-Westfalen",
    "woe:placetype":"Town",
    "wof:name":"Zentrum",
    "wof:placetype":"neighbourhood"
},
  "geometry": {"coordinates":[8.752039,51.718139],"type":"Point"}
}