{
  "type": "Feature",
  "properties": {
    "gn:admin1_code":"2.0",
    "gn:admin2_code":"92.0",
    "gn:admin3_code":"9279.0",
    "gn:admin4_code":"9279137.0",
    "gn:asciiname":"Altenbuch",
    "gn:country_code":"DE",
    "gn:dem":332,
    "gn:feature_class":"P",
    "gn:feature_code":"PPL",
    "gn:name":"Altenbuch",
    "gn:population":0,
    "gn:timezone":"Europe/Berlin",
    "iso:country":"DE",
    "wof:name":"Altenbuch",
    "wof:placetype":"neighbourhood"
},
  "geometry": {"coordinates":[12.75125,48.78497],"type":"Point"}
}