{
  "type": "Feature",
  "properties": {
    "gn:admin1_code":"2.0",
    "gn:admin2_code":"92.0",
    "gn:admin3_code":"9279.0",
    "gn:admin4_code":"9279137.0",
    "gn:asciiname":"Altenbuch",
    "gn:country_code":"DE",
    "gn:dem":332,
    "gn:feature_class":"P",
    "gn:feature_code":"PPL",
    "gn:name":"Altenbuch",
    "gn:population":0,
    "gn:timezone":"Europe/Berlin",
    "iso:country":"DE",
    "name:bar_x_preferred":[
        "Altenbuch"
    ],
    "name:ceb_x_preferred":[
        "Altenbuch"
    ],
    "name:dan_x_preferred":[
        "Altenbuch"
    ],
    "name:deu_x_preferred":[
        "Altenbuch"
    ],
    "name:epo_x_preferred":[
        "Altenbuch"
    ],
    "name:eus_x_preferred":[
        "Altenbuch"
    ],
    "name:fas_x_preferred":[
        "\u0627\u062a\u0646\u0628\u0627\u062e"
    ],
    "name:fra_x_preferred":[
        "Altenbuch"
    ],
    "name:hun_x_preferred":[
        "Altenbuch"
    ],
    "name:hye_x_preferred":[
        "\u0531\u056c\u0569\u0565\u0576\u0562\u0578\u0582\u056d"
    ],
    "name:ind_x_preferred":[
        "Altenbuch"
    ],
    "name:ita_x_preferred":[
        "Altenbuch"
    ],
    "name:jpn_x_preferred":[
        "\u30a2\u30eb\u30c6\u30f3\u30d6\u30fc\u30d5"
    ],
    "name:lat_x_preferred":[
        "Altenbuch"
    ],
    "name:lmo_x_preferred":[
        "Altenbuch"
    ],
    "name:msa_x_preferred":[
        "Altenbuch"
    ],
    "name:nld_x_preferred":[
        "Altenbuch"
    ],
    "name:pol_x_preferred":[
        "Altenbuch"
    ],
    "name:por_x_preferred":[
        "Altenbuch"
    ],
    "name:ron_x_preferred":[
        "Altenbuch"
    ],
    "name:rus_x_preferred":[
        "\u0410\u043b\u044c\u0442\u0435\u043d\u0431\u0443\u0445"
    ],
    "name:spa_x_preferred":[
        "Altenbuch"
    ],
    "name:srp_x_preferred":[
        "\u0410\u043b\u0442\u0435\u043d\u0431\u0443\u0445"
    ],
    "name:ukr_x_preferred":[
        "\u0410\u043b\u044c\u0442\u0435\u043d\u0431\u0443\u0445"
    ],
    "name:uzb_x_preferred":[
        "Altenbuch"
    ],
    "name:vie_x_preferred":[
        "Altenbuch"
    ],
    "name:vol_x_preferred":[
        "Altenbuch"
    ],
    "name:war_x_preferred":[
        "Altenbuch"
    ],
    "name:zho_x_preferred":[
        "\u963f\u5c14\u6ed5\u5e03\u8d6b"
    ],
    "wof:name":"Altenbuch",
    "wof:placetype":"neighbourhood"
},
  "geometry": {"coordinates":[12.75125,48.78497],"type":"Point"}
}