{
  "type": "Feature",
  "properties": {
    "gn:admin1_code":"2",
    "gn:admin2_code":"91.0",
    "gn:admin3_code":"9189.0",
    "gn:admin4_code":"9189143.0",
    "gn:asciiname":"Burgham",
    "gn:country_code":"DE",
    "gn:dem":535,
    "gn:feature_class":"P",
    "gn:feature_code":"PPL",
    "gn:name":"Burgham",
    "gn:population":0,
    "gn:timezone":"Europe/Berlin",
    "iso:country":"DE",
    "wof:name":"Burgham",
    "wof:placetype":"neighbourhood"
},
  "geometry": {"coordinates":[12.4585,47.9394],"type":"Point"}
}