{
  "type": "Feature",
  "properties": {
    "gn:admin1_code":"1",
    "gn:admin2_code":"83.0",
    "gn:admin3_code":"8317.0",
    "gn:admin4_code":"8317098.0",
    "gn:asciiname":"Lierbach",
    "gn:country_code":"DE",
    "gn:dem":454,
    "gn:feature_class":"P",
    "gn:feature_code":"PPL",
    "gn:name":"Lierbach",
    "gn:population":0,
    "gn:timezone":"Europe/Berlin",
    "iso:country":"DE",
    "name:ceb_x_preferred":[
        "Lierbach"
    ],
    "name:chv_x_preferred":[
        "\u041b\u0438\u0440\u0431\u0430\u0445"
    ],
    "name:deu_x_preferred":[
        "Lierbach"
    ],
    "wof:name":"Lierbach",
    "wof:placetype":"neighbourhood"
},
  "geometry": {"coordinates":[8.18279,48.51543],"type":"Point"}
}