{
  "type": "Feature",
  "properties": {
    "gn:admin1_code":"2",
    "gn:admin2_code":"93.0",
    "gn:admin3_code":"9376.0",
    "gn:admin4_code":"9376147.0",
    "gn:asciiname":"Stetten",
    "gn:country_code":"DE",
    "gn:dem":441,
    "gn:feature_class":"P",
    "gn:feature_code":"PPL",
    "gn:name":"Stetten",
    "gn:population":0,
    "gn:timezone":"Europe/Berlin",
    "iso:country":"DE",
    "name:als_x_preferred":[
        "Stetten"
    ],
    "name:ceb_x_preferred":[
        "Stetten"
    ],
    "name:deu_x_preferred":[
        "Stetten"
    ],
    "name:epo_x_preferred":[
        "Stetten"
    ],
    "name:fra_x_preferred":[
        "Stetten"
    ],
    "name:hye_x_preferred":[
        "\u0547\u057f\u0565\u0569\u0565\u0576"
    ],
    "name:ita_x_preferred":[
        "Stetten"
    ],
    "name:lmo_x_preferred":[
        "Stetten"
    ],
    "name:nld_x_preferred":[
        "Stetten"
    ],
    "name:pms_x_preferred":[
        "Stetten"
    ],
    "name:pol_x_preferred":[
        "Stetten"
    ],
    "name:por_x_preferred":[
        "Stetten"
    ],
    "name:rus_x_preferred":[
        "\u0428\u0442\u0435\u0442\u0442\u0435\u043d"
    ],
    "name:spa_x_preferred":[
        "Stetten"
    ],
    "name:srp_x_preferred":[
        "\u0428\u0442\u0435\u0442\u0435\u043d"
    ],
    "name:swe_x_preferred":[
        "Stetten"
    ],
    "name:vol_x_preferred":[
        "Stetten"
    ],
    "wof:name":"Stetten",
    "wof:placetype":"neighbourhood"
},
  "geometry": {"coordinates":[12.42781,49.32363],"type":"Point"}
}