{
  "type": "Feature",
  "properties": {
    "gn:admin1_code":"13",
    "gn:admin2_code":"0.0",
    "gn:admin3_code":"14730.0",
    "gn:admin4_code":"14730050.0",
    "gn:asciiname":"Moehla",
    "gn:country_code":"DE",
    "gn:dem":112,
    "gn:feature_class":"P",
    "gn:feature_code":"PPL",
    "gn:name":"M\u00f6hla",
    "gn:population":0,
    "gn:timezone":"Europe/Berlin",
    "iso:country":"DE",
    "wof:name":"Moehla",
    "wof:placetype":"neighbourhood"
},
  "geometry": {"coordinates":[13.10247,51.37192],"type":"Point"}
}