{
  "type": "Feature",
  "properties": {
    "gn:admin1_code":"7.0",
    "gn:admin2_code":"053",
    "gn:admin3_code":"5374.0",
    "gn:admin4_code":"5374044.0",
    "gn:asciiname":"Ziegenhardt",
    "gn:country_code":"DE",
    "gn:dem":224,
    "gn:feature_class":"P",
    "gn:feature_code":"PPLL",
    "gn:name":"Ziegenhardt",
    "gn:population":0,
    "gn:timezone":"Europe/Berlin",
    "iso:country":"DE",
    "wof:name":"Ziegenhardt",
    "wof:placetype":"neighbourhood"
},
  "geometry": {"coordinates":[7.5594,50.85976],"type":"Point"}
}