{
  "type": "Feature",
  "properties": {
    "gn:admin1_code":"8",
    "gn:admin2_code":"0.0",
    "gn:admin3_code":"7336.0",
    "gn:admin4_code":"7336089.0",
    "gn:asciiname":"Rutsweiler an der Glan",
    "gn:country_code":"DE",
    "gn:dem":213,
    "gn:feature_class":"P",
    "gn:feature_code":"PPL",
    "gn:name":"Rutsweiler an der Glan",
    "gn:population":0,
    "gn:timezone":"Europe/Berlin",
    "iso:country":"DE",
    "wof:name":"Rutsweiler an der Glan",
    "wof:placetype":"neighbourhood"
},
  "geometry": {"coordinates":[7.45555,49.52817],"type":"Point"}
}