{
  "type": "Feature",
  "properties": {
    "gn:admin1_code":"7",
    "gn:admin2_code":"51.0",
    "gn:admin3_code":"5162.0",
    "gn:admin4_code":"5162012.0",
    "gn:asciiname":"Damm",
    "gn:country_code":"DE",
    "gn:dem":54,
    "gn:feature_class":"P",
    "gn:feature_code":"PPL",
    "gn:name":"Damm",
    "gn:population":0,
    "gn:timezone":"Europe/Berlin",
    "iso:country":"DE",
    "name:ceb_x_preferred":[
        "Damm"
    ],
    "name:deu_x_preferred":[
        "Damm"
    ],
    "name:epo_x_preferred":[
        "Damm"
    ],
    "name:fra_x_preferred":[
        "Damm"
    ],
    "name:ita_x_preferred":[
        "Damm"
    ],
    "name:nds_x_preferred":[
        "Damm"
    ],
    "name:nld_x_preferred":[
        "Damm"
    ],
    "name:pol_x_preferred":[
        "Damm"
    ],
    "name:rus_x_preferred":[
        "\u0414\u0430\u043c\u043c"
    ],
    "name:swe_x_preferred":[
        "Damm"
    ],
    "name:vol_x_preferred":[
        "Damm"
    ],
    "wof:name":"Damm",
    "wof:placetype":"neighbourhood"
},
  "geometry": {"coordinates":[6.5748,51.14533],"type":"Point"}
}