{
  "type": "Feature",
  "properties": {
    "gn:admin1_code":"2",
    "gn:admin2_code":"93.0",
    "gn:admin3_code":"9375.0",
    "gn:admin4_code":"9375148.0",
    "gn:asciiname":"Bugerleithen",
    "gn:country_code":"DE",
    "gn:dem":554,
    "gn:feature_class":"P",
    "gn:feature_code":"PPL",
    "gn:name":"B\u00fcgerleithen",
    "gn:population":0,
    "gn:timezone":"Europe/Berlin",
    "iso:country":"DE",
    "name:und_x_variant":[
        "B\u00fcrgerlleiten",
        "B\u00fcgerleithen"
    ],
    "wof:name":"Bugerleithen",
    "wof:placetype":"neighbourhood"
},
  "geometry": {"coordinates":[11.76555,49.01765],"type":"Point"}
}