{
  "type": "Feature",
  "properties": {
    "gn:admin1_code":"2.0",
    "gn:admin2_code":"094",
    "gn:admin3_code":"9471.0",
    "gn:admin4_code":"9471189.0",
    "gn:asciiname":"Wolkendorf",
    "gn:country_code":"DE",
    "gn:dem":477,
    "gn:feature_class":"P",
    "gn:feature_code":"PPL",
    "gn:name":"W\u00f6lkendorf",
    "gn:population":0,
    "gn:timezone":"Europe/Berlin",
    "iso:country":"DE",
    "wof:name":"Wolkendorf",
    "wof:placetype":"neighbourhood"
},
  "geometry": {"coordinates":[11.17872,50.00443],"type":"Point"}
}