{
  "type": "Feature",
  "properties": {
    "gn:admin1_code":"7",
    "gn:admin2_code":"55.0",
    "gn:admin3_code":"5554.0",
    "gn:admin4_code":"5554068.0",
    "gn:asciiname":"Gaxel",
    "gn:country_code":"DE",
    "gn:dem":39,
    "gn:feature_class":"P",
    "gn:feature_code":"PPL",
    "gn:name":"Gaxel",
    "gn:population":0,
    "gn:timezone":"Europe/Berlin",
    "iso:country":"DE",
    "wof:name":"Gaxel",
    "wof:placetype":"neighbourhood"
},
  "geometry": {"coordinates":[6.8138,52.03283],"type":"Point"}
}