{
  "type": "Feature",
  "properties": {
    "gn:admin1_code":"15",
    "gn:admin2_code":"0.0",
    "gn:admin3_code":"16075.0",
    "gn:admin4_code":"16075133.0",
    "gn:asciiname":"Ossla",
    "gn:country_code":"DE",
    "gn:dem":637,
    "gn:feature_class":"P",
    "gn:feature_code":"PPL",
    "gn:name":"O\u00dfla",
    "gn:population":0,
    "gn:timezone":"Europe/Berlin",
    "iso:country":"DE",
    "wof:name":"Ossla",
    "wof:placetype":"neighbourhood"
},
  "geometry": {"coordinates":[11.50703,50.46393],"type":"Point"}
}