{
  "type": "Feature",
  "properties": {
    "gn:admin1_code":"13",
    "gn:admin2_code":"0.0",
    "gn:admin3_code":"14627.0",
    "gn:admin4_code":"14627100.0",
    "gn:asciiname":"Lampersdorf",
    "gn:country_code":"DE",
    "gn:dem":245,
    "gn:feature_class":"P",
    "gn:feature_code":"PPL",
    "gn:name":"Lampersdorf",
    "gn:population":0,
    "gn:timezone":"Europe/Berlin",
    "iso:country":"DE",
    "wof:name":"Lampersdorf",
    "wof:placetype":"neighbourhood"
},
  "geometry": {"coordinates":[13.48548,51.07731],"type":"Point"}
}