{
  "type": "Feature",
  "properties": {
    "gn:admin1_code":"2",
    "gn:admin2_code":"91.0",
    "gn:admin3_code":"9184.0",
    "gn:admin4_code":"9184149.0",
    "gn:asciiname":"Lohhof",
    "gn:country_code":"DE",
    "gn:dem":473,
    "gn:feature_class":"P",
    "gn:feature_code":"PPL",
    "gn:name":"Lohhof",
    "gn:population":0,
    "gn:timezone":"Europe/Berlin",
    "iso:country":"DE",
    "wof:name":"Lohhof",
    "wof:placetype":"neighbourhood"
},
  "geometry": {"coordinates":[11.5879,48.28311],"type":"Point"}
}