{
  "type": "Feature",
  "properties": {
    "iso:country":"DE",
    "name:chv_x_preferred":[
        "\u0411\u043b\u043e\u043c\u0431\u0430\u0445"
    ],
    "name:deu_x_preferred":[
        "Blombach"
    ],
    "wof:name":"Blombach",
    "wof:placetype":"neighbourhood"
},
  "geometry": {"coordinates":[7.22687532922258,51.23456653385108],"type":"Point"}
}