{
  "type": "Feature",
  "properties": {
    "iso:country":"DE",
    "wof:name":"Blombach",
    "wof:placetype":"neighbourhood"
},
  "geometry": {"coordinates":[7.22687532922258,51.23456653385108],"type":"Point"}
}