{
  "type": "Feature",
  "properties": {
    "gn:admin1_code":"6",
    "gn:admin2_code":"0.0",
    "gn:admin3_code":"3459.0",
    "gn:admin4_code":"3459013.0",
    "gn:asciiname":"Nierhuesen",
    "gn:country_code":"DE",
    "gn:dem":42,
    "gn:feature_class":"P",
    "gn:feature_code":"PPL",
    "gn:name":"Nierh\u00fcsen",
    "gn:population":0,
    "gn:timezone":"Europe/Berlin",
    "iso:country":"DE",
    "wof:name":"Nierhuesen",
    "wof:placetype":"neighbourhood"
},
  "geometry": {"coordinates":[8.29051,52.44441],"type":"Point"}
}