{
  "type": "Feature",
  "properties": {
    "iso:country":"DE",
    "wof:name":"Poppelsdorf",
    "wof:placetype":"neighbourhood"
},
  "geometry": {"coordinates":[7.08822411906011,50.7190942352761],"type":"Point"}
}