{
  "type": "Feature",
  "properties": {
    "gn:gn_country":"DE",
    "gn:gn_fcode":"PPLA4",
    "gn:gn_pop":181,
    "gn:population":181,
    "iso:country":"DE",
    "name:baq_x_preferred":[
        "Holt"
    ],
    "name:cat_x_preferred":[
        "Holt"
    ],
    "name:dan_x_preferred":[
        "Holt"
    ],
    "name:dut_x_preferred":[
        "Holt"
    ],
    "name:eng_x_preferred":[
        "Holt"
    ],
    "name:epo_x_preferred":[
        "Holt"
    ],
    "name:fre_x_preferred":[
        "Holt"
    ],
    "name:ger_x_preferred":[
        "Holt"
    ],
    "name:hun_x_preferred":[
        "Holt"
    ],
    "name:ita_x_preferred":[
        "Holt"
    ],
    "name:kaz_x_preferred":[
        "\u0425\u043e\u043b\u044c\u0442"
    ],
    "name:kir_x_preferred":[
        "\u0425\u043e\u043b\u044c\u0442"
    ],
    "name:mac_x_preferred":[
        "\u0425\u043e\u043b\u0442"
    ],
    "name:may_x_preferred":[
        "Holt"
    ],
    "name:per_x_preferred":[
        "\u0647\u0648\u0644\u062a"
    ],
    "name:pol_x_preferred":[
        "Holt"
    ],
    "name:por_x_preferred":[
        "Holt"
    ],
    "name:rum_x_preferred":[
        "Holt"
    ],
    "name:rus_x_preferred":[
        "\u0425\u043e\u043b\u044c\u0442"
    ],
    "name:spa_x_preferred":[
        "Holt"
    ],
    "name:srp_x_preferred":[
        "\u0425\u043e\u043b\u0442"
    ],
    "name:tur_x_preferred":[
        "Holt"
    ],
    "name:ukr_x_preferred":[
        "\u0413\u043e\u043b\u044c\u0442"
    ],
    "name:uzb_x_preferred":[
        "Holt"
    ],
    "name:vie_x_preferred":[
        "Holt"
    ],
    "name:vol_x_preferred":[
        "Holt"
    ],
    "name:war_x_preferred":[
        "Holt"
    ],
    "qs_pg:aaroncc":"DE",
    "qs_pg:gn_country":"DE",
    "qs_pg:gn_fcode":"PPLA4",
    "qs_pg:gn_pop":181,
    "qs_pg:name":"Holt",
    "qs_pg:photos_9r":0,
    "qs_pg:photos_sr":0,
    "qs_pg:pop_sr":1,
    "qs_pg:qs_pg_placetype":"locality",
    "wof:name":"Holt",
    "wof:placetype":"locality",
    "wof:population":181
},
  "geometry": {"coordinates":[9.15,54.81667],"type":"Point"}
}