{
  "type": "Feature",
  "properties": {
    "iso:country":"DE",
    "name:bel_x_preferred":[
        "\u0412\u0430\u0440\u043a\u0430"
    ],
    "name:ceb_x_preferred":[
        "Warka"
    ],
    "name:deu_x_preferred":[
        "Fahrland"
    ],
    "name:deu_x_variant":[
        "Warka"
    ],
    "name:epo_x_preferred":[
        "Warka"
    ],
    "name:est_x_preferred":[
        "Warka"
    ],
    "name:fra_x_preferred":[
        "Warka"
    ],
    "name:heb_x_preferred":[
        "\u05d5\u05d5\u05e8\u05e7\u05d0"
    ],
    "name:hrv_x_preferred":[
        "Warka"
    ],
    "name:hun_x_preferred":[
        "Warka"
    ],
    "name:ind_x_preferred":[
        "Warka"
    ],
    "name:ita_x_preferred":[
        "Warka"
    ],
    "name:jav_x_preferred":[
        "Warka"
    ],
    "name:lav_x_preferred":[
        "Varka"
    ],
    "name:msa_x_preferred":[
        "Warka"
    ],
    "name:nld_x_preferred":[
        "Warka"
    ],
    "name:pol_x_preferred":[
        "Warka"
    ],
    "name:por_x_preferred":[
        "Warka"
    ],
    "name:ron_x_preferred":[
        "Warka"
    ],
    "name:rus_x_preferred":[
        "\u0412\u0430\u0440\u043a\u0430"
    ],
    "name:slk_x_preferred":[
        "Warka"
    ],
    "name:spa_x_preferred":[
        "Warka"
    ],
    "name:srp_x_preferred":[
        "\u0412\u0430\u0440\u043a\u0430"
    ],
    "name:ukr_x_preferred":[
        "\u0412\u0430\u0440\u043a\u0430"
    ],
    "name:unk_x_variant":[
        "Fahrland"
    ],
    "name:vie_x_preferred":[
        "Warka"
    ],
    "name:yid_x_preferred":[
        "\u05d5\u05d5\u05d0\u05e8\u05e7\u05e2"
    ],
    "name:zho_x_preferred":[
        "\u74e6\u723e\u5361"
    ],
    "qs:gn_adm0_cc":"DE",
    "qs:gn_fcode":"PPL",
    "qs:gn_local":2852458,
    "qs:gn_namadm1":"11",
    "qs:gn_name":"Fahrland",
    "qs:local_max":6891,
    "qs:local_sum":26199,
    "qs:localhoods":32,
    "qs:name":"Fahrland",
    "qs:name_adm0":"Deutschland",
    "qs:name_adm1":"Bundesland Brandenburg",
    "qs:name_adm2":"Stadtkreis Potsdam",
    "qs:name_lau":"Gemeinde Potsdam",
    "qs:name_local":"Potsdam",
    "qs:photo_max":89,
    "qs:photo_sum":146,
    "qs:placetype":"Suburb",
    "qs:quad_count":17,
    "qs:woe_adm0":23424829,
    "qs:woe_adm1":2345491,
    "qs:woe_adm2":12597070,
    "qs:woe_lau":12632873,
    "qs:woe_local":685783,
    "qs:woe_ver":"7.10.0",
    "wof:lang":[
        "ger"
    ],
    "wof:name":"Fahrland",
    "wof:placetype":"neighbourhood"
},
  "geometry": {"coordinates":[13.013327,52.467797],"type":"Point"}
}