{
  "type": "Feature",
  "properties": {
    "gn:admin1_code":"15",
    "gn:admin2_code":"0.0",
    "gn:admin3_code":"16077.0",
    "gn:admin4_code":"16077044.0",
    "gn:asciiname":"Dobraschuetz",
    "gn:country_code":"DE",
    "gn:dem":243,
    "gn:feature_class":"P",
    "gn:feature_code":"PPL",
    "gn:name":"Dobrasch\u00fctz",
    "gn:population":0,
    "gn:timezone":"Europe/Berlin",
    "iso:country":"DE",
    "wof:name":"Dobraschuetz",
    "wof:placetype":"neighbourhood"
},
  "geometry": {"coordinates":[12.28426,50.97157],"type":"Point"}
}