{
  "type": "Feature",
  "properties": {
    "gn:admin1_code":"2",
    "gn:admin2_code":"96.0",
    "gn:admin3_code":"9673.0",
    "gn:admin4_code":"9673172.0",
    "gn:asciiname":"Serrfeld",
    "gn:country_code":"DE",
    "gn:dem":321,
    "gn:feature_class":"P",
    "gn:feature_code":"PPL",
    "gn:name":"Serrfeld",
    "gn:population":0,
    "gn:timezone":"Europe/Berlin",
    "iso:country":"DE",
    "wof:name":"Serrfeld",
    "wof:placetype":"neighbourhood"
},
  "geometry": {"coordinates":[10.57009,50.2136],"type":"Point"}
}