{
  "type": "Feature",
  "properties": {
    "gn:admin1_code":"1",
    "gn:admin2_code":"84.0",
    "gn:admin3_code":"8436.0",
    "gn:admin4_code":"8436008.0",
    "gn:asciiname":"Fassmacher",
    "gn:country_code":"DE",
    "gn:dem":560,
    "gn:feature_class":"P",
    "gn:feature_code":"PPL",
    "gn:name":"Fa\u00dfmacher",
    "gn:population":0,
    "gn:timezone":"Europe/Berlin",
    "iso:country":"DE",
    "wof:name":"Fassmacher",
    "wof:placetype":"neighbourhood"
},
  "geometry": {"coordinates":[9.66595,47.91886],"type":"Point"}
}