{
  "type": "Feature",
  "properties": {
    "gn:admin1_code":"6.0",
    "gn:admin2_code":"00",
    "gn:admin3_code":"3462.0",
    "gn:admin4_code":"3462005.0",
    "gn:asciiname":"Wiesede",
    "gn:country_code":"DE",
    "gn:dem":7,
    "gn:feature_class":"P",
    "gn:feature_code":"PPL",
    "gn:name":"Wiesede",
    "gn:population":0,
    "gn:timezone":"Europe/Berlin",
    "iso:country":"DE",
    "wof:name":"Wiesede",
    "wof:placetype":"neighbourhood"
},
  "geometry": {"coordinates":[7.76843,53.44852],"type":"Point"}
}