{
  "type": "Feature",
  "properties": {
    "gn:admin1_code":"12",
    "gn:admin2_code":"0.0",
    "gn:admin3_code":"13072.0",
    "gn:admin4_code":"13072112.0",
    "gn:asciiname":"Klein Wardow",
    "gn:country_code":"DE",
    "gn:dem":34,
    "gn:feature_class":"P",
    "gn:feature_code":"PPL",
    "gn:name":"Klein Wardow",
    "gn:population":0,
    "gn:timezone":"Europe/Berlin",
    "iso:country":"DE",
    "wof:name":"Klein Wardow",
    "wof:placetype":"neighbourhood"
},
  "geometry": {"coordinates":[12.41667,53.93333000000001],"type":"Point"}
}