{
  "type": "Feature",
  "properties": {
    "iso:country":"DE",
    "wof:name":"Wichlinghausen",
    "wof:placetype":"neighbourhood"
},
  "geometry": {"coordinates":[7.21617509800866,51.28355267968367],"type":"Point"}
}