{
  "type": "Feature",
  "properties": {
    "gn:admin1_code":"8",
    "gn:admin2_code":"0.0",
    "gn:admin3_code":"7339.0",
    "gn:admin4_code":"7339030.0",
    "gn:asciiname":"Haxthaeuserhof",
    "gn:country_code":"DE",
    "gn:dem":238,
    "gn:feature_class":"P",
    "gn:feature_code":"PPL",
    "gn:name":"Haxth\u00e4userhof",
    "gn:population":0,
    "gn:timezone":"Europe/Berlin",
    "iso:country":"DE",
    "wof:name":"Haxthaeuserhof",
    "wof:placetype":"neighbourhood"
},
  "geometry": {"coordinates":[8.11005,49.96266],"type":"Point"}
}