{
  "type": "Feature",
  "properties": {
    "gn:admin1_code":"7",
    "gn:admin2_code":"51.0",
    "gn:admin3_code":"5112.0",
    "gn:admin4_code":"5112000.0",
    "gn:asciiname":"Vierbaum",
    "gn:country_code":"DE",
    "gn:dem":25,
    "gn:feature_class":"P",
    "gn:feature_code":"PPLL",
    "gn:name":"Vierbaum",
    "gn:population":0,
    "gn:timezone":"Europe/Berlin",
    "iso:country":"DE",
    "wof:name":"Vierbaum",
    "wof:placetype":"neighbourhood"
},
  "geometry": {"coordinates":[6.65231,51.5103],"type":"Point"}
}