{
  "type": "Feature",
  "properties": {
    "gn:admin1_code":"11.0",
    "gn:admin2_code":"00",
    "gn:admin3_code":"12062.0",
    "gn:admin4_code":"12062092.0",
    "gn:asciiname":"Werenzhain",
    "gn:country_code":"DE",
    "gn:dem":100,
    "gn:feature_class":"P",
    "gn:feature_code":"PPL",
    "gn:name":"Werenzhain",
    "gn:population":0,
    "gn:timezone":"Europe/Berlin",
    "iso:country":"DE",
    "wof:name":"Werenzhain",
    "wof:placetype":"neighbourhood"
},
  "geometry": {"coordinates":[13.53215,51.65464],"type":"Point"}
}