{
  "type": "Feature",
  "properties": {
    "gn:admin1_code":"2",
    "gn:admin2_code":"95.0",
    "gn:admin3_code":"9571.0",
    "gn:admin4_code":"9571200.0",
    "gn:asciiname":"Dickersbronn",
    "gn:country_code":"DE",
    "gn:dem":473,
    "gn:feature_class":"P",
    "gn:feature_code":"PPL",
    "gn:name":"Dickersbronn",
    "gn:population":0,
    "gn:timezone":"Europe/Berlin",
    "iso:country":"DE",
    "wof:name":"Dickersbronn",
    "wof:placetype":"neighbourhood"
},
  "geometry": {"coordinates":[10.3218,49.10385],"type":"Point"}
}