{
  "type": "Feature",
  "properties": {
    "gn:admin1_code":"12",
    "gn:admin2_code":"0.0",
    "gn:admin3_code":"13073.0",
    "gn:admin4_code":"13073070.0",
    "gn:asciiname":"Kasnevitz",
    "gn:country_code":"DE",
    "gn:dem":16,
    "gn:feature_class":"P",
    "gn:feature_code":"PPL",
    "gn:name":"Kasnevitz",
    "gn:population":0,
    "gn:timezone":"Europe/Berlin",
    "iso:country":"DE",
    "wof:name":"Kasnevitz",
    "wof:placetype":"neighbourhood"
},
  "geometry": {"coordinates":[13.42346,54.34161999999999],"type":"Point"}
}