{
  "type": "Feature",
  "properties": {
    "gn:admin1_code":"8",
    "gn:admin2_code":"0.0",
    "gn:admin3_code":"7140.0",
    "gn:admin4_code":"7140501.0",
    "gn:asciiname":"Holzfeld",
    "gn:country_code":"DE",
    "gn:dem":287,
    "gn:feature_class":"P",
    "gn:feature_code":"PPL",
    "gn:name":"Holzfeld",
    "gn:population":0,
    "gn:timezone":"Europe/Berlin",
    "iso:country":"DE",
    "wof:name":"Holzfeld",
    "wof:placetype":"neighbourhood"
},
  "geometry": {"coordinates":[7.64695,50.16315],"type":"Point"}
}