{
  "type": "Feature",
  "properties": {
    "gn:country":"DE",
    "gn:fcode":"PPL",
    "gn:population":0,
    "iso:country":"DE",
    "name:ceb_x_preferred":[
        "Wisch"
    ],
    "name:ces_x_preferred":[
        "Wisch"
    ],
    "name:dan_x_preferred":[
        "Wisch"
    ],
    "name:deu_x_preferred":[
        "Wisch"
    ],
    "name:epo_x_preferred":[
        "Wisch"
    ],
    "name:eus_x_preferred":[
        "Wisch"
    ],
    "name:fra_x_preferred":[
        "Wisch"
    ],
    "name:mkd_x_preferred":[
        "\u0412\u0438\u0448"
    ],
    "name:nds_x_preferred":[
        "Wisch"
    ],
    "name:nld_x_preferred":[
        "Wisch"
    ],
    "name:pol_x_preferred":[
        "Wisch"
    ],
    "name:rus_x_preferred":[
        "\u0412\u0438\u0448"
    ],
    "name:swe_x_preferred":[
        "Wisch"
    ],
    "name:tur_x_preferred":[
        "Wisch"
    ],
    "name:ukr_x_preferred":[
        "\u0412\u0456\u0448"
    ],
    "qs_pg:aaroncc":"DE",
    "qs_pg:gn_country":"DE",
    "qs_pg:gn_fcode":"PPL",
    "qs_pg:gn_pop":0,
    "qs_pg:name":"Wisch",
    "qs_pg:name_adm0":"Deutschland",
    "qs_pg:name_adm1":"Niedersachsen",
    "qs_pg:photos":101,
    "qs_pg:photos_1k":20,
    "qs_pg:photos_9k":1,
    "qs_pg:photos_9r":3,
    "qs_pg:photos_all":101,
    "qs_pg:photos_sr":3,
    "qs_pg:pop_sr":0,
    "qs_pg:qs_pg_placetype":"locality",
    "qs_pg:qs_pg_placetype_gp":"Town",
    "qs_pg:woe_adm0":23424829,
    "woe:adm0_id":23424829,
    "woe:name_adm0":"Deutschland",
    "woe:name_adm1":"Niedersachsen",
    "woe:placetype":"Town",
    "wof:name":"Wisch",
    "wof:placetype":"neighbourhood"
},
  "geometry": {"coordinates":[9.65327,53.56255],"type":"Point"}
}