{
  "type": "Feature",
  "properties": {
    "gn:country":"DE",
    "gn:fcode":"PPL",
    "gn:population":0,
    "iso:country":"DE",
    "name:ceb_x_preferred":[
        "Baven"
    ],
    "name:deu_x_preferred":[
        "Baven (Landkreis Celle)"
    ],
    "name:deu_x_variant":[
        "Hermannsburg-Baven",
        "Baven"
    ],
    "name:fas_x_preferred":[
        "\u0628\u0627\u0641\u0646"
    ],
    "name:nds_x_preferred":[
        "b\u0254\u02d0bm\u0329"
    ],
    "name:nds_x_variant":[
        "B\u01fbbm\u0325",
        "Baben"
    ],
    "qs_pg:aaroncc":"DE",
    "qs_pg:gn_country":"DE",
    "qs_pg:gn_fcode":"PPL",
    "qs_pg:gn_pop":0,
    "qs_pg:name":"Baven",
    "qs_pg:name_adm0":"Deutschland",
    "qs_pg:name_adm1":"Niedersachsen",
    "qs_pg:photos_9k":1,
    "qs_pg:photos_9r":1,
    "qs_pg:photos_all":3,
    "qs_pg:photos_sr":0,
    "qs_pg:pop_sr":0,
    "qs_pg:qs_pg_placetype":"locality",
    "qs_pg:qs_pg_placetype_gp":"Town",
    "qs_pg:woe_adm0":23424829,
    "woe:adm0_id":23424829,
    "woe:name_adm0":"Deutschland",
    "woe:name_adm1":"Niedersachsen",
    "woe:placetype":"Town",
    "wof:name":"Baven",
    "wof:placetype":"neighbourhood"
},
  "geometry": {"coordinates":[10.07747,52.84617],"type":"Point"}
}