{
  "type": "Feature",
  "properties": {
    "gn:admin1_code":"2",
    "gn:admin2_code":"92.0",
    "gn:admin3_code":"9275.0",
    "gn:admin4_code":"9275118.0",
    "gn:asciiname":"Jagerbild",
    "gn:country_code":"DE",
    "gn:dem":804,
    "gn:feature_class":"P",
    "gn:feature_code":"PPL",
    "gn:name":"J\u00e4gerbild",
    "gn:population":0,
    "gn:timezone":"Europe/Berlin",
    "iso:country":"DE",
    "wof:name":"Jagerbild",
    "wof:placetype":"neighbourhood"
},
  "geometry": {"coordinates":[13.75729,48.68631],"type":"Point"}
}