{
  "type": "Feature",
  "properties": {
    "gn:admin1_code":"15",
    "gn:admin2_code":"0.0",
    "gn:admin3_code":"16075.0",
    "gn:admin4_code":"16075125.0",
    "gn:asciiname":"Koselstein",
    "gn:country_code":"DE",
    "gn:dem":341,
    "gn:feature_class":"P",
    "gn:feature_code":"PPL",
    "gn:name":"Koselstein",
    "gn:population":0,
    "gn:timezone":"Europe/Berlin",
    "iso:country":"DE",
    "wof:name":"Koselstein",
    "wof:placetype":"neighbourhood"
},
  "geometry": {"coordinates":[11.55,50.61667],"type":"Point"}
}