{
  "type": "Feature",
  "properties": {
    "iso:country":"DE",
    "name:deu_x_preferred":[
        "Giesenkirchen"
    ],
    "name:ksh_x_preferred":[
        "Jissekerreke"
    ],
    "wof:name":"Giesenkirchen",
    "wof:placetype":"neighbourhood"
},
  "geometry": {"coordinates":[6.50135131620925,51.15944680496825],"type":"Point"}
}