{
  "type": "Feature",
  "properties": {
    "gn:admin1_code":"2",
    "gn:admin2_code":"94.0",
    "gn:admin3_code":"9472.0",
    "gn:admin4_code":"9472146.0",
    "gn:asciiname":"Culmberg",
    "gn:country_code":"DE",
    "gn:dem":519,
    "gn:feature_class":"P",
    "gn:feature_code":"PPL",
    "gn:name":"Culmberg",
    "gn:population":0,
    "gn:timezone":"Europe/Berlin",
    "iso:country":"DE",
    "wof:name":"Culmberg",
    "wof:placetype":"neighbourhood"
},
  "geometry": {"coordinates":[11.55268,49.88739],"type":"Point"}
}