{
  "type": "Feature",
  "properties": {
    "gn:admin1_code":"13",
    "gn:admin2_code":"0.0",
    "gn:admin3_code":"14625.0",
    "gn:admin4_code":"14625360.0",
    "gn:asciiname":"Weidlitz",
    "gn:country_code":"DE",
    "gn:dem":174,
    "gn:feature_class":"P",
    "gn:feature_code":"PPL",
    "gn:name":"Weidlitz",
    "gn:population":0,
    "gn:timezone":"Europe/Berlin",
    "iso:country":"DE",
    "name:hsb_x_preferred":[
        "Wuto\u0142\u010dicy"
    ],
    "wof:name":"Weidlitz",
    "wof:placetype":"neighbourhood"
},
  "geometry": {"coordinates":[14.30925,51.22774],"type":"Point"}
}