{
  "type": "Feature",
  "properties": {
    "gn:admin1_code":"7",
    "gn:admin2_code":"59.0",
    "gn:admin3_code":"5913.0",
    "gn:admin4_code":"5913000.0",
    "gn:asciiname":"Loh",
    "gn:country_code":"DE",
    "gn:dem":154,
    "gn:feature_class":"P",
    "gn:feature_code":"PPL",
    "gn:name":"Loh",
    "gn:population":0,
    "gn:timezone":"Europe/Berlin",
    "iso:country":"DE",
    "name:ceb_x_preferred":[
        "Loh"
    ],
    "name:deu_x_preferred":[
        "Loh"
    ],
    "name:nds_x_preferred":[
        "Loh"
    ],
    "name:swe_x_preferred":[
        "Loh"
    ],
    "wof:name":"Loh",
    "wof:placetype":"neighbourhood"
},
  "geometry": {"coordinates":[7.51667,51.46667],"type":"Point"}
}