{
  "type": "Feature",
  "properties": {
    "gn:admin1_code":"10",
    "gn:admin2_code":"0.0",
    "gn:admin3_code":"1059.0",
    "gn:admin4_code":"1059144.0",
    "gn:asciiname":"Meynfeld",
    "gn:country_code":"DE",
    "gn:dem":21,
    "gn:feature_class":"P",
    "gn:feature_code":"PPL",
    "gn:name":"Meynfeld",
    "gn:population":0,
    "gn:timezone":"Europe/Berlin",
    "iso:country":"DE",
    "wof:name":"Meynfeld",
    "wof:placetype":"neighbourhood"
},
  "geometry": {"coordinates":[9.2284,54.74199],"type":"Point"}
}