{
  "type": "Feature",
  "properties": {
    "gn:admin1_code":"13.0",
    "gn:admin2_code":"0.0",
    "gn:admin3_code":"14522.0",
    "gn:admin4_code":"14522450.0",
    "gn:asciiname":"Pfarrsteina",
    "gn:country_code":"DE",
    "gn:dem":179,
    "gn:feature_class":"P",
    "gn:feature_code":"PPL",
    "gn:name":"Pfarrsteina",
    "gn:population":0,
    "gn:timezone":"Europe/Berlin",
    "iso:country":"DE",
    "wof:name":"Pfarrsteina",
    "wof:placetype":"neighbourhood"
},
  "geometry": {"coordinates":[13.10148,51.19321],"type":"Point"}
}