{
  "type": "Feature",
  "properties": {
    "gn:admin1_code":"1",
    "gn:admin2_code":"84.0",
    "gn:admin3_code":"8437.0",
    "gn:admin4_code":"8437005.0",
    "gn:asciiname":"Unterneidingen",
    "gn:country_code":"DE",
    "gn:dem":599,
    "gn:feature_class":"P",
    "gn:feature_code":"PPL",
    "gn:name":"Unterneidingen",
    "gn:population":0,
    "gn:timezone":"Europe/Berlin",
    "iso:country":"DE",
    "wof:name":"Unterneidingen",
    "wof:placetype":"neighbourhood"
},
  "geometry": {"coordinates":[9.06551,48.09572],"type":"Point"}
}