{
  "type": "Feature",
  "properties": {
    "gn:admin1_code":"7",
    "gn:admin2_code":"51.0",
    "gn:admin3_code":"5154.0",
    "gn:admin4_code":"5154024.0",
    "gn:asciiname":"Muehlenfeld",
    "gn:country_code":"DE",
    "gn:dem":17,
    "gn:feature_class":"P",
    "gn:feature_code":"PPL",
    "gn:name":"M\u00fchlenfeld",
    "gn:population":0,
    "gn:timezone":"Europe/Berlin",
    "iso:country":"DE",
    "wof:name":"Muehlenfeld",
    "wof:placetype":"neighbourhood"
},
  "geometry": {"coordinates":[6.3491,51.74767],"type":"Point"}
}