{
  "type": "Feature",
  "properties": {
    "gn:admin1_code":"14",
    "gn:admin2_code":"0.0",
    "gn:admin3_code":"15087.0",
    "gn:admin4_code":"15087386.0",
    "gn:asciiname":"Volkmaritz",
    "gn:country_code":"DE",
    "gn:dem":167,
    "gn:feature_class":"P",
    "gn:feature_code":"PPL",
    "gn:name":"Volkmaritz",
    "gn:population":0,
    "gn:timezone":"Europe/Berlin",
    "iso:country":"DE",
    "wof:name":"Volkmaritz",
    "wof:placetype":"neighbourhood"
},
  "geometry": {"coordinates":[11.69362,51.52822000000001],"type":"Point"}
}