{
  "type": "Feature",
  "properties": {
    "gn:admin1_code":"2",
    "gn:admin2_code":"92.0",
    "gn:admin3_code":"9275.0",
    "gn:admin4_code":"9275124.0",
    "gn:asciiname":"Singham",
    "gn:country_code":"DE",
    "gn:dem":334,
    "gn:feature_class":"P",
    "gn:feature_code":"PPL",
    "gn:name":"Singham",
    "gn:population":0,
    "gn:timezone":"Europe/Berlin",
    "iso:country":"DE",
    "name:ara_x_preferred":[
        "\u0633\u064a\u0646\u063a\u0647\u0627\u0645"
    ],
    "name:fas_x_preferred":[
        "\u0633\u06cc\u0646\u06af\u0647\u0627\u0645"
    ],
    "name:fra_x_preferred":[
        "Singham"
    ],
    "name:hin_x_preferred":[
        "\u0938\u093f\u0902\u0918\u092e"
    ],
    "name:ind_x_preferred":[
        "Singham"
    ],
    "name:ita_x_preferred":[
        "Singham"
    ],
    "name:kor_x_preferred":[
        "\ubaa8\ubc94\uacbd\ucc30 \uc2f1\uac10"
    ],
    "name:mar_x_preferred":[
        "\u0938\u093f\u0902\u0918\u092e"
    ],
    "wof:name":"Singham",
    "wof:placetype":"neighbourhood"
},
  "geometry": {"coordinates":[13.19634,48.41619],"type":"Point"}
}