{
  "type": "Feature",
  "properties": {
    "gn:admin1_code":"2",
    "gn:admin2_code":"92.0",
    "gn:admin3_code":"9275.0",
    "gn:admin4_code":"9275124.0",
    "gn:asciiname":"Singham",
    "gn:country_code":"DE",
    "gn:dem":334,
    "gn:feature_class":"P",
    "gn:feature_code":"PPL",
    "gn:name":"Singham",
    "gn:population":0,
    "gn:timezone":"Europe/Berlin",
    "iso:country":"DE",
    "wof:name":"Singham",
    "wof:placetype":"neighbourhood"
},
  "geometry": {"coordinates":[13.19634,48.41619],"type":"Point"}
}