{
  "type": "Feature",
  "properties": {
    "iso:country":"DE",
    "name:cat_x_preferred":[
        "Alsterdorf"
    ],
    "name:deu_x_preferred":[
        "Hamburg-Alsterdorf"
    ],
    "name:deu_x_variant":[
        "Alsterdorf"
    ],
    "name:eng_x_preferred":[
        "Alsterdorf"
    ],
    "name:fas_x_preferred":[
        "\u0627\u0644\u0633\u062a\u0631\u062f\u0631\u0627\u0641"
    ],
    "name:fra_x_preferred":[
        "Hamburg-Alsterdorf"
    ],
    "name:hun_x_preferred":[
        "Alsterdorf"
    ],
    "name:ita_x_preferred":[
        "Alsterdorf"
    ],
    "name:lat_x_preferred":[
        "Hamburg-Alsterdorf"
    ],
    "name:mkd_x_preferred":[
        "\u0410\u043b\u0441\u0442\u0435\u0440\u0434\u043e\u0440\u0444"
    ],
    "name:nld_x_preferred":[
        "Alsterdorf"
    ],
    "name:oci_x_preferred":[
        "Alsterdorf"
    ],
    "name:pol_x_preferred":[
        "Alsterdorf"
    ],
    "name:rus_x_preferred":[
        "\u0410\u043b\u044c\u0441\u0442\u0435\u0440\u0434\u043e\u0440\u0444"
    ],
    "name:spa_x_preferred":[
        "Alsterdorf"
    ],
    "name:swe_x_preferred":[
        "Hamburg-Alsterdorf"
    ],
    "name:tam_x_preferred":[
        "\u0b85\u0bb2\u0bcd\u0bb8\u0bcd\u0b9f\u0bc6\u0bb0\u0bcd\u0b9f\u0bbe\u0bb0\u0bcd\u0b83\u0baa\u0bcd"
    ],
    "wof:name":"Alsterdorf",
    "wof:placetype":"neighbourhood"
},
  "geometry": {"coordinates":[10.0188373020032,53.612459582882],"type":"Point"}
}