{
  "type": "Feature",
  "properties": {
    "gn:country":"DE",
    "gn:fcode":"PPL",
    "gn:population":245,
    "iso:country":"DE",
    "qs_pg:aaroncc":"DE",
    "qs_pg:gn_country":"DE",
    "qs_pg:gn_fcode":"PPL",
    "qs_pg:gn_pop":245,
    "qs_pg:name":"Daasdorf",
    "qs_pg:name_adm0":"Deutschland",
    "qs_pg:name_adm1":"Th\u00fcringen",
    "qs_pg:photos_9r":0,
    "qs_pg:photos_sr":0,
    "qs_pg:pop_sr":2,
    "qs_pg:qs_pg_placetype":"locality",
    "qs_pg:qs_pg_placetype_gp":"Town",
    "qs_pg:woe_adm0":23424829,
    "woe:adm0_id":23424829,
    "woe:name_adm0":"Deutschland",
    "woe:name_adm1":"Th\u00fcringen",
    "woe:placetype":"Town",
    "wof:name":"Daasdorf",
    "wof:placetype":"neighbourhood",
    "wof:population":245
},
  "geometry": {"coordinates":[11.34192,51.06427],"type":"Point"}
}