{
  "type": "Feature",
  "properties": {
    "gn:country":"DE",
    "gn:fcode":"PPL",
    "gn:population":122,
    "iso:country":"DE",
    "name:bak_x_preferred":[
        "\u041a\u044e\u0437\u0435\u043b\u044c"
    ],
    "name:ceb_x_preferred":[
        "K\u00fcsel"
    ],
    "name:deu_x_preferred":[
        "K\u00fcsel"
    ],
    "name:epo_x_preferred":[
        "K\u00fcsel"
    ],
    "name:fas_x_preferred":[
        "\u06a9\u0648\u0632\u0644"
    ],
    "name:nld_x_preferred":[
        "K\u00fcsel"
    ],
    "name:ron_x_preferred":[
        "K\u00fcsel"
    ],
    "name:rus_x_preferred":[
        "\u041a\u044e\u0437\u0435\u043b\u044c"
    ],
    "name:uzb_x_preferred":[
        "K\u00fcsel"
    ],
    "name:vol_x_preferred":[
        "K\u00fcsel"
    ],
    "qs_pg:aaroncc":"DE",
    "qs_pg:gn_country":"DE",
    "qs_pg:gn_fcode":"PPL",
    "qs_pg:gn_pop":122,
    "qs_pg:name":"K\u00fcsel",
    "qs_pg:name_adm0":"Deutschland",
    "qs_pg:name_adm1":"Sachsen-Anhalt",
    "qs_pg:photos_9r":0,
    "qs_pg:photos_sr":0,
    "qs_pg:pop_sr":1,
    "qs_pg:qs_pg_placetype":"locality",
    "qs_pg:qs_pg_placetype_gp":"Town",
    "qs_pg:woe_adm0":23424829,
    "woe:adm0_id":23424829,
    "woe:name_adm0":"Deutschland",
    "woe:name_adm1":"Sachsen-Anhalt",
    "woe:placetype":"Town",
    "wof:name":"K\u00fcsel",
    "wof:placetype":"neighbourhood",
    "wof:population":122
},
  "geometry": {"coordinates":[12.07273,52.22857],"type":"Point"}
}