{
  "type": "Feature",
  "properties": {
    "gn:country":"DE",
    "gn:fcode":"PPL",
    "gn:population":261,
    "iso:country":"DE",
    "name:bak_x_preferred":[
        "\u0424\u0440\u0438\u0434\u0435\u0431\u0443\u0440\u0433\u0435\u0440\u0445\u044e\u0442\u0442\u0435"
    ],
    "name:ceb_x_preferred":[
        "Friedeburgerh\u00fctte"
    ],
    "name:deu_x_preferred":[
        "Friedeburgerh\u00fctte"
    ],
    "name:epo_x_preferred":[
        "Friedeburgerh\u00fctte"
    ],
    "name:fas_x_preferred":[
        "\u0641\u0631\u06cc\u062f\u0628\u0648\u0631\u06af\u0631\u0647\u0648\u062a\u0647"
    ],
    "name:ita_x_preferred":[
        "Friedeburgerh\u00fctte"
    ],
    "name:kaz_x_preferred":[
        "\u0424\u0440\u0438\u0434\u0435\u0431\u0443\u0440\u0433\u0435\u0440\u0445\u044e\u0442\u0442\u0435"
    ],
    "name:kir_x_preferred":[
        "\u0424\u0440\u0438\u0434\u0435\u0431\u0443\u0440\u0433\u0435\u0440\u0445\u044e\u0442\u0442\u0435"
    ],
    "name:mkd_x_preferred":[
        "\u0424\u0440\u0438\u0434\u0435\u0431\u0443\u0440\u0433\u0435\u0440\u0445\u0438\u0442\u0435"
    ],
    "name:nld_x_preferred":[
        "Friedeburgerh\u00fctte"
    ],
    "name:ron_x_preferred":[
        "Friedeburgerh\u00fctte"
    ],
    "name:rus_x_preferred":[
        "\u0424\u0440\u0438\u0434\u0435\u0431\u0443\u0440\u0433\u0435\u0440\u0445\u044e\u0442\u0442\u0435"
    ],
    "name:uzb_x_preferred":[
        "Friedeburgerh\u00fctte"
    ],
    "name:vie_x_preferred":[
        "Friedeburgerh\u00fctte"
    ],
    "name:vol_x_preferred":[
        "Friedeburgerh\u00fctte"
    ],
    "qs_pg:aaroncc":"DE",
    "qs_pg:gn_country":"DE",
    "qs_pg:gn_fcode":"PPL",
    "qs_pg:gn_pop":261,
    "qs_pg:name":"Friedeburgerh\u00fctte",
    "qs_pg:name_adm0":"Deutschland",
    "qs_pg:name_adm1":"Sachsen-Anhalt",
    "qs_pg:photos_9r":0,
    "qs_pg:photos_sr":0,
    "qs_pg:pop_sr":2,
    "qs_pg:qs_pg_placetype":"locality",
    "qs_pg:qs_pg_placetype_gp":"Town",
    "qs_pg:woe_adm0":23424829,
    "woe:adm0_id":23424829,
    "woe:name_adm0":"Deutschland",
    "woe:name_adm1":"Sachsen-Anhalt",
    "woe:placetype":"Town",
    "wof:name":"Friedeburgerh\u00fctte",
    "wof:placetype":"neighbourhood",
    "wof:population":261
},
  "geometry": {"coordinates":[11.68704,51.6249],"type":"Point"}
}