{
  "type": "Feature",
  "properties": {
    "gn:admin1_code":"14",
    "gn:admin2_code":"0.0",
    "gn:admin3_code":"15003.0",
    "gn:admin4_code":"15003000.0",
    "gn:asciiname":"Herrenkrug",
    "gn:country_code":"DE",
    "gn:dem":44,
    "gn:feature_class":"P",
    "gn:feature_code":"PPL",
    "gn:name":"Herrenkrug",
    "gn:population":0,
    "gn:timezone":"Europe/Berlin",
    "iso:country":"DE",
    "wof:name":"Herrenkrug",
    "wof:placetype":"neighbourhood"
},
  "geometry": {"coordinates":[11.67546,52.13742],"type":"Point"}
}