{
  "type": "Feature",
  "properties": {
    "gn:admin1_code":"13",
    "gn:admin2_code":"0.0",
    "gn:admin3_code":"14521.0",
    "gn:admin4_code":"14521460.0",
    "gn:asciiname":"Hutha",
    "gn:country_code":"DE",
    "gn:dem":558,
    "gn:feature_class":"P",
    "gn:feature_code":"PPL",
    "gn:name":"Hutha",
    "gn:population":0,
    "gn:timezone":"Europe/Berlin",
    "iso:country":"DE",
    "wof:name":"Hutha",
    "wof:placetype":"neighbourhood"
},
  "geometry": {"coordinates":[13.30038,50.69921],"type":"Point"}
}