{
  "type": "Feature",
  "properties": {
    "gn:admin1_code":"2",
    "gn:admin2_code":"91.0",
    "gn:admin3_code":"9188.0",
    "gn:admin4_code":"9188127.0",
    "gn:asciiname":"Hull",
    "gn:country_code":"DE",
    "gn:dem":582,
    "gn:feature_class":"P",
    "gn:feature_code":"PPL",
    "gn:name":"H\u00fcll",
    "gn:population":0,
    "gn:timezone":"Europe/Berlin",
    "iso:country":"DE",
    "wof:name":"Hull",
    "wof:placetype":"neighbourhood"
},
  "geometry": {"coordinates":[11.32448,48.09468],"type":"Point"}
}