{
  "type": "Feature",
  "properties": {
    "gn:admin1_code":"2",
    "gn:admin2_code":"91.0",
    "gn:admin3_code":"9188.0",
    "gn:admin4_code":"9188127.0",
    "gn:asciiname":"Hull",
    "gn:country_code":"DE",
    "gn:dem":582,
    "gn:feature_class":"P",
    "gn:feature_code":"PPL",
    "gn:name":"H\u00fcll",
    "gn:population":0,
    "gn:timezone":"Europe/Berlin",
    "iso:country":"DE",
    "name:bul_x_preferred":[
        "\u0425\u044a\u043b"
    ],
    "name:cat_x_preferred":[
        "Hull"
    ],
    "name:ceb_x_preferred":[
        "Hull"
    ],
    "name:ces_x_preferred":[
        "Hull"
    ],
    "name:cym_x_preferred":[
        "Hull"
    ],
    "name:deu_x_preferred":[
        "Hull"
    ],
    "name:est_x_preferred":[
        "Hull"
    ],
    "name:fas_x_preferred":[
        "\u0647\u0627\u0644"
    ],
    "name:fin_x_preferred":[
        "Hull"
    ],
    "name:fra_x_preferred":[
        "Hull"
    ],
    "name:heb_x_preferred":[
        "\u05d4\u05d0\u05dc"
    ],
    "name:hun_x_preferred":[
        "Hull"
    ],
    "name:ind_x_preferred":[
        "Hull"
    ],
    "name:ita_x_preferred":[
        "Hull"
    ],
    "name:lav_x_preferred":[
        "Hull"
    ],
    "name:lmo_x_preferred":[
        "Hull"
    ],
    "name:nld_x_preferred":[
        "Hull"
    ],
    "name:nor_x_preferred":[
        "Hull"
    ],
    "name:pol_x_preferred":[
        "Hull"
    ],
    "name:por_x_preferred":[
        "Hull"
    ],
    "name:rus_x_preferred":[
        "\u0425\u0430\u043b\u043b"
    ],
    "name:slk_x_preferred":[
        "Hull"
    ],
    "name:slv_x_preferred":[
        "Hull"
    ],
    "name:spa_x_preferred":[
        "Hull"
    ],
    "name:swa_x_preferred":[
        "Hull"
    ],
    "name:swe_x_preferred":[
        "Hull"
    ],
    "name:ukr_x_preferred":[
        "\u0425\u0430\u043b\u043b"
    ],
    "name:vol_x_preferred":[
        "Hull"
    ],
    "wof:name":"Hull",
    "wof:placetype":"neighbourhood"
},
  "geometry": {"coordinates":[11.32448,48.09468],"type":"Point"}
}