{
  "type": "Feature",
  "properties": {
    "gn:admin1_code":"10.0",
    "gn:admin2_code":"0.0",
    "gn:admin3_code":"1054.0",
    "gn:admin4_code":"1054165.0",
    "gn:asciiname":"Blocksberg",
    "gn:country_code":"DE",
    "gn:dem":-3,
    "gn:feature_class":"P",
    "gn:feature_code":"PPL",
    "gn:name":"Blocksberg",
    "gn:population":0,
    "gn:timezone":"Europe/Berlin",
    "iso:country":"DE",
    "wof:name":"Blocksberg",
    "wof:placetype":"neighbourhood"
},
  "geometry": {"coordinates":[8.76667,54.73333],"type":"Point"}
}