{
  "type": "Feature",
  "properties": {
    "gn:admin1_code":"2",
    "gn:admin2_code":"97.0",
    "gn:admin3_code":"9780.0",
    "gn:admin4_code":"9780146.0",
    "gn:asciiname":"Unterried",
    "gn:country_code":"DE",
    "gn:dem":845,
    "gn:feature_class":"P",
    "gn:feature_code":"PPL",
    "gn:name":"Unterried",
    "gn:population":0,
    "gn:timezone":"Europe/Berlin",
    "iso:country":"DE",
    "wof:name":"Unterried",
    "wof:placetype":"neighbourhood"
},
  "geometry": {"coordinates":[10.24058,47.73396],"type":"Point"}
}