{
  "type": "Feature",
  "properties": {
    "gn:admin1_code":"6",
    "gn:admin2_code":"0.0",
    "gn:admin3_code":"3257.0",
    "gn:admin4_code":"3257035.0",
    "gn:asciiname":"Enzen",
    "gn:country_code":"DE",
    "gn:dem":71,
    "gn:feature_class":"P",
    "gn:feature_code":"PPL",
    "gn:name":"Enzen",
    "gn:population":0,
    "gn:timezone":"Europe/Berlin",
    "iso:country":"DE",
    "name:ceb_x_preferred":[
        "Enzen"
    ],
    "name:deu_x_preferred":[
        "Enzen"
    ],
    "name:epo_x_preferred":[
        "Enzen"
    ],
    "name:eus_x_preferred":[
        "Enzen"
    ],
    "name:fas_x_preferred":[
        "\u0627\u0646\u062a\u0633\u0646"
    ],
    "name:fra_x_preferred":[
        "Enzen"
    ],
    "name:hun_x_preferred":[
        "Enzen"
    ],
    "name:ita_x_preferred":[
        "Enzen"
    ],
    "name:kaz_x_preferred":[
        "\u042d\u043d\u0446\u0435\u043d"
    ],
    "name:kir_x_preferred":[
        "\u042d\u043d\u0446\u0435\u043d"
    ],
    "name:msa_x_preferred":[
        "Enzen"
    ],
    "name:nld_x_preferred":[
        "Enzen"
    ],
    "name:pol_x_preferred":[
        "Enzen"
    ],
    "name:por_x_preferred":[
        "Enzen"
    ],
    "name:ron_x_preferred":[
        "Enzen"
    ],
    "name:rus_x_preferred":[
        "\u042d\u043d\u0446\u0435\u043d"
    ],
    "name:spa_x_preferred":[
        "Enzen"
    ],
    "name:srp_x_preferred":[
        "\u0415\u043d\u0446\u0435\u043d"
    ],
    "name:ukr_x_preferred":[
        "\u0415\u043d\u0446\u0435\u043d"
    ],
    "name:uzb_x_preferred":[
        "Enzen"
    ],
    "name:vie_x_preferred":[
        "Enzen"
    ],
    "name:vol_x_preferred":[
        "Enzen"
    ],
    "name:war_x_preferred":[
        "Enzen"
    ],
    "wof:name":"Enzen",
    "wof:placetype":"neighbourhood"
},
  "geometry": {"coordinates":[9.15575,52.32375],"type":"Point"}
}