{
  "type": "Feature",
  "properties": {
    "gn:admin1_code":"1",
    "gn:admin2_code":"81.0",
    "gn:admin3_code":"8117.0",
    "gn:admin4_code":"8117016.0",
    "gn:asciiname":"Oberdrackenstein",
    "gn:country_code":"DE",
    "gn:dem":741,
    "gn:feature_class":"P",
    "gn:feature_code":"PPL",
    "gn:name":"Oberdrackenstein",
    "gn:population":0,
    "gn:timezone":"Europe/Berlin",
    "iso:country":"DE",
    "wof:name":"Oberdrackenstein",
    "wof:placetype":"neighbourhood"
},
  "geometry": {"coordinates":[9.67973,48.55667],"type":"Point"}
}