{
  "type": "Feature",
  "properties": {
    "gn:admin1_code":"2",
    "gn:admin2_code":"91.0",
    "gn:admin3_code":"9183.0",
    "gn:admin4_code":"9183131.0",
    "gn:asciiname":"Haunertsholzen",
    "gn:country_code":"DE",
    "gn:dem":488,
    "gn:feature_class":"P",
    "gn:feature_code":"PPL",
    "gn:name":"Haunertsholzen",
    "gn:population":0,
    "gn:timezone":"Europe/Berlin",
    "iso:country":"DE",
    "wof:name":"Haunertsholzen",
    "wof:placetype":"neighbourhood"
},
  "geometry": {"coordinates":[12.56606,48.35091],"type":"Point"}
}