{
  "type": "Feature",
  "properties": {
    "gn:admin1_code":"2",
    "gn:admin2_code":"95.0",
    "gn:admin3_code":"9574.0",
    "gn:admin4_code":"9574128.0",
    "gn:asciiname":"Schupf",
    "gn:country_code":"DE",
    "gn:dem":544,
    "gn:feature_class":"P",
    "gn:feature_code":"PPL",
    "gn:name":"Schupf",
    "gn:population":0,
    "gn:timezone":"Europe/Berlin",
    "iso:country":"DE",
    "wof:name":"Schupf",
    "wof:placetype":"neighbourhood"
},
  "geometry": {"coordinates":[11.482,49.44486],"type":"Point"}
}