{
  "type": "Feature",
  "properties": {
    "gn:admin1_code":"5.0",
    "gn:admin2_code":"066",
    "gn:admin3_code":"6635.0",
    "gn:admin4_code":"6635006.0",
    "gn:asciiname":"Wiesenfeld",
    "gn:country_code":"DE",
    "gn:dem":306,
    "gn:feature_class":"P",
    "gn:feature_code":"PPL",
    "gn:name":"Wiesenfeld",
    "gn:population":0,
    "gn:timezone":"Europe/Berlin",
    "iso:country":"DE",
    "name:ceb_x_preferred":[
        "Wiesenfeld"
    ],
    "name:deu_x_preferred":[
        "Wiesenfeld"
    ],
    "name:epo_x_preferred":[
        "Wiesenfeld"
    ],
    "name:nld_x_preferred":[
        "Wiesenfeld"
    ],
    "name:pol_x_preferred":[
        "Wiesenfeld"
    ],
    "name:swe_x_preferred":[
        "Wiesenfeld"
    ],
    "wof:name":"Wiesenfeld",
    "wof:placetype":"neighbourhood"
},
  "geometry": {"coordinates":[8.75093,51.00612],"type":"Point"}
}