{
  "type": "Feature",
  "properties": {
    "gn:admin1_code":"5.0",
    "gn:admin2_code":"65.0",
    "gn:admin3_code":"6534.0",
    "gn:admin4_code":"6534021.0",
    "gn:asciiname":"Amoenau",
    "gn:country_code":"DE",
    "gn:dem":225,
    "gn:feature_class":"P",
    "gn:feature_code":"PPL",
    "gn:name":"Am\u00f6nau",
    "gn:population":0,
    "gn:timezone":"Europe/Berlin",
    "iso:country":"DE",
    "wof:name":"Amoenau",
    "wof:placetype":"neighbourhood"
},
  "geometry": {"coordinates":[8.686,50.90838],"type":"Point"}
}