{
  "type": "Feature",
  "properties": {
    "gn:admin1_code":"6.0",
    "gn:admin2_code":"0.0",
    "gn:admin3_code":"3256.0",
    "gn:admin4_code":"3256013.0",
    "gn:asciiname":"Auf dem Floth",
    "gn:country_code":"DE",
    "gn:dem":14,
    "gn:feature_class":"P",
    "gn:feature_code":"PPL",
    "gn:name":"Auf dem Floth",
    "gn:population":0,
    "gn:timezone":"Europe/Berlin",
    "iso:country":"DE",
    "wof:name":"Auf dem Floth",
    "wof:placetype":"neighbourhood"
},
  "geometry": {"coordinates":[9.12311,52.86832],"type":"Point"}
}