{
  "type": "Feature",
  "properties": {
    "gn:admin1_code":"2.0",
    "gn:admin2_code":"091",
    "gn:admin3_code":"9180.0",
    "gn:admin4_code":"9180124.0",
    "gn:asciiname":"Weindorf",
    "gn:country_code":"DE",
    "gn:dem":695,
    "gn:feature_class":"P",
    "gn:feature_code":"PPL",
    "gn:name":"Weindorf",
    "gn:population":0,
    "gn:timezone":"Europe/Berlin",
    "iso:country":"DE",
    "wof:name":"Weindorf",
    "wof:placetype":"neighbourhood"
},
  "geometry": {"coordinates":[11.20949,47.68157],"type":"Point"}
}