{
  "type": "Feature",
  "properties": {
    "gn:admin1_code":"2",
    "gn:admin2_code":"91.0",
    "gn:admin3_code":"9175.0",
    "gn:admin4_code":"9175122.0",
    "gn:asciiname":"Gasteig",
    "gn:country_code":"DE",
    "gn:dem":533,
    "gn:feature_class":"P",
    "gn:feature_code":"PPL",
    "gn:name":"Gasteig",
    "gn:population":0,
    "gn:timezone":"Europe/Berlin",
    "iso:country":"DE",
    "name:deu_x_preferred":[
        "Gasteig"
    ],
    "name:fra_x_preferred":[
        "Gasteig"
    ],
    "name:ita_x_preferred":[
        "Gasteig"
    ],
    "name:jpn_x_preferred":[
        "\u30ac\u30b9\u30bf\u30a4\u30af"
    ],
    "name:nor_x_preferred":[
        "Gasteig"
    ],
    "name:ron_x_preferred":[
        "Gasteig"
    ],
    "name:spa_x_preferred":[
        "Gasteig"
    ],
    "wof:name":"Gasteig",
    "wof:placetype":"neighbourhood"
},
  "geometry": {"coordinates":[11.98317,48.05651],"type":"Point"}
}