{
  "type": "Feature",
  "properties": {
    "gn:gn_country":"DE",
    "gn:gn_fcode":"PPLA4",
    "gn:gn_pop":248,
    "gn:population":248,
    "iso:country":"DE",
    "name:bak_x_preferred":[
        "\u0413\u0440\u043e\u0431\u0435\u043d\u0433\u0435\u0440\u043e\u0439\u0442"
    ],
    "name:baq_x_preferred":[
        "Grobengereuth"
    ],
    "name:chi_x_preferred":[
        "\u683c\u7f57\u672c\u683c\u7f57\u4f0a\u7279"
    ],
    "name:dut_x_preferred":[
        "Grobengereuth"
    ],
    "name:eng_x_preferred":[
        "Grobengereuth"
    ],
    "name:epo_x_preferred":[
        "Grobengereuth"
    ],
    "name:fre_x_preferred":[
        "Grobengereuth"
    ],
    "name:ger_x_preferred":[
        "Grobengereuth"
    ],
    "name:hun_x_preferred":[
        "Grobengereuth"
    ],
    "name:ita_x_preferred":[
        "Grobengereuth"
    ],
    "name:mac_x_preferred":[
        "\u0413\u0440\u043e\u0431\u0435\u043d\u0433\u0435\u0440\u043e\u0458\u0442"
    ],
    "name:may_x_preferred":[
        "Grobengereuth"
    ],
    "name:per_x_preferred":[
        "\u06af\u0631\u0648\u0628\u0646\u06af\u0631\u0648\u06cc\u062a"
    ],
    "name:pol_x_preferred":[
        "Grobengereuth"
    ],
    "name:por_x_preferred":[
        "Grobengereuth"
    ],
    "name:rum_x_preferred":[
        "Grobengereuth"
    ],
    "name:rus_x_preferred":[
        "\u0413\u0440\u043e\u0431\u0435\u043d\u0433\u0435\u0440\u043e\u0439\u0442"
    ],
    "name:srp_x_preferred":[
        "\u0413\u0440\u043e\u0431\u0435\u043d\u0433\u0435\u0440\u043e\u0458\u0442"
    ],
    "name:ukr_x_preferred":[
        "\u0413\u0440\u043e\u0431\u0435\u043d\u0433\u0435\u0440\u043e\u0439\u0442"
    ],
    "name:uzb_x_preferred":[
        "Grobengereuth"
    ],
    "name:vie_x_preferred":[
        "Grobengereuth"
    ],
    "name:vol_x_preferred":[
        "Grobengereuth"
    ],
    "name:war_x_preferred":[
        "Grobengereuth"
    ],
    "qs_pg:aaroncc":"DE",
    "qs_pg:gn_country":"DE",
    "qs_pg:gn_fcode":"PPLA4",
    "qs_pg:gn_pop":248,
    "qs_pg:name":"Grobengereuth",
    "qs_pg:photos_9r":0,
    "qs_pg:photos_sr":0,
    "qs_pg:pop_sr":2,
    "qs_pg:qs_pg_placetype":"locality",
    "wof:name":"Grobengereuth",
    "wof:placetype":"locality",
    "wof:population":248
},
  "geometry": {"coordinates":[11.66937,50.66916],"type":"Point"}
}