{
  "type": "Feature",
  "properties": {
    "gn:admin1_code":"2",
    "gn:admin2_code":"92.0",
    "gn:admin3_code":"9275.0",
    "gn:admin4_code":"9275149.0",
    "gn:asciiname":"Oberschwarzenbach",
    "gn:country_code":"DE",
    "gn:dem":337,
    "gn:feature_class":"P",
    "gn:feature_code":"PPL",
    "gn:name":"Oberschw\u00e4rzenbach",
    "gn:population":0,
    "gn:timezone":"Europe/Berlin",
    "iso:country":"DE",
    "wof:name":"Oberschwarzenbach",
    "wof:placetype":"neighbourhood"
},
  "geometry": {"coordinates":[13.2847,48.44525],"type":"Point"}
}