{
  "type": "Feature",
  "properties": {
    "gn:country":"DE",
    "gn:fcode":"PPL",
    "gn:population":286,
    "iso:country":"DE",
    "name:bak_x_preferred":[
        "\u0417\u0430\u043d\u0434\u0431\u0430\u0439\u0435\u043d\u0434\u043e\u0440\u0444"
    ],
    "name:ceb_x_preferred":[
        "Sandbeiendorf"
    ],
    "name:deu_x_preferred":[
        "Sandbeiendorf"
    ],
    "name:epo_x_preferred":[
        "Sandbeiendorf"
    ],
    "name:fas_x_preferred":[
        "\u0632\u0627\u0646\u062f\u0628\u0627\u06cc\u0646\u062f\u0648\u0631\u0641"
    ],
    "name:ita_x_preferred":[
        "Sandbeiendorf"
    ],
    "name:kaz_x_preferred":[
        "\u0417\u0430\u043d\u0434\u0431\u0430\u0439\u0435\u043d\u0434\u043e\u0440\u0444"
    ],
    "name:kir_x_preferred":[
        "\u0417\u0430\u043d\u0434\u0431\u0430\u0439\u0435\u043d\u0434\u043e\u0440\u0444"
    ],
    "name:nld_x_preferred":[
        "Sandbeiendorf"
    ],
    "name:pol_x_preferred":[
        "Sandbeiendorf"
    ],
    "name:ron_x_preferred":[
        "Sandbeiendorf"
    ],
    "name:rus_x_preferred":[
        "\u0417\u0430\u043d\u0434\u0431\u0430\u0439\u0435\u043d\u0434\u043e\u0440\u0444"
    ],
    "name:uzb_x_preferred":[
        "Sandbeiendorf"
    ],
    "name:vie_x_preferred":[
        "Sandbeiendorf"
    ],
    "name:vol_x_preferred":[
        "Sandbeiendorf"
    ],
    "qs_pg:aaroncc":"DE",
    "qs_pg:gn_country":"DE",
    "qs_pg:gn_fcode":"PPL",
    "qs_pg:gn_pop":286,
    "qs_pg:name":"Sandbeiendorf",
    "qs_pg:name_adm0":"Deutschland",
    "qs_pg:name_adm1":"Sachsen-Anhalt",
    "qs_pg:photos_9r":0,
    "qs_pg:photos_sr":0,
    "qs_pg:pop_sr":2,
    "qs_pg:qs_pg_placetype":"locality",
    "qs_pg:qs_pg_placetype_gp":"Town",
    "qs_pg:woe_adm0":23424829,
    "woe:adm0_id":23424829,
    "woe:name_adm0":"Deutschland",
    "woe:name_adm1":"Sachsen-Anhalt",
    "woe:placetype":"Town",
    "wof:name":"Sandbeiendorf",
    "wof:placetype":"neighbourhood",
    "wof:population":286
},
  "geometry": {"coordinates":[11.71932,52.39592],"type":"Point"}
}