{
  "type": "Feature",
  "properties": {
    "gn:population":1526,
    "iso:country":"DE",
    "name:cat_x_preferred":[
        "Bell"
    ],
    "name:ceb_x_preferred":[
        "Bell"
    ],
    "name:che_x_preferred":[
        "\u0411\u0435\u043b\u043b\u044c"
    ],
    "name:deu_x_preferred":[
        "Bell"
    ],
    "name:eng_x_preferred":[
        "Bell"
    ],
    "name:epo_x_preferred":[
        "Bell"
    ],
    "name:eus_x_preferred":[
        "Bell"
    ],
    "name:fas_x_preferred":[
        "\u0628\u0644"
    ],
    "name:fra_x_preferred":[
        "Bell"
    ],
    "name:hun_x_preferred":[
        "Bell"
    ],
    "name:ibo_x_preferred":[
        "Bell"
    ],
    "name:ita_x_preferred":[
        "Bell"
    ],
    "name:jpn_x_preferred":[
        "\u30d9\u30eb"
    ],
    "name:kaz_x_preferred":[
        "\u0411\u0435\u043b\u043b\u044c"
    ],
    "name:kir_x_preferred":[
        "\u0411\u0435\u043b\u043b\u044c"
    ],
    "name:lld_x_preferred":[
        "Bell"
    ],
    "name:msa_x_preferred":[
        "Bell"
    ],
    "name:nan_x_preferred":[
        "Bell"
    ],
    "name:nld_x_preferred":[
        "Bell"
    ],
    "name:nob_x_preferred":[
        "Bell"
    ],
    "name:pol_x_preferred":[
        "Bell"
    ],
    "name:por_x_preferred":[
        "Bell"
    ],
    "name:ron_x_preferred":[
        "Bell"
    ],
    "name:rus_x_preferred":[
        "\u0411\u0435\u043b\u043b\u044c"
    ],
    "name:spa_x_preferred":[
        "Bell"
    ],
    "name:srp_x_preferred":[
        "\u0411\u0435\u043b"
    ],
    "name:swe_x_preferred":[
        "Bell"
    ],
    "name:tat_x_preferred":[
        "\u0411\u0435\u043b\u043b\u044c"
    ],
    "name:ukr_x_preferred":[
        "\u0411\u0435\u043b\u044c"
    ],
    "name:uzb_x_preferred":[
        "Bell"
    ],
    "name:vie_x_preferred":[
        "Bell"
    ],
    "name:war_x_preferred":[
        "Bell"
    ],
    "qs:a0":"Bundesrepublik Deutschland",
    "qs:a1":"*Rheinland-Pfalz",
    "qs:a1r":"0",
    "qs:a2":"Rhein-Hunsr\u00fcck-Kreis",
    "qs:adm0":"Bundesrepublik Deutschland",
    "qs:la_lc":"*",
    "qs:level":"locality",
    "qs:loc":"Bell (Hunsr\u00fcck)",
    "qs:loc_alt":"Bell (Hunsrueck)",
    "qs:pop":0,
    "qs:type":"buffered point",
    "wd:wordcount":1904,
    "wof:name":"Bell (Hunsr\u00fcck)",
    "wof:placetype":"neighbourhood",
    "wof:population":1526
},
  "geometry": {"coordinates":[7.417407,50.064475],"type":"Point"}
}