{
  "type": "Feature",
  "properties": {
    "gn:admin1_code":"2",
    "gn:admin2_code":"91.0",
    "gn:admin3_code":"9183.0",
    "gn:admin4_code":"9183143.0",
    "gn:asciiname":"Misthilgen",
    "gn:country_code":"DE",
    "gn:dem":470,
    "gn:feature_class":"P",
    "gn:feature_code":"PPL",
    "gn:name":"Misthilgen",
    "gn:population":0,
    "gn:timezone":"Europe/Berlin",
    "iso:country":"DE",
    "wof:name":"Misthilgen",
    "wof:placetype":"neighbourhood"
},
  "geometry": {"coordinates":[12.40321,48.33465],"type":"Point"}
}