{
  "type": "Feature",
  "properties": {
    "gn:admin1_code":"8",
    "gn:admin2_code":"0.0",
    "gn:admin3_code":"7335.0",
    "gn:admin4_code":"7335004.0",
    "gn:asciiname":"Daubenbornerhof",
    "gn:country_code":"DE",
    "gn:dem":277,
    "gn:feature_class":"P",
    "gn:feature_code":"PPL",
    "gn:name":"Daubenbornerhof",
    "gn:population":0,
    "gn:timezone":"Europe/Berlin",
    "iso:country":"DE",
    "wof:name":"Daubenbornerhof",
    "wof:placetype":"neighbourhood"
},
  "geometry": {"coordinates":[7.86346,49.46615],"type":"Point"}
}