{
  "type": "Feature",
  "properties": {
    "gn:admin1_code":"6",
    "gn:admin2_code":"0.0",
    "gn:admin3_code":"3358.0",
    "gn:admin4_code":"3358022.0",
    "gn:asciiname":"Stellichte",
    "gn:country_code":"DE",
    "gn:dem":49,
    "gn:feature_class":"P",
    "gn:feature_code":"PPL",
    "gn:name":"Stellichte",
    "gn:population":0,
    "gn:timezone":"Europe/Berlin",
    "iso:country":"DE",
    "wof:name":"Stellichte",
    "wof:placetype":"neighbourhood"
},
  "geometry": {"coordinates":[9.52068,52.93646],"type":"Point"}
}