{
  "type": "Feature",
  "properties": {
    "gn:gn_country":"DE",
    "gn:gn_fcode":"PPLA4",
    "gn:gn_pop":274,
    "gn:population":274,
    "iso:country":"DE",
    "name:chi_x_preferred":[
        "\u95e8\u5c91\u591a\u592b"
    ],
    "name:dut_x_preferred":[
        "Menzendorf"
    ],
    "name:eng_x_preferred":[
        "Menzendorf"
    ],
    "name:epo_x_preferred":[
        "Menzendorf"
    ],
    "name:fre_x_preferred":[
        "Menzendorf"
    ],
    "name:ger_x_preferred":[
        "Menzendorf"
    ],
    "name:hun_x_preferred":[
        "Menzendorf"
    ],
    "name:ita_x_preferred":[
        "Menzendorf"
    ],
    "name:kaz_x_preferred":[
        "\u041c\u0435\u043d\u0446\u0435\u043d\u0434\u043e\u0440\u0444"
    ],
    "name:kir_x_preferred":[
        "\u041c\u0435\u043d\u0446\u0435\u043d\u0434\u043e\u0440\u0444"
    ],
    "name:mac_x_preferred":[
        "\u041c\u0435\u043d\u0446\u0435\u043d\u0434\u043e\u0440\u0444"
    ],
    "name:may_x_preferred":[
        "Menzendorf"
    ],
    "name:per_x_preferred":[
        "\u0645\u0646\u062a\u0633\u0646\u062f\u0648\u0631\u0641"
    ],
    "name:pol_x_preferred":[
        "Menzendorf"
    ],
    "name:por_x_preferred":[
        "Menzendorf"
    ],
    "name:rum_x_preferred":[
        "Menzendorf"
    ],
    "name:rus_x_preferred":[
        "\u041c\u0435\u043d\u0446\u0435\u043d\u0434\u043e\u0440\u0444"
    ],
    "name:srp_x_preferred":[
        "\u041c\u0435\u043d\u0446\u0435\u043d\u0434\u043e\u0440\u0444"
    ],
    "name:ukr_x_preferred":[
        "\u041c\u0435\u043d\u0446\u0435\u043d\u0434\u043e\u0440\u0444"
    ],
    "name:unk_x_variant":[
        "Menzendorf-Dorf"
    ],
    "name:uzb_x_preferred":[
        "Menzendorf"
    ],
    "name:vie_x_preferred":[
        "Menzendorf"
    ],
    "name:vol_x_preferred":[
        "Menzendorf"
    ],
    "name:war_x_preferred":[
        "Menzendorf"
    ],
    "qs_pg:aaroncc":"DE",
    "qs_pg:gn_country":"DE",
    "qs_pg:gn_fcode":"PPLA4",
    "qs_pg:gn_pop":274,
    "qs_pg:name":"Menzendorf",
    "qs_pg:photos_9r":0,
    "qs_pg:photos_sr":0,
    "qs_pg:pop_sr":2,
    "qs_pg:qs_pg_placetype":"locality",
    "wof:name":"Menzendorf",
    "wof:placetype":"locality",
    "wof:population":274
},
  "geometry": {"coordinates":[11.01667,53.85],"type":"Point"}
}