{
  "type": "Feature",
  "properties": {
    "gn:admin1_code":"15",
    "gn:admin2_code":"0.0",
    "gn:admin3_code":"16071.0",
    "gn:admin4_code":"16071047.0",
    "gn:asciiname":"Haindorf",
    "gn:country_code":"DE",
    "gn:dem":182,
    "gn:feature_class":"P",
    "gn:feature_code":"PPL",
    "gn:name":"Haindorf",
    "gn:population":0,
    "gn:timezone":"Europe/Berlin",
    "iso:country":"DE",
    "wof:name":"Haindorf",
    "wof:placetype":"neighbourhood"
},
  "geometry": {"coordinates":[11.32097,51.08819],"type":"Point"}
}