{
  "type": "Feature",
  "properties": {
    "gn:admin1_code":"7.0",
    "gn:admin2_code":"59.0",
    "gn:admin3_code":"5954.0",
    "gn:admin4_code":"5954012.0",
    "gn:asciiname":"Berge",
    "gn:country_code":"DE",
    "gn:dem":186,
    "gn:feature_class":"P",
    "gn:feature_code":"PPL",
    "gn:name":"Berge",
    "gn:population":0,
    "gn:timezone":"Europe/Berlin",
    "iso:country":"DE",
    "name:ceb_x_preferred":[
        "Berge"
    ],
    "name:deu_x_preferred":[
        "Berge"
    ],
    "name:epo_x_preferred":[
        "Berge"
    ],
    "name:est_x_preferred":[
        "Berge"
    ],
    "name:eus_x_preferred":[
        "Berge"
    ],
    "name:fra_x_preferred":[
        "Berge"
    ],
    "name:hun_x_preferred":[
        "Berge"
    ],
    "name:ita_x_preferred":[
        "Berge"
    ],
    "name:nds_x_preferred":[
        "Berge"
    ],
    "name:nld_x_preferred":[
        "Berge"
    ],
    "name:nno_x_preferred":[
        "Berge"
    ],
    "name:pol_x_preferred":[
        "Berge"
    ],
    "name:por_x_preferred":[
        "Berge"
    ],
    "name:rus_x_preferred":[
        "\u0411\u0435\u0440\u0433\u0435"
    ],
    "name:srp_x_preferred":[
        "\u0411\u0435\u0440\u0433\u0435"
    ],
    "name:swe_x_preferred":[
        "Berge"
    ],
    "name:ukr_x_preferred":[
        "\u0411\u0435\u0440\u0433\u0435"
    ],
    "name:vol_x_preferred":[
        "Berge"
    ],
    "wof:name":"Berge",
    "wof:placetype":"neighbourhood"
},
  "geometry": {"coordinates":[7.36582,51.34804000000001],"type":"Point"}
}