{
  "type": "Feature",
  "properties": {
    "gn:admin1_code":"1",
    "gn:admin2_code":"82.0",
    "gn:admin3_code":"8216.0",
    "gn:admin4_code":"8216049.0",
    "gn:asciiname":"Lieberstung",
    "gn:country_code":"DE",
    "gn:dem":125,
    "gn:feature_class":"P",
    "gn:feature_code":"PPL",
    "gn:name":"Lieberstung",
    "gn:population":0,
    "gn:timezone":"Europe/Berlin",
    "iso:country":"DE",
    "name:eng_x_preferred":[
        "Leiberstung"
    ],
    "name:eng_x_variant":[
        "Lieberstung"
    ],
    "wof:name":"Leiberstung",
    "wof:placetype":"neighbourhood"
},
  "geometry": {"coordinates":[8.09817,48.7525],"type":"Point"}
}