{
  "type": "Feature",
  "properties": {
    "iso:country":"DE",
    "name:deu_x_preferred":[
        "Kleefeld"
    ],
    "name:nld_x_preferred":[
        "Kleefeld"
    ],
    "name:pol_x_preferred":[
        "Kleefeld"
    ],
    "wof:name":"Kleefeld",
    "wof:placetype":"neighbourhood"
},
  "geometry": {"coordinates":[9.79477700877551,52.37487093722475],"type":"Point"}
}