{
  "type": "Feature",
  "properties": {
    "iso:country":"DE",
    "wof:name":"Kleefeld",
    "wof:placetype":"neighbourhood"
},
  "geometry": {"coordinates":[9.79477700877551,52.37487093722475],"type":"Point"}
}