{
  "type": "Feature",
  "properties": {
    "gn:admin1_code":"15",
    "gn:admin2_code":"0.0",
    "gn:admin3_code":"16077.0",
    "gn:admin4_code":"16077002.0",
    "gn:asciiname":"Platschuetz",
    "gn:country_code":"DE",
    "gn:dem":236,
    "gn:feature_class":"P",
    "gn:feature_code":"PPL",
    "gn:name":"Platsch\u00fctz",
    "gn:population":0,
    "gn:timezone":"Europe/Berlin",
    "iso:country":"DE",
    "wof:name":"Platschuetz",
    "wof:placetype":"neighbourhood"
},
  "geometry": {"coordinates":[12.33966,50.92637],"type":"Point"}
}