{
  "type": "Feature",
  "properties": {
    "gn:admin1_code":"2",
    "gn:admin2_code":"92.0",
    "gn:admin3_code":"9275.0",
    "gn:admin4_code":"9275131.0",
    "gn:asciiname":"Malgertsham",
    "gn:country_code":"DE",
    "gn:dem":408,
    "gn:feature_class":"P",
    "gn:feature_code":"PPL",
    "gn:name":"Malgertsham",
    "gn:population":0,
    "gn:timezone":"Europe/Berlin",
    "iso:country":"DE",
    "wof:name":"Malgertsham",
    "wof:placetype":"neighbourhood"
},
  "geometry": {"coordinates":[13.13433,48.3725],"type":"Point"}
}