{
  "type": "Feature",
  "properties": {
    "gn:admin1_code":"2",
    "gn:admin2_code":"94.0",
    "gn:admin3_code":"9471.0",
    "gn:admin4_code":"9471220.0",
    "gn:asciiname":"Possenfelden",
    "gn:country_code":"DE",
    "gn:dem":304,
    "gn:feature_class":"P",
    "gn:feature_code":"PPL",
    "gn:name":"Possenfelden",
    "gn:population":0,
    "gn:timezone":"Europe/Berlin",
    "iso:country":"DE",
    "wof:name":"Possenfelden",
    "wof:placetype":"neighbourhood"
},
  "geometry": {"coordinates":[10.66781,49.75118],"type":"Point"}
}