{
  "type": "Feature",
  "properties": {
    "gn:admin1_code":"14",
    "gn:admin2_code":"0.0",
    "gn:admin3_code":"15091.0",
    "gn:admin4_code":"15091060.0",
    "gn:asciiname":"Luko",
    "gn:country_code":"DE",
    "gn:dem":83,
    "gn:feature_class":"P",
    "gn:feature_code":"PPL",
    "gn:name":"Luko",
    "gn:population":0,
    "gn:timezone":"Europe/Berlin",
    "iso:country":"DE",
    "name:bos_x_preferred":[
        "Luko"
    ],
    "name:fra_x_preferred":[
        "Luko"
    ],
    "name:srp_x_preferred":[
        "\u041b\u0443\u043a\u043e"
    ],
    "wof:name":"Luko",
    "wof:placetype":"neighbourhood"
},
  "geometry": {"coordinates":[12.32453,51.92484],"type":"Point"}
}