{
  "type": "Feature",
  "properties": {
    "iso:country":"DE",
    "name:ceb_x_preferred":[
        "Bayenthal"
    ],
    "name:deu_x_preferred":[
        "Bayenthal"
    ],
    "name:lat_x_preferred":[
        "K\u00f6ln-Bayenthal"
    ],
    "name:pol_x_preferred":[
        "Bayenthal"
    ],
    "wof:name":"Bayenthal",
    "wof:placetype":"neighbourhood"
},
  "geometry": {"coordinates":[6.96857848046199,50.91024654786654],"type":"Point"}
}