{
  "type": "Feature",
  "properties": {
    "gn:admin1_code":"6",
    "gn:admin2_code":"0.0",
    "gn:admin3_code":"3456.0",
    "gn:admin4_code":"3456008.0",
    "gn:asciiname":"Hardingen",
    "gn:country_code":"DE",
    "gn:dem":23,
    "gn:feature_class":"P",
    "gn:feature_code":"PPL",
    "gn:name":"Hardingen",
    "gn:population":0,
    "gn:timezone":"Europe/Berlin",
    "iso:country":"DE",
    "wof:name":"Hardingen",
    "wof:placetype":"neighbourhood"
},
  "geometry": {"coordinates":[6.93233,52.4727],"type":"Point"}
}