{
  "type": "Feature",
  "properties": {
    "gn:admin1_code":"8",
    "gn:admin2_code":"0.0",
    "gn:admin3_code":"7231.0",
    "gn:admin4_code":"7231005.0",
    "gn:asciiname":"Springiersbach",
    "gn:country_code":"DE",
    "gn:dem":171,
    "gn:feature_class":"P",
    "gn:feature_code":"PPL",
    "gn:name":"Springiersbach",
    "gn:population":0,
    "gn:timezone":"Europe/Berlin",
    "iso:country":"DE",
    "name:deu_x_preferred":[
        "Kloster Springiersbach"
    ],
    "name:epo_x_preferred":[
        "Klostro Springiersbach"
    ],
    "name:rus_x_preferred":[
        "\u0410\u0431\u0431\u0430\u0442\u0441\u0442\u0432\u043e \u0428\u043f\u0440\u0438\u043d\u0433\u0435\u0440\u0441\u0431\u0430\u0445"
    ],
    "wof:name":"Springiersbach",
    "wof:placetype":"neighbourhood"
},
  "geometry": {"coordinates":[7.06875,50.02572],"type":"Point"}
}