{
  "type": "Feature",
  "properties": {
    "gn:gn_country":"DE",
    "gn:gn_fcode":"PPLA4",
    "gn:gn_pop":664,
    "gn:population":664,
    "iso:country":"DE",
    "name:baq_x_preferred":[
        "Erdesbach"
    ],
    "name:chi_x_preferred":[
        "\u57c3\u5c14\u5fb7\u65af\u5df4\u8d6b"
    ],
    "name:dut_x_preferred":[
        "Erdesbach"
    ],
    "name:eng_x_preferred":[
        "Erdesbach"
    ],
    "name:epo_x_preferred":[
        "Erdesbach"
    ],
    "name:fre_x_preferred":[
        "Erdesbach"
    ],
    "name:ger_x_preferred":[
        "Erdesbach"
    ],
    "name:hun_x_preferred":[
        "Erdesbach"
    ],
    "name:ita_x_preferred":[
        "Erdesbach"
    ],
    "name:jpn_x_preferred":[
        "\u30a8\u30a2\u30c7\u30b9\u30d0\u30c3\u30cf"
    ],
    "name:kaz_x_preferred":[
        "\u042d\u0440\u0434\u0435\u0441\u0431\u0430\u0445"
    ],
    "name:kir_x_preferred":[
        "\u042d\u0440\u0434\u0435\u0441\u0431\u0430\u0445"
    ],
    "name:may_x_preferred":[
        "Erdesbach"
    ],
    "name:per_x_preferred":[
        "\u0627\u0631\u062f\u0633\u0628\u0627\u062e"
    ],
    "name:pol_x_preferred":[
        "Erdesbach"
    ],
    "name:por_x_preferred":[
        "Erdesbach"
    ],
    "name:rum_x_preferred":[
        "Erdesbach"
    ],
    "name:rus_x_preferred":[
        "\u042d\u0440\u0434\u0435\u0441\u0431\u0430\u0445"
    ],
    "name:spa_x_preferred":[
        "Erdesbach"
    ],
    "name:srp_x_preferred":[
        "\u0415\u0440\u0434\u0435\u0441\u0431\u0430\u0445"
    ],
    "name:ukr_x_preferred":[
        "\u0415\u0440\u0434\u0435\u0441\u0431\u0430\u0445"
    ],
    "name:uzb_x_preferred":[
        "Erdesbach"
    ],
    "name:vie_x_preferred":[
        "Erdesbach"
    ],
    "name:vol_x_preferred":[
        "Erdesbach"
    ],
    "name:war_x_preferred":[
        "Erdesbach"
    ],
    "name:zho_x_preferred":[
        "\u57c3\u5c14\u5fb7\u65af\u5df4\u8d6b"
    ],
    "qs_pg:aaroncc":"DE",
    "qs_pg:gn_country":"DE",
    "qs_pg:gn_fcode":"PPLA4",
    "qs_pg:gn_pop":664,
    "qs_pg:name":"Erdesbach",
    "qs_pg:photos_9r":0,
    "qs_pg:photos_sr":0,
    "qs_pg:pop_sr":2,
    "qs_pg:qs_pg_placetype":"locality",
    "wof:name":"Erdesbach",
    "wof:placetype":"locality",
    "wof:population":664
},
  "geometry": {"coordinates":[7.45,49.56667],"type":"Point"}
}