{
  "type": "Feature",
  "properties": {
    "gn:admin1_code":"2",
    "gn:admin2_code":"92.0",
    "gn:admin3_code":"9275.0",
    "gn:admin4_code":"9275154.0",
    "gn:asciiname":"Primsdobl",
    "gn:country_code":"DE",
    "gn:dem":377,
    "gn:feature_class":"P",
    "gn:feature_code":"PPLL",
    "gn:name":"Primsdobl",
    "gn:population":0,
    "gn:timezone":"Europe/Berlin",
    "iso:country":"DE",
    "wof:name":"Primsdobl",
    "wof:placetype":"neighbourhood"
},
  "geometry": {"coordinates":[13.29712,48.58412],"type":"Point"}
}