{
  "type": "Feature",
  "properties": {
    "iso:country":"DE",
    "name:deu_x_preferred":[
        "Speick"
    ],
    "qs:gn_adm0_cc":"DE",
    "qs:gn_local":2869894,
    "qs:gn_nam_loc":"monchengladbach",
    "qs:gn_namadm1":"07",
    "qs:local_max":967,
    "qs:local_sum":3437,
    "qs:localhoods":20,
    "qs:name":"Speick",
    "qs:name_adm0":"Deutschland",
    "qs:name_adm1":"Nordrhein-Westfalen",
    "qs:name_adm2":"Stadtkreis M\u00f6nchengladbach",
    "qs:name_lau":"Stadtteil Ohler",
    "qs:name_local":"M\u00f6nchengladbach",
    "qs:photo_max":2,
    "qs:photo_sum":2,
    "qs:placetype":"Suburb",
    "qs:quad_count":1,
    "qs:woe_adm0":23424829,
    "qs:woe_adm1":2345487,
    "qs:woe_adm2":12596896,
    "qs:woe_lau":26823035,
    "qs:woe_local":675922,
    "qs:woe_ver":"7.10.0",
    "wof:lang":[
        "ger"
    ],
    "wof:name":"Speick",
    "wof:placetype":"neighbourhood"
},
  "geometry": {"coordinates":[6.420593,51.184653],"type":"Point"}
}