{
  "type": "Feature",
  "properties": {
    "gn:admin1_code":"15",
    "gn:admin2_code":"0.0",
    "gn:admin3_code":"16063.0",
    "gn:admin4_code":"16063003.0",
    "gn:asciiname":"Langenfeld",
    "gn:country_code":"DE",
    "gn:dem":306,
    "gn:feature_class":"P",
    "gn:feature_code":"PPL",
    "gn:name":"Langenfeld",
    "gn:population":0,
    "gn:timezone":"Europe/Berlin",
    "iso:country":"DE",
    "name:ceb_x_preferred":[
        "Langenfeld"
    ],
    "name:dan_x_preferred":[
        "Langenfeld"
    ],
    "name:deu_x_preferred":[
        "Langenfeld"
    ],
    "name:epo_x_preferred":[
        "Langenfeld"
    ],
    "name:fra_x_preferred":[
        "Langenfeld"
    ],
    "name:ita_x_preferred":[
        "Langenfeld"
    ],
    "name:kor_x_preferred":[
        "\ub791\uc5d4\ud3a0\ud2b8"
    ],
    "name:nds_x_preferred":[
        "Langenfeld"
    ],
    "name:nld_x_preferred":[
        "Langenfeld"
    ],
    "name:pol_x_preferred":[
        "Langenfeld"
    ],
    "name:rus_x_preferred":[
        "\u041b\u0430\u043d\u0433\u0435\u043d\u0444\u0435\u043b\u044c\u0434"
    ],
    "name:sco_x_preferred":[
        "Langenfeld"
    ],
    "name:spa_x_preferred":[
        "Langenfeld"
    ],
    "name:srp_x_preferred":[
        "\u041b\u0430\u043d\u0433\u0435\u043d\u0444\u0435\u043b\u0434"
    ],
    "name:swe_x_preferred":[
        "Langenfeld"
    ],
    "name:vol_x_preferred":[
        "Langenfeld"
    ],
    "name:zho_x_preferred":[
        "\u5170\u6839\u8d39\u5c14\u5fb7"
    ],
    "wof:name":"Langenfeld",
    "wof:placetype":"neighbourhood"
},
  "geometry": {"coordinates":[10.21018,50.79076],"type":"Point"}
}