{
  "type": "Feature",
  "properties": {
    "gn:admin1_code":"2.0",
    "gn:admin2_code":"92.0",
    "gn:admin3_code":"9275.0",
    "gn:admin4_code":"9275132.0",
    "gn:asciiname":"Biberg",
    "gn:country_code":"DE",
    "gn:dem":331,
    "gn:feature_class":"P",
    "gn:feature_code":"PPL",
    "gn:name":"Biberg",
    "gn:population":0,
    "gn:timezone":"Europe/Berlin",
    "iso:country":"DE",
    "name:deu_x_preferred":[
        "Biberg"
    ],
    "name:fas_x_preferred":[
        "\u0628\u06cc\u0628\u0631\u06af"
    ],
    "wof:name":"Biberg",
    "wof:placetype":"neighbourhood"
},
  "geometry": {"coordinates":[13.20333,48.30267],"type":"Point"}
}