{
  "type": "Feature",
  "properties": {
    "gn:admin1_code":"2",
    "gn:admin2_code":"92.0",
    "gn:admin3_code":"9277.0",
    "gn:admin4_code":"9277154.0",
    "gn:asciiname":"Dambach",
    "gn:country_code":"DE",
    "gn:dem":448,
    "gn:feature_class":"P",
    "gn:feature_code":"PPL",
    "gn:name":"Dambach",
    "gn:population":0,
    "gn:timezone":"Europe/Berlin",
    "iso:country":"DE",
    "name:cat_x_preferred":[
        "Dambach"
    ],
    "name:ceb_x_preferred":[
        "Dambach"
    ],
    "name:deu_x_preferred":[
        "Dambach"
    ],
    "name:fra_x_preferred":[
        "Dambach"
    ],
    "name:ita_x_preferred":[
        "Dambach"
    ],
    "name:nld_x_preferred":[
        "Dambach"
    ],
    "name:pol_x_preferred":[
        "Dambach"
    ],
    "name:por_x_preferred":[
        "Dambach"
    ],
    "name:swe_x_preferred":[
        "Dambach"
    ],
    "name:vol_x_preferred":[
        "Dambach"
    ],
    "wof:name":"Dambach",
    "wof:placetype":"neighbourhood"
},
  "geometry": {"coordinates":[12.88026,48.28793],"type":"Point"}
}