{
  "type": "Feature",
  "properties": {
    "gn:admin1_code":"7",
    "gn:admin2_code":"57.0",
    "gn:admin3_code":"5770.0",
    "gn:admin4_code":"5770016.0",
    "gn:asciiname":"Buettendorf",
    "gn:country_code":"DE",
    "gn:dem":113,
    "gn:feature_class":"P",
    "gn:feature_code":"PPL",
    "gn:name":"B\u00fcttendorf",
    "gn:population":0,
    "gn:timezone":"Europe/Berlin",
    "iso:country":"DE",
    "name:osx_x_preferred":[
        "Buttingthorp"
    ],
    "wof:name":"Buettendorf",
    "wof:placetype":"neighbourhood"
},
  "geometry": {"coordinates":[8.65311,52.26122],"type":"Point"}
}