{
  "type": "Feature",
  "properties": {
    "gn:admin1_code":"13",
    "gn:admin2_code":"0.0",
    "gn:admin3_code":"14627.0",
    "gn:admin4_code":"14627270.0",
    "gn:asciiname":"Kleinruegeln",
    "gn:country_code":"DE",
    "gn:dem":116,
    "gn:feature_class":"P",
    "gn:feature_code":"PPL",
    "gn:name":"Kleinr\u00fcgeln",
    "gn:population":0,
    "gn:timezone":"Europe/Berlin",
    "iso:country":"DE",
    "wof:name":"Kleinruegeln",
    "wof:placetype":"neighbourhood"
},
  "geometry": {"coordinates":[13.21901,51.34856],"type":"Point"}
}