{
  "type": "Feature",
  "properties": {
    "gn:admin1_code":"2.0",
    "gn:admin2_code":"93.0",
    "gn:admin3_code":"9375.0",
    "gn:admin4_code":"9375148.0",
    "gn:asciiname":"Pittmannsdorf",
    "gn:country_code":"DE",
    "gn:dem":473,
    "gn:feature_class":"P",
    "gn:feature_code":"PPL",
    "gn:name":"Pittmannsdorf",
    "gn:population":0,
    "gn:timezone":"Europe/Berlin",
    "iso:country":"DE",
    "name:und_x_variant":[
        "Bittmannsdorf",
        "Pittmannsdorf"
    ],
    "wof:name":"Pittmannsdorf",
    "wof:placetype":"neighbourhood"
},
  "geometry": {"coordinates":[11.87673,49.03674],"type":"Point"}
}