{
  "type": "Feature",
  "properties": {
    "gn:admin1_code":"7",
    "gn:admin2_code":"59.0",
    "gn:admin3_code":"5966.0",
    "gn:admin4_code":"5966024.0",
    "gn:asciiname":"Rhode",
    "gn:country_code":"DE",
    "gn:dem":416,
    "gn:feature_class":"P",
    "gn:feature_code":"PPL",
    "gn:name":"Rhode",
    "gn:population":0,
    "gn:timezone":"Europe/Berlin",
    "iso:country":"DE",
    "name:deu_x_preferred":[
        "Rhode"
    ],
    "name:fra_x_preferred":[
        "Rhode"
    ],
    "name:ita_x_preferred":[
        "Rhode"
    ],
    "name:lat_x_preferred":[
        "Rhode"
    ],
    "name:nds_x_preferred":[
        "Rhode"
    ],
    "name:nld_x_preferred":[
        "Rhode"
    ],
    "name:pol_x_preferred":[
        "Rhode"
    ],
    "name:swe_x_preferred":[
        "Rhode"
    ],
    "name:vie_x_preferred":[
        "Rhode"
    ],
    "wof:name":"Rhode",
    "wof:placetype":"neighbourhood"
},
  "geometry": {"coordinates":[7.86275,51.05025],"type":"Point"}
}