{
  "type": "Feature",
  "properties": {
    "gn:admin1_code":"2",
    "gn:admin2_code":"94.0",
    "gn:admin3_code":"9471.0",
    "gn:admin4_code":"9471191.0",
    "gn:asciiname":"Hofen",
    "gn:country_code":"DE",
    "gn:dem":262,
    "gn:feature_class":"P",
    "gn:feature_code":"PPL",
    "gn:name":"H\u00f6fen",
    "gn:population":0,
    "gn:timezone":"Europe/Berlin",
    "iso:country":"DE",
    "wof:name":"Hofen",
    "wof:placetype":"neighbourhood"
},
  "geometry": {"coordinates":[10.89363,49.84651],"type":"Point"}
}