{
  "type": "Feature",
  "properties": {
    "gn:admin1_code":"2",
    "gn:admin2_code":"96.0",
    "gn:admin3_code":"9674.0",
    "gn:admin4_code":"9674139.0",
    "gn:asciiname":"Gresshausen",
    "gn:country_code":"DE",
    "gn:dem":304,
    "gn:feature_class":"P",
    "gn:feature_code":"PPL",
    "gn:name":"Gre\u00dfhausen",
    "gn:population":0,
    "gn:timezone":"Europe/Berlin",
    "iso:country":"DE",
    "wof:name":"Gresshausen",
    "wof:placetype":"neighbourhood"
},
  "geometry": {"coordinates":[10.38348,50.03539],"type":"Point"}
}