{
  "type": "Feature",
  "properties": {
    "gn:admin1_code":"2",
    "gn:admin2_code":"94.0",
    "gn:admin3_code":"9471.0",
    "gn:admin4_code":"9471209.0",
    "gn:asciiname":"Schneeberg",
    "gn:country_code":"DE",
    "gn:dem":484,
    "gn:feature_class":"P",
    "gn:feature_code":"PPL",
    "gn:name":"Schneeberg",
    "gn:population":0,
    "gn:timezone":"Europe/Berlin",
    "iso:country":"DE",
    "wof:name":"Schneeberg",
    "wof:placetype":"neighbourhood"
},
  "geometry": {"coordinates":[11.10306,50.0223],"type":"Point"}
}