{
  "type": "Feature",
  "properties": {
    "gn:admin1_code":"2.0",
    "gn:admin2_code":"091",
    "gn:admin3_code":"9175.0",
    "gn:admin4_code":"9175137.0",
    "gn:asciiname":"Zaissing",
    "gn:country_code":"DE",
    "gn:dem":550,
    "gn:feature_class":"P",
    "gn:feature_code":"PPL",
    "gn:name":"Zai\u00dfing",
    "gn:population":0,
    "gn:timezone":"Europe/Berlin",
    "iso:country":"DE",
    "wof:name":"Zaissing",
    "wof:placetype":"neighbourhood"
},
  "geometry": {"coordinates":[12.02552,48.10973],"type":"Point"}
}