{
  "type": "Feature",
  "properties": {
    "gn:admin1_code":"6",
    "gn:admin2_code":"0.0",
    "gn:admin3_code":"3353.0",
    "gn:admin4_code":"3353035.0",
    "gn:asciiname":"Lohbergen",
    "gn:country_code":"DE",
    "gn:dem":50,
    "gn:feature_class":"P",
    "gn:feature_code":"PPL",
    "gn:name":"Lohbergen",
    "gn:population":0,
    "gn:timezone":"Europe/Berlin",
    "iso:country":"DE",
    "wof:name":"Lohbergen",
    "wof:placetype":"neighbourhood"
},
  "geometry": {"coordinates":[9.79208,53.29005],"type":"Point"}
}