{
  "type": "Feature",
  "properties": {
    "gn:admin1_code":"2",
    "gn:admin2_code":"92.0",
    "gn:admin3_code":"9277.0",
    "gn:admin4_code":"9277153.0",
    "gn:asciiname":"Strass",
    "gn:country_code":"DE",
    "gn:dem":474,
    "gn:feature_class":"P",
    "gn:feature_code":"PPL",
    "gn:name":"Stra\u00df",
    "gn:population":0,
    "gn:timezone":"Europe/Berlin",
    "iso:country":"DE",
    "name:deu_x_preferred":[
        "Strass"
    ],
    "name:fra_x_preferred":[
        "Strass"
    ],
    "name:ita_x_preferred":[
        "Strass"
    ],
    "name:nld_x_preferred":[
        "Strass"
    ],
    "name:pol_x_preferred":[
        "Strass"
    ],
    "name:rus_x_preferred":[
        "\u0428\u0442\u0440\u0430\u0441"
    ],
    "wof:name":"Strass",
    "wof:placetype":"neighbourhood"
},
  "geometry": {"coordinates":[12.78895,48.36141],"type":"Point"}
}