{
  "type": "Feature",
  "properties": {
    "gn:admin1_code":"2",
    "gn:admin2_code":"93.0",
    "gn:admin3_code":"9372.0",
    "gn:admin4_code":"9372157.0",
    "gn:asciiname":"Lixendofering",
    "gn:country_code":"DE",
    "gn:dem":460,
    "gn:feature_class":"P",
    "gn:feature_code":"PPL",
    "gn:name":"Lixend\u00f6fering",
    "gn:population":0,
    "gn:timezone":"Europe/Berlin",
    "iso:country":"DE",
    "wof:name":"Lixendofering",
    "wof:placetype":"neighbourhood"
},
  "geometry": {"coordinates":[12.62644,49.33249],"type":"Point"}
}