{
  "type": "Feature",
  "properties": {
    "gn:admin1_code":"1.0",
    "gn:admin2_code":"83.0",
    "gn:admin3_code":"8325.0",
    "gn:admin4_code":"8325001.0",
    "gn:asciiname":"Bach und Altenberg",
    "gn:country_code":"DE",
    "gn:dem":544,
    "gn:feature_class":"P",
    "gn:feature_code":"PPL",
    "gn:name":"Bach und Altenberg",
    "gn:population":0,
    "gn:timezone":"Europe/Berlin",
    "iso:country":"DE",
    "wof:name":"Bach und Altenberg",
    "wof:placetype":"neighbourhood"
},
  "geometry": {"coordinates":[8.43333,48.31667],"type":"Point"}
}