{
  "type": "Feature",
  "properties": {
    "gn:admin1_code":"2",
    "gn:admin2_code":"92.0",
    "gn:admin3_code":"9276.0",
    "gn:admin4_code":"9276116.0",
    "gn:asciiname":"Ritzmais",
    "gn:country_code":"DE",
    "gn:dem":671,
    "gn:feature_class":"P",
    "gn:feature_code":"PPL",
    "gn:name":"Ritzmais",
    "gn:population":0,
    "gn:timezone":"Europe/Berlin",
    "iso:country":"DE",
    "wof:name":"Ritzmais",
    "wof:placetype":"neighbourhood"
},
  "geometry": {"coordinates":[13.09244,48.90744],"type":"Point"}
}