{
  "type": "Feature",
  "properties": {
    "gn:admin1_code":"11",
    "gn:admin2_code":"0.0",
    "gn:admin3_code":"12067.0",
    "gn:admin4_code":"12067426.0",
    "gn:asciiname":"Goerzig",
    "gn:country_code":"DE",
    "gn:dem":68,
    "gn:feature_class":"P",
    "gn:feature_code":"PPL",
    "gn:name":"G\u00f6rzig",
    "gn:population":0,
    "gn:timezone":"Europe/Berlin",
    "iso:country":"DE",
    "wof:name":"Goerzig",
    "wof:placetype":"neighbourhood"
},
  "geometry": {"coordinates":[14.20173,52.23918],"type":"Point"}
}