{
  "type": "Feature",
  "properties": {
    "gn:admin1_code":"1",
    "gn:admin2_code":"83.0",
    "gn:admin3_code":"8326.0",
    "gn:admin4_code":"8326068.0",
    "gn:asciiname":"Fuchsloch",
    "gn:country_code":"DE",
    "gn:dem":893,
    "gn:feature_class":"P",
    "gn:feature_code":"PPL",
    "gn:name":"Fuchsloch",
    "gn:population":0,
    "gn:timezone":"Europe/Berlin",
    "iso:country":"DE",
    "wof:name":"Fuchsloch",
    "wof:placetype":"neighbourhood"
},
  "geometry": {"coordinates":[8.27162,48.0234],"type":"Point"}
}