{
  "type": "Feature",
  "properties": {
    "gn:admin1_code":"2",
    "gn:admin2_code":"97.0",
    "gn:admin3_code":"9762.0",
    "gn:admin4_code":"9762000.0",
    "gn:asciiname":"Marzisried",
    "gn:country_code":"DE",
    "gn:dem":729,
    "gn:feature_class":"P",
    "gn:feature_code":"PPL",
    "gn:name":"M\u00e4rzisried",
    "gn:population":0,
    "gn:timezone":"Europe/Berlin",
    "iso:country":"DE",
    "wof:name":"Marzisried",
    "wof:placetype":"neighbourhood"
},
  "geometry": {"coordinates":[10.59675,47.85708],"type":"Point"}
}