{
  "type": "Feature",
  "properties": {
    "gn:admin1_code":"11",
    "gn:admin2_code":"0.0",
    "gn:admin3_code":"12071.0",
    "gn:admin4_code":"12071244.0",
    "gn:asciiname":"Haenchen",
    "gn:country_code":"DE",
    "gn:dem":68,
    "gn:feature_class":"P",
    "gn:feature_code":"PPL",
    "gn:name":"H\u00e4nchen",
    "gn:population":0,
    "gn:timezone":"Europe/Berlin",
    "iso:country":"DE",
    "wof:name":"Haenchen",
    "wof:placetype":"neighbourhood"
},
  "geometry": {"coordinates":[14.27351,51.72552],"type":"Point"}
}