{
  "type": "Feature",
  "properties": {
    "gn:admin1_code":"2",
    "gn:admin2_code":"92.0",
    "gn:admin3_code":"9278.0",
    "gn:admin4_code":"9278192.0",
    "gn:asciiname":"Paitzkofen",
    "gn:country_code":"DE",
    "gn:dem":335,
    "gn:feature_class":"P",
    "gn:feature_code":"PPL",
    "gn:name":"Paitzkofen",
    "gn:population":0,
    "gn:timezone":"Europe/Berlin",
    "iso:country":"DE",
    "wof:name":"Paitzkofen",
    "wof:placetype":"neighbourhood"
},
  "geometry": {"coordinates":[12.70766,48.80918],"type":"Point"}
}