{
  "type": "Feature",
  "properties": {
    "gn:admin1_code":"2",
    "gn:admin2_code":"91.0",
    "gn:admin3_code":"9186.0",
    "gn:admin4_code":"9186128.0",
    "gn:asciiname":"Seibersdorf",
    "gn:country_code":"DE",
    "gn:dem":441,
    "gn:feature_class":"P",
    "gn:feature_code":"PPL",
    "gn:name":"Seibersdorf",
    "gn:population":0,
    "gn:timezone":"Europe/Berlin",
    "iso:country":"DE",
    "name:ceb_x_preferred":[
        "Seibersdorf"
    ],
    "name:deu_x_preferred":[
        "Seibersdorf"
    ],
    "name:epo_x_preferred":[
        "Seibersdorf"
    ],
    "name:fas_x_preferred":[
        "\u0633\u0627\u06cc\u0628\u0631\u0633\u062f\u0648\u0631\u0641"
    ],
    "name:fra_x_preferred":[
        "Seibersdorf"
    ],
    "name:hun_x_preferred":[
        "Seibersdorf"
    ],
    "name:ile_x_preferred":[
        "Seibersdorf"
    ],
    "name:ind_x_preferred":[
        "Seibersdorf"
    ],
    "name:ita_x_preferred":[
        "Seibersdorf"
    ],
    "name:kaz_x_preferred":[
        "\u0417\u0430\u0439\u0431\u0435\u0440\u0441\u0434\u043e\u0440\u0444"
    ],
    "name:nld_x_preferred":[
        "Seibersdorf"
    ],
    "name:pol_x_preferred":[
        "Seibersdorf"
    ],
    "name:por_x_preferred":[
        "Seibersdorf"
    ],
    "name:rus_x_preferred":[
        "\u0417\u0430\u0439\u0431\u0435\u0440\u0441\u0434\u043e\u0440\u0444"
    ],
    "name:slk_x_preferred":[
        "Seibersdorf"
    ],
    "name:spa_x_preferred":[
        "Seibersdorf"
    ],
    "name:swe_x_preferred":[
        "Seibersdorf"
    ],
    "name:uzb_x_preferred":[
        "Seibersdorf"
    ],
    "name:vie_x_preferred":[
        "Seibersdorf"
    ],
    "name:vol_x_preferred":[
        "Seibersdorf"
    ],
    "name:war_x_preferred":[
        "Seibersdorf"
    ],
    "name:zho_x_preferred":[
        "\u8d5b\u4f2f\u5c14\u65af\u591a\u592b"
    ],
    "wof:name":"Seibersdorf",
    "wof:placetype":"neighbourhood"
},
  "geometry": {"coordinates":[11.39986,48.57008],"type":"Point"}
}