{
  "type": "Feature",
  "properties": {
    "gn:admin1_code":"13",
    "gn:admin2_code":"0.0",
    "gn:admin3_code":"14628.0",
    "gn:admin4_code":"14628340.0",
    "gn:asciiname":"Reichstein",
    "gn:country_code":"DE",
    "gn:dem":292,
    "gn:feature_class":"P",
    "gn:feature_code":"PPL",
    "gn:name":"Reichstein",
    "gn:population":0,
    "gn:timezone":"Europe/Berlin",
    "iso:country":"DE",
    "wof:name":"Reichstein",
    "wof:placetype":"neighbourhood"
},
  "geometry": {"coordinates":[14.04679,50.87786],"type":"Point"}
}