{
  "type": "Feature",
  "properties": {
    "gn:admin1_code":"7.0",
    "gn:admin2_code":"059",
    "gn:admin3_code":"5974.0",
    "gn:admin4_code":"5974016.0",
    "gn:asciiname":"Wiggeringhausen",
    "gn:country_code":"DE",
    "gn:dem":88,
    "gn:feature_class":"P",
    "gn:feature_code":"PPL",
    "gn:name":"Wiggeringhausen",
    "gn:population":0,
    "gn:timezone":"Europe/Berlin",
    "iso:country":"DE",
    "wof:name":"Wiggeringhausen",
    "wof:placetype":"neighbourhood"
},
  "geometry": {"coordinates":[8.22752,51.62138],"type":"Point"}
}