{
  "type": "Feature",
  "properties": {
    "gn:admin1_code":"2",
    "gn:admin2_code":"93.0",
    "gn:admin3_code":"9373.0",
    "gn:admin4_code":"9373153.0",
    "gn:asciiname":"Habertshofen",
    "gn:country_code":"DE",
    "gn:dem":522,
    "gn:feature_class":"P",
    "gn:feature_code":"PPL",
    "gn:name":"Habertshofen",
    "gn:population":0,
    "gn:timezone":"Europe/Berlin",
    "iso:country":"DE",
    "wof:name":"Habertshofen",
    "wof:placetype":"neighbourhood"
},
  "geometry": {"coordinates":[11.59212,49.29255],"type":"Point"}
}