{
  "type": "Feature",
  "properties": {
    "gn:admin1_code":"7",
    "gn:admin2_code":"53.0",
    "gn:admin3_code":"5378.0",
    "gn:admin4_code":"5378004.0",
    "gn:asciiname":"Lueckerath",
    "gn:country_code":"DE",
    "gn:dem":119,
    "gn:feature_class":"P",
    "gn:feature_code":"PPL",
    "gn:name":"L\u00fcckerath",
    "gn:population":0,
    "gn:timezone":"Europe/Berlin",
    "iso:country":"DE",
    "wof:name":"Lueckerath",
    "wof:placetype":"neighbourhood"
},
  "geometry": {"coordinates":[7.14764,50.96751],"type":"Point"}
}