{
  "type": "Feature",
  "properties": {
    "gn:admin1_code":"2",
    "gn:admin2_code":"93.0",
    "gn:admin3_code":"9371.0",
    "gn:admin4_code":"9371116.0",
    "gn:asciiname":"Eckertsfeld",
    "gn:country_code":"DE",
    "gn:dem":563,
    "gn:feature_class":"P",
    "gn:feature_code":"PPL",
    "gn:name":"Eckertsfeld",
    "gn:population":0,
    "gn:timezone":"Europe/Berlin",
    "iso:country":"DE",
    "wof:name":"Eckertsfeld",
    "wof:placetype":"neighbourhood"
},
  "geometry": {"coordinates":[11.64027,49.44715],"type":"Point"}
}