{
  "type": "Feature",
  "properties": {
    "gn:admin1_code":"7.0",
    "gn:admin2_code":"051",
    "gn:admin3_code":"5162.0",
    "gn:admin4_code":"5162008.0",
    "gn:asciiname":"Wevelinghoven",
    "gn:country_code":"DE",
    "gn:dem":55,
    "gn:feature_class":"P",
    "gn:feature_code":"PPL",
    "gn:name":"Wevelinghoven",
    "gn:population":0,
    "gn:timezone":"Europe/Berlin",
    "iso:country":"DE",
    "wof:name":"Wevelinghoven",
    "wof:placetype":"neighbourhood"
},
  "geometry": {"coordinates":[6.62236,51.10583],"type":"Point"}
}