{
  "type": "Feature",
  "properties": {
    "gn:admin1_code":"2.0",
    "gn:admin2_code":"91.0",
    "gn:admin3_code":"9178.0",
    "gn:admin4_code":"9178156.0",
    "gn:asciiname":"Badendorf",
    "gn:country_code":"DE",
    "gn:dem":479,
    "gn:feature_class":"P",
    "gn:feature_code":"PPL",
    "gn:name":"Badendorf",
    "gn:population":0,
    "gn:timezone":"Europe/Berlin",
    "iso:country":"DE",
    "name:ceb_x_preferred":[
        "Badendorf"
    ],
    "name:dan_x_preferred":[
        "Badendorf"
    ],
    "name:deu_x_preferred":[
        "Badendorf"
    ],
    "name:epo_x_preferred":[
        "Badendorf"
    ],
    "name:eus_x_preferred":[
        "Badendorf"
    ],
    "name:fas_x_preferred":[
        "\u0628\u0627\u062f\u0646\u062f\u0648\u0631\u0641"
    ],
    "name:fra_x_preferred":[
        "Badendorf"
    ],
    "name:hun_x_preferred":[
        "Badendorf"
    ],
    "name:ita_x_preferred":[
        "Badendorf"
    ],
    "name:mkd_x_preferred":[
        "\u0411\u0430\u0434\u0435\u043d\u0434\u043e\u0440\u0444"
    ],
    "name:msa_x_preferred":[
        "Badendorf"
    ],
    "name:nld_x_preferred":[
        "Badendorf"
    ],
    "name:pol_x_preferred":[
        "Badendorf"
    ],
    "name:por_x_preferred":[
        "Badendorf"
    ],
    "name:ron_x_preferred":[
        "Badendorf"
    ],
    "name:rus_x_preferred":[
        "\u0411\u0430\u0434\u0435\u043d\u0434\u043e\u0440\u0444"
    ],
    "name:spa_x_preferred":[
        "Badendorf"
    ],
    "name:srp_x_preferred":[
        "\u0411\u0430\u0434\u0435\u043d\u0434\u043e\u0440\u0444"
    ],
    "name:tur_x_preferred":[
        "Badendorf"
    ],
    "name:ukr_x_preferred":[
        "\u0411\u0430\u0434\u0435\u043d\u0434\u043e\u0440\u0444"
    ],
    "name:uzb_x_preferred":[
        "Badendorf"
    ],
    "name:vie_x_preferred":[
        "Badendorf"
    ],
    "name:vol_x_preferred":[
        "Badendorf"
    ],
    "name:war_x_preferred":[
        "Badendorf"
    ],
    "name:zho_x_preferred":[
        "\u5df4\u767b\u591a\u592b"
    ],
    "wof:name":"Badendorf",
    "wof:placetype":"neighbourhood"
},
  "geometry": {"coordinates":[11.72264,48.50525],"type":"Point"}
}