{
  "type": "Feature",
  "properties": {
    "gn:admin1_code":"15",
    "gn:admin2_code":"0.0",
    "gn:admin3_code":"16052.0",
    "gn:admin4_code":"16052000.0",
    "gn:asciiname":"Poris-Lengefeld",
    "gn:country_code":"DE",
    "gn:dem":280,
    "gn:feature_class":"P",
    "gn:feature_code":"PPL",
    "gn:name":"Poris-Lengefeld",
    "gn:population":0,
    "gn:timezone":"Europe/Berlin",
    "iso:country":"DE",
    "name:und_x_variant":[
        "Lengefeld",
        "Poris-Lengefeld"
    ],
    "wof:name":"Poris-Lengefeld",
    "wof:placetype":"neighbourhood"
},
  "geometry": {"coordinates":[12.11899,50.83656],"type":"Point"}
}