{
  "type": "Feature",
  "properties": {
    "gn:admin1_code":"1",
    "gn:admin2_code":"83.0",
    "gn:admin3_code":"8325.0",
    "gn:admin4_code":"8325045.0",
    "gn:asciiname":"Hochmossingen",
    "gn:country_code":"DE",
    "gn:dem":685,
    "gn:feature_class":"P",
    "gn:feature_code":"PPL",
    "gn:name":"Hochm\u00f6ssingen",
    "gn:population":0,
    "gn:timezone":"Europe/Berlin",
    "iso:country":"DE",
    "wof:name":"Hochmossingen",
    "wof:placetype":"neighbourhood"
},
  "geometry": {"coordinates":[8.53506,48.31177],"type":"Point"}
}