{
  "type": "Feature",
  "properties": {
    "gn:country":"DE",
    "gn:fcode":"PPL",
    "gn:population":0,
    "iso:country":"DE",
    "name:ceb_x_preferred":[
        "Lauterbach"
    ],
    "name:chv_x_preferred":[
        "\u041b\u0430\u0443\u0442\u0435\u0440\u0431\u0430\u0445"
    ],
    "name:deu_x_preferred":[
        "Lauterbach"
    ],
    "name:epo_x_preferred":[
        "Lauterbach"
    ],
    "name:fra_x_preferred":[
        "Lauterbach"
    ],
    "name:heb_x_preferred":[
        "\u05dc\u05d5\u05d9\u05d8\u05e8\u05d1\u05da"
    ],
    "name:hun_x_preferred":[
        "Lauterbach"
    ],
    "name:ita_x_preferred":[
        "Lauterbach"
    ],
    "name:jpn_x_preferred":[
        "\u30e9\u30a6\u30bf\u30fc\u30d0\u30c3\u30cf"
    ],
    "name:nld_x_preferred":[
        "Lauterbach"
    ],
    "name:nor_x_preferred":[
        "Lauterbach"
    ],
    "name:pol_x_preferred":[
        "Lauterbach"
    ],
    "name:ron_x_preferred":[
        "Lauterbach"
    ],
    "name:rus_x_preferred":[
        "\u041b\u0430\u0443\u0442\u0435\u0440\u0431\u0430\u0445"
    ],
    "name:srp_x_preferred":[
        "\u041b\u0430\u0443\u0442\u0435\u0440\u0431\u0430\u0445"
    ],
    "name:swe_x_preferred":[
        "Lauterbach"
    ],
    "name:und_x_variant":[
        "Lauterbach R\u00fcgen"
    ],
    "name:vol_x_preferred":[
        "Lauterbach"
    ],
    "qs_pg:aaroncc":"DE",
    "qs_pg:gn_country":"DE",
    "qs_pg:gn_fcode":"PPL",
    "qs_pg:gn_pop":0,
    "qs_pg:name":"Lauterbach",
    "qs_pg:name_adm0":"Deutschland",
    "qs_pg:name_adm1":"Mecklenburg-Vorpommern",
    "qs_pg:photos":78,
    "qs_pg:photos_1k":16,
    "qs_pg:photos_9k":1,
    "qs_pg:photos_9r":3,
    "qs_pg:photos_all":78,
    "qs_pg:photos_sr":3,
    "qs_pg:pop_sr":0,
    "qs_pg:qs_pg_placetype":"locality",
    "qs_pg:qs_pg_placetype_gp":"Town",
    "qs_pg:woe_adm0":23424829,
    "woe:adm0_id":23424829,
    "woe:name_adm0":"Deutschland",
    "woe:name_adm1":"Mecklenburg-Vorpommern",
    "woe:placetype":"Town",
    "wof:name":"Lauterbach",
    "wof:placetype":"neighbourhood"
},
  "geometry": {"coordinates":[13.49934,54.34387],"type":"Point"}
}