{
  "type": "Feature",
  "properties": {
    "gn:admin1_code":"1.0",
    "gn:admin2_code":"082",
    "gn:admin3_code":"8237.0",
    "gn:admin4_code":"8237002.0",
    "gn:asciiname":"Zelleracker",
    "gn:country_code":"DE",
    "gn:dem":668,
    "gn:feature_class":"P",
    "gn:feature_code":"PPL",
    "gn:name":"Zelleracker",
    "gn:population":0,
    "gn:timezone":"Europe/Berlin",
    "iso:country":"DE",
    "wof:name":"Zelleracker",
    "wof:placetype":"neighbourhood"
},
  "geometry": {"coordinates":[8.4614,48.33151],"type":"Point"}
}