{
  "type": "Feature",
  "properties": {
    "gn:admin1_code":"1",
    "gn:admin2_code":"84.0",
    "gn:admin3_code":"8435.0",
    "gn:admin4_code":"8435020.0",
    "gn:asciiname":"Heiligenholz",
    "gn:country_code":"DE",
    "gn:dem":727,
    "gn:feature_class":"P",
    "gn:feature_code":"PPL",
    "gn:name":"Heiligenholz",
    "gn:population":0,
    "gn:timezone":"Europe/Berlin",
    "iso:country":"DE",
    "wof:name":"Heiligenholz",
    "wof:placetype":"neighbourhood"
},
  "geometry": {"coordinates":[9.26558,47.85343],"type":"Point"}
}