{
  "type": "Feature",
  "properties": {
    "gn:country":"DE",
    "gn:fcode":"PPL",
    "gn:population":0,
    "iso:country":"DE",
    "name:ceb_x_preferred":[
        "Holzen"
    ],
    "name:dan_x_preferred":[
        "Holzen"
    ],
    "name:deu_x_preferred":[
        "Holzen"
    ],
    "name:epo_x_preferred":[
        "Holzen"
    ],
    "name:est_x_preferred":[
        "Holzen"
    ],
    "name:eus_x_preferred":[
        "Holzen"
    ],
    "name:fas_x_preferred":[
        "\u0647\u0648\u0644\u062a\u0633\u0646"
    ],
    "name:fra_x_preferred":[
        "Holzen"
    ],
    "name:hun_x_preferred":[
        "Holzen"
    ],
    "name:ita_x_preferred":[
        "Holzen"
    ],
    "name:jpn_x_preferred":[
        "\u30db\u30eb\u30c4\u30a7\u30f3"
    ],
    "name:kaz_x_preferred":[
        "\u0425\u043e\u043b\u044c\u0446\u0435\u043d"
    ],
    "name:kir_x_preferred":[
        "\u0425\u043e\u043b\u044c\u0446\u0435\u043d"
    ],
    "name:lat_x_preferred":[
        "Holzen"
    ],
    "name:mkd_x_preferred":[
        "\u0425\u043e\u043b\u0446\u0435\u043d"
    ],
    "name:msa_x_preferred":[
        "Holzen"
    ],
    "name:nld_x_preferred":[
        "Holzen"
    ],
    "name:pol_x_preferred":[
        "Holzen"
    ],
    "name:por_x_preferred":[
        "Holzen"
    ],
    "name:ron_x_preferred":[
        "Holzen"
    ],
    "name:rus_x_preferred":[
        "\u0425\u043e\u043b\u044c\u0446\u0435\u043d"
    ],
    "name:spa_x_preferred":[
        "Holzen"
    ],
    "name:srp_x_preferred":[
        "\u0425\u043e\u043b\u0446\u0435\u043d"
    ],
    "name:ukr_x_preferred":[
        "\u0413\u043e\u043b\u044c\u0446\u0435\u043d"
    ],
    "name:uzb_x_preferred":[
        "Holzen"
    ],
    "name:vie_x_preferred":[
        "Holzen"
    ],
    "name:vol_x_preferred":[
        "Holzen"
    ],
    "name:war_x_preferred":[
        "Holzen"
    ],
    "name:zho_x_preferred":[
        "\u970d\u5c14\u5c91"
    ],
    "qs_pg:aaroncc":"DE",
    "qs_pg:gn_country":"DE",
    "qs_pg:gn_fcode":"PPL",
    "qs_pg:gn_pop":0,
    "qs_pg:name":"Holzen",
    "qs_pg:name_adm0":"Deutschland",
    "qs_pg:name_adm1":"Baden-W\u00fcrttemberg",
    "qs_pg:photos":73,
    "qs_pg:photos_1k":15,
    "qs_pg:photos_9k":1,
    "qs_pg:photos_9r":2,
    "qs_pg:photos_all":73,
    "qs_pg:photos_sr":2,
    "qs_pg:pop_sr":0,
    "qs_pg:qs_pg_placetype":"locality",
    "qs_pg:qs_pg_placetype_gp":"Town",
    "qs_pg:woe_adm0":23424829,
    "woe:adm0_id":23424829,
    "woe:name_adm0":"Deutschland",
    "woe:name_adm1":"Baden-W\u00fcrttemberg",
    "woe:placetype":"Town",
    "wof:name":"Holzen",
    "wof:placetype":"neighbourhood"
},
  "geometry": {"coordinates":[7.62648,47.69534],"type":"Point"}
}