{
  "type": "Feature",
  "properties": {
    "gn:admin1_code":"2",
    "gn:admin2_code":"91.0",
    "gn:admin3_code":"9189.0",
    "gn:admin4_code":"9189140.0",
    "gn:asciiname":"Vordermiesenbach",
    "gn:country_code":"DE",
    "gn:dem":692,
    "gn:feature_class":"P",
    "gn:feature_code":"PPL",
    "gn:name":"Vordermiesenbach",
    "gn:population":0,
    "gn:timezone":"Europe/Berlin",
    "iso:country":"DE",
    "name:und_x_variant":[
        "Miesenbach",
        "Vordermiesenbach"
    ],
    "wof:name":"Vordermiesenbach",
    "wof:placetype":"neighbourhood"
},
  "geometry": {"coordinates":[12.64913,47.77832],"type":"Point"}
}