{
  "type": "Feature",
  "properties": {
    "gn:admin1_code":"10",
    "gn:admin2_code":"0.0",
    "gn:admin3_code":"1054.0",
    "gn:admin4_code":"1054084.0",
    "gn:asciiname":"Rosendahl",
    "gn:country_code":"DE",
    "gn:dem":12,
    "gn:feature_class":"P",
    "gn:feature_code":"PPL",
    "gn:name":"Rosendahl",
    "gn:population":0,
    "gn:timezone":"Europe/Berlin",
    "iso:country":"DE",
    "name:ceb_x_preferred":[
        "Rosendahl"
    ],
    "name:deu_x_preferred":[
        "Rosendahl"
    ],
    "name:epo_x_preferred":[
        "Rosendahl"
    ],
    "name:eus_x_preferred":[
        "Rosendahl"
    ],
    "name:fra_x_preferred":[
        "Rosendahl"
    ],
    "name:hun_x_preferred":[
        "Rosendahl"
    ],
    "name:ita_x_preferred":[
        "Rosendahl"
    ],
    "name:kaz_x_preferred":[
        "\u0420\u043e\u0437\u0435\u043d\u0434\u0430\u043b\u044c"
    ],
    "name:kir_x_preferred":[
        "\u0420\u043e\u0437\u0435\u043d\u0434\u0430\u043b\u044c"
    ],
    "name:lim_x_preferred":[
        "Rosendahl"
    ],
    "name:lit_x_preferred":[
        "Rozendalis"
    ],
    "name:msa_x_preferred":[
        "Rosendahl"
    ],
    "name:nld_x_preferred":[
        "Rosendahl"
    ],
    "name:pol_x_preferred":[
        "Rosendahl"
    ],
    "name:por_x_preferred":[
        "Rosendahl"
    ],
    "name:ron_x_preferred":[
        "Rosendahl"
    ],
    "name:rus_x_preferred":[
        "\u0420\u043e\u0437\u0435\u043d\u0434\u0430\u043b\u044c"
    ],
    "name:spa_x_preferred":[
        "Rosendahl"
    ],
    "name:srp_x_preferred":[
        "\u0420\u043e\u0437\u0435\u043d\u0434\u0430\u043b"
    ],
    "name:ukr_x_preferred":[
        "\u0420\u043e\u0437\u0435\u043d\u0434\u0430\u043b\u044c"
    ],
    "name:uzb_x_preferred":[
        "Rosendahl"
    ],
    "name:vie_x_preferred":[
        "Rosendahl"
    ],
    "name:vol_x_preferred":[
        "Rosendahl"
    ],
    "name:war_x_preferred":[
        "Rosendahl"
    ],
    "name:zho_x_preferred":[
        "\u7f57\u68ee\u8fbe\u5c14"
    ],
    "wof:name":"Rosendahl",
    "wof:placetype":"neighbourhood"
},
  "geometry": {"coordinates":[9.10071,54.47776999999999],"type":"Point"}
}