{
  "type": "Feature",
  "properties": {
    "gn:admin1_code":"7",
    "gn:admin2_code":"57.0",
    "gn:admin3_code":"5770.0",
    "gn:admin4_code":"5770020.0",
    "gn:asciiname":"Eichholz",
    "gn:country_code":"DE",
    "gn:dem":50,
    "gn:feature_class":"P",
    "gn:feature_code":"PPL",
    "gn:name":"Eichholz",
    "gn:population":0,
    "gn:timezone":"Europe/Berlin",
    "iso:country":"DE",
    "name:und_x_variant":[
        "Eickholz",
        "Eichholz"
    ],
    "wof:name":"Eichholz",
    "wof:placetype":"neighbourhood"
},
  "geometry": {"coordinates":[8.66728,52.32596],"type":"Point"}
}