{
  "type": "Feature",
  "properties": {
    "gn:admin1_code":"2.0",
    "gn:admin2_code":"093",
    "gn:admin3_code":"9373.0",
    "gn:admin4_code":"9373153.0",
    "gn:asciiname":"Wunn",
    "gn:country_code":"DE",
    "gn:dem":496,
    "gn:feature_class":"P",
    "gn:feature_code":"PPL",
    "gn:name":"W\u00fcnn",
    "gn:population":0,
    "gn:timezone":"Europe/Berlin",
    "iso:country":"DE",
    "wof:name":"Wunn",
    "wof:placetype":"neighbourhood"
},
  "geometry": {"coordinates":[11.49788,49.34705],"type":"Point"}
}