{
  "type": "Feature",
  "properties": {
    "iso:country":"DE",
    "wof:name":"Hahnenfurth",
    "wof:placetype":"neighbourhood"
},
  "geometry": {"coordinates":[7.04225342541664,51.24894014003046],"type":"Point"}
}