{
  "type": "Feature",
  "properties": {
    "gn:admin1_code":"1",
    "gn:admin2_code":"84.0",
    "gn:admin3_code":"8417.0",
    "gn:admin4_code":"8417044.0",
    "gn:asciiname":"Heinstetten",
    "gn:country_code":"DE",
    "gn:dem":913,
    "gn:feature_class":"P",
    "gn:feature_code":"PPL",
    "gn:name":"Heinstetten",
    "gn:population":0,
    "gn:timezone":"Europe/Berlin",
    "iso:country":"DE",
    "wof:name":"Heinstetten",
    "wof:placetype":"neighbourhood"
},
  "geometry": {"coordinates":[8.96404,48.13515],"type":"Point"}
}