{
  "type": "Feature",
  "properties": {
    "gn:gn_country":"DE",
    "gn:gn_fcode":"PPL",
    "gn:gn_pop":331,
    "gn:population":331,
    "iso:country":"DE",
    "name:baq_x_preferred":[
        "Nister-M\u00f6hrendorf"
    ],
    "name:chi_x_preferred":[
        "\u5c3c\u65af\u7279\u5c14-\u9ed8\u8d6b\u4f26\u591a\u5c14\u592b"
    ],
    "name:dut_x_preferred":[
        "Nister-M\u00f6hrendorf"
    ],
    "name:eng_x_preferred":[
        "Nister-M\u00f6hrendorf"
    ],
    "name:epo_x_preferred":[
        "Nister-M\u00f6hrendorf"
    ],
    "name:fre_x_preferred":[
        "Nister-M\u00f6hrendorf"
    ],
    "name:ger_x_preferred":[
        "Nister-M\u00f6hrendorf"
    ],
    "name:hun_x_preferred":[
        "Nister-M\u00f6hrendorf"
    ],
    "name:ita_x_preferred":[
        "Nister-M\u00f6hrendorf"
    ],
    "name:jpn_x_preferred":[
        "\u30cb\u30b9\u30bf\u30fc\uff1d\u30e1\u30fc\u30ec\u30f3\u30c9\u30eb\u30d5"
    ],
    "name:may_x_preferred":[
        "Nister-M\u00f6hrendorf"
    ],
    "name:per_x_preferred":[
        "\u0646\u06cc\u0634\u062a\u0631-\u0645\u0648\u0647\u0631\u0646\u062f\u0648\u0631\u0641"
    ],
    "name:pol_x_preferred":[
        "Nister-M\u00f6hrendorf"
    ],
    "name:por_x_preferred":[
        "Nister-M\u00f6hrendorf"
    ],
    "name:rum_x_preferred":[
        "Nister-M\u00f6hrendorf"
    ],
    "name:rus_x_preferred":[
        "\u041d\u0438\u0441\u0442\u0435\u0440-\u041c\u0451\u0440\u0435\u043d\u0434\u043e\u0440\u0444"
    ],
    "name:srp_x_preferred":[
        "\u041d\u0438\u0441\u0442\u0435\u0440-\u041c\u0435\u0440\u0435\u043d\u0434\u043e\u0440\u0444"
    ],
    "name:ukr_x_preferred":[
        "\u041d\u0456\u0441\u0442\u0435\u0440-\u041c\u0435\u0440\u0435\u043d\u0434\u043e\u0440\u0444"
    ],
    "name:unk_x_variant":[
        "Nister M\u00f6hrendorf"
    ],
    "name:uzb_x_preferred":[
        "Nister-M\u00f6hrendorf"
    ],
    "name:vie_x_preferred":[
        "Nister-M\u00f6hrendorf"
    ],
    "name:vol_x_preferred":[
        "Nister-M\u00f6hrendorf"
    ],
    "name:war_x_preferred":[
        "Nister-M\u00f6hrendorf"
    ],
    "qs_pg:aaroncc":"DE",
    "qs_pg:gn_country":"DE",
    "qs_pg:gn_fcode":"PPL",
    "qs_pg:gn_pop":331,
    "qs_pg:name":"Nister-M\u00f6hrendorf",
    "qs_pg:name_adm0":"Deutschland",
    "qs_pg:name_adm1":"Rheinland-Pfalz",
    "qs_pg:photos_9k":1,
    "qs_pg:photos_9r":1,
    "qs_pg:photos_all":7,
    "qs_pg:photos_sr":0,
    "qs_pg:pop_sr":2,
    "qs_pg:qs_pg_placetype":"locality",
    "qs_pg:qs_pg_placetype_gp":"Town",
    "qs_pg:woe_adm0":23424829,
    "woe:adm0_id":23424829,
    "woe:name_adm0":"Deutschland",
    "woe:name_adm1":"Rheinland-Pfalz",
    "woe:placetype":"Town",
    "wof:name":"Nister-M\u00f6hrendorf",
    "wof:placetype":"locality",
    "wof:population":331
},
  "geometry": {"coordinates":[8.07764,50.65563],"type":"Point"}
}