{
  "type": "Feature",
  "properties": {
    "gn:admin1_code":"5",
    "gn:admin2_code":"65.0",
    "gn:admin3_code":"6532.0",
    "gn:admin4_code":"6532011.0",
    "gn:asciiname":"Rodenbach",
    "gn:country_code":"DE",
    "gn:dem":292,
    "gn:feature_class":"P",
    "gn:feature_code":"PPL",
    "gn:name":"Rodenbach",
    "gn:population":0,
    "gn:timezone":"Europe/Berlin",
    "iso:country":"DE",
    "name:ceb_x_preferred":[
        "Rodenbach"
    ],
    "name:deu_x_preferred":[
        "Rodenbach"
    ],
    "name:epo_x_preferred":[
        "Rodenbach"
    ],
    "name:fra_x_preferred":[
        "Rodenbach"
    ],
    "name:hun_x_preferred":[
        "Rodenbach"
    ],
    "name:ita_x_preferred":[
        "Rodenbach"
    ],
    "name:jpn_x_preferred":[
        "\u30ed\u30fc\u30c7\u30f3\u30d0\u30c3\u30cf"
    ],
    "name:nld_x_preferred":[
        "Rodenbach"
    ],
    "name:pol_x_preferred":[
        "Rodenbach"
    ],
    "name:rus_x_preferred":[
        "\u0420\u043e\u0434\u0435\u043d\u0431\u0430\u0445"
    ],
    "name:srp_x_preferred":[
        "\u0420\u043e\u0434\u0435\u043d\u0431\u0430\u0445"
    ],
    "name:vls_x_preferred":[
        "Rodenbach"
    ],
    "name:vol_x_preferred":[
        "Rodenbach"
    ],
    "wof:name":"Rodenbach",
    "wof:placetype":"neighbourhood"
},
  "geometry": {"coordinates":[8.20869,50.77197],"type":"Point"}
}