{
  "type": "Feature",
  "properties": {
    "gn:admin1_code":"14",
    "gn:asciiname":"Breddin Abbau",
    "gn:country_code":"DE",
    "gn:dem":36,
    "gn:feature_class":"P",
    "gn:feature_code":"PPL",
    "gn:name":"Breddin Abbau",
    "gn:population":0,
    "gn:timezone":"Europe/Berlin",
    "iso:country":"DE",
    "wof:name":"Breddin Abbau",
    "wof:placetype":"neighbourhood"
},
  "geometry": {"coordinates":[12.21916,52.86107],"type":"Point"}
}