{
  "type": "Feature",
  "properties": {
    "gn:admin1_code":"10",
    "gn:admin2_code":"0.0",
    "gn:admin3_code":"1059.0",
    "gn:admin4_code":"1059183.0",
    "gn:asciiname":"Haurup",
    "gn:country_code":"DE",
    "gn:dem":33,
    "gn:feature_class":"P",
    "gn:feature_code":"PPL",
    "gn:name":"Haurup",
    "gn:population":0,
    "gn:timezone":"Europe/Berlin",
    "iso:country":"DE",
    "wof:name":"Haurup",
    "wof:placetype":"neighbourhood"
},
  "geometry": {"coordinates":[9.34554,54.72634],"type":"Point"}
}