{
  "type": "Feature",
  "properties": {
    "gn:admin1_code":"7",
    "gn:admin2_code":"53.0",
    "gn:admin3_code":"5382.0",
    "gn:admin4_code":"5382076.0",
    "gn:asciiname":"Elisenthal",
    "gn:country_code":"DE",
    "gn:dem":250,
    "gn:feature_class":"P",
    "gn:feature_code":"PPLL",
    "gn:name":"Elisenthal",
    "gn:population":0,
    "gn:timezone":"Europe/Berlin",
    "iso:country":"DE",
    "wof:name":"Elisenthal",
    "wof:placetype":"neighbourhood"
},
  "geometry": {"coordinates":[7.56667,50.81667],"type":"Point"}
}