{
  "type": "Feature",
  "properties": {
    "gn:admin1_code":"2",
    "gn:admin2_code":"91.0",
    "gn:admin3_code":"9183.0",
    "gn:admin4_code":"9183124.0",
    "gn:asciiname":"Maximilian",
    "gn:country_code":"DE",
    "gn:dem":401,
    "gn:feature_class":"P",
    "gn:feature_code":"PPL",
    "gn:name":"Maximilian",
    "gn:population":0,
    "gn:timezone":"Europe/Berlin",
    "iso:country":"DE",
    "name:aze_x_preferred":[
        "Maksimilian"
    ],
    "name:deu_x_preferred":[
        "Maximilian"
    ],
    "name:fas_x_preferred":[
        "\u0645\u0627\u06a9\u0633\u06cc\u0645\u06cc\u0644\u06cc\u0627\u0646"
    ],
    "name:fin_x_preferred":[
        "Maximilian"
    ],
    "name:swe_x_preferred":[
        "Maximilian"
    ],
    "wof:name":"Maximilian",
    "wof:placetype":"neighbourhood"
},
  "geometry": {"coordinates":[12.41232,48.18062000000001],"type":"Point"}
}