{
  "type": "Feature",
  "properties": {
    "gn:admin1_code":"2",
    "gn:admin2_code":"91.0",
    "gn:admin3_code":"9183.0",
    "gn:admin4_code":"9183130.0",
    "gn:asciiname":"Etzmanning",
    "gn:country_code":"DE",
    "gn:dem":456,
    "gn:feature_class":"P",
    "gn:feature_code":"PPL",
    "gn:name":"Etzmanning",
    "gn:population":0,
    "gn:timezone":"Europe/Berlin",
    "iso:country":"DE",
    "wof:name":"Etzmanning",
    "wof:placetype":"neighbourhood"
},
  "geometry": {"coordinates":[12.50671,48.31609],"type":"Point"}
}