{
  "type": "Feature",
  "properties": {
    "gn:admin1_code":"6",
    "gn:admin2_code":"0.0",
    "gn:admin3_code":"3251.0",
    "gn:admin4_code":"3251040.0",
    "gn:asciiname":"Doehrel",
    "gn:cc2":"DE",
    "gn:country_code":"DE",
    "gn:dem":43,
    "gn:feature_class":"P",
    "gn:feature_code":"PPL",
    "gn:name":"D\u00f6hrel",
    "gn:population":0,
    "gn:timezone":"Europe/Berlin",
    "iso:country":"DE",
    "name:und_x_variant":[
        "D\u00f6hrei"
    ],
    "wof:name":"Doehrel",
    "wof:placetype":"neighbourhood"
},
  "geometry": {"coordinates":[8.87712,52.68055],"type":"Point"}
}