{
  "type": "Feature",
  "properties": {
    "gn:admin1_code":"11.0",
    "gn:admin2_code":"0.0",
    "gn:admin3_code":"12060.0",
    "gn:admin4_code":"12060020.0",
    "gn:asciiname":"Waldfrieden",
    "gn:country_code":"DE",
    "gn:dem":77,
    "gn:feature_class":"P",
    "gn:feature_code":"PPL",
    "gn:name":"Waldfrieden",
    "gn:population":0,
    "gn:timezone":"Europe/Berlin",
    "iso:country":"DE",
    "wof:name":"Waldfrieden",
    "wof:placetype":"neighbourhood"
},
  "geometry": {"coordinates":[13.54451,52.69808],"type":"Point"}
}