{
  "type": "Feature",
  "properties": {
    "gn:admin1_code":"7",
    "gn:admin2_code":"57.0",
    "gn:admin3_code":"5770.0",
    "gn:admin4_code":"5770028.0",
    "gn:asciiname":"Feuerschicht",
    "gn:country_code":"DE",
    "gn:dem":52,
    "gn:feature_class":"P",
    "gn:feature_code":"PPL",
    "gn:name":"Feuerschicht",
    "gn:population":0,
    "gn:timezone":"Europe/Berlin",
    "iso:country":"DE",
    "wof:name":"Feuerschicht",
    "wof:placetype":"neighbourhood"
},
  "geometry": {"coordinates":[9.05796,52.40004],"type":"Point"}
}