{
  "type": "Feature",
  "properties": {
    "gn:admin1_code":"6",
    "gn:admin2_code":"0.0",
    "gn:admin3_code":"3352.0",
    "gn:admin4_code":"3352056.0",
    "gn:asciiname":"Voigtding",
    "gn:country_code":"DE",
    "gn:dem":-2,
    "gn:feature_class":"P",
    "gn:feature_code":"PPL",
    "gn:name":"Voigtding",
    "gn:population":0,
    "gn:timezone":"Europe/Berlin",
    "iso:country":"DE",
    "wof:name":"Voigtding",
    "wof:placetype":"neighbourhood"
},
  "geometry": {"coordinates":[9.0959,53.74822],"type":"Point"}
}