{
  "type": "Feature",
  "properties": {
    "gn:admin1_code":"15",
    "gn:admin2_code":"0.0",
    "gn:admin3_code":"16069.0",
    "gn:admin4_code":"16069043.0",
    "gn:asciiname":"Rappelsdorf",
    "gn:country_code":"DE",
    "gn:dem":357,
    "gn:feature_class":"P",
    "gn:feature_code":"PPL",
    "gn:name":"Rappelsdorf",
    "gn:population":0,
    "gn:timezone":"Europe/Berlin",
    "iso:country":"DE",
    "wof:name":"Rappelsdorf",
    "wof:placetype":"neighbourhood"
},
  "geometry": {"coordinates":[10.72245,50.49646],"type":"Point"}
}