{
  "type": "Feature",
  "properties": {
    "gn:admin1_code":"1",
    "gn:admin2_code":"81.0",
    "gn:admin3_code":"8127.0",
    "gn:admin4_code":"8127102.0",
    "gn:asciiname":"Rotlein",
    "gn:country_code":"DE",
    "gn:dem":496,
    "gn:feature_class":"P",
    "gn:feature_code":"PPL",
    "gn:name":"R\u00f6tlein",
    "gn:population":0,
    "gn:timezone":"Europe/Berlin",
    "iso:country":"DE",
    "wof:name":"Rotlein",
    "wof:placetype":"neighbourhood"
},
  "geometry": {"coordinates":[10.22113,49.0839],"type":"Point"}
}