{
  "type": "Feature",
  "properties": {
    "gn:admin1_code":"6",
    "gn:admin2_code":"0.0",
    "gn:admin3_code":"3451.0",
    "gn:admin4_code":"3451008.0",
    "gn:asciiname":"Hinterm Stratjebusch",
    "gn:country_code":"DE",
    "gn:dem":15,
    "gn:feature_class":"P",
    "gn:feature_code":"PPL",
    "gn:name":"Hinterm Stratjebusch",
    "gn:population":0,
    "gn:timezone":"Europe/Berlin",
    "iso:country":"DE",
    "wof:name":"Hinterm Stratjebusch",
    "wof:placetype":"neighbourhood"
},
  "geometry": {"coordinates":[8.16667,53.23333],"type":"Point"}
}