{
  "type": "Feature",
  "properties": {
    "gn:admin1_code":"7",
    "gn:admin2_code":"51.0",
    "gn:admin3_code":"5116.0",
    "gn:admin4_code":"5116000.0",
    "gn:asciiname":"Buchholz",
    "gn:country_code":"DE",
    "gn:dem":78,
    "gn:feature_class":"P",
    "gn:feature_code":"PPL",
    "gn:name":"Buchholz",
    "gn:population":0,
    "gn:timezone":"Europe/Berlin",
    "iso:country":"DE",
    "wof:name":"Buchholz",
    "wof:placetype":"neighbourhood"
},
  "geometry": {"coordinates":[6.35721,51.11714],"type":"Point"}
}