{
  "type": "Feature",
  "properties": {
    "gn:admin1_code":"6",
    "gn:admin2_code":"0.0",
    "gn:admin3_code":"3458.0",
    "gn:admin4_code":"3458010.0",
    "gn:asciiname":"Heiligenloh",
    "gn:country_code":"DE",
    "gn:dem":20,
    "gn:feature_class":"P",
    "gn:feature_code":"PPL",
    "gn:name":"Heiligenloh",
    "gn:population":0,
    "gn:timezone":"Europe/Berlin",
    "iso:country":"DE",
    "wof:name":"Heiligenloh",
    "wof:placetype":"neighbourhood"
},
  "geometry": {"coordinates":[8.40297,53.08824],"type":"Point"}
}