{
  "type": "Feature",
  "properties": {
    "gn:admin1_code":"2",
    "gn:admin2_code":"93.0",
    "gn:admin3_code":"9372.0",
    "gn:admin4_code":"9372115.0",
    "gn:asciiname":"Pulling",
    "gn:country_code":"DE",
    "gn:dem":388,
    "gn:feature_class":"P",
    "gn:feature_code":"PPL",
    "gn:name":"Pulling",
    "gn:population":0,
    "gn:timezone":"Europe/Berlin",
    "iso:country":"DE",
    "name:deu_x_preferred":[
        "Pulling"
    ],
    "wof:name":"Pulling",
    "wof:placetype":"neighbourhood"
},
  "geometry": {"coordinates":[12.82577,49.15864000000001],"type":"Point"}
}