{
  "type": "Feature",
  "properties": {
    "gn:admin1_code":"2",
    "gn:admin2_code":"92.0",
    "gn:admin3_code":"9277.0",
    "gn:admin4_code":"9277113.0",
    "gn:asciiname":"Hirschbach",
    "gn:country_code":"DE",
    "gn:dem":374,
    "gn:feature_class":"P",
    "gn:feature_code":"PPL",
    "gn:name":"Hirschbach",
    "gn:population":0,
    "gn:timezone":"Europe/Berlin",
    "iso:country":"DE",
    "wof:name":"Hirschbach",
    "wof:placetype":"neighbourhood"
},
  "geometry": {"coordinates":[13.03579,48.45343],"type":"Point"}
}