{
  "type": "Feature",
  "properties": {
    "gn:admin1_code":"13",
    "gn:admin2_code":"0.0",
    "gn:admin3_code":"14729.0",
    "gn:admin4_code":"14729245.0",
    "gn:asciiname":"Mark Schoenstaedt",
    "gn:country_code":"DE",
    "gn:dem":166,
    "gn:feature_class":"P",
    "gn:feature_code":"PPL",
    "gn:name":"Mark Sch\u00f6nst\u00e4dt",
    "gn:population":0,
    "gn:timezone":"Europe/Berlin",
    "iso:country":"DE",
    "wof:name":"Mark Schoenstaedt",
    "wof:placetype":"neighbourhood"
},
  "geometry": {"coordinates":[12.87872,51.35517],"type":"Point"}
}