{
  "type": "Feature",
  "properties": {
    "gn:admin1_code":"2",
    "gn:admin2_code":"93.0",
    "gn:admin3_code":"9372.0",
    "gn:admin4_code":"9372116.0",
    "gn:asciiname":"Michelsdorf",
    "gn:country_code":"DE",
    "gn:dem":369,
    "gn:feature_class":"P",
    "gn:feature_code":"PPL",
    "gn:name":"Michelsdorf",
    "gn:population":0,
    "gn:timezone":"Europe/Berlin",
    "iso:country":"DE",
    "name:ceb_x_preferred":[
        "Michelsdorf"
    ],
    "name:deu_x_preferred":[
        "Michelsdorf"
    ],
    "name:pol_x_preferred":[
        "Michelsdorf"
    ],
    "name:rus_x_preferred":[
        "\u041c\u0438\u0445\u0435\u043b\u044c\u0441\u0434\u043e\u0440\u0444"
    ],
    "name:swe_x_preferred":[
        "Michelsdorf"
    ],
    "wof:name":"Michelsdorf",
    "wof:placetype":"neighbourhood"
},
  "geometry": {"coordinates":[12.63627,49.21706],"type":"Point"}
}