{
  "type": "Feature",
  "properties": {
    "gn:admin1_code":"13",
    "gn:admin2_code":"0.0",
    "gn:admin3_code":"14511.0",
    "gn:admin4_code":"14511000.0",
    "gn:asciiname":"Reichenhain",
    "gn:country_code":"DE",
    "gn:dem":407,
    "gn:feature_class":"P",
    "gn:feature_code":"PPL",
    "gn:name":"Reichenhain",
    "gn:population":0,
    "gn:timezone":"Europe/Berlin",
    "iso:country":"DE",
    "wof:name":"Reichenhain",
    "wof:placetype":"neighbourhood"
},
  "geometry": {"coordinates":[12.96147,50.79886],"type":"Point"}
}