{
  "type": "Feature",
  "properties": {
    "gn:admin1_code":"5.0",
    "gn:admin2_code":"64.0",
    "gn:admin3_code":"6440.0",
    "gn:admin4_code":"6440016.0",
    "gn:asciiname":"Harb",
    "gn:country_code":"DE",
    "gn:dem":166,
    "gn:feature_class":"P",
    "gn:feature_code":"PPL",
    "gn:name":"Harb",
    "gn:population":0,
    "gn:timezone":"Europe/Berlin",
    "iso:country":"DE",
    "name:deu_x_preferred":[
        "Harb"
    ],
    "name:fra_x_preferred":[
        "Harb"
    ],
    "wof:name":"Harb",
    "wof:placetype":"neighbourhood"
},
  "geometry": {"coordinates":[8.98663,50.43114],"type":"Point"}
}