{
  "type": "Feature",
  "properties": {
    "gn:admin1_code":"1",
    "gn:admin2_code":"81.0",
    "gn:admin3_code":"8136.0",
    "gn:admin4_code":"8136042.0",
    "gn:asciiname":"Rattenharz",
    "gn:country_code":"DE",
    "gn:dem":467,
    "gn:feature_class":"P",
    "gn:feature_code":"PPL",
    "gn:name":"Rattenharz",
    "gn:population":0,
    "gn:timezone":"Europe/Berlin",
    "iso:country":"DE",
    "wof:name":"Rattenharz",
    "wof:placetype":"neighbourhood"
},
  "geometry": {"coordinates":[9.66042,48.77984],"type":"Point"}
}