{
  "type": "Feature",
  "properties": {
    "gn:admin1_code":"11.0",
    "gn:admin2_code":"00",
    "gn:admin3_code":"12060.0",
    "gn:admin4_code":"12060280.0",
    "gn:asciiname":"Willmersdorf",
    "gn:country_code":"DE",
    "gn:dem":80,
    "gn:feature_class":"P",
    "gn:feature_code":"PPL",
    "gn:name":"Willmersdorf",
    "gn:population":0,
    "gn:timezone":"Europe/Berlin",
    "iso:country":"DE",
    "wof:name":"Willmersdorf",
    "wof:placetype":"neighbourhood"
},
  "geometry": {"coordinates":[13.68802,52.66373000000001],"type":"Point"}
}