{
  "type": "Feature",
  "properties": {
    "gn:admin1_code":"2.0",
    "gn:admin2_code":"96.0",
    "gn:admin3_code":"9672.0",
    "gn:admin4_code":"9672127.0",
    "gn:asciiname":"Lager Hammelburg",
    "gn:country_code":"DE",
    "gn:dem":325,
    "gn:feature_class":"P",
    "gn:feature_code":"PPL",
    "gn:name":"Lager Hammelburg",
    "gn:population":0,
    "gn:timezone":"Europe/Berlin",
    "iso:country":"DE",
    "wof:name":"Lager Hammelburg",
    "wof:placetype":"neighbourhood"
},
  "geometry": {"coordinates":[9.90212,50.08908],"type":"Point"}
}