{
  "type": "Feature",
  "properties": {
    "gn:admin1_code":"7",
    "gn:admin2_code":"53.0",
    "gn:admin3_code":"5378.0",
    "gn:admin4_code":"5378012.0",
    "gn:asciiname":"Doerpe",
    "gn:country_code":"DE",
    "gn:dem":210,
    "gn:feature_class":"P",
    "gn:feature_code":"PPL",
    "gn:name":"D\u00f6rpe",
    "gn:population":0,
    "gn:timezone":"Europe/Berlin",
    "iso:country":"DE",
    "wof:name":"Doerpe",
    "wof:placetype":"neighbourhood"
},
  "geometry": {"coordinates":[7.31212,51.05095],"type":"Point"}
}