{
  "type": "Feature",
  "properties": {
    "gn:admin1_code":"11",
    "gn:admin2_code":"0.0",
    "gn:admin3_code":"12068.0",
    "gn:admin4_code":"12068181.0",
    "gn:asciiname":"Koenigsberg",
    "gn:country_code":"DE",
    "gn:dem":56,
    "gn:feature_class":"P",
    "gn:feature_code":"PPL",
    "gn:name":"K\u00f6nigsberg",
    "gn:population":0,
    "gn:timezone":"Europe/Berlin",
    "iso:country":"DE",
    "wof:name":"Koenigsberg",
    "wof:placetype":"neighbourhood"
},
  "geometry": {"coordinates":[12.43532,53.06371],"type":"Point"}
}