{
  "type": "Feature",
  "properties": {
    "gn:admin1_code":"12.0",
    "gn:admin2_code":"00",
    "gn:admin3_code":"13071.0",
    "gn:admin4_code":"13071075.0",
    "gn:asciiname":"Zachow",
    "gn:country_code":"DE",
    "gn:dem":71,
    "gn:feature_class":"P",
    "gn:feature_code":"PPL",
    "gn:name":"Zachow",
    "gn:population":0,
    "gn:timezone":"Europe/Berlin",
    "iso:country":"DE",
    "wof:name":"Zachow",
    "wof:placetype":"neighbourhood"
},
  "geometry": {"coordinates":[13.05,53.45],"type":"Point"}
}