{
  "type": "Feature",
  "properties": {
    "gn:admin1_code":"2",
    "gn:admin2_code":"97.0",
    "gn:admin3_code":"9777.0",
    "gn:admin4_code":"9777171.0",
    "gn:asciiname":"Pracht",
    "gn:country_code":"DE",
    "gn:dem":835,
    "gn:feature_class":"P",
    "gn:feature_code":"PPL",
    "gn:name":"Pracht",
    "gn:population":0,
    "gn:timezone":"Europe/Berlin",
    "iso:country":"DE",
    "name:ceb_x_preferred":[
        "Pracht"
    ],
    "name:deu_x_preferred":[
        "Pracht"
    ],
    "name:epo_x_preferred":[
        "Pracht"
    ],
    "name:eus_x_preferred":[
        "Pracht"
    ],
    "name:fas_x_preferred":[
        "\u067e\u0631\u0627\u062e\u062a"
    ],
    "name:fra_x_preferred":[
        "Pracht"
    ],
    "name:hun_x_preferred":[
        "Pracht"
    ],
    "name:ita_x_preferred":[
        "Pracht"
    ],
    "name:msa_x_preferred":[
        "Pracht"
    ],
    "name:nld_x_preferred":[
        "Pracht"
    ],
    "name:pol_x_preferred":[
        "Pracht"
    ],
    "name:por_x_preferred":[
        "Pracht"
    ],
    "name:ron_x_preferred":[
        "Pracht"
    ],
    "name:rus_x_preferred":[
        "\u041f\u0440\u0430\u0445\u0442"
    ],
    "name:spa_x_preferred":[
        "Pracht"
    ],
    "name:srp_x_preferred":[
        "\u041f\u0440\u0430\u0445\u0442"
    ],
    "name:ukr_x_preferred":[
        "\u041f\u0440\u0430\u0445\u0442"
    ],
    "name:uzb_x_preferred":[
        "Pracht"
    ],
    "name:vie_x_preferred":[
        "Pracht"
    ],
    "name:vol_x_preferred":[
        "Pracht"
    ],
    "name:war_x_preferred":[
        "Pracht"
    ],
    "wof:name":"Pracht",
    "wof:placetype":"neighbourhood"
},
  "geometry": {"coordinates":[10.71212,47.72657],"type":"Point"}
}