{
  "type": "Feature",
  "properties": {
    "iso:country":"DE",
    "name:bar_x_preferred":[
        "Petersdorf"
    ],
    "name:ceb_x_preferred":[
        "Petersdorf"
    ],
    "name:ces_x_preferred":[
        "Petersdorf"
    ],
    "name:deu_x_preferred":[
        "Petersdorf"
    ],
    "name:epo_x_preferred":[
        "Petersdorf"
    ],
    "name:hbs_x_preferred":[
        "Petersdorf"
    ],
    "name:ita_x_preferred":[
        "Petersdorf"
    ],
    "name:mkd_x_preferred":[
        "\u041f\u0435\u0442\u0435\u0440\u0441\u0434\u043e\u0440\u0444"
    ],
    "name:nld_x_preferred":[
        "Petersdorf"
    ],
    "name:pol_x_preferred":[
        "Petersdorf"
    ],
    "name:rus_x_preferred":[
        "\u041f\u0435\u0442\u0435\u0440\u0441\u0434\u043e\u0440\u0444"
    ],
    "name:spa_x_preferred":[
        "Petersdorf"
    ],
    "name:unk_x_variant":[
        "Petersdorf"
    ],
    "name:vol_x_preferred":[
        "Petersdorf"
    ],
    "name:zho_x_preferred":[
        "\u5f7c\u5f97\u65af\u591a\u592b"
    ],
    "qs:gn_adm0_cc":"DE",
    "qs:gn_fcode":"PPL",
    "qs:gn_local":2844588,
    "qs:gn_nam_loc":"rostock",
    "qs:gn_namadm1":"12",
    "qs:gn_name":"Petersdorf",
    "qs:local_max":6613,
    "qs:local_sum":19240,
    "qs:localhoods":23,
    "qs:name":"Petersdorf",
    "qs:name_adm0":"Deutschland",
    "qs:name_adm1":"Mecklenburg-Vorpommern",
    "qs:name_adm2":"Stadtkreis Rostock",
    "qs:name_lau":"Stadtteil Lichtenhagen",
    "qs:name_local":"Rostock",
    "qs:photo_max":33,
    "qs:photo_sum":267,
    "qs:placetype":"Suburb",
    "qs:quad_count":41,
    "qs:woe_adm0":23424829,
    "qs:woe_adm1":2345492,
    "qs:woe_adm2":12597074,
    "qs:woe_lau":26823184,
    "qs:woe_local":689776,
    "qs:woe_ver":"7.10.0",
    "wof:lang":[
        "ger"
    ],
    "wof:name":"Petersdorf",
    "wof:placetype":"neighbourhood"
},
  "geometry": {"coordinates":[12.104539,54.151026],"type":"Point"}
}