{
  "type": "Feature",
  "properties": {
    "gn:admin1_code":"2",
    "gn:admin2_code":"91.0",
    "gn:admin3_code":"9185.0",
    "gn:admin4_code":"9185166.0",
    "gn:asciiname":"Schenkenau",
    "gn:country_code":"DE",
    "gn:dem":400,
    "gn:feature_class":"P",
    "gn:feature_code":"PPL",
    "gn:name":"Schenkenau",
    "gn:population":0,
    "gn:timezone":"Europe/Berlin",
    "iso:country":"DE",
    "wof:name":"Schenkenau",
    "wof:placetype":"neighbourhood"
},
  "geometry": {"coordinates":[11.37349,48.58573],"type":"Point"}
}