{
  "type": "Feature",
  "properties": {
    "gn:admin1_code":"2",
    "gn:admin2_code":"91.0",
    "gn:admin3_code":"9177.0",
    "gn:admin4_code":"9177139.0",
    "gn:asciiname":"Schnaupping",
    "gn:country_code":"DE",
    "gn:dem":484,
    "gn:feature_class":"P",
    "gn:feature_code":"PPL",
    "gn:name":"Schnaupping",
    "gn:population":0,
    "gn:timezone":"Europe/Berlin",
    "iso:country":"DE",
    "wof:name":"Schnaupping",
    "wof:placetype":"neighbourhood"
},
  "geometry": {"coordinates":[12.12373,48.31425],"type":"Point"}
}