{
  "type": "Feature",
  "properties": {
    "gn:admin1_code":"15",
    "gn:admin2_code":"0.0",
    "gn:admin3_code":"16063.0",
    "gn:admin4_code":"16063097.0",
    "gn:asciiname":"Dietrichsberg",
    "gn:country_code":"DE",
    "gn:dem":295,
    "gn:feature_class":"P",
    "gn:feature_code":"PPL",
    "gn:name":"Dietrichsberg",
    "gn:population":0,
    "gn:timezone":"Europe/Berlin",
    "iso:country":"DE",
    "wof:name":"Dietrichsberg",
    "wof:placetype":"neighbourhood"
},
  "geometry": {"coordinates":[10.15,50.95],"type":"Point"}
}