{
  "type": "Feature",
  "properties": {
    "gn:admin1_code":"2",
    "gn:admin2_code":"96.0",
    "gn:admin3_code":"9676.0",
    "gn:admin4_code":"9676145.0",
    "gn:asciiname":"Eisenbach",
    "gn:country_code":"DE",
    "gn:dem":131,
    "gn:feature_class":"P",
    "gn:feature_code":"PPL",
    "gn:name":"Eisenbach",
    "gn:population":0,
    "gn:timezone":"Europe/Berlin",
    "iso:country":"DE",
    "name:als_x_preferred":[
        "Eisenbach"
    ],
    "name:deu_x_preferred":[
        "Eisenbach"
    ],
    "name:epo_x_preferred":[
        "Eisenbach"
    ],
    "name:eus_x_preferred":[
        "Eisenbach"
    ],
    "name:fas_x_preferred":[
        "\u0622\u06cc\u0632\u0646\u0628\u0627\u062e"
    ],
    "name:fra_x_preferred":[
        "Eisenbach"
    ],
    "name:hun_x_preferred":[
        "Eisenbach"
    ],
    "name:hye_x_preferred":[
        "\u0531\u0575\u0566\u0565\u0576\u0562\u0561\u056d"
    ],
    "name:ita_x_preferred":[
        "Eisenbach"
    ],
    "name:kat_x_preferred":[
        "\u10d0\u10d8\u10d6\u10d4\u10dc\u10d1\u10d0\u10ee\u10d8"
    ],
    "name:kaz_x_preferred":[
        "\u0410\u0439\u0437\u0435\u043d\u0431\u0430\u0445"
    ],
    "name:lat_x_preferred":[
        "Eisenbach"
    ],
    "name:lmo_x_preferred":[
        "Eisenbach"
    ],
    "name:msa_x_preferred":[
        "Eisenbach"
    ],
    "name:nld_x_preferred":[
        "Eisenbach"
    ],
    "name:pol_x_preferred":[
        "Eisenbach"
    ],
    "name:por_x_preferred":[
        "Eisenbach"
    ],
    "name:ron_x_preferred":[
        "Eisenbach"
    ],
    "name:rus_x_preferred":[
        "\u0410\u0439\u0437\u0435\u043d\u0431\u0430\u0445"
    ],
    "name:spa_x_preferred":[
        "Eisenbach"
    ],
    "name:srp_x_preferred":[
        "\u0410\u0458\u0437\u0435\u043d\u0431\u0430\u0445"
    ],
    "name:ukr_x_preferred":[
        "\u0410\u0439\u0437\u0435\u043d\u0431\u0430\u0445"
    ],
    "name:uzb_x_preferred":[
        "Eisenbach"
    ],
    "name:vie_x_preferred":[
        "Eisenbach"
    ],
    "name:vol_x_preferred":[
        "Eisenbach"
    ],
    "name:war_x_preferred":[
        "Eisenbach"
    ],
    "name:zho_x_preferred":[
        "\u827e\u68ee\u5df4\u8d6b"
    ],
    "wof:name":"Eisenbach",
    "wof:placetype":"neighbourhood"
},
  "geometry": {"coordinates":[9.1117,49.83264000000001],"type":"Point"}
}