{
  "type": "Feature",
  "properties": {
    "gn:admin1_code":"11.0",
    "gn:admin2_code":"00",
    "gn:admin3_code":"12064.0",
    "gn:admin4_code":"12064408.0",
    "gn:asciiname":"Zinndorf",
    "gn:country_code":"DE",
    "gn:dem":54,
    "gn:feature_class":"P",
    "gn:feature_code":"PPL",
    "gn:name":"Zinndorf",
    "gn:population":0,
    "gn:timezone":"Europe/Berlin",
    "iso:country":"DE",
    "wof:name":"Zinndorf",
    "wof:placetype":"neighbourhood"
},
  "geometry": {"coordinates":[13.92253,52.50147],"type":"Point"}
}