{
  "type": "Feature",
  "properties": {
    "iso:country":"DE",
    "wof:name":"Meiswinkel",
    "wof:placetype":"neighbourhood"
},
  "geometry": {"coordinates":[7.04317610578194,51.13613689794428],"type":"Point"}
}