{
  "type": "Feature",
  "properties": {
    "gn:admin1_code":"6",
    "gn:admin2_code":"0.0",
    "gn:admin3_code":"3357.0",
    "gn:admin4_code":"3357035.0",
    "gn:asciiname":"Glinde",
    "gn:country_code":"DE",
    "gn:dem":10,
    "gn:feature_class":"P",
    "gn:feature_code":"PPL",
    "gn:name":"Glinde",
    "gn:population":0,
    "gn:timezone":"Europe/Berlin",
    "iso:country":"DE",
    "name:ceb_x_preferred":[
        "Glinde"
    ],
    "name:deu_x_preferred":[
        "Glinde"
    ],
    "name:ita_x_preferred":[
        "Glinde"
    ],
    "name:nld_x_preferred":[
        "Glinde"
    ],
    "name:pol_x_preferred":[
        "Glinde"
    ],
    "name:rus_x_preferred":[
        "\u0413\u043b\u0438\u043d\u0434\u0435"
    ],
    "name:vol_x_preferred":[
        "Glinde"
    ],
    "wof:name":"Glinde",
    "wof:placetype":"neighbourhood"
},
  "geometry": {"coordinates":[9.09221,53.49618],"type":"Point"}
}