{
  "type": "Feature",
  "properties": {
    "gn:admin1_code":"2",
    "gn:admin2_code":"97.0",
    "gn:admin3_code":"9777.0",
    "gn:admin4_code":"9777138.0",
    "gn:asciiname":"Thal",
    "gn:country_code":"DE",
    "gn:dem":767,
    "gn:feature_class":"P",
    "gn:feature_code":"PPL",
    "gn:name":"Thal",
    "gn:population":0,
    "gn:timezone":"Europe/Berlin",
    "iso:country":"DE",
    "wof:name":"Thal",
    "wof:placetype":"neighbourhood"
},
  "geometry": {"coordinates":[10.4329,47.8263],"type":"Point"}
}