{
  "type": "Feature",
  "properties": {
    "gn:admin1_code":"2",
    "gn:admin2_code":"97.0",
    "gn:admin3_code":"9777.0",
    "gn:admin4_code":"9777138.0",
    "gn:asciiname":"Thal",
    "gn:country_code":"DE",
    "gn:dem":767,
    "gn:feature_class":"P",
    "gn:feature_code":"PPL",
    "gn:name":"Thal",
    "gn:population":0,
    "gn:timezone":"Europe/Berlin",
    "iso:country":"DE",
    "name:als_x_preferred":[
        "Thal"
    ],
    "name:ceb_x_preferred":[
        "Thal"
    ],
    "name:deu_x_preferred":[
        "Thal"
    ],
    "name:epo_x_preferred":[
        "Thal"
    ],
    "name:fra_x_preferred":[
        "Thal"
    ],
    "name:ita_x_preferred":[
        "Thal"
    ],
    "name:nld_x_preferred":[
        "Thal"
    ],
    "name:pol_x_preferred":[
        "Thal"
    ],
    "name:spa_x_preferred":[
        "Thal"
    ],
    "name:swe_x_preferred":[
        "Thal"
    ],
    "name:vol_x_preferred":[
        "Thal"
    ],
    "wof:name":"Thal",
    "wof:placetype":"neighbourhood"
},
  "geometry": {"coordinates":[10.4329,47.8263],"type":"Point"}
}