{
  "type": "Feature",
  "properties": {
    "gn:admin1_code":"7.0",
    "gn:admin2_code":"53.0",
    "gn:admin3_code":"5374.0",
    "gn:admin4_code":"5374032.0",
    "gn:asciiname":"Berkenroth",
    "gn:country_code":"DE",
    "gn:dem":237,
    "gn:feature_class":"P",
    "gn:feature_code":"PPL",
    "gn:name":"Berkenroth",
    "gn:population":0,
    "gn:timezone":"Europe/Berlin",
    "iso:country":"DE",
    "wof:name":"Berkenroth",
    "wof:placetype":"neighbourhood"
},
  "geometry": {"coordinates":[7.54806,50.86365],"type":"Point"}
}