{
  "type": "Feature",
  "properties": {
    "gn:admin1_code":"7",
    "gn:admin2_code":"53.0",
    "gn:admin3_code":"5378.0",
    "gn:admin4_code":"5378024.0",
    "gn:asciiname":"Warth",
    "gn:country_code":"DE",
    "gn:dem":221,
    "gn:feature_class":"P",
    "gn:feature_code":"PPL",
    "gn:name":"Warth",
    "gn:population":0,
    "gn:timezone":"Europe/Berlin",
    "iso:country":"DE",
    "name:als_x_preferred":[
        "Warth"
    ],
    "name:ceb_x_preferred":[
        "Warth"
    ],
    "name:deu_x_preferred":[
        "Warth"
    ],
    "name:epo_x_preferred":[
        "Warth"
    ],
    "name:fra_x_preferred":[
        "Warth"
    ],
    "name:ita_x_preferred":[
        "Warth"
    ],
    "name:lmo_x_preferred":[
        "Warth"
    ],
    "name:nld_x_preferred":[
        "Warth"
    ],
    "name:pol_x_preferred":[
        "Warth"
    ],
    "name:rus_x_preferred":[
        "\u0412\u0430\u0440\u0442"
    ],
    "name:swe_x_preferred":[
        "Warth"
    ],
    "name:vol_x_preferred":[
        "Warth"
    ],
    "wof:name":"Warth",
    "wof:placetype":"neighbourhood"
},
  "geometry": {"coordinates":[7.30273,50.92249],"type":"Point"}
}