{
  "type": "Feature",
  "properties": {
    "gn:admin1_code":"2",
    "gn:admin2_code":"95.0",
    "gn:admin3_code":"9573.0",
    "gn:admin4_code":"9573114.0",
    "gn:asciiname":"Deberndorf",
    "gn:country_code":"DE",
    "gn:dem":365,
    "gn:feature_class":"P",
    "gn:feature_code":"PPL",
    "gn:name":"Deberndorf",
    "gn:population":0,
    "gn:timezone":"Europe/Berlin",
    "iso:country":"DE",
    "wof:name":"Deberndorf",
    "wof:placetype":"neighbourhood"
},
  "geometry": {"coordinates":[10.79778,49.44022],"type":"Point"}
}