{
  "type": "Feature",
  "properties": {
    "gn:admin1_code":"2",
    "gn:admin2_code":"91.0",
    "gn:admin3_code":"9176.0",
    "gn:admin4_code":"9176153.0",
    "gn:asciiname":"Gaden bei Pforring",
    "gn:country_code":"DE",
    "gn:dem":352,
    "gn:feature_class":"P",
    "gn:feature_code":"PPL",
    "gn:name":"Gaden bei Pf\u00f6rring",
    "gn:population":0,
    "gn:timezone":"Europe/Berlin",
    "iso:country":"DE",
    "wof:name":"Gaden bei Pforring",
    "wof:placetype":"neighbourhood"
},
  "geometry": {"coordinates":[11.70916,48.79702],"type":"Point"}
}