{
  "type": "Feature",
  "properties": {
    "gn:admin1_code":"2",
    "gn:admin2_code":"91.0",
    "gn:admin3_code":"9174.0",
    "gn:admin4_code":"9174115.0",
    "gn:asciiname":"Oberaugustenfeld",
    "gn:country_code":"DE",
    "gn:dem":483,
    "gn:feature_class":"P",
    "gn:feature_code":"PPL",
    "gn:name":"Oberaugustenfeld",
    "gn:population":0,
    "gn:timezone":"Europe/Berlin",
    "iso:country":"DE",
    "wof:name":"Oberaugustenfeld",
    "wof:placetype":"neighbourhood"
},
  "geometry": {"coordinates":[11.44762,48.2474],"type":"Point"}
}