{
  "type": "Feature",
  "properties": {
    "gn:country":"DE",
    "gn:fcode":"PPL",
    "gn:population":0,
    "iso:country":"DE",
    "name:bul_x_preferred":[
        "\u041d\u0438\u043d\u043e\u0444\u0435\u0440"
    ],
    "name:deu_x_preferred":[
        "Nienover"
    ],
    "name:eng_x_preferred":[
        "Nienover"
    ],
    "name:fas_x_preferred":[
        "\u0646\u0627\u06cc\u0646\u0648\u0641\u0631"
    ],
    "name:fra_x_preferred":[
        "Nienover"
    ],
    "name:gle_x_preferred":[
        "Nienover"
    ],
    "name:nld_x_preferred":[
        "Nienover"
    ],
    "name:nob_x_preferred":[
        "Nienover"
    ],
    "qs_pg:aaroncc":"DE",
    "qs_pg:gn_country":"DE",
    "qs_pg:gn_fcode":"PPL",
    "qs_pg:gn_pop":0,
    "qs_pg:name":"Nienover",
    "qs_pg:name_adm0":"Deutschland",
    "qs_pg:name_adm1":"Niedersachsen",
    "qs_pg:photos":9,
    "qs_pg:photos_1k":2,
    "qs_pg:photos_9k":1,
    "qs_pg:photos_9r":1,
    "qs_pg:photos_all":9,
    "qs_pg:photos_sr":1,
    "qs_pg:pop_sr":0,
    "qs_pg:qs_pg_placetype":"locality",
    "qs_pg:qs_pg_placetype_gp":"Town",
    "qs_pg:woe_adm0":23424829,
    "woe:adm0_id":23424829,
    "woe:name_adm0":"Deutschland",
    "woe:name_adm1":"Niedersachsen",
    "woe:placetype":"Town",
    "wof:name":"Nienover",
    "wof:placetype":"neighbourhood"
},
  "geometry": {"coordinates":[9.52522,51.68042],"type":"Point"}
}