{
  "type": "Feature",
  "properties": {
    "iso:country":"DE",
    "oa:elevation_ft":"397",
    "oa:type":"small_airport",
    "woe:hierarchy":{
        "country_id":23424829,
        "county_id":12596966,
        "localadmin_id":12632593,
        "planet_id":1,
        "state_id":2345485
    },
    "wof:name":"Flugplatz Reichelsheim",
    "wof:placetype":"campus"
},
  "geometry": {"coordinates":[8.87806,50.3358],"type":"Point"}
}