{
  "type": "Feature",
  "properties": {
    "iso:country":"DE",
    "name:deu_x_preferred":[
        "Flugplatz Reichelsheim"
    ],
    "name:eng_x_preferred":[
        "Reichelsheim Airport"
    ],
    "name:eng_x_variant":[
        "EDFB",
        "Reichelsheim airfield"
    ],
    "name:fra_x_preferred":[
        "Flugplatz Reichelsheim"
    ],
    "name:msa_x_preferred":[
        "Lapangan Terbang Reichelsheim"
    ],
    "name:swe_x_preferred":[
        "Flugplatz Reichelsheim"
    ],
    "oa:elevation_ft":"397",
    "oa:type":"small_airport",
    "woe:hierarchy":{
        "country_id":23424829,
        "county_id":12596966,
        "localadmin_id":12632593,
        "planet_id":1,
        "state_id":2345485
    },
    "wof:name":"Flugplatz Reichelsheim",
    "wof:placetype":"campus"
},
  "geometry": {"coordinates":[8.87806,50.3358],"type":"Point"}
}