{
  "type": "Feature",
  "properties": {
    "gn:admin1_code":"12",
    "gn:admin2_code":"0.0",
    "gn:admin3_code":"13076.0",
    "gn:admin4_code":"13076005.0",
    "gn:asciiname":"Jamel",
    "gn:country_code":"DE",
    "gn:dem":34,
    "gn:feature_class":"P",
    "gn:feature_code":"PPL",
    "gn:name":"Jamel",
    "gn:population":0,
    "gn:timezone":"Europe/Berlin",
    "iso:country":"DE",
    "wof:name":"Jamel",
    "wof:placetype":"neighbourhood"
},
  "geometry": {"coordinates":[11.51762,53.48294],"type":"Point"}
}