{
  "type": "Feature",
  "properties": {
    "gn:admin1_code":"2",
    "gn:admin2_code":"92.0",
    "gn:admin3_code":"9277.0",
    "gn:admin4_code":"9277138.0",
    "gn:asciiname":"Kuhstetten",
    "gn:country_code":"DE",
    "gn:dem":389,
    "gn:feature_class":"P",
    "gn:feature_code":"PPL",
    "gn:name":"K\u00fchstetten",
    "gn:population":0,
    "gn:timezone":"Europe/Berlin",
    "iso:country":"DE",
    "wof:name":"Kuhstetten",
    "wof:placetype":"neighbourhood"
},
  "geometry": {"coordinates":[12.96751,48.45],"type":"Point"}
}