{
  "type": "Feature",
  "properties": {
    "gn:admin1_code":"2",
    "gn:admin2_code":"97.0",
    "gn:admin3_code":"9778.0",
    "gn:admin4_code":"9778134.0",
    "gn:asciiname":"Ellenried",
    "gn:country_code":"DE",
    "gn:dem":573,
    "gn:feature_class":"P",
    "gn:feature_code":"PPL",
    "gn:name":"Ellenried",
    "gn:population":0,
    "gn:timezone":"Europe/Berlin",
    "iso:country":"DE",
    "wof:name":"Ellenried",
    "wof:placetype":"neighbourhood"
},
  "geometry": {"coordinates":[10.58593,48.19048],"type":"Point"}
}