{
  "type": "Feature",
  "properties": {
    "gn:admin1_code":"7",
    "gn:admin2_code":"53.0",
    "gn:admin3_code":"5374.0",
    "gn:admin4_code":"5374024.0",
    "gn:asciiname":"Siemerkusen",
    "gn:country_code":"DE",
    "gn:dem":387,
    "gn:feature_class":"P",
    "gn:feature_code":"PPL",
    "gn:name":"Siemerkusen",
    "gn:population":0,
    "gn:timezone":"Europe/Berlin",
    "iso:country":"DE",
    "wof:name":"Siemerkusen",
    "wof:placetype":"neighbourhood"
},
  "geometry": {"coordinates":[7.49259,51.07892],"type":"Point"}
}