{
  "type": "Feature",
  "properties": {
    "gn:admin1_code":"5",
    "gn:admin2_code":"66.0",
    "gn:admin3_code":"6631.0",
    "gn:admin4_code":"6631002.0",
    "gn:asciiname":"Grossenmoor",
    "gn:country_code":"DE",
    "gn:dem":299,
    "gn:feature_class":"P",
    "gn:feature_code":"PPL",
    "gn:name":"Gro\u00dfenmoor",
    "gn:population":0,
    "gn:timezone":"Europe/Berlin",
    "iso:country":"DE",
    "wof:name":"Grossenmoor",
    "wof:placetype":"neighbourhood"
},
  "geometry": {"coordinates":[9.65301,50.70244],"type":"Point"}
}