{
  "type": "Feature",
  "properties": {
    "gn:admin1_code":"2",
    "gn:admin2_code":"93.0",
    "gn:admin3_code":"9376.0",
    "gn:admin4_code":"9376169.0",
    "gn:asciiname":"Freiung",
    "gn:country_code":"DE",
    "gn:dem":399,
    "gn:feature_class":"P",
    "gn:feature_code":"PPL",
    "gn:name":"Freiung",
    "gn:population":0,
    "gn:timezone":"Europe/Berlin",
    "iso:country":"DE",
    "wof:name":"Freiung",
    "wof:placetype":"neighbourhood"
},
  "geometry": {"coordinates":[12.10832,49.43773],"type":"Point"}
}