{
  "type": "Feature",
  "properties": {
    "gn:admin1_code":"2",
    "gn:admin2_code":"92.0",
    "gn:admin3_code":"9277.0",
    "gn:admin4_code":"9277127.0",
    "gn:asciiname":"Mehlmausl",
    "gn:country_code":"DE",
    "gn:dem":374,
    "gn:feature_class":"P",
    "gn:feature_code":"PPL",
    "gn:name":"Mehlm\u00e4usl",
    "gn:population":0,
    "gn:timezone":"Europe/Berlin",
    "iso:country":"DE",
    "wof:name":"Mehlmausl",
    "wof:placetype":"neighbourhood"
},
  "geometry": {"coordinates":[12.90379,48.25062],"type":"Point"}
}