{
  "type": "Feature",
  "properties": {
    "gn:admin1_code":"13",
    "gn:admin2_code":"0.0",
    "gn:admin3_code":"14522.0",
    "gn:admin4_code":"14522220.0",
    "gn:asciiname":"Kleinweitzschen",
    "gn:country_code":"DE",
    "gn:dem":244,
    "gn:feature_class":"P",
    "gn:feature_code":"PPL",
    "gn:name":"Kleinweitzschen",
    "gn:population":0,
    "gn:timezone":"Europe/Berlin",
    "iso:country":"DE",
    "wof:name":"Kleinweitzschen",
    "wof:placetype":"neighbourhood"
},
  "geometry": {"coordinates":[13.0382,51.16058],"type":"Point"}
}