{
  "type": "Feature",
  "properties": {
    "gn:admin1_code":"5",
    "gn:admin2_code":"66.0",
    "gn:admin3_code":"6636.0",
    "gn:admin4_code":"6636010.0",
    "gn:asciiname":"Renda",
    "gn:country_code":"DE",
    "gn:dem":387,
    "gn:feature_class":"P",
    "gn:feature_code":"PPL",
    "gn:name":"Renda",
    "gn:population":0,
    "gn:timezone":"Europe/Berlin",
    "iso:country":"DE",
    "name:ita_x_preferred":[
        "Renda"
    ],
    "name:por_x_preferred":[
        "Renda"
    ],
    "wof:name":"Renda",
    "wof:placetype":"neighbourhood"
},
  "geometry": {"coordinates":[10.07466,51.06799],"type":"Point"}
}