{
  "type": "Feature",
  "properties": {
    "gn:admin1_code":"7",
    "gn:admin2_code":"57.0",
    "gn:admin3_code":"5774.0",
    "gn:admin4_code":"5774016.0",
    "gn:asciiname":"Steinhausen",
    "gn:country_code":"DE",
    "gn:dem":234,
    "gn:feature_class":"P",
    "gn:feature_code":"PPL",
    "gn:name":"Steinhausen",
    "gn:population":0,
    "gn:timezone":"Europe/Berlin",
    "iso:country":"DE",
    "name:als_x_preferred":[
        "Steinhausen"
    ],
    "name:ceb_x_preferred":[
        "Steinhausen"
    ],
    "name:deu_x_preferred":[
        "Steinhausen"
    ],
    "name:epo_x_preferred":[
        "Steinhausen"
    ],
    "name:eus_x_preferred":[
        "Steinhausen"
    ],
    "name:fra_x_preferred":[
        "Steinhausen"
    ],
    "name:ita_x_preferred":[
        "Steinhausen"
    ],
    "name:nld_x_preferred":[
        "Steinhausen"
    ],
    "name:pol_x_preferred":[
        "Steinhausen"
    ],
    "name:por_x_preferred":[
        "Steinhausen"
    ],
    "name:swe_x_preferred":[
        "Steinhausen"
    ],
    "wof:name":"Steinhausen",
    "wof:placetype":"neighbourhood"
},
  "geometry": {"coordinates":[8.52342,51.5825],"type":"Point"}
}