{
  "type": "Feature",
  "properties": {
    "gn:admin1_code":"1",
    "gn:admin2_code":"81.0",
    "gn:admin3_code":"8116.0",
    "gn:admin4_code":"8116020.0",
    "gn:asciiname":"Linsenhofen",
    "gn:country_code":"DE",
    "gn:dem":353,
    "gn:feature_class":"P",
    "gn:feature_code":"PPL",
    "gn:name":"Linsenhofen",
    "gn:population":0,
    "gn:timezone":"Europe/Berlin",
    "iso:country":"DE",
    "wof:name":"Linsenhofen",
    "wof:placetype":"neighbourhood"
},
  "geometry": {"coordinates":[9.37108,48.57857],"type":"Point"}
}