{
  "type": "Feature",
  "properties": {
    "gn:admin1_code":"6.0",
    "gn:admin2_code":"0.0",
    "gn:admin3_code":"3360.0",
    "gn:admin4_code":"3360023.0",
    "gn:asciiname":"Bahnhof Suderburg",
    "gn:country_code":"DE",
    "gn:dem":72,
    "gn:feature_class":"P",
    "gn:feature_code":"PPL",
    "gn:name":"Bahnhof Suderburg",
    "gn:population":0,
    "gn:timezone":"Europe/Berlin",
    "iso:country":"DE",
    "wof:name":"Bahnhof Suderburg",
    "wof:placetype":"neighbourhood"
},
  "geometry": {"coordinates":[10.43324,52.9051],"type":"Point"}
}