{
  "type": "Feature",
  "properties": {
    "gn:admin1_code":"8",
    "gn:admin2_code":"0.0",
    "gn:admin3_code":"7235.0",
    "gn:admin4_code":"7235068.0",
    "gn:asciiname":"Oberemmel",
    "gn:country_code":"DE",
    "gn:dem":199,
    "gn:feature_class":"P",
    "gn:feature_code":"PPL",
    "gn:name":"Oberemmel",
    "gn:population":0,
    "gn:timezone":"Europe/Berlin",
    "iso:country":"DE",
    "wof:name":"Oberemmel",
    "wof:placetype":"neighbourhood"
},
  "geometry": {"coordinates":[6.63081,49.66129],"type":"Point"}
}