{
  "type": "Feature",
  "properties": {
    "gn:admin1_code":"2.0",
    "gn:admin2_code":"97.0",
    "gn:admin3_code":"9778.0",
    "gn:admin4_code":"9778187.0",
    "gn:asciiname":"Weilbach",
    "gn:country_code":"DE",
    "gn:dem":561,
    "gn:feature_class":"P",
    "gn:feature_code":"PPL",
    "gn:name":"Weilbach",
    "gn:population":0,
    "gn:timezone":"Europe/Berlin",
    "iso:country":"DE",
    "name:ceb_x_preferred":[
        "Weilbach"
    ],
    "name:dan_x_preferred":[
        "Weilbach"
    ],
    "name:deu_x_preferred":[
        "Weilbach"
    ],
    "name:fra_x_preferred":[
        "Weilbach"
    ],
    "name:ita_x_preferred":[
        "Weilbach"
    ],
    "name:nld_x_preferred":[
        "Weilbach"
    ],
    "name:pol_x_preferred":[
        "Weilbach"
    ],
    "name:rus_x_preferred":[
        "\u0412\u0430\u0439\u043b\u044c\u0431\u0430\u0445"
    ],
    "name:swe_x_preferred":[
        "Weilbach"
    ],
    "name:vol_x_preferred":[
        "Weilbach"
    ],
    "wof:name":"Weilbach",
    "wof:placetype":"neighbourhood"
},
  "geometry": {"coordinates":[10.42654,48.12428],"type":"Point"}
}