{
  "type": "Feature",
  "properties": {
    "gn:admin1_code":"1",
    "gn:admin2_code":"84.0",
    "gn:admin3_code":"8426.0",
    "gn:admin4_code":"8426108.0",
    "gn:asciiname":"Grossschafhausen",
    "gn:country_code":"DE",
    "gn:dem":533,
    "gn:feature_class":"P",
    "gn:feature_code":"PPL",
    "gn:name":"Gro\u00dfschafhausen",
    "gn:population":0,
    "gn:timezone":"Europe/Berlin",
    "iso:country":"DE",
    "wof:name":"Grossschafhausen",
    "wof:placetype":"neighbourhood"
},
  "geometry": {"coordinates":[9.97267,48.19075],"type":"Point"}
}