{
  "type": "Feature",
  "properties": {
    "gn:admin1_code":"5",
    "gn:admin2_code":"66.0",
    "gn:admin3_code":"6633.0",
    "gn:admin4_code":"6633024.0",
    "gn:asciiname":"Wattenbach",
    "gn:country_code":"DE",
    "gn:dem":376,
    "gn:feature_class":"P",
    "gn:feature_code":"PPL",
    "gn:name":"Wattenbach",
    "gn:population":0,
    "gn:timezone":"Europe/Berlin",
    "iso:country":"DE",
    "name:deu_x_preferred":[
        "Wattenbach"
    ],
    "name:nld_x_preferred":[
        "Wattenbach"
    ],
    "wof:name":"Wattenbach",
    "wof:placetype":"neighbourhood"
},
  "geometry": {"coordinates":[9.59236,51.21333],"type":"Point"}
}