{
  "type": "Feature",
  "properties": {
    "gn:admin1_code":"10",
    "gn:admin2_code":"0.0",
    "gn:admin3_code":"1060.0",
    "gn:admin4_code":"1060067.0",
    "gn:asciiname":"Diekhof",
    "gn:country_code":"DE",
    "gn:dem":56,
    "gn:feature_class":"P",
    "gn:feature_code":"PPL",
    "gn:name":"Diekhof",
    "gn:population":0,
    "gn:timezone":"Europe/Berlin",
    "iso:country":"DE",
    "name:deu_x_preferred":[
        "Diekhof"
    ],
    "name:epo_x_preferred":[
        "Diekhof"
    ],
    "name:fas_x_preferred":[
        "\u062f\u06cc\u06a9\u0647\u0648\u0641"
    ],
    "name:fra_x_preferred":[
        "Diekhof"
    ],
    "name:hun_x_preferred":[
        "Diekhof"
    ],
    "name:ita_x_preferred":[
        "Diekhof"
    ],
    "name:kaz_x_preferred":[
        "\u0414\u0438\u043a\u0445\u043e\u0444"
    ],
    "name:kir_x_preferred":[
        "\u0414\u0438\u043a\u0445\u043e\u0444"
    ],
    "name:mkd_x_preferred":[
        "\u0414\u0438\u043a\u0445\u043e\u0444"
    ],
    "name:msa_x_preferred":[
        "Diekhof"
    ],
    "name:nld_x_preferred":[
        "Diekhof"
    ],
    "name:pol_x_preferred":[
        "Diekhof"
    ],
    "name:ron_x_preferred":[
        "Diekhof"
    ],
    "name:rus_x_preferred":[
        "\u0414\u0438\u043a\u0445\u043e\u0444"
    ],
    "name:spa_x_preferred":[
        "Diekhof"
    ],
    "name:srp_x_preferred":[
        "\u0414\u0438\u043a\u0445\u043e\u0444"
    ],
    "name:ukr_x_preferred":[
        "\u0414\u0456\u043a\u0433\u043e\u0444"
    ],
    "name:uzb_x_preferred":[
        "Diekhof"
    ],
    "name:vie_x_preferred":[
        "Diekhof"
    ],
    "name:vol_x_preferred":[
        "Diekhof"
    ],
    "name:war_x_preferred":[
        "Diekhof"
    ],
    "name:zho_x_preferred":[
        "\u8fea\u514b\u970d\u592b"
    ],
    "wof:name":"Diekhof",
    "wof:placetype":"neighbourhood"
},
  "geometry": {"coordinates":[10.50461,53.97452],"type":"Point"}
}