{
  "type": "Feature",
  "properties": {
    "gn:admin1_code":"5",
    "gn:admin2_code":"65.0",
    "gn:admin3_code":"6532.0",
    "gn:admin4_code":"6532009.0",
    "gn:asciiname":"Eiershausen",
    "gn:country_code":"DE",
    "gn:dem":345,
    "gn:feature_class":"P",
    "gn:feature_code":"PPL",
    "gn:name":"Eiershausen",
    "gn:population":0,
    "gn:timezone":"Europe/Berlin",
    "iso:country":"DE",
    "wof:name":"Eiershausen",
    "wof:placetype":"neighbourhood"
},
  "geometry": {"coordinates":[8.36283,50.80419000000001],"type":"Point"}
}