{
  "type": "Feature",
  "properties": {
    "gn:admin1_code":"2",
    "gn:admin2_code":"91.0",
    "gn:admin3_code":"9190.0",
    "gn:admin4_code":"9190135.0",
    "gn:asciiname":"Maxlried",
    "gn:country_code":"DE",
    "gn:dem":588,
    "gn:feature_class":"P",
    "gn:feature_code":"PPL",
    "gn:name":"Maxlried",
    "gn:population":0,
    "gn:timezone":"Europe/Berlin",
    "iso:country":"DE",
    "wof:name":"Maxlried",
    "wof:placetype":"neighbourhood"
},
  "geometry": {"coordinates":[11.11105,47.7721],"type":"Point"}
}