{
  "type": "Feature",
  "properties": {
    "gn:admin1_code":"13.0",
    "gn:admin2_code":"00",
    "gn:admin3_code":"14523.0",
    "gn:admin4_code":"14523230.0",
    "gn:asciiname":"Wohlbach",
    "gn:country_code":"DE",
    "gn:dem":533,
    "gn:feature_class":"P",
    "gn:feature_code":"PPL",
    "gn:name":"Wohlbach",
    "gn:population":0,
    "gn:timezone":"Europe/Berlin",
    "iso:country":"DE",
    "wof:name":"Wohlbach",
    "wof:placetype":"neighbourhood"
},
  "geometry": {"coordinates":[12.3109,50.35398],"type":"Point"}
}