{
  "type": "Feature",
  "properties": {
    "gn:admin1_code":"7.0",
    "gn:admin2_code":"51.0",
    "gn:admin3_code":"5170.0",
    "gn:admin4_code":"5170012.0",
    "gn:asciiname":"Auf dem Hammel",
    "gn:country_code":"DE",
    "gn:dem":35,
    "gn:feature_class":"P",
    "gn:feature_code":"PPL",
    "gn:name":"Auf dem Hammel",
    "gn:population":0,
    "gn:timezone":"Europe/Berlin",
    "iso:country":"DE",
    "wof:name":"Auf dem Hammel",
    "wof:placetype":"neighbourhood"
},
  "geometry": {"coordinates":[6.55,51.71667],"type":"Point"}
}