{
  "type": "Feature",
  "properties": {
    "gn:admin1_code":"14.0",
    "gn:admin2_code":"0.0",
    "gn:admin3_code":"15089.0",
    "gn:admin4_code":"15089045.0",
    "gn:asciiname":"Bisdorf",
    "gn:country_code":"DE",
    "gn:dem":89,
    "gn:feature_class":"P",
    "gn:feature_code":"PPL",
    "gn:name":"Bisdorf",
    "gn:population":0,
    "gn:timezone":"Europe/Berlin",
    "iso:country":"DE",
    "name:osx_x_preferred":[
        "Biscopesthorp"
    ],
    "wof:name":"Bisdorf",
    "wof:placetype":"neighbourhood"
},
  "geometry": {"coordinates":[11.55134,51.9519],"type":"Point"}
}