{
  "type": "Feature",
  "properties": {
    "gn:admin1_code":"5",
    "gn:admin2_code":"65.0",
    "gn:admin3_code":"6535.0",
    "gn:admin4_code":"6535016.0",
    "gn:asciiname":"Eschenrod",
    "gn:country_code":"DE",
    "gn:dem":352,
    "gn:feature_class":"P",
    "gn:feature_code":"PPL",
    "gn:name":"Eschenrod",
    "gn:population":0,
    "gn:timezone":"Europe/Berlin",
    "iso:country":"DE",
    "wof:name":"Eschenrod",
    "wof:placetype":"neighbourhood"
},
  "geometry": {"coordinates":[9.15804,50.47832],"type":"Point"}
}