{
  "type": "Feature",
  "properties": {
    "gn:admin1_code":"10",
    "gn:admin2_code":"0.0",
    "gn:admin3_code":"1058.0",
    "gn:admin4_code":"1058003.0",
    "gn:asciiname":"Krummenort",
    "gn:country_code":"DE",
    "gn:dem":8,
    "gn:feature_class":"P",
    "gn:feature_code":"PPL",
    "gn:name":"Krummenort",
    "gn:population":0,
    "gn:timezone":"Europe/Berlin",
    "iso:country":"DE",
    "wof:name":"Krummenort",
    "wof:placetype":"neighbourhood"
},
  "geometry": {"coordinates":[9.59246,54.35717],"type":"Point"}
}