{
  "type": "Feature",
  "properties": {
    "gn:admin1_code":"2.0",
    "gn:admin2_code":"95.0",
    "gn:admin3_code":"9576.0",
    "gn:admin4_code":"9576117.0",
    "gn:asciiname":"Breitenlohe",
    "gn:country_code":"DE",
    "gn:dem":362,
    "gn:feature_class":"P",
    "gn:feature_code":"PPL",
    "gn:name":"Breitenlohe",
    "gn:population":0,
    "gn:timezone":"Europe/Berlin",
    "iso:country":"DE",
    "name:deu_x_preferred":[
        "Breitenlohe"
    ],
    "wof:name":"Breitenlohe",
    "wof:placetype":"neighbourhood"
},
  "geometry": {"coordinates":[11.03036,49.25979],"type":"Point"}
}