{
  "type": "Feature",
  "properties": {
    "gn:admin1_code":"11",
    "gn:admin2_code":"0.0",
    "gn:admin3_code":"12070.0",
    "gn:admin4_code":"12070125.0",
    "gn:asciiname":"Horst",
    "gn:country_code":"DE",
    "gn:dem":51,
    "gn:feature_class":"P",
    "gn:feature_code":"PPL",
    "gn:name":"Horst",
    "gn:population":0,
    "gn:timezone":"Europe/Berlin",
    "iso:country":"DE",
    "name:afr_x_preferred":[
        "Horst"
    ],
    "name:ara_x_preferred":[
        "\u0647\u0648\u0631\u0633\u062a"
    ],
    "name:ceb_x_preferred":[
        "Horst"
    ],
    "name:ces_x_preferred":[
        "Horst"
    ],
    "name:dan_x_preferred":[
        "Horst"
    ],
    "name:deu_x_preferred":[
        "Horst"
    ],
    "name:epo_x_preferred":[
        "Horst"
    ],
    "name:fas_x_preferred":[
        "\u0647\u0648\u0631\u0633\u062a"
    ],
    "name:fin_x_preferred":[
        "Horst"
    ],
    "name:fra_x_preferred":[
        "Horst"
    ],
    "name:hrv_x_preferred":[
        "Horst"
    ],
    "name:ita_x_preferred":[
        "Horst"
    ],
    "name:jpn_x_preferred":[
        "\u30db\u30eb\u30b9\u30c8"
    ],
    "name:mkd_x_preferred":[
        "\u0425\u043e\u0440\u0441\u0442"
    ],
    "name:nds_x_preferred":[
        "Horst"
    ],
    "name:nld_x_preferred":[
        "Horst"
    ],
    "name:pol_x_preferred":[
        "Horst"
    ],
    "name:por_x_preferred":[
        "Horst"
    ],
    "name:ron_x_preferred":[
        "Horst"
    ],
    "name:rus_x_preferred":[
        "\u0425\u043e\u0440\u0441\u0442"
    ],
    "name:srp_x_preferred":[
        "\u0425\u043e\u0440\u0441\u0442"
    ],
    "name:vol_x_preferred":[
        "Horst"
    ],
    "wof:name":"Horst",
    "wof:placetype":"neighbourhood"
},
  "geometry": {"coordinates":[12.05047,53.15098],"type":"Point"}
}