{
  "type": "Feature",
  "properties": {
    "gn:admin1_code":"2",
    "gn:admin2_code":"92.0",
    "gn:admin3_code":"9271.0",
    "gn:admin4_code":"9271114.0",
    "gn:asciiname":"Reiserhof",
    "gn:country_code":"DE",
    "gn:dem":393,
    "gn:feature_class":"P",
    "gn:feature_code":"PPL",
    "gn:name":"Reiserhof",
    "gn:population":0,
    "gn:timezone":"Europe/Berlin",
    "iso:country":"DE",
    "wof:name":"Reiserhof",
    "wof:placetype":"neighbourhood"
},
  "geometry": {"coordinates":[13.22805,48.72832],"type":"Point"}
}