{
  "type": "Feature",
  "properties": {
    "gn:admin1_code":"7",
    "gn:admin2_code":"53.0",
    "gn:admin3_code":"5366.0",
    "gn:admin4_code":"5366020.0",
    "gn:asciiname":"Oberschoembach",
    "gn:country_code":"DE",
    "gn:dem":576,
    "gn:feature_class":"P",
    "gn:feature_code":"PPL",
    "gn:name":"Obersch\u00f6mbach",
    "gn:population":0,
    "gn:timezone":"Europe/Berlin",
    "iso:country":"DE",
    "wof:name":"Oberschoembach",
    "wof:placetype":"neighbourhood"
},
  "geometry": {"coordinates":[6.49758,50.43955],"type":"Point"}
}