{
  "type": "Feature",
  "properties": {
    "gn:admin1_code":"12",
    "gn:admin2_code":"0.0",
    "gn:admin3_code":"13074.0",
    "gn:admin4_code":"13074057.0",
    "gn:asciiname":"Ruegkamp",
    "gn:country_code":"DE",
    "gn:dem":48,
    "gn:feature_class":"P",
    "gn:feature_code":"PPL",
    "gn:name":"R\u00fcgkamp",
    "gn:population":0,
    "gn:timezone":"Europe/Berlin",
    "iso:country":"DE",
    "wof:name":"Ruegkamp",
    "wof:placetype":"neighbourhood"
},
  "geometry": {"coordinates":[11.6557,53.86526],"type":"Point"}
}