{
  "type": "Feature",
  "properties": {
    "gn:admin1_code":"7",
    "gn:admin2_code":"51.0",
    "gn:admin3_code":"5166.0",
    "gn:admin4_code":"5166016.0",
    "gn:asciiname":"Busch",
    "gn:country_code":"DE",
    "gn:dem":41,
    "gn:feature_class":"P",
    "gn:feature_code":"PPL",
    "gn:name":"Busch",
    "gn:population":0,
    "gn:timezone":"Europe/Berlin",
    "iso:country":"DE",
    "name:ceb_x_preferred":[
        "Busch"
    ],
    "name:deu_x_preferred":[
        "Busch"
    ],
    "name:fra_x_preferred":[
        "Busch"
    ],
    "name:frr_x_preferred":[
        "Bosk"
    ],
    "name:ita_x_preferred":[
        "Busch"
    ],
    "name:nld_x_preferred":[
        "Busch"
    ],
    "name:spa_x_preferred":[
        "Busch"
    ],
    "name:swe_x_preferred":[
        "Busch"
    ],
    "wof:name":"Busch",
    "wof:placetype":"neighbourhood"
},
  "geometry": {"coordinates":[6.22836,51.32514000000001],"type":"Point"}
}