{
  "type": "Feature",
  "properties": {
    "gn:admin1_code":"2",
    "gn:admin2_code":"94.0",
    "gn:admin3_code":"9475.0",
    "gn:admin4_code":"9475165.0",
    "gn:asciiname":"Pinzig",
    "gn:country_code":"DE",
    "gn:dem":621,
    "gn:feature_class":"P",
    "gn:feature_code":"PPL",
    "gn:name":"Pinzig",
    "gn:population":0,
    "gn:timezone":"Europe/Berlin",
    "iso:country":"DE",
    "wof:name":"Pinzig",
    "wof:placetype":"neighbourhood"
},
  "geometry": {"coordinates":[11.78167,50.26826],"type":"Point"}
}