{
  "type": "Feature",
  "properties": {
    "gn:admin1_code":"2.0",
    "gn:admin2_code":"92.0",
    "gn:admin3_code":"9278.0",
    "gn:admin4_code":"9278116.0",
    "gn:asciiname":"Au",
    "gn:country_code":"DE",
    "gn:dem":337,
    "gn:feature_class":"P",
    "gn:feature_code":"PPL",
    "gn:name":"Au",
    "gn:population":0,
    "gn:timezone":"Europe/Berlin",
    "iso:country":"DE",
    "name:cat_x_preferred":[
        "Au"
    ],
    "name:est_x_preferred":[
        "Au"
    ],
    "name:hun_x_preferred":[
        "Au"
    ],
    "wof:name":"Au",
    "wof:placetype":"neighbourhood"
},
  "geometry": {"coordinates":[12.63713,48.98467],"type":"Point"}
}