{
  "type": "Feature",
  "properties": {
    "gn:admin1_code":"13",
    "gn:admin2_code":"0.0",
    "gn:admin3_code":"14627.0",
    "gn:admin4_code":"14627260.0",
    "gn:asciiname":"Gleina",
    "gn:country_code":"DE",
    "gn:dem":141,
    "gn:feature_class":"P",
    "gn:feature_code":"PPL",
    "gn:name":"Gleina",
    "gn:population":0,
    "gn:timezone":"Europe/Berlin",
    "iso:country":"DE",
    "name:bak_x_preferred":[
        "\u0413\u043b\u0430\u0439\u043d\u0430"
    ],
    "name:deu_x_preferred":[
        "Gleina"
    ],
    "name:epo_x_preferred":[
        "Gleina"
    ],
    "name:fas_x_preferred":[
        "\u06af\u0644\u0627\u06cc\u0646\u0627"
    ],
    "name:fra_x_preferred":[
        "Gleina"
    ],
    "name:hun_x_preferred":[
        "Gleina"
    ],
    "name:ita_x_preferred":[
        "Gleina"
    ],
    "name:kaz_x_preferred":[
        "\u0413\u043b\u0430\u0439\u043d\u0430"
    ],
    "name:kir_x_preferred":[
        "\u0413\u043b\u0430\u0439\u043d\u0430"
    ],
    "name:mkd_x_preferred":[
        "\u0413\u043b\u0430\u0458\u043d\u0430"
    ],
    "name:msa_x_preferred":[
        "Gleina"
    ],
    "name:nld_x_preferred":[
        "Gleina"
    ],
    "name:pol_x_preferred":[
        "Gleina"
    ],
    "name:ron_x_preferred":[
        "Gleina"
    ],
    "name:rus_x_preferred":[
        "\u0413\u043b\u0430\u0439\u043d\u0430"
    ],
    "name:spa_x_preferred":[
        "Gleina"
    ],
    "name:srp_x_preferred":[
        "\u0413\u043b\u0430\u0458\u043d\u0430"
    ],
    "name:ukr_x_preferred":[
        "\u0413\u043b\u044f\u0439\u043d\u0430"
    ],
    "name:uzb_x_preferred":[
        "Gleina"
    ],
    "name:vie_x_preferred":[
        "Gleina"
    ],
    "name:vol_x_preferred":[
        "Gleina"
    ],
    "name:war_x_preferred":[
        "Gleina"
    ],
    "name:zho_x_preferred":[
        "\u683c\u83b1\u7eb3"
    ],
    "wof:name":"Gleina",
    "wof:placetype":"neighbourhood"
},
  "geometry": {"coordinates":[13.24563,51.23412],"type":"Point"}
}