{
  "type": "Feature",
  "properties": {
    "gn:admin1_code":"6",
    "gn:admin2_code":"0.0",
    "gn:admin3_code":"3458.0",
    "gn:admin4_code":"3458007.0",
    "gn:asciiname":"Ostsiedlung Alhorn",
    "gn:country_code":"DE",
    "gn:dem":48,
    "gn:feature_class":"P",
    "gn:feature_code":"PPL",
    "gn:name":"Ostsiedlung Alhorn",
    "gn:population":0,
    "gn:timezone":"Europe/Berlin",
    "iso:country":"DE",
    "wof:name":"Ostsiedlung Alhorn",
    "wof:placetype":"neighbourhood"
},
  "geometry": {"coordinates":[8.24569,52.88342],"type":"Point"}
}