{
  "type": "Feature",
  "properties": {
    "gn:admin1_code":"5",
    "gn:admin2_code":"66.0",
    "gn:admin3_code":"6634.0",
    "gn:admin4_code":"6634003.0",
    "gn:asciiname":"Niedervorschuetz",
    "gn:country_code":"DE",
    "gn:dem":167,
    "gn:feature_class":"P",
    "gn:feature_code":"PPL",
    "gn:name":"Niedervorsch\u00fctz",
    "gn:population":0,
    "gn:timezone":"Europe/Berlin",
    "iso:country":"DE",
    "wof:name":"Niedervorschuetz",
    "wof:placetype":"neighbourhood"
},
  "geometry": {"coordinates":[9.38153,51.15051],"type":"Point"}
}