{
  "type": "Feature",
  "properties": {
    "iso:country":"DE",
    "wof:name":"Horn Marsch",
    "wof:placetype":"microhood"
},
  "geometry": {"coordinates":[10.077152,53.544803],"type":"Point"}
}