{
  "type": "Feature",
  "properties": {
    "gn:admin1_code":"13",
    "gn:admin2_code":"0.0",
    "gn:admin3_code":"14511.0",
    "gn:admin4_code":"14511000.0",
    "gn:asciiname":"Gablenz",
    "gn:country_code":"DE",
    "gn:dem":339,
    "gn:feature_class":"P",
    "gn:feature_code":"PPL",
    "gn:name":"Gablenz",
    "gn:population":0,
    "gn:timezone":"Europe/Berlin",
    "iso:country":"DE",
    "name:bak_x_preferred":[
        "\u0413\u0430\u0431\u043b\u0435\u043d\u0446"
    ],
    "name:ceb_x_preferred":[
        "Gablenz"
    ],
    "name:deu_x_preferred":[
        "Gablenz"
    ],
    "name:fra_x_preferred":[
        "Gablenz"
    ],
    "name:pol_x_preferred":[
        "Gablenz"
    ],
    "name:rus_x_preferred":[
        "\u0413\u0430\u0431\u043b\u0435\u043d\u0446"
    ],
    "name:swe_x_preferred":[
        "Gablenz"
    ],
    "name:ukr_x_preferred":[
        "\u0413\u0430\u0431\u043b\u0435\u043d\u0446"
    ],
    "wof:name":"Gablenz",
    "wof:placetype":"neighbourhood"
},
  "geometry": {"coordinates":[12.96763,50.82723],"type":"Point"}
}