{
  "type": "Feature",
  "properties": {
    "gn:admin1_code":"1",
    "gn:admin2_code":"81.0",
    "gn:admin3_code":"8117.0",
    "gn:admin4_code":"8117020.0",
    "gn:asciiname":"Lotenberg",
    "gn:country_code":"DE",
    "gn:dem":482,
    "gn:feature_class":"P",
    "gn:feature_code":"PPL",
    "gn:name":"Lotenberg",
    "gn:population":0,
    "gn:timezone":"Europe/Berlin",
    "iso:country":"DE",
    "wof:name":"Lotenberg",
    "wof:placetype":"neighbourhood"
},
  "geometry": {"coordinates":[9.66123,48.64051],"type":"Point"}
}