{
  "type": "Feature",
  "properties": {
    "gn:admin1_code":"2",
    "gn:admin2_code":"96.0",
    "gn:admin3_code":"9674.0",
    "gn:admin4_code":"9674111.0",
    "gn:asciiname":"Nassach",
    "gn:country_code":"DE",
    "gn:dem":327,
    "gn:feature_class":"P",
    "gn:feature_code":"PPL",
    "gn:name":"Nassach",
    "gn:population":0,
    "gn:timezone":"Europe/Berlin",
    "iso:country":"DE",
    "name:ceb_x_preferred":[
        "Nassach"
    ],
    "name:deu_x_preferred":[
        "Nassach"
    ],
    "name:swe_x_preferred":[
        "Nassach"
    ],
    "wof:name":"Nassach",
    "wof:placetype":"neighbourhood"
},
  "geometry": {"coordinates":[10.45965,50.1877],"type":"Point"}
}