{
  "type": "Feature",
  "properties": {
    "gn:admin1_code":"2",
    "gn:admin2_code":"97.0",
    "gn:admin3_code":"9780.0",
    "gn:admin4_code":"9780140.0",
    "gn:asciiname":"Eigen",
    "gn:country_code":"DE",
    "gn:dem":735,
    "gn:feature_class":"P",
    "gn:feature_code":"PPL",
    "gn:name":"Eigen",
    "gn:population":0,
    "gn:timezone":"Europe/Berlin",
    "iso:country":"DE",
    "name:ceb_x_preferred":[
        "Eigen"
    ],
    "name:deu_x_preferred":[
        "Eigen"
    ],
    "name:epo_x_preferred":[
        "Eigen"
    ],
    "name:fra_x_preferred":[
        "Eigen"
    ],
    "name:pol_x_preferred":[
        "Eigen"
    ],
    "name:spa_x_preferred":[
        "Eigen"
    ],
    "name:swe_x_preferred":[
        "Eigen"
    ],
    "wof:name":"Eigen",
    "wof:placetype":"neighbourhood"
},
  "geometry": {"coordinates":[10.34319,47.67027],"type":"Point"}
}