{
  "type": "Feature",
  "properties": {
    "gn:admin1_code":"2",
    "gn:admin2_code":"96.0",
    "gn:admin3_code":"9678.0",
    "gn:admin4_code":"9678192.0",
    "gn:asciiname":"Kaisten",
    "gn:country_code":"DE",
    "gn:dem":302,
    "gn:feature_class":"P",
    "gn:feature_code":"PPL",
    "gn:name":"Kaisten",
    "gn:population":0,
    "gn:timezone":"Europe/Berlin",
    "iso:country":"DE",
    "name:ceb_x_preferred":[
        "Kaisten"
    ],
    "name:deu_x_preferred":[
        "Kaisten"
    ],
    "name:epo_x_preferred":[
        "Kaisten"
    ],
    "name:eus_x_preferred":[
        "Kaisten"
    ],
    "name:pol_x_preferred":[
        "Kaisten"
    ],
    "wof:name":"Kaisten",
    "wof:placetype":"neighbourhood"
},
  "geometry": {"coordinates":[10.05438,50.04347],"type":"Point"}
}