{
  "type": "Feature",
  "properties": {
    "iso:country":"DE",
    "wof:name":"Horn",
    "wof:placetype":"neighbourhood"
},
  "geometry": {"coordinates":[7.01404372494357,51.12774800348559],"type":"Point"}
}