{
  "type": "Feature",
  "properties": {
    "gn:admin1_code":"8",
    "gn:admin2_code":"0.0",
    "gn:admin3_code":"7133.0",
    "gn:admin4_code":"7133006.0",
    "gn:asciiname":"Theodorshalle",
    "gn:country_code":"DE",
    "gn:dem":111,
    "gn:feature_class":"P",
    "gn:feature_code":"PPL",
    "gn:name":"Theodorshalle",
    "gn:population":0,
    "gn:timezone":"Europe/Berlin",
    "iso:country":"DE",
    "wof:name":"Theodorshalle",
    "wof:placetype":"neighbourhood"
},
  "geometry": {"coordinates":[7.85,49.81667],"type":"Point"}
}