{
  "type": "Feature",
  "properties": {
    "gn:admin1_code":"1",
    "gn:admin2_code":"83.0",
    "gn:admin3_code":"8337.0",
    "gn:admin4_code":"8337128.0",
    "gn:asciiname":"Riedern am Wald",
    "gn:country_code":"DE",
    "gn:dem":693,
    "gn:feature_class":"P",
    "gn:feature_code":"PPL",
    "gn:name":"Riedern am Wald",
    "gn:population":0,
    "gn:timezone":"Europe/Berlin",
    "iso:country":"DE",
    "name:als_x_preferred":[
        "Riedern am Wald"
    ],
    "name:deu_x_preferred":[
        "Riedern am Wald"
    ],
    "name:und_x_variant":[
        "Riedern"
    ],
    "wof:name":"Riedern am Wald",
    "wof:placetype":"neighbourhood"
},
  "geometry": {"coordinates":[8.29176,47.71711],"type":"Point"}
}