{
  "type": "Feature",
  "properties": {
    "gn:admin1_code":"2",
    "gn:admin2_code":"91.0",
    "gn:admin3_code":"9185.0",
    "gn:admin4_code":"9185166.0",
    "gn:asciiname":"Kaifeck",
    "gn:country_code":"DE",
    "gn:dem":404,
    "gn:feature_class":"P",
    "gn:feature_code":"PPL",
    "gn:name":"Kaifeck",
    "gn:population":0,
    "gn:timezone":"Europe/Berlin",
    "iso:country":"DE",
    "wof:name":"Kaifeck",
    "wof:placetype":"neighbourhood"
},
  "geometry": {"coordinates":[11.32718,48.58496],"type":"Point"}
}