{
  "type": "Feature",
  "properties": {
    "gn:admin1_code":"7",
    "gn:admin2_code":"59.0",
    "gn:admin3_code":"5966.0",
    "gn:admin4_code":"5966028.0",
    "gn:asciiname":"Schoenau",
    "gn:country_code":"DE",
    "gn:dem":385,
    "gn:feature_class":"P",
    "gn:feature_code":"PPL",
    "gn:name":"Sch\u00f6nau",
    "gn:population":0,
    "gn:timezone":"Europe/Berlin",
    "iso:country":"DE",
    "wof:name":"Schoenau",
    "wof:placetype":"neighbourhood"
},
  "geometry": {"coordinates":[7.90613,50.97589],"type":"Point"}
}