{
  "type": "Feature",
  "properties": {
    "gn:admin1_code":"10",
    "gn:admin2_code":"0.0",
    "gn:admin3_code":"1051.0",
    "gn:admin4_code":"1051062.0",
    "gn:asciiname":"Schafstedt",
    "gn:country_code":"DE",
    "gn:dem":0,
    "gn:feature_class":"P",
    "gn:feature_code":"PPLL",
    "gn:name":"Schafstedt",
    "gn:population":0,
    "gn:timezone":"Europe/Berlin",
    "iso:country":"DE",
    "name:ceb_x_preferred":[
        "Schafstedt"
    ],
    "name:dan_x_preferred":[
        "Schafstedt"
    ],
    "name:deu_x_preferred":[
        "Schafstedt"
    ],
    "name:epo_x_preferred":[
        "Schafstedt"
    ],
    "name:eus_x_preferred":[
        "Schafstedt"
    ],
    "name:fas_x_preferred":[
        "\u0634\u0627\u0641\u0634\u062a\u062f\u062a"
    ],
    "name:fra_x_preferred":[
        "Schafstedt"
    ],
    "name:hun_x_preferred":[
        "Schafstedt"
    ],
    "name:ind_x_preferred":[
        "Schafstedt"
    ],
    "name:ita_x_preferred":[
        "Schafstedt"
    ],
    "name:mkd_x_preferred":[
        "\u0428\u0430\u0444\u0448\u0442\u0435\u0442"
    ],
    "name:msa_x_preferred":[
        "Schafstedt"
    ],
    "name:nld_x_preferred":[
        "Schafstedt"
    ],
    "name:nor_x_preferred":[
        "Schafstedt"
    ],
    "name:pol_x_preferred":[
        "Schafstedt"
    ],
    "name:por_x_preferred":[
        "Schafstedt"
    ],
    "name:ron_x_preferred":[
        "Schafstedt"
    ],
    "name:rus_x_preferred":[
        "\u0428\u0430\u0444\u0448\u0442\u0435\u0434\u0442"
    ],
    "name:spa_x_preferred":[
        "Schafstedt"
    ],
    "name:srp_x_preferred":[
        "\u0428\u0430\u0444\u0448\u0442\u0435\u0442"
    ],
    "name:tur_x_preferred":[
        "Schafstedt"
    ],
    "name:ukr_x_preferred":[
        "\u0428\u0430\u0444\u0448\u0442\u0435\u0434\u0442"
    ],
    "name:uzb_x_preferred":[
        "Schafstedt"
    ],
    "name:vie_x_preferred":[
        "Schafstedt"
    ],
    "name:vol_x_preferred":[
        "Schafstedt"
    ],
    "name:war_x_preferred":[
        "Schafstedt"
    ],
    "name:zho_x_preferred":[
        "\u6c99\u592b\u65bd\u6cf0\u7279"
    ],
    "wof:name":"Schafstedt",
    "wof:placetype":"neighbourhood"
},
  "geometry": {"coordinates":[8.96375,53.94027],"type":"Point"}
}