{
  "type": "Feature",
  "properties": {
    "gn:admin1_code":"2",
    "gn:admin2_code":"94.0",
    "gn:admin3_code":"9475.0",
    "gn:admin4_code":"9475171.0",
    "gn:asciiname":"Wachholderbusch",
    "gn:country_code":"DE",
    "gn:dem":611,
    "gn:feature_class":"P",
    "gn:feature_code":"PPL",
    "gn:name":"Wachholderbusch",
    "gn:population":0,
    "gn:timezone":"Europe/Berlin",
    "iso:country":"DE",
    "wof:name":"Wachholderbusch",
    "wof:placetype":"neighbourhood"
},
  "geometry": {"coordinates":[11.77386,50.34276],"type":"Point"}
}