{
  "type": "Feature",
  "properties": {
    "gn:admin1_code":"1.0",
    "gn:admin2_code":"82.0",
    "gn:admin3_code":"8235.0",
    "gn:admin4_code":"8235006.0",
    "gn:asciiname":"Berneck",
    "gn:country_code":"DE",
    "gn:dem":457,
    "gn:feature_class":"P",
    "gn:feature_code":"PPL",
    "gn:name":"Berneck",
    "gn:population":0,
    "gn:timezone":"Europe/Berlin",
    "iso:country":"DE",
    "name:ceb_x_preferred":[
        "Berneck"
    ],
    "name:deu_x_preferred":[
        "Berneck"
    ],
    "name:pol_x_preferred":[
        "Berneck"
    ],
    "name:rus_x_preferred":[
        "\u0411\u0435\u0440\u043d\u0435\u043a"
    ],
    "name:swe_x_preferred":[
        "Berneck"
    ],
    "wof:name":"Berneck",
    "wof:placetype":"neighbourhood"
},
  "geometry": {"coordinates":[8.61657,48.60355],"type":"Point"}
}