{
  "type": "Feature",
  "properties": {
    "gn:admin1_code":"12",
    "gn:admin2_code":"0.0",
    "gn:admin3_code":"13073.0",
    "gn:admin4_code":"13073019.0",
    "gn:asciiname":"Hof Dranske",
    "gn:country_code":"DE",
    "gn:dem":7,
    "gn:feature_class":"P",
    "gn:feature_code":"PPL",
    "gn:name":"Hof Dranske",
    "gn:population":0,
    "gn:timezone":"Europe/Berlin",
    "iso:country":"DE",
    "wof:name":"Hof Dranske",
    "wof:placetype":"neighbourhood"
},
  "geometry": {"coordinates":[13.23874,54.64014],"type":"Point"}
}