{
  "type": "Feature",
  "properties": {
    "gn:admin1_code":"7",
    "gn:admin2_code":"53.0",
    "gn:admin3_code":"5374.0",
    "gn:admin4_code":"5374020.0",
    "gn:asciiname":"Oberbreidenbach",
    "gn:country_code":"DE",
    "gn:dem":208,
    "gn:feature_class":"P",
    "gn:feature_code":"PPL",
    "gn:name":"Oberbreidenbach",
    "gn:population":0,
    "gn:timezone":"Europe/Berlin",
    "iso:country":"DE",
    "wof:name":"Oberbreidenbach",
    "wof:placetype":"neighbourhood"
},
  "geometry": {"coordinates":[7.34149,51.03206],"type":"Point"}
}