{
  "type": "Feature",
  "properties": {
    "gn:admin1_code":"9",
    "gn:admin2_code":"0.0",
    "gn:admin3_code":"10044.0",
    "gn:admin4_code":"10044115.0",
    "gn:asciiname":"Neuforweiler",
    "gn:country_code":"DE",
    "gn:dem":216,
    "gn:feature_class":"P",
    "gn:feature_code":"PPL",
    "gn:name":"Neuforweiler",
    "gn:population":0,
    "gn:timezone":"Europe/Berlin",
    "iso:country":"DE",
    "wof:name":"Neuforweiler",
    "wof:placetype":"locality"
},
  "geometry": {"coordinates":[6.72971,49.28695],"type":"Point"}
}