{
  "type": "Feature",
  "properties": {
    "gn:admin1_code":"2",
    "gn:admin2_code":"94.0",
    "gn:admin3_code":"9472.0",
    "gn:admin4_code":"9472179.0",
    "gn:asciiname":"Tragweis",
    "gn:country_code":"DE",
    "gn:dem":495,
    "gn:feature_class":"P",
    "gn:feature_code":"PPL",
    "gn:name":"Tr\u00e4gweis",
    "gn:population":0,
    "gn:timezone":"Europe/Berlin",
    "iso:country":"DE",
    "wof:name":"Tragweis",
    "wof:placetype":"neighbourhood"
},
  "geometry": {"coordinates":[11.37447,49.74193],"type":"Point"}
}