{
  "type": "Feature",
  "properties": {
    "gn:admin1_code":"2.0",
    "gn:admin2_code":"97.0",
    "gn:admin3_code":"9777.0",
    "gn:admin4_code":"9777111.0",
    "gn:asciiname":"Binnings",
    "gn:country_code":"DE",
    "gn:dem":808,
    "gn:feature_class":"P",
    "gn:feature_code":"PPL",
    "gn:name":"Binnings",
    "gn:population":0,
    "gn:timezone":"Europe/Berlin",
    "iso:country":"DE",
    "wof:name":"Binnings",
    "wof:placetype":"neighbourhood"
},
  "geometry": {"coordinates":[10.49578,47.82954],"type":"Point"}
}