{
  "type": "Feature",
  "properties": {
    "gn:admin1_code":"2",
    "gn:admin2_code":"94.0",
    "gn:admin3_code":"9477.0",
    "gn:admin4_code":"9477136.0",
    "gn:asciiname":"Fassoldshof",
    "gn:country_code":"DE",
    "gn:dem":301,
    "gn:feature_class":"P",
    "gn:feature_code":"PPL",
    "gn:name":"Fassoldshof",
    "gn:population":0,
    "gn:timezone":"Europe/Berlin",
    "iso:country":"DE",
    "wof:name":"Fassoldshof",
    "wof:placetype":"neighbourhood"
},
  "geometry": {"coordinates":[11.34484,50.11491],"type":"Point"}
}