{
  "type": "Feature",
  "properties": {
    "gn:admin1_code":"7",
    "gn:admin2_code":"57.0",
    "gn:admin3_code":"5766.0",
    "gn:admin4_code":"5766028.0",
    "gn:asciiname":"Hohensonne",
    "gn:country_code":"DE",
    "gn:dem":300,
    "gn:feature_class":"P",
    "gn:feature_code":"PPL",
    "gn:name":"Hohensonne",
    "gn:population":0,
    "gn:timezone":"Europe/Berlin",
    "iso:country":"DE",
    "wof:name":"Hohensonne",
    "wof:placetype":"neighbourhood"
},
  "geometry": {"coordinates":[9.07771,52.04299],"type":"Point"}
}