{
  "type": "Feature",
  "properties": {
    "gn:gn_country":"DE",
    "gn:gn_fcode":"PPLA4",
    "gn:gn_pop":368,
    "gn:population":368,
    "iso:country":"DE",
    "name:baq_x_preferred":[
        "Manubach"
    ],
    "name:chi_x_preferred":[
        "\u9a6c\u52aa\u5df4\u8d6b"
    ],
    "name:dut_x_preferred":[
        "Manubach"
    ],
    "name:eng_x_preferred":[
        "Manubach"
    ],
    "name:epo_x_preferred":[
        "Manubach"
    ],
    "name:fre_x_preferred":[
        "Manubach"
    ],
    "name:ger_x_preferred":[
        "Manubach"
    ],
    "name:hun_x_preferred":[
        "Manubach"
    ],
    "name:ita_x_preferred":[
        "Manubach"
    ],
    "name:jpn_x_preferred":[
        "\u30de\u30cc\u30d0\u30c3\u30cf"
    ],
    "name:kaz_x_preferred":[
        "\u041c\u0430\u043d\u0443\u0431\u0430\u0445"
    ],
    "name:kir_x_preferred":[
        "\u041c\u0430\u043d\u0443\u0431\u0430\u0445"
    ],
    "name:may_x_preferred":[
        "Manubach"
    ],
    "name:per_x_preferred":[
        "\u0645\u0627\u0646\u0648\u0628\u0627\u062e"
    ],
    "name:pol_x_preferred":[
        "Manubach"
    ],
    "name:por_x_preferred":[
        "Manubach"
    ],
    "name:rum_x_preferred":[
        "Manubach"
    ],
    "name:rus_x_preferred":[
        "\u041c\u0430\u043d\u0443\u0431\u0430\u0445"
    ],
    "name:srp_x_preferred":[
        "\u041c\u0430\u043d\u0443\u0431\u0430\u0445"
    ],
    "name:ukr_x_preferred":[
        "\u041c\u0430\u043d\u0443\u0431\u0430\u0445"
    ],
    "name:uzb_x_preferred":[
        "Manubach"
    ],
    "name:vol_x_preferred":[
        "Manubach"
    ],
    "name:war_x_preferred":[
        "Manubach"
    ],
    "qs_pg:aaroncc":"DE",
    "qs_pg:gn_country":"DE",
    "qs_pg:gn_fcode":"PPLA4",
    "qs_pg:gn_pop":368,
    "qs_pg:name":"Manubach",
    "qs_pg:photos_9r":0,
    "qs_pg:photos_sr":0,
    "qs_pg:pop_sr":2,
    "qs_pg:qs_pg_placetype":"locality",
    "wof:name":"Manubach",
    "wof:placetype":"locality",
    "wof:population":368
},
  "geometry": {"coordinates":[7.75,50.03333],"type":"Point"}
}