{
  "type": "Feature",
  "properties": {
    "gn:admin1_code":"13",
    "gn:admin2_code":"0.0",
    "gn:admin3_code":"14729.0",
    "gn:admin4_code":"14729220.0",
    "gn:asciiname":"Thierbach",
    "gn:country_code":"DE",
    "gn:dem":162,
    "gn:feature_class":"P",
    "gn:feature_code":"PPL",
    "gn:name":"Thierbach",
    "gn:population":0,
    "gn:timezone":"Europe/Berlin",
    "iso:country":"DE",
    "name:chv_x_preferred":[
        "\u0422\u0438\u0440\u0431\u0430\u0445"
    ],
    "name:deu_x_preferred":[
        "Thierbach"
    ],
    "name:rus_x_preferred":[
        "\u0422\u0438\u0440\u0431\u0430\u0445"
    ],
    "wof:name":"Thierbach",
    "wof:placetype":"neighbourhood"
},
  "geometry": {"coordinates":[12.53107,51.17271],"type":"Point"}
}