{
  "type": "Feature",
  "properties": {
    "gn:admin1_code":"2",
    "gn:admin2_code":"97.0",
    "gn:admin3_code":"9777.0",
    "gn:admin4_code":"9777128.0",
    "gn:asciiname":"Salenwang",
    "gn:country_code":"DE",
    "gn:dem":750,
    "gn:feature_class":"P",
    "gn:feature_code":"PPL",
    "gn:name":"Salenwang",
    "gn:population":0,
    "gn:timezone":"Europe/Berlin",
    "iso:country":"DE",
    "wof:name":"Salenwang",
    "wof:placetype":"neighbourhood"
},
  "geometry": {"coordinates":[10.53252,47.85461],"type":"Point"}
}