{
  "type": "Feature",
  "properties": {
    "gn:admin1_code":"13",
    "gn:admin2_code":"0.0",
    "gn:admin3_code":"14625.0",
    "gn:admin4_code":"14625470.0",
    "gn:asciiname":"Neudoerfel",
    "gn:country_code":"DE",
    "gn:dem":151,
    "gn:feature_class":"P",
    "gn:feature_code":"PPL",
    "gn:name":"Neud\u00f6rfel",
    "gn:population":0,
    "gn:timezone":"Europe/Berlin",
    "iso:country":"DE",
    "name:hsb_x_preferred":[
        "Nowa Wjeska"
    ],
    "wof:name":"Neudoerfel",
    "wof:placetype":"neighbourhood"
},
  "geometry": {"coordinates":[14.23294,51.26794],"type":"Point"}
}