{
  "type": "Feature",
  "properties": {
    "gn:admin1_code":"2.0",
    "gn:admin2_code":"094",
    "gn:admin3_code":"9471.0",
    "gn:admin4_code":"9471185.0",
    "gn:asciiname":"Wiesengiech",
    "gn:country_code":"DE",
    "gn:dem":281,
    "gn:feature_class":"P",
    "gn:feature_code":"PPL",
    "gn:name":"Wiesengiech",
    "gn:population":0,
    "gn:timezone":"Europe/Berlin",
    "iso:country":"DE",
    "wof:name":"Wiesengiech",
    "wof:placetype":"neighbourhood"
},
  "geometry": {"coordinates":[10.99646,49.9626],"type":"Point"}
}