{
  "type": "Feature",
  "properties": {
    "gn:admin1_code":"6.0",
    "gn:admin2_code":"00",
    "gn:admin3_code":"3351.0",
    "gn:admin4_code":"3351006.0",
    "gn:asciiname":"Wietzenbruch",
    "gn:country_code":"DE",
    "gn:dem":38,
    "gn:feature_class":"P",
    "gn:feature_code":"PPL",
    "gn:name":"Wietzenbruch",
    "gn:population":0,
    "gn:timezone":"Europe/Berlin",
    "iso:country":"DE",
    "name:ceb_x_preferred":[
        "Wietzenbruch"
    ],
    "name:deu_x_preferred":[
        "Wietzenbruch"
    ],
    "name:fas_x_preferred":[
        "\u0648\u06cc\u062a\u0633\u0646\u0628\u0631\u0648\u062e"
    ],
    "wof:name":"Wietzenbruch",
    "wof:placetype":"neighbourhood"
},
  "geometry": {"coordinates":[10.01551,52.60337],"type":"Point"}
}