{
  "type": "Feature",
  "properties": {
    "gn:admin1_code":"9",
    "gn:admin2_code":"0.0",
    "gn:admin3_code":"10041.0",
    "gn:admin4_code":"10041513.0",
    "gn:asciiname":"Numborn",
    "gn:country_code":"DE",
    "gn:dem":293,
    "gn:feature_class":"P",
    "gn:feature_code":"PPL",
    "gn:name":"Numborn",
    "gn:population":0,
    "gn:timezone":"Europe/Berlin",
    "iso:country":"DE",
    "wof:name":"Numborn",
    "wof:placetype":"neighbourhood"
},
  "geometry": {"coordinates":[6.97215,49.34783],"type":"Point"}
}