{
  "type": "Feature",
  "properties": {
    "gn:admin1_code":"13",
    "gn:admin2_code":"0.0",
    "gn:admin3_code":"14625.0",
    "gn:admin4_code":"14625525.0",
    "gn:asciiname":"Halbendorf",
    "gn:country_code":"DE",
    "gn:dem":246,
    "gn:feature_class":"P",
    "gn:feature_code":"PPL",
    "gn:name":"Halbendorf",
    "gn:population":0,
    "gn:timezone":"Europe/Berlin",
    "iso:country":"DE",
    "name:deu_x_preferred":[
        "Halbendorf/Gebirge"
    ],
    "name:hsb_x_preferred":[
        "Wbohow"
    ],
    "wof:name":"Halbendorf",
    "wof:placetype":"neighbourhood"
},
  "geometry": {"coordinates":[14.46467,51.09816],"type":"Point"}
}