{
  "type": "Feature",
  "properties": {
    "gn:admin1_code":"2",
    "gn:admin2_code":"91.0",
    "gn:admin3_code":"9182.0",
    "gn:admin4_code":"9182116.0",
    "gn:asciiname":"Ostin",
    "gn:country_code":"DE",
    "gn:dem":778,
    "gn:feature_class":"P",
    "gn:feature_code":"PPL",
    "gn:name":"Ostin",
    "gn:population":0,
    "gn:timezone":"Europe/Berlin",
    "iso:country":"DE",
    "wof:name":"Ostin",
    "wof:placetype":"neighbourhood"
},
  "geometry": {"coordinates":[11.76215,47.74521],"type":"Point"}
}