{
  "type": "Feature",
  "properties": {
    "gn:admin1_code":"2",
    "gn:admin2_code":"92.0",
    "gn:admin3_code":"9272.0",
    "gn:admin4_code":"9272149.0",
    "gn:asciiname":"Pronfelden",
    "gn:country_code":"DE",
    "gn:dem":727,
    "gn:feature_class":"P",
    "gn:feature_code":"PPL",
    "gn:name":"Pronfelden",
    "gn:population":0,
    "gn:timezone":"Europe/Berlin",
    "iso:country":"DE",
    "wof:name":"Pronfelden",
    "wof:placetype":"neighbourhood"
},
  "geometry": {"coordinates":[13.36581,48.91184000000001],"type":"Point"}
}