{
  "type": "Feature",
  "properties": {
    "gn:admin1_code":"2",
    "gn:admin2_code":"91.0",
    "gn:admin3_code":"9174.0",
    "gn:admin4_code":"9174141.0",
    "gn:asciiname":"Grossinzemoos",
    "gn:country_code":"DE",
    "gn:dem":489,
    "gn:feature_class":"P",
    "gn:feature_code":"PPL",
    "gn:name":"Gro\u00dfinzemoos",
    "gn:population":0,
    "gn:timezone":"Europe/Berlin",
    "iso:country":"DE",
    "wof:name":"Grossinzemoos",
    "wof:placetype":"neighbourhood"
},
  "geometry": {"coordinates":[11.42715,48.33725],"type":"Point"}
}