{
  "type": "Feature",
  "properties": {
    "gn:admin1_code":"9",
    "gn:admin2_code":"0.0",
    "gn:admin3_code":"10046.0",
    "gn:admin4_code":"10046115.0",
    "gn:asciiname":"Otzenhausen",
    "gn:country_code":"DE",
    "gn:dem":451,
    "gn:feature_class":"P",
    "gn:feature_code":"PPL",
    "gn:name":"Otzenhausen",
    "gn:population":0,
    "gn:timezone":"Europe/Berlin",
    "iso:country":"DE",
    "wof:name":"Otzenhausen",
    "wof:placetype":"neighbourhood"
},
  "geometry": {"coordinates":[6.9918,49.60496],"type":"Point"}
}