{
  "type": "Feature",
  "properties": {
    "gn:admin1_code":"13.0",
    "gn:admin2_code":"0.0",
    "gn:admin3_code":"14523.0",
    "gn:admin4_code":"14523020.0",
    "gn:asciiname":"Bad Reiboldsgruen",
    "gn:country_code":"DE",
    "gn:dem":687,
    "gn:feature_class":"P",
    "gn:feature_code":"PPL",
    "gn:name":"Bad Reiboldsgr\u00fcn",
    "gn:population":0,
    "gn:timezone":"Europe/Berlin",
    "iso:country":"DE",
    "wof:name":"Bad Reiboldsgruen",
    "wof:placetype":"neighbourhood"
},
  "geometry": {"coordinates":[12.45595,50.48945],"type":"Point"}
}