{
  "type": "Feature",
  "properties": {
    "gn:admin1_code":"11",
    "gn:admin2_code":"0.0",
    "gn:admin3_code":"12070.0",
    "gn:admin4_code":"12070052.0",
    "gn:asciiname":"Mittel-Breese",
    "gn:country_code":"DE",
    "gn:dem":26,
    "gn:feature_class":"P",
    "gn:feature_code":"PPL",
    "gn:name":"Mittel-Breese",
    "gn:population":0,
    "gn:timezone":"Europe/Berlin",
    "iso:country":"DE",
    "name:und_x_variant":[
        "Breese",
        "Mittel-Breese"
    ],
    "wof:name":"Mittel-Breese",
    "wof:placetype":"neighbourhood"
},
  "geometry": {"coordinates":[11.79075,53.0048],"type":"Point"}
}