{
  "type": "Feature",
  "properties": {
    "iso:country":"DE",
    "name:deu_x_preferred":[
        "Frankfurt-Gutleutviertel"
    ],
    "name:fra_x_preferred":[
        "Gutleutviertel"
    ],
    "name:nld_x_preferred":[
        "Frankfurt-Gutleutviertel"
    ],
    "name:pol_x_preferred":[
        "Gutleutviertel"
    ],
    "wof:name":"Gutleutviertel",
    "wof:placetype":"neighbourhood"
},
  "geometry": {"coordinates":[8.65414479273808,50.09969808996119],"type":"Point"}
}