{
  "type": "Feature",
  "properties": {
    "gn:admin1_code":"6",
    "gn:admin2_code":"0.0",
    "gn:admin3_code":"3257.0",
    "gn:admin4_code":"3257031.0",
    "gn:asciiname":"Nottberg",
    "gn:country_code":"DE",
    "gn:dem":85,
    "gn:feature_class":"P",
    "gn:feature_code":"PPL",
    "gn:name":"Nottberg",
    "gn:population":0,
    "gn:timezone":"Europe/Berlin",
    "iso:country":"DE",
    "wof:name":"Nottberg",
    "wof:placetype":"neighbourhood"
},
  "geometry": {"coordinates":[9.08089,52.1573],"type":"Point"}
}