{
  "type": "Feature",
  "properties": {
    "gn:admin1_code":"6.0",
    "gn:admin2_code":"00",
    "gn:admin3_code":"3151.0",
    "gn:admin4_code":"3151038.0",
    "gn:asciiname":"Westerholz",
    "gn:country_code":"DE",
    "gn:dem":61,
    "gn:feature_class":"P",
    "gn:feature_code":"PPL",
    "gn:name":"Westerholz",
    "gn:population":0,
    "gn:timezone":"Europe/Berlin",
    "iso:country":"DE",
    "name:dan_x_preferred":[
        "Vesterskov"
    ],
    "name:deu_x_preferred":[
        "Westerholz"
    ],
    "name:epo_x_preferred":[
        "Westerholz"
    ],
    "name:eus_x_preferred":[
        "Westerholz"
    ],
    "name:fas_x_preferred":[
        "\u0648\u0634\u062a\u0631\u0647\u0648\u0644\u062a\u0633"
    ],
    "name:fra_x_preferred":[
        "Westerholz"
    ],
    "name:hun_x_preferred":[
        "Westerholz"
    ],
    "name:ita_x_preferred":[
        "Westerholz"
    ],
    "name:kaz_x_preferred":[
        "\u0412\u0435\u0441\u0442\u0435\u0440\u0445\u043e\u043b\u044c\u0446"
    ],
    "name:kir_x_preferred":[
        "\u0412\u0435\u0441\u0442\u0435\u0440\u0445\u043e\u043b\u044c\u0446"
    ],
    "name:mkd_x_preferred":[
        "\u0412\u0435\u0441\u0442\u0435\u0440\u0445\u043e\u043b\u0446"
    ],
    "name:msa_x_preferred":[
        "Westerholz"
    ],
    "name:nld_x_preferred":[
        "Westerholz"
    ],
    "name:pol_x_preferred":[
        "Westerholz"
    ],
    "name:por_x_preferred":[
        "Westerholz"
    ],
    "name:ron_x_preferred":[
        "Westerholz"
    ],
    "name:rus_x_preferred":[
        "\u0412\u0435\u0441\u0442\u0435\u0440\u0445\u043e\u043b\u044c\u0446"
    ],
    "name:sco_x_preferred":[
        "Westerholz"
    ],
    "name:spa_x_preferred":[
        "Westerholz"
    ],
    "name:srp_x_preferred":[
        "\u0412\u0435\u0441\u0442\u0435\u0440\u0445\u043e\u043b\u0446"
    ],
    "name:tur_x_preferred":[
        "Westerholz"
    ],
    "name:ukr_x_preferred":[
        "\u0412\u0435\u0441\u0442\u0435\u0440\u0433\u043e\u043b\u044c\u0446"
    ],
    "name:uzb_x_preferred":[
        "Westerholz"
    ],
    "name:vie_x_preferred":[
        "Westerholz"
    ],
    "name:vol_x_preferred":[
        "Westerholz"
    ],
    "name:war_x_preferred":[
        "Westerholz"
    ],
    "name:zho_x_preferred":[
        "\u97e6\u65af\u7279\u970d\u5c14\u8328"
    ],
    "wof:name":"Westerholz",
    "wof:placetype":"neighbourhood"
},
  "geometry": {"coordinates":[10.56306,52.59951],"type":"Point"}
}