{
  "type": "Feature",
  "properties": {
    "gn:admin1_code":"2",
    "gn:admin2_code":"95.0",
    "gn:admin3_code":"9576.0",
    "gn:admin4_code":"9576121.0",
    "gn:asciiname":"Mabenberg",
    "gn:country_code":"DE",
    "gn:dem":426,
    "gn:feature_class":"P",
    "gn:feature_code":"PPL",
    "gn:name":"M\u00e4benberg",
    "gn:population":0,
    "gn:timezone":"Europe/Berlin",
    "iso:country":"DE",
    "wof:name":"Mabenberg",
    "wof:placetype":"neighbourhood"
},
  "geometry": {"coordinates":[11.00298,49.22404],"type":"Point"}
}