{
  "type": "Feature",
  "properties": {
    "gn:admin1_code":"7",
    "gn:admin2_code":"57.0",
    "gn:admin3_code":"5770.0",
    "gn:admin4_code":"5770032.0",
    "gn:asciiname":"Holzhausen an der Porta",
    "gn:country_code":"DE",
    "gn:dem":73,
    "gn:feature_class":"P",
    "gn:feature_code":"PPL",
    "gn:name":"Holzhausen an der Porta",
    "gn:population":0,
    "gn:timezone":"Europe/Berlin",
    "iso:country":"DE",
    "name:und_x_variant":[
        "Holzhausen",
        "Holzhausen an der Porta"
    ],
    "wof:name":"Holzhausen an der Porta",
    "wof:placetype":"neighbourhood"
},
  "geometry": {"coordinates":[8.90394,52.2283],"type":"Point"}
}