{
  "type": "Feature",
  "properties": {
    "gn:admin1_code":"2",
    "gn:admin2_code":"92.0",
    "gn:admin3_code":"9276.0",
    "gn:admin4_code":"9276113.0",
    "gn:asciiname":"Exenbach",
    "gn:country_code":"DE",
    "gn:dem":540,
    "gn:feature_class":"P",
    "gn:feature_code":"PPL",
    "gn:name":"Exenbach",
    "gn:population":0,
    "gn:timezone":"Europe/Berlin",
    "iso:country":"DE",
    "wof:name":"Exenbach",
    "wof:placetype":"neighbourhood"
},
  "geometry": {"coordinates":[13.00049,49.11888],"type":"Point"}
}