{
  "type": "Feature",
  "properties": {
    "gn:admin1_code":"2",
    "gn:admin2_code":"97.0",
    "gn:admin3_code":"9776.0",
    "gn:admin4_code":"9776128.0",
    "gn:asciiname":"Hengnau",
    "gn:country_code":"DE",
    "gn:dem":449,
    "gn:feature_class":"P",
    "gn:feature_code":"PPL",
    "gn:name":"Hengnau",
    "gn:population":0,
    "gn:timezone":"Europe/Berlin",
    "iso:country":"DE",
    "wof:name":"Hengnau",
    "wof:placetype":"neighbourhood"
},
  "geometry": {"coordinates":[9.64056,47.5863],"type":"Point"}
}