{
  "type": "Feature",
  "properties": {
    "gn:admin1_code":"13",
    "gn:admin2_code":"0.0",
    "gn:admin3_code":"14628.0",
    "gn:admin4_code":"14628230.0",
    "gn:asciiname":"Waltersdorf",
    "gn:country_code":"DE",
    "gn:dem":501,
    "gn:feature_class":"P",
    "gn:feature_code":"PPL",
    "gn:name":"Waltersdorf",
    "gn:population":0,
    "gn:timezone":"Europe/Berlin",
    "iso:country":"DE",
    "name:ceb_x_preferred":[
        "Waltersdorf"
    ],
    "name:deu_x_preferred":[
        "Waltersdorf"
    ],
    "name:epo_x_preferred":[
        "Waltersdorf"
    ],
    "name:fra_x_preferred":[
        "Waltersdorf"
    ],
    "name:ita_x_preferred":[
        "Waltersdorf"
    ],
    "name:nld_x_preferred":[
        "Waltersdorf"
    ],
    "name:pol_x_preferred":[
        "Waltersdorf"
    ],
    "wof:name":"Waltersdorf",
    "wof:placetype":"neighbourhood"
},
  "geometry": {"coordinates":[13.83776,50.82125],"type":"Point"}
}