{
  "type": "Feature",
  "properties": {
    "gn:admin1_code":"2",
    "gn:admin2_code":"93.0",
    "gn:admin3_code":"9377.0",
    "gn:admin4_code":"9377143.0",
    "gn:asciiname":"Schwarzenreuth",
    "gn:country_code":"DE",
    "gn:dem":622,
    "gn:feature_class":"P",
    "gn:feature_code":"PPL",
    "gn:name":"Schwarzenreuth",
    "gn:population":0,
    "gn:timezone":"Europe/Berlin",
    "iso:country":"DE",
    "wof:name":"Schwarzenreuth",
    "wof:placetype":"neighbourhood"
},
  "geometry": {"coordinates":[11.95919,49.95464000000001],"type":"Point"}
}