{
  "type": "Feature",
  "properties": {
    "gn:admin1_code":"11",
    "gn:admin2_code":"0.0",
    "gn:admin3_code":"12067.0",
    "gn:admin4_code":"12067137.0",
    "gn:asciiname":"Glowe",
    "gn:country_code":"DE",
    "gn:dem":50,
    "gn:feature_class":"P",
    "gn:feature_code":"PPL",
    "gn:name":"Glowe",
    "gn:population":0,
    "gn:timezone":"Europe/Berlin",
    "iso:country":"DE",
    "name:ceb_x_preferred":[
        "Glowe"
    ],
    "name:dan_x_preferred":[
        "Glowe"
    ],
    "name:deu_x_preferred":[
        "Glowe"
    ],
    "name:epo_x_preferred":[
        "Glowe"
    ],
    "name:fas_x_preferred":[
        "\u06af\u0644\u0648\u0648\u0647"
    ],
    "name:fra_x_preferred":[
        "Glowe"
    ],
    "name:hun_x_preferred":[
        "Glowe"
    ],
    "name:ita_x_preferred":[
        "Glowe"
    ],
    "name:kaz_x_preferred":[
        "\u0413\u043b\u043e\u0432\u0435"
    ],
    "name:kir_x_preferred":[
        "\u0413\u043b\u043e\u0432\u0435"
    ],
    "name:mkd_x_preferred":[
        "\u0413\u043b\u043e\u0432\u0435"
    ],
    "name:msa_x_preferred":[
        "Glowe"
    ],
    "name:nld_x_preferred":[
        "Glowe"
    ],
    "name:pol_x_preferred":[
        "Glowe"
    ],
    "name:por_x_preferred":[
        "Glowe"
    ],
    "name:ron_x_preferred":[
        "Glowe"
    ],
    "name:rus_x_preferred":[
        "\u0413\u043b\u043e\u0432\u0435"
    ],
    "name:spa_x_preferred":[
        "Glowe"
    ],
    "name:srp_x_preferred":[
        "\u0413\u043b\u043e\u0432\u0435"
    ],
    "name:ukr_x_preferred":[
        "\u0413\u043b\u043e\u0432\u0435"
    ],
    "name:uzb_x_preferred":[
        "Glowe"
    ],
    "name:vie_x_preferred":[
        "Glowe"
    ],
    "name:vol_x_preferred":[
        "Glowe"
    ],
    "name:war_x_preferred":[
        "Glowe"
    ],
    "name:zho_x_preferred":[
        "\u683c\u6d1b\u97e6"
    ],
    "wof:name":"Glowe",
    "wof:placetype":"neighbourhood"
},
  "geometry": {"coordinates":[14.20232,52.09603],"type":"Point"}
}