{
  "type": "Feature",
  "properties": {
    "gn:admin1_code":"6",
    "gn:admin2_code":"0.0",
    "gn:admin3_code":"3241.0",
    "gn:admin4_code":"3241010.0",
    "gn:asciiname":"Hainhaus",
    "gn:country_code":"DE",
    "gn:dem":48,
    "gn:feature_class":"P",
    "gn:feature_code":"PPL",
    "gn:name":"Hainhaus",
    "gn:population":0,
    "gn:timezone":"Europe/Berlin",
    "iso:country":"DE",
    "name:nds_x_preferred":[
        "Heinhus"
    ],
    "wof:name":"Hainhaus",
    "wof:placetype":"neighbourhood"
},
  "geometry": {"coordinates":[9.7646,52.48356999999999],"type":"Point"}
}