{
  "type": "Feature",
  "properties": {
    "gn:admin1_code":"7.0",
    "gn:admin2_code":"059",
    "gn:admin3_code":"5962.0",
    "gn:admin4_code":"5962036.0",
    "gn:asciiname":"Windebruch",
    "gn:country_code":"DE",
    "gn:dem":344,
    "gn:feature_class":"P",
    "gn:feature_code":"PPL",
    "gn:name":"Windebruch",
    "gn:population":0,
    "gn:timezone":"Europe/Berlin",
    "iso:country":"DE",
    "wof:name":"Windebruch",
    "wof:placetype":"neighbourhood"
},
  "geometry": {"coordinates":[7.81384,51.07958],"type":"Point"}
}