{
  "type": "Feature",
  "properties": {
    "gn:admin1_code":"10",
    "gn:admin2_code":"0.0",
    "gn:admin3_code":"1056.0",
    "gn:admin4_code":"1056020.0",
    "gn:asciiname":"Deichreihe",
    "gn:country_code":"DE",
    "gn:dem":0,
    "gn:feature_class":"P",
    "gn:feature_code":"PPL",
    "gn:name":"Deichreihe",
    "gn:population":0,
    "gn:timezone":"Europe/Berlin",
    "iso:country":"DE",
    "wof:name":"Deichreihe",
    "wof:placetype":"neighbourhood"
},
  "geometry": {"coordinates":[9.59094,53.63794],"type":"Point"}
}