{
  "type": "Feature",
  "properties": {
    "gn:admin1_code":"13.0",
    "gn:admin2_code":"0.0",
    "gn:admin3_code":"14628.0",
    "gn:admin4_code":"14628300.0",
    "gn:asciiname":"Spechtritz",
    "gn:country_code":"DE",
    "gn:dem":336,
    "gn:feature_class":"P",
    "gn:feature_code":"PPL",
    "gn:name":"Spechtritz",
    "gn:population":0,
    "gn:timezone":"Europe/Berlin",
    "iso:country":"DE",
    "wof:name":"Spechtritz",
    "wof:placetype":"neighbourhood"
},
  "geometry": {"coordinates":[13.63498,50.95053],"type":"Point"}
}