{
  "type": "Feature",
  "properties": {
    "gn:admin1_code":"2",
    "gn:admin2_code":"96.0",
    "gn:admin3_code":"9672.0",
    "gn:admin4_code":"9672112.0",
    "gn:asciiname":"Hohn",
    "gn:country_code":"DE",
    "gn:dem":221,
    "gn:feature_class":"P",
    "gn:feature_code":"PPL",
    "gn:name":"Hohn",
    "gn:population":0,
    "gn:timezone":"Europe/Berlin",
    "iso:country":"DE",
    "name:ceb_x_preferred":[
        "Hohn"
    ],
    "name:deu_x_preferred":[
        "Hohn"
    ],
    "name:eus_x_preferred":[
        "Hohn"
    ],
    "name:fra_x_preferred":[
        "Hohn"
    ],
    "name:ita_x_preferred":[
        "Hohn"
    ],
    "name:nld_x_preferred":[
        "Hohn"
    ],
    "name:pol_x_preferred":[
        "Hohn"
    ],
    "name:rus_x_preferred":[
        "\u0425\u043e\u043d"
    ],
    "name:swe_x_preferred":[
        "Hohn"
    ],
    "wof:name":"Hohn",
    "wof:placetype":"neighbourhood"
},
  "geometry": {"coordinates":[10.08051,50.28015],"type":"Point"}
}