{
  "type": "Feature",
  "properties": {
    "gn:admin1_code":"15",
    "gn:admin2_code":"0.0",
    "gn:admin3_code":"16051.0",
    "gn:admin4_code":"16051000.0",
    "gn:asciiname":"Niedernissa",
    "gn:country_code":"DE",
    "gn:dem":260,
    "gn:feature_class":"P",
    "gn:feature_code":"PPL",
    "gn:name":"Niedernissa",
    "gn:population":0,
    "gn:timezone":"Europe/Berlin",
    "iso:country":"DE",
    "wof:name":"Niedernissa",
    "wof:placetype":"neighbourhood"
},
  "geometry": {"coordinates":[11.10343,50.94972],"type":"Point"}
}