{
  "type": "Feature",
  "properties": {
    "gn:admin1_code":"2",
    "gn:admin2_code":"91.0",
    "gn:admin3_code":"9187.0",
    "gn:admin4_code":"9187116.0",
    "gn:asciiname":"Schonberg",
    "gn:country_code":"DE",
    "gn:dem":511,
    "gn:feature_class":"P",
    "gn:feature_code":"PPL",
    "gn:name":"Sch\u00f6nberg",
    "gn:population":964,
    "gn:timezone":"Europe/Berlin",
    "iso:country":"DE",
    "wof:name":"Schonberg",
    "wof:placetype":"neighbourhood",
    "wof:population":964
},
  "geometry": {"coordinates":[12.28543,48.05963],"type":"Point"}
}