{
  "type": "Feature",
  "properties": {
    "gn:gn_country":"DE",
    "gn:gn_fcode":"PPLA4",
    "gn:gn_pop":917,
    "gn:population":917,
    "iso:country":"DE",
    "name:baq_x_preferred":[
        "Oberdreis"
    ],
    "name:chi_x_preferred":[
        "\u4e0a\u5fb7\u8d56\u65af"
    ],
    "name:dut_x_preferred":[
        "Oberdreis"
    ],
    "name:eng_x_preferred":[
        "Oberdreis"
    ],
    "name:epo_x_preferred":[
        "Oberdreis"
    ],
    "name:fre_x_preferred":[
        "Oberdreis"
    ],
    "name:ger_x_preferred":[
        "Oberdreis"
    ],
    "name:hun_x_preferred":[
        "Oberdreis"
    ],
    "name:ita_x_preferred":[
        "Oberdreis"
    ],
    "name:jpn_x_preferred":[
        "\u30aa\u30fc\u30d0\u30fc\u30c9\u30e9\u30a4\u30b9"
    ],
    "name:may_x_preferred":[
        "Oberdreis"
    ],
    "name:per_x_preferred":[
        "\u0627\u0648\u0628\u0631\u062f\u0631\u0627\u06cc\u0633"
    ],
    "name:pol_x_preferred":[
        "Oberdreis"
    ],
    "name:por_x_preferred":[
        "Oberdreis"
    ],
    "name:rum_x_preferred":[
        "Oberdreis"
    ],
    "name:rus_x_preferred":[
        "\u041e\u0431\u0435\u0440\u0434\u0440\u0430\u0439\u0441"
    ],
    "name:slv_x_preferred":[
        "Oberdreis"
    ],
    "name:srp_x_preferred":[
        "\u041e\u0431\u0435\u0440\u0434\u0440\u0430\u0458\u0441"
    ],
    "name:ukr_x_preferred":[
        "\u041e\u0431\u0435\u0440\u0434\u0440\u0430\u0439\u0441"
    ],
    "name:uzb_x_preferred":[
        "Oberdreis"
    ],
    "name:vie_x_preferred":[
        "Oberdreis"
    ],
    "name:vol_x_preferred":[
        "Oberdreis"
    ],
    "name:war_x_preferred":[
        "Oberdreis"
    ],
    "qs_pg:aaroncc":"DE",
    "qs_pg:gn_country":"DE",
    "qs_pg:gn_fcode":"PPLA4",
    "qs_pg:gn_pop":917,
    "qs_pg:name":"Oberdreis",
    "qs_pg:photos_9r":0,
    "qs_pg:photos_sr":0,
    "qs_pg:pop_sr":2,
    "qs_pg:qs_pg_placetype":"locality",
    "wof:name":"Oberdreis",
    "wof:placetype":"locality",
    "wof:population":917
},
  "geometry": {"coordinates":[7.66667,50.63333],"type":"Point"}
}