{
  "type": "Feature",
  "properties": {
    "gn:admin1_code":"5.0",
    "gn:admin2_code":"66.0",
    "gn:admin3_code":"6632.0",
    "gn:admin4_code":"6632003.0",
    "gn:asciiname":"Braunhausen",
    "gn:country_code":"DE",
    "gn:dem":276,
    "gn:feature_class":"P",
    "gn:feature_code":"PPL",
    "gn:name":"Braunhausen",
    "gn:population":0,
    "gn:timezone":"Europe/Berlin",
    "iso:country":"DE",
    "wof:name":"Braunhausen",
    "wof:placetype":"neighbourhood"
},
  "geometry": {"coordinates":[9.83244,51.00466],"type":"Point"}
}