{
  "type": "Feature",
  "properties": {
    "gn:admin1_code":"15",
    "gn:admin2_code":"0.0",
    "gn:admin3_code":"16065.0",
    "gn:admin4_code":"16065081.0",
    "gn:asciiname":"Garnbach",
    "gn:country_code":"DE",
    "gn:dem":192,
    "gn:feature_class":"P",
    "gn:feature_code":"PPL",
    "gn:name":"Garnbach",
    "gn:population":0,
    "gn:timezone":"Europe/Berlin",
    "iso:country":"DE",
    "wof:name":"Garnbach",
    "wof:placetype":"neighbourhood"
},
  "geometry": {"coordinates":[11.38572,51.26046],"type":"Point"}
}