{
  "type": "Feature",
  "properties": {
    "gn:admin1_code":"2.0",
    "gn:admin2_code":"92.0",
    "gn:admin3_code":"9277.0",
    "gn:admin4_code":"9277111.0",
    "gn:asciiname":"Breitenbach",
    "gn:country_code":"DE",
    "gn:dem":440,
    "gn:feature_class":"P",
    "gn:feature_code":"PPLL",
    "gn:name":"Breitenbach",
    "gn:population":0,
    "gn:timezone":"Europe/Berlin",
    "iso:country":"DE",
    "name:als_x_preferred":[
        "Breitenbach"
    ],
    "name:cat_x_preferred":[
        "Breitenbach"
    ],
    "name:ceb_x_preferred":[
        "Breitenbach"
    ],
    "name:deu_x_preferred":[
        "Breitenbach"
    ],
    "name:epo_x_preferred":[
        "Breitenbach"
    ],
    "name:eus_x_preferred":[
        "Breitenbach"
    ],
    "name:fra_x_preferred":[
        "Breitenbach"
    ],
    "name:ita_x_preferred":[
        "Breitenbach"
    ],
    "name:jpn_x_preferred":[
        "\u30d6\u30e9\u30a4\u30c6\u30f3\u30d0\u30c3\u30cf"
    ],
    "name:kor_x_preferred":[
        "\ube0c\ub77c\uc774\ud150\ubc14\ud750"
    ],
    "name:nld_x_preferred":[
        "Breitenbach"
    ],
    "name:pol_x_preferred":[
        "Breitenbach"
    ],
    "name:por_x_preferred":[
        "Breitenbach"
    ],
    "name:rus_x_preferred":[
        "\u0411\u0440\u0430\u0439\u0442\u0435\u043d\u0431\u0430\u0445"
    ],
    "name:spa_x_preferred":[
        "Breitenbach"
    ],
    "name:srp_x_preferred":[
        "\u0411\u0440\u0430\u0458\u0442\u0435\u043d\u0431\u0430\u0445"
    ],
    "name:swe_x_preferred":[
        "Breitenbach"
    ],
    "name:vol_x_preferred":[
        "Breitenbach"
    ],
    "wof:name":"Breitenbach",
    "wof:placetype":"neighbourhood"
},
  "geometry": {"coordinates":[12.86667,48.53333],"type":"Point"}
}