{
  "type": "Feature",
  "properties": {
    "gn:admin1_code":"13",
    "gn:admin2_code":"0.0",
    "gn:admin3_code":"14522.0",
    "gn:admin4_code":"14522530.0",
    "gn:asciiname":"Kolkau",
    "gn:country_code":"DE",
    "gn:dem":239,
    "gn:feature_class":"P",
    "gn:feature_code":"PPL",
    "gn:name":"Kolkau",
    "gn:population":0,
    "gn:timezone":"Europe/Berlin",
    "iso:country":"DE",
    "name:csb_x_preferred":[
        "K\u00f4\u0142k\u00f2w\u00f2"
    ],
    "wof:name":"Kolkau",
    "wof:placetype":"neighbourhood"
},
  "geometry": {"coordinates":[12.83136,51.01915],"type":"Point"}
}