{
  "type": "Feature",
  "properties": {
    "gn:admin1_code":"7",
    "gn:admin2_code":"53.0",
    "gn:admin3_code":"5378.0",
    "gn:admin4_code":"5378008.0",
    "gn:asciiname":"Oberwietsche",
    "gn:country_code":"DE",
    "gn:dem":150,
    "gn:feature_class":"P",
    "gn:feature_code":"PPL",
    "gn:name":"Oberwietsche",
    "gn:population":0,
    "gn:timezone":"Europe/Berlin",
    "iso:country":"DE",
    "wof:name":"Oberwietsche",
    "wof:placetype":"neighbourhood"
},
  "geometry": {"coordinates":[7.10105,51.1026],"type":"Point"}
}