{
  "type": "Feature",
  "properties": {
    "gn:admin1_code":"2",
    "gn:admin2_code":"91.0",
    "gn:admin3_code":"9187.0",
    "gn:admin4_code":"9187182.0",
    "gn:asciiname":"Limburg",
    "gn:country_code":"DE",
    "gn:dem":485,
    "gn:feature_class":"P",
    "gn:feature_code":"PPL",
    "gn:name":"Limburg",
    "gn:population":0,
    "gn:timezone":"Europe/Berlin",
    "iso:country":"DE",
    "wof:name":"Limburg",
    "wof:placetype":"neighbourhood"
},
  "geometry": {"coordinates":[12.18221,48.03138],"type":"Point"}
}