{
  "type": "Feature",
  "properties": {
    "gn:admin1_code":"6",
    "gn:admin2_code":"0.0",
    "gn:admin3_code":"3461.0",
    "gn:admin4_code":"3461009.0",
    "gn:asciiname":"Sueder-Suederschwei",
    "gn:country_code":"DE",
    "gn:dem":2,
    "gn:feature_class":"P",
    "gn:feature_code":"PPL",
    "gn:name":"S\u00fcder-S\u00fcderschwei",
    "gn:population":0,
    "gn:timezone":"Europe/Berlin",
    "iso:country":"DE",
    "wof:name":"Sueder-Suederschwei",
    "wof:placetype":"neighbourhood"
},
  "geometry": {"coordinates":[8.34045,53.38899],"type":"Point"}
}