{
  "type": "Feature",
  "properties": {
    "gn:admin1_code":"7.0",
    "gn:admin2_code":"053",
    "gn:admin3_code":"5366.0",
    "gn:admin4_code":"5366036.0",
    "gn:asciiname":"Wintzen",
    "gn:country_code":"DE",
    "gn:dem":482,
    "gn:feature_class":"P",
    "gn:feature_code":"PPL",
    "gn:name":"Wintzen",
    "gn:population":0,
    "gn:timezone":"Europe/Berlin",
    "iso:country":"DE",
    "wof:name":"Wintzen",
    "wof:placetype":"neighbourhood"
},
  "geometry": {"coordinates":[6.50867,50.53578],"type":"Point"}
}