{
  "type": "Feature",
  "properties": {
    "gn:admin1_code":"2",
    "gn:admin2_code":"91.0",
    "gn:admin3_code":"9177.0",
    "gn:admin4_code":"9177127.0",
    "gn:asciiname":"Mehnbach",
    "gn:country_code":"DE",
    "gn:dem":482,
    "gn:feature_class":"P",
    "gn:feature_code":"PPL",
    "gn:name":"Mehnbach",
    "gn:population":0,
    "gn:timezone":"Europe/Berlin",
    "iso:country":"DE",
    "wof:name":"Mehnbach",
    "wof:placetype":"neighbourhood"
},
  "geometry": {"coordinates":[12.02897,48.25538],"type":"Point"}
}