{
  "type": "Feature",
  "properties": {
    "gn:admin1_code":"2",
    "gn:admin2_code":"92.0",
    "gn:admin3_code":"9273.0",
    "gn:admin4_code":"9273164.0",
    "gn:asciiname":"Sankt Gregor",
    "gn:country_code":"DE",
    "gn:dem":510,
    "gn:feature_class":"P",
    "gn:feature_code":"PPL",
    "gn:name":"Sankt Gregor",
    "gn:population":0,
    "gn:timezone":"Europe/Berlin",
    "iso:country":"DE",
    "wof:name":"Sankt Gregor",
    "wof:placetype":"neighbourhood"
},
  "geometry": {"coordinates":[11.64586,48.99379],"type":"Point"}
}