{
  "type": "Feature",
  "properties": {
    "gn:admin1_code":"2",
    "gn:admin2_code":"91.0",
    "gn:admin3_code":"9189.0",
    "gn:admin4_code":"9189126.0",
    "gn:asciiname":"Ortmaring",
    "gn:country_code":"DE",
    "gn:dem":542,
    "gn:feature_class":"P",
    "gn:feature_code":"PPL",
    "gn:name":"Ortmaring",
    "gn:population":0,
    "gn:timezone":"Europe/Berlin",
    "iso:country":"DE",
    "wof:name":"Ortmaring",
    "wof:placetype":"neighbourhood"
},
  "geometry": {"coordinates":[12.46442,48.03257],"type":"Point"}
}