{
  "type": "Feature",
  "properties": {
    "gn:admin1_code":"6",
    "gn:admin2_code":"0.0",
    "gn:admin3_code":"3251.0",
    "gn:admin4_code":"3251034.0",
    "gn:asciiname":"Paepsen",
    "gn:country_code":"DE",
    "gn:dem":43,
    "gn:feature_class":"P",
    "gn:feature_code":"PPL",
    "gn:name":"P\u00e4psen",
    "gn:population":0,
    "gn:timezone":"Europe/Berlin",
    "iso:country":"DE",
    "wof:name":"Paepsen",
    "wof:placetype":"neighbourhood"
},
  "geometry": {"coordinates":[8.95935,52.70926],"type":"Point"}
}