{
  "type": "Feature",
  "properties": {
    "gn:admin1_code":"6.0",
    "gn:admin2_code":"00",
    "gn:admin3_code":"3451.0",
    "gn:admin4_code":"3451007.0",
    "gn:asciiname":"Westerloyerfeld",
    "gn:country_code":"DE",
    "gn:dem":4,
    "gn:feature_class":"P",
    "gn:feature_code":"PPL",
    "gn:name":"Westerloyerfeld",
    "gn:population":0,
    "gn:timezone":"Europe/Berlin",
    "iso:country":"DE",
    "wof:name":"Westerloyerfeld",
    "wof:placetype":"neighbourhood"
},
  "geometry": {"coordinates":[7.85984,53.24296999999999],"type":"Point"}
}