{
  "type": "Feature",
  "properties": {
    "gn:admin1_code":"7",
    "gn:admin2_code":"51.0",
    "gn:admin3_code":"5154.0",
    "gn:admin4_code":"5154008.0",
    "gn:asciiname":"Huethum",
    "gn:country_code":"DE",
    "gn:dem":16,
    "gn:feature_class":"P",
    "gn:feature_code":"PPL",
    "gn:name":"H\u00fcthum",
    "gn:population":0,
    "gn:timezone":"Europe/Berlin",
    "iso:country":"DE",
    "wof:name":"Huethum",
    "wof:placetype":"neighbourhood"
},
  "geometry": {"coordinates":[6.20456,51.84787],"type":"Point"}
}