{
  "type": "Feature",
  "properties": {
    "gn:admin1_code":"10",
    "gn:admin2_code":"0.0",
    "gn:admin3_code":"1062.0",
    "gn:admin4_code":"1062026.0",
    "gn:asciiname":"Hamfelde in Holstein",
    "gn:cc2":"DE",
    "gn:country_code":"DE",
    "gn:dem":38,
    "gn:feature_class":"P",
    "gn:feature_code":"PPL",
    "gn:name":"Hamfelde in Holstein",
    "gn:population":0,
    "gn:timezone":"Europe/Berlin",
    "iso:country":"DE",
    "name:und_x_variant":[
        "Hamfelde",
        "Hamfelde in Holstein"
    ],
    "wof:name":"Hamfelde in Holstein",
    "wof:placetype":"neighbourhood"
},
  "geometry": {"coordinates":[10.45126,53.60371],"type":"Point"}
}