{
  "type": "Feature",
  "properties": {
    "gn:admin1_code":"1",
    "gn:admin2_code":"81.0",
    "gn:admin3_code":"8128.0",
    "gn:admin4_code":"8128061.0",
    "gn:asciiname":"Gissigheim",
    "gn:country_code":"DE",
    "gn:dem":273,
    "gn:feature_class":"P",
    "gn:feature_code":"PPL",
    "gn:name":"Gissigheim",
    "gn:population":0,
    "gn:timezone":"Europe/Berlin",
    "iso:country":"DE",
    "wof:name":"Gissigheim",
    "wof:placetype":"neighbourhood"
},
  "geometry": {"coordinates":[9.58765,49.59465],"type":"Point"}
}