{
  "type": "Feature",
  "properties": {
    "gn:admin1_code":"14",
    "gn:admin2_code":"0.0",
    "gn:admin3_code":"15089.0",
    "gn:admin4_code":"15089310.0",
    "gn:asciiname":"Loederburg",
    "gn:country_code":"DE",
    "gn:dem":67,
    "gn:feature_class":"P",
    "gn:feature_code":"PPL",
    "gn:name":"L\u00f6derburg",
    "gn:population":0,
    "gn:timezone":"Europe/Berlin",
    "iso:country":"DE",
    "name:deu_x_preferred":[
        "L\u00f6derburg"
    ],
    "wof:name":"Loederburg",
    "wof:placetype":"neighbourhood"
},
  "geometry": {"coordinates":[11.5397,51.87611],"type":"Point"}
}