{
  "type": "Feature",
  "properties": {
    "gn:admin1_code":"1.0",
    "gn:admin2_code":"081",
    "gn:admin3_code":"8127.0",
    "gn:admin4_code":"8127062.0",
    "gn:asciiname":"Wolfenbruck",
    "gn:country_code":"DE",
    "gn:dem":487,
    "gn:feature_class":"P",
    "gn:feature_code":"PPL",
    "gn:name":"Wolfenbr\u00fcck",
    "gn:population":0,
    "gn:timezone":"Europe/Berlin",
    "iso:country":"DE",
    "wof:name":"Wolfenbruck",
    "wof:placetype":"neighbourhood"
},
  "geometry": {"coordinates":[9.61106,49.01253],"type":"Point"}
}