{
  "type": "Feature",
  "properties": {
    "gn:admin1_code":"10.0",
    "gn:admin2_code":"0.0",
    "gn:admin3_code":"1059.0",
    "gn:admin4_code":"1059024.0",
    "gn:asciiname":"Bargen",
    "gn:country_code":"DE",
    "gn:dem":8,
    "gn:feature_class":"P",
    "gn:feature_code":"PPL",
    "gn:name":"Bargen",
    "gn:population":0,
    "gn:timezone":"Europe/Berlin",
    "iso:country":"DE",
    "name:als_x_preferred":[
        "Bargen"
    ],
    "name:ceb_x_preferred":[
        "Bargen"
    ],
    "name:deu_x_preferred":[
        "Bargen"
    ],
    "name:epo_x_preferred":[
        "Bargen"
    ],
    "name:fra_x_preferred":[
        "Bargen"
    ],
    "name:ita_x_preferred":[
        "Bargen"
    ],
    "name:lmo_x_preferred":[
        "Bargen"
    ],
    "name:nds_x_preferred":[
        "Bargen"
    ],
    "name:nld_x_preferred":[
        "Bargen"
    ],
    "name:pol_x_preferred":[
        "Bargen"
    ],
    "name:por_x_preferred":[
        "Bargen"
    ],
    "name:rus_x_preferred":[
        "\u0411\u0430\u0440\u0433\u0435\u043d"
    ],
    "name:spa_x_preferred":[
        "Bargen"
    ],
    "name:swe_x_preferred":[
        "Bargen"
    ],
    "wof:name":"Bargen",
    "wof:placetype":"neighbourhood"
},
  "geometry": {"coordinates":[9.27736,54.29984],"type":"Point"}
}