{
  "type": "Feature",
  "properties": {
    "gn:admin1_code":"15",
    "gn:admin2_code":"0.0",
    "gn:admin3_code":"16066.0",
    "gn:admin4_code":"16066093.0",
    "gn:asciiname":"Hermannsfeld",
    "gn:country_code":"DE",
    "gn:dem":380,
    "gn:feature_class":"P",
    "gn:feature_code":"PPL",
    "gn:name":"Hermannsfeld",
    "gn:population":0,
    "gn:timezone":"Europe/Berlin",
    "iso:country":"DE",
    "wof:name":"Hermannsfeld",
    "wof:placetype":"neighbourhood"
},
  "geometry": {"coordinates":[10.32078,50.50429000000001],"type":"Point"}
}