{
  "type": "Feature",
  "properties": {
    "gn:admin1_code":"7",
    "gn:admin2_code":"59.0",
    "gn:admin3_code":"5915.0",
    "gn:admin4_code":"5915000.0",
    "gn:asciiname":"Osterflierich",
    "gn:country_code":"DE",
    "gn:dem":82,
    "gn:feature_class":"P",
    "gn:feature_code":"PPL",
    "gn:name":"Osterflierich",
    "gn:population":0,
    "gn:timezone":"Europe/Berlin",
    "iso:country":"DE",
    "wof:name":"Osterflierich",
    "wof:placetype":"neighbourhood"
},
  "geometry": {"coordinates":[7.84072,51.59731],"type":"Point"}
}