{
  "type": "Feature",
  "properties": {
    "gn:admin1_code":"7",
    "gn:admin2_code":"53.0",
    "gn:admin3_code":"5362.0",
    "gn:admin4_code":"5362028.0",
    "gn:asciiname":"Hermuelheim",
    "gn:country_code":"DE",
    "gn:dem":59,
    "gn:feature_class":"P",
    "gn:feature_code":"PPL",
    "gn:name":"Herm\u00fclheim",
    "gn:population":0,
    "gn:timezone":"Europe/Berlin",
    "iso:country":"DE",
    "wof:name":"Hermuelheim",
    "wof:placetype":"neighbourhood"
},
  "geometry": {"coordinates":[6.89106,50.88649],"type":"Point"}
}