{
  "type": "Feature",
  "properties": {
    "gn:admin1_code":"2.0",
    "gn:admin2_code":"92.0",
    "gn:admin3_code":"9277.0",
    "gn:admin4_code":"9277114.0",
    "gn:asciiname":"Baumgarten",
    "gn:country_code":"DE",
    "gn:dem":437,
    "gn:feature_class":"P",
    "gn:feature_code":"PPL",
    "gn:name":"Baumgarten",
    "gn:population":0,
    "gn:timezone":"Europe/Berlin",
    "iso:country":"DE",
    "wof:name":"Baumgarten",
    "wof:placetype":"neighbourhood"
},
  "geometry": {"coordinates":[12.99073,48.49362],"type":"Point"}
}