{
  "type": "Feature",
  "properties": {
    "gn:gn_country":"DE",
    "gn:gn_fcode":"PPLA4",
    "gn:gn_pop":41,
    "gn:population":41,
    "iso:country":"DE",
    "name:baq_x_preferred":[
        "Wallen"
    ],
    "name:dan_x_preferred":[
        "Wallen"
    ],
    "name:dut_x_preferred":[
        "Wallen"
    ],
    "name:eng_x_preferred":[
        "Wallen"
    ],
    "name:epo_x_preferred":[
        "Wallen"
    ],
    "name:fre_x_preferred":[
        "Wallen"
    ],
    "name:ger_x_preferred":[
        "Wallen"
    ],
    "name:hun_x_preferred":[
        "Wallen"
    ],
    "name:ind_x_preferred":[
        "Wallen"
    ],
    "name:ita_x_preferred":[
        "Wallen"
    ],
    "name:kaz_x_preferred":[
        "\u0412\u0430\u043b\u043b\u0435\u043d"
    ],
    "name:kir_x_preferred":[
        "\u0412\u0430\u043b\u043b\u0435\u043d"
    ],
    "name:mac_x_preferred":[
        "\u0412\u0430\u043b\u0435\u043d"
    ],
    "name:may_x_preferred":[
        "Wallen"
    ],
    "name:nob_x_preferred":[
        "Wallen"
    ],
    "name:per_x_preferred":[
        "\u0648\u0627\u0644\u0646"
    ],
    "name:pol_x_preferred":[
        "Wallen"
    ],
    "name:por_x_preferred":[
        "Wallen"
    ],
    "name:rum_x_preferred":[
        "Wallen"
    ],
    "name:rus_x_preferred":[
        "\u0412\u0430\u043b\u043b\u0435\u043d"
    ],
    "name:srp_x_preferred":[
        "\u0412\u0430\u043b\u0435\u043d"
    ],
    "name:tur_x_preferred":[
        "Wallen"
    ],
    "name:ukr_x_preferred":[
        "\u0412\u0430\u043b\u043b\u0435\u043d"
    ],
    "name:uzb_x_preferred":[
        "Wallen"
    ],
    "name:vie_x_preferred":[
        "Wallen"
    ],
    "name:vol_x_preferred":[
        "Wallen"
    ],
    "name:war_x_preferred":[
        "Wallen"
    ],
    "qs_pg:aaroncc":"DE",
    "qs_pg:gn_country":"DE",
    "qs_pg:gn_fcode":"PPLA4",
    "qs_pg:gn_pop":41,
    "qs_pg:name":"Wallen",
    "qs_pg:photos_9r":0,
    "qs_pg:photos_sr":0,
    "qs_pg:pop_sr":1,
    "qs_pg:qs_pg_placetype":"locality",
    "wof:name":"Wallen",
    "wof:placetype":"locality",
    "wof:population":41
},
  "geometry": {"coordinates":[9.26667,54.28333],"type":"Point"}
}