{
  "type": "Feature",
  "properties": {
    "gn:admin1_code":"2",
    "gn:admin2_code":"92.0",
    "gn:admin3_code":"9278.0",
    "gn:admin4_code":"9278148.0",
    "gn:asciiname":"Galling",
    "gn:country_code":"DE",
    "gn:dem":419,
    "gn:feature_class":"P",
    "gn:feature_code":"PPL",
    "gn:name":"Galling",
    "gn:population":0,
    "gn:timezone":"Europe/Berlin",
    "iso:country":"DE",
    "name:deu_x_preferred":[
        "Fressen"
    ],
    "name:fas_x_preferred":[
        "\u06af\u0627\u0644\u06cc\u0646\u06af"
    ],
    "name:fra_x_preferred":[
        "Grippage"
    ],
    "name:ita_x_preferred":[
        "Grippaggio"
    ],
    "name:jpn_x_preferred":[
        "\u713c\u304d\u3064\u304d"
    ],
    "name:nld_x_preferred":[
        "Vreten"
    ],
    "wof:name":"Galling",
    "wof:placetype":"neighbourhood"
},
  "geometry": {"coordinates":[12.16416,48.78223],"type":"Point"}
}