{
  "type": "Feature",
  "properties": {
    "gn:admin1_code":"2",
    "gn:admin2_code":"95.0",
    "gn:admin3_code":"9575.0",
    "gn:admin4_code":"9575152.0",
    "gn:asciiname":"Rothenhof",
    "gn:country_code":"DE",
    "gn:dem":428,
    "gn:feature_class":"P",
    "gn:feature_code":"PPL",
    "gn:name":"Rothenhof",
    "gn:population":0,
    "gn:timezone":"Europe/Berlin",
    "iso:country":"DE",
    "wof:name":"Rothenhof",
    "wof:placetype":"neighbourhood"
},
  "geometry": {"coordinates":[10.60557,49.4298],"type":"Point"}
}