{
  "type": "Feature",
  "properties": {
    "gn:admin1_code":"7",
    "gn:admin2_code":"53.0",
    "gn:admin3_code":"5374.0",
    "gn:admin4_code":"5374028.0",
    "gn:asciiname":"Volperhausen",
    "gn:country_code":"DE",
    "gn:dem":195,
    "gn:feature_class":"P",
    "gn:feature_code":"PPL",
    "gn:name":"Volperhausen",
    "gn:population":0,
    "gn:timezone":"Europe/Berlin",
    "iso:country":"DE",
    "wof:name":"Volperhausen",
    "wof:placetype":"neighbourhood"
},
  "geometry": {"coordinates":[7.70333,50.83715],"type":"Point"}
}