{
  "type": "Feature",
  "properties": {
    "gn:admin1_code":"1.0",
    "gn:admin2_code":"84.0",
    "gn:admin3_code":"8426.0",
    "gn:admin4_code":"8426128.0",
    "gn:asciiname":"Birkenhard",
    "gn:country_code":"DE",
    "gn:dem":582,
    "gn:feature_class":"P",
    "gn:feature_code":"PPL",
    "gn:name":"Birkenhard",
    "gn:population":0,
    "gn:timezone":"Europe/Berlin",
    "iso:country":"DE",
    "wof:name":"Birkenhard",
    "wof:placetype":"neighbourhood"
},
  "geometry": {"coordinates":[9.76729,48.12414],"type":"Point"}
}