{
  "type": "Feature",
  "properties": {
    "gn:admin1_code":"1",
    "gn:admin2_code":"83.0",
    "gn:admin3_code":"8315.0",
    "gn:admin4_code":"8315064.0",
    "gn:asciiname":"Schlempenfeld",
    "gn:country_code":"DE",
    "gn:dem":404,
    "gn:feature_class":"P",
    "gn:feature_code":"PPL",
    "gn:name":"Schlempenfeld",
    "gn:population":0,
    "gn:timezone":"Europe/Berlin",
    "iso:country":"DE",
    "wof:name":"Schlempenfeld",
    "wof:placetype":"neighbourhood"
},
  "geometry": {"coordinates":[7.95335,47.95209000000001],"type":"Point"}
}