{
  "type": "Feature",
  "properties": {
    "gn:admin1_code":"2",
    "gn:admin2_code":"96.0",
    "gn:admin3_code":"9674.0",
    "gn:admin4_code":"9674130.0",
    "gn:asciiname":"Neuses am Raueneck",
    "gn:country_code":"DE",
    "gn:dem":288,
    "gn:feature_class":"P",
    "gn:feature_code":"PPL",
    "gn:name":"Neuses am Raueneck",
    "gn:population":0,
    "gn:timezone":"Europe/Berlin",
    "iso:country":"DE",
    "name:und_x_variant":[
        "Neuses",
        "Neuses am Raueneck"
    ],
    "wof:name":"Neuses am Raueneck",
    "wof:placetype":"neighbourhood"
},
  "geometry": {"coordinates":[10.70647,50.11056],"type":"Point"}
}