{
  "type": "Feature",
  "properties": {
    "gn:admin1_code":"5",
    "gn:admin2_code":"66.0",
    "gn:admin3_code":"6632.0",
    "gn:admin4_code":"6632012.0",
    "gn:asciiname":"Mecklar",
    "gn:country_code":"DE",
    "gn:dem":201,
    "gn:feature_class":"P",
    "gn:feature_code":"PPL",
    "gn:name":"Mecklar",
    "gn:population":0,
    "gn:timezone":"Europe/Berlin",
    "iso:country":"DE",
    "wof:name":"Mecklar",
    "wof:placetype":"neighbourhood"
},
  "geometry": {"coordinates":[9.7621,50.91838],"type":"Point"}
}