{
  "type": "Feature",
  "properties": {
    "gn:gn_country":"DE",
    "gn:gn_fcode":"PPLA4",
    "gn:gn_pop":350,
    "gn:population":350,
    "iso:country":"DE",
    "name:baq_x_preferred":[
        "M\u00f6rschbach"
    ],
    "name:chi_x_preferred":[
        "\u9ed8\u5c14\u65bd\u5df4\u8d6b"
    ],
    "name:dut_x_preferred":[
        "M\u00f6rschbach"
    ],
    "name:eng_x_preferred":[
        "M\u00f6rschbach"
    ],
    "name:epo_x_preferred":[
        "M\u00f6rschbach"
    ],
    "name:fre_x_preferred":[
        "M\u00f6rschbach"
    ],
    "name:ger_x_preferred":[
        "M\u00f6rschbach"
    ],
    "name:hun_x_preferred":[
        "M\u00f6rschbach"
    ],
    "name:ita_x_preferred":[
        "M\u00f6rschbach"
    ],
    "name:jpn_x_preferred":[
        "\u30e1\u30eb\u30b7\u30e5\u30d0\u30c3\u30cf"
    ],
    "name:per_x_preferred":[
        "\u0645\u0648\u0631\u0634\u0628\u0627\u062e"
    ],
    "name:pol_x_preferred":[
        "M\u00f6rschbach"
    ],
    "name:por_x_preferred":[
        "M\u00f6rschbach"
    ],
    "name:rum_x_preferred":[
        "M\u00f6rschbach"
    ],
    "name:rus_x_preferred":[
        "\u041c\u0451\u0440\u0448\u0431\u0430\u0445"
    ],
    "name:srp_x_preferred":[
        "\u041c\u0435\u0440\u0448\u0431\u0430\u0445"
    ],
    "name:ukr_x_preferred":[
        "\u041c\u0435\u0440\u0448\u0431\u0430\u0445"
    ],
    "name:uzb_x_preferred":[
        "M\u00f6rschbach"
    ],
    "name:vie_x_preferred":[
        "M\u00f6rschbach"
    ],
    "name:vol_x_preferred":[
        "M\u00f6rschbach"
    ],
    "name:war_x_preferred":[
        "M\u00f6rschbach"
    ],
    "qs_pg:aaroncc":"DE",
    "qs_pg:gn_country":"DE",
    "qs_pg:gn_fcode":"PPLA4",
    "qs_pg:gn_pop":350,
    "qs_pg:name":"M\u00f6rschbach",
    "qs_pg:photos_9r":0,
    "qs_pg:photos_sr":0,
    "qs_pg:pop_sr":2,
    "qs_pg:qs_pg_placetype":"locality",
    "wof:name":"M\u00f6rschbach",
    "wof:placetype":"locality",
    "wof:population":350
},
  "geometry": {"coordinates":[7.61667,50.01667],"type":"Point"}
}