{
  "type": "Feature",
  "properties": {
    "gn:admin1_code":"1",
    "gn:admin2_code":"81.0",
    "gn:admin3_code":"8126.0",
    "gn:admin4_code":"8126011.0",
    "gn:asciiname":"Geddelsbach",
    "gn:country_code":"DE",
    "gn:dem":253,
    "gn:feature_class":"P",
    "gn:feature_code":"PPL",
    "gn:name":"Geddelsbach",
    "gn:population":0,
    "gn:timezone":"Europe/Berlin",
    "iso:country":"DE",
    "wof:name":"Geddelsbach",
    "wof:placetype":"neighbourhood"
},
  "geometry": {"coordinates":[9.49855,49.1439],"type":"Point"}
}