{
  "type": "Feature",
  "properties": {
    "gn:country":"DE",
    "gn:fcode":"PPL",
    "gn:population":0,
    "iso:country":"DE",
    "qs_pg:aaroncc":"DE",
    "qs_pg:gn_country":"DE",
    "qs_pg:gn_fcode":"PPL",
    "qs_pg:gn_pop":0,
    "qs_pg:name":"Gr\u00fcnefeld",
    "qs_pg:name_adm0":"Deutschland",
    "qs_pg:name_adm1":"Bundesland Brandenburg",
    "qs_pg:photos":1421,
    "qs_pg:photos_1k":288,
    "qs_pg:photos_9k":6,
    "qs_pg:photos_9r":7,
    "qs_pg:photos_all":1421,
    "qs_pg:photos_sr":12,
    "qs_pg:pop_sr":0,
    "qs_pg:qs_pg_placetype":"locality",
    "qs_pg:qs_pg_placetype_gp":"Town",
    "qs_pg:woe_adm0":23424829,
    "woe:adm0_id":23424829,
    "woe:name_adm0":"Deutschland",
    "woe:name_adm1":"Bundesland Brandenburg",
    "woe:placetype":"Town",
    "wof:name":"Gr\u00fcnefeld",
    "wof:placetype":"neighbourhood"
},
  "geometry": {"coordinates":[12.96455,52.67628],"type":"Point"}
}