{
  "type": "Feature",
  "properties": {
    "gn:admin1_code":"2",
    "gn:admin2_code":"95.0",
    "gn:admin3_code":"9572.0",
    "gn:admin4_code":"9572133.0",
    "gn:asciiname":"Rohrach",
    "gn:country_code":"DE",
    "gn:dem":292,
    "gn:feature_class":"P",
    "gn:feature_code":"PPL",
    "gn:name":"R\u00f6hrach",
    "gn:population":0,
    "gn:timezone":"Europe/Berlin",
    "iso:country":"DE",
    "name:ceb_x_preferred":[
        "Rohrach"
    ],
    "name:deu_x_preferred":[
        "Rohrach"
    ],
    "name:rus_x_preferred":[
        "\u0420\u043e\u0440\u0430\u0445"
    ],
    "name:swe_x_preferred":[
        "Rohrach"
    ],
    "wof:name":"Rohrach",
    "wof:placetype":"neighbourhood"
},
  "geometry": {"coordinates":[10.91552,49.64735],"type":"Point"}
}