{
  "type": "Feature",
  "properties": {
    "gn:admin1_code":"2",
    "gn:admin2_code":"92.0",
    "gn:admin3_code":"9275.0",
    "gn:admin4_code":"9275128.0",
    "gn:asciiname":"Kalteneck",
    "gn:country_code":"DE",
    "gn:dem":361,
    "gn:feature_class":"P",
    "gn:feature_code":"PPL",
    "gn:name":"Kalteneck",
    "gn:population":0,
    "gn:timezone":"Europe/Berlin",
    "iso:country":"DE",
    "wof:name":"Kalteneck",
    "wof:placetype":"neighbourhood"
},
  "geometry": {"coordinates":[13.45542,48.68778],"type":"Point"}
}