{
  "type": "Feature",
  "properties": {
    "gn:admin1_code":"7",
    "gn:admin2_code":"59.0",
    "gn:admin3_code":"5966.0",
    "gn:admin4_code":"5966004.0",
    "gn:asciiname":"Buerberg",
    "gn:country_code":"DE",
    "gn:dem":377,
    "gn:feature_class":"P",
    "gn:feature_code":"PPL",
    "gn:name":"B\u00fcrberg",
    "gn:population":0,
    "gn:timezone":"Europe/Berlin",
    "iso:country":"DE",
    "wof:name":"Buerberg",
    "wof:placetype":"neighbourhood"
},
  "geometry": {"coordinates":[7.88835,51.08817],"type":"Point"}
}