{
  "type": "Feature",
  "properties": {
    "gn:admin1_code":"6",
    "gn:admin2_code":"0.0",
    "gn:admin3_code":"3360.0",
    "gn:admin4_code":"3360002.0",
    "gn:asciiname":"Jastorf",
    "gn:country_code":"DE",
    "gn:dem":32,
    "gn:feature_class":"P",
    "gn:feature_code":"PPL",
    "gn:name":"Jastorf",
    "gn:population":0,
    "gn:timezone":"Europe/Berlin",
    "iso:country":"DE",
    "wof:name":"Jastorf",
    "wof:placetype":"neighbourhood"
},
  "geometry": {"coordinates":[10.60314,53.04405],"type":"Point"}
}