{
  "type": "Feature",
  "properties": {
    "gn:admin1_code":"6.0",
    "gn:admin2_code":"0.0",
    "gn:admin3_code":"3459.0",
    "gn:admin4_code":"3459029.0",
    "gn:asciiname":"Vennermoor",
    "gn:country_code":"DE",
    "gn:dem":42,
    "gn:feature_class":"P",
    "gn:feature_code":"PPL",
    "gn:name":"Vennermoor",
    "gn:population":0,
    "gn:timezone":"Europe/Berlin",
    "iso:country":"DE",
    "wof:name":"Vennermoor",
    "wof:placetype":"neighbourhood"
},
  "geometry": {"coordinates":[8.21667,52.41667],"type":"Point"}
}