{
  "type": "Feature",
  "properties": {
    "gn:admin1_code":"7",
    "gn:admin2_code":"57.0",
    "gn:admin3_code":"5758.0",
    "gn:admin4_code":"5758032.0",
    "gn:asciiname":"Harrenheide",
    "gn:country_code":"DE",
    "gn:dem":111,
    "gn:feature_class":"P",
    "gn:feature_code":"PPLL",
    "gn:name":"Harrenheide",
    "gn:population":0,
    "gn:timezone":"Europe/Berlin",
    "iso:country":"DE",
    "wof:name":"Harrenheide",
    "wof:placetype":"neighbourhood"
},
  "geometry": {"coordinates":[8.44301,52.13767],"type":"Point"}
}