{
  "type": "Feature",
  "properties": {
    "gn:admin1_code":"11",
    "gn:admin2_code":"0.0",
    "gn:admin3_code":"12069.0",
    "gn:admin4_code":"12069249.0",
    "gn:asciiname":"Neu Bochow",
    "gn:country_code":"DE",
    "gn:dem":54,
    "gn:feature_class":"P",
    "gn:feature_code":"PPL",
    "gn:name":"Neu Bochow",
    "gn:population":0,
    "gn:timezone":"Europe/Berlin",
    "iso:country":"DE",
    "wof:name":"Neu Bochow",
    "wof:placetype":"neighbourhood"
},
  "geometry": {"coordinates":[12.76548,52.37596],"type":"Point"}
}