{
  "type": "Feature",
  "properties": {
    "gn:admin1_code":"2.0",
    "gn:admin2_code":"097",
    "gn:admin3_code":"9778.0",
    "gn:admin4_code":"9778144.0",
    "gn:asciiname":"Wieslings",
    "gn:country_code":"DE",
    "gn:dem":708,
    "gn:feature_class":"P",
    "gn:feature_code":"PPL",
    "gn:name":"Wieslings",
    "gn:population":0,
    "gn:timezone":"Europe/Berlin",
    "iso:country":"DE",
    "wof:name":"Wieslings",
    "wof:placetype":"neighbourhood"
},
  "geometry": {"coordinates":[10.19004,47.89698],"type":"Point"}
}