{
  "type": "Feature",
  "properties": {
    "gn:admin1_code":"2",
    "gn:admin2_code":"93.0",
    "gn:admin3_code":"9372.0",
    "gn:admin4_code":"9372137.0",
    "gn:asciiname":"Grub",
    "gn:country_code":"DE",
    "gn:dem":427,
    "gn:feature_class":"P",
    "gn:feature_code":"PPL",
    "gn:name":"Grub",
    "gn:population":0,
    "gn:timezone":"Europe/Berlin",
    "iso:country":"DE",
    "name:ceb_x_preferred":[
        "Grub"
    ],
    "name:deu_x_preferred":[
        "Grub"
    ],
    "name:epo_x_preferred":[
        "Grub"
    ],
    "name:fra_x_preferred":[
        "Grub"
    ],
    "name:ita_x_preferred":[
        "Grub"
    ],
    "name:nld_x_preferred":[
        "Grub"
    ],
    "name:pol_x_preferred":[
        "Grub"
    ],
    "name:por_x_preferred":[
        "Grub"
    ],
    "name:ron_x_preferred":[
        "Grub"
    ],
    "name:rus_x_preferred":[
        "\u0413\u0440\u0443\u0431"
    ],
    "name:spa_x_preferred":[
        "Grub"
    ],
    "name:srp_x_preferred":[
        "\u0413\u0440\u0443\u0431"
    ],
    "name:swe_x_preferred":[
        "Grub"
    ],
    "name:vol_x_preferred":[
        "Grub"
    ],
    "wof:name":"Grub",
    "wof:placetype":"neighbourhood"
},
  "geometry": {"coordinates":[12.87744,49.1638],"type":"Point"}
}