{
  "type": "Feature",
  "properties": {
    "gn:admin1_code":"12",
    "gn:admin2_code":"0.0",
    "gn:admin3_code":"13075.0",
    "gn:admin4_code":"13075116.0",
    "gn:asciiname":"Charlottenhof",
    "gn:country_code":"DE",
    "gn:dem":10,
    "gn:feature_class":"P",
    "gn:feature_code":"PPL",
    "gn:name":"Charlottenhof",
    "gn:population":0,
    "gn:timezone":"Europe/Berlin",
    "iso:country":"DE",
    "name:ceb_x_preferred":[
        "Charlottenhof"
    ],
    "name:ces_x_preferred":[
        "Charlottenhof"
    ],
    "name:deu_x_preferred":[
        "Charlottenhof"
    ],
    "name:lav_x_preferred":[
        "Charlottenhof"
    ],
    "name:swe_x_preferred":[
        "Charlottenhof"
    ],
    "wof:name":"Charlottenhof",
    "wof:placetype":"neighbourhood"
},
  "geometry": {"coordinates":[13.73884,53.76881],"type":"Point"}
}