{
  "type": "Feature",
  "properties": {
    "gn:admin1_code":"6",
    "gn:admin2_code":"0.0",
    "gn:admin3_code":"3153.0",
    "gn:admin4_code":"3153017.0",
    "gn:asciiname":"Hahndorf",
    "gn:country_code":"DE",
    "gn:dem":224,
    "gn:feature_class":"P",
    "gn:feature_code":"PPL",
    "gn:name":"Hahndorf",
    "gn:population":0,
    "gn:timezone":"Europe/Berlin",
    "iso:country":"DE",
    "wof:name":"Hahndorf",
    "wof:placetype":"neighbourhood"
},
  "geometry": {"coordinates":[10.43444,51.95707],"type":"Point"}
}