{
  "type": "Feature",
  "properties": {
    "gn:admin1_code":"7",
    "gn:admin2_code":"53.0",
    "gn:admin3_code":"5382.0",
    "gn:admin4_code":"5382048.0",
    "gn:asciiname":"Flerzheim",
    "gn:country_code":"DE",
    "gn:dem":156,
    "gn:feature_class":"P",
    "gn:feature_code":"PPL",
    "gn:name":"Flerzheim",
    "gn:population":0,
    "gn:timezone":"Europe/Berlin",
    "iso:country":"DE",
    "name:deu_x_preferred":[
        "Flerzheim"
    ],
    "name:fas_x_preferred":[
        "\u0641\u0644\u0631\u062a\u0633\u0647\u0627\u06cc\u0645"
    ],
    "wof:name":"Flerzheim",
    "wof:placetype":"neighbourhood"
},
  "geometry": {"coordinates":[6.98708,50.64762],"type":"Point"}
}