{
  "type": "Feature",
  "properties": {
    "gn:admin1_code":"13",
    "gn:admin2_code":"0.0",
    "gn:admin3_code":"14521.0",
    "gn:admin4_code":"14521670.0",
    "gn:asciiname":"Schoenbrunn",
    "gn:country_code":"DE",
    "gn:dem":472,
    "gn:feature_class":"P",
    "gn:feature_code":"PPL",
    "gn:name":"Sch\u00f6nbrunn",
    "gn:population":0,
    "gn:timezone":"Europe/Berlin",
    "iso:country":"DE",
    "wof:name":"Schoenbrunn",
    "wof:placetype":"neighbourhood"
},
  "geometry": {"coordinates":[13.04709,50.65427],"type":"Point"}
}