{
  "type": "Feature",
  "properties": {
    "gn:admin1_code":"2",
    "gn:admin2_code":"94.0",
    "gn:admin3_code":"9472.0",
    "gn:admin4_code":"9472150.0",
    "gn:asciiname":"Cottenbach",
    "gn:country_code":"DE",
    "gn:dem":358,
    "gn:feature_class":"P",
    "gn:feature_code":"PPL",
    "gn:name":"Cottenbach",
    "gn:population":0,
    "gn:timezone":"Europe/Berlin",
    "iso:country":"DE",
    "wof:name":"Cottenbach",
    "wof:placetype":"neighbourhood"
},
  "geometry": {"coordinates":[11.55247,49.97137],"type":"Point"}
}