{
  "type": "Feature",
  "properties": {
    "gn:admin1_code":"7.0",
    "gn:admin2_code":"053",
    "gn:admin3_code":"5366.0",
    "gn:admin4_code":"5366020.0",
    "gn:asciiname":"Wollenberg",
    "gn:country_code":"DE",
    "gn:dem":519,
    "gn:feature_class":"P",
    "gn:feature_code":"PPL",
    "gn:name":"Wollenberg",
    "gn:population":0,
    "gn:timezone":"Europe/Berlin",
    "iso:country":"DE",
    "wof:name":"Wollenberg",
    "wof:placetype":"neighbourhood"
},
  "geometry": {"coordinates":[6.48439,50.48434],"type":"Point"}
}