{
  "type": "Feature",
  "properties": {
    "gn:admin1_code":"1",
    "gn:admin2_code":"84.0",
    "gn:admin3_code":"8436.0",
    "gn:admin4_code":"8436027.0",
    "gn:asciiname":"Hangen",
    "gn:country_code":"DE",
    "gn:dem":629,
    "gn:feature_class":"P",
    "gn:feature_code":"PPL",
    "gn:name":"Hangen",
    "gn:population":0,
    "gn:timezone":"Europe/Berlin",
    "iso:country":"DE",
    "wof:name":"Hangen",
    "wof:placetype":"neighbourhood"
},
  "geometry": {"coordinates":[9.50805,47.95861],"type":"Point"}
}