{
  "type": "Feature",
  "properties": {
    "gn:admin1_code":"7",
    "gn:admin2_code":"55.0",
    "gn:admin3_code":"5562.0",
    "gn:admin4_code":"5562024.0",
    "gn:asciiname":"Drewer Sued",
    "gn:country_code":"DE",
    "gn:dem":67,
    "gn:feature_class":"P",
    "gn:feature_code":"PPLL",
    "gn:name":"Drewer S\u00fcd",
    "gn:population":0,
    "gn:timezone":"Europe/Berlin",
    "iso:country":"DE",
    "wof:name":"Drewer Sued",
    "wof:placetype":"neighbourhood"
},
  "geometry": {"coordinates":[7.11667,51.65],"type":"Point"}
}