{
  "type": "Feature",
  "properties": {
    "gn:country":"DE",
    "gn:fcode":"PPL",
    "gn:population":0,
    "iso:country":"DE",
    "name:ara_x_preferred":[
        "\u0644\u064a\u0632"
    ],
    "name:bug_x_preferred":[
        "Laiz"
    ],
    "name:cat_x_preferred":[
        "Laiz"
    ],
    "name:ceb_x_preferred":[
        "Laiz"
    ],
    "name:deu_x_preferred":[
        "Laiz"
    ],
    "name:eus_x_preferred":[
        "Laiz"
    ],
    "name:fra_x_preferred":[
        "Laiz"
    ],
    "name:glg_x_preferred":[
        "Laiz"
    ],
    "name:hun_x_preferred":[
        "Laiz"
    ],
    "name:hye_x_preferred":[
        "\u053c\u0565"
    ],
    "name:ind_x_preferred":[
        "Laiz"
    ],
    "name:ita_x_preferred":[
        "Laiz"
    ],
    "name:lat_x_preferred":[
        "Laiz"
    ],
    "name:lmo_x_preferred":[
        "Laiz"
    ],
    "name:mlg_x_preferred":[
        "Laiz"
    ],
    "name:msa_x_preferred":[
        "Laiz"
    ],
    "name:nld_x_preferred":[
        "Laiz"
    ],
    "name:oci_x_preferred":[
        "Laiz"
    ],
    "name:pms_x_preferred":[
        "Laiz"
    ],
    "name:pol_x_preferred":[
        "Laiz"
    ],
    "name:por_x_preferred":[
        "Laiz"
    ],
    "name:ron_x_preferred":[
        "Laiz"
    ],
    "name:rus_x_preferred":[
        "\u041b\u0435"
    ],
    "name:slk_x_preferred":[
        "Laiz"
    ],
    "name:spa_x_preferred":[
        "Laiz"
    ],
    "name:swe_x_preferred":[
        "Laiz"
    ],
    "name:tgl_x_preferred":[
        "Laiz"
    ],
    "name:ukr_x_preferred":[
        "\u041b\u0435"
    ],
    "name:uzb_x_preferred":[
        "Laiz"
    ],
    "name:vie_x_preferred":[
        "Laiz"
    ],
    "name:vol_x_preferred":[
        "Laiz"
    ],
    "name:war_x_preferred":[
        "Laiz"
    ],
    "name:zea_x_preferred":[
        "Laiz"
    ],
    "qs_pg:aaroncc":"DE",
    "qs_pg:gn_country":"DE",
    "qs_pg:gn_fcode":"PPL",
    "qs_pg:gn_pop":0,
    "qs_pg:name":"Laiz",
    "qs_pg:name_adm0":"Deutschland",
    "qs_pg:name_adm1":"Baden-W\u00fcrttemberg",
    "qs_pg:photos_9r":0,
    "qs_pg:photos_sr":0,
    "qs_pg:pop_sr":0,
    "qs_pg:qs_pg_placetype":"locality",
    "qs_pg:qs_pg_placetype_gp":"Town",
    "qs_pg:woe_adm0":23424829,
    "woe:adm0_id":23424829,
    "woe:name_adm0":"Deutschland",
    "woe:name_adm1":"Baden-W\u00fcrttemberg",
    "woe:placetype":"Town",
    "wof:name":"Laiz",
    "wof:placetype":"neighbourhood"
},
  "geometry": {"coordinates":[9.19581,48.07871],"type":"Point"}
}