{
  "type": "Feature",
  "properties": {
    "gn:admin1_code":"12",
    "gn:admin2_code":"0.0",
    "gn:admin3_code":"13071.0",
    "gn:admin4_code":"13071029.0",
    "gn:asciiname":"Erdmannshoehe",
    "gn:country_code":"DE",
    "gn:dem":13,
    "gn:feature_class":"P",
    "gn:feature_code":"PPL",
    "gn:name":"Erdmannsh\u00f6he",
    "gn:population":0,
    "gn:timezone":"Europe/Berlin",
    "iso:country":"DE",
    "wof:name":"Erdmannshoehe",
    "wof:placetype":"neighbourhood"
},
  "geometry": {"coordinates":[13.01468,53.92648000000001],"type":"Point"}
}