{
  "type": "Feature",
  "properties": {
    "gn:admin1_code":"13",
    "gn:admin2_code":"0.0",
    "gn:admin3_code":"14729.0",
    "gn:admin4_code":"14729150.0",
    "gn:asciiname":"Oberpickenhain",
    "gn:country_code":"DE",
    "gn:dem":240,
    "gn:feature_class":"P",
    "gn:feature_code":"PPL",
    "gn:name":"Oberpickenhain",
    "gn:population":0,
    "gn:timezone":"Europe/Berlin",
    "iso:country":"DE",
    "wof:name":"Oberpickenhain",
    "wof:placetype":"neighbourhood"
},
  "geometry": {"coordinates":[12.67024,51.0106],"type":"Point"}
}