{
  "type": "Feature",
  "properties": {
    "gn:admin1_code":"2.0",
    "gn:admin2_code":"91.0",
    "gn:admin3_code":"9189.0",
    "gn:admin4_code":"9189137.0",
    "gn:asciiname":"Altersham",
    "gn:country_code":"DE",
    "gn:dem":633,
    "gn:feature_class":"P",
    "gn:feature_code":"PPL",
    "gn:name":"Altersham",
    "gn:population":0,
    "gn:timezone":"Europe/Berlin",
    "iso:country":"DE",
    "wof:name":"Altersham",
    "wof:placetype":"neighbourhood"
},
  "geometry": {"coordinates":[12.34548,47.98141],"type":"Point"}
}