{
  "type": "Feature",
  "properties": {
    "gn:admin1_code":"11.0",
    "gn:admin2_code":"0.0",
    "gn:admin3_code":"12063.0",
    "gn:admin4_code":"12063142.0",
    "gn:asciiname":"Braedikow",
    "gn:country_code":"DE",
    "gn:dem":35,
    "gn:feature_class":"P",
    "gn:feature_code":"PPL",
    "gn:name":"Br\u00e4dikow",
    "gn:population":0,
    "gn:timezone":"Europe/Berlin",
    "iso:country":"DE",
    "wof:name":"Braedikow",
    "wof:placetype":"neighbourhood"
},
  "geometry": {"coordinates":[12.64998,52.68981],"type":"Point"}
}