{
  "type": "Feature",
  "properties": {
    "gn:admin1_code":"1.0",
    "gn:admin2_code":"81.0",
    "gn:admin3_code":"8136.0",
    "gn:admin4_code":"8136037.0",
    "gn:asciiname":"Benzenzimmern",
    "gn:country_code":"DE",
    "gn:dem":452,
    "gn:feature_class":"P",
    "gn:feature_code":"PPL",
    "gn:name":"Benzenzimmern",
    "gn:population":0,
    "gn:timezone":"Europe/Berlin",
    "iso:country":"DE",
    "wof:name":"Benzenzimmern",
    "wof:placetype":"neighbourhood"
},
  "geometry": {"coordinates":[10.43667,48.88958],"type":"Point"}
}