{
  "type": "Feature",
  "properties": {
    "gn:admin1_code":"2.0",
    "gn:admin2_code":"91.0",
    "gn:admin3_code":"9180.0",
    "gn:admin4_code":"9180127.0",
    "gn:asciiname":"Buchenried",
    "gn:country_code":"DE",
    "gn:dem":651,
    "gn:feature_class":"P",
    "gn:feature_code":"PPL",
    "gn:name":"Buchenried",
    "gn:population":0,
    "gn:timezone":"Europe/Berlin",
    "iso:country":"DE",
    "wof:name":"Buchenried",
    "wof:placetype":"neighbourhood"
},
  "geometry": {"coordinates":[11.21983,47.62816],"type":"Point"}
}