{
  "type": "Feature",
  "properties": {
    "gn:admin1_code":"1",
    "gn:admin2_code":"84.0",
    "gn:admin3_code":"8437.0",
    "gn:admin4_code":"8437053.0",
    "gn:asciiname":"Hagelsburg",
    "gn:country_code":"DE",
    "gn:dem":595,
    "gn:feature_class":"P",
    "gn:feature_code":"PPL",
    "gn:name":"Hagelsburg",
    "gn:population":0,
    "gn:timezone":"Europe/Berlin",
    "iso:country":"DE",
    "wof:name":"Hagelsburg",
    "wof:placetype":"neighbourhood"
},
  "geometry": {"coordinates":[9.40658,48.03875],"type":"Point"}
}