{
  "type": "Feature",
  "properties": {
    "gn:admin1_code":"1.0",
    "gn:admin2_code":"83.0",
    "gn:admin3_code":"8316.0",
    "gn:admin4_code":"8316043.0",
    "gn:asciiname":"Bottingen",
    "gn:country_code":"DE",
    "gn:dem":195,
    "gn:feature_class":"P",
    "gn:feature_code":"PPL",
    "gn:name":"Bottingen",
    "gn:population":0,
    "gn:timezone":"Europe/Berlin",
    "iso:country":"DE",
    "wof:name":"Bottingen",
    "wof:placetype":"neighbourhood"
},
  "geometry": {"coordinates":[7.78364,48.09112],"type":"Point"}
}