{
  "type": "Feature",
  "properties": {
    "gn:admin1_code":"8",
    "gn:admin2_code":"0.0",
    "gn:admin3_code":"7141.0",
    "gn:admin4_code":"7141120.0",
    "gn:asciiname":"Ruppertshofen",
    "gn:country_code":"DE",
    "gn:dem":327,
    "gn:feature_class":"P",
    "gn:feature_code":"PPLA4",
    "gn:name":"Ruppertshofen",
    "gn:population":402,
    "gn:timezone":"Europe/Berlin",
    "iso:country":"DE",
    "wof:name":"Ruppertshofen",
    "wof:placetype":"locality",
    "wof:population":402
},
  "geometry": {"coordinates":[7.80553,50.20086],"type":"Point"}
}