{
  "type": "Feature",
  "properties": {
    "gn:admin1_code":"7.0",
    "gn:admin2_code":"059",
    "gn:admin3_code":"5966.0",
    "gn:admin4_code":"5966028.0",
    "gn:asciiname":"Wendenerhuette",
    "gn:country_code":"DE",
    "gn:dem":354,
    "gn:feature_class":"P",
    "gn:feature_code":"PPL",
    "gn:name":"Wendenerh\u00fctte",
    "gn:population":0,
    "gn:timezone":"Europe/Berlin",
    "iso:country":"DE",
    "wof:name":"Wendenerhuette",
    "wof:placetype":"neighbourhood"
},
  "geometry": {"coordinates":[7.82927,50.97076],"type":"Point"}
}