{
  "type": "Feature",
  "properties": {
    "gn:admin1_code":"6.0",
    "gn:admin2_code":"0.0",
    "gn:admin3_code":"3353.0",
    "gn:admin4_code":"3353020.0",
    "gn:asciiname":"Osterberg",
    "gn:country_code":"DE",
    "gn:dem":64,
    "gn:feature_class":"P",
    "gn:feature_code":"PPL",
    "gn:name":"Osterberg",
    "gn:population":0,
    "gn:timezone":"Europe/Berlin",
    "iso:country":"DE",
    "name:als_x_preferred":[
        "Osterberg"
    ],
    "name:ceb_x_preferred":[
        "Osterberg"
    ],
    "name:dan_x_preferred":[
        "Osterberg"
    ],
    "name:deu_x_preferred":[
        "Osterberg"
    ],
    "name:epo_x_preferred":[
        "Osterberg"
    ],
    "name:eus_x_preferred":[
        "Osterberg"
    ],
    "name:fas_x_preferred":[
        "\u0627\u0648\u0634\u062a\u0631\u0628\u0631\u06af"
    ],
    "name:fra_x_preferred":[
        "Osterberg"
    ],
    "name:hun_x_preferred":[
        "Osterberg"
    ],
    "name:hye_x_preferred":[
        "\u0555\u057d\u0569\u0565\u0580\u0562\u0565\u0580\u0563"
    ],
    "name:ile_x_preferred":[
        "Osterberg"
    ],
    "name:ita_x_preferred":[
        "Osterberg"
    ],
    "name:kaz_x_preferred":[
        "\u041e\u0441\u0442\u0435\u0440\u0431\u0435\u0440\u0433"
    ],
    "name:kir_x_preferred":[
        "\u041e\u0441\u0442\u0435\u0440\u0431\u0435\u0440\u0433"
    ],
    "name:lmo_x_preferred":[
        "Osterberg"
    ],
    "name:msa_x_preferred":[
        "Osterberg"
    ],
    "name:nld_x_preferred":[
        "Osterberg"
    ],
    "name:pol_x_preferred":[
        "Osterberg"
    ],
    "name:por_x_preferred":[
        "Osterberg"
    ],
    "name:ron_x_preferred":[
        "Osterberg"
    ],
    "name:rus_x_preferred":[
        "\u041e\u0441\u0442\u0435\u0440\u0431\u0435\u0440\u0433"
    ],
    "name:spa_x_preferred":[
        "Osterberg"
    ],
    "name:srp_x_preferred":[
        "\u041e\u0441\u0442\u0435\u0440\u0431\u0435\u0440\u0433"
    ],
    "name:ukr_x_preferred":[
        "\u041e\u0441\u0442\u0435\u0440\u0431\u0435\u0440\u0433"
    ],
    "name:uzb_x_preferred":[
        "Osterberg"
    ],
    "name:vie_x_preferred":[
        "Osterberg"
    ],
    "name:vol_x_preferred":[
        "Osterberg"
    ],
    "name:war_x_preferred":[
        "Osterberg"
    ],
    "name:zho_x_preferred":[
        "\u5965\u65af\u7279\u8d1d\u683c"
    ],
    "wof:name":"Osterberg",
    "wof:placetype":"neighbourhood"
},
  "geometry": {"coordinates":[9.92491,53.31375],"type":"Point"}
}