{
  "type": "Feature",
  "properties": {
    "abrv:eng_x_preferred":[
        "Olem"
    ],
    "gn:admin1_code":"15",
    "gn:admin2_code":"0.0",
    "gn:admin3_code":"16075.0",
    "gn:admin4_code":"16075062.0",
    "gn:asciiname":"Oberlemnitz",
    "gn:country_code":"DE",
    "gn:dem":589,
    "gn:feature_class":"P",
    "gn:feature_code":"PPL",
    "gn:name":"Oberlemnitz",
    "gn:population":0,
    "gn:timezone":"Europe/Berlin",
    "iso:country":"DE",
    "wof:name":"Oberlemnitz",
    "wof:placetype":"neighbourhood",
    "wof:shortcode":"Olem"
},
  "geometry": {"coordinates":[11.60617,50.48605],"type":"Point"}
}