{
  "type": "Feature",
  "properties": {
    "gn:admin1_code":"7",
    "gn:admin2_code":"51.0",
    "gn:admin3_code":"5162.0",
    "gn:admin4_code":"5162028.0",
    "gn:asciiname":"Doetzdorf",
    "gn:country_code":"DE",
    "gn:dem":76,
    "gn:feature_class":"P",
    "gn:feature_code":"PPL",
    "gn:name":"D\u00f6tzdorf",
    "gn:population":0,
    "gn:timezone":"Europe/Berlin",
    "iso:country":"DE",
    "wof:name":"Doetzdorf",
    "wof:placetype":"neighbourhood"
},
  "geometry": {"coordinates":[6.67745,51.03312],"type":"Point"}
}