{
  "type": "Feature",
  "properties": {
    "gn:admin1_code":"1",
    "gn:admin2_code":"84.0",
    "gn:admin3_code":"8436.0",
    "gn:admin4_code":"8436083.0",
    "gn:asciiname":"Frimmenweiler",
    "gn:country_code":"DE",
    "gn:dem":672,
    "gn:feature_class":"P",
    "gn:feature_code":"PPL",
    "gn:name":"Frimmenweiler",
    "gn:population":0,
    "gn:timezone":"Europe/Berlin",
    "iso:country":"DE",
    "wof:name":"Frimmenweiler",
    "wof:placetype":"neighbourhood"
},
  "geometry": {"coordinates":[9.4766,47.85627],"type":"Point"}
}