{
  "type": "Feature",
  "properties": {
    "gn:admin1_code":"2",
    "gn:admin2_code":"93.0",
    "gn:admin3_code":"9376.0",
    "gn:admin4_code":"9376163.0",
    "gn:asciiname":"Kogl",
    "gn:country_code":"DE",
    "gn:dem":395,
    "gn:feature_class":"P",
    "gn:feature_code":"PPL",
    "gn:name":"K\u00f6gl",
    "gn:population":0,
    "gn:timezone":"Europe/Berlin",
    "iso:country":"DE",
    "name:deu_x_preferred":[
        "Kogl"
    ],
    "name:ita_x_preferred":[
        "Kogl"
    ],
    "wof:name":"Kogl",
    "wof:placetype":"neighbourhood"
},
  "geometry": {"coordinates":[12.11243,49.39422],"type":"Point"}
}