{
  "type": "Feature",
  "properties": {
    "gn:admin1_code":"2",
    "gn:admin2_code":"91.0",
    "gn:admin3_code":"9190.0",
    "gn:admin4_code":"9190117.0",
    "gn:asciiname":"Leithen",
    "gn:country_code":"DE",
    "gn:dem":759,
    "gn:feature_class":"P",
    "gn:feature_code":"PPL",
    "gn:name":"Leithen",
    "gn:population":0,
    "gn:timezone":"Europe/Berlin",
    "iso:country":"DE",
    "wof:name":"Leithen",
    "wof:placetype":"neighbourhood"
},
  "geometry": {"coordinates":[10.98034,47.76373],"type":"Point"}
}