{
  "type": "Feature",
  "properties": {
    "gn:population":1390,
    "iso:country":"DE",
    "name:als_x_preferred":[
        "Lachen"
    ],
    "name:arm_x_preferred":[
        "\u053c\u0561\u056d\u0565\u0576"
    ],
    "name:baq_x_preferred":[
        "Lachen"
    ],
    "name:ceb_x_preferred":[
        "Lachen"
    ],
    "name:cze_x_preferred":[
        "Lachen"
    ],
    "name:deu_x_preferred":[
        "Lachen"
    ],
    "name:dut_x_preferred":[
        "Lachen"
    ],
    "name:eng_x_preferred":[
        "Lachen"
    ],
    "name:epo_x_preferred":[
        "Lachen"
    ],
    "name:eus_x_preferred":[
        "Lachen"
    ],
    "name:fra_x_preferred":[
        "Lachen"
    ],
    "name:fre_x_preferred":[
        "Lachen"
    ],
    "name:ger_x_preferred":[
        "Lachen"
    ],
    "name:gsw_x_preferred":[
        "Lachen"
    ],
    "name:hun_x_preferred":[
        "Lachen"
    ],
    "name:ita_x_preferred":[
        "Lachen"
    ],
    "name:lmo_x_preferred":[
        "Lachen"
    ],
    "name:may_x_preferred":[
        "Lachen"
    ],
    "name:nld_x_preferred":[
        "Lachen"
    ],
    "name:per_x_preferred":[
        "\u0644\u0627\u062e\u0646"
    ],
    "name:pol_x_preferred":[
        "Lachen"
    ],
    "name:rum_x_preferred":[
        "Lachen"
    ],
    "name:rus_x_preferred":[
        "\u041b\u0430\u0445\u0435\u043d"
    ],
    "name:srp_x_preferred":[
        "\u041b\u0430\u0445\u0435\u043d"
    ],
    "name:swe_x_preferred":[
        "Lachen"
    ],
    "name:ukr_x_preferred":[
        "\u041b\u0430\u0445\u0435\u043d"
    ],
    "name:uzb_x_preferred":[
        "Lachen"
    ],
    "name:vie_x_preferred":[
        "Lachen"
    ],
    "name:vol_x_preferred":[
        "Lachen"
    ],
    "name:war_x_preferred":[
        "Lachen"
    ],
    "qs:a0":"Bundesrepublik Deutschland",
    "qs:a1":"*Bayern",
    "qs:a1r":"0",
    "qs:a2":"Unterallg\u00e4u",
    "qs:adm0":"Bundesrepublik Deutschland",
    "qs:la_lc":"*",
    "qs:level":"locality",
    "qs:loc":"Lachen",
    "qs:loc_alt":"Lachen",
    "qs:pop":0,
    "qs:type":"buffered point",
    "wd:wordcount":36,
    "wof:lang":[
        "ger"
    ],
    "wof:name":"Lachen",
    "wof:placetype":"locality",
    "wof:population":1390
},
  "geometry": {"coordinates":[10.240378,47.944475],"type":"Point"}
}