{
  "type": "Feature",
  "properties": {
    "gn:admin1_code":"8",
    "gn:admin2_code":"0.0",
    "gn:admin3_code":"7231.0",
    "gn:admin4_code":"7231124.0",
    "gn:asciiname":"Rissbach",
    "gn:country_code":"DE",
    "gn:dem":106,
    "gn:feature_class":"P",
    "gn:feature_code":"PPL",
    "gn:name":"Ri\u00dfbach",
    "gn:population":0,
    "gn:timezone":"Europe/Berlin",
    "iso:country":"DE",
    "wof:name":"Rissbach",
    "wof:placetype":"neighbourhood"
},
  "geometry": {"coordinates":[7.10529,49.96255],"type":"Point"}
}