{
  "type": "Feature",
  "properties": {
    "gn:admin1_code":"2.0",
    "gn:admin2_code":"91.0",
    "gn:admin3_code":"9187.0",
    "gn:admin4_code":"9187163.0",
    "gn:asciiname":"Bamham",
    "gn:country_code":"DE",
    "gn:dem":516,
    "gn:feature_class":"P",
    "gn:feature_code":"PPL",
    "gn:name":"Bamham",
    "gn:population":0,
    "gn:timezone":"Europe/Berlin",
    "iso:country":"DE",
    "wof:name":"Bamham",
    "wof:placetype":"neighbourhood"
},
  "geometry": {"coordinates":[12.1898,47.887],"type":"Point"}
}