{
  "type": "Feature",
  "properties": {
    "gn:admin1_code":"5",
    "gn:admin2_code":"66.0",
    "gn:admin3_code":"6632.0",
    "gn:admin4_code":"6632004.0",
    "gn:asciiname":"Gehau",
    "gn:country_code":"DE",
    "gn:dem":307,
    "gn:feature_class":"P",
    "gn:feature_code":"PPL",
    "gn:name":"Gehau",
    "gn:population":0,
    "gn:timezone":"Europe/Berlin",
    "iso:country":"DE",
    "wof:name":"Gehau",
    "wof:placetype":"neighbourhood"
},
  "geometry": {"coordinates":[9.47629,50.77995],"type":"Point"}
}