{
  "type": "Feature",
  "properties": {
    "iso:country":"DE",
    "wof:name":"Selikum",
    "wof:placetype":"neighbourhood"
},
  "geometry": {"coordinates":[6.70305353561528,51.17251647691248],"type":"Point"}
}