{
  "type": "Feature",
  "properties": {
    "gn:admin1_code":"2.0",
    "gn:admin2_code":"94.0",
    "gn:admin3_code":"9472.0",
    "gn:admin4_code":"9472139.0",
    "gn:asciiname":"Boseneck",
    "gn:country_code":"DE",
    "gn:dem":474,
    "gn:feature_class":"P",
    "gn:feature_code":"PPL",
    "gn:name":"B\u00f6seneck",
    "gn:population":0,
    "gn:timezone":"Europe/Berlin",
    "iso:country":"DE",
    "wof:name":"Boseneck",
    "wof:placetype":"neighbourhood"
},
  "geometry": {"coordinates":[11.71504,50.09358],"type":"Point"}
}