{
  "type": "Feature",
  "properties": {
    "gn:admin1_code":"11",
    "gn:admin2_code":"0.0",
    "gn:admin3_code":"12065.0",
    "gn:admin4_code":"12065084.0",
    "gn:asciiname":"Neubau",
    "gn:country_code":"DE",
    "gn:dem":57,
    "gn:feature_class":"P",
    "gn:feature_code":"PPL",
    "gn:name":"Neubau",
    "gn:population":0,
    "gn:timezone":"Europe/Berlin",
    "iso:country":"DE",
    "name:bar_x_preferred":[
        "Neibau"
    ],
    "name:bul_x_preferred":[
        "\u041d\u043e\u0439\u0431\u0430\u0443"
    ],
    "name:ceb_x_preferred":[
        "Gemeindebezirk Neubau"
    ],
    "name:ces_x_preferred":[
        "Neubau"
    ],
    "name:dan_x_preferred":[
        "Neubau"
    ],
    "name:deu_x_preferred":[
        "Neubau"
    ],
    "name:est_x_preferred":[
        "Neubau"
    ],
    "name:fra_x_preferred":[
        "Neubau"
    ],
    "name:ita_x_preferred":[
        "Neubau"
    ],
    "name:kor_x_preferred":[
        "\ub178\uc774\ubc14\uc6b0"
    ],
    "name:lat_x_preferred":[
        "Neubau"
    ],
    "name:ltz_x_preferred":[
        "Neubau"
    ],
    "name:mkd_x_preferred":[
        "\u041d\u043e\u0458\u0431\u0430\u0443"
    ],
    "name:nld_x_preferred":[
        "Neubau"
    ],
    "name:nor_x_preferred":[
        "Neubau"
    ],
    "name:pol_x_preferred":[
        "Neubau"
    ],
    "name:por_x_preferred":[
        "Neubau"
    ],
    "name:ron_x_preferred":[
        "Neubau"
    ],
    "name:rus_x_preferred":[
        "\u041d\u043e\u0439\u0431\u0430\u0443"
    ],
    "name:slk_x_preferred":[
        "Neubau"
    ],
    "name:spa_x_preferred":[
        "Neubau"
    ],
    "name:srp_x_preferred":[
        "\u041d\u043e\u0458\u0431\u0430\u0443"
    ],
    "name:swe_x_preferred":[
        "Neubau"
    ],
    "name:tur_x_preferred":[
        "Neubau"
    ],
    "name:ukr_x_preferred":[
        "\u041d\u043e\u0439\u0431\u0430\u0443"
    ],
    "name:zho_x_preferred":[
        "\u8bfa\u4f0a\u9c8d"
    ],
    "wof:name":"Neubau",
    "wof:placetype":"neighbourhood"
},
  "geometry": {"coordinates":[13.2364,53.07429000000001],"type":"Point"}
}