{
  "type": "Feature",
  "properties": {
    "gn:admin1_code":"1",
    "gn:admin2_code":"83.0",
    "gn:admin3_code":"8336.0",
    "gn:admin4_code":"8336069.0",
    "gn:asciiname":"Herten",
    "gn:country_code":"DE",
    "gn:dem":276,
    "gn:feature_class":"P",
    "gn:feature_code":"PPL",
    "gn:name":"Herten",
    "gn:population":0,
    "gn:timezone":"Europe/Berlin",
    "iso:country":"DE",
    "name:ara_x_preferred":[
        "\u0647\u064a\u0631\u062a\u0646"
    ],
    "name:azb_x_preferred":[
        "\u0647\u0631\u062a\u0646"
    ],
    "name:bul_x_preferred":[
        "\u0425\u0435\u0440\u0442\u0435\u043d"
    ],
    "name:ceb_x_preferred":[
        "Herten"
    ],
    "name:ces_x_preferred":[
        "Herten"
    ],
    "name:dan_x_preferred":[
        "Herten"
    ],
    "name:deu_x_preferred":[
        "Herten"
    ],
    "name:epo_x_preferred":[
        "Herten"
    ],
    "name:est_x_preferred":[
        "Herten"
    ],
    "name:eus_x_preferred":[
        "Herten"
    ],
    "name:fas_x_preferred":[
        "\u0647\u0631\u062a\u0646"
    ],
    "name:fin_x_preferred":[
        "Herten"
    ],
    "name:fra_x_preferred":[
        "Herten"
    ],
    "name:hun_x_preferred":[
        "Herten"
    ],
    "name:ita_x_preferred":[
        "Herten"
    ],
    "name:kaz_x_preferred":[
        "\u0425\u0435\u0440\u0442\u0435\u043d"
    ],
    "name:kir_x_preferred":[
        "\u0425\u0435\u0440\u0442\u0435\u043d"
    ],
    "name:lim_x_preferred":[
        "Herten"
    ],
    "name:lmo_x_preferred":[
        "Herten"
    ],
    "name:msa_x_preferred":[
        "Herten"
    ],
    "name:nds_x_preferred":[
        "Hi\u00e4tten"
    ],
    "name:nld_x_preferred":[
        "Herten"
    ],
    "name:nno_x_preferred":[
        "Herten"
    ],
    "name:nor_x_preferred":[
        "Herten"
    ],
    "name:oci_x_preferred":[
        "Herten"
    ],
    "name:pol_x_preferred":[
        "Herten"
    ],
    "name:por_x_preferred":[
        "Herten"
    ],
    "name:ron_x_preferred":[
        "Herten"
    ],
    "name:rus_x_preferred":[
        "\u0425\u0435\u0440\u0442\u0435\u043d"
    ],
    "name:spa_x_preferred":[
        "Herten"
    ],
    "name:srp_x_preferred":[
        "\u0425\u0435\u0440\u0442\u0435\u043d"
    ],
    "name:swa_x_preferred":[
        "Herten"
    ],
    "name:swe_x_preferred":[
        "Herten"
    ],
    "name:szl_x_preferred":[
        "Herten"
    ],
    "name:tat_x_preferred":[
        "\u04ba\u0435\u0440\u0442\u0435\u043d"
    ],
    "name:tur_x_preferred":[
        "Herten"
    ],
    "name:ukr_x_preferred":[
        "\u0413\u0435\u0440\u0442\u0435\u043d"
    ],
    "name:uzb_x_preferred":[
        "Herten"
    ],
    "name:vol_x_preferred":[
        "Herten"
    ],
    "name:war_x_preferred":[
        "Herten"
    ],
    "name:zho_x_preferred":[
        "\u9ed1\u5c14\u6ed5"
    ],
    "wof:name":"Herten",
    "wof:placetype":"neighbourhood"
},
  "geometry": {"coordinates":[7.73609,47.55502],"type":"Point"}
}