{
  "type": "Feature",
  "properties": {
    "iso:country":"DE",
    "name:deu_x_preferred":[
        "Malstatt-Burbach"
    ],
    "name:eng_x_preferred":[
        "Burbach-Malstatt"
    ],
    "name:eng_x_variant":[
        "Burbach-Malstatt"
    ],
    "name:unk_x_variant":[
        "Burbach-Malstatt",
        "Malstatt-Burbach"
    ],
    "qs:gn_fcode":"PPLX",
    "qs:gn_local":0,
    "qs:gn_namadm1":"09",
    "qs:gn_name":"Malstatt-Burbach",
    "qs:local_max":4137,
    "qs:local_sum":6400,
    "qs:localhoods":13,
    "qs:name":"Malstatt-Burbach",
    "qs:name_adm0":"Deutschland",
    "qs:name_adm1":"Saarland",
    "qs:name_adm2":"Landkreis Saarbr\u00fccken",
    "qs:name_en":"Burbach-Malstatt",
    "qs:name_lau":"Stadtteil Malstatt",
    "qs:name_local":"Saarbr\u00fccken",
    "qs:photo_max":33,
    "qs:photo_sum":93,
    "qs:placetype":"Suburb",
    "qs:quad_count":17,
    "qs:woe_adm0":23424829,
    "qs:woe_adm1":2345489,
    "qs:woe_adm2":12597017,
    "qs:woe_lau":26823191,
    "qs:woe_local":690631,
    "qs:woe_ver":"7.10.0",
    "wd:wordcount":246,
    "wof:lang":[
        "ger"
    ],
    "wof:name":"Malstatt-Burbach",
    "wof:placetype":"neighbourhood"
},
  "geometry": {"coordinates":[6.950876,49.239158],"type":"Point"}
}