{
  "type": "Feature",
  "properties": {
    "gn:admin1_code":"13.0",
    "gn:admin2_code":"00",
    "gn:admin3_code":"14522.0",
    "gn:admin4_code":"14522460.0",
    "gn:asciiname":"Zinnberg",
    "gn:country_code":"DE",
    "gn:dem":240,
    "gn:feature_class":"P",
    "gn:feature_code":"PPL",
    "gn:name":"Zinnberg",
    "gn:population":0,
    "gn:timezone":"Europe/Berlin",
    "iso:country":"DE",
    "wof:name":"Zinnberg",
    "wof:placetype":"neighbourhood"
},
  "geometry": {"coordinates":[12.6887,50.9152],"type":"Point"}
}