{
  "type": "Feature",
  "properties": {
    "gn:admin1_code":"5",
    "gn:admin2_code":"65.0",
    "gn:admin3_code":"6531.0",
    "gn:admin4_code":"6531009.0",
    "gn:asciiname":"Dornholzhausen",
    "gn:country_code":"DE",
    "gn:dem":201,
    "gn:feature_class":"P",
    "gn:feature_code":"PPL",
    "gn:name":"Dornholzhausen",
    "gn:population":0,
    "gn:timezone":"Europe/Berlin",
    "iso:country":"DE",
    "name:ceb_x_preferred":[
        "Dornholzhausen"
    ],
    "name:deu_x_preferred":[
        "Dornholzhausen"
    ],
    "name:epo_x_preferred":[
        "Dornholzhausen"
    ],
    "name:eus_x_preferred":[
        "Dornholzhausen"
    ],
    "name:fas_x_preferred":[
        "\u062f\u0648\u0631\u0646\u0647\u0648\u0644\u062a\u0633\u0647\u0627\u0648\u0632\u0646"
    ],
    "name:fra_x_preferred":[
        "Dornholzhausen"
    ],
    "name:hun_x_preferred":[
        "Dornholzhausen"
    ],
    "name:ita_x_preferred":[
        "Dornholzhausen"
    ],
    "name:kaz_x_preferred":[
        "\u0414\u043e\u0440\u043d\u0445\u043e\u043b\u044c\u0446\u0445\u0430\u0443\u0437\u0435\u043d"
    ],
    "name:kir_x_preferred":[
        "\u0414\u043e\u0440\u043d\u0445\u043e\u043b\u044c\u0446\u0445\u0430\u0443\u0437\u0435\u043d"
    ],
    "name:msa_x_preferred":[
        "Dornholzhausen"
    ],
    "name:nld_x_preferred":[
        "Dornholzhausen"
    ],
    "name:pol_x_preferred":[
        "Dornholzhausen"
    ],
    "name:por_x_preferred":[
        "Dornholzhausen"
    ],
    "name:ron_x_preferred":[
        "Dornholzhausen"
    ],
    "name:rus_x_preferred":[
        "\u0414\u043e\u0440\u043d\u0445\u043e\u043b\u044c\u0446\u0445\u0430\u0443\u0437\u0435\u043d"
    ],
    "name:spa_x_preferred":[
        "Dornholzhausen"
    ],
    "name:srp_x_preferred":[
        "\u0414\u043e\u0440\u043d\u0445\u043e\u043b\u0446\u0445\u0430\u0443\u0437\u0435\u043d"
    ],
    "name:ukr_x_preferred":[
        "\u0414\u043e\u0440\u043d\u0433\u043e\u043b\u044c\u0446\u0433\u0430\u0443\u0437\u0435\u043d"
    ],
    "name:uzb_x_preferred":[
        "Dornholzhausen"
    ],
    "name:vie_x_preferred":[
        "Dornholzhausen"
    ],
    "name:vol_x_preferred":[
        "Dornholzhausen"
    ],
    "name:war_x_preferred":[
        "Dornholzhausen"
    ],
    "name:zho_x_preferred":[
        "\u591a\u6069\u970d\u5c14\u8328\u8c6a\u68ee"
    ],
    "wof:name":"Dornholzhausen",
    "wof:placetype":"neighbourhood"
},
  "geometry": {"coordinates":[8.60916,50.49454],"type":"Point"}
}