{
  "type": "Feature",
  "properties": {
    "gn:admin1_code":"2.0",
    "gn:admin2_code":"95.0",
    "gn:admin3_code":"9571.0",
    "gn:admin4_code":"9571115.0",
    "gn:asciiname":"Birkach",
    "gn:country_code":"DE",
    "gn:dem":438,
    "gn:feature_class":"P",
    "gn:feature_code":"PPL",
    "gn:name":"Birkach",
    "gn:population":0,
    "gn:timezone":"Europe/Berlin",
    "iso:country":"DE",
    "name:deu_x_preferred":[
        "Birkach"
    ],
    "name:fas_x_preferred":[
        "\u0628\u06cc\u0631\u06a9\u0627\u062e"
    ],
    "name:lat_x_preferred":[
        "Birkach"
    ],
    "name:pol_x_preferred":[
        "Birkach"
    ],
    "wof:name":"Birkach",
    "wof:placetype":"neighbourhood"
},
  "geometry": {"coordinates":[10.5625,49.13985],"type":"Point"}
}