{
  "type": "Feature",
  "properties": {
    "gn:admin1_code":"1",
    "gn:admin2_code":"81.0",
    "gn:admin3_code":"8127.0",
    "gn:admin4_code":"8127102.0",
    "gn:asciiname":"Unterdeufstetten",
    "gn:country_code":"DE",
    "gn:dem":480,
    "gn:feature_class":"P",
    "gn:feature_code":"PPL",
    "gn:name":"Unterdeufstetten",
    "gn:population":0,
    "gn:timezone":"Europe/Berlin",
    "iso:country":"DE",
    "name:und_x_variant":[
        "Unterdeutstetten",
        "Unterdeufstetten"
    ],
    "wof:name":"Unterdeufstetten",
    "wof:placetype":"neighbourhood"
},
  "geometry": {"coordinates":[10.23099,49.05319],"type":"Point"}
}