{
  "type": "Feature",
  "properties": {
    "gn:admin1_code":"5",
    "gn:admin2_code":"66.0",
    "gn:admin3_code":"6634.0",
    "gn:admin4_code":"6634004.0",
    "gn:asciiname":"Linsingen",
    "gn:country_code":"DE",
    "gn:dem":273,
    "gn:feature_class":"P",
    "gn:feature_code":"PPL",
    "gn:name":"Linsingen",
    "gn:population":0,
    "gn:timezone":"Europe/Berlin",
    "iso:country":"DE",
    "name:deu_x_preferred":[
        "Linsingen"
    ],
    "wof:name":"Linsingen",
    "wof:placetype":"neighbourhood"
},
  "geometry": {"coordinates":[9.28337,50.96213],"type":"Point"}
}