{
  "type": "Feature",
  "properties": {
    "iso:country":"DE",
    "name:deu_x_preferred":[
        "Wei\u00df"
    ],
    "wof:name":"Weiss",
    "wof:placetype":"neighbourhood"
},
  "geometry": {"coordinates":[7.03033129055371,50.87347672794495],"type":"Point"}
}