{
  "type": "Feature",
  "properties": {
    "iso:country":"DE",
    "name:bul_x_preferred":[
        "\u0412\u0430\u0439\u0441"
    ],
    "name:cat_x_preferred":[
        "Weiss"
    ],
    "name:ces_x_preferred":[
        "Weiss"
    ],
    "name:deu_x_preferred":[
        "Wei\u00df"
    ],
    "name:deu_x_variant":[
        "Weiss"
    ],
    "name:est_x_preferred":[
        "Weiss"
    ],
    "name:fin_x_preferred":[
        "Weiss"
    ],
    "name:fra_x_preferred":[
        "Weiss"
    ],
    "name:heb_x_preferred":[
        "\u05d5\u05d9\u05d9\u05e1"
    ],
    "name:ita_x_preferred":[
        "Weiss"
    ],
    "name:jpn_x_preferred":[
        "\u30ef\u30a4\u30b9"
    ],
    "name:nld_x_preferred":[
        "Weiss"
    ],
    "name:pol_x_preferred":[
        "Weiss"
    ],
    "name:rus_x_preferred":[
        "\u0412\u0430\u0439\u0441"
    ],
    "name:slk_x_preferred":[
        "Weiss"
    ],
    "name:ukr_x_preferred":[
        "\u0412\u0430\u0439\u0441\u0441"
    ],
    "wof:name":"Weiss",
    "wof:placetype":"neighbourhood"
},
  "geometry": {"coordinates":[7.03033129055371,50.87347672794495],"type":"Point"}
}