{
  "type": "Feature",
  "properties": {
    "gn:admin1_code":"8",
    "gn:admin2_code":"0.0",
    "gn:admin3_code":"7232.0",
    "gn:admin4_code":"7232310.0",
    "gn:asciiname":"Sevenig",
    "gn:country_code":"DE",
    "gn:dem":478,
    "gn:feature_class":"P",
    "gn:feature_code":"PPL",
    "gn:name":"Sevenig",
    "gn:population":0,
    "gn:timezone":"Europe/Berlin",
    "iso:country":"DE",
    "name:deu_x_preferred":[
        "Sevenig"
    ],
    "name:epo_x_preferred":[
        "Sevenig"
    ],
    "name:fra_x_preferred":[
        "Sevenig"
    ],
    "name:ita_x_preferred":[
        "Sevenig"
    ],
    "name:nld_x_preferred":[
        "Sevenig"
    ],
    "name:pol_x_preferred":[
        "Sevenig"
    ],
    "name:srp_x_preferred":[
        "\u0417\u0435\u0432\u0435\u043d\u0438\u0433"
    ],
    "wof:name":"Sevenig",
    "wof:placetype":"neighbourhood"
},
  "geometry": {"coordinates":[6.16545,50.12909000000001],"type":"Point"}
}