{
  "type": "Feature",
  "properties": {
    "gn:admin1_code":"7",
    "gn:admin2_code":"53.0",
    "gn:admin3_code":"5382.0",
    "gn:admin4_code":"5382020.0",
    "gn:asciiname":"Lanzenbach",
    "gn:country_code":"DE",
    "gn:dem":95,
    "gn:feature_class":"P",
    "gn:feature_code":"PPL",
    "gn:name":"Lanzenbach",
    "gn:population":0,
    "gn:timezone":"Europe/Berlin",
    "iso:country":"DE",
    "name:deu_x_preferred":[
        "Lanzenbach"
    ],
    "wof:name":"Lanzenbach",
    "wof:placetype":"neighbourhood"
},
  "geometry": {"coordinates":[7.30943,50.74938],"type":"Point"}
}