{
  "type": "Feature",
  "properties": {
    "gn:admin1_code":"11",
    "gn:admin2_code":"0.0",
    "gn:admin3_code":"12070.0",
    "gn:admin4_code":"12070302.0",
    "gn:asciiname":"Gross Gottschow",
    "gn:country_code":"DE",
    "gn:dem":46,
    "gn:feature_class":"P",
    "gn:feature_code":"PPL",
    "gn:name":"Gro\u00df Gottschow",
    "gn:population":0,
    "gn:timezone":"Europe/Berlin",
    "iso:country":"DE",
    "wof:name":"Gross Gottschow",
    "wof:placetype":"neighbourhood"
},
  "geometry": {"coordinates":[11.96898,53.07124],"type":"Point"}
}