{
  "type": "Feature",
  "properties": {
    "gn:admin1_code":"2",
    "gn:admin2_code":"94.0",
    "gn:admin3_code":"9472.0",
    "gn:admin4_code":"9472133.0",
    "gn:asciiname":"Unterolschnitz",
    "gn:country_code":"DE",
    "gn:dem":388,
    "gn:feature_class":"P",
    "gn:feature_code":"PPL",
    "gn:name":"Unter\u00f6lschnitz",
    "gn:population":0,
    "gn:timezone":"Europe/Berlin",
    "iso:country":"DE",
    "wof:name":"Unterolschnitz",
    "wof:placetype":"neighbourhood"
},
  "geometry": {"coordinates":[11.66844,49.87858],"type":"Point"}
}