{
  "type": "Feature",
  "properties": {
    "gn:admin1_code":"5.0",
    "gn:admin2_code":"64.0",
    "gn:admin3_code":"6435.0",
    "gn:admin4_code":"6435028.0",
    "gn:asciiname":"Barackenhoefe",
    "gn:country_code":"DE",
    "gn:dem":244,
    "gn:feature_class":"P",
    "gn:feature_code":"PPL",
    "gn:name":"Barackenh\u00f6fe",
    "gn:population":0,
    "gn:timezone":"Europe/Berlin",
    "iso:country":"DE",
    "wof:name":"Barackenhoefe",
    "wof:placetype":"neighbourhood"
},
  "geometry": {"coordinates":[9.54935,50.26279],"type":"Point"}
}