{
  "type": "Feature",
  "properties": {
    "gn:admin1_code":"11",
    "gn:admin2_code":"0.0",
    "gn:admin3_code":"12069.0",
    "gn:admin4_code":"12069632.0",
    "gn:asciiname":"Rietzer Grenze",
    "gn:country_code":"DE",
    "gn:dem":68,
    "gn:feature_class":"P",
    "gn:feature_code":"PPL",
    "gn:name":"Rietzer Grenze",
    "gn:population":0,
    "gn:timezone":"Europe/Berlin",
    "iso:country":"DE",
    "wof:name":"Rietzer Grenze",
    "wof:placetype":"neighbourhood"
},
  "geometry": {"coordinates":[12.85,52.08333],"type":"Point"}
}