{
  "type": "Feature",
  "properties": {
    "gn:admin1_code":"6",
    "gn:admin2_code":"0.0",
    "gn:admin3_code":"3157.0",
    "gn:admin4_code":"3157007.0",
    "gn:asciiname":"Gross Gleidingen",
    "gn:country_code":"DE",
    "gn:dem":80,
    "gn:feature_class":"P",
    "gn:feature_code":"PPL",
    "gn:name":"Gro\u00df Gleidingen",
    "gn:population":0,
    "gn:timezone":"Europe/Berlin",
    "iso:country":"DE",
    "name:gml_x_preferred":[
        "Gledinge [a. 1195]"
    ],
    "name:gml_x_variant":[
        "Snitgledinge [a. 1260]",
        "Groten Gleon [a. 1570]"
    ],
    "name:nds_x_preferred":[
        "Groten Glei"
    ],
    "name:osx_x_preferred":[
        "Sudergletinge"
    ],
    "name:und_x_variant":[
        "Gro\u00df Gleidingen"
    ],
    "wof:name":"Gross Gleidingen",
    "wof:placetype":"neighbourhood"
},
  "geometry": {"coordinates":[10.42712,52.23091],"type":"Point"}
}