{
  "type": "Feature",
  "properties": {
    "gn:admin1_code":"12.0",
    "gn:admin2_code":"0.0",
    "gn:admin3_code":"13076.0",
    "gn:admin4_code":"13076140.0",
    "gn:asciiname":"Bahlenhueschen",
    "gn:country_code":"DE",
    "gn:dem":50,
    "gn:feature_class":"P",
    "gn:feature_code":"PPL",
    "gn:name":"Bahlenh\u00fcschen",
    "gn:population":0,
    "gn:timezone":"Europe/Berlin",
    "iso:country":"DE",
    "wof:name":"Bahlenhueschen",
    "wof:placetype":"neighbourhood"
},
  "geometry": {"coordinates":[11.59073,53.52294000000001],"type":"Point"}
}