{
  "type": "Feature",
  "properties": {
    "gn:admin1_code":"6",
    "gn:admin2_code":"0.0",
    "gn:admin3_code":"3459.0",
    "gn:admin4_code":"3459022.0",
    "gn:asciiname":"Ebbendorf",
    "gn:country_code":"DE",
    "gn:dem":108,
    "gn:feature_class":"P",
    "gn:feature_code":"PPL",
    "gn:name":"Ebbendorf",
    "gn:population":0,
    "gn:timezone":"Europe/Berlin",
    "iso:country":"DE",
    "wof:name":"Ebbendorf",
    "wof:placetype":"neighbourhood"
},
  "geometry": {"coordinates":[8.15969,52.19953],"type":"Point"}
}