{
  "type": "Feature",
  "properties": {
    "gn:admin1_code":"2.0",
    "gn:admin2_code":"94.0",
    "gn:admin3_code":"9475.0",
    "gn:admin4_code":"9475184.0",
    "gn:asciiname":"Benk",
    "gn:country_code":"DE",
    "gn:dem":568,
    "gn:feature_class":"P",
    "gn:feature_code":"PPL",
    "gn:name":"Benk",
    "gn:population":0,
    "gn:timezone":"Europe/Berlin",
    "iso:country":"DE",
    "name:deu_x_preferred":[
        "Benk"
    ],
    "name:epo_x_preferred":[
        "Benk"
    ],
    "name:fas_x_preferred":[
        "\u0628\u0646\u06a9"
    ],
    "name:fra_x_preferred":[
        "Benk"
    ],
    "name:hun_x_preferred":[
        "Benk"
    ],
    "name:ita_x_preferred":[
        "Benk"
    ],
    "name:msa_x_preferred":[
        "Benk"
    ],
    "name:nld_x_preferred":[
        "Benk"
    ],
    "name:ron_x_preferred":[
        "Benk"
    ],
    "name:slk_x_preferred":[
        "Benk"
    ],
    "name:slv_x_preferred":[
        "Benk"
    ],
    "name:vie_x_preferred":[
        "Benk"
    ],
    "wof:name":"Benk",
    "wof:placetype":"neighbourhood"
},
  "geometry": {"coordinates":[11.86486,50.17567],"type":"Point"}
}