{
  "type": "Feature",
  "properties": {
    "gn:admin1_code":"1.0",
    "gn:admin2_code":"82.0",
    "gn:admin3_code":"8225.0",
    "gn:admin4_code":"8225032.0",
    "gn:asciiname":"Bretzingen",
    "gn:country_code":"DE",
    "gn:dem":287,
    "gn:feature_class":"P",
    "gn:feature_code":"PPL",
    "gn:name":"Bretzingen",
    "gn:population":0,
    "gn:timezone":"Europe/Berlin",
    "iso:country":"DE",
    "wof:name":"Bretzingen",
    "wof:placetype":"neighbourhood"
},
  "geometry": {"coordinates":[9.48728,49.57666],"type":"Point"}
}