{
  "type": "Feature",
  "properties": {
    "gn:admin1_code":"1",
    "gn:admin2_code":"82.0",
    "gn:admin3_code":"8236.0",
    "gn:admin4_code":"8236062.0",
    "gn:asciiname":"Lehningen",
    "gn:country_code":"DE",
    "gn:dem":429,
    "gn:feature_class":"P",
    "gn:feature_code":"PPL",
    "gn:name":"Lehningen",
    "gn:population":0,
    "gn:timezone":"Europe/Berlin",
    "iso:country":"DE",
    "wof:name":"Lehningen",
    "wof:placetype":"neighbourhood"
},
  "geometry": {"coordinates":[8.8161,48.79567],"type":"Point"}
}