{
  "type": "Feature",
  "properties": {
    "gn:admin1_code":"7",
    "gn:admin2_code":"53.0",
    "gn:admin3_code":"5370.0",
    "gn:admin4_code":"5370020.0",
    "gn:asciiname":"Gendorf",
    "gn:country_code":"DE",
    "gn:dem":50,
    "gn:feature_class":"P",
    "gn:feature_code":"PPL",
    "gn:name":"Gendorf",
    "gn:population":0,
    "gn:timezone":"Europe/Berlin",
    "iso:country":"DE",
    "wof:name":"Gendorf",
    "wof:placetype":"neighbourhood"
},
  "geometry": {"coordinates":[6.18143,51.07081],"type":"Point"}
}