{
  "type": "Feature",
  "properties": {
    "gn:admin1_code":"1",
    "gn:admin2_code":"83.0",
    "gn:admin3_code":"8337.0",
    "gn:admin4_code":"8337049.0",
    "gn:asciiname":"Muhle",
    "gn:country_code":"DE",
    "gn:dem":828,
    "gn:feature_class":"P",
    "gn:feature_code":"PPL",
    "gn:name":"M\u00fchle",
    "gn:population":0,
    "gn:timezone":"Europe/Berlin",
    "iso:country":"DE",
    "wof:name":"Muhle",
    "wof:placetype":"neighbourhood"
},
  "geometry": {"coordinates":[8.00471,47.65909],"type":"Point"}
}