{
  "type": "Feature",
  "properties": {
    "gn:admin1_code":"1",
    "gn:admin2_code":"84.0",
    "gn:admin3_code":"8415.0",
    "gn:admin4_code":"8415093.0",
    "gn:asciiname":"Ohnastetten",
    "gn:country_code":"DE",
    "gn:dem":759,
    "gn:feature_class":"P",
    "gn:feature_code":"PPL",
    "gn:name":"Ohnastetten",
    "gn:population":0,
    "gn:timezone":"Europe/Berlin",
    "iso:country":"DE",
    "wof:name":"Ohnastetten",
    "wof:placetype":"neighbourhood"
},
  "geometry": {"coordinates":[9.32276,48.43826],"type":"Point"}
}