{
  "type": "Feature",
  "properties": {
    "gn:admin1_code":"13.0",
    "gn:admin2_code":"0.0",
    "gn:admin3_code":"14627.0",
    "gn:admin4_code":"14627140.0",
    "gn:asciiname":"Buschbad",
    "gn:country_code":"DE",
    "gn:dem":176,
    "gn:feature_class":"P",
    "gn:feature_code":"PPL",
    "gn:name":"Buschbad",
    "gn:population":0,
    "gn:timezone":"Europe/Berlin",
    "iso:country":"DE",
    "wof:name":"Buschbad",
    "wof:placetype":"neighbourhood"
},
  "geometry": {"coordinates":[13.45473,51.13878],"type":"Point"}
}