{
  "type": "Feature",
  "properties": {
    "gn:admin1_code":"1",
    "gn:admin2_code":"83.0",
    "gn:admin3_code":"8316.0",
    "gn:admin4_code":"8316054.0",
    "gn:asciiname":"Brunnicher Berg",
    "gn:country_code":"DE",
    "gn:dem":436,
    "gn:feature_class":"P",
    "gn:feature_code":"PPL",
    "gn:name":"Brunnicher Berg",
    "gn:population":0,
    "gn:timezone":"Europe/Berlin",
    "iso:country":"DE",
    "wof:name":"Brunnicher Berg",
    "wof:placetype":"neighbourhood"
},
  "geometry": {"coordinates":[7.87002,48.18921],"type":"Point"}
}