{
  "type": "Feature",
  "properties": {
    "gn:admin1_code":"8",
    "gn:admin2_code":"0.0",
    "gn:admin3_code":"7138.0",
    "gn:admin4_code":"7138057.0",
    "gn:asciiname":"Reichenstein",
    "gn:country_code":"DE",
    "gn:dem":231,
    "gn:feature_class":"P",
    "gn:feature_code":"PPL",
    "gn:name":"Reichenstein",
    "gn:population":0,
    "gn:timezone":"Europe/Berlin",
    "iso:country":"DE",
    "name:ceb_x_preferred":[
        "Reichenstein"
    ],
    "name:deu_x_preferred":[
        "Reichenstein"
    ],
    "name:ita_x_preferred":[
        "Reichenstein"
    ],
    "name:swe_x_preferred":[
        "Reichenstein"
    ],
    "wof:name":"Reichenstein",
    "wof:placetype":"neighbourhood"
},
  "geometry": {"coordinates":[7.59334,50.60301],"type":"Point"}
}