{
  "type": "Feature",
  "properties": {
    "gn:admin1_code":"1.0",
    "gn:admin2_code":"081",
    "gn:admin3_code":"8126.0",
    "gn:admin4_code":"8126011.0",
    "gn:asciiname":"Weisslensburg",
    "gn:country_code":"DE",
    "gn:dem":206,
    "gn:feature_class":"P",
    "gn:feature_code":"PPL",
    "gn:name":"Wei\u00dflensburg",
    "gn:population":0,
    "gn:timezone":"Europe/Berlin",
    "iso:country":"DE",
    "wof:name":"Weisslensburg",
    "wof:placetype":"neighbourhood"
},
  "geometry": {"coordinates":[9.43088,49.2028],"type":"Point"}
}