{
  "type": "Feature",
  "properties": {
    "gn:admin1_code":"1",
    "gn:admin2_code":"83.0",
    "gn:admin3_code":"8316.0",
    "gn:admin4_code":"8316042.0",
    "gn:asciiname":"Ettersbach",
    "gn:country_code":"DE",
    "gn:dem":437,
    "gn:feature_class":"P",
    "gn:feature_code":"PPLL",
    "gn:name":"Ettersbach",
    "gn:population":0,
    "gn:timezone":"Europe/Berlin",
    "iso:country":"DE",
    "wof:name":"Ettersbach",
    "wof:placetype":"neighbourhood"
},
  "geometry": {"coordinates":[8.05262,48.09303],"type":"Point"}
}