{
  "type": "Feature",
  "properties": {
    "gn:admin1_code":"7",
    "gn:admin2_code":"57.0",
    "gn:admin3_code":"5766.0",
    "gn:admin4_code":"5766008.0",
    "gn:asciiname":"Lindemannsheide",
    "gn:country_code":"DE",
    "gn:dem":80,
    "gn:feature_class":"P",
    "gn:feature_code":"PPL",
    "gn:name":"Lindemannsheide",
    "gn:population":0,
    "gn:timezone":"Europe/Berlin",
    "iso:country":"DE",
    "wof:name":"Lindemannsheide",
    "wof:placetype":"neighbourhood"
},
  "geometry": {"coordinates":[8.76263,52.05903],"type":"Point"}
}