{
  "type": "Feature",
  "properties": {
    "gn:admin1_code":"11",
    "gn:admin2_code":"0.0",
    "gn:admin3_code":"12062.0",
    "gn:admin4_code":"12062333.0",
    "gn:asciiname":"Rehain",
    "gn:country_code":"DE",
    "gn:dem":117,
    "gn:feature_class":"P",
    "gn:feature_code":"PPL",
    "gn:name":"Rehain",
    "gn:population":0,
    "gn:timezone":"Europe/Berlin",
    "iso:country":"DE",
    "wof:name":"Rehain",
    "wof:placetype":"neighbourhood"
},
  "geometry": {"coordinates":[13.82615,51.66579],"type":"Point"}
}