{
  "type": "Feature",
  "properties": {
    "iso:country":"DE",
    "name:ceb_x_preferred":[
        "Orlovat"
    ],
    "name:deu_x_preferred":[
        "Essenberg"
    ],
    "name:deu_x_variant":[
        "Orlovat"
    ],
    "name:epo_x_preferred":[
        "Orlovat"
    ],
    "name:fra_x_preferred":[
        "Orlovat"
    ],
    "name:hrv_x_preferred":[
        "Orlovat"
    ],
    "name:hun_x_preferred":[
        "Orl\u00f3d"
    ],
    "name:msa_x_preferred":[
        "Orlovat"
    ],
    "name:ron_x_preferred":[
        "Orlovat"
    ],
    "name:rus_x_preferred":[
        "\u041e\u0440\u043b\u043e\u0432\u0430\u0442"
    ],
    "name:slv_x_preferred":[
        "Orlovat"
    ],
    "name:srp_x_preferred":[
        "\u041e\u0440\u043b\u043e\u0432\u0430\u0442"
    ],
    "qs:gn_adm0_cc":"DE",
    "qs:gn_fcode":"PPLX",
    "qs:gn_local":2934691,
    "qs:gn_namadm1":"07",
    "qs:gn_name":"Essenberg",
    "qs:local_max":4851,
    "qs:local_sum":11005,
    "qs:localhoods":24,
    "qs:name":"Essenberg",
    "qs:name_adm0":"Deutschland",
    "qs:name_adm1":"Nordrhein-Westfalen",
    "qs:name_adm2":"Stadtkreis Duisburg",
    "qs:name_lau":"Stadtteil Bergheim",
    "qs:name_local":"Duisburg",
    "qs:photo_max":30,
    "qs:photo_sum":116,
    "qs:placetype":"Suburb",
    "qs:quad_count":17,
    "qs:woe_adm0":23424829,
    "qs:woe_adm1":2345487,
    "qs:woe_adm2":12596956,
    "qs:woe_lau":26822199,
    "qs:woe_local":645877,
    "qs:woe_ver":"7.10.0",
    "wof:lang":[
        "ger"
    ],
    "wof:name":"Essenberg",
    "wof:placetype":"neighbourhood"
},
  "geometry": {"coordinates":[6.705168,51.439106],"type":"Point"}
}