{
  "type": "Feature",
  "properties": {
    "gn:gn_country":"DE",
    "gn:gn_fcode":"PPLA4",
    "gn:gn_pop":394,
    "gn:population":394,
    "iso:country":"DE",
    "name:baq_x_preferred":[
        "Kr\u00fcmmel"
    ],
    "name:chi_x_preferred":[
        "\u514b\u5415\u6885\u5c14"
    ],
    "name:deu_x_preferred":[
        "Kr\u00fcmmel"
    ],
    "name:dut_x_preferred":[
        "Kr\u00fcmmel"
    ],
    "name:eng_x_preferred":[
        "Kr\u00fcmmel"
    ],
    "name:epo_x_preferred":[
        "Kr\u00fcmmel"
    ],
    "name:fre_x_preferred":[
        "Kr\u00fcmmel"
    ],
    "name:ger_x_preferred":[
        "Kr\u00fcmmel"
    ],
    "name:hun_x_preferred":[
        "Kr\u00fcmmel"
    ],
    "name:ita_x_preferred":[
        "Kr\u00fcmmel"
    ],
    "name:jpn_x_preferred":[
        "\u30af\u30ea\u30e5\u30fc\u30f3\u30e1\u30eb"
    ],
    "name:may_x_preferred":[
        "Kr\u00fcmmel"
    ],
    "name:per_x_preferred":[
        "\u06a9\u0631\u0648\u0645\u0644"
    ],
    "name:pol_x_preferred":[
        "Kr\u00fcmmel"
    ],
    "name:por_x_preferred":[
        "Kr\u00fcmmel"
    ],
    "name:rum_x_preferred":[
        "Kr\u00fcmmel"
    ],
    "name:rus_x_preferred":[
        "\u041a\u0440\u044e\u043c\u043c\u0435\u043b\u044c"
    ],
    "name:srp_x_preferred":[
        "\u041a\u0440\u0438\u043c\u0435\u043b"
    ],
    "name:ukr_x_preferred":[
        "\u041a\u0440\u044e\u043c\u043c\u0435\u043b\u044c"
    ],
    "name:uzb_x_preferred":[
        "Kr\u00fcmmel"
    ],
    "name:vol_x_preferred":[
        "Kr\u00fcmmel"
    ],
    "name:war_x_preferred":[
        "Kr\u00fcmmel"
    ],
    "qs_pg:aaroncc":"DE",
    "qs_pg:gn_country":"DE",
    "qs_pg:gn_fcode":"PPLA4",
    "qs_pg:gn_pop":394,
    "qs_pg:name":"Kr\u00fcmmel",
    "qs_pg:photos_9r":0,
    "qs_pg:photos_sr":0,
    "qs_pg:pop_sr":2,
    "qs_pg:qs_pg_placetype":"locality",
    "wof:name":"Kr\u00fcmmel",
    "wof:placetype":"locality",
    "wof:population":394
},
  "geometry": {"coordinates":[7.71667,50.53333],"type":"Point"}
}