{
  "type": "Feature",
  "properties": {
    "iso:country":"DE",
    "wof:name":"Mobschatz",
    "wof:placetype":"neighbourhood"
},
  "geometry": {"coordinates":[13.6450967770878,51.07751301418114],"type":"Point"}
}