{
  "type": "Feature",
  "properties": {
    "gn:admin1_code":"2",
    "gn:admin2_code":"92.0",
    "gn:admin3_code":"9272.0",
    "gn:admin4_code":"9272134.0",
    "gn:asciiname":"Neuhutte",
    "gn:cc2":"DE",
    "gn:country_code":"DE",
    "gn:dem":791,
    "gn:feature_class":"P",
    "gn:feature_code":"PPL",
    "gn:name":"Neuh\u00fctte",
    "gn:population":0,
    "gn:timezone":"Europe/Berlin",
    "iso:country":"DE",
    "name:und_x_variant":[
        "Neuh\u00fctte F\u00fcrstenh\u00fctte",
        "Neuh\u00fctte"
    ],
    "wof:name":"Neuhutte",
    "wof:placetype":"neighbourhood"
},
  "geometry": {"coordinates":[13.57498,48.86596],"type":"Point"}
}