{
  "type": "Feature",
  "properties": {
    "gn:admin1_code":"2.0",
    "gn:admin2_code":"092",
    "gn:admin3_code":"9278.0",
    "gn:admin4_code":"9278167.0",
    "gn:asciiname":"Wolferkofen",
    "gn:country_code":"DE",
    "gn:dem":340,
    "gn:feature_class":"P",
    "gn:feature_code":"PPL",
    "gn:name":"Wolferkofen",
    "gn:population":0,
    "gn:timezone":"Europe/Berlin",
    "iso:country":"DE",
    "wof:name":"Wolferkofen",
    "wof:placetype":"neighbourhood"
},
  "geometry": {"coordinates":[12.64235,48.81726],"type":"Point"}
}