{
  "type": "Feature",
  "properties": {
    "gn:admin1_code":"10.0",
    "gn:admin2_code":"0.0",
    "gn:admin3_code":"1051.0",
    "gn:admin4_code":"1051012.0",
    "gn:asciiname":"Buchholzermoor",
    "gn:country_code":"DE",
    "gn:dem":-3,
    "gn:feature_class":"P",
    "gn:feature_code":"PPL",
    "gn:name":"Buchholzermoor",
    "gn:population":0,
    "gn:timezone":"Europe/Berlin",
    "iso:country":"DE",
    "wof:name":"Buchholzermoor",
    "wof:placetype":"neighbourhood"
},
  "geometry": {"coordinates":[9.23751,53.96556],"type":"Point"}
}