{
  "type": "Feature",
  "properties": {
    "gn:admin1_code":"12",
    "gn:admin2_code":"0.0",
    "gn:admin3_code":"13074.0",
    "gn:admin4_code":"13074044.0",
    "gn:asciiname":"Gagzow",
    "gn:country_code":"DE",
    "gn:dem":14,
    "gn:feature_class":"P",
    "gn:feature_code":"PPL",
    "gn:name":"Gagzow",
    "gn:population":0,
    "gn:timezone":"Europe/Berlin",
    "iso:country":"DE",
    "wof:name":"Gagzow",
    "wof:placetype":"neighbourhood"
},
  "geometry": {"coordinates":[11.52599,53.93259000000001],"type":"Point"}
}