{
  "type": "Feature",
  "properties": {
    "gn:admin1_code":"2",
    "gn:admin2_code":"91.0",
    "gn:admin3_code":"9189.0",
    "gn:admin4_code":"9189159.0",
    "gn:asciiname":"Moosen",
    "gn:country_code":"DE",
    "gn:dem":527,
    "gn:feature_class":"P",
    "gn:feature_code":"PPLL",
    "gn:name":"Moosen",
    "gn:population":0,
    "gn:timezone":"Europe/Berlin",
    "iso:country":"DE",
    "wof:name":"Moosen",
    "wof:placetype":"neighbourhood"
},
  "geometry": {"coordinates":[12.49799,47.82004000000001],"type":"Point"}
}