{
  "type": "Feature",
  "properties": {
    "gn:admin1_code":"2.0",
    "gn:admin2_code":"92.0",
    "gn:admin3_code":"9278.0",
    "gn:admin4_code":"9278118.0",
    "gn:asciiname":"Breitenweinzier",
    "gn:country_code":"DE",
    "gn:dem":343,
    "gn:feature_class":"P",
    "gn:feature_code":"PPL",
    "gn:name":"Breitenweinzier",
    "gn:population":0,
    "gn:timezone":"Europe/Berlin",
    "iso:country":"DE",
    "name:und_x_variant":[
        "Breitenweinzler",
        "Breitenweinzier"
    ],
    "wof:name":"Breitenweinzier",
    "wof:placetype":"neighbourhood"
},
  "geometry": {"coordinates":[12.72913,48.90275],"type":"Point"}
}