{
  "type": "Feature",
  "properties": {
    "gn:admin1_code":"1",
    "gn:admin2_code":"82.0",
    "gn:admin3_code":"8216.0",
    "gn:admin4_code":"8216015.0",
    "gn:asciiname":"Mittelberg",
    "gn:country_code":"DE",
    "gn:dem":508,
    "gn:feature_class":"P",
    "gn:feature_code":"PPL",
    "gn:name":"Mittelberg",
    "gn:population":0,
    "gn:timezone":"Europe/Berlin",
    "iso:country":"DE",
    "name:als_x_preferred":[
        "Mittelberg"
    ],
    "name:ceb_x_preferred":[
        "Mittelberg"
    ],
    "name:deu_x_preferred":[
        "Mittelberg"
    ],
    "name:fas_x_preferred":[
        "\u0645\u06cc\u062a\u0644\u0628\u0631\u06af"
    ],
    "name:fin_x_preferred":[
        "Mittelberg"
    ],
    "name:fra_x_preferred":[
        "Mittelberg"
    ],
    "name:fur_x_preferred":[
        "Mittelberg"
    ],
    "name:hun_x_preferred":[
        "Mittelberg"
    ],
    "name:ita_x_preferred":[
        "Mittelberg"
    ],
    "name:nld_x_preferred":[
        "Mittelberg"
    ],
    "name:nno_x_preferred":[
        "Mittelberg"
    ],
    "name:nor_x_preferred":[
        "Mittelberg"
    ],
    "name:pol_x_preferred":[
        "Mittelberg"
    ],
    "name:rus_x_preferred":[
        "\u041c\u0438\u0442\u0442\u0435\u043b\u044c\u0431\u0435\u0440\u0433"
    ],
    "name:slk_x_preferred":[
        "Mittelberg"
    ],
    "name:spa_x_preferred":[
        "Mittelberg"
    ],
    "name:swe_x_preferred":[
        "Mittelberg"
    ],
    "name:szl_x_preferred":[
        "Mittelberg"
    ],
    "name:ukr_x_preferred":[
        "\u041c\u0456\u0442\u0442\u0435\u043b\u044c\u0431\u0435\u0440\u0433"
    ],
    "name:uzb_x_preferred":[
        "Mittelberg"
    ],
    "name:vol_x_preferred":[
        "Mittelberg"
    ],
    "name:war_x_preferred":[
        "Mittelberg"
    ],
    "name:zho_x_preferred":[
        "\u7c73\u7279\u723e\u8c9d\u683c"
    ],
    "wof:name":"Mittelberg",
    "wof:placetype":"neighbourhood"
},
  "geometry": {"coordinates":[8.40523,48.84563],"type":"Point"}
}