{
  "type": "Feature",
  "properties": {
    "gn:admin1_code":"2",
    "gn:admin2_code":"92.0",
    "gn:admin3_code":"9275.0",
    "gn:admin4_code":"9275153.0",
    "gn:asciiname":"Lammersdorf",
    "gn:country_code":"DE",
    "gn:dem":536,
    "gn:feature_class":"P",
    "gn:feature_code":"PPL",
    "gn:name":"L\u00e4mmersdorf",
    "gn:population":0,
    "gn:timezone":"Europe/Berlin",
    "iso:country":"DE",
    "wof:name":"Lammersdorf",
    "wof:placetype":"neighbourhood"
},
  "geometry": {"coordinates":[13.69532,48.5586],"type":"Point"}
}