{
  "type": "Feature",
  "properties": {
    "gn:admin1_code":"6",
    "gn:admin2_code":"0.0",
    "gn:admin3_code":"3459.0",
    "gn:admin4_code":"3459031.0",
    "gn:asciiname":"Gross Wittefelderort",
    "gn:country_code":"DE",
    "gn:dem":39,
    "gn:feature_class":"P",
    "gn:feature_code":"PPL",
    "gn:name":"Gro\u00df Wittefelderort",
    "gn:population":0,
    "gn:timezone":"Europe/Berlin",
    "iso:country":"DE",
    "wof:name":"Gross Wittefelderort",
    "wof:placetype":"neighbourhood"
},
  "geometry": {"coordinates":[8.03313,52.48843000000001],"type":"Point"}
}