{
  "type": "Feature",
  "properties": {
    "gn:admin1_code":"2",
    "gn:admin2_code":"96.0",
    "gn:admin3_code":"9674.0",
    "gn:admin4_code":"9674159.0",
    "gn:asciiname":"Trossenfurt",
    "gn:country_code":"DE",
    "gn:dem":305,
    "gn:feature_class":"P",
    "gn:feature_code":"PPL",
    "gn:name":"Trossenfurt",
    "gn:population":0,
    "gn:timezone":"Europe/Berlin",
    "iso:country":"DE",
    "wof:name":"Trossenfurt",
    "wof:placetype":"neighbourhood"
},
  "geometry": {"coordinates":[10.66069,49.92592],"type":"Point"}
}