{
  "type": "Feature",
  "properties": {
    "gn:gn_country":"DE",
    "gn:gn_fcode":"PPLA4",
    "gn:gn_pop":843,
    "gn:population":843,
    "iso:country":"DE",
    "name:baq_x_preferred":[
        "Hardert"
    ],
    "name:chi_x_preferred":[
        "\u54c8\u5c14\u5fb7\u5c14\u7279"
    ],
    "name:dut_x_preferred":[
        "Hardert"
    ],
    "name:eng_x_preferred":[
        "Hardert"
    ],
    "name:epo_x_preferred":[
        "Hardert"
    ],
    "name:fre_x_preferred":[
        "Hardert"
    ],
    "name:ger_x_preferred":[
        "Hardert"
    ],
    "name:hun_x_preferred":[
        "Hardert"
    ],
    "name:ita_x_preferred":[
        "Hardert"
    ],
    "name:jpn_x_preferred":[
        "\u30cf\u30eb\u30c0\u30fc\u30c8"
    ],
    "name:kaz_x_preferred":[
        "\u0425\u0430\u0440\u0434\u0435\u0440\u0442"
    ],
    "name:kir_x_preferred":[
        "\u0425\u0430\u0440\u0434\u0435\u0440\u0442"
    ],
    "name:may_x_preferred":[
        "Hardert"
    ],
    "name:per_x_preferred":[
        "\u0647\u0627\u0631\u062f\u0631\u062a"
    ],
    "name:pol_x_preferred":[
        "Hardert"
    ],
    "name:por_x_preferred":[
        "Hardert"
    ],
    "name:rum_x_preferred":[
        "Hardert"
    ],
    "name:rus_x_preferred":[
        "\u0425\u0430\u0440\u0434\u0435\u0440\u0442"
    ],
    "name:srp_x_preferred":[
        "\u0425\u0430\u0440\u0434\u0435\u0440\u0442"
    ],
    "name:ukr_x_preferred":[
        "\u0413\u0430\u0440\u0434\u0435\u0440\u0442"
    ],
    "name:uzb_x_preferred":[
        "Hardert"
    ],
    "name:vie_x_preferred":[
        "Hardert"
    ],
    "name:vol_x_preferred":[
        "Hardert"
    ],
    "name:war_x_preferred":[
        "Hardert"
    ],
    "qs_pg:aaroncc":"DE",
    "qs_pg:gn_country":"DE",
    "qs_pg:gn_fcode":"PPLA4",
    "qs_pg:gn_pop":843,
    "qs_pg:name":"Hardert",
    "qs_pg:photos_9r":0,
    "qs_pg:photos_sr":0,
    "qs_pg:pop_sr":2,
    "qs_pg:qs_pg_placetype":"locality",
    "wof:name":"Hardert",
    "wof:placetype":"locality",
    "wof:population":843
},
  "geometry": {"coordinates":[7.51667,50.51667],"type":"Point"}
}