{
  "type": "Feature",
  "properties": {
    "gn:admin1_code":"2",
    "gn:admin2_code":"94.0",
    "gn:admin3_code":"9472.0",
    "gn:admin4_code":"9472180.0",
    "gn:asciiname":"Voita",
    "gn:country_code":"DE",
    "gn:dem":452,
    "gn:feature_class":"P",
    "gn:feature_code":"PPL",
    "gn:name":"Voita",
    "gn:population":0,
    "gn:timezone":"Europe/Berlin",
    "iso:country":"DE",
    "wof:name":"Voita",
    "wof:placetype":"neighbourhood"
},
  "geometry": {"coordinates":[11.70799,49.82337],"type":"Point"}
}