{
  "type": "Feature",
  "properties": {
    "gn:admin1_code":"1.0",
    "gn:admin2_code":"084",
    "gn:admin3_code":"8436.0",
    "gn:admin4_code":"8436010.0",
    "gn:asciiname":"Weitprechts",
    "gn:country_code":"DE",
    "gn:dem":696,
    "gn:feature_class":"P",
    "gn:feature_code":"PPL",
    "gn:name":"Weitprechts",
    "gn:population":0,
    "gn:timezone":"Europe/Berlin",
    "iso:country":"DE",
    "wof:name":"Weitprechts",
    "wof:placetype":"neighbourhood"
},
  "geometry": {"coordinates":[9.82625,47.84693],"type":"Point"}
}