{
  "type": "Feature",
  "properties": {
    "gn:admin1_code":"12",
    "gn:admin2_code":"0.0",
    "gn:admin3_code":"13073.0",
    "gn:admin4_code":"13073079.0",
    "gn:asciiname":"Stoenkvitz",
    "gn:country_code":"DE",
    "gn:dem":12,
    "gn:feature_class":"P",
    "gn:feature_code":"PPL",
    "gn:name":"St\u00f6nkvitz",
    "gn:population":0,
    "gn:timezone":"Europe/Berlin",
    "iso:country":"DE",
    "wof:name":"Stoenkvitz",
    "wof:placetype":"neighbourhood"
},
  "geometry": {"coordinates":[13.34616,54.37366],"type":"Point"}
}