{
  "type": "Feature",
  "properties": {
    "gn:admin1_code":"15",
    "gn:admin2_code":"0.0",
    "gn:admin3_code":"16077.0",
    "gn:admin4_code":"16077036.0",
    "gn:asciiname":"Nirkendorf",
    "gn:country_code":"DE",
    "gn:dem":221,
    "gn:feature_class":"P",
    "gn:feature_code":"PPL",
    "gn:name":"Nirkendorf",
    "gn:population":0,
    "gn:timezone":"Europe/Berlin",
    "iso:country":"DE",
    "wof:name":"Nirkendorf",
    "wof:placetype":"neighbourhood"
},
  "geometry": {"coordinates":[12.52991,50.94235],"type":"Point"}
}