{
  "type": "Feature",
  "properties": {
    "gn:admin1_code":"6",
    "gn:admin2_code":"0.0",
    "gn:admin3_code":"3353.0",
    "gn:admin4_code":"3353026.0",
    "gn:asciiname":"Daerstorf",
    "gn:country_code":"DE",
    "gn:dem":61,
    "gn:feature_class":"P",
    "gn:feature_code":"PPL",
    "gn:name":"Daerstorf",
    "gn:population":0,
    "gn:timezone":"Europe/Berlin",
    "iso:country":"DE",
    "name:deu_x_preferred":[
        "Daerstorf"
    ],
    "name:fas_x_preferred":[
        "\u062f\u0627\u0626\u0631\u0634\u062a\u0648\u0631\u0641"
    ],
    "name:fra_x_preferred":[
        "Daerstorf"
    ],
    "name:nds_x_preferred":[
        "Doasd\u00f6rp"
    ],
    "wof:name":"Daerstorf",
    "wof:placetype":"neighbourhood"
},
  "geometry": {"coordinates":[9.80676,53.4382],"type":"Point"}
}