{
  "type": "Feature",
  "properties": {
    "gn:admin1_code":"6",
    "gn:admin2_code":"0.0",
    "gn:admin3_code":"3353.0",
    "gn:admin4_code":"3353026.0",
    "gn:asciiname":"Daerstorf",
    "gn:country_code":"DE",
    "gn:dem":61,
    "gn:feature_class":"P",
    "gn:feature_code":"PPL",
    "gn:name":"Daerstorf",
    "gn:population":0,
    "gn:timezone":"Europe/Berlin",
    "iso:country":"DE",
    "wof:name":"Daerstorf",
    "wof:placetype":"neighbourhood"
},
  "geometry": {"coordinates":[9.80676,53.4382],"type":"Point"}
}