{
  "type": "Feature",
  "properties": {
    "gn:admin1_code":"13",
    "gn:admin2_code":"0.0",
    "gn:admin3_code":"14729.0",
    "gn:admin4_code":"14729060.0",
    "gn:asciiname":"Cunnersdorf",
    "gn:country_code":"DE",
    "gn:dem":132,
    "gn:feature_class":"P",
    "gn:feature_code":"PPL",
    "gn:name":"Cunnersdorf",
    "gn:population":0,
    "gn:timezone":"Europe/Berlin",
    "iso:country":"DE",
    "wof:name":"Cunnersdorf",
    "wof:placetype":"neighbourhood"
},
  "geometry": {"coordinates":[12.56218,51.36594],"type":"Point"}
}