{
  "type": "Feature",
  "properties": {
    "gn:admin1_code":"9",
    "gn:admin2_code":"0.0",
    "gn:admin3_code":"10044.0",
    "gn:admin4_code":"10044121.0",
    "gn:asciiname":"Ihn",
    "gn:country_code":"DE",
    "gn:dem":208,
    "gn:feature_class":"P",
    "gn:feature_code":"PPL",
    "gn:name":"Ihn",
    "gn:population":0,
    "gn:timezone":"Europe/Berlin",
    "iso:country":"DE",
    "wof:name":"Ihn",
    "wof:placetype":"neighbourhood"
},
  "geometry": {"coordinates":[6.60461,49.32355],"type":"Point"}
}