{
  "type": "Feature",
  "properties": {
    "gn:country":"DE",
    "gn:fcode":"PPL",
    "gn:population":0,
    "iso:country":"DE",
    "name:eng_x_preferred":[
        "Rott"
    ],
    "name:fra_x_preferred":[
        "Rott"
    ],
    "name:jpn_x_preferred":[
        "\u30ed\u30c3\u30c8"
    ],
    "name:lim_x_preferred":[
        "Rot"
    ],
    "name:ltz_x_preferred":[
        "Rott"
    ],
    "name:nan_x_preferred":[
        "Rott"
    ],
    "name:nld_x_preferred":[
        "Rott"
    ],
    "qs_pg:aaroncc":"DE",
    "qs_pg:gn_country":"DE",
    "qs_pg:gn_fcode":"PPL",
    "qs_pg:gn_pop":0,
    "qs_pg:name":"Rott",
    "qs_pg:name_adm0":"Deutschland",
    "qs_pg:name_adm1":"Nordrhein-Westfalen",
    "qs_pg:photos":76,
    "qs_pg:photos_1k":15,
    "qs_pg:photos_9k":1,
    "qs_pg:photos_9r":3,
    "qs_pg:photos_all":76,
    "qs_pg:photos_sr":3,
    "qs_pg:pop_sr":0,
    "qs_pg:qs_pg_placetype":"locality",
    "qs_pg:qs_pg_placetype_gp":"Town",
    "qs_pg:woe_adm0":23424829,
    "woe:adm0_id":23424829,
    "woe:name_adm0":"Deutschland",
    "woe:name_adm1":"Nordrhein-Westfalen",
    "woe:placetype":"Town",
    "wof:name":"Rott",
    "wof:placetype":"neighbourhood"
},
  "geometry": {"coordinates":[6.21011,50.68243],"type":"Point"}
}