{
  "type": "Feature",
  "properties": {
    "gn:admin1_code":"1",
    "gn:admin2_code":"81.0",
    "gn:admin3_code":"8136.0",
    "gn:admin4_code":"8136010.0",
    "gn:asciiname":"Unterriffingen",
    "gn:country_code":"DE",
    "gn:dem":623,
    "gn:feature_class":"P",
    "gn:feature_code":"PPL",
    "gn:name":"Unterriffingen",
    "gn:population":0,
    "gn:timezone":"Europe/Berlin",
    "iso:country":"DE",
    "wof:name":"Unterriffingen",
    "wof:placetype":"neighbourhood"
},
  "geometry": {"coordinates":[10.31719,48.82699],"type":"Point"}
}