{
  "type": "Feature",
  "properties": {
    "gn:country":"DE",
    "gn:fcode":"PPL",
    "gn:population":0,
    "iso:country":"DE",
    "name:als_x_preferred":[
        "Schauinsland"
    ],
    "name:ceb_x_preferred":[
        "Schauinsland"
    ],
    "name:dan_x_preferred":[
        "Schauinsland"
    ],
    "name:deu_x_preferred":[
        "Schauinsland"
    ],
    "name:epo_x_preferred":[
        "Schauinsland"
    ],
    "name:fra_x_preferred":[
        "Schauinsland"
    ],
    "name:nld_x_preferred":[
        "Schauinsland"
    ],
    "name:nno_x_preferred":[
        "Schauinsland"
    ],
    "name:pnb_x_preferred":[
        "\u0634\u0648\u0627\u0646\u0632\u0644\u06cc\u0646\u0688"
    ],
    "name:pol_x_preferred":[
        "Schauinsland"
    ],
    "name:por_x_preferred":[
        "Schauinsland"
    ],
    "name:spa_x_preferred":[
        "Schauinsland"
    ],
    "qs_pg:aaroncc":"DE",
    "qs_pg:gn_country":"DE",
    "qs_pg:gn_fcode":"PPL",
    "qs_pg:gn_pop":0,
    "qs_pg:name":"Schauinsland",
    "qs_pg:name_adm0":"Deutschland",
    "qs_pg:name_adm1":"Baden-W\u00fcrttemberg",
    "qs_pg:photos":426,
    "qs_pg:photos_1k":86,
    "qs_pg:photos_9k":2,
    "qs_pg:photos_9r":5,
    "qs_pg:photos_all":426,
    "qs_pg:photos_sr":6,
    "qs_pg:pop_sr":0,
    "qs_pg:qs_pg_placetype":"locality",
    "qs_pg:qs_pg_placetype_gp":"Town",
    "qs_pg:woe_adm0":23424829,
    "woe:adm0_id":23424829,
    "woe:name_adm0":"Deutschland",
    "woe:name_adm1":"Baden-W\u00fcrttemberg",
    "woe:placetype":"Town",
    "wof:name":"Schauinsland",
    "wof:placetype":"neighbourhood"
},
  "geometry": {"coordinates":[7.89619,47.93547],"type":"Point"}
}