{
  "type": "Feature",
  "properties": {
    "gn:admin1_code":"15.0",
    "gn:admin2_code":"00",
    "gn:admin3_code":"16074.0",
    "gn:admin4_code":"16074057.0",
    "gn:asciiname":"Zimmritz",
    "gn:country_code":"DE",
    "gn:dem":413,
    "gn:feature_class":"P",
    "gn:feature_code":"PPL",
    "gn:name":"Zimmritz",
    "gn:population":0,
    "gn:timezone":"Europe/Berlin",
    "iso:country":"DE",
    "wof:name":"Zimmritz",
    "wof:placetype":"neighbourhood"
},
  "geometry": {"coordinates":[11.49942,50.85657],"type":"Point"}
}