{
  "type": "Feature",
  "properties": {
    "gn:admin1_code":"15",
    "gn:admin2_code":"0.0",
    "gn:admin3_code":"16071.0",
    "gn:admin4_code":"16071079.0",
    "gn:asciiname":"Mohrental",
    "gn:country_code":"DE",
    "gn:dem":401,
    "gn:feature_class":"P",
    "gn:feature_code":"PPL",
    "gn:name":"Mohrental",
    "gn:population":0,
    "gn:timezone":"Europe/Berlin",
    "iso:country":"DE",
    "name:und_x_variant":[
        "Mohrenthal",
        "Mohrental"
    ],
    "wof:name":"Mohrental",
    "wof:placetype":"neighbourhood"
},
  "geometry": {"coordinates":[11.20811,50.81989],"type":"Point"}
}