{
  "type": "Feature",
  "properties": {
    "gn:admin1_code":"2",
    "gn:admin2_code":"95.0",
    "gn:admin3_code":"9561.0",
    "gn:admin4_code":"9561000.0",
    "gn:asciiname":"Liegenbach",
    "gn:country_code":"DE",
    "gn:dem":450,
    "gn:feature_class":"P",
    "gn:feature_code":"PPL",
    "gn:name":"Liegenbach",
    "gn:population":0,
    "gn:timezone":"Europe/Berlin",
    "iso:country":"DE",
    "wof:name":"Liegenbach",
    "wof:placetype":"neighbourhood"
},
  "geometry": {"coordinates":[10.47868,49.28283],"type":"Point"}
}