{
  "type": "Feature",
  "properties": {
    "iso:country":"DE",
    "wof:name":"Woof",
    "wof:placetype":"neighbourhood"
},
  "geometry": {"coordinates":[6.32519804459463,51.15298685028848],"type":"Point"}
}