{
  "type": "Feature",
  "properties": {
    "gn:admin1_code":"7",
    "gn:admin2_code":"57.0",
    "gn:admin3_code":"5762.0",
    "gn:admin4_code":"5762024.0",
    "gn:asciiname":"Saumer",
    "gn:country_code":"DE",
    "gn:dem":284,
    "gn:feature_class":"P",
    "gn:feature_code":"PPL",
    "gn:name":"Saumer",
    "gn:population":0,
    "gn:timezone":"Europe/Berlin",
    "iso:country":"DE",
    "wof:name":"Saumer",
    "wof:placetype":"neighbourhood"
},
  "geometry": {"coordinates":[9.2977,51.84055],"type":"Point"}
}