{
  "type": "Feature",
  "properties": {
    "gn:admin1_code":"1",
    "gn:admin2_code":"84.0",
    "gn:admin3_code":"8426.0",
    "gn:admin4_code":"8426100.0",
    "gn:asciiname":"Schontal",
    "gn:country_code":"DE",
    "gn:dem":666,
    "gn:feature_class":"P",
    "gn:feature_code":"PPL",
    "gn:name":"Sch\u00f6ntal",
    "gn:population":0,
    "gn:timezone":"Europe/Berlin",
    "iso:country":"DE",
    "name:deu_x_preferred":[
        "Sch\u00f6ntal"
    ],
    "wof:name":"Schontal",
    "wof:placetype":"neighbourhood"
},
  "geometry": {"coordinates":[10.01047,47.97789],"type":"Point"}
}