{
  "type": "Feature",
  "properties": {
    "gn:admin1_code":"15",
    "gn:admin2_code":"0.0",
    "gn:admin3_code":"16073.0",
    "gn:admin4_code":"16073111.0",
    "gn:asciiname":"Saaltal",
    "gn:country_code":"DE",
    "gn:dem":322,
    "gn:feature_class":"P",
    "gn:feature_code":"PPL",
    "gn:name":"Saaltal",
    "gn:population":0,
    "gn:timezone":"Europe/Berlin",
    "iso:country":"DE",
    "wof:name":"Saaltal",
    "wof:placetype":"neighbourhood"
},
  "geometry": {"coordinates":[11.50856,50.6224],"type":"Point"}
}