{
  "type": "Feature",
  "properties": {
    "gn:admin1_code":"6.0",
    "gn:admin2_code":"00",
    "gn:admin3_code":"3352.0",
    "gn:admin4_code":"3352032.0",
    "gn:asciiname":"Wiemsdorf",
    "gn:country_code":"DE",
    "gn:dem":1,
    "gn:feature_class":"P",
    "gn:feature_code":"PPL",
    "gn:name":"Wiemsdorf",
    "gn:population":0,
    "gn:timezone":"Europe/Berlin",
    "iso:country":"DE",
    "wof:name":"Wiemsdorf",
    "wof:placetype":"neighbourhood"
},
  "geometry": {"coordinates":[8.52136,53.44564],"type":"Point"}
}