{
  "type": "Feature",
  "properties": {
    "gn:admin1_code":"11",
    "gn:admin2_code":"0.0",
    "gn:admin3_code":"12062.0",
    "gn:admin4_code":"12062500.0",
    "gn:asciiname":"Domsdorf",
    "gn:country_code":"DE",
    "gn:dem":93,
    "gn:feature_class":"P",
    "gn:feature_code":"PPL",
    "gn:name":"Domsdorf",
    "gn:population":0,
    "gn:timezone":"Europe/Berlin",
    "iso:country":"DE",
    "name:und_x_variant":[
        "Domsdort",
        "Domsdorf"
    ],
    "wof:name":"Domsdorf",
    "wof:placetype":"neighbourhood"
},
  "geometry": {"coordinates":[13.40954,51.57429000000001],"type":"Point"}
}