{
  "type": "Feature",
  "properties": {
    "gn:admin1_code":"6",
    "gn:admin2_code":"0.0",
    "gn:admin3_code":"3158.0",
    "gn:admin4_code":"3158008.0",
    "gn:asciiname":"Klein Denkte",
    "gn:country_code":"DE",
    "gn:dem":83,
    "gn:feature_class":"P",
    "gn:feature_code":"PPL",
    "gn:name":"Klein Denkte",
    "gn:population":0,
    "gn:timezone":"Europe/Berlin",
    "iso:country":"DE",
    "wof:name":"Klein Denkte",
    "wof:placetype":"neighbourhood"
},
  "geometry": {"coordinates":[10.58584,52.14234],"type":"Point"}
}