{
  "type": "Feature",
  "properties": {
    "gn:admin1_code":"2.0",
    "gn:admin2_code":"92.0",
    "gn:admin3_code":"9275.0",
    "gn:admin4_code":"9275119.0",
    "gn:asciiname":"Barnreuth",
    "gn:cc2":"DE",
    "gn:country_code":"DE",
    "gn:dem":547,
    "gn:feature_class":"P",
    "gn:feature_code":"PPL",
    "gn:name":"B\u00e4rnreuth",
    "gn:population":0,
    "gn:timezone":"Europe/Berlin",
    "iso:country":"DE",
    "name:und_x_variant":[
        "B\u00e4rnreut",
        "B\u00e4rnreuth"
    ],
    "wof:name":"Barnreuth",
    "wof:placetype":"neighbourhood"
},
  "geometry": {"coordinates":[13.5676,48.69141],"type":"Point"}
}