{
  "type": "Feature",
  "properties": {
    "gn:country":"DE",
    "gn:fcode":"PPLA4",
    "gn:population":108,
    "iso:country":"DE",
    "name:bak_x_preferred":[
        "\u0411\u0440\u0430\u043d\u0434\u0445\u043e\u0440\u0441\u0442"
    ],
    "name:che_x_preferred":[
        "\u0411\u0440\u0430\u043d\u0434\u0445\u043e\u0440\u0441\u0442"
    ],
    "name:deu_x_preferred":[
        "Brandhorst"
    ],
    "name:eng_x_preferred":[
        "Brandhorst"
    ],
    "name:epo_x_preferred":[
        "Brandhorst"
    ],
    "name:fas_x_preferred":[
        "\u0628\u0631\u0627\u0646\u062f\u0647\u0648\u0631\u0633\u062a"
    ],
    "name:fra_x_preferred":[
        "Brandhorst"
    ],
    "name:ita_x_preferred":[
        "Brandhorst"
    ],
    "name:kaz_x_preferred":[
        "\u0411\u0440\u0430\u043d\u0434\u0445\u043e\u0440\u0441\u0442"
    ],
    "name:kir_x_preferred":[
        "\u0411\u0440\u0430\u043d\u0434\u0445\u043e\u0440\u0441\u0442"
    ],
    "name:mkd_x_preferred":[
        "\u0411\u0440\u0430\u043d\u0434\u0445\u043e\u0440\u0441\u0442"
    ],
    "name:nld_x_preferred":[
        "Brandhorst"
    ],
    "name:por_x_preferred":[
        "Brandhorst"
    ],
    "name:ron_x_preferred":[
        "Brandhorst"
    ],
    "name:rus_x_preferred":[
        "\u0411\u0440\u0430\u043d\u0434\u0445\u043e\u0440\u0441\u0442"
    ],
    "name:srp_x_preferred":[
        "\u0411\u0440\u0430\u043d\u0434\u0445\u043e\u0440\u0441\u0442"
    ],
    "name:swe_x_preferred":[
        "Brandhorst"
    ],
    "name:tat_x_preferred":[
        "\u0411\u0440\u0430\u043d\u0434\u0445\u043e\u0440\u0441\u0442"
    ],
    "name:uzb_x_preferred":[
        "Brandhorst"
    ],
    "name:vie_x_preferred":[
        "Brandhorst"
    ],
    "name:vol_x_preferred":[
        "Brandhorst"
    ],
    "name:war_x_preferred":[
        "Brandhorst"
    ],
    "qs_pg:aaroncc":"DE",
    "qs_pg:gn_country":"DE",
    "qs_pg:gn_fcode":"PPLA4",
    "qs_pg:gn_pop":108,
    "qs_pg:name":"Brandhorst",
    "qs_pg:photos_9r":0,
    "qs_pg:photos_sr":0,
    "qs_pg:pop_sr":1,
    "qs_pg:qs_pg_placetype":"locality",
    "wof:name":"Brandhorst",
    "wof:placetype":"neighbourhood",
    "wof:population":108
},
  "geometry": {"coordinates":[12.41667,51.81667],"type":"Point"}
}