{
  "type": "Feature",
  "properties": {
    "gn:admin1_code":"11.0",
    "gn:admin2_code":"00",
    "gn:admin3_code":"12062.0",
    "gn:admin4_code":"12062461.0",
    "gn:asciiname":"Wiepersdorf",
    "gn:country_code":"DE",
    "gn:dem":86,
    "gn:feature_class":"P",
    "gn:feature_code":"PPL",
    "gn:name":"Wiepersdorf",
    "gn:population":0,
    "gn:timezone":"Europe/Berlin",
    "iso:country":"DE",
    "wof:name":"Wiepersdorf",
    "wof:placetype":"neighbourhood"
},
  "geometry": {"coordinates":[13.30423,51.80692],"type":"Point"}
}