{
  "type": "Feature",
  "properties": {
    "gn:admin1_code":"2.0",
    "gn:admin2_code":"92.0",
    "gn:admin3_code":"9275.0",
    "gn:admin4_code":"9275116.0",
    "gn:asciiname":"Angering",
    "gn:country_code":"DE",
    "gn:dem":322,
    "gn:feature_class":"P",
    "gn:feature_code":"PPL",
    "gn:name":"Angering",
    "gn:population":0,
    "gn:timezone":"Europe/Berlin",
    "iso:country":"DE",
    "wof:name":"Angering",
    "wof:placetype":"neighbourhood"
},
  "geometry": {"coordinates":[13.31037,48.3656],"type":"Point"}
}