{
  "type": "Feature",
  "properties": {
    "gn:country":"DE",
    "gn:fcode":"PPL",
    "gn:population":0,
    "iso:country":"DE",
    "name:ara_x_preferred":[
        "\u0631\u064a\u062f\u0646\u0628\u0648\u0631\u063a"
    ],
    "name:azb_x_preferred":[
        "\u0631\u06cc\u062f\u0646\u0628\u0648\u0631\u0642"
    ],
    "name:bar_x_preferred":[
        "Rianbuach"
    ],
    "name:bul_x_preferred":[
        "\u0420\u0438\u0434\u0435\u043d\u0431\u0443\u0440\u0433"
    ],
    "name:ceb_x_preferred":[
        "Riedenburg"
    ],
    "name:dan_x_preferred":[
        "Riedenburg"
    ],
    "name:deu_x_preferred":[
        "Riedenburg"
    ],
    "name:epo_x_preferred":[
        "Riedenburg"
    ],
    "name:fas_x_preferred":[
        "\u0631\u06cc\u062f\u0646\u0628\u0648\u0631\u06af"
    ],
    "name:fra_x_preferred":[
        "Riedenburg"
    ],
    "name:hun_x_preferred":[
        "Riedenburg"
    ],
    "name:hye_x_preferred":[
        "\u054c\u056b\u0564\u0565\u0576\u0562\u0578\u0582\u0580\u0563"
    ],
    "name:ind_x_preferred":[
        "Riedenburg"
    ],
    "name:ita_x_preferred":[
        "Riedenburg"
    ],
    "name:jpn_x_preferred":[
        "\u30ea\u30fc\u30c7\u30f3\u30d6\u30eb\u30af"
    ],
    "name:kaz_x_preferred":[
        "\u0420\u0438\u0434\u0435\u043d\u0431\u0443\u0440\u0433"
    ],
    "name:kir_x_preferred":[
        "\u0420\u0438\u0434\u0435\u043d\u0431\u0443\u0440\u0433"
    ],
    "name:lmo_x_preferred":[
        "Riedenburg"
    ],
    "name:msa_x_preferred":[
        "Riedenburg"
    ],
    "name:nld_x_preferred":[
        "Riedenburg"
    ],
    "name:pol_x_preferred":[
        "Riedenburg"
    ],
    "name:por_x_preferred":[
        "Riedenburg"
    ],
    "name:ron_x_preferred":[
        "Riedenburg"
    ],
    "name:rus_x_preferred":[
        "\u0420\u0438\u0434\u0435\u043d\u0431\u0443\u0440\u0433"
    ],
    "name:spa_x_preferred":[
        "Riedenburg"
    ],
    "name:srp_x_preferred":[
        "\u0420\u0438\u0434\u0435\u043d\u0431\u0443\u0440\u0433"
    ],
    "name:swe_x_preferred":[
        "Riedenburg"
    ],
    "name:tur_x_preferred":[
        "Riedenburg"
    ],
    "name:ukr_x_preferred":[
        "\u0420\u0456\u0434\u0435\u043d\u0431\u0443\u0440\u0433"
    ],
    "name:uzb_x_preferred":[
        "Riedenburg"
    ],
    "name:vie_x_preferred":[
        "Riedenburg"
    ],
    "name:vol_x_preferred":[
        "Riedenburg"
    ],
    "name:war_x_preferred":[
        "Riedenburg"
    ],
    "name:zho_x_preferred":[
        "\u91cc\u767b\u5821"
    ],
    "qs_pg:aaroncc":"DE",
    "qs_pg:gn_country":"DE",
    "qs_pg:gn_fcode":"PPL",
    "qs_pg:gn_pop":0,
    "qs_pg:name":"Riedenburg",
    "qs_pg:name_adm0":"\u00d6sterreich",
    "qs_pg:name_adm1":"Salzburg",
    "qs_pg:photos":2361,
    "qs_pg:photos_1k":478,
    "qs_pg:photos_9k":10,
    "qs_pg:photos_9r":10,
    "qs_pg:photos_all":2361,
    "qs_pg:photos_sr":17,
    "qs_pg:pop_sr":0,
    "qs_pg:qs_pg_placetype":"neighbourhood",
    "qs_pg:qs_pg_placetype_gp":"Suburb",
    "qs_pg:woe_adm0":23424750,
    "woe:adm0_id":23424750,
    "woe:name_adm0":"\u00d6sterreich",
    "woe:name_adm1":"Salzburg",
    "woe:placetype":"Suburb",
    "wof:name":"Riedenburg",
    "wof:placetype":"neighbourhood"
},
  "geometry": {"coordinates":[13.32307,48.34461],"type":"Point"}
}