{
  "type": "Feature",
  "properties": {
    "gn:gn_country":"DE",
    "gn:gn_fcode":"PPL",
    "gn:gn_pop":0,
    "iso:country":"DE",
    "qs_pg:aaroncc":"DE",
    "qs_pg:gn_country":"DE",
    "qs_pg:gn_fcode":"PPL",
    "qs_pg:gn_pop":0,
    "qs_pg:name":"Riedenburg",
    "qs_pg:name_adm0":"\u00d6sterreich",
    "qs_pg:name_adm1":"Salzburg",
    "qs_pg:photos":2361,
    "qs_pg:photos_1k":478,
    "qs_pg:photos_9k":10,
    "qs_pg:photos_9r":10,
    "qs_pg:photos_all":2361,
    "qs_pg:photos_sr":17,
    "qs_pg:pop_sr":0,
    "qs_pg:qs_pg_placetype":"neighbourhood",
    "qs_pg:qs_pg_placetype_gp":"Suburb",
    "qs_pg:woe_adm0":23424750,
    "woe:adm0_id":23424750,
    "woe:name_adm0":"\u00d6sterreich",
    "woe:name_adm1":"Salzburg",
    "woe:placetype":"Suburb",
    "wof:name":"Riedenburg",
    "wof:placetype":"neighbourhood"
},
  "geometry": {"coordinates":[13.32307,48.34461],"type":"Point"}
}