{
  "type": "Feature",
  "properties": {
    "iso:country":"DE",
    "name:als_x_preferred":[
        "Linn"
    ],
    "name:bul_x_preferred":[
        "\u041b\u0438\u043d"
    ],
    "name:ceb_x_preferred":[
        "Linn"
    ],
    "name:deu_x_preferred":[
        "Linn"
    ],
    "name:epo_x_preferred":[
        "Linn"
    ],
    "name:fra_x_preferred":[
        "Linn"
    ],
    "name:gla_x_preferred":[
        "Linn"
    ],
    "name:ita_x_preferred":[
        "Linn"
    ],
    "name:nld_x_preferred":[
        "Linn"
    ],
    "name:nno_x_preferred":[
        "Linn"
    ],
    "name:pol_x_preferred":[
        "Linn"
    ],
    "name:por_x_preferred":[
        "Linn"
    ],
    "name:rus_x_preferred":[
        "\u041b\u0438\u043d"
    ],
    "name:srp_x_preferred":[
        "\u041b\u0438\u043d"
    ],
    "name:swe_x_preferred":[
        "Linn"
    ],
    "name:tur_x_preferred":[
        "Linn"
    ],
    "name:vol_x_preferred":[
        "Linn"
    ],
    "name:zho_x_preferred":[
        "Linn"
    ],
    "wof:name":"Linn",
    "wof:placetype":"neighbourhood"
},
  "geometry": {"coordinates":[6.64408782296335,51.33667875403842],"type":"Point"}
}