{
  "type": "Feature",
  "properties": {
    "gn:admin1_code":"1.0",
    "gn:admin2_code":"083",
    "gn:admin3_code":"8317.0",
    "gn:admin4_code":"8317127.0",
    "gn:asciiname":"Wolfersbach",
    "gn:country_code":"DE",
    "gn:dem":316,
    "gn:feature_class":"P",
    "gn:feature_code":"PPLL",
    "gn:name":"Wolfersbach",
    "gn:population":0,
    "gn:timezone":"Europe/Berlin",
    "iso:country":"DE",
    "wof:name":"Wolfersbach",
    "wof:placetype":"neighbourhood"
},
  "geometry": {"coordinates":[7.93589,48.28376],"type":"Point"}
}