{
  "type": "Feature",
  "properties": {
    "gn:admin1_code":"2",
    "gn:admin2_code":"91.0",
    "gn:admin3_code":"9187.0",
    "gn:admin4_code":"9187174.0",
    "gn:asciiname":"Oberthal",
    "gn:country_code":"DE",
    "gn:dem":468,
    "gn:feature_class":"P",
    "gn:feature_code":"PPL",
    "gn:name":"Oberthal",
    "gn:population":0,
    "gn:timezone":"Europe/Berlin",
    "iso:country":"DE",
    "name:als_x_preferred":[
        "Oberthal"
    ],
    "name:cat_x_preferred":[
        "Oberthal"
    ],
    "name:ceb_x_preferred":[
        "Oberthal"
    ],
    "name:deu_x_preferred":[
        "Oberthal"
    ],
    "name:epo_x_preferred":[
        "Oberthal"
    ],
    "name:eus_x_preferred":[
        "Oberthal"
    ],
    "name:fra_x_preferred":[
        "Oberthal"
    ],
    "name:ita_x_preferred":[
        "Oberthal"
    ],
    "name:nld_x_preferred":[
        "Oberthal"
    ],
    "name:pol_x_preferred":[
        "Oberthal"
    ],
    "name:rus_x_preferred":[
        "\u041e\u0431\u0435\u0440\u0442\u0430\u043b\u044c"
    ],
    "name:swe_x_preferred":[
        "Oberthal"
    ],
    "name:vol_x_preferred":[
        "Oberthal"
    ],
    "wof:name":"Oberthal",
    "wof:placetype":"neighbourhood"
},
  "geometry": {"coordinates":[12.21929,47.94811],"type":"Point"}
}