{
  "type": "Feature",
  "properties": {
    "gn:admin1_code":"2",
    "gn:admin2_code":"93.0",
    "gn:admin3_code":"9373.0",
    "gn:admin4_code":"9373112.0",
    "gn:asciiname":"Sollngriesbach",
    "gn:country_code":"DE",
    "gn:dem":400,
    "gn:feature_class":"P",
    "gn:feature_code":"PPL",
    "gn:name":"Sollngriesbach",
    "gn:population":0,
    "gn:timezone":"Europe/Berlin",
    "iso:country":"DE",
    "wof:name":"Sollngriesbach",
    "wof:placetype":"neighbourhood"
},
  "geometry": {"coordinates":[11.43368,49.12051],"type":"Point"}
}