{
  "type": "Feature",
  "properties": {
    "gn:admin1_code":"6",
    "gn:admin2_code":"0.0",
    "gn:admin3_code":"3360.0",
    "gn:admin4_code":"3360014.0",
    "gn:asciiname":"Oldendorf II",
    "gn:cc2":"DE",
    "gn:country_code":"DE",
    "gn:dem":59,
    "gn:feature_class":"P",
    "gn:feature_code":"PPL",
    "gn:name":"Oldendorf II",
    "gn:population":0,
    "gn:timezone":"Europe/Berlin",
    "iso:country":"DE",
    "name:und_x_variant":[
        "Oldendorf Zwei"
    ],
    "wof:name":"Oldendorf II",
    "wof:placetype":"neighbourhood"
},
  "geometry": {"coordinates":[10.44559,53.08469],"type":"Point"}
}