{
  "type": "Feature",
  "properties": {
    "gn:admin1_code":"2",
    "gn:admin2_code":"91.0",
    "gn:admin3_code":"9182.0",
    "gn:admin4_code":"9182125.0",
    "gn:asciiname":"Unterhoger",
    "gn:country_code":"DE",
    "gn:dem":780,
    "gn:feature_class":"P",
    "gn:feature_code":"PPL",
    "gn:name":"Unterh\u00f6ger",
    "gn:population":0,
    "gn:timezone":"Europe/Berlin",
    "iso:country":"DE",
    "wof:name":"Unterhoger",
    "wof:placetype":"neighbourhood"
},
  "geometry": {"coordinates":[11.7997,47.78023],"type":"Point"}
}