{
  "type": "Feature",
  "properties": {
    "gn:admin1_code":"13",
    "gn:admin2_code":"0.0",
    "gn:admin3_code":"14521.0",
    "gn:admin4_code":"14521170.0",
    "gn:asciiname":"Neidhardtsthal",
    "gn:country_code":"DE",
    "gn:dem":500,
    "gn:feature_class":"P",
    "gn:feature_code":"PPL",
    "gn:name":"Neidhardtsthal",
    "gn:population":0,
    "gn:timezone":"Europe/Berlin",
    "iso:country":"DE",
    "name:und_x_variant":[
        "Blauenthal-Neidhardtsthal",
        "Neidhardtsthal"
    ],
    "wof:name":"Neidhardtsthal",
    "wof:placetype":"neighbourhood"
},
  "geometry": {"coordinates":[12.6055,50.53045],"type":"Point"}
}