{
  "type": "Feature",
  "properties": {
    "gn:admin1_code":"2",
    "gn:admin2_code":"97.0",
    "gn:admin3_code":"9777.0",
    "gn:admin4_code":"9777141.0",
    "gn:asciiname":"Frankenhofen",
    "gn:country_code":"DE",
    "gn:dem":720,
    "gn:feature_class":"P",
    "gn:feature_code":"PPL",
    "gn:name":"Frankenhofen",
    "gn:population":0,
    "gn:timezone":"Europe/Berlin",
    "iso:country":"DE",
    "wof:name":"Frankenhofen",
    "wof:placetype":"neighbourhood"
},
  "geometry": {"coordinates":[10.75162,47.8875],"type":"Point"}
}