{
  "type": "Feature",
  "properties": {
    "gn:gn_country":"DE",
    "gn:gn_fcode":"PPLA4",
    "gn:gn_pop":248,
    "gn:population":248,
    "iso:country":"DE",
    "name:bak_x_preferred":[
        "\u041d\u043e\u0439\u0437\u0438\u0441"
    ],
    "name:kaz_x_preferred":[
        "\u041d\u043e\u0439\u0437\u0438\u0441"
    ],
    "name:mkd_x_preferred":[
        "\u041d\u043e\u0458\u0437\u0438\u0441"
    ],
    "name:rus_x_preferred":[
        "\u041d\u043e\u0439\u0437\u0438\u0441"
    ],
    "name:srp_x_preferred":[
        "\u041d\u043e\u0458\u0437\u0438\u0441"
    ],
    "name:zho_x_preferred":[
        "\u8bfa\u4f0a\u897f\u65af"
    ],
    "qs_pg:aaroncc":"DE",
    "qs_pg:gn_country":"DE",
    "qs_pg:gn_fcode":"PPLA4",
    "qs_pg:gn_pop":248,
    "qs_pg:name":"Neusi\u00df",
    "qs_pg:photos_9r":0,
    "qs_pg:photos_sr":0,
    "qs_pg:pop_sr":2,
    "qs_pg:qs_pg_placetype":"locality",
    "wof:name":"Neusi\u00df",
    "wof:placetype":"locality",
    "wof:population":248
},
  "geometry": {"coordinates":[10.88333,50.75],"type":"Point"}
}