{
  "type": "Feature",
  "properties": {
    "gn:admin1_code":"2",
    "gn:admin2_code":"92.0",
    "gn:admin3_code":"9278.0",
    "gn:admin4_code":"9278129.0",
    "gn:asciiname":"Ehren",
    "gn:country_code":"DE",
    "gn:dem":618,
    "gn:feature_class":"P",
    "gn:feature_code":"PPL",
    "gn:name":"Ehren",
    "gn:population":0,
    "gn:timezone":"Europe/Berlin",
    "iso:country":"DE",
    "name:deu_x_preferred":[
        "Ehren"
    ],
    "name:fra_x_preferred":[
        "Ehren"
    ],
    "name:und_x_variant":[
        "Ehrn"
    ],
    "wof:name":"Ehren",
    "wof:placetype":"neighbourhood"
},
  "geometry": {"coordinates":[12.75056,49.018],"type":"Point"}
}