{
  "type": "Feature",
  "properties": {
    "gn:admin1_code":"14",
    "gn:admin2_code":"0.0",
    "gn:admin3_code":"15083.0",
    "gn:admin4_code":"15083270.0",
    "gn:asciiname":"Planken",
    "gn:country_code":"DE",
    "gn:dem":73,
    "gn:feature_class":"P",
    "gn:feature_code":"PPL",
    "gn:name":"Planken",
    "gn:population":0,
    "gn:timezone":"Europe/Berlin",
    "iso:country":"DE",
    "name:als_x_preferred":[
        "Planken"
    ],
    "name:arg_x_preferred":[
        "Planken"
    ],
    "name:bel_x_preferred":[
        "\u041f\u043b\u0430\u043d\u043a\u0435\u043d"
    ],
    "name:ben_x_preferred":[
        "\u09aa\u09cd\u09b2\u09cd\u09af\u09be\u0999\u09cd\u0995\u09c7\u09a8"
    ],
    "name:cat_x_preferred":[
        "Planken"
    ],
    "name:ceb_x_preferred":[
        "Planken"
    ],
    "name:ces_x_preferred":[
        "Planken"
    ],
    "name:dan_x_preferred":[
        "Planken"
    ],
    "name:deu_x_preferred":[
        "Planken"
    ],
    "name:ell_x_preferred":[
        "\u03a0\u03bb\u03ac\u03bd\u03ba\u03b5\u03bd"
    ],
    "name:epo_x_preferred":[
        "Planken"
    ],
    "name:eus_x_preferred":[
        "Planken"
    ],
    "name:fas_x_preferred":[
        "\u067e\u0644\u0627\u0646\u06a9\u0646"
    ],
    "name:fin_x_preferred":[
        "Planken"
    ],
    "name:fra_x_preferred":[
        "Planken"
    ],
    "name:glg_x_preferred":[
        "Planken"
    ],
    "name:heb_x_preferred":[
        "\u05e4\u05dc\u05e0\u05e7\u05df"
    ],
    "name:hin_x_preferred":[
        "\u092a\u094d\u0932\u0902\u0915\u0947\u0928"
    ],
    "name:ind_x_preferred":[
        "Planken"
    ],
    "name:ita_x_preferred":[
        "Planken"
    ],
    "name:jpn_x_preferred":[
        "\u30d7\u30e9\u30f3\u30b1\u30f3"
    ],
    "name:kor_x_preferred":[
        "\ud50c\ub791\ucf04"
    ],
    "name:lat_x_preferred":[
        "Planken"
    ],
    "name:lit_x_preferred":[
        "Plankenas"
    ],
    "name:lmo_x_preferred":[
        "Planken"
    ],
    "name:mkd_x_preferred":[
        "\u041f\u043b\u0430\u043d\u043a\u0435\u043d"
    ],
    "name:nld_x_preferred":[
        "Planken"
    ],
    "name:nno_x_preferred":[
        "Planken"
    ],
    "name:nor_x_preferred":[
        "Planken"
    ],
    "name:oci_x_preferred":[
        "Planken"
    ],
    "name:pnb_x_preferred":[
        "\u067e\u0644\u0627\u0646\u06a9\u0646"
    ],
    "name:pol_x_preferred":[
        "Planken"
    ],
    "name:por_x_preferred":[
        "Planken"
    ],
    "name:roh_x_preferred":[
        "Planken"
    ],
    "name:rus_x_preferred":[
        "\u041f\u043b\u0430\u043d\u043a\u0435\u043d"
    ],
    "name:scn_x_preferred":[
        "Planka"
    ],
    "name:sco_x_preferred":[
        "Planken"
    ],
    "name:slk_x_preferred":[
        "Planken"
    ],
    "name:swe_x_preferred":[
        "Planken"
    ],
    "name:tha_x_preferred":[
        "\u0e1e\u0e25\u0e31\u0e07\u0e40\u0e04\u0e34\u0e19"
    ],
    "name:tur_x_preferred":[
        "Planken"
    ],
    "name:ukr_x_preferred":[
        "\u041f\u043b\u0430\u043d\u043a\u0435\u043d"
    ],
    "name:urd_x_preferred":[
        "\u067e\u0644\u0646\u06a9\u06cc\u0646"
    ],
    "name:vie_x_preferred":[
        "Planken"
    ],
    "name:vol_x_preferred":[
        "Planken"
    ],
    "name:zho_x_preferred":[
        "\u666e\u5170\u80af"
    ],
    "wof:name":"Planken",
    "wof:placetype":"neighbourhood"
},
  "geometry": {"coordinates":[11.48562,52.3471],"type":"Point"}
}