{
  "type": "Feature",
  "properties": {
    "gn:admin1_code":"1",
    "gn:admin2_code":"81.0",
    "gn:admin3_code":"8127.0",
    "gn:admin4_code":"8127079.0",
    "gn:asciiname":"Heerberg",
    "gn:country_code":"DE",
    "gn:dem":393,
    "gn:feature_class":"P",
    "gn:feature_code":"PPL",
    "gn:name":"Heerberg",
    "gn:population":0,
    "gn:timezone":"Europe/Berlin",
    "iso:country":"DE",
    "wof:name":"Heerberg",
    "wof:placetype":"neighbourhood"
},
  "geometry": {"coordinates":[9.85499,48.94891],"type":"Point"}
}