{
  "type": "Feature",
  "properties": {
    "gn:admin1_code":"15.0",
    "gn:admin2_code":"0.0",
    "gn:admin3_code":"16077.0",
    "gn:admin4_code":"16077009.0",
    "gn:asciiname":"Zschoepperitz",
    "gn:country_code":"DE",
    "gn:dem":239,
    "gn:feature_class":"P",
    "gn:feature_code":"PPL",
    "gn:name":"Zsch\u00f6pperitz",
    "gn:population":0,
    "gn:timezone":"Europe/Berlin",
    "iso:country":"DE",
    "wof:name":"Zschoepperitz",
    "wof:placetype":"neighbourhood"
},
  "geometry": {"coordinates":[12.30638,50.95034],"type":"Point"}
}