{
  "type": "Feature",
  "properties": {
    "gn:admin1_code":"14",
    "gn:admin2_code":"0.0",
    "gn:admin3_code":"15090.0",
    "gn:admin4_code":"15090635.0",
    "gn:asciiname":"Haverland",
    "gn:country_code":"DE",
    "gn:dem":20,
    "gn:feature_class":"P",
    "gn:feature_code":"PPL",
    "gn:name":"Haverland",
    "gn:population":0,
    "gn:timezone":"Europe/Berlin",
    "iso:country":"DE",
    "wof:name":"Haverland",
    "wof:placetype":"neighbourhood"
},
  "geometry": {"coordinates":[11.60544,52.92523000000001],"type":"Point"}
}