{
  "type": "Feature",
  "properties": {
    "gn:admin1_code":"9",
    "gn:admin2_code":"0.0",
    "gn:admin3_code":"10043.0",
    "gn:admin4_code":"10043115.0",
    "gn:asciiname":"Steinbach",
    "gn:country_code":"DE",
    "gn:dem":349,
    "gn:feature_class":"P",
    "gn:feature_code":"PPL",
    "gn:name":"Steinbach",
    "gn:population":0,
    "gn:timezone":"Europe/Berlin",
    "iso:country":"DE",
    "wof:name":"Steinbach",
    "wof:placetype":"neighbourhood"
},
  "geometry": {"coordinates":[7.21038,49.40701],"type":"Point"}
}