{
  "type": "Feature",
  "properties": {
    "gn:admin1_code":"10",
    "gn:admin2_code":"0.0",
    "gn:admin3_code":"1059.0",
    "gn:admin4_code":"1059182.0",
    "gn:asciiname":"Kleinwolstrup",
    "gn:country_code":"DE",
    "gn:dem":56,
    "gn:feature_class":"P",
    "gn:feature_code":"PPL",
    "gn:name":"Kleinwolstrup",
    "gn:population":0,
    "gn:timezone":"Europe/Berlin",
    "iso:country":"DE",
    "wof:name":"Kleinwolstrup",
    "wof:placetype":"neighbourhood"
},
  "geometry": {"coordinates":[9.49151,54.73506999999999],"type":"Point"}
}