{
  "type": "Feature",
  "properties": {
    "gn:admin1_code":"6",
    "gn:admin2_code":"0.0",
    "gn:admin3_code":"3452.0",
    "gn:admin4_code":"3452019.0",
    "gn:asciiname":"Utlandshoern",
    "gn:country_code":"DE",
    "gn:dem":0,
    "gn:feature_class":"P",
    "gn:feature_code":"PPL",
    "gn:name":"Utlandsh\u00f6rn",
    "gn:population":0,
    "gn:timezone":"Europe/Berlin",
    "iso:country":"DE",
    "wof:name":"Utlandshoern",
    "wof:placetype":"neighbourhood"
},
  "geometry": {"coordinates":[7.10695,53.56412],"type":"Point"}
}