{
  "type": "Feature",
  "properties": {
    "gn:admin1_code":"2",
    "gn:admin2_code":"91.0",
    "gn:admin3_code":"9171.0",
    "gn:admin4_code":"9171135.0",
    "gn:asciiname":"Hirten",
    "gn:country_code":"DE",
    "gn:dem":421,
    "gn:feature_class":"P",
    "gn:feature_code":"PPL",
    "gn:name":"Hirten",
    "gn:population":0,
    "gn:timezone":"Europe/Berlin",
    "iso:country":"DE",
    "name:ceb_x_preferred":[
        "Hirten"
    ],
    "name:deu_x_preferred":[
        "Hirten"
    ],
    "name:epo_x_preferred":[
        "Hirten"
    ],
    "name:eus_x_preferred":[
        "Hirten"
    ],
    "name:fas_x_preferred":[
        "\u0647\u06cc\u0631\u062a\u0646"
    ],
    "name:fra_x_preferred":[
        "Hirten"
    ],
    "name:hun_x_preferred":[
        "Hirten"
    ],
    "name:ita_x_preferred":[
        "Hirten"
    ],
    "name:kaz_x_preferred":[
        "\u0425\u0438\u0440\u0442\u0435\u043d"
    ],
    "name:kir_x_preferred":[
        "\u0425\u0438\u0440\u0442\u0435\u043d"
    ],
    "name:msa_x_preferred":[
        "Hirten"
    ],
    "name:nld_x_preferred":[
        "Hirten"
    ],
    "name:pol_x_preferred":[
        "Hirten"
    ],
    "name:por_x_preferred":[
        "Hirten"
    ],
    "name:ron_x_preferred":[
        "Hirten"
    ],
    "name:rus_x_preferred":[
        "\u0425\u0438\u0440\u0442\u0435\u043d"
    ],
    "name:srp_x_preferred":[
        "\u0425\u0438\u0440\u0442\u0435\u043d"
    ],
    "name:ukr_x_preferred":[
        "\u0413\u0456\u0440\u0442\u0435\u043d"
    ],
    "name:uzb_x_preferred":[
        "Hirten"
    ],
    "name:vie_x_preferred":[
        "Hirten"
    ],
    "name:vol_x_preferred":[
        "Hirten"
    ],
    "name:war_x_preferred":[
        "Hirten"
    ],
    "name:zho_x_preferred":[
        "\u5e0c\u5c14\u6ed5"
    ],
    "wof:name":"Hirten",
    "wof:placetype":"neighbourhood"
},
  "geometry": {"coordinates":[12.66072,48.14911],"type":"Point"}
}