{
  "type": "Feature",
  "properties": {
    "gn:admin1_code":"2",
    "gn:admin2_code":"91.0",
    "gn:admin3_code":"9171.0",
    "gn:admin4_code":"9171135.0",
    "gn:asciiname":"Hirten",
    "gn:country_code":"DE",
    "gn:dem":421,
    "gn:feature_class":"P",
    "gn:feature_code":"PPL",
    "gn:name":"Hirten",
    "gn:population":0,
    "gn:timezone":"Europe/Berlin",
    "iso:country":"DE",
    "wof:name":"Hirten",
    "wof:placetype":"neighbourhood"
},
  "geometry": {"coordinates":[12.66072,48.14911],"type":"Point"}
}