{
  "type": "Feature",
  "properties": {
    "gn:admin1_code":"2.0",
    "gn:admin2_code":"095",
    "gn:admin3_code":"9577.0",
    "gn:admin4_code":"9577173.0",
    "gn:asciiname":"Wieshof",
    "gn:country_code":"DE",
    "gn:dem":558,
    "gn:feature_class":"P",
    "gn:feature_code":"PPL",
    "gn:name":"Wieshof",
    "gn:population":0,
    "gn:timezone":"Europe/Berlin",
    "iso:country":"DE",
    "wof:name":"Wieshof",
    "wof:placetype":"neighbourhood"
},
  "geometry": {"coordinates":[10.79556,48.95028],"type":"Point"}
}