{
  "type": "Feature",
  "properties": {
    "gn:country":"DE",
    "gn:fcode":"PPL",
    "gn:population":0,
    "iso:country":"DE",
    "name:deu_x_preferred":[
        "Neufinsing"
    ],
    "name:deu_x_variant":[
        "Neukissing"
    ],
    "name:eng_x_preferred":[
        "Neufinsing"
    ],
    "name:eng_x_variant":[
        "Neukissing"
    ],
    "name:fra_x_preferred":[
        "Neufinsing"
    ],
    "name:gle_x_preferred":[
        "Neufinsing"
    ],
    "name:nld_x_preferred":[
        "Neufinsing"
    ],
    "qs_pg:aaroncc":"DE",
    "qs_pg:gn_country":"DE",
    "qs_pg:gn_fcode":"PPL",
    "qs_pg:gn_pop":0,
    "qs_pg:name":"Neukissing",
    "qs_pg:name_adm0":"Deutschland",
    "qs_pg:name_adm1":"Bayern",
    "qs_pg:photos_9k":1,
    "qs_pg:photos_9r":1,
    "qs_pg:photos_all":2,
    "qs_pg:photos_sr":0,
    "qs_pg:pop_sr":0,
    "qs_pg:qs_pg_placetype":"locality",
    "qs_pg:qs_pg_placetype_gp":"Town",
    "qs_pg:woe_adm0":23424829,
    "woe:adm0_id":23424829,
    "woe:name_adm0":"Deutschland",
    "woe:name_adm1":"Bayern",
    "woe:placetype":"Town",
    "wof:name":"Neufinsing",
    "wof:placetype":"neighbourhood"
},
  "geometry": {"coordinates":[11.80103,48.22084],"type":"Point"}
}