{
  "type": "Feature",
  "properties": {
    "gn:admin1_code":"2.0",
    "gn:admin2_code":"097",
    "gn:admin3_code":"9780.0",
    "gn:admin4_code":"9780119.0",
    "gn:asciiname":"Wirthshalde",
    "gn:country_code":"DE",
    "gn:dem":844,
    "gn:feature_class":"P",
    "gn:feature_code":"PPL",
    "gn:name":"Wirthshalde",
    "gn:population":0,
    "gn:timezone":"Europe/Berlin",
    "iso:country":"DE",
    "wof:name":"Wirthshalde",
    "wof:placetype":"neighbourhood"
},
  "geometry": {"coordinates":[10.32743,47.8325],"type":"Point"}
}