{
  "type": "Feature",
  "properties": {
    "gn:admin1_code":"7",
    "gn:admin2_code":"55.0",
    "gn:admin3_code":"5570.0",
    "gn:admin4_code":"5570048.0",
    "gn:asciiname":"Osthusen",
    "gn:country_code":"DE",
    "gn:dem":76,
    "gn:feature_class":"P",
    "gn:feature_code":"PPLL",
    "gn:name":"Osthusen",
    "gn:population":0,
    "gn:timezone":"Europe/Berlin",
    "iso:country":"DE",
    "wof:name":"Osthusen",
    "wof:placetype":"neighbourhood"
},
  "geometry": {"coordinates":[8.28099,51.71031],"type":"Point"}
}