{
  "type": "Feature",
  "properties": {
    "gn:admin1_code":"12",
    "gn:admin2_code":"0.0",
    "gn:admin3_code":"13073.0",
    "gn:admin4_code":"13073099.0",
    "gn:asciiname":"Teschenhagen",
    "gn:country_code":"DE",
    "gn:dem":15,
    "gn:feature_class":"P",
    "gn:feature_code":"PPL",
    "gn:name":"Teschenhagen",
    "gn:population":0,
    "gn:timezone":"Europe/Berlin",
    "iso:country":"DE",
    "wof:name":"Teschenhagen",
    "wof:placetype":"neighbourhood"
},
  "geometry": {"coordinates":[13.11768,54.25485],"type":"Point"}
}