{
  "type": "Feature",
  "properties": {
    "gn:admin1_code":"1",
    "gn:admin2_code":"83.0",
    "gn:admin3_code":"8337.0",
    "gn:admin4_code":"8337049.0",
    "gn:asciiname":"Sage",
    "gn:country_code":"DE",
    "gn:dem":856,
    "gn:feature_class":"P",
    "gn:feature_code":"PPL",
    "gn:name":"S\u00e4ge",
    "gn:population":0,
    "gn:timezone":"Europe/Berlin",
    "iso:country":"DE",
    "name:cat_x_preferred":[
        "Sage"
    ],
    "name:deu_x_preferred":[
        "Sage"
    ],
    "name:fin_x_preferred":[
        "Sage"
    ],
    "name:fra_x_preferred":[
        "Sage"
    ],
    "name:ita_x_preferred":[
        "Sage"
    ],
    "name:jpn_x_preferred":[
        "Sage"
    ],
    "name:kor_x_preferred":[
        "\uc138\uc774\uc9c0"
    ],
    "name:nld_x_preferred":[
        "Sage"
    ],
    "name:pol_x_preferred":[
        "Sage"
    ],
    "name:rus_x_preferred":[
        "Sage"
    ],
    "name:spa_x_preferred":[
        "Sage"
    ],
    "wof:name":"Sage",
    "wof:placetype":"neighbourhood"
},
  "geometry": {"coordinates":[7.99089,47.66285],"type":"Point"}
}