{
  "type": "Feature",
  "properties": {
    "gn:admin1_code":"2",
    "gn:admin2_code":"93.0",
    "gn:admin3_code":"9371.0",
    "gn:admin4_code":"9371132.0",
    "gn:asciiname":"Guttenberg",
    "gn:country_code":"DE",
    "gn:dem":510,
    "gn:feature_class":"P",
    "gn:feature_code":"PPL",
    "gn:name":"Guttenberg",
    "gn:population":0,
    "gn:timezone":"Europe/Berlin",
    "iso:country":"DE",
    "name:ceb_x_preferred":[
        "Guttenberg"
    ],
    "name:deu_x_preferred":[
        "Guttenberg"
    ],
    "name:fra_x_preferred":[
        "Guttenberg"
    ],
    "name:ita_x_preferred":[
        "Guttenberg"
    ],
    "name:lit_x_preferred":[
        "Guttenberg"
    ],
    "name:pol_x_preferred":[
        "Guttenberg"
    ],
    "name:por_x_preferred":[
        "Guttenberg"
    ],
    "name:rus_x_preferred":[
        "\u0413\u0443\u0442\u0442\u0435\u043d\u0431\u0435\u0440\u0433"
    ],
    "name:spa_x_preferred":[
        "Guttenberg"
    ],
    "name:srp_x_preferred":[
        "\u0413\u0430\u0442\u0435\u043d\u0431\u0435\u0440\u0433"
    ],
    "name:swe_x_preferred":[
        "Guttenberg"
    ],
    "name:tha_x_preferred":[
        "\u0e01\u0e39\u0e40\u0e17\u0e19\u0e40\u0e1a\u0e34\u0e23\u0e4c\u0e01"
    ],
    "name:ukr_x_preferred":[
        "\u0413\u0430\u0442\u0442\u0435\u043d\u0431\u0435\u0440\u0433"
    ],
    "name:vol_x_preferred":[
        "Guttenberg"
    ],
    "wof:name":"Guttenberg",
    "wof:placetype":"neighbourhood"
},
  "geometry": {"coordinates":[11.72773,49.37187],"type":"Point"}
}