{
  "type": "Feature",
  "properties": {
    "gn:admin1_code":"12.0",
    "gn:admin2_code":"00",
    "gn:admin3_code":"13073.0",
    "gn:admin4_code":"13073010.0",
    "gn:asciiname":"Zirzevitz",
    "gn:country_code":"DE",
    "gn:dem":4,
    "gn:feature_class":"P",
    "gn:feature_code":"PPL",
    "gn:name":"Zirzevitz",
    "gn:population":0,
    "gn:timezone":"Europe/Berlin",
    "iso:country":"DE",
    "wof:name":"Zirzevitz",
    "wof:placetype":"neighbourhood"
},
  "geometry": {"coordinates":[13.48894,54.4167],"type":"Point"}
}