{
  "type": "Feature",
  "properties": {
    "gn:admin1_code":"14",
    "gn:admin2_code":"0.0",
    "gn:admin3_code":"15086.0",
    "gn:admin4_code":"15086035.0",
    "gn:asciiname":"Derbenscheberg",
    "gn:country_code":"DE",
    "gn:dem":63,
    "gn:feature_class":"P",
    "gn:feature_code":"PPL",
    "gn:name":"Derbenscheberg",
    "gn:population":0,
    "gn:timezone":"Europe/Berlin",
    "iso:country":"DE",
    "wof:name":"Derbenscheberg",
    "wof:placetype":"neighbourhood"
},
  "geometry": {"coordinates":[12.00359,52.4242],"type":"Point"}
}