{
  "type": "Feature",
  "properties": {
    "gn:admin1_code":"2",
    "gn:admin2_code":"95.0",
    "gn:admin3_code":"9574.0",
    "gn:admin4_code":"9574138.0",
    "gn:asciiname":"Vogelhof",
    "gn:country_code":"DE",
    "gn:dem":346,
    "gn:feature_class":"P",
    "gn:feature_code":"PPL",
    "gn:name":"Vogelhof",
    "gn:population":0,
    "gn:timezone":"Europe/Berlin",
    "iso:country":"DE",
    "wof:name":"Vogelhof",
    "wof:placetype":"neighbourhood"
},
  "geometry": {"coordinates":[11.25592,49.52944],"type":"Point"}
}