{
  "type": "Feature",
  "properties": {
    "gn:admin1_code":"8",
    "gn:admin2_code":"0.0",
    "gn:admin3_code":"7317.0",
    "gn:admin4_code":"7317000.0",
    "gn:asciiname":"Ruhbank",
    "gn:country_code":"DE",
    "gn:dem":415,
    "gn:feature_class":"P",
    "gn:feature_code":"PPL",
    "gn:name":"Ruhbank",
    "gn:population":0,
    "gn:timezone":"Europe/Berlin",
    "iso:country":"DE",
    "wof:name":"Ruhbank",
    "wof:placetype":"neighbourhood"
},
  "geometry": {"coordinates":[7.63235,49.18311],"type":"Point"}
}