{
  "type": "Feature",
  "properties": {
    "gn:admin1_code":"2.0",
    "gn:admin2_code":"092",
    "gn:admin3_code":"9275.0",
    "gn:admin4_code":"9275153.0",
    "gn:asciiname":"Ziering",
    "gn:country_code":"DE",
    "gn:dem":492,
    "gn:feature_class":"P",
    "gn:feature_code":"PPL",
    "gn:name":"Ziering",
    "gn:population":0,
    "gn:timezone":"Europe/Berlin",
    "iso:country":"DE",
    "wof:name":"Ziering",
    "wof:placetype":"neighbourhood"
},
  "geometry": {"coordinates":[13.65084,48.60579],"type":"Point"}
}