{
  "type": "Feature",
  "properties": {
    "gn:admin1_code":"2",
    "gn:admin2_code":"93.0",
    "gn:admin3_code":"9376.0",
    "gn:admin4_code":"9376116.0",
    "gn:asciiname":"Pingarten",
    "gn:country_code":"DE",
    "gn:dem":469,
    "gn:feature_class":"P",
    "gn:feature_code":"PPL",
    "gn:name":"Pingarten",
    "gn:population":0,
    "gn:timezone":"Europe/Berlin",
    "iso:country":"DE",
    "wof:name":"Pingarten",
    "wof:placetype":"neighbourhood"
},
  "geometry": {"coordinates":[12.32644,49.31869],"type":"Point"}
}