{
  "type": "Feature",
  "properties": {
    "gn:admin1_code":"14",
    "gn:admin2_code":"0.0",
    "gn:admin3_code":"15083.0",
    "gn:admin4_code":"15083130.0",
    "gn:asciiname":"Kesselsohl",
    "gn:cc2":"DE",
    "gn:country_code":"DE",
    "gn:dem":98,
    "gn:feature_class":"P",
    "gn:feature_code":"PPL",
    "gn:name":"Kesselsohl",
    "gn:population":0,
    "gn:timezone":"Europe/Berlin",
    "iso:country":"DE",
    "name:und_x_variant":[
        "F\u00f6rsterei Kesselsohl",
        "Kesselsohl"
    ],
    "wof:name":"Kesselsohl",
    "wof:placetype":"neighbourhood"
},
  "geometry": {"coordinates":[11.61667,52.36667],"type":"Point"}
}