{
  "type": "Feature",
  "properties": {
    "gn:admin1_code":"1",
    "gn:admin2_code":"82.0",
    "gn:admin3_code":"8215.0",
    "gn:admin4_code":"8215009.0",
    "gn:asciiname":"Helmsheim",
    "gn:country_code":"DE",
    "gn:dem":148,
    "gn:feature_class":"P",
    "gn:feature_code":"PPL",
    "gn:name":"Helmsheim",
    "gn:population":0,
    "gn:timezone":"Europe/Berlin",
    "iso:country":"DE",
    "wof:name":"Helmsheim",
    "wof:placetype":"neighbourhood"
},
  "geometry": {"coordinates":[8.64271,49.08465],"type":"Point"}
}