{
  "type": "Feature",
  "properties": {
    "gn:admin1_code":"5",
    "gn:admin2_code":"64.0",
    "gn:admin3_code":"6434.0",
    "gn:admin4_code":"6434012.0",
    "gn:asciiname":"Friedrichsthal",
    "gn:country_code":"DE",
    "gn:dem":290,
    "gn:feature_class":"P",
    "gn:feature_code":"PPL",
    "gn:name":"Friedrichsthal",
    "gn:population":0,
    "gn:timezone":"Europe/Berlin",
    "iso:country":"DE",
    "wof:name":"Friedrichsthal",
    "wof:placetype":"neighbourhood"
},
  "geometry": {"coordinates":[8.61594,50.34245],"type":"Point"}
}