{
  "type": "Feature",
  "properties": {
    "gn:admin1_code":"5",
    "gn:admin2_code":"64.0",
    "gn:admin3_code":"6434.0",
    "gn:admin4_code":"6434012.0",
    "gn:asciiname":"Friedrichsthal",
    "gn:country_code":"DE",
    "gn:dem":290,
    "gn:feature_class":"P",
    "gn:feature_code":"PPL",
    "gn:name":"Friedrichsthal",
    "gn:population":0,
    "gn:timezone":"Europe/Berlin",
    "iso:country":"DE",
    "name:ara_x_preferred":[
        "\u0641\u0631\u064a\u062f\u0631\u064a\u0634\u062a\u0627\u0644"
    ],
    "name:azb_x_preferred":[
        "\u0641\u0631\u06cc\u062f\u0631\u06cc\u0634\u062a\u0627\u0644"
    ],
    "name:cat_x_preferred":[
        "Friedrichsthal"
    ],
    "name:deu_x_preferred":[
        "Friedrichsthal"
    ],
    "name:epo_x_preferred":[
        "Friedrichsthal"
    ],
    "name:eus_x_preferred":[
        "Friedrichsthal"
    ],
    "name:fas_x_preferred":[
        "\u0641\u0631\u06cc\u062f\u0631\u06cc\u0634\u062a\u0627\u0644"
    ],
    "name:fra_x_preferred":[
        "Friedrichsthal"
    ],
    "name:hun_x_preferred":[
        "Friedrichsthal"
    ],
    "name:ita_x_preferred":[
        "Friedrichsthal"
    ],
    "name:kaz_x_preferred":[
        "\u0424\u0440\u0438\u0434\u0440\u0438\u0445\u0441\u0442\u0430\u043b\u044c"
    ],
    "name:kir_x_preferred":[
        "\u0424\u0440\u0438\u0434\u0440\u0438\u0445\u0441\u0442\u0430\u043b\u044c"
    ],
    "name:msa_x_preferred":[
        "Friedrichsthal"
    ],
    "name:nld_x_preferred":[
        "Friedrichsthal"
    ],
    "name:pol_x_preferred":[
        "Friedrichsthal"
    ],
    "name:por_x_preferred":[
        "Friedrichsthal"
    ],
    "name:ron_x_preferred":[
        "Friedrichsthal"
    ],
    "name:rus_x_preferred":[
        "\u0424\u0440\u0438\u0434\u0440\u0438\u0445\u0441\u0442\u0430\u043b\u044c"
    ],
    "name:spa_x_preferred":[
        "Friedrichsthal"
    ],
    "name:srp_x_preferred":[
        "\u0424\u0440\u0438\u0434\u0440\u0438\u0445\u0441\u0442\u0430\u043b"
    ],
    "name:tur_x_preferred":[
        "Friedrichsthal"
    ],
    "name:ukr_x_preferred":[
        "\u0424\u0440\u0456\u0434\u0440\u0456\u0445\u0441\u0442\u0430\u043b\u044c"
    ],
    "name:uzb_x_preferred":[
        "Friedrichsthal"
    ],
    "name:vol_x_preferred":[
        "Friedrichsthal"
    ],
    "name:war_x_preferred":[
        "Friedrichsthal"
    ],
    "name:zho_x_preferred":[
        "\u8153\u7279\u70c8\u65af\u5854\u5c14"
    ],
    "wof:name":"Friedrichsthal",
    "wof:placetype":"neighbourhood"
},
  "geometry": {"coordinates":[8.61594,50.34245],"type":"Point"}
}