{
  "type": "Feature",
  "properties": {
    "gn:admin1_code":"12",
    "gn:admin2_code":"0.0",
    "gn:admin3_code":"13071.0",
    "gn:admin4_code":"13071074.0",
    "gn:asciiname":"Mittelhof",
    "gn:country_code":"DE",
    "gn:dem":52,
    "gn:feature_class":"P",
    "gn:feature_code":"PPL",
    "gn:name":"Mittelhof",
    "gn:population":0,
    "gn:timezone":"Europe/Berlin",
    "iso:country":"DE",
    "name:ceb_x_preferred":[
        "Mittelhof"
    ],
    "name:deu_x_preferred":[
        "Mittelhof"
    ],
    "name:epo_x_preferred":[
        "Mittelhof"
    ],
    "name:eus_x_preferred":[
        "Mittelhof"
    ],
    "name:fas_x_preferred":[
        "\u0645\u06cc\u062a\u0644\u0647\u0627\u0641"
    ],
    "name:fra_x_preferred":[
        "Mittelhof"
    ],
    "name:hun_x_preferred":[
        "Mittelhof"
    ],
    "name:ita_x_preferred":[
        "Mittelhof"
    ],
    "name:msa_x_preferred":[
        "Mittelhof"
    ],
    "name:nld_x_preferred":[
        "Mittelhof"
    ],
    "name:pol_x_preferred":[
        "Mittelhof"
    ],
    "name:por_x_preferred":[
        "Mittelhof"
    ],
    "name:ron_x_preferred":[
        "Mittelhof"
    ],
    "name:rus_x_preferred":[
        "\u041c\u0438\u0442\u0442\u0435\u043b\u044c\u0445\u043e\u0444"
    ],
    "name:spa_x_preferred":[
        "Mittelhof"
    ],
    "name:srp_x_preferred":[
        "\u041c\u0438\u0442\u0435\u043b\u0445\u043e\u0444"
    ],
    "name:ukr_x_preferred":[
        "\u041c\u0456\u0442\u0442\u0435\u043b\u044c\u0433\u043e\u0444"
    ],
    "name:uzb_x_preferred":[
        "Mittelhof"
    ],
    "name:vie_x_preferred":[
        "Mittelhof"
    ],
    "name:vol_x_preferred":[
        "Mittelhof"
    ],
    "name:war_x_preferred":[
        "Mittelhof"
    ],
    "name:zho_x_preferred":[
        "\u7c73\u7279\u5c14\u970d\u592b"
    ],
    "wof:name":"Mittelhof",
    "wof:placetype":"neighbourhood"
},
  "geometry": {"coordinates":[12.88208,53.61466],"type":"Point"}
}