{
  "type": "Feature",
  "properties": {
    "gn:admin1_code":"2.0",
    "gn:admin2_code":"095",
    "gn:admin3_code":"9572.0",
    "gn:admin4_code":"9572115.0",
    "gn:asciiname":"Wellerstadt",
    "gn:country_code":"DE",
    "gn:dem":267,
    "gn:feature_class":"P",
    "gn:feature_code":"PPL",
    "gn:name":"Wellerstadt",
    "gn:population":0,
    "gn:timezone":"Europe/Berlin",
    "iso:country":"DE",
    "wof:name":"Wellerstadt",
    "wof:placetype":"neighbourhood"
},
  "geometry": {"coordinates":[11.03778,49.66461],"type":"Point"}
}