{
  "type": "Feature",
  "properties": {
    "gn:admin1_code":"1",
    "gn:admin2_code":"82.0",
    "gn:admin3_code":"8236.0",
    "gn:admin4_code":"8236070.0",
    "gn:asciiname":"Weiler",
    "gn:country_code":"DE",
    "gn:dem":213,
    "gn:feature_class":"P",
    "gn:feature_code":"PPL",
    "gn:name":"Weiler",
    "gn:population":0,
    "gn:timezone":"Europe/Berlin",
    "iso:country":"DE",
    "name:als_x_preferred":[
        "Weiler"
    ],
    "name:bar_x_preferred":[
        "Weiler"
    ],
    "name:ceb_x_preferred":[
        "Weiler"
    ],
    "name:deu_x_preferred":[
        "Weiler"
    ],
    "name:epo_x_preferred":[
        "Weiler"
    ],
    "name:fra_x_preferred":[
        "Weiler"
    ],
    "name:hun_x_preferred":[
        "Weiler"
    ],
    "name:ita_x_preferred":[
        "Weiler"
    ],
    "name:ltz_x_preferred":[
        "Weiler"
    ],
    "name:nld_x_preferred":[
        "Weiler"
    ],
    "name:pol_x_preferred":[
        "Weiler"
    ],
    "name:por_x_preferred":[
        "Weiler"
    ],
    "name:rus_x_preferred":[
        "\u0412\u0430\u0439\u043b\u0435\u0440"
    ],
    "name:srp_x_preferred":[
        "\u0412\u0430\u0458\u043b\u0435\u0440"
    ],
    "name:swe_x_preferred":[
        "Weiler"
    ],
    "name:ukr_x_preferred":[
        "\u0412\u0430\u0439\u043b\u0435\u0440"
    ],
    "name:vol_x_preferred":[
        "Weiler"
    ],
    "wof:name":"Weiler",
    "wof:placetype":"neighbourhood"
},
  "geometry": {"coordinates":[8.54419,48.88622],"type":"Point"}
}