{
  "type": "Feature",
  "properties": {
    "gn:admin1_code":"14.0",
    "gn:admin2_code":"0.0",
    "gn:admin3_code":"15083.0",
    "gn:admin4_code":"15083515.0",
    "gn:asciiname":"Badeleben",
    "gn:cc2":"DE",
    "gn:country_code":"DE",
    "gn:dem":151,
    "gn:feature_class":"P",
    "gn:feature_code":"PPL",
    "gn:name":"Badeleben",
    "gn:population":0,
    "gn:timezone":"Europe/Berlin",
    "iso:country":"DE",
    "name:deu_x_preferred":[
        "Badeleben"
    ],
    "name:osx_x_preferred":[
        "Bodenleve"
    ],
    "name:und_x_variant":[
        "Badelegen"
    ],
    "wof:name":"Badeleben",
    "wof:placetype":"neighbourhood"
},
  "geometry": {"coordinates":[11.12537,52.14634],"type":"Point"}
}