{
  "type": "Feature",
  "properties": {
    "gn:admin1_code":"7",
    "gn:admin2_code":"57.0",
    "gn:admin3_code":"5770.0",
    "gn:admin4_code":"5770004.0",
    "gn:asciiname":"Volmerdingsen",
    "gn:country_code":"DE",
    "gn:dem":102,
    "gn:feature_class":"P",
    "gn:feature_code":"PPL",
    "gn:name":"Volmerdingsen",
    "gn:population":0,
    "gn:timezone":"Europe/Berlin",
    "iso:country":"DE",
    "name:und_x_variant":[
        "Vollmerdingsen",
        "Volmerdingsen"
    ],
    "wof:name":"Volmerdingsen",
    "wof:placetype":"neighbourhood"
},
  "geometry": {"coordinates":[8.78183,52.25222],"type":"Point"}
}