{
  "type": "Feature",
  "properties": {
    "gn:admin1_code":"5",
    "gn:admin2_code":"64.0",
    "gn:admin3_code":"6434.0",
    "gn:admin4_code":"6434001.0",
    "gn:asciiname":"Kirdorf",
    "gn:country_code":"DE",
    "gn:dem":186,
    "gn:feature_class":"P",
    "gn:feature_code":"PPL",
    "gn:name":"Kirdorf",
    "gn:population":0,
    "gn:timezone":"Europe/Berlin",
    "iso:country":"DE",
    "wof:name":"Kirdorf",
    "wof:placetype":"neighbourhood"
},
  "geometry": {"coordinates":[8.60882,50.24062],"type":"Point"}
}