{
  "type": "Feature",
  "properties": {
    "gn:admin1_code":"10",
    "gn:admin2_code":"0.0",
    "gn:admin3_code":"1055.0",
    "gn:admin4_code":"1055046.0",
    "gn:asciiname":"Sundhauser",
    "gn:country_code":"DE",
    "gn:dem":6,
    "gn:feature_class":"P",
    "gn:feature_code":"PPL",
    "gn:name":"Sundh\u00e4user",
    "gn:population":0,
    "gn:timezone":"Europe/Berlin",
    "iso:country":"DE",
    "wof:name":"Sundhauser",
    "wof:placetype":"neighbourhood"
},
  "geometry": {"coordinates":[11.18202,54.43301],"type":"Point"}
}