{
  "type": "Feature",
  "properties": {
    "gn:admin1_code":"6",
    "gn:admin2_code":"0.0",
    "gn:admin3_code":"3241.0",
    "gn:admin4_code":"3241019.0",
    "gn:asciiname":"Ickhorst",
    "gn:country_code":"DE",
    "gn:dem":51,
    "gn:feature_class":"P",
    "gn:feature_code":"PPL",
    "gn:name":"Ickhorst",
    "gn:population":0,
    "gn:timezone":"Europe/Berlin",
    "iso:country":"DE",
    "name:nds_x_preferred":[
        "Ickhost"
    ],
    "wof:name":"Ickhorst",
    "wof:placetype":"neighbourhood"
},
  "geometry": {"coordinates":[9.73088,52.50685],"type":"Point"}
}