{
  "type": "Feature",
  "properties": {
    "gn:admin1_code":"6",
    "gn:admin2_code":"0.0",
    "gn:admin3_code":"3454.0",
    "gn:admin4_code":"3454030.0",
    "gn:asciiname":"Devermuehlen",
    "gn:country_code":"DE",
    "gn:dem":5,
    "gn:feature_class":"P",
    "gn:feature_code":"PPL",
    "gn:name":"Deverm\u00fchlen",
    "gn:population":0,
    "gn:timezone":"Europe/Berlin",
    "iso:country":"DE",
    "wof:name":"Devermuehlen",
    "wof:placetype":"neighbourhood"
},
  "geometry": {"coordinates":[7.35904,53.01595],"type":"Point"}
}