{
  "type": "Feature",
  "properties": {
    "gn:admin1_code":"2",
    "gn:admin2_code":"93.0",
    "gn:admin3_code":"9375.0",
    "gn:admin4_code":"9375211.0",
    "gn:asciiname":"Hohenwarth",
    "gn:country_code":"DE",
    "gn:dem":448,
    "gn:feature_class":"P",
    "gn:feature_code":"PPL",
    "gn:name":"Hohenwarth",
    "gn:population":0,
    "gn:timezone":"Europe/Berlin",
    "iso:country":"DE",
    "name:bar_x_preferred":[
        "Hohenwarth"
    ],
    "name:ceb_x_preferred":[
        "Hohenwarth"
    ],
    "name:dan_x_preferred":[
        "Hohenwarth"
    ],
    "name:deu_x_preferred":[
        "Hohenwarth"
    ],
    "name:epo_x_preferred":[
        "Hohenwarth"
    ],
    "name:fra_x_preferred":[
        "Hohenwarth"
    ],
    "name:hun_x_preferred":[
        "Hohenwarth"
    ],
    "name:hye_x_preferred":[
        "\u0540\u0578\u0570\u0565\u0576\u057e\u0561\u0580\u0569"
    ],
    "name:ind_x_preferred":[
        "Hohenwarth"
    ],
    "name:ita_x_preferred":[
        "Hohenwarth"
    ],
    "name:lmo_x_preferred":[
        "Hohenwarth"
    ],
    "name:msa_x_preferred":[
        "Hohenwarth"
    ],
    "name:nld_x_preferred":[
        "Hohenwarth"
    ],
    "name:pol_x_preferred":[
        "Hohenwarth"
    ],
    "name:por_x_preferred":[
        "Hohenwarth"
    ],
    "name:ron_x_preferred":[
        "Hohenwarth"
    ],
    "name:rus_x_preferred":[
        "\u0425\u043e\u044d\u043d\u0432\u0430\u0440\u0442"
    ],
    "name:spa_x_preferred":[
        "Hohenwarth"
    ],
    "name:srp_x_preferred":[
        "\u0425\u043e\u0435\u043d\u0432\u0430\u0440\u0442"
    ],
    "name:ukr_x_preferred":[
        "\u0413\u043e\u0435\u043d\u0432\u0430\u0440\u0442"
    ],
    "name:vie_x_preferred":[
        "Hohenwarth"
    ],
    "name:vol_x_preferred":[
        "Hohenwarth"
    ],
    "name:war_x_preferred":[
        "Hohenwarth"
    ],
    "wof:name":"Hohenwarth",
    "wof:placetype":"neighbourhood"
},
  "geometry": {"coordinates":[11.98909,49.0941],"type":"Point"}
}