{
  "type": "Feature",
  "properties": {
    "gn:admin1_code":"11",
    "gn:admin2_code":"0.0",
    "gn:admin3_code":"12069.0",
    "gn:admin4_code":"12069470.0",
    "gn:asciiname":"Oberjuenne",
    "gn:country_code":"DE",
    "gn:dem":46,
    "gn:feature_class":"P",
    "gn:feature_code":"PPL",
    "gn:name":"Oberj\u00fcnne",
    "gn:population":0,
    "gn:timezone":"Europe/Berlin",
    "iso:country":"DE",
    "wof:name":"Oberjuenne",
    "wof:placetype":"neighbourhood"
},
  "geometry": {"coordinates":[12.63977,52.27991],"type":"Point"}
}