{
  "type": "Feature",
  "properties": {
    "gn:admin1_code":"2",
    "gn:admin2_code":"94.0",
    "gn:admin3_code":"9476.0",
    "gn:admin4_code":"9476145.0",
    "gn:asciiname":"Hinterstocken",
    "gn:country_code":"DE",
    "gn:dem":342,
    "gn:feature_class":"P",
    "gn:feature_code":"PPL",
    "gn:name":"Hinterst\u00f6cken",
    "gn:population":0,
    "gn:timezone":"Europe/Berlin",
    "iso:country":"DE",
    "wof:name":"Hinterstocken",
    "wof:placetype":"neighbourhood"
},
  "geometry": {"coordinates":[11.36593,50.21883],"type":"Point"}
}