{
  "type": "Feature",
  "properties": {
    "gn:admin1_code":"6.0",
    "gn:admin2_code":"0.0",
    "gn:admin3_code":"3354.0",
    "gn:admin4_code":"3354003.0",
    "gn:asciiname":"Kamerun",
    "gn:country_code":"DE",
    "gn:dem":14,
    "gn:feature_class":"P",
    "gn:feature_code":"PPL",
    "gn:name":"Kamerun",
    "gn:population":0,
    "gn:timezone":"Europe/Berlin",
    "iso:country":"DE",
    "name:afr_x_preferred":[
        "Duits-Kameroen"
    ],
    "name:ara_x_preferred":[
        "\u0627\u0644\u0643\u0627\u0645\u064a\u0631\u0648\u0646 \u0627\u0644\u0623\u0644\u0645\u0627\u0646\u064a\u0629"
    ],
    "name:ast_x_preferred":[
        "Kamerun"
    ],
    "name:azb_x_preferred":[
        "\u0622\u0644\u0645\u0627\u0646 \u06a9\u0627\u0645\u0631\u0648\u0646\u0648"
    ],
    "name:cat_x_preferred":[
        "Camerun Alemany"
    ],
    "name:ces_x_preferred":[
        "N\u011bmeck\u00fd Kamerun"
    ],
    "name:dan_x_preferred":[
        "Kamerun"
    ],
    "name:deu_x_preferred":[
        "Kamerun"
    ],
    "name:eus_x_preferred":[
        "Kamerun Alemana"
    ],
    "name:fas_x_preferred":[
        "\u06a9\u0627\u0645\u0631\u0648\u0646 \u0622\u0644\u0645\u0627\u0646"
    ],
    "name:fin_x_preferred":[
        "Saksan Kamerun"
    ],
    "name:fra_x_preferred":[
        "Kamerun"
    ],
    "name:glg_x_preferred":[
        "Camer\u00fan alem\u00e1n"
    ],
    "name:hrv_x_preferred":[
        "Njema\u010dki Kamerun"
    ],
    "name:hye_x_preferred":[
        "\u0533\u0565\u0580\u0574\u0561\u0576\u0561\u056f\u0561\u0576 \u053f\u0561\u0574\u0565\u0580\u0578\u0582\u0576"
    ],
    "name:ind_x_preferred":[
        "Kamerun Jerman"
    ],
    "name:ita_x_preferred":[
        "Camerun tedesco"
    ],
    "name:jpn_x_preferred":[
        "\u30c9\u30a4\u30c4\u4fdd\u8b77\u9818\u30ab\u30e1\u30eb\u30fc\u30f3"
    ],
    "name:lit_x_preferred":[
        "Vokietijos Kamer\u016bnas"
    ],
    "name:nld_x_preferred":[
        "Duits-Kameroen"
    ],
    "name:pol_x_preferred":[
        "Kamerun Niemiecki"
    ],
    "name:por_x_preferred":[
        "Camar\u00f5es Alem\u00e3es"
    ],
    "name:rus_x_preferred":[
        "\u0413\u0435\u0440\u043c\u0430\u043d\u0441\u043a\u0438\u0439 \u041a\u0430\u043c\u0435\u0440\u0443\u043d"
    ],
    "name:spa_x_preferred":[
        "Kamerun"
    ],
    "name:srp_x_preferred":[
        "\u041d\u0435\u043c\u0430\u0447\u043a\u0438 \u041a\u0430\u043c\u0435\u0440\u0443\u043d"
    ],
    "name:swe_x_preferred":[
        "Tyska Kamerun"
    ],
    "name:tur_x_preferred":[
        "Alman Kamerunu"
    ],
    "name:ukr_x_preferred":[
        "\u041d\u0456\u043c\u0435\u0446\u044c\u043a\u0438\u0439 \u041a\u0430\u043c\u0435\u0440\u0443\u043d"
    ],
    "name:urd_x_preferred":[
        "\u06a9\u0627\u0645\u06cc\u0631\u0648\u0646"
    ],
    "name:vie_x_preferred":[
        "Kamerun"
    ],
    "name:zho_x_preferred":[
        "\u5fb7\u5c5e\u5580\u9ea6\u9686"
    ],
    "wof:name":"Kamerun",
    "wof:placetype":"neighbourhood"
},
  "geometry": {"coordinates":[11.1858,53.12494],"type":"Point"}
}