{
  "type": "Feature",
  "properties": {
    "gn:admin1_code":"7",
    "gn:admin2_code":"51.0",
    "gn:admin3_code":"5162.0",
    "gn:admin4_code":"5162016.0",
    "gn:asciiname":"Broicherseite",
    "gn:country_code":"DE",
    "gn:dem":39,
    "gn:feature_class":"P",
    "gn:feature_code":"PPL",
    "gn:name":"Broicherseite",
    "gn:population":0,
    "gn:timezone":"Europe/Berlin",
    "iso:country":"DE",
    "wof:name":"Broicherseite",
    "wof:placetype":"neighbourhood"
},
  "geometry": {"coordinates":[6.64796,51.25068],"type":"Point"}
}