{
  "type": "Feature",
  "properties": {
    "iso:country":"DE",
    "name:deu_x_colloquial":[
        "Vosspass"
    ],
    "name:deu_x_preferred":[
        "Bahnstrecke Braunschweig\u2013Derneburg"
    ],
    "name:deu_x_variant":[
        "Vo\u00dfpa\u00df"
    ],
    "name:unk_x_variant":[
        "Vo\u00dfpa\u00df"
    ],
    "qs:gn_fcode":"PPL",
    "qs:gn_local":0,
    "qs:gn_namadm1":"06",
    "qs:gn_name":"Vo\u00dfpa\u00df",
    "qs:local_max":122,
    "qs:local_sum":398,
    "qs:localhoods":10,
    "qs:name":"Vo\u00dfpa\u00df",
    "qs:name_adm0":"Deutschland",
    "qs:name_adm1":"Niedersachsen",
    "qs:name_adm2":"Stadtkreis Salzgitter",
    "qs:name_lau":"Stadtteil Gro\u00df Mahner",
    "qs:name_local":"Salzgitter",
    "qs:photo_max":6,
    "qs:photo_sum":13,
    "qs:placetype":"Suburb",
    "qs:quad_count":3,
    "qs:woe_adm0":23424829,
    "qs:woe_adm1":2345486,
    "qs:woe_adm2":12596994,
    "qs:woe_lau":26823229,
    "qs:woe_local":690863,
    "qs:woe_ver":"7.10.0",
    "wof:lang":[
        "ger"
    ],
    "wof:name":"Vo\u00dfpa\u00df",
    "wof:placetype":"neighbourhood"
},
  "geometry": {"coordinates":[10.3937,52.047162],"type":"Point"}
}