{
  "type": "Feature",
  "properties": {
    "gn:admin1_code":"6",
    "gn:admin2_code":"0.0",
    "gn:admin3_code":"3455.0",
    "gn:admin4_code":"3455015.0",
    "gn:asciiname":"Moorhausen",
    "gn:country_code":"DE",
    "gn:dem":6,
    "gn:feature_class":"P",
    "gn:feature_code":"PPLL",
    "gn:name":"Moorhausen",
    "gn:population":0,
    "gn:timezone":"Europe/Berlin",
    "iso:country":"DE",
    "wof:name":"Moorhausen",
    "wof:placetype":"neighbourhood"
},
  "geometry": {"coordinates":[7.95972,53.56201],"type":"Point"}
}