{
  "type": "Feature",
  "properties": {
    "gn:admin1_code":"14",
    "gn:admin2_code":"0.0",
    "gn:admin3_code":"15086.0",
    "gn:admin4_code":"15086140.0",
    "gn:asciiname":"Kalitz",
    "gn:country_code":"DE",
    "gn:dem":88,
    "gn:feature_class":"P",
    "gn:feature_code":"PPL",
    "gn:name":"Kalitz",
    "gn:population":0,
    "gn:timezone":"Europe/Berlin",
    "iso:country":"DE",
    "wof:name":"Kalitz",
    "wof:placetype":"neighbourhood"
},
  "geometry": {"coordinates":[12.02219,52.09737],"type":"Point"}
}