{
  "type": "Feature",
  "properties": {
    "gn:admin1_code":"13.0",
    "gn:admin2_code":"0.0",
    "gn:admin3_code":"14523.0",
    "gn:admin4_code":"14523160.0",
    "gn:asciiname":"Aschberg",
    "gn:country_code":"DE",
    "gn:dem":809,
    "gn:feature_class":"P",
    "gn:feature_code":"PPL",
    "gn:name":"Aschberg",
    "gn:population":0,
    "gn:timezone":"Europe/Berlin",
    "iso:country":"DE",
    "name:afr_x_preferred":[
        "Aschberg"
    ],
    "name:deu_x_preferred":[
        "Kamen\u00e1\u010d"
    ],
    "name:nld_x_preferred":[
        "Kamen\u00e1\u010d"
    ],
    "wof:name":"Aschberg",
    "wof:placetype":"neighbourhood"
},
  "geometry": {"coordinates":[12.49753,50.38848],"type":"Point"}
}