{
  "type": "Feature",
  "properties": {
    "gn:admin1_code":"2",
    "gn:admin2_code":"94.0",
    "gn:admin3_code":"9472.0",
    "gn:admin4_code":"9472156.0",
    "gn:asciiname":"Schmetterslohe",
    "gn:country_code":"DE",
    "gn:dem":517,
    "gn:feature_class":"P",
    "gn:feature_code":"PPL",
    "gn:name":"Schmetterslohe",
    "gn:population":0,
    "gn:timezone":"Europe/Berlin",
    "iso:country":"DE",
    "wof:name":"Schmetterslohe",
    "wof:placetype":"neighbourhood"
},
  "geometry": {"coordinates":[11.80656,49.91648],"type":"Point"}
}