{
  "type": "Feature",
  "properties": {
    "gn:admin1_code":"1",
    "gn:admin2_code":"81.0",
    "gn:admin3_code":"8127.0",
    "gn:admin4_code":"8127008.0",
    "gn:asciiname":"Naicha",
    "gn:country_code":"DE",
    "gn:dem":476,
    "gn:feature_class":"P",
    "gn:feature_code":"PPL",
    "gn:name":"Naicha",
    "gn:population":0,
    "gn:timezone":"Europe/Berlin",
    "iso:country":"DE",
    "wof:name":"Naicha",
    "wof:placetype":"neighbourhood"
},
  "geometry": {"coordinates":[10.02941,49.31582],"type":"Point"}
}