{
  "type": "Feature",
  "properties": {
    "gn:admin1_code":"2",
    "gn:admin2_code":"94.0",
    "gn:admin3_code":"9472.0",
    "gn:admin4_code":"9472179.0",
    "gn:asciiname":"Waidach",
    "gn:country_code":"DE",
    "gn:dem":483,
    "gn:feature_class":"P",
    "gn:feature_code":"PPL",
    "gn:name":"Waidach",
    "gn:population":0,
    "gn:timezone":"Europe/Berlin",
    "iso:country":"DE",
    "wof:name":"Waidach",
    "wof:placetype":"locality"
},
  "geometry": {"coordinates":[11.42011,49.73068],"type":"Point"}
}