{
  "type": "Feature",
  "properties": {
    "gn:admin1_code":"1",
    "gn:admin2_code":"83.0",
    "gn:admin3_code":"8336.0",
    "gn:admin4_code":"8336025.0",
    "gn:asciiname":"Niederhepschingen",
    "gn:country_code":"DE",
    "gn:dem":513,
    "gn:feature_class":"P",
    "gn:feature_code":"PPL",
    "gn:name":"Niederhepschingen",
    "gn:population":0,
    "gn:timezone":"Europe/Berlin",
    "iso:country":"DE",
    "wof:name":"Niederhepschingen",
    "wof:placetype":"neighbourhood"
},
  "geometry": {"coordinates":[7.88012,47.74792],"type":"Point"}
}