{
  "type": "Feature",
  "properties": {
    "gn:admin1_code":"7.0",
    "gn:admin2_code":"55.0",
    "gn:admin3_code":"5554.0",
    "gn:admin4_code":"5554004.0",
    "gn:asciiname":"Averesch",
    "gn:country_code":"DE",
    "gn:dem":44,
    "gn:feature_class":"P",
    "gn:feature_code":"PPL",
    "gn:name":"Averesch",
    "gn:population":0,
    "gn:timezone":"Europe/Berlin",
    "iso:country":"DE",
    "wof:name":"Averesch",
    "wof:placetype":"neighbourhood"
},
  "geometry": {"coordinates":[6.95999,52.10901],"type":"Point"}
}