{
  "type": "Feature",
  "properties": {
    "gn:admin1_code":"1",
    "gn:admin2_code":"81.0",
    "gn:admin3_code":"8125.0",
    "gn:admin4_code":"8125059.0",
    "gn:asciiname":"Rittelhof",
    "gn:country_code":"DE",
    "gn:dem":270,
    "gn:feature_class":"P",
    "gn:feature_code":"PPL",
    "gn:name":"Rittelhof",
    "gn:population":0,
    "gn:timezone":"Europe/Berlin",
    "iso:country":"DE",
    "wof:name":"Rittelhof",
    "wof:placetype":"neighbourhood"
},
  "geometry": {"coordinates":[9.37052,49.10227],"type":"Point"}
}