{
  "type": "Feature",
  "properties": {
    "gn:admin1_code":"2",
    "gn:admin2_code":"91.0",
    "gn:admin3_code":"9173.0",
    "gn:admin4_code":"9173145.0",
    "gn:asciiname":"Rimslrain",
    "gn:country_code":"DE",
    "gn:dem":690,
    "gn:feature_class":"P",
    "gn:feature_code":"PPL",
    "gn:name":"Rimslrain",
    "gn:population":0,
    "gn:timezone":"Europe/Berlin",
    "iso:country":"DE",
    "wof:name":"Rimslrain",
    "wof:placetype":"neighbourhood"
},
  "geometry": {"coordinates":[11.53959,47.80266],"type":"Point"}
}