{
  "type": "Feature",
  "properties": {
    "gn:admin1_code":"14",
    "gn:admin2_code":"0.0",
    "gn:admin3_code":"15085.0",
    "gn:admin4_code":"15085110.0",
    "gn:asciiname":"Endorf",
    "gn:country_code":"DE",
    "gn:dem":222,
    "gn:feature_class":"P",
    "gn:feature_code":"PPL",
    "gn:name":"Endorf",
    "gn:population":0,
    "gn:timezone":"Europe/Berlin",
    "iso:country":"DE",
    "name:deu_x_preferred":[
        "Endorf"
    ],
    "name:ita_x_preferred":[
        "Endorf"
    ],
    "name:pol_x_preferred":[
        "Endorf"
    ],
    "wof:name":"Endorf",
    "wof:placetype":"neighbourhood"
},
  "geometry": {"coordinates":[11.37538,51.71299000000001],"type":"Point"}
}