{
  "type": "Feature",
  "properties": {
    "gn:admin1_code":"2",
    "gn:admin2_code":"95.0",
    "gn:admin3_code":"9575.0",
    "gn:admin4_code":"9575145.0",
    "gn:asciiname":"Mettelaurach",
    "gn:country_code":"DE",
    "gn:dem":375,
    "gn:feature_class":"P",
    "gn:feature_code":"PPL",
    "gn:name":"Mettelaurach",
    "gn:population":0,
    "gn:timezone":"Europe/Berlin",
    "iso:country":"DE",
    "wof:name":"Mettelaurach",
    "wof:placetype":"neighbourhood"
},
  "geometry": {"coordinates":[10.61126,49.51362],"type":"Point"}
}