{
  "type": "Feature",
  "properties": {
    "gn:admin1_code":"10",
    "gn:admin2_code":"0.0",
    "gn:admin3_code":"1059.0",
    "gn:admin4_code":"1059112.0",
    "gn:asciiname":"Goldhoeft",
    "gn:country_code":"DE",
    "gn:dem":6,
    "gn:feature_class":"P",
    "gn:feature_code":"PPL",
    "gn:name":"Goldh\u00f6ft",
    "gn:population":0,
    "gn:timezone":"Europe/Berlin",
    "iso:country":"DE",
    "wof:name":"Goldhoeft",
    "wof:placetype":"neighbourhood"
},
  "geometry": {"coordinates":[9.92449,54.76176],"type":"Point"}
}