{
  "type": "Feature",
  "properties": {
    "gn:admin1_code":"1",
    "gn:admin2_code":"83.0",
    "gn:admin3_code":"8317.0",
    "gn:admin4_code":"8317056.0",
    "gn:asciiname":"Weiher",
    "gn:country_code":"DE",
    "gn:dem":247,
    "gn:feature_class":"P",
    "gn:feature_code":"PPLL",
    "gn:name":"Weiher",
    "gn:population":0,
    "gn:timezone":"Europe/Berlin",
    "iso:country":"DE",
    "wof:name":"Weiher",
    "wof:placetype":"neighbourhood"
},
  "geometry": {"coordinates":[8.11164,48.58706],"type":"Point"}
}