{
  "type": "Feature",
  "properties": {
    "gn:admin1_code":"11.0",
    "gn:admin2_code":"0.0",
    "gn:admin3_code":"12073.0",
    "gn:admin4_code":"12073008.0",
    "gn:asciiname":"Altkuenkendorf",
    "gn:country_code":"DE",
    "gn:dem":64,
    "gn:feature_class":"P",
    "gn:feature_code":"PPL",
    "gn:name":"Altk\u00fcnkendorf",
    "gn:population":0,
    "gn:timezone":"Europe/Berlin",
    "iso:country":"DE",
    "wof:name":"Altkuenkendorf",
    "wof:placetype":"neighbourhood"
},
  "geometry": {"coordinates":[13.87496,53.00802],"type":"Point"}
}