{
  "type": "Feature",
  "properties": {
    "gn:gn_country":"DE",
    "gn:gn_fcode":"PPLA4",
    "gn:gn_pop":328,
    "gn:population":328,
    "iso:country":"DE",
    "name:baq_x_preferred":[
        "Finkenbach-Gersweiler"
    ],
    "name:chi_x_preferred":[
        "\u82ac\u80af\u5df4-\u683c\u5c14\u65af\u9b4f\u83b1\u5c14"
    ],
    "name:dut_x_preferred":[
        "Finkenbach-Gersweiler"
    ],
    "name:eng_x_preferred":[
        "Finkenbach-Gersweiler"
    ],
    "name:epo_x_preferred":[
        "Finkenbach-Gersweiler"
    ],
    "name:fre_x_preferred":[
        "Finkenbach-Gersweiler"
    ],
    "name:ger_x_preferred":[
        "Finkenbach-Gersweiler"
    ],
    "name:hun_x_preferred":[
        "Finkenbach-Gersweiler"
    ],
    "name:ita_x_preferred":[
        "Finkenbach-Gersweiler"
    ],
    "name:jpn_x_preferred":[
        "\u30d5\u30a3\u30f3\u30b1\u30f3\u30d0\u30c3\u30cf\uff1d\u30b2\u30eb\u30b9\u30f4\u30a1\u30a4\u30e9\u30fc"
    ],
    "name:kaz_x_preferred":[
        "\u0424\u0438\u043d\u043a\u0435\u043d\u0431\u0430\u0445-\u0413\u0435\u0440\u0441\u0432\u0430\u0439\u043b\u0435\u0440"
    ],
    "name:kir_x_preferred":[
        "\u0424\u0438\u043d\u043a\u0435\u043d\u0431\u0430\u0445-\u0413\u0435\u0440\u0441\u0432\u0430\u0439\u043b\u0435\u0440"
    ],
    "name:may_x_preferred":[
        "Finkenbach-Gersweiler"
    ],
    "name:per_x_preferred":[
        "\u0641\u06cc\u0646\u06a9\u0646\u0628\u0627\u062e-\u06af\u0631\u0633\u0648\u0627\u06cc\u0644\u0631"
    ],
    "name:pol_x_preferred":[
        "Finkenbach-Gersweiler"
    ],
    "name:por_x_preferred":[
        "Finkenbach-Gersweiler"
    ],
    "name:rum_x_preferred":[
        "Finkenbach-Gersweiler"
    ],
    "name:rus_x_preferred":[
        "\u0424\u0438\u043d\u043a\u0435\u043d\u0431\u0430\u0445-\u0413\u0435\u0440\u0441\u0432\u0430\u0439\u043b\u0435\u0440"
    ],
    "name:srp_x_preferred":[
        "\u0424\u0438\u043d\u043a\u0435\u043d\u0431\u0430\u0445-\u0413\u0435\u0440\u0441\u0432\u0430\u0458\u043b\u0435\u0440"
    ],
    "name:ukr_x_preferred":[
        "\u0424\u0456\u043d\u043a\u0435\u043d\u0431\u0430\u0445-\u0413\u0435\u0440\u0441\u0432\u0430\u0439\u043b\u0435\u0440"
    ],
    "name:uzb_x_preferred":[
        "Finkenbach-Gersweiler"
    ],
    "name:vie_x_preferred":[
        "Finkenbach-Gersweiler"
    ],
    "name:vol_x_preferred":[
        "Finkenbach-Gersweiler"
    ],
    "name:war_x_preferred":[
        "Finkenbach-Gersweiler"
    ],
    "qs_pg:aaroncc":"DE",
    "qs_pg:gn_country":"DE",
    "qs_pg:gn_fcode":"PPLA4",
    "qs_pg:gn_pop":328,
    "qs_pg:name":"Finkenbach-Gersweiler",
    "qs_pg:photos_9r":0,
    "qs_pg:photos_sr":0,
    "qs_pg:pop_sr":2,
    "qs_pg:qs_pg_placetype":"locality",
    "wof:name":"Finkenbach-Gersweiler",
    "wof:placetype":"locality",
    "wof:population":328
},
  "geometry": {"coordinates":[7.75,49.68333],"type":"Point"}
}