{
  "type": "Feature",
  "properties": {
    "gn:admin1_code":"15.0",
    "gn:admin2_code":"0.0",
    "gn:admin3_code":"16073.0",
    "gn:admin4_code":"16073105.0",
    "gn:asciiname":"Breitenheerda",
    "gn:country_code":"DE",
    "gn:dem":413,
    "gn:feature_class":"P",
    "gn:feature_code":"PPL",
    "gn:name":"Breitenheerda",
    "gn:population":0,
    "gn:timezone":"Europe/Berlin",
    "iso:country":"DE",
    "wof:name":"Breitenheerda",
    "wof:placetype":"neighbourhood"
},
  "geometry": {"coordinates":[11.20236,50.78384000000001],"type":"Point"}
}