{
  "type": "Feature",
  "properties": {
    "gn:admin1_code":"13",
    "gn:admin2_code":"0.0",
    "gn:admin3_code":"14521.0",
    "gn:admin4_code":"14521240.0",
    "gn:asciiname":"Hohndorf",
    "gn:country_code":"DE",
    "gn:dem":536,
    "gn:feature_class":"P",
    "gn:feature_code":"PPL",
    "gn:name":"Hohndorf",
    "gn:population":0,
    "gn:timezone":"Europe/Berlin",
    "iso:country":"DE",
    "name:bak_x_preferred":[
        "\u0425\u043e\u043d\u0434\u043e\u0440\u0444"
    ],
    "name:ceb_x_preferred":[
        "Hohndorf"
    ],
    "name:deu_x_preferred":[
        "Hohndorf"
    ],
    "name:epo_x_preferred":[
        "Hohndorf"
    ],
    "name:eus_x_preferred":[
        "Hohndorf"
    ],
    "name:fra_x_preferred":[
        "Hohndorf"
    ],
    "name:hun_x_preferred":[
        "Hohndorf"
    ],
    "name:ita_x_preferred":[
        "Hohndorf"
    ],
    "name:kaz_x_preferred":[
        "\u0425\u043e\u043d\u0434\u043e\u0440\u0444"
    ],
    "name:kir_x_preferred":[
        "\u0425\u043e\u043d\u0434\u043e\u0440\u0444"
    ],
    "name:mkd_x_preferred":[
        "\u0425\u043e\u043d\u0434\u043e\u0440\u0444"
    ],
    "name:msa_x_preferred":[
        "Hohndorf"
    ],
    "name:nld_x_preferred":[
        "Hohndorf"
    ],
    "name:nor_x_preferred":[
        "Hohndorf"
    ],
    "name:pol_x_preferred":[
        "Hohndorf"
    ],
    "name:por_x_preferred":[
        "Hohndorf"
    ],
    "name:ron_x_preferred":[
        "Hohndorf"
    ],
    "name:rus_x_preferred":[
        "\u0425\u043e\u043d\u0434\u043e\u0440\u0444"
    ],
    "name:spa_x_preferred":[
        "Hohndorf"
    ],
    "name:srp_x_preferred":[
        "\u0425\u043e\u043d\u0434\u043e\u0440\u0444"
    ],
    "name:ukr_x_preferred":[
        "\u0413\u043e\u043d\u0434\u043e\u0440\u0444"
    ],
    "name:uzb_x_preferred":[
        "Hohndorf"
    ],
    "name:vol_x_preferred":[
        "Hohndorf"
    ],
    "name:war_x_preferred":[
        "Hohndorf"
    ],
    "name:zho_x_preferred":[
        "\u970d\u6069\u591a\u592b"
    ],
    "wof:name":"Hohndorf",
    "wof:placetype":"neighbourhood"
},
  "geometry": {"coordinates":[13.09102,50.72087],"type":"Point"}
}