{
  "type": "Feature",
  "properties": {
    "gn:admin1_code":"1",
    "gn:admin2_code":"84.0",
    "gn:admin3_code":"8425.0",
    "gn:admin4_code":"8425033.0",
    "gn:asciiname":"Volkersheim",
    "gn:country_code":"DE",
    "gn:dem":518,
    "gn:feature_class":"P",
    "gn:feature_code":"PPL",
    "gn:name":"Volkersheim",
    "gn:population":0,
    "gn:timezone":"Europe/Berlin",
    "iso:country":"DE",
    "wof:name":"Volkersheim",
    "wof:placetype":"neighbourhood"
},
  "geometry": {"coordinates":[9.7268,48.22021],"type":"Point"}
}