{
  "type": "Feature",
  "properties": {
    "gn:gn_country":"DE",
    "gn:gn_fcode":"PPLA4",
    "gn:gn_pop":243,
    "gn:population":243,
    "iso:country":"DE",
    "name:baq_x_preferred":[
        "L\u00f6llbach"
    ],
    "name:chi_x_preferred":[
        "\u52d2\u5c14\u5df4\u8d6b"
    ],
    "name:dut_x_preferred":[
        "L\u00f6llbach"
    ],
    "name:eng_x_preferred":[
        "L\u00f6llbach"
    ],
    "name:epo_x_preferred":[
        "L\u00f6llbach"
    ],
    "name:fre_x_preferred":[
        "L\u00f6llbach"
    ],
    "name:ger_x_preferred":[
        "L\u00f6llbach"
    ],
    "name:hun_x_preferred":[
        "L\u00f6llbach"
    ],
    "name:ita_x_preferred":[
        "L\u00f6llbach"
    ],
    "name:jpn_x_preferred":[
        "\u30ec\u30eb\u30d0\u30c3\u30cf"
    ],
    "name:kaz_x_preferred":[
        "\u041b\u0451\u043b\u044c\u0431\u0430\u0445"
    ],
    "name:kir_x_preferred":[
        "\u041b\u04e9\u043b\u044c\u0431\u0430\u0445"
    ],
    "name:may_x_preferred":[
        "L\u00f6llbach"
    ],
    "name:per_x_preferred":[
        "\u0644\u0648\u0644\u0628\u0627\u062e"
    ],
    "name:pol_x_preferred":[
        "L\u00f6llbach"
    ],
    "name:por_x_preferred":[
        "L\u00f6llbach"
    ],
    "name:rum_x_preferred":[
        "L\u00f6llbach"
    ],
    "name:rus_x_preferred":[
        "\u041b\u0451\u043b\u044c\u0431\u0430\u0445"
    ],
    "name:srp_x_preferred":[
        "\u041b\u0435\u043b\u0431\u0430\u0445"
    ],
    "name:ukr_x_preferred":[
        "\u041b\u0435\u043b\u044c\u0431\u0430\u0445"
    ],
    "name:uzb_x_preferred":[
        "L\u00f6llbach"
    ],
    "name:vie_x_preferred":[
        "L\u00f6llbach"
    ],
    "name:vol_x_preferred":[
        "L\u00f6llbach"
    ],
    "name:war_x_preferred":[
        "L\u00f6llbach"
    ],
    "name:zho_x_preferred":[
        "\u52d2\u5c14\u5df4\u8d6b"
    ],
    "qs_pg:aaroncc":"DE",
    "qs_pg:gn_country":"DE",
    "qs_pg:gn_fcode":"PPLA4",
    "qs_pg:gn_pop":243,
    "qs_pg:name":"L\u00f6llbach",
    "qs_pg:photos_9r":0,
    "qs_pg:photos_sr":0,
    "qs_pg:pop_sr":2,
    "qs_pg:qs_pg_placetype":"locality",
    "wof:name":"L\u00f6llbach",
    "wof:placetype":"locality",
    "wof:population":243
},
  "geometry": {"coordinates":[7.58333,49.68333],"type":"Point"}
}