{
  "type": "Feature",
  "properties": {
    "gn:admin1_code":"1",
    "gn:admin2_code":"81.0",
    "gn:admin3_code":"8115.0",
    "gn:admin4_code":"8115021.0",
    "gn:asciiname":"Haslach",
    "gn:country_code":"DE",
    "gn:dem":493,
    "gn:feature_class":"P",
    "gn:feature_code":"PPL",
    "gn:name":"Haslach",
    "gn:population":0,
    "gn:timezone":"Europe/Berlin",
    "iso:country":"DE",
    "name:als_x_preferred":[
        "Haslach"
    ],
    "name:ceb_x_preferred":[
        "Haslach"
    ],
    "name:deu_x_preferred":[
        "Haslach"
    ],
    "name:epo_x_preferred":[
        "Haslach"
    ],
    "name:fra_x_preferred":[
        "Haslach"
    ],
    "name:ita_x_preferred":[
        "Haslach"
    ],
    "name:nld_x_preferred":[
        "Haslach"
    ],
    "name:pol_x_preferred":[
        "Haslach"
    ],
    "name:swe_x_preferred":[
        "Haslach"
    ],
    "wof:name":"Haslach",
    "wof:placetype":"neighbourhood"
},
  "geometry": {"coordinates":[8.8397,48.58251],"type":"Point"}
}