{
  "type": "Feature",
  "properties": {
    "gn:admin1_code":"8",
    "gn:admin2_code":"0.0",
    "gn:admin3_code":"7339.0",
    "gn:admin4_code":"7339028.0",
    "gn:asciiname":"Hillesheim",
    "gn:country_code":"DE",
    "gn:dem":162,
    "gn:feature_class":"P",
    "gn:feature_code":"PPLA4",
    "gn:name":"Hillesheim",
    "gn:population":588,
    "gn:timezone":"Europe/Berlin",
    "iso:country":"DE",
    "wof:name":"Hillesheim",
    "wof:placetype":"locality",
    "wof:population":588
},
  "geometry": {"coordinates":[8.25611,49.77639],"type":"Point"}
}