{
  "type": "Feature",
  "properties": {
    "gn:admin1_code":"2",
    "gn:admin2_code":"91.0",
    "gn:admin3_code":"9179.0",
    "gn:admin4_code":"9179134.0",
    "gn:asciiname":"Fussberg",
    "gn:country_code":"DE",
    "gn:dem":517,
    "gn:feature_class":"P",
    "gn:feature_code":"PPL",
    "gn:name":"Fu\u00dfberg",
    "gn:population":0,
    "gn:timezone":"Europe/Berlin",
    "iso:country":"DE",
    "wof:name":"Fussberg",
    "wof:placetype":"neighbourhood"
},
  "geometry": {"coordinates":[11.2891,48.2468],"type":"Point"}
}