{
  "type": "Feature",
  "properties": {
    "gn:admin1_code":"1",
    "gn:admin2_code":"81.0",
    "gn:admin3_code":"8111.0",
    "gn:admin4_code":"8111000.0",
    "gn:asciiname":"Rotenberg",
    "gn:country_code":"DE",
    "gn:dem":374,
    "gn:feature_class":"P",
    "gn:feature_code":"PPL",
    "gn:name":"Rotenberg",
    "gn:population":0,
    "gn:timezone":"Europe/Berlin",
    "iso:country":"DE",
    "name:deu_x_preferred":[
        "Rotenberg"
    ],
    "wof:name":"Rotenberg",
    "wof:placetype":"neighbourhood"
},
  "geometry": {"coordinates":[9.27179,48.78363],"type":"Point"}
}