{
  "type": "Feature",
  "properties": {
    "gn:country":"DE",
    "gn:fcode":"PPLA4",
    "gn:population":727,
    "iso:country":"DE",
    "name:ceb_x_preferred":[
        "Brodersby"
    ],
    "name:dan_x_preferred":[
        "Brodersby"
    ],
    "name:deu_x_preferred":[
        "Brodersby"
    ],
    "name:epo_x_preferred":[
        "Brodersby"
    ],
    "name:eus_x_preferred":[
        "Brodersby"
    ],
    "name:fra_x_preferred":[
        "Brodersby"
    ],
    "name:ita_x_preferred":[
        "Brodersby"
    ],
    "name:mkd_x_preferred":[
        "\u0411\u0440\u043e\u0434\u0435\u0440\u0441\u0431\u0438"
    ],
    "name:nld_x_preferred":[
        "Brodersby"
    ],
    "name:pol_x_preferred":[
        "Brodersby"
    ],
    "name:rus_x_preferred":[
        "\u0411\u0440\u043e\u0434\u0435\u0440\u0441\u0431\u0438"
    ],
    "name:sco_x_preferred":[
        "Brodersby"
    ],
    "name:srp_x_preferred":[
        "\u0411\u0440\u043e\u0434\u0435\u0440\u0441\u0431\u0438"
    ],
    "name:swe_x_preferred":[
        "Brodersby"
    ],
    "qs_pg:aaroncc":"DE",
    "qs_pg:gn_country":"DE",
    "qs_pg:gn_fcode":"PPLA4",
    "qs_pg:gn_pop":727,
    "qs_pg:name":"Brodersby",
    "qs_pg:photos_9r":0,
    "qs_pg:photos_sr":0,
    "qs_pg:pop_sr":2,
    "qs_pg:qs_pg_placetype":"locality",
    "wof:name":"Brodersby",
    "wof:placetype":"neighbourhood",
    "wof:population":727
},
  "geometry": {"coordinates":[9.71667,54.53333],"type":"Point"}
}