{
  "type": "Feature",
  "properties": {
    "gn:admin1_code":"7",
    "gn:admin2_code":"57.0",
    "gn:admin3_code":"5758.0",
    "gn:admin4_code":"5758008.0",
    "gn:asciiname":"Klausheide",
    "gn:country_code":"DE",
    "gn:dem":102,
    "gn:feature_class":"P",
    "gn:feature_code":"PPLL",
    "gn:name":"Klausheide",
    "gn:population":0,
    "gn:timezone":"Europe/Berlin",
    "iso:country":"DE",
    "wof:name":"Klausheide",
    "wof:placetype":"neighbourhood"
},
  "geometry": {"coordinates":[8.52108,52.14485],"type":"Point"}
}