{
  "type": "Feature",
  "properties": {
    "gn:admin1_code":"6",
    "gn:admin2_code":"0.0",
    "gn:admin3_code":"3256.0",
    "gn:admin4_code":"3256034.0",
    "gn:asciiname":"Morlinge",
    "gn:country_code":"DE",
    "gn:dem":51,
    "gn:feature_class":"P",
    "gn:feature_code":"PPL",
    "gn:name":"Morlinge",
    "gn:population":0,
    "gn:timezone":"Europe/Berlin",
    "iso:country":"DE",
    "name:und_x_variant":[
        "Morlingen",
        "Morlinge"
    ],
    "wof:name":"Morlinge",
    "wof:placetype":"neighbourhood"
},
  "geometry": {"coordinates":[8.89316,52.42271],"type":"Point"}
}