{
  "type": "Feature",
  "properties": {
    "gn:admin1_code":"6",
    "gn:admin2_code":"0.0",
    "gn:admin3_code":"3456.0",
    "gn:admin4_code":"3456019.0",
    "gn:asciiname":"Wagenholt",
    "gn:country_code":"DE",
    "gn:dem":17,
    "gn:feature_class":"P",
    "gn:feature_code":"PPLL",
    "gn:name":"Wagenholt",
    "gn:population":0,
    "gn:timezone":"Europe/Berlin",
    "iso:country":"DE",
    "wof:name":"Wagenholt",
    "wof:placetype":"neighbourhood"
},
  "geometry": {"coordinates":[6.94243,52.59435],"type":"Point"}
}