{
  "type": "Feature",
  "properties": {
    "gn:admin1_code":"2",
    "gn:admin2_code":"93.0",
    "gn:admin3_code":"9371.0",
    "gn:admin4_code":"9371129.0",
    "gn:asciiname":"Friebertsheim",
    "gn:country_code":"DE",
    "gn:dem":466,
    "gn:feature_class":"P",
    "gn:feature_code":"PPL",
    "gn:name":"Friebertsheim",
    "gn:population":0,
    "gn:timezone":"Europe/Berlin",
    "iso:country":"DE",
    "wof:name":"Friebertsheim",
    "wof:placetype":"neighbourhood"
},
  "geometry": {"coordinates":[11.84947,49.31644],"type":"Point"}
}