{
  "type": "Feature",
  "properties": {
    "gn:admin1_code":"2",
    "gn:admin2_code":"91.0",
    "gn:admin3_code":"9173.0",
    "gn:admin4_code":"9173120.0",
    "gn:asciiname":"Neufahrn",
    "gn:country_code":"DE",
    "gn:dem":665,
    "gn:feature_class":"P",
    "gn:feature_code":"PPL",
    "gn:name":"Neufahrn",
    "gn:population":0,
    "gn:timezone":"Europe/Berlin",
    "iso:country":"DE",
    "name:ceb_x_preferred":[
        "Neufahrn"
    ],
    "name:deu_x_preferred":[
        "Neufahrn"
    ],
    "name:epo_x_preferred":[
        "Neufahrn"
    ],
    "name:fra_x_preferred":[
        "Neufahrn"
    ],
    "name:nld_x_preferred":[
        "Neufahrn"
    ],
    "name:pol_x_preferred":[
        "Neufahrn"
    ],
    "name:swe_x_preferred":[
        "Neufahrn"
    ],
    "wof:name":"Neufahrn",
    "wof:placetype":"neighbourhood"
},
  "geometry": {"coordinates":[11.4808,47.91513],"type":"Point"}
}