{
  "type": "Feature",
  "properties": {
    "gn:admin1_code":"13",
    "gn:admin2_code":"0.0",
    "gn:admin3_code":"14729.0",
    "gn:admin4_code":"14729430.0",
    "gn:asciiname":"Grossdalzig",
    "gn:country_code":"DE",
    "gn:dem":125,
    "gn:feature_class":"P",
    "gn:feature_code":"PPL",
    "gn:name":"Gro\u00dfdalzig",
    "gn:population":0,
    "gn:timezone":"Europe/Berlin",
    "iso:country":"DE",
    "wof:name":"Grossdalzig",
    "wof:placetype":"neighbourhood"
},
  "geometry": {"coordinates":[12.27314,51.20661],"type":"Point"}
}