{
  "type": "Feature",
  "properties": {
    "iso:country":"DE",
    "name:deu_x_preferred":[
        "Elmsb\u00fcttel"
    ],
    "wof:name":"Elmsbuettel",
    "wof:placetype":"neighbourhood"
},
  "geometry": {"coordinates":[9.92988065068326,53.60877503224963],"type":"Point"}
}