{
  "type": "Feature",
  "properties": {
    "iso:country":"DE",
    "name:deu_x_preferred":[
        "Eimsb\u00fcttel"
    ],
    "name:deu_x_variant":[
        "Elmsb\u00fcttel"
    ],
    "name:eng_x_preferred":[
        "Eimsbuttel"
    ],
    "name:eng_x_variant":[
        "Elmsbuettel"
    ],
    "wof:name":"Eimsbuttel",
    "wof:placetype":"neighbourhood"
},
  "geometry": {"coordinates":[9.929881,53.608775],"type":"Point"}
}