{
  "type": "Feature",
  "properties": {
    "gn:admin1_code":"2",
    "gn:admin2_code":"92.0",
    "gn:admin3_code":"9275.0",
    "gn:admin4_code":"9275141.0",
    "gn:asciiname":"Gstetten",
    "gn:cc2":"DE",
    "gn:country_code":"DE",
    "gn:dem":317,
    "gn:feature_class":"P",
    "gn:feature_code":"PPL",
    "gn:name":"Gstetten",
    "gn:population":0,
    "gn:timezone":"Europe/Berlin",
    "iso:country":"DE",
    "name:und_x_variant":[
        "Gst\u00f6tten",
        "Gstetten"
    ],
    "wof:name":"Gstetten",
    "wof:placetype":"neighbourhood"
},
  "geometry": {"coordinates":[13.32178,48.41792],"type":"Point"}
}