{
  "type": "Feature",
  "properties": {
    "gn:admin1_code":"1",
    "gn:admin2_code":"83.0",
    "gn:admin3_code":"8317.0",
    "gn:admin4_code":"8317011.0",
    "gn:asciiname":"Erzbach",
    "gn:country_code":"DE",
    "gn:dem":249,
    "gn:feature_class":"P",
    "gn:feature_code":"PPLL",
    "gn:name":"Erzbach",
    "gn:population":0,
    "gn:timezone":"Europe/Berlin",
    "iso:country":"DE",
    "wof:name":"Erzbach",
    "wof:placetype":"neighbourhood"
},
  "geometry": {"coordinates":[8.00573,48.34448],"type":"Point"}
}