{
  "type": "Feature",
  "properties": {
    "gn:admin1_code":"12.0",
    "gn:admin2_code":"0.0",
    "gn:admin3_code":"13073.0",
    "gn:admin4_code":"13073055.0",
    "gn:asciiname":"Kneese Ausbau",
    "gn:country_code":"DE",
    "gn:dem":31,
    "gn:feature_class":"P",
    "gn:feature_code":"PPL",
    "gn:name":"Kneese Ausbau",
    "gn:population":0,
    "gn:timezone":"Europe/Berlin",
    "iso:country":"DE",
    "wof:name":"Kneese Ausbau",
    "wof:placetype":"neighbourhood"
},
  "geometry": {"coordinates":[12.57767,54.11301],"type":"Point"}
}