{
  "type": "Feature",
  "properties": {
    "gn:admin1_code":"7",
    "gn:admin2_code":"55.0",
    "gn:admin3_code":"5558.0",
    "gn:admin4_code":"5558024.0",
    "gn:asciiname":"Emkum",
    "gn:country_code":"DE",
    "gn:dem":63,
    "gn:feature_class":"P",
    "gn:feature_code":"PPLL",
    "gn:name":"Emkum",
    "gn:population":0,
    "gn:timezone":"Europe/Berlin",
    "iso:country":"DE",
    "name:osx_x_preferred":[
        "Emmingh\u00eam"
    ],
    "wof:name":"Emkum",
    "wof:placetype":"neighbourhood"
},
  "geometry": {"coordinates":[7.34264,51.75116],"type":"Point"}
}