{
  "type": "Feature",
  "properties": {
    "gn:admin1_code":"2",
    "gn:admin2_code":"92.0",
    "gn:admin3_code":"9275.0",
    "gn:admin4_code":"9275126.0",
    "gn:asciiname":"Redling",
    "gn:country_code":"DE",
    "gn:dem":426,
    "gn:feature_class":"P",
    "gn:feature_code":"PPL",
    "gn:name":"Redling",
    "gn:population":0,
    "gn:timezone":"Europe/Berlin",
    "iso:country":"DE",
    "wof:name":"Redling",
    "wof:placetype":"neighbourhood"
},
  "geometry": {"coordinates":[13.58333,48.63333],"type":"Point"}
}