{
  "type": "Feature",
  "properties": {
    "gn:admin1_code":"2.0",
    "gn:admin2_code":"93.0",
    "gn:admin3_code":"9377.0",
    "gn:admin4_code":"9377129.0",
    "gn:asciiname":"Berndorf",
    "gn:country_code":"DE",
    "gn:dem":474,
    "gn:feature_class":"P",
    "gn:feature_code":"PPL",
    "gn:name":"Berndorf",
    "gn:population":0,
    "gn:timezone":"Europe/Berlin",
    "iso:country":"DE",
    "name:ceb_x_preferred":[
        "Berndorf"
    ],
    "name:deu_x_preferred":[
        "Berndorf"
    ],
    "name:fra_x_preferred":[
        "Berndorf"
    ],
    "name:ita_x_preferred":[
        "Berndorf"
    ],
    "name:nld_x_preferred":[
        "Berndorf"
    ],
    "name:pol_x_preferred":[
        "Berndorf"
    ],
    "name:swe_x_preferred":[
        "Berndorf"
    ],
    "name:vol_x_preferred":[
        "Berndorf"
    ],
    "name:zho_x_preferred":[
        "\u8d1d\u6069\u591a\u592b"
    ],
    "wof:name":"Berndorf",
    "wof:placetype":"neighbourhood"
},
  "geometry": {"coordinates":[11.87262,49.88015],"type":"Point"}
}