{
  "type": "Feature",
  "properties": {
    "gn:admin1_code":"2",
    "gn:admin2_code":"96.0",
    "gn:admin3_code":"9678.0",
    "gn:admin4_code":"9678168.0",
    "gn:asciiname":"Maibach",
    "gn:country_code":"DE",
    "gn:dem":275,
    "gn:feature_class":"P",
    "gn:feature_code":"PPL",
    "gn:name":"Maibach",
    "gn:population":0,
    "gn:timezone":"Europe/Berlin",
    "iso:country":"DE",
    "name:deu_x_preferred":[
        "Maibach"
    ],
    "wof:name":"Maibach",
    "wof:placetype":"neighbourhood"
},
  "geometry": {"coordinates":[10.17454,50.09515],"type":"Point"}
}