{
  "type": "Feature",
  "properties": {
    "gn:admin1_code":"2.0",
    "gn:admin2_code":"094",
    "gn:admin3_code":"9475.0",
    "gn:admin4_code":"9475182.0",
    "gn:asciiname":"Ziegelhutten",
    "gn:country_code":"DE",
    "gn:dem":519,
    "gn:feature_class":"P",
    "gn:feature_code":"PPL",
    "gn:name":"Ziegelh\u00fctten",
    "gn:population":0,
    "gn:timezone":"Europe/Berlin",
    "iso:country":"DE",
    "wof:name":"Ziegelhutten",
    "wof:placetype":"neighbourhood"
},
  "geometry": {"coordinates":[11.9693,50.37426],"type":"Point"}
}