{
  "type": "Feature",
  "properties": {
    "gn:admin1_code":"5",
    "gn:admin2_code":"66.0",
    "gn:admin3_code":"6633.0",
    "gn:admin4_code":"6633029.0",
    "gn:asciiname":"Oelshausen",
    "gn:country_code":"DE",
    "gn:dem":339,
    "gn:feature_class":"P",
    "gn:feature_code":"PPL",
    "gn:name":"Oelshausen",
    "gn:population":0,
    "gn:timezone":"Europe/Berlin",
    "iso:country":"DE",
    "wof:name":"Oelshausen",
    "wof:placetype":"neighbourhood"
},
  "geometry": {"coordinates":[9.26285,51.31355],"type":"Point"}
}