{
  "type": "Feature",
  "properties": {
    "gn:admin1_code":"14",
    "gn:admin2_code":"0.0",
    "gn:admin3_code":"15084.0",
    "gn:admin4_code":"15084590.0",
    "gn:asciiname":"Gaumnitz",
    "gn:country_code":"DE",
    "gn:dem":172,
    "gn:feature_class":"P",
    "gn:feature_code":"PPL",
    "gn:name":"Gaumnitz",
    "gn:population":0,
    "gn:timezone":"Europe/Berlin",
    "iso:country":"DE",
    "wof:name":"Gaumnitz",
    "wof:placetype":"neighbourhood"
},
  "geometry": {"coordinates":[12.06667,51.08333],"type":"Point"}
}