{
  "type": "Feature",
  "properties": {
    "gn:admin1_code":"8",
    "gn:admin2_code":"0.0",
    "gn:admin3_code":"7232.0",
    "gn:admin4_code":"7232231.0",
    "gn:asciiname":"Niederhabscheid",
    "gn:country_code":"DE",
    "gn:dem":474,
    "gn:feature_class":"P",
    "gn:feature_code":"PPL",
    "gn:name":"Niederhabscheid",
    "gn:population":0,
    "gn:timezone":"Europe/Berlin",
    "iso:country":"DE",
    "wof:name":"Niederhabscheid",
    "wof:placetype":"neighbourhood"
},
  "geometry": {"coordinates":[6.2658,50.19202],"type":"Point"}
}