{
  "type": "Feature",
  "properties": {
    "gn:admin1_code":"1",
    "gn:admin2_code":"83.0",
    "gn:admin3_code":"8317.0",
    "gn:admin4_code":"8317093.0",
    "gn:asciiname":"Schrannen",
    "gn:country_code":"DE",
    "gn:dem":302,
    "gn:feature_class":"P",
    "gn:feature_code":"PPLL",
    "gn:name":"Schrannen",
    "gn:population":0,
    "gn:timezone":"Europe/Berlin",
    "iso:country":"DE",
    "wof:name":"Schrannen",
    "wof:placetype":"neighbourhood"
},
  "geometry": {"coordinates":[8.21518,48.32632],"type":"Point"}
}