{
  "type": "Feature",
  "properties": {
    "gn:admin1_code":"2",
    "gn:admin2_code":"97.0",
    "gn:admin3_code":"9779.0",
    "gn:admin4_code":"9779231.0",
    "gn:asciiname":"Hagau",
    "gn:country_code":"DE",
    "gn:dem":542,
    "gn:feature_class":"P",
    "gn:feature_code":"PPL",
    "gn:name":"Hagau",
    "gn:population":0,
    "gn:timezone":"Europe/Berlin",
    "iso:country":"DE",
    "wof:name":"Hagau",
    "wof:placetype":"neighbourhood"
},
  "geometry": {"coordinates":[10.74502,48.91338],"type":"Point"}
}