{
  "type": "Feature",
  "properties": {
    "gn:admin1_code":"2",
    "gn:admin2_code":"96.0",
    "gn:admin3_code":"9675.0",
    "gn:admin4_code":"9675167.0",
    "gn:asciiname":"Wasserndorf",
    "gn:country_code":"DE",
    "gn:dem":258,
    "gn:feature_class":"P",
    "gn:feature_code":"PPL",
    "gn:name":"W\u00e4sserndorf",
    "gn:population":0,
    "gn:timezone":"Europe/Berlin",
    "iso:country":"DE",
    "wof:name":"Wasserndorf",
    "wof:placetype":"neighbourhood"
},
  "geometry": {"coordinates":[10.20372,49.63918],"type":"Point"}
}