{
  "type": "Feature",
  "properties": {
    "gn:admin1_code":"2",
    "gn:admin2_code":"92.0",
    "gn:admin3_code":"9277.0",
    "gn:admin4_code":"9277118.0",
    "gn:asciiname":"Pettenau",
    "gn:country_code":"DE",
    "gn:dem":364,
    "gn:feature_class":"P",
    "gn:feature_code":"PPL",
    "gn:name":"Pettenau",
    "gn:population":0,
    "gn:timezone":"Europe/Berlin",
    "iso:country":"DE",
    "wof:name":"Pettenau",
    "wof:placetype":"neighbourhood"
},
  "geometry": {"coordinates":[13.10592,48.29736],"type":"Point"}
}