{
  "type": "Feature",
  "properties": {
    "gn:admin1_code":"10",
    "gn:admin2_code":"0.0",
    "gn:admin3_code":"1055.0",
    "gn:admin4_code":"1055001.0",
    "gn:asciiname":"Havekost",
    "gn:country_code":"DE",
    "gn:dem":48,
    "gn:feature_class":"P",
    "gn:feature_code":"PPL",
    "gn:name":"Havekost",
    "gn:population":0,
    "gn:timezone":"Europe/Berlin",
    "iso:country":"DE",
    "name:ceb_x_preferred":[
        "Havekost"
    ],
    "name:dan_x_preferred":[
        "Havekost"
    ],
    "name:deu_x_preferred":[
        "Havekost"
    ],
    "name:epo_x_preferred":[
        "Havekost"
    ],
    "name:eus_x_preferred":[
        "Havekost"
    ],
    "name:fas_x_preferred":[
        "\u0647\u0627\u0641\u06a9\u0648\u0634\u062a"
    ],
    "name:fra_x_preferred":[
        "Havekost"
    ],
    "name:hun_x_preferred":[
        "Havekost"
    ],
    "name:ita_x_preferred":[
        "Havekost"
    ],
    "name:mkd_x_preferred":[
        "\u0425\u0430\u0444\u0435\u043a\u043e\u0441\u0442"
    ],
    "name:msa_x_preferred":[
        "Havekost"
    ],
    "name:nld_x_preferred":[
        "Havekost"
    ],
    "name:pol_x_preferred":[
        "Havekost"
    ],
    "name:por_x_preferred":[
        "Havekost"
    ],
    "name:ron_x_preferred":[
        "Havekost"
    ],
    "name:rus_x_preferred":[
        "\u0425\u0430\u0432\u0435\u043a\u043e\u0441\u0442"
    ],
    "name:spa_x_preferred":[
        "Havekost"
    ],
    "name:srp_x_preferred":[
        "\u0425\u0430\u0432\u0435\u043a\u043e\u0441\u0442"
    ],
    "name:tur_x_preferred":[
        "Havekost"
    ],
    "name:ukr_x_preferred":[
        "\u0413\u0430\u0444\u0435\u043a\u043e\u0441\u0442"
    ],
    "name:uzb_x_preferred":[
        "Havekost"
    ],
    "name:vie_x_preferred":[
        "Havekost"
    ],
    "name:vol_x_preferred":[
        "Havekost"
    ],
    "name:war_x_preferred":[
        "Havekost"
    ],
    "name:zho_x_preferred":[
        "\u54c8\u8d39\u79d1\u65af\u7279"
    ],
    "wof:name":"Havekost",
    "wof:placetype":"neighbourhood"
},
  "geometry": {"coordinates":[10.62089,54.018],"type":"Point"}
}