{
  "type": "Feature",
  "properties": {
    "gn:admin1_code":"1",
    "gn:admin2_code":"81.0",
    "gn:admin3_code":"8126.0",
    "gn:admin4_code":"8126011.0",
    "gn:asciiname":"Hohenacker",
    "gn:country_code":"DE",
    "gn:dem":293,
    "gn:feature_class":"P",
    "gn:feature_code":"PPL",
    "gn:name":"Hohenacker",
    "gn:population":0,
    "gn:timezone":"Europe/Berlin",
    "iso:country":"DE",
    "name:deu_x_preferred":[
        "Hohenacker"
    ],
    "wof:name":"Hohenacker",
    "wof:placetype":"neighbourhood"
},
  "geometry": {"coordinates":[9.44949,49.14381],"type":"Point"}
}