{
  "type": "Feature",
  "properties": {
    "gn:admin1_code":"2.0",
    "gn:admin2_code":"092",
    "gn:admin3_code":"9271.0",
    "gn:admin4_code":"9271151.0",
    "gn:asciiname":"Wolferskofen",
    "gn:country_code":"DE",
    "gn:dem":316,
    "gn:feature_class":"P",
    "gn:feature_code":"PPL",
    "gn:name":"Wolferskofen",
    "gn:population":0,
    "gn:timezone":"Europe/Berlin",
    "iso:country":"DE",
    "wof:name":"Wolferskofen",
    "wof:placetype":"neighbourhood"
},
  "geometry": {"coordinates":[12.78387,48.82734],"type":"Point"}
}