{
  "type": "Feature",
  "properties": {
    "gn:admin1_code":"7",
    "gn:admin2_code":"57.0",
    "gn:admin3_code":"5758.0",
    "gn:admin4_code":"5758012.0",
    "gn:asciiname":"Egge",
    "gn:country_code":"DE",
    "gn:dem":224,
    "gn:feature_class":"P",
    "gn:feature_code":"PPLL",
    "gn:name":"Egge",
    "gn:population":0,
    "gn:timezone":"Europe/Berlin",
    "iso:country":"DE",
    "name:ceb_x_preferred":[
        "Egge"
    ],
    "name:deu_x_preferred":[
        "Egge"
    ],
    "name:jpn_x_preferred":[
        "\u30a8\u30c3\u30b2"
    ],
    "name:nor_x_preferred":[
        "Egge"
    ],
    "wof:name":"Egge",
    "wof:placetype":"neighbourhood"
},
  "geometry": {"coordinates":[8.72481,52.1465],"type":"Point"}
}