{
  "type": "Feature",
  "properties": {
    "gn:admin1_code":"2.0",
    "gn:admin2_code":"92.0",
    "gn:admin3_code":"9276.0",
    "gn:admin4_code":"9276120.0",
    "gn:asciiname":"Blachendorf",
    "gn:country_code":"DE",
    "gn:dem":617,
    "gn:feature_class":"P",
    "gn:feature_code":"PPL",
    "gn:name":"Blachendorf",
    "gn:population":0,
    "gn:timezone":"Europe/Berlin",
    "iso:country":"DE",
    "wof:name":"Blachendorf",
    "wof:placetype":"neighbourhood"
},
  "geometry": {"coordinates":[13.02584,49.10703],"type":"Point"}
}