{
  "type": "Feature",
  "properties": {
    "gn:admin1_code":"6",
    "gn:admin2_code":"0.0",
    "gn:admin3_code":"3157.0",
    "gn:admin4_code":"3157008.0",
    "gn:asciiname":"Meerdorf",
    "gn:country_code":"DE",
    "gn:dem":72,
    "gn:feature_class":"P",
    "gn:feature_code":"PPL",
    "gn:name":"Meerdorf",
    "gn:population":1140,
    "gn:timezone":"Europe/Berlin",
    "iso:country":"DE",
    "name:nds_x_preferred":[
        "M\u00e4rd\u00f6rp"
    ],
    "name:nds_x_variant":[
        "Meerdorp"
    ],
    "wof:name":"Meerdorf",
    "wof:placetype":"neighbourhood",
    "wof:population":1140
},
  "geometry": {"coordinates":[10.31745,52.34583],"type":"Point"}
}