{
  "type": "Feature",
  "properties": {
    "gn:admin1_code":"2",
    "gn:admin2_code":"97.0",
    "gn:admin3_code":"9779.0",
    "gn:admin4_code":"9779112.0",
    "gn:asciiname":"Seelbronn",
    "gn:country_code":"DE",
    "gn:dem":523,
    "gn:feature_class":"P",
    "gn:feature_code":"PPL",
    "gn:name":"Seelbronn",
    "gn:population":0,
    "gn:timezone":"Europe/Berlin",
    "iso:country":"DE",
    "wof:name":"Seelbronn",
    "wof:placetype":"neighbourhood"
},
  "geometry": {"coordinates":[10.465,48.73264],"type":"Point"}
}