{
  "type": "Feature",
  "properties": {
    "gn:admin1_code":"2",
    "gn:admin2_code":"97.0",
    "gn:admin3_code":"9780.0",
    "gn:admin4_code":"9780132.0",
    "gn:asciiname":"Laufenegg",
    "gn:country_code":"DE",
    "gn:dem":873,
    "gn:feature_class":"P",
    "gn:feature_code":"PPL",
    "gn:name":"Laufenegg",
    "gn:population":0,
    "gn:timezone":"Europe/Berlin",
    "iso:country":"DE",
    "wof:name":"Laufenegg",
    "wof:placetype":"neighbourhood"
},
  "geometry": {"coordinates":[9.98969,47.54974],"type":"Point"}
}