{
  "type": "Feature",
  "properties": {
    "gn:country":"DE",
    "gn:fcode":"PPLA4",
    "gn:population":238,
    "iso:country":"DE",
    "name:ceb_x_preferred":[
        "Saalburg"
    ],
    "name:deu_x_preferred":[
        "Kastell Saalburg"
    ],
    "name:ell_x_preferred":[
        "\u0396\u03ac\u03b1\u03bb\u03bc\u03c0\u03bf\u03c5\u03c1\u03ba"
    ],
    "name:epo_x_preferred":[
        "Saalburg"
    ],
    "name:fra_x_preferred":[
        "Saalburg"
    ],
    "name:ita_x_preferred":[
        "Saalburg"
    ],
    "name:lat_x_preferred":[
        "Castellum Saalaburgense"
    ],
    "name:spa_x_preferred":[
        "Saalburg"
    ],
    "qs_pg:aaroncc":"DE",
    "qs_pg:gn_country":"DE",
    "qs_pg:gn_fcode":"PPLA4",
    "qs_pg:gn_pop":238,
    "qs_pg:name":"Saalburg",
    "qs_pg:name_adm0":"Deutschland",
    "qs_pg:name_adm1":"Hessen",
    "qs_pg:photos_9k":1,
    "qs_pg:photos_9r":2,
    "qs_pg:photos_all":40,
    "qs_pg:photos_sr":0,
    "qs_pg:pop_sr":2,
    "qs_pg:qs_pg_placetype":"locality",
    "qs_pg:qs_pg_placetype_gp":"Town",
    "qs_pg:woe_adm0":23424829,
    "woe:adm0_id":23424829,
    "woe:name_adm0":"Deutschland",
    "woe:name_adm1":"Hessen",
    "woe:placetype":"Town",
    "wof:name":"Saalburg",
    "wof:placetype":"neighbourhood",
    "wof:population":238
},
  "geometry": {"coordinates":[8.05,50.66667],"type":"Point"}
}