{
  "type": "Feature",
  "properties": {
    "gn:admin1_code":"10.0",
    "gn:admin2_code":"00",
    "gn:admin3_code":"1002.0",
    "gn:admin4_code":"1002000.0",
    "gn:asciiname":"Wellsee",
    "gn:country_code":"DE",
    "gn:dem":44,
    "gn:feature_class":"P",
    "gn:feature_code":"PPL",
    "gn:name":"Wellsee",
    "gn:population":0,
    "gn:timezone":"Europe/Berlin",
    "iso:country":"DE",
    "wof:name":"Wellsee",
    "wof:placetype":"neighbourhood"
},
  "geometry": {"coordinates":[10.16579,54.28983],"type":"Point"}
}