{
  "type": "Feature",
  "properties": {
    "gn:admin1_code":"7",
    "gn:admin2_code":"53.0",
    "gn:admin3_code":"5370.0",
    "gn:admin4_code":"5370040.0",
    "gn:asciiname":"Watern",
    "gn:country_code":"DE",
    "gn:dem":71,
    "gn:feature_class":"P",
    "gn:feature_code":"PPL",
    "gn:name":"Watern",
    "gn:population":0,
    "gn:timezone":"Europe/Berlin",
    "iso:country":"DE",
    "wof:name":"Watern",
    "wof:placetype":"neighbourhood"
},
  "geometry": {"coordinates":[6.26653,51.12928],"type":"Point"}
}