{
  "type": "Feature",
  "properties": {
    "gn:admin1_code":"7",
    "gn:admin2_code":"53.0",
    "gn:admin3_code":"5366.0",
    "gn:admin4_code":"5366032.0",
    "gn:asciiname":"Engelgau",
    "gn:country_code":"DE",
    "gn:dem":520,
    "gn:feature_class":"P",
    "gn:feature_code":"PPL",
    "gn:name":"Engelgau",
    "gn:population":0,
    "gn:timezone":"Europe/Berlin",
    "iso:country":"DE",
    "wof:name":"Engelgau",
    "wof:placetype":"neighbourhood"
},
  "geometry": {"coordinates":[6.67742,50.49487],"type":"Point"}
}