{
  "type": "Feature",
  "properties": {
    "gn:admin1_code":"2",
    "gn:admin2_code":"91.0",
    "gn:admin3_code":"9175.0",
    "gn:admin4_code":"9175112.0",
    "gn:asciiname":"Obereichhofen",
    "gn:country_code":"DE",
    "gn:dem":561,
    "gn:feature_class":"P",
    "gn:feature_code":"PPL",
    "gn:name":"Obereichhofen",
    "gn:population":0,
    "gn:timezone":"Europe/Berlin",
    "iso:country":"DE",
    "wof:name":"Obereichhofen",
    "wof:placetype":"neighbourhood"
},
  "geometry": {"coordinates":[11.95467,48.00399],"type":"Point"}
}