{
  "type": "Feature",
  "properties": {
    "gn:admin1_code":"6",
    "gn:admin2_code":"0.0",
    "gn:admin3_code":"3459.0",
    "gn:admin4_code":"3459007.0",
    "gn:asciiname":"Fresenbrink",
    "gn:country_code":"DE",
    "gn:dem":27,
    "gn:feature_class":"P",
    "gn:feature_code":"PPL",
    "gn:name":"Fresenbrink",
    "gn:population":0,
    "gn:timezone":"Europe/Berlin",
    "iso:country":"DE",
    "wof:name":"Fresenbrink",
    "wof:placetype":"neighbourhood"
},
  "geometry": {"coordinates":[8.02377,52.64451],"type":"Point"}
}