{
  "type": "Feature",
  "properties": {
    "gn:admin1_code":"10",
    "gn:admin2_code":"0.0",
    "gn:admin3_code":"1058.0",
    "gn:admin4_code":"1058089.0",
    "gn:asciiname":"Konigshugel",
    "gn:country_code":"DE",
    "gn:dem":-1,
    "gn:feature_class":"P",
    "gn:feature_code":"PPLA4",
    "gn:name":"K\u00f6nigsh\u00fcgel",
    "gn:population":0,
    "gn:timezone":"Europe/Berlin",
    "iso:country":"DE",
    "name:und_x_variant":[
        "K\u00f6nigsh\u00fcgel"
    ],
    "wof:name":"Konigshugel",
    "wof:placetype":"neighbourhood"
},
  "geometry": {"coordinates":[9.46667,54.33333],"type":"Point"}
}