{
  "type": "Feature",
  "properties": {
    "gn:admin1_code":"15",
    "gn:admin2_code":"0.0",
    "gn:admin3_code":"16066.0",
    "gn:admin4_code":"16066075.0",
    "gn:asciiname":"Doerrensolz",
    "gn:country_code":"DE",
    "gn:dem":470,
    "gn:feature_class":"P",
    "gn:feature_code":"PPL",
    "gn:name":"D\u00f6rrensolz",
    "gn:population":0,
    "gn:timezone":"Europe/Berlin",
    "iso:country":"DE",
    "wof:name":"Doerrensolz",
    "wof:placetype":"neighbourhood"
},
  "geometry": {"coordinates":[10.25549,50.6052],"type":"Point"}
}