{
  "type": "Feature",
  "properties": {
    "gn:admin1_code":"1.0",
    "gn:admin2_code":"84.0",
    "gn:admin3_code":"8416.0",
    "gn:admin4_code":"8416048.0",
    "gn:asciiname":"Breitenholz",
    "gn:country_code":"DE",
    "gn:dem":414,
    "gn:feature_class":"P",
    "gn:feature_code":"PPL",
    "gn:name":"Breitenholz",
    "gn:population":0,
    "gn:timezone":"Europe/Berlin",
    "iso:country":"DE",
    "wof:name":"Breitenholz",
    "wof:placetype":"neighbourhood"
},
  "geometry": {"coordinates":[8.95823,48.57047],"type":"Point"}
}