{
  "type": "Feature",
  "properties": {
    "gn:admin1_code":"2.0",
    "gn:admin2_code":"91.0",
    "gn:admin3_code":"9177.0",
    "gn:admin4_code":"9177137.0",
    "gn:asciiname":"Bennoberg",
    "gn:country_code":"DE",
    "gn:dem":485,
    "gn:feature_class":"P",
    "gn:feature_code":"PPL",
    "gn:name":"Bennoberg",
    "gn:population":0,
    "gn:timezone":"Europe/Berlin",
    "iso:country":"DE",
    "name:und_x_variant":[
        "Benoberg",
        "Bennoberg"
    ],
    "wof:name":"Bennoberg",
    "wof:placetype":"neighbourhood"
},
  "geometry": {"coordinates":[12.16216,48.24998],"type":"Point"}
}