{
  "type": "Feature",
  "properties": {
    "iso:country":"DE",
    "name:deu_x_preferred":[
        "Kirchhuchting"
    ],
    "qs:gn_adm0_cc":"DE",
    "qs:gn_fcode":"PPL",
    "qs:gn_local":2944388,
    "qs:gn_namadm1":"03",
    "qs:gn_name":"Kirchhuchting",
    "qs:local_max":10591,
    "qs:local_sum":29027,
    "qs:localhoods":40,
    "qs:name":"Kirchhuchting",
    "qs:name_adm0":"Deutschland",
    "qs:name_adm1":"Freie Hansestadt Bremen",
    "qs:name_adm2":"Stadtkreis Bremen",
    "qs:name_lau":"Stadtteil Huchting",
    "qs:name_local":"Bremen",
    "qs:photo_max":19,
    "qs:photo_sum":72,
    "qs:placetype":"Suburb",
    "qs:quad_count":18,
    "qs:woe_adm0":23424829,
    "qs:woe_adm1":2345483,
    "qs:woe_adm2":12597033,
    "qs:woe_lau":26822050,
    "qs:woe_local":641142,
    "qs:woe_ver":"7.10.0",
    "wof:lang":[
        "ger"
    ],
    "wof:name":"Kirchhuchting",
    "wof:placetype":"neighbourhood"
},
  "geometry": {"coordinates":[8.746033,53.0458],"type":"Point"}
}