{
  "type": "Feature",
  "properties": {
    "gn:admin1_code":"2.0",
    "gn:admin2_code":"91.0",
    "gn:admin3_code":"9176.0",
    "gn:admin4_code":"9176148.0",
    "gn:asciiname":"Apfelthal",
    "gn:country_code":"DE",
    "gn:dem":539,
    "gn:feature_class":"P",
    "gn:feature_code":"PPL",
    "gn:name":"Apfelthal",
    "gn:population":0,
    "gn:timezone":"Europe/Berlin",
    "iso:country":"DE",
    "wof:name":"Apfelthal",
    "wof:placetype":"neighbourhood"
},
  "geometry": {"coordinates":[10.97448,48.87376],"type":"Point"}
}