{
  "type": "Feature",
  "properties": {
    "gn:admin1_code":"1",
    "gn:admin2_code":"83.0",
    "gn:admin3_code":"8326.0",
    "gn:admin4_code":"8326074.0",
    "gn:asciiname":"Tannheim",
    "gn:country_code":"DE",
    "gn:dem":749,
    "gn:feature_class":"P",
    "gn:feature_code":"PPL",
    "gn:name":"Tannheim",
    "gn:population":0,
    "gn:timezone":"Europe/Berlin",
    "iso:country":"DE",
    "wof:name":"Tannheim",
    "wof:placetype":"neighbourhood"
},
  "geometry": {"coordinates":[8.41193,48.00334],"type":"Point"}
}