{
  "type": "Feature",
  "properties": {
    "gn:admin1_code":"1",
    "gn:admin2_code":"83.0",
    "gn:admin3_code":"8326.0",
    "gn:admin4_code":"8326074.0",
    "gn:asciiname":"Tannheim",
    "gn:country_code":"DE",
    "gn:dem":749,
    "gn:feature_class":"P",
    "gn:feature_code":"PPL",
    "gn:name":"Tannheim",
    "gn:population":0,
    "gn:timezone":"Europe/Berlin",
    "iso:country":"DE",
    "name:als_x_preferred":[
        "Tannheim"
    ],
    "name:deu_x_preferred":[
        "Tannheim"
    ],
    "name:epo_x_preferred":[
        "Tannheim"
    ],
    "name:eus_x_preferred":[
        "Tannheim"
    ],
    "name:fas_x_preferred":[
        "\u062a\u0627\u0646\u0647\u0627\u06cc\u0645"
    ],
    "name:fra_x_preferred":[
        "Tannheim"
    ],
    "name:hun_x_preferred":[
        "Tannheim"
    ],
    "name:hye_x_preferred":[
        "\u054f\u0561\u0576\u0570\u0561\u0575\u0574"
    ],
    "name:ita_x_preferred":[
        "Tannheim"
    ],
    "name:kat_x_preferred":[
        "\u10e2\u10d0\u10dc\u10f0\u10d0\u10d8\u10db\u10d8"
    ],
    "name:kaz_x_preferred":[
        "\u0422\u0430\u043d\u0445\u0430\u0439\u043c"
    ],
    "name:kir_x_preferred":[
        "\u0422\u0430\u043d\u0445\u0430\u0439\u043c"
    ],
    "name:lat_x_preferred":[
        "Tannheim"
    ],
    "name:lmo_x_preferred":[
        "Tannheim"
    ],
    "name:msa_x_preferred":[
        "Tannheim"
    ],
    "name:nld_x_preferred":[
        "Tannheim"
    ],
    "name:pol_x_preferred":[
        "Tannheim"
    ],
    "name:por_x_preferred":[
        "Tannheim"
    ],
    "name:ron_x_preferred":[
        "Tannheim"
    ],
    "name:rus_x_preferred":[
        "\u0422\u0430\u043d\u0445\u0430\u0439\u043c"
    ],
    "name:spa_x_preferred":[
        "Tannheim"
    ],
    "name:srp_x_preferred":[
        "\u0422\u0430\u043d\u0445\u0430\u0458\u043c"
    ],
    "name:ukr_x_preferred":[
        "\u0422\u0430\u043d\u043d\u0433\u0430\u0439\u043c"
    ],
    "name:uzb_x_preferred":[
        "Tannheim"
    ],
    "name:vie_x_preferred":[
        "Tannheim"
    ],
    "name:vol_x_preferred":[
        "Tannheim"
    ],
    "name:war_x_preferred":[
        "Tannheim"
    ],
    "name:zho_x_preferred":[
        "\u5766\u6d77\u59c6"
    ],
    "wof:name":"Tannheim",
    "wof:placetype":"neighbourhood"
},
  "geometry": {"coordinates":[8.41193,48.00334],"type":"Point"}
}