{
  "type": "Feature",
  "properties": {
    "gn:admin1_code":"13",
    "gn:admin2_code":"0.0",
    "gn:admin3_code":"14626.0",
    "gn:admin4_code":"14626410.0",
    "gn:asciiname":"Picka",
    "gn:country_code":"DE",
    "gn:dem":387,
    "gn:feature_class":"P",
    "gn:feature_code":"PPL",
    "gn:name":"Picka",
    "gn:population":0,
    "gn:timezone":"Europe/Berlin",
    "iso:country":"DE",
    "wof:name":"Picka",
    "wof:placetype":"neighbourhood"
},
  "geometry": {"coordinates":[14.48015,51.0706],"type":"Point"}
}