{
  "type": "Feature",
  "properties": {
    "gn:admin1_code":"6",
    "gn:admin2_code":"0.0",
    "gn:admin3_code":"3459.0",
    "gn:admin4_code":"3459025.0",
    "gn:asciiname":"Schandorf",
    "gn:country_code":"DE",
    "gn:dem":23,
    "gn:feature_class":"P",
    "gn:feature_code":"PPL",
    "gn:name":"Schandorf",
    "gn:population":0,
    "gn:timezone":"Europe/Berlin",
    "iso:country":"DE",
    "name:ceb_x_preferred":[
        "Schandorf"
    ],
    "name:deu_x_preferred":[
        "Schandorf"
    ],
    "name:epo_x_preferred":[
        "Schandorf"
    ],
    "name:fas_x_preferred":[
        "\u0634\u0627\u0646\u062f\u0648\u0631\u0641"
    ],
    "name:fra_x_preferred":[
        "Schandorf"
    ],
    "name:hrv_x_preferred":[
        "\u010cemba"
    ],
    "name:hun_x_preferred":[
        "Cs\u00e9m"
    ],
    "name:ita_x_preferred":[
        "Schandorf"
    ],
    "name:kaz_x_preferred":[
        "\u0428\u0430\u043d\u0434\u043e\u0440\u0444"
    ],
    "name:nld_x_preferred":[
        "Schandorf"
    ],
    "name:pol_x_preferred":[
        "Schandorf"
    ],
    "name:por_x_preferred":[
        "Schandorf"
    ],
    "name:rus_x_preferred":[
        "\u0428\u0430\u043d\u0434\u043e\u0440\u0444"
    ],
    "name:slk_x_preferred":[
        "Schandorf"
    ],
    "name:spa_x_preferred":[
        "Schandorf"
    ],
    "name:swe_x_preferred":[
        "Schandorf"
    ],
    "name:ukr_x_preferred":[
        "\u0428\u0430\u043d\u0434\u043e\u0440\u0444"
    ],
    "name:uzb_x_preferred":[
        "Schandorf"
    ],
    "name:vol_x_preferred":[
        "Schandorf"
    ],
    "name:war_x_preferred":[
        "Schandorf"
    ],
    "name:zho_x_preferred":[
        "\u5c1a\u591a\u592b"
    ],
    "wof:name":"Schandorf",
    "wof:placetype":"neighbourhood"
},
  "geometry": {"coordinates":[7.83932,52.67561],"type":"Point"}
}