{
  "type": "Feature",
  "properties": {
    "gn:admin1_code":"6.0",
    "gn:admin2_code":"00",
    "gn:admin3_code":"3360.0",
    "gn:admin4_code":"3360019.0",
    "gn:asciiname":"Wittenwater",
    "gn:country_code":"DE",
    "gn:dem":59,
    "gn:feature_class":"P",
    "gn:feature_code":"PPL",
    "gn:name":"Wittenwater",
    "gn:population":0,
    "gn:timezone":"Europe/Berlin",
    "iso:country":"DE",
    "wof:name":"Wittenwater",
    "wof:placetype":"neighbourhood"
},
  "geometry": {"coordinates":[10.41178,53.00053000000001],"type":"Point"}
}