{
  "type": "Feature",
  "properties": {
    "gn:country":"DE",
    "gn:fcode":"PPL",
    "gn:population":0,
    "iso:country":"DE",
    "name:ceb_x_preferred":[
        "Langenwang"
    ],
    "name:deu_x_preferred":[
        "Langenwang"
    ],
    "name:epo_x_preferred":[
        "Langenwang"
    ],
    "name:fas_x_preferred":[
        "\u0644\u0627\u0646\u06af\u0646\u0648\u0627\u0646\u06af"
    ],
    "name:fra_x_preferred":[
        "Langenwang"
    ],
    "name:hun_x_preferred":[
        "Langenwang"
    ],
    "name:ita_x_preferred":[
        "Langenwang"
    ],
    "name:lat_x_preferred":[
        "Langenwang"
    ],
    "name:nld_x_preferred":[
        "Langenwang"
    ],
    "name:pol_x_preferred":[
        "Langenwang"
    ],
    "name:rus_x_preferred":[
        "\u041b\u0430\u043d\u0433\u0435\u043d\u0432\u0430\u043d\u0433"
    ],
    "name:slk_x_preferred":[
        "Langenwang"
    ],
    "name:spa_x_preferred":[
        "Langenwang"
    ],
    "name:swe_x_preferred":[
        "Langenwang"
    ],
    "name:ukr_x_preferred":[
        "\u041b\u0430\u043d\u0433\u0435\u043d\u0432\u0430\u043d\u0433"
    ],
    "name:uzb_x_preferred":[
        "Langenwang"
    ],
    "name:vie_x_preferred":[
        "Langenwang"
    ],
    "name:vol_x_preferred":[
        "Langenwang"
    ],
    "name:war_x_preferred":[
        "Langenwang"
    ],
    "name:zho_x_preferred":[
        "\u6717\u6839\u65fa"
    ],
    "qs_pg:aaroncc":"DE",
    "qs_pg:gn_country":"DE",
    "qs_pg:gn_fcode":"PPL",
    "qs_pg:gn_pop":0,
    "qs_pg:name":"Langenwang",
    "qs_pg:name_adm0":"Deutschland",
    "qs_pg:name_adm1":"Bayern",
    "qs_pg:photos":24,
    "qs_pg:photos_1k":5,
    "qs_pg:photos_9k":1,
    "qs_pg:photos_9r":1,
    "qs_pg:photos_all":24,
    "qs_pg:photos_sr":1,
    "qs_pg:pop_sr":0,
    "qs_pg:qs_pg_placetype":"locality",
    "qs_pg:qs_pg_placetype_gp":"Town",
    "qs_pg:woe_adm0":23424829,
    "woe:adm0_id":23424829,
    "woe:name_adm0":"Deutschland",
    "woe:name_adm1":"Bayern",
    "woe:placetype":"Town",
    "wof:name":"Langenwang",
    "wof:placetype":"neighbourhood"
},
  "geometry": {"coordinates":[10.27498,47.43876],"type":"Point"}
}