{
  "type": "Feature",
  "properties": {
    "gn:admin1_code":"1",
    "gn:admin2_code":"81.0",
    "gn:admin3_code":"8127.0",
    "gn:admin4_code":"8127047.0",
    "gn:asciiname":"Nesselbach",
    "gn:country_code":"DE",
    "gn:dem":445,
    "gn:feature_class":"P",
    "gn:feature_code":"PPL",
    "gn:name":"Nesselbach",
    "gn:population":0,
    "gn:timezone":"Europe/Berlin",
    "iso:country":"DE",
    "name:ceb_x_preferred":[
        "Nesselbach"
    ],
    "name:deu_x_preferred":[
        "Nesselbach"
    ],
    "name:swe_x_preferred":[
        "Nesselbach"
    ],
    "wof:name":"Nesselbach",
    "wof:placetype":"neighbourhood"
},
  "geometry": {"coordinates":[9.84693,49.22598],"type":"Point"}
}