{
  "type": "Feature",
  "properties": {
    "gn:admin1_code":"2",
    "gn:admin2_code":"95.0",
    "gn:admin3_code":"9575.0",
    "gn:admin4_code":"9575168.0",
    "gn:asciiname":"Langensteinach",
    "gn:country_code":"DE",
    "gn:dem":359,
    "gn:feature_class":"P",
    "gn:feature_code":"PPL",
    "gn:name":"Langensteinach",
    "gn:population":0,
    "gn:timezone":"Europe/Berlin",
    "iso:country":"DE",
    "wof:name":"Langensteinach",
    "wof:placetype":"neighbourhood"
},
  "geometry": {"coordinates":[10.17898,49.49653],"type":"Point"}
}