{
  "type": "Feature",
  "properties": {
    "gn:admin1_code":"12",
    "gn:admin2_code":"0.0",
    "gn:admin3_code":"13071.0",
    "gn:admin4_code":"13071110.0",
    "gn:asciiname":"Domjuech",
    "gn:country_code":"DE",
    "gn:dem":63,
    "gn:feature_class":"P",
    "gn:feature_code":"PPL",
    "gn:name":"Domj\u00fcch",
    "gn:population":0,
    "gn:timezone":"Europe/Berlin",
    "iso:country":"DE",
    "wof:name":"Domjuech",
    "wof:placetype":"neighbourhood"
},
  "geometry": {"coordinates":[13.12039,53.3284],"type":"Point"}
}