{
  "type": "Feature",
  "properties": {
    "gn:admin1_code":"1",
    "gn:admin2_code":"81.0",
    "gn:admin3_code":"8116.0",
    "gn:admin4_code":"8116049.0",
    "gn:asciiname":"Hardt",
    "gn:country_code":"DE",
    "gn:dem":356,
    "gn:feature_class":"P",
    "gn:feature_code":"PPL",
    "gn:name":"Hardt",
    "gn:population":0,
    "gn:timezone":"Europe/Berlin",
    "iso:country":"DE",
    "wof:name":"Hardt",
    "wof:placetype":"neighbourhood"
},
  "geometry": {"coordinates":[9.30117,48.64091],"type":"Point"}
}