{
  "type": "Feature",
  "properties": {
    "gn:admin1_code":"1",
    "gn:admin2_code":"81.0",
    "gn:admin3_code":"8116.0",
    "gn:admin4_code":"8116049.0",
    "gn:asciiname":"Hardt",
    "gn:country_code":"DE",
    "gn:dem":356,
    "gn:feature_class":"P",
    "gn:feature_code":"PPL",
    "gn:name":"Hardt",
    "gn:population":0,
    "gn:timezone":"Europe/Berlin",
    "iso:country":"DE",
    "name:ceb_x_preferred":[
        "Hardt"
    ],
    "name:deu_x_preferred":[
        "Hardt"
    ],
    "name:epo_x_preferred":[
        "Hardt"
    ],
    "name:fra_x_preferred":[
        "Hardt"
    ],
    "name:hun_x_preferred":[
        "Hardt"
    ],
    "name:ita_x_preferred":[
        "Hardt"
    ],
    "name:nld_x_preferred":[
        "Hardt"
    ],
    "name:pol_x_preferred":[
        "Hardt"
    ],
    "name:por_x_preferred":[
        "Hardt"
    ],
    "name:ron_x_preferred":[
        "Hardt"
    ],
    "name:rus_x_preferred":[
        "\u0425\u0430\u0440\u0434\u0442"
    ],
    "name:srp_x_preferred":[
        "\u0425\u0430\u0440\u0434\u0442"
    ],
    "name:swe_x_preferred":[
        "Hardt"
    ],
    "name:vol_x_preferred":[
        "Hardt"
    ],
    "wof:name":"Hardt",
    "wof:placetype":"neighbourhood"
},
  "geometry": {"coordinates":[9.30117,48.64091],"type":"Point"}
}