{
  "type": "Feature",
  "properties": {
    "gn:admin1_code":"13.0",
    "gn:admin2_code":"00",
    "gn:admin3_code":"14729.0",
    "gn:admin4_code":"14729160.0",
    "gn:asciiname":"Zschoppach",
    "gn:country_code":"DE",
    "gn:dem":221,
    "gn:feature_class":"P",
    "gn:feature_code":"PPL",
    "gn:name":"Zschoppach",
    "gn:population":0,
    "gn:timezone":"Europe/Berlin",
    "iso:country":"DE",
    "wof:name":"Zschoppach",
    "wof:placetype":"neighbourhood"
},
  "geometry": {"coordinates":[12.88689,51.21516],"type":"Point"}
}