{
  "type": "Feature",
  "properties": {
    "gn:admin1_code":"1",
    "gn:admin2_code":"84.0",
    "gn:admin3_code":"8436.0",
    "gn:admin4_code":"8436078.0",
    "gn:asciiname":"Reckendurren",
    "gn:country_code":"DE",
    "gn:dem":662,
    "gn:feature_class":"P",
    "gn:feature_code":"PPL",
    "gn:name":"Reckend\u00fcrren",
    "gn:population":0,
    "gn:timezone":"Europe/Berlin",
    "iso:country":"DE",
    "wof:name":"Reckendurren",
    "wof:placetype":"neighbourhood"
},
  "geometry": {"coordinates":[9.76667,47.76667],"type":"Point"}
}