{
  "type": "Feature",
  "properties": {
    "gn:admin1_code":"5",
    "gn:admin2_code":"64.0",
    "gn:admin3_code":"6435.0",
    "gn:admin4_code":"6435028.0",
    "gn:asciiname":"Elisabethenhof",
    "gn:country_code":"DE",
    "gn:dem":405,
    "gn:feature_class":"P",
    "gn:feature_code":"PPL",
    "gn:name":"Elisabethenhof",
    "gn:population":0,
    "gn:timezone":"Europe/Berlin",
    "iso:country":"DE",
    "wof:name":"Elisabethenhof",
    "wof:placetype":"neighbourhood"
},
  "geometry": {"coordinates":[9.41297,50.38565],"type":"Point"}
}