{
  "type": "Feature",
  "properties": {
    "gn:admin1_code":"2",
    "gn:admin2_code":"97.0",
    "gn:admin3_code":"9780.0",
    "gn:admin4_code":"9780112.0",
    "gn:asciiname":"Fischers",
    "gn:country_code":"DE",
    "gn:dem":643,
    "gn:feature_class":"P",
    "gn:feature_code":"PPL",
    "gn:name":"Fischers",
    "gn:population":0,
    "gn:timezone":"Europe/Berlin",
    "iso:country":"DE",
    "wof:name":"Fischers",
    "wof:placetype":"neighbourhood"
},
  "geometry": {"coordinates":[10.21868,47.82846],"type":"Point"}
}