{
  "type": "Feature",
  "properties": {
    "gn:admin1_code":"14",
    "gn:admin2_code":"0.0",
    "gn:admin3_code":"15088.0",
    "gn:admin4_code":"15088025.0",
    "gn:asciiname":"Unterkriegstedt",
    "gn:country_code":"DE",
    "gn:dem":102,
    "gn:feature_class":"P",
    "gn:feature_code":"PPL",
    "gn:name":"Unterkriegstedt",
    "gn:population":0,
    "gn:timezone":"Europe/Berlin",
    "iso:country":"DE",
    "wof:name":"Unterkriegstedt",
    "wof:placetype":"neighbourhood"
},
  "geometry": {"coordinates":[11.88537,51.37034],"type":"Point"}
}