{
  "type": "Feature",
  "properties": {
    "gn:admin1_code":"6",
    "gn:admin2_code":"0.0",
    "gn:admin3_code":"3459.0",
    "gn:admin4_code":"3459024.0",
    "gn:asciiname":"Bullenheide",
    "gn:country_code":"DE",
    "gn:dem":86,
    "gn:feature_class":"P",
    "gn:feature_code":"PPL",
    "gn:name":"Bullenheide",
    "gn:population":0,
    "gn:timezone":"Europe/Berlin",
    "iso:country":"DE",
    "wof:name":"Bullenheide",
    "wof:placetype":"neighbourhood"
},
  "geometry": {"coordinates":[8.35729,52.19034],"type":"Point"}
}