{
  "type": "Feature",
  "properties": {
    "gn:admin1_code":"2.0",
    "gn:admin2_code":"93.0",
    "gn:admin3_code":"9374.0",
    "gn:admin4_code":"9374124.0",
    "gn:asciiname":"Bergfried",
    "gn:country_code":"DE",
    "gn:dem":441,
    "gn:feature_class":"P",
    "gn:feature_code":"PPL",
    "gn:name":"Bergfried",
    "gn:population":0,
    "gn:timezone":"Europe/Berlin",
    "iso:country":"DE",
    "name:bel_x_preferred":[
        "\u0411\u0435\u0440\u0433\u0444\u0440\u044b\u0434"
    ],
    "name:ces_x_preferred":[
        "Bergfrit"
    ],
    "name:deu_x_preferred":[
        "Bergfried"
    ],
    "name:epo_x_preferred":[
        "Burgfrido"
    ],
    "name:fra_x_preferred":[
        "Bergfried"
    ],
    "name:ina_x_preferred":[
        "Bergfried"
    ],
    "name:lit_x_preferred":[
        "Bergfrydas"
    ],
    "name:nld_x_preferred":[
        "Bergfried"
    ],
    "name:pol_x_preferred":[
        "Sto\u0142p"
    ],
    "name:rus_x_preferred":[
        "\u0411\u0435\u0440\u0433\u0444\u0440\u0438\u0434"
    ],
    "name:slv_x_preferred":[
        "Bergfrid"
    ],
    "name:vie_x_preferred":[
        "Bergfried"
    ],
    "wof:name":"Bergfried",
    "wof:placetype":"neighbourhood"
},
  "geometry": {"coordinates":[11.77267,49.67317],"type":"Point"}
}