{
  "type": "Feature",
  "properties": {
    "gn:admin1_code":"2.0",
    "gn:admin2_code":"091",
    "gn:admin3_code":"9186.0",
    "gn:admin4_code":"9186151.0",
    "gn:asciiname":"Ziegelnobach",
    "gn:country_code":"DE",
    "gn:dem":471,
    "gn:feature_class":"P",
    "gn:feature_code":"PPL",
    "gn:name":"Ziegeln\u00f6bach",
    "gn:population":0,
    "gn:timezone":"Europe/Berlin",
    "iso:country":"DE",
    "wof:name":"Ziegelnobach",
    "wof:placetype":"neighbourhood"
},
  "geometry": {"coordinates":[11.45194,48.4772],"type":"Point"}
}