{
  "type": "Feature",
  "properties": {
    "gn:admin1_code":"7.0",
    "gn:admin2_code":"53.0",
    "gn:admin3_code":"5378.0",
    "gn:admin4_code":"5378024.0",
    "gn:asciiname":"Neuhurden",
    "gn:country_code":"DE",
    "gn:dem":194,
    "gn:feature_class":"P",
    "gn:feature_code":"PPL",
    "gn:name":"Neuhurden",
    "gn:population":0,
    "gn:timezone":"Europe/Berlin",
    "iso:country":"DE",
    "wof:name":"Neuhurden",
    "wof:placetype":"neighbourhood"
},
  "geometry": {"coordinates":[7.24323,50.95437],"type":"Point"}
}