{
  "type": "Feature",
  "properties": {
    "gn:admin1_code":"1",
    "gn:admin2_code":"83.0",
    "gn:admin3_code":"8337.0",
    "gn:admin4_code":"8337049.0",
    "gn:asciiname":"Grossherrischwand",
    "gn:country_code":"DE",
    "gn:dem":881,
    "gn:feature_class":"P",
    "gn:feature_code":"PPL",
    "gn:name":"Gro\u00dfherrischwand",
    "gn:population":0,
    "gn:timezone":"Europe/Berlin",
    "iso:country":"DE",
    "wof:name":"Grossherrischwand",
    "wof:placetype":"neighbourhood"
},
  "geometry": {"coordinates":[8.00756,47.67947],"type":"Point"}
}