{
  "type": "Feature",
  "properties": {
    "gn:country":"DE",
    "gn:fcode":"PPL",
    "gn:population":0,
    "iso:country":"DE",
    "name:bar_x_preferred":[
        "Fellen"
    ],
    "name:ceb_x_preferred":[
        "Fellen"
    ],
    "name:dan_x_preferred":[
        "Fellen"
    ],
    "name:deu_x_preferred":[
        "Fellen"
    ],
    "name:epo_x_preferred":[
        "Fellen"
    ],
    "name:eus_x_preferred":[
        "Fellen"
    ],
    "name:fra_x_preferred":[
        "Fellen"
    ],
    "name:hun_x_preferred":[
        "Fellen"
    ],
    "name:hye_x_preferred":[
        "\u0556\u0565\u056c\u0565\u0576"
    ],
    "name:ind_x_preferred":[
        "Fellen"
    ],
    "name:ita_x_preferred":[
        "Fellen"
    ],
    "name:kaz_x_preferred":[
        "\u0424\u0435\u043b\u043b\u0435\u043d"
    ],
    "name:kir_x_preferred":[
        "\u0424\u0435\u043b\u043b\u0435\u043d"
    ],
    "name:lmo_x_preferred":[
        "Fellen"
    ],
    "name:msa_x_preferred":[
        "Fellen"
    ],
    "name:nld_x_preferred":[
        "Fellen"
    ],
    "name:pol_x_preferred":[
        "Fellen"
    ],
    "name:por_x_preferred":[
        "Fellen"
    ],
    "name:ron_x_preferred":[
        "Fellen"
    ],
    "name:rus_x_preferred":[
        "\u0424\u0435\u043b\u043b\u0435\u043d"
    ],
    "name:spa_x_preferred":[
        "Fellen"
    ],
    "name:srp_x_preferred":[
        "\u0424\u0435\u043b\u0435\u043d"
    ],
    "name:ukr_x_preferred":[
        "\u0424\u0435\u043b\u043b\u0435\u043d"
    ],
    "name:uzb_x_preferred":[
        "Fellen"
    ],
    "name:vie_x_preferred":[
        "Fellen"
    ],
    "name:vol_x_preferred":[
        "Fellen"
    ],
    "name:war_x_preferred":[
        "Fellen"
    ],
    "qs_pg:aaroncc":"DE",
    "qs_pg:gn_country":"DE",
    "qs_pg:gn_fcode":"PPL",
    "qs_pg:gn_pop":0,
    "qs_pg:name":"Fellen",
    "qs_pg:name_adm0":"Deutschland",
    "qs_pg:name_adm1":"Rheinland-Pfalz",
    "qs_pg:photos":36,
    "qs_pg:photos_1k":7,
    "qs_pg:photos_9k":1,
    "qs_pg:photos_9r":2,
    "qs_pg:photos_all":36,
    "qs_pg:photos_sr":2,
    "qs_pg:pop_sr":0,
    "qs_pg:qs_pg_placetype":"locality",
    "qs_pg:qs_pg_placetype_gp":"Town",
    "qs_pg:woe_adm0":23424829,
    "woe:adm0_id":23424829,
    "woe:name_adm0":"Deutschland",
    "woe:name_adm1":"Rheinland-Pfalz",
    "woe:placetype":"Town",
    "wof:name":"Fellen",
    "wof:placetype":"neighbourhood"
},
  "geometry": {"coordinates":[7.68801,50.16712],"type":"Point"}
}