{
  "type": "Feature",
  "properties": {
    "gn:admin1_code":"2.0",
    "gn:admin2_code":"094",
    "gn:admin3_code":"9473.0",
    "gn:admin4_code":"9473159.0",
    "gn:asciiname":"Weissenbrunn vorm Wald",
    "gn:country_code":"DE",
    "gn:dem":382,
    "gn:feature_class":"P",
    "gn:feature_code":"PPL",
    "gn:name":"Wei\u00dfenbrunn vorm Wald",
    "gn:population":0,
    "gn:timezone":"Europe/Berlin",
    "iso:country":"DE",
    "wof:name":"Weissenbrunn vorm Wald",
    "wof:placetype":"neighbourhood"
},
  "geometry": {"coordinates":[11.01102,50.35604],"type":"Point"}
}