{
  "type": "Feature",
  "properties": {
    "gn:admin1_code":"7",
    "gn:admin2_code":"51.0",
    "gn:admin3_code":"5158.0",
    "gn:admin4_code":"5158036.0",
    "gn:asciiname":"Duessel",
    "gn:country_code":"DE",
    "gn:dem":161,
    "gn:feature_class":"P",
    "gn:feature_code":"PPL",
    "gn:name":"D\u00fcssel",
    "gn:population":0,
    "gn:timezone":"Europe/Berlin",
    "iso:country":"DE",
    "wof:name":"Duessel",
    "wof:placetype":"neighbourhood"
},
  "geometry": {"coordinates":[7.05213,51.2628],"type":"Point"}
}