{
  "type": "Feature",
  "properties": {
    "gn:admin1_code":"11",
    "gn:admin2_code":"0.0",
    "gn:admin3_code":"12073.0",
    "gn:admin4_code":"12073309.0",
    "gn:asciiname":"Gross Pinnow",
    "gn:country_code":"DE",
    "gn:dem":46,
    "gn:feature_class":"P",
    "gn:feature_code":"PPL",
    "gn:name":"Gro\u00df Pinnow",
    "gn:population":0,
    "gn:timezone":"Europe/Berlin",
    "iso:country":"DE",
    "wof:name":"Gross Pinnow",
    "wof:placetype":"neighbourhood"
},
  "geometry": {"coordinates":[14.27622,53.18423000000001],"type":"Point"}
}