{
  "type": "Feature",
  "properties": {
    "gn:admin1_code":"2",
    "gn:admin2_code":"94.0",
    "gn:admin3_code":"9475.0",
    "gn:admin4_code":"9475156.0",
    "gn:asciiname":"Molkenbrunn",
    "gn:country_code":"DE",
    "gn:dem":585,
    "gn:feature_class":"P",
    "gn:feature_code":"PPL",
    "gn:name":"Molkenbrunn",
    "gn:population":0,
    "gn:timezone":"Europe/Berlin",
    "iso:country":"DE",
    "wof:name":"Molkenbrunn",
    "wof:placetype":"neighbourhood"
},
  "geometry": {"coordinates":[11.70285,50.30826],"type":"Point"}
}