{
  "type": "Feature",
  "properties": {
    "iso:country":"DE",
    "name:deu_x_colloquial":[
        "Oppum-Sud",
        "Oppum-Sued"
    ],
    "name:deu_x_preferred":[
        "Oppum-S\u00fcd"
    ],
    "name:unk_x_variant":[
        "Oppum-S\u00fcd"
    ],
    "qs:gn_adm0_cc":"DE",
    "qs:gn_local":2884509,
    "qs:gn_nam_loc":"krefeld",
    "qs:gn_namadm1":"07",
    "qs:local_max":3369,
    "qs:local_sum":5777,
    "qs:localhoods":16,
    "qs:name":"Oppum-S\u00fcd",
    "qs:name_adm0":"Deutschland",
    "qs:name_adm1":"Nordrhein-Westfalen",
    "qs:name_adm2":"Stadtkreis Krefeld",
    "qs:name_lau":"Stadtteil Oppum",
    "qs:name_local":"Krefeld",
    "qs:photo_max":26,
    "qs:photo_sum":42,
    "qs:placetype":"Suburb",
    "qs:quad_count":6,
    "qs:woe_adm0":23424829,
    "qs:woe_adm1":2345487,
    "qs:woe_adm2":12597091,
    "qs:woe_lau":26822859,
    "qs:woe_local":668736,
    "qs:woe_ver":"7.10.0",
    "wof:lang":[
        "ger"
    ],
    "wof:name":"Oppum-S\u00fcd",
    "wof:placetype":"neighbourhood"
},
  "geometry": {"coordinates":[6.627633,51.314918],"type":"Point"}
}