{
  "type": "Feature",
  "properties": {
    "gn:admin1_code":"2",
    "gn:admin2_code":"94.0",
    "gn:admin3_code":"9472.0",
    "gn:admin4_code":"9472119.0",
    "gn:asciiname":"Obergrafenthal",
    "gn:country_code":"DE",
    "gn:dem":370,
    "gn:feature_class":"P",
    "gn:feature_code":"PPL",
    "gn:name":"Obergr\u00e4fenthal",
    "gn:population":0,
    "gn:timezone":"Europe/Berlin",
    "iso:country":"DE",
    "wof:name":"Obergrafenthal",
    "wof:placetype":"neighbourhood"
},
  "geometry": {"coordinates":[11.55449,50.00671],"type":"Point"}
}