{
  "type": "Feature",
  "properties": {
    "gn:admin1_code":"7",
    "gn:admin2_code":"59.0",
    "gn:admin3_code":"5958.0",
    "gn:admin4_code":"5958032.0",
    "gn:asciiname":"Vellinghausen",
    "gn:country_code":"DE",
    "gn:dem":398,
    "gn:feature_class":"P",
    "gn:feature_code":"PPL",
    "gn:name":"Vellinghausen",
    "gn:population":0,
    "gn:timezone":"Europe/Berlin",
    "iso:country":"DE",
    "wof:name":"Vellinghausen",
    "wof:placetype":"locality"
},
  "geometry": {"coordinates":[8.28435,51.3128],"type":"Point"}
}