{
  "type": "Feature",
  "properties": {
    "gn:admin1_code":"2",
    "gn:admin2_code":"97.0",
    "gn:admin3_code":"9773.0",
    "gn:admin4_code":"9773182.0",
    "gn:asciiname":"Possenried",
    "gn:country_code":"DE",
    "gn:dem":439,
    "gn:feature_class":"P",
    "gn:feature_code":"PPL",
    "gn:name":"Possenried",
    "gn:population":0,
    "gn:timezone":"Europe/Berlin",
    "iso:country":"DE",
    "wof:name":"Possenried",
    "wof:placetype":"neighbourhood"
},
  "geometry": {"coordinates":[10.74596,48.56293],"type":"Point"}
}