{
  "type": "Feature",
  "properties": {
    "gn:admin1_code":"2",
    "gn:admin2_code":"92.0",
    "gn:admin3_code":"9271.0",
    "gn:admin4_code":"9271119.0",
    "gn:asciiname":"Niederkandelbach",
    "gn:cc2":"DE",
    "gn:country_code":"DE",
    "gn:dem":330,
    "gn:feature_class":"P",
    "gn:feature_code":"PPL",
    "gn:name":"Niederkandelbach",
    "gn:population":0,
    "gn:timezone":"Europe/Berlin",
    "iso:country":"DE",
    "name:und_x_variant":[
        "Nieder Kandlbach",
        "Niederkandelbach"
    ],
    "wof:name":"Niederkandelbach",
    "wof:placetype":"neighbourhood"
},
  "geometry": {"coordinates":[12.95454,48.86256],"type":"Point"}
}