{
  "type": "Feature",
  "properties": {
    "gn:country":"DE",
    "gn:fcode":"PPL",
    "gn:population":178,
    "iso:country":"DE",
    "name:azb_x_preferred":[
        "\u0648\u0648\u0644\u0641\u0633\u0628\u0631\u0642"
    ],
    "name:ceb_x_preferred":[
        "Wolfsberg"
    ],
    "name:deu_x_preferred":[
        "Wolfsberg"
    ],
    "name:epo_x_preferred":[
        "Wolfsberg"
    ],
    "name:fin_x_preferred":[
        "Wolfsberg"
    ],
    "name:fra_x_preferred":[
        "Wolfsberg"
    ],
    "name:hun_x_preferred":[
        "Wolfsberg"
    ],
    "name:ind_x_preferred":[
        "Wolfsberg"
    ],
    "name:ita_x_preferred":[
        "Wolfsberg"
    ],
    "name:kaz_x_preferred":[
        "\u0412\u043e\u043b\u044c\u0444\u0441\u0431\u0435\u0440\u0433"
    ],
    "name:kir_x_preferred":[
        "\u0412\u043e\u043b\u044c\u0444\u0441\u0431\u0435\u0440\u0433"
    ],
    "name:nld_x_preferred":[
        "Wolfsberg"
    ],
    "name:pol_x_preferred":[
        "Wolfsberg"
    ],
    "name:por_x_preferred":[
        "Wolfsberg"
    ],
    "name:rus_x_preferred":[
        "\u0412\u043e\u043b\u044c\u0444\u0441\u0431\u0435\u0440\u0433"
    ],
    "name:spa_x_preferred":[
        "Wolfsberg"
    ],
    "name:swe_x_preferred":[
        "Wolfsberg"
    ],
    "name:vol_x_preferred":[
        "Wolfsberg"
    ],
    "name:zho_x_preferred":[
        "\u6c83\u723e\u592b\u65af\u8c9d\u683c"
    ],
    "qs_pg:aaroncc":"DE",
    "qs_pg:gn_country":"DE",
    "qs_pg:gn_fcode":"PPL",
    "qs_pg:gn_pop":178,
    "qs_pg:name":"Wolfsberg",
    "qs_pg:name_adm0":"Deutschland",
    "qs_pg:name_adm1":"Sachsen-Anhalt",
    "qs_pg:photos_9r":0,
    "qs_pg:photos_sr":0,
    "qs_pg:pop_sr":1,
    "qs_pg:qs_pg_placetype":"locality",
    "qs_pg:qs_pg_placetype_gp":"Town",
    "qs_pg:woe_adm0":23424829,
    "woe:adm0_id":23424829,
    "woe:name_adm0":"Deutschland",
    "woe:name_adm1":"Sachsen-Anhalt",
    "woe:placetype":"Town",
    "wof:name":"Wolfsberg",
    "wof:placetype":"neighbourhood",
    "wof:population":178
},
  "geometry": {"coordinates":[11.09717,51.55259],"type":"Point"}
}