{
  "type": "Feature",
  "properties": {
    "gn:admin1_code":"2",
    "gn:admin2_code":"96.0",
    "gn:admin3_code":"9677.0",
    "gn:admin4_code":"9677135.0",
    "gn:asciiname":"Einsiedel",
    "gn:country_code":"DE",
    "gn:dem":219,
    "gn:feature_class":"P",
    "gn:feature_code":"PPL",
    "gn:name":"Einsiedel",
    "gn:population":0,
    "gn:timezone":"Europe/Berlin",
    "iso:country":"DE",
    "wof:name":"Einsiedel",
    "wof:placetype":"neighbourhood"
},
  "geometry": {"coordinates":[9.50308,49.92889],"type":"Point"}
}