{
  "type": "Feature",
  "properties": {
    "iso:country":"DE",
    "name:deu_x_preferred":[
        "H\u00f6hrath"
    ],
    "wof:name":"Hoehrath",
    "wof:placetype":"neighbourhood"
},
  "geometry": {"coordinates":[7.14887663529992,51.12825525212587],"type":"Point"}
}