{
  "type": "Feature",
  "properties": {
    "gn:admin1_code":"2",
    "gn:admin2_code":"93.0",
    "gn:admin3_code":"9375.0",
    "gn:admin4_code":"9375148.0",
    "gn:asciiname":"Oberreiselberg",
    "gn:country_code":"DE",
    "gn:dem":547,
    "gn:feature_class":"P",
    "gn:feature_code":"PPL",
    "gn:name":"Oberreiselberg",
    "gn:population":0,
    "gn:timezone":"Europe/Berlin",
    "iso:country":"DE",
    "wof:name":"Oberreiselberg",
    "wof:placetype":"neighbourhood"
},
  "geometry": {"coordinates":[11.77091,49.09084],"type":"Point"}
}