{
  "type": "Feature",
  "properties": {
    "gn:admin1_code":"9",
    "gn:admin2_code":"0.0",
    "gn:admin3_code":"10044.0",
    "gn:admin4_code":"10044114.0",
    "gn:asciiname":"Eimersdorf",
    "gn:country_code":"DE",
    "gn:dem":230,
    "gn:feature_class":"P",
    "gn:feature_code":"PPL",
    "gn:name":"Eimersdorf",
    "gn:population":0,
    "gn:timezone":"Europe/Berlin",
    "iso:country":"DE",
    "wof:name":"Eimersdorf",
    "wof:placetype":"neighbourhood"
},
  "geometry": {"coordinates":[6.65266,49.38029],"type":"Point"}
}