{
  "type": "Feature",
  "properties": {
    "gn:admin1_code":"2.0",
    "gn:admin2_code":"093",
    "gn:admin3_code":"9375.0",
    "gn:admin4_code":"9375196.0",
    "gn:asciiname":"Zaitzkofen",
    "gn:country_code":"DE",
    "gn:dem":379,
    "gn:feature_class":"P",
    "gn:feature_code":"PPL",
    "gn:name":"Zaitzkofen",
    "gn:population":0,
    "gn:timezone":"Europe/Berlin",
    "iso:country":"DE",
    "wof:name":"Zaitzkofen",
    "wof:placetype":"neighbourhood"
},
  "geometry": {"coordinates":[12.21064,48.8363],"type":"Point"}
}