{
  "type": "Feature",
  "properties": {
    "gn:admin1_code":"2",
    "gn:admin2_code":"92.0",
    "gn:admin3_code":"9277.0",
    "gn:admin4_code":"9277148.0",
    "gn:asciiname":"Grasensee",
    "gn:country_code":"DE",
    "gn:dem":424,
    "gn:feature_class":"P",
    "gn:feature_code":"PPL",
    "gn:name":"Grasensee",
    "gn:population":0,
    "gn:timezone":"Europe/Berlin",
    "iso:country":"DE",
    "name:und_x_variant":[
        "Hann\u00f6d",
        "Grasensee"
    ],
    "wof:name":"Grasensee",
    "wof:placetype":"neighbourhood"
},
  "geometry": {"coordinates":[12.88615,48.36538],"type":"Point"}
}