{
  "type": "Feature",
  "properties": {
    "gn:admin1_code":"12",
    "gn:admin2_code":"0.0",
    "gn:admin3_code":"13074.0",
    "gn:admin4_code":"13074019.0",
    "gn:asciiname":"Rosenthal",
    "gn:country_code":"DE",
    "gn:dem":11,
    "gn:feature_class":"P",
    "gn:feature_code":"PPL",
    "gn:name":"Rosenthal",
    "gn:population":0,
    "gn:timezone":"Europe/Berlin",
    "iso:country":"DE",
    "name:bel_x_preferred":[
        "\u0420\u0430\u0437\u0435\u043d\u0442\u0430\u043b\u044c"
    ],
    "name:cat_x_preferred":[
        "Rosenthal"
    ],
    "name:ceb_x_preferred":[
        "Rosenthal"
    ],
    "name:ces_x_preferred":[
        "Rosenthal"
    ],
    "name:deu_x_preferred":[
        "Rosenthal"
    ],
    "name:epo_x_preferred":[
        "Rosenthal"
    ],
    "name:fas_x_preferred":[
        "\u0631\u0632\u0646\u062a\u0627\u0644"
    ],
    "name:fin_x_preferred":[
        "Rosenthal"
    ],
    "name:fra_x_preferred":[
        "Rosenthal"
    ],
    "name:heb_x_preferred":[
        "\u05e8\u05d5\u05d6\u05e0\u05d8\u05dc"
    ],
    "name:ita_x_preferred":[
        "Rosenthal"
    ],
    "name:jpn_x_preferred":[
        "\u30ed\u30fc\u30bc\u30f3\u30bf\u30fc\u30eb"
    ],
    "name:nld_x_preferred":[
        "Rosenthal"
    ],
    "name:pol_x_preferred":[
        "Rosenthal"
    ],
    "name:por_x_preferred":[
        "Rosenthal"
    ],
    "name:ron_x_preferred":[
        "Rosenthal"
    ],
    "name:rus_x_preferred":[
        "\u0420\u043e\u0437\u0435\u043d\u0442\u0430\u043b\u044c"
    ],
    "name:spa_x_preferred":[
        "Rosenthal"
    ],
    "name:swe_x_preferred":[
        "Rosenthal"
    ],
    "name:ukr_x_preferred":[
        "\u0420\u043e\u0437\u0435\u043d\u0442\u0430\u043b\u044c"
    ],
    "wof:name":"Rosenthal",
    "wof:placetype":"neighbourhood"
},
  "geometry": {"coordinates":[11.47393,53.85997],"type":"Point"}
}