{
  "type": "Feature",
  "properties": {
    "gn:admin1_code":"1",
    "gn:admin2_code":"81.0",
    "gn:admin3_code":"8117.0",
    "gn:admin4_code":"8117019.0",
    "gn:asciiname":"Krummwalden",
    "gn:country_code":"DE",
    "gn:dem":351,
    "gn:feature_class":"P",
    "gn:feature_code":"PPL",
    "gn:name":"Krummw\u00e4lden",
    "gn:population":0,
    "gn:timezone":"Europe/Berlin",
    "iso:country":"DE",
    "wof:name":"Krummwalden",
    "wof:placetype":"neighbourhood"
},
  "geometry": {"coordinates":[9.73372,48.70756],"type":"Point"}
}