{
  "type": "Feature",
  "properties": {
    "gn:admin1_code":"7",
    "gn:admin2_code":"59.0",
    "gn:admin3_code":"5958.0",
    "gn:admin4_code":"5958004.0",
    "gn:asciiname":"Hoellinghofer Heide",
    "gn:country_code":"DE",
    "gn:dem":213,
    "gn:feature_class":"P",
    "gn:feature_code":"PPLL",
    "gn:name":"H\u00f6llinghofer Heide",
    "gn:population":0,
    "gn:timezone":"Europe/Berlin",
    "iso:country":"DE",
    "wof:name":"Hoellinghofer Heide",
    "wof:placetype":"neighbourhood"
},
  "geometry": {"coordinates":[7.89807,51.46736],"type":"Point"}
}