{
  "type": "Feature",
  "properties": {
    "gn:admin1_code":"2",
    "gn:admin2_code":"97.0",
    "gn:admin3_code":"9777.0",
    "gn:admin4_code":"9777173.0",
    "gn:asciiname":"Schober",
    "gn:country_code":"DE",
    "gn:dem":843,
    "gn:feature_class":"P",
    "gn:feature_code":"PPL",
    "gn:name":"Schober",
    "gn:population":0,
    "gn:timezone":"Europe/Berlin",
    "iso:country":"DE",
    "wof:name":"Schober",
    "wof:placetype":"neighbourhood"
},
  "geometry": {"coordinates":[10.85792,47.65773],"type":"Point"}
}