{
  "type": "Feature",
  "properties": {
    "gn:admin1_code":"2",
    "gn:admin2_code":"97.0",
    "gn:admin3_code":"9777.0",
    "gn:admin4_code":"9777173.0",
    "gn:asciiname":"Schober",
    "gn:country_code":"DE",
    "gn:dem":843,
    "gn:feature_class":"P",
    "gn:feature_code":"PPL",
    "gn:name":"Schober",
    "gn:population":0,
    "gn:timezone":"Europe/Berlin",
    "iso:country":"DE",
    "name:ceb_x_preferred":[
        "Schober"
    ],
    "name:ces_x_preferred":[
        "Schober"
    ],
    "name:deu_x_preferred":[
        "Schober"
    ],
    "name:jpn_x_preferred":[
        "\u30b7\u30e7\u30fc\u30d0\u30fc"
    ],
    "name:rus_x_preferred":[
        "\u0428\u043e\u0431\u0435\u0440"
    ],
    "name:swe_x_preferred":[
        "Schober"
    ],
    "wof:name":"Schober",
    "wof:placetype":"neighbourhood"
},
  "geometry": {"coordinates":[10.85792,47.65773],"type":"Point"}
}