{
  "type": "Feature",
  "properties": {
    "gn:admin1_code":"2",
    "gn:admin2_code":"97.0",
    "gn:admin3_code":"9776.0",
    "gn:admin4_code":"9776122.0",
    "gn:asciiname":"Spattweg",
    "gn:country_code":"DE",
    "gn:dem":610,
    "gn:feature_class":"P",
    "gn:feature_code":"PPL",
    "gn:name":"Spattweg",
    "gn:population":0,
    "gn:timezone":"Europe/Berlin",
    "iso:country":"DE",
    "wof:name":"Spattweg",
    "wof:placetype":"neighbourhood"
},
  "geometry": {"coordinates":[9.85,47.63333],"type":"Point"}
}