{
  "type": "Feature",
  "properties": {
    "gn:admin1_code":"7.0",
    "gn:admin2_code":"055",
    "gn:admin3_code":"5554.0",
    "gn:admin4_code":"5554004.0",
    "gn:asciiname":"Wuellen",
    "gn:country_code":"DE",
    "gn:dem":54,
    "gn:feature_class":"P",
    "gn:feature_code":"PPL",
    "gn:name":"W\u00fcllen",
    "gn:population":0,
    "gn:timezone":"Europe/Berlin",
    "iso:country":"DE",
    "wof:name":"Wuellen",
    "wof:placetype":"neighbourhood"
},
  "geometry": {"coordinates":[6.97872,52.06827],"type":"Point"}
}