{
  "type": "Feature",
  "properties": {
    "gn:admin1_code":"13.0",
    "gn:admin2_code":"0.0",
    "gn:admin3_code":"14626.0",
    "gn:admin4_code":"14626480.0",
    "gn:asciiname":"Bremenhain",
    "gn:country_code":"DE",
    "gn:dem":158,
    "gn:feature_class":"P",
    "gn:feature_code":"PPL",
    "gn:name":"Bremenhain",
    "gn:population":0,
    "gn:timezone":"Europe/Berlin",
    "iso:country":"DE",
    "name:und_x_variant":[
        "Bremerhain",
        "Bremenhain"
    ],
    "wof:name":"Bremenhain",
    "wof:placetype":"neighbourhood"
},
  "geometry": {"coordinates":[14.94062,51.36018],"type":"Point"}
}