{
  "type": "Feature",
  "properties": {
    "gn:admin1_code":"8",
    "gn:admin2_code":"0.0",
    "gn:admin3_code":"7340.0",
    "gn:admin4_code":"7340035.0",
    "gn:asciiname":"Huberhof",
    "gn:country_code":"DE",
    "gn:dem":336,
    "gn:feature_class":"P",
    "gn:feature_code":"PPL",
    "gn:name":"Huberhof",
    "gn:population":0,
    "gn:timezone":"Europe/Berlin",
    "iso:country":"DE",
    "wof:name":"Huberhof",
    "wof:placetype":"neighbourhood"
},
  "geometry": {"coordinates":[7.49803,49.20496],"type":"Point"}
}