{
  "type": "Feature",
  "properties": {
    "gn:admin1_code":"6",
    "gn:admin2_code":"0.0",
    "gn:admin3_code":"3155.0",
    "gn:admin4_code":"3155012.0",
    "gn:asciiname":"Fuerstenhagen",
    "gn:country_code":"DE",
    "gn:dem":231,
    "gn:feature_class":"P",
    "gn:feature_code":"PPL",
    "gn:name":"F\u00fcrstenhagen",
    "gn:population":0,
    "gn:timezone":"Europe/Berlin",
    "iso:country":"DE",
    "wof:name":"Fuerstenhagen",
    "wof:placetype":"neighbourhood"
},
  "geometry": {"coordinates":[9.64651,51.57387],"type":"Point"}
}