{
  "type": "Feature",
  "properties": {
    "gn:admin1_code":"7",
    "gn:admin2_code":"53.0",
    "gn:admin3_code":"5382.0",
    "gn:admin4_code":"5382028.0",
    "gn:asciiname":"Eigen",
    "gn:country_code":"DE",
    "gn:dem":216,
    "gn:feature_class":"P",
    "gn:feature_code":"PPL",
    "gn:name":"Eigen",
    "gn:population":0,
    "gn:timezone":"Europe/Berlin",
    "iso:country":"DE",
    "name:ceb_x_preferred":[
        "Eigen"
    ],
    "name:deu_x_preferred":[
        "Eigen"
    ],
    "name:epo_x_preferred":[
        "Eigen"
    ],
    "name:fra_x_preferred":[
        "Eigen"
    ],
    "name:pol_x_preferred":[
        "Eigen"
    ],
    "name:spa_x_preferred":[
        "Eigen"
    ],
    "name:swe_x_preferred":[
        "Eigen"
    ],
    "wof:name":"Eigen",
    "wof:placetype":"neighbourhood"
},
  "geometry": {"coordinates":[7.23239,50.91291],"type":"Point"}
}