{
  "type": "Feature",
  "properties": {
    "gn:admin1_code":"2",
    "gn:admin2_code":"93.0",
    "gn:admin3_code":"9376.0",
    "gn:admin4_code":"9376164.0",
    "gn:asciiname":"Meischendorf",
    "gn:country_code":"DE",
    "gn:dem":376,
    "gn:feature_class":"P",
    "gn:feature_code":"PPL",
    "gn:name":"Meischendorf",
    "gn:population":0,
    "gn:timezone":"Europe/Berlin",
    "iso:country":"DE",
    "wof:name":"Meischendorf",
    "wof:placetype":"neighbourhood"
},
  "geometry": {"coordinates":[12.30184,49.39359],"type":"Point"}
}