{
  "type": "Feature",
  "properties": {
    "gn:admin1_code":"12",
    "gn:admin2_code":"0.0",
    "gn:admin3_code":"13076.0",
    "gn:admin4_code":"13076049.0",
    "gn:asciiname":"Grittel",
    "gn:country_code":"DE",
    "gn:dem":23,
    "gn:feature_class":"P",
    "gn:feature_code":"PPL",
    "gn:name":"Grittel",
    "gn:population":0,
    "gn:timezone":"Europe/Berlin",
    "iso:country":"DE",
    "wof:name":"Grittel",
    "wof:placetype":"neighbourhood"
},
  "geometry": {"coordinates":[11.43295,53.16013],"type":"Point"}
}