{
  "type": "Feature",
  "properties": {
    "gn:admin1_code":"5.0",
    "gn:admin2_code":"65.0",
    "gn:admin3_code":"6532.0",
    "gn:admin4_code":"6532014.0",
    "gn:asciiname":"Rechtenbach",
    "gn:country_code":"DE",
    "gn:dem":189,
    "gn:feature_class":"P",
    "gn:feature_code":"PPL",
    "gn:name":"Rechtenbach",
    "gn:population":0,
    "gn:timezone":"Europe/Berlin",
    "iso:country":"DE",
    "name:ceb_x_preferred":[
        "Rechtenbach"
    ],
    "name:dan_x_preferred":[
        "Rechtenbach"
    ],
    "name:deu_x_preferred":[
        "Rechtenbach"
    ],
    "name:epo_x_preferred":[
        "Rechtenbach"
    ],
    "name:eus_x_preferred":[
        "Rechtenbach"
    ],
    "name:fas_x_preferred":[
        "\u0631\u0627\u0634\u062a\u0646\u0628\u0627\u062e"
    ],
    "name:fra_x_preferred":[
        "Rechtenbach"
    ],
    "name:hun_x_preferred":[
        "Rechtenbach"
    ],
    "name:hye_x_preferred":[
        "\u054c\u0565\u056d\u057f\u0565\u0576\u0562\u0561\u056d"
    ],
    "name:ind_x_preferred":[
        "Rechtenbach"
    ],
    "name:ita_x_preferred":[
        "Rechtenbach"
    ],
    "name:kaz_x_preferred":[
        "\u0420\u0435\u0445\u0442\u0435\u043d\u0431\u0430\u0445"
    ],
    "name:kir_x_preferred":[
        "\u0420\u0435\u0445\u0442\u0435\u043d\u0431\u0430\u0445"
    ],
    "name:lmo_x_preferred":[
        "Rechtenbach"
    ],
    "name:msa_x_preferred":[
        "Rechtenbach"
    ],
    "name:nld_x_preferred":[
        "Rechtenbach"
    ],
    "name:pol_x_preferred":[
        "Rechtenbach"
    ],
    "name:por_x_preferred":[
        "Rechtenbach"
    ],
    "name:ron_x_preferred":[
        "Rechtenbach"
    ],
    "name:rus_x_preferred":[
        "\u0420\u0435\u0445\u0442\u0435\u043d\u0431\u0430\u0445"
    ],
    "name:spa_x_preferred":[
        "Rechtenbach"
    ],
    "name:srp_x_preferred":[
        "\u0420\u0435\u0445\u0442\u0435\u043d\u0431\u0430\u0445"
    ],
    "name:ukr_x_preferred":[
        "\u0420\u0435\u0445\u0442\u0435\u043d\u0431\u0430\u0445"
    ],
    "name:uzb_x_preferred":[
        "Rechtenbach"
    ],
    "name:vol_x_preferred":[
        "Rechtenbach"
    ],
    "name:war_x_preferred":[
        "Rechtenbach"
    ],
    "name:zho_x_preferred":[
        "\u96f7\u5e0c\u6ed5\u5df4\u8d6b"
    ],
    "wof:name":"Rechtenbach",
    "wof:placetype":"neighbourhood"
},
  "geometry": {"coordinates":[8.62062,50.51905],"type":"Point"}
}