{
  "type": "Feature",
  "properties": {
    "gn:admin1_code":"5.0",
    "gn:admin2_code":"65.0",
    "gn:admin3_code":"6532.0",
    "gn:admin4_code":"6532014.0",
    "gn:asciiname":"Rechtenbach",
    "gn:country_code":"DE",
    "gn:dem":189,
    "gn:feature_class":"P",
    "gn:feature_code":"PPL",
    "gn:name":"Rechtenbach",
    "gn:population":0,
    "gn:timezone":"Europe/Berlin",
    "iso:country":"DE",
    "wof:name":"Rechtenbach",
    "wof:placetype":"neighbourhood"
},
  "geometry": {"coordinates":[8.62062,50.51905],"type":"Point"}
}