{
  "type": "Feature",
  "properties": {
    "gn:admin1_code":"13",
    "gn:admin2_code":"0.0",
    "gn:admin3_code":"14625.0",
    "gn:admin4_code":"14625480.0",
    "gn:asciiname":"Liegau-Augustusbad",
    "gn:country_code":"DE",
    "gn:dem":246,
    "gn:feature_class":"P",
    "gn:feature_code":"PPL",
    "gn:name":"Liegau-Augustusbad",
    "gn:population":0,
    "gn:timezone":"Europe/Berlin",
    "iso:country":"DE",
    "name:deu_x_preferred":[
        "Liegau-Augustusbad"
    ],
    "wof:name":"Liegau-Augustusbad",
    "wof:placetype":"neighbourhood"
},
  "geometry": {"coordinates":[13.87786,51.13701],"type":"Point"}
}