{
  "type": "Feature",
  "properties": {
    "gn:admin1_code":"1",
    "gn:admin2_code":"81.0",
    "gn:admin3_code":"8126.0",
    "gn:admin4_code":"8126046.0",
    "gn:asciiname":"Morsbach",
    "gn:country_code":"DE",
    "gn:dem":257,
    "gn:feature_class":"P",
    "gn:feature_code":"PPL",
    "gn:name":"Morsbach",
    "gn:population":0,
    "gn:timezone":"Europe/Berlin",
    "iso:country":"DE",
    "name:deu_x_preferred":[
        "Morsbach"
    ],
    "name:epo_x_preferred":[
        "Morsbach"
    ],
    "name:eus_x_preferred":[
        "Morsbach"
    ],
    "name:fas_x_preferred":[
        "\u0645\u0648\u0631\u0633\u0628\u0627\u062e"
    ],
    "name:fra_x_preferred":[
        "Morsbach"
    ],
    "name:hun_x_preferred":[
        "Morsbach"
    ],
    "name:ita_x_preferred":[
        "Morsbach"
    ],
    "name:kaz_x_preferred":[
        "\u041c\u043e\u0440\u0441\u0431\u0430\u0445"
    ],
    "name:kir_x_preferred":[
        "\u041c\u043e\u0440\u0441\u0431\u0430\u0445"
    ],
    "name:lim_x_preferred":[
        "Morsbach"
    ],
    "name:msa_x_preferred":[
        "Morsbach"
    ],
    "name:nld_x_preferred":[
        "Morsbach"
    ],
    "name:pol_x_preferred":[
        "Morsbach"
    ],
    "name:ron_x_preferred":[
        "Morsbach"
    ],
    "name:rus_x_preferred":[
        "\u041c\u043e\u0440\u0441\u0431\u0430\u0445"
    ],
    "name:spa_x_preferred":[
        "Morsbach"
    ],
    "name:srp_x_preferred":[
        "\u041c\u043e\u0440\u0441\u0431\u0430\u0445"
    ],
    "name:ukr_x_preferred":[
        "\u041c\u043e\u0440\u0441\u0431\u0430\u0445"
    ],
    "name:vie_x_preferred":[
        "Morsbach"
    ],
    "name:vol_x_preferred":[
        "Morsbach"
    ],
    "name:war_x_preferred":[
        "Morsbach"
    ],
    "name:zho_x_preferred":[
        "\u83ab\u65af\u5df4\u8d6b"
    ],
    "wof:name":"Morsbach",
    "wof:placetype":"neighbourhood"
},
  "geometry": {"coordinates":[9.72542,49.27583],"type":"Point"}
}