{
  "type": "Feature",
  "properties": {
    "gn:admin1_code":"2",
    "gn:admin2_code":"91.0",
    "gn:admin3_code":"9177.0",
    "gn:admin4_code":"9177137.0",
    "gn:asciiname":"Pyramoos",
    "gn:country_code":"DE",
    "gn:dem":554,
    "gn:feature_class":"P",
    "gn:feature_code":"PPL",
    "gn:name":"Pyramoos",
    "gn:population":0,
    "gn:timezone":"Europe/Berlin",
    "iso:country":"DE",
    "wof:name":"Pyramoos",
    "wof:placetype":"neighbourhood"
},
  "geometry": {"coordinates":[12.12526,48.18829],"type":"Point"}
}