{
  "type": "Feature",
  "properties": {
    "iso:country":"DE",
    "name:deu_x_preferred":[
        "Hosterwitz/pillnitz"
    ],
    "qs:gn_local":0,
    "qs:local_max":13108,
    "qs:local_sum":52556,
    "qs:localhoods":61,
    "qs:name":"Hosterwitz/pillnitz",
    "qs:name_adm0":"Deutschland",
    "qs:name_adm1":"Sachsen",
    "qs:name_adm2":"Kreisfreie Stadt Dresden",
    "qs:name_lau":"Stadtteil Hosterwitz",
    "qs:name_local":"Dresden",
    "qs:photo_max":145,
    "qs:photo_sum":1115,
    "qs:placetype":"Suburb",
    "qs:quad_count":53,
    "qs:woe_adm0":23424829,
    "qs:woe_adm1":2345493,
    "qs:woe_adm2":12596943,
    "qs:woe_lau":26822193,
    "qs:woe_local":645686,
    "qs:woe_ver":"7.10.0",
    "wof:lang":[
        "ger"
    ],
    "wof:name":"Hosterwitz",
    "wof:placetype":"neighbourhood"
},
  "geometry": {"coordinates":[13.861698,51.015666],"type":"Point"}
}