{
  "type": "Feature",
  "properties": {
    "gn:admin1_code":"1",
    "gn:admin2_code":"83.0",
    "gn:admin3_code":"8317.0",
    "gn:admin4_code":"8317098.0",
    "gn:asciiname":"Ibach",
    "gn:country_code":"DE",
    "gn:dem":295,
    "gn:feature_class":"P",
    "gn:feature_code":"PPL",
    "gn:name":"Ibach",
    "gn:population":0,
    "gn:timezone":"Europe/Berlin",
    "iso:country":"DE",
    "name:als_x_preferred":[
        "Ibach"
    ],
    "name:ceb_x_preferred":[
        "Ibach"
    ],
    "name:deu_x_preferred":[
        "Ibach"
    ],
    "name:epo_x_preferred":[
        "Ibach"
    ],
    "name:fra_x_preferred":[
        "Ibach"
    ],
    "name:ita_x_preferred":[
        "Ibach"
    ],
    "name:nld_x_preferred":[
        "Ibach"
    ],
    "name:pol_x_preferred":[
        "Ibach"
    ],
    "name:rus_x_preferred":[
        "\u0418\u0431\u0430\u0445"
    ],
    "name:swe_x_preferred":[
        "Ibach"
    ],
    "wof:name":"Ibach",
    "wof:placetype":"neighbourhood"
},
  "geometry": {"coordinates":[8.16295,48.45474],"type":"Point"}
}