{
  "type": "Feature",
  "properties": {
    "iso:country":"DE",
    "name:deu_x_preferred":[
        "St. John\u2019s Church"
    ],
    "wof:name":"St. Johannis",
    "wof:placetype":"neighbourhood"
},
  "geometry": {"coordinates":[11.06596754734976,49.45940952359807],"type":"Point"}
}