{
  "type": "Feature",
  "properties": {
    "gn:admin1_code":"1.0",
    "gn:admin2_code":"81.0",
    "gn:admin3_code":"8126.0",
    "gn:admin4_code":"8126085.0",
    "gn:asciiname":"Bahnhofsiedlung",
    "gn:country_code":"DE",
    "gn:dem":353,
    "gn:feature_class":"P",
    "gn:feature_code":"PPL",
    "gn:name":"Bahnhofsiedlung",
    "gn:population":0,
    "gn:timezone":"Europe/Berlin",
    "iso:country":"DE",
    "wof:name":"Bahnhofsiedlung",
    "wof:placetype":"neighbourhood"
},
  "geometry": {"coordinates":[9.66702,49.19913],"type":"Point"}
}