{
  "type": "Feature",
  "properties": {
    "gn:admin1_code":"7",
    "gn:admin2_code":"57.0",
    "gn:admin3_code":"5766.0",
    "gn:admin4_code":"5766024.0",
    "gn:asciiname":"Krubberg",
    "gn:country_code":"DE",
    "gn:dem":241,
    "gn:feature_class":"P",
    "gn:feature_code":"PPL",
    "gn:name":"Krubberg",
    "gn:population":0,
    "gn:timezone":"Europe/Berlin",
    "iso:country":"DE",
    "wof:name":"Krubberg",
    "wof:placetype":"neighbourhood"
},
  "geometry": {"coordinates":[9.01368,52.06294000000001],"type":"Point"}
}