{
  "type": "Feature",
  "properties": {
    "gn:admin1_code":"7",
    "gn:admin2_code":"59.0",
    "gn:admin3_code":"5970.0",
    "gn:admin4_code":"5970032.0",
    "gn:asciiname":"Irmgarteichen",
    "gn:country_code":"DE",
    "gn:dem":410,
    "gn:feature_class":"P",
    "gn:feature_code":"PPL",
    "gn:name":"Irmgarteichen",
    "gn:population":0,
    "gn:timezone":"Europe/Berlin",
    "iso:country":"DE",
    "name:und_x_variant":[
        "Irmgardeichen",
        "Irmgarteichen"
    ],
    "wof:name":"Irmgarteichen",
    "wof:placetype":"neighbourhood"
},
  "geometry": {"coordinates":[8.1978,50.85708],"type":"Point"}
}