{
  "type": "Feature",
  "properties": {
    "gn:admin1_code":"5",
    "gn:admin2_code":"64.0",
    "gn:admin3_code":"6435.0",
    "gn:admin4_code":"6435019.0",
    "gn:asciiname":"Hochstadt",
    "gn:country_code":"DE",
    "gn:dem":124,
    "gn:feature_class":"P",
    "gn:feature_code":"PPL",
    "gn:name":"Hochstadt",
    "gn:population":0,
    "gn:timezone":"Europe/Berlin",
    "iso:country":"DE",
    "name:deu_x_preferred":[
        "Hochstadt"
    ],
    "name:fra_x_preferred":[
        "Hochstadt"
    ],
    "name:lat_x_preferred":[
        "Maintal-Hochstadt"
    ],
    "name:nld_x_preferred":[
        "Maintal-Hochstadt"
    ],
    "wof:name":"Hochstadt",
    "wof:placetype":"neighbourhood"
},
  "geometry": {"coordinates":[8.83578,50.15313],"type":"Point"}
}