{
  "type": "Feature",
  "properties": {
    "iso:country":"DE",
    "name:deu_x_preferred":[
        "Lirich"
    ],
    "name:unk_x_variant":[
        "Lirich"
    ],
    "qs:gn_local":0,
    "qs:local_max":2572,
    "qs:local_sum":4350,
    "qs:localhoods":10,
    "qs:name":"Lirich",
    "qs:name_adm0":"Deutschland",
    "qs:name_adm1":"Nordrhein-Westfalen",
    "qs:name_adm2":"Stadtkreis Oberhausen",
    "qs:name_lau":"Lirich-Nord",
    "qs:name_local":"Oberhausen",
    "qs:photo_max":158,
    "qs:photo_sum":393,
    "qs:placetype":"Suburb",
    "qs:quad_count":37,
    "qs:woe_adm0":23424829,
    "qs:woe_adm1":2345487,
    "qs:woe_adm2":12596983,
    "qs:woe_lau":26823131,
    "qs:woe_local":681362,
    "qs:woe_ver":"7.10.0",
    "wof:lang":[
        "ger"
    ],
    "wof:name":"Lirich",
    "wof:placetype":"neighbourhood"
},
  "geometry": {"coordinates":[6.835062,51.480814],"type":"Point"}
}