{
  "type": "Feature",
  "properties": {
    "gn:admin1_code":"10",
    "gn:admin2_code":"0.0",
    "gn:admin3_code":"1059.0",
    "gn:admin4_code":"1059185.0",
    "gn:asciiname":"Rehberg",
    "gn:country_code":"DE",
    "gn:dem":37,
    "gn:feature_class":"P",
    "gn:feature_code":"PPL",
    "gn:name":"Rehberg",
    "gn:population":0,
    "gn:timezone":"Europe/Berlin",
    "iso:country":"DE",
    "name:ceb_x_preferred":[
        "Rehberg"
    ],
    "name:deu_x_preferred":[
        "Rehberg"
    ],
    "name:epo_x_preferred":[
        "Rehberg"
    ],
    "name:fra_x_preferred":[
        "Rehberg"
    ],
    "name:pol_x_preferred":[
        "Rehberg"
    ],
    "name:swe_x_preferred":[
        "Rehberg"
    ],
    "wof:name":"Rehberg",
    "wof:placetype":"neighbourhood"
},
  "geometry": {"coordinates":[9.61667,54.68333000000001],"type":"Point"}
}