{
  "type": "Feature",
  "properties": {
    "gn:admin1_code":"5",
    "gn:admin2_code":"64.0",
    "gn:admin3_code":"6440.0",
    "gn:admin4_code":"6440013.0",
    "gn:asciiname":"Hitzkirchen",
    "gn:country_code":"DE",
    "gn:dem":313,
    "gn:feature_class":"P",
    "gn:feature_code":"PPL",
    "gn:name":"Hitzkirchen",
    "gn:population":0,
    "gn:timezone":"Europe/Berlin",
    "iso:country":"DE",
    "wof:name":"Hitzkirchen",
    "wof:placetype":"neighbourhood"
},
  "geometry": {"coordinates":[9.25296,50.34378],"type":"Point"}
}