{
  "type": "Feature",
  "properties": {
    "gn:admin1_code":"11",
    "gn:admin2_code":"0.0",
    "gn:admin3_code":"12069.0",
    "gn:admin4_code":"12069604.0",
    "gn:asciiname":"Marggraffshof",
    "gn:country_code":"DE",
    "gn:dem":43,
    "gn:feature_class":"P",
    "gn:feature_code":"PPL",
    "gn:name":"Marggraffshof",
    "gn:population":0,
    "gn:timezone":"Europe/Berlin",
    "iso:country":"DE",
    "wof:name":"Marggraffshof",
    "wof:placetype":"neighbourhood"
},
  "geometry": {"coordinates":[13.23898,52.3602],"type":"Point"}
}