{
  "type": "Feature",
  "properties": {
    "gn:admin1_code":"10",
    "gn:admin2_code":"0.0",
    "gn:admin3_code":"1055.0",
    "gn:admin4_code":"1055042.0",
    "gn:asciiname":"Hemmelsdorf",
    "gn:country_code":"DE",
    "gn:dem":5,
    "gn:feature_class":"P",
    "gn:feature_code":"PPL",
    "gn:name":"Hemmelsdorf",
    "gn:population":0,
    "gn:timezone":"Europe/Berlin",
    "iso:country":"DE",
    "wof:name":"Hemmelsdorf",
    "wof:placetype":"neighbourhood"
},
  "geometry": {"coordinates":[10.77089,53.97004],"type":"Point"}
}