{
  "type": "Feature",
  "properties": {
    "gn:admin1_code":"2.0",
    "gn:admin2_code":"91.0",
    "gn:admin3_code":"9183.0",
    "gn:admin4_code":"9183132.0",
    "gn:asciiname":"Asenham",
    "gn:country_code":"DE",
    "gn:dem":462,
    "gn:feature_class":"P",
    "gn:feature_code":"PPL",
    "gn:name":"Asenham",
    "gn:population":0,
    "gn:timezone":"Europe/Berlin",
    "iso:country":"DE",
    "wof:name":"Asenham",
    "wof:placetype":"neighbourhood"
},
  "geometry": {"coordinates":[12.37256,48.31213],"type":"Point"}
}