{
  "type": "Feature",
  "properties": {
    "gn:admin1_code":"11",
    "gn:admin2_code":"0.0",
    "gn:admin3_code":"12053.0",
    "gn:admin4_code":"12053000.0",
    "gn:asciiname":"Sandgrund",
    "gn:country_code":"DE",
    "gn:dem":84,
    "gn:feature_class":"P",
    "gn:feature_code":"PPL",
    "gn:name":"Sandgrund",
    "gn:population":0,
    "gn:timezone":"Europe/Berlin",
    "iso:country":"DE",
    "wof:name":"Sandgrund",
    "wof:placetype":"neighbourhood"
},
  "geometry": {"coordinates":[14.51667,52.33333],"type":"Point"}
}