{
  "type": "Feature",
  "properties": {
    "gn:admin1_code":"13",
    "gn:admin2_code":"0.0",
    "gn:admin3_code":"14713.0",
    "gn:admin4_code":"14713000.0",
    "gn:asciiname":"Doesen",
    "gn:country_code":"DE",
    "gn:dem":134,
    "gn:feature_class":"P",
    "gn:feature_code":"PPL",
    "gn:name":"D\u00f6sen",
    "gn:population":0,
    "gn:timezone":"Europe/Berlin",
    "iso:country":"DE",
    "name:deu_x_preferred":[
        "D\u00f6sen"
    ],
    "wof:name":"Doesen",
    "wof:placetype":"neighbourhood"
},
  "geometry": {"coordinates":[12.408265,51.28519],"type":"Point"}
}