{
  "type": "Feature",
  "properties": {
    "iso:country":"DE",
    "wof:name":"Althen",
    "wof:placetype":"neighbourhood"
},
  "geometry": {"coordinates":[12.52084020583926,51.34183940872719],"type":"Point"}
}