{
  "type": "Feature",
  "properties": {
    "gn:admin1_code":"12",
    "gn:admin2_code":"0.0",
    "gn:admin3_code":"13071.0",
    "gn:admin4_code":"13071101.0",
    "gn:asciiname":"Freidorf",
    "gn:country_code":"DE",
    "gn:dem":81,
    "gn:feature_class":"P",
    "gn:feature_code":"PPL",
    "gn:name":"Freidorf",
    "gn:population":0,
    "gn:timezone":"Europe/Berlin",
    "iso:country":"DE",
    "name:deu_x_preferred":[
        "Freidorf"
    ],
    "name:epo_x_preferred":[
        "Freidorf"
    ],
    "name:hun_x_preferred":[
        "Szabadfalu"
    ],
    "name:nld_x_preferred":[
        "Freidorf"
    ],
    "name:ron_x_preferred":[
        "Freidorf"
    ],
    "name:srp_x_preferred":[
        "\u0424\u0440\u0430\u0458\u0434\u043e\u0440\u0444"
    ],
    "wof:name":"Freidorf",
    "wof:placetype":"neighbourhood"
},
  "geometry": {"coordinates":[12.91117,53.49356],"type":"Point"}
}