{
  "type": "Feature",
  "properties": {
    "gn:country":"DE",
    "gn:fcode":"PPL",
    "gn:population":0,
    "iso:country":"DE",
    "name:ceb_x_preferred":[
        "Dahlen"
    ],
    "name:deu_x_preferred":[
        "Dahlen"
    ],
    "name:epo_x_preferred":[
        "Dahlen"
    ],
    "name:est_x_preferred":[
        "Dahlen"
    ],
    "name:fra_x_preferred":[
        "Dahlen"
    ],
    "name:ita_x_preferred":[
        "Dahlen"
    ],
    "name:kaz_x_preferred":[
        "\u0414\u0430\u043b\u0435\u043d"
    ],
    "name:kir_x_preferred":[
        "\u0414\u0430\u043b\u0435\u043d"
    ],
    "name:lav_x_preferred":[
        "Dahlen"
    ],
    "name:nds_x_preferred":[
        "Dahlen"
    ],
    "name:nld_x_preferred":[
        "Dahlen"
    ],
    "name:pol_x_preferred":[
        "Dahlen"
    ],
    "name:rus_x_preferred":[
        "\u0414\u0430\u043b\u0435\u043d"
    ],
    "name:vol_x_preferred":[
        "Dahlen"
    ],
    "qs_pg:aaroncc":"DE",
    "qs_pg:gn_country":"DE",
    "qs_pg:gn_fcode":"PPL",
    "qs_pg:gn_pop":0,
    "qs_pg:name":"Dahlen",
    "qs_pg:name_adm0":"Deutschland",
    "qs_pg:name_adm1":"Rheinland-Pfalz",
    "qs_pg:photos_9r":0,
    "qs_pg:photos_sr":0,
    "qs_pg:pop_sr":0,
    "qs_pg:qs_pg_placetype":"locality",
    "qs_pg:qs_pg_placetype_gp":"Town",
    "qs_pg:woe_adm0":23424829,
    "woe:adm0_id":23424829,
    "woe:name_adm0":"Deutschland",
    "woe:name_adm1":"Rheinland-Pfalz",
    "woe:placetype":"Town",
    "wof:name":"Dahlen",
    "wof:placetype":"neighbourhood"
},
  "geometry": {"coordinates":[7.90028,50.47902],"type":"Point"}
}