{
  "type": "Feature",
  "properties": {
    "gn:admin1_code":"13",
    "gn:admin2_code":"0.0",
    "gn:admin3_code":"14523.0",
    "gn:admin4_code":"14523430.0",
    "gn:asciiname":"Pfaffengruen",
    "gn:country_code":"DE",
    "gn:dem":454,
    "gn:feature_class":"P",
    "gn:feature_code":"PPL",
    "gn:name":"Pfaffengr\u00fcn",
    "gn:population":0,
    "gn:timezone":"Europe/Berlin",
    "iso:country":"DE",
    "name:und_x_variant":[
        "Hartmannsgr\u00fcn-Pfaffengr\u00fcn",
        "Pfaffengr\u00fcn"
    ],
    "wof:name":"Pfaffengruen",
    "wof:placetype":"neighbourhood"
},
  "geometry": {"coordinates":[12.27614,50.56129],"type":"Point"}
}