{
  "type": "Feature",
  "properties": {
    "gn:admin1_code":"13",
    "gn:admin2_code":"0.0",
    "gn:admin3_code":"14524.0",
    "gn:admin4_code":"14524080.0",
    "gn:asciiname":"Voigtlaide",
    "gn:country_code":"DE",
    "gn:dem":323,
    "gn:feature_class":"P",
    "gn:feature_code":"PPL",
    "gn:name":"Voigtlaide",
    "gn:population":0,
    "gn:timezone":"Europe/Berlin",
    "iso:country":"DE",
    "wof:name":"Voigtlaide",
    "wof:placetype":"neighbourhood"
},
  "geometry": {"coordinates":[12.55584,50.78923],"type":"Point"}
}