{
  "type": "Feature",
  "properties": {
    "gn:admin1_code":"8",
    "gn:admin2_code":"0.0",
    "gn:admin3_code":"7133.0",
    "gn:admin4_code":"7133035.0",
    "gn:asciiname":"Waldhilbersheim",
    "gn:country_code":"DE",
    "gn:dem":152,
    "gn:feature_class":"P",
    "gn:feature_code":"PPL",
    "gn:name":"Waldhilbersheim",
    "gn:population":0,
    "gn:timezone":"Europe/Berlin",
    "iso:country":"DE",
    "wof:name":"Waldhilbersheim",
    "wof:placetype":"neighbourhood"
},
  "geometry": {"coordinates":[7.83422,49.89562],"type":"Point"}
}