{
  "type": "Feature",
  "properties": {
    "gn:admin1_code":"6",
    "gn:admin2_code":"0.0",
    "gn:admin3_code":"3457.0",
    "gn:admin4_code":"3457020.0",
    "gn:asciiname":"Stapel",
    "gn:country_code":"DE",
    "gn:dem":11,
    "gn:feature_class":"P",
    "gn:feature_code":"PPL",
    "gn:name":"Stapel",
    "gn:population":0,
    "gn:timezone":"Europe/Berlin",
    "iso:country":"DE",
    "name:deu_x_preferred":[
        "Stapel"
    ],
    "name:fra_x_preferred":[
        "Stapel"
    ],
    "name:nds_x_preferred":[
        "Stapel"
    ],
    "name:nld_x_preferred":[
        "Stapel"
    ],
    "name:rus_x_preferred":[
        "\u0428\u0442\u0430\u043f\u0435\u043b\u044c"
    ],
    "name:swe_x_preferred":[
        "Stapel"
    ],
    "name:ukr_x_preferred":[
        "\u0428\u0442\u0430\u043f\u0435\u043b\u044c"
    ],
    "wof:name":"Stapel",
    "wof:placetype":"neighbourhood"
},
  "geometry": {"coordinates":[7.81751,53.32569],"type":"Point"}
}