{
  "type": "Feature",
  "properties": {
    "gn:country":"DE",
    "gn:fcode":"PPL",
    "gn:population":489,
    "iso:country":"DE",
    "name:ceb_x_preferred":[
        "Zella"
    ],
    "name:deu_x_preferred":[
        "Zella"
    ],
    "name:ita_x_preferred":[
        "Zella"
    ],
    "name:nld_x_preferred":[
        "Zella"
    ],
    "name:pol_x_preferred":[
        "Zella"
    ],
    "name:swe_x_preferred":[
        "Zella"
    ],
    "qs_pg:aaroncc":"DE",
    "qs_pg:gn_country":"DE",
    "qs_pg:gn_fcode":"PPL",
    "qs_pg:gn_pop":489,
    "qs_pg:name":"Zella",
    "qs_pg:name_adm0":"Deutschland",
    "qs_pg:name_adm1":"Th\u00fcringen",
    "qs_pg:photos_9k":1,
    "qs_pg:photos_9r":1,
    "qs_pg:photos_all":3,
    "qs_pg:photos_sr":0,
    "qs_pg:pop_sr":2,
    "qs_pg:qs_pg_placetype":"locality",
    "qs_pg:qs_pg_placetype_gp":"Town",
    "qs_pg:woe_adm0":23424829,
    "woe:adm0_id":23424829,
    "woe:name_adm0":"Deutschland",
    "woe:name_adm1":"Th\u00fcringen",
    "woe:placetype":"Town",
    "wof:name":"Zella",
    "wof:placetype":"neighbourhood",
    "wof:population":489
},
  "geometry": {"coordinates":[10.10785,50.67162],"type":"Point"}
}