{
  "type": "Feature",
  "properties": {
    "gn:admin1_code":"7",
    "gn:admin2_code":"59.0",
    "gn:admin3_code":"5958.0",
    "gn:admin4_code":"5958044.0",
    "gn:asciiname":"Hellefeld",
    "gn:country_code":"DE",
    "gn:dem":358,
    "gn:feature_class":"P",
    "gn:feature_code":"PPL",
    "gn:name":"Hellefeld",
    "gn:population":0,
    "gn:timezone":"Europe/Berlin",
    "iso:country":"DE",
    "name:osx_x_preferred":[
        "Helifeldun"
    ],
    "wof:name":"Hellefeld",
    "wof:placetype":"locality"
},
  "geometry": {"coordinates":[8.08924,51.33212],"type":"Point"}
}