{
  "type": "Feature",
  "properties": {
    "gn:admin1_code":"2.0",
    "gn:admin2_code":"094",
    "gn:admin3_code":"9474.0",
    "gn:admin4_code":"9474145.0",
    "gn:asciiname":"Weingarts",
    "gn:country_code":"DE",
    "gn:dem":357,
    "gn:feature_class":"P",
    "gn:feature_code":"PPL",
    "gn:name":"Weingarts",
    "gn:population":0,
    "gn:timezone":"Europe/Berlin",
    "iso:country":"DE",
    "wof:name":"Weingarts",
    "wof:placetype":"neighbourhood"
},
  "geometry": {"coordinates":[11.17108,49.67313],"type":"Point"}
}