{
  "type": "Feature",
  "properties": {
    "gn:admin1_code":"7",
    "gn:admin2_code":"59.0",
    "gn:admin3_code":"5913.0",
    "gn:admin4_code":"5913000.0",
    "gn:asciiname":"Fleier",
    "gn:country_code":"DE",
    "gn:dem":68,
    "gn:feature_class":"P",
    "gn:feature_code":"PPL",
    "gn:name":"Fleier",
    "gn:population":0,
    "gn:timezone":"Europe/Berlin",
    "iso:country":"DE",
    "wof:name":"Fleier",
    "wof:placetype":"neighbourhood"
},
  "geometry": {"coordinates":[7.58451,51.54924000000001],"type":"Point"}
}