{
  "type": "Feature",
  "properties": {
    "gn:admin1_code":"2",
    "gn:admin2_code":"91.0",
    "gn:admin3_code":"9178.0",
    "gn:admin4_code":"9178157.0",
    "gn:asciiname":"Palzing",
    "gn:country_code":"DE",
    "gn:dem":439,
    "gn:feature_class":"P",
    "gn:feature_code":"PPL",
    "gn:name":"Palzing",
    "gn:population":0,
    "gn:timezone":"Europe/Berlin",
    "iso:country":"DE",
    "wof:name":"Palzing",
    "wof:placetype":"neighbourhood"
},
  "geometry": {"coordinates":[11.70783,48.45965],"type":"Point"}
}