{
  "type": "Feature",
  "properties": {
    "gn:gn_country":"DE",
    "gn:gn_fcode":"PPLA4",
    "gn:gn_pop":289,
    "gn:population":289,
    "iso:country":"DE",
    "name:baq_x_preferred":[
        "Ellweiler"
    ],
    "name:chi_x_preferred":[
        "\u57c3\u5c14\u9b4f\u83b1\u5c14"
    ],
    "name:dut_x_preferred":[
        "Ellweiler"
    ],
    "name:eng_x_preferred":[
        "Ellweiler"
    ],
    "name:epo_x_preferred":[
        "Ellweiler"
    ],
    "name:fre_x_preferred":[
        "Ellweiler"
    ],
    "name:ger_x_preferred":[
        "Ellweiler"
    ],
    "name:hun_x_preferred":[
        "Ellweiler"
    ],
    "name:ita_x_preferred":[
        "Ellweiler"
    ],
    "name:jpn_x_preferred":[
        "\u30a8\u30eb\u30f4\u30a1\u30a4\u30e9\u30fc"
    ],
    "name:kaz_x_preferred":[
        "\u042d\u043b\u044c\u0432\u0430\u0439\u043b\u0435\u0440"
    ],
    "name:kir_x_preferred":[
        "\u042d\u043b\u044c\u0432\u0430\u0439\u043b\u0435\u0440"
    ],
    "name:may_x_preferred":[
        "Ellweiler"
    ],
    "name:per_x_preferred":[
        "\u0627\u0644\u0648\u0627\u06cc\u0644\u0631"
    ],
    "name:pol_x_preferred":[
        "Ellweiler"
    ],
    "name:por_x_preferred":[
        "Ellweiler"
    ],
    "name:rum_x_preferred":[
        "Ellweiler"
    ],
    "name:rus_x_preferred":[
        "\u042d\u043b\u044c\u0432\u0430\u0439\u043b\u0435\u0440"
    ],
    "name:spa_x_preferred":[
        "Ellweiler"
    ],
    "name:srp_x_preferred":[
        "\u0415\u043b\u0432\u0430\u0458\u043b\u0435\u0440"
    ],
    "name:ukr_x_preferred":[
        "\u0415\u043b\u044c\u0432\u0430\u0439\u043b\u0435\u0440"
    ],
    "name:uzb_x_preferred":[
        "Ellweiler"
    ],
    "name:vie_x_preferred":[
        "Ellweiler"
    ],
    "name:vol_x_preferred":[
        "Ellweiler"
    ],
    "name:war_x_preferred":[
        "Ellweiler"
    ],
    "qs_pg:aaroncc":"DE",
    "qs_pg:gn_country":"DE",
    "qs_pg:gn_fcode":"PPLA4",
    "qs_pg:gn_pop":289,
    "qs_pg:name":"Ellweiler",
    "qs_pg:photos_9r":0,
    "qs_pg:photos_sr":0,
    "qs_pg:pop_sr":2,
    "qs_pg:qs_pg_placetype":"locality",
    "wof:name":"Ellweiler",
    "wof:placetype":"locality",
    "wof:population":289
},
  "geometry": {"coordinates":[7.15,49.61667],"type":"Point"}
}