{
  "type": "Feature",
  "properties": {
    "gn:admin1_code":"7.0",
    "gn:admin2_code":"55.0",
    "gn:admin3_code":"5566.0",
    "gn:admin4_code":"5566020.0",
    "gn:asciiname":"Bertlingen",
    "gn:country_code":"DE",
    "gn:dem":39,
    "gn:feature_class":"P",
    "gn:feature_code":"PPL",
    "gn:name":"Bertlingen",
    "gn:population":0,
    "gn:timezone":"Europe/Berlin",
    "iso:country":"DE",
    "wof:name":"Bertlingen",
    "wof:placetype":"neighbourhood"
},
  "geometry": {"coordinates":[7.64485,52.45484],"type":"Point"}
}