{
  "type": "Feature",
  "properties": {
    "gn:admin1_code":"7",
    "gn:admin2_code":"57.0",
    "gn:admin3_code":"5774.0",
    "gn:admin4_code":"5774016.0",
    "gn:asciiname":"Weiberg",
    "gn:country_code":"DE",
    "gn:dem":344,
    "gn:feature_class":"P",
    "gn:feature_code":"PPL",
    "gn:name":"Weiberg",
    "gn:population":0,
    "gn:timezone":"Europe/Berlin",
    "iso:country":"DE",
    "wof:name":"Weiberg",
    "wof:placetype":"neighbourhood"
},
  "geometry": {"coordinates":[8.59115,51.51376],"type":"Point"}
}