{
  "type": "Feature",
  "properties": {
    "gn:admin1_code":"7.0",
    "gn:admin2_code":"053",
    "gn:admin3_code":"5378.0",
    "gn:admin4_code":"5378016.0",
    "gn:asciiname":"Wietsche",
    "gn:country_code":"DE",
    "gn:dem":108,
    "gn:feature_class":"P",
    "gn:feature_code":"PPL",
    "gn:name":"Wietsche",
    "gn:population":0,
    "gn:timezone":"Europe/Berlin",
    "iso:country":"DE",
    "wof:name":"Wietsche",
    "wof:placetype":"neighbourhood"
},
  "geometry": {"coordinates":[7.03191,51.09463],"type":"Point"}
}