{
  "type": "Feature",
  "properties": {
    "gn:admin1_code":"13",
    "gn:admin2_code":"0.0",
    "gn:admin3_code":"14521.0",
    "gn:admin4_code":"14521560.0",
    "gn:asciiname":"Rothensehma",
    "gn:country_code":"DE",
    "gn:dem":706,
    "gn:feature_class":"P",
    "gn:feature_code":"PPL",
    "gn:name":"Rothensehma",
    "gn:population":0,
    "gn:timezone":"Europe/Berlin",
    "iso:country":"DE",
    "wof:name":"Rothensehma",
    "wof:placetype":"neighbourhood"
},
  "geometry": {"coordinates":[13.01709,50.52421],"type":"Point"}
}