{
  "type": "Feature",
  "properties": {
    "gn:admin1_code":"15.0",
    "gn:admin2_code":"0.0",
    "gn:admin3_code":"16075.0",
    "gn:admin4_code":"16075133.0",
    "gn:asciiname":"Altefeld",
    "gn:country_code":"DE",
    "gn:dem":610,
    "gn:feature_class":"P",
    "gn:feature_code":"PPL",
    "gn:name":"Altefeld",
    "gn:population":0,
    "gn:timezone":"Europe/Berlin",
    "iso:country":"DE",
    "name:deu_x_preferred":[
        "Altefeld"
    ],
    "name:ita_x_preferred":[
        "Altefeld"
    ],
    "wof:name":"Altefeld",
    "wof:placetype":"neighbourhood"
},
  "geometry": {"coordinates":[11.49689,50.44889000000001],"type":"Point"}
}