{
  "type": "Feature",
  "properties": {
    "gn:admin1_code":"1",
    "gn:admin2_code":"84.0",
    "gn:admin3_code":"8436.0",
    "gn:admin4_code":"8436095.0",
    "gn:asciiname":"Hasenweiler",
    "gn:country_code":"DE",
    "gn:dem":575,
    "gn:feature_class":"P",
    "gn:feature_code":"PPL",
    "gn:name":"Hasenweiler",
    "gn:population":0,
    "gn:timezone":"Europe/Berlin",
    "iso:country":"DE",
    "wof:name":"Hasenweiler",
    "wof:placetype":"neighbourhood"
},
  "geometry": {"coordinates":[9.46144,47.83357],"type":"Point"}
}