{
  "type": "Feature",
  "properties": {
    "gn:admin1_code":"2",
    "gn:admin2_code":"91.0",
    "gn:admin3_code":"9187.0",
    "gn:admin4_code":"9187172.0",
    "gn:asciiname":"Ried",
    "gn:country_code":"DE",
    "gn:dem":724,
    "gn:feature_class":"P",
    "gn:feature_code":"PPL",
    "gn:name":"Ried",
    "gn:population":0,
    "gn:timezone":"Europe/Berlin",
    "iso:country":"DE",
    "wof:name":"Ried",
    "wof:placetype":"neighbourhood"
},
  "geometry": {"coordinates":[12.24971,47.77911],"type":"Point"}
}