{
  "type": "Feature",
  "properties": {
    "gn:admin1_code":"8",
    "gn:admin2_code":"0.0",
    "gn:admin3_code":"7138.0",
    "gn:admin4_code":"7138068.0",
    "gn:asciiname":"Lorscheid",
    "gn:country_code":"DE",
    "gn:dem":351,
    "gn:feature_class":"P",
    "gn:feature_code":"PPL",
    "gn:name":"Lorscheid",
    "gn:population":0,
    "gn:timezone":"Europe/Berlin",
    "iso:country":"DE",
    "name:ceb_x_preferred":[
        "Lorscheid"
    ],
    "name:deu_x_preferred":[
        "Lorscheid"
    ],
    "name:epo_x_preferred":[
        "Lorscheid"
    ],
    "name:eus_x_preferred":[
        "Lorscheid"
    ],
    "name:fas_x_preferred":[
        "\u0644\u0648\u0631\u0634\u0627\u06cc\u062f"
    ],
    "name:fra_x_preferred":[
        "Lorscheid"
    ],
    "name:hun_x_preferred":[
        "Lorscheid"
    ],
    "name:ita_x_preferred":[
        "Lorscheid"
    ],
    "name:kaz_x_preferred":[
        "\u041b\u043e\u0440\u0448\u0430\u0439\u0434"
    ],
    "name:kir_x_preferred":[
        "\u041b\u043e\u0440\u0448\u0430\u0439\u0434"
    ],
    "name:ltz_x_preferred":[
        "Lorscheid"
    ],
    "name:msa_x_preferred":[
        "Lorscheid"
    ],
    "name:nld_x_preferred":[
        "Lorscheid"
    ],
    "name:pol_x_preferred":[
        "Lorscheid"
    ],
    "name:por_x_preferred":[
        "Lorscheid"
    ],
    "name:ron_x_preferred":[
        "Lorscheid"
    ],
    "name:rus_x_preferred":[
        "\u041b\u043e\u0440\u0448\u0430\u0439\u0434"
    ],
    "name:spa_x_preferred":[
        "Lorscheid"
    ],
    "name:srp_x_preferred":[
        "\u041b\u043e\u0440\u0448\u0430\u0458\u0434"
    ],
    "name:ukr_x_preferred":[
        "\u041b\u043e\u0440\u0448\u0430\u0439\u0434"
    ],
    "name:uzb_x_preferred":[
        "Lorscheid"
    ],
    "name:vie_x_preferred":[
        "Lorscheid"
    ],
    "name:vol_x_preferred":[
        "Lorscheid"
    ],
    "name:war_x_preferred":[
        "Lorscheid"
    ],
    "name:zho_x_preferred":[
        "\u6d1b\u5c14\u6c99\u4f0a\u5fb7"
    ],
    "wof:name":"Lorscheid",
    "wof:placetype":"neighbourhood"
},
  "geometry": {"coordinates":[7.35167,50.59412],"type":"Point"}
}