{
  "type": "Feature",
  "properties": {
    "gn:admin1_code":"8",
    "gn:admin2_code":"0.0",
    "gn:admin3_code":"7138.0",
    "gn:admin4_code":"7138068.0",
    "gn:asciiname":"Lorscheid",
    "gn:country_code":"DE",
    "gn:dem":351,
    "gn:feature_class":"P",
    "gn:feature_code":"PPL",
    "gn:name":"Lorscheid",
    "gn:population":0,
    "gn:timezone":"Europe/Berlin",
    "iso:country":"DE",
    "wof:name":"Lorscheid",
    "wof:placetype":"neighbourhood"
},
  "geometry": {"coordinates":[7.35167,50.59412],"type":"Point"}
}