{
  "type": "Feature",
  "properties": {
    "gn:admin1_code":"2",
    "gn:admin2_code":"93.0",
    "gn:admin3_code":"9377.0",
    "gn:admin4_code":"9377112.0",
    "gn:asciiname":"Iglersreuth",
    "gn:country_code":"DE",
    "gn:dem":573,
    "gn:feature_class":"P",
    "gn:feature_code":"PPL",
    "gn:name":"Iglersreuth",
    "gn:population":0,
    "gn:timezone":"Europe/Berlin",
    "iso:country":"DE",
    "wof:name":"Iglersreuth",
    "wof:placetype":"neighbourhood"
},
  "geometry": {"coordinates":[12.37082,49.81356],"type":"Point"}
}