{
  "type": "Feature",
  "properties": {
    "gn:admin1_code":"7",
    "gn:admin2_code":"51.0",
    "gn:admin3_code":"5158.0",
    "gn:admin4_code":"5158024.0",
    "gn:asciiname":"Niederschwarzbach",
    "gn:country_code":"DE",
    "gn:dem":175,
    "gn:feature_class":"P",
    "gn:feature_code":"PPLL",
    "gn:name":"Niederschwarzbach",
    "gn:population":0,
    "gn:timezone":"Europe/Berlin",
    "iso:country":"DE",
    "wof:name":"Niederschwarzbach",
    "wof:placetype":"neighbourhood"
},
  "geometry": {"coordinates":[6.98562,51.28816],"type":"Point"}
}