{
  "type": "Feature",
  "properties": {
    "gn:admin1_code":"5.0",
    "gn:admin2_code":"66.0",
    "gn:admin3_code":"6635.0",
    "gn:admin4_code":"6635003.0",
    "gn:asciiname":"Albertshausen",
    "gn:country_code":"DE",
    "gn:dem":357,
    "gn:elevation":"253.0",
    "gn:feature_class":"P",
    "gn:feature_code":"PPL",
    "gn:name":"Albertshausen",
    "gn:population":246,
    "gn:timezone":"Europe/Berlin",
    "iso:country":"DE",
    "wof:name":"Albertshausen",
    "wof:placetype":"neighbourhood",
    "wof:population":246
},
  "geometry": {"coordinates":[9.05462,51.11457],"type":"Point"}
}