{
  "type": "Feature",
  "properties": {
    "gn:admin1_code":"8",
    "gn:asciiname":"Kaplaneihof",
    "gn:country_code":"DE",
    "gn:dem":266,
    "gn:feature_class":"P",
    "gn:feature_code":"PPL",
    "gn:name":"Kaplaneihof",
    "gn:population":0,
    "gn:timezone":"Europe/Berlin",
    "iso:country":"DE",
    "wof:name":"Kaplaneihof",
    "wof:placetype":"neighbourhood"
},
  "geometry": {"coordinates":[7.33333,49.26667],"type":"Point"}
}