{
  "type": "Feature",
  "properties": {
    "gn:admin1_code":"13",
    "gn:admin2_code":"0.0",
    "gn:admin3_code":"14730.0",
    "gn:admin4_code":"14730080.0",
    "gn:asciiname":"Mensdorf",
    "gn:country_code":"DE",
    "gn:dem":103,
    "gn:feature_class":"P",
    "gn:feature_code":"PPL",
    "gn:name":"Mensdorf",
    "gn:population":0,
    "gn:timezone":"Europe/Berlin",
    "iso:country":"DE",
    "name:cat_x_preferred":[
        "Mensdorf"
    ],
    "name:ceb_x_preferred":[
        "Mensdorf"
    ],
    "name:fra_x_preferred":[
        "Mensdorf"
    ],
    "name:ltz_x_preferred":[
        "Menster"
    ],
    "name:nld_x_preferred":[
        "Mensdorf"
    ],
    "name:pol_x_preferred":[
        "Mensdorf"
    ],
    "name:swe_x_preferred":[
        "Mensdorf"
    ],
    "wof:name":"Mensdorf",
    "wof:placetype":"neighbourhood"
},
  "geometry": {"coordinates":[12.64252,51.4972],"type":"Point"}
}