{
  "type": "Feature",
  "properties": {
    "gn:admin1_code":"13.0",
    "gn:admin2_code":"00",
    "gn:admin3_code":"14522.0",
    "gn:admin4_code":"14522220.0",
    "gn:asciiname":"Zschepplitz",
    "gn:country_code":"DE",
    "gn:dem":239,
    "gn:feature_class":"P",
    "gn:feature_code":"PPL",
    "gn:name":"Zschepplitz",
    "gn:population":0,
    "gn:timezone":"Europe/Berlin",
    "iso:country":"DE",
    "wof:name":"Zschepplitz",
    "wof:placetype":"neighbourhood"
},
  "geometry": {"coordinates":[13.08801,51.1488],"type":"Point"}
}