{
  "type": "Feature",
  "properties": {
    "gn:admin1_code":"1",
    "gn:admin2_code":"83.0",
    "gn:admin3_code":"8337.0",
    "gn:admin4_code":"8337038.0",
    "gn:asciiname":"Niederwihl",
    "gn:country_code":"DE",
    "gn:dem":631,
    "gn:feature_class":"P",
    "gn:feature_code":"PPL",
    "gn:name":"Niederwihl",
    "gn:population":0,
    "gn:timezone":"Europe/Berlin",
    "iso:country":"DE",
    "wof:name":"Niederwihl",
    "wof:placetype":"neighbourhood"
},
  "geometry": {"coordinates":[8.07265,47.61872],"type":"Point"}
}