{
  "type": "Feature",
  "properties": {
    "gn:admin1_code":"2",
    "gn:admin2_code":"92.0",
    "gn:admin3_code":"9275.0",
    "gn:admin4_code":"9275145.0",
    "gn:asciiname":"Kleeberg",
    "gn:country_code":"DE",
    "gn:dem":355,
    "gn:feature_class":"P",
    "gn:feature_code":"PPL",
    "gn:name":"Kleeberg",
    "gn:population":0,
    "gn:timezone":"Europe/Berlin",
    "iso:country":"DE",
    "wof:name":"Kleeberg",
    "wof:placetype":"neighbourhood"
},
  "geometry": {"coordinates":[13.3089,48.44613],"type":"Point"}
}