{
  "type": "Feature",
  "properties": {
    "gn:admin1_code":"1",
    "gn:admin2_code":"82.0",
    "gn:admin3_code":"8212.0",
    "gn:admin4_code":"8212000.0",
    "gn:asciiname":"Gut Scheibenhardt",
    "gn:country_code":"DE",
    "gn:dem":119,
    "gn:feature_class":"P",
    "gn:feature_code":"PPL",
    "gn:name":"Gut Scheibenhardt",
    "gn:population":0,
    "gn:timezone":"Europe/Berlin",
    "iso:country":"DE",
    "wof:name":"Gut Scheibenhardt",
    "wof:placetype":"neighbourhood"
},
  "geometry": {"coordinates":[8.37244,48.97475],"type":"Point"}
}