{
  "type": "Feature",
  "properties": {
    "gn:admin1_code":"2.0",
    "gn:admin2_code":"93.0",
    "gn:admin3_code":"9362.0",
    "gn:admin4_code":"9362000.0",
    "gn:asciiname":"Brandlberg",
    "gn:country_code":"DE",
    "gn:dem":374,
    "gn:feature_class":"P",
    "gn:feature_code":"PPL",
    "gn:name":"Brandlberg",
    "gn:population":0,
    "gn:timezone":"Europe/Berlin",
    "iso:country":"DE",
    "wof:name":"Brandlberg",
    "wof:placetype":"neighbourhood"
},
  "geometry": {"coordinates":[12.1381,49.04023],"type":"Point"}
}