{
  "type": "Feature",
  "properties": {
    "gn:country":"DE",
    "gn:fcode":"PPL",
    "gn:population":0,
    "iso:country":"DE",
    "name:als_x_preferred":[
        "Ettendorf"
    ],
    "name:ara_x_preferred":[
        "\u0625\u062a\u064a\u0646\u062f\u0648\u0631\u0641"
    ],
    "name:cat_x_preferred":[
        "Ettendorf"
    ],
    "name:ceb_x_preferred":[
        "Ettendorf"
    ],
    "name:deu_x_preferred":[
        "Ettendorf"
    ],
    "name:eus_x_preferred":[
        "Ettendorf"
    ],
    "name:fas_x_preferred":[
        "\u0627\u062a\u0646\u062f\u0648\u0631\u0641"
    ],
    "name:fra_x_preferred":[
        "Ettendorf"
    ],
    "name:hun_x_preferred":[
        "Ettendorf"
    ],
    "name:hye_x_preferred":[
        "\u0537\u0569\u0565\u0576\u0564\u0578\u0580\u0586"
    ],
    "name:ita_x_preferred":[
        "Ettendorf"
    ],
    "name:kaz_x_preferred":[
        "\u0415\u0442\u0442\u0435\u043d\u0434\u043e\u0440\u0444"
    ],
    "name:lat_x_preferred":[
        "Ettendorf"
    ],
    "name:mlg_x_preferred":[
        "Ettendorf"
    ],
    "name:msa_x_preferred":[
        "Ettendorf"
    ],
    "name:nld_x_preferred":[
        "Ettendorf"
    ],
    "name:oci_x_preferred":[
        "Ettendorf"
    ],
    "name:pfl_x_preferred":[
        "Ettendorf"
    ],
    "name:pms_x_preferred":[
        "Ettendorf"
    ],
    "name:pol_x_preferred":[
        "Ettendorf"
    ],
    "name:por_x_preferred":[
        "Ettendorf"
    ],
    "name:ron_x_preferred":[
        "Ettendorf"
    ],
    "name:rus_x_preferred":[
        "\u042d\u0442\u0442\u0435\u043d\u0434\u043e\u0440\u0444"
    ],
    "name:slk_x_preferred":[
        "Ettendorf"
    ],
    "name:slv_x_preferred":[
        "Ettendorf"
    ],
    "name:spa_x_preferred":[
        "Ettendorf"
    ],
    "name:srp_x_preferred":[
        "\u0415\u0442\u0435\u043d\u0434\u043e\u0440\u0444"
    ],
    "name:swe_x_preferred":[
        "Ettendorf"
    ],
    "name:ukr_x_preferred":[
        "\u0415\u0442\u0442\u0435\u043d\u0434\u043e\u0440\u0444"
    ],
    "name:uzb_x_preferred":[
        "Ettendorf"
    ],
    "name:vie_x_preferred":[
        "Ettendorf"
    ],
    "name:vol_x_preferred":[
        "Ettendorf"
    ],
    "name:war_x_preferred":[
        "Ettendorf"
    ],
    "name:zho_x_preferred":[
        "\u57c3\u6ed5\u591a\u592b"
    ],
    "qs_pg:aaroncc":"DE",
    "qs_pg:gn_country":"DE",
    "qs_pg:gn_fcode":"PPL",
    "qs_pg:gn_pop":0,
    "qs_pg:name":"Ettendorf",
    "qs_pg:name_adm0":"Deutschland",
    "qs_pg:name_adm1":"Bayern",
    "qs_pg:photos":35,
    "qs_pg:photos_1k":7,
    "qs_pg:photos_9k":1,
    "qs_pg:photos_9r":2,
    "qs_pg:photos_all":35,
    "qs_pg:photos_sr":2,
    "qs_pg:pop_sr":0,
    "qs_pg:qs_pg_placetype":"locality",
    "qs_pg:qs_pg_placetype_gp":"Town",
    "qs_pg:woe_adm0":23424829,
    "woe:adm0_id":23424829,
    "woe:name_adm0":"Deutschland",
    "woe:name_adm1":"Bayern",
    "woe:placetype":"Town",
    "wof:name":"Ettendorf",
    "wof:placetype":"neighbourhood"
},
  "geometry": {"coordinates":[12.65207,47.8759],"type":"Point"}
}