{
  "type": "Feature",
  "properties": {
    "gn:gn_country":"DE",
    "gn:gn_fcode":"PPLA4",
    "gn:gn_pop":617,
    "gn:population":617,
    "iso:country":"DE",
    "name:baq_x_preferred":[
        "Odisheim"
    ],
    "name:chi_x_preferred":[
        "\u5965\u8fea\u65af\u6d77\u59c6"
    ],
    "name:dut_x_preferred":[
        "Odisheim"
    ],
    "name:eng_x_preferred":[
        "Odisheim"
    ],
    "name:epo_x_preferred":[
        "Odisheim"
    ],
    "name:fre_x_preferred":[
        "Odisheim"
    ],
    "name:ger_x_preferred":[
        "Odisheim"
    ],
    "name:hun_x_preferred":[
        "Odisheim"
    ],
    "name:ita_x_preferred":[
        "Odisheim"
    ],
    "name:kaz_x_preferred":[
        "\u041e\u0434\u0438\u0441\u0445\u0430\u0439\u043c"
    ],
    "name:kir_x_preferred":[
        "\u041e\u0434\u0438\u0441\u0445\u0430\u0439\u043c"
    ],
    "name:may_x_preferred":[
        "Odisheim"
    ],
    "name:nan_x_preferred":[
        "Odisheim"
    ],
    "name:nds_x_preferred":[
        "Godshem"
    ],
    "name:per_x_preferred":[
        "\u0627\u0648\u062f\u06cc\u0633\u0647\u0627\u06cc\u0645"
    ],
    "name:pol_x_preferred":[
        "Odisheim"
    ],
    "name:por_x_preferred":[
        "Odisheim"
    ],
    "name:rum_x_preferred":[
        "Odisheim"
    ],
    "name:rus_x_preferred":[
        "\u041e\u0434\u0438\u0441\u0445\u0430\u0439\u043c"
    ],
    "name:srp_x_preferred":[
        "\u041e\u0434\u0438\u0441\u0445\u0430\u0458\u043c"
    ],
    "name:uzb_x_preferred":[
        "Odisheim"
    ],
    "name:vol_x_preferred":[
        "Odisheim"
    ],
    "name:war_x_preferred":[
        "Odisheim"
    ],
    "qs_pg:aaroncc":"DE",
    "qs_pg:gn_country":"DE",
    "qs_pg:gn_fcode":"PPLA4",
    "qs_pg:gn_pop":617,
    "qs_pg:name":"Odisheim",
    "qs_pg:photos_9r":0,
    "qs_pg:photos_sr":0,
    "qs_pg:pop_sr":2,
    "qs_pg:qs_pg_placetype":"locality",
    "wof:name":"Odisheim",
    "wof:placetype":"locality",
    "wof:population":617
},
  "geometry": {"coordinates":[8.93333,53.68333],"type":"Point"}
}