{
  "type": "Feature",
  "properties": {
    "gn:admin1_code":"5",
    "gn:admin2_code":"64.0",
    "gn:admin3_code":"6440.0",
    "gn:admin4_code":"6440025.0",
    "gn:asciiname":"Niederwoellstadt",
    "gn:country_code":"DE",
    "gn:dem":124,
    "gn:feature_class":"P",
    "gn:feature_code":"PPL",
    "gn:name":"Niederw\u00f6llstadt",
    "gn:population":0,
    "gn:timezone":"Europe/Berlin",
    "iso:country":"DE",
    "wof:name":"Niederwoellstadt",
    "wof:placetype":"neighbourhood"
},
  "geometry": {"coordinates":[8.77083,50.28024],"type":"Point"}
}