{
  "type": "Feature",
  "properties": {
    "gn:admin1_code":"2.0",
    "gn:admin2_code":"091",
    "gn:admin3_code":"9187.0",
    "gn:admin4_code":"9187134.0",
    "gn:asciiname":"Weng",
    "gn:country_code":"DE",
    "gn:dem":466,
    "gn:feature_class":"P",
    "gn:feature_code":"PPL",
    "gn:name":"Weng",
    "gn:population":0,
    "gn:timezone":"Europe/Berlin",
    "iso:country":"DE",
    "name:ceb_x_preferred":[
        "Weng"
    ],
    "name:deu_x_preferred":[
        "Weng"
    ],
    "name:fas_x_preferred":[
        "\u0648\u0646\u06af"
    ],
    "name:fra_x_preferred":[
        "Weng"
    ],
    "name:ita_x_preferred":[
        "Weng"
    ],
    "name:nld_x_preferred":[
        "Weng"
    ],
    "name:pol_x_preferred":[
        "Weng"
    ],
    "name:rus_x_preferred":[
        "\u0412\u0435\u043d\u0433"
    ],
    "name:swe_x_preferred":[
        "Weng"
    ],
    "wof:name":"Weng",
    "wof:placetype":"neighbourhood"
},
  "geometry": {"coordinates":[12.17304,47.97679],"type":"Point"}
}