{
  "type": "Feature",
  "properties": {
    "gn:admin1_code":"2",
    "gn:admin2_code":"95.0",
    "gn:admin3_code":"9576.0",
    "gn:admin4_code":"9576147.0",
    "gn:asciiname":"Stockheim",
    "gn:country_code":"DE",
    "gn:dem":471,
    "gn:feature_class":"P",
    "gn:feature_code":"PPL",
    "gn:name":"Stockheim",
    "gn:population":0,
    "gn:timezone":"Europe/Berlin",
    "iso:country":"DE",
    "wof:name":"Stockheim",
    "wof:placetype":"neighbourhood"
},
  "geometry": {"coordinates":[10.89353,49.15865],"type":"Point"}
}