{
  "type": "Feature",
  "properties": {
    "gn:admin1_code":"8",
    "gn:admin2_code":"0.0",
    "gn:admin3_code":"7235.0",
    "gn:admin4_code":"7235094.0",
    "gn:asciiname":"Lorich",
    "gn:country_code":"DE",
    "gn:dem":319,
    "gn:feature_class":"P",
    "gn:feature_code":"PPL",
    "gn:name":"Lorich",
    "gn:population":0,
    "gn:timezone":"Europe/Berlin",
    "iso:country":"DE",
    "wof:name":"Lorich",
    "wof:placetype":"neighbourhood"
},
  "geometry": {"coordinates":[6.62808,49.79504],"type":"Point"}
}