{
  "type": "Feature",
  "properties": {
    "gn:admin1_code":"10",
    "gn:admin2_code":"0.0",
    "gn:admin3_code":"1061.0",
    "gn:admin4_code":"1061118.0",
    "gn:asciiname":"Essfleth",
    "gn:country_code":"DE",
    "gn:dem":0,
    "gn:feature_class":"P",
    "gn:feature_code":"PPL",
    "gn:name":"E\u00dffleth",
    "gn:population":0,
    "gn:timezone":"Europe/Berlin",
    "iso:country":"DE",
    "wof:name":"Essfleth",
    "wof:placetype":"neighbourhood"
},
  "geometry": {"coordinates":[9.45,53.73333],"type":"Point"}
}