{
  "type": "Feature",
  "properties": {
    "iso:country":"DE",
    "name:deu_x_preferred":[
        "Genh\u00fclsen"
    ],
    "wof:name":"Genhuelsen",
    "wof:placetype":"neighbourhood"
},
  "geometry": {"coordinates":[6.39513578577734,51.15448528166497],"type":"Point"}
}