{
  "type": "Feature",
  "properties": {
    "gn:admin1_code":"5",
    "gn:admin2_code":"64.0",
    "gn:admin3_code":"6435.0",
    "gn:admin4_code":"6435009.0",
    "gn:asciiname":"Neuses",
    "gn:country_code":"DE",
    "gn:dem":174,
    "gn:feature_class":"P",
    "gn:feature_code":"PPL",
    "gn:name":"Neuses",
    "gn:population":0,
    "gn:timezone":"Europe/Berlin",
    "iso:country":"DE",
    "name:deu_x_preferred":[
        "Neuses"
    ],
    "name:nld_x_preferred":[
        "Neuses"
    ],
    "wof:name":"Neuses",
    "wof:placetype":"neighbourhood"
},
  "geometry": {"coordinates":[9.13752,50.12768],"type":"Point"}
}