{
  "type": "Feature",
  "properties": {
    "gn:admin1_code":"1",
    "gn:admin2_code":"82.0",
    "gn:admin3_code":"8235.0",
    "gn:admin4_code":"8235008.0",
    "gn:asciiname":"Mottlingen",
    "gn:country_code":"DE",
    "gn:dem":530,
    "gn:feature_class":"P",
    "gn:feature_code":"PPL",
    "gn:name":"M\u00f6ttlingen",
    "gn:population":0,
    "gn:timezone":"Europe/Berlin",
    "iso:country":"DE",
    "wof:name":"Mottlingen",
    "wof:placetype":"neighbourhood"
},
  "geometry": {"coordinates":[8.80035,48.76173],"type":"Point"}
}