{
  "type": "Feature",
  "properties": {
    "gn:admin1_code":"13",
    "gn:admin2_code":"0.0",
    "gn:admin3_code":"14729.0",
    "gn:admin4_code":"14729050.0",
    "gn:asciiname":"Thraena",
    "gn:country_code":"DE",
    "gn:dem":157,
    "gn:feature_class":"P",
    "gn:feature_code":"PPL",
    "gn:name":"Thr\u00e4na",
    "gn:population":0,
    "gn:timezone":"Europe/Berlin",
    "iso:country":"DE",
    "wof:name":"Thraena",
    "wof:placetype":"neighbourhood"
},
  "geometry": {"coordinates":[12.46664,51.07131],"type":"Point"}
}