{
  "type": "Feature",
  "properties": {
    "gn:admin1_code":"10",
    "gn:admin2_code":"0.0",
    "gn:admin3_code":"1051.0",
    "gn:admin4_code":"1051086.0",
    "gn:asciiname":"Juetzbuettel",
    "gn:country_code":"DE",
    "gn:dem":45,
    "gn:feature_class":"P",
    "gn:feature_code":"PPL",
    "gn:name":"J\u00fctzb\u00fcttel",
    "gn:population":0,
    "gn:timezone":"Europe/Berlin",
    "iso:country":"DE",
    "wof:name":"Juetzbuettel",
    "wof:placetype":"neighbourhood"
},
  "geometry": {"coordinates":[9.32998,54.18264],"type":"Point"}
}