{
  "type": "Feature",
  "properties": {
    "gn:admin1_code":"2",
    "gn:admin2_code":"97.0",
    "gn:admin3_code":"9771.0",
    "gn:admin4_code":"9771112.0",
    "gn:asciiname":"Muhlhausen",
    "gn:country_code":"DE",
    "gn:dem":459,
    "gn:feature_class":"P",
    "gn:feature_code":"PPL",
    "gn:name":"M\u00fchlhausen",
    "gn:population":0,
    "gn:timezone":"Europe/Berlin",
    "iso:country":"DE",
    "wof:name":"Muhlhausen",
    "wof:placetype":"neighbourhood"
},
  "geometry": {"coordinates":[10.93484,48.4405],"type":"Point"}
}