{
  "type": "Feature",
  "properties": {
    "gn:admin1_code":"9.0",
    "gn:admin2_code":"00",
    "gn:admin3_code":"10042.0",
    "gn:admin4_code":"10042115.0",
    "gn:asciiname":"Wochern",
    "gn:country_code":"DE",
    "gn:dem":250,
    "gn:feature_class":"P",
    "gn:feature_code":"PPL",
    "gn:name":"Wochern",
    "gn:population":0,
    "gn:timezone":"Europe/Berlin",
    "iso:country":"DE",
    "wof:name":"Wochern",
    "wof:placetype":"neighbourhood"
},
  "geometry": {"coordinates":[6.40554,49.50214],"type":"Point"}
}