{
  "type": "Feature",
  "properties": {
    "gn:admin1_code":"13",
    "gn:admin2_code":"0.0",
    "gn:admin3_code":"14627.0",
    "gn:admin4_code":"14627260.0",
    "gn:asciiname":"Panitz",
    "gn:country_code":"DE",
    "gn:dem":120,
    "gn:feature_class":"P",
    "gn:feature_code":"PPL",
    "gn:name":"Panitz",
    "gn:population":0,
    "gn:timezone":"Europe/Berlin",
    "iso:country":"DE",
    "wof:name":"Panitz",
    "wof:placetype":"neighbourhood"
},
  "geometry": {"coordinates":[13.226,51.25211],"type":"Point"}
}