{
  "type": "Feature",
  "properties": {
    "gn:admin1_code":"6",
    "gn:admin2_code":"0.0",
    "gn:admin3_code":"3454.0",
    "gn:admin4_code":"3454019.0",
    "gn:asciiname":"Kreyenborg",
    "gn:country_code":"DE",
    "gn:dem":15,
    "gn:feature_class":"P",
    "gn:feature_code":"PPL",
    "gn:name":"Kreyenborg",
    "gn:population":0,
    "gn:timezone":"Europe/Berlin",
    "iso:country":"DE",
    "wof:name":"Kreyenborg",
    "wof:placetype":"neighbourhood"
},
  "geometry": {"coordinates":[7.38917,52.68292],"type":"Point"}
}