{
  "type": "Feature",
  "properties": {
    "gn:admin1_code":"13",
    "gn:admin2_code":"0.0",
    "gn:admin3_code":"14523.0",
    "gn:admin4_code":"14523245.0",
    "gn:asciiname":"Muldenhammer",
    "gn:country_code":"DE",
    "gn:dem":652,
    "gn:feature_class":"P",
    "gn:feature_code":"PPLA4",
    "gn:name":"Muldenhammer",
    "gn:population":0,
    "gn:timezone":"Europe/Berlin",
    "iso:country":"DE",
    "wof:name":"Muldenhammer",
    "wof:placetype":"locality"
},
  "geometry": {"coordinates":[12.48333,50.45],"type":"Point"}
}