{
  "type": "Feature",
  "properties": {
    "gn:admin1_code":"8",
    "gn:admin2_code":"0.0",
    "gn:admin3_code":"7137.0",
    "gn:admin4_code":"7137068.0",
    "gn:asciiname":"Sankt Johann Nitz",
    "gn:country_code":"DE",
    "gn:dem":355,
    "gn:feature_class":"P",
    "gn:feature_code":"PPL",
    "gn:name":"Sankt Johann Nitz",
    "gn:population":0,
    "gn:timezone":"Europe/Berlin",
    "iso:country":"DE",
    "wof:name":"Sankt Johann Nitz",
    "wof:placetype":"neighbourhood"
},
  "geometry": {"coordinates":[7.15,50.35],"type":"Point"}
}