{
  "type": "Feature",
  "properties": {
    "gn:admin1_code":"10",
    "gn:admin2_code":"0.0",
    "gn:admin3_code":"1060.0",
    "gn:admin4_code":"1060034.0",
    "gn:asciiname":"Vosshoehlen",
    "gn:country_code":"DE",
    "gn:dem":27,
    "gn:feature_class":"P",
    "gn:feature_code":"PPL",
    "gn:name":"Vo\u00dfh\u00f6hlen",
    "gn:population":0,
    "gn:timezone":"Europe/Berlin",
    "iso:country":"DE",
    "wof:name":"Vosshoehlen",
    "wof:placetype":"neighbourhood"
},
  "geometry": {"coordinates":[10.10619,53.88713000000001],"type":"Point"}
}