{
  "type": "Feature",
  "properties": {
    "gn:admin1_code":"7",
    "gn:admin2_code":"55.0",
    "gn:admin3_code":"5562.0",
    "gn:admin4_code":"5562020.0",
    "gn:asciiname":"Langenbochum",
    "gn:country_code":"DE",
    "gn:dem":84,
    "gn:feature_class":"P",
    "gn:feature_code":"PPL",
    "gn:name":"Langenbochum",
    "gn:population":0,
    "gn:timezone":"Europe/Berlin",
    "iso:country":"DE",
    "wof:name":"Langenbochum",
    "wof:placetype":"neighbourhood"
},
  "geometry": {"coordinates":[7.11714,51.61473],"type":"Point"}
}