{
  "type": "Feature",
  "properties": {
    "gn:admin1_code":"2",
    "gn:admin2_code":"97.0",
    "gn:admin3_code":"9780.0",
    "gn:admin4_code":"9780119.0",
    "gn:asciiname":"Todtenberg",
    "gn:country_code":"DE",
    "gn:dem":841,
    "gn:feature_class":"P",
    "gn:feature_code":"PPL",
    "gn:name":"Todtenberg",
    "gn:population":0,
    "gn:timezone":"Europe/Berlin",
    "iso:country":"DE",
    "wof:name":"Todtenberg",
    "wof:placetype":"neighbourhood"
},
  "geometry": {"coordinates":[10.34034,47.82752],"type":"Point"}
}