{
  "type": "Feature",
  "properties": {
    "gn:admin1_code":"11",
    "gn:admin2_code":"0.0",
    "gn:admin3_code":"12067.0",
    "gn:admin4_code":"12067552.0",
    "gn:asciiname":"Ernst-Thaelmann-Siedlung",
    "gn:country_code":"DE",
    "gn:dem":23,
    "gn:feature_class":"P",
    "gn:feature_code":"PPL",
    "gn:name":"Ernst-Th\u00e4lmann-Siedlung",
    "gn:population":0,
    "gn:timezone":"Europe/Berlin",
    "iso:country":"DE",
    "wof:name":"Ernst-Thaelmann-Siedlung",
    "wof:placetype":"neighbourhood"
},
  "geometry": {"coordinates":[14.63937,52.22859],"type":"Point"}
}