{
  "type": "Feature",
  "properties": {
    "gn:admin1_code":"13",
    "gn:admin2_code":"0.0",
    "gn:admin3_code":"14628.0",
    "gn:admin4_code":"14628020.0",
    "gn:asciiname":"Markersbach",
    "gn:country_code":"DE",
    "gn:dem":366,
    "gn:feature_class":"P",
    "gn:feature_code":"PPL",
    "gn:name":"Markersbach",
    "gn:population":0,
    "gn:timezone":"Europe/Berlin",
    "iso:country":"DE",
    "name:bak_x_preferred":[
        "\u041c\u0430\u0440\u043a\u0435\u0440\u0441\u0431\u0430\u0445"
    ],
    "name:ceb_x_preferred":[
        "Markersbach"
    ],
    "name:deu_x_preferred":[
        "Markersbach"
    ],
    "name:epo_x_preferred":[
        "Markersbach"
    ],
    "name:est_x_preferred":[
        "Markersbach"
    ],
    "name:fas_x_preferred":[
        "\u0645\u0627\u0631\u06a9\u0631\u0633\u0628\u0627\u062e"
    ],
    "name:mkd_x_preferred":[
        "\u041c\u0430\u0440\u043a\u0435\u0440\u0441\u0431\u0430\u0445"
    ],
    "name:nld_x_preferred":[
        "Markersbach"
    ],
    "name:ron_x_preferred":[
        "Markersbach"
    ],
    "name:rus_x_preferred":[
        "\u041c\u0430\u0440\u043a\u0435\u0440\u0441\u0431\u0430\u0445"
    ],
    "name:uzb_x_preferred":[
        "Markersbach"
    ],
    "name:vol_x_preferred":[
        "Markersbach"
    ],
    "wof:name":"Markersbach",
    "wof:placetype":"neighbourhood"
},
  "geometry": {"coordinates":[13.98641,50.84004],"type":"Point"}
}