{
  "type": "Feature",
  "properties": {
    "gn:admin1_code":"1",
    "gn:admin2_code":"81.0",
    "gn:admin3_code":"8136.0",
    "gn:admin4_code":"8136068.0",
    "gn:asciiname":"Oberzell",
    "gn:country_code":"DE",
    "gn:dem":528,
    "gn:feature_class":"P",
    "gn:feature_code":"PPL",
    "gn:name":"Oberzell",
    "gn:population":0,
    "gn:timezone":"Europe/Berlin",
    "iso:country":"DE",
    "wof:name":"Oberzell",
    "wof:placetype":"neighbourhood"
},
  "geometry": {"coordinates":[10.31398,48.99281],"type":"Point"}
}