{
  "type": "Feature",
  "properties": {
    "iso:country":"DE",
    "wof:name":"Mathildenhof",
    "wof:placetype":"neighbourhood"
},
  "geometry": {"coordinates":[7.07486912417391,51.04872171672867],"type":"Point"}
}