{
  "type": "Feature",
  "properties": {
    "gn:admin1_code":"1",
    "gn:admin2_code":"81.0",
    "gn:admin3_code":"8127.0",
    "gn:admin4_code":"8127009.0",
    "gn:asciiname":"Buhlerzimmern",
    "gn:country_code":"DE",
    "gn:dem":408,
    "gn:feature_class":"P",
    "gn:feature_code":"PPL",
    "gn:name":"B\u00fchlerzimmern",
    "gn:population":0,
    "gn:timezone":"Europe/Berlin",
    "iso:country":"DE",
    "name:und_x_variant":[
        "B\u00fchlerzimmern"
    ],
    "wof:name":"Buhlerzimmern",
    "wof:placetype":"neighbourhood"
},
  "geometry": {"coordinates":[9.79447,49.15119],"type":"Point"}
}