{
  "type": "Feature",
  "properties": {
    "gn:admin1_code":"13",
    "gn:admin2_code":"0.0",
    "gn:admin3_code":"14627.0",
    "gn:admin4_code":"14627070.0",
    "gn:asciiname":"Kobeln",
    "gn:country_code":"DE",
    "gn:dem":126,
    "gn:feature_class":"P",
    "gn:feature_code":"PPL",
    "gn:name":"Kobeln",
    "gn:population":0,
    "gn:timezone":"Europe/Berlin",
    "iso:country":"DE",
    "wof:name":"Kobeln",
    "wof:placetype":"neighbourhood"
},
  "geometry": {"coordinates":[13.33938,51.24824],"type":"Point"}
}