{
  "type": "Feature",
  "properties": {
    "gn:admin1_code":"2",
    "gn:admin2_code":"93.0",
    "gn:admin3_code":"9372.0",
    "gn:admin4_code":"9372164.0",
    "gn:asciiname":"Dinzling",
    "gn:country_code":"DE",
    "gn:dem":476,
    "gn:feature_class":"P",
    "gn:feature_code":"PPL",
    "gn:name":"Dinzling",
    "gn:population":0,
    "gn:timezone":"Europe/Berlin",
    "iso:country":"DE",
    "wof:name":"Dinzling",
    "wof:placetype":"neighbourhood"
},
  "geometry": {"coordinates":[12.63635,49.13433],"type":"Point"}
}