{
  "type": "Feature",
  "properties": {
    "gn:admin1_code":"1",
    "gn:admin2_code":"84.0",
    "gn:admin3_code":"8436.0",
    "gn:admin4_code":"8436055.0",
    "gn:asciiname":"Hofs",
    "gn:country_code":"DE",
    "gn:dem":674,
    "gn:feature_class":"P",
    "gn:feature_code":"PPL",
    "gn:name":"Hofs",
    "gn:population":0,
    "gn:timezone":"Europe/Berlin",
    "iso:country":"DE",
    "wof:name":"Hofs",
    "wof:placetype":"neighbourhood"
},
  "geometry": {"coordinates":[10.09447,47.83523],"type":"Point"}
}