{
  "type": "Feature",
  "properties": {
    "gn:admin1_code":"5",
    "gn:admin2_code":"65.0",
    "gn:admin3_code":"6533.0",
    "gn:admin4_code":"6533017.0",
    "gn:asciiname":"Odersbach",
    "gn:country_code":"DE",
    "gn:dem":136,
    "gn:feature_class":"P",
    "gn:feature_code":"PPL",
    "gn:name":"Odersbach",
    "gn:population":0,
    "gn:timezone":"Europe/Berlin",
    "iso:country":"DE",
    "wof:name":"Odersbach",
    "wof:placetype":"neighbourhood"
},
  "geometry": {"coordinates":[8.24224,50.47624],"type":"Point"}
}