{
  "type": "Feature",
  "properties": {
    "gn:admin1_code":"6",
    "gn:admin2_code":"0.0",
    "gn:admin3_code":"3351.0",
    "gn:admin4_code":"3351005.0",
    "gn:asciiname":"Broeckel",
    "gn:country_code":"DE",
    "gn:dem":45,
    "gn:feature_class":"P",
    "gn:feature_code":"PPLA4",
    "gn:name":"Br\u00f6ckel",
    "gn:population":0,
    "gn:timezone":"Europe/Berlin",
    "iso:country":"DE",
    "name:ceb_x_preferred":[
        "Br\u00f6ckel"
    ],
    "name:deu_x_preferred":[
        "Br\u00f6ckel"
    ],
    "name:epo_x_preferred":[
        "Br\u00f6ckel"
    ],
    "name:est_x_preferred":[
        "Br\u00f6ckel"
    ],
    "name:eus_x_preferred":[
        "Br\u00f6ckel"
    ],
    "name:fra_x_preferred":[
        "Br\u00f6ckel"
    ],
    "name:gml_x_preferred":[
        "Brockelde [a. 1215]"
    ],
    "name:hun_x_preferred":[
        "Br\u00f6ckel"
    ],
    "name:ita_x_preferred":[
        "Br\u00f6ckel"
    ],
    "name:kaz_x_preferred":[
        "\u0411\u0440\u0451\u043a\u043a\u0435\u043b\u044c"
    ],
    "name:kir_x_preferred":[
        "\u0411\u0440\u04e9\u043a\u043a\u0435\u043b\u044c"
    ],
    "name:lat_x_preferred":[
        "Br\u00f6ckel"
    ],
    "name:mkd_x_preferred":[
        "\u0411\u0440\u0435\u043a\u0435\u043b"
    ],
    "name:msa_x_preferred":[
        "Br\u00f6ckel"
    ],
    "name:nds_x_preferred":[
        "Br\u00e4ukel"
    ],
    "name:nds_x_variant":[
        "Breukel"
    ],
    "name:nld_x_preferred":[
        "Br\u00f6ckel"
    ],
    "name:pol_x_preferred":[
        "Br\u00f6ckel"
    ],
    "name:por_x_preferred":[
        "Br\u00f6ckel"
    ],
    "name:ron_x_preferred":[
        "Br\u00f6ckel"
    ],
    "name:rus_x_preferred":[
        "\u0411\u0440\u0451\u043a\u043a\u0435\u043b\u044c"
    ],
    "name:spa_x_preferred":[
        "Br\u00f6ckel"
    ],
    "name:srp_x_preferred":[
        "\u0411\u0440\u0435\u043a\u0435\u043b"
    ],
    "name:ukr_x_preferred":[
        "\u0411\u0440\u0435\u043a\u0435\u043b\u044c"
    ],
    "name:uzb_x_preferred":[
        "Br\u00f6ckel"
    ],
    "name:vie_x_preferred":[
        "Br\u00f6ckel"
    ],
    "name:vol_x_preferred":[
        "Br\u00f6ckel"
    ],
    "name:war_x_preferred":[
        "Br\u00f6ckel"
    ],
    "name:zho_x_preferred":[
        "\u5e03\u52d2\u514b\u5c14"
    ],
    "wof:name":"Broeckel",
    "wof:placetype":"neighbourhood"
},
  "geometry": {"coordinates":[10.21505,52.51627],"type":"Point"}
}