{
  "type": "Feature",
  "properties": {
    "gn:admin1_code":"6",
    "gn:admin2_code":"0.0",
    "gn:admin3_code":"3351.0",
    "gn:admin4_code":"3351005.0",
    "gn:asciiname":"Broeckel",
    "gn:country_code":"DE",
    "gn:dem":45,
    "gn:feature_class":"P",
    "gn:feature_code":"PPLA4",
    "gn:name":"Br\u00f6ckel",
    "gn:population":0,
    "gn:timezone":"Europe/Berlin",
    "iso:country":"DE",
    "name:deu_x_preferred":[
        "Br\u00f6ckel"
    ],
    "name:gml_x_preferred":[
        "Brockelde [a. 1215]"
    ],
    "name:nds_x_preferred":[
        "Br\u00e4ukel"
    ],
    "name:nds_x_variant":[
        "Breukel"
    ],
    "wof:name":"Broeckel",
    "wof:placetype":"neighbourhood"
},
  "geometry": {"coordinates":[10.21505,52.51627],"type":"Point"}
}