{
  "type": "Feature",
  "properties": {
    "iso:country":"DE",
    "name:deu_x_preferred":[
        "Schwetzingerstadt"
    ],
    "name:eng_x_preferred":[
        "Schwetzingerstadt"
    ],
    "wof:name":"Schwetzingerstadt",
    "wof:placetype":"neighbourhood"
},
  "geometry": {"coordinates":[8.48007740451468,49.47670151691885],"type":"Point"}
}