{
  "type": "Feature",
  "properties": {
    "gn:gn_country":"DE",
    "gn:gn_fcode":"PPLA4",
    "gn:gn_pop":801,
    "gn:population":801,
    "iso:country":"DE",
    "name:arm_x_preferred":[
        "\u053c\u056b\u057a\u0565"
    ],
    "name:baq_x_preferred":[
        "Liepe"
    ],
    "name:chi_x_preferred":[
        "\u5229\u4f69"
    ],
    "name:dut_x_preferred":[
        "Liepe"
    ],
    "name:eng_x_preferred":[
        "Liepe"
    ],
    "name:epo_x_preferred":[
        "Liepe"
    ],
    "name:fre_x_preferred":[
        "Liepe"
    ],
    "name:ger_x_preferred":[
        "Liepe"
    ],
    "name:hun_x_preferred":[
        "Liepe"
    ],
    "name:ita_x_preferred":[
        "Liepe"
    ],
    "name:jpn_x_preferred":[
        "\u30ea\u30fc\u30da"
    ],
    "name:mac_x_preferred":[
        "\u041b\u0438\u043f\u0435"
    ],
    "name:may_x_preferred":[
        "Liepe"
    ],
    "name:pol_x_preferred":[
        "Liepe"
    ],
    "name:por_x_preferred":[
        "Liepe"
    ],
    "name:rum_x_preferred":[
        "Liepe"
    ],
    "name:rus_x_preferred":[
        "\u041b\u0438\u043f\u0435"
    ],
    "name:spa_x_preferred":[
        "Liepe"
    ],
    "name:srp_x_preferred":[
        "\u041b\u0438\u043f\u0435"
    ],
    "name:swe_x_preferred":[
        "Liepe"
    ],
    "name:ukr_x_preferred":[
        "\u041b\u0456\u043f\u0435"
    ],
    "name:uzb_x_preferred":[
        "Liepe"
    ],
    "name:vie_x_preferred":[
        "Liepe"
    ],
    "name:vol_x_preferred":[
        "Liepe"
    ],
    "name:war_x_preferred":[
        "Liepe"
    ],
    "qs_pg:aaroncc":"DE",
    "qs_pg:gn_country":"DE",
    "qs_pg:gn_fcode":"PPLA4",
    "qs_pg:gn_pop":801,
    "qs_pg:name":"Liepe",
    "qs_pg:photos_9r":0,
    "qs_pg:photos_sr":0,
    "qs_pg:pop_sr":2,
    "qs_pg:qs_pg_placetype":"locality",
    "wof:name":"Liepe",
    "wof:placetype":"locality",
    "wof:population":801
},
  "geometry": {"coordinates":[13.96946,52.86213],"type":"Point"}
}