{
  "type": "Feature",
  "properties": {
    "gn:admin1_code":"12",
    "gn:admin2_code":"0.0",
    "gn:admin3_code":"13071.0",
    "gn:admin4_code":"13071169.0",
    "gn:asciiname":"Peenwerder",
    "gn:country_code":"DE",
    "gn:dem":37,
    "gn:feature_class":"P",
    "gn:feature_code":"PPL",
    "gn:name":"Peenwerder",
    "gn:population":0,
    "gn:timezone":"Europe/Berlin",
    "iso:country":"DE",
    "wof:name":"Peenwerder",
    "wof:placetype":"neighbourhood"
},
  "geometry": {"coordinates":[12.82504,53.61676],"type":"Point"}
}