{
  "type": "Feature",
  "properties": {
    "gn:admin1_code":"7",
    "gn:admin2_code":"53.0",
    "gn:admin3_code":"5358.0",
    "gn:admin4_code":"5358032.0",
    "gn:asciiname":"Geich",
    "gn:country_code":"DE",
    "gn:dem":127,
    "gn:feature_class":"P",
    "gn:feature_code":"PPL",
    "gn:name":"Geich",
    "gn:population":0,
    "gn:timezone":"Europe/Berlin",
    "iso:country":"DE",
    "wof:name":"Geich",
    "wof:placetype":"neighbourhood"
},
  "geometry": {"coordinates":[6.39922,50.81817],"type":"Point"}
}