{
  "type": "Feature",
  "properties": {
    "gn:admin1_code":"2",
    "gn:admin2_code":"91.0",
    "gn:admin3_code":"9178.0",
    "gn:admin4_code":"9178155.0",
    "gn:asciiname":"Sporerau",
    "gn:country_code":"DE",
    "gn:dem":408,
    "gn:feature_class":"P",
    "gn:feature_code":"PPL",
    "gn:name":"Sp\u00f6rerau",
    "gn:population":0,
    "gn:timezone":"Europe/Berlin",
    "iso:country":"DE",
    "wof:name":"Sporerau",
    "wof:placetype":"neighbourhood"
},
  "geometry": {"coordinates":[12.00256,48.49031],"type":"Point"}
}