{
  "type": "Feature",
  "properties": {
    "gn:admin1_code":"8.0",
    "gn:admin2_code":"0.0",
    "gn:admin3_code":"7232.0",
    "gn:admin4_code":"7232253.0",
    "gn:asciiname":"Bellscheid",
    "gn:country_code":"DE",
    "gn:dem":465,
    "gn:feature_class":"P",
    "gn:feature_code":"PPL",
    "gn:name":"Bellscheid",
    "gn:population":0,
    "gn:timezone":"Europe/Berlin",
    "iso:country":"DE",
    "wof:name":"Bellscheid",
    "wof:placetype":"neighbourhood"
},
  "geometry": {"coordinates":[6.34826,50.07298],"type":"Point"}
}