{
  "type": "Feature",
  "properties": {
    "gn:admin1_code":"12",
    "gn:admin2_code":"0.0",
    "gn:admin3_code":"13073.0",
    "gn:admin4_code":"13073059.0",
    "gn:asciiname":"Moor",
    "gn:country_code":"DE",
    "gn:dem":1,
    "gn:feature_class":"P",
    "gn:feature_code":"PPL",
    "gn:name":"Moor",
    "gn:population":0,
    "gn:timezone":"Europe/Berlin",
    "iso:country":"DE",
    "name:ceb_x_preferred":[
        "Moor"
    ],
    "name:ces_x_preferred":[
        "Moor"
    ],
    "name:deu_x_preferred":[
        "Moor"
    ],
    "name:fra_x_preferred":[
        "Moor"
    ],
    "name:hye_x_preferred":[
        "\u0544\u0561\u057e\u0580\u0565\u0580"
    ],
    "name:ita_x_preferred":[
        "Moor"
    ],
    "name:nds_x_preferred":[
        "Moor"
    ],
    "name:nld_x_preferred":[
        "Moor"
    ],
    "name:pol_x_preferred":[
        "Moor"
    ],
    "name:rus_x_preferred":[
        "\u041c\u043e\u043e\u0440"
    ],
    "name:swe_x_preferred":[
        "Moor"
    ],
    "wof:name":"Moor",
    "wof:placetype":"neighbourhood"
},
  "geometry": {"coordinates":[13.32739,54.54924000000001],"type":"Point"}
}