{
  "type": "Feature",
  "properties": {
    "gn:admin1_code":"11.0",
    "gn:admin2_code":"0.0",
    "gn:admin3_code":"12064.0",
    "gn:admin4_code":"12064057.0",
    "gn:asciiname":"Bleyen",
    "gn:cc2":"DE",
    "gn:country_code":"DE",
    "gn:dem":10,
    "gn:feature_class":"P",
    "gn:feature_code":"PPL",
    "gn:name":"Bleyen",
    "gn:population":0,
    "gn:timezone":"Europe/Berlin",
    "iso:country":"DE",
    "name:und_x_variant":[
        "Alt und Neu Bleyen"
    ],
    "wof:name":"Bleyen",
    "wof:placetype":"neighbourhood"
},
  "geometry": {"coordinates":[14.59765,52.58944],"type":"Point"}
}