{
  "type": "Feature",
  "properties": {
    "gn:admin1_code":"7",
    "gn:admin2_code":"59.0",
    "gn:admin3_code":"5970.0",
    "gn:admin4_code":"5970032.0",
    "gn:asciiname":"OElgershausen",
    "gn:country_code":"DE",
    "gn:dem":312,
    "gn:feature_class":"P",
    "gn:feature_code":"PPL",
    "gn:name":"\u00d6lgershausen",
    "gn:population":0,
    "gn:timezone":"Europe/Berlin",
    "iso:country":"DE",
    "wof:name":"OElgershausen",
    "wof:placetype":"neighbourhood"
},
  "geometry": {"coordinates":[8.08856,50.92414],"type":"Point"}
}