{
  "type": "Feature",
  "properties": {
    "gn:admin1_code":"15",
    "gn:admin2_code":"0.0",
    "gn:admin3_code":"16070.0",
    "gn:admin4_code":"16070053.0",
    "gn:asciiname":"Ettischleben",
    "gn:country_code":"DE",
    "gn:dem":299,
    "gn:feature_class":"P",
    "gn:feature_code":"PPL",
    "gn:name":"Ettischleben",
    "gn:population":0,
    "gn:timezone":"Europe/Berlin",
    "iso:country":"DE",
    "wof:name":"Ettischleben",
    "wof:placetype":"neighbourhood"
},
  "geometry": {"coordinates":[11.0359,50.83805],"type":"Point"}
}