{
  "type": "Feature",
  "properties": {
    "gn:admin1_code":"2",
    "gn:admin2_code":"93.0",
    "gn:admin3_code":"9376.0",
    "gn:admin4_code":"9376149.0",
    "gn:asciiname":"Goppeltshof",
    "gn:country_code":"DE",
    "gn:dem":455,
    "gn:feature_class":"P",
    "gn:feature_code":"PPL",
    "gn:name":"Goppeltshof",
    "gn:population":0,
    "gn:timezone":"Europe/Berlin",
    "iso:country":"DE",
    "wof:name":"Goppeltshof",
    "wof:placetype":"neighbourhood"
},
  "geometry": {"coordinates":[12.27737,49.15729],"type":"Point"}
}