{
  "type": "Feature",
  "properties": {
    "gn:admin1_code":"2",
    "gn:admin2_code":"97.0",
    "gn:admin3_code":"9776.0",
    "gn:admin4_code":"9776114.0",
    "gn:asciiname":"Menzen",
    "gn:country_code":"DE",
    "gn:dem":691,
    "gn:feature_class":"P",
    "gn:feature_code":"PPL",
    "gn:name":"Menzen",
    "gn:population":0,
    "gn:timezone":"Europe/Berlin",
    "iso:country":"DE",
    "wof:name":"Menzen",
    "wof:placetype":"neighbourhood"
},
  "geometry": {"coordinates":[9.91667,47.63333],"type":"Point"}
}