{
  "type": "Feature",
  "properties": {
    "gn:admin1_code":"15",
    "gn:admin2_code":"0.0",
    "gn:admin3_code":"16063.0",
    "gn:admin4_code":"16063098.0",
    "gn:asciiname":"Ettenhausen",
    "gn:country_code":"DE",
    "gn:dem":250,
    "gn:feature_class":"P",
    "gn:feature_code":"PPL",
    "gn:name":"Ettenhausen",
    "gn:population":0,
    "gn:timezone":"Europe/Berlin",
    "iso:country":"DE",
    "name:chv_x_preferred":[
        "\u042d\u0442\u0442\u0435\u043d\u0445\u0430\u0443\u0437\u0435\u043d"
    ],
    "name:deu_x_preferred":[
        "Ettenhausen"
    ],
    "name:hye_x_preferred":[
        "\u0537\u057f\u057f\u0565\u0576\u0570\u0561\u0578\u0582\u0566\u0565\u0576"
    ],
    "name:ita_x_preferred":[
        "Ettenhausen"
    ],
    "name:kaz_x_preferred":[
        "\u042d\u0442\u0442\u0435\u043d\u0445\u0430\u0443\u0437\u0435\u043d"
    ],
    "name:nld_x_preferred":[
        "Ettenhausen"
    ],
    "name:rus_x_preferred":[
        "\u042d\u0442\u0442\u0435\u043d\u0445\u0430\u0443\u0437\u0435\u043d"
    ],
    "name:uzb_x_preferred":[
        "Ettenhausen"
    ],
    "wof:name":"Ettenhausen",
    "wof:placetype":"neighbourhood"
},
  "geometry": {"coordinates":[10.47432,50.97416],"type":"Point"}
}