{
  "type": "Feature",
  "properties": {
    "gn:admin1_code":"2.0",
    "gn:admin2_code":"92.0",
    "gn:admin3_code":"9273.0",
    "gn:admin4_code":"9273164.0",
    "gn:asciiname":"Baiersdorf",
    "gn:country_code":"DE",
    "gn:dem":531,
    "gn:feature_class":"P",
    "gn:feature_code":"PPL",
    "gn:name":"Baiersdorf",
    "gn:population":0,
    "gn:timezone":"Europe/Berlin",
    "iso:country":"DE",
    "name:ara_x_preferred":[
        "\u0628\u0627\u064a\u0631\u0633\u062f\u0648\u0631\u0641"
    ],
    "name:azb_x_preferred":[
        "\u0628\u0627\u06cc\u0631\u0633\u062f\u0648\u0631\u0641"
    ],
    "name:bre_x_preferred":[
        "Baiersdorf"
    ],
    "name:bul_x_preferred":[
        "\u0411\u0430\u0439\u0435\u0440\u0441\u0434\u043e\u0440\u0444"
    ],
    "name:dan_x_preferred":[
        "Baiersdorf"
    ],
    "name:deu_x_preferred":[
        "Baiersdorf"
    ],
    "name:epo_x_preferred":[
        "Baiersdorf"
    ],
    "name:fas_x_preferred":[
        "\u0628\u0627\u06cc\u0631\u0633\u062f\u0648\u0631\u0641"
    ],
    "name:fra_x_preferred":[
        "Baiersdorf"
    ],
    "name:hun_x_preferred":[
        "Baiersdorf"
    ],
    "name:ind_x_preferred":[
        "Baiersdorf"
    ],
    "name:ita_x_preferred":[
        "Baiersdorf"
    ],
    "name:jpn_x_preferred":[
        "\u30d0\u30a4\u30a2\u30fc\u30b9\u30c9\u30eb\u30d5"
    ],
    "name:kaz_x_preferred":[
        "\u0411\u0430\u0439\u0435\u0440\u0441\u0434\u043e\u0440\u0444"
    ],
    "name:kir_x_preferred":[
        "\u0411\u0430\u0439\u0435\u0440\u0441\u0434\u043e\u0440\u0444"
    ],
    "name:lat_x_preferred":[
        "Baiersdorf"
    ],
    "name:lmo_x_preferred":[
        "Baiersdorf"
    ],
    "name:msa_x_preferred":[
        "Baiersdorf"
    ],
    "name:nld_x_preferred":[
        "Baiersdorf"
    ],
    "name:pnb_x_preferred":[
        "\u0628\u06cc\u0631\u0633\u0688\u0648\u0631\u0641"
    ],
    "name:pol_x_preferred":[
        "Baiersdorf"
    ],
    "name:por_x_preferred":[
        "Baiersdorf"
    ],
    "name:ron_x_preferred":[
        "Baiersdorf"
    ],
    "name:rus_x_preferred":[
        "\u0411\u0430\u0439\u0435\u0440\u0441\u0434\u043e\u0440\u0444"
    ],
    "name:spa_x_preferred":[
        "Baiersdorf"
    ],
    "name:srp_x_preferred":[
        "\u0411\u0430\u0458\u0440\u0441\u0434\u043e\u0440\u0444"
    ],
    "name:swe_x_preferred":[
        "Baiersdorf"
    ],
    "name:tur_x_preferred":[
        "Baiersdorf"
    ],
    "name:ukr_x_preferred":[
        "\u0411\u0430\u0454\u0440\u0441\u0434\u043e\u0440\u0444"
    ],
    "name:vie_x_preferred":[
        "Baiersdorf"
    ],
    "name:vol_x_preferred":[
        "Baiersdorf"
    ],
    "name:war_x_preferred":[
        "Baiersdorf"
    ],
    "name:zho_x_preferred":[
        "\u62dc\u5c14\u65af\u591a\u592b"
    ],
    "wof:name":"Baiersdorf",
    "wof:placetype":"neighbourhood"
},
  "geometry": {"coordinates":[11.74503,48.96397],"type":"Point"}
}