{
  "type": "Feature",
  "properties": {
    "gn:admin1_code":"2.0",
    "gn:admin2_code":"92.0",
    "gn:admin3_code":"9273.0",
    "gn:admin4_code":"9273164.0",
    "gn:asciiname":"Baiersdorf",
    "gn:country_code":"DE",
    "gn:dem":531,
    "gn:feature_class":"P",
    "gn:feature_code":"PPL",
    "gn:name":"Baiersdorf",
    "gn:population":0,
    "gn:timezone":"Europe/Berlin",
    "iso:country":"DE",
    "wof:name":"Baiersdorf",
    "wof:placetype":"neighbourhood"
},
  "geometry": {"coordinates":[11.74503,48.96397],"type":"Point"}
}