{
  "type": "Feature",
  "properties": {
    "gn:admin1_code":"15",
    "gn:admin2_code":"0.0",
    "gn:admin3_code":"16076.0",
    "gn:admin4_code":"16076092.0",
    "gn:asciiname":"Kroelpa",
    "gn:country_code":"DE",
    "gn:dem":401,
    "gn:feature_class":"P",
    "gn:feature_code":"PPL",
    "gn:name":"Kr\u00f6lpa",
    "gn:population":0,
    "gn:timezone":"Europe/Berlin",
    "iso:country":"DE",
    "wof:name":"Kroelpa",
    "wof:placetype":"neighbourhood"
},
  "geometry": {"coordinates":[11.87954,50.6739],"type":"Point"}
}