{
  "type": "Feature",
  "properties": {
    "gn:admin1_code":"6.0",
    "gn:admin2_code":"0.0",
    "gn:admin3_code":"3459.0",
    "gn:admin4_code":"3459022.0",
    "gn:asciiname":"Auheide",
    "gn:country_code":"DE",
    "gn:dem":138,
    "gn:feature_class":"P",
    "gn:feature_code":"PPLL",
    "gn:name":"Auheide",
    "gn:population":0,
    "gn:timezone":"Europe/Berlin",
    "iso:country":"DE",
    "wof:name":"Auheide",
    "wof:placetype":"neighbourhood"
},
  "geometry": {"coordinates":[8.18333,52.18333],"type":"Point"}
}