{
  "type": "Feature",
  "properties": {
    "gn:admin1_code":"12",
    "gn:admin2_code":"0.0",
    "gn:admin3_code":"13074.0",
    "gn:admin4_code":"13074008.0",
    "gn:asciiname":"Koechelsdorf",
    "gn:country_code":"DE",
    "gn:dem":67,
    "gn:feature_class":"P",
    "gn:feature_code":"PPL",
    "gn:name":"K\u00f6chelsdorf",
    "gn:population":0,
    "gn:timezone":"Europe/Berlin",
    "iso:country":"DE",
    "wof:name":"Koechelsdorf",
    "wof:placetype":"neighbourhood"
},
  "geometry": {"coordinates":[11.35401,53.82978000000001],"type":"Point"}
}