{
  "type": "Feature",
  "properties": {
    "gn:admin1_code":"2",
    "gn:admin2_code":"97.0",
    "gn:admin3_code":"9778.0",
    "gn:admin4_code":"9778137.0",
    "gn:asciiname":"Forsthofen",
    "gn:country_code":"DE",
    "gn:dem":591,
    "gn:feature_class":"P",
    "gn:feature_code":"PPL",
    "gn:name":"Forsthofen",
    "gn:population":0,
    "gn:timezone":"Europe/Berlin",
    "iso:country":"DE",
    "wof:name":"Forsthofen",
    "wof:placetype":"neighbourhood"
},
  "geometry": {"coordinates":[10.66128,48.16418],"type":"Point"}
}