{
  "type": "Feature",
  "properties": {
    "gn:gn_country":"DE",
    "gn:gn_fcode":"PPL",
    "gn:gn_pop":0,
    "iso:country":"DE",
    "name:ceb_x_preferred":[
        "Werse"
    ],
    "name:chv_x_preferred":[
        "\u0412\u0435\u0440\u0437\u0435"
    ],
    "name:deu_x_preferred":[
        "Werse"
    ],
    "name:fry_x_preferred":[
        "Werse"
    ],
    "name:rus_x_preferred":[
        "\u0412\u0435\u0440\u0437\u0435"
    ],
    "qs_pg:aaroncc":"DE",
    "qs_pg:gn_country":"DE",
    "qs_pg:gn_fcode":"PPL",
    "qs_pg:gn_pop":0,
    "qs_pg:name":"Werse",
    "qs_pg:name_adm0":"Deutschland",
    "qs_pg:name_adm1":"Nordrhein-Westfalen",
    "qs_pg:photos":24,
    "qs_pg:photos_1k":5,
    "qs_pg:photos_9k":1,
    "qs_pg:photos_9r":1,
    "qs_pg:photos_all":24,
    "qs_pg:photos_sr":1,
    "qs_pg:pop_sr":0,
    "qs_pg:qs_pg_placetype":"neighbourhood",
    "qs_pg:qs_pg_placetype_gp":"Suburb",
    "qs_pg:woe_adm0":23424829,
    "woe:adm0_id":23424829,
    "woe:name_adm0":"Deutschland",
    "woe:name_adm1":"Nordrhein-Westfalen",
    "woe:placetype":"Suburb",
    "wof:name":"Werse",
    "wof:placetype":"neighbourhood"
},
  "geometry": {"coordinates":[7.93448,52.31308],"type":"Point"}
}