{
  "type": "Feature",
  "properties": {
    "gn:admin1_code":"2",
    "gn:admin2_code":"93.0",
    "gn:admin3_code":"9373.0",
    "gn:admin4_code":"9373134.0",
    "gn:asciiname":"Holzheim",
    "gn:country_code":"DE",
    "gn:dem":459,
    "gn:feature_class":"P",
    "gn:feature_code":"PPL",
    "gn:name":"Holzheim",
    "gn:population":0,
    "gn:timezone":"Europe/Berlin",
    "iso:country":"DE",
    "wof:name":"Holzheim",
    "wof:placetype":"neighbourhood"
},
  "geometry": {"coordinates":[11.84369,49.18608],"type":"Point"}
}