{
  "type": "Feature",
  "properties": {
    "gn:admin1_code":"10.0",
    "gn:admin2_code":"00",
    "gn:admin3_code":"1058.0",
    "gn:admin4_code":"1058030.0",
    "gn:asciiname":"Wolfskrug",
    "gn:country_code":"DE",
    "gn:dem":24,
    "gn:feature_class":"P",
    "gn:feature_code":"PPL",
    "gn:name":"Wolfskrug",
    "gn:population":0,
    "gn:timezone":"Europe/Berlin",
    "iso:country":"DE",
    "wof:name":"Wolfskrug",
    "wof:placetype":"neighbourhood"
},
  "geometry": {"coordinates":[9.64269,54.45441999999999],"type":"Point"}
}