{
  "type": "Feature",
  "properties": {
    "gn:admin1_code":"2.0",
    "gn:admin2_code":"092",
    "gn:admin3_code":"9278.0",
    "gn:admin4_code":"9278116.0",
    "gn:asciiname":"Willerszell",
    "gn:country_code":"DE",
    "gn:dem":442,
    "gn:feature_class":"P",
    "gn:feature_code":"PPL",
    "gn:name":"Willerszell",
    "gn:population":0,
    "gn:timezone":"Europe/Berlin",
    "iso:country":"DE",
    "wof:name":"Willerszell",
    "wof:placetype":"neighbourhood"
},
  "geometry": {"coordinates":[12.61748,49.01605],"type":"Point"}
}