{
  "type": "Feature",
  "properties": {
    "gn:admin1_code":"2",
    "gn:admin2_code":"93.0",
    "gn:admin3_code":"9377.0",
    "gn:admin4_code":"9377154.0",
    "gn:asciiname":"Pilmersreuth an der Strasse",
    "gn:country_code":"DE",
    "gn:dem":540,
    "gn:feature_class":"P",
    "gn:feature_code":"PPL",
    "gn:name":"Pilmersreuth an der Stra\u00dfe",
    "gn:population":0,
    "gn:timezone":"Europe/Berlin",
    "iso:country":"DE",
    "name:und_x_variant":[
        "Pilmersreuth",
        "Pilmersreuth an der Stra\u00dfe"
    ],
    "wof:name":"Pilmersreuth an der Strasse",
    "wof:placetype":"neighbourhood"
},
  "geometry": {"coordinates":[12.30769,49.83309000000001],"type":"Point"}
}