{
  "type": "Feature",
  "properties": {
    "gn:admin1_code":"7",
    "gn:admin2_code":"59.0",
    "gn:admin3_code":"5958.0",
    "gn:admin4_code":"5958008.0",
    "gn:asciiname":"Grimlinghausen",
    "gn:country_code":"DE",
    "gn:dem":403,
    "gn:feature_class":"P",
    "gn:feature_code":"PPL",
    "gn:name":"Grimlinghausen",
    "gn:population":0,
    "gn:timezone":"Europe/Berlin",
    "iso:country":"DE",
    "wof:name":"Grimlinghausen",
    "wof:placetype":"neighbourhood"
},
  "geometry": {"coordinates":[8.44109,51.39489],"type":"Point"}
}