{
  "type": "Feature",
  "properties": {
    "gn:country":"DE",
    "gn:fcode":"PPL",
    "gn:population":0,
    "iso:country":"DE",
    "name:als_x_preferred":[
        "Scheuren"
    ],
    "name:ceb_x_preferred":[
        "Scheuren"
    ],
    "name:deu_x_preferred":[
        "Scheuren"
    ],
    "name:epo_x_preferred":[
        "Scheuren"
    ],
    "name:eus_x_preferred":[
        "Scheuren"
    ],
    "name:fra_x_preferred":[
        "Scheuren"
    ],
    "name:ita_x_preferred":[
        "Scheuren"
    ],
    "name:kaz_x_preferred":[
        "\u0428\u043e\u0439\u0440\u0435\u043d"
    ],
    "name:lmo_x_preferred":[
        "Scheuren"
    ],
    "name:msa_x_preferred":[
        "Scheuren"
    ],
    "name:nld_x_preferred":[
        "Scheuren"
    ],
    "name:nno_x_preferred":[
        "Scheuren"
    ],
    "name:rus_x_preferred":[
        "\u0428\u043e\u0439\u0440\u0435\u043d"
    ],
    "name:spa_x_preferred":[
        "Scheuren"
    ],
    "name:sqi_x_preferred":[
        "Scheuren"
    ],
    "name:swe_x_preferred":[
        "Scheuren"
    ],
    "name:vol_x_preferred":[
        "Scheuren"
    ],
    "name:war_x_preferred":[
        "Scheuren"
    ],
    "name:zho_x_preferred":[
        "\u7d39\u4f0a\u502b"
    ],
    "qs_pg:aaroncc":"DE",
    "qs_pg:gn_country":"DE",
    "qs_pg:gn_fcode":"PPL",
    "qs_pg:gn_pop":0,
    "qs_pg:name":"Scheuren",
    "qs_pg:name_adm0":"Deutschland",
    "qs_pg:name_adm1":"Nordrhein-Westfalen",
    "qs_pg:photos":5,
    "qs_pg:photos_1k":1,
    "qs_pg:photos_9k":1,
    "qs_pg:photos_9r":1,
    "qs_pg:photos_all":5,
    "qs_pg:photos_sr":1,
    "qs_pg:pop_sr":0,
    "qs_pg:qs_pg_placetype":"locality",
    "qs_pg:qs_pg_placetype_gp":"Town",
    "qs_pg:woe_adm0":23424829,
    "woe:adm0_id":23424829,
    "woe:name_adm0":"Deutschland",
    "woe:name_adm1":"Nordrhein-Westfalen",
    "woe:placetype":"Town",
    "wof:name":"Scheuren",
    "wof:placetype":"neighbourhood"
},
  "geometry": {"coordinates":[6.90238,50.55822],"type":"Point"}
}