{
  "type": "Feature",
  "properties": {
    "gn:admin1_code":"2",
    "gn:admin2_code":"94.0",
    "gn:admin3_code":"9474.0",
    "gn:admin4_code":"9474126.0",
    "gn:asciiname":"Buckenhofen",
    "gn:country_code":"DE",
    "gn:dem":265,
    "gn:feature_class":"P",
    "gn:feature_code":"PPL",
    "gn:name":"Buckenhofen",
    "gn:population":0,
    "gn:timezone":"Europe/Berlin",
    "iso:country":"DE",
    "wof:name":"Buckenhofen",
    "wof:placetype":"neighbourhood"
},
  "geometry": {"coordinates":[11.04507,49.72865],"type":"Point"}
}