{
  "type": "Feature",
  "properties": {
    "gn:admin1_code":"2",
    "gn:admin2_code":"91.0",
    "gn:admin3_code":"9183.0",
    "gn:admin4_code":"9183132.0",
    "gn:asciiname":"Ritzing",
    "gn:country_code":"DE",
    "gn:dem":475,
    "gn:feature_class":"P",
    "gn:feature_code":"PPL",
    "gn:name":"Ritzing",
    "gn:population":0,
    "gn:timezone":"Europe/Berlin",
    "iso:country":"DE",
    "name:ceb_x_preferred":[
        "Ritzing"
    ],
    "name:ces_x_preferred":[
        "Ritzing"
    ],
    "name:deu_x_preferred":[
        "Ritzing"
    ],
    "name:epo_x_preferred":[
        "Ritzing"
    ],
    "name:fas_x_preferred":[
        "\u0631\u06cc\u062a\u0633\u06cc\u0646\u06af"
    ],
    "name:fra_x_preferred":[
        "Ritzing"
    ],
    "name:hrv_x_preferred":[
        "Ricinja"
    ],
    "name:hun_x_preferred":[
        "R\u00e9c\u00e9ny"
    ],
    "name:ita_x_preferred":[
        "Ritzing"
    ],
    "name:kaz_x_preferred":[
        "\u0420\u0438\u0442\u0446\u0438\u043d\u0433"
    ],
    "name:nld_x_preferred":[
        "Ritzing"
    ],
    "name:pol_x_preferred":[
        "Ritzing"
    ],
    "name:por_x_preferred":[
        "Ritzing"
    ],
    "name:rus_x_preferred":[
        "\u0420\u0438\u0442\u0446\u0438\u043d\u0433"
    ],
    "name:slk_x_preferred":[
        "Ritzing"
    ],
    "name:spa_x_preferred":[
        "Ritzing"
    ],
    "name:swe_x_preferred":[
        "Ritzing"
    ],
    "name:tur_x_preferred":[
        "Ritzing"
    ],
    "name:ukr_x_preferred":[
        "\u0420\u0456\u0442\u0446\u0438\u043d\u0433"
    ],
    "name:uzb_x_preferred":[
        "Ritzing"
    ],
    "name:vol_x_preferred":[
        "Ritzing"
    ],
    "name:war_x_preferred":[
        "Ritzing"
    ],
    "name:zho_x_preferred":[
        "\u91cc\u7279\u8d5e"
    ],
    "wof:name":"Ritzing",
    "wof:placetype":"neighbourhood"
},
  "geometry": {"coordinates":[12.36157,48.3168],"type":"Point"}
}