{
  "type": "Feature",
  "properties": {
    "gn:admin1_code":"7",
    "gn:admin2_code":"53.0",
    "gn:admin3_code":"5366.0",
    "gn:admin4_code":"5366024.0",
    "gn:asciiname":"Dottel",
    "gn:country_code":"DE",
    "gn:dem":460,
    "gn:feature_class":"P",
    "gn:feature_code":"PPL",
    "gn:name":"Dottel",
    "gn:population":0,
    "gn:timezone":"Europe/Berlin",
    "iso:country":"DE",
    "wof:name":"Dottel",
    "wof:placetype":"neighbourhood"
},
  "geometry": {"coordinates":[6.59745,50.5481],"type":"Point"}
}