{
  "type": "Feature",
  "properties": {
    "gn:admin1_code":"8.0",
    "gn:admin2_code":"00",
    "gn:admin3_code":"7135.0",
    "gn:admin4_code":"7135090.0",
    "gn:asciiname":"Wirfuserbach",
    "gn:country_code":"DE",
    "gn:dem":318,
    "gn:feature_class":"P",
    "gn:feature_code":"PPL",
    "gn:name":"Wirfuserbach",
    "gn:population":0,
    "gn:timezone":"Europe/Berlin",
    "iso:country":"DE",
    "wof:name":"Wirfuserbach",
    "wof:placetype":"neighbourhood"
},
  "geometry": {"coordinates":[7.19397,50.21049],"type":"Point"}
}