{
  "type": "Feature",
  "properties": {
    "gn:admin1_code":"11.0",
    "gn:admin2_code":"0.0",
    "gn:admin3_code":"12073.0",
    "gn:admin4_code":"12073097.0",
    "gn:asciiname":"Blumberg",
    "gn:country_code":"DE",
    "gn:dem":59,
    "gn:feature_class":"P",
    "gn:feature_code":"PPL",
    "gn:name":"Blumberg",
    "gn:population":0,
    "gn:timezone":"Europe/Berlin",
    "iso:country":"DE",
    "wof:name":"Blumberg",
    "wof:placetype":"neighbourhood"
},
  "geometry": {"coordinates":[14.15245,53.20614000000001],"type":"Point"}
}