{
  "type": "Feature",
  "properties": {
    "gn:admin1_code":"11.0",
    "gn:admin2_code":"0.0",
    "gn:admin3_code":"12073.0",
    "gn:admin4_code":"12073097.0",
    "gn:asciiname":"Blumberg",
    "gn:country_code":"DE",
    "gn:dem":59,
    "gn:feature_class":"P",
    "gn:feature_code":"PPL",
    "gn:name":"Blumberg",
    "gn:population":0,
    "gn:timezone":"Europe/Berlin",
    "iso:country":"DE",
    "name:als_x_preferred":[
        "Blumberg"
    ],
    "name:ara_x_preferred":[
        "\u0628\u0644\u0648\u0645\u0628\u0631\u063a"
    ],
    "name:ceb_x_preferred":[
        "Blumberg"
    ],
    "name:deu_x_preferred":[
        "Blumberg"
    ],
    "name:epo_x_preferred":[
        "Blumberg"
    ],
    "name:fas_x_preferred":[
        "\u0628\u0644\u0648\u0645\u0628\u0631\u06af"
    ],
    "name:fra_x_preferred":[
        "Blumberg"
    ],
    "name:hun_x_preferred":[
        "Blumberg"
    ],
    "name:ita_x_preferred":[
        "Blumberg"
    ],
    "name:lat_x_preferred":[
        "Blumberg"
    ],
    "name:lmo_x_preferred":[
        "Blumberg"
    ],
    "name:msa_x_preferred":[
        "Blumberg"
    ],
    "name:nld_x_preferred":[
        "Blumberg"
    ],
    "name:pol_x_preferred":[
        "Blumberg"
    ],
    "name:por_x_preferred":[
        "Blumberg"
    ],
    "name:ron_x_preferred":[
        "Blumberg"
    ],
    "name:rus_x_preferred":[
        "\u0411\u043b\u0443\u043c\u0431\u0435\u0440\u0433"
    ],
    "name:spa_x_preferred":[
        "Blumberg"
    ],
    "name:srp_x_preferred":[
        "\u0411\u043b\u0443\u043c\u0431\u0435\u0440\u0433"
    ],
    "name:tur_x_preferred":[
        "Blumberg"
    ],
    "name:ukr_x_preferred":[
        "\u0411\u043b\u0443\u043c\u0431\u0435\u0440\u0433"
    ],
    "name:vol_x_preferred":[
        "Blumberg"
    ],
    "name:war_x_preferred":[
        "Blumberg"
    ],
    "wof:name":"Blumberg",
    "wof:placetype":"neighbourhood"
},
  "geometry": {"coordinates":[14.15245,53.20614000000001],"type":"Point"}
}