{
  "type": "Feature",
  "properties": {
    "gn:country":"DE",
    "gn:fcode":"PPLX",
    "gn:population":0,
    "iso:country":"DE",
    "name:deu_x_colloquial":[
        "Neumuhlen",
        "Neumuehlen"
    ],
    "name:deu_x_preferred":[
        "Neum\u00fchlen"
    ],
    "qs:gn_fcode":"PPLX",
    "qs:gn_local":0,
    "qs:gn_namadm1":"10",
    "qs:gn_name":"Neum\u00fchlen",
    "qs:local_max":513,
    "qs:local_sum":878,
    "qs:localhoods":2,
    "qs:name":"Neum\u00fchlen",
    "qs:name_adm0":"Deutschland",
    "qs:name_adm1":"Schleswig-Holstein",
    "qs:name_adm2":"Stadtkreis Kiel",
    "qs:name_lau":"Neum\u00fchlen-Dietrichsdorf",
    "qs:name_local":"Neum\u00fchlen-Dietrichsdorf",
    "qs:photo_max":399,
    "qs:photo_sum":513,
    "qs:placetype":"Suburb",
    "qs:quad_count":10,
    "qs:woe_adm0":23424829,
    "qs:woe_adm1":2345490,
    "qs:woe_adm2":12597053,
    "qs:woe_lau":26822754,
    "qs:woe_local":26822754,
    "qs:woe_ver":"7.10.0",
    "qs_pg:aaroncc":"DE",
    "qs_pg:gn_country":"DE",
    "qs_pg:gn_fcode":"PPLX",
    "qs_pg:gn_pop":0,
    "qs_pg:name":"Neum\u00fchlen",
    "qs_pg:name_adm0":"Deutschland",
    "qs_pg:name_adm1":"Schleswig-Holstein",
    "qs_pg:photos":544,
    "qs_pg:photos_1k":110,
    "qs_pg:photos_9k":2,
    "qs_pg:photos_9r":5,
    "qs_pg:photos_all":544,
    "qs_pg:photos_sr":7,
    "qs_pg:pop_sr":0,
    "qs_pg:qs_pg_placetype":"neighbourhood",
    "qs_pg:qs_pg_placetype_gp":"Suburb",
    "qs_pg:woe_adm0":23424829,
    "wof:lang":[
        "ger"
    ],
    "wof:name":"Neum\u00fchlen",
    "wof:placetype":"neighbourhood"
},
  "geometry": {"coordinates":[10.216886,54.335435],"type":"Point"}
}