{
  "type": "Feature",
  "properties": {
    "gn:admin1_code":"15",
    "gn:admin2_code":"0.0",
    "gn:admin3_code":"16064.0",
    "gn:admin4_code":"16064071.0",
    "gn:asciiname":"Dachrieden",
    "gn:country_code":"DE",
    "gn:dem":259,
    "gn:feature_class":"P",
    "gn:feature_code":"PPL",
    "gn:name":"Dachrieden",
    "gn:population":0,
    "gn:timezone":"Europe/Berlin",
    "iso:country":"DE",
    "wof:name":"Dachrieden",
    "wof:placetype":"neighbourhood"
},
  "geometry": {"coordinates":[10.44519,51.26584],"type":"Point"}
}