{
  "type": "Feature",
  "properties": {
    "gn:admin1_code":"6.0",
    "gn:admin2_code":"00",
    "gn:admin3_code":"3151.0",
    "gn:admin4_code":"3151040.0",
    "gn:asciiname":"Wollerstorf",
    "gn:country_code":"DE",
    "gn:dem":73,
    "gn:feature_class":"P",
    "gn:feature_code":"PPL",
    "gn:name":"Wollerstorf",
    "gn:population":0,
    "gn:timezone":"Europe/Berlin",
    "iso:country":"DE",
    "wof:name":"Wollerstorf",
    "wof:placetype":"neighbourhood"
},
  "geometry": {"coordinates":[10.6788,52.75193],"type":"Point"}
}