{
  "type": "Feature",
  "properties": {
    "gn:admin1_code":"13",
    "gn:admin2_code":"0.0",
    "gn:admin3_code":"14522.0",
    "gn:admin4_code":"14522520.0",
    "gn:asciiname":"Friedebach",
    "gn:country_code":"DE",
    "gn:dem":599,
    "gn:feature_class":"P",
    "gn:feature_code":"PPL",
    "gn:name":"Friedebach",
    "gn:population":0,
    "gn:timezone":"Europe/Berlin",
    "iso:country":"DE",
    "wof:name":"Friedebach",
    "wof:placetype":"neighbourhood"
},
  "geometry": {"coordinates":[13.45223,50.72462],"type":"Point"}
}