{
  "type": "Feature",
  "properties": {
    "gn:gn_country":"DE",
    "gn:gn_fcode":"PPLA4",
    "gn:gn_pop":709,
    "gn:population":709,
    "iso:country":"DE",
    "name:baq_x_preferred":[
        "Gevenich"
    ],
    "name:chi_x_preferred":[
        "\u683c\u8d39\u5c3c\u5e0c"
    ],
    "name:dut_x_preferred":[
        "Gevenich"
    ],
    "name:eng_x_preferred":[
        "Gevenich"
    ],
    "name:epo_x_preferred":[
        "Gevenich"
    ],
    "name:fre_x_preferred":[
        "Gevenich"
    ],
    "name:ger_x_preferred":[
        "Gevenich"
    ],
    "name:hun_x_preferred":[
        "Gevenich"
    ],
    "name:ita_x_preferred":[
        "Gevenich"
    ],
    "name:jpn_x_preferred":[
        "\u30b2\u30d5\u30a7\u30cb\u30d2"
    ],
    "name:may_x_preferred":[
        "Gevenich"
    ],
    "name:per_x_preferred":[
        "\u06af\u0641\u0646\u0627\u06cc\u0634"
    ],
    "name:pol_x_preferred":[
        "Gevenich"
    ],
    "name:por_x_preferred":[
        "Gevenich"
    ],
    "name:rum_x_preferred":[
        "Gevenich"
    ],
    "name:rus_x_preferred":[
        "\u0413\u0435\u0444\u0435\u043d\u0438\u0445"
    ],
    "name:srp_x_preferred":[
        "\u0413\u0435\u0432\u0435\u043d\u0438\u0445"
    ],
    "name:ukr_x_preferred":[
        "\u0413\u0435\u0444\u0435\u043d\u0456\u0445"
    ],
    "name:uzb_x_preferred":[
        "Gevenich"
    ],
    "name:vie_x_preferred":[
        "Gevenich"
    ],
    "name:vol_x_preferred":[
        "Gevenich"
    ],
    "name:war_x_preferred":[
        "Gevenich"
    ],
    "qs_pg:aaroncc":"DE",
    "qs_pg:gn_country":"DE",
    "qs_pg:gn_fcode":"PPLA4",
    "qs_pg:gn_pop":709,
    "qs_pg:name":"Gevenich",
    "qs_pg:photos_9r":0,
    "qs_pg:photos_sr":0,
    "qs_pg:pop_sr":2,
    "qs_pg:qs_pg_placetype":"locality",
    "wof:name":"Gevenich",
    "wof:placetype":"locality",
    "wof:population":709
},
  "geometry": {"coordinates":[7.08333,50.15],"type":"Point"}
}