{
  "type": "Feature",
  "properties": {
    "gn:admin1_code":"6",
    "gn:admin2_code":"0.0",
    "gn:admin3_code":"3458.0",
    "gn:admin4_code":"3458007.0",
    "gn:asciiname":"Haast",
    "gn:country_code":"DE",
    "gn:dem":33,
    "gn:feature_class":"P",
    "gn:feature_code":"PPL",
    "gn:name":"Haast",
    "gn:population":0,
    "gn:timezone":"Europe/Berlin",
    "iso:country":"DE",
    "name:ceb_x_preferred":[
        "Haast"
    ],
    "name:deu_x_preferred":[
        "Haast"
    ],
    "name:fra_x_preferred":[
        "Haast"
    ],
    "name:nds_x_preferred":[
        "Haast"
    ],
    "name:spa_x_preferred":[
        "Haast"
    ],
    "wof:name":"Haast",
    "wof:placetype":"neighbourhood"
},
  "geometry": {"coordinates":[8.20116,52.95085],"type":"Point"}
}