{
  "type": "Feature",
  "properties": {
    "gn:admin1_code":"7.0",
    "gn:admin2_code":"57.0",
    "gn:admin3_code":"5766.0",
    "gn:admin4_code":"5766020.0",
    "gn:asciiname":"Bremke",
    "gn:country_code":"DE",
    "gn:dem":160,
    "gn:feature_class":"P",
    "gn:feature_code":"PPL",
    "gn:name":"Bremke",
    "gn:population":0,
    "gn:timezone":"Europe/Berlin",
    "iso:country":"DE",
    "name:deu_x_preferred":[
        "Bremke"
    ],
    "name:mkd_x_preferred":[
        "\u0411\u0440\u0435\u043c\u043a\u0435"
    ],
    "name:nld_x_preferred":[
        "Bremke"
    ],
    "wof:name":"Bremke",
    "wof:placetype":"neighbourhood"
},
  "geometry": {"coordinates":[8.86668,51.96625],"type":"Point"}
}