{
  "type": "Feature",
  "properties": {
    "gn:admin1_code":"2",
    "gn:admin2_code":"93.0",
    "gn:admin3_code":"9377.0",
    "gn:admin4_code":"9377157.0",
    "gn:asciiname":"Lengenfeld bei Groschlattengrun",
    "gn:country_code":"DE",
    "gn:dem":562,
    "gn:feature_class":"P",
    "gn:feature_code":"PPL",
    "gn:name":"Lengenfeld bei Groschlattengr\u00fcn",
    "gn:population":0,
    "gn:timezone":"Europe/Berlin",
    "iso:country":"DE",
    "name:und_x_variant":[
        "Lengenfeld",
        "Lengenfeld bei Groschlattengr\u00fcn"
    ],
    "wof:name":"Lengenfeld bei Groschlattengrun",
    "wof:placetype":"neighbourhood"
},
  "geometry": {"coordinates":[12.11814,49.98045],"type":"Point"}
}