{
  "type": "Feature",
  "properties": {
    "gn:admin1_code":"7",
    "gn:admin2_code":"55.0",
    "gn:admin3_code":"5570.0",
    "gn:admin4_code":"5570052.0",
    "gn:asciiname":"Hoerste",
    "gn:country_code":"DE",
    "gn:dem":59,
    "gn:feature_class":"P",
    "gn:feature_code":"PPLL",
    "gn:name":"H\u00f6rste",
    "gn:population":0,
    "gn:timezone":"Europe/Berlin",
    "iso:country":"DE",
    "wof:name":"Hoerste",
    "wof:placetype":"neighbourhood"
},
  "geometry": {"coordinates":[7.92572,52.00768],"type":"Point"}
}