{
  "type": "Feature",
  "properties": {
    "gn:admin1_code":"7",
    "gn:admin2_code":"53.0",
    "gn:admin3_code":"5358.0",
    "gn:admin4_code":"5358020.0",
    "gn:asciiname":"Schophoven",
    "gn:country_code":"DE",
    "gn:dem":94,
    "gn:feature_class":"P",
    "gn:feature_code":"PPL",
    "gn:name":"Schophoven",
    "gn:population":0,
    "gn:timezone":"Europe/Berlin",
    "iso:country":"DE",
    "wof:name":"Schophoven",
    "wof:placetype":"neighbourhood"
},
  "geometry": {"coordinates":[6.39748,50.87809],"type":"Point"}
}