{
  "type": "Feature",
  "properties": {
    "gn:admin1_code":"2",
    "gn:admin2_code":"92.0",
    "gn:admin3_code":"9275.0",
    "gn:admin4_code":"9275126.0",
    "gn:asciiname":"Giessubl",
    "gn:country_code":"DE",
    "gn:dem":634,
    "gn:feature_class":"P",
    "gn:feature_code":"PPL",
    "gn:name":"Gie\u00df\u00fcbl",
    "gn:population":0,
    "gn:timezone":"Europe/Berlin",
    "iso:country":"DE",
    "wof:name":"Giessubl",
    "wof:placetype":"neighbourhood"
},
  "geometry": {"coordinates":[13.64333,48.67559],"type":"Point"}
}