{
  "type": "Feature",
  "properties": {
    "gn:admin1_code":"1",
    "gn:admin2_code":"83.0",
    "gn:admin3_code":"8317.0",
    "gn:admin4_code":"8317097.0",
    "gn:asciiname":"Nothalde",
    "gn:country_code":"DE",
    "gn:dem":191,
    "gn:feature_class":"P",
    "gn:feature_code":"PPLL",
    "gn:name":"Nothalde",
    "gn:population":0,
    "gn:timezone":"Europe/Berlin",
    "iso:country":"DE",
    "wof:name":"Nothalde",
    "wof:placetype":"locality"
},
  "geometry": {"coordinates":[7.99032,48.43908],"type":"Point"}
}