{
  "type": "Feature",
  "properties": {
    "gn:admin1_code":"2",
    "gn:admin2_code":"92.0",
    "gn:admin3_code":"9275.0",
    "gn:admin4_code":"9275133.0",
    "gn:asciiname":"Pfenningbach",
    "gn:country_code":"DE",
    "gn:dem":404,
    "gn:feature_class":"P",
    "gn:feature_code":"PPL",
    "gn:name":"Pfenningbach",
    "gn:population":0,
    "gn:timezone":"Europe/Berlin",
    "iso:country":"DE",
    "wof:name":"Pfenningbach",
    "wof:placetype":"neighbourhood"
},
  "geometry": {"coordinates":[13.38344,48.52936],"type":"Point"}
}