{
  "type": "Feature",
  "properties": {
    "gn:gn_country":"DE",
    "gn:gn_fcode":"PPLA4",
    "gn:gn_pop":198,
    "gn:population":198,
    "iso:country":"DE",
    "name:baq_x_preferred":[
        "Gro\u00dfbarkau"
    ],
    "name:chi_x_preferred":[
        "\u683c\u7f57\u65af\u5df4\u5c14\u8003"
    ],
    "name:dan_x_preferred":[
        "Gro\u00dfbarkau"
    ],
    "name:dut_x_preferred":[
        "Gro\u00dfbarkau"
    ],
    "name:eng_x_preferred":[
        "Gro\u00dfbarkau"
    ],
    "name:epo_x_preferred":[
        "Gro\u00dfbarkau"
    ],
    "name:fre_x_preferred":[
        "Gro\u00dfbarkau"
    ],
    "name:ger_x_preferred":[
        "Gro\u00dfbarkau"
    ],
    "name:hun_x_preferred":[
        "Gro\u00dfbarkau"
    ],
    "name:ita_x_preferred":[
        "Gro\u00dfbarkau"
    ],
    "name:mac_x_preferred":[
        "\u0413\u0440\u043e\u0441\u0431\u0430\u0440\u043a\u0430\u0443"
    ],
    "name:may_x_preferred":[
        "Gro\u00dfbarkau"
    ],
    "name:per_x_preferred":[
        "\u06af\u0631\u0648\u0633\u0628\u0627\u0631\u06a9\u0627\u0648"
    ],
    "name:pol_x_preferred":[
        "Gro\u00dfbarkau"
    ],
    "name:por_x_preferred":[
        "Gro\u00dfbarkau"
    ],
    "name:rum_x_preferred":[
        "Gro\u00dfbarkau"
    ],
    "name:rus_x_preferred":[
        "\u0413\u0440\u043e\u0441\u0431\u0430\u0440\u043a\u0430\u0443"
    ],
    "name:spa_x_preferred":[
        "Gro\u00dfbarkau"
    ],
    "name:srp_x_preferred":[
        "\u0413\u0440\u043e\u0441\u0431\u0430\u0440\u043a\u0430\u0443"
    ],
    "name:tur_x_preferred":[
        "Grossbarkau"
    ],
    "name:ukr_x_preferred":[
        "\u0413\u0440\u043e\u0441\u0431\u0430\u0440\u043a\u0430\u0443"
    ],
    "name:uzb_x_preferred":[
        "Gro\u00dfbarkau"
    ],
    "name:vie_x_preferred":[
        "Gro\u00dfbarkau"
    ],
    "name:vol_x_preferred":[
        "Gro\u00dfbarkau"
    ],
    "name:war_x_preferred":[
        "Gro\u00dfbarkau"
    ],
    "qs_pg:aaroncc":"DE",
    "qs_pg:gn_country":"DE",
    "qs_pg:gn_fcode":"PPLA4",
    "qs_pg:gn_pop":198,
    "qs_pg:name":"Gro\u00dfbarkau",
    "qs_pg:photos_9r":0,
    "qs_pg:photos_sr":0,
    "qs_pg:pop_sr":1,
    "qs_pg:qs_pg_placetype":"locality",
    "wof:name":"Gro\u00dfbarkau",
    "wof:placetype":"locality",
    "wof:population":198
},
  "geometry": {"coordinates":[10.16667,54.23333],"type":"Point"}
}