{
  "type": "Feature",
  "properties": {
    "iso:country":"DE",
    "name:deu_x_preferred":[
        "K\u00f6tter"
    ],
    "name:fry_x_preferred":[
        "Gernier"
    ],
    "name:nld_x_preferred":[
        "Keuterboer"
    ],
    "name:pol_x_preferred":[
        "Cha\u0142upnik"
    ],
    "name:rus_x_preferred":[
        "\u041a\u043e\u0442\u0442\u0430\u0440\u0438\u0438"
    ],
    "name:ukr_x_preferred":[
        "\u041a\u043e\u0442\u0442\u0430\u0440\u0456\u0457"
    ],
    "qs_pg:aaroncc":"DE",
    "qs_pg:name":"K\u00f6tter",
    "qs_pg:name_adm0":"Deutschland",
    "qs_pg:name_adm1":"Niedersachsen",
    "qs_pg:photos":137,
    "qs_pg:photos_1k":28,
    "qs_pg:photos_9k":1,
    "qs_pg:photos_9r":3,
    "qs_pg:photos_all":137,
    "qs_pg:photos_sr":3,
    "qs_pg:pop_sr":0,
    "qs_pg:qs_pg_placetype":"locality",
    "qs_pg:qs_pg_placetype_gp":"Town",
    "qs_pg:woe_adm0":23424829,
    "woe:adm0_id":23424829,
    "woe:name_adm0":"Deutschland",
    "woe:name_adm1":"Niedersachsen",
    "woe:placetype":"Town",
    "wof:name":"K\u00f6tter",
    "wof:placetype":"neighbourhood"
},
  "geometry": {"coordinates":[8.518991,52.180195],"type":"Point"}
}