{
  "type": "Feature",
  "properties": {
    "gn:admin1_code":"5",
    "gn:admin2_code":"64.0",
    "gn:admin3_code":"6435.0",
    "gn:admin4_code":"6435025.0",
    "gn:asciiname":"Herolz",
    "gn:country_code":"DE",
    "gn:dem":227,
    "gn:feature_class":"P",
    "gn:feature_code":"PPL",
    "gn:name":"Herolz",
    "gn:population":0,
    "gn:timezone":"Europe/Berlin",
    "iso:country":"DE",
    "wof:name":"Herolz",
    "wof:placetype":"neighbourhood"
},
  "geometry": {"coordinates":[9.55612,50.34677],"type":"Point"}
}