{
  "type": "Feature",
  "properties": {
    "iso:country":"DE",
    "name:deu_x_preferred":[
        "S\u00fcdstadt"
    ],
    "wof:name":"Suedstadt",
    "wof:placetype":"neighbourhood"
},
  "geometry": {"coordinates":[7.15005682438468,51.25211874204859],"type":"Point"}
}