{
  "type": "Feature",
  "properties": {
    "gn:admin1_code":"12",
    "gn:admin2_code":"0.0",
    "gn:admin3_code":"13075.0",
    "gn:admin4_code":"13075044.0",
    "gn:asciiname":"Pentin",
    "gn:country_code":"DE",
    "gn:dem":16,
    "gn:feature_class":"P",
    "gn:feature_code":"PPL",
    "gn:name":"Pentin",
    "gn:population":0,
    "gn:timezone":"Europe/Berlin",
    "iso:country":"DE",
    "wof:name":"Pentin",
    "wof:placetype":"neighbourhood"
},
  "geometry": {"coordinates":[13.46738,53.91769],"type":"Point"}
}