{
  "type": "Feature",
  "properties": {
    "gn:admin1_code":"1",
    "gn:admin2_code":"81.0",
    "gn:admin3_code":"8118.0",
    "gn:admin4_code":"8118010.0",
    "gn:asciiname":"Hofen",
    "gn:country_code":"DE",
    "gn:dem":259,
    "gn:feature_class":"P",
    "gn:feature_code":"PPL",
    "gn:name":"Hofen",
    "gn:population":0,
    "gn:timezone":"Europe/Berlin",
    "iso:country":"DE",
    "name:deu_x_preferred":[
        "Hofen"
    ],
    "name:epo_x_preferred":[
        "Hofen"
    ],
    "name:ita_x_preferred":[
        "Hofen"
    ],
    "name:pol_x_preferred":[
        "Hofen"
    ],
    "wof:name":"Hofen",
    "wof:placetype":"locality"
},
  "geometry": {"coordinates":[9.11881,49.02441],"type":"Point"}
}