{
  "type": "Feature",
  "properties": {
    "gn:admin1_code":"7",
    "gn:admin2_code":"59.0",
    "gn:admin3_code":"5915.0",
    "gn:admin4_code":"5915000.0",
    "gn:asciiname":"Killwinkel",
    "gn:country_code":"DE",
    "gn:dem":70,
    "gn:feature_class":"P",
    "gn:feature_code":"PPL",
    "gn:name":"Killwinkel",
    "gn:population":0,
    "gn:timezone":"Europe/Berlin",
    "iso:country":"DE",
    "wof:name":"Killwinkel",
    "wof:placetype":"locality"
},
  "geometry": {"coordinates":[7.7936,51.69405],"type":"Point"}
}