{
  "type": "Feature",
  "properties": {
    "gn:admin1_code":"13",
    "gn:admin2_code":"0.0",
    "gn:admin3_code":"14523.0",
    "gn:admin4_code":"14523450.0",
    "gn:asciiname":"Burgsteinhaeuser",
    "gn:country_code":"DE",
    "gn:dem":526,
    "gn:feature_class":"P",
    "gn:feature_code":"PPL",
    "gn:name":"Burgsteinh\u00e4user",
    "gn:population":0,
    "gn:timezone":"Europe/Berlin",
    "iso:country":"DE",
    "wof:name":"Burgsteinhaeuser",
    "wof:placetype":"neighbourhood"
},
  "geometry": {"coordinates":[11.99893,50.41882],"type":"Point"}
}