{
  "type": "Feature",
  "properties": {
    "gn:admin1_code":"8",
    "gn:admin2_code":"0.0",
    "gn:admin3_code":"7340.0",
    "gn:admin4_code":"7340028.0",
    "gn:asciiname":"Salzwoog",
    "gn:country_code":"DE",
    "gn:dem":248,
    "gn:feature_class":"P",
    "gn:feature_code":"PPL",
    "gn:name":"Salzwoog",
    "gn:population":0,
    "gn:timezone":"Europe/Berlin",
    "iso:country":"DE",
    "wof:name":"Salzwoog",
    "wof:placetype":"neighbourhood"
},
  "geometry": {"coordinates":[7.72141,49.16747],"type":"Point"}
}