{
  "type": "Feature",
  "properties": {
    "gn:admin1_code":"15.0",
    "gn:admin2_code":"00",
    "gn:admin3_code":"16069.0",
    "gn:admin4_code":"16069056.0",
    "gn:asciiname":"Westhausen",
    "gn:country_code":"DE",
    "gn:dem":316,
    "gn:feature_class":"P",
    "gn:feature_code":"PPLA4",
    "gn:name":"Westhausen",
    "gn:population":580,
    "gn:timezone":"Europe/Berlin",
    "iso:country":"DE",
    "wof:name":"Westhausen",
    "wof:placetype":"locality",
    "wof:population":580
},
  "geometry": {"coordinates":[10.66236,50.31568],"type":"Point"}
}