{
  "type": "Feature",
  "properties": {
    "gn:admin1_code":"2",
    "gn:admin2_code":"91.0",
    "gn:admin3_code":"9175.0",
    "gn:admin4_code":"9175136.0",
    "gn:asciiname":"Esterndorf",
    "gn:country_code":"DE",
    "gn:dem":499,
    "gn:feature_class":"P",
    "gn:feature_code":"PPL",
    "gn:name":"Esterndorf",
    "gn:population":0,
    "gn:timezone":"Europe/Berlin",
    "iso:country":"DE",
    "wof:name":"Esterndorf",
    "wof:placetype":"neighbourhood"
},
  "geometry": {"coordinates":[12.09153,48.00457],"type":"Point"}
}