{
  "type": "Feature",
  "properties": {
    "gn:admin1_code":"2.0",
    "gn:admin2_code":"094",
    "gn:admin3_code":"9471.0",
    "gn:admin4_code":"9471185.0",
    "gn:asciiname":"Weingarten",
    "gn:country_code":"DE",
    "gn:dem":407,
    "gn:feature_class":"P",
    "gn:feature_code":"PPL",
    "gn:name":"Weingarten",
    "gn:population":0,
    "gn:timezone":"Europe/Berlin",
    "iso:country":"DE",
    "name:als_x_preferred":[
        "Weingarten"
    ],
    "name:ceb_x_preferred":[
        "Weingarten"
    ],
    "name:ces_x_preferred":[
        "Weingarten"
    ],
    "name:deu_x_preferred":[
        "Weingarten"
    ],
    "name:epo_x_preferred":[
        "Weingarten"
    ],
    "name:fra_x_preferred":[
        "Weingarten"
    ],
    "name:heb_x_preferred":[
        "\u05d5\u05d9\u05d9\u05e0\u05d2\u05e8\u05d8\u05df"
    ],
    "name:ita_x_preferred":[
        "Weingarten"
    ],
    "name:lmo_x_preferred":[
        "Weingarten"
    ],
    "name:nld_x_preferred":[
        "Weingarten"
    ],
    "name:nor_x_preferred":[
        "Weingarten"
    ],
    "name:pol_x_preferred":[
        "Weingarten"
    ],
    "name:rus_x_preferred":[
        "\u0412\u0430\u0439\u043d\u0433\u0430\u0440\u0442\u0435\u043d"
    ],
    "name:spa_x_preferred":[
        "Weingarten"
    ],
    "name:srp_x_preferred":[
        "\u0412\u0430\u0458\u043d\u0433\u0430\u0440\u0442\u0435\u043d"
    ],
    "name:swe_x_preferred":[
        "Weingarten"
    ],
    "name:vol_x_preferred":[
        "Weingarten"
    ],
    "wof:name":"Weingarten",
    "wof:placetype":"neighbourhood"
},
  "geometry": {"coordinates":[11.04692,49.95043],"type":"Point"}
}