{
  "type": "Feature",
  "properties": {
    "gn:population":3343,
    "iso:country":"DE",
    "name:als_x_preferred":[
        "Schuttertal"
    ],
    "name:baq_x_preferred":[
        "Schuttertal"
    ],
    "name:chi_x_preferred":[
        "\u8212\u7279\u5c14\u5854\u5c14"
    ],
    "name:deu_x_preferred":[
        "Schuttertal"
    ],
    "name:dut_x_preferred":[
        "Schuttertal"
    ],
    "name:eng_x_preferred":[
        "Schuttertal"
    ],
    "name:epo_x_preferred":[
        "Schuttertal"
    ],
    "name:eus_x_preferred":[
        "Schuttertal"
    ],
    "name:fra_x_preferred":[
        "Schuttertal"
    ],
    "name:fre_x_preferred":[
        "Schuttertal"
    ],
    "name:ger_x_preferred":[
        "Schuttertal"
    ],
    "name:gsw_x_preferred":[
        "Schudderdoal"
    ],
    "name:hbs_x_preferred":[
        "Schuttertal"
    ],
    "name:hun_x_preferred":[
        "Schuttertal"
    ],
    "name:ita_x_preferred":[
        "Schuttertal"
    ],
    "name:lat_x_preferred":[
        "Schuttertal"
    ],
    "name:lmo_x_preferred":[
        "Schuttertal"
    ],
    "name:may_x_preferred":[
        "Schuttertal"
    ],
    "name:msa_x_preferred":[
        "Schuttertal"
    ],
    "name:nan_x_preferred":[
        "Schuttertal"
    ],
    "name:nld_x_preferred":[
        "Schuttertal"
    ],
    "name:per_x_preferred":[
        "\u0634\u0648\u062a\u0631\u062a\u0627\u0644"
    ],
    "name:pol_x_preferred":[
        "Schuttertal"
    ],
    "name:por_x_preferred":[
        "Schuttertal"
    ],
    "name:ron_x_preferred":[
        "Schuttertal"
    ],
    "name:rum_x_preferred":[
        "Schuttertal"
    ],
    "name:rus_x_preferred":[
        "\u0428\u0443\u0442\u0442\u0435\u0440\u0442\u0430\u043b\u044c"
    ],
    "name:spa_x_preferred":[
        "Schuttertal"
    ],
    "name:srp_x_preferred":[
        "\u0428\u0443\u0442\u0435\u0440\u0442\u0430\u043b"
    ],
    "name:ukr_x_preferred":[
        "\u0428\u0443\u0442\u0442\u0435\u0440\u0442\u0430\u043b\u044c"
    ],
    "name:uzb_x_preferred":[
        "Schuttertal"
    ],
    "name:vie_x_preferred":[
        "Schuttertal"
    ],
    "name:vol_x_preferred":[
        "Schuttertal"
    ],
    "name:war_x_preferred":[
        "Schuttertal"
    ],
    "name:zho_min_nan_x_preferred":[
        "Schuttertal"
    ],
    "name:zho_x_preferred":[
        "\u8212\u7279\u5c14\u5854\u5c14"
    ],
    "qs:a0":"Bundesrepublik Deutschland",
    "qs:a1":"*Baden-W\u00fcrttemberg",
    "qs:a1r":"0",
    "qs:a2":"Ortenaukreis",
    "qs:adm0":"Bundesrepublik Deutschland",
    "qs:la_lc":"*",
    "qs:level":"locality",
    "qs:loc":"Schuttertal",
    "qs:loc_alt":"Schuttertal",
    "qs:pop":0,
    "qs:type":"buffered point",
    "wd:wordcount":61,
    "wof:lang":[
        "ger"
    ],
    "wof:name":"Schuttertal",
    "wof:placetype":"locality",
    "wof:population":3343
},
  "geometry": {"coordinates":[7.966194,48.220201],"type":"Point"}
}