{
  "type": "Feature",
  "properties": {
    "gn:admin1_code":"2",
    "gn:admin2_code":"93.0",
    "gn:admin3_code":"9375.0",
    "gn:admin4_code":"9375180.0",
    "gn:asciiname":"Holkering",
    "gn:country_code":"DE",
    "gn:dem":430,
    "gn:feature_class":"P",
    "gn:feature_code":"PPL",
    "gn:name":"H\u00f6lkering",
    "gn:population":0,
    "gn:timezone":"Europe/Berlin",
    "iso:country":"DE",
    "wof:name":"Holkering",
    "wof:placetype":"neighbourhood"
},
  "geometry": {"coordinates":[12.06583,48.98001],"type":"Point"}
}