{
  "type": "Feature",
  "properties": {
    "gn:admin1_code":"2.0",
    "gn:admin2_code":"093",
    "gn:admin3_code":"9372.0",
    "gn:admin4_code":"9372117.0",
    "gn:asciiname":"Wolsting",
    "gn:country_code":"DE",
    "gn:dem":377,
    "gn:feature_class":"P",
    "gn:feature_code":"PPL",
    "gn:name":"W\u00f6lsting",
    "gn:population":0,
    "gn:timezone":"Europe/Berlin",
    "iso:country":"DE",
    "wof:name":"Wolsting",
    "wof:placetype":"neighbourhood"
},
  "geometry": {"coordinates":[12.73228,49.20554],"type":"Point"}
}