{
  "type": "Feature",
  "properties": {
    "gn:country":"DE",
    "gn:fcode":"PPL",
    "gn:population":946,
    "iso:country":"DE",
    "name:bak_x_preferred":[
        "\u041c\u0438\u043b\u044c\u0446\u0430\u0443"
    ],
    "name:ceb_x_preferred":[
        "Milzau"
    ],
    "name:che_x_preferred":[
        "\u041c\u0438\u043b\u044c\u0446\u0430\u0443"
    ],
    "name:deu_x_preferred":[
        "Milzau"
    ],
    "name:eng_x_preferred":[
        "Milzau"
    ],
    "name:epo_x_preferred":[
        "Milzau"
    ],
    "name:fas_x_preferred":[
        "\u0645\u06cc\u0644\u062a\u0633\u0627\u0648"
    ],
    "name:fra_x_preferred":[
        "Milzau"
    ],
    "name:ita_x_preferred":[
        "Milzau"
    ],
    "name:mkd_x_preferred":[
        "\u041c\u0438\u043b\u0446\u0430\u0443"
    ],
    "name:nld_x_preferred":[
        "Milzau"
    ],
    "name:pol_x_preferred":[
        "Milzau"
    ],
    "name:ron_x_preferred":[
        "Milzau"
    ],
    "name:rus_x_preferred":[
        "\u041c\u0438\u043b\u044c\u0446\u0430\u0443"
    ],
    "name:tat_x_preferred":[
        "\u041c\u0438\u043b\u044c\u0446\u0430\u0443"
    ],
    "name:uzb_x_preferred":[
        "Milzau"
    ],
    "name:vie_x_preferred":[
        "Milzau"
    ],
    "name:vol_x_preferred":[
        "Milzau"
    ],
    "qs_pg:aaroncc":"DE",
    "qs_pg:gn_country":"DE",
    "qs_pg:gn_fcode":"PPL",
    "qs_pg:gn_pop":946,
    "qs_pg:name":"Milzau",
    "qs_pg:name_adm0":"Deutschland",
    "qs_pg:name_adm1":"Sachsen-Anhalt",
    "qs_pg:photos_9k":1,
    "qs_pg:photos_9r":1,
    "qs_pg:photos_all":1,
    "qs_pg:photos_sr":0,
    "qs_pg:pop_sr":2,
    "qs_pg:qs_pg_placetype":"locality",
    "qs_pg:qs_pg_placetype_gp":"Town",
    "qs_pg:woe_adm0":23424829,
    "woe:adm0_id":23424829,
    "woe:name_adm0":"Deutschland",
    "woe:name_adm1":"Sachsen-Anhalt",
    "woe:placetype":"Town",
    "wof:name":"Milzau",
    "wof:placetype":"neighbourhood",
    "wof:population":946
},
  "geometry": {"coordinates":[11.899,51.37502],"type":"Point"}
}