{
  "type": "Feature",
  "properties": {
    "gn:admin1_code":"2",
    "gn:admin2_code":"95.0",
    "gn:admin3_code":"9576.0",
    "gn:admin4_code":"9576127.0",
    "gn:asciiname":"Federhof",
    "gn:country_code":"DE",
    "gn:dem":409,
    "gn:feature_class":"P",
    "gn:feature_code":"PPL",
    "gn:name":"Federhof",
    "gn:population":0,
    "gn:timezone":"Europe/Berlin",
    "iso:country":"DE",
    "wof:name":"Federhof",
    "wof:placetype":"neighbourhood"
},
  "geometry": {"coordinates":[11.30083,49.16041],"type":"Point"}
}