{
  "type": "Feature",
  "properties": {
    "gn:admin1_code":"2",
    "gn:admin2_code":"95.0",
    "gn:admin3_code":"9574.0",
    "gn:admin4_code":"9574147.0",
    "gn:asciiname":"Mittelburg",
    "gn:country_code":"DE",
    "gn:dem":530,
    "gn:feature_class":"P",
    "gn:feature_code":"PPL",
    "gn:name":"Mittelburg",
    "gn:population":0,
    "gn:timezone":"Europe/Berlin",
    "iso:country":"DE",
    "wof:name":"Mittelburg",
    "wof:placetype":"neighbourhood"
},
  "geometry": {"coordinates":[11.53719,49.47783],"type":"Point"}
}