{
  "type": "Feature",
  "properties": {
    "iso:country":"DE",
    "name:ceb_x_preferred":[
        "Schlo\u00df Styrum"
    ],
    "name:dan_x_preferred":[
        "Heerlijkheid Styrum"
    ],
    "name:deu_x_preferred":[
        "Herrschaft Styrum"
    ],
    "name:deu_x_variant":[
        "Styrum",
        "Schloss Styrum"
    ],
    "name:eng_x_preferred":[
        "Styrum"
    ],
    "name:nld_x_preferred":[
        "Heerlijkheid Styrum"
    ],
    "name:nno_x_preferred":[
        "Heerlijkheid Styrum"
    ],
    "name:nob_x_preferred":[
        "Heerlijkheid Styrum"
    ],
    "name:ron_x_preferred":[
        "Castelul Styrum"
    ],
    "name:rus_x_preferred":[
        "\u0428\u0442\u044e\u0440\u0443\u043c"
    ],
    "name:swe_x_preferred":[
        "Heerlijkheid Styrum"
    ],
    "name:unk_x_variant":[
        "Styrum"
    ],
    "qs:gn_adm0_cc":"DE",
    "qs:gn_fcode":"PPLX",
    "qs:gn_local":2867838,
    "qs:gn_nam_loc":"M\u00fclheim an der Ruhr, Nordrhein-Westfalen, DE",
    "qs:gn_namadm1":"07",
    "qs:gn_name":"Styrum",
    "qs:local_max":6349,
    "qs:local_sum":9575,
    "qs:localhoods":14,
    "qs:name":"Styrum",
    "qs:name_adm0":"Deutschland",
    "qs:name_adm1":"Nordrhein-Westfalen",
    "qs:name_adm2":"Stadtkreis M\u00fclheim an der Ruhr",
    "qs:name_lau":"Stadtteil M\u00fclheim an der Ruhr",
    "qs:name_local":"Stadtteil M\u00fclheim an der Ruhr",
    "qs:photo_max":44,
    "qs:photo_sum":254,
    "qs:placetype":"Suburb",
    "qs:quad_count":42,
    "qs:woe_adm0":23424829,
    "qs:woe_adm1":2345487,
    "qs:woe_adm2":12597066,
    "qs:woe_lau":28350219,
    "qs:woe_local":28350219,
    "qs:woe_ver":"7.10.0",
    "wd:wordcount":386,
    "wof:lang":[
        "ger"
    ],
    "wof:name":"Styrum",
    "wof:placetype":"neighbourhood"
},
  "geometry": {"coordinates":[6.853809,51.451449],"type":"Point"}
}