{
  "type": "Feature",
  "properties": {
    "gn:admin1_code":"2",
    "gn:admin2_code":"93.0",
    "gn:admin3_code":"9371.0",
    "gn:admin4_code":"9371156.0",
    "gn:asciiname":"Sigl",
    "gn:country_code":"DE",
    "gn:dem":413,
    "gn:feature_class":"P",
    "gn:feature_code":"PPL",
    "gn:name":"Sigl",
    "gn:population":0,
    "gn:timezone":"Europe/Berlin",
    "iso:country":"DE",
    "name:als_x_preferred":[
        "Sigl"
    ],
    "name:deu_x_preferred":[
        "Sigl"
    ],
    "name:nds_x_preferred":[
        "Sigl"
    ],
    "wof:name":"Sigl",
    "wof:placetype":"neighbourhood"
},
  "geometry": {"coordinates":[11.74871,49.62107],"type":"Point"}
}