{
  "type": "Feature",
  "properties": {
    "gn:admin1_code":"2",
    "gn:admin2_code":"97.0",
    "gn:admin3_code":"9773.0",
    "gn:admin4_code":"9773117.0",
    "gn:asciiname":"Komertshof",
    "gn:country_code":"DE",
    "gn:dem":512,
    "gn:feature_class":"P",
    "gn:feature_code":"PPL",
    "gn:name":"K\u00f6mertshof",
    "gn:population":0,
    "gn:timezone":"Europe/Berlin",
    "iso:country":"DE",
    "wof:name":"Komertshof",
    "wof:placetype":"neighbourhood"
},
  "geometry": {"coordinates":[10.56711,48.71487],"type":"Point"}
}