{
  "type": "Feature",
  "properties": {
    "gn:country":"DE",
    "gn:fcode":"PPL",
    "gn:population":0,
    "iso:country":"DE",
    "name:ast_x_preferred":[
        "Todtnauberg"
    ],
    "name:deu_x_preferred":[
        "Todtnauberg"
    ],
    "name:eng_x_preferred":[
        "Todtnauberg"
    ],
    "name:fas_x_preferred":[
        "\u062a\u0648\u062a\u0646\u0627\u0648\u0628\u0631\u06af"
    ],
    "name:fra_x_preferred":[
        "Todtnauberg"
    ],
    "name:jpn_x_preferred":[
        "\u30c8\u30fc\u30c8\u30ca\u30a6\u30d9\u30eb\u30af"
    ],
    "name:mkd_x_preferred":[
        "\u0422\u043e\u0442\u043d\u0430\u0443\u0431\u0435\u0440\u0433"
    ],
    "name:nld_x_preferred":[
        "Todtnauberg"
    ],
    "name:spa_x_preferred":[
        "Todtnauberg"
    ],
    "qs_pg:aaroncc":"DE",
    "qs_pg:gn_country":"DE",
    "qs_pg:gn_fcode":"PPL",
    "qs_pg:gn_pop":0,
    "qs_pg:name":"Todtnauberg",
    "qs_pg:name_adm0":"Deutschland",
    "qs_pg:name_adm1":"Baden-W\u00fcrttemberg",
    "qs_pg:photos":104,
    "qs_pg:photos_1k":21,
    "qs_pg:photos_9k":1,
    "qs_pg:photos_9r":3,
    "qs_pg:photos_all":104,
    "qs_pg:photos_sr":3,
    "qs_pg:pop_sr":0,
    "qs_pg:qs_pg_placetype":"locality",
    "qs_pg:qs_pg_placetype_gp":"Town",
    "qs_pg:woe_adm0":23424829,
    "woe:adm0_id":23424829,
    "woe:name_adm0":"Deutschland",
    "woe:name_adm1":"Baden-W\u00fcrttemberg",
    "woe:placetype":"Town",
    "wof:name":"Todtnauberg",
    "wof:placetype":"neighbourhood"
},
  "geometry": {"coordinates":[7.94003,47.85026],"type":"Point"}
}