{
  "type": "Feature",
  "properties": {
    "gn:admin1_code":"6.0",
    "gn:admin2_code":"0.0",
    "gn:admin3_code":"3402.0",
    "gn:admin4_code":"3402000.0",
    "gn:asciiname":"Borssum",
    "gn:country_code":"DE",
    "gn:dem":2,
    "gn:feature_class":"P",
    "gn:feature_code":"PPL",
    "gn:name":"Bor\u00dfum",
    "gn:population":0,
    "gn:timezone":"Europe/Berlin",
    "iso:country":"DE",
    "name:und_x_variant":[
        "Emden-Bor\u00dfum",
        "Bor\u00dfum"
    ],
    "wof:name":"Borssum",
    "wof:placetype":"neighbourhood"
},
  "geometry": {"coordinates":[7.22833,53.34259],"type":"Point"}
}