{
  "type": "Feature",
  "properties": {
    "iso:country":"DE",
    "wof:name":"Scharpwinkelring",
    "wof:placetype":"neighbourhood"
},
  "geometry": {"coordinates":[7.17665457287079,51.53968501280639],"type":"Point"}
}