{
  "type": "Feature",
  "properties": {
    "gn:admin1_code":"1",
    "gn:admin2_code":"83.0",
    "gn:admin3_code":"8327.0",
    "gn:admin4_code":"8327038.0",
    "gn:asciiname":"Holzach",
    "gn:country_code":"DE",
    "gn:dem":670,
    "gn:feature_class":"P",
    "gn:feature_code":"PPL",
    "gn:name":"Holzach",
    "gn:population":0,
    "gn:timezone":"Europe/Berlin",
    "iso:country":"DE",
    "wof:name":"Holzach",
    "wof:placetype":"neighbourhood"
},
  "geometry": {"coordinates":[8.99851,47.94202],"type":"Point"}
}