{
  "type": "Feature",
  "properties": {
    "gn:admin1_code":"7",
    "gn:admin2_code":"53.0",
    "gn:admin3_code":"5374.0",
    "gn:admin4_code":"5374052.0",
    "gn:asciiname":"Niederkemmerich",
    "gn:country_code":"DE",
    "gn:dem":248,
    "gn:feature_class":"P",
    "gn:feature_code":"PPL",
    "gn:name":"Niederkemmerich",
    "gn:population":0,
    "gn:timezone":"Europe/Berlin",
    "iso:country":"DE",
    "wof:name":"Niederkemmerich",
    "wof:placetype":"neighbourhood"
},
  "geometry": {"coordinates":[7.4253,51.0712],"type":"Point"}
}