{
  "type": "Feature",
  "properties": {
    "iso:country":"DE",
    "wof:name":"Alte Kaserne",
    "wof:placetype":"neighbourhood"
},
  "geometry": {"coordinates":[11.54663693399926,48.15561917865902],"type":"Point"}
}