{
  "type": "Feature",
  "properties": {
    "gn:admin1_code":"13",
    "gn:admin2_code":"0.0",
    "gn:admin3_code":"14524.0",
    "gn:admin4_code":"14524210.0",
    "gn:asciiname":"Daenkritz",
    "gn:country_code":"DE",
    "gn:dem":324,
    "gn:feature_class":"P",
    "gn:feature_code":"PPL",
    "gn:name":"D\u00e4nkritz",
    "gn:population":0,
    "gn:timezone":"Europe/Berlin",
    "iso:country":"DE",
    "wof:name":"Daenkritz",
    "wof:placetype":"neighbourhood"
},
  "geometry": {"coordinates":[12.42698,50.7763],"type":"Point"}
}