{
  "type": "Feature",
  "properties": {
    "gn:admin1_code":"12",
    "gn:admin2_code":"0.0",
    "gn:admin3_code":"13073.0",
    "gn:admin4_code":"13073055.0",
    "gn:asciiname":"Daenschenburg",
    "gn:cc2":"DE",
    "gn:country_code":"DE",
    "gn:dem":48,
    "gn:feature_class":"P",
    "gn:feature_code":"PPL",
    "gn:name":"D\u00e4nschenburg",
    "gn:population":0,
    "gn:timezone":"Europe/Berlin",
    "iso:country":"DE",
    "name:und_x_variant":[
        "D\u00e4nscheburg"
    ],
    "wof:name":"Daenschenburg",
    "wof:placetype":"neighbourhood"
},
  "geometry": {"coordinates":[12.40648,54.12865],"type":"Point"}
}