{
  "type": "Feature",
  "properties": {
    "gn:admin1_code":"2.0",
    "gn:admin2_code":"93.0",
    "gn:admin3_code":"9377.0",
    "gn:admin4_code":"9377116.0",
    "gn:asciiname":"Aschenhof",
    "gn:country_code":"DE",
    "gn:dem":578,
    "gn:feature_class":"P",
    "gn:feature_code":"PPL",
    "gn:name":"Aschenhof",
    "gn:population":0,
    "gn:timezone":"Europe/Berlin",
    "iso:country":"DE",
    "wof:name":"Aschenhof",
    "wof:placetype":"neighbourhood"
},
  "geometry": {"coordinates":[12.01999,49.82779],"type":"Point"}
}