{
  "type": "Feature",
  "properties": {
    "gn:admin1_code":"2",
    "gn:admin2_code":"91.0",
    "gn:admin3_code":"9187.0",
    "gn:admin4_code":"9187130.0",
    "gn:asciiname":"Sterneck",
    "gn:country_code":"DE",
    "gn:dem":616,
    "gn:feature_class":"P",
    "gn:feature_code":"PPL",
    "gn:name":"Sterneck",
    "gn:population":0,
    "gn:timezone":"Europe/Berlin",
    "iso:country":"DE",
    "wof:name":"Sterneck",
    "wof:placetype":"neighbourhood"
},
  "geometry": {"coordinates":[11.83395,47.88561],"type":"Point"}
}