{
  "type": "Feature",
  "properties": {
    "iso:country":"DE",
    "name:deu_x_preferred":[
        "Delstrup"
    ],
    "name:unk_x_variant":[
        "Delstrup"
    ],
    "qs:gn_fcode":"PPL",
    "qs:gn_local":0,
    "qs:gn_namadm1":"06",
    "qs:gn_name":"Melstrup",
    "qs:local_max":4321,
    "qs:local_sum":13562,
    "qs:localhoods":28,
    "qs:name":"Delstrup",
    "qs:name_adm0":"Deutschland",
    "qs:name_adm1":"Nordrhein-Westfalen",
    "qs:name_adm2":"Stadtkreis M\u00fcnster",
    "qs:name_lau":"Mitte-Nordost",
    "qs:name_local":"M\u00fcnster",
    "qs:photo_max":56,
    "qs:photo_sum":57,
    "qs:placetype":"Suburb",
    "qs:quad_count":2,
    "qs:woe_adm0":23424829,
    "qs:woe_adm1":2345487,
    "qs:woe_adm2":12596927,
    "qs:woe_lau":26823097,
    "qs:woe_local":676864,
    "qs:woe_ver":"7.10.0",
    "wof:lang":[
        "ger"
    ],
    "wof:name":"Delstrup",
    "wof:placetype":"neighbourhood"
},
  "geometry": {"coordinates":[7.689032,51.953621],"type":"Point"}
}