{
  "type": "Feature",
  "properties": {
    "gn:admin1_code":"2",
    "gn:admin2_code":"92.0",
    "gn:admin3_code":"9277.0",
    "gn:admin4_code":"9277139.0",
    "gn:asciiname":"Kumpfmuhl",
    "gn:country_code":"DE",
    "gn:dem":421,
    "gn:feature_class":"P",
    "gn:feature_code":"PPL",
    "gn:name":"Kumpfm\u00fchl",
    "gn:population":0,
    "gn:timezone":"Europe/Berlin",
    "iso:country":"DE",
    "wof:name":"Kumpfmuhl",
    "wof:placetype":"neighbourhood"
},
  "geometry": {"coordinates":[12.88914,48.39005],"type":"Point"}
}