{
  "type": "Feature",
  "properties": {
    "gn:admin1_code":"12",
    "gn:admin2_code":"0.0",
    "gn:admin3_code":"13074.0",
    "gn:admin4_code":"13074005.0",
    "gn:asciiname":"Jeese",
    "gn:country_code":"DE",
    "gn:dem":45,
    "gn:feature_class":"P",
    "gn:feature_code":"PPL",
    "gn:name":"Jeese",
    "gn:population":0,
    "gn:timezone":"Europe/Berlin",
    "iso:country":"DE",
    "wof:name":"Jeese",
    "wof:placetype":"neighbourhood"
},
  "geometry": {"coordinates":[11.12469,53.8154],"type":"Point"}
}