{
  "type": "Feature",
  "properties": {
    "gn:admin1_code":"15",
    "gn:admin2_code":"0.0",
    "gn:admin3_code":"16065.0",
    "gn:admin4_code":"16065032.0",
    "gn:asciiname":"Kleinbruechter",
    "gn:country_code":"DE",
    "gn:dem":321,
    "gn:feature_class":"P",
    "gn:feature_code":"PPL",
    "gn:name":"Kleinbr\u00fcchter",
    "gn:population":0,
    "gn:timezone":"Europe/Berlin",
    "iso:country":"DE",
    "wof:name":"Kleinbruechter",
    "wof:placetype":"neighbourhood"
},
  "geometry": {"coordinates":[10.64494,51.31072],"type":"Point"}
}