{
  "type": "Feature",
  "properties": {
    "gn:admin1_code":"12",
    "gn:admin2_code":"0.0",
    "gn:admin3_code":"13073.0",
    "gn:admin4_code":"13073090.0",
    "gn:asciiname":"Klein Miltzow",
    "gn:country_code":"DE",
    "gn:dem":24,
    "gn:feature_class":"P",
    "gn:feature_code":"PPL",
    "gn:name":"Klein Miltzow",
    "gn:population":0,
    "gn:timezone":"Europe/Berlin",
    "iso:country":"DE",
    "wof:name":"Klein Miltzow",
    "wof:placetype":"neighbourhood"
},
  "geometry": {"coordinates":[13.1957,54.19955],"type":"Point"}
}