{
  "type": "Feature",
  "properties": {
    "gn:admin1_code":"1",
    "gn:admin2_code":"82.0",
    "gn:admin3_code":"8237.0",
    "gn:admin4_code":"8237002.0",
    "gn:asciiname":"Rodt",
    "gn:country_code":"DE",
    "gn:dem":691,
    "gn:feature_class":"P",
    "gn:feature_code":"PPL",
    "gn:name":"Rodt",
    "gn:population":0,
    "gn:timezone":"Europe/Berlin",
    "iso:country":"DE",
    "wof:name":"Rodt",
    "wof:placetype":"neighbourhood"
},
  "geometry": {"coordinates":[8.36667,48.41667],"type":"Point"}
}