{
  "type": "Feature",
  "properties": {
    "gn:admin1_code":"15",
    "gn:admin2_code":"0.0",
    "gn:admin3_code":"16076.0",
    "gn:admin4_code":"16076039.0",
    "gn:asciiname":"Nitschareuth",
    "gn:country_code":"DE",
    "gn:dem":332,
    "gn:feature_class":"P",
    "gn:feature_code":"PPL",
    "gn:name":"Nitschareuth",
    "gn:population":0,
    "gn:timezone":"Europe/Berlin",
    "iso:country":"DE",
    "wof:name":"Nitschareuth",
    "wof:placetype":"neighbourhood"
},
  "geometry": {"coordinates":[12.15212,50.69628],"type":"Point"}
}