{
  "type": "Feature",
  "properties": {
    "gn:admin1_code":"13",
    "gn:admin2_code":"0.0",
    "gn:admin3_code":"14627.0",
    "gn:admin4_code":"14627180.0",
    "gn:asciiname":"Proeda",
    "gn:country_code":"DE",
    "gn:dem":182,
    "gn:feature_class":"P",
    "gn:feature_code":"PPL",
    "gn:name":"Pr\u00f6da",
    "gn:population":0,
    "gn:timezone":"Europe/Berlin",
    "iso:country":"DE",
    "wof:name":"Proeda",
    "wof:placetype":"neighbourhood"
},
  "geometry": {"coordinates":[13.28192,51.15084],"type":"Point"}
}