{
  "type": "Feature",
  "properties": {
    "gn:admin1_code":"2",
    "gn:admin2_code":"96.0",
    "gn:admin3_code":"9671.0",
    "gn:admin4_code":"9671112.0",
    "gn:asciiname":"Keilberg",
    "gn:country_code":"DE",
    "gn:dem":171,
    "gn:feature_class":"P",
    "gn:feature_code":"PPL",
    "gn:name":"Keilberg",
    "gn:population":0,
    "gn:timezone":"Europe/Berlin",
    "iso:country":"DE",
    "wof:name":"Keilberg",
    "wof:placetype":"neighbourhood"
},
  "geometry": {"coordinates":[9.25628,49.97668],"type":"Point"}
}