{
  "type": "Feature",
  "properties": {
    "gn:admin1_code":"12",
    "gn:admin2_code":"0.0",
    "gn:admin3_code":"13076.0",
    "gn:admin4_code":"13076102.0",
    "gn:asciiname":"Huehnerbusch",
    "gn:country_code":"DE",
    "gn:dem":14,
    "gn:feature_class":"P",
    "gn:feature_code":"PPL",
    "gn:name":"H\u00fchnerbusch",
    "gn:population":0,
    "gn:timezone":"Europe/Berlin",
    "iso:country":"DE",
    "wof:name":"Huehnerbusch",
    "wof:placetype":"neighbourhood"
},
  "geometry": {"coordinates":[10.81854,53.36703000000001],"type":"Point"}
}