{
  "type": "Feature",
  "properties": {
    "gn:admin1_code":"2",
    "gn:admin2_code":"92.0",
    "gn:admin3_code":"9273.0",
    "gn:admin4_code":"9273115.0",
    "gn:asciiname":"Potzmes",
    "gn:country_code":"DE",
    "gn:dem":468,
    "gn:feature_class":"P",
    "gn:feature_code":"PPL",
    "gn:name":"P\u00f6tzmes",
    "gn:population":0,
    "gn:timezone":"Europe/Berlin",
    "iso:country":"DE",
    "wof:name":"Potzmes",
    "wof:placetype":"neighbourhood"
},
  "geometry": {"coordinates":[11.81976,48.64811],"type":"Point"}
}