{
  "type": "Feature",
  "properties": {
    "gn:admin1_code":"13",
    "gn:admin2_code":"0.0",
    "gn:admin3_code":"14522.0",
    "gn:admin4_code":"14522240.0",
    "gn:asciiname":"Haida",
    "gn:country_code":"DE",
    "gn:dem":382,
    "gn:feature_class":"P",
    "gn:feature_code":"PPL",
    "gn:name":"Haida",
    "gn:population":0,
    "gn:timezone":"Europe/Berlin",
    "iso:country":"DE",
    "name:ceb_x_preferred":[
        "Haida"
    ],
    "name:ces_x_preferred":[
        "Haida"
    ],
    "name:deu_x_preferred":[
        "Haida"
    ],
    "name:ind_x_preferred":[
        "Haida"
    ],
    "name:ita_x_preferred":[
        "Haida"
    ],
    "name:jpn_x_preferred":[
        "\u30cf\u30a4\u30c0"
    ],
    "name:nld_x_preferred":[
        "Haida"
    ],
    "name:tur_x_preferred":[
        "Hayda"
    ],
    "wof:name":"Haida",
    "wof:placetype":"neighbourhood"
},
  "geometry": {"coordinates":[13.43036,50.98248],"type":"Point"}
}