{
  "type": "Feature",
  "properties": {
    "gn:admin1_code":"12",
    "gn:admin2_code":"0.0",
    "gn:admin3_code":"13073.0",
    "gn:admin4_code":"13073059.0",
    "gn:asciiname":"Klein Grubnow",
    "gn:country_code":"DE",
    "gn:dem":2,
    "gn:feature_class":"P",
    "gn:feature_code":"PPL",
    "gn:name":"Klein Grubnow",
    "gn:population":0,
    "gn:timezone":"Europe/Berlin",
    "iso:country":"DE",
    "wof:name":"Klein Grubnow",
    "wof:placetype":"neighbourhood"
},
  "geometry": {"coordinates":[13.33897,54.55103],"type":"Point"}
}