{
  "type": "Feature",
  "properties": {
    "gn:admin1_code":"7",
    "gn:admin2_code":"51.0",
    "gn:admin3_code":"5114.0",
    "gn:admin4_code":"5114000.0",
    "gn:asciiname":"Ortsmannsheide",
    "gn:country_code":"DE",
    "gn:dem":39,
    "gn:feature_class":"P",
    "gn:feature_code":"PPL",
    "gn:name":"Ortsmannsheide",
    "gn:population":0,
    "gn:timezone":"Europe/Berlin",
    "iso:country":"DE",
    "name:und_x_variant":[
        "Ortmannsheide",
        "Ortsmannsheide"
    ],
    "wof:name":"Ortsmannsheide",
    "wof:placetype":"neighbourhood"
},
  "geometry": {"coordinates":[6.51862,51.33672],"type":"Point"}
}