{
  "type": "Feature",
  "properties": {
    "gn:admin1_code":"2",
    "gn:admin2_code":"91.0",
    "gn:admin3_code":"9175.0",
    "gn:admin4_code":"9175115.0",
    "gn:asciiname":"Neuhausen",
    "gn:country_code":"DE",
    "gn:dem":521,
    "gn:feature_class":"P",
    "gn:feature_code":"PPL",
    "gn:name":"Neuhausen",
    "gn:population":0,
    "gn:timezone":"Europe/Berlin",
    "iso:country":"DE",
    "wof:name":"Neuhausen",
    "wof:placetype":"neighbourhood"
},
  "geometry": {"coordinates":[12.00994,48.08054],"type":"Point"}
}