{
  "type": "Feature",
  "properties": {
    "gn:admin1_code":"2",
    "gn:admin2_code":"92.0",
    "gn:admin3_code":"9277.0",
    "gn:admin4_code":"9277128.0",
    "gn:asciiname":"Weier",
    "gn:country_code":"DE",
    "gn:dem":361,
    "gn:feature_class":"P",
    "gn:feature_code":"PPL",
    "gn:name":"Weier",
    "gn:population":0,
    "gn:timezone":"Europe/Berlin",
    "iso:country":"DE",
    "wof:name":"Weier",
    "wof:placetype":"neighbourhood"
},
  "geometry": {"coordinates":[12.98867,48.25468],"type":"Point"}
}