{
  "type": "Feature",
  "properties": {
    "iso:country":"DE",
    "wof:name":"Mengede",
    "wof:placetype":"neighbourhood"
},
  "geometry": {"coordinates":[7.38460098303631,51.57293194231337],"type":"Point"}
}