{
  "type": "Feature",
  "properties": {
    "gn:admin1_code":"7",
    "gn:admin2_code":"51.0",
    "gn:admin3_code":"5124.0",
    "gn:admin4_code":"5124000.0",
    "gn:asciiname":"Grosssporkert",
    "gn:country_code":"DE",
    "gn:dem":271,
    "gn:feature_class":"P",
    "gn:feature_code":"PPL",
    "gn:name":"Gro\u00dfsporkert",
    "gn:population":0,
    "gn:timezone":"Europe/Berlin",
    "iso:country":"DE",
    "wof:name":"Grosssporkert",
    "wof:placetype":"neighbourhood"
},
  "geometry": {"coordinates":[7.24029,51.22864000000001],"type":"Point"}
}