{
  "type": "Feature",
  "properties": {
    "gn:admin1_code":"14.0",
    "gn:admin2_code":"00",
    "gn:admin3_code":"15084.0",
    "gn:admin4_code":"15084335.0",
    "gn:asciiname":"Wetterscheidt",
    "gn:country_code":"DE",
    "gn:dem":129,
    "gn:feature_class":"P",
    "gn:feature_code":"PPL",
    "gn:name":"Wetterscheidt",
    "gn:population":0,
    "gn:timezone":"Europe/Berlin",
    "iso:country":"DE",
    "wof:name":"Wetterscheidt",
    "wof:placetype":"neighbourhood"
},
  "geometry": {"coordinates":[11.84524,51.10842],"type":"Point"}
}