{
  "type": "Feature",
  "properties": {
    "gn:admin1_code":"7.0",
    "gn:admin2_code":"59.0",
    "gn:admin3_code":"5962.0",
    "gn:admin4_code":"5962056.0",
    "gn:asciiname":"Altenhuelscheid",
    "gn:country_code":"DE",
    "gn:dem":394,
    "gn:feature_class":"P",
    "gn:feature_code":"PPL",
    "gn:name":"Altenh\u00fclscheid",
    "gn:population":0,
    "gn:timezone":"Europe/Berlin",
    "iso:country":"DE",
    "wof:name":"Altenhuelscheid",
    "wof:placetype":"neighbourhood"
},
  "geometry": {"coordinates":[7.58215,51.26548],"type":"Point"}
}