{
  "type": "Feature",
  "properties": {
    "gn:admin1_code":"5.0",
    "gn:admin2_code":"65.0",
    "gn:admin3_code":"6531.0",
    "gn:admin4_code":"6531015.0",
    "gn:asciiname":"Allertshausen",
    "gn:country_code":"DE",
    "gn:dem":301,
    "gn:feature_class":"P",
    "gn:feature_code":"PPL",
    "gn:name":"Allertshausen",
    "gn:population":0,
    "gn:timezone":"Europe/Berlin",
    "iso:country":"DE",
    "name:deu_x_preferred":[
        "Rabenau-Allertshausen"
    ],
    "wof:name":"Allertshausen",
    "wof:placetype":"neighbourhood"
},
  "geometry": {"coordinates":[8.84932,50.65795],"type":"Point"}
}