{
  "type": "Feature",
  "properties": {
    "gn:admin1_code":"2",
    "gn:admin2_code":"94.0",
    "gn:admin3_code":"9472.0",
    "gn:admin4_code":"9472190.0",
    "gn:asciiname":"Lettenhof",
    "gn:country_code":"DE",
    "gn:dem":477,
    "gn:feature_class":"P",
    "gn:feature_code":"PPL",
    "gn:name":"Lettenhof",
    "gn:population":0,
    "gn:timezone":"Europe/Berlin",
    "iso:country":"DE",
    "wof:name":"Lettenhof",
    "wof:placetype":"neighbourhood"
},
  "geometry": {"coordinates":[11.81296,49.87655],"type":"Point"}
}