{
  "type": "Feature",
  "properties": {
    "gn:admin1_code":"13",
    "gn:admin2_code":"0.0",
    "gn:admin3_code":"14524.0",
    "gn:admin4_code":"14524030.0",
    "gn:asciiname":"Grosspillingsdorf",
    "gn:country_code":"DE",
    "gn:dem":326,
    "gn:feature_class":"P",
    "gn:feature_code":"PPL",
    "gn:name":"Gro\u00dfpillingsdorf",
    "gn:population":0,
    "gn:timezone":"Europe/Berlin",
    "iso:country":"DE",
    "wof:name":"Grosspillingsdorf",
    "wof:placetype":"neighbourhood"
},
  "geometry": {"coordinates":[12.25658,50.81252],"type":"Point"}
}