{
  "type": "Feature",
  "properties": {
    "gn:admin1_code":"1.0",
    "gn:admin2_code":"84.0",
    "gn:admin3_code":"8436.0",
    "gn:admin4_code":"8436085.0",
    "gn:asciiname":"Alttann",
    "gn:country_code":"DE",
    "gn:dem":673,
    "gn:feature_class":"P",
    "gn:feature_code":"PPL",
    "gn:name":"Alttann",
    "gn:population":0,
    "gn:timezone":"Europe/Berlin",
    "iso:country":"DE",
    "name:und_x_variant":[
        "Altann",
        "Alttann"
    ],
    "wof:name":"Alttann",
    "wof:placetype":"neighbourhood"
},
  "geometry": {"coordinates":[9.79207,47.83908],"type":"Point"}
}