{
  "type": "Feature",
  "properties": {
    "gn:admin1_code":"13",
    "gn:admin2_code":"0.0",
    "gn:admin3_code":"14522.0",
    "gn:admin4_code":"14522230.0",
    "gn:asciiname":"Gersdorf",
    "gn:country_code":"DE",
    "gn:dem":353,
    "gn:feature_class":"P",
    "gn:feature_code":"PPL",
    "gn:name":"Gersdorf",
    "gn:population":0,
    "gn:timezone":"Europe/Berlin",
    "iso:country":"DE",
    "name:ceb_x_preferred":[
        "Gersdorf"
    ],
    "name:ces_x_preferred":[
        "Gersdorf"
    ],
    "name:deu_x_preferred":[
        "Gersdorf"
    ],
    "name:fra_x_preferred":[
        "Gersdorf"
    ],
    "name:ita_x_preferred":[
        "Gersdorf"
    ],
    "name:pol_x_preferred":[
        "Gersdorf"
    ],
    "name:rus_x_preferred":[
        "\u0413\u0435\u0440\u0441\u0434\u043e\u0440\u0444"
    ],
    "name:swe_x_preferred":[
        "Gersdorf"
    ],
    "wof:name":"Gersdorf",
    "wof:placetype":"neighbourhood"
},
  "geometry": {"coordinates":[13.07923,50.95461],"type":"Point"}
}