{
  "type": "Feature",
  "properties": {
    "gn:admin1_code":"7",
    "gn:admin2_code":"51.0",
    "gn:admin3_code":"5154.0",
    "gn:admin4_code":"5154032.0",
    "gn:asciiname":"Huedderath",
    "gn:country_code":"DE",
    "gn:dem":20,
    "gn:feature_class":"P",
    "gn:feature_code":"PPLL",
    "gn:name":"H\u00fcdderath",
    "gn:population":0,
    "gn:timezone":"Europe/Berlin",
    "iso:country":"DE",
    "wof:name":"Huedderath",
    "wof:placetype":"neighbourhood"
},
  "geometry": {"coordinates":[6.24162,51.6016],"type":"Point"}
}