{
  "type": "Feature",
  "properties": {
    "gn:admin1_code":"2",
    "gn:admin2_code":"94.0",
    "gn:admin3_code":"9474.0",
    "gn:admin4_code":"9474132.0",
    "gn:asciiname":"Hofles",
    "gn:country_code":"DE",
    "gn:dem":503,
    "gn:feature_class":"P",
    "gn:feature_code":"PPL",
    "gn:name":"H\u00f6fles",
    "gn:population":0,
    "gn:timezone":"Europe/Berlin",
    "iso:country":"DE",
    "name:und_x_variant":[
        "H\u00f6flas",
        "H\u00f6fles"
    ],
    "wof:name":"Hofles",
    "wof:placetype":"neighbourhood"
},
  "geometry": {"coordinates":[11.27211,49.67639000000001],"type":"Point"}
}