{
  "type": "Feature",
  "properties": {
    "iso:country":"DE",
    "qs_pg:aaroncc":"DE",
    "qs_pg:name":"Niendorf/ostsee",
    "qs_pg:name_adm0":"Deutschland",
    "qs_pg:name_adm1":"Schleswig-Holstein",
    "qs_pg:photos":163,
    "qs_pg:photos_1k":33,
    "qs_pg:photos_9k":1,
    "qs_pg:photos_9r":4,
    "qs_pg:photos_all":163,
    "qs_pg:photos_sr":4,
    "qs_pg:pop_sr":0,
    "qs_pg:qs_pg_placetype":"locality",
    "qs_pg:qs_pg_placetype_gp":"Town",
    "qs_pg:woe_adm0":23424829,
    "woe:adm0_id":23424829,
    "woe:name_adm0":"Deutschland",
    "woe:name_adm1":"Schleswig-Holstein",
    "woe:placetype":"Town",
    "wof:name":"Niendorf/ostsee",
    "wof:placetype":"neighbourhood"
},
  "geometry": {"coordinates":[10.815964,53.99223],"type":"Point"}
}