{
  "type": "Feature",
  "properties": {
    "gn:admin1_code":"2",
    "gn:admin2_code":"91.0",
    "gn:admin3_code":"9189.0",
    "gn:admin4_code":"9189133.0",
    "gn:asciiname":"Diepoldsberg",
    "gn:country_code":"DE",
    "gn:dem":616,
    "gn:feature_class":"P",
    "gn:feature_code":"PPL",
    "gn:name":"Diepoldsberg",
    "gn:population":0,
    "gn:timezone":"Europe/Berlin",
    "iso:country":"DE",
    "name:und_x_variant":[
        "Diepoltsberg",
        "Diepoldsberg"
    ],
    "wof:name":"Diepoldsberg",
    "wof:placetype":"neighbourhood"
},
  "geometry": {"coordinates":[12.34754,48.00936],"type":"Point"}
}