{
  "type": "Feature",
  "properties": {
    "gn:admin1_code":"2",
    "gn:admin2_code":"92.0",
    "gn:admin3_code":"9271.0",
    "gn:admin4_code":"9271135.0",
    "gn:asciiname":"Kurzenisarhofen",
    "gn:cc2":"DE",
    "gn:country_code":"DE",
    "gn:dem":321,
    "gn:feature_class":"P",
    "gn:feature_code":"PPL",
    "gn:name":"Kurzenisarhofen",
    "gn:population":0,
    "gn:timezone":"Europe/Berlin",
    "iso:country":"DE",
    "name:und_x_variant":[
        "Klein Iserhofen",
        "Kurzenisarhofen"
    ],
    "wof:name":"Kurzenisarhofen",
    "wof:placetype":"neighbourhood"
},
  "geometry": {"coordinates":[12.95271,48.74589],"type":"Point"}
}