{
  "type": "Feature",
  "properties": {
    "gn:admin1_code":"10.0",
    "gn:admin2_code":"0.0",
    "gn:admin3_code":"1059.0",
    "gn:admin4_code":"1059187.0",
    "gn:asciiname":"Bremswatt",
    "gn:country_code":"DE",
    "gn:dem":25,
    "gn:feature_class":"P",
    "gn:feature_code":"PPL",
    "gn:name":"Bremswatt",
    "gn:population":0,
    "gn:timezone":"Europe/Berlin",
    "iso:country":"DE",
    "wof:name":"Bremswatt",
    "wof:placetype":"neighbourhood"
},
  "geometry": {"coordinates":[9.85,54.61666999999999],"type":"Point"}
}