{
  "type": "Feature",
  "properties": {
    "gn:admin1_code":"13",
    "gn:admin2_code":"0.0",
    "gn:admin3_code":"14524.0",
    "gn:admin4_code":"14524120.0",
    "gn:asciiname":"Kuehler Morgen",
    "gn:country_code":"DE",
    "gn:dem":431,
    "gn:feature_class":"P",
    "gn:feature_code":"PPL",
    "gn:name":"K\u00fchler Morgen",
    "gn:population":0,
    "gn:timezone":"Europe/Berlin",
    "iso:country":"DE",
    "wof:name":"Kuehler Morgen",
    "wof:placetype":"neighbourhood"
},
  "geometry": {"coordinates":[12.74398,50.82103],"type":"Point"}
}