{
  "type": "Feature",
  "properties": {
    "gn:admin1_code":"12",
    "gn:admin2_code":"0.0",
    "gn:admin3_code":"13075.0",
    "gn:admin4_code":"13075131.0",
    "gn:asciiname":"Pfenningshorst",
    "gn:country_code":"DE",
    "gn:dem":-1,
    "gn:feature_class":"P",
    "gn:feature_code":"PPL",
    "gn:name":"Pfenningshorst",
    "gn:population":0,
    "gn:timezone":"Europe/Berlin",
    "iso:country":"DE",
    "wof:name":"Pfenningshorst",
    "wof:placetype":"neighbourhood"
},
  "geometry": {"coordinates":[14.04243,53.67936],"type":"Point"}
}