{
  "type": "Feature",
  "properties": {
    "gn:admin1_code":"2",
    "gn:admin2_code":"94.0",
    "gn:admin3_code":"9471.0",
    "gn:admin4_code":"9471152.0",
    "gn:asciiname":"Leppelsdorf",
    "gn:country_code":"DE",
    "gn:dem":293,
    "gn:feature_class":"P",
    "gn:feature_code":"PPL",
    "gn:name":"Leppelsdorf",
    "gn:population":0,
    "gn:timezone":"Europe/Berlin",
    "iso:country":"DE",
    "wof:name":"Leppelsdorf",
    "wof:placetype":"neighbourhood"
},
  "geometry": {"coordinates":[10.75832,49.99088],"type":"Point"}
}