{
  "type": "Feature",
  "properties": {
    "gn:admin1_code":"6.0",
    "gn:admin2_code":"0.0",
    "gn:admin3_code":"3361.0",
    "gn:admin4_code":"3361001.0",
    "gn:asciiname":"Bollen",
    "gn:country_code":"DE",
    "gn:dem":8,
    "gn:feature_class":"P",
    "gn:feature_code":"PPL",
    "gn:name":"Bollen",
    "gn:population":0,
    "gn:timezone":"Europe/Berlin",
    "iso:country":"DE",
    "name:ceb_x_preferred":[
        "Bollen"
    ],
    "name:deu_x_preferred":[
        "Bollen"
    ],
    "name:fra_x_preferred":[
        "Bollen"
    ],
    "name:swe_x_preferred":[
        "Bollen"
    ],
    "wof:name":"Bollen",
    "wof:placetype":"neighbourhood"
},
  "geometry": {"coordinates":[8.94337,53.00948],"type":"Point"}
}