{
  "type": "Feature",
  "properties": {
    "gn:population":1261,
    "iso:country":"DE",
    "name:arm_x_preferred":[
        "\u0539\u0561\u0575\u057d\u0561\u0575\u056c"
    ],
    "name:baq_x_preferred":[
        "Theisseil"
    ],
    "name:bar_x_preferred":[
        "Theisseil"
    ],
    "name:chi_x_preferred":[
        "\u6cf0\u8d5b\u5c14"
    ],
    "name:dan_x_preferred":[
        "Theisseil"
    ],
    "name:deu_x_preferred":[
        "Theisseil"
    ],
    "name:dut_x_preferred":[
        "Theisseil"
    ],
    "name:eng_x_preferred":[
        "Theisseil"
    ],
    "name:epo_x_preferred":[
        "Theisseil"
    ],
    "name:eus_x_preferred":[
        "Theisseil"
    ],
    "name:fra_x_preferred":[
        "Theisseil"
    ],
    "name:fre_x_preferred":[
        "Theisseil"
    ],
    "name:ger_x_preferred":[
        "Theisseil"
    ],
    "name:hbs_x_preferred":[
        "Theisseil"
    ],
    "name:hun_x_preferred":[
        "Theisseil"
    ],
    "name:hye_x_preferred":[
        "\u0539\u0561\u0575\u057d\u0561\u0575\u056c"
    ],
    "name:ind_x_preferred":[
        "Theisseil"
    ],
    "name:ita_x_preferred":[
        "Theisseil"
    ],
    "name:kaz_x_preferred":[
        "\u0422\u0430\u0439\u0441\u0430\u0439\u043b\u044c"
    ],
    "name:kir_x_preferred":[
        "\u0422\u0430\u0439\u0441\u0430\u0439\u043b\u044c"
    ],
    "name:lmo_x_preferred":[
        "Theisseil"
    ],
    "name:may_x_preferred":[
        "Theisseil"
    ],
    "name:msa_x_preferred":[
        "Theisseil"
    ],
    "name:nan_x_preferred":[
        "Theisseil"
    ],
    "name:nld_x_preferred":[
        "Theisseil"
    ],
    "name:per_x_preferred":[
        "\u062a\u0627\u06cc\u0633\u0633\u0627\u06cc\u0644"
    ],
    "name:pol_x_preferred":[
        "Theisseil"
    ],
    "name:por_x_preferred":[
        "Theisseil"
    ],
    "name:ron_x_preferred":[
        "Theisseil"
    ],
    "name:rum_x_preferred":[
        "Theisseil"
    ],
    "name:rus_x_preferred":[
        "\u0422\u0430\u0439\u0441\u0430\u0439\u043b\u044c"
    ],
    "name:srp_x_preferred":[
        "\u0422\u0430\u0458\u0441\u0430\u0458\u043b"
    ],
    "name:ukr_x_preferred":[
        "\u0422\u0430\u0439\u0441\u0441\u0430\u0439\u043b\u044c"
    ],
    "name:uzb_x_preferred":[
        "Theisseil"
    ],
    "name:vie_x_preferred":[
        "Theisseil"
    ],
    "name:vol_x_preferred":[
        "Theisseil"
    ],
    "name:war_x_preferred":[
        "Theisseil"
    ],
    "name:zho_min_nan_x_preferred":[
        "Theisseil"
    ],
    "name:zho_x_preferred":[
        "\u6cf0\u8d5b\u5c14"
    ],
    "qs:a0":"Bundesrepublik Deutschland",
    "qs:a1":"*Bayern",
    "qs:a1r":"0",
    "qs:a2":"Neustadt a.d. Waldnaab",
    "qs:adm0":"Bundesrepublik Deutschland",
    "qs:la_lc":"*",
    "qs:level":"locality",
    "qs:loc":"Theisseil",
    "qs:loc_alt":"Theisseil",
    "qs:pop":0,
    "qs:type":"buffered point",
    "wd:wordcount":27,
    "wof:lang":[
        "ger"
    ],
    "wof:name":"Theisseil",
    "wof:placetype":"locality",
    "wof:population":1261
},
  "geometry": {"coordinates":[12.227039,49.690771],"type":"Point"}
}