{
  "type": "Feature",
  "properties": {
    "gn:admin1_code":"9",
    "gn:admin2_code":"0.0",
    "gn:admin3_code":"10042.0",
    "gn:admin4_code":"10042116.0",
    "gn:asciiname":"Niederloestern",
    "gn:country_code":"DE",
    "gn:dem":294,
    "gn:feature_class":"P",
    "gn:feature_code":"PPL",
    "gn:name":"Niederl\u00f6stern",
    "gn:population":0,
    "gn:timezone":"Europe/Berlin",
    "iso:country":"DE",
    "wof:name":"Niederloestern",
    "wof:placetype":"neighbourhood"
},
  "geometry": {"coordinates":[6.911,49.54661],"type":"Point"}
}