{
  "type": "Feature",
  "properties": {
    "gn:population":1410,
    "iso:country":"DE",
    "name:baq_x_preferred":[
        "Hohenpolding"
    ],
    "name:chi_x_preferred":[
        "\u970d\u4ea8\u6ce2\u5c14\u4e01\u683c"
    ],
    "name:dan_x_preferred":[
        "Hohenpolding"
    ],
    "name:deu_x_preferred":[
        "Hohenpolding"
    ],
    "name:deu_x_variant":[
        "Gemeinde Hohenpolding"
    ],
    "name:dut_x_preferred":[
        "Hohenpolding"
    ],
    "name:eng_x_preferred":[
        "Hohenpolding"
    ],
    "name:epo_x_preferred":[
        "Hohenpolding"
    ],
    "name:eus_x_preferred":[
        "Hohenpolding"
    ],
    "name:fas_x_preferred":[
        "\u0647\u0648\u0647\u0646 \u067e\u0648\u0644\u062f\u06cc\u0646\u06af"
    ],
    "name:fra_x_preferred":[
        "Hohenpolding"
    ],
    "name:fre_x_preferred":[
        "Hohenpolding"
    ],
    "name:ger_x_preferred":[
        "Hohenpolding"
    ],
    "name:hbs_x_preferred":[
        "Hohenpolding"
    ],
    "name:hun_x_preferred":[
        "Hohenpolding"
    ],
    "name:ind_x_preferred":[
        "Hohenpolding"
    ],
    "name:ita_x_preferred":[
        "Hohenpolding"
    ],
    "name:kaz_x_preferred":[
        "\u0425\u043e\u044d\u043d\u043f\u043e\u043b\u044c\u0434\u0438\u043d\u0433"
    ],
    "name:kir_x_preferred":[
        "\u0425\u043e\u044d\u043d\u043f\u043e\u043b\u044c\u0434\u0438\u043d\u0433"
    ],
    "name:lmo_x_preferred":[
        "Hohenpolding"
    ],
    "name:may_x_preferred":[
        "Hohenpolding"
    ],
    "name:msa_x_preferred":[
        "Hohenpolding"
    ],
    "name:nan_x_preferred":[
        "Hohenpolding"
    ],
    "name:nld_x_preferred":[
        "Hohenpolding"
    ],
    "name:per_x_preferred":[
        "\u0647\u0648\u0647\u0646 \u067e\u0648\u0644\u062f\u06cc\u0646\u06af"
    ],
    "name:pol_x_preferred":[
        "Hohenpolding"
    ],
    "name:por_x_preferred":[
        "Hohenpolding"
    ],
    "name:ron_x_preferred":[
        "Hohenpolding"
    ],
    "name:rum_x_preferred":[
        "Hohenpolding"
    ],
    "name:rus_x_preferred":[
        "\u0425\u043e\u044d\u043d\u043f\u043e\u043b\u044c\u0434\u0438\u043d\u0433"
    ],
    "name:srp_x_preferred":[
        "\u0425\u043e\u0435\u043d\u043f\u043e\u043b\u0434\u0438\u043d\u0433"
    ],
    "name:ukr_x_preferred":[
        "\u0413\u043e\u0435\u043d\u043f\u043e\u043b\u044c\u0434\u0456\u043d\u0433"
    ],
    "name:uzb_x_preferred":[
        "Hohenpolding"
    ],
    "name:vol_x_preferred":[
        "Hohenpolding"
    ],
    "name:war_x_preferred":[
        "Hohenpolding"
    ],
    "name:zho_min_nan_x_preferred":[
        "Hohenpolding"
    ],
    "name:zho_x_preferred":[
        "\u970d\u4ea8\u6ce2\u5c14\u4e01"
    ],
    "qs:a0":"Bundesrepublik Deutschland",
    "qs:a1":"*Bayern",
    "qs:a1r":"0",
    "qs:a2":"Erding",
    "qs:adm0":"Bundesrepublik Deutschland",
    "qs:la_lc":"*",
    "qs:level":"locality",
    "qs:loc":"Hohenpolding",
    "qs:loc_alt":"Hohenpolding",
    "qs:pop":0,
    "qs:type":"buffered point",
    "wd:wordcount":26,
    "wof:lang":[
        "ger"
    ],
    "wof:name":"Hohenpolding",
    "wof:placetype":"locality",
    "wof:population":1410
},
  "geometry": {"coordinates":[12.130669,48.383354],"type":"Point"}
}