{
  "type": "Feature",
  "properties": {
    "gn:admin1_code":"2",
    "gn:admin2_code":"91.0",
    "gn:admin3_code":"9188.0",
    "gn:admin4_code":"9188124.0",
    "gn:asciiname":"Ried",
    "gn:country_code":"DE",
    "gn:dem":557,
    "gn:feature_class":"P",
    "gn:feature_code":"PPL",
    "gn:name":"Ried",
    "gn:population":0,
    "gn:timezone":"Europe/Berlin",
    "iso:country":"DE",
    "wof:name":"Ried",
    "wof:placetype":"neighbourhood"
},
  "geometry": {"coordinates":[11.14494,48.00698],"type":"Point"}
}