{
  "type": "Feature",
  "properties": {
    "gn:admin1_code":"2",
    "gn:admin2_code":"92.0",
    "gn:admin3_code":"9278.0",
    "gn:admin4_code":"9278118.0",
    "gn:asciiname":"Liepolding",
    "gn:country_code":"DE",
    "gn:dem":330,
    "gn:feature_class":"P",
    "gn:feature_code":"PPL",
    "gn:name":"Liepolding",
    "gn:population":0,
    "gn:timezone":"Europe/Berlin",
    "iso:country":"DE",
    "wof:name":"Liepolding",
    "wof:placetype":"neighbourhood"
},
  "geometry": {"coordinates":[12.74143,48.89439],"type":"Point"}
}