{
  "type": "Feature",
  "properties": {
    "gn:admin1_code":"10",
    "gn:admin2_code":"0.0",
    "gn:admin3_code":"1058.0",
    "gn:admin4_code":"1058142.0",
    "gn:asciiname":"Schinkeler Huetten",
    "gn:country_code":"DE",
    "gn:dem":19,
    "gn:feature_class":"P",
    "gn:feature_code":"PPLL",
    "gn:name":"Schinkeler H\u00fctten",
    "gn:population":0,
    "gn:timezone":"Europe/Berlin",
    "iso:country":"DE",
    "wof:name":"Schinkeler Huetten",
    "wof:placetype":"neighbourhood"
},
  "geometry": {"coordinates":[9.95325,54.36831],"type":"Point"}
}