{
  "type": "Feature",
  "properties": {
    "gn:admin1_code":"7",
    "gn:admin2_code":"59.0",
    "gn:admin3_code":"5954.0",
    "gn:admin4_code":"5954008.0",
    "gn:asciiname":"Steherberg",
    "gn:country_code":"DE",
    "gn:dem":377,
    "gn:feature_class":"P",
    "gn:feature_code":"PPL",
    "gn:name":"Steherberg",
    "gn:population":0,
    "gn:timezone":"Europe/Berlin",
    "iso:country":"DE",
    "wof:name":"Steherberg",
    "wof:placetype":"neighbourhood"
},
  "geometry": {"coordinates":[7.4253,51.28768],"type":"Point"}
}