{
  "type": "Feature",
  "properties": {
    "gn:admin1_code":"2",
    "gn:admin2_code":"96.0",
    "gn:admin3_code":"9677.0",
    "gn:admin4_code":"9677148.0",
    "gn:asciiname":"Rettersbach",
    "gn:country_code":"DE",
    "gn:dem":277,
    "gn:feature_class":"P",
    "gn:feature_code":"PPL",
    "gn:name":"Rettersbach",
    "gn:population":0,
    "gn:timezone":"Europe/Berlin",
    "iso:country":"DE",
    "wof:name":"Rettersbach",
    "wof:placetype":"neighbourhood"
},
  "geometry": {"coordinates":[9.63214,49.99008],"type":"Point"}
}