{
  "type": "Feature",
  "properties": {
    "gn:admin1_code":"2.0",
    "gn:admin2_code":"95.0",
    "gn:admin3_code":"9575.0",
    "gn:admin4_code":"9575119.0",
    "gn:asciiname":"Beerbach",
    "gn:country_code":"DE",
    "gn:dem":352,
    "gn:feature_class":"P",
    "gn:feature_code":"PPL",
    "gn:name":"Beerbach",
    "gn:population":0,
    "gn:timezone":"Europe/Berlin",
    "iso:country":"DE",
    "name:deu_x_preferred":[
        "Beerbach"
    ],
    "wof:name":"Beerbach",
    "wof:placetype":"neighbourhood"
},
  "geometry": {"coordinates":[10.56485,49.54069000000001],"type":"Point"}
}