{
  "type": "Feature",
  "properties": {
    "gn:admin1_code":"2",
    "gn:admin2_code":"95.0",
    "gn:admin3_code":"9571.0",
    "gn:admin4_code":"9571115.0",
    "gn:asciiname":"Heinersdorf",
    "gn:country_code":"DE",
    "gn:dem":425,
    "gn:feature_class":"P",
    "gn:feature_code":"PPL",
    "gn:name":"Heinersdorf",
    "gn:population":0,
    "gn:timezone":"Europe/Berlin",
    "iso:country":"DE",
    "name:bre_x_preferred":[
        "Heinersdorf"
    ],
    "name:ceb_x_preferred":[
        "Heinersdorf"
    ],
    "name:deu_x_preferred":[
        "Berlin-Heinersdorf"
    ],
    "name:fas_x_preferred":[
        "\u0647\u0627\u06cc\u0646\u0631\u0633\u062f\u0648\u0631\u0641"
    ],
    "name:fra_x_preferred":[
        "Berlin-Heinersdorf"
    ],
    "name:ita_x_preferred":[
        "Heinersdorf"
    ],
    "name:nor_x_preferred":[
        "Heinersdorf"
    ],
    "name:pol_x_preferred":[
        "Heinersdorf"
    ],
    "name:rus_x_preferred":[
        "\u0425\u0430\u0439\u043d\u0435\u0440\u0441\u0434\u043e\u0440\u0444"
    ],
    "name:swe_x_preferred":[
        "Heinersdorf"
    ],
    "wof:name":"Heinersdorf",
    "wof:placetype":"neighbourhood"
},
  "geometry": {"coordinates":[10.57596,49.15774],"type":"Point"}
}