{
  "type": "Feature",
  "properties": {
    "gn:admin1_code":"11.0",
    "gn:admin2_code":"00",
    "gn:admin3_code":"12068.0",
    "gn:admin4_code":"12068264.0",
    "gn:asciiname":"Wilhelmsgrille",
    "gn:country_code":"DE",
    "gn:dem":49,
    "gn:feature_class":"P",
    "gn:feature_code":"PPL",
    "gn:name":"Wilhelmsgrille",
    "gn:population":0,
    "gn:timezone":"Europe/Berlin",
    "iso:country":"DE",
    "wof:name":"Wilhelmsgrille",
    "wof:placetype":"neighbourhood"
},
  "geometry": {"coordinates":[12.32745,52.93318000000001],"type":"Point"}
}