{
  "type": "Feature",
  "properties": {
    "gn:admin1_code":"2",
    "gn:admin2_code":"92.0",
    "gn:admin3_code":"9263.0",
    "gn:admin4_code":"9263000.0",
    "gn:asciiname":"Sossau",
    "gn:country_code":"DE",
    "gn:dem":318,
    "gn:feature_class":"P",
    "gn:feature_code":"PPL",
    "gn:name":"Sossau",
    "gn:population":0,
    "gn:timezone":"Europe/Berlin",
    "iso:country":"DE",
    "wof:name":"Sossau",
    "wof:placetype":"neighbourhood"
},
  "geometry": {"coordinates":[12.56213,48.90582],"type":"Point"}
}