{
  "type": "Feature",
  "properties": {
    "gn:admin1_code":"1",
    "gn:admin2_code":"83.0",
    "gn:admin3_code":"8337.0",
    "gn:admin4_code":"8337062.0",
    "gn:asciiname":"Oberhof",
    "gn:country_code":"DE",
    "gn:dem":499,
    "gn:feature_class":"P",
    "gn:feature_code":"PPL",
    "gn:name":"Oberhof",
    "gn:population":0,
    "gn:timezone":"Europe/Berlin",
    "iso:country":"DE",
    "name:als_x_preferred":[
        "Oberhof"
    ],
    "name:ceb_x_preferred":[
        "Oberhof"
    ],
    "name:deu_x_preferred":[
        "Oberhof"
    ],
    "name:epo_x_preferred":[
        "Oberhof"
    ],
    "name:eus_x_preferred":[
        "Oberhof"
    ],
    "name:fra_x_preferred":[
        "Oberhof"
    ],
    "name:ita_x_preferred":[
        "Oberhof"
    ],
    "name:lmo_x_preferred":[
        "Oberhof"
    ],
    "name:nld_x_preferred":[
        "Oberhof"
    ],
    "name:pol_x_preferred":[
        "Oberhof"
    ],
    "name:rus_x_preferred":[
        "\u041e\u0431\u0435\u0440\u0445\u043e\u0444"
    ],
    "name:swe_x_preferred":[
        "Oberhof"
    ],
    "name:vol_x_preferred":[
        "Oberhof"
    ],
    "wof:name":"Oberhof",
    "wof:placetype":"neighbourhood"
},
  "geometry": {"coordinates":[8.45654,47.61253],"type":"Point"}
}