{
  "type": "Feature",
  "properties": {
    "gn:admin1_code":"13",
    "gn:admin2_code":"0.0",
    "gn:admin3_code":"14522.0",
    "gn:admin4_code":"14522570.0",
    "gn:asciiname":"Heyda",
    "gn:country_code":"DE",
    "gn:dem":248,
    "gn:feature_class":"P",
    "gn:feature_code":"PPL",
    "gn:name":"Heyda",
    "gn:population":0,
    "gn:timezone":"Europe/Berlin",
    "iso:country":"DE",
    "name:und_x_variant":[
        "Knobelsdorf-Heyda",
        "Heyda"
    ],
    "wof:name":"Heyda",
    "wof:placetype":"neighbourhood"
},
  "geometry": {"coordinates":[13.10076,51.09062],"type":"Point"}
}