{
  "type": "Feature",
  "properties": {
    "gn:admin1_code":"2.0",
    "gn:admin2_code":"093",
    "gn:admin3_code":"9374.0",
    "gn:admin4_code":"9374157.0",
    "gn:asciiname":"Zettlitz",
    "gn:country_code":"DE",
    "gn:dem":422,
    "gn:feature_class":"P",
    "gn:feature_code":"PPL",
    "gn:name":"Zettlitz",
    "gn:population":0,
    "gn:timezone":"Europe/Berlin",
    "iso:country":"DE",
    "name:bak_x_preferred":[
        "\u0426\u0435\u0442\u043b\u0438\u0446"
    ],
    "name:ceb_x_preferred":[
        "Zettlitz"
    ],
    "name:deu_x_preferred":[
        "Zettlitz"
    ],
    "name:epo_x_preferred":[
        "Zettlitz"
    ],
    "name:est_x_preferred":[
        "Zettlitzi vald"
    ],
    "name:eus_x_preferred":[
        "Zettlitz"
    ],
    "name:fas_x_preferred":[
        "\u062a\u0633\u062a\u0644\u06cc\u062a\u0633"
    ],
    "name:fra_x_preferred":[
        "Zettlitz"
    ],
    "name:hun_x_preferred":[
        "Zettlitz"
    ],
    "name:ita_x_preferred":[
        "Zettlitz"
    ],
    "name:mkd_x_preferred":[
        "\u0426\u0435\u0442\u043b\u0438\u0446"
    ],
    "name:msa_x_preferred":[
        "Zettlitz"
    ],
    "name:nld_x_preferred":[
        "Zettlitz"
    ],
    "name:pol_x_preferred":[
        "Zettlitz"
    ],
    "name:ron_x_preferred":[
        "Zettlitz"
    ],
    "name:rus_x_preferred":[
        "\u0426\u0435\u0442\u043b\u0438\u0446"
    ],
    "name:spa_x_preferred":[
        "Zettlitz"
    ],
    "name:srp_x_preferred":[
        "\u0426\u0435\u0442\u043b\u0438\u0446"
    ],
    "name:ukr_x_preferred":[
        "\u0426\u0435\u0442\u0442\u043b\u0456\u0446"
    ],
    "name:uzb_x_preferred":[
        "Zettlitz"
    ],
    "name:vie_x_preferred":[
        "Zettlitz"
    ],
    "name:vol_x_preferred":[
        "Zettlitz"
    ],
    "name:war_x_preferred":[
        "Zettlitz"
    ],
    "name:zho_x_preferred":[
        "\u7b56\u7279\u5229\u8328"
    ],
    "wof:name":"Zettlitz",
    "wof:placetype":"neighbourhood"
},
  "geometry": {"coordinates":[11.85872,49.77428],"type":"Point"}
}