{
  "type": "Feature",
  "properties": {
    "gn:admin1_code":"2",
    "gn:admin2_code":"92.0",
    "gn:admin3_code":"9276.0",
    "gn:admin4_code":"9276113.0",
    "gn:asciiname":"Rohrlhof",
    "gn:country_code":"DE",
    "gn:dem":561,
    "gn:feature_class":"P",
    "gn:feature_code":"PPL",
    "gn:name":"R\u00f6hrlhof",
    "gn:population":0,
    "gn:timezone":"Europe/Berlin",
    "iso:country":"DE",
    "wof:name":"Rohrlhof",
    "wof:placetype":"neighbourhood"
},
  "geometry": {"coordinates":[12.99222,49.11026],"type":"Point"}
}