{
  "type": "Feature",
  "properties": {
    "gn:admin1_code":"1",
    "gn:admin2_code":"84.0",
    "gn:admin3_code":"8437.0",
    "gn:admin4_code":"8437100.0",
    "gn:asciiname":"Untereggatsweiler",
    "gn:country_code":"DE",
    "gn:dem":612,
    "gn:feature_class":"P",
    "gn:feature_code":"PPL",
    "gn:name":"Untereggatsweiler",
    "gn:population":0,
    "gn:timezone":"Europe/Berlin",
    "iso:country":"DE",
    "wof:name":"Untereggatsweiler",
    "wof:placetype":"neighbourhood"
},
  "geometry": {"coordinates":[9.56216,48.03255],"type":"Point"}
}