{
  "type": "Feature",
  "properties": {
    "gn:country":"DE",
    "gn:fcode":"PPL",
    "gn:population":0,
    "iso:country":"DE",
    "name:bel_x_preferred":[
        "\u0411\u0443\u0433"
    ],
    "name:bul_x_preferred":[
        "\u0411\u0443\u0433"
    ],
    "name:cat_x_preferred":[
        "Bug"
    ],
    "name:ceb_x_preferred":[
        "Bug"
    ],
    "name:ces_x_preferred":[
        "Bug"
    ],
    "name:dan_x_preferred":[
        "Bug"
    ],
    "name:deu_x_preferred":[
        "Bug"
    ],
    "name:fas_x_preferred":[
        "\u062d\u0634\u0631\u0647"
    ],
    "name:fin_x_preferred":[
        "Bug"
    ],
    "name:fra_x_preferred":[
        "Bug"
    ],
    "name:heb_x_preferred":[
        "\u05d1\u05d5\u05d2"
    ],
    "name:hrv_x_preferred":[
        "Bug"
    ],
    "name:hun_x_preferred":[
        "Bug"
    ],
    "name:lav_x_preferred":[
        "Bug"
    ],
    "name:lit_x_preferred":[
        "Bugas"
    ],
    "name:nld_x_preferred":[
        "Bug"
    ],
    "name:nno_x_preferred":[
        "Bug"
    ],
    "name:nor_x_preferred":[
        "Bug"
    ],
    "name:oci_x_preferred":[
        "Bug"
    ],
    "name:pol_x_preferred":[
        "Bug"
    ],
    "name:por_x_preferred":[
        "Bug"
    ],
    "name:rus_x_preferred":[
        "\u0411\u0443\u0433"
    ],
    "name:spa_x_preferred":[
        "Bug"
    ],
    "name:srp_x_preferred":[
        "\u0411\u0443\u0433"
    ],
    "name:swa_x_preferred":[
        "Mdudu"
    ],
    "name:swe_x_preferred":[
        "Bug"
    ],
    "name:tgl_x_preferred":[
        "Bug"
    ],
    "name:tha_x_preferred":[
        "\u0e1a\u0e31\u0e4a\u0e01"
    ],
    "name:ukr_x_preferred":[
        "\u0411\u0443\u0433"
    ],
    "name:uzb_x_preferred":[
        "Bug"
    ],
    "qs_pg:aaroncc":"DE",
    "qs_pg:gn_country":"DE",
    "qs_pg:gn_fcode":"PPL",
    "qs_pg:gn_pop":0,
    "qs_pg:name":"Bug",
    "qs_pg:name_adm0":"Deutschland",
    "qs_pg:name_adm1":"Bayern",
    "qs_pg:photos_9k":1,
    "qs_pg:photos_9r":1,
    "qs_pg:photos_all":1,
    "qs_pg:photos_sr":0,
    "qs_pg:pop_sr":0,
    "qs_pg:qs_pg_placetype":"locality",
    "qs_pg:qs_pg_placetype_gp":"Town",
    "qs_pg:woe_adm0":23424829,
    "woe:adm0_id":23424829,
    "woe:name_adm0":"Deutschland",
    "woe:name_adm1":"Bayern",
    "woe:placetype":"Town",
    "wof:name":"Bug",
    "wof:placetype":"neighbourhood"
},
  "geometry": {"coordinates":[10.9096,49.86491],"type":"Point"}
}