{
  "type": "Feature",
  "properties": {
    "gn:admin1_code":"2.0",
    "gn:admin2_code":"094",
    "gn:admin3_code":"9474.0",
    "gn:admin4_code":"9474121.0",
    "gn:asciiname":"Wolkenstein",
    "gn:country_code":"DE",
    "gn:dem":490,
    "gn:feature_class":"P",
    "gn:feature_code":"PPL",
    "gn:name":"Wolkenstein",
    "gn:population":0,
    "gn:timezone":"Europe/Berlin",
    "iso:country":"DE",
    "name:ara_x_preferred":[
        "\u0641\u0648\u0644\u0643\u0646\u0634\u062a\u0627\u064a\u0646"
    ],
    "name:azb_x_preferred":[
        "\u0648\u0648\u0644\u06a9\u0646\u200c\u0627\u0634\u062a\u0627\u06cc\u0646"
    ],
    "name:ceb_x_preferred":[
        "Wolkenstein"
    ],
    "name:deu_x_preferred":[
        "Wolkenstein"
    ],
    "name:epo_x_preferred":[
        "Wolkenstein"
    ],
    "name:est_x_preferred":[
        "Wolkenstein"
    ],
    "name:fas_x_preferred":[
        "\u0648\u0648\u0644\u06a9\u0646\u200c\u0627\u0634\u062a\u0627\u06cc\u0646"
    ],
    "name:fra_x_preferred":[
        "Wolkenstein"
    ],
    "name:hrv_x_preferred":[
        "Wolkenstein"
    ],
    "name:hun_x_preferred":[
        "Wolkenstein"
    ],
    "name:ita_x_preferred":[
        "Wolkenstein"
    ],
    "name:lav_x_preferred":[
        "Volken\u0161teina"
    ],
    "name:mkd_x_preferred":[
        "\u0412\u043e\u043b\u043a\u0435\u043d\u0448\u0442\u0430\u0458\u043d"
    ],
    "name:msa_x_preferred":[
        "Wolkenstein"
    ],
    "name:nld_x_preferred":[
        "Wolkenstein"
    ],
    "name:nor_x_preferred":[
        "Wolkenstein"
    ],
    "name:pol_x_preferred":[
        "Wolkenstein"
    ],
    "name:por_x_preferred":[
        "Wolkenstein"
    ],
    "name:ron_x_preferred":[
        "Wolkenstein"
    ],
    "name:rus_x_preferred":[
        "\u0412\u043e\u043b\u044c\u043a\u0435\u043d\u0448\u0442\u0430\u0439\u043d"
    ],
    "name:spa_x_preferred":[
        "Wolkenstein"
    ],
    "name:srp_x_preferred":[
        "\u0412\u043e\u043b\u043a\u0435\u043d\u0448\u0442\u0430\u0458\u043d"
    ],
    "name:swe_x_preferred":[
        "Wolkenstein"
    ],
    "name:tur_x_preferred":[
        "Wolkenstein"
    ],
    "name:ukr_x_preferred":[
        "\u0412\u043e\u043b\u044c\u043a\u0435\u043d\u0448\u0442\u0430\u0439\u043d"
    ],
    "name:uzb_x_preferred":[
        "Wolkenstein"
    ],
    "name:vol_x_preferred":[
        "Wolkenstein"
    ],
    "name:war_x_preferred":[
        "Wolkenstein"
    ],
    "name:zho_x_preferred":[
        "\u6c83\u5c14\u80af\u65bd\u6cf0\u56e0"
    ],
    "wof:name":"Wolkenstein",
    "wof:placetype":"neighbourhood"
},
  "geometry": {"coordinates":[11.24216,49.75667],"type":"Point"}
}