{
  "type": "Feature",
  "properties": {
    "gn:admin1_code":"12.0",
    "gn:admin2_code":"0.0",
    "gn:admin3_code":"13071.0",
    "gn:admin4_code":"13071046.0",
    "gn:asciiname":"Below",
    "gn:country_code":"DE",
    "gn:dem":75,
    "gn:feature_class":"P",
    "gn:feature_code":"PPL",
    "gn:name":"Below",
    "gn:population":0,
    "gn:timezone":"Europe/Berlin",
    "iso:country":"DE",
    "name:deu_x_preferred":[
        "Below"
    ],
    "name:fra_x_preferred":[
        "Below"
    ],
    "name:ita_x_preferred":[
        "Below"
    ],
    "name:swe_x_preferred":[
        "Below"
    ],
    "wof:name":"Below",
    "wof:placetype":"neighbourhood"
},
  "geometry": {"coordinates":[12.46382,53.25946],"type":"Point"}
}