{
  "type": "Feature",
  "properties": {
    "gn:admin1_code":"2",
    "gn:admin2_code":"91.0",
    "gn:admin3_code":"9171.0",
    "gn:admin4_code":"9171113.0",
    "gn:asciiname":"Hasenbuhl",
    "gn:country_code":"DE",
    "gn:dem":459,
    "gn:feature_class":"P",
    "gn:feature_code":"PPL",
    "gn:name":"Hasenb\u00fchl",
    "gn:population":0,
    "gn:timezone":"Europe/Berlin",
    "iso:country":"DE",
    "wof:name":"Hasenbuhl",
    "wof:placetype":"neighbourhood"
},
  "geometry": {"coordinates":[12.71667,48.11667],"type":"Point"}
}