{
  "type": "Feature",
  "properties": {
    "gn:admin1_code":"12",
    "gn:admin2_code":"0.0",
    "gn:admin3_code":"13071.0",
    "gn:admin4_code":"13071140.0",
    "gn:asciiname":"Ruehlow",
    "gn:country_code":"DE",
    "gn:dem":72,
    "gn:feature_class":"P",
    "gn:feature_code":"PPL",
    "gn:name":"R\u00fchlow",
    "gn:population":0,
    "gn:timezone":"Europe/Berlin",
    "iso:country":"DE",
    "wof:name":"Ruehlow",
    "wof:placetype":"neighbourhood"
},
  "geometry": {"coordinates":[13.44086,53.56341],"type":"Point"}
}