{
  "type": "Feature",
  "properties": {
    "gn:admin1_code":"7",
    "gn:admin2_code":"53.0",
    "gn:admin3_code":"5370.0",
    "gn:admin4_code":"5370040.0",
    "gn:asciiname":"Uevekoven",
    "gn:country_code":"DE",
    "gn:dem":75,
    "gn:feature_class":"P",
    "gn:feature_code":"PPL",
    "gn:name":"Uevekoven",
    "gn:population":0,
    "gn:timezone":"Europe/Berlin",
    "iso:country":"DE",
    "wof:name":"Uevekoven",
    "wof:placetype":"neighbourhood"
},
  "geometry": {"coordinates":[6.2888,51.12443],"type":"Point"}
}