{
  "type": "Feature",
  "properties": {
    "gn:admin1_code":"8",
    "gn:admin2_code":"0.0",
    "gn:admin3_code":"7232.0",
    "gn:admin4_code":"7232095.0",
    "gn:asciiname":"Freilingen",
    "gn:country_code":"DE",
    "gn:dem":371,
    "gn:feature_class":"P",
    "gn:feature_code":"PPL",
    "gn:name":"Freilingen",
    "gn:population":0,
    "gn:timezone":"Europe/Berlin",
    "iso:country":"DE",
    "wof:name":"Freilingen",
    "wof:placetype":"locality"
},
  "geometry": {"coordinates":[6.33347,49.9194],"type":"Point"}
}