{
  "type": "Feature",
  "properties": {
    "gn:admin1_code":"11",
    "gn:admin2_code":"0.0",
    "gn:admin3_code":"12069.0",
    "gn:admin4_code":"12069632.0",
    "gn:asciiname":"Feldheim",
    "gn:country_code":"DE",
    "gn:dem":150,
    "gn:feature_class":"P",
    "gn:feature_code":"PPL",
    "gn:name":"Feldheim",
    "gn:population":0,
    "gn:timezone":"Europe/Berlin",
    "iso:country":"DE",
    "name:deu_x_preferred":[
        "Feldheim"
    ],
    "name:pol_x_preferred":[
        "Feldheim"
    ],
    "wof:name":"Feldheim",
    "wof:placetype":"neighbourhood"
},
  "geometry": {"coordinates":[12.81972,52.01136],"type":"Point"}
}