{
  "type": "Feature",
  "properties": {
    "gn:admin1_code":"7.0",
    "gn:admin2_code":"053",
    "gn:admin3_code":"5334.0",
    "gn:admin4_code":"5334004.0",
    "gn:asciiname":"Zopp",
    "gn:country_code":"DE",
    "gn:dem":150,
    "gn:feature_class":"P",
    "gn:feature_code":"PPL",
    "gn:name":"Zopp",
    "gn:population":0,
    "gn:timezone":"Europe/Berlin",
    "iso:country":"DE",
    "wof:name":"Zopp",
    "wof:placetype":"neighbourhood"
},
  "geometry": {"coordinates":[6.13639,50.86787],"type":"Point"}
}