{
  "type": "Feature",
  "properties": {
    "gn:admin1_code":"2",
    "gn:admin2_code":"93.0",
    "gn:admin3_code":"9374.0",
    "gn:admin4_code":"9374148.0",
    "gn:asciiname":"Weihersberg",
    "gn:country_code":"DE",
    "gn:dem":460,
    "gn:feature_class":"P",
    "gn:feature_code":"PPL",
    "gn:name":"Weihersberg",
    "gn:population":0,
    "gn:timezone":"Europe/Berlin",
    "iso:country":"DE",
    "wof:name":"Weihersberg",
    "wof:placetype":"neighbourhood"
},
  "geometry": {"coordinates":[11.92976,49.7856],"type":"Point"}
}