{
  "type": "Feature",
  "properties": {
    "gn:admin1_code":"7.0",
    "gn:admin2_code":"59.0",
    "gn:admin3_code":"5958.0",
    "gn:admin4_code":"5958004.0",
    "gn:asciiname":"Bergheim",
    "gn:country_code":"DE",
    "gn:dem":212,
    "gn:feature_class":"P",
    "gn:feature_code":"PPL",
    "gn:name":"Bergheim",
    "gn:population":0,
    "gn:timezone":"Europe/Berlin",
    "iso:country":"DE",
    "name:bar_x_preferred":[
        "Bergheim"
    ],
    "name:ceb_x_preferred":[
        "Bergheim"
    ],
    "name:dan_x_preferred":[
        "Bergheim"
    ],
    "name:deu_x_preferred":[
        "Bergheim"
    ],
    "name:eus_x_preferred":[
        "Bergheim"
    ],
    "name:fra_x_preferred":[
        "Bergheim"
    ],
    "name:hye_x_preferred":[
        "\u0532\u0565\u0580\u0563\u0570\u0561\u0575\u0574"
    ],
    "name:ita_x_preferred":[
        "Bergheim"
    ],
    "name:nds_x_preferred":[
        "Bergheim"
    ],
    "name:nld_x_preferred":[
        "Bergheim"
    ],
    "name:nno_x_preferred":[
        "Bergheim"
    ],
    "name:nor_x_preferred":[
        "Bergheim"
    ],
    "name:pol_x_preferred":[
        "Bergheim"
    ],
    "name:por_x_preferred":[
        "Bergheim"
    ],
    "name:rus_x_preferred":[
        "\u0411\u0435\u0440\u0433\u0445\u0430\u0439\u043c"
    ],
    "name:slk_x_preferred":[
        "Bergheim"
    ],
    "name:srp_x_preferred":[
        "\u0411\u0435\u0440\u0433\u0445\u0430\u0458\u043c"
    ],
    "name:swe_x_preferred":[
        "Bergheim"
    ],
    "name:ukr_x_preferred":[
        "\u0411\u0435\u0440\u0433\u0433\u0430\u0439\u043c"
    ],
    "name:vol_x_preferred":[
        "Bergheim"
    ],
    "name:zho_x_preferred":[
        "\u8d1d\u683c\u6d77\u59c6"
    ],
    "wof:name":"Bergheim",
    "wof:placetype":"neighbourhood"
},
  "geometry": {"coordinates":[7.94348,51.45542],"type":"Point"}
}