{
  "type": "Feature",
  "properties": {
    "gn:admin1_code":"7.0",
    "gn:admin2_code":"59.0",
    "gn:admin3_code":"5958.0",
    "gn:admin4_code":"5958004.0",
    "gn:asciiname":"Bergheim",
    "gn:country_code":"DE",
    "gn:dem":212,
    "gn:feature_class":"P",
    "gn:feature_code":"PPL",
    "gn:name":"Bergheim",
    "gn:population":0,
    "gn:timezone":"Europe/Berlin",
    "iso:country":"DE",
    "wof:name":"Bergheim",
    "wof:placetype":"neighbourhood"
},
  "geometry": {"coordinates":[7.94348,51.45542],"type":"Point"}
}