{
  "type": "Feature",
  "properties": {
    "gn:admin1_code":"2.0",
    "gn:admin2_code":"97.0",
    "gn:admin3_code":"9780.0",
    "gn:admin4_code":"9780127.0",
    "gn:asciiname":"Aigis",
    "gn:country_code":"DE",
    "gn:dem":918,
    "gn:feature_class":"P",
    "gn:feature_code":"PPL",
    "gn:name":"Aigis",
    "gn:population":0,
    "gn:timezone":"Europe/Berlin",
    "iso:country":"DE",
    "wof:name":"Aigis",
    "wof:placetype":"neighbourhood"
},
  "geometry": {"coordinates":[10.09472,47.60772],"type":"Point"}
}