{
  "type": "Feature",
  "properties": {
    "gn:admin1_code":"6",
    "gn:admin2_code":"0.0",
    "gn:admin3_code":"3102.0",
    "gn:admin4_code":"3102000.0",
    "gn:asciiname":"Immendorf",
    "gn:country_code":"DE",
    "gn:dem":93,
    "gn:feature_class":"P",
    "gn:feature_code":"PPL",
    "gn:name":"Immendorf",
    "gn:population":0,
    "gn:timezone":"Europe/Berlin",
    "iso:country":"DE",
    "wof:name":"Immendorf",
    "wof:placetype":"neighbourhood"
},
  "geometry": {"coordinates":[10.44221,52.14603],"type":"Point"}
}