{
  "type": "Feature",
  "properties": {
    "gn:admin1_code":"6.0",
    "gn:admin2_code":"00",
    "gn:admin3_code":"3461.0",
    "gn:admin4_code":"3461008.0",
    "gn:asciiname":"Wolfsstrasse",
    "gn:country_code":"DE",
    "gn:dem":0,
    "gn:feature_class":"P",
    "gn:feature_code":"PPLL",
    "gn:name":"Wolfsstra\u00dfe",
    "gn:population":0,
    "gn:timezone":"Europe/Berlin",
    "iso:country":"DE",
    "wof:name":"Wolfsstrasse",
    "wof:placetype":"neighbourhood"
},
  "geometry": {"coordinates":[8.28259,53.28892],"type":"Point"}
}