{
  "type": "Feature",
  "properties": {
    "gn:admin1_code":"2",
    "gn:admin2_code":"92.0",
    "gn:admin3_code":"9278.0",
    "gn:admin4_code":"9278129.0",
    "gn:asciiname":"Krottenholz",
    "gn:country_code":"DE",
    "gn:dem":426,
    "gn:feature_class":"P",
    "gn:feature_code":"PPL",
    "gn:name":"Krottenholz",
    "gn:population":0,
    "gn:timezone":"Europe/Berlin",
    "iso:country":"DE",
    "wof:name":"Krottenholz",
    "wof:placetype":"neighbourhood"
},
  "geometry": {"coordinates":[12.7073,49.03023],"type":"Point"}
}