{
  "type": "Feature",
  "properties": {
    "gn:country":"DE",
    "gn:fcode":"PPL",
    "gn:population":0,
    "iso:country":"DE",
    "name:als_x_preferred":[
        "Dippech"
    ],
    "name:bel_x_preferred":[
        "\u0414\u0437\u0456\u043f\u0430\u0445"
    ],
    "name:cat_x_preferred":[
        "Dippach"
    ],
    "name:ceb_x_preferred":[
        "Dippach"
    ],
    "name:ces_x_preferred":[
        "Dippach"
    ],
    "name:dan_x_preferred":[
        "Dippach"
    ],
    "name:deu_x_preferred":[
        "Dippach"
    ],
    "name:fas_x_preferred":[
        "\u062f\u06cc\u067e\u0627\u062e"
    ],
    "name:fra_x_preferred":[
        "Dippach"
    ],
    "name:ita_x_preferred":[
        "Dippach"
    ],
    "name:ltz_x_preferred":[
        "Gemeng Dippech"
    ],
    "name:msa_x_preferred":[
        "Dippach"
    ],
    "name:nds_x_preferred":[
        "Gemeen Dippach"
    ],
    "name:nld_x_preferred":[
        "Dippach"
    ],
    "name:nor_x_preferred":[
        "Dippach"
    ],
    "name:pol_x_preferred":[
        "Dippach"
    ],
    "name:por_x_preferred":[
        "Dippach"
    ],
    "name:rus_x_preferred":[
        "\u0414\u0438\u043f\u043f\u0430\u0445"
    ],
    "name:slk_x_preferred":[
        "Dippach"
    ],
    "name:spa_x_preferred":[
        "Dippach"
    ],
    "name:swe_x_preferred":[
        "Dippach"
    ],
    "name:ukr_x_preferred":[
        "\u0414\u0456\u043f\u043f\u0430\u0445"
    ],
    "qs_pg:aaroncc":"DE",
    "qs_pg:gn_country":"DE",
    "qs_pg:gn_fcode":"PPL",
    "qs_pg:gn_pop":0,
    "qs_pg:name":"Dippach",
    "qs_pg:name_adm0":"Deutschland",
    "qs_pg:name_adm1":"Bayern",
    "qs_pg:photos_9k":1,
    "qs_pg:photos_9r":1,
    "qs_pg:photos_all":1,
    "qs_pg:photos_sr":0,
    "qs_pg:pop_sr":0,
    "qs_pg:qs_pg_placetype":"locality",
    "qs_pg:qs_pg_placetype_gp":"Town",
    "qs_pg:woe_adm0":23424829,
    "woe:adm0_id":23424829,
    "woe:name_adm0":"Deutschland",
    "woe:name_adm1":"Bayern",
    "woe:placetype":"Town",
    "wof:name":"Dippach",
    "wof:placetype":"neighbourhood"
},
  "geometry": {"coordinates":[10.70841,49.95641],"type":"Point"}
}