{
  "type": "Feature",
  "properties": {
    "gn:admin1_code":"2",
    "gn:admin2_code":"94.0",
    "gn:admin3_code":"9477.0",
    "gn:admin4_code":"9477127.0",
    "gn:asciiname":"Ebersbach",
    "gn:country_code":"DE",
    "gn:dem":319,
    "gn:feature_class":"P",
    "gn:feature_code":"PPL",
    "gn:name":"Ebersbach",
    "gn:population":0,
    "gn:timezone":"Europe/Berlin",
    "iso:country":"DE",
    "name:ceb_x_preferred":[
        "Ebersbach"
    ],
    "name:deu_x_preferred":[
        "Ebersbach"
    ],
    "name:epo_x_preferred":[
        "Ebersbach"
    ],
    "name:est_x_preferred":[
        "Ebersbach"
    ],
    "name:fra_x_preferred":[
        "Ebersbach"
    ],
    "name:ita_x_preferred":[
        "Ebersbach"
    ],
    "name:mkd_x_preferred":[
        "\u0415\u0431\u0435\u0440\u0441\u0431\u0430\u0445"
    ],
    "name:nld_x_preferred":[
        "Ebersbach"
    ],
    "name:pol_x_preferred":[
        "Ebersbach"
    ],
    "name:rus_x_preferred":[
        "\u042d\u0431\u0435\u0440\u0441\u0431\u0430\u0445"
    ],
    "name:swe_x_preferred":[
        "Ebersbach"
    ],
    "name:ukr_x_preferred":[
        "\u0415\u0431\u0435\u0440\u0441\u0431\u0430\u0445"
    ],
    "wof:name":"Ebersbach",
    "wof:placetype":"neighbourhood"
},
  "geometry": {"coordinates":[11.51494,50.09762],"type":"Point"}
}