{
  "type": "Feature",
  "properties": {
    "gn:admin1_code":"2",
    "gn:admin2_code":"96.0",
    "gn:admin3_code":"9674.0",
    "gn:admin4_code":"9674130.0",
    "gn:asciiname":"Brunn",
    "gn:country_code":"DE",
    "gn:dem":274,
    "gn:feature_class":"P",
    "gn:feature_code":"PPL",
    "gn:name":"Br\u00fcnn",
    "gn:population":0,
    "gn:timezone":"Europe/Berlin",
    "iso:country":"DE",
    "name:ceb_x_preferred":[
        "Brunn"
    ],
    "name:deu_x_preferred":[
        "Brunn"
    ],
    "name:epo_x_preferred":[
        "Brunn"
    ],
    "name:eus_x_preferred":[
        "Brunn"
    ],
    "name:fra_x_preferred":[
        "Brunn"
    ],
    "name:ita_x_preferred":[
        "Brunn"
    ],
    "name:nld_x_preferred":[
        "Brunn"
    ],
    "name:pol_x_preferred":[
        "Brunn"
    ],
    "name:rus_x_preferred":[
        "\u0411\u0440\u0443\u043d\u043d"
    ],
    "name:swe_x_preferred":[
        "Brunn"
    ],
    "name:vie_x_preferred":[
        "Brunn"
    ],
    "name:vol_x_preferred":[
        "Brunn"
    ],
    "wof:name":"Brunn",
    "wof:placetype":"neighbourhood"
},
  "geometry": {"coordinates":[10.71762,50.12078],"type":"Point"}
}