{
  "type": "Feature",
  "properties": {
    "gn:admin1_code":"2",
    "gn:admin2_code":"92.0",
    "gn:admin3_code":"9278.0",
    "gn:admin4_code":"9278116.0",
    "gn:asciiname":"Oberniedersteinach",
    "gn:country_code":"DE",
    "gn:dem":356,
    "gn:feature_class":"P",
    "gn:feature_code":"PPL",
    "gn:name":"Oberniedersteinach",
    "gn:population":0,
    "gn:timezone":"Europe/Berlin",
    "iso:country":"DE",
    "wof:name":"Oberniedersteinach",
    "wof:placetype":"neighbourhood"
},
  "geometry": {"coordinates":[12.61281,48.97657],"type":"Point"}
}