{
  "type": "Feature",
  "properties": {
    "gn:admin1_code":"7.0",
    "gn:admin2_code":"51.0",
    "gn:admin3_code":"5116.0",
    "gn:admin4_code":"5116000.0",
    "gn:asciiname":"Baum",
    "gn:country_code":"DE",
    "gn:dem":77,
    "gn:feature_class":"P",
    "gn:feature_code":"PPL",
    "gn:name":"Baum",
    "gn:population":0,
    "gn:timezone":"Europe/Berlin",
    "iso:country":"DE",
    "name:deu_x_preferred":[
        "Baum"
    ],
    "name:heb_x_preferred":[
        "\u05d1\u05d5\u05d9\u05dd"
    ],
    "name:ita_x_preferred":[
        "Baum"
    ],
    "name:nor_x_preferred":[
        "Baum"
    ],
    "name:pol_x_preferred":[
        "Baum"
    ],
    "name:ron_x_preferred":[
        "Baum"
    ],
    "name:rus_x_preferred":[
        "\u0411\u0430\u0443\u043c"
    ],
    "name:slv_x_preferred":[
        "Baum"
    ],
    "name:swe_x_preferred":[
        "Baum"
    ],
    "wof:name":"Baum",
    "wof:placetype":"neighbourhood"
},
  "geometry": {"coordinates":[6.36156,51.12978],"type":"Point"}
}