{
  "type": "Feature",
  "properties": {
    "gn:admin1_code":"7.0",
    "gn:admin2_code":"51.0",
    "gn:admin3_code":"5116.0",
    "gn:admin4_code":"5116000.0",
    "gn:asciiname":"Baum",
    "gn:country_code":"DE",
    "gn:dem":77,
    "gn:feature_class":"P",
    "gn:feature_code":"PPL",
    "gn:name":"Baum",
    "gn:population":0,
    "gn:timezone":"Europe/Berlin",
    "iso:country":"DE",
    "wof:name":"Baum",
    "wof:placetype":"neighbourhood"
},
  "geometry": {"coordinates":[6.36156,51.12978],"type":"Point"}
}