{
  "type": "Feature",
  "properties": {
    "gn:admin1_code":"2",
    "gn:admin2_code":"92.0",
    "gn:admin3_code":"9274.0",
    "gn:admin4_code":"9274145.0",
    "gn:asciiname":"Stocka",
    "gn:country_code":"DE",
    "gn:dem":483,
    "gn:feature_class":"P",
    "gn:feature_code":"PPL",
    "gn:name":"Stocka",
    "gn:population":0,
    "gn:timezone":"Europe/Berlin",
    "iso:country":"DE",
    "name:ceb_x_preferred":[
        "Stocka"
    ],
    "name:ita_x_preferred":[
        "Stocka"
    ],
    "name:nld_x_preferred":[
        "Stocka"
    ],
    "name:nno_x_preferred":[
        "Stocka"
    ],
    "name:nor_x_preferred":[
        "Stocka"
    ],
    "name:swe_x_preferred":[
        "Stocka"
    ],
    "wof:name":"Stocka",
    "wof:placetype":"neighbourhood"
},
  "geometry": {"coordinates":[12.33331,48.56892],"type":"Point"}
}