{
  "type": "Feature",
  "properties": {
    "gn:admin1_code":"11",
    "gn:admin2_code":"0.0",
    "gn:admin3_code":"12067.0",
    "gn:admin4_code":"12067469.0",
    "gn:asciiname":"Markgrafpieske",
    "gn:country_code":"DE",
    "gn:dem":41,
    "gn:feature_class":"P",
    "gn:feature_code":"PPL",
    "gn:name":"Markgrafpieske",
    "gn:population":0,
    "gn:timezone":"Europe/Berlin",
    "iso:country":"DE",
    "wof:name":"Markgrafpieske",
    "wof:placetype":"neighbourhood"
},
  "geometry": {"coordinates":[13.95038,52.32658],"type":"Point"}
}