{
  "type": "Feature",
  "properties": {
    "gn:admin1_code":"14",
    "gn:admin2_code":"0.0",
    "gn:admin3_code":"15082.0",
    "gn:admin4_code":"15082377.0",
    "gn:asciiname":"Diesdorf",
    "gn:country_code":"DE",
    "gn:dem":79,
    "gn:feature_class":"P",
    "gn:feature_code":"PPL",
    "gn:name":"Diesdorf",
    "gn:population":0,
    "gn:timezone":"Europe/Berlin",
    "iso:country":"DE",
    "name:bak_x_preferred":[
        "\u0414\u0438\u0441\u0434\u043e\u0440\u0444"
    ],
    "name:deu_x_preferred":[
        "Diesdorf"
    ],
    "name:epo_x_preferred":[
        "Diesdorf"
    ],
    "name:fas_x_preferred":[
        "\u062f\u06cc\u0633\u062f\u0648\u0631\u0641"
    ],
    "name:fra_x_preferred":[
        "Diesdorf"
    ],
    "name:hun_x_preferred":[
        "Diesdorf"
    ],
    "name:ita_x_preferred":[
        "Diesdorf"
    ],
    "name:kaz_x_preferred":[
        "\u0414\u0438\u0441\u0434\u043e\u0440\u0444"
    ],
    "name:kir_x_preferred":[
        "\u0414\u0438\u0441\u0434\u043e\u0440\u0444"
    ],
    "name:mkd_x_preferred":[
        "\u0414\u0438\u0441\u0434\u043e\u0440\u0444"
    ],
    "name:msa_x_preferred":[
        "Diesdorf"
    ],
    "name:nld_x_preferred":[
        "Diesdorf"
    ],
    "name:pol_x_preferred":[
        "Diesdorf"
    ],
    "name:ron_x_preferred":[
        "Diesdorf"
    ],
    "name:rus_x_preferred":[
        "\u0414\u0438\u0441\u0434\u043e\u0440\u0444"
    ],
    "name:spa_x_preferred":[
        "Diesdorf"
    ],
    "name:srp_x_preferred":[
        "\u0414\u0438\u0441\u0434\u043e\u0440\u0444"
    ],
    "name:swe_x_preferred":[
        "Diesdorf"
    ],
    "name:ukr_x_preferred":[
        "\u0414\u0456\u0441\u0434\u043e\u0440\u0444"
    ],
    "name:uzb_x_preferred":[
        "Diesdorf"
    ],
    "name:vie_x_preferred":[
        "Diesdorf"
    ],
    "name:vol_x_preferred":[
        "Diesdorf"
    ],
    "name:war_x_preferred":[
        "Diesdorf"
    ],
    "name:zho_x_preferred":[
        "\u8fea\u65af\u591a\u592b"
    ],
    "wof:name":"Diesdorf",
    "wof:placetype":"neighbourhood"
},
  "geometry": {"coordinates":[12.15696,51.76264000000001],"type":"Point"}
}