{
  "type": "Feature",
  "properties": {
    "gn:admin1_code":"13",
    "gn:admin2_code":"0.0",
    "gn:admin3_code":"14521.0",
    "gn:admin4_code":"14521020.0",
    "gn:asciiname":"Kleinrueckerswalde",
    "gn:country_code":"DE",
    "gn:dem":699,
    "gn:feature_class":"P",
    "gn:feature_code":"PPL",
    "gn:name":"Kleinr\u00fcckerswalde",
    "gn:population":0,
    "gn:timezone":"Europe/Berlin",
    "iso:country":"DE",
    "wof:name":"Kleinrueckerswalde",
    "wof:placetype":"neighbourhood"
},
  "geometry": {"coordinates":[13.01799,50.56813],"type":"Point"}
}