{
  "type": "Feature",
  "properties": {
    "iso:country":"DE",
    "name:ceb_x_preferred":[
        "Hartmannsdorf"
    ],
    "name:deu_x_preferred":[
        "Hartmannsdorf"
    ],
    "name:epo_x_preferred":[
        "Hartmannsdorf"
    ],
    "name:fra_x_preferred":[
        "Hartmannsdorf"
    ],
    "name:hbs_x_preferred":[
        "Hartmannsdorf"
    ],
    "name:ita_x_preferred":[
        "Hartmannsdorf"
    ],
    "name:kaz_x_preferred":[
        "\u0425\u0430\u0440\u0442\u043c\u0430\u043d\u0441\u0434\u043e\u0440\u0444"
    ],
    "name:mkd_x_preferred":[
        "\u0425\u0430\u0440\u0442\u043c\u0430\u043d\u0441\u0434\u043e\u0440\u0444"
    ],
    "name:nld_x_preferred":[
        "Hartmannsdorf"
    ],
    "name:pol_x_preferred":[
        "Hartmannsdorf"
    ],
    "name:rus_x_preferred":[
        "\u0425\u0430\u0440\u0442\u043c\u0430\u043d\u0441\u0434\u043e\u0440\u0444"
    ],
    "name:srp_x_preferred":[
        "\u0425\u0430\u0440\u0442\u043c\u0430\u043d\u0441\u0434\u043e\u0440\u0444"
    ],
    "name:swe_x_preferred":[
        "Hartmannsdorf"
    ],
    "name:vol_x_preferred":[
        "Hartmannsdorf"
    ],
    "qs:gn_adm0_cc":"DE",
    "qs:gn_fcode":"PPL",
    "qs:gn_local":2879139,
    "qs:gn_nam_loc":"Leipzig, Kreisfreie Stadt Leipzig, Sachsen, DE",
    "qs:gn_namadm1":"13",
    "qs:gn_name":"Hartmannsdorf",
    "qs:local_max":18559,
    "qs:local_sum":46030,
    "qs:localhoods":28,
    "qs:name":"Hartmannsdorf",
    "qs:name_adm0":"Deutschland",
    "qs:name_adm1":"Sachsen",
    "qs:name_adm2":"Kreisfreie Stadt Leipzig",
    "qs:name_lau":"Knauthain-Hartmannsdorf",
    "qs:name_local":"Leipzig",
    "qs:photo_max":22,
    "qs:photo_sum":45,
    "qs:placetype":"Suburb",
    "qs:quad_count":7,
    "qs:woe_adm0":23424829,
    "qs:woe_adm1":2345493,
    "qs:woe_adm2":12596753,
    "qs:woe_lau":26822866,
    "qs:woe_local":671072,
    "qs:woe_ver":"7.10.0",
    "wof:lang":[
        "ger"
    ],
    "wof:name":"Hartmannsdorf",
    "wof:placetype":"neighbourhood"
},
  "geometry": {"coordinates":[12.30423,51.261362],"type":"Point"}
}