{
  "type": "Feature",
  "properties": {
    "gn:admin1_code":"7.0",
    "gn:admin2_code":"053",
    "gn:admin3_code":"5374.0",
    "gn:admin4_code":"5374016.0",
    "gn:asciiname":"Wickesberg",
    "gn:country_code":"DE",
    "gn:dem":289,
    "gn:feature_class":"P",
    "gn:feature_code":"PPL",
    "gn:name":"Wickesberg",
    "gn:population":0,
    "gn:timezone":"Europe/Berlin",
    "iso:country":"DE",
    "wof:name":"Wickesberg",
    "wof:placetype":"neighbourhood"
},
  "geometry": {"coordinates":[7.29918,51.1169],"type":"Point"}
}