{
  "type": "Feature",
  "properties": {
    "gn:admin1_code":"11.0",
    "gn:admin2_code":"00",
    "gn:admin3_code":"12073.0",
    "gn:admin4_code":"12073093.0",
    "gn:asciiname":"Wendtshof",
    "gn:country_code":"DE",
    "gn:dem":61,
    "gn:feature_class":"P",
    "gn:feature_code":"PPL",
    "gn:name":"Wendtshof",
    "gn:population":0,
    "gn:timezone":"Europe/Berlin",
    "iso:country":"DE",
    "wof:name":"Wendtshof",
    "wof:placetype":"neighbourhood"
},
  "geometry": {"coordinates":[14.06868,53.35834000000001],"type":"Point"}
}