{
  "type": "Feature",
  "properties": {
    "iso:country":"DE",
    "name:arm_x_preferred":[
        "\u054e\u056b\u0569\u056b\u0562\u0580\u0578\u0575\u0569"
    ],
    "name:baq_x_preferred":[
        "Wittibreut"
    ],
    "name:bar_x_preferred":[
        "Wittibreut"
    ],
    "name:ces_x_preferred":[
        "Wittibreut"
    ],
    "name:chi_x_preferred":[
        "\u7ef4\u8482\u5e03\u7f57\u4f0a\u7279"
    ],
    "name:cze_x_preferred":[
        "Wittibreut"
    ],
    "name:deu_x_preferred":[
        "Wittibreut"
    ],
    "name:dut_x_preferred":[
        "Wittibreut"
    ],
    "name:eng_x_preferred":[
        "Wittibreut"
    ],
    "name:epo_x_preferred":[
        "Wittibreut"
    ],
    "name:eus_x_preferred":[
        "Wittibreut"
    ],
    "name:fas_x_preferred":[
        "\u0648\u06cc\u062a\u06cc\u0628\u0631\u0648\u06cc\u062a"
    ],
    "name:fra_x_preferred":[
        "Wittibreut"
    ],
    "name:fre_x_preferred":[
        "Wittibreut"
    ],
    "name:ger_x_preferred":[
        "Wittibreut"
    ],
    "name:hbs_x_preferred":[
        "Wittibreut"
    ],
    "name:hun_x_preferred":[
        "Wittibreut"
    ],
    "name:hye_x_preferred":[
        "\u054e\u056b\u0569\u056b\u0562\u0580\u0578\u0575\u0569"
    ],
    "name:ita_x_preferred":[
        "Wittibreut"
    ],
    "name:kaz_x_preferred":[
        "\u0412\u0438\u0442\u0442\u0438\u0431\u0440\u043e\u0439\u0442"
    ],
    "name:kir_x_preferred":[
        "\u0412\u0438\u0442\u0442\u0438\u0431\u0440\u043e\u0439\u0442"
    ],
    "name:lmo_x_preferred":[
        "Wittibreut"
    ],
    "name:may_x_preferred":[
        "Wittibreut"
    ],
    "name:msa_x_preferred":[
        "Wittibreut"
    ],
    "name:nan_x_preferred":[
        "Wittibreut"
    ],
    "name:nld_x_preferred":[
        "Wittibreut"
    ],
    "name:per_x_preferred":[
        "\u0648\u06cc\u062a\u06cc\u0628\u0631\u0648\u06cc\u062a"
    ],
    "name:pol_x_preferred":[
        "Wittibreut"
    ],
    "name:ron_x_preferred":[
        "Wittibreut"
    ],
    "name:rum_x_preferred":[
        "Wittibreut"
    ],
    "name:rus_x_preferred":[
        "\u0412\u0438\u0442\u0442\u0438\u0431\u0440\u043e\u0439\u0442"
    ],
    "name:srp_x_preferred":[
        "\u0412\u0438\u0442\u0438\u0431\u0440\u043e\u0458\u0442"
    ],
    "name:ukr_x_preferred":[
        "\u0412\u0456\u0442\u0442\u0456\u0431\u0440\u043e\u0439\u0442"
    ],
    "name:uzb_x_preferred":[
        "Wittibreut"
    ],
    "name:vie_x_preferred":[
        "Wittibreut"
    ],
    "name:vol_x_preferred":[
        "Wittibreut"
    ],
    "name:war_x_preferred":[
        "Wittibreut"
    ],
    "name:zho_min_nan_x_preferred":[
        "Wittibreut"
    ],
    "name:zho_x_preferred":[
        "\u7ef4\u8482\u5e03\u7f57\u4f0a\u7279"
    ],
    "qs:a0":"Bundesrepublik Deutschland",
    "qs:a1":"*Bayern",
    "qs:a1r":"0",
    "qs:a2":"Rottal-Inn",
    "qs:adm0":"Bundesrepublik Deutschland",
    "qs:la_lc":"*",
    "qs:level":"locality",
    "qs:loc":"Wittibreut",
    "qs:loc_alt":"Wittibreut",
    "qs:pop":0,
    "qs:type":"buffered point",
    "wd:wordcount":26,
    "wof:name":"Wittibreut",
    "wof:placetype":"locality"
},
  "geometry": {"coordinates":[12.987358,48.32927],"type":"Point"}
}