{
  "type": "Feature",
  "properties": {
    "gn:admin1_code":"8.0",
    "gn:admin2_code":"0.0",
    "gn:admin3_code":"7141.0",
    "gn:admin4_code":"7141011.0",
    "gn:asciiname":"Ackerbach",
    "gn:country_code":"DE",
    "gn:dem":356,
    "gn:feature_class":"P",
    "gn:feature_code":"PPL",
    "gn:name":"Ackerbach",
    "gn:population":0,
    "gn:timezone":"Europe/Berlin",
    "iso:country":"DE",
    "wof:name":"Ackerbach",
    "wof:placetype":"neighbourhood"
},
  "geometry": {"coordinates":[7.98087,50.23771],"type":"Point"}
}