{
  "type": "Feature",
  "properties": {
    "gn:admin1_code":"2",
    "gn:admin2_code":"91.0",
    "gn:admin3_code":"9190.0",
    "gn:admin4_code":"9190126.0",
    "gn:asciiname":"Durnhausen",
    "gn:country_code":"DE",
    "gn:dem":623,
    "gn:feature_class":"P",
    "gn:feature_code":"PPL",
    "gn:name":"D\u00fcrnhausen",
    "gn:population":0,
    "gn:timezone":"Europe/Berlin",
    "iso:country":"DE",
    "name:und_x_variant":[
        "D\u00fcrrnhausen",
        "D\u00fcrnhausen"
    ],
    "wof:name":"Durnhausen",
    "wof:placetype":"neighbourhood"
},
  "geometry": {"coordinates":[11.30764,47.73333],"type":"Point"}
}