{
  "type": "Feature",
  "properties": {
    "gn:admin1_code":"1.0",
    "gn:admin2_code":"083",
    "gn:admin3_code":"8337.0",
    "gn:admin4_code":"8337027.0",
    "gn:asciiname":"Wittenschwand",
    "gn:country_code":"DE",
    "gn:dem":914,
    "gn:feature_class":"P",
    "gn:feature_code":"PPL",
    "gn:name":"Wittenschwand",
    "gn:population":0,
    "gn:timezone":"Europe/Berlin",
    "iso:country":"DE",
    "wof:name":"Wittenschwand",
    "wof:placetype":"neighbourhood"
},
  "geometry": {"coordinates":[8.09976,47.72998],"type":"Point"}
}