{
  "type": "Feature",
  "properties": {
    "gn:admin1_code":"15",
    "gn:admin2_code":"0.0",
    "gn:admin3_code":"16076.0",
    "gn:admin4_code":"16076084.0",
    "gn:asciiname":"Untitz",
    "gn:country_code":"DE",
    "gn:dem":215,
    "gn:feature_class":"P",
    "gn:feature_code":"PPL",
    "gn:name":"Untitz",
    "gn:population":0,
    "gn:timezone":"Europe/Berlin",
    "iso:country":"DE",
    "wof:name":"Untitz",
    "wof:placetype":"neighbourhood"
},
  "geometry": {"coordinates":[12.09675,50.81939000000001],"type":"Point"}
}