{
  "type": "Feature",
  "properties": {
    "gn:admin1_code":"5",
    "gn:admin2_code":"66.0",
    "gn:admin3_code":"6634.0",
    "gn:admin4_code":"6634007.0",
    "gn:asciiname":"Deute",
    "gn:country_code":"DE",
    "gn:dem":211,
    "gn:feature_class":"P",
    "gn:feature_code":"PPL",
    "gn:name":"Deute",
    "gn:population":0,
    "gn:timezone":"Europe/Berlin",
    "iso:country":"DE",
    "wof:name":"Deute",
    "wof:placetype":"neighbourhood"
},
  "geometry": {"coordinates":[9.41244,51.17901],"type":"Point"}
}