{
  "type": "Feature",
  "properties": {
    "gn:admin1_code":"1",
    "gn:admin2_code":"84.0",
    "gn:admin3_code":"8426.0",
    "gn:admin4_code":"8426120.0",
    "gn:asciiname":"Hausern",
    "gn:country_code":"DE",
    "gn:dem":647,
    "gn:feature_class":"P",
    "gn:feature_code":"PPL",
    "gn:name":"H\u00e4usern",
    "gn:population":0,
    "gn:timezone":"Europe/Berlin",
    "iso:country":"DE",
    "wof:name":"Hausern",
    "wof:placetype":"neighbourhood"
},
  "geometry": {"coordinates":[9.85308,48.0656],"type":"Point"}
}