{
  "type": "Feature",
  "properties": {
    "gn:admin1_code":"2",
    "gn:admin2_code":"94.0",
    "gn:admin3_code":"9477.0",
    "gn:admin4_code":"9477117.0",
    "gn:asciiname":"Horbach",
    "gn:country_code":"DE",
    "gn:dem":634,
    "gn:feature_class":"P",
    "gn:feature_code":"PPL",
    "gn:name":"Horbach",
    "gn:population":0,
    "gn:timezone":"Europe/Berlin",
    "iso:country":"DE",
    "name:ceb_x_preferred":[
        "Horbach"
    ],
    "name:deu_x_preferred":[
        "Horbach"
    ],
    "name:epo_x_preferred":[
        "Horbach"
    ],
    "name:fra_x_preferred":[
        "Horbach"
    ],
    "name:ita_x_preferred":[
        "Horbach"
    ],
    "name:nld_x_preferred":[
        "Horbach"
    ],
    "name:pol_x_preferred":[
        "Horbach"
    ],
    "name:rus_x_preferred":[
        "\u0425\u043e\u0440\u0431\u0430\u0445"
    ],
    "name:srp_x_preferred":[
        "\u0425\u043e\u0440\u0431\u0430\u0445"
    ],
    "name:swe_x_preferred":[
        "Horbach"
    ],
    "wof:name":"Horbach",
    "wof:placetype":"neighbourhood"
},
  "geometry": {"coordinates":[11.64195,50.21187000000001],"type":"Point"}
}