{
  "type": "Feature",
  "properties": {
    "gn:admin1_code":"2",
    "gn:admin2_code":"94.0",
    "gn:admin3_code":"9477.0",
    "gn:admin4_code":"9477117.0",
    "gn:asciiname":"Horbach",
    "gn:country_code":"DE",
    "gn:dem":634,
    "gn:feature_class":"P",
    "gn:feature_code":"PPL",
    "gn:name":"Horbach",
    "gn:population":0,
    "gn:timezone":"Europe/Berlin",
    "iso:country":"DE",
    "wof:name":"Horbach",
    "wof:placetype":"neighbourhood"
},
  "geometry": {"coordinates":[11.64195,50.21187000000001],"type":"Point"}
}