{
  "type": "Feature",
  "properties": {
    "iso:country":"DE",
    "wof:name":"Ost",
    "wof:placetype":"neighbourhood"
},
  "geometry": {"coordinates":[9.20863325638017,48.78000462125427],"type":"Point"}
}