{
  "type": "Feature",
  "properties": {
    "gn:admin1_code":"2",
    "gn:admin2_code":"91.0",
    "gn:admin3_code":"9187.0",
    "gn:admin4_code":"9187128.0",
    "gn:asciiname":"Dorfbach",
    "gn:country_code":"DE",
    "gn:dem":522,
    "gn:feature_class":"P",
    "gn:feature_code":"PPL",
    "gn:name":"Dorfbach",
    "gn:population":0,
    "gn:timezone":"Europe/Berlin",
    "iso:country":"DE",
    "wof:name":"Dorfbach",
    "wof:placetype":"neighbourhood"
},
  "geometry": {"coordinates":[12.29636,47.92293],"type":"Point"}
}