{
  "type": "Feature",
  "properties": {
    "gn:admin1_code":"2",
    "gn:admin2_code":"93.0",
    "gn:admin3_code":"9377.0",
    "gn:admin4_code":"9377149.0",
    "gn:asciiname":"Escheldorf",
    "gn:country_code":"DE",
    "gn:dem":491,
    "gn:feature_class":"P",
    "gn:feature_code":"PPL",
    "gn:name":"Escheldorf",
    "gn:population":0,
    "gn:timezone":"Europe/Berlin",
    "iso:country":"DE",
    "wof:name":"Escheldorf",
    "wof:placetype":"neighbourhood"
},
  "geometry": {"coordinates":[12.1341,49.85395],"type":"Point"}
}