{
  "type": "Feature",
  "properties": {
    "gn:admin1_code":"6",
    "gn:admin2_code":"0.0",
    "gn:admin3_code":"3453.0",
    "gn:admin4_code":"3453007.0",
    "gn:asciiname":"Hohefeld",
    "gn:country_code":"DE",
    "gn:dem":8,
    "gn:feature_class":"P",
    "gn:feature_code":"PPL",
    "gn:name":"Hohefeld",
    "gn:population":0,
    "gn:timezone":"Europe/Berlin",
    "iso:country":"DE",
    "wof:name":"Hohefeld",
    "wof:placetype":"neighbourhood"
},
  "geometry": {"coordinates":[7.90173,53.04075],"type":"Point"}
}