{
  "type": "Feature",
  "properties": {
    "iso:country":"DE",
    "name:deu_x_preferred":[
        "Rheindorf"
    ],
    "name:deu_x_variant":[
        "Leverkusen-Rheindorf"
    ],
    "qs:gn_fcode":"PPLX",
    "qs:gn_local":0,
    "qs:gn_namadm1":"07",
    "qs:gn_name":"Rheindorf",
    "qs:local_max":2310,
    "qs:local_sum":4408,
    "qs:localhoods":17,
    "qs:name":"Rheindorf",
    "qs:name_adm0":"Deutschland",
    "qs:name_adm1":"Nordrhein-Westfalen",
    "qs:name_adm2":"Stadtkreis Leverkusen",
    "qs:name_lau":"Stadtteil Leverkusen",
    "qs:name_local":"Stadtteil Leverkusen",
    "qs:photo_max":13,
    "qs:photo_sum":58,
    "qs:placetype":"Suburb",
    "qs:quad_count":15,
    "qs:woe_adm0":23424829,
    "qs:woe_adm1":2345487,
    "qs:woe_adm2":12597015,
    "qs:woe_lau":28350225,
    "qs:woe_local":28350225,
    "qs:woe_ver":"7.10.0",
    "wof:lang":[
        "ger"
    ],
    "wof:name":"Rheindorf",
    "wof:placetype":"neighbourhood"
},
  "geometry": {"coordinates":[6.948433,51.0534],"type":"Point"}
}