{
  "type": "Feature",
  "properties": {
    "gn:admin1_code":"13",
    "gn:admin2_code":"0.0",
    "gn:admin3_code":"14627.0",
    "gn:admin4_code":"14627020.0",
    "gn:asciiname":"Kleinzadel",
    "gn:country_code":"DE",
    "gn:dem":112,
    "gn:feature_class":"P",
    "gn:feature_code":"PPL",
    "gn:name":"Kleinzadel",
    "gn:population":0,
    "gn:timezone":"Europe/Berlin",
    "iso:country":"DE",
    "wof:name":"Kleinzadel",
    "wof:placetype":"neighbourhood"
},
  "geometry": {"coordinates":[13.4096,51.20664],"type":"Point"}
}