{
  "type": "Feature",
  "properties": {
    "gn:admin1_code":"7.0",
    "gn:admin2_code":"59.0",
    "gn:admin3_code":"5978.0",
    "gn:admin4_code":"5978008.0",
    "gn:asciiname":"Altefeld",
    "gn:country_code":"DE",
    "gn:dem":77,
    "gn:feature_class":"P",
    "gn:feature_code":"PPL",
    "gn:name":"Altefeld",
    "gn:population":0,
    "gn:timezone":"Europe/Berlin",
    "iso:country":"DE",
    "name:deu_x_preferred":[
        "Altefeld"
    ],
    "name:ita_x_preferred":[
        "Altefeld"
    ],
    "wof:name":"Altefeld",
    "wof:placetype":"neighbourhood"
},
  "geometry": {"coordinates":[7.75068,51.6129],"type":"Point"}
}