{
  "type": "Feature",
  "properties": {
    "gn:admin1_code":"8",
    "gn:admin2_code":"0.0",
    "gn:admin3_code":"7138.0",
    "gn:admin4_code":"7138003.0",
    "gn:asciiname":"Krumbach",
    "gn:country_code":"DE",
    "gn:dem":231,
    "gn:feature_class":"P",
    "gn:feature_code":"PPL",
    "gn:name":"Krumbach",
    "gn:population":0,
    "gn:timezone":"Europe/Berlin",
    "iso:country":"DE",
    "name:als_x_preferred":[
        "Krumbach"
    ],
    "name:ceb_x_preferred":[
        "Krumbach"
    ],
    "name:ces_x_preferred":[
        "Krumbach"
    ],
    "name:deu_x_preferred":[
        "Krumbach"
    ],
    "name:fra_x_preferred":[
        "Krumbach"
    ],
    "name:hun_x_preferred":[
        "Krumbach"
    ],
    "name:ita_x_preferred":[
        "Krumbach"
    ],
    "name:lmo_x_preferred":[
        "Krumbach"
    ],
    "name:nld_x_preferred":[
        "Krumbach"
    ],
    "name:pol_x_preferred":[
        "Krumbach"
    ],
    "name:ron_x_preferred":[
        "Krumbach"
    ],
    "name:swe_x_preferred":[
        "Krumbach"
    ],
    "name:vol_x_preferred":[
        "Krumbach"
    ],
    "wof:name":"Krumbach",
    "wof:placetype":"neighbourhood"
},
  "geometry": {"coordinates":[7.45167,50.66967],"type":"Point"}
}