{
  "type": "Feature",
  "properties": {
    "iso:country":"DE",
    "wof:name":"Benrad",
    "wof:placetype":"neighbourhood"
},
  "geometry": {"coordinates":[6.52412772789884,51.3227562856275],"type":"Point"}
}