{
  "type": "Feature",
  "properties": {
    "gn:admin1_code":"13",
    "gn:admin2_code":"0.0",
    "gn:admin3_code":"14523.0",
    "gn:admin4_code":"14523020.0",
    "gn:asciiname":"Hahnenhaeuser",
    "gn:country_code":"DE",
    "gn:dem":635,
    "gn:feature_class":"P",
    "gn:feature_code":"PPL",
    "gn:name":"Hahnenh\u00e4user",
    "gn:population":0,
    "gn:timezone":"Europe/Berlin",
    "iso:country":"DE",
    "name:und_x_variant":[
        "Hahnenhaus",
        "Hahnenh\u00e4user"
    ],
    "wof:name":"Hahnenhaeuser",
    "wof:placetype":"neighbourhood"
},
  "geometry": {"coordinates":[12.46953,50.51277],"type":"Point"}
}