{
  "type": "Feature",
  "properties": {
    "gn:admin1_code":"2",
    "gn:admin2_code":"91.0",
    "gn:admin3_code":"9183.0",
    "gn:admin4_code":"9183126.0",
    "gn:asciiname":"Haslach",
    "gn:country_code":"DE",
    "gn:dem":546,
    "gn:feature_class":"P",
    "gn:feature_code":"PPL",
    "gn:name":"Haslach",
    "gn:population":0,
    "gn:timezone":"Europe/Berlin",
    "iso:country":"DE",
    "name:als_x_preferred":[
        "Haslach"
    ],
    "name:ceb_x_preferred":[
        "Haslach"
    ],
    "name:deu_x_preferred":[
        "Haslach"
    ],
    "name:epo_x_preferred":[
        "Haslach"
    ],
    "name:fra_x_preferred":[
        "Haslach"
    ],
    "name:ita_x_preferred":[
        "Haslach"
    ],
    "name:nld_x_preferred":[
        "Haslach"
    ],
    "name:pol_x_preferred":[
        "Haslach"
    ],
    "name:swe_x_preferred":[
        "Haslach"
    ],
    "wof:name":"Haslach",
    "wof:placetype":"neighbourhood"
},
  "geometry": {"coordinates":[12.14406,48.15223],"type":"Point"}
}