{
  "type": "Feature",
  "properties": {
    "gn:admin1_code":"2",
    "gn:admin2_code":"92.0",
    "gn:admin3_code":"9278.0",
    "gn:admin4_code":"9278198.0",
    "gn:asciiname":"Netzstuhl",
    "gn:country_code":"DE",
    "gn:dem":457,
    "gn:feature_class":"P",
    "gn:feature_code":"PPL",
    "gn:name":"Netzstuhl",
    "gn:population":0,
    "gn:timezone":"Europe/Berlin",
    "iso:country":"DE",
    "wof:name":"Netzstuhl",
    "wof:placetype":"neighbourhood"
},
  "geometry": {"coordinates":[12.75798,48.93467],"type":"Point"}
}