{
  "type": "Feature",
  "properties": {
    "gn:admin1_code":"2",
    "gn:admin2_code":"91.0",
    "gn:admin3_code":"9189.0",
    "gn:admin4_code":"9189157.0",
    "gn:asciiname":"Gainharting",
    "gn:country_code":"DE",
    "gn:dem":554,
    "gn:feature_class":"P",
    "gn:feature_code":"PPL",
    "gn:name":"Gainharting",
    "gn:population":0,
    "gn:timezone":"Europe/Berlin",
    "iso:country":"DE",
    "wof:name":"Gainharting",
    "wof:placetype":"neighbourhood"
},
  "geometry": {"coordinates":[12.53255,48.03744],"type":"Point"}
}