{
  "type": "Feature",
  "properties": {
    "gn:admin1_code":"2",
    "gn:admin2_code":"91.0",
    "gn:admin3_code":"9189.0",
    "gn:admin4_code":"9189145.0",
    "gn:asciiname":"Horgering",
    "gn:country_code":"DE",
    "gn:dem":659,
    "gn:feature_class":"P",
    "gn:feature_code":"PPL",
    "gn:name":"H\u00f6rgering",
    "gn:population":0,
    "gn:timezone":"Europe/Berlin",
    "iso:country":"DE",
    "name:deu_x_preferred":[
        "H\u00f6rgering"
    ],
    "wof:name":"Horgering",
    "wof:placetype":"neighbourhood"
},
  "geometry": {"coordinates":[12.64447,47.79361],"type":"Point"}
}