{
  "type": "Feature",
  "properties": {
    "gn:admin1_code":"2",
    "gn:admin2_code":"94.0",
    "gn:admin3_code":"9473.0",
    "gn:admin4_code":"9473158.0",
    "gn:asciiname":"Schweighof",
    "gn:country_code":"DE",
    "gn:dem":299,
    "gn:feature_class":"P",
    "gn:feature_code":"PPL",
    "gn:name":"Schweighof",
    "gn:population":0,
    "gn:timezone":"Europe/Berlin",
    "iso:country":"DE",
    "wof:name":"Schweighof",
    "wof:placetype":"neighbourhood"
},
  "geometry": {"coordinates":[10.79949,50.33139],"type":"Point"}
}