{
  "type": "Feature",
  "properties": {
    "gn:admin1_code":"2",
    "gn:admin2_code":"94.0",
    "gn:admin3_code":"9472.0",
    "gn:admin4_code":"9472143.0",
    "gn:asciiname":"Nemmersdorf",
    "gn:country_code":"DE",
    "gn:dem":452,
    "gn:feature_class":"P",
    "gn:feature_code":"PPL",
    "gn:name":"Nemmersdorf",
    "gn:population":0,
    "gn:timezone":"Europe/Berlin",
    "iso:country":"DE",
    "name:deu_x_preferred":[
        "Nemmersdorf"
    ],
    "wof:name":"Nemmersdorf",
    "wof:placetype":"neighbourhood"
},
  "geometry": {"coordinates":[11.68586,49.99358],"type":"Point"}
}