{
  "type": "Feature",
  "properties": {
    "gn:country":"DE",
    "gn:fcode":"PPL",
    "gn:population":1617,
    "iso:country":"DE",
    "name:bak_x_preferred":[
        "\u041e\u0439\u0431\u0438\u043d"
    ],
    "name:cat_x_preferred":[
        "Oybin"
    ],
    "name:ceb_x_preferred":[
        "Oybin"
    ],
    "name:ces_x_preferred":[
        "Oybin"
    ],
    "name:che_x_preferred":[
        "\u041e\u0439\u0431\u0438\u043d"
    ],
    "name:cym_x_preferred":[
        "Oybin"
    ],
    "name:deu_x_preferred":[
        "Oybin"
    ],
    "name:eng_x_preferred":[
        "Oybin"
    ],
    "name:epo_x_preferred":[
        "Oybin"
    ],
    "name:est_x_preferred":[
        "Oybini vald"
    ],
    "name:eus_x_preferred":[
        "Oybin"
    ],
    "name:fas_x_preferred":[
        "\u0627\u0648\u06cc\u0628\u06cc\u0646"
    ],
    "name:fra_x_preferred":[
        "Oybin"
    ],
    "name:hsb_x_preferred":[
        "Ojbin"
    ],
    "name:hun_x_preferred":[
        "Oybin"
    ],
    "name:ita_x_preferred":[
        "Oybin"
    ],
    "name:kaz_x_preferred":[
        "\u041e\u0439\u0431\u0438\u043d"
    ],
    "name:kir_x_preferred":[
        "\u041e\u0439\u0431\u0438\u043d"
    ],
    "name:lld_x_preferred":[
        "Oybin"
    ],
    "name:mkd_x_preferred":[
        "\u041e\u0458\u0431\u0438\u043d"
    ],
    "name:msa_x_preferred":[
        "Oybin"
    ],
    "name:nld_x_preferred":[
        "Oybin"
    ],
    "name:nob_x_preferred":[
        "Oybin"
    ],
    "name:pol_x_preferred":[
        "Oybin"
    ],
    "name:por_x_preferred":[
        "Oybin"
    ],
    "name:ron_x_preferred":[
        "Oybin"
    ],
    "name:rus_x_preferred":[
        "\u041e\u0439\u0431\u0438\u043d"
    ],
    "name:spa_x_preferred":[
        "Oybin"
    ],
    "name:srp_x_preferred":[
        "\u041e\u0458\u0431\u0438\u043d"
    ],
    "name:swe_x_preferred":[
        "Oybin"
    ],
    "name:tat_x_preferred":[
        "\u041e\u0439\u0431\u0438\u043d"
    ],
    "name:ukr_x_preferred":[
        "\u041e\u0439\u0431\u0456\u043d"
    ],
    "name:uzb_x_preferred":[
        "Oybin"
    ],
    "name:vol_x_preferred":[
        "Oybin"
    ],
    "name:war_x_preferred":[
        "Oybin"
    ],
    "name:zho_x_preferred":[
        "\u5965\u4f0a\u5bbe"
    ],
    "qs_pg:aaroncc":"DE",
    "qs_pg:gn_country":"DE",
    "qs_pg:gn_fcode":"PPL",
    "qs_pg:gn_pop":1617,
    "qs_pg:name":"Kurort Oybin",
    "qs_pg:name_adm0":"Deutschland",
    "qs_pg:name_adm1":"Sachsen",
    "qs_pg:photos":44,
    "qs_pg:photos_1k":9,
    "qs_pg:photos_9k":1,
    "qs_pg:photos_9r":2,
    "qs_pg:photos_all":44,
    "qs_pg:photos_sr":2,
    "qs_pg:pop_sr":3,
    "qs_pg:qs_pg_placetype":"locality",
    "qs_pg:qs_pg_placetype_gp":"Town",
    "qs_pg:woe_adm0":23424829,
    "woe:adm0_id":23424829,
    "woe:name_adm0":"Deutschland",
    "woe:name_adm1":"Sachsen",
    "woe:placetype":"Town",
    "wof:name":"Kurort Oybin",
    "wof:placetype":"neighbourhood",
    "wof:population":1617
},
  "geometry": {"coordinates":[14.74124,50.84105],"type":"Point"}
}