{
  "type": "Feature",
  "properties": {
    "gn:admin1_code":"5",
    "gn:admin2_code":"66.0",
    "gn:admin3_code":"6634.0",
    "gn:admin4_code":"6634009.0",
    "gn:asciiname":"Dickershausen",
    "gn:country_code":"DE",
    "gn:dem":329,
    "gn:feature_class":"P",
    "gn:feature_code":"PPL",
    "gn:name":"Dickershausen",
    "gn:population":0,
    "gn:timezone":"Europe/Berlin",
    "iso:country":"DE",
    "wof:name":"Dickershausen",
    "wof:placetype":"neighbourhood"
},
  "geometry": {"coordinates":[9.46573,51.05701],"type":"Point"}
}