{
  "type": "Feature",
  "properties": {
    "gn:admin1_code":"12",
    "gn:admin2_code":"0.0",
    "gn:admin3_code":"13075.0",
    "gn:admin4_code":"13075107.0",
    "gn:asciiname":"Radewitz",
    "gn:country_code":"DE",
    "gn:dem":40,
    "gn:feature_class":"P",
    "gn:feature_code":"PPL",
    "gn:name":"Radewitz",
    "gn:population":0,
    "gn:timezone":"Europe/Berlin",
    "iso:country":"DE",
    "wof:name":"Radewitz",
    "wof:placetype":"neighbourhood"
},
  "geometry": {"coordinates":[14.15463,53.2954],"type":"Point"}
}