{
  "type": "Feature",
  "properties": {
    "gn:admin1_code":"7",
    "gn:admin2_code":"53.0",
    "gn:admin3_code":"5374.0",
    "gn:admin4_code":"5374012.0",
    "gn:asciiname":"Neudieringhausen",
    "gn:country_code":"DE",
    "gn:dem":187,
    "gn:feature_class":"P",
    "gn:feature_code":"PPL",
    "gn:name":"Neudieringhausen",
    "gn:population":0,
    "gn:timezone":"Europe/Berlin",
    "iso:country":"DE",
    "wof:name":"Neudieringhausen",
    "wof:placetype":"neighbourhood"
},
  "geometry": {"coordinates":[7.5293,50.97985],"type":"Point"}
}