{
  "type": "Feature",
  "properties": {
    "gn:admin1_code":"13",
    "gn:admin2_code":"0.0",
    "gn:admin3_code":"14627.0",
    "gn:admin4_code":"14627050.0",
    "gn:asciiname":"Schweinfurth",
    "gn:country_code":"DE",
    "gn:dem":92,
    "gn:feature_class":"P",
    "gn:feature_code":"PPL",
    "gn:name":"Schweinfurth",
    "gn:population":0,
    "gn:timezone":"Europe/Berlin",
    "iso:country":"DE",
    "name:deu_x_preferred":[
        "Schweinfurth"
    ],
    "name:fra_x_preferred":[
        "Schweinfurth"
    ],
    "wof:name":"Schweinfurth",
    "wof:placetype":"neighbourhood"
},
  "geometry": {"coordinates":[13.39138,51.44714000000001],"type":"Point"}
}