{
  "type": "Feature",
  "properties": {
    "gn:admin1_code":"14",
    "gn:admin2_code":"0.0",
    "gn:admin3_code":"15084.0",
    "gn:admin4_code":"15084550.0",
    "gn:asciiname":"Pettstaedt",
    "gn:country_code":"DE",
    "gn:dem":169,
    "gn:feature_class":"P",
    "gn:feature_code":"PPL",
    "gn:name":"Pettst\u00e4dt",
    "gn:population":0,
    "gn:timezone":"Europe/Berlin",
    "iso:country":"DE",
    "wof:name":"Pettstaedt",
    "wof:placetype":"neighbourhood"
},
  "geometry": {"coordinates":[11.87981,51.23709],"type":"Point"}
}