{
  "type": "Feature",
  "properties": {
    "gn:admin1_code":"7.0",
    "gn:admin2_code":"57.0",
    "gn:admin3_code":"5766.0",
    "gn:admin4_code":"5766044.0",
    "gn:asciiname":"Bentrup",
    "gn:country_code":"DE",
    "gn:dem":104,
    "gn:feature_class":"P",
    "gn:feature_code":"PPL",
    "gn:name":"Bentrup",
    "gn:population":0,
    "gn:timezone":"Europe/Berlin",
    "iso:country":"DE",
    "name:osx_x_preferred":[
        "B\u0117nningthorp"
    ],
    "wof:name":"Bentrup",
    "wof:placetype":"neighbourhood"
},
  "geometry": {"coordinates":[8.94184,52.01828],"type":"Point"}
}