{
  "type": "Feature",
  "properties": {
    "gn:admin1_code":"11.0",
    "gn:admin2_code":"0.0",
    "gn:admin3_code":"12063.0",
    "gn:admin4_code":"12063208.0",
    "gn:asciiname":"Boernicke",
    "gn:country_code":"DE",
    "gn:dem":31,
    "gn:feature_class":"P",
    "gn:feature_code":"PPL",
    "gn:name":"B\u00f6rnicke",
    "gn:population":0,
    "gn:timezone":"Europe/Berlin",
    "iso:country":"DE",
    "name:ceb_x_preferred":[
        "B\u00f6rnicke"
    ],
    "name:deu_x_preferred":[
        "B\u00f6rnicke"
    ],
    "name:fas_x_preferred":[
        "\u0628\u0648\u0631\u0646\u06cc\u06a9"
    ],
    "wof:name":"Boernicke",
    "wof:placetype":"neighbourhood"
},
  "geometry": {"coordinates":[12.93554,52.68596],"type":"Point"}
}