{
  "type": "Feature",
  "properties": {
    "gn:admin1_code":"2.0",
    "gn:admin2_code":"97.0",
    "gn:admin3_code":"9775.0",
    "gn:admin4_code":"9775164.0",
    "gn:asciiname":"Asch",
    "gn:country_code":"DE",
    "gn:dem":496,
    "gn:feature_class":"P",
    "gn:feature_code":"PPL",
    "gn:name":"Asch",
    "gn:population":0,
    "gn:timezone":"Europe/Berlin",
    "iso:country":"DE",
    "name:ceb_x_preferred":[
        "Asch"
    ],
    "name:ces_x_preferred":[
        "Asch"
    ],
    "name:deu_x_preferred":[
        "Asch"
    ],
    "name:fra_x_preferred":[
        "Asch"
    ],
    "name:heb_x_preferred":[
        "\u05d0\u05e9"
    ],
    "name:ita_x_preferred":[
        "Asch"
    ],
    "name:jpn_x_preferred":[
        "\u30a2\u30c3\u30b7\u30e5"
    ],
    "name:nds_x_preferred":[
        "Asch"
    ],
    "name:rus_x_preferred":[
        "\u0410\u0448"
    ],
    "name:swe_x_preferred":[
        "Asch"
    ],
    "name:ukr_x_preferred":[
        "\u0410\u0448"
    ],
    "wof:name":"Asch",
    "wof:placetype":"neighbourhood"
},
  "geometry": {"coordinates":[10.21248,48.29964],"type":"Point"}
}