{
  "type": "Feature",
  "properties": {
    "gn:country":"DE",
    "gn:fcode":"PPL",
    "gn:population":794,
    "iso:country":"DE",
    "name:bak_x_preferred":[
        "\u0412\u0435\u0441\u0442\u0434\u043e\u0440\u0444"
    ],
    "name:bul_x_preferred":[
        "\u0412\u0435\u0441\u0442\u0434\u043e\u0440\u0444"
    ],
    "name:cat_x_preferred":[
        "Westdorf"
    ],
    "name:ceb_x_preferred":[
        "Westdorf"
    ],
    "name:che_x_preferred":[
        "\u0412\u0435\u0441\u0442\u0434\u043e\u0440\u0444"
    ],
    "name:deu_x_preferred":[
        "Westdorf"
    ],
    "name:ell_x_preferred":[
        "\u0392\u03ad\u03c3\u03c4\u03bd\u03c4\u03bf\u03c1\u03c6"
    ],
    "name:eng_x_preferred":[
        "Westdorf"
    ],
    "name:epo_x_preferred":[
        "Westdorf"
    ],
    "name:fas_x_preferred":[
        "\u0648\u0634\u062a\u062f\u0648\u0631\u0641"
    ],
    "name:fra_x_preferred":[
        "Westdorf"
    ],
    "name:gle_x_preferred":[
        "Westdorf"
    ],
    "name:hun_x_preferred":[
        "Westdorf"
    ],
    "name:ita_x_preferred":[
        "Westdorf"
    ],
    "name:kaz_x_preferred":[
        "\u0412\u0435\u0441\u0442\u0434\u043e\u0440\u0444"
    ],
    "name:kir_x_preferred":[
        "\u0412\u0435\u0441\u0442\u0434\u043e\u0440\u0444"
    ],
    "name:mkd_x_preferred":[
        "\u0412\u0435\u0441\u0442\u0434\u043e\u0440\u0444"
    ],
    "name:nld_x_preferred":[
        "Westdorf"
    ],
    "name:nob_x_preferred":[
        "Westdorf"
    ],
    "name:pol_x_preferred":[
        "Westdorf"
    ],
    "name:ron_x_preferred":[
        "Westdorf"
    ],
    "name:rus_x_preferred":[
        "\u0412\u0435\u0441\u0442\u0434\u043e\u0440\u0444"
    ],
    "name:tat_x_preferred":[
        "\u0412\u0435\u0441\u0442\u0434\u043e\u0440\u0444"
    ],
    "name:uzb_x_preferred":[
        "Westdorf"
    ],
    "name:vol_x_preferred":[
        "Westdorf"
    ],
    "qs_pg:aaroncc":"DE",
    "qs_pg:gn_country":"DE",
    "qs_pg:gn_fcode":"PPL",
    "qs_pg:gn_pop":794,
    "qs_pg:name":"Westdorf",
    "qs_pg:name_adm0":"Deutschland",
    "qs_pg:name_adm1":"Sachsen-Anhalt",
    "qs_pg:photos_9k":1,
    "qs_pg:photos_9r":1,
    "qs_pg:photos_all":1,
    "qs_pg:photos_sr":0,
    "qs_pg:pop_sr":2,
    "qs_pg:qs_pg_placetype":"locality",
    "qs_pg:qs_pg_placetype_gp":"Town",
    "qs_pg:woe_adm0":23424829,
    "woe:adm0_id":23424829,
    "woe:name_adm0":"Deutschland",
    "woe:name_adm1":"Sachsen-Anhalt",
    "woe:placetype":"Town",
    "wof:name":"Westdorf",
    "wof:placetype":"neighbourhood",
    "wof:population":794
},
  "geometry": {"coordinates":[11.435,51.73552],"type":"Point"}
}