{
  "type": "Feature",
  "properties": {
    "gn:admin1_code":"11",
    "gn:admin2_code":"0.0",
    "gn:admin3_code":"12069.0",
    "gn:admin4_code":"12069270.0",
    "gn:asciiname":"Kolonie Tieckow",
    "gn:country_code":"DE",
    "gn:dem":29,
    "gn:feature_class":"P",
    "gn:feature_code":"PPL",
    "gn:name":"Kolonie Tieckow",
    "gn:population":0,
    "gn:timezone":"Europe/Berlin",
    "iso:country":"DE",
    "wof:name":"Kolonie Tieckow",
    "wof:placetype":"neighbourhood"
},
  "geometry": {"coordinates":[12.45697,52.45992],"type":"Point"}
}