{
  "type": "Feature",
  "properties": {
    "gn:admin1_code":"2.0",
    "gn:admin2_code":"95.0",
    "gn:admin3_code":"9573.0",
    "gn:admin4_code":"9573114.0",
    "gn:asciiname":"Ballersdorf",
    "gn:country_code":"DE",
    "gn:dem":346,
    "gn:feature_class":"P",
    "gn:feature_code":"PPL",
    "gn:name":"Ballersdorf",
    "gn:population":0,
    "gn:timezone":"Europe/Berlin",
    "iso:country":"DE",
    "name:als_x_preferred":[
        "Ballersdorf"
    ],
    "name:bre_x_preferred":[
        "Ballersdorf"
    ],
    "name:bug_x_preferred":[
        "Ballersdorf"
    ],
    "name:cat_x_preferred":[
        "Ballersdorf"
    ],
    "name:ceb_x_preferred":[
        "Ballersdorf"
    ],
    "name:ces_x_preferred":[
        "Ballersdorf"
    ],
    "name:deu_x_preferred":[
        "Ballersdorf"
    ],
    "name:epo_x_preferred":[
        "Ballersdorf"
    ],
    "name:eus_x_preferred":[
        "Ballersdorf"
    ],
    "name:fas_x_preferred":[
        "\u0628\u0627\u0644\u0631\u0633\u062f\u0648\u0631\u0641"
    ],
    "name:fra_x_preferred":[
        "Ballersdorf"
    ],
    "name:hun_x_preferred":[
        "Ballersdorf"
    ],
    "name:ita_x_preferred":[
        "Ballersdorf"
    ],
    "name:kaz_x_preferred":[
        "\u0411\u0430\u043b\u043b\u0435\u0440\u0441\u0434\u043e\u0440\u0444"
    ],
    "name:lat_x_preferred":[
        "Ballersdorf"
    ],
    "name:mlg_x_preferred":[
        "Ballersdorf"
    ],
    "name:msa_x_preferred":[
        "Ballersdorf"
    ],
    "name:nld_x_preferred":[
        "Ballersdorf"
    ],
    "name:oci_x_preferred":[
        "Ballersdorf"
    ],
    "name:pfl_x_preferred":[
        "Ballersdorf"
    ],
    "name:pms_x_preferred":[
        "Ballersdorf"
    ],
    "name:pol_x_preferred":[
        "Ballersdorf"
    ],
    "name:por_x_preferred":[
        "Ballersdorf"
    ],
    "name:ron_x_preferred":[
        "Ballersdorf"
    ],
    "name:rus_x_preferred":[
        "\u0411\u0430\u043b\u043b\u0435\u0440\u0441\u0434\u043e\u0440\u0444"
    ],
    "name:slk_x_preferred":[
        "Ballersdorf"
    ],
    "name:slv_x_preferred":[
        "Ballersdorf"
    ],
    "name:spa_x_preferred":[
        "Ballersdorf"
    ],
    "name:sqi_x_preferred":[
        "Ballersdorf"
    ],
    "name:srp_x_preferred":[
        "\u0411\u0430\u043b\u0435\u0440\u0441\u0434\u043e\u0440\u0444"
    ],
    "name:swe_x_preferred":[
        "Ballersdorf"
    ],
    "name:ukr_x_preferred":[
        "\u0411\u0430\u043b\u043b\u0435\u0440\u0441\u0434\u043e\u0440\u0444"
    ],
    "name:uzb_x_preferred":[
        "Ballersdorf"
    ],
    "name:vie_x_preferred":[
        "Ballersdorf"
    ],
    "name:vol_x_preferred":[
        "Ballersdorf"
    ],
    "name:war_x_preferred":[
        "Ballersdorf"
    ],
    "name:zho_x_preferred":[
        "\u5df4\u52d2\u65af\u591a\u592b"
    ],
    "wof:name":"Ballersdorf",
    "wof:placetype":"neighbourhood"
},
  "geometry": {"coordinates":[10.79991,49.42714],"type":"Point"}
}