{
  "type": "Feature",
  "properties": {
    "gn:admin1_code":"14",
    "gn:admin2_code":"0.0",
    "gn:admin3_code":"15083.0",
    "gn:admin4_code":"15083390.0",
    "gn:asciiname":"Meseberg",
    "gn:country_code":"DE",
    "gn:dem":52,
    "gn:feature_class":"P",
    "gn:feature_code":"PPL",
    "gn:name":"Meseberg",
    "gn:population":462,
    "gn:timezone":"Europe/Berlin",
    "iso:country":"DE",
    "name:bak_x_preferred":[
        "\u041c\u0435\u0437\u0435\u0431\u0435\u0440\u0433"
    ],
    "name:deu_x_preferred":[
        "Meseberg"
    ],
    "name:epo_x_preferred":[
        "Meseberg"
    ],
    "name:fas_x_preferred":[
        "\u0645\u0632\u0628\u0631\u06af"
    ],
    "name:nld_x_preferred":[
        "Meseberg"
    ],
    "name:ron_x_preferred":[
        "Meseberg"
    ],
    "name:rus_x_preferred":[
        "\u041c\u0435\u0437\u0435\u0431\u0435\u0440\u0433"
    ],
    "name:uzb_x_preferred":[
        "Meseberg"
    ],
    "name:vol_x_preferred":[
        "Meseberg"
    ],
    "wof:name":"Meseberg",
    "wof:placetype":"neighbourhood",
    "wof:population":462
},
  "geometry": {"coordinates":[11.53015,52.27404],"type":"Point"}
}