{
  "type": "Feature",
  "properties": {
    "gn:admin1_code":"13",
    "gn:admin2_code":"0.0",
    "gn:admin3_code":"14730.0",
    "gn:admin4_code":"14730330.0",
    "gn:asciiname":"Liptitz",
    "gn:country_code":"DE",
    "gn:dem":180,
    "gn:feature_class":"P",
    "gn:feature_code":"PPL",
    "gn:name":"Liptitz",
    "gn:population":0,
    "gn:timezone":"Europe/Berlin",
    "iso:country":"DE",
    "wof:name":"Liptitz",
    "wof:placetype":"neighbourhood"
},
  "geometry": {"coordinates":[12.93596,51.25561],"type":"Point"}
}