{
  "type": "Feature",
  "properties": {
    "gn:admin1_code":"2",
    "gn:admin2_code":"93.0",
    "gn:admin3_code":"9375.0",
    "gn:admin4_code":"9375190.0",
    "gn:asciiname":"Hagenau",
    "gn:country_code":"DE",
    "gn:dem":364,
    "gn:feature_class":"P",
    "gn:feature_code":"PPL",
    "gn:name":"Hagenau",
    "gn:population":0,
    "gn:timezone":"Europe/Berlin",
    "iso:country":"DE",
    "wof:name":"Hagenau",
    "wof:placetype":"neighbourhood"
},
  "geometry": {"coordinates":[12.1126,49.15072],"type":"Point"}
}