{
  "type": "Feature",
  "properties": {
    "gn:gn_country":"DE",
    "gn:gn_fcode":"PPLA4",
    "gn:gn_pop":543,
    "gn:population":543,
    "iso:country":"DE",
    "name:bak_x_preferred":[
        "\u0428\u0451\u043d\u0433\u043b\u0430\u0439\u043d\u0430"
    ],
    "name:baq_x_preferred":[
        "Sch\u00f6ngleina"
    ],
    "name:chi_x_preferred":[
        "\u7533\u683c\u83b1\u7eb3"
    ],
    "name:dut_x_preferred":[
        "Sch\u00f6ngleina"
    ],
    "name:eng_x_preferred":[
        "Sch\u00f6ngleina"
    ],
    "name:epo_x_preferred":[
        "Sch\u00f6ngleina"
    ],
    "name:fre_x_preferred":[
        "Sch\u00f6ngleina"
    ],
    "name:ger_x_preferred":[
        "Sch\u00f6ngleina"
    ],
    "name:hun_x_preferred":[
        "Sch\u00f6ngleina"
    ],
    "name:ita_x_preferred":[
        "Sch\u00f6ngleina"
    ],
    "name:kaz_x_preferred":[
        "\u0428\u0451\u043d\u0433\u043b\u0430\u0439\u043d\u0430"
    ],
    "name:kir_x_preferred":[
        "\u0428\u04e9\u043d\u0433\u043b\u0430\u0439\u043d\u0430"
    ],
    "name:mac_x_preferred":[
        "\u0428\u0435\u043d\u0433\u043b\u0430\u0458\u043d\u0430"
    ],
    "name:may_x_preferred":[
        "Sch\u00f6ngleina"
    ],
    "name:per_x_preferred":[
        "\u0634\u0648\u0646\u06af\u0644\u0627\u06cc\u0646\u0627"
    ],
    "name:pol_x_preferred":[
        "Sch\u00f6ngleina"
    ],
    "name:por_x_preferred":[
        "Sch\u00f6ngleina"
    ],
    "name:rum_x_preferred":[
        "Sch\u00f6ngleina"
    ],
    "name:rus_x_preferred":[
        "\u0428\u0451\u043d\u0433\u043b\u0430\u0439\u043d\u0430"
    ],
    "name:srp_x_preferred":[
        "\u0428\u0435\u043d\u0433\u043b\u0430\u0458\u043d\u0430"
    ],
    "name:ukr_x_preferred":[
        "\u0428\u0435\u043d\u0433\u043b\u044f\u0439\u043d\u0430"
    ],
    "name:uzb_x_preferred":[
        "Sch\u00f6ngleina"
    ],
    "name:vie_x_preferred":[
        "Sch\u00f6ngleina"
    ],
    "name:vol_x_preferred":[
        "Sch\u00f6ngleina"
    ],
    "name:war_x_preferred":[
        "Sch\u00f6ngleina"
    ],
    "qs_pg:aaroncc":"DE",
    "qs_pg:gn_country":"DE",
    "qs_pg:gn_fcode":"PPLA4",
    "qs_pg:gn_pop":543,
    "qs_pg:name":"Sch\u00f6ngleina",
    "qs_pg:photos_9r":0,
    "qs_pg:photos_sr":0,
    "qs_pg:pop_sr":2,
    "qs_pg:qs_pg_placetype":"locality",
    "wof:name":"Sch\u00f6ngleina",
    "wof:placetype":"locality",
    "wof:population":543
},
  "geometry": {"coordinates":[11.72379,50.90747],"type":"Point"}
}