{
  "type": "Feature",
  "properties": {
    "gn:admin1_code":"1.0",
    "gn:admin2_code":"83.0",
    "gn:admin3_code":"8337.0",
    "gn:admin4_code":"8337106.0",
    "gn:asciiname":"Blumegg",
    "gn:country_code":"DE",
    "gn:dem":662,
    "gn:feature_class":"P",
    "gn:feature_code":"PPL",
    "gn:name":"Blumegg",
    "gn:population":0,
    "gn:timezone":"Europe/Berlin",
    "iso:country":"DE",
    "wof:name":"Blumegg",
    "wof:placetype":"neighbourhood"
},
  "geometry": {"coordinates":[8.49844,47.80785],"type":"Point"}
}