{
  "type": "Feature",
  "properties": {
    "gn:admin1_code":"2",
    "gn:admin2_code":"93.0",
    "gn:admin3_code":"9372.0",
    "gn:admin4_code":"9372153.0",
    "gn:asciiname":"Obertrubenbach",
    "gn:country_code":"DE",
    "gn:dem":460,
    "gn:feature_class":"P",
    "gn:feature_code":"PPL",
    "gn:name":"Obertr\u00fcbenbach",
    "gn:population":0,
    "gn:timezone":"Europe/Berlin",
    "iso:country":"DE",
    "wof:name":"Obertrubenbach",
    "wof:placetype":"neighbourhood"
},
  "geometry": {"coordinates":[12.55917,49.16042],"type":"Point"}
}