{
  "type": "Feature",
  "properties": {
    "gn:gn_country":"DE",
    "gn:gn_fcode":"PPLA4",
    "gn:gn_pop":662,
    "gn:population":662,
    "iso:country":"DE",
    "name:cat_x_preferred":[
        "Sietow"
    ],
    "name:chi_x_preferred":[
        "\u9521\u6258"
    ],
    "name:dut_x_preferred":[
        "Sietow"
    ],
    "name:eng_x_preferred":[
        "Sietow"
    ],
    "name:epo_x_preferred":[
        "Sietow"
    ],
    "name:fre_x_preferred":[
        "Sietow"
    ],
    "name:ger_x_preferred":[
        "Sietow"
    ],
    "name:hun_x_preferred":[
        "Sietow"
    ],
    "name:ita_x_preferred":[
        "Sietow"
    ],
    "name:kaz_x_preferred":[
        "\u0417\u0438\u0442\u043e\u0432"
    ],
    "name:kir_x_preferred":[
        "\u0417\u0438\u0442\u043e\u0432"
    ],
    "name:mac_x_preferred":[
        "\u0417\u0438\u0442\u043e\u0432"
    ],
    "name:may_x_preferred":[
        "Sietow"
    ],
    "name:oci_x_preferred":[
        "Sietow"
    ],
    "name:per_x_preferred":[
        "\u0633\u06cc\u062a\u0648\u0648"
    ],
    "name:pol_x_preferred":[
        "Sietow"
    ],
    "name:por_x_preferred":[
        "Sietow"
    ],
    "name:rum_x_preferred":[
        "Sietow"
    ],
    "name:rus_x_preferred":[
        "\u0417\u0438\u0442\u043e\u0432"
    ],
    "name:spa_x_preferred":[
        "Sietow"
    ],
    "name:srp_x_preferred":[
        "\u0417\u0438\u0442\u043e\u0432"
    ],
    "name:ukr_x_preferred":[
        "\u0417\u0456\u0442\u043e\u0432"
    ],
    "name:uzb_x_preferred":[
        "Sietow"
    ],
    "name:vie_x_preferred":[
        "Sietow"
    ],
    "name:vol_x_preferred":[
        "Sietow"
    ],
    "name:war_x_preferred":[
        "Sietow"
    ],
    "qs_pg:aaroncc":"DE",
    "qs_pg:gn_country":"DE",
    "qs_pg:gn_fcode":"PPLA4",
    "qs_pg:gn_pop":662,
    "qs_pg:name":"Sietow",
    "qs_pg:photos_9r":0,
    "qs_pg:photos_sr":0,
    "qs_pg:pop_sr":2,
    "qs_pg:qs_pg_placetype":"locality",
    "wof:name":"Sietow",
    "wof:placetype":"locality",
    "wof:population":662
},
  "geometry": {"coordinates":[12.55,53.45],"type":"Point"}
}