{
  "type": "Feature",
  "properties": {
    "gn:admin1_code":"6",
    "gn:admin2_code":"0.0",
    "gn:admin3_code":"3453.0",
    "gn:admin4_code":"3453009.0",
    "gn:asciiname":"Klein Roscharden",
    "gn:country_code":"DE",
    "gn:dem":38,
    "gn:feature_class":"P",
    "gn:feature_code":"PPL",
    "gn:name":"Klein Roscharden",
    "gn:population":0,
    "gn:timezone":"Europe/Berlin",
    "iso:country":"DE",
    "wof:name":"Klein Roscharden",
    "wof:placetype":"neighbourhood"
},
  "geometry": {"coordinates":[7.86087,52.81175],"type":"Point"}
}