{
  "type": "Feature",
  "properties": {
    "iso:country":"DE",
    "wof:name":"Jungferntal",
    "wof:placetype":"neighbourhood"
},
  "geometry": {"coordinates":[7.38093887181872,51.53123230564786],"type":"Point"}
}