{
  "type": "Feature",
  "properties": {
    "gn:admin1_code":"6",
    "gn:admin2_code":"0.0",
    "gn:admin3_code":"3452.0",
    "gn:admin4_code":"3452014.0",
    "gn:asciiname":"Eilsum",
    "gn:country_code":"DE",
    "gn:dem":4,
    "gn:feature_class":"P",
    "gn:feature_code":"PPL",
    "gn:name":"Eilsum",
    "gn:population":0,
    "gn:timezone":"Europe/Berlin",
    "iso:country":"DE",
    "wof:name":"Eilsum",
    "wof:placetype":"neighbourhood"
},
  "geometry": {"coordinates":[7.14139,53.47273000000001],"type":"Point"}
}