{
  "type": "Feature",
  "properties": {
    "gn:admin1_code":"2",
    "gn:admin2_code":"93.0",
    "gn:admin3_code":"9371.0",
    "gn:admin4_code":"9371128.0",
    "gn:asciiname":"Hirschbach",
    "gn:country_code":"DE",
    "gn:dem":448,
    "gn:feature_class":"P",
    "gn:feature_code":"PPLA4",
    "gn:name":"Hirschbach",
    "gn:population":1299,
    "gn:timezone":"Europe/Berlin",
    "iso:country":"DE",
    "wof:name":"Hirschbach",
    "wof:placetype":"locality",
    "wof:population":1299
},
  "geometry": {"coordinates":[11.53333,49.55],"type":"Point"}
}