{
  "type": "Feature",
  "properties": {
    "gn:admin1_code":"1.0",
    "gn:admin2_code":"84.0",
    "gn:admin3_code":"8426.0",
    "gn:admin4_code":"8426073.0",
    "gn:asciiname":"Baltringen",
    "gn:country_code":"DE",
    "gn:dem":516,
    "gn:feature_class":"P",
    "gn:feature_code":"PPL",
    "gn:name":"Baltringen",
    "gn:population":0,
    "gn:timezone":"Europe/Berlin",
    "iso:country":"DE",
    "name:deu_x_preferred":[
        "Baltringen"
    ],
    "wof:name":"Baltringen",
    "wof:placetype":"neighbourhood"
},
  "geometry": {"coordinates":[9.86416,48.17309],"type":"Point"}
}