{
  "type": "Feature",
  "properties": {
    "gn:admin1_code":"13",
    "gn:admin2_code":"0.0",
    "gn:admin3_code":"14627.0",
    "gn:admin4_code":"14627100.0",
    "gn:asciiname":"Neurobschuetz",
    "gn:country_code":"DE",
    "gn:dem":176,
    "gn:feature_class":"P",
    "gn:feature_code":"PPL",
    "gn:name":"Neurobsch\u00fctz",
    "gn:population":0,
    "gn:timezone":"Europe/Berlin",
    "iso:country":"DE",
    "wof:name":"Neurobschuetz",
    "wof:placetype":"neighbourhood"
},
  "geometry": {"coordinates":[13.42712,51.12581],"type":"Point"}
}