{
  "type": "Feature",
  "properties": {
    "gn:admin1_code":"2.0",
    "gn:admin2_code":"097",
    "gn:admin3_code":"9780.0",
    "gn:admin4_code":"9780134.0",
    "gn:asciiname":"Wielenberg",
    "gn:country_code":"DE",
    "gn:dem":851,
    "gn:feature_class":"P",
    "gn:feature_code":"PPL",
    "gn:name":"Wielenberg",
    "gn:population":0,
    "gn:timezone":"Europe/Berlin",
    "iso:country":"DE",
    "wof:name":"Wielenberg",
    "wof:placetype":"neighbourhood"
},
  "geometry": {"coordinates":[10.24653,47.49573],"type":"Point"}
}