{
  "type": "Feature",
  "properties": {
    "iso:country":"DE",
    "wof:name":"Schoppershof",
    "wof:placetype":"neighbourhood"
},
  "geometry": {"coordinates":[11.10198784440019,49.46674520486082],"type":"Point"}
}