{
  "type": "Feature",
  "properties": {
    "gn:admin1_code":"6.0",
    "gn:admin2_code":"00",
    "gn:admin3_code":"3459.0",
    "gn:admin4_code":"3459024.0",
    "gn:asciiname":"Wesperhoefen",
    "gn:country_code":"DE",
    "gn:dem":80,
    "gn:feature_class":"P",
    "gn:feature_code":"PPL",
    "gn:name":"Wesperh\u00f6fen",
    "gn:population":0,
    "gn:timezone":"Europe/Berlin",
    "iso:country":"DE",
    "wof:name":"Wesperhoefen",
    "wof:placetype":"neighbourhood"
},
  "geometry": {"coordinates":[8.26323,52.20312],"type":"Point"}
}