{
  "type": "Feature",
  "properties": {
    "gn:admin1_code":"5",
    "gn:admin2_code":"66.0",
    "gn:admin3_code":"6632.0",
    "gn:admin4_code":"6632008.0",
    "gn:asciiname":"Holzheim",
    "gn:country_code":"DE",
    "gn:dem":324,
    "gn:feature_class":"P",
    "gn:feature_code":"PPL",
    "gn:name":"Holzheim",
    "gn:population":0,
    "gn:timezone":"Europe/Berlin",
    "iso:country":"DE",
    "name:bar_x_preferred":[
        "Holzheim"
    ],
    "name:ceb_x_preferred":[
        "Holzheim"
    ],
    "name:dan_x_preferred":[
        "Holzheim"
    ],
    "name:deu_x_preferred":[
        "Holzheim"
    ],
    "name:epo_x_preferred":[
        "Holzheim"
    ],
    "name:fra_x_preferred":[
        "Holzheim"
    ],
    "name:hye_x_preferred":[
        "\u0540\u0578\u056c\u0581\u0570\u0561\u0575\u0574"
    ],
    "name:ita_x_preferred":[
        "Holzheim"
    ],
    "name:jpn_x_preferred":[
        "\u30db\u30eb\u30c4\u30cf\u30a4\u30e0"
    ],
    "name:lmo_x_preferred":[
        "Holzheim"
    ],
    "name:nld_x_preferred":[
        "Holzheim"
    ],
    "name:pol_x_preferred":[
        "Holzheim"
    ],
    "name:ron_x_preferred":[
        "Holzheim"
    ],
    "name:rus_x_preferred":[
        "\u0425\u043e\u043b\u044c\u0446\u0445\u0430\u0439\u043c"
    ],
    "name:spa_x_preferred":[
        "Holzheim"
    ],
    "name:srp_x_preferred":[
        "\u0425\u043e\u043b\u0446\u0445\u0430\u0458\u043c"
    ],
    "name:swe_x_preferred":[
        "Holzheim"
    ],
    "name:vie_x_preferred":[
        "Holzheim"
    ],
    "name:vol_x_preferred":[
        "Holzheim"
    ],
    "wof:name":"Holzheim",
    "wof:placetype":"neighbourhood"
},
  "geometry": {"coordinates":[9.66965,50.78275],"type":"Point"}
}