{
  "type": "Feature",
  "properties": {
    "gn:admin1_code":"5",
    "gn:admin2_code":"66.0",
    "gn:admin3_code":"6632.0",
    "gn:admin4_code":"6632008.0",
    "gn:asciiname":"Holzheim",
    "gn:country_code":"DE",
    "gn:dem":324,
    "gn:feature_class":"P",
    "gn:feature_code":"PPL",
    "gn:name":"Holzheim",
    "gn:population":0,
    "gn:timezone":"Europe/Berlin",
    "iso:country":"DE",
    "wof:name":"Holzheim",
    "wof:placetype":"neighbourhood"
},
  "geometry": {"coordinates":[9.66965,50.78275],"type":"Point"}
}