{
  "type": "Feature",
  "properties": {
    "gn:admin1_code":"5",
    "gn:admin2_code":"66.0",
    "gn:admin3_code":"6635.0",
    "gn:admin4_code":"6635004.0",
    "gn:asciiname":"Frohnhausen",
    "gn:country_code":"DE",
    "gn:dem":333,
    "gn:feature_class":"P",
    "gn:feature_code":"PPL",
    "gn:name":"Frohnhausen",
    "gn:population":0,
    "gn:timezone":"Europe/Berlin",
    "iso:country":"DE",
    "name:und_x_variant":[
        "Frohnhausen bei Battenberg",
        "Frohnhausen"
    ],
    "wof:name":"Frohnhausen",
    "wof:placetype":"neighbourhood"
},
  "geometry": {"coordinates":[8.62244,50.96537],"type":"Point"}
}