{
  "type": "Feature",
  "properties": {
    "gn:admin1_code":"6",
    "gn:admin2_code":"0.0",
    "gn:admin3_code":"3357.0",
    "gn:admin4_code":"3357016.0",
    "gn:asciiname":"Neu Kuhstedtermoor",
    "gn:country_code":"DE",
    "gn:dem":6,
    "gn:feature_class":"P",
    "gn:feature_code":"PPL",
    "gn:name":"Neu Kuhstedtermoor",
    "gn:population":0,
    "gn:timezone":"Europe/Berlin",
    "iso:country":"DE",
    "wof:name":"Neu Kuhstedtermoor",
    "wof:placetype":"neighbourhood"
},
  "geometry": {"coordinates":[8.9476,53.34719000000001],"type":"Point"}
}