{
  "type": "Feature",
  "properties": {
    "gn:admin1_code":"1.0",
    "gn:admin2_code":"83.0",
    "gn:admin3_code":"8326.0",
    "gn:admin4_code":"8326012.0",
    "gn:asciiname":"Allmendshofen",
    "gn:country_code":"DE",
    "gn:dem":683,
    "gn:feature_class":"P",
    "gn:feature_code":"PPL",
    "gn:name":"Allmendshofen",
    "gn:population":0,
    "gn:timezone":"Europe/Berlin",
    "iso:country":"DE",
    "wof:name":"Allmendshofen",
    "wof:placetype":"neighbourhood"
},
  "geometry": {"coordinates":[8.50101,47.94188],"type":"Point"}
}