{
  "type": "Feature",
  "properties": {
    "gn:admin1_code":"2.0",
    "gn:admin2_code":"91.0",
    "gn:admin3_code":"9174.0",
    "gn:admin4_code":"9174111.0",
    "gn:asciiname":"Schielach",
    "gn:country_code":"DE",
    "gn:dem":507,
    "gn:feature_class":"P",
    "gn:feature_code":"PPL",
    "gn:name":"Schielach",
    "gn:population":0,
    "gn:timezone":"Europe/Berlin",
    "iso:country":"DE",
    "wof:name":"Schielach",
    "wof:placetype":"neighbourhood"
},
  "geometry": {"coordinates":[11.23571,48.41502],"type":"Point"}
}