{
  "type": "Feature",
  "properties": {
    "gn:admin1_code":"1",
    "gn:admin2_code":"84.0",
    "gn:admin3_code":"8426.0",
    "gn:admin4_code":"8426014.0",
    "gn:asciiname":"Dunzenhausen",
    "gn:country_code":"DE",
    "gn:dem":579,
    "gn:feature_class":"P",
    "gn:feature_code":"PPL",
    "gn:name":"Dunzenhausen",
    "gn:population":0,
    "gn:timezone":"Europe/Berlin",
    "iso:country":"DE",
    "wof:name":"Dunzenhausen",
    "wof:placetype":"locality"
},
  "geometry": {"coordinates":[9.68333,48.01667],"type":"Point"}
}