{
  "type": "Feature",
  "properties": {
    "gn:admin1_code":"6",
    "gn:admin2_code":"0.0",
    "gn:admin3_code":"3452.0",
    "gn:admin4_code":"3452024.0",
    "gn:asciiname":"Neu Siegelsum",
    "gn:country_code":"DE",
    "gn:dem":1,
    "gn:feature_class":"P",
    "gn:feature_code":"PPL",
    "gn:name":"Neu Siegelsum",
    "gn:population":0,
    "gn:timezone":"Europe/Berlin",
    "iso:country":"DE",
    "wof:name":"Neu Siegelsum",
    "wof:placetype":"neighbourhood"
},
  "geometry": {"coordinates":[7.31474,53.51432],"type":"Point"}
}