{
  "type": "Feature",
  "properties": {
    "gn:gn_country":"DE",
    "gn:gn_fcode":"PPL",
    "gn:gn_pop":0,
    "iso:country":"DE",
    "qs_pg:aaroncc":"DE",
    "qs_pg:gn_country":"DE",
    "qs_pg:gn_fcode":"PPL",
    "qs_pg:gn_pop":0,
    "qs_pg:name":"Baur",
    "qs_pg:name_adm0":"Deutschland",
    "qs_pg:name_adm1":"Nordrhein-Westfalen",
    "qs_pg:photos":53,
    "qs_pg:photos_1k":11,
    "qs_pg:photos_9k":1,
    "qs_pg:photos_9r":2,
    "qs_pg:photos_all":53,
    "qs_pg:photos_sr":2,
    "qs_pg:pop_sr":0,
    "qs_pg:qs_pg_placetype":"neighbourhood",
    "qs_pg:qs_pg_placetype_gp":"Suburb",
    "qs_pg:woe_adm0":23424829,
    "woe:adm0_id":23424829,
    "woe:name_adm0":"Deutschland",
    "woe:name_adm1":"Nordrhein-Westfalen",
    "woe:placetype":"Suburb",
    "wof:name":"Baur",
    "wof:placetype":"neighbourhood"
},
  "geometry": {"coordinates":[7.18304,51.23704],"type":"Point"}
}