{
  "type": "Feature",
  "properties": {
    "gn:admin1_code":"2.0",
    "gn:admin2_code":"91.0",
    "gn:admin3_code":"9175.0",
    "gn:admin4_code":"9175115.0",
    "gn:asciiname":"Asslkofen",
    "gn:country_code":"DE",
    "gn:dem":565,
    "gn:feature_class":"P",
    "gn:feature_code":"PPL",
    "gn:name":"A\u00dflkofen",
    "gn:population":0,
    "gn:timezone":"Europe/Berlin",
    "iso:country":"DE",
    "wof:name":"Asslkofen",
    "wof:placetype":"neighbourhood"
},
  "geometry": {"coordinates":[11.95347,48.07054],"type":"Point"}
}