{
  "type": "Feature",
  "properties": {
    "gn:admin1_code":"2.0",
    "gn:admin2_code":"091",
    "gn:admin3_code":"9183.0",
    "gn:admin4_code":"9183129.0",
    "gn:asciiname":"Wiesbach",
    "gn:country_code":"DE",
    "gn:dem":451,
    "gn:feature_class":"P",
    "gn:feature_code":"PPL",
    "gn:name":"Wiesbach",
    "gn:population":0,
    "gn:timezone":"Europe/Berlin",
    "iso:country":"DE",
    "name:ceb_x_preferred":[
        "Wiesbach"
    ],
    "name:deu_x_preferred":[
        "Wiesbach"
    ],
    "name:epo_x_preferred":[
        "Wiesbach"
    ],
    "name:ita_x_preferred":[
        "Wiesbach"
    ],
    "name:pol_x_preferred":[
        "Wiesbach"
    ],
    "name:rus_x_preferred":[
        "\u0412\u0438\u0441\u0431\u0430\u0445"
    ],
    "name:swe_x_preferred":[
        "Wiesbach"
    ],
    "wof:name":"Wiesbach",
    "wof:placetype":"neighbourhood"
},
  "geometry": {"coordinates":[12.50115,48.40676],"type":"Point"}
}