{
  "type": "Feature",
  "properties": {
    "gn:admin1_code":"2",
    "gn:admin2_code":"94.0",
    "gn:admin3_code":"9478.0",
    "gn:admin4_code":"9478139.0",
    "gn:asciiname":"Lahm",
    "gn:country_code":"DE",
    "gn:dem":543,
    "gn:feature_class":"P",
    "gn:feature_code":"PPL",
    "gn:name":"Lahm",
    "gn:population":0,
    "gn:timezone":"Europe/Berlin",
    "iso:country":"DE",
    "wof:name":"Lahm",
    "wof:placetype":"neighbourhood"
},
  "geometry": {"coordinates":[11.13434,50.08058],"type":"Point"}
}