{
  "type": "Feature",
  "properties": {
    "gn:admin1_code":"2",
    "gn:admin2_code":"94.0",
    "gn:admin3_code":"9479.0",
    "gn:admin4_code":"9479169.0",
    "gn:asciiname":"Gopfersgrun",
    "gn:country_code":"DE",
    "gn:dem":555,
    "gn:feature_class":"P",
    "gn:feature_code":"PPL",
    "gn:name":"G\u00f6pfersgr\u00fcn",
    "gn:population":0,
    "gn:timezone":"Europe/Berlin",
    "iso:country":"DE",
    "wof:name":"Gopfersgrun",
    "wof:placetype":"neighbourhood"
},
  "geometry": {"coordinates":[12.06192,50.05703],"type":"Point"}
}