{
  "type": "Feature",
  "properties": {
    "gn:admin1_code":"10",
    "gn:admin2_code":"0.0",
    "gn:admin3_code":"1051.0",
    "gn:admin4_code":"1051117.0",
    "gn:asciiname":"Schuettingdeich",
    "gn:country_code":"DE",
    "gn:dem":-1,
    "gn:feature_class":"P",
    "gn:feature_code":"PPLL",
    "gn:name":"Sch\u00fcttingdeich",
    "gn:population":0,
    "gn:timezone":"Europe/Berlin",
    "iso:country":"DE",
    "wof:name":"Schuettingdeich",
    "wof:placetype":"neighbourhood"
},
  "geometry": {"coordinates":[9.34866,54.26908],"type":"Point"}
}