{
  "type": "Feature",
  "properties": {
    "gn:admin1_code":"8",
    "gn:admin2_code":"0.0",
    "gn:admin3_code":"7138.0",
    "gn:admin4_code":"7138044.0",
    "gn:asciiname":"Prangenberg",
    "gn:country_code":"DE",
    "gn:dem":269,
    "gn:feature_class":"P",
    "gn:feature_code":"PPL",
    "gn:name":"Prangenberg",
    "gn:population":0,
    "gn:timezone":"Europe/Berlin",
    "iso:country":"DE",
    "wof:name":"Prangenberg",
    "wof:placetype":"neighbourhood"
},
  "geometry": {"coordinates":[7.39695,50.63801],"type":"Point"}
}