{
  "type": "Feature",
  "properties": {
    "gn:admin1_code":"8",
    "gn:admin2_code":"0.0",
    "gn:admin3_code":"7339.0",
    "gn:admin4_code":"7339005.0",
    "gn:asciiname":"Dromersheim",
    "gn:country_code":"DE",
    "gn:dem":144,
    "gn:feature_class":"P",
    "gn:feature_code":"PPL",
    "gn:name":"Dromersheim",
    "gn:population":0,
    "gn:timezone":"Europe/Berlin",
    "iso:country":"DE",
    "wof:name":"Dromersheim",
    "wof:placetype":"neighbourhood"
},
  "geometry": {"coordinates":[7.9643,49.92395],"type":"Point"}
}