{
  "type": "Feature",
  "properties": {
    "gn:admin1_code":"13",
    "gn:admin2_code":"0.0",
    "gn:admin3_code":"14522.0",
    "gn:admin4_code":"14522210.0",
    "gn:asciiname":"Rothenfurth",
    "gn:country_code":"DE",
    "gn:dem":297,
    "gn:feature_class":"P",
    "gn:feature_code":"PPL",
    "gn:name":"Rothenfurth",
    "gn:population":0,
    "gn:timezone":"Europe/Berlin",
    "iso:country":"DE",
    "name:und_x_variant":[
        "Gro\u00dfschirma-Rothenfurth",
        "Rothenfurth"
    ],
    "wof:name":"Rothenfurth",
    "wof:placetype":"neighbourhood"
},
  "geometry": {"coordinates":[13.31596,50.96548],"type":"Point"}
}