{
  "type": "Feature",
  "properties": {
    "gn:admin1_code":"2",
    "gn:admin2_code":"92.0",
    "gn:admin3_code":"9273.0",
    "gn:admin4_code":"9273178.0",
    "gn:asciiname":"Grossschwaiba",
    "gn:country_code":"DE",
    "gn:dem":496,
    "gn:feature_class":"P",
    "gn:feature_code":"PPL",
    "gn:name":"Gro\u00dfschwaiba",
    "gn:population":0,
    "gn:timezone":"Europe/Berlin",
    "iso:country":"DE",
    "name:und_x_variant":[
        "Gro\u00dfschweiba",
        "Gro\u00dfschwaiba"
    ],
    "wof:name":"Grossschwaiba",
    "wof:placetype":"neighbourhood"
},
  "geometry": {"coordinates":[11.87161,48.58994000000001],"type":"Point"}
}