{
  "type": "Feature",
  "properties": {
    "gn:admin1_code":"7",
    "gn:admin2_code":"57.0",
    "gn:admin3_code":"5754.0",
    "gn:admin4_code":"5754048.0",
    "gn:asciiname":"Hesselteich",
    "gn:country_code":"DE",
    "gn:dem":74,
    "gn:feature_class":"P",
    "gn:feature_code":"PPL",
    "gn:name":"Hesselteich",
    "gn:population":0,
    "gn:timezone":"Europe/Berlin",
    "iso:country":"DE",
    "wof:name":"Hesselteich",
    "wof:placetype":"neighbourhood"
},
  "geometry": {"coordinates":[8.23793,52.02842],"type":"Point"}
}