{
  "type": "Feature",
  "properties": {
    "gn:admin1_code":"9",
    "gn:admin2_code":"0.0",
    "gn:admin3_code":"10041.0",
    "gn:admin4_code":"10041100.0",
    "gn:asciiname":"Guedingen",
    "gn:country_code":"DE",
    "gn:dem":202,
    "gn:feature_class":"P",
    "gn:feature_code":"PPL",
    "gn:name":"G\u00fcdingen",
    "gn:population":0,
    "gn:timezone":"Europe/Berlin",
    "iso:country":"DE",
    "wof:name":"Guedingen",
    "wof:placetype":"neighbourhood"
},
  "geometry": {"coordinates":[7.03574,49.20241],"type":"Point"}
}