{
  "type": "Feature",
  "properties": {
    "gn:gn_country":"DE",
    "gn:gn_fcode":"PPLA4",
    "gn:gn_pop":282,
    "gn:population":282,
    "iso:country":"DE",
    "name:baq_x_preferred":[
        "Wiesemscheid"
    ],
    "name:chi_x_preferred":[
        "\u7ef4\u585e\u59c6\u6c99\u4f0a\u5fb7"
    ],
    "name:dut_x_preferred":[
        "Wiesemscheid"
    ],
    "name:eng_x_preferred":[
        "Wiesemscheid"
    ],
    "name:epo_x_preferred":[
        "Wiesemscheid"
    ],
    "name:fre_x_preferred":[
        "Wiesemscheid"
    ],
    "name:ger_x_preferred":[
        "Wiesemscheid"
    ],
    "name:hun_x_preferred":[
        "Wiesemscheid"
    ],
    "name:ita_x_preferred":[
        "Wiesemscheid"
    ],
    "name:jpn_x_preferred":[
        "\u30f4\u30a3\u30fc\u30bc\u30e0\u30b7\u30e3\u30a4\u30c8"
    ],
    "name:kaz_x_preferred":[
        "\u0412\u0438\u0437\u0435\u043c\u0448\u0430\u0439\u0434"
    ],
    "name:kir_x_preferred":[
        "\u0412\u0438\u0437\u0435\u043c\u0448\u0430\u0439\u0434"
    ],
    "name:may_x_preferred":[
        "Wiesemscheid"
    ],
    "name:per_x_preferred":[
        "\u0648\u06cc\u0632\u0645\u0634\u0627\u06cc\u062f"
    ],
    "name:pol_x_preferred":[
        "Wiesemscheid"
    ],
    "name:por_x_preferred":[
        "Wiesemscheid"
    ],
    "name:rum_x_preferred":[
        "Wiesemscheid"
    ],
    "name:rus_x_preferred":[
        "\u0412\u0438\u0437\u0435\u043c\u0448\u0430\u0439\u0434"
    ],
    "name:srp_x_preferred":[
        "\u0412\u0438\u0437\u0435\u043c\u0448\u0430\u0458\u0434"
    ],
    "name:ukr_x_preferred":[
        "\u0412\u0456\u0437\u0435\u043c\u0448\u0430\u0439\u0434"
    ],
    "name:uzb_x_preferred":[
        "Wiesemscheid"
    ],
    "name:vie_x_preferred":[
        "Wiesemscheid"
    ],
    "name:vol_x_preferred":[
        "Wiesemscheid"
    ],
    "name:war_x_preferred":[
        "Wiesemscheid"
    ],
    "qs_pg:aaroncc":"DE",
    "qs_pg:gn_country":"DE",
    "qs_pg:gn_fcode":"PPLA4",
    "qs_pg:gn_pop":282,
    "qs_pg:name":"Wiesemscheid",
    "qs_pg:photos_9r":0,
    "qs_pg:photos_sr":0,
    "qs_pg:pop_sr":2,
    "qs_pg:qs_pg_placetype":"locality",
    "wof:name":"Wiesemscheid",
    "wof:placetype":"locality",
    "wof:population":282
},
  "geometry": {"coordinates":[6.88333,50.33333],"type":"Point"}
}