{
  "type": "Feature",
  "properties": {
    "gn:admin1_code":"2",
    "gn:admin2_code":"91.0",
    "gn:admin3_code":"9189.0",
    "gn:admin4_code":"9189154.0",
    "gn:asciiname":"Horzing",
    "gn:country_code":"DE",
    "gn:dem":549,
    "gn:feature_class":"P",
    "gn:feature_code":"PPL",
    "gn:name":"H\u00f6rzing",
    "gn:population":0,
    "gn:timezone":"Europe/Berlin",
    "iso:country":"DE",
    "wof:name":"Horzing",
    "wof:placetype":"neighbourhood"
},
  "geometry": {"coordinates":[12.59668,47.94602],"type":"Point"}
}