{
  "type": "Feature",
  "properties": {
    "gn:admin1_code":"2",
    "gn:admin2_code":"93.0",
    "gn:admin3_code":"9376.0",
    "gn:admin4_code":"9376119.0",
    "gn:asciiname":"Pistlwies",
    "gn:country_code":"DE",
    "gn:dem":478,
    "gn:feature_class":"P",
    "gn:feature_code":"PPL",
    "gn:name":"Pistlwies",
    "gn:population":0,
    "gn:timezone":"Europe/Berlin",
    "iso:country":"DE",
    "wof:name":"Pistlwies",
    "wof:placetype":"neighbourhood"
},
  "geometry": {"coordinates":[12.04139,49.26183],"type":"Point"}
}