{
  "type": "Feature",
  "properties": {
    "gn:admin1_code":"2",
    "gn:admin2_code":"91.0",
    "gn:admin3_code":"9190.0",
    "gn:admin4_code":"9190120.0",
    "gn:asciiname":"Gandershofen",
    "gn:country_code":"DE",
    "gn:dem":607,
    "gn:feature_class":"P",
    "gn:feature_code":"PPL",
    "gn:name":"Gandershofen",
    "gn:population":0,
    "gn:timezone":"Europe/Berlin",
    "iso:country":"DE",
    "wof:name":"Gandershofen",
    "wof:placetype":"neighbourhood"
},
  "geometry": {"coordinates":[11.19795,47.80003],"type":"Point"}
}