{
  "type": "Feature",
  "properties": {
    "gn:admin1_code":"2",
    "gn:admin2_code":"91.0",
    "gn:admin3_code":"9182.0",
    "gn:admin4_code":"9182133.0",
    "gn:asciiname":"Mitterdarching",
    "gn:country_code":"DE",
    "gn:dem":666,
    "gn:feature_class":"P",
    "gn:feature_code":"PPL",
    "gn:name":"Mitterdarching",
    "gn:population":0,
    "gn:timezone":"Europe/Berlin",
    "iso:country":"DE",
    "wof:name":"Mitterdarching",
    "wof:placetype":"neighbourhood"
},
  "geometry": {"coordinates":[11.77151,47.86855],"type":"Point"}
}