{
  "type": "Feature",
  "properties": {
    "gn:admin1_code":"13",
    "gn:admin2_code":"0.0",
    "gn:admin3_code":"14524.0",
    "gn:admin4_code":"14524020.0",
    "gn:asciiname":"Langenberg",
    "gn:country_code":"DE",
    "gn:dem":353,
    "gn:feature_class":"P",
    "gn:feature_code":"PPL",
    "gn:name":"Langenberg",
    "gn:population":0,
    "gn:timezone":"Europe/Berlin",
    "iso:country":"DE",
    "name:ceb_x_preferred":[
        "Langenberg"
    ],
    "name:deu_x_preferred":[
        "Langenberg"
    ],
    "name:eus_x_preferred":[
        "Langenberg"
    ],
    "name:nld_x_preferred":[
        "Langenberg"
    ],
    "name:pol_x_preferred":[
        "Langenberg"
    ],
    "name:rus_x_preferred":[
        "\u041b\u0430\u043d\u0433\u0435\u043d\u0431\u0435\u0440\u0433"
    ],
    "name:swe_x_preferred":[
        "Langenberg"
    ],
    "name:und_x_variant":[
        "Langenberg-Falken"
    ],
    "wof:name":"Langenberg",
    "wof:placetype":"neighbourhood"
},
  "geometry": {"coordinates":[12.70671,50.83328],"type":"Point"}
}