{
  "type": "Feature",
  "properties": {
    "gn:admin1_code":"2",
    "gn:admin2_code":"92.0",
    "gn:admin3_code":"9275.0",
    "gn:admin4_code":"9275125.0",
    "gn:asciiname":"Hotzenham",
    "gn:country_code":"DE",
    "gn:dem":397,
    "gn:feature_class":"P",
    "gn:feature_code":"PPL",
    "gn:name":"H\u00f6tzenham",
    "gn:population":0,
    "gn:timezone":"Europe/Berlin",
    "iso:country":"DE",
    "wof:name":"Hotzenham",
    "wof:placetype":"neighbourhood"
},
  "geometry": {"coordinates":[13.1496,48.48699000000001],"type":"Point"}
}