{
  "type": "Feature",
  "properties": {
    "gn:admin1_code":"6",
    "gn:admin2_code":"0.0",
    "gn:admin3_code":"3361.0",
    "gn:admin4_code":"3361013.0",
    "gn:asciiname":"Neu Wulmstorf",
    "gn:country_code":"DE",
    "gn:dem":11,
    "gn:feature_class":"P",
    "gn:feature_code":"PPL",
    "gn:name":"Neu Wulmstorf",
    "gn:population":0,
    "gn:timezone":"Europe/Berlin",
    "iso:country":"DE",
    "wof:name":"Neu Wulmstorf",
    "wof:placetype":"neighbourhood"
},
  "geometry": {"coordinates":[9.06955,52.92209],"type":"Point"}
}