{
  "type": "Feature",
  "properties": {
    "gn:admin1_code":"6",
    "gn:admin2_code":"0.0",
    "gn:admin3_code":"3361.0",
    "gn:admin4_code":"3361013.0",
    "gn:asciiname":"Neu Wulmstorf",
    "gn:country_code":"DE",
    "gn:dem":11,
    "gn:feature_class":"P",
    "gn:feature_code":"PPL",
    "gn:name":"Neu Wulmstorf",
    "gn:population":0,
    "gn:timezone":"Europe/Berlin",
    "iso:country":"DE",
    "name:ceb_x_preferred":[
        "Neu Wulmstorf"
    ],
    "name:deu_x_preferred":[
        "Neu Wulmstorf"
    ],
    "name:epo_x_preferred":[
        "Neu Wulmstorf"
    ],
    "name:est_x_preferred":[
        "Neu Wulmstorf"
    ],
    "name:eus_x_preferred":[
        "Neu Wulmstorf"
    ],
    "name:fas_x_preferred":[
        "\u0646\u0648\u06cc \u0648\u0648\u0644\u0645\u0634\u062a\u0648\u0631\u0641"
    ],
    "name:fra_x_preferred":[
        "Neu Wulmstorf"
    ],
    "name:hun_x_preferred":[
        "Neu Wulmstorf"
    ],
    "name:ita_x_preferred":[
        "Neu Wulmstorf"
    ],
    "name:kaz_x_preferred":[
        "\u041d\u043e\u0439-\u0412\u0443\u043b\u044c\u043c\u0441\u0442\u043e\u0440\u0444"
    ],
    "name:kir_x_preferred":[
        "\u041d\u043e\u0439-\u0412\u0443\u043b\u044c\u043c\u0441\u0442\u043e\u0440\u0444"
    ],
    "name:lat_x_preferred":[
        "Neu Wulmstorf"
    ],
    "name:msa_x_preferred":[
        "Neu Wulmstorf"
    ],
    "name:nds_x_preferred":[
        "Gemeen Vosshusen"
    ],
    "name:nld_x_preferred":[
        "Neu Wulmstorf"
    ],
    "name:pol_x_preferred":[
        "Neu Wulmstorf"
    ],
    "name:por_x_preferred":[
        "Neu Wulmstorf"
    ],
    "name:ron_x_preferred":[
        "Neu Wulmstorf"
    ],
    "name:rus_x_preferred":[
        "\u041d\u043e\u0439-\u0412\u0443\u043b\u044c\u043c\u0441\u0442\u043e\u0440\u0444"
    ],
    "name:spa_x_preferred":[
        "Neu Wulmstorf"
    ],
    "name:srp_x_preferred":[
        "\u041d\u043e\u0458 \u0412\u0443\u043b\u043c\u0441\u0442\u043e\u0440\u0444"
    ],
    "name:ukr_x_preferred":[
        "\u041d\u043e\u0439-\u0412\u0443\u043b\u044c\u043c\u0441\u0442\u043e\u0440\u0444"
    ],
    "name:uzb_x_preferred":[
        "Neu Wulmstorf"
    ],
    "name:vie_x_preferred":[
        "Neu Wulmstorf"
    ],
    "name:vol_x_preferred":[
        "Neu Wulmstorf"
    ],
    "name:war_x_preferred":[
        "Neu Wulmstorf"
    ],
    "name:zho_x_preferred":[
        "\u65b0\u6b66\u5c14\u59c6\u65af\u6258\u592b"
    ],
    "wof:name":"Neu Wulmstorf",
    "wof:placetype":"neighbourhood"
},
  "geometry": {"coordinates":[9.06955,52.92209],"type":"Point"}
}