{
  "type": "Feature",
  "properties": {
    "gn:admin1_code":"6",
    "gn:admin2_code":"0.0",
    "gn:admin3_code":"3254.0",
    "gn:admin4_code":"3254028.0",
    "gn:asciiname":"Goedringen",
    "gn:country_code":"DE",
    "gn:dem":85,
    "gn:feature_class":"P",
    "gn:feature_code":"PPL",
    "gn:name":"G\u00f6dringen",
    "gn:population":0,
    "gn:timezone":"Europe/Berlin",
    "iso:country":"DE",
    "wof:name":"Goedringen",
    "wof:placetype":"neighbourhood"
},
  "geometry": {"coordinates":[9.89662,52.2421],"type":"Point"}
}