{
  "type": "Feature",
  "properties": {
    "gn:admin1_code":"15",
    "gn:admin2_code":"0.0",
    "gn:admin3_code":"16066.0",
    "gn:admin4_code":"16066038.0",
    "gn:asciiname":"Charlottenhaus",
    "gn:country_code":"DE",
    "gn:dem":731,
    "gn:feature_class":"P",
    "gn:feature_code":"PPL",
    "gn:name":"Charlottenhaus",
    "gn:population":0,
    "gn:timezone":"Europe/Berlin",
    "iso:country":"DE",
    "wof:name":"Charlottenhaus",
    "wof:placetype":"neighbourhood"
},
  "geometry": {"coordinates":[10.47521,50.62732000000001],"type":"Point"}
}