{
  "type": "Feature",
  "properties": {
    "gn:country":"DE",
    "gn:fcode":"PPL",
    "gn:population":0,
    "iso:country":"DE",
    "name:azb_x_preferred":[
        "\u0648\u0627\u06cc\u0633\u0646\u200c\u0627\u0634\u062a\u0627\u06cc\u0646"
    ],
    "name:ceb_x_preferred":[
        "Wei\u00dfenstein"
    ],
    "name:deu_x_preferred":[
        "Wei\u00dfenstein"
    ],
    "name:epo_x_preferred":[
        "Wei\u00dfenstein"
    ],
    "name:fas_x_preferred":[
        "\u0648\u0627\u06cc\u0633\u0646\u200c\u0627\u0634\u062a\u0627\u06cc\u0646"
    ],
    "name:fra_x_preferred":[
        "Wei\u00dfenstein"
    ],
    "name:fur_x_preferred":[
        "Wei\u00dfenstein"
    ],
    "name:hun_x_preferred":[
        "Wei\u00dfenstein"
    ],
    "name:ita_x_preferred":[
        "Wei\u00dfenstein"
    ],
    "name:kaz_x_preferred":[
        "\u0412\u0430\u0439\u0441\u0441\u0435\u043d\u0448\u0442\u0430\u0439\u043d"
    ],
    "name:nld_x_preferred":[
        "Wei\u00dfenstein"
    ],
    "name:pol_x_preferred":[
        "Wei\u00dfenstein"
    ],
    "name:por_x_preferred":[
        "Wei\u00dfenstein"
    ],
    "name:rus_x_preferred":[
        "\u0412\u0430\u0439\u0441\u0435\u043d\u0448\u0442\u0430\u0439\u043d"
    ],
    "name:slk_x_preferred":[
        "Wei\u00dfenstein"
    ],
    "name:spa_x_preferred":[
        "Wei\u00dfenstein"
    ],
    "name:swe_x_preferred":[
        "Wei\u00dfenstein"
    ],
    "name:uzb_x_preferred":[
        "Wei\u00dfenstein"
    ],
    "name:vie_x_preferred":[
        "Wei\u00dfenstein"
    ],
    "name:vol_x_preferred":[
        "Wei\u00dfenstein"
    ],
    "name:war_x_preferred":[
        "Wei\u00dfenstein"
    ],
    "name:zho_x_preferred":[
        "\u9b4f\u68ee\u65bd\u6cf0\u56e0"
    ],
    "qs_pg:aaroncc":"DE",
    "qs_pg:gn_country":"DE",
    "qs_pg:gn_fcode":"PPL",
    "qs_pg:gn_pop":0,
    "qs_pg:name":"Wei\u00dfenstein",
    "qs_pg:name_adm0":"Deutschland",
    "qs_pg:name_adm1":"Bayern",
    "qs_pg:photos":130,
    "qs_pg:photos_1k":26,
    "qs_pg:photos_9k":1,
    "qs_pg:photos_9r":3,
    "qs_pg:photos_all":130,
    "qs_pg:photos_sr":3,
    "qs_pg:pop_sr":0,
    "qs_pg:qs_pg_placetype":"locality",
    "qs_pg:qs_pg_placetype_gp":"Town",
    "qs_pg:woe_adm0":23424829,
    "woe:adm0_id":23424829,
    "woe:name_adm0":"Deutschland",
    "woe:name_adm1":"Bayern",
    "woe:placetype":"Town",
    "wof:name":"Wei\u00dfenstein",
    "wof:placetype":"neighbourhood"
},
  "geometry": {"coordinates":[13.14351,48.95027],"type":"Point"}
}