{
  "type": "Feature",
  "properties": {
    "gn:admin1_code":"6.0",
    "gn:admin2_code":"00",
    "gn:admin3_code":"3241.0",
    "gn:admin4_code":"3241016.0",
    "gn:asciiname":"Wirringen",
    "gn:country_code":"DE",
    "gn:dem":81,
    "gn:feature_class":"P",
    "gn:feature_code":"PPL",
    "gn:name":"Wirringen",
    "gn:population":0,
    "gn:timezone":"Europe/Berlin",
    "iso:country":"DE",
    "wof:name":"Wirringen",
    "wof:placetype":"neighbourhood"
},
  "geometry": {"coordinates":[9.91688,52.29704],"type":"Point"}
}