{
  "type": "Feature",
  "properties": {
    "gn:admin1_code":"2",
    "gn:admin2_code":"93.0",
    "gn:admin3_code":"9371.0",
    "gn:admin4_code":"9371148.0",
    "gn:asciiname":"Harschhof",
    "gn:country_code":"DE",
    "gn:dem":360,
    "gn:feature_class":"P",
    "gn:feature_code":"PPL",
    "gn:name":"Harschhof",
    "gn:population":0,
    "gn:timezone":"Europe/Berlin",
    "iso:country":"DE",
    "wof:name":"Harschhof",
    "wof:placetype":"neighbourhood"
},
  "geometry": {"coordinates":[11.93507,49.27421],"type":"Point"}
}