{
  "type": "Feature",
  "properties": {
    "gn:admin1_code":"1.0",
    "gn:admin2_code":"82.0",
    "gn:admin3_code":"8215.0",
    "gn:admin4_code":"8215007.0",
    "gn:asciiname":"Bauerbach",
    "gn:country_code":"DE",
    "gn:dem":199,
    "gn:feature_class":"P",
    "gn:feature_code":"PPL",
    "gn:name":"Bauerbach",
    "gn:population":0,
    "gn:timezone":"Europe/Berlin",
    "iso:country":"DE",
    "name:bak_x_preferred":[
        "\u0411\u0430\u0443\u0435\u0440\u0431\u0430\u0445"
    ],
    "name:deu_x_preferred":[
        "Bauerbach"
    ],
    "name:epo_x_preferred":[
        "Bauerbach"
    ],
    "name:ita_x_preferred":[
        "Bauerbach"
    ],
    "name:kaz_x_preferred":[
        "\u0411\u0430\u0443\u0435\u0440\u0431\u0430\u0445"
    ],
    "name:kir_x_preferred":[
        "\u0411\u0430\u0443\u0435\u0440\u0431\u0430\u0445"
    ],
    "name:mkd_x_preferred":[
        "\u0411\u0430\u0443\u0435\u0440\u0431\u0430\u0445"
    ],
    "name:nld_x_preferred":[
        "Bauerbach"
    ],
    "name:pol_x_preferred":[
        "Bauerbach"
    ],
    "name:por_x_preferred":[
        "Bauerbach"
    ],
    "name:ron_x_preferred":[
        "Bauerbach"
    ],
    "name:rus_x_preferred":[
        "\u0411\u0430\u0443\u044d\u0440\u0431\u0430\u0445"
    ],
    "name:srp_x_preferred":[
        "\u0411\u0430\u0443\u0435\u0440\u0431\u0430\u0445"
    ],
    "name:uzb_x_preferred":[
        "Bauerbach"
    ],
    "name:vie_x_preferred":[
        "Bauerbach"
    ],
    "name:vol_x_preferred":[
        "Bauerbach"
    ],
    "name:war_x_preferred":[
        "Bauerbach"
    ],
    "wof:name":"Bauerbach",
    "wof:placetype":"neighbourhood"
},
  "geometry": {"coordinates":[8.7426,49.07294],"type":"Point"}
}