{
  "type": "Feature",
  "properties": {
    "gn:admin1_code":"15",
    "gn:admin2_code":"0.0",
    "gn:admin3_code":"16071.0",
    "gn:admin4_code":"16071008.0",
    "gn:asciiname":"Lengefeld",
    "gn:country_code":"DE",
    "gn:dem":434,
    "gn:feature_class":"P",
    "gn:feature_code":"PPL",
    "gn:name":"Lengefeld",
    "gn:population":0,
    "gn:timezone":"Europe/Berlin",
    "iso:country":"DE",
    "name:ara_x_preferred":[
        "\u0644\u0646\u063a\u0647\u0641\u0644\u062f"
    ],
    "name:azb_x_preferred":[
        "\u0644\u0646\u0642\u0641\u0644\u062f"
    ],
    "name:bak_x_preferred":[
        "\u041b\u0435\u043d\u0433\u0435\u0444\u0435\u043b\u044c\u0434"
    ],
    "name:deu_x_preferred":[
        "Lengefeld"
    ],
    "name:epo_x_preferred":[
        "Lengefeld"
    ],
    "name:est_x_preferred":[
        "Lengefeld"
    ],
    "name:fas_x_preferred":[
        "\u0644\u0646\u06af\u0641\u0644\u062f"
    ],
    "name:fra_x_preferred":[
        "Lengefeld"
    ],
    "name:ita_x_preferred":[
        "Lengefeld"
    ],
    "name:lav_x_preferred":[
        "Lengefelde"
    ],
    "name:mkd_x_preferred":[
        "\u041b\u0435\u043d\u0433\u0435\u0444\u0435\u043b\u0434"
    ],
    "name:msa_x_preferred":[
        "Lengefeld"
    ],
    "name:nld_x_preferred":[
        "Lengefeld"
    ],
    "name:nor_x_preferred":[
        "Lengefeld"
    ],
    "name:pol_x_preferred":[
        "Lengefeld"
    ],
    "name:por_x_preferred":[
        "Lengefeld"
    ],
    "name:ron_x_preferred":[
        "Lengefeld"
    ],
    "name:rus_x_preferred":[
        "\u041b\u0435\u043d\u0433\u0435\u0444\u0435\u043b\u044c\u0434"
    ],
    "name:srp_x_preferred":[
        "\u041b\u0435\u043d\u0433\u0435\u0444\u0435\u043b\u0434"
    ],
    "name:uzb_x_preferred":[
        "Lengefeld"
    ],
    "name:vol_x_preferred":[
        "Lengefeld"
    ],
    "name:war_x_preferred":[
        "Lengefeld"
    ],
    "name:zho_x_preferred":[
        "\u4f26\u683c\u8d39\u5c14\u5fb7"
    ],
    "wof:name":"Lengefeld",
    "wof:placetype":"neighbourhood"
},
  "geometry": {"coordinates":[11.34304,50.82871],"type":"Point"}
}