{
  "type": "Feature",
  "properties": {
    "gn:admin1_code":"11",
    "gn:admin2_code":"0.0",
    "gn:admin3_code":"12070.0",
    "gn:admin4_code":"12070125.0",
    "gn:asciiname":"Steinberg",
    "gn:country_code":"DE",
    "gn:dem":46,
    "gn:feature_class":"P",
    "gn:feature_code":"PPL",
    "gn:name":"Steinberg",
    "gn:population":0,
    "gn:timezone":"Europe/Berlin",
    "iso:country":"DE",
    "name:hun_x_preferred":[
        "Steinberg"
    ],
    "name:jpn_x_preferred":[
        "\u30b9\u30bf\u30a4\u30f3\u30d0\u30fc\u30b0"
    ],
    "name:kor_x_preferred":[
        "\uc2a4\ud14c\uc778\ubc84\uadf8"
    ],
    "name:nld_x_preferred":[
        "Steinberg"
    ],
    "name:por_x_preferred":[
        "Steinberg"
    ],
    "name:spa_x_preferred":[
        "Steinberg"
    ],
    "name:swe_x_preferred":[
        "Steinberg"
    ],
    "name:tha_x_preferred":[
        "\u0e2a\u0e44\u0e15\u0e19\u0e4c\u0e40\u0e1a\u0e34\u0e23\u0e4c\u0e01"
    ],
    "name:tur_x_preferred":[
        "Steinberg"
    ],
    "name:ukr_x_preferred":[
        "Steinberg"
    ],
    "name:zho_x_preferred":[
        "Steinberg"
    ],
    "wof:name":"Steinberg",
    "wof:placetype":"neighbourhood"
},
  "geometry": {"coordinates":[11.89106,53.15154],"type":"Point"}
}