{
  "type": "Feature",
  "properties": {
    "gn:admin1_code":"15",
    "gn:admin2_code":"0.0",
    "gn:admin3_code":"16066.0",
    "gn:admin4_code":"16066086.0",
    "gn:asciiname":"Maienluft",
    "gn:country_code":"DE",
    "gn:dem":298,
    "gn:feature_class":"P",
    "gn:feature_code":"PPL",
    "gn:name":"Maienluft",
    "gn:population":0,
    "gn:timezone":"Europe/Berlin",
    "iso:country":"DE",
    "wof:name":"Maienluft",
    "wof:placetype":"neighbourhood"
},
  "geometry": {"coordinates":[10.36667,50.66667],"type":"Point"}
}