{
  "type": "Feature",
  "properties": {
    "gn:admin1_code":"6",
    "gn:admin2_code":"0.0",
    "gn:admin3_code":"3355.0",
    "gn:admin4_code":"3355013.0",
    "gn:asciiname":"Dumstorf",
    "gn:country_code":"DE",
    "gn:dem":51,
    "gn:feature_class":"P",
    "gn:feature_code":"PPL",
    "gn:name":"Dumstorf",
    "gn:population":0,
    "gn:timezone":"Europe/Berlin",
    "iso:country":"DE",
    "wof:name":"Dumstorf",
    "wof:placetype":"neighbourhood"
},
  "geometry": {"coordinates":[10.69501,53.17796],"type":"Point"}
}