{
  "type": "Feature",
  "properties": {
    "gn:admin1_code":"13",
    "gn:admin2_code":"0.0",
    "gn:admin3_code":"14625.0",
    "gn:admin4_code":"14625060.0",
    "gn:asciiname":"Neraditz",
    "gn:country_code":"DE",
    "gn:dem":211,
    "gn:feature_class":"P",
    "gn:feature_code":"PPL",
    "gn:name":"Neraditz",
    "gn:population":0,
    "gn:timezone":"Europe/Berlin",
    "iso:country":"DE",
    "name:hsb_x_preferred":[
        "Njeradecy"
    ],
    "wof:name":"Neraditz",
    "wof:placetype":"neighbourhood"
},
  "geometry": {"coordinates":[14.23538,51.20662],"type":"Point"}
}