{
  "type": "Feature",
  "properties": {
    "gn:admin1_code":"2",
    "gn:admin2_code":"93.0",
    "gn:admin3_code":"9377.0",
    "gn:admin4_code":"9377146.0",
    "gn:asciiname":"Leichau",
    "gn:country_code":"DE",
    "gn:dem":523,
    "gn:feature_class":"P",
    "gn:feature_code":"PPL",
    "gn:name":"Leichau",
    "gn:population":0,
    "gn:timezone":"Europe/Berlin",
    "iso:country":"DE",
    "wof:name":"Leichau",
    "wof:placetype":"neighbourhood"
},
  "geometry": {"coordinates":[12.27034,49.81897],"type":"Point"}
}