{
  "type": "Feature",
  "properties": {
    "gn:admin1_code":"12",
    "gn:admin2_code":"0.0",
    "gn:admin3_code":"13072.0",
    "gn:admin4_code":"13072063.0",
    "gn:asciiname":"Neu Zierhagen",
    "gn:country_code":"DE",
    "gn:dem":81,
    "gn:feature_class":"P",
    "gn:feature_code":"PPL",
    "gn:name":"Neu Zierhagen",
    "gn:population":0,
    "gn:timezone":"Europe/Berlin",
    "iso:country":"DE",
    "name:und_x_variant":[
        "Kniep",
        "Neu Zierhagen"
    ],
    "wof:name":"Neu Zierhagen",
    "wof:placetype":"neighbourhood"
},
  "geometry": {"coordinates":[12.36646,53.82542],"type":"Point"}
}