{
  "type": "Feature",
  "properties": {
    "gn:admin1_code":"12",
    "gn:admin2_code":"0.0",
    "gn:admin3_code":"13072.0",
    "gn:admin4_code":"13072049.0",
    "gn:asciiname":"Klenz",
    "gn:country_code":"DE",
    "gn:dem":37,
    "gn:feature_class":"P",
    "gn:feature_code":"PPL",
    "gn:name":"Klenz",
    "gn:population":0,
    "gn:timezone":"Europe/Berlin",
    "iso:country":"DE",
    "wof:name":"Klenz",
    "wof:placetype":"neighbourhood"
},
  "geometry": {"coordinates":[12.64431,53.86195],"type":"Point"}
}