{
  "type": "Feature",
  "properties": {
    "gn:admin1_code":"14",
    "gn:admin2_code":"0.0",
    "gn:admin3_code":"15083.0",
    "gn:admin4_code":"15083035.0",
    "gn:asciiname":"UEplingen",
    "gn:country_code":"DE",
    "gn:dem":159,
    "gn:feature_class":"P",
    "gn:feature_code":"PPL",
    "gn:name":"\u00dcplingen",
    "gn:population":0,
    "gn:timezone":"Europe/Berlin",
    "iso:country":"DE",
    "wof:name":"UEplingen",
    "wof:placetype":"neighbourhood"
},
  "geometry": {"coordinates":[11.13757,52.11842],"type":"Point"}
}