{
  "type": "Feature",
  "properties": {
    "gn:admin1_code":"7",
    "gn:admin2_code":"59.0",
    "gn:admin3_code":"5978.0",
    "gn:admin4_code":"5978040.0",
    "gn:asciiname":"Holthausen",
    "gn:country_code":"DE",
    "gn:dem":70,
    "gn:feature_class":"P",
    "gn:feature_code":"PPLL",
    "gn:name":"Holthausen",
    "gn:population":0,
    "gn:timezone":"Europe/Berlin",
    "iso:country":"DE",
    "name:deu_x_preferred":[
        "Holthausen"
    ],
    "name:nld_x_preferred":[
        "Holthausen"
    ],
    "name:pol_x_preferred":[
        "Holthausen"
    ],
    "wof:name":"Holthausen",
    "wof:placetype":"neighbourhood"
},
  "geometry": {"coordinates":[7.63454,51.68235],"type":"Point"}
}