{
  "type": "Feature",
  "properties": {
    "gn:country":"DE",
    "gn:fcode":"PPL",
    "gn:population":0,
    "iso:country":"DE",
    "name:ceb_x_preferred":[
        "Basse"
    ],
    "name:deu_x_preferred":[
        "Basse"
    ],
    "name:fra_x_preferred":[
        "Basse"
    ],
    "name:pol_x_preferred":[
        "Basse"
    ],
    "name:srp_x_preferred":[
        "Basse"
    ],
    "name:wln_x_preferred":[
        "Basse"
    ],
    "qs_pg:aaroncc":"DE",
    "qs_pg:gn_country":"DE",
    "qs_pg:gn_fcode":"PPL",
    "qs_pg:gn_pop":0,
    "qs_pg:name":"Basse",
    "qs_pg:name_adm0":"Deutschland",
    "qs_pg:name_adm1":"Mecklenburg-Vorpommern",
    "qs_pg:photos_9r":0,
    "qs_pg:photos_sr":0,
    "qs_pg:pop_sr":0,
    "qs_pg:qs_pg_placetype":"locality",
    "qs_pg:qs_pg_placetype_gp":"Town",
    "qs_pg:woe_adm0":23424829,
    "woe:adm0_id":23424829,
    "woe:name_adm0":"Deutschland",
    "woe:name_adm1":"Mecklenburg-Vorpommern",
    "woe:placetype":"Town",
    "wof:name":"Basse",
    "wof:placetype":"neighbourhood"
},
  "geometry": {"coordinates":[12.57428,53.99263],"type":"Point"}
}