{
  "type": "Feature",
  "properties": {
    "gn:admin1_code":"14",
    "gn:admin2_code":"0.0",
    "gn:admin3_code":"15088.0",
    "gn:admin4_code":"15088205.0",
    "gn:asciiname":"Thalschuetz",
    "gn:country_code":"DE",
    "gn:dem":106,
    "gn:feature_class":"P",
    "gn:feature_code":"PPL",
    "gn:name":"Thalsch\u00fctz",
    "gn:population":0,
    "gn:timezone":"Europe/Berlin",
    "iso:country":"DE",
    "wof:name":"Thalschuetz",
    "wof:placetype":"neighbourhood"
},
  "geometry": {"coordinates":[12.12868,51.29608],"type":"Point"}
}