{
  "type": "Feature",
  "properties": {
    "gn:admin1_code":"5",
    "gn:admin2_code":"64.0",
    "gn:admin3_code":"6432.0",
    "gn:admin4_code":"6432007.0",
    "gn:asciiname":"Messbach",
    "gn:country_code":"DE",
    "gn:dem":309,
    "gn:feature_class":"P",
    "gn:feature_code":"PPL",
    "gn:name":"Me\u00dfbach",
    "gn:population":0,
    "gn:timezone":"Europe/Berlin",
    "iso:country":"DE",
    "wof:name":"Messbach",
    "wof:placetype":"neighbourhood"
},
  "geometry": {"coordinates":[8.80893,49.74875],"type":"Point"}
}