{
  "type": "Feature",
  "properties": {
    "gn:admin1_code":"6",
    "gn:admin2_code":"0.0",
    "gn:admin3_code":"3357.0",
    "gn:admin4_code":"3357013.0",
    "gn:asciiname":"Nindorf",
    "gn:country_code":"DE",
    "gn:dem":35,
    "gn:feature_class":"P",
    "gn:feature_code":"PPL",
    "gn:name":"Nindorf",
    "gn:population":0,
    "gn:timezone":"Europe/Berlin",
    "iso:country":"DE",
    "name:dan_x_preferred":[
        "Nindorf"
    ],
    "name:deu_x_preferred":[
        "Nindorf"
    ],
    "name:epo_x_preferred":[
        "Nindorf"
    ],
    "name:eus_x_preferred":[
        "Nindorf"
    ],
    "name:fas_x_preferred":[
        "\u0646\u06cc\u0646\u062f\u0648\u0631\u0641"
    ],
    "name:fra_x_preferred":[
        "Nindorf"
    ],
    "name:hun_x_preferred":[
        "Nindorf"
    ],
    "name:ind_x_preferred":[
        "Nindorf"
    ],
    "name:ita_x_preferred":[
        "Nindorf"
    ],
    "name:kaz_x_preferred":[
        "\u041d\u0438\u044d\u043d\u0434\u043e\u0440\u0444"
    ],
    "name:kir_x_preferred":[
        "\u041d\u0438\u044d\u043d\u0434\u043e\u0440\u0444"
    ],
    "name:mkd_x_preferred":[
        "\u041d\u0438\u043d\u0434\u043e\u0440\u0444"
    ],
    "name:msa_x_preferred":[
        "Nindorf"
    ],
    "name:nld_x_preferred":[
        "Nindorf"
    ],
    "name:nor_x_preferred":[
        "Nindorf"
    ],
    "name:pol_x_preferred":[
        "Nindorf"
    ],
    "name:por_x_preferred":[
        "Nindorf"
    ],
    "name:ron_x_preferred":[
        "Nindorf"
    ],
    "name:rus_x_preferred":[
        "\u041d\u0438\u043d\u0434\u043e\u0440\u0444"
    ],
    "name:spa_x_preferred":[
        "Nindorf"
    ],
    "name:srp_x_preferred":[
        "\u041d\u0438\u043d\u0434\u043e\u0440\u0444"
    ],
    "name:tur_x_preferred":[
        "Nindorf"
    ],
    "name:ukr_x_preferred":[
        "\u041d\u0456\u043d\u0434\u043e\u0440\u0444"
    ],
    "name:uzb_x_preferred":[
        "Nindorf"
    ],
    "name:vie_x_preferred":[
        "Nindorf"
    ],
    "name:vol_x_preferred":[
        "Nindorf"
    ],
    "name:war_x_preferred":[
        "Nindorf"
    ],
    "name:zho_x_preferred":[
        "\u5b81\u591a\u592b"
    ],
    "wof:name":"Nindorf",
    "wof:placetype":"neighbourhood"
},
  "geometry": {"coordinates":[9.40865,53.26939],"type":"Point"}
}