{
  "type": "Feature",
  "properties": {
    "gn:admin1_code":"2",
    "gn:admin2_code":"93.0",
    "gn:admin3_code":"9376.0",
    "gn:admin4_code":"9376150.0",
    "gn:asciiname":"Schwarzberg",
    "gn:country_code":"DE",
    "gn:dem":451,
    "gn:feature_class":"P",
    "gn:feature_code":"PPL",
    "gn:name":"Schwarzberg",
    "gn:population":0,
    "gn:timezone":"Europe/Berlin",
    "iso:country":"DE",
    "name:ceb_x_preferred":[
        "Schwarzberg"
    ],
    "name:deu_x_preferred":[
        "Schwarzberg"
    ],
    "name:swe_x_preferred":[
        "Schwarzberg"
    ],
    "wof:name":"Schwarzberg",
    "wof:placetype":"neighbourhood"
},
  "geometry": {"coordinates":[12.21284,49.5833],"type":"Point"}
}