{
  "type": "Feature",
  "properties": {
    "gn:admin1_code":"1",
    "gn:admin2_code":"81.0",
    "gn:admin3_code":"8117.0",
    "gn:admin4_code":"8117010.0",
    "gn:asciiname":"Treffelhausen",
    "gn:country_code":"DE",
    "gn:dem":614,
    "gn:feature_class":"P",
    "gn:feature_code":"PPL",
    "gn:name":"Treffelhausen",
    "gn:population":0,
    "gn:timezone":"Europe/Berlin",
    "iso:country":"DE",
    "wof:name":"Treffelhausen",
    "wof:placetype":"locality"
},
  "geometry": {"coordinates":[9.8919,48.69124],"type":"Point"}
}