{
  "type": "Feature",
  "properties": {
    "gn:admin1_code":"13",
    "gn:admin2_code":"0.0",
    "gn:admin3_code":"14625.0",
    "gn:admin4_code":"14625150.0",
    "gn:asciiname":"Passditz",
    "gn:country_code":"DE",
    "gn:dem":211,
    "gn:feature_class":"P",
    "gn:feature_code":"PPL",
    "gn:name":"Pa\u00dfditz",
    "gn:population":0,
    "gn:timezone":"Europe/Berlin",
    "iso:country":"DE",
    "name:hsb_x_preferred":[
        "Pozdecy"
    ],
    "name:und_x_variant":[
        "Pa\u00dfditz"
    ],
    "wof:name":"Passditz",
    "wof:placetype":"neighbourhood"
},
  "geometry": {"coordinates":[14.27337,51.21605],"type":"Point"}
}