{
  "type": "Feature",
  "properties": {
    "gn:admin1_code":"6",
    "gn:admin2_code":"0.0",
    "gn:admin3_code":"3352.0",
    "gn:admin4_code":"3352002.0",
    "gn:asciiname":"Dornsode",
    "gn:country_code":"DE",
    "gn:dem":8,
    "gn:feature_class":"P",
    "gn:feature_code":"PPL",
    "gn:name":"Dornsode",
    "gn:population":0,
    "gn:timezone":"Europe/Berlin",
    "iso:country":"DE",
    "wof:name":"Dornsode",
    "wof:placetype":"neighbourhood"
},
  "geometry": {"coordinates":[9.03731,53.56756],"type":"Point"}
}