{
  "type": "Feature",
  "properties": {
    "gn:admin1_code":"12",
    "gn:admin2_code":"0.0",
    "gn:admin3_code":"13075.0",
    "gn:admin4_code":"13075027.0",
    "gn:asciiname":"Dersekow Hof",
    "gn:country_code":"DE",
    "gn:dem":31,
    "gn:feature_class":"P",
    "gn:feature_code":"PPL",
    "gn:name":"Dersekow Hof",
    "gn:population":0,
    "gn:timezone":"Europe/Berlin",
    "iso:country":"DE",
    "wof:name":"Dersekow Hof",
    "wof:placetype":"neighbourhood"
},
  "geometry": {"coordinates":[13.27595,54.04431999999999],"type":"Point"}
}