{
  "type": "Feature",
  "properties": {
    "gn:admin1_code":"6",
    "gn:admin2_code":"0.0",
    "gn:admin3_code":"3452.0",
    "gn:admin4_code":"3452012.0",
    "gn:asciiname":"Huellenerfehn",
    "gn:country_code":"DE",
    "gn:dem":-1,
    "gn:feature_class":"P",
    "gn:feature_code":"PPLL",
    "gn:name":"H\u00fcllenerfehn",
    "gn:population":0,
    "gn:timezone":"Europe/Berlin",
    "iso:country":"DE",
    "wof:name":"Huellenerfehn",
    "wof:placetype":"neighbourhood"
},
  "geometry": {"coordinates":[7.46307,53.38571],"type":"Point"}
}