{
  "type": "Feature",
  "properties": {
    "gn:country":"DE",
    "gn:fcode":"PPL",
    "gn:population":0,
    "iso:country":"DE",
    "name:arg_x_preferred":[
        "Sora"
    ],
    "name:bos_x_preferred":[
        "Sora"
    ],
    "name:cat_x_preferred":[
        "Sora"
    ],
    "name:ceb_x_preferred":[
        "Sora"
    ],
    "name:deu_x_preferred":[
        "Sora"
    ],
    "name:eus_x_preferred":[
        "Sora"
    ],
    "name:fin_x_preferred":[
        "Sora"
    ],
    "name:fra_x_preferred":[
        "Sora"
    ],
    "name:hun_x_preferred":[
        "Sora"
    ],
    "name:ita_x_preferred":[
        "Sora"
    ],
    "name:kor_x_preferred":[
        "\uc18c\ub77c"
    ],
    "name:kur_x_preferred":[
        "Sora"
    ],
    "name:lat_x_preferred":[
        "Sora"
    ],
    "name:nld_x_preferred":[
        "Sora"
    ],
    "name:por_x_preferred":[
        "Sora"
    ],
    "name:ron_x_preferred":[
        "Sora"
    ],
    "name:rus_x_preferred":[
        "\u0421\u043e\u0440\u0430"
    ],
    "name:slv_x_preferred":[
        "Sora"
    ],
    "name:spa_x_preferred":[
        "Sora"
    ],
    "name:srp_x_preferred":[
        "Sora"
    ],
    "name:swe_x_preferred":[
        "Sora"
    ],
    "name:war_x_preferred":[
        "Sora"
    ],
    "name:zho_x_preferred":[
        "Sora"
    ],
    "qs_pg:aaroncc":"DE",
    "qs_pg:gn_country":"DE",
    "qs_pg:gn_fcode":"PPL",
    "qs_pg:gn_pop":0,
    "qs_pg:name":"Sora",
    "qs_pg:name_adm0":"Deutschland",
    "qs_pg:name_adm1":"Sachsen",
    "qs_pg:photos_9r":0,
    "qs_pg:photos_sr":0,
    "qs_pg:pop_sr":0,
    "qs_pg:qs_pg_placetype":"locality",
    "qs_pg:qs_pg_placetype_gp":"Town",
    "qs_pg:woe_adm0":23424829,
    "woe:adm0_id":23424829,
    "woe:name_adm0":"Deutschland",
    "woe:name_adm1":"Sachsen",
    "woe:placetype":"Town",
    "wof:name":"Sora",
    "wof:placetype":"neighbourhood"
},
  "geometry": {"coordinates":[13.50181,51.07823],"type":"Point"}
}