{
  "type": "Feature",
  "properties": {
    "gn:admin1_code":"12",
    "gn:admin2_code":"0.0",
    "gn:admin3_code":"13073.0",
    "gn:admin4_code":"13073070.0",
    "gn:asciiname":"Dumgenevitz",
    "gn:country_code":"DE",
    "gn:dem":34,
    "gn:feature_class":"P",
    "gn:feature_code":"PPL",
    "gn:name":"Dumgenevitz",
    "gn:population":0,
    "gn:timezone":"Europe/Berlin",
    "iso:country":"DE",
    "wof:name":"Dumgenevitz",
    "wof:placetype":"neighbourhood"
},
  "geometry": {"coordinates":[13.38856,54.34521],"type":"Point"}
}