{
  "type": "Feature",
  "properties": {
    "gn:admin1_code":"5.0",
    "gn:admin2_code":"66.0",
    "gn:admin3_code":"6631.0",
    "gn:admin4_code":"6631010.0",
    "gn:asciiname":"Altenfeld",
    "gn:country_code":"DE",
    "gn:dem":406,
    "gn:feature_class":"P",
    "gn:feature_code":"PPL",
    "gn:name":"Altenfeld",
    "gn:population":0,
    "gn:timezone":"Europe/Berlin",
    "iso:country":"DE",
    "name:bak_x_preferred":[
        "\u0410\u043b\u044c\u0442\u0435\u043d\u0444\u0435\u043b\u044c\u0434"
    ],
    "name:ceb_x_preferred":[
        "Altenfeld"
    ],
    "name:deu_x_preferred":[
        "Altenfeld"
    ],
    "name:epo_x_preferred":[
        "Altenfeld"
    ],
    "name:eus_x_preferred":[
        "Altenfeld"
    ],
    "name:fas_x_preferred":[
        "\u0627\u0644\u062a\u0646\u0641\u06cc\u0644\u062f"
    ],
    "name:fra_x_preferred":[
        "Altenfeld"
    ],
    "name:hun_x_preferred":[
        "Altenfeld"
    ],
    "name:ita_x_preferred":[
        "Altenfeld"
    ],
    "name:kaz_x_preferred":[
        "\u0410\u043b\u044c\u0442\u0435\u043d\u0444\u0435\u043b\u044c\u0434"
    ],
    "name:kir_x_preferred":[
        "\u0410\u043b\u044c\u0442\u0435\u043d\u0444\u0435\u043b\u044c\u0434"
    ],
    "name:mkd_x_preferred":[
        "\u0410\u043b\u0442\u0435\u043d\u0444\u0435\u043b\u0434"
    ],
    "name:msa_x_preferred":[
        "Altenfeld"
    ],
    "name:nld_x_preferred":[
        "Altenfeld"
    ],
    "name:pol_x_preferred":[
        "Altenfeld"
    ],
    "name:por_x_preferred":[
        "Altenfeld"
    ],
    "name:ron_x_preferred":[
        "Altenfeld"
    ],
    "name:rus_x_preferred":[
        "\u0410\u043b\u044c\u0442\u0435\u043d\u0444\u0435\u043b\u044c\u0434"
    ],
    "name:spa_x_preferred":[
        "Altenfeld"
    ],
    "name:srp_x_preferred":[
        "\u0410\u043b\u0442\u0435\u043d\u0444\u0435\u043b\u0434"
    ],
    "name:ukr_x_preferred":[
        "\u0410\u043b\u044c\u0442\u0435\u043d\u0444\u0435\u043b\u044c\u0434"
    ],
    "name:uzb_x_preferred":[
        "Altenfeld"
    ],
    "name:vie_x_preferred":[
        "Altenfeld"
    ],
    "name:vol_x_preferred":[
        "Altenfeld"
    ],
    "name:war_x_preferred":[
        "Altenfeld"
    ],
    "name:zho_x_preferred":[
        "\u963f\u5c14\u6ed5\u8d39\u5c14\u5fb7"
    ],
    "wof:name":"Altenfeld",
    "wof:placetype":"neighbourhood"
},
  "geometry": {"coordinates":[9.84706,50.45233],"type":"Point"}
}