{
  "type": "Feature",
  "properties": {
    "gn:admin1_code":"5",
    "gn:admin2_code":"64.0",
    "gn:admin3_code":"6440.0",
    "gn:admin4_code":"6440005.0",
    "gn:asciiname":"Kirch Goens",
    "gn:cc2":"DE",
    "gn:country_code":"DE",
    "gn:dem":238,
    "gn:feature_class":"P",
    "gn:feature_code":"PPL",
    "gn:name":"Kirch G\u00f6ns",
    "gn:population":0,
    "gn:timezone":"Europe/Berlin",
    "iso:country":"DE",
    "name:und_x_variant":[
        "Kirschgoen"
    ],
    "wof:name":"Kirch Goens",
    "wof:placetype":"neighbourhood"
},
  "geometry": {"coordinates":[8.65285,50.47133],"type":"Point"}
}