{
  "type": "Feature",
  "properties": {
    "gn:admin1_code":"13",
    "gn:admin2_code":"0.0",
    "gn:admin3_code":"14625.0",
    "gn:admin4_code":"14625640.0",
    "gn:asciiname":"Keula",
    "gn:country_code":"DE",
    "gn:dem":124,
    "gn:feature_class":"P",
    "gn:feature_code":"PPL",
    "gn:name":"Keula",
    "gn:population":0,
    "gn:timezone":"Europe/Berlin",
    "iso:country":"DE",
    "name:hsb_x_preferred":[
        "Kulowc"
    ],
    "wof:name":"Keula",
    "wof:placetype":"neighbourhood"
},
  "geometry": {"coordinates":[14.24326,51.39128],"type":"Point"}
}