{
  "type": "Feature",
  "properties": {
    "gn:admin1_code":"2",
    "gn:admin2_code":"95.0",
    "gn:admin3_code":"9571.0",
    "gn:admin4_code":"9571170.0",
    "gn:asciiname":"Dorfkemmathen",
    "gn:country_code":"DE",
    "gn:dem":436,
    "gn:feature_class":"P",
    "gn:feature_code":"PPL",
    "gn:name":"Dorfkemmathen",
    "gn:population":0,
    "gn:timezone":"Europe/Berlin",
    "iso:country":"DE",
    "wof:name":"Dorfkemmathen",
    "wof:placetype":"neighbourhood"
},
  "geometry": {"coordinates":[10.44472,49.08361],"type":"Point"}
}