{
  "type": "Feature",
  "properties": {
    "gn:admin1_code":"7.0",
    "gn:admin2_code":"57.0",
    "gn:admin3_code":"5770.0",
    "gn:admin4_code":"5770020.0",
    "gn:asciiname":"Aspel",
    "gn:country_code":"DE",
    "gn:dem":49,
    "gn:feature_class":"P",
    "gn:feature_code":"PPL",
    "gn:name":"Aspel",
    "gn:population":0,
    "gn:timezone":"Europe/Berlin",
    "iso:country":"DE",
    "name:und_x_variant":[
        "Aspeln",
        "Aspel"
    ],
    "wof:name":"Aspel",
    "wof:placetype":"neighbourhood"
},
  "geometry": {"coordinates":[8.70606,52.31479],"type":"Point"}
}