{
  "type": "Feature",
  "properties": {
    "gn:country":"DE",
    "gn:fcode":"PPL",
    "gn:population":163,
    "iso:country":"DE",
    "name:bak_x_preferred":[
        "\u0422\u043e\u0442\u043b\u0435\u0431\u0435\u043d"
    ],
    "name:ceb_x_preferred":[
        "Tottleben"
    ],
    "name:deu_x_preferred":[
        "Tottleben"
    ],
    "name:deu_x_variant":[
        "T\u00f6ttleben"
    ],
    "name:epo_x_preferred":[
        "Tottleben"
    ],
    "name:eus_x_preferred":[
        "Tottleben"
    ],
    "name:fra_x_preferred":[
        "Tottleben"
    ],
    "name:hbs_x_preferred":[
        "Tottleben"
    ],
    "name:hun_x_preferred":[
        "Tottleben"
    ],
    "name:ita_x_preferred":[
        "Tottleben"
    ],
    "name:mkd_x_preferred":[
        "\u0422\u043e\u0442\u043b\u0435\u0431\u0435\u043d"
    ],
    "name:msa_x_preferred":[
        "Tottleben"
    ],
    "name:nld_x_preferred":[
        "Tottleben"
    ],
    "name:pol_x_preferred":[
        "Tottleben"
    ],
    "name:ron_x_preferred":[
        "Tottleben"
    ],
    "name:rus_x_preferred":[
        "\u0422\u043e\u0442\u043b\u0435\u0431\u0435\u043d"
    ],
    "name:spa_x_preferred":[
        "Tottleben"
    ],
    "name:srp_x_preferred":[
        "\u0422\u043e\u0442\u043b\u0435\u0431\u0435\u043d"
    ],
    "name:ukr_x_preferred":[
        "\u0422\u043e\u0442\u0442\u043b\u0435\u0431\u0435\u043d"
    ],
    "name:uzb_x_preferred":[
        "Tottleben"
    ],
    "name:vol_x_preferred":[
        "Tottleben"
    ],
    "name:war_x_preferred":[
        "Tottleben"
    ],
    "name:zho_x_preferred":[
        "\u6258\u7279\u83b1\u672c"
    ],
    "qs_pg:aaroncc":"DE",
    "qs_pg:gn_country":"DE",
    "qs_pg:gn_fcode":"PPL",
    "qs_pg:gn_pop":163,
    "qs_pg:name":"Tottleben",
    "qs_pg:name_adm0":"Deutschland",
    "qs_pg:name_adm1":"Th\u00fcringen",
    "qs_pg:photos":37,
    "qs_pg:photos_1k":7,
    "qs_pg:photos_9k":1,
    "qs_pg:photos_9r":2,
    "qs_pg:photos_all":37,
    "qs_pg:photos_sr":2,
    "qs_pg:pop_sr":1,
    "qs_pg:qs_pg_placetype":"neighbourhood",
    "qs_pg:qs_pg_placetype_gp":"Suburb",
    "qs_pg:woe_adm0":23424829,
    "woe:adm0_id":23424829,
    "woe:name_adm0":"Deutschland",
    "woe:name_adm1":"Th\u00fcringen",
    "woe:placetype":"Suburb",
    "wof:name":"Tottleben",
    "wof:placetype":"neighbourhood",
    "wof:population":163
},
  "geometry": {"coordinates":[11.11533,51.01769],"type":"Point"}
}