{
  "type": "Feature",
  "properties": {
    "gn:admin1_code":"6",
    "gn:admin2_code":"0.0",
    "gn:admin3_code":"3460.0",
    "gn:admin4_code":"3460002.0",
    "gn:asciiname":"Neuenwalde",
    "gn:country_code":"DE",
    "gn:dem":67,
    "gn:feature_class":"P",
    "gn:feature_code":"PPL",
    "gn:name":"Neuenwalde",
    "gn:population":0,
    "gn:timezone":"Europe/Berlin",
    "iso:country":"DE",
    "name:deu_x_preferred":[
        "Neuenwalde"
    ],
    "name:fas_x_preferred":[
        "\u0646\u0648\u06cc\u0646\u0648\u0627\u0644\u062f\u0647"
    ],
    "name:nds_x_preferred":[
        "Niewohl"
    ],
    "name:nld_x_preferred":[
        "Neuenwalde"
    ],
    "wof:name":"Neuenwalde",
    "wof:placetype":"neighbourhood"
},
  "geometry": {"coordinates":[8.15394,52.50265],"type":"Point"}
}