{
  "type": "Feature",
  "properties": {
    "gn:admin1_code":"12",
    "gn:admin2_code":"0.0",
    "gn:admin3_code":"13073.0",
    "gn:admin4_code":"13073041.0",
    "gn:asciiname":"Gruen Kordshagen",
    "gn:country_code":"DE",
    "gn:dem":18,
    "gn:feature_class":"P",
    "gn:feature_code":"PPL",
    "gn:name":"Gr\u00fcn Kordshagen",
    "gn:population":0,
    "gn:timezone":"Europe/Berlin",
    "iso:country":"DE",
    "wof:name":"Gruen Kordshagen",
    "wof:placetype":"neighbourhood"
},
  "geometry": {"coordinates":[12.95623,54.21938000000001],"type":"Point"}
}