{
  "type": "Feature",
  "properties": {
    "gn:admin1_code":"6",
    "gn:admin2_code":"0.0",
    "gn:admin3_code":"3461.0",
    "gn:admin4_code":"3461005.0",
    "gn:asciiname":"Roennelmoor",
    "gn:country_code":"DE",
    "gn:dem":0,
    "gn:feature_class":"P",
    "gn:feature_code":"PPLL",
    "gn:name":"R\u00f6nnelmoor",
    "gn:population":0,
    "gn:timezone":"Europe/Berlin",
    "iso:country":"DE",
    "wof:name":"Roennelmoor",
    "wof:placetype":"locality"
},
  "geometry": {"coordinates":[8.30661,53.36259],"type":"Point"}
}