{
  "type": "Feature",
  "properties": {
    "gn:admin1_code":"1.0",
    "gn:admin2_code":"83.0",
    "gn:admin3_code":"8336.0",
    "gn:admin4_code":"8336087.0",
    "gn:asciiname":"Brandenberg",
    "gn:country_code":"DE",
    "gn:dem":734,
    "gn:feature_class":"P",
    "gn:feature_code":"PPL",
    "gn:name":"Brandenberg",
    "gn:population":0,
    "gn:timezone":"Europe/Berlin",
    "iso:country":"DE",
    "name:bar_x_preferred":[
        "Brandnberg"
    ],
    "name:ceb_x_preferred":[
        "Brandenberg"
    ],
    "name:ces_x_preferred":[
        "Brandenberg"
    ],
    "name:deu_x_preferred":[
        "Brandenberg"
    ],
    "name:est_x_preferred":[
        "Brandenberg"
    ],
    "name:fas_x_preferred":[
        "\u0628\u0631\u0627\u0646\u062f\u0646\u0628\u0631\u06af"
    ],
    "name:fra_x_preferred":[
        "Brandenberg"
    ],
    "name:hun_x_preferred":[
        "Brandenberg"
    ],
    "name:ita_x_preferred":[
        "Brandenberg"
    ],
    "name:kaz_x_preferred":[
        "\u0411\u0440\u0430\u043d\u0434\u0435\u043d\u0431\u0435\u0440\u0433"
    ],
    "name:nld_x_preferred":[
        "Brandenberg"
    ],
    "name:pol_x_preferred":[
        "Brandenberg"
    ],
    "name:ron_x_preferred":[
        "Brandenberg"
    ],
    "name:rus_x_preferred":[
        "\u0411\u0440\u0430\u043d\u0434\u0435\u043d\u0431\u0435\u0440\u0433"
    ],
    "name:slk_x_preferred":[
        "Brandenberg"
    ],
    "name:spa_x_preferred":[
        "Brandenberg"
    ],
    "name:swe_x_preferred":[
        "Brandenberg"
    ],
    "name:ukr_x_preferred":[
        "\u0411\u0440\u0430\u043d\u0434\u0435\u043d\u0431\u0435\u0440\u0433"
    ],
    "name:uzb_x_preferred":[
        "Brandenberg"
    ],
    "name:vol_x_preferred":[
        "Brandenberg"
    ],
    "name:war_x_preferred":[
        "Brandenberg"
    ],
    "name:zho_x_preferred":[
        "\u52c3\u862d\u767b\u5821"
    ],
    "wof:name":"Brandenberg",
    "wof:placetype":"neighbourhood"
},
  "geometry": {"coordinates":[7.97221,47.83557],"type":"Point"}
}