{
  "type": "Feature",
  "properties": {
    "gn:admin1_code":"2",
    "gn:admin2_code":"92.0",
    "gn:admin3_code":"9278.0",
    "gn:admin4_code":"9278139.0",
    "gn:asciiname":"Hoch",
    "gn:country_code":"DE",
    "gn:dem":390,
    "gn:feature_class":"P",
    "gn:feature_code":"PPLL",
    "gn:name":"Hoch",
    "gn:population":0,
    "gn:timezone":"Europe/Berlin",
    "iso:country":"DE",
    "name:che_x_preferred":[
        "\u0425\u043e\u0445"
    ],
    "name:rus_x_preferred":[
        "\u0425\u043e\u0445"
    ],
    "wof:name":"Hoch",
    "wof:placetype":"neighbourhood"
},
  "geometry": {"coordinates":[12.70408,48.94824000000001],"type":"Point"}
}