{
  "type": "Feature",
  "properties": {
    "gn:country":"DE",
    "gn:fcode":"PPL",
    "gn:population":0,
    "iso:country":"DE",
    "name:ast_x_preferred":[
        "Knutb\u00fchren"
    ],
    "name:deu_x_preferred":[
        "Knutb\u00fchren"
    ],
    "name:eng_x_preferred":[
        "Knutb\u00fchren"
    ],
    "name:fas_x_preferred":[
        "\u06a9\u0646\u0648\u062a\u0628\u0648\u0647\u0631\u0646"
    ],
    "name:fra_x_preferred":[
        "Knutb\u00fchren"
    ],
    "name:hye_x_preferred":[
        "\u053f\u0576\u0578\u0582\u0569\u0562\u0575\u0578\u0582\u0570\u0580\u0565\u0576"
    ],
    "name:nld_x_preferred":[
        "Knutb\u00fchren"
    ],
    "qs_pg:aaroncc":"DE",
    "qs_pg:gn_country":"DE",
    "qs_pg:gn_fcode":"PPL",
    "qs_pg:gn_pop":0,
    "qs_pg:name":"Knutb\u00fchren",
    "qs_pg:name_adm0":"Deutschland",
    "qs_pg:name_adm1":"Niedersachsen",
    "qs_pg:photos_9k":1,
    "qs_pg:photos_9r":1,
    "qs_pg:photos_all":1,
    "qs_pg:photos_sr":0,
    "qs_pg:pop_sr":0,
    "qs_pg:qs_pg_placetype":"locality",
    "qs_pg:qs_pg_placetype_gp":"Town",
    "qs_pg:woe_adm0":23424829,
    "woe:adm0_id":23424829,
    "woe:name_adm0":"Deutschland",
    "woe:name_adm1":"Niedersachsen",
    "woe:placetype":"Town",
    "wof:name":"Knutb\u00fchren",
    "wof:placetype":"neighbourhood"
},
  "geometry": {"coordinates":[9.81996,51.53875],"type":"Point"}
}