{
  "type": "Feature",
  "properties": {
    "gn:admin1_code":"6",
    "gn:admin2_code":"0.0",
    "gn:admin3_code":"3154.0",
    "gn:admin4_code":"3154013.0",
    "gn:asciiname":"Rottorf",
    "gn:country_code":"DE",
    "gn:dem":110,
    "gn:feature_class":"P",
    "gn:feature_code":"PPL",
    "gn:name":"Rottorf",
    "gn:population":0,
    "gn:timezone":"Europe/Berlin",
    "iso:country":"DE",
    "wof:name":"Rottorf",
    "wof:placetype":"neighbourhood"
},
  "geometry": {"coordinates":[10.84076,52.25586],"type":"Point"}
}