{
  "type": "Feature",
  "properties": {
    "gn:admin1_code":"2",
    "gn:admin2_code":"93.0",
    "gn:admin3_code":"9371.0",
    "gn:admin4_code":"9371113.0",
    "gn:asciiname":"Ohrenbach",
    "gn:country_code":"DE",
    "gn:dem":457,
    "gn:feature_class":"P",
    "gn:feature_code":"PPL",
    "gn:name":"Ohrenbach",
    "gn:population":0,
    "gn:timezone":"Europe/Berlin",
    "iso:country":"DE",
    "name:ara_x_preferred":[
        "\u0623\u0648\u0631\u0646\u0628\u0622\u062e"
    ],
    "name:ceb_x_preferred":[
        "Ohrenbach"
    ],
    "name:deu_x_preferred":[
        "Ohrenbach"
    ],
    "name:epo_x_preferred":[
        "Ohrenbach"
    ],
    "name:eus_x_preferred":[
        "Ohrenbach"
    ],
    "name:fas_x_preferred":[
        "\u0627\u0648\u0631\u0646\u0628\u0627\u062e"
    ],
    "name:fra_x_preferred":[
        "Ohrenbach"
    ],
    "name:hun_x_preferred":[
        "Ohrenbach"
    ],
    "name:hye_x_preferred":[
        "\u0555\u0580\u0565\u0576\u0562\u0561\u056d"
    ],
    "name:ile_x_preferred":[
        "Ohrenbach"
    ],
    "name:ind_x_preferred":[
        "Ohrenbach"
    ],
    "name:ita_x_preferred":[
        "Ohrenbach"
    ],
    "name:jpn_x_preferred":[
        "\u30aa\u30fc\u30ec\u30f3\u30d0\u30c3\u30cf"
    ],
    "name:kaz_x_preferred":[
        "\u041e\u0440\u0435\u043d\u0431\u0430\u0445"
    ],
    "name:kir_x_preferred":[
        "\u041e\u0440\u0435\u043d\u0431\u0430\u0445"
    ],
    "name:lmo_x_preferred":[
        "Ohrenbach"
    ],
    "name:msa_x_preferred":[
        "Ohrenbach"
    ],
    "name:nld_x_preferred":[
        "Ohrenbach"
    ],
    "name:pol_x_preferred":[
        "Ohrenbach"
    ],
    "name:por_x_preferred":[
        "Ohrenbach"
    ],
    "name:ron_x_preferred":[
        "Ohrenbach"
    ],
    "name:rus_x_preferred":[
        "\u041e\u0440\u0435\u043d\u0431\u0430\u0445"
    ],
    "name:spa_x_preferred":[
        "Ohrenbach"
    ],
    "name:srp_x_preferred":[
        "\u041e\u0440\u0435\u043d\u0431\u0430\u0445"
    ],
    "name:ukr_x_preferred":[
        "\u041e\u0440\u0435\u043d\u0431\u0430\u0445"
    ],
    "name:uzb_x_preferred":[
        "Ohrenbach"
    ],
    "name:vie_x_preferred":[
        "Ohrenbach"
    ],
    "name:vol_x_preferred":[
        "Ohrenbach"
    ],
    "name:war_x_preferred":[
        "Ohrenbach"
    ],
    "name:zho_x_preferred":[
        "\u5965\u4f26\u5df4\u8d6b"
    ],
    "wof:name":"Ohrenbach",
    "wof:placetype":"neighbourhood"
},
  "geometry": {"coordinates":[11.61819,49.72051],"type":"Point"}
}