{
  "type": "Feature",
  "properties": {
    "gn:admin1_code":"2",
    "gn:admin2_code":"91.0",
    "gn:admin3_code":"9182.0",
    "gn:admin4_code":"9182116.0",
    "gn:asciiname":"Festenbach",
    "gn:country_code":"DE",
    "gn:dem":741,
    "gn:feature_class":"P",
    "gn:feature_code":"PPL",
    "gn:name":"Festenbach",
    "gn:population":0,
    "gn:timezone":"Europe/Berlin",
    "iso:country":"DE",
    "name:deu_x_preferred":[
        "Festenbach"
    ],
    "wof:name":"Festenbach",
    "wof:placetype":"neighbourhood"
},
  "geometry": {"coordinates":[11.74664,47.76778],"type":"Point"}
}