{
  "type": "Feature",
  "properties": {
    "gn:admin1_code":"6",
    "gn:admin2_code":"0.0",
    "gn:admin3_code":"3159.0",
    "gn:admin4_code":"3159010.0",
    "gn:asciiname":"Nesselroeden",
    "gn:country_code":"DE",
    "gn:dem":192,
    "gn:feature_class":"P",
    "gn:feature_code":"PPL",
    "gn:name":"Nesselr\u00f6den",
    "gn:population":0,
    "gn:timezone":"Europe/Berlin",
    "iso:country":"DE",
    "wof:name":"Nesselroeden",
    "wof:placetype":"neighbourhood"
},
  "geometry": {"coordinates":[10.18141,51.49357],"type":"Point"}
}