{
  "type": "Feature",
  "properties": {
    "gn:admin1_code":"1",
    "gn:admin2_code":"82.0",
    "gn:admin3_code":"8237.0",
    "gn:admin4_code":"8237002.0",
    "gn:asciiname":"Unteres Dorfle",
    "gn:country_code":"DE",
    "gn:dem":486,
    "gn:feature_class":"P",
    "gn:feature_code":"PPL",
    "gn:name":"Unteres D\u00f6rfle",
    "gn:population":0,
    "gn:timezone":"Europe/Berlin",
    "iso:country":"DE",
    "wof:name":"Unteres Dorfle",
    "wof:placetype":"neighbourhood"
},
  "geometry": {"coordinates":[8.37232,48.35795],"type":"Point"}
}