{
  "type": "Feature",
  "properties": {
    "gn:admin1_code":"6",
    "gn:admin2_code":"0.0",
    "gn:admin3_code":"3256.0",
    "gn:admin4_code":"3256032.0",
    "gn:asciiname":"Haustedt",
    "gn:country_code":"DE",
    "gn:dem":37,
    "gn:feature_class":"P",
    "gn:feature_code":"PPL",
    "gn:name":"Haustedt",
    "gn:population":0,
    "gn:timezone":"Europe/Berlin",
    "iso:country":"DE",
    "wof:name":"Haustedt",
    "wof:placetype":"neighbourhood"
},
  "geometry": {"coordinates":[8.97782,52.49146999999999],"type":"Point"}
}