{
  "type": "Feature",
  "properties": {
    "gn:admin1_code":"13",
    "gn:admin2_code":"0.0",
    "gn:admin3_code":"14521.0",
    "gn:admin4_code":"14521630.0",
    "gn:asciiname":"Hinterfalkenbach",
    "gn:country_code":"DE",
    "gn:dem":469,
    "gn:feature_class":"P",
    "gn:feature_code":"PPL",
    "gn:name":"Hinterfalkenbach",
    "gn:population":0,
    "gn:timezone":"Europe/Berlin",
    "iso:country":"DE",
    "wof:name":"Hinterfalkenbach",
    "wof:placetype":"neighbourhood"
},
  "geometry": {"coordinates":[13.05,50.61667],"type":"Point"}
}