{
  "type": "Feature",
  "properties": {
    "gn:admin1_code":"1",
    "gn:admin2_code":"83.0",
    "gn:admin3_code":"8336.0",
    "gn:admin4_code":"8336106.0",
    "gn:asciiname":"Hag",
    "gn:country_code":"DE",
    "gn:dem":686,
    "gn:feature_class":"P",
    "gn:feature_code":"PPL",
    "gn:name":"H\u00e4g",
    "gn:population":0,
    "gn:timezone":"Europe/Berlin",
    "iso:country":"DE",
    "name:ara_x_preferred":[
        "\u0639\u062c\u0648\u0632 \u0634\u0645\u0637\u0627\u0621"
    ],
    "name:bre_x_preferred":[
        "Gwrac'h"
    ],
    "name:deu_x_preferred":[
        "Hexe"
    ],
    "name:fra_x_preferred":[
        "Hag"
    ],
    "name:gla_x_preferred":[
        "Baobh"
    ],
    "name:jpn_x_preferred":[
        "\u30cf\u30c3\u30b0"
    ],
    "name:por_x_preferred":[
        "Hag"
    ],
    "name:spa_x_preferred":[
        "Hag"
    ],
    "wof:name":"Hag",
    "wof:placetype":"neighbourhood"
},
  "geometry": {"coordinates":[7.91568,47.73324],"type":"Point"}
}