{
  "type": "Feature",
  "properties": {
    "gn:admin1_code":"2",
    "gn:admin2_code":"93.0",
    "gn:admin3_code":"9377.0",
    "gn:admin4_code":"9377154.0",
    "gn:asciiname":"Matzersreuth",
    "gn:country_code":"DE",
    "gn:dem":548,
    "gn:feature_class":"P",
    "gn:feature_code":"PPL",
    "gn:name":"Matzersreuth",
    "gn:population":0,
    "gn:timezone":"Europe/Berlin",
    "iso:country":"DE",
    "wof:name":"Matzersreuth",
    "wof:placetype":"neighbourhood"
},
  "geometry": {"coordinates":[12.37953,49.87445],"type":"Point"}
}