{
  "type": "Feature",
  "properties": {
    "gn:admin1_code":"12",
    "gn:admin2_code":"0.0",
    "gn:admin3_code":"13073.0",
    "gn:admin4_code":"13073035.0",
    "gn:asciiname":"Klein Lehmhagen",
    "gn:country_code":"DE",
    "gn:dem":14,
    "gn:feature_class":"P",
    "gn:feature_code":"PPL",
    "gn:name":"Klein Lehmhagen",
    "gn:population":0,
    "gn:timezone":"Europe/Berlin",
    "iso:country":"DE",
    "wof:name":"Klein Lehmhagen",
    "wof:placetype":"neighbourhood"
},
  "geometry": {"coordinates":[13.05725,54.13564],"type":"Point"}
}