{
  "type": "Feature",
  "properties": {
    "gn:admin1_code":"13",
    "gn:admin2_code":"0.0",
    "gn:admin3_code":"14522.0",
    "gn:admin4_code":"14522035.0",
    "gn:asciiname":"Oberbobritzsch",
    "gn:country_code":"DE",
    "gn:dem":438,
    "gn:feature_class":"P",
    "gn:feature_code":"PPL",
    "gn:name":"Oberbobritzsch",
    "gn:population":0,
    "gn:timezone":"Europe/Berlin",
    "iso:country":"DE",
    "wof:name":"Oberbobritzsch",
    "wof:placetype":"neighbourhood"
},
  "geometry": {"coordinates":[13.46318,50.86425],"type":"Point"}
}