{
  "type": "Feature",
  "properties": {
    "gn:admin1_code":"13",
    "gn:admin2_code":"0.0",
    "gn:admin3_code":"14627.0",
    "gn:admin4_code":"14627230.0",
    "gn:asciiname":"Riesa-Goehlis",
    "gn:country_code":"DE",
    "gn:dem":101,
    "gn:feature_class":"P",
    "gn:feature_code":"PPL",
    "gn:name":"Riesa-G\u00f6hlis",
    "gn:population":0,
    "gn:timezone":"Europe/Berlin",
    "iso:country":"DE",
    "wof:name":"Riesa-Goehlis",
    "wof:placetype":"neighbourhood"
},
  "geometry": {"coordinates":[13.34684,51.301],"type":"Point"}
}