{
  "type": "Feature",
  "properties": {
    "gn:admin1_code":"13",
    "gn:admin2_code":"0.0",
    "gn:admin3_code":"14626.0",
    "gn:admin4_code":"14626480.0",
    "gn:asciiname":"Neusorge",
    "gn:country_code":"DE",
    "gn:dem":154,
    "gn:feature_class":"P",
    "gn:feature_code":"PPL",
    "gn:name":"Neusorge",
    "gn:population":0,
    "gn:timezone":"Europe/Berlin",
    "iso:country":"DE",
    "wof:name":"Neusorge",
    "wof:placetype":"neighbourhood"
},
  "geometry": {"coordinates":[14.93174,51.38103],"type":"Point"}
}