{
  "type": "Feature",
  "properties": {
    "gn:admin1_code":"7.0",
    "gn:admin2_code":"59.0",
    "gn:admin3_code":"5954.0",
    "gn:admin4_code":"5954012.0",
    "gn:asciiname":"Asbeck",
    "gn:country_code":"DE",
    "gn:dem":185,
    "gn:feature_class":"P",
    "gn:feature_code":"PPL",
    "gn:name":"Asbeck",
    "gn:population":0,
    "gn:timezone":"Europe/Berlin",
    "iso:country":"DE",
    "wof:name":"Asbeck",
    "wof:placetype":"neighbourhood"
},
  "geometry": {"coordinates":[7.31904,51.34109],"type":"Point"}
}