{
  "type": "Feature",
  "properties": {
    "gn:admin1_code":"10",
    "gn:admin2_code":"0.0",
    "gn:admin3_code":"1054.0",
    "gn:admin4_code":"1054123.0",
    "gn:asciiname":"Pobuell",
    "gn:country_code":"DE",
    "gn:dem":25,
    "gn:feature_class":"P",
    "gn:feature_code":"PPL",
    "gn:name":"Pob\u00fcll",
    "gn:population":0,
    "gn:timezone":"Europe/Berlin",
    "iso:country":"DE",
    "wof:name":"Pobuell",
    "wof:placetype":"neighbourhood"
},
  "geometry": {"coordinates":[9.23431,54.60804],"type":"Point"}
}