{
  "type": "Feature",
  "properties": {
    "gn:country":"DE",
    "gn:fcode":"PPL",
    "gn:population":0,
    "iso:country":"DE",
    "name:als_x_preferred":[
        "Ehingen"
    ],
    "name:ara_x_preferred":[
        "\u0625\u064a\u0647\u0646\u063a\u0646"
    ],
    "name:azb_x_preferred":[
        "\u0627\u0646\u06cc\u0646\u0642\u0646"
    ],
    "name:ceb_x_preferred":[
        "Ehingen"
    ],
    "name:deu_x_preferred":[
        "Ehingen"
    ],
    "name:epo_x_preferred":[
        "Ehingen"
    ],
    "name:fas_x_preferred":[
        "\u0627\u0646\u06cc\u0646\u06af\u0646"
    ],
    "name:fra_x_preferred":[
        "Ehingen"
    ],
    "name:hun_x_preferred":[
        "Ehingen"
    ],
    "name:hye_x_preferred":[
        "\u0537\u0570\u056b\u0576\u0563\u0565\u0576"
    ],
    "name:ita_x_preferred":[
        "Ehingen"
    ],
    "name:kat_x_preferred":[
        "\u10d4\u10f0\u10d8\u10dc\u10d2\u10d4\u10dc\u10d8"
    ],
    "name:kaz_x_preferred":[
        "\u042d\u0445\u0438\u043d\u0433\u0435\u043d"
    ],
    "name:kir_x_preferred":[
        "\u042d\u0445\u0438\u043d\u0433\u0435\u043d"
    ],
    "name:lat_x_preferred":[
        "Ehingen"
    ],
    "name:lmo_x_preferred":[
        "Ehingen"
    ],
    "name:msa_x_preferred":[
        "Ehingen"
    ],
    "name:nld_x_preferred":[
        "Ehingen"
    ],
    "name:pol_x_preferred":[
        "Ehingen"
    ],
    "name:por_x_preferred":[
        "Ehingen"
    ],
    "name:ron_x_preferred":[
        "Ehingen"
    ],
    "name:rus_x_preferred":[
        "\u042d\u0438\u043d\u0433\u0435\u043d"
    ],
    "name:slk_x_preferred":[
        "Ehingen"
    ],
    "name:spa_x_preferred":[
        "Ehingen"
    ],
    "name:srp_x_preferred":[
        "\u0415\u0445\u0438\u043d\u0433\u0435\u043d"
    ],
    "name:tur_x_preferred":[
        "Ehingen"
    ],
    "name:ukr_x_preferred":[
        "\u0415\u0433\u0456\u043d\u0433\u0435\u043d"
    ],
    "name:vol_x_preferred":[
        "Ehingen"
    ],
    "name:war_x_preferred":[
        "Ehingen"
    ],
    "name:zho_x_preferred":[
        "\u57c3\u82f1\u6839"
    ],
    "qs_pg:aaroncc":"DE",
    "qs_pg:gn_country":"DE",
    "qs_pg:gn_fcode":"PPL",
    "qs_pg:gn_pop":0,
    "qs_pg:name":"Ehingen",
    "qs_pg:name_adm0":"Deutschland",
    "qs_pg:name_adm1":"Nordrhein-Westfalen",
    "qs_pg:photos":7,
    "qs_pg:photos_1k":1,
    "qs_pg:photos_9k":1,
    "qs_pg:photos_9r":1,
    "qs_pg:photos_all":7,
    "qs_pg:photos_sr":1,
    "qs_pg:pop_sr":0,
    "qs_pg:qs_pg_placetype":"neighbourhood",
    "qs_pg:qs_pg_placetype_gp":"Suburb",
    "qs_pg:woe_adm0":23424829,
    "woe:adm0_id":23424829,
    "woe:name_adm0":"Deutschland",
    "woe:name_adm1":"Nordrhein-Westfalen",
    "woe:placetype":"Suburb",
    "wof:name":"Ehingen",
    "wof:placetype":"neighbourhood"
},
  "geometry": {"coordinates":[6.69088,51.36009],"type":"Point"}
}