{
  "type": "Feature",
  "properties": {
    "iso:country":"DE",
    "name:deu_x_colloquial":[
        "Wuermsee",
        "Wurmsee"
    ],
    "name:deu_x_preferred":[
        "W\u00fcrmsee"
    ],
    "qs:gn_fcode":"PPL",
    "qs:gn_local":0,
    "qs:gn_namadm1":"06",
    "qs:gn_name":"W\u00fcrmsee",
    "qs:local_max":34,
    "qs:local_sum":34,
    "qs:localhoods":1,
    "qs:name":"W\u00fcrmsee",
    "qs:name_adm0":"Deutschland",
    "qs:name_adm1":"Niedersachsen",
    "qs:name_adm2":"Region Hannover",
    "qs:name_lau":"Stadtteil Kleinburgwedel",
    "qs:name_local":"Stadtteil Kleinburgwedel",
    "qs:photo_max":10,
    "qs:photo_sum":34,
    "qs:placetype":"Suburb",
    "qs:quad_count":13,
    "qs:woe_adm0":23424829,
    "qs:woe_adm1":2345486,
    "qs:woe_adm2":20071101,
    "qs:woe_lau":26823454,
    "qs:woe_local":26823454,
    "qs:woe_ver":"7.10.0",
    "wof:lang":[
        "ger"
    ],
    "wof:name":"W\u00fcrmsee",
    "wof:placetype":"neighbourhood"
},
  "geometry": {"coordinates":[9.815638,52.532047],"type":"Point"}
}