{
  "type": "Feature",
  "properties": {
    "gn:admin1_code":"1.0",
    "gn:admin2_code":"84.0",
    "gn:admin3_code":"8435.0",
    "gn:admin4_code":"8435015.0",
    "gn:asciiname":"Altheim",
    "gn:country_code":"DE",
    "gn:dem":509,
    "gn:feature_class":"P",
    "gn:feature_code":"PPL",
    "gn:name":"Altheim",
    "gn:population":0,
    "gn:timezone":"Europe/Berlin",
    "iso:country":"DE",
    "name:bos_x_preferred":[
        "Altheim"
    ],
    "name:cat_x_preferred":[
        "Altheim"
    ],
    "name:ceb_x_preferred":[
        "Altheim"
    ],
    "name:deu_x_preferred":[
        "Altheim"
    ],
    "name:epo_x_preferred":[
        "Altheim"
    ],
    "name:eus_x_preferred":[
        "Altheim"
    ],
    "name:fas_x_preferred":[
        "\u0627\u0644\u062a\u06cc\u0645"
    ],
    "name:fra_x_preferred":[
        "Altheim"
    ],
    "name:hye_x_preferred":[
        "\u0531\u056c\u0569\u0570\u0561\u0575\u0574"
    ],
    "name:ita_x_preferred":[
        "Altheim"
    ],
    "name:kat_x_preferred":[
        "\u10d0\u10da\u10e2\u10f0\u10d0\u10d8\u10db\u10d8"
    ],
    "name:lmo_x_preferred":[
        "Altheim"
    ],
    "name:nld_x_preferred":[
        "Altheim"
    ],
    "name:pol_x_preferred":[
        "Altheim"
    ],
    "name:slk_x_preferred":[
        "Altheim"
    ],
    "name:srp_x_preferred":[
        "\u0410\u043b\u0442\u0445\u0430\u0458\u043c"
    ],
    "name:swe_x_preferred":[
        "Altheim"
    ],
    "name:vie_x_preferred":[
        "Altheim"
    ],
    "name:vol_x_preferred":[
        "Altheim"
    ],
    "wof:name":"Altheim",
    "wof:placetype":"neighbourhood"
},
  "geometry": {"coordinates":[9.25463,47.82636],"type":"Point"}
}