{
  "type": "Feature",
  "properties": {
    "gn:admin1_code":"1.0",
    "gn:admin2_code":"84.0",
    "gn:admin3_code":"8435.0",
    "gn:admin4_code":"8435015.0",
    "gn:asciiname":"Altheim",
    "gn:country_code":"DE",
    "gn:dem":509,
    "gn:feature_class":"P",
    "gn:feature_code":"PPL",
    "gn:name":"Altheim",
    "gn:population":0,
    "gn:timezone":"Europe/Berlin",
    "iso:country":"DE",
    "wof:name":"Altheim",
    "wof:placetype":"neighbourhood"
},
  "geometry": {"coordinates":[9.25463,47.82636],"type":"Point"}
}