{
  "type": "Feature",
  "properties": {
    "gn:admin1_code":"2",
    "gn:admin2_code":"92.0",
    "gn:admin3_code":"9275.0",
    "gn:admin4_code":"9275143.0",
    "gn:asciiname":"Buch",
    "gn:country_code":"DE",
    "gn:dem":388,
    "gn:feature_class":"P",
    "gn:feature_code":"PPL",
    "gn:name":"Buch",
    "gn:population":0,
    "gn:timezone":"Europe/Berlin",
    "iso:country":"DE",
    "name:als_x_preferred":[
        "Buch"
    ],
    "name:ceb_x_preferred":[
        "Buch"
    ],
    "name:ces_x_preferred":[
        "Buch"
    ],
    "name:dan_x_preferred":[
        "Buch"
    ],
    "name:deu_x_preferred":[
        "Buch"
    ],
    "name:epo_x_preferred":[
        "Buch"
    ],
    "name:fra_x_preferred":[
        "Buch"
    ],
    "name:ita_x_preferred":[
        "Buch"
    ],
    "name:ksh_x_preferred":[
        "Buch"
    ],
    "name:lmo_x_preferred":[
        "Buch"
    ],
    "name:ltz_x_preferred":[
        "Buch"
    ],
    "name:nld_x_preferred":[
        "Buch"
    ],
    "name:pol_x_preferred":[
        "Buch"
    ],
    "name:por_x_preferred":[
        "Buch"
    ],
    "name:rus_x_preferred":[
        "\u0411\u0443\u0445"
    ],
    "name:spa_x_preferred":[
        "Buch"
    ],
    "name:swe_x_preferred":[
        "Buch"
    ],
    "name:vol_x_preferred":[
        "Buch"
    ],
    "wof:name":"Buch",
    "wof:placetype":"neighbourhood"
},
  "geometry": {"coordinates":[13.22831,48.38179],"type":"Point"}
}