{
  "type": "Feature",
  "properties": {
    "gn:admin1_code":"13",
    "gn:admin2_code":"0.0",
    "gn:admin3_code":"14627.0",
    "gn:admin4_code":"14627260.0",
    "gn:asciiname":"Stoesitz",
    "gn:country_code":"DE",
    "gn:dem":115,
    "gn:feature_class":"P",
    "gn:feature_code":"PPL",
    "gn:name":"St\u00f6sitz",
    "gn:population":0,
    "gn:timezone":"Europe/Berlin",
    "iso:country":"DE",
    "wof:name":"Stoesitz",
    "wof:placetype":"neighbourhood"
},
  "geometry": {"coordinates":[13.23582,51.25463],"type":"Point"}
}