{
  "type": "Feature",
  "properties": {
    "iso:country":"DE",
    "name:deu_x_preferred":[
        "Flugplatz Rinteln"
    ],
    "name:eng_x_preferred":[
        "Rinteln Airport"
    ],
    "name:eng_x_variant":[
        "EDVR",
        "Rinteln airfield"
    ],
    "name:msa_x_preferred":[
        "Lapangan Terbang Rinteln"
    ],
    "oa:elevation_ft":"180",
    "oa:type":"small_airport",
    "woe:hierarchy":{
        "country_id":23424829,
        "county_id":12596789,
        "localadmin_id":12629576,
        "planet_id":1,
        "state_id":2345486
    },
    "wof:name":"Flugplatz Rinteln",
    "wof:placetype":"campus"
},
  "geometry": {"coordinates":[9.05556,52.1811],"type":"Point"}
}