{
  "type": "Feature",
  "properties": {
    "gn:admin1_code":"7.0",
    "gn:admin2_code":"055",
    "gn:admin3_code":"5566.0",
    "gn:admin4_code":"5566044.0",
    "gn:asciiname":"Westerbeck",
    "gn:country_code":"DE",
    "gn:dem":75,
    "gn:feature_class":"P",
    "gn:feature_code":"PPLL",
    "gn:name":"Westerbeck",
    "gn:population":0,
    "gn:timezone":"Europe/Berlin",
    "iso:country":"DE",
    "wof:name":"Westerbeck",
    "wof:placetype":"neighbourhood"
},
  "geometry": {"coordinates":[7.94532,52.14404],"type":"Point"}
}