{
  "type": "Feature",
  "properties": {
    "iso:country":"DE",
    "wof:name":"Ansgaritor",
    "wof:placetype":"neighbourhood"
},
  "geometry": {"coordinates":[8.80327097153151,53.08003618902791],"type":"Point"}
}