{
  "type": "Feature",
  "properties": {
    "gn:admin1_code":"6",
    "gn:admin2_code":"0.0",
    "gn:admin3_code":"3453.0",
    "gn:admin4_code":"3453013.0",
    "gn:asciiname":"Hollenermoor",
    "gn:country_code":"DE",
    "gn:dem":4,
    "gn:feature_class":"P",
    "gn:feature_code":"PPL",
    "gn:name":"Hollenermoor",
    "gn:population":0,
    "gn:timezone":"Europe/Berlin",
    "iso:country":"DE",
    "wof:name":"Hollenermoor",
    "wof:placetype":"neighbourhood"
},
  "geometry": {"coordinates":[7.70006,53.10434],"type":"Point"}
}