{
  "type": "Feature",
  "properties": {
    "gn:admin1_code":"2",
    "gn:admin2_code":"97.0",
    "gn:admin3_code":"9771.0",
    "gn:admin4_code":"9771114.0",
    "gn:asciiname":"Nesslach",
    "gn:country_code":"DE",
    "gn:dem":492,
    "gn:feature_class":"P",
    "gn:feature_code":"PPL",
    "gn:name":"Ne\u00dflach",
    "gn:population":0,
    "gn:timezone":"Europe/Berlin",
    "iso:country":"DE",
    "wof:name":"Nesslach",
    "wof:placetype":"neighbourhood"
},
  "geometry": {"coordinates":[11.01679,48.482],"type":"Point"}
}