{
  "type": "Feature",
  "properties": {
    "gn:admin1_code":"7",
    "gn:admin2_code":"51.0",
    "gn:admin3_code":"5120.0",
    "gn:admin4_code":"5120000.0",
    "gn:asciiname":"Doerperhoehe",
    "gn:country_code":"DE",
    "gn:dem":267,
    "gn:feature_class":"P",
    "gn:feature_code":"PPL",
    "gn:name":"D\u00f6rperh\u00f6he",
    "gn:population":0,
    "gn:timezone":"Europe/Berlin",
    "iso:country":"DE",
    "wof:name":"Doerperhoehe",
    "wof:placetype":"neighbourhood"
},
  "geometry": {"coordinates":[7.30456,51.18017],"type":"Point"}
}