{
  "type": "Feature",
  "properties": {
    "gn:admin1_code":"15.0",
    "gn:admin2_code":"0.0",
    "gn:admin3_code":"16073.0",
    "gn:admin4_code":"16073109.0",
    "gn:asciiname":"Beutelsdorf",
    "gn:country_code":"DE",
    "gn:dem":203,
    "gn:feature_class":"P",
    "gn:feature_code":"PPL",
    "gn:name":"Beutelsdorf",
    "gn:population":0,
    "gn:timezone":"Europe/Berlin",
    "iso:country":"DE",
    "wof:name":"Beutelsdorf",
    "wof:placetype":"neighbourhood"
},
  "geometry": {"coordinates":[11.48386,50.76028],"type":"Point"}
}