{
  "type": "Feature",
  "properties": {
    "gn:admin1_code":"15",
    "gn:admin2_code":"0.0",
    "gn:admin3_code":"16076.0",
    "gn:admin4_code":"16076087.0",
    "gn:asciiname":"Gruena",
    "gn:country_code":"DE",
    "gn:dem":403,
    "gn:feature_class":"P",
    "gn:feature_code":"PPL",
    "gn:name":"Gr\u00fcna",
    "gn:population":0,
    "gn:timezone":"Europe/Berlin",
    "iso:country":"DE",
    "wof:name":"Gruena",
    "wof:placetype":"neighbourhood"
},
  "geometry": {"coordinates":[12.02383,50.65437],"type":"Point"}
}