{
  "type": "Feature",
  "properties": {
    "gn:admin1_code":"6",
    "gn:admin2_code":"0.0",
    "gn:admin3_code":"3360.0",
    "gn:admin4_code":"3360026.0",
    "gn:asciiname":"Hover",
    "gn:country_code":"DE",
    "gn:dem":48,
    "gn:feature_class":"P",
    "gn:feature_code":"PPL",
    "gn:name":"H\u00f6ver",
    "gn:population":0,
    "gn:timezone":"Europe/Berlin",
    "iso:country":"DE",
    "name:deu_x_preferred":[
        "Hover"
    ],
    "name:nld_x_preferred":[
        "Hover"
    ],
    "name:pol_x_preferred":[
        "Zawis"
    ],
    "name:rus_x_preferred":[
        "\u0417\u0430\u0432\u0438\u0441\u0430\u043d\u0438\u0435"
    ],
    "wof:name":"Hover",
    "wof:placetype":"neighbourhood"
},
  "geometry": {"coordinates":[10.66511,53.06126],"type":"Point"}
}