{
  "type": "Feature",
  "properties": {
    "gn:admin1_code":"1.0",
    "gn:admin2_code":"84.0",
    "gn:admin3_code":"8437.0",
    "gn:admin4_code":"8437100.0",
    "gn:asciiname":"Bogenweiler",
    "gn:country_code":"DE",
    "gn:dem":619,
    "gn:feature_class":"P",
    "gn:feature_code":"PPL",
    "gn:name":"Bogenweiler",
    "gn:population":0,
    "gn:timezone":"Europe/Berlin",
    "iso:country":"DE",
    "wof:name":"Bogenweiler",
    "wof:placetype":"neighbourhood"
},
  "geometry": {"coordinates":[9.4916,47.99717],"type":"Point"}
}