{
  "type": "Feature",
  "properties": {
    "gn:admin1_code":"2",
    "gn:admin2_code":"92.0",
    "gn:admin3_code":"9271.0",
    "gn:admin4_code":"9271111.0",
    "gn:asciiname":"Neutiefenweg",
    "gn:country_code":"DE",
    "gn:dem":323,
    "gn:feature_class":"P",
    "gn:feature_code":"PPLL",
    "gn:name":"Neutiefenweg",
    "gn:population":0,
    "gn:timezone":"Europe/Berlin",
    "iso:country":"DE",
    "wof:name":"Neutiefenweg",
    "wof:placetype":"neighbourhood"
},
  "geometry": {"coordinates":[12.86082,48.73354000000001],"type":"Point"}
}