{
  "type": "Feature",
  "properties": {
    "gn:admin1_code":"13",
    "gn:admin2_code":"0.0",
    "gn:admin3_code":"14522.0",
    "gn:admin4_code":"14522300.0",
    "gn:asciiname":"Kriebethal",
    "gn:country_code":"DE",
    "gn:dem":197,
    "gn:feature_class":"P",
    "gn:feature_code":"PPL",
    "gn:name":"Kriebethal",
    "gn:population":0,
    "gn:timezone":"Europe/Berlin",
    "iso:country":"DE",
    "wof:name":"Kriebethal",
    "wof:placetype":"neighbourhood"
},
  "geometry": {"coordinates":[13.01916,51.04971],"type":"Point"}
}