{
  "type": "Feature",
  "properties": {
    "gn:gn_country":"DE",
    "gn:gn_fcode":"PPL",
    "gn:gn_pop":0,
    "iso:country":"DE",
    "name:deu_x_colloquial":[
        "Ludorf",
        "Luedorf"
    ],
    "name:deu_x_preferred":[
        "L\u00fcdorf"
    ],
    "name:unk_x_variant":[
        "L\u00fcdorf"
    ],
    "qs:gn_fcode":"PPL",
    "qs:gn_local":0,
    "qs:gn_namadm1":"07",
    "qs:gn_name":"L\u00fcdorf",
    "qs:local_max":1159,
    "qs:local_sum":2186,
    "qs:localhoods":16,
    "qs:name":"L\u00fcdorf",
    "qs:name_adm0":"Deutschland",
    "qs:name_adm1":"Nordrhein-Westfalen",
    "qs:name_adm2":"Stadtkreis Remscheid",
    "qs:name_lau":"Stadtteil Remscheid",
    "qs:name_local":"Stadtteil Remscheid",
    "qs:photo_max":3,
    "qs:photo_sum":13,
    "qs:placetype":"Suburb",
    "qs:quad_count":8,
    "qs:woe_adm0":23424829,
    "qs:woe_adm1":2345487,
    "qs:woe_adm2":12597081,
    "qs:woe_lau":28350224,
    "qs:woe_local":28350224,
    "qs:woe_ver":"7.10.0",
    "qs_pg:aaroncc":"DE",
    "qs_pg:gn_country":"DE",
    "qs_pg:gn_fcode":"PPL",
    "qs_pg:gn_pop":0,
    "qs_pg:name":"L\u00fcdorf",
    "qs_pg:name_adm0":"Deutschland",
    "qs_pg:name_adm1":"Nordrhein-Westfalen",
    "qs_pg:photos":12,
    "qs_pg:photos_1k":2,
    "qs_pg:photos_9k":1,
    "qs_pg:photos_9r":1,
    "qs_pg:photos_all":12,
    "qs_pg:photos_sr":1,
    "qs_pg:pop_sr":0,
    "qs_pg:qs_pg_placetype":"neighbourhood",
    "qs_pg:qs_pg_placetype_gp":"Suburb",
    "qs_pg:woe_adm0":23424829,
    "wof:lang":[
        "ger"
    ],
    "wof:name":"L\u00fcdorf",
    "wof:placetype":"neighbourhood"
},
  "geometry": {"coordinates":[7.265132,51.170204],"type":"Point"}
}