{
  "type": "Feature",
  "properties": {
    "gn:admin1_code":"2",
    "gn:admin2_code":"97.0",
    "gn:admin3_code":"9780.0",
    "gn:admin4_code":"9780132.0",
    "gn:asciiname":"Pfalzen",
    "gn:country_code":"DE",
    "gn:dem":803,
    "gn:feature_class":"P",
    "gn:feature_code":"PPL",
    "gn:name":"Pfalzen",
    "gn:population":0,
    "gn:timezone":"Europe/Berlin",
    "iso:country":"DE",
    "name:bul_x_preferred":[
        "\u0424\u0430\u043b\u0446\u0435\u0441"
    ],
    "name:cat_x_preferred":[
        "Pfalzen"
    ],
    "name:deu_x_preferred":[
        "Pfalzen"
    ],
    "name:epo_x_preferred":[
        "Pfalzen"
    ],
    "name:est_x_preferred":[
        "Pfalzen"
    ],
    "name:eus_x_preferred":[
        "Pfalzen"
    ],
    "name:fra_x_preferred":[
        "Falzes"
    ],
    "name:hun_x_preferred":[
        "Falzes"
    ],
    "name:hye_x_preferred":[
        "\u0556\u0561\u056c\u0581\u0565\u057d"
    ],
    "name:ina_x_preferred":[
        "Falzes"
    ],
    "name:ita_x_preferred":[
        "Falzes"
    ],
    "name:jpn_x_preferred":[
        "\u30d5\u30a1\u30eb\u30c4\u30a7\u30b9"
    ],
    "name:kaz_x_preferred":[
        "\u0424\u0430\u043b\u044c\u0446\u0435\u0441"
    ],
    "name:lat_x_preferred":[
        "Phalanza"
    ],
    "name:lmo_x_preferred":[
        "Falzes"
    ],
    "name:msa_x_preferred":[
        "Pfalzen"
    ],
    "name:nap_x_preferred":[
        "Falzes"
    ],
    "name:nld_x_preferred":[
        "Pfalzen"
    ],
    "name:pms_x_preferred":[
        "Pfalzen"
    ],
    "name:pol_x_preferred":[
        "Pfalzen"
    ],
    "name:por_x_preferred":[
        "Falzes"
    ],
    "name:ron_x_preferred":[
        "Falzes"
    ],
    "name:rus_x_preferred":[
        "\u0424\u0430\u043b\u044c\u0446\u0435\u0441"
    ],
    "name:scn_x_preferred":[
        "Falzes"
    ],
    "name:spa_x_preferred":[
        "Falzes"
    ],
    "name:srp_x_preferred":[
        "\u0424\u0430\u043b\u0446\u0435\u0441"
    ],
    "name:tgl_x_preferred":[
        "Pfalzen"
    ],
    "name:ukr_x_preferred":[
        "\u0424\u0430\u043b\u044c\u0446\u0435\u0441"
    ],
    "name:vie_x_preferred":[
        "Falzes"
    ],
    "name:vol_x_preferred":[
        "Falzes"
    ],
    "name:war_x_preferred":[
        "Pfalzen"
    ],
    "name:zho_x_preferred":[
        "\u6cd5\u5c14\u6cfd\u65af"
    ],
    "wof:name":"Pfalzen",
    "wof:placetype":"neighbourhood"
},
  "geometry": {"coordinates":[10.02155,47.5598],"type":"Point"}
}