{
  "type": "Feature",
  "properties": {
    "gn:admin1_code":"8.0",
    "gn:admin2_code":"0.0",
    "gn:admin3_code":"7134.0",
    "gn:admin4_code":"7134042.0",
    "gn:asciiname":"Bleiderdingen",
    "gn:country_code":"DE",
    "gn:dem":353,
    "gn:feature_class":"P",
    "gn:feature_code":"PPL",
    "gn:name":"Bleiderdingen",
    "gn:population":0,
    "gn:timezone":"Europe/Berlin",
    "iso:country":"DE",
    "wof:name":"Bleiderdingen",
    "wof:placetype":"neighbourhood"
},
  "geometry": {"coordinates":[7.19747,49.61035],"type":"Point"}
}