{
  "type": "Feature",
  "properties": {
    "gn:admin1_code":"2",
    "gn:admin2_code":"93.0",
    "gn:admin3_code":"9374.0",
    "gn:admin4_code":"9374146.0",
    "gn:asciiname":"Matzlesberg",
    "gn:country_code":"DE",
    "gn:dem":446,
    "gn:feature_class":"P",
    "gn:feature_code":"PPL",
    "gn:name":"Matzlesberg",
    "gn:population":0,
    "gn:timezone":"Europe/Berlin",
    "iso:country":"DE",
    "wof:name":"Matzlesberg",
    "wof:placetype":"neighbourhood"
},
  "geometry": {"coordinates":[12.21423,49.59288],"type":"Point"}
}