{
  "type": "Feature",
  "properties": {
    "gn:admin1_code":"1.0",
    "gn:admin2_code":"81.0",
    "gn:admin3_code":"8126.0",
    "gn:admin4_code":"8126072.0",
    "gn:asciiname":"Bieringen",
    "gn:country_code":"DE",
    "gn:dem":223,
    "gn:feature_class":"P",
    "gn:feature_code":"PPL",
    "gn:name":"Bieringen",
    "gn:population":0,
    "gn:timezone":"Europe/Berlin",
    "iso:country":"DE",
    "wof:name":"Bieringen",
    "wof:placetype":"neighbourhood"
},
  "geometry": {"coordinates":[9.52963,49.3439],"type":"Point"}
}