{
  "type": "Feature",
  "properties": {
    "gn:admin1_code":"1",
    "gn:admin2_code":"81.0",
    "gn:admin3_code":"8125.0",
    "gn:admin4_code":"8125006.0",
    "gn:asciiname":"Grombach",
    "gn:country_code":"DE",
    "gn:dem":246,
    "gn:feature_class":"P",
    "gn:feature_code":"PPL",
    "gn:name":"Grombach",
    "gn:population":0,
    "gn:timezone":"Europe/Berlin",
    "iso:country":"DE",
    "wof:name":"Grombach",
    "wof:placetype":"neighbourhood"
},
  "geometry": {"coordinates":[8.99606,49.22684],"type":"Point"}
}