{
  "type": "Feature",
  "properties": {
    "gn:admin1_code":"2",
    "gn:admin2_code":"92.0",
    "gn:admin3_code":"9275.0",
    "gn:admin4_code":"9275118.0",
    "gn:asciiname":"Ungarsteig",
    "gn:country_code":"DE",
    "gn:dem":658,
    "gn:feature_class":"P",
    "gn:feature_code":"PPLL",
    "gn:name":"Ungarsteig",
    "gn:population":0,
    "gn:timezone":"Europe/Berlin",
    "iso:country":"DE",
    "wof:name":"Ungarsteig",
    "wof:placetype":"neighbourhood"
},
  "geometry": {"coordinates":[13.77857,48.71271],"type":"Point"}
}