{
  "type": "Feature",
  "properties": {
    "gn:admin1_code":"5",
    "gn:admin2_code":"66.0",
    "gn:admin3_code":"6634.0",
    "gn:admin4_code":"6634005.0",
    "gn:asciiname":"Lohne",
    "gn:country_code":"DE",
    "gn:dem":238,
    "gn:feature_class":"P",
    "gn:feature_code":"PPL",
    "gn:name":"Lohne",
    "gn:population":0,
    "gn:timezone":"Europe/Berlin",
    "iso:country":"DE",
    "name:ceb_x_preferred":[
        "Lohne"
    ],
    "name:deu_x_preferred":[
        "Lohne"
    ],
    "name:fra_x_preferred":[
        "Lohne"
    ],
    "name:nld_x_preferred":[
        "Lohne"
    ],
    "name:pol_x_preferred":[
        "Lohne"
    ],
    "wof:name":"Lohne",
    "wof:placetype":"neighbourhood"
},
  "geometry": {"coordinates":[9.26779,51.18037],"type":"Point"}
}