{
  "type": "Feature",
  "properties": {
    "gn:admin1_code":"2.0",
    "gn:admin2_code":"093",
    "gn:admin3_code":"9376.0",
    "gn:admin4_code":"9376161.0",
    "gn:asciiname":"Wiefelsdorf",
    "gn:country_code":"DE",
    "gn:dem":390,
    "gn:feature_class":"P",
    "gn:feature_code":"PPL",
    "gn:name":"Wiefelsdorf",
    "gn:population":0,
    "gn:timezone":"Europe/Berlin",
    "iso:country":"DE",
    "wof:name":"Wiefelsdorf",
    "wof:placetype":"neighbourhood"
},
  "geometry": {"coordinates":[12.0769,49.27932],"type":"Point"}
}