{
  "type": "Feature",
  "properties": {
    "gn:admin1_code":"8.0",
    "gn:admin2_code":"00",
    "gn:admin3_code":"7235.0",
    "gn:admin4_code":"7235111.0",
    "gn:asciiname":"Wintersdorf",
    "gn:country_code":"DE",
    "gn:dem":166,
    "gn:feature_class":"P",
    "gn:feature_code":"PPL",
    "gn:name":"Wintersdorf",
    "gn:population":0,
    "gn:timezone":"Europe/Berlin",
    "iso:country":"DE",
    "name:bak_x_preferred":[
        "\u0412\u0438\u043d\u0442\u0435\u0440\u0441\u0434\u043e\u0440\u0444"
    ],
    "name:ceb_x_preferred":[
        "Wintersdorf"
    ],
    "name:deu_x_preferred":[
        "Wintersdorf"
    ],
    "name:fas_x_preferred":[
        "\u0648\u06cc\u0646\u062a\u0631\u0633\u062f\u0648\u0631\u0641"
    ],
    "name:kaz_x_preferred":[
        "\u0412\u0438\u043d\u0442\u0435\u0440\u0441\u0434\u043e\u0440\u0444"
    ],
    "name:kir_x_preferred":[
        "\u0412\u0438\u043d\u0442\u0435\u0440\u0441\u0434\u043e\u0440\u0444"
    ],
    "name:mkd_x_preferred":[
        "\u0412\u0438\u043d\u0442\u0435\u0440\u0441\u0434\u043e\u0440\u0444"
    ],
    "name:nld_x_preferred":[
        "Wintersdorf"
    ],
    "name:ron_x_preferred":[
        "Wintersdorf"
    ],
    "name:rus_x_preferred":[
        "\u0412\u0438\u043d\u0442\u0435\u0440\u0441\u0434\u043e\u0440\u0444"
    ],
    "name:uzb_x_preferred":[
        "Wintersdorf"
    ],
    "wof:name":"Wintersdorf",
    "wof:placetype":"neighbourhood"
},
  "geometry": {"coordinates":[6.51212,49.78859],"type":"Point"}
}