{
  "type": "Feature",
  "properties": {
    "gn:admin1_code":"8.0",
    "gn:admin2_code":"00",
    "gn:admin3_code":"7235.0",
    "gn:admin4_code":"7235111.0",
    "gn:asciiname":"Wintersdorf",
    "gn:country_code":"DE",
    "gn:dem":166,
    "gn:feature_class":"P",
    "gn:feature_code":"PPL",
    "gn:name":"Wintersdorf",
    "gn:population":0,
    "gn:timezone":"Europe/Berlin",
    "iso:country":"DE",
    "wof:name":"Wintersdorf",
    "wof:placetype":"neighbourhood"
},
  "geometry": {"coordinates":[6.51212,49.78859],"type":"Point"}
}