{
  "type": "Feature",
  "properties": {
    "gn:country":"DE",
    "gn:fcode":"PPL",
    "gn:population":0,
    "iso:country":"DE",
    "name:dan_x_preferred":[
        "Westfeld"
    ],
    "name:deu_x_preferred":[
        "Westfeld"
    ],
    "name:epo_x_preferred":[
        "Westfeld"
    ],
    "name:eus_x_preferred":[
        "Westfeld"
    ],
    "name:fas_x_preferred":[
        "\u0648\u0634\u062a\u0641\u0644\u062f"
    ],
    "name:fra_x_preferred":[
        "Westfeld"
    ],
    "name:hun_x_preferred":[
        "Westfeld"
    ],
    "name:ita_x_preferred":[
        "Westfeld"
    ],
    "name:kaz_x_preferred":[
        "\u0412\u0435\u0441\u0442\u0444\u0435\u043b\u044c\u0434"
    ],
    "name:kir_x_preferred":[
        "\u0412\u0435\u0441\u0442\u0444\u0435\u043b\u044c\u0434"
    ],
    "name:lat_x_preferred":[
        "Westfeld"
    ],
    "name:mkd_x_preferred":[
        "\u0412\u0435\u0441\u0442\u0444\u0435\u043b\u0434"
    ],
    "name:msa_x_preferred":[
        "Westfeld"
    ],
    "name:nld_x_preferred":[
        "Westfeld"
    ],
    "name:pol_x_preferred":[
        "Westfeld"
    ],
    "name:por_x_preferred":[
        "Westfeld"
    ],
    "name:ron_x_preferred":[
        "Westfeld"
    ],
    "name:rus_x_preferred":[
        "\u0412\u0435\u0441\u0442\u0444\u0435\u043b\u044c\u0434"
    ],
    "name:srp_x_preferred":[
        "\u0412\u0435\u0441\u0442\u0444\u0435\u043b\u0434"
    ],
    "name:uzb_x_preferred":[
        "Westfeld"
    ],
    "name:vie_x_preferred":[
        "Westfeld"
    ],
    "name:vol_x_preferred":[
        "Westfeld"
    ],
    "name:war_x_preferred":[
        "Westfeld"
    ],
    "name:zho_x_preferred":[
        "\u97e6\u65af\u7279\u8d39\u5c14\u5fb7"
    ],
    "qs_pg:aaroncc":"DE",
    "qs_pg:gn_country":"DE",
    "qs_pg:gn_fcode":"PPL",
    "qs_pg:gn_pop":0,
    "qs_pg:name":"Westfeld",
    "qs_pg:name_adm0":"Deutschland",
    "qs_pg:name_adm1":"Nordrhein-Westfalen",
    "qs_pg:photos":31,
    "qs_pg:photos_1k":6,
    "qs_pg:photos_9k":1,
    "qs_pg:photos_9r":2,
    "qs_pg:photos_all":31,
    "qs_pg:photos_sr":2,
    "qs_pg:pop_sr":0,
    "qs_pg:qs_pg_placetype":"locality",
    "qs_pg:qs_pg_placetype_gp":"Town",
    "qs_pg:woe_adm0":23424829,
    "woe:adm0_id":23424829,
    "woe:name_adm0":"Deutschland",
    "woe:name_adm1":"Nordrhein-Westfalen",
    "woe:placetype":"Town",
    "wof:name":"Westfeld",
    "wof:placetype":"neighbourhood"
},
  "geometry": {"coordinates":[8.41899,51.1607],"type":"Point"}
}