{
  "type": "Feature",
  "properties": {
    "gn:admin1_code":"10.0",
    "gn:admin2_code":"00",
    "gn:admin3_code":"1051.0",
    "gn:admin4_code":"1051081.0",
    "gn:asciiname":"Wellinghusen",
    "gn:country_code":"DE",
    "gn:dem":1,
    "gn:feature_class":"P",
    "gn:feature_code":"PPL",
    "gn:name":"Wellinghusen",
    "gn:population":0,
    "gn:timezone":"Europe/Berlin",
    "iso:country":"DE",
    "wof:name":"Wellinghusen",
    "wof:placetype":"neighbourhood"
},
  "geometry": {"coordinates":[8.96595,54.17762],"type":"Point"}
}