{
  "type": "Feature",
  "properties": {
    "gn:admin1_code":"1",
    "gn:admin2_code":"81.0",
    "gn:admin3_code":"8128.0",
    "gn:admin4_code":"8128020.0",
    "gn:asciiname":"Standorf",
    "gn:country_code":"DE",
    "gn:dem":377,
    "gn:feature_class":"P",
    "gn:feature_code":"PPL",
    "gn:name":"Standorf",
    "gn:population":0,
    "gn:timezone":"Europe/Berlin",
    "iso:country":"DE",
    "wof:name":"Standorf",
    "wof:placetype":"neighbourhood"
},
  "geometry": {"coordinates":[9.99911,49.44386],"type":"Point"}
}