{
  "type": "Feature",
  "properties": {
    "gn:admin1_code":"1.0",
    "gn:admin2_code":"84.0",
    "gn:admin3_code":"8426.0",
    "gn:admin4_code":"8426135.0",
    "gn:asciiname":"Allmethofen",
    "gn:country_code":"DE",
    "gn:dem":553,
    "gn:feature_class":"P",
    "gn:feature_code":"PPL",
    "gn:name":"Allmethofen",
    "gn:population":0,
    "gn:timezone":"Europe/Berlin",
    "iso:country":"DE",
    "wof:name":"Allmethofen",
    "wof:placetype":"neighbourhood"
},
  "geometry": {"coordinates":[9.95,48.13333],"type":"Point"}
}