{
  "type": "Feature",
  "properties": {
    "gn:admin1_code":"6",
    "gn:admin2_code":"0.0",
    "gn:admin3_code":"3354.0",
    "gn:admin4_code":"3354018.0",
    "gn:asciiname":"Loge",
    "gn:country_code":"DE",
    "gn:dem":18,
    "gn:feature_class":"P",
    "gn:feature_code":"PPL",
    "gn:name":"Loge",
    "gn:population":0,
    "gn:timezone":"Europe/Berlin",
    "iso:country":"DE",
    "name:ceb_x_preferred":[
        "Loge"
    ],
    "name:dan_x_preferred":[
        "Loge"
    ],
    "name:deu_x_preferred":[
        "Loge"
    ],
    "name:epo_x_preferred":[
        "Lo\u011dio"
    ],
    "name:fra_x_preferred":[
        "Loge"
    ],
    "name:nld_x_preferred":[
        "Loge"
    ],
    "name:swe_x_preferred":[
        "Loge"
    ],
    "wof:name":"Loge",
    "wof:placetype":"neighbourhood"
},
  "geometry": {"coordinates":[11.18291,52.95882],"type":"Point"}
}