{
  "type": "Feature",
  "properties": {
    "gn:admin1_code":"15",
    "gn:admin2_code":"0.0",
    "gn:admin3_code":"16073.0",
    "gn:admin4_code":"16073111.0",
    "gn:asciiname":"Dorfkulm",
    "gn:country_code":"DE",
    "gn:dem":350,
    "gn:feature_class":"P",
    "gn:feature_code":"PPL",
    "gn:name":"Dorfkulm",
    "gn:population":0,
    "gn:timezone":"Europe/Berlin",
    "iso:country":"DE",
    "wof:name":"Dorfkulm",
    "wof:placetype":"neighbourhood"
},
  "geometry": {"coordinates":[11.37179,50.68024000000001],"type":"Point"}
}