{
  "type": "Feature",
  "properties": {
    "iso:country":"DE",
    "name:eng_x_variant":[
        "Schlo\u00df Styrum"
    ],
    "name:unk_x_variant":[
        "Schlo\u00df Styrum"
    ],
    "qs:gn_adm0_cc":"DE",
    "qs:gn_local":2867838,
    "qs:gn_nam_loc":"M\u00fclheim an der Ruhr, Nordrhein-Westfalen, DE",
    "qs:gn_namadm1":"07",
    "qs:local_max":6349,
    "qs:local_sum":9575,
    "qs:localhoods":14,
    "qs:name":"Schlo\u00df Styrum",
    "qs:name_adm0":"Deutschland",
    "qs:name_adm1":"Nordrhein-Westfalen",
    "qs:name_adm2":"Stadtkreis M\u00fclheim an der Ruhr",
    "qs:name_en":"Schlo\u00df Styrum",
    "qs:name_lau":"Stadtteil M\u00fclheim an der Ruhr",
    "qs:name_local":"Stadtteil M\u00fclheim an der Ruhr",
    "qs:photo_max":3,
    "qs:photo_sum":26,
    "qs:placetype":"Suburb",
    "qs:quad_count":15,
    "qs:woe_adm0":23424829,
    "qs:woe_adm1":2345487,
    "qs:woe_adm2":12597066,
    "qs:woe_lau":28350219,
    "qs:woe_local":28350219,
    "qs:woe_ver":"7.3.1",
    "wof:name":"Schlo\u00df Styrum",
    "wof:placetype":"neighbourhood"
},
  "geometry": {"coordinates":[6.858398,51.438487],"type":"Point"}
}