{
  "type": "Feature",
  "properties": {
    "gn:admin1_code":"13.0",
    "gn:admin2_code":"0.0",
    "gn:admin3_code":"14626.0",
    "gn:admin4_code":"14626230.0",
    "gn:asciiname":"Rengersdorf (Lausitz)",
    "gn:country_code":"DE",
    "gn:dem":188,
    "gn:feature_class":"P",
    "gn:feature_code":"PPL",
    "gn:name":"Rengersdorf (Lausitz)",
    "gn:population":0,
    "gn:timezone":"Europe/Berlin",
    "iso:country":"DE",
    "wof:name":"Rengersdorf (Lausitz)",
    "wof:placetype":"neighbourhood"
},
  "geometry": {"coordinates":[14.89489,51.22207],"type":"Point"}
}