{
  "type": "Feature",
  "properties": {
    "gn:admin1_code":"7",
    "gn:admin2_code":"53.0",
    "gn:admin3_code":"5378.0",
    "gn:admin4_code":"5378004.0",
    "gn:asciiname":"Dombach",
    "gn:country_code":"DE",
    "gn:dem":123,
    "gn:feature_class":"P",
    "gn:feature_code":"PPL",
    "gn:name":"Dombach",
    "gn:population":0,
    "gn:timezone":"Europe/Berlin",
    "iso:country":"DE",
    "name:deu_x_preferred":[
        "Dombach"
    ],
    "wof:name":"Dombach",
    "wof:placetype":"neighbourhood"
},
  "geometry": {"coordinates":[7.15577,50.99465],"type":"Point"}
}