{
  "type": "Feature",
  "properties": {
    "gn:admin1_code":"13",
    "gn:admin2_code":"0.0",
    "gn:admin3_code":"14522.0",
    "gn:admin4_code":"14522600.0",
    "gn:asciiname":"Ceesewitz",
    "gn:country_code":"DE",
    "gn:dem":254,
    "gn:feature_class":"P",
    "gn:feature_code":"PPL",
    "gn:name":"Ceesewitz",
    "gn:population":0,
    "gn:timezone":"Europe/Berlin",
    "iso:country":"DE",
    "wof:name":"Ceesewitz",
    "wof:placetype":"neighbourhood"
},
  "geometry": {"coordinates":[12.82009,51.06914],"type":"Point"}
}