{
  "type": "Feature",
  "properties": {
    "gn:admin1_code":"2",
    "gn:admin2_code":"91.0",
    "gn:admin3_code":"9183.0",
    "gn:admin4_code":"9183124.0",
    "gn:asciiname":"Ensdorf",
    "gn:country_code":"DE",
    "gn:dem":418,
    "gn:feature_class":"P",
    "gn:feature_code":"PPL",
    "gn:name":"Ensdorf",
    "gn:population":0,
    "gn:timezone":"Europe/Berlin",
    "iso:country":"DE",
    "name:cat_x_preferred":[
        "Ensdorf"
    ],
    "name:ceb_x_preferred":[
        "Ensdorf"
    ],
    "name:deu_x_preferred":[
        "Ensdorf"
    ],
    "name:epo_x_preferred":[
        "Ensdorf"
    ],
    "name:fra_x_preferred":[
        "Ensdorf"
    ],
    "name:ita_x_preferred":[
        "Ensdorf"
    ],
    "name:kaz_x_preferred":[
        "\u042d\u043d\u0441\u0434\u043e\u0440\u0444"
    ],
    "name:nld_x_preferred":[
        "Ensdorf"
    ],
    "name:pol_x_preferred":[
        "Ensdorf"
    ],
    "name:rus_x_preferred":[
        "\u042d\u043d\u0441\u0434\u043e\u0440\u0444"
    ],
    "name:spa_x_preferred":[
        "Ensdorf"
    ],
    "name:srp_x_preferred":[
        "\u0415\u043d\u0441\u0434\u043e\u0440\u0444"
    ],
    "name:swe_x_preferred":[
        "Ensdorf"
    ],
    "name:vol_x_preferred":[
        "Ensdorf"
    ],
    "name:zho_x_preferred":[
        "\u6069\u65af\u591a\u592b"
    ],
    "wof:name":"Ensdorf",
    "wof:placetype":"neighbourhood"
},
  "geometry": {"coordinates":[12.44691,48.1864],"type":"Point"}
}