{
  "type": "Feature",
  "properties": {
    "gn:admin1_code":"13",
    "gn:admin2_code":"0.0",
    "gn:admin3_code":"14523.0",
    "gn:admin4_code":"14523245.0",
    "gn:asciiname":"Pechseifen",
    "gn:country_code":"DE",
    "gn:dem":680,
    "gn:feature_class":"P",
    "gn:feature_code":"PPL",
    "gn:name":"Pechseifen",
    "gn:population":0,
    "gn:timezone":"Europe/Berlin",
    "iso:country":"DE",
    "wof:name":"Pechseifen",
    "wof:placetype":"neighbourhood"
},
  "geometry": {"coordinates":[12.46129,50.43241],"type":"Point"}
}