{
  "type": "Feature",
  "properties": {
    "gn:admin1_code":"10",
    "gn:admin2_code":"0.0",
    "gn:admin3_code":"1054.0",
    "gn:admin4_code":"1054166.0",
    "gn:asciiname":"Hunwerthhusum",
    "gn:country_code":"DE",
    "gn:dem":0,
    "gn:feature_class":"P",
    "gn:feature_code":"PPL",
    "gn:name":"Hunwerthhusum",
    "gn:population":0,
    "gn:timezone":"Europe/Berlin",
    "iso:country":"DE",
    "wof:name":"Hunwerthhusum",
    "wof:placetype":"neighbourhood"
},
  "geometry": {"coordinates":[8.65,54.81667],"type":"Point"}
}