{
  "type": "Feature",
  "properties": {
    "gn:admin1_code":"7.0",
    "gn:admin2_code":"051",
    "gn:admin3_code":"5154.0",
    "gn:admin4_code":"5154044.0",
    "gn:asciiname":"Wittenhorst",
    "gn:country_code":"DE",
    "gn:dem":19,
    "gn:feature_class":"P",
    "gn:feature_code":"PPL",
    "gn:name":"Wittenhorst",
    "gn:population":0,
    "gn:timezone":"Europe/Berlin",
    "iso:country":"DE",
    "wof:name":"Wittenhorst",
    "wof:placetype":"neighbourhood"
},
  "geometry": {"coordinates":[6.51608,51.76796],"type":"Point"}
}