{
  "type": "Feature",
  "properties": {
    "gn:admin1_code":"15",
    "gn:admin2_code":"0.0",
    "gn:admin3_code":"16067.0",
    "gn:admin4_code":"16067088.0",
    "gn:asciiname":"Laucha",
    "gn:country_code":"DE",
    "gn:dem":302,
    "gn:feature_class":"P",
    "gn:feature_code":"PPL",
    "gn:name":"Laucha",
    "gn:population":533,
    "gn:timezone":"Europe/Berlin",
    "iso:country":"DE",
    "name:ceb_x_preferred":[
        "Laucha"
    ],
    "name:deu_x_preferred":[
        "Laucha"
    ],
    "name:epo_x_preferred":[
        "Laucha"
    ],
    "name:hsb_x_preferred":[
        "Laucha"
    ],
    "name:nld_x_preferred":[
        "Laucha"
    ],
    "name:pol_x_preferred":[
        "Laucha"
    ],
    "name:rus_x_preferred":[
        "\u041b\u0430\u0443\u0445\u0430"
    ],
    "name:srp_x_preferred":[
        "\u041b\u0430\u0443\u0445\u0430"
    ],
    "name:swe_x_preferred":[
        "Laucha"
    ],
    "wof:name":"Laucha",
    "wof:placetype":"neighbourhood",
    "wof:population":533
},
  "geometry": {"coordinates":[10.54313,50.92582],"type":"Point"}
}