{
  "type": "Feature",
  "properties": {
    "gn:admin1_code":"13",
    "gn:admin2_code":"0.0",
    "gn:admin3_code":"14729.0",
    "gn:admin4_code":"14729080.0",
    "gn:asciiname":"Erlln",
    "gn:country_code":"DE",
    "gn:dem":196,
    "gn:feature_class":"P",
    "gn:feature_code":"PPL",
    "gn:name":"Erlln",
    "gn:population":0,
    "gn:timezone":"Europe/Berlin",
    "iso:country":"DE",
    "wof:name":"Erlln",
    "wof:placetype":"neighbourhood"
},
  "geometry": {"coordinates":[12.81667,51.15],"type":"Point"}
}