{
  "type": "Feature",
  "properties": {
    "gn:admin1_code":"2",
    "gn:admin2_code":"93.0",
    "gn:admin3_code":"9371.0",
    "gn:admin4_code":"9371121.0",
    "gn:asciiname":"Konradinsgrund",
    "gn:country_code":"DE",
    "gn:dem":433,
    "gn:feature_class":"P",
    "gn:feature_code":"PPL",
    "gn:name":"Konradinsgrund",
    "gn:population":0,
    "gn:timezone":"Europe/Berlin",
    "iso:country":"DE",
    "wof:name":"Konradinsgrund",
    "wof:placetype":"neighbourhood"
},
  "geometry": {"coordinates":[11.95107,49.63017],"type":"Point"}
}