{
  "type": "Feature",
  "properties": {
    "gn:admin1_code":"6.0",
    "gn:admin2_code":"0.0",
    "gn:admin3_code":"3352.0",
    "gn:admin4_code":"3352032.0",
    "gn:asciiname":"Bexhoevede",
    "gn:country_code":"DE",
    "gn:dem":12,
    "gn:feature_class":"P",
    "gn:feature_code":"PPL",
    "gn:name":"Bexh\u00f6vede",
    "gn:population":0,
    "gn:timezone":"Europe/Berlin",
    "iso:country":"DE",
    "name:deu_x_preferred":[
        "Bexh\u00f6vede"
    ],
    "name:fas_x_preferred":[
        "\u0628\u06a9\u0633\u0647\u0648\u0641\u062f\u0647"
    ],
    "name:fin_x_preferred":[
        "Bexh\u00f6vede"
    ],
    "name:nds_x_preferred":[
        "Bexh\u00f6v"
    ],
    "name:nld_x_preferred":[
        "Bexh\u00f6vede"
    ],
    "name:rus_x_preferred":[
        "\u0411\u0435\u043a\u0441\u0445\u0451\u0444\u0435\u0434\u0435"
    ],
    "name:ukr_x_preferred":[
        "\u0411\u0435\u043a\u0441\u0433\u0435\u0444\u0435\u0434\u0435"
    ],
    "wof:name":"Bexhoevede",
    "wof:placetype":"neighbourhood"
},
  "geometry": {"coordinates":[8.68967,53.48584],"type":"Point"}
}