{
  "type": "Feature",
  "properties": {
    "gn:admin1_code":"7.0",
    "gn:admin2_code":"057",
    "gn:admin3_code":"5766.0",
    "gn:admin4_code":"5766032.0",
    "gn:asciiname":"Wilberg",
    "gn:country_code":"DE",
    "gn:dem":190,
    "gn:feature_class":"P",
    "gn:feature_code":"PPL",
    "gn:name":"Wilberg",
    "gn:population":0,
    "gn:timezone":"Europe/Berlin",
    "iso:country":"DE",
    "wof:name":"Wilberg",
    "wof:placetype":"neighbourhood"
},
  "geometry": {"coordinates":[8.95712,51.89646],"type":"Point"}
}