{
  "type": "Feature",
  "properties": {
    "gn:admin1_code":"2",
    "gn:admin2_code":"92.0",
    "gn:admin3_code":"9277.0",
    "gn:admin4_code":"9277121.0",
    "gn:asciiname":"Taubendorf",
    "gn:country_code":"DE",
    "gn:dem":451,
    "gn:feature_class":"P",
    "gn:feature_code":"PPL",
    "gn:name":"Taubendorf",
    "gn:population":0,
    "gn:timezone":"Europe/Berlin",
    "iso:country":"DE",
    "wof:name":"Taubendorf",
    "wof:placetype":"neighbourhood"
},
  "geometry": {"coordinates":[12.59605,48.5053],"type":"Point"}
}