{
  "type": "Feature",
  "properties": {
    "gn:admin1_code":"1",
    "gn:admin2_code":"81.0",
    "gn:admin3_code":"8126.0",
    "gn:admin4_code":"8126069.0",
    "gn:asciiname":"Harsberg",
    "gn:country_code":"DE",
    "gn:dem":256,
    "gn:feature_class":"P",
    "gn:feature_code":"PPL",
    "gn:name":"Harsberg",
    "gn:population":0,
    "gn:timezone":"Europe/Berlin",
    "iso:country":"DE",
    "wof:name":"Harsberg",
    "wof:placetype":"neighbourhood"
},
  "geometry": {"coordinates":[9.53878,49.15695],"type":"Point"}
}