{
  "type": "Feature",
  "properties": {
    "iso:country":"DE",
    "wof:name":"Oberbarmen",
    "wof:placetype":"neighbourhood"
},
  "geometry": {"coordinates":[7.22696115995424,51.29071002732015],"type":"Point"}
}