{
  "type": "Feature",
  "properties": {
    "gn:admin1_code":"2",
    "gn:admin2_code":"95.0",
    "gn:admin3_code":"9574.0",
    "gn:admin4_code":"9574128.0",
    "gn:asciiname":"Molsberg",
    "gn:country_code":"DE",
    "gn:dem":514,
    "gn:feature_class":"P",
    "gn:feature_code":"PPL",
    "gn:name":"Molsberg",
    "gn:population":0,
    "gn:timezone":"Europe/Berlin",
    "iso:country":"DE",
    "wof:name":"Molsberg",
    "wof:placetype":"neighbourhood"
},
  "geometry": {"coordinates":[11.49745,49.44882],"type":"Point"}
}