{
  "type": "Feature",
  "properties": {
    "gn:admin1_code":"12",
    "gn:admin2_code":"0.0",
    "gn:admin3_code":"13072.0",
    "gn:admin4_code":"13072045.0",
    "gn:asciiname":"Klein Koethel",
    "gn:country_code":"DE",
    "gn:dem":28,
    "gn:feature_class":"P",
    "gn:feature_code":"PPL",
    "gn:name":"Klein K\u00f6thel",
    "gn:population":0,
    "gn:timezone":"Europe/Berlin",
    "iso:country":"DE",
    "wof:name":"Klein Koethel",
    "wof:placetype":"neighbourhood"
},
  "geometry": {"coordinates":[12.53969,53.75308],"type":"Point"}
}