{
  "type": "Feature",
  "properties": {
    "gn:admin1_code":"2",
    "gn:admin2_code":"96.0",
    "gn:admin3_code":"9673.0",
    "gn:admin4_code":"9673141.0",
    "gn:asciiname":"Merkershausen",
    "gn:country_code":"DE",
    "gn:dem":292,
    "gn:feature_class":"P",
    "gn:feature_code":"PPL",
    "gn:name":"Merkershausen",
    "gn:population":0,
    "gn:timezone":"Europe/Berlin",
    "iso:country":"DE",
    "wof:name":"Merkershausen",
    "wof:placetype":"neighbourhood"
},
  "geometry": {"coordinates":[10.4447,50.28661],"type":"Point"}
}