{
  "type": "Feature",
  "properties": {
    "gn:admin1_code":"6",
    "gn:admin2_code":"0.0",
    "gn:admin3_code":"3241.0",
    "gn:admin4_code":"3241003.0",
    "gn:asciiname":"Heessel",
    "gn:country_code":"DE",
    "gn:dem":59,
    "gn:elevation":"58.0",
    "gn:feature_class":"P",
    "gn:feature_code":"PPL",
    "gn:name":"Hee\u00dfel",
    "gn:population":0,
    "gn:timezone":"Europe/Berlin",
    "iso:country":"DE",
    "name:ceb_x_preferred":[
        "Hee\u00dfel"
    ],
    "name:deu_x_preferred":[
        "Hee\u00dfel"
    ],
    "name:fas_x_preferred":[
        "\u0647\u06cc\u0633\u0644"
    ],
    "name:nld_x_preferred":[
        "Hee\u00dfel"
    ],
    "wof:name":"Heessel",
    "wof:placetype":"neighbourhood"
},
  "geometry": {"coordinates":[9.98056,52.44387],"type":"Point"}
}