{
  "type": "Feature",
  "properties": {
    "gn:admin1_code":"8",
    "gn:admin2_code":"0.0",
    "gn:admin3_code":"7320.0",
    "gn:admin4_code":"7320000.0",
    "gn:asciiname":"Ernstweilerthalhof",
    "gn:country_code":"DE",
    "gn:dem":259,
    "gn:feature_class":"P",
    "gn:feature_code":"PPL",
    "gn:name":"Ernstweilerthalhof",
    "gn:population":0,
    "gn:timezone":"Europe/Berlin",
    "iso:country":"DE",
    "name:und_x_variant":[
        "Dibeliushof",
        "Ernstweilerthalhof"
    ],
    "wof:name":"Ernstweilerthalhof",
    "wof:placetype":"neighbourhood"
},
  "geometry": {"coordinates":[7.36018,49.26789],"type":"Point"}
}