{
  "type": "Feature",
  "properties": {
    "gn:admin1_code":"2",
    "gn:admin2_code":"97.0",
    "gn:admin3_code":"9776.0",
    "gn:admin4_code":"9776131.0",
    "gn:asciiname":"Schreckelberg",
    "gn:country_code":"DE",
    "gn:dem":564,
    "gn:feature_class":"P",
    "gn:feature_code":"PPL",
    "gn:name":"Schreckelberg",
    "gn:population":0,
    "gn:timezone":"Europe/Berlin",
    "iso:country":"DE",
    "wof:name":"Schreckelberg",
    "wof:placetype":"locality"
},
  "geometry": {"coordinates":[9.83333,47.66667],"type":"Point"}
}