{
  "type": "Feature",
  "properties": {
    "gn:admin1_code":"2",
    "gn:admin2_code":"92.0",
    "gn:admin3_code":"9275.0",
    "gn:admin4_code":"9275125.0",
    "gn:asciiname":"Grongorgen",
    "gn:country_code":"DE",
    "gn:dem":383,
    "gn:feature_class":"P",
    "gn:feature_code":"PPL",
    "gn:name":"Grong\u00f6rgen",
    "gn:population":0,
    "gn:timezone":"Europe/Berlin",
    "iso:country":"DE",
    "wof:name":"Grongorgen",
    "wof:placetype":"neighbourhood"
},
  "geometry": {"coordinates":[13.12832,48.49737],"type":"Point"}
}