{
  "type": "Feature",
  "properties": {
    "gn:admin1_code":"1.0",
    "gn:admin2_code":"84.0",
    "gn:admin3_code":"8435.0",
    "gn:admin4_code":"8435059.0",
    "gn:asciiname":"Andelshofen",
    "gn:country_code":"DE",
    "gn:dem":488,
    "gn:feature_class":"P",
    "gn:feature_code":"PPL",
    "gn:name":"Andelshofen",
    "gn:population":0,
    "gn:timezone":"Europe/Berlin",
    "iso:country":"DE",
    "wof:name":"Andelshofen",
    "wof:placetype":"locality"
},
  "geometry": {"coordinates":[9.18783,47.77992],"type":"Point"}
}