{
  "type": "Feature",
  "properties": {
    "gn:admin1_code":"1",
    "gn:admin2_code":"83.0",
    "gn:admin3_code":"8315.0",
    "gn:admin4_code":"8315070.0",
    "gn:asciiname":"Seppenhofen",
    "gn:country_code":"DE",
    "gn:dem":790,
    "gn:feature_class":"P",
    "gn:feature_code":"PPL",
    "gn:name":"Seppenhofen",
    "gn:population":0,
    "gn:timezone":"Europe/Berlin",
    "iso:country":"DE",
    "wof:name":"Seppenhofen",
    "wof:placetype":"neighbourhood"
},
  "geometry": {"coordinates":[8.34888,47.87389],"type":"Point"}
}