{
  "type": "Feature",
  "properties": {
    "gn:admin1_code":"7.0",
    "gn:admin2_code":"051",
    "gn:admin3_code":"5154.0",
    "gn:admin4_code":"5154052.0",
    "gn:asciiname":"Westerbroek",
    "gn:country_code":"DE",
    "gn:dem":25,
    "gn:feature_class":"P",
    "gn:feature_code":"PPL",
    "gn:name":"Westerbroek",
    "gn:population":0,
    "gn:timezone":"Europe/Berlin",
    "iso:country":"DE",
    "wof:name":"Westerbroek",
    "wof:placetype":"neighbourhood"
},
  "geometry": {"coordinates":[6.24201,51.43665],"type":"Point"}
}