{
  "type": "Feature",
  "properties": {
    "iso:country":"DE",
    "wof:name":"Neumarktviertel",
    "wof:placetype":"neighbourhood"
},
  "geometry": {"coordinates":[6.94932716762233,50.93858847585402],"type":"Point"}
}