{
  "type": "Feature",
  "properties": {
    "gn:admin1_code":"1",
    "gn:admin2_code":"81.0",
    "gn:admin3_code":"8115.0",
    "gn:admin4_code":"8115004.0",
    "gn:asciiname":"Niederreutin",
    "gn:country_code":"DE",
    "gn:dem":479,
    "gn:feature_class":"P",
    "gn:feature_code":"PPL",
    "gn:name":"Niederreutin",
    "gn:population":0,
    "gn:timezone":"Europe/Berlin",
    "iso:country":"DE",
    "wof:name":"Niederreutin",
    "wof:placetype":"neighbourhood"
},
  "geometry": {"coordinates":[8.80553,48.52716],"type":"Point"}
}