{
  "type": "Feature",
  "properties": {
    "gn:admin1_code":"2",
    "gn:admin2_code":"94.0",
    "gn:admin3_code":"9476.0",
    "gn:admin4_code":"9476178.0",
    "gn:asciiname":"Hasslach bei Kronach",
    "gn:country_code":"DE",
    "gn:dem":333,
    "gn:feature_class":"P",
    "gn:feature_code":"PPL",
    "gn:name":"Ha\u00dflach bei Kronach",
    "gn:population":0,
    "gn:timezone":"Europe/Berlin",
    "iso:country":"DE",
    "name:und_x_variant":[
        "Ha\u00dflach",
        "Ha\u00dflach bei Kronach"
    ],
    "wof:name":"Hasslach bei Kronach",
    "wof:placetype":"neighbourhood"
},
  "geometry": {"coordinates":[11.29124,50.29095],"type":"Point"}
}