{
  "type": "Feature",
  "properties": {
    "gn:admin1_code":"5",
    "gn:admin2_code":"65.0",
    "gn:admin3_code":"6535.0",
    "gn:admin4_code":"6535009.0",
    "gn:asciiname":"Erbenhausen",
    "gn:country_code":"DE",
    "gn:dem":250,
    "gn:feature_class":"P",
    "gn:feature_code":"PPL",
    "gn:name":"Erbenhausen",
    "gn:population":0,
    "gn:timezone":"Europe/Berlin",
    "iso:country":"DE",
    "name:bak_x_preferred":[
        "\u042d\u0440\u0431\u0435\u043d\u0445\u0430\u0443\u0437\u0435\u043d"
    ],
    "name:ceb_x_preferred":[
        "Erbenhausen"
    ],
    "name:deu_x_preferred":[
        "Erbenhausen"
    ],
    "name:epo_x_preferred":[
        "Erbenhausen"
    ],
    "name:eus_x_preferred":[
        "Erbenhausen"
    ],
    "name:fas_x_preferred":[
        "\u0627\u0631\u0628\u0646\u0647\u0627\u0648\u0632\u0646"
    ],
    "name:fra_x_preferred":[
        "Erbenhausen"
    ],
    "name:hun_x_preferred":[
        "Erbenhausen"
    ],
    "name:ita_x_preferred":[
        "Erbenhausen"
    ],
    "name:kaz_x_preferred":[
        "\u042d\u0440\u0431\u0435\u043d\u0445\u0430\u0443\u0437\u0435\u043d"
    ],
    "name:kir_x_preferred":[
        "\u042d\u0440\u0431\u0435\u043d\u0445\u0430\u0443\u0437\u0435\u043d"
    ],
    "name:mkd_x_preferred":[
        "\u0415\u0440\u0431\u0435\u043d\u0445\u0430\u0443\u0437\u0435\u043d"
    ],
    "name:msa_x_preferred":[
        "Erbenhausen"
    ],
    "name:nld_x_preferred":[
        "Erbenhausen"
    ],
    "name:pol_x_preferred":[
        "Erbenhausen"
    ],
    "name:por_x_preferred":[
        "Erbenhausen"
    ],
    "name:ron_x_preferred":[
        "Erbenhausen"
    ],
    "name:rus_x_preferred":[
        "\u042d\u0440\u0431\u0435\u043d\u0445\u0430\u0443\u0437\u0435\u043d"
    ],
    "name:spa_x_preferred":[
        "Erbenhausen"
    ],
    "name:srp_x_preferred":[
        "\u0415\u0440\u0431\u0435\u043d\u0445\u0430\u0443\u0437\u0435\u043d"
    ],
    "name:ukr_x_preferred":[
        "\u0415\u0440\u0431\u0435\u043d\u0433\u0430\u0443\u0437\u0435\u043d"
    ],
    "name:uzb_x_preferred":[
        "Erbenhausen"
    ],
    "name:vie_x_preferred":[
        "Erbenhausen"
    ],
    "name:vol_x_preferred":[
        "Erbenhausen"
    ],
    "name:war_x_preferred":[
        "Erbenhausen"
    ],
    "name:zho_x_preferred":[
        "\u57c3\u5c14\u672c\u8c6a\u68ee"
    ],
    "wof:name":"Erbenhausen",
    "wof:placetype":"neighbourhood"
},
  "geometry": {"coordinates":[9.06712,50.75601],"type":"Point"}
}