{
  "type": "Feature",
  "properties": {
    "gn:admin1_code":"7.0",
    "gn:admin2_code":"51.0",
    "gn:admin3_code":"5162.0",
    "gn:admin4_code":"5162012.0",
    "gn:asciiname":"Aldenhoven",
    "gn:country_code":"DE",
    "gn:dem":63,
    "gn:feature_class":"P",
    "gn:feature_code":"PPL",
    "gn:name":"Aldenhoven",
    "gn:population":0,
    "gn:timezone":"Europe/Berlin",
    "iso:country":"DE",
    "name:ceb_x_preferred":[
        "Aldenhoven"
    ],
    "name:deu_x_preferred":[
        "Aldenhoven"
    ],
    "name:diq_x_preferred":[
        "Aldenhoven"
    ],
    "name:epo_x_preferred":[
        "Aldenhoven"
    ],
    "name:eus_x_preferred":[
        "Aldenhoven"
    ],
    "name:fas_x_preferred":[
        "\u0627\u0644\u062f\u06cc\u0646\u0647\u0627\u0648\u06cc\u0646"
    ],
    "name:fra_x_preferred":[
        "Aldenhoven"
    ],
    "name:hrv_x_preferred":[
        "Aldenhoven"
    ],
    "name:hun_x_preferred":[
        "Aldenhoven"
    ],
    "name:ina_x_preferred":[
        "Aldenhoven"
    ],
    "name:ita_x_preferred":[
        "Aldenhoven"
    ],
    "name:kaz_x_preferred":[
        "\u0410\u043b\u044c\u0434\u0435\u043d\u0445\u043e\u0444\u0435\u043d"
    ],
    "name:kir_x_preferred":[
        "\u0410\u043b\u044c\u0434\u0435\u043d\u0445\u043e\u0444\u0435\u043d"
    ],
    "name:lim_x_preferred":[
        "Aldenhoven"
    ],
    "name:msa_x_preferred":[
        "Aldenhoven"
    ],
    "name:nld_x_preferred":[
        "Aldenhoven"
    ],
    "name:pol_x_preferred":[
        "Aldenhoven"
    ],
    "name:por_x_preferred":[
        "Aldenhoven"
    ],
    "name:ron_x_preferred":[
        "Aldenhoven"
    ],
    "name:rus_x_preferred":[
        "\u0410\u043b\u044c\u0434\u0435\u043d\u0445\u043e\u0444\u0435\u043d"
    ],
    "name:spa_x_preferred":[
        "Aldenhoven"
    ],
    "name:srp_x_preferred":[
        "\u0410\u043b\u0434\u0435\u043d\u0445\u043e\u0444\u0435\u043d"
    ],
    "name:ukr_x_preferred":[
        "\u0410\u043b\u044c\u0434\u0435\u043d\u0433\u043e\u0444\u0435\u043d"
    ],
    "name:uzb_x_preferred":[
        "Aldenhoven"
    ],
    "name:vie_x_preferred":[
        "Aldenhoven"
    ],
    "name:vol_x_preferred":[
        "Aldenhoven"
    ],
    "name:war_x_preferred":[
        "Aldenhoven"
    ],
    "name:zho_x_preferred":[
        "\u963f\u5c14\u767b\u970d\u82ac"
    ],
    "wof:name":"Aldenhoven",
    "wof:placetype":"neighbourhood"
},
  "geometry": {"coordinates":[6.56776,51.13762],"type":"Point"}
}