{
  "type": "Feature",
  "properties": {
    "gn:admin1_code":"2",
    "gn:admin2_code":"91.0",
    "gn:admin3_code":"9188.0",
    "gn:admin4_code":"9188141.0",
    "gn:asciiname":"Traubing",
    "gn:country_code":"DE",
    "gn:dem":669,
    "gn:feature_class":"P",
    "gn:feature_code":"PPL",
    "gn:name":"Traubing",
    "gn:population":0,
    "gn:timezone":"Europe/Berlin",
    "iso:country":"DE",
    "wof:name":"Traubing",
    "wof:placetype":"neighbourhood"
},
  "geometry": {"coordinates":[11.25549,47.94211],"type":"Point"}
}