{
  "type": "Feature",
  "properties": {
    "gn:admin1_code":"2",
    "gn:admin2_code":"91.0",
    "gn:admin3_code":"9178.0",
    "gn:admin4_code":"9178116.0",
    "gn:asciiname":"Reichertshausen",
    "gn:country_code":"DE",
    "gn:dem":515,
    "gn:feature_class":"P",
    "gn:feature_code":"PPL",
    "gn:name":"Reichertshausen",
    "gn:population":0,
    "gn:timezone":"Europe/Berlin",
    "iso:country":"DE",
    "name:ceb_x_preferred":[
        "Reichertshausen"
    ],
    "name:deu_x_preferred":[
        "Reichertshausen"
    ],
    "name:epo_x_preferred":[
        "Reichertshausen"
    ],
    "name:eus_x_preferred":[
        "Reichertshausen"
    ],
    "name:fas_x_preferred":[
        "\u0631\u0627\u06cc\u0634\u0631\u062a\u0633\u0647\u0627\u0648\u0632\u0646"
    ],
    "name:fra_x_preferred":[
        "Reichertshausen"
    ],
    "name:hun_x_preferred":[
        "Reichertshausen"
    ],
    "name:hye_x_preferred":[
        "\u054c\u0561\u0575\u0570\u0565\u0580\u0569\u057d\u0570\u0561\u0578\u0582\u0566\u0565\u0576"
    ],
    "name:ita_x_preferred":[
        "Reichertshausen"
    ],
    "name:kaz_x_preferred":[
        "\u0420\u0430\u0439\u0445\u0435\u0440\u0442\u0441\u0445\u0430\u0443\u0437\u0435\u043d"
    ],
    "name:kir_x_preferred":[
        "\u0420\u0430\u0439\u0445\u0435\u0440\u0442\u0441\u0445\u0430\u0443\u0437\u0435\u043d"
    ],
    "name:lmo_x_preferred":[
        "Reichertshausen"
    ],
    "name:msa_x_preferred":[
        "Reichertshausen"
    ],
    "name:nld_x_preferred":[
        "Reichertshausen"
    ],
    "name:pol_x_preferred":[
        "Reichertshausen"
    ],
    "name:por_x_preferred":[
        "Reichertshausen"
    ],
    "name:ron_x_preferred":[
        "Reichertshausen"
    ],
    "name:rus_x_preferred":[
        "\u0420\u0430\u0439\u0445\u0435\u0440\u0442\u0441\u0445\u0430\u0443\u0437\u0435\u043d"
    ],
    "name:spa_x_preferred":[
        "Reichertshausen"
    ],
    "name:srp_x_preferred":[
        "\u0420\u0430\u0458\u0445\u0435\u0440\u0442\u0441\u0445\u0430\u0443\u0437\u0435\u043d"
    ],
    "name:ukr_x_preferred":[
        "\u0420\u0430\u0439\u0445\u0435\u0440\u0442\u0441\u0433\u0430\u0443\u0437\u0435\u043d"
    ],
    "name:uzb_x_preferred":[
        "Reichertshausen"
    ],
    "name:vie_x_preferred":[
        "Reichertshausen"
    ],
    "name:vol_x_preferred":[
        "Reichertshausen"
    ],
    "name:war_x_preferred":[
        "Reichertshausen"
    ],
    "name:zho_x_preferred":[
        "\u8d56\u8c22\u8328\u8c6a\u68ee"
    ],
    "wof:name":"Reichertshausen",
    "wof:placetype":"neighbourhood"
},
  "geometry": {"coordinates":[11.75457,48.53717],"type":"Point"}
}