{
  "type": "Feature",
  "properties": {
    "gn:admin1_code":"2.0",
    "gn:admin2_code":"092",
    "gn:admin3_code":"9275.0",
    "gn:admin4_code":"9275159.0",
    "gn:asciiname":"Wilhelmhof",
    "gn:country_code":"DE",
    "gn:dem":395,
    "gn:feature_class":"P",
    "gn:feature_code":"PPL",
    "gn:name":"Wilhelmhof",
    "gn:population":0,
    "gn:timezone":"Europe/Berlin",
    "iso:country":"DE",
    "wof:name":"Wilhelmhof",
    "wof:placetype":"neighbourhood"
},
  "geometry": {"coordinates":[13.23472,48.6343],"type":"Point"}
}