{
  "type": "Feature",
  "properties": {
    "gn:admin1_code":"12",
    "gn:admin2_code":"0.0",
    "gn:admin3_code":"13076.0",
    "gn:admin4_code":"13076043.0",
    "gn:asciiname":"Burow",
    "gn:country_code":"DE",
    "gn:dem":51,
    "gn:feature_class":"P",
    "gn:feature_code":"PPL",
    "gn:name":"Burow",
    "gn:population":0,
    "gn:timezone":"Europe/Berlin",
    "iso:country":"DE",
    "name:ceb_x_preferred":[
        "Burow"
    ],
    "name:deu_x_preferred":[
        "Burow"
    ],
    "name:epo_x_preferred":[
        "Burow"
    ],
    "name:fas_x_preferred":[
        "\u0628\u0648\u0631\u0648\u0648"
    ],
    "name:fra_x_preferred":[
        "Burow"
    ],
    "name:hun_x_preferred":[
        "Burow"
    ],
    "name:ita_x_preferred":[
        "Burow"
    ],
    "name:mkd_x_preferred":[
        "\u0411\u0443\u0440\u043e\u0432"
    ],
    "name:msa_x_preferred":[
        "Burow"
    ],
    "name:nld_x_preferred":[
        "Burow"
    ],
    "name:pol_x_preferred":[
        "Burow"
    ],
    "name:ron_x_preferred":[
        "Burow"
    ],
    "name:rus_x_preferred":[
        "\u0411\u0443\u0440\u043e\u0432"
    ],
    "name:spa_x_preferred":[
        "Burow"
    ],
    "name:srp_x_preferred":[
        "\u0411\u0443\u0440\u043e\u0432"
    ],
    "name:ukr_x_preferred":[
        "\u0411\u0443\u0440\u043e\u0432"
    ],
    "name:vie_x_preferred":[
        "Burow"
    ],
    "name:vol_x_preferred":[
        "Burow"
    ],
    "name:war_x_preferred":[
        "Burow"
    ],
    "name:zho_x_preferred":[
        "\u5e03\u7f57"
    ],
    "wof:name":"Burow",
    "wof:placetype":"neighbourhood"
},
  "geometry": {"coordinates":[12.00977,53.40227],"type":"Point"}
}