{
  "type": "Feature",
  "properties": {
    "gn:admin1_code":"6.0",
    "gn:admin2_code":"0.0",
    "gn:admin3_code":"3453.0",
    "gn:admin4_code":"3453004.0",
    "gn:asciiname":"Emstekerfeld",
    "gn:country_code":"DE",
    "gn:dem":44,
    "gn:feature_class":"P",
    "gn:feature_code":"PPL",
    "gn:name":"Emstekerfeld",
    "gn:population":0,
    "gn:timezone":"Europe/Berlin",
    "iso:country":"DE",
    "wof:name":"Emstekerfeld",
    "wof:placetype":"neighbourhood"
},
  "geometry": {"coordinates":[8.08014,52.8413],"type":"Point"}
}