{
  "type": "Feature",
  "properties": {
    "gn:admin1_code":"7",
    "gn:admin2_code":"59.0",
    "gn:admin3_code":"5966.0",
    "gn:admin4_code":"5966020.0",
    "gn:asciiname":"Gleierbrueck",
    "gn:country_code":"DE",
    "gn:dem":325,
    "gn:feature_class":"P",
    "gn:feature_code":"PPL",
    "gn:name":"Gleierbr\u00fcck",
    "gn:population":0,
    "gn:timezone":"Europe/Berlin",
    "iso:country":"DE",
    "name:und_x_variant":[
        "Gleierbr\u00fccke",
        "Gleierbr\u00fcck"
    ],
    "wof:name":"Gleierbrueck",
    "wof:placetype":"neighbourhood"
},
  "geometry": {"coordinates":[8.14398,51.11729],"type":"Point"}
}