{
  "type": "Feature",
  "properties": {
    "gn:admin1_code":"2",
    "gn:admin2_code":"94.0",
    "gn:admin3_code":"9478.0",
    "gn:admin4_code":"9478139.0",
    "gn:asciiname":"Klosterlangheim",
    "gn:cc2":"DE",
    "gn:country_code":"DE",
    "gn:dem":315,
    "gn:feature_class":"P",
    "gn:feature_code":"PPL",
    "gn:name":"Klosterlangheim",
    "gn:population":0,
    "gn:timezone":"Europe/Berlin",
    "iso:country":"DE",
    "name:und_x_variant":[
        "Langheim"
    ],
    "wof:name":"Klosterlangheim",
    "wof:placetype":"neighbourhood"
},
  "geometry": {"coordinates":[11.11113,50.11216],"type":"Point"}
}