{
  "type": "Feature",
  "properties": {
    "gn:admin1_code":"7",
    "gn:admin2_code":"53.0",
    "gn:admin3_code":"5366.0",
    "gn:admin4_code":"5366032.0",
    "gn:asciiname":"Marmagen",
    "gn:country_code":"DE",
    "gn:dem":547,
    "gn:feature_class":"P",
    "gn:feature_code":"PPL",
    "gn:name":"Marmagen",
    "gn:population":0,
    "gn:timezone":"Europe/Berlin",
    "iso:country":"DE",
    "name:deu_x_preferred":[
        "Marmagen"
    ],
    "name:fas_x_preferred":[
        "\u0645\u0627\u0631\u0645\u0627\u06af\u0646"
    ],
    "name:fra_x_preferred":[
        "Marmagen"
    ],
    "name:ita_x_preferred":[
        "Marmagen"
    ],
    "name:ron_x_preferred":[
        "Marmagen"
    ],
    "wof:name":"Marmagen",
    "wof:placetype":"neighbourhood"
},
  "geometry": {"coordinates":[6.57821,50.47708],"type":"Point"}
}