{
  "type": "Feature",
  "properties": {
    "gn:admin1_code":"2",
    "gn:admin2_code":"93.0",
    "gn:admin3_code":"9377.0",
    "gn:admin4_code":"9377132.0",
    "gn:asciiname":"Sassenhof",
    "gn:country_code":"DE",
    "gn:dem":501,
    "gn:feature_class":"P",
    "gn:feature_code":"PPL",
    "gn:name":"Sassenhof",
    "gn:population":0,
    "gn:timezone":"Europe/Berlin",
    "iso:country":"DE",
    "wof:name":"Sassenhof",
    "wof:placetype":"neighbourhood"
},
  "geometry": {"coordinates":[12.06321,49.82706],"type":"Point"}
}