{
  "type": "Feature",
  "properties": {
    "gn:admin1_code":"11",
    "gn:admin2_code":"0.0",
    "gn:admin3_code":"12069.0",
    "gn:admin4_code":"12069017.0",
    "gn:asciiname":"Buchholz",
    "gn:country_code":"DE",
    "gn:dem":44,
    "gn:feature_class":"P",
    "gn:feature_code":"PPL",
    "gn:name":"Buchholz",
    "gn:population":0,
    "gn:timezone":"Europe/Berlin",
    "iso:country":"DE",
    "name:ceb_x_preferred":[
        "Buchholz"
    ],
    "name:ces_x_preferred":[
        "Buchholz"
    ],
    "name:dan_x_preferred":[
        "Buchholz"
    ],
    "name:deu_x_preferred":[
        "Buchholz"
    ],
    "name:epo_x_preferred":[
        "Buchholz"
    ],
    "name:eus_x_preferred":[
        "Buchholz"
    ],
    "name:fra_x_preferred":[
        "Buchholz"
    ],
    "name:heb_x_preferred":[
        "\u05d1\u05d5\u05db\u05d4\u05d5\u05dc\u05e5"
    ],
    "name:hun_x_preferred":[
        "Buchholz"
    ],
    "name:ita_x_preferred":[
        "Buchholz"
    ],
    "name:jpn_x_preferred":[
        "\u30d6\u30fc\u30d5\u30db\u30eb\u30c4"
    ],
    "name:mkd_x_preferred":[
        "\u0411\u0443\u0445\u043e\u043b\u0446"
    ],
    "name:nds_x_preferred":[
        "Buchholz"
    ],
    "name:nld_x_preferred":[
        "Buchholz"
    ],
    "name:pol_x_preferred":[
        "Buchholz"
    ],
    "name:rus_x_preferred":[
        "\u0411\u0443\u0445\u0433\u043e\u043b\u044c\u0446"
    ],
    "name:spa_x_preferred":[
        "Buchholz"
    ],
    "name:srp_x_preferred":[
        "\u0411\u0443\u0445\u043e\u043b\u0446"
    ],
    "name:swe_x_preferred":[
        "Buchholz"
    ],
    "name:vol_x_preferred":[
        "Buchholz"
    ],
    "wof:name":"Buchholz",
    "wof:placetype":"neighbourhood"
},
  "geometry": {"coordinates":[12.92513,52.1598],"type":"Point"}
}