{
  "type": "Feature",
  "properties": {
    "gn:country":"DE",
    "gn:fcode":"PPL",
    "gn:population":0,
    "iso:country":"DE",
    "name:ceb_x_preferred":[
        "Schwirzheim"
    ],
    "name:deu_x_preferred":[
        "Schwirzheim"
    ],
    "name:epo_x_preferred":[
        "Schwirzheim"
    ],
    "name:eus_x_preferred":[
        "Schwirzheim"
    ],
    "name:fas_x_preferred":[
        "\u0634\u0648\u06cc\u0631\u062a\u0633\u0647\u0627\u06cc\u0645"
    ],
    "name:fra_x_preferred":[
        "Schwirzheim"
    ],
    "name:hun_x_preferred":[
        "Schwirzheim"
    ],
    "name:ita_x_preferred":[
        "Schwirzheim"
    ],
    "name:msa_x_preferred":[
        "Schwirzheim"
    ],
    "name:nld_x_preferred":[
        "Schwirzheim"
    ],
    "name:pol_x_preferred":[
        "Schwirzheim"
    ],
    "name:por_x_preferred":[
        "Schwirzheim"
    ],
    "name:ron_x_preferred":[
        "Schwirzheim"
    ],
    "name:rus_x_preferred":[
        "\u0428\u0432\u0438\u0440\u0446\u0445\u0430\u0439\u043c"
    ],
    "name:srp_x_preferred":[
        "\u0428\u0432\u0438\u0440\u0446\u0445\u0430\u0458\u043c"
    ],
    "name:ukr_x_preferred":[
        "\u0428\u0432\u0456\u0440\u0446\u0433\u0430\u0439\u043c"
    ],
    "name:uzb_x_preferred":[
        "Schwirzheim"
    ],
    "name:vie_x_preferred":[
        "Schwirzheim"
    ],
    "name:vol_x_preferred":[
        "Schwirzheim"
    ],
    "name:war_x_preferred":[
        "Schwirzheim"
    ],
    "name:zho_x_preferred":[
        "\u65bd\u7ef4\u5c14\u8328\u6d77\u59c6"
    ],
    "qs_pg:aaroncc":"DE",
    "qs_pg:gn_country":"DE",
    "qs_pg:gn_fcode":"PPL",
    "qs_pg:gn_pop":0,
    "qs_pg:name":"Schwirzheim",
    "qs_pg:name_adm0":"Deutschland",
    "qs_pg:name_adm1":"Rheinland-Pfalz",
    "qs_pg:photos":47,
    "qs_pg:photos_1k":10,
    "qs_pg:photos_9k":1,
    "qs_pg:photos_9r":2,
    "qs_pg:photos_all":47,
    "qs_pg:photos_sr":2,
    "qs_pg:pop_sr":0,
    "qs_pg:qs_pg_placetype":"locality",
    "qs_pg:qs_pg_placetype_gp":"Town",
    "qs_pg:woe_adm0":23424829,
    "woe:adm0_id":23424829,
    "woe:name_adm0":"Deutschland",
    "woe:name_adm1":"Rheinland-Pfalz",
    "woe:placetype":"Town",
    "wof:name":"Schwirzheim",
    "wof:placetype":"neighbourhood"
},
  "geometry": {"coordinates":[6.8676,50.61374],"type":"Point"}
}