{
  "type": "Feature",
  "properties": {
    "gn:admin1_code":"6.0",
    "gn:admin2_code":"00",
    "gn:admin3_code":"3351.0",
    "gn:admin4_code":"3351010.0",
    "gn:asciiname":"Willighausen",
    "gn:country_code":"DE",
    "gn:dem":70,
    "gn:feature_class":"P",
    "gn:feature_code":"PPL",
    "gn:name":"Willighausen",
    "gn:population":0,
    "gn:timezone":"Europe/Berlin",
    "iso:country":"DE",
    "wof:name":"Willighausen",
    "wof:placetype":"neighbourhood"
},
  "geometry": {"coordinates":[10.08579,52.86156],"type":"Point"}
}