{
  "type": "Feature",
  "properties": {
    "gn:population":1472,
    "iso:country":"DE",
    "name:baq_x_preferred":[
        "Lehmkuhlen"
    ],
    "name:chi_x_preferred":[
        "\u83b1\u59c6\u5e93\u4f26"
    ],
    "name:dan_x_preferred":[
        "Lehmkuhlen"
    ],
    "name:deu_x_preferred":[
        "Lehmkuhlen"
    ],
    "name:dut_x_preferred":[
        "Lehmkuhlen"
    ],
    "name:eng_x_preferred":[
        "Lehmkuhlen"
    ],
    "name:epo_x_preferred":[
        "Lehmkuhlen"
    ],
    "name:eus_x_preferred":[
        "Lehmkuhlen"
    ],
    "name:fra_x_preferred":[
        "Lehmkuhlen"
    ],
    "name:fre_x_preferred":[
        "Lehmkuhlen"
    ],
    "name:ger_x_preferred":[
        "Lehmkuhlen"
    ],
    "name:hun_x_preferred":[
        "Lehmkuhlen"
    ],
    "name:ita_x_preferred":[
        "Lehmkuhlen"
    ],
    "name:mac_x_preferred":[
        "\u041b\u0435\u043c\u043a\u0443\u043b\u0435\u043d"
    ],
    "name:may_x_preferred":[
        "Lehmkuhlen"
    ],
    "name:mkd_x_preferred":[
        "\u041b\u0435\u043c\u043a\u0443\u043b\u0435\u043d"
    ],
    "name:msa_x_preferred":[
        "Lehmkuhlen"
    ],
    "name:nld_x_preferred":[
        "Lehmkuhlen"
    ],
    "name:per_x_preferred":[
        "\u0644\u0647\u0645\u06a9\u0648\u0647\u0644\u0646"
    ],
    "name:pol_x_preferred":[
        "Lehmkuhlen"
    ],
    "name:por_x_preferred":[
        "Lehmkuhlen"
    ],
    "name:ron_x_preferred":[
        "Lehmkuhlen"
    ],
    "name:rum_x_preferred":[
        "Lehmkuhlen"
    ],
    "name:rus_x_preferred":[
        "\u041b\u0435\u043c\u043a\u0443\u043b\u0435\u043d"
    ],
    "name:tur_x_preferred":[
        "Lehmkuhlen"
    ],
    "name:ukr_x_preferred":[
        "\u041b\u0435\u043c\u043a\u0443\u043b\u0435\u043d"
    ],
    "name:uzb_x_preferred":[
        "Lehmkuhlen"
    ],
    "name:vie_x_preferred":[
        "Lehmkuhlen"
    ],
    "name:vol_x_preferred":[
        "Lehmkuhlen"
    ],
    "name:war_x_preferred":[
        "Lehmkuhlen"
    ],
    "name:zho_x_preferred":[
        "\u83b1\u59c6\u5e93\u4f26"
    ],
    "qs:a0":"Bundesrepublik Deutschland",
    "qs:a1":"*Schleswig-Holstein",
    "qs:a1r":"0",
    "qs:a2":"Pl\u00f6n",
    "qs:adm0":"Bundesrepublik Deutschland",
    "qs:la_lc":"*",
    "qs:level":"locality",
    "qs:loc":"Lehmkuhlen",
    "qs:loc_alt":"Lehmkuhlen",
    "qs:pop":0,
    "qs:type":"buffered point",
    "wd:wordcount":37,
    "wof:name":"Lehmkuhlen",
    "wof:placetype":"locality",
    "wof:population":1472
},
  "geometry": {"coordinates":[10.37703,54.220827],"type":"Point"}
}