{
  "type": "Feature",
  "properties": {
    "gn:admin1_code":"2",
    "gn:admin2_code":"97.0",
    "gn:admin3_code":"9762.0",
    "gn:admin4_code":"9762000.0",
    "gn:asciiname":"Grosskemnat",
    "gn:country_code":"DE",
    "gn:dem":809,
    "gn:feature_class":"P",
    "gn:feature_code":"PPL",
    "gn:name":"Gro\u00dfkemnat",
    "gn:population":0,
    "gn:timezone":"Europe/Berlin",
    "iso:country":"DE",
    "wof:name":"Grosskemnat",
    "wof:placetype":"neighbourhood"
},
  "geometry": {"coordinates":[10.58367,47.88202],"type":"Point"}
}