{
  "type": "Feature",
  "properties": {
    "gn:admin1_code":"2",
    "gn:admin2_code":"97.0",
    "gn:admin3_code":"9763.0",
    "gn:admin4_code":"9763000.0",
    "gn:asciiname":"Hub",
    "gn:country_code":"DE",
    "gn:dem":690,
    "gn:feature_class":"P",
    "gn:feature_code":"PPL",
    "gn:name":"Hub",
    "gn:population":0,
    "gn:timezone":"Europe/Berlin",
    "iso:country":"DE",
    "name:cat_x_preferred":[
        "Hub"
    ],
    "name:ceb_x_preferred":[
        "Hub"
    ],
    "name:dan_x_preferred":[
        "Hub"
    ],
    "name:deu_x_preferred":[
        "Hub"
    ],
    "name:ell_x_preferred":[
        "Hub"
    ],
    "name:epo_x_preferred":[
        "Hub"
    ],
    "name:eus_x_preferred":[
        "Hub"
    ],
    "name:fin_x_preferred":[
        "Hub"
    ],
    "name:fra_x_preferred":[
        "Hub"
    ],
    "name:heb_x_preferred":[
        "Hub"
    ],
    "name:hrv_x_preferred":[
        "Hub"
    ],
    "name:hun_x_preferred":[
        "Hub"
    ],
    "name:ido_x_preferred":[
        "Nabo"
    ],
    "name:kaz_x_preferred":[
        "\u0425\u0430\u0431"
    ],
    "name:nld_x_preferred":[
        "Hub"
    ],
    "name:pol_x_preferred":[
        "Hub"
    ],
    "name:por_x_preferred":[
        "Hub"
    ],
    "name:rus_x_preferred":[
        "\u0425\u0430\u0431"
    ],
    "name:slk_x_preferred":[
        "Hub"
    ],
    "name:snd_x_preferred":[
        "\u062d\u0628 \u0686\u0648\u06aa\u064a"
    ],
    "name:spa_x_preferred":[
        "Hub"
    ],
    "name:srp_x_preferred":[
        "\u0425\u0430\u0431"
    ],
    "name:tur_x_preferred":[
        "Hub"
    ],
    "name:ukr_x_preferred":[
        "\u0425\u0430\u0431"
    ],
    "wof:name":"Hub",
    "wof:placetype":"neighbourhood"
},
  "geometry": {"coordinates":[10.32493,47.75923],"type":"Point"}
}