{
  "type": "Feature",
  "properties": {
    "gn:admin1_code":"8",
    "gn:admin2_code":"0.0",
    "gn:admin3_code":"7132.0",
    "gn:admin4_code":"7132082.0",
    "gn:asciiname":"Rimbach",
    "gn:country_code":"DE",
    "gn:dem":228,
    "gn:feature_class":"P",
    "gn:feature_code":"PPL",
    "gn:name":"Rimbach",
    "gn:population":0,
    "gn:timezone":"Europe/Berlin",
    "iso:country":"DE",
    "name:als_x_preferred":[
        "Rimbach"
    ],
    "name:ceb_x_preferred":[
        "Rimbach"
    ],
    "name:deu_x_preferred":[
        "Rimbach"
    ],
    "name:epo_x_preferred":[
        "Rimbach"
    ],
    "name:fra_x_preferred":[
        "Rimbach"
    ],
    "name:hye_x_preferred":[
        "\u054c\u056b\u0574\u0562\u0561\u056d"
    ],
    "name:ita_x_preferred":[
        "Rimbach"
    ],
    "name:nld_x_preferred":[
        "Rimbach"
    ],
    "name:pol_x_preferred":[
        "Rimbach"
    ],
    "name:rus_x_preferred":[
        "\u0420\u0438\u043c\u0431\u0430\u0445"
    ],
    "name:spa_x_preferred":[
        "Rimbach"
    ],
    "name:srp_x_preferred":[
        "\u0420\u0438\u043c\u0431\u0430\u0445"
    ],
    "name:swe_x_preferred":[
        "Rimbach"
    ],
    "name:vol_x_preferred":[
        "Rimbach"
    ],
    "wof:name":"Rimbach",
    "wof:placetype":"neighbourhood"
},
  "geometry": {"coordinates":[7.57917,50.73245],"type":"Point"}
}