{
  "type": "Feature",
  "properties": {
    "gn:admin1_code":"11",
    "gn:admin2_code":"0.0",
    "gn:admin3_code":"12068.0",
    "gn:admin4_code":"12068353.0",
    "gn:asciiname":"Neukoepernitz",
    "gn:country_code":"DE",
    "gn:dem":73,
    "gn:feature_class":"P",
    "gn:feature_code":"PPL",
    "gn:name":"Neuk\u00f6pernitz",
    "gn:population":0,
    "gn:timezone":"Europe/Berlin",
    "iso:country":"DE",
    "wof:name":"Neukoepernitz",
    "wof:placetype":"neighbourhood"
},
  "geometry": {"coordinates":[12.96172,53.06324],"type":"Point"}
}