{
  "type": "Feature",
  "properties": {
    "gn:gn_country":"DE",
    "gn:gn_fcode":"PPLA4",
    "gn:gn_pop":292,
    "gn:population":292,
    "iso:country":"DE",
    "name:baq_x_preferred":[
        "Hollnich"
    ],
    "name:chi_x_preferred":[
        "\u970d\u5c14\u5c3c\u5e0c"
    ],
    "name:dut_x_preferred":[
        "Hollnich"
    ],
    "name:eng_x_preferred":[
        "Hollnich"
    ],
    "name:epo_x_preferred":[
        "Hollnich"
    ],
    "name:fre_x_preferred":[
        "Hollnich"
    ],
    "name:ger_x_preferred":[
        "Hollnich"
    ],
    "name:hun_x_preferred":[
        "Hollnich"
    ],
    "name:ita_x_preferred":[
        "Hollnich"
    ],
    "name:jpn_x_preferred":[
        "\u30db\u30eb\u30cb\u30d2"
    ],
    "name:kaz_x_preferred":[
        "\u0425\u043e\u043b\u044c\u043d\u0438\u0445"
    ],
    "name:kir_x_preferred":[
        "\u0425\u043e\u043b\u044c\u043d\u0438\u0445"
    ],
    "name:per_x_preferred":[
        "\u0647\u0648\u0644\u0646\u0627\u06cc\u0634"
    ],
    "name:pol_x_preferred":[
        "Hollnich"
    ],
    "name:por_x_preferred":[
        "Hollnich"
    ],
    "name:rum_x_preferred":[
        "Hollnich"
    ],
    "name:rus_x_preferred":[
        "\u0425\u043e\u043b\u044c\u043d\u0438\u0445"
    ],
    "name:srp_x_preferred":[
        "\u0425\u043e\u043b\u043d\u0438\u0445"
    ],
    "name:ukr_x_preferred":[
        "\u0413\u043e\u043b\u044c\u043d\u0456\u0445"
    ],
    "name:uzb_x_preferred":[
        "Hollnich"
    ],
    "name:vie_x_preferred":[
        "Hollnich"
    ],
    "name:vol_x_preferred":[
        "Hollnich"
    ],
    "name:war_x_preferred":[
        "Hollnich"
    ],
    "qs_pg:aaroncc":"DE",
    "qs_pg:gn_country":"DE",
    "qs_pg:gn_fcode":"PPLA4",
    "qs_pg:gn_pop":292,
    "qs_pg:name":"Hollnich",
    "qs_pg:photos_9r":0,
    "qs_pg:photos_sr":0,
    "qs_pg:pop_sr":2,
    "qs_pg:qs_pg_placetype":"locality",
    "wof:name":"Hollnich",
    "wof:placetype":"locality",
    "wof:population":292
},
  "geometry": {"coordinates":[7.48333,50.06667],"type":"Point"}
}