{
  "type": "Feature",
  "properties": {
    "gn:admin1_code":"2",
    "gn:admin2_code":"93.0",
    "gn:admin3_code":"9371.0",
    "gn:admin4_code":"9371123.0",
    "gn:asciiname":"Kainsricht",
    "gn:country_code":"DE",
    "gn:dem":450,
    "gn:feature_class":"P",
    "gn:feature_code":"PPL",
    "gn:name":"Kainsricht",
    "gn:population":0,
    "gn:timezone":"Europe/Berlin",
    "iso:country":"DE",
    "wof:name":"Kainsricht",
    "wof:placetype":"neighbourhood"
},
  "geometry": {"coordinates":[11.85404,49.54474],"type":"Point"}
}