{
  "type": "Feature",
  "properties": {
    "gn:admin1_code":"7",
    "gn:admin2_code":"51.0",
    "gn:admin3_code":"5166.0",
    "gn:admin4_code":"5166024.0",
    "gn:asciiname":"Felderseite",
    "gn:country_code":"DE",
    "gn:dem":53,
    "gn:feature_class":"P",
    "gn:feature_code":"PPL",
    "gn:name":"Felderseite",
    "gn:population":0,
    "gn:timezone":"Europe/Berlin",
    "iso:country":"DE",
    "wof:name":"Felderseite",
    "wof:placetype":"neighbourhood"
},
  "geometry": {"coordinates":[6.27528,51.24856],"type":"Point"}
}