{
  "type": "Feature",
  "properties": {
    "gn:admin1_code":"10",
    "gn:admin2_code":"0.0",
    "gn:admin3_code":"1055.0",
    "gn:admin4_code":"1055033.0",
    "gn:asciiname":"Kroess",
    "gn:country_code":"DE",
    "gn:dem":25,
    "gn:feature_class":"P",
    "gn:feature_code":"PPL",
    "gn:name":"Kr\u00f6\u00df",
    "gn:population":0,
    "gn:timezone":"Europe/Berlin",
    "iso:country":"DE",
    "wof:name":"Kroess",
    "wof:placetype":"neighbourhood"
},
  "geometry": {"coordinates":[10.88357,54.31856],"type":"Point"}
}