{
  "type": "Feature",
  "properties": {
    "gn:admin1_code":"10",
    "gn:admin2_code":"0.0",
    "gn:admin3_code":"1055.0",
    "gn:admin4_code":"1055041.0",
    "gn:asciiname":"Kesdorf",
    "gn:country_code":"DE",
    "gn:dem":23,
    "gn:feature_class":"P",
    "gn:feature_code":"PPL",
    "gn:name":"Kesdorf",
    "gn:population":0,
    "gn:timezone":"Europe/Berlin",
    "iso:country":"DE",
    "wof:name":"Kesdorf",
    "wof:placetype":"neighbourhood"
},
  "geometry": {"coordinates":[10.65704,54.067],"type":"Point"}
}