{
  "type": "Feature",
  "properties": {
    "gn:admin1_code":"10",
    "gn:admin2_code":"0.0",
    "gn:admin3_code":"1051.0",
    "gn:admin4_code":"1051027.0",
    "gn:asciiname":"Eesch",
    "gn:country_code":"DE",
    "gn:dem":3,
    "gn:feature_class":"P",
    "gn:feature_code":"PPL",
    "gn:name":"Eesch",
    "gn:population":0,
    "gn:timezone":"Europe/Berlin",
    "iso:country":"DE",
    "wof:name":"Eesch",
    "wof:placetype":"neighbourhood"
},
  "geometry": {"coordinates":[9.03021,54.05707],"type":"Point"}
}