{
  "type": "Feature",
  "properties": {
    "gn:admin1_code":"6",
    "gn:admin2_code":"0.0",
    "gn:admin3_code":"3354.0",
    "gn:admin4_code":"3354004.0",
    "gn:asciiname":"Predoehlsau",
    "gn:country_code":"DE",
    "gn:dem":15,
    "gn:feature_class":"P",
    "gn:feature_code":"PPL",
    "gn:name":"Pred\u00f6hlsau",
    "gn:population":0,
    "gn:timezone":"Europe/Berlin",
    "iso:country":"DE",
    "wof:name":"Predoehlsau",
    "wof:placetype":"neighbourhood"
},
  "geometry": {"coordinates":[11.10005,53.12159000000001],"type":"Point"}
}