{
  "type": "Feature",
  "properties": {
    "gn:admin1_code":"5",
    "gn:admin2_code":"65.0",
    "gn:admin3_code":"6531.0",
    "gn:admin4_code":"6531015.0",
    "gn:asciiname":"Londorf",
    "gn:country_code":"DE",
    "gn:dem":225,
    "gn:feature_class":"P",
    "gn:feature_code":"PPL",
    "gn:name":"Londorf",
    "gn:population":0,
    "gn:timezone":"Europe/Berlin",
    "iso:country":"DE",
    "name:deu_x_preferred":[
        "Rabenau-Londorf"
    ],
    "wof:name":"Londorf",
    "wof:placetype":"neighbourhood"
},
  "geometry": {"coordinates":[8.86219,50.67416],"type":"Point"}
}