{
  "type": "Feature",
  "properties": {
    "gn:admin1_code":"14",
    "gn:admin2_code":"0.0",
    "gn:admin3_code":"15088.0",
    "gn:admin4_code":"15088195.0",
    "gn:asciiname":"Schwaetz",
    "gn:country_code":"DE",
    "gn:dem":101,
    "gn:feature_class":"P",
    "gn:feature_code":"PPL",
    "gn:name":"Schw\u00e4tz",
    "gn:population":0,
    "gn:timezone":"Europe/Berlin",
    "iso:country":"DE",
    "wof:name":"Schwaetz",
    "wof:placetype":"neighbourhood"
},
  "geometry": {"coordinates":[12.16179,51.51582],"type":"Point"}
}