{
  "type": "Feature",
  "properties": {
    "iso:country":"DE",
    "wof:name":"Oberpilghausen",
    "wof:placetype":"neighbourhood"
},
  "geometry": {"coordinates":[7.0706991604017,51.16230368439163],"type":"Point"}
}