{
  "type": "Feature",
  "properties": {
    "gn:admin1_code":"7",
    "gn:admin2_code":"53.0",
    "gn:admin3_code":"5374.0",
    "gn:admin4_code":"5374012.0",
    "gn:asciiname":"Elbach",
    "gn:country_code":"DE",
    "gn:dem":206,
    "gn:feature_class":"P",
    "gn:feature_code":"PPL",
    "gn:name":"Elbach",
    "gn:population":0,
    "gn:timezone":"Europe/Berlin",
    "iso:country":"DE",
    "name:als_x_preferred":[
        "Elbach"
    ],
    "name:bug_x_preferred":[
        "Elbach"
    ],
    "name:cat_x_preferred":[
        "Elbach"
    ],
    "name:ceb_x_preferred":[
        "Elbach"
    ],
    "name:deu_x_preferred":[
        "Elbach"
    ],
    "name:eus_x_preferred":[
        "Elbach"
    ],
    "name:fra_x_preferred":[
        "Elbach"
    ],
    "name:hun_x_preferred":[
        "Elbach"
    ],
    "name:ita_x_preferred":[
        "Elbach"
    ],
    "name:kaz_x_preferred":[
        "\u0415\u043b\u044c\u0431\u0430\u043a"
    ],
    "name:lat_x_preferred":[
        "Elbach"
    ],
    "name:msa_x_preferred":[
        "Elbach"
    ],
    "name:nld_x_preferred":[
        "Elbach"
    ],
    "name:oci_x_preferred":[
        "Elbach"
    ],
    "name:pfl_x_preferred":[
        "Elbach"
    ],
    "name:pms_x_preferred":[
        "Elbach"
    ],
    "name:pol_x_preferred":[
        "Elbach"
    ],
    "name:por_x_preferred":[
        "Elbach"
    ],
    "name:ron_x_preferred":[
        "Elbach"
    ],
    "name:rus_x_preferred":[
        "\u042d\u043b\u044c\u0431\u0430\u043a"
    ],
    "name:slk_x_preferred":[
        "Elbach"
    ],
    "name:slv_x_preferred":[
        "Elbach"
    ],
    "name:spa_x_preferred":[
        "Elbach"
    ],
    "name:swe_x_preferred":[
        "Elbach"
    ],
    "name:ukr_x_preferred":[
        "\u0415\u043b\u044c\u0431\u0430\u043a"
    ],
    "name:uzb_x_preferred":[
        "Elbach"
    ],
    "name:vie_x_preferred":[
        "Elbach"
    ],
    "name:vol_x_preferred":[
        "Elbach"
    ],
    "name:war_x_preferred":[
        "Elbach"
    ],
    "name:zho_x_preferred":[
        "\u57c3\u5c14\u5df4\u514b"
    ],
    "wof:name":"Elbach",
    "wof:placetype":"neighbourhood"
},
  "geometry": {"coordinates":[7.45981,51.02522],"type":"Point"}
}