{
  "type": "Feature",
  "properties": {
    "gn:admin1_code":"1",
    "gn:admin2_code":"84.0",
    "gn:admin3_code":"8435.0",
    "gn:admin4_code":"8435067.0",
    "gn:asciiname":"Harresheim",
    "gn:country_code":"DE",
    "gn:dem":663,
    "gn:feature_class":"P",
    "gn:feature_code":"PPL",
    "gn:name":"Harresheim",
    "gn:population":0,
    "gn:timezone":"Europe/Berlin",
    "iso:country":"DE",
    "wof:name":"Harresheim",
    "wof:placetype":"neighbourhood"
},
  "geometry": {"coordinates":[9.40344,47.74822],"type":"Point"}
}