{
  "type": "Feature",
  "properties": {
    "iso:country":"DE",
    "wof:name":"Vegesack",
    "wof:placetype":"neighbourhood"
},
  "geometry": {"coordinates":[8.62598181264665,53.17621374000658],"type":"Point"}
}