{
  "type": "Feature",
  "properties": {
    "gn:admin1_code":"1",
    "gn:admin2_code":"81.0",
    "gn:admin3_code":"8115.0",
    "gn:admin4_code":"8115050.0",
    "gn:asciiname":"Merklingen",
    "gn:country_code":"DE",
    "gn:dem":394,
    "gn:feature_class":"P",
    "gn:feature_code":"PPL",
    "gn:name":"Merklingen",
    "gn:population":0,
    "gn:timezone":"Europe/Berlin",
    "iso:country":"DE",
    "name:als_x_preferred":[
        "Merklingen"
    ],
    "name:ceb_x_preferred":[
        "Merklingen"
    ],
    "name:deu_x_preferred":[
        "Merklingen"
    ],
    "name:epo_x_preferred":[
        "Merklingen"
    ],
    "name:eus_x_preferred":[
        "Merklingen"
    ],
    "name:fas_x_preferred":[
        "\u0645\u0631\u06a9\u0644\u06cc\u0646\u06af\u0646"
    ],
    "name:fra_x_preferred":[
        "Merklingen"
    ],
    "name:hun_x_preferred":[
        "Merklingen"
    ],
    "name:hye_x_preferred":[
        "\u0544\u0565\u0580\u056f\u056c\u056b\u0576\u0563\u0565\u0576"
    ],
    "name:ita_x_preferred":[
        "Merklingen"
    ],
    "name:kat_x_preferred":[
        "\u10db\u10d4\u10e0\u10d9\u10da\u10d8\u10dc\u10d2\u10d4\u10dc\u10d8"
    ],
    "name:lat_x_preferred":[
        "Merklingen"
    ],
    "name:lmo_x_preferred":[
        "Merklingen"
    ],
    "name:msa_x_preferred":[
        "Merklingen"
    ],
    "name:nld_x_preferred":[
        "Merklingen"
    ],
    "name:pol_x_preferred":[
        "Merklingen"
    ],
    "name:por_x_preferred":[
        "Merklingen"
    ],
    "name:ron_x_preferred":[
        "Merklingen"
    ],
    "name:rus_x_preferred":[
        "\u041c\u0435\u0440\u043a\u043b\u0438\u043d\u0433\u0435\u043d"
    ],
    "name:slk_x_preferred":[
        "Merklingen"
    ],
    "name:spa_x_preferred":[
        "Merklingen"
    ],
    "name:srp_x_preferred":[
        "\u041c\u0435\u0440\u043a\u043b\u0438\u043d\u0433\u0435\u043d"
    ],
    "name:ukr_x_preferred":[
        "\u041c\u0435\u0440\u043a\u043b\u0456\u043d\u0433\u0435\u043d"
    ],
    "name:uzb_x_preferred":[
        "Merklingen"
    ],
    "name:vol_x_preferred":[
        "Merklingen"
    ],
    "name:war_x_preferred":[
        "Merklingen"
    ],
    "name:zho_x_preferred":[
        "\u6885\u5c14\u514b\u6797\u6839"
    ],
    "wof:name":"Merklingen",
    "wof:placetype":"neighbourhood"
},
  "geometry": {"coordinates":[8.85199,48.76898],"type":"Point"}
}