{
  "type": "Feature",
  "properties": {
    "gn:admin1_code":"15",
    "gn:admin2_code":"0.0",
    "gn:admin3_code":"16074.0",
    "gn:admin4_code":"16074009.0",
    "gn:asciiname":"Hetzdorf",
    "gn:country_code":"DE",
    "gn:dem":283,
    "gn:feature_class":"P",
    "gn:feature_code":"PPL",
    "gn:name":"Hetzdorf",
    "gn:population":0,
    "gn:timezone":"Europe/Berlin",
    "iso:country":"DE",
    "wof:name":"Hetzdorf",
    "wof:placetype":"neighbourhood"
},
  "geometry": {"coordinates":[11.78884,50.93759],"type":"Point"}
}