{
  "type": "Feature",
  "properties": {
    "gn:admin1_code":"8",
    "gn:admin2_code":"0.0",
    "gn:admin3_code":"7340.0",
    "gn:admin4_code":"7340222.0",
    "gn:asciiname":"Hoehmuehlbach",
    "gn:country_code":"DE",
    "gn:dem":267,
    "gn:feature_class":"P",
    "gn:feature_code":"PPL",
    "gn:name":"H\u00f6hm\u00fchlbach",
    "gn:population":0,
    "gn:timezone":"Europe/Berlin",
    "iso:country":"DE",
    "wof:name":"Hoehmuehlbach",
    "wof:placetype":"neighbourhood"
},
  "geometry": {"coordinates":[7.526,49.24119],"type":"Point"}
}