{
  "type": "Feature",
  "properties": {
    "gn:admin1_code":"6",
    "gn:admin2_code":"0.0",
    "gn:admin3_code":"3351.0",
    "gn:admin4_code":"3351006.0",
    "gn:asciiname":"Jaegerei",
    "gn:country_code":"DE",
    "gn:dem":55,
    "gn:feature_class":"P",
    "gn:feature_code":"PPL",
    "gn:name":"J\u00e4gerei",
    "gn:population":0,
    "gn:timezone":"Europe/Berlin",
    "iso:country":"DE",
    "wof:name":"Jaegerei",
    "wof:placetype":"neighbourhood"
},
  "geometry": {"coordinates":[10.06337,52.70208],"type":"Point"}
}