{
  "type": "Feature",
  "properties": {
    "gn:admin1_code":"1",
    "gn:admin2_code":"81.0",
    "gn:admin3_code":"8118.0",
    "gn:admin4_code":"8118078.0",
    "gn:asciiname":"Geisingen",
    "gn:cc2":"DE",
    "gn:country_code":"DE",
    "gn:dem":202,
    "gn:feature_class":"P",
    "gn:feature_code":"PPL",
    "gn:name":"Geisingen",
    "gn:population":0,
    "gn:timezone":"Europe/Berlin",
    "iso:country":"DE",
    "name:als_x_preferred":[
        "Geisingen"
    ],
    "name:ara_x_preferred":[
        "\u063a\u0627\u064a\u0632\u064a\u0646\u063a\u0646"
    ],
    "name:azb_x_preferred":[
        "\u0642\u0627\u0632\u06cc\u0646\u0642\u0646"
    ],
    "name:ceb_x_preferred":[
        "Geisingen"
    ],
    "name:deu_x_preferred":[
        "Geisingen"
    ],
    "name:epo_x_preferred":[
        "Geisingen"
    ],
    "name:fas_x_preferred":[
        "\u06af\u0627\u0632\u06cc\u0646\u06af\u0646"
    ],
    "name:fra_x_preferred":[
        "Geisingen"
    ],
    "name:hun_x_preferred":[
        "Geisingen"
    ],
    "name:ita_x_preferred":[
        "Geisingen"
    ],
    "name:kaz_x_preferred":[
        "\u0413\u0430\u0439\u0437\u0438\u043d\u0433\u0435\u043d"
    ],
    "name:kir_x_preferred":[
        "\u0413\u0430\u0439\u0437\u0438\u043d\u0433\u0435\u043d"
    ],
    "name:lat_x_preferred":[
        "Geisingen"
    ],
    "name:lmo_x_preferred":[
        "Geisingen"
    ],
    "name:msa_x_preferred":[
        "Geisingen"
    ],
    "name:nld_x_preferred":[
        "Geisingen"
    ],
    "name:pol_x_preferred":[
        "Geisingen"
    ],
    "name:por_x_preferred":[
        "Geisingen"
    ],
    "name:ron_x_preferred":[
        "Geisingen"
    ],
    "name:rus_x_preferred":[
        "\u0413\u0430\u0439\u0437\u0438\u043d\u0433\u0435\u043d"
    ],
    "name:spa_x_preferred":[
        "Geisingen"
    ],
    "name:srp_x_preferred":[
        "\u0413\u0430\u0458\u0437\u0438\u043d\u0433\u0435\u043d"
    ],
    "name:tur_x_preferred":[
        "Geisingen"
    ],
    "name:und_x_variant":[
        "Geisingen am Neckar"
    ],
    "name:uzb_x_preferred":[
        "Geisingen"
    ],
    "name:vie_x_preferred":[
        "Geisingen"
    ],
    "name:vol_x_preferred":[
        "Geisingen"
    ],
    "name:war_x_preferred":[
        "Geisingen"
    ],
    "name:zho_x_preferred":[
        "\u76d6\u8f9b\u6839"
    ],
    "wof:name":"Geisingen",
    "wof:placetype":"neighbourhood"
},
  "geometry": {"coordinates":[9.18517,48.94043],"type":"Point"}
}