{
  "type": "Feature",
  "properties": {
    "gn:country":"DE",
    "gn:fcode":"PPL",
    "gn:population":0,
    "iso:country":"DE",
    "name:als_x_preferred":[
        "Weiler"
    ],
    "name:bar_x_preferred":[
        "Weiler"
    ],
    "name:ceb_x_preferred":[
        "Weiler"
    ],
    "name:deu_x_preferred":[
        "Weiler"
    ],
    "name:epo_x_preferred":[
        "Weiler"
    ],
    "name:fra_x_preferred":[
        "Weiler"
    ],
    "name:hun_x_preferred":[
        "Weiler"
    ],
    "name:ita_x_preferred":[
        "Weiler"
    ],
    "name:ltz_x_preferred":[
        "Weiler"
    ],
    "name:nld_x_preferred":[
        "Weiler"
    ],
    "name:pol_x_preferred":[
        "Weiler"
    ],
    "name:por_x_preferred":[
        "Weiler"
    ],
    "name:rus_x_preferred":[
        "\u0412\u0430\u0439\u043b\u0435\u0440"
    ],
    "name:srp_x_preferred":[
        "\u0412\u0430\u0458\u043b\u0435\u0440"
    ],
    "name:swe_x_preferred":[
        "Weiler"
    ],
    "name:ukr_x_preferred":[
        "\u0412\u0430\u0439\u043b\u0435\u0440"
    ],
    "name:vol_x_preferred":[
        "Weiler"
    ],
    "qs_pg:aaroncc":"DE",
    "qs_pg:gn_country":"DE",
    "qs_pg:gn_fcode":"PPL",
    "qs_pg:gn_pop":0,
    "qs_pg:name":"Weiler",
    "qs_pg:name_adm0":"Deutschland",
    "qs_pg:name_adm1":"Baden-W\u00fcrttemberg",
    "qs_pg:photos_9r":0,
    "qs_pg:photos_sr":0,
    "qs_pg:pop_sr":0,
    "qs_pg:qs_pg_placetype":"locality",
    "qs_pg:qs_pg_placetype_gp":"Town",
    "qs_pg:woe_adm0":23424829,
    "woe:adm0_id":23424829,
    "woe:name_adm0":"Deutschland",
    "woe:name_adm1":"Baden-W\u00fcrttemberg",
    "woe:placetype":"Town",
    "wof:name":"Weiler",
    "wof:placetype":"neighbourhood"
},
  "geometry": {"coordinates":[9.50081,48.79754],"type":"Point"}
}