{
  "type": "Feature",
  "properties": {
    "gn:admin1_code":"1",
    "gn:admin2_code":"83.0",
    "gn:admin3_code":"8336.0",
    "gn:admin4_code":"8336010.0",
    "gn:asciiname":"Oberbollen",
    "gn:country_code":"DE",
    "gn:dem":808,
    "gn:feature_class":"P",
    "gn:feature_code":"PPL",
    "gn:name":"Oberb\u00f6llen",
    "gn:population":0,
    "gn:timezone":"Europe/Berlin",
    "iso:country":"DE",
    "wof:name":"Oberbollen",
    "wof:placetype":"neighbourhood"
},
  "geometry": {"coordinates":[7.83761,47.80346],"type":"Point"}
}