{
  "type": "Feature",
  "properties": {
    "gn:admin1_code":"7",
    "gn:admin2_code":"53.0",
    "gn:admin3_code":"5374.0",
    "gn:admin4_code":"5374040.0",
    "gn:asciiname":"Komp",
    "gn:country_code":"DE",
    "gn:dem":414,
    "gn:feature_class":"P",
    "gn:feature_code":"PPL",
    "gn:name":"Komp",
    "gn:population":0,
    "gn:timezone":"Europe/Berlin",
    "iso:country":"DE",
    "name:deu_x_preferred":[
        "Komp"
    ],
    "wof:name":"Komp",
    "wof:placetype":"neighbourhood"
},
  "geometry": {"coordinates":[7.77891,50.95692],"type":"Point"}
}