{
  "type": "Feature",
  "properties": {
    "gn:admin1_code":"2",
    "gn:admin2_code":"91.0",
    "gn:admin3_code":"9177.0",
    "gn:admin4_code":"9177126.0",
    "gn:asciiname":"Vorderholzhausen",
    "gn:country_code":"DE",
    "gn:dem":443,
    "gn:feature_class":"P",
    "gn:feature_code":"PPL",
    "gn:name":"Vorderholzhausen",
    "gn:population":0,
    "gn:timezone":"Europe/Berlin",
    "iso:country":"DE",
    "wof:name":"Vorderholzhausen",
    "wof:placetype":"neighbourhood"
},
  "geometry": {"coordinates":[11.99891,48.41866],"type":"Point"}
}