{
  "type": "Feature",
  "properties": {
    "gn:admin1_code":"2",
    "gn:admin2_code":"96.0",
    "gn:admin3_code":"9673.0",
    "gn:admin4_code":"9673114.0",
    "gn:asciiname":"Schweinhof",
    "gn:country_code":"DE",
    "gn:dem":278,
    "gn:feature_class":"P",
    "gn:feature_code":"PPL",
    "gn:name":"Schweinhof",
    "gn:population":0,
    "gn:timezone":"Europe/Berlin",
    "iso:country":"DE",
    "wof:name":"Schweinhof",
    "wof:placetype":"neighbourhood"
},
  "geometry": {"coordinates":[10.17092,50.34955],"type":"Point"}
}