{
  "type": "Feature",
  "properties": {
    "gn:admin1_code":"11",
    "gn:admin2_code":"0.0",
    "gn:admin3_code":"12062.0",
    "gn:admin4_code":"12062092.0",
    "gn:asciiname":"Lugau",
    "gn:country_code":"DE",
    "gn:dem":105,
    "gn:feature_class":"P",
    "gn:feature_code":"PPL",
    "gn:name":"Lugau",
    "gn:population":0,
    "gn:timezone":"Europe/Berlin",
    "iso:country":"DE",
    "name:ara_x_preferred":[
        "\u0644\u0648\u063a\u0627\u0648"
    ],
    "name:azb_x_preferred":[
        "\u0644\u0627\u0642\u0627\u0648"
    ],
    "name:bak_x_preferred":[
        "\u041b\u0443\u0433\u0430\u0443"
    ],
    "name:ceb_x_preferred":[
        "Lugau"
    ],
    "name:deu_x_preferred":[
        "Lugau"
    ],
    "name:epo_x_preferred":[
        "Lugau"
    ],
    "name:fas_x_preferred":[
        "\u0644\u0627\u06af\u0627\u0648"
    ],
    "name:fra_x_preferred":[
        "Lugau/Erzgebirge"
    ],
    "name:hun_x_preferred":[
        "Lugau/Erzgeb."
    ],
    "name:ita_x_preferred":[
        "Lugau/Erzgeb."
    ],
    "name:lav_x_preferred":[
        "L\u016bgava"
    ],
    "name:mkd_x_preferred":[
        "\u041b\u0443\u0433\u0430\u0443"
    ],
    "name:msa_x_preferred":[
        "Lugau"
    ],
    "name:nld_x_preferred":[
        "Lugau/Erzgeb."
    ],
    "name:nor_x_preferred":[
        "Lugau"
    ],
    "name:pol_x_preferred":[
        "Lugau/Erzgeb."
    ],
    "name:por_x_preferred":[
        "Lugau"
    ],
    "name:ron_x_preferred":[
        "Lugau/Erzgeb."
    ],
    "name:rus_x_preferred":[
        "\u041b\u0443\u0433\u0430\u0443"
    ],
    "name:spa_x_preferred":[
        "Lugau"
    ],
    "name:srp_x_preferred":[
        "\u041b\u0443\u0433\u0430\u0443"
    ],
    "name:swe_x_preferred":[
        "Lugau"
    ],
    "name:ukr_x_preferred":[
        "\u041b\u0443\u0433\u0430\u0443"
    ],
    "name:uzb_x_preferred":[
        "Lugau/Erzgeb."
    ],
    "name:vol_x_preferred":[
        "Lugau/Erzgeb."
    ],
    "name:war_x_preferred":[
        "Lugau"
    ],
    "wof:name":"Lugau",
    "wof:placetype":"neighbourhood"
},
  "geometry": {"coordinates":[13.59793,51.61086],"type":"Point"}
}