{
  "type": "Feature",
  "properties": {
    "gn:admin1_code":"2",
    "gn:admin2_code":"93.0",
    "gn:admin3_code":"9372.0",
    "gn:admin4_code":"9372116.0",
    "gn:asciiname":"Eichberg",
    "gn:country_code":"DE",
    "gn:dem":513,
    "gn:feature_class":"P",
    "gn:feature_code":"PPL",
    "gn:name":"Eichberg",
    "gn:population":0,
    "gn:timezone":"Europe/Berlin",
    "iso:country":"DE",
    "name:als_x_preferred":[
        "Eichberg"
    ],
    "name:cat_x_preferred":[
        "Eichberg"
    ],
    "name:ceb_x_preferred":[
        "Eichberg"
    ],
    "name:deu_x_preferred":[
        "Eichberg"
    ],
    "name:epo_x_preferred":[
        "Eichberg"
    ],
    "name:eus_x_preferred":[
        "Eichberg"
    ],
    "name:fra_x_preferred":[
        "Eichberg"
    ],
    "name:ita_x_preferred":[
        "Eichberg"
    ],
    "name:kaz_x_preferred":[
        "\u0410\u0439\u0445\u0431\u0435\u0440\u0433"
    ],
    "name:lmo_x_preferred":[
        "Eichberg"
    ],
    "name:nld_x_preferred":[
        "Eichberg"
    ],
    "name:pol_x_preferred":[
        "Eichberg"
    ],
    "name:rus_x_preferred":[
        "\u0410\u0439\u0445\u0431\u0435\u0440\u0433"
    ],
    "name:swe_x_preferred":[
        "Eichberg"
    ],
    "name:vol_x_preferred":[
        "Eichberg"
    ],
    "wof:name":"Eichberg",
    "wof:placetype":"neighbourhood"
},
  "geometry": {"coordinates":[12.6856,49.14453],"type":"Point"}
}