{
  "type": "Feature",
  "properties": {
    "gn:gn_country":"DE",
    "gn:gn_fcode":"PPLA4",
    "gn:gn_pop":234,
    "gn:population":234,
    "iso:country":"DE",
    "name:baq_x_preferred":[
        "Besdorf"
    ],
    "name:chi_x_preferred":[
        "\u8d1d\u65af\u591a\u5c14\u592b"
    ],
    "name:dan_x_preferred":[
        "Besdorf"
    ],
    "name:dut_x_preferred":[
        "Besdorf"
    ],
    "name:eng_x_preferred":[
        "Besdorf"
    ],
    "name:epo_x_preferred":[
        "Besdorf"
    ],
    "name:fre_x_preferred":[
        "Besdorf"
    ],
    "name:ger_x_preferred":[
        "Besdorf"
    ],
    "name:hun_x_preferred":[
        "Besdorf"
    ],
    "name:ita_x_preferred":[
        "Besdorf"
    ],
    "name:mac_x_preferred":[
        "\u0411\u0435\u0441\u0434\u043e\u0440\u0444"
    ],
    "name:may_x_preferred":[
        "Besdorf"
    ],
    "name:per_x_preferred":[
        "\u0628\u0633\u062f\u0648\u0631\u0641"
    ],
    "name:pol_x_preferred":[
        "Besdorf"
    ],
    "name:por_x_preferred":[
        "Besdorf"
    ],
    "name:rum_x_preferred":[
        "Besdorf"
    ],
    "name:rus_x_preferred":[
        "\u0411\u0435\u0441\u0434\u043e\u0440\u0444"
    ],
    "name:spa_x_preferred":[
        "Besdorf"
    ],
    "name:srp_x_preferred":[
        "\u0411\u0435\u0441\u0434\u043e\u0440\u0444"
    ],
    "name:tur_x_preferred":[
        "Besdorf"
    ],
    "name:ukr_x_preferred":[
        "\u0411\u0435\u0441\u0434\u043e\u0440\u0444"
    ],
    "name:uzb_x_preferred":[
        "Besdorf"
    ],
    "name:vie_x_preferred":[
        "Besdorf"
    ],
    "name:vol_x_preferred":[
        "Besdorf"
    ],
    "name:war_x_preferred":[
        "Besdorf"
    ],
    "qs_pg:aaroncc":"DE",
    "qs_pg:gn_country":"DE",
    "qs_pg:gn_fcode":"PPLA4",
    "qs_pg:gn_pop":234,
    "qs_pg:name":"Besdorf",
    "qs_pg:photos_9r":0,
    "qs_pg:photos_sr":0,
    "qs_pg:pop_sr":2,
    "qs_pg:qs_pg_placetype":"locality",
    "wof:name":"Besdorf",
    "wof:placetype":"locality",
    "wof:population":234
},
  "geometry": {"coordinates":[9.36003,54.05007],"type":"Point"}
}