{
  "type": "Feature",
  "properties": {
    "gn:admin1_code":"1",
    "gn:admin2_code":"84.0",
    "gn:admin3_code":"8436.0",
    "gn:admin4_code":"8436096.0",
    "gn:asciiname":"Oberspringen",
    "gn:country_code":"DE",
    "gn:dem":571,
    "gn:feature_class":"P",
    "gn:feature_code":"PPL",
    "gn:name":"Oberspringen",
    "gn:population":0,
    "gn:timezone":"Europe/Berlin",
    "iso:country":"DE",
    "wof:name":"Oberspringen",
    "wof:placetype":"neighbourhood"
},
  "geometry": {"coordinates":[9.59866,47.8748],"type":"Point"}
}