{
  "type": "Feature",
  "properties": {
    "gn:admin1_code":"2",
    "gn:admin2_code":"97.0",
    "gn:admin3_code":"9778.0",
    "gn:admin4_code":"9778121.0",
    "gn:asciiname":"Unterberghofe",
    "gn:country_code":"DE",
    "gn:dem":557,
    "gn:feature_class":"P",
    "gn:feature_code":"PPL",
    "gn:name":"Unterbergh\u00f6fe",
    "gn:population":0,
    "gn:timezone":"Europe/Berlin",
    "iso:country":"DE",
    "wof:name":"Unterberghofe",
    "wof:placetype":"neighbourhood"
},
  "geometry": {"coordinates":[10.42256,48.15711],"type":"Point"}
}