{
  "type": "Feature",
  "properties": {
    "gn:admin1_code":"2",
    "gn:admin2_code":"91.0",
    "gn:admin3_code":"9187.0",
    "gn:admin4_code":"9187142.0",
    "gn:asciiname":"Stadl",
    "gn:country_code":"DE",
    "gn:dem":465,
    "gn:feature_class":"P",
    "gn:feature_code":"PPLL",
    "gn:name":"Stadl",
    "gn:population":0,
    "gn:timezone":"Europe/Berlin",
    "iso:country":"DE",
    "wof:name":"Stadl",
    "wof:placetype":"neighbourhood"
},
  "geometry": {"coordinates":[12.09367,47.90803],"type":"Point"}
}