{
  "type": "Feature",
  "properties": {
    "gn:admin1_code":"10",
    "gn:admin2_code":"0.0",
    "gn:admin3_code":"1054.0",
    "gn:admin4_code":"1054009.0",
    "gn:asciiname":"Hungerburg",
    "gn:country_code":"DE",
    "gn:dem":1,
    "gn:feature_class":"P",
    "gn:feature_code":"PPL",
    "gn:name":"Hungerburg",
    "gn:population":0,
    "gn:timezone":"Europe/Berlin",
    "iso:country":"DE",
    "name:deu_x_preferred":[
        "Hungerburg"
    ],
    "name:swe_x_preferred":[
        "Hungerburg"
    ],
    "wof:name":"Hungerburg",
    "wof:placetype":"neighbourhood"
},
  "geometry": {"coordinates":[8.83039,54.90377],"type":"Point"}
}