{
  "type": "Feature",
  "properties": {
    "gn:admin1_code":"11",
    "gn:admin2_code":"0.0",
    "gn:admin3_code":"12067.0",
    "gn:admin4_code":"12067072.0",
    "gn:asciiname":"Kersdorf",
    "gn:country_code":"DE",
    "gn:dem":42,
    "gn:feature_class":"P",
    "gn:feature_code":"PPL",
    "gn:name":"Kersdorf",
    "gn:population":0,
    "gn:timezone":"Europe/Berlin",
    "iso:country":"DE",
    "wof:name":"Kersdorf",
    "wof:placetype":"neighbourhood"
},
  "geometry": {"coordinates":[14.26149,52.33999],"type":"Point"}
}