{
  "type": "Feature",
  "properties": {
    "iso:country":"DE",
    "qs_pg:aaroncc":"DE",
    "qs_pg:name":"\u00dcberseehafengebiet",
    "qs_pg:name_adm0":"Deutschland",
    "qs_pg:name_adm1":"Freie Hansestadt Bremen",
    "qs_pg:photos":285,
    "qs_pg:photos_1k":58,
    "qs_pg:photos_9k":1,
    "qs_pg:photos_9r":4,
    "qs_pg:photos_all":285,
    "qs_pg:photos_sr":5,
    "qs_pg:pop_sr":0,
    "qs_pg:qs_pg_placetype":"locality",
    "qs_pg:qs_pg_placetype_gp":"Town",
    "qs_pg:woe_adm0":23424829,
    "woe:adm0_id":23424829,
    "woe:name_adm0":"Deutschland",
    "woe:name_adm1":"Freie Hansestadt Bremen",
    "woe:placetype":"Town",
    "wof:name":"\u00dcberseehafengebiet",
    "wof:placetype":"neighbourhood"
},
  "geometry": {"coordinates":[8.549734,53.571027],"type":"Point"}
}