{
  "type": "Feature",
  "properties": {
    "gn:admin1_code":"2",
    "gn:admin2_code":"93.0",
    "gn:admin3_code":"9376.0",
    "gn:admin4_code":"9376163.0",
    "gn:asciiname":"Sonnenried",
    "gn:country_code":"DE",
    "gn:dem":439,
    "gn:feature_class":"P",
    "gn:feature_code":"PPL",
    "gn:name":"Sonnenried",
    "gn:population":0,
    "gn:timezone":"Europe/Berlin",
    "iso:country":"DE",
    "wof:name":"Sonnenried",
    "wof:placetype":"neighbourhood"
},
  "geometry": {"coordinates":[12.23705,49.35767],"type":"Point"}
}