{
  "type": "Feature",
  "properties": {
    "iso:country":"DE",
    "wof:name":"Vollmerswerth",
    "wof:placetype":"neighbourhood"
},
  "geometry": {"coordinates":[6.75253058189891,51.18781482045879],"type":"Point"}
}