{
  "type": "Feature",
  "properties": {
    "gn:admin1_code":"13",
    "gn:admin2_code":"0.0",
    "gn:admin3_code":"14524.0",
    "gn:admin4_code":"14524320.0",
    "gn:asciiname":"Haara",
    "gn:country_code":"DE",
    "gn:dem":291,
    "gn:feature_class":"P",
    "gn:feature_code":"PPL",
    "gn:name":"Haara",
    "gn:population":0,
    "gn:timezone":"Europe/Berlin",
    "iso:country":"DE",
    "wof:name":"Haara",
    "wof:placetype":"neighbourhood"
},
  "geometry": {"coordinates":[12.52413,50.66481],"type":"Point"}
}