{
  "type": "Feature",
  "properties": {
    "iso:country":"DE",
    "name:bul_x_preferred":[
        "\u0421\u043f\u0438\u0441\u044a\u043a"
    ],
    "name:ceb_x_preferred":[
        "List"
    ],
    "name:ces_x_preferred":[
        "List"
    ],
    "name:dan_x_preferred":[
        "List"
    ],
    "name:deu_x_preferred":[
        "List"
    ],
    "name:ell_x_preferred":[
        "\u039b\u03b9\u03c3\u03c4"
    ],
    "name:fas_x_preferred":[
        "\u0644\u06cc\u0633\u062a"
    ],
    "name:fra_x_preferred":[
        "List"
    ],
    "name:heb_x_preferred":[
        "\u05dc\u05d9\u05e1\u05d8"
    ],
    "name:ita_x_preferred":[
        "List"
    ],
    "name:jpn_x_preferred":[
        "\u30ea\u30b9\u30c8"
    ],
    "name:kor_x_preferred":[
        "\ub9ac\uc2a4\ud2b8"
    ],
    "name:mkd_x_preferred":[
        "\u041b\u0438\u0441\u0442"
    ],
    "name:nds_x_preferred":[
        "List"
    ],
    "name:new_x_preferred":[
        "\u0927\u0932\u0903"
    ],
    "name:nld_x_preferred":[
        "List"
    ],
    "name:pol_x_preferred":[
        "List"
    ],
    "name:por_x_preferred":[
        "List"
    ],
    "name:pus_x_preferred":[
        "\u0644\u0693\u0644\u064a\u06a9"
    ],
    "name:rus_x_preferred":[
        "\u0421\u043f\u0438\u0441\u043e\u043a"
    ],
    "name:slk_x_preferred":[
        "List"
    ],
    "name:slv_x_preferred":[
        "List"
    ],
    "name:srp_x_preferred":[
        "\u041b\u0438\u0441\u0442"
    ],
    "name:swe_x_preferred":[
        "List"
    ],
    "name:tam_x_preferred":[
        "\u0baa\u0b9f\u0bcd\u0b9f\u0bbf\u0baf\u0bb2\u0bcd"
    ],
    "wof:name":"List",
    "wof:placetype":"neighbourhood"
},
  "geometry": {"coordinates":[9.75031668977436,52.39187989519251],"type":"Point"}
}