{
  "type": "Feature",
  "properties": {
    "iso:country":"DE",
    "wof:name":"List",
    "wof:placetype":"neighbourhood"
},
  "geometry": {"coordinates":[9.75031668977436,52.39187989519251],"type":"Point"}
}