{
  "type": "Feature",
  "properties": {
    "gn:admin1_code":"2",
    "gn:admin2_code":"95.0",
    "gn:admin3_code":"9574.0",
    "gn:admin4_code":"9574155.0",
    "gn:asciiname":"Untersdorf",
    "gn:country_code":"DE",
    "gn:dem":375,
    "gn:feature_class":"P",
    "gn:feature_code":"PPL",
    "gn:name":"Untersdorf",
    "gn:population":0,
    "gn:timezone":"Europe/Berlin",
    "iso:country":"DE",
    "wof:name":"Untersdorf",
    "wof:placetype":"neighbourhood"
},
  "geometry": {"coordinates":[11.29811,49.56876],"type":"Point"}
}