{
  "type": "Feature",
  "properties": {
    "gn:admin1_code":"2",
    "gn:admin2_code":"93.0",
    "gn:admin3_code":"9371.0",
    "gn:admin4_code":"9371119.0",
    "gn:asciiname":"Steinling",
    "gn:country_code":"DE",
    "gn:dem":448,
    "gn:feature_class":"P",
    "gn:feature_code":"PPL",
    "gn:name":"Steinling",
    "gn:population":0,
    "gn:timezone":"Europe/Berlin",
    "iso:country":"DE",
    "wof:name":"Steinling",
    "wof:placetype":"neighbourhood"
},
  "geometry": {"coordinates":[11.71082,49.56609],"type":"Point"}
}