{
  "type": "Feature",
  "properties": {
    "gn:admin1_code":"8.0",
    "gn:admin2_code":"0.0",
    "gn:admin3_code":"7141.0",
    "gn:admin4_code":"7141089.0",
    "gn:asciiname":"Bonscheuer",
    "gn:country_code":"DE",
    "gn:dem":357,
    "gn:feature_class":"P",
    "gn:feature_code":"PPL",
    "gn:name":"Bonscheuer",
    "gn:population":0,
    "gn:timezone":"Europe/Berlin",
    "iso:country":"DE",
    "wof:name":"Bonscheuer",
    "wof:placetype":"neighbourhood"
},
  "geometry": {"coordinates":[8.02858,50.27105],"type":"Point"}
}