{
  "type": "Feature",
  "properties": {
    "gn:admin1_code":"2",
    "gn:admin2_code":"94.0",
    "gn:admin3_code":"9473.0",
    "gn:admin4_code":"9473141.0",
    "gn:asciiname":"Tiefenlauter",
    "gn:country_code":"DE",
    "gn:dem":357,
    "gn:feature_class":"P",
    "gn:feature_code":"PPL",
    "gn:name":"Tiefenlauter",
    "gn:population":0,
    "gn:timezone":"Europe/Berlin",
    "iso:country":"DE",
    "wof:name":"Tiefenlauter",
    "wof:placetype":"neighbourhood"
},
  "geometry": {"coordinates":[10.97073,50.32959],"type":"Point"}
}