{
  "type": "Feature",
  "properties": {
    "gn:admin1_code":"5.0",
    "gn:admin2_code":"64.0",
    "gn:admin3_code":"6435.0",
    "gn:admin4_code":"6435029.0",
    "gn:asciiname":"Aufenau",
    "gn:country_code":"DE",
    "gn:dem":145,
    "gn:feature_class":"P",
    "gn:feature_code":"PPL",
    "gn:name":"Aufenau",
    "gn:population":0,
    "gn:timezone":"Europe/Berlin",
    "iso:country":"DE",
    "wof:name":"Aufenau",
    "wof:placetype":"neighbourhood"
},
  "geometry": {"coordinates":[9.32122,50.25235],"type":"Point"}
}