{
  "type": "Feature",
  "properties": {
    "iso:country":"DE",
    "name:als_x_preferred":[
        "Erlen"
    ],
    "name:ara_x_preferred":[
        "\u0625\u0631\u0644\u0646"
    ],
    "name:cat_x_preferred":[
        "Erlen"
    ],
    "name:ceb_x_preferred":[
        "Erlen"
    ],
    "name:chv_x_preferred":[
        "\u042d\u0440\u043b\u0435\u043d"
    ],
    "name:deu_x_preferred":[
        "Erlen"
    ],
    "name:epo_x_preferred":[
        "Erlen"
    ],
    "name:eus_x_preferred":[
        "Erlen"
    ],
    "name:fra_x_preferred":[
        "Erlen"
    ],
    "name:ita_x_preferred":[
        "Erlen"
    ],
    "name:kaz_x_preferred":[
        "\u042d\u0440\u043b\u0435\u043d"
    ],
    "name:lmo_x_preferred":[
        "Erlen"
    ],
    "name:msa_x_preferred":[
        "Erlen"
    ],
    "name:nld_x_preferred":[
        "Erlen"
    ],
    "name:nno_x_preferred":[
        "Erlen"
    ],
    "name:pms_x_preferred":[
        "Erlen"
    ],
    "name:pol_x_preferred":[
        "Erlen"
    ],
    "name:por_x_preferred":[
        "Erlen"
    ],
    "name:rus_x_preferred":[
        "\u042d\u0440\u043b\u0435\u043d"
    ],
    "name:spa_x_preferred":[
        "Erlen"
    ],
    "name:swe_x_preferred":[
        "Erlen"
    ],
    "name:uzb_x_preferred":[
        "Erlen"
    ],
    "name:vol_x_preferred":[
        "Erlen"
    ],
    "name:war_x_preferred":[
        "Erlen"
    ],
    "qs_pg:aaroncc":"DE",
    "qs_pg:name":"Erlen",
    "qs_pg:name_adm0":"Deutschland",
    "qs_pg:name_adm1":"Nordrhein-Westfalen",
    "qs_pg:photos":3,
    "qs_pg:photos_1k":1,
    "qs_pg:photos_9k":1,
    "qs_pg:photos_9r":1,
    "qs_pg:photos_all":3,
    "qs_pg:photos_sr":1,
    "qs_pg:pop_sr":0,
    "qs_pg:qs_pg_placetype":"neighbourhood",
    "qs_pg:qs_pg_placetype_gp":"Suburb",
    "qs_pg:woe_adm0":23424829,
    "woe:adm0_id":23424829,
    "woe:name_adm0":"Deutschland",
    "woe:name_adm1":"Nordrhein-Westfalen",
    "woe:placetype":"Suburb",
    "wof:name":"Erlen",
    "wof:placetype":"neighbourhood"
},
  "geometry": {"coordinates":[7.331335,51.438453],"type":"Point"}
}