{
  "type": "Feature",
  "properties": {
    "gn:admin1_code":"1.0",
    "gn:admin2_code":"81.0",
    "gn:admin3_code":"8117.0",
    "gn:admin4_code":"8117011.0",
    "gn:asciiname":"Breech",
    "gn:country_code":"DE",
    "gn:dem":472,
    "gn:feature_class":"P",
    "gn:feature_code":"PPL",
    "gn:name":"Breech",
    "gn:population":0,
    "gn:timezone":"Europe/Berlin",
    "iso:country":"DE",
    "name:deu_x_preferred":[
        "Breech"
    ],
    "wof:name":"Breech",
    "wof:placetype":"neighbourhood"
},
  "geometry": {"coordinates":[9.62583,48.76948],"type":"Point"}
}