{
  "type": "Feature",
  "properties": {
    "gn:admin1_code":"2",
    "gn:admin2_code":"91.0",
    "gn:admin3_code":"9173.0",
    "gn:admin4_code":"9173120.0",
    "gn:asciiname":"Ohnbock",
    "gn:country_code":"DE",
    "gn:dem":648,
    "gn:feature_class":"P",
    "gn:feature_code":"PPL",
    "gn:name":"\u00d6hnb\u00f6ck",
    "gn:population":0,
    "gn:timezone":"Europe/Berlin",
    "iso:country":"DE",
    "name:deu_x_preferred":[
        "Oehnb\u00f6ck"
    ],
    "wof:name":"Ohnbock",
    "wof:placetype":"neighbourhood"
},
  "geometry": {"coordinates":[11.5317,47.92635],"type":"Point"}
}