{
  "type": "Feature",
  "properties": {
    "iso:country":"DE",
    "name:deu_x_colloquial":[
        "Gross Drienhausen"
    ],
    "name:deu_x_preferred":[
        "Gro\u00df Drienhausen"
    ],
    "name:unk_x_variant":[
        "Gro\u00df Drienhausen"
    ],
    "qs:gn_adm0_cc":"DE",
    "qs:gn_local":2805753,
    "qs:gn_nam_loc":"wuppertal",
    "qs:gn_namadm1":"07",
    "qs:local_max":2358,
    "qs:local_sum":9442,
    "qs:localhoods":28,
    "qs:name":"Gro\u00df Drienhausen",
    "qs:name_adm0":"Deutschland",
    "qs:name_adm1":"Nordrhein-Westfalen",
    "qs:name_adm2":"Stadtkreis Wuppertal",
    "qs:name_lau":"Sch\u00f6ller-Dornap",
    "qs:name_local":"Wuppertal",
    "qs:photo_max":7,
    "qs:photo_sum":31,
    "qs:placetype":"Suburb",
    "qs:quad_count":14,
    "qs:woe_adm0":23424829,
    "qs:woe_adm1":2345487,
    "qs:woe_adm2":12597064,
    "qs:woe_lau":26823398,
    "qs:woe_local":708228,
    "qs:woe_ver":"7.10.0",
    "wof:lang":[
        "ger"
    ],
    "wof:name":"Gro\u00df Drienhausen",
    "wof:placetype":"neighbourhood"
},
  "geometry": {"coordinates":[6.994127,51.238565],"type":"Point"}
}