{
  "type": "Feature",
  "properties": {
    "gn:admin1_code":"1",
    "gn:admin2_code":"81.0",
    "gn:admin3_code":"8128.0",
    "gn:admin4_code":"8128126.0",
    "gn:asciiname":"Bronn",
    "gn:country_code":"DE",
    "gn:dem":372,
    "gn:feature_class":"P",
    "gn:feature_code":"PPL",
    "gn:name":"Bronn",
    "gn:population":0,
    "gn:timezone":"Europe/Berlin",
    "iso:country":"DE",
    "name:deu_x_preferred":[
        "Bronn"
    ],
    "name:fra_x_preferred":[
        "Bronn"
    ],
    "name:nld_x_preferred":[
        "Bronn"
    ],
    "name:rus_x_preferred":[
        "\u0411\u0440\u043e\u043d\u043d"
    ],
    "wof:name":"Bronn",
    "wof:placetype":"neighbourhood"
},
  "geometry": {"coordinates":[9.89042,49.43937],"type":"Point"}
}