{
  "type": "Feature",
  "properties": {
    "gn:admin1_code":"2",
    "gn:admin2_code":"92.0",
    "gn:admin3_code":"9278.0",
    "gn:admin4_code":"9278139.0",
    "gn:asciiname":"Rammersberg",
    "gn:country_code":"DE",
    "gn:dem":430,
    "gn:feature_class":"P",
    "gn:feature_code":"PPL",
    "gn:name":"Rammersberg",
    "gn:population":0,
    "gn:timezone":"Europe/Berlin",
    "iso:country":"DE",
    "wof:name":"Rammersberg",
    "wof:placetype":"neighbourhood"
},
  "geometry": {"coordinates":[12.6887,48.95112],"type":"Point"}
}