{
  "type": "Feature",
  "properties": {
    "gn:admin1_code":"7",
    "gn:admin2_code":"53.0",
    "gn:admin3_code":"5370.0",
    "gn:admin4_code":"5370040.0",
    "gn:asciiname":"Petersholz",
    "gn:country_code":"DE",
    "gn:dem":87,
    "gn:feature_class":"P",
    "gn:feature_code":"PPL",
    "gn:name":"Petersholz",
    "gn:population":0,
    "gn:timezone":"Europe/Berlin",
    "iso:country":"DE",
    "wof:name":"Petersholz",
    "wof:placetype":"neighbourhood"
},
  "geometry": {"coordinates":[6.22132,51.13312],"type":"Point"}
}