{
  "type": "Feature",
  "properties": {
    "gn:admin1_code":"2",
    "gn:admin2_code":"95.0",
    "gn:admin3_code":"9574.0",
    "gn:admin4_code":"9574112.0",
    "gn:asciiname":"Rothenbach bei Altdorf",
    "gn:country_code":"DE",
    "gn:dem":411,
    "gn:feature_class":"P",
    "gn:feature_code":"PPL",
    "gn:name":"R\u00f6thenbach bei Altdorf",
    "gn:population":0,
    "gn:timezone":"Europe/Berlin",
    "iso:country":"DE",
    "wof:name":"Rothenbach bei Altdorf",
    "wof:placetype":"neighbourhood"
},
  "geometry": {"coordinates":[11.33798,49.40131],"type":"Point"}
}