{
  "type": "Feature",
  "properties": {
    "gn:admin1_code":"12",
    "gn:admin2_code":"0.0",
    "gn:admin3_code":"13071.0",
    "gn:admin4_code":"13071071.0",
    "gn:asciiname":"Priesterbak",
    "gn:country_code":"DE",
    "gn:dem":70,
    "gn:feature_class":"P",
    "gn:feature_code":"PPL",
    "gn:name":"Priesterbak",
    "gn:population":0,
    "gn:timezone":"Europe/Berlin",
    "iso:country":"DE",
    "wof:name":"Priesterbak",
    "wof:placetype":"neighbourhood"
},
  "geometry": {"coordinates":[12.85,53.41667],"type":"Point"}
}