{
  "type": "Feature",
  "properties": {
    "gn:admin1_code":"1",
    "gn:admin2_code":"81.0",
    "gn:admin3_code":"8128.0",
    "gn:admin4_code":"8128131.0",
    "gn:asciiname":"Sonderriet",
    "gn:country_code":"DE",
    "gn:dem":319,
    "gn:feature_class":"P",
    "gn:feature_code":"PPL",
    "gn:name":"Sonderriet",
    "gn:population":0,
    "gn:timezone":"Europe/Berlin",
    "iso:country":"DE",
    "name:und_x_variant":[
        "Sonderrieth",
        "Sonderriet"
    ],
    "wof:name":"Sonderriet",
    "wof:placetype":"neighbourhood"
},
  "geometry": {"coordinates":[9.4385,49.71845],"type":"Point"}
}