{
  "type": "Feature",
  "properties": {
    "gn:admin1_code":"2",
    "gn:admin2_code":"91.0",
    "gn:admin3_code":"9174.0",
    "gn:admin4_code":"9174111.0",
    "gn:asciiname":"Schmarnzell",
    "gn:country_code":"DE",
    "gn:dem":545,
    "gn:feature_class":"P",
    "gn:feature_code":"PPL",
    "gn:name":"Schmarnzell",
    "gn:population":0,
    "gn:timezone":"Europe/Berlin",
    "iso:country":"DE",
    "wof:name":"Schmarnzell",
    "wof:placetype":"neighbourhood"
},
  "geometry": {"coordinates":[11.27064,48.42321],"type":"Point"}
}