{
  "type": "Feature",
  "properties": {
    "gn:admin1_code":"2",
    "gn:admin2_code":"97.0",
    "gn:admin3_code":"9779.0",
    "gn:admin4_code":"9779155.0",
    "gn:asciiname":"Ebermergen",
    "gn:country_code":"DE",
    "gn:dem":406,
    "gn:feature_class":"P",
    "gn:feature_code":"PPL",
    "gn:name":"Ebermergen",
    "gn:population":0,
    "gn:timezone":"Europe/Berlin",
    "iso:country":"DE",
    "wof:name":"Ebermergen",
    "wof:placetype":"neighbourhood"
},
  "geometry": {"coordinates":[10.71462,48.75418],"type":"Point"}
}