{
  "type": "Feature",
  "properties": {
    "gn:admin1_code":"15",
    "gn:admin2_code":"0.0",
    "gn:admin3_code":"16074.0",
    "gn:admin4_code":"16074095.0",
    "gn:asciiname":"Sulza",
    "gn:country_code":"DE",
    "gn:dem":217,
    "gn:feature_class":"P",
    "gn:feature_code":"PPLA4",
    "gn:name":"Sulza",
    "gn:population":316,
    "gn:timezone":"Europe/Berlin",
    "iso:country":"DE",
    "wof:name":"Sulza",
    "wof:placetype":"locality",
    "wof:population":316
},
  "geometry": {"coordinates":[11.61667,50.86667],"type":"Point"}
}