{
  "type": "Feature",
  "properties": {
    "gn:admin1_code":"12",
    "gn:admin2_code":"0.0",
    "gn:admin3_code":"13076.0",
    "gn:admin4_code":"13076128.0",
    "gn:asciiname":"Klein Goernow",
    "gn:country_code":"DE",
    "gn:dem":38,
    "gn:feature_class":"P",
    "gn:feature_code":"PPL",
    "gn:name":"Klein G\u00f6rnow",
    "gn:population":0,
    "gn:timezone":"Europe/Berlin",
    "iso:country":"DE",
    "wof:name":"Klein Goernow",
    "wof:placetype":"neighbourhood"
},
  "geometry": {"coordinates":[11.8034,53.75776],"type":"Point"}
}