{
  "type": "Feature",
  "properties": {
    "gn:admin1_code":"2",
    "gn:admin2_code":"97.0",
    "gn:admin3_code":"9780.0",
    "gn:admin4_code":"9780145.0",
    "gn:asciiname":"Gereute",
    "gn:country_code":"DE",
    "gn:dem":1088,
    "gn:feature_class":"P",
    "gn:feature_code":"PPL",
    "gn:name":"Gereute",
    "gn:population":0,
    "gn:timezone":"Europe/Berlin",
    "iso:country":"DE",
    "wof:name":"Gereute",
    "wof:placetype":"neighbourhood"
},
  "geometry": {"coordinates":[10.38981,47.61338],"type":"Point"}
}