{
  "type": "Feature",
  "properties": {
    "gn:admin1_code":"11",
    "gn:admin2_code":"0.0",
    "gn:admin3_code":"12067.0",
    "gn:admin4_code":"12067426.0",
    "gn:asciiname":"Herzberg",
    "gn:country_code":"DE",
    "gn:dem":94,
    "gn:feature_class":"P",
    "gn:feature_code":"PPL",
    "gn:name":"Herzberg",
    "gn:population":0,
    "gn:timezone":"Europe/Berlin",
    "iso:country":"DE",
    "name:ceb_x_preferred":[
        "Herzberg"
    ],
    "name:deu_x_preferred":[
        "Herzberg"
    ],
    "name:epo_x_preferred":[
        "Herzberg"
    ],
    "name:fas_x_preferred":[
        "\u0647\u0631\u062a\u0633\u0628\u0631\u06af"
    ],
    "name:fra_x_preferred":[
        "Herzberg"
    ],
    "name:hye_x_preferred":[
        "\u0540\u0565\u0580\u0581\u0562\u0565\u0580\u0563"
    ],
    "name:ita_x_preferred":[
        "Herzberg"
    ],
    "name:jpn_x_preferred":[
        "\u30d8\u30eb\u30c4\u30d9\u30eb\u30af"
    ],
    "name:mkd_x_preferred":[
        "\u0425\u0435\u0440\u0446\u0431\u0435\u0440\u0433"
    ],
    "name:nld_x_preferred":[
        "Herzberg"
    ],
    "name:pol_x_preferred":[
        "Herzberg"
    ],
    "name:por_x_preferred":[
        "Herzberg"
    ],
    "name:rus_x_preferred":[
        "\u0425\u0435\u0440\u0446\u0431\u0435\u0440\u0433"
    ],
    "name:spa_x_preferred":[
        "Herzberg"
    ],
    "name:srp_x_preferred":[
        "\u0425\u0435\u0440\u0446\u0431\u0435\u0440\u0433"
    ],
    "name:swe_x_preferred":[
        "Herzberg"
    ],
    "name:uzb_x_preferred":[
        "Xersberg"
    ],
    "name:vol_x_preferred":[
        "Herzberg"
    ],
    "wof:name":"Herzberg",
    "wof:placetype":"neighbourhood"
},
  "geometry": {"coordinates":[14.11809,52.21769000000001],"type":"Point"}
}