{
  "type": "Feature",
  "properties": {
    "gn:admin1_code":"15",
    "gn:admin2_code":"0.0",
    "gn:admin3_code":"16075.0",
    "gn:admin4_code":"16075132.0",
    "gn:asciiname":"Mielesdorf",
    "gn:country_code":"DE",
    "gn:dem":532,
    "gn:feature_class":"P",
    "gn:feature_code":"PPL",
    "gn:name":"Mielesdorf",
    "gn:population":0,
    "gn:timezone":"Europe/Berlin",
    "iso:country":"DE",
    "wof:name":"Mielesdorf",
    "wof:placetype":"neighbourhood"
},
  "geometry": {"coordinates":[11.86443,50.52939],"type":"Point"}
}