{
  "type": "Feature",
  "properties": {
    "gn:admin1_code":"15",
    "gn:admin2_code":"0.0",
    "gn:admin3_code":"16068.0",
    "gn:admin4_code":"16068051.0",
    "gn:asciiname":"Schallenburg",
    "gn:country_code":"DE",
    "gn:dem":150,
    "gn:feature_class":"P",
    "gn:feature_code":"PPL",
    "gn:name":"Schallenburg",
    "gn:population":0,
    "gn:timezone":"Europe/Berlin",
    "iso:country":"DE",
    "wof:name":"Schallenburg",
    "wof:placetype":"neighbourhood"
},
  "geometry": {"coordinates":[11.0845,51.14014],"type":"Point"}
}