{
  "type": "Feature",
  "properties": {
    "gn:admin1_code":"13",
    "gn:admin2_code":"0.0",
    "gn:admin3_code":"14523.0",
    "gn:admin4_code":"14523020.0",
    "gn:asciiname":"Fichtzig",
    "gn:country_code":"DE",
    "gn:dem":573,
    "gn:feature_class":"P",
    "gn:feature_code":"PPL",
    "gn:name":"Fichtzig",
    "gn:population":0,
    "gn:timezone":"Europe/Berlin",
    "iso:country":"DE",
    "wof:name":"Fichtzig",
    "wof:placetype":"neighbourhood"
},
  "geometry": {"coordinates":[12.4233,50.48999],"type":"Point"}
}