{
  "type": "Feature",
  "properties": {
    "gn:gn_country":"DE",
    "gn:gn_fcode":"PPL",
    "gn:gn_pop":149,
    "gn:population":149,
    "iso:country":"DE",
    "qs_pg:aaroncc":"DE",
    "qs_pg:gn_country":"DE",
    "qs_pg:gn_fcode":"PPL",
    "qs_pg:gn_pop":149,
    "qs_pg:name":"D\u00f6nitz",
    "qs_pg:name_adm0":"Deutschland",
    "qs_pg:name_adm1":"Sachsen-Anhalt",
    "qs_pg:photos_9r":0,
    "qs_pg:photos_sr":0,
    "qs_pg:pop_sr":1,
    "qs_pg:qs_pg_placetype":"locality",
    "qs_pg:qs_pg_placetype_gp":"Town",
    "qs_pg:woe_adm0":23424829,
    "woe:adm0_id":23424829,
    "woe:name_adm0":"Deutschland",
    "woe:name_adm1":"Sachsen-Anhalt",
    "woe:placetype":"Town",
    "wof:name":"D\u00f6nitz",
    "wof:placetype":"neighbourhood",
    "wof:population":149
},
  "geometry": {"coordinates":[11.04589,52.61222],"type":"Point"}
}