{
  "type": "Feature",
  "properties": {
    "gn:country":"DE",
    "gn:fcode":"PPL",
    "gn:population":149,
    "iso:country":"DE",
    "name:bak_x_preferred":[
        "\u0414\u0451\u043d\u0438\u0446"
    ],
    "name:ceb_x_preferred":[
        "D\u00f6nitz"
    ],
    "name:deu_x_preferred":[
        "D\u00f6nitz"
    ],
    "name:epo_x_preferred":[
        "D\u00f6nitz"
    ],
    "name:fas_x_preferred":[
        "\u062f\u0648\u0646\u06cc\u062a\u0633"
    ],
    "name:ita_x_preferred":[
        "D\u00f6nitz"
    ],
    "name:kaz_x_preferred":[
        "\u0414\u0451\u043d\u0438\u0446"
    ],
    "name:kir_x_preferred":[
        "\u0414\u04e9\u043d\u0438\u0446"
    ],
    "name:nld_x_preferred":[
        "D\u00f6nitz"
    ],
    "name:ron_x_preferred":[
        "D\u00f6nitz"
    ],
    "name:rus_x_preferred":[
        "\u0414\u0451\u043d\u0438\u0446"
    ],
    "name:uzb_x_preferred":[
        "D\u00f6nitz"
    ],
    "name:vie_x_preferred":[
        "D\u00f6nitz"
    ],
    "name:vol_x_preferred":[
        "D\u00f6nitz"
    ],
    "qs_pg:aaroncc":"DE",
    "qs_pg:gn_country":"DE",
    "qs_pg:gn_fcode":"PPL",
    "qs_pg:gn_pop":149,
    "qs_pg:name":"D\u00f6nitz",
    "qs_pg:name_adm0":"Deutschland",
    "qs_pg:name_adm1":"Sachsen-Anhalt",
    "qs_pg:photos_9r":0,
    "qs_pg:photos_sr":0,
    "qs_pg:pop_sr":1,
    "qs_pg:qs_pg_placetype":"locality",
    "qs_pg:qs_pg_placetype_gp":"Town",
    "qs_pg:woe_adm0":23424829,
    "woe:adm0_id":23424829,
    "woe:name_adm0":"Deutschland",
    "woe:name_adm1":"Sachsen-Anhalt",
    "woe:placetype":"Town",
    "wof:name":"D\u00f6nitz",
    "wof:placetype":"neighbourhood",
    "wof:population":149
},
  "geometry": {"coordinates":[11.04589,52.61222],"type":"Point"}
}