{
  "type": "Feature",
  "properties": {
    "gn:admin1_code":"2",
    "gn:admin2_code":"92.0",
    "gn:admin3_code":"9273.0",
    "gn:admin4_code":"9273147.0",
    "gn:asciiname":"Kleingundertshausen",
    "gn:country_code":"DE",
    "gn:dem":455,
    "gn:feature_class":"P",
    "gn:feature_code":"PPL",
    "gn:name":"Kleingundertshausen",
    "gn:population":0,
    "gn:timezone":"Europe/Berlin",
    "iso:country":"DE",
    "wof:name":"Kleingundertshausen",
    "wof:placetype":"neighbourhood"
},
  "geometry": {"coordinates":[11.81053,48.6162],"type":"Point"}
}