{
  "type": "Feature",
  "properties": {
    "gn:admin1_code":"2",
    "gn:admin2_code":"93.0",
    "gn:admin3_code":"9374.0",
    "gn:admin4_code":"9374168.0",
    "gn:asciiname":"Johannisthal",
    "gn:country_code":"DE",
    "gn:dem":445,
    "gn:feature_class":"P",
    "gn:feature_code":"PPL",
    "gn:name":"Johannisthal",
    "gn:population":0,
    "gn:timezone":"Europe/Berlin",
    "iso:country":"DE",
    "name:ceb_x_preferred":[
        "Johannisthal"
    ],
    "name:deu_x_preferred":[
        "Johannisthal"
    ],
    "name:pol_x_preferred":[
        "Johannisthal"
    ],
    "name:rus_x_preferred":[
        "\u0419\u043e\u0445\u0430\u043d\u043d\u0438\u0441\u0442\u0430\u043b\u044c"
    ],
    "wof:name":"Johannisthal",
    "wof:placetype":"neighbourhood"
},
  "geometry": {"coordinates":[12.16868,49.81214],"type":"Point"}
}