{
  "type": "Feature",
  "properties": {
    "gn:admin1_code":"11",
    "gn:admin2_code":"0.0",
    "gn:admin3_code":"12065.0",
    "gn:admin4_code":"12065084.0",
    "gn:asciiname":"Steinhavelmuehle",
    "gn:country_code":"DE",
    "gn:dem":60,
    "gn:feature_class":"P",
    "gn:feature_code":"PPL",
    "gn:name":"Steinhavelm\u00fchle",
    "gn:population":0,
    "gn:timezone":"Europe/Berlin",
    "iso:country":"DE",
    "wof:name":"Steinhavelmuehle",
    "wof:placetype":"neighbourhood"
},
  "geometry": {"coordinates":[13.10559,53.19317],"type":"Point"}
}