{
  "type": "Feature",
  "properties": {
    "gn:admin1_code":"2.0",
    "gn:admin2_code":"092",
    "gn:admin3_code":"9278.0",
    "gn:admin4_code":"9278187.0",
    "gn:asciiname":"Wimpassing",
    "gn:country_code":"DE",
    "gn:dem":447,
    "gn:feature_class":"P",
    "gn:feature_code":"PPL",
    "gn:name":"Wimpassing",
    "gn:population":0,
    "gn:timezone":"Europe/Berlin",
    "iso:country":"DE",
    "wof:name":"Wimpassing",
    "wof:placetype":"neighbourhood"
},
  "geometry": {"coordinates":[12.84868,48.91784000000001],"type":"Point"}
}