{
  "type": "Feature",
  "properties": {
    "gn:admin1_code":"7.0",
    "gn:admin2_code":"59.0",
    "gn:admin3_code":"5962.0",
    "gn:admin4_code":"5962052.0",
    "gn:asciiname":"Blemke",
    "gn:country_code":"DE",
    "gn:dem":249,
    "gn:feature_class":"P",
    "gn:feature_code":"PPL",
    "gn:name":"Blemke",
    "gn:population":0,
    "gn:timezone":"Europe/Berlin",
    "iso:country":"DE",
    "name:und_x_variant":[
        "Blemcke",
        "Blemke"
    ],
    "wof:name":"Blemke",
    "wof:placetype":"neighbourhood"
},
  "geometry": {"coordinates":[7.87772,51.24034],"type":"Point"}
}