{
  "type": "Feature",
  "properties": {
    "gn:admin1_code":"2",
    "gn:admin2_code":"91.0",
    "gn:admin3_code":"9178.0",
    "gn:admin4_code":"9178144.0",
    "gn:asciiname":"Faistenberg",
    "gn:country_code":"DE",
    "gn:dem":502,
    "gn:feature_class":"P",
    "gn:feature_code":"PPL",
    "gn:name":"Faistenberg",
    "gn:population":0,
    "gn:timezone":"Europe/Berlin",
    "iso:country":"DE",
    "wof:name":"Faistenberg",
    "wof:placetype":"neighbourhood"
},
  "geometry": {"coordinates":[11.80305,48.5502],"type":"Point"}
}