{
  "type": "Feature",
  "properties": {
    "gn:admin1_code":"1",
    "gn:admin2_code":"82.0",
    "gn:admin3_code":"8235.0",
    "gn:admin4_code":"8235067.0",
    "gn:asciiname":"Buchelbronn",
    "gn:country_code":"DE",
    "gn:dem":524,
    "gn:feature_class":"P",
    "gn:feature_code":"PPL",
    "gn:name":"B\u00fcchelbronn",
    "gn:population":0,
    "gn:timezone":"Europe/Berlin",
    "iso:country":"DE",
    "wof:name":"Buchelbronn",
    "wof:placetype":"neighbourhood"
},
  "geometry": {"coordinates":[8.81314,48.74097],"type":"Point"}
}