{
  "type": "Feature",
  "properties": {
    "gn:country":"DE",
    "gn:fcode":"PPL",
    "gn:population":840,
    "iso:country":"DE",
    "name:ceb_x_preferred":[
        "Forst"
    ],
    "name:deu_x_preferred":[
        "Forst"
    ],
    "name:epo_x_preferred":[
        "Forst"
    ],
    "name:eus_x_preferred":[
        "Forst"
    ],
    "name:fra_x_preferred":[
        "Forst"
    ],
    "name:hun_x_preferred":[
        "Forst"
    ],
    "name:ita_x_preferred":[
        "Forst"
    ],
    "name:lim_x_preferred":[
        "Forst"
    ],
    "name:nld_x_preferred":[
        "Forst"
    ],
    "name:pfl_x_preferred":[
        "Forst"
    ],
    "name:pol_x_preferred":[
        "Forst"
    ],
    "name:por_x_preferred":[
        "Forst"
    ],
    "name:ron_x_preferred":[
        "Forst"
    ],
    "name:rus_x_preferred":[
        "\u0424\u043e\u0440\u0441\u0442"
    ],
    "name:spa_x_preferred":[
        "Forst"
    ],
    "name:srp_x_preferred":[
        "\u0424\u043e\u0440\u0441\u0442"
    ],
    "name:swe_x_preferred":[
        "Forst"
    ],
    "name:ukr_x_preferred":[
        "\u0424\u043e\u0440\u0441\u0442"
    ],
    "name:vol_x_preferred":[
        "Forst"
    ],
    "qs_pg:aaroncc":"DE",
    "qs_pg:gn_country":"DE",
    "qs_pg:gn_fcode":"PPL",
    "qs_pg:gn_pop":840,
    "qs_pg:name":"Forst",
    "qs_pg:photos_9r":0,
    "qs_pg:photos_sr":0,
    "qs_pg:pop_sr":2,
    "qs_pg:qs_pg_placetype":"locality",
    "wof:name":"Forst",
    "wof:placetype":"neighbourhood",
    "wof:population":840
},
  "geometry": {"coordinates":[8.1897,49.42567],"type":"Point"}
}