{
  "type": "Feature",
  "properties": {
    "gn:admin1_code":"2.0",
    "gn:admin2_code":"96.0",
    "gn:admin3_code":"9661.0",
    "gn:admin4_code":"9661000.0",
    "gn:asciiname":"Strietwald",
    "gn:country_code":"DE",
    "gn:dem":131,
    "gn:feature_class":"P",
    "gn:feature_code":"PPL",
    "gn:name":"Strietwald",
    "gn:population":0,
    "gn:timezone":"Europe/Berlin",
    "iso:country":"DE",
    "wof:name":"Strietwald",
    "wof:placetype":"neighbourhood"
},
  "geometry": {"coordinates":[9.11831,49.9911],"type":"Point"}
}