{
  "type": "Feature",
  "properties": {
    "gn:admin1_code":"2",
    "gn:admin2_code":"94.0",
    "gn:admin3_code":"9474.0",
    "gn:admin4_code":"9474124.0",
    "gn:asciiname":"Egloffsteinerhull",
    "gn:country_code":"DE",
    "gn:dem":473,
    "gn:feature_class":"P",
    "gn:feature_code":"PPL",
    "gn:name":"Egloffsteinerh\u00fcll",
    "gn:population":0,
    "gn:timezone":"Europe/Berlin",
    "iso:country":"DE",
    "name:und_x_variant":[
        "Egloffsteinerh\u00fctt",
        "Egloffsteinerh\u00fcll"
    ],
    "wof:name":"Egloffsteinerhull",
    "wof:placetype":"neighbourhood"
},
  "geometry": {"coordinates":[11.2268,49.70799],"type":"Point"}
}