{
  "type": "Feature",
  "properties": {
    "gn:admin1_code":"2",
    "gn:admin2_code":"93.0",
    "gn:admin3_code":"9375.0",
    "gn:admin4_code":"9375190.0",
    "gn:asciiname":"Kleinramspau",
    "gn:country_code":"DE",
    "gn:dem":345,
    "gn:feature_class":"P",
    "gn:feature_code":"PPL",
    "gn:name":"Kleinramspau",
    "gn:population":0,
    "gn:timezone":"Europe/Berlin",
    "iso:country":"DE",
    "wof:name":"Kleinramspau",
    "wof:placetype":"neighbourhood"
},
  "geometry": {"coordinates":[12.15329,49.15524],"type":"Point"}
}