{
  "type": "Feature",
  "properties": {
    "gn:gn_country":"DE",
    "gn:gn_fcode":"PPLA4",
    "gn:gn_pop":552,
    "gn:population":552,
    "iso:country":"DE",
    "qs_pg:aaroncc":"DE",
    "qs_pg:gn_country":"DE",
    "qs_pg:gn_fcode":"PPLA4",
    "qs_pg:gn_pop":552,
    "qs_pg:name":"H\u00fcbingen",
    "qs_pg:photos_9r":0,
    "qs_pg:photos_sr":0,
    "qs_pg:pop_sr":2,
    "qs_pg:qs_pg_placetype":"locality",
    "wof:name":"H\u00fcbingen",
    "wof:placetype":"locality",
    "wof:population":552
},
  "geometry": {"coordinates":[7.83333,50.36667],"type":"Point"}
}