{
  "type": "Feature",
  "properties": {
    "gn:admin1_code":"6.0",
    "gn:admin2_code":"0.0",
    "gn:admin3_code":"3356.0",
    "gn:admin4_code":"3356009.0",
    "gn:asciiname":"Brande",
    "gn:country_code":"DE",
    "gn:dem":34,
    "gn:feature_class":"P",
    "gn:feature_code":"PPL",
    "gn:name":"Brande",
    "gn:population":0,
    "gn:timezone":"Europe/Berlin",
    "iso:country":"DE",
    "wof:name":"Brande",
    "wof:placetype":"neighbourhood"
},
  "geometry": {"coordinates":[8.64896,53.21528000000001],"type":"Point"}
}