{
  "type": "Feature",
  "properties": {
    "gn:admin1_code":"5",
    "gn:admin2_code":"65.0",
    "gn:admin3_code":"6532.0",
    "gn:admin4_code":"6532013.0",
    "gn:asciiname":"Mudersbach",
    "gn:country_code":"DE",
    "gn:dem":286,
    "gn:feature_class":"P",
    "gn:feature_code":"PPL",
    "gn:name":"Mudersbach",
    "gn:population":0,
    "gn:timezone":"Europe/Berlin",
    "iso:country":"DE",
    "name:ceb_x_preferred":[
        "Mudersbach"
    ],
    "name:deu_x_preferred":[
        "Mudersbach"
    ],
    "name:epo_x_preferred":[
        "Mudersbach"
    ],
    "name:eus_x_preferred":[
        "Mudersbach"
    ],
    "name:fas_x_preferred":[
        "\u0645\u0648\u062f\u0631\u0632\u0628\u0627\u062e"
    ],
    "name:fra_x_preferred":[
        "Mudersbach"
    ],
    "name:hun_x_preferred":[
        "Mudersbach"
    ],
    "name:ita_x_preferred":[
        "Mudersbach"
    ],
    "name:msa_x_preferred":[
        "Mudersbach"
    ],
    "name:nld_x_preferred":[
        "Mudersbach"
    ],
    "name:pol_x_preferred":[
        "Mudersbach"
    ],
    "name:por_x_preferred":[
        "Mudersbach"
    ],
    "name:ron_x_preferred":[
        "Mudersbach"
    ],
    "name:rus_x_preferred":[
        "\u041c\u0443\u0434\u0435\u0440\u0441\u0431\u0430\u0445"
    ],
    "name:spa_x_preferred":[
        "Mudersbach"
    ],
    "name:srp_x_preferred":[
        "\u041c\u0443\u0434\u0435\u0440\u0441\u0431\u0430\u0445"
    ],
    "name:ukr_x_preferred":[
        "\u041c\u0443\u0434\u0435\u0440\u0441\u0431\u0430\u0445"
    ],
    "name:uzb_x_preferred":[
        "Mudersbach"
    ],
    "name:vie_x_preferred":[
        "Mudersbach"
    ],
    "name:vol_x_preferred":[
        "Mudersbach"
    ],
    "name:war_x_preferred":[
        "Mudersbach"
    ],
    "name:zho_x_preferred":[
        "\u7a46\u5fb7\u65af\u5df4\u8d6b"
    ],
    "wof:name":"Mudersbach",
    "wof:placetype":"neighbourhood"
},
  "geometry": {"coordinates":[8.48972,50.68628],"type":"Point"}
}