{
  "type": "Feature",
  "properties": {
    "gn:gn_country":"DE",
    "gn:gn_fcode":"PPL",
    "gn:gn_pop":0,
    "iso:country":"DE",
    "name:deu_x_preferred":[
        "Sch\u00f6nflie\u00df"
    ],
    "qs_pg:aaroncc":"DE",
    "qs_pg:gn_country":"DE",
    "qs_pg:gn_fcode":"PPL",
    "qs_pg:gn_pop":0,
    "qs_pg:name":"Sch\u00f6nfliess",
    "qs_pg:name_adm0":"Deutschland",
    "qs_pg:name_adm1":"Bundesland Brandenburg",
    "qs_pg:photos":1,
    "qs_pg:photos_1k":1,
    "qs_pg:photos_9k":1,
    "qs_pg:photos_9r":1,
    "qs_pg:photos_all":1,
    "qs_pg:photos_sr":1,
    "qs_pg:pop_sr":0,
    "qs_pg:qs_pg_placetype":"neighbourhood",
    "qs_pg:qs_pg_placetype_gp":"Suburb",
    "qs_pg:woe_adm0":23424829,
    "woe:adm0_id":23424829,
    "woe:name_adm0":"Deutschland",
    "woe:name_adm1":"Bundesland Brandenburg",
    "woe:placetype":"Suburb",
    "wof:name":"Sch\u00f6nfliess",
    "wof:placetype":"neighbourhood"
},
  "geometry": {"coordinates":[14.61096,52.15593],"type":"Point"}
}