{
  "type": "Feature",
  "properties": {
    "gn:admin1_code":"7",
    "gn:admin2_code":"59.0",
    "gn:admin3_code":"5962.0",
    "gn:admin4_code":"5962056.0",
    "gn:asciiname":"Dahlhausen",
    "gn:country_code":"DE",
    "gn:dem":354,
    "gn:feature_class":"P",
    "gn:feature_code":"PPL",
    "gn:name":"Dahlhausen",
    "gn:population":0,
    "gn:timezone":"Europe/Berlin",
    "iso:country":"DE",
    "name:deu_x_preferred":[
        "Dahlhausen"
    ],
    "name:tur_x_preferred":[
        "Bochum-Dahlhausen"
    ],
    "wof:name":"Dahlhausen",
    "wof:placetype":"neighbourhood"
},
  "geometry": {"coordinates":[7.53751,51.24857],"type":"Point"}
}