{
  "type": "Feature",
  "properties": {
    "gn:admin1_code":"2",
    "gn:admin2_code":"95.0",
    "gn:admin3_code":"9575.0",
    "gn:admin4_code":"9575153.0",
    "gn:asciiname":"Kleinerlbach",
    "gn:country_code":"DE",
    "gn:dem":306,
    "gn:feature_class":"P",
    "gn:feature_code":"PPL",
    "gn:name":"Kleinerlbach",
    "gn:population":0,
    "gn:timezone":"Europe/Berlin",
    "iso:country":"DE",
    "wof:name":"Kleinerlbach",
    "wof:placetype":"neighbourhood"
},
  "geometry": {"coordinates":[10.63016,49.58457],"type":"Point"}
}