{
  "type": "Feature",
  "properties": {
    "gn:admin1_code":"10.0",
    "gn:admin2_code":"0.0",
    "gn:admin3_code":"1061.0",
    "gn:admin4_code":"1061012.0",
    "gn:asciiname":"An der Chaussee",
    "gn:country_code":"DE",
    "gn:dem":-1,
    "gn:feature_class":"P",
    "gn:feature_code":"PPL",
    "gn:name":"An der Chaussee",
    "gn:population":0,
    "gn:timezone":"Europe/Berlin",
    "iso:country":"DE",
    "wof:name":"An der Chaussee",
    "wof:placetype":"neighbourhood"
},
  "geometry": {"coordinates":[9.44817,53.80367],"type":"Point"}
}