{
  "type": "Feature",
  "properties": {
    "iso:country":"DE",
    "name:und_x_variant":[
        "Holt"
    ],
    "wof:name":"Hehnerholt",
    "wof:placetype":"neighbourhood"
},
  "geometry": {"coordinates":[6.40127268309118,51.18500858831934],"type":"Point"}
}