{
  "type": "Feature",
  "properties": {
    "gn:admin1_code":"2.0",
    "gn:admin2_code":"097",
    "gn:admin3_code":"9780.0",
    "gn:admin4_code":"9780147.0",
    "gn:asciiname":"Wolkenberg",
    "gn:country_code":"DE",
    "gn:dem":781,
    "gn:feature_class":"P",
    "gn:feature_code":"PPL",
    "gn:name":"Wolkenberg",
    "gn:population":0,
    "gn:timezone":"Europe/Berlin",
    "iso:country":"DE",
    "wof:name":"Wolkenberg",
    "wof:placetype":"neighbourhood"
},
  "geometry": {"coordinates":[10.40985,47.75361],"type":"Point"}
}