{
  "type": "Feature",
  "properties": {
    "gn:admin1_code":"1.0",
    "gn:admin2_code":"84.0",
    "gn:admin3_code":"8426.0",
    "gn:admin4_code":"8426070.0",
    "gn:asciiname":"Bihlafingen",
    "gn:country_code":"DE",
    "gn:dem":520,
    "gn:feature_class":"P",
    "gn:feature_code":"PPL",
    "gn:name":"Bihlafingen",
    "gn:population":0,
    "gn:timezone":"Europe/Berlin",
    "iso:country":"DE",
    "wof:name":"Bihlafingen",
    "wof:placetype":"neighbourhood"
},
  "geometry": {"coordinates":[9.95722,48.26097],"type":"Point"}
}