{
  "type": "Feature",
  "properties": {
    "gn:admin1_code":"2",
    "gn:admin2_code":"93.0",
    "gn:admin3_code":"9372.0",
    "gn:admin4_code":"9372142.0",
    "gn:asciiname":"Glocklswies",
    "gn:country_code":"DE",
    "gn:dem":554,
    "gn:feature_class":"P",
    "gn:feature_code":"PPL",
    "gn:name":"Gl\u00f6cklswies",
    "gn:population":0,
    "gn:timezone":"Europe/Berlin",
    "iso:country":"DE",
    "wof:name":"Glocklswies",
    "wof:placetype":"neighbourhood"
},
  "geometry": {"coordinates":[12.56526,49.12076],"type":"Point"}
}