{
  "type": "Feature",
  "properties": {
    "gn:admin1_code":"2",
    "gn:admin2_code":"91.0",
    "gn:admin3_code":"9172.0",
    "gn:admin4_code":"9172118.0",
    "gn:asciiname":"Brodhausen",
    "gn:country_code":"DE",
    "gn:dem":424,
    "gn:feature_class":"P",
    "gn:feature_code":"PPL",
    "gn:name":"Brodhausen",
    "gn:population":0,
    "gn:timezone":"Europe/Berlin",
    "iso:country":"DE",
    "wof:name":"Brodhausen",
    "wof:placetype":"neighbourhood"
},
  "geometry": {"coordinates":[12.9561,47.84371],"type":"Point"}
}