{
  "type": "Feature",
  "properties": {
    "gn:admin1_code":"13",
    "gn:admin2_code":"0.0",
    "gn:admin3_code":"14522.0",
    "gn:admin4_code":"14522480.0",
    "gn:asciiname":"Dittmannsdorf",
    "gn:country_code":"DE",
    "gn:dem":343,
    "gn:feature_class":"P",
    "gn:feature_code":"PPL",
    "gn:name":"Dittmannsdorf",
    "gn:population":0,
    "gn:timezone":"Europe/Berlin",
    "iso:country":"DE",
    "wof:name":"Dittmannsdorf",
    "wof:placetype":"neighbourhood"
},
  "geometry": {"coordinates":[13.41702,50.99874000000001],"type":"Point"}
}