{
  "type": "Feature",
  "properties": {
    "gn:admin1_code":"6",
    "gn:admin2_code":"0.0",
    "gn:admin3_code":"3461.0",
    "gn:admin4_code":"3461004.0",
    "gn:asciiname":"Uhlenbusch",
    "gn:country_code":"DE",
    "gn:dem":0,
    "gn:feature_class":"P",
    "gn:feature_code":"PPL",
    "gn:name":"Uhlenbusch",
    "gn:population":0,
    "gn:timezone":"Europe/Berlin",
    "iso:country":"DE",
    "wof:name":"Uhlenbusch",
    "wof:placetype":"neighbourhood"
},
  "geometry": {"coordinates":[8.37445,53.21348],"type":"Point"}
}