{
  "type": "Feature",
  "properties": {
    "gn:admin1_code":"11",
    "gn:admin2_code":"0.0",
    "gn:admin3_code":"12066.0",
    "gn:admin4_code":"12066320.0",
    "gn:asciiname":"Lobendorf",
    "gn:country_code":"DE",
    "gn:dem":66,
    "gn:feature_class":"P",
    "gn:feature_code":"PPL",
    "gn:name":"Lobendorf",
    "gn:population":0,
    "gn:timezone":"Europe/Berlin",
    "iso:country":"DE",
    "name:dsb_x_preferred":[
        "\u0141obo\u017aice"
    ],
    "wof:name":"Lobendorf",
    "wof:placetype":"neighbourhood"
},
  "geometry": {"coordinates":[14.08293,51.76984],"type":"Point"}
}