{
  "type": "Feature",
  "properties": {
    "gn:admin1_code":"2",
    "gn:admin2_code":"96.0",
    "gn:admin3_code":"9673.0",
    "gn:admin4_code":"9673117.0",
    "gn:asciiname":"Wegfurt",
    "gn:country_code":"DE",
    "gn:dem":341,
    "gn:feature_class":"P",
    "gn:feature_code":"PPL",
    "gn:name":"Wegfurt",
    "gn:population":0,
    "gn:timezone":"Europe/Berlin",
    "iso:country":"DE",
    "wof:name":"Wegfurt",
    "wof:placetype":"neighbourhood"
},
  "geometry": {"coordinates":[10.0865,50.39538],"type":"Point"}
}