{
  "type": "Feature",
  "properties": {
    "gn:admin1_code":"2",
    "gn:admin2_code":"93.0",
    "gn:admin3_code":"9371.0",
    "gn:admin4_code":"9371141.0",
    "gn:asciiname":"Holnstein",
    "gn:country_code":"DE",
    "gn:dem":470,
    "gn:feature_class":"P",
    "gn:feature_code":"PPL",
    "gn:name":"Holnstein",
    "gn:population":0,
    "gn:timezone":"Europe/Berlin",
    "iso:country":"DE",
    "name:bar_x_preferred":[
        "Holnstein"
    ],
    "name:deu_x_preferred":[
        "Holnstein"
    ],
    "wof:name":"Holnstein",
    "wof:placetype":"neighbourhood"
},
  "geometry": {"coordinates":[11.64474,49.5569],"type":"Point"}
}