{
  "type": "Feature",
  "properties": {
    "gn:admin1_code":"6",
    "gn:admin2_code":"0.0",
    "gn:admin3_code":"3451.0",
    "gn:admin4_code":"3451004.0",
    "gn:asciiname":"Portsloge",
    "gn:country_code":"DE",
    "gn:dem":9,
    "gn:feature_class":"P",
    "gn:feature_code":"PPL",
    "gn:name":"Portsloge",
    "gn:population":0,
    "gn:timezone":"Europe/Berlin",
    "iso:country":"DE",
    "wof:name":"Portsloge",
    "wof:placetype":"neighbourhood"
},
  "geometry": {"coordinates":[8.00955,53.14371],"type":"Point"}
}