{
  "type": "Feature",
  "properties": {
    "gn:admin1_code":"8.0",
    "gn:admin2_code":"0.0",
    "gn:admin3_code":"7132.0",
    "gn:admin4_code":"7132015.0",
    "gn:asciiname":"Buerdenbach-Bruchermuehle",
    "gn:country_code":"DE",
    "gn:dem":179,
    "gn:feature_class":"P",
    "gn:feature_code":"PPL",
    "gn:name":"B\u00fcrdenbach-Brucherm\u00fchle",
    "gn:population":0,
    "gn:timezone":"Europe/Berlin",
    "iso:country":"DE",
    "wof:name":"Buerdenbach-Bruchermuehle",
    "wof:placetype":"neighbourhood"
},
  "geometry": {"coordinates":[7.53181,50.61941],"type":"Point"}
}