{
  "type": "Feature",
  "properties": {
    "gn:admin1_code":"2.0",
    "gn:admin2_code":"094",
    "gn:admin3_code":"9479.0",
    "gn:admin4_code":"9479169.0",
    "gn:asciiname":"Wintersberg",
    "gn:country_code":"DE",
    "gn:dem":583,
    "gn:feature_class":"P",
    "gn:feature_code":"PPL",
    "gn:name":"Wintersberg",
    "gn:population":0,
    "gn:timezone":"Europe/Berlin",
    "iso:country":"DE",
    "wof:name":"Wintersberg",
    "wof:placetype":"neighbourhood"
},
  "geometry": {"coordinates":[12.049,50.04537],"type":"Point"}
}