{
  "type": "Feature",
  "properties": {
    "gn:admin1_code":"1",
    "gn:admin2_code":"84.0",
    "gn:admin3_code":"8436.0",
    "gn:admin4_code":"8436095.0",
    "gn:asciiname":"Oberschoren",
    "gn:country_code":"DE",
    "gn:dem":656,
    "gn:feature_class":"P",
    "gn:feature_code":"PPL",
    "gn:name":"Oberschoren",
    "gn:population":0,
    "gn:timezone":"Europe/Berlin",
    "iso:country":"DE",
    "wof:name":"Oberschoren",
    "wof:placetype":"neighbourhood"
},
  "geometry": {"coordinates":[9.51678,47.84073],"type":"Point"}
}