{
  "type": "Feature",
  "properties": {
    "gn:admin1_code":"2",
    "gn:admin2_code":"96.0",
    "gn:admin3_code":"9673.0",
    "gn:admin4_code":"9673171.0",
    "gn:asciiname":"Reinfeldshof",
    "gn:country_code":"DE",
    "gn:dem":375,
    "gn:feature_class":"P",
    "gn:feature_code":"PPL",
    "gn:name":"Reinfeldshof",
    "gn:population":0,
    "gn:timezone":"Europe/Berlin",
    "iso:country":"DE",
    "wof:name":"Reinfeldshof",
    "wof:placetype":"neighbourhood"
},
  "geometry": {"coordinates":[10.28123,50.2929],"type":"Point"}
}