{
  "type": "Feature",
  "properties": {
    "gn:gn_country":"DE",
    "gn:gn_fcode":"PPLA4",
    "gn:gn_pop":430,
    "gn:population":430,
    "iso:country":"DE",
    "name:ara_x_preferred":[
        "\u0641\u0627\u0644\u0648\u064a\u063a"
    ],
    "name:baq_x_preferred":[
        "Valwig"
    ],
    "name:chi_x_preferred":[
        "\u6cd5\u5c14\u7ef4\u5e0c"
    ],
    "name:deu_x_preferred":[
        "Valwig bei Cochem"
    ],
    "name:dut_x_preferred":[
        "Valwig"
    ],
    "name:eng_x_preferred":[
        "Valwig"
    ],
    "name:epo_x_preferred":[
        "Valwig"
    ],
    "name:fre_x_preferred":[
        "Valwig"
    ],
    "name:ger_x_preferred":[
        "Valwig"
    ],
    "name:hun_x_preferred":[
        "Valwig"
    ],
    "name:ita_x_preferred":[
        "Valwig"
    ],
    "name:jpn_x_preferred":[
        "\u30d5\u30a1\u30eb\u30f4\u30a3\u30d2"
    ],
    "name:kaz_x_preferred":[
        "\u0424\u0430\u043b\u044c\u0432\u0438\u0433"
    ],
    "name:kir_x_preferred":[
        "\u0424\u0430\u043b\u044c\u0432\u0438\u0433"
    ],
    "name:may_x_preferred":[
        "Valwig"
    ],
    "name:per_x_preferred":[
        "\u0641\u0627\u0644\u0648\u06cc\u06af"
    ],
    "name:pol_x_preferred":[
        "Valwig"
    ],
    "name:por_x_preferred":[
        "Valwig"
    ],
    "name:rum_x_preferred":[
        "Valwig"
    ],
    "name:rus_x_preferred":[
        "\u0424\u0430\u043b\u044c\u0432\u0438\u0433"
    ],
    "name:srp_x_preferred":[
        "\u0424\u0430\u043b\u0432\u0438\u0433"
    ],
    "name:ukr_x_preferred":[
        "\u0424\u0430\u043b\u044c\u0432\u0456\u0433"
    ],
    "name:vie_x_preferred":[
        "Valwig"
    ],
    "name:vol_x_preferred":[
        "Valwig"
    ],
    "name:war_x_preferred":[
        "Valwig"
    ],
    "qs_pg:aaroncc":"DE",
    "qs_pg:gn_country":"DE",
    "qs_pg:gn_fcode":"PPLA4",
    "qs_pg:gn_pop":430,
    "qs_pg:name":"Valwig",
    "qs_pg:photos_9r":0,
    "qs_pg:photos_sr":0,
    "qs_pg:pop_sr":2,
    "qs_pg:qs_pg_placetype":"locality",
    "wof:name":"Valwig",
    "wof:placetype":"locality",
    "wof:population":430
},
  "geometry": {"coordinates":[7.21667,50.15],"type":"Point"}
}