{
  "type": "Feature",
  "properties": {
    "gn:admin1_code":"6",
    "gn:admin2_code":"0.0",
    "gn:admin3_code":"3255.0",
    "gn:admin4_code":"3255036.0",
    "gn:asciiname":"Denkiehausen",
    "gn:country_code":"DE",
    "gn:dem":264,
    "gn:feature_class":"P",
    "gn:feature_code":"PPL",
    "gn:name":"Denkiehausen",
    "gn:population":0,
    "gn:timezone":"Europe/Berlin",
    "iso:country":"DE",
    "wof:name":"Denkiehausen",
    "wof:placetype":"neighbourhood"
},
  "geometry": {"coordinates":[9.67242,51.84444000000001],"type":"Point"}
}