{
  "type": "Feature",
  "properties": {
    "gn:admin1_code":"8",
    "gn:admin2_code":"0.0",
    "gn:admin3_code":"7339.0",
    "gn:admin4_code":"7339005.0",
    "gn:asciiname":"Dietersheim",
    "gn:country_code":"DE",
    "gn:dem":89,
    "gn:feature_class":"P",
    "gn:feature_code":"PPL",
    "gn:name":"Dietersheim",
    "gn:population":0,
    "gn:timezone":"Europe/Berlin",
    "iso:country":"DE",
    "name:ara_x_preferred":[
        "\u062f\u064a\u062a\u064a\u0631\u0633\u0647\u0627\u064a\u0645"
    ],
    "name:ceb_x_preferred":[
        "Dietersheim"
    ],
    "name:dan_x_preferred":[
        "Dietersheim"
    ],
    "name:deu_x_preferred":[
        "Dietersheim"
    ],
    "name:epo_x_preferred":[
        "Dietersheim"
    ],
    "name:eus_x_preferred":[
        "Dietersheim"
    ],
    "name:fas_x_preferred":[
        "\u062f\u06cc\u062a\u0631\u0633\u0647\u0627\u06cc\u0645"
    ],
    "name:fra_x_preferred":[
        "Dietersheim"
    ],
    "name:hun_x_preferred":[
        "Dietersheim"
    ],
    "name:hye_x_preferred":[
        "\u0534\u056b\u0569\u0565\u0580\u057d\u0570\u0561\u0575\u0574"
    ],
    "name:ind_x_preferred":[
        "Dietersheim"
    ],
    "name:ita_x_preferred":[
        "Dietersheim"
    ],
    "name:kaz_x_preferred":[
        "\u0414\u0438\u0442\u0435\u0440\u0441\u0445\u0430\u0439\u043c"
    ],
    "name:kir_x_preferred":[
        "\u0414\u0438\u0442\u0435\u0440\u0441\u0445\u0430\u0439\u043c"
    ],
    "name:lmo_x_preferred":[
        "Dietersheim"
    ],
    "name:msa_x_preferred":[
        "Dietersheim"
    ],
    "name:nld_x_preferred":[
        "Dietersheim"
    ],
    "name:pol_x_preferred":[
        "Dietersheim"
    ],
    "name:por_x_preferred":[
        "Dietersheim"
    ],
    "name:ron_x_preferred":[
        "Dietersheim"
    ],
    "name:rus_x_preferred":[
        "\u0414\u0438\u0442\u0435\u0440\u0441\u0445\u0430\u0439\u043c"
    ],
    "name:spa_x_preferred":[
        "Dietersheim"
    ],
    "name:srp_x_preferred":[
        "\u0414\u0438\u0442\u0435\u0440\u0441\u0445\u0430\u0458\u043c"
    ],
    "name:ukr_x_preferred":[
        "\u0414\u0456\u0442\u0435\u0440\u0441\u0433\u0430\u0439\u043c"
    ],
    "name:uzb_x_preferred":[
        "Dietersheim"
    ],
    "name:vie_x_preferred":[
        "Dietersheim"
    ],
    "name:vol_x_preferred":[
        "Dietersheim"
    ],
    "name:war_x_preferred":[
        "Dietersheim"
    ],
    "name:zho_x_preferred":[
        "\u8fea\u7279\u65af\u6d77\u59c6"
    ],
    "wof:name":"Dietersheim",
    "wof:placetype":"neighbourhood"
},
  "geometry": {"coordinates":[7.9085,49.93828],"type":"Point"}
}