{
  "type": "Feature",
  "properties": {
    "gn:admin1_code":"1",
    "gn:admin2_code":"83.0",
    "gn:admin3_code":"8325.0",
    "gn:admin4_code":"8325053.0",
    "gn:asciiname":"Lienberg",
    "gn:country_code":"DE",
    "gn:dem":700,
    "gn:feature_class":"P",
    "gn:feature_code":"PPLL",
    "gn:name":"Lienberg",
    "gn:population":0,
    "gn:timezone":"Europe/Berlin",
    "iso:country":"DE",
    "wof:name":"Lienberg",
    "wof:placetype":"neighbourhood"
},
  "geometry": {"coordinates":[8.41126,48.23945],"type":"Point"}
}