{
  "type": "Feature",
  "properties": {
    "gn:admin1_code":"1",
    "gn:admin2_code":"84.0",
    "gn:admin3_code":"8436.0",
    "gn:admin4_code":"8436004.0",
    "gn:asciiname":"Marstetten",
    "gn:country_code":"DE",
    "gn:dem":595,
    "gn:feature_class":"P",
    "gn:feature_code":"PPL",
    "gn:name":"Marstetten",
    "gn:population":0,
    "gn:timezone":"Europe/Berlin",
    "iso:country":"DE",
    "wof:name":"Marstetten",
    "wof:placetype":"neighbourhood"
},
  "geometry": {"coordinates":[10.08416,47.94153],"type":"Point"}
}