{
  "type": "Feature",
  "properties": {
    "gn:admin1_code":"8",
    "gn:admin2_code":"0.0",
    "gn:admin3_code":"7335.0",
    "gn:admin4_code":"7335035.0",
    "gn:asciiname":"Reichenbacherhof",
    "gn:country_code":"DE",
    "gn:dem":262,
    "gn:feature_class":"P",
    "gn:feature_code":"PPL",
    "gn:name":"Reichenbacherhof",
    "gn:population":0,
    "gn:timezone":"Europe/Berlin",
    "iso:country":"DE",
    "wof:name":"Reichenbacherhof",
    "wof:placetype":"neighbourhood"
},
  "geometry": {"coordinates":[7.74324,49.49745],"type":"Point"}
}