{
  "type": "Feature",
  "properties": {
    "gn:admin1_code":"2",
    "gn:admin2_code":"92.0",
    "gn:admin3_code":"9275.0",
    "gn:admin4_code":"9275144.0",
    "gn:asciiname":"During",
    "gn:country_code":"DE",
    "gn:dem":429,
    "gn:feature_class":"P",
    "gn:feature_code":"PPL",
    "gn:name":"During",
    "gn:population":0,
    "gn:timezone":"Europe/Berlin",
    "iso:country":"DE",
    "wof:name":"During",
    "wof:placetype":"neighbourhood"
},
  "geometry": {"coordinates":[13.4042,48.65835],"type":"Point"}
}