{
  "type": "Feature",
  "properties": {
    "gn:admin1_code":"5",
    "gn:admin2_code":"66.0",
    "gn:admin3_code":"6631.0",
    "gn:admin4_code":"6631009.0",
    "gn:asciiname":"Niesig",
    "gn:country_code":"DE",
    "gn:dem":273,
    "gn:feature_class":"P",
    "gn:feature_code":"PPL",
    "gn:name":"Niesig",
    "gn:population":0,
    "gn:timezone":"Europe/Berlin",
    "iso:country":"DE",
    "wof:name":"Niesig",
    "wof:placetype":"neighbourhood"
},
  "geometry": {"coordinates":[9.67724,50.57533],"type":"Point"}
}