{
  "type": "Feature",
  "properties": {
    "gn:admin1_code":"6",
    "gn:admin2_code":"0.0",
    "gn:admin3_code":"3352.0",
    "gn:admin4_code":"3352062.0",
    "gn:asciiname":"Holssel",
    "gn:country_code":"DE",
    "gn:dem":10,
    "gn:feature_class":"P",
    "gn:feature_code":"PPL",
    "gn:name":"Holssel",
    "gn:population":0,
    "gn:timezone":"Europe/Berlin",
    "iso:country":"DE",
    "name:und_x_variant":[
        "Hol\u00dfel",
        "Holssel"
    ],
    "wof:name":"Holssel",
    "wof:placetype":"neighbourhood"
},
  "geometry": {"coordinates":[8.61848,53.68894],"type":"Point"}
}