{
  "type": "Feature",
  "properties": {
    "gn:admin1_code":"5",
    "gn:admin2_code":"66.0",
    "gn:admin3_code":"6632.0",
    "gn:admin4_code":"6632002.0",
    "gn:asciiname":"Kalkobes",
    "gn:country_code":"DE",
    "gn:dem":276,
    "gn:feature_class":"P",
    "gn:feature_code":"PPL",
    "gn:name":"Kalkobes",
    "gn:population":0,
    "gn:timezone":"Europe/Berlin",
    "iso:country":"DE",
    "wof:name":"Kalkobes",
    "wof:placetype":"neighbourhood"
},
  "geometry": {"coordinates":[9.68333,50.86667],"type":"Point"}
}