{
  "type": "Feature",
  "properties": {
    "gn:admin1_code":"12",
    "gn:admin2_code":"0.0",
    "gn:admin3_code":"13075.0",
    "gn:admin4_code":"13075098.0",
    "gn:asciiname":"Dammmuehle",
    "gn:country_code":"DE",
    "gn:dem":4,
    "gn:feature_class":"P",
    "gn:feature_code":"PPL",
    "gn:name":"Dammm\u00fchle",
    "gn:population":0,
    "gn:timezone":"Europe/Berlin",
    "iso:country":"DE",
    "name:und_x_variant":[
        "Damm\u00fchl",
        "Dammm\u00fchle"
    ],
    "wof:name":"Dammmuehle",
    "wof:placetype":"neighbourhood"
},
  "geometry": {"coordinates":[13.73428,53.80699],"type":"Point"}
}