{
  "type": "Feature",
  "properties": {
    "gn:admin1_code":"6",
    "gn:admin2_code":"0.0",
    "gn:admin3_code":"3458.0",
    "gn:admin4_code":"3458009.0",
    "gn:asciiname":"Sandhatten",
    "gn:country_code":"DE",
    "gn:dem":28,
    "gn:feature_class":"P",
    "gn:feature_code":"PPL",
    "gn:name":"Sandhatten",
    "gn:population":0,
    "gn:timezone":"Europe/Berlin",
    "iso:country":"DE",
    "wof:name":"Sandhatten",
    "wof:placetype":"neighbourhood"
},
  "geometry": {"coordinates":[8.31996,53.00948],"type":"Point"}
}