{
  "type": "Feature",
  "properties": {
    "gn:admin1_code":"1",
    "gn:admin2_code":"81.0",
    "gn:admin3_code":"8136.0",
    "gn:admin4_code":"8136019.0",
    "gn:asciiname":"Kalkhofe",
    "gn:country_code":"DE",
    "gn:dem":428,
    "gn:feature_class":"P",
    "gn:feature_code":"PPL",
    "gn:name":"Kalkh\u00f6fe",
    "gn:population":0,
    "gn:timezone":"Europe/Berlin",
    "iso:country":"DE",
    "wof:name":"Kalkhofe",
    "wof:placetype":"neighbourhood"
},
  "geometry": {"coordinates":[10.11746,49.00401],"type":"Point"}
}