{
  "type": "Feature",
  "properties": {
    "gn:admin1_code":"2",
    "gn:admin2_code":"92.0",
    "gn:admin3_code":"9275.0",
    "gn:admin4_code":"9275114.0",
    "gn:asciiname":"Uttigkofen",
    "gn:country_code":"DE",
    "gn:dem":332,
    "gn:feature_class":"P",
    "gn:feature_code":"PPL",
    "gn:name":"Uttigkofen",
    "gn:population":0,
    "gn:timezone":"Europe/Berlin",
    "iso:country":"DE",
    "wof:name":"Uttigkofen",
    "wof:placetype":"neighbourhood"
},
  "geometry": {"coordinates":[13.03084,48.58083],"type":"Point"}
}