{
  "type": "Feature",
  "properties": {
    "gn:admin1_code":"2.0",
    "gn:admin2_code":"91.0",
    "gn:admin3_code":"9189.0",
    "gn:admin4_code":"9189152.0",
    "gn:asciiname":"Bergham",
    "gn:country_code":"DE",
    "gn:dem":513,
    "gn:feature_class":"P",
    "gn:feature_code":"PPL",
    "gn:name":"Bergham",
    "gn:population":0,
    "gn:timezone":"Europe/Berlin",
    "iso:country":"DE",
    "wof:name":"Bergham",
    "wof:placetype":"neighbourhood"
},
  "geometry": {"coordinates":[12.69804,48.05054000000001],"type":"Point"}
}