{
  "type": "Feature",
  "properties": {
    "gn:admin1_code":"7",
    "gn:admin2_code":"57.0",
    "gn:admin3_code":"5754.0",
    "gn:admin4_code":"5754020.0",
    "gn:asciiname":"Groppel",
    "gn:country_code":"DE",
    "gn:dem":74,
    "gn:feature_class":"P",
    "gn:feature_code":"PPLL",
    "gn:name":"Groppel",
    "gn:population":0,
    "gn:timezone":"Europe/Berlin",
    "iso:country":"DE",
    "name:osx_x_preferred":[
        "Gropanl\u00f4h"
    ],
    "wof:name":"Groppel",
    "wof:placetype":"neighbourhood"
},
  "geometry": {"coordinates":[8.23769,51.89895],"type":"Point"}
}