{
  "type": "Feature",
  "properties": {
    "gn:gn_country":"DE",
    "gn:gn_fcode":"PPLA4",
    "gn:gn_pop":153,
    "gn:population":153,
    "iso:country":"DE",
    "name:baq_x_preferred":[
        "Heinkenborstel"
    ],
    "name:chi_x_preferred":[
        "\u6d77\u6069\u80af\u535a\u5c14\u65af\u7279\u5c14"
    ],
    "name:dan_x_preferred":[
        "Heinkenborstel"
    ],
    "name:dut_x_preferred":[
        "Heinkenborstel"
    ],
    "name:eng_x_preferred":[
        "Heinkenborstel"
    ],
    "name:epo_x_preferred":[
        "Heinkenborstel"
    ],
    "name:fre_x_preferred":[
        "Heinkenborstel"
    ],
    "name:ger_x_preferred":[
        "Heinkenborstel"
    ],
    "name:hun_x_preferred":[
        "Heinkenborstel"
    ],
    "name:ita_x_preferred":[
        "Heinkenborstel"
    ],
    "name:kaz_x_preferred":[
        "\u0425\u0430\u0439\u043d\u043a\u0435\u043d\u0431\u043e\u0440\u0441\u0442\u0435\u043b\u044c"
    ],
    "name:kir_x_preferred":[
        "\u0425\u0430\u0439\u043d\u043a\u0435\u043d\u0431\u043e\u0440\u0441\u0442\u0435\u043b\u044c"
    ],
    "name:mac_x_preferred":[
        "\u0425\u0430\u0458\u043d\u043a\u0435\u043d\u0431\u043e\u0440\u0441\u0442\u0435\u043b"
    ],
    "name:may_x_preferred":[
        "Heinkenborstel"
    ],
    "name:per_x_preferred":[
        "\u0647\u0627\u06cc\u0646\u06a9\u0646\u0628\u0648\u0631\u0634\u062a\u0644"
    ],
    "name:pol_x_preferred":[
        "Heinkenborstel"
    ],
    "name:por_x_preferred":[
        "Heinkenborstel"
    ],
    "name:rum_x_preferred":[
        "Heinkenborstel"
    ],
    "name:rus_x_preferred":[
        "\u0425\u0430\u0439\u043d\u043a\u0435\u043d\u0431\u043e\u0440\u0441\u0442\u0435\u043b\u044c"
    ],
    "name:spa_x_preferred":[
        "Heinkenborstel"
    ],
    "name:srp_x_preferred":[
        "\u0425\u0430\u0458\u043d\u043a\u0435\u043d\u0431\u043e\u0440\u0441\u0442\u0435\u043b"
    ],
    "name:tur_x_preferred":[
        "Heinkenborstel"
    ],
    "name:ukr_x_preferred":[
        "\u0413\u0430\u0439\u043d\u043a\u0435\u043d\u0431\u043e\u0440\u0441\u0442\u0435\u043b\u044c"
    ],
    "name:uzb_x_preferred":[
        "Heinkenborstel"
    ],
    "name:vie_x_preferred":[
        "Heinkenborstel"
    ],
    "name:vol_x_preferred":[
        "Heinkenborstel"
    ],
    "name:war_x_preferred":[
        "Heinkenborstel"
    ],
    "qs_pg:aaroncc":"DE",
    "qs_pg:gn_country":"DE",
    "qs_pg:gn_fcode":"PPLA4",
    "qs_pg:gn_pop":153,
    "qs_pg:name":"Heinkenborstel",
    "qs_pg:photos_9r":0,
    "qs_pg:photos_sr":0,
    "qs_pg:pop_sr":1,
    "qs_pg:qs_pg_placetype":"locality",
    "wof:name":"Heinkenborstel",
    "wof:placetype":"locality",
    "wof:population":153
},
  "geometry": {"coordinates":[9.75,54.13333],"type":"Point"}
}