{
  "type": "Feature",
  "properties": {
    "gn:admin1_code":"2.0",
    "gn:admin2_code":"94.0",
    "gn:admin3_code":"9472.0",
    "gn:admin4_code":"9472118.0",
    "gn:asciiname":"Altenwiesen",
    "gn:country_code":"DE",
    "gn:dem":535,
    "gn:feature_class":"P",
    "gn:feature_code":"PPL",
    "gn:name":"Altenwiesen",
    "gn:population":0,
    "gn:timezone":"Europe/Berlin",
    "iso:country":"DE",
    "name:und_x_variant":[
        "Altenwiese",
        "Altenwiesen"
    ],
    "wof:name":"Altenwiesen",
    "wof:placetype":"neighbourhood"
},
  "geometry": {"coordinates":[11.4024,49.70312],"type":"Point"}
}