{
  "type": "Feature",
  "properties": {
    "gn:admin1_code":"1",
    "gn:admin2_code":"81.0",
    "gn:admin3_code":"8127.0",
    "gn:admin4_code":"8127025.0",
    "gn:asciiname":"Unterrot",
    "gn:country_code":"DE",
    "gn:dem":334,
    "gn:feature_class":"P",
    "gn:feature_code":"PPL",
    "gn:name":"Unterrot",
    "gn:population":0,
    "gn:timezone":"Europe/Berlin",
    "iso:country":"DE",
    "wof:name":"Unterrot",
    "wof:placetype":"neighbourhood"
},
  "geometry": {"coordinates":[9.77294,48.98253],"type":"Point"}
}