{
  "type": "Feature",
  "properties": {
    "gn:admin1_code":"2",
    "gn:admin2_code":"92.0",
    "gn:admin3_code":"9278.0",
    "gn:admin4_code":"9278197.0",
    "gn:asciiname":"Hauptenberg",
    "gn:country_code":"DE",
    "gn:dem":672,
    "gn:feature_class":"P",
    "gn:feature_code":"PPL",
    "gn:name":"Hauptenberg",
    "gn:population":0,
    "gn:timezone":"Europe/Berlin",
    "iso:country":"DE",
    "wof:name":"Hauptenberg",
    "wof:placetype":"neighbourhood"
},
  "geometry": {"coordinates":[12.54973,49.02129],"type":"Point"}
}