{
  "type": "Feature",
  "properties": {
    "gn:admin1_code":"13",
    "gn:admin2_code":"0.0",
    "gn:admin3_code":"14522.0",
    "gn:admin4_code":"14522570.0",
    "gn:asciiname":"Gebersbach",
    "gn:country_code":"DE",
    "gn:dem":234,
    "gn:feature_class":"P",
    "gn:feature_code":"PPL",
    "gn:name":"Gebersbach",
    "gn:population":0,
    "gn:timezone":"Europe/Berlin",
    "iso:country":"DE",
    "wof:name":"Gebersbach",
    "wof:placetype":"neighbourhood"
},
  "geometry": {"coordinates":[13.06691,51.08766],"type":"Point"}
}