{
  "type": "Feature",
  "properties": {
    "gn:admin1_code":"13.0",
    "gn:admin2_code":"00",
    "gn:admin3_code":"14730.0",
    "gn:admin4_code":"14730340.0",
    "gn:asciiname":"Zwochau-Grabschuetz",
    "gn:country_code":"DE",
    "gn:dem":106,
    "gn:feature_class":"P",
    "gn:feature_code":"PPL",
    "gn:name":"Zwochau-Grabsch\u00fctz",
    "gn:population":0,
    "gn:timezone":"Europe/Berlin",
    "iso:country":"DE",
    "name:und_x_variant":[
        "Grabsch\u00fctz",
        "Zwochau-Grabsch\u00fctz"
    ],
    "wof:name":"Zwochau-Grabschuetz",
    "wof:placetype":"neighbourhood"
},
  "geometry": {"coordinates":[12.27766,51.47205],"type":"Point"}
}