{
  "type": "Feature",
  "properties": {
    "gn:admin1_code":"13",
    "gn:admin2_code":"0.0",
    "gn:admin3_code":"14627.0",
    "gn:admin4_code":"14627130.0",
    "gn:asciiname":"Striegnitz",
    "gn:country_code":"DE",
    "gn:dem":158,
    "gn:feature_class":"P",
    "gn:feature_code":"PPL",
    "gn:name":"Striegnitz",
    "gn:population":0,
    "gn:timezone":"Europe/Berlin",
    "iso:country":"DE",
    "wof:name":"Striegnitz",
    "wof:placetype":"neighbourhood"
},
  "geometry": {"coordinates":[13.28367,51.22458],"type":"Point"}
}