{
  "type": "Feature",
  "properties": {
    "gn:admin1_code":"1",
    "gn:admin2_code":"82.0",
    "gn:admin3_code":"8226.0",
    "gn:admin4_code":"8226054.0",
    "gn:asciiname":"Tairnbach",
    "gn:country_code":"DE",
    "gn:dem":187,
    "gn:feature_class":"P",
    "gn:feature_code":"PPL",
    "gn:name":"Tairnbach",
    "gn:population":0,
    "gn:timezone":"Europe/Berlin",
    "iso:country":"DE",
    "wof:name":"Tairnbach",
    "wof:placetype":"neighbourhood"
},
  "geometry": {"coordinates":[8.75705,49.26405],"type":"Point"}
}