{
  "type": "Feature",
  "properties": {
    "gn:admin1_code":"7",
    "gn:admin2_code":"53.0",
    "gn:admin3_code":"5378.0",
    "gn:admin4_code":"5378004.0",
    "gn:asciiname":"Obersteinbach",
    "gn:country_code":"DE",
    "gn:dem":210,
    "gn:feature_class":"P",
    "gn:feature_code":"PPL",
    "gn:name":"Obersteinbach",
    "gn:population":0,
    "gn:timezone":"Europe/Berlin",
    "iso:country":"DE",
    "name:als_x_preferred":[
        "Obersteinbach"
    ],
    "name:ara_x_preferred":[
        "\u0623\u0648\u0628\u0631\u0633\u062a\u064a\u0646\u0628\u0627\u062a\u0634"
    ],
    "name:cat_x_preferred":[
        "Obersteinbach"
    ],
    "name:ceb_x_preferred":[
        "Obersteinbach"
    ],
    "name:deu_x_preferred":[
        "Obersteinbach"
    ],
    "name:eus_x_preferred":[
        "Obersteinbach"
    ],
    "name:fas_x_preferred":[
        "\u0627\u0628\u0631\u0634\u062a\u0627\u06cc\u0646\u0628\u0627\u062e"
    ],
    "name:fra_x_preferred":[
        "Obersteinbach"
    ],
    "name:hun_x_preferred":[
        "Obersteinbach"
    ],
    "name:hye_x_preferred":[
        "\u0555\u0562\u0565\u0580\u057d\u057f\u0565\u0576\u0562\u0561\u056f"
    ],
    "name:ita_x_preferred":[
        "Obersteinbach"
    ],
    "name:kaz_x_preferred":[
        "\u041e\u0431\u0435\u0440\u0441\u0442\u0435\u043d\u0431\u0430\u043a"
    ],
    "name:lat_x_preferred":[
        "Obersteinbach"
    ],
    "name:mlg_x_preferred":[
        "Obersteinbach"
    ],
    "name:msa_x_preferred":[
        "Obersteinbach"
    ],
    "name:nld_x_preferred":[
        "Obersteinbach"
    ],
    "name:oci_x_preferred":[
        "Obersteinbach"
    ],
    "name:pfl_x_preferred":[
        "Obersteinbach"
    ],
    "name:pms_x_preferred":[
        "Obersteinbach"
    ],
    "name:pol_x_preferred":[
        "Obersteinbach"
    ],
    "name:por_x_preferred":[
        "Obersteinbach"
    ],
    "name:ron_x_preferred":[
        "Obersteinbach"
    ],
    "name:rus_x_preferred":[
        "\u041e\u0431\u0435\u0440\u0441\u0442\u0435\u043d\u0431\u0430\u043a"
    ],
    "name:slk_x_preferred":[
        "Obersteinbach"
    ],
    "name:slv_x_preferred":[
        "Obersteinbach"
    ],
    "name:spa_x_preferred":[
        "Obersteinbach"
    ],
    "name:swe_x_preferred":[
        "Obersteinbach"
    ],
    "name:ukr_x_preferred":[
        "\u041e\u0431\u0435\u0440\u0441\u0442\u0435\u043d\u0431\u0430\u043a"
    ],
    "name:uzb_x_preferred":[
        "Obersteinbach"
    ],
    "name:vie_x_preferred":[
        "Obersteinbach"
    ],
    "name:vol_x_preferred":[
        "Obersteinbach"
    ],
    "name:war_x_preferred":[
        "Obersteinbach"
    ],
    "name:zho_x_preferred":[
        "\u4e0a\u4ec0\u6cf0\u56e0\u5df4\u514b"
    ],
    "wof:name":"Obersteinbach",
    "wof:placetype":"neighbourhood"
},
  "geometry": {"coordinates":[7.20828,50.99738],"type":"Point"}
}