{
  "type": "Feature",
  "properties": {
    "iso:country":"DE",
    "wof:name":"Koppenhof",
    "wof:placetype":"neighbourhood"
},
  "geometry": {"coordinates":[11.03124901639608,49.39007081277776],"type":"Point"}
}