{
  "type": "Feature",
  "properties": {
    "gn:admin1_code":"12",
    "gn:admin2_code":"0.0",
    "gn:admin3_code":"13074.0",
    "gn:admin4_code":"13074042.0",
    "gn:asciiname":"Buelow",
    "gn:country_code":"DE",
    "gn:dem":59,
    "gn:feature_class":"P",
    "gn:feature_code":"PPL",
    "gn:name":"B\u00fclow",
    "gn:population":0,
    "gn:timezone":"Europe/Berlin",
    "iso:country":"DE",
    "name:und_x_variant":[
        "B\u00fclow-Dorf",
        "B\u00fclow"
    ],
    "wof:name":"Buelow",
    "wof:placetype":"neighbourhood"
},
  "geometry": {"coordinates":[11.02552,53.77127],"type":"Point"}
}