{
  "type": "Feature",
  "properties": {
    "gn:admin1_code":"2.0",
    "gn:admin2_code":"91.0",
    "gn:admin3_code":"9174.0",
    "gn:admin4_code":"9174137.0",
    "gn:asciiname":"Bayerzell",
    "gn:country_code":"DE",
    "gn:dem":524,
    "gn:feature_class":"P",
    "gn:feature_code":"PPL",
    "gn:name":"Bayerzell",
    "gn:population":0,
    "gn:timezone":"Europe/Berlin",
    "iso:country":"DE",
    "wof:name":"Bayerzell",
    "wof:placetype":"neighbourhood"
},
  "geometry": {"coordinates":[11.13064,48.2802],"type":"Point"}
}