{
  "type": "Feature",
  "properties": {
    "gn:admin1_code":"12",
    "gn:admin2_code":"0.0",
    "gn:admin3_code":"13074.0",
    "gn:admin4_code":"13074065.0",
    "gn:asciiname":"Neu Bruetzkow",
    "gn:country_code":"DE",
    "gn:dem":39,
    "gn:feature_class":"P",
    "gn:feature_code":"PPL",
    "gn:name":"Neu Br\u00fctzkow",
    "gn:population":0,
    "gn:timezone":"Europe/Berlin",
    "iso:country":"DE",
    "wof:name":"Neu Bruetzkow",
    "wof:placetype":"neighbourhood"
},
  "geometry": {"coordinates":[11.08221,53.79223],"type":"Point"}
}