{
  "type": "Feature",
  "properties": {
    "gn:admin1_code":"2",
    "gn:admin2_code":"94.0",
    "gn:admin3_code":"9479.0",
    "gn:admin4_code":"9479138.0",
    "gn:asciiname":"Muhlbuhl",
    "gn:country_code":"DE",
    "gn:dem":631,
    "gn:feature_class":"P",
    "gn:feature_code":"PPL",
    "gn:name":"M\u00fchlb\u00fchl",
    "gn:population":0,
    "gn:timezone":"Europe/Berlin",
    "iso:country":"DE",
    "wof:name":"Muhlbuhl",
    "wof:placetype":"neighbourhood"
},
  "geometry": {"coordinates":[11.93548,49.98136],"type":"Point"}
}