{
  "type": "Feature",
  "properties": {
    "gn:gn_country":"DE",
    "gn:gn_fcode":"PPLA4",
    "gn:gn_pop":493,
    "gn:population":493,
    "iso:country":"DE",
    "name:baq_x_preferred":[
        "K\u00fcmbdchen"
    ],
    "name:chi_x_preferred":[
        "\u91d1\u5e03\u5fb7\u5174"
    ],
    "name:dut_x_preferred":[
        "K\u00fcmbdchen"
    ],
    "name:eng_x_preferred":[
        "K\u00fcmbdchen"
    ],
    "name:epo_x_preferred":[
        "K\u00fcmbdchen"
    ],
    "name:fre_x_preferred":[
        "K\u00fcmbdchen"
    ],
    "name:ger_x_preferred":[
        "K\u00fcmbdchen"
    ],
    "name:hun_x_preferred":[
        "K\u00fcmbdchen"
    ],
    "name:ita_x_preferred":[
        "K\u00fcmbdchen"
    ],
    "name:jpn_x_preferred":[
        "\u30ad\u30e5\u30e0\u30c8\u30d2\u30a7\u30f3"
    ],
    "name:per_x_preferred":[
        "\u06a9\u0648\u0645\u0628\u062f\u0634\u0646"
    ],
    "name:pol_x_preferred":[
        "K\u00fcmbdchen"
    ],
    "name:por_x_preferred":[
        "K\u00fcmbdchen"
    ],
    "name:rum_x_preferred":[
        "K\u00fcmbdchen"
    ],
    "name:rus_x_preferred":[
        "\u041a\u044e\u043c\u0431\u0434\u0445\u0435\u043d"
    ],
    "name:srp_x_preferred":[
        "\u041a\u0438\u043c\u0431\u0434\u0445\u0435\u043d"
    ],
    "name:ukr_x_preferred":[
        "\u041a\u044e\u043c\u0431\u0434\u0445\u0435\u043d"
    ],
    "name:uzb_x_preferred":[
        "K\u00fcmbdchen"
    ],
    "name:vie_x_preferred":[
        "K\u00fcmbdchen"
    ],
    "name:vol_x_preferred":[
        "K\u00fcmbdchen"
    ],
    "name:war_x_preferred":[
        "K\u00fcmbdchen"
    ],
    "qs_pg:aaroncc":"DE",
    "qs_pg:gn_country":"DE",
    "qs_pg:gn_fcode":"PPLA4",
    "qs_pg:gn_pop":493,
    "qs_pg:name":"K\u00fcmbdchen",
    "qs_pg:photos_9r":0,
    "qs_pg:photos_sr":0,
    "qs_pg:pop_sr":2,
    "qs_pg:qs_pg_placetype":"locality",
    "wof:name":"K\u00fcmbdchen",
    "wof:placetype":"locality",
    "wof:population":493
},
  "geometry": {"coordinates":[7.51667,49.98333],"type":"Point"}
}