{
  "type": "Feature",
  "properties": {
    "gn:admin1_code":"14",
    "gn:admin2_code":"0.0",
    "gn:admin3_code":"15091.0",
    "gn:admin4_code":"15091375.0",
    "gn:asciiname":"Labetz",
    "gn:country_code":"DE",
    "gn:dem":76,
    "gn:feature_class":"P",
    "gn:feature_code":"PPL",
    "gn:name":"Labetz",
    "gn:population":416,
    "gn:timezone":"Europe/Berlin",
    "iso:country":"DE",
    "wof:name":"Labetz",
    "wof:placetype":"neighbourhood",
    "wof:population":416
},
  "geometry": {"coordinates":[12.69662,51.87237],"type":"Point"}
}