{
  "type": "Feature",
  "properties": {
    "gn:admin1_code":"2",
    "gn:admin2_code":"93.0",
    "gn:admin3_code":"9376.0",
    "gn:admin4_code":"9376144.0",
    "gn:asciiname":"Etzelhof",
    "gn:country_code":"DE",
    "gn:dem":472,
    "gn:feature_class":"P",
    "gn:feature_code":"PPL",
    "gn:name":"Etzelhof",
    "gn:population":0,
    "gn:timezone":"Europe/Berlin",
    "iso:country":"DE",
    "wof:name":"Etzelhof",
    "wof:placetype":"neighbourhood"
},
  "geometry": {"coordinates":[12.1325,49.45068],"type":"Point"}
}