{
  "type": "Feature",
  "properties": {
    "gn:admin1_code":"12.0",
    "gn:admin2_code":"0.0",
    "gn:admin3_code":"13071.0",
    "gn:admin4_code":"13071142.0",
    "gn:asciiname":"Basepohl",
    "gn:country_code":"DE",
    "gn:dem":59,
    "gn:feature_class":"P",
    "gn:feature_code":"PPL",
    "gn:name":"Basepohl",
    "gn:population":0,
    "gn:timezone":"Europe/Berlin",
    "iso:country":"DE",
    "wof:name":"Basepohl",
    "wof:placetype":"neighbourhood"
},
  "geometry": {"coordinates":[12.9174,53.72461],"type":"Point"}
}