{
  "type": "Feature",
  "properties": {
    "gn:admin1_code":"7",
    "gn:admin2_code":"57.0",
    "gn:admin3_code":"5758.0",
    "gn:admin4_code":"5758016.0",
    "gn:asciiname":"OEtinghausen",
    "gn:country_code":"DE",
    "gn:dem":83,
    "gn:feature_class":"P",
    "gn:feature_code":"PPL",
    "gn:name":"\u00d6tinghausen",
    "gn:population":0,
    "gn:timezone":"Europe/Berlin",
    "iso:country":"DE",
    "name:und_x_variant":[
        "Oetinghausen"
    ],
    "wof:name":"OEtinghausen",
    "wof:placetype":"neighbourhood"
},
  "geometry": {"coordinates":[8.61952,52.14451],"type":"Point"}
}