{
  "type": "Feature",
  "properties": {
    "iso:country":"DE",
    "name:deu_x_preferred":[
        "Flugplatz Nienburg-Holzbalge"
    ],
    "name:eng_x_preferred":[
        "Nienburg-Holzbalge Airport"
    ],
    "name:eng_x_variant":[
        "EDXI",
        "Nienburg-Holzbalge airfield"
    ],
    "name:msa_x_preferred":[
        "Lapangan Terbang Nienburg-Holzbalge"
    ],
    "oa:elevation_ft":"82",
    "oa:type":"small_airport",
    "woe:hierarchy":{
        "country_id":23424829,
        "county_id":12597006,
        "localadmin_id":12630103,
        "planet_id":1,
        "state_id":2345486
    },
    "wof:name":"Flugplatz Nienburg-holzbalge",
    "wof:placetype":"campus"
},
  "geometry": {"coordinates":[9.1625,52.709667],"type":"Point"}
}