{
  "type": "Feature",
  "properties": {
    "iso:country":"DE",
    "oa:elevation_ft":"82",
    "oa:type":"small_airport",
    "woe:hierarchy":{
        "country_id":23424829,
        "county_id":12597006,
        "localadmin_id":12630103,
        "planet_id":1,
        "state_id":2345486
    },
    "wof:name":"Flugplatz Nienburg-holzbalge",
    "wof:placetype":"campus"
},
  "geometry": {"coordinates":[9.1625,52.709667],"type":"Point"}
}