{
  "type": "Feature",
  "properties": {
    "gn:admin1_code":"1",
    "gn:admin2_code":"81.0",
    "gn:admin3_code":"8118.0",
    "gn:admin4_code":"8118007.0",
    "gn:asciiname":"Husarenhof",
    "gn:country_code":"DE",
    "gn:dem":286,
    "gn:feature_class":"P",
    "gn:feature_code":"PPL",
    "gn:name":"Husarenhof",
    "gn:population":0,
    "gn:timezone":"Europe/Berlin",
    "iso:country":"DE",
    "wof:name":"Husarenhof",
    "wof:placetype":"neighbourhood"
},
  "geometry": {"coordinates":[9.16259,48.98019],"type":"Point"}
}