{
  "type": "Feature",
  "properties": {
    "gn:admin1_code":"2.0",
    "gn:admin2_code":"91.0",
    "gn:admin3_code":"9177.0",
    "gn:admin4_code":"9177122.0",
    "gn:asciiname":"Adlberg",
    "gn:country_code":"DE",
    "gn:dem":487,
    "gn:feature_class":"P",
    "gn:feature_code":"PPL",
    "gn:name":"Adlberg",
    "gn:population":0,
    "gn:timezone":"Europe/Berlin",
    "iso:country":"DE",
    "wof:name":"Adlberg",
    "wof:placetype":"neighbourhood"
},
  "geometry": {"coordinates":[12.08811,48.3359],"type":"Point"}
}