{
  "type": "Feature",
  "properties": {
    "gn:admin1_code":"7",
    "gn:admin2_code":"57.0",
    "gn:admin3_code":"5762.0",
    "gn:admin4_code":"5762004.0",
    "gn:asciiname":"Dringenberg",
    "gn:country_code":"DE",
    "gn:dem":291,
    "gn:feature_class":"P",
    "gn:feature_code":"PPL",
    "gn:name":"Dringenberg",
    "gn:population":0,
    "gn:timezone":"Europe/Berlin",
    "iso:country":"DE",
    "wof:name":"Dringenberg",
    "wof:placetype":"neighbourhood"
},
  "geometry": {"coordinates":[9.05668,51.67117],"type":"Point"}
}