{
  "type": "Feature",
  "properties": {
    "gn:admin1_code":"8",
    "gn:admin2_code":"0.0",
    "gn:admin3_code":"7312.0",
    "gn:admin4_code":"7312000.0",
    "gn:asciiname":"Erfenbach",
    "gn:country_code":"DE",
    "gn:dem":231,
    "gn:feature_class":"P",
    "gn:feature_code":"PPL",
    "gn:name":"Erfenbach",
    "gn:population":0,
    "gn:timezone":"Europe/Berlin",
    "iso:country":"DE",
    "wof:name":"Erfenbach",
    "wof:placetype":"neighbourhood"
},
  "geometry": {"coordinates":[7.71231,49.47966],"type":"Point"}
}