{
  "type": "Feature",
  "properties": {
    "gn:admin1_code":"1",
    "gn:admin2_code":"84.0",
    "gn:admin3_code":"8436.0",
    "gn:admin4_code":"8436004.0",
    "gn:asciiname":"Treherz",
    "gn:country_code":"DE",
    "gn:dem":678,
    "gn:feature_class":"P",
    "gn:feature_code":"PPL",
    "gn:name":"Treherz",
    "gn:population":0,
    "gn:timezone":"Europe/Berlin",
    "iso:country":"DE",
    "wof:name":"Treherz",
    "wof:placetype":"neighbourhood"
},
  "geometry": {"coordinates":[10.04602,47.93497],"type":"Point"}
}