{
  "type": "Feature",
  "properties": {
    "gn:admin1_code":"7",
    "gn:admin2_code":"55.0",
    "gn:admin3_code":"5570.0",
    "gn:admin4_code":"5570020.0",
    "gn:asciiname":"Koentrup",
    "gn:country_code":"DE",
    "gn:dem":80,
    "gn:feature_class":"P",
    "gn:feature_code":"PPLL",
    "gn:name":"K\u00f6ntrup",
    "gn:population":0,
    "gn:timezone":"Europe/Berlin",
    "iso:country":"DE",
    "wof:name":"Koentrup",
    "wof:placetype":"neighbourhood"
},
  "geometry": {"coordinates":[8.11443,51.86271],"type":"Point"}
}