{
  "type": "Feature",
  "properties": {
    "gn:admin1_code":"15",
    "gn:admin2_code":"0.0",
    "gn:admin3_code":"16077.0",
    "gn:admin4_code":"16077029.0",
    "gn:asciiname":"Hartha",
    "gn:country_code":"DE",
    "gn:dem":284,
    "gn:feature_class":"P",
    "gn:feature_code":"PPL",
    "gn:name":"Hartha",
    "gn:population":0,
    "gn:timezone":"Europe/Berlin",
    "iso:country":"DE",
    "wof:name":"Hartha",
    "wof:placetype":"neighbourhood"
},
  "geometry": {"coordinates":[12.24268,50.93963],"type":"Point"}
}