{
  "type": "Feature",
  "properties": {
    "gn:admin1_code":"15",
    "gn:admin2_code":"0.0",
    "gn:admin3_code":"16077.0",
    "gn:admin4_code":"16077029.0",
    "gn:asciiname":"Hartha",
    "gn:country_code":"DE",
    "gn:dem":284,
    "gn:feature_class":"P",
    "gn:feature_code":"PPL",
    "gn:name":"Hartha",
    "gn:population":0,
    "gn:timezone":"Europe/Berlin",
    "iso:country":"DE",
    "name:ara_x_preferred":[
        "\u0647\u0627\u0631\u062a\u0627"
    ],
    "name:azb_x_preferred":[
        "\u0647\u0631\u0627\u062a\u0627"
    ],
    "name:bak_x_preferred":[
        "\u0425\u0430\u0440\u0442\u0430"
    ],
    "name:deu_x_preferred":[
        "Hartha"
    ],
    "name:epo_x_preferred":[
        "Hartha"
    ],
    "name:est_x_preferred":[
        "Hartha"
    ],
    "name:fas_x_preferred":[
        "\u0647\u0631\u0627\u062a\u0627"
    ],
    "name:fra_x_preferred":[
        "Hartha"
    ],
    "name:hsb_x_preferred":[
        "Hartha"
    ],
    "name:hun_x_preferred":[
        "Hartha"
    ],
    "name:ita_x_preferred":[
        "Hartha"
    ],
    "name:kaz_x_preferred":[
        "\u0425\u0430\u0440\u0442\u0430"
    ],
    "name:kir_x_preferred":[
        "\u0425\u0430\u0440\u0442\u0430"
    ],
    "name:lav_x_preferred":[
        "Harta"
    ],
    "name:mkd_x_preferred":[
        "\u0425\u0430\u0440\u0442\u0430"
    ],
    "name:msa_x_preferred":[
        "Hartha"
    ],
    "name:nld_x_preferred":[
        "Hartha"
    ],
    "name:pol_x_preferred":[
        "Hartha"
    ],
    "name:ron_x_preferred":[
        "Hartha"
    ],
    "name:rus_x_preferred":[
        "\u0425\u0430\u0440\u0442\u0430"
    ],
    "name:spa_x_preferred":[
        "Hartha"
    ],
    "name:srp_x_preferred":[
        "\u0425\u0430\u0440\u0442\u0430"
    ],
    "name:swe_x_preferred":[
        "Hartha"
    ],
    "name:tur_x_preferred":[
        "Hartha"
    ],
    "name:ukr_x_preferred":[
        "\u0413\u0430\u0440\u0442\u0430"
    ],
    "name:uzb_x_preferred":[
        "Hartha"
    ],
    "name:vie_x_preferred":[
        "Hartha"
    ],
    "name:vol_x_preferred":[
        "Hartha"
    ],
    "name:war_x_preferred":[
        "Hartha"
    ],
    "name:zho_x_preferred":[
        "\u54c8\u5c14\u5854"
    ],
    "wof:name":"Hartha",
    "wof:placetype":"neighbourhood"
},
  "geometry": {"coordinates":[12.24268,50.93963],"type":"Point"}
}