{
  "type": "Feature",
  "properties": {
    "gn:admin1_code":"13",
    "gn:admin2_code":"0.0",
    "gn:admin3_code":"14521.0",
    "gn:admin4_code":"14521700.0",
    "gn:asciiname":"Neuer Anbau",
    "gn:country_code":"DE",
    "gn:dem":462,
    "gn:feature_class":"P",
    "gn:feature_code":"PPL",
    "gn:name":"Neuer Anbau",
    "gn:population":0,
    "gn:timezone":"Europe/Berlin",
    "iso:country":"DE",
    "wof:name":"Neuer Anbau",
    "wof:placetype":"neighbourhood"
},
  "geometry": {"coordinates":[12.65602,50.5403],"type":"Point"}
}