{
  "type": "Feature",
  "properties": {
    "gn:admin1_code":"2",
    "gn:admin2_code":"93.0",
    "gn:admin3_code":"9372.0",
    "gn:admin4_code":"9372130.0",
    "gn:asciiname":"Thurnhofen",
    "gn:country_code":"DE",
    "gn:dem":488,
    "gn:feature_class":"P",
    "gn:feature_code":"PPL",
    "gn:name":"Th\u00fcrnhofen",
    "gn:population":0,
    "gn:timezone":"Europe/Berlin",
    "iso:country":"DE",
    "wof:name":"Thurnhofen",
    "wof:placetype":"neighbourhood"
},
  "geometry": {"coordinates":[12.8775,49.21514000000001],"type":"Point"}
}