{
  "type": "Feature",
  "properties": {
    "gn:admin1_code":"2",
    "gn:admin2_code":"94.0",
    "gn:admin3_code":"9472.0",
    "gn:admin4_code":"9472139.0",
    "gn:asciiname":"Stein",
    "gn:country_code":"DE",
    "gn:dem":491,
    "gn:feature_class":"P",
    "gn:feature_code":"PPL",
    "gn:name":"Stein",
    "gn:population":0,
    "gn:timezone":"Europe/Berlin",
    "iso:country":"DE",
    "name:als_x_preferred":[
        "Stein"
    ],
    "name:ara_x_preferred":[
        "\u0634\u062a\u0627\u064a\u0646"
    ],
    "name:ceb_x_preferred":[
        "Stein"
    ],
    "name:ces_x_preferred":[
        "Stein"
    ],
    "name:dan_x_preferred":[
        "Stein"
    ],
    "name:deu_x_preferred":[
        "Stein"
    ],
    "name:epo_x_preferred":[
        "Stein"
    ],
    "name:eus_x_preferred":[
        "Stein"
    ],
    "name:fas_x_preferred":[
        "\u0627\u0634\u062a\u0627\u06cc\u0646"
    ],
    "name:fin_x_preferred":[
        "Stein"
    ],
    "name:fra_x_preferred":[
        "Stein"
    ],
    "name:frr_x_preferred":[
        "Stian"
    ],
    "name:heb_x_preferred":[
        "\u05e9\u05d8\u05d9\u05d9\u05df"
    ],
    "name:ita_x_preferred":[
        "Stein"
    ],
    "name:jpn_x_preferred":[
        "\u30b7\u30e5\u30bf\u30a4\u30f3"
    ],
    "name:kor_x_preferred":[
        "\uc288\ud0c0\uc778"
    ],
    "name:lmo_x_preferred":[
        "Stein"
    ],
    "name:mkd_x_preferred":[
        "\u0428\u0442\u0430\u0458\u043d"
    ],
    "name:nld_x_preferred":[
        "Stein"
    ],
    "name:nor_x_preferred":[
        "Stein"
    ],
    "name:pol_x_preferred":[
        "Stein"
    ],
    "name:por_x_preferred":[
        "Stein"
    ],
    "name:ron_x_preferred":[
        "Stein"
    ],
    "name:rus_x_preferred":[
        "\u0421\u0442\u0435\u0439\u043d"
    ],
    "name:sco_x_preferred":[
        "Stein"
    ],
    "name:slk_x_preferred":[
        "Stein"
    ],
    "name:spa_x_preferred":[
        "Stein"
    ],
    "name:srp_x_preferred":[
        "\u0428\u0442\u0430\u0458\u043d"
    ],
    "name:swe_x_preferred":[
        "Stein"
    ],
    "name:ukr_x_preferred":[
        "\u0421\u0442\u0435\u0439\u043d"
    ],
    "name:vol_x_preferred":[
        "Stein"
    ],
    "wof:name":"Stein",
    "wof:placetype":"neighbourhood"
},
  "geometry": {"coordinates":[11.70111,50.0648],"type":"Point"}
}