{
  "type": "Feature",
  "properties": {
    "gn:admin1_code":"14",
    "gn:admin2_code":"0.0",
    "gn:admin3_code":"15088.0",
    "gn:admin4_code":"15088355.0",
    "gn:asciiname":"Kalzendorf",
    "gn:country_code":"DE",
    "gn:dem":216,
    "gn:feature_class":"P",
    "gn:feature_code":"PPL",
    "gn:name":"Kalzendorf",
    "gn:population":0,
    "gn:timezone":"Europe/Berlin",
    "iso:country":"DE",
    "name:und_x_variant":[
        "Calzendorf",
        "Katzendorf \u00dcber Querfurt",
        "Kalzendorf"
    ],
    "wof:name":"Kalzendorf",
    "wof:placetype":"neighbourhood"
},
  "geometry": {"coordinates":[11.67632,51.30316],"type":"Point"}
}