{
  "type": "Feature",
  "properties": {
    "gn:admin1_code":"6",
    "gn:admin2_code":"0.0",
    "gn:admin3_code":"3351.0",
    "gn:admin4_code":"3351006.0",
    "gn:asciiname":"Klein Hehlen",
    "gn:country_code":"DE",
    "gn:dem":43,
    "gn:feature_class":"P",
    "gn:feature_code":"PPL",
    "gn:name":"Klein Hehlen",
    "gn:population":0,
    "gn:timezone":"Europe/Berlin",
    "iso:country":"DE",
    "name:ceb_x_preferred":[
        "Klein Hehlen"
    ],
    "name:deu_x_preferred":[
        "Klein Hehlen"
    ],
    "name:fas_x_preferred":[
        "\u06a9\u0644\u0627\u06cc\u0646 \u0647\u0647\u0644\u0646"
    ],
    "wof:name":"Klein Hehlen",
    "wof:placetype":"neighbourhood"
},
  "geometry": {"coordinates":[10.06099,52.63546],"type":"Point"}
}