{
  "type": "Feature",
  "properties": {
    "gn:admin1_code":"5",
    "gn:admin2_code":"66.0",
    "gn:admin3_code":"6635.0",
    "gn:admin4_code":"6635015.0",
    "gn:asciiname":"Oberense",
    "gn:country_code":"DE",
    "gn:dem":364,
    "gn:feature_class":"P",
    "gn:feature_code":"PPL",
    "gn:name":"Oberense",
    "gn:population":0,
    "gn:timezone":"Europe/Berlin",
    "iso:country":"DE",
    "wof:name":"Oberense",
    "wof:placetype":"neighbourhood"
},
  "geometry": {"coordinates":[8.83987,51.23537],"type":"Point"}
}