{
  "type": "Feature",
  "properties": {
    "gn:country":"DE",
    "gn:fcode":"PPL",
    "gn:population":165,
    "iso:country":"DE",
    "name:bak_x_preferred":[
        "\u0413\u0438\u0437\u0435\u0440\u0438\u0446"
    ],
    "name:cat_x_preferred":[
        "Gieseritz"
    ],
    "name:ceb_x_preferred":[
        "Gieseritz"
    ],
    "name:che_x_preferred":[
        "\u0413\u0438\u0437\u0435\u0440\u0438\u0446"
    ],
    "name:deu_x_preferred":[
        "Gieseritz"
    ],
    "name:eng_x_preferred":[
        "Gieseritz"
    ],
    "name:epo_x_preferred":[
        "Gieseritz"
    ],
    "name:fas_x_preferred":[
        "\u06af\u06cc\u0632\u0631\u06cc\u062a\u0633"
    ],
    "name:fra_x_preferred":[
        "Gieseritz"
    ],
    "name:gle_x_preferred":[
        "Gieseritz"
    ],
    "name:ita_x_preferred":[
        "Gieseritz"
    ],
    "name:kaz_x_preferred":[
        "\u0413\u0438\u0437\u0435\u0440\u0438\u0446"
    ],
    "name:kir_x_preferred":[
        "\u0413\u0438\u0437\u0435\u0440\u0438\u0446"
    ],
    "name:nld_x_preferred":[
        "Gieseritz"
    ],
    "name:nob_x_preferred":[
        "Gieseritz"
    ],
    "name:ron_x_preferred":[
        "Gieseritz"
    ],
    "name:rus_x_preferred":[
        "\u0413\u0438\u0437\u0435\u0440\u0438\u0446"
    ],
    "name:tat_x_preferred":[
        "\u0413\u0438\u0437\u0435\u0440\u0438\u0446"
    ],
    "name:uzb_x_preferred":[
        "Gieseritz"
    ],
    "name:vol_x_preferred":[
        "Gieseritz"
    ],
    "qs_pg:aaroncc":"DE",
    "qs_pg:gn_country":"DE",
    "qs_pg:gn_fcode":"PPL",
    "qs_pg:gn_pop":165,
    "qs_pg:name":"Gieseritz",
    "qs_pg:name_adm0":"Deutschland",
    "qs_pg:name_adm1":"Sachsen-Anhalt",
    "qs_pg:photos_9k":1,
    "qs_pg:photos_9r":1,
    "qs_pg:photos_all":1,
    "qs_pg:photos_sr":0,
    "qs_pg:pop_sr":1,
    "qs_pg:qs_pg_placetype":"locality",
    "qs_pg:qs_pg_placetype_gp":"Town",
    "qs_pg:woe_adm0":23424829,
    "woe:adm0_id":23424829,
    "woe:name_adm0":"Deutschland",
    "woe:name_adm1":"Sachsen-Anhalt",
    "woe:placetype":"Town",
    "wof:name":"Gieseritz",
    "wof:placetype":"neighbourhood",
    "wof:population":165
},
  "geometry": {"coordinates":[11.0081,52.77419],"type":"Point"}
}