{
  "type": "Feature",
  "properties": {
    "gn:country":"DE",
    "gn:fcode":"PPL",
    "gn:population":0,
    "iso:country":"DE",
    "name:ceb_x_preferred":[
        "Zugerberg"
    ],
    "name:deu_x_preferred":[
        "Zugerberg"
    ],
    "name:epo_x_preferred":[
        "Zugerberg"
    ],
    "name:ita_x_preferred":[
        "Zugerberg"
    ],
    "name:nld_x_preferred":[
        "Zugerberg"
    ],
    "name:swe_x_preferred":[
        "Zugerberg"
    ],
    "qs_pg:aaroncc":"DE",
    "qs_pg:gn_country":"DE",
    "qs_pg:gn_fcode":"PPL",
    "qs_pg:gn_pop":0,
    "qs_pg:name":"Zugerberg",
    "qs_pg:name_adm0":"Schweiz",
    "qs_pg:name_adm1":"Kanton Zug",
    "qs_pg:photos":190,
    "qs_pg:photos_1k":39,
    "qs_pg:photos_9k":1,
    "qs_pg:photos_9r":4,
    "qs_pg:photos_all":190,
    "qs_pg:photos_sr":4,
    "qs_pg:pop_sr":0,
    "qs_pg:qs_pg_placetype":"locality",
    "qs_pg:qs_pg_placetype_gp":"Town",
    "qs_pg:woe_adm0":23424957,
    "woe:adm0_id":23424957,
    "woe:name_adm0":"Schweiz",
    "woe:name_adm1":"Kanton Zug",
    "woe:placetype":"Town",
    "wof:name":"Zugerberg",
    "wof:placetype":"neighbourhood"
},
  "geometry": {"coordinates":[8.11667,47.73333],"type":"Point"}
}