{
  "type": "Feature",
  "properties": {
    "gn:country":"DE",
    "gn:fcode":"PPLX",
    "gn:population":0,
    "iso:country":"DE",
    "name:deu_x_preferred":[
        "Coerde"
    ],
    "qs:gn_fcode":"PPLX",
    "qs:gn_local":0,
    "qs:gn_namadm1":"07",
    "qs:gn_name":"Coerde",
    "qs:local_max":4321,
    "qs:local_sum":13562,
    "qs:localhoods":28,
    "qs:name":"Coerde",
    "qs:name_adm0":"Deutschland",
    "qs:name_adm1":"Nordrhein-Westfalen",
    "qs:name_adm2":"Stadtkreis M\u00fcnster",
    "qs:name_lau":"Stadtteil Ost",
    "qs:name_local":"M\u00fcnster",
    "qs:photo_max":21,
    "qs:photo_sum":96,
    "qs:placetype":"Suburb",
    "qs:quad_count":14,
    "qs:woe_adm0":23424829,
    "qs:woe_adm1":2345487,
    "qs:woe_adm2":12596927,
    "qs:woe_lau":26823102,
    "qs:woe_local":676864,
    "qs:woe_ver":"7.10.0",
    "qs_pg:aaroncc":"DE",
    "qs_pg:gn_country":"DE",
    "qs_pg:gn_fcode":"PPLX",
    "qs_pg:gn_pop":0,
    "qs_pg:name":"Coerde",
    "qs_pg:name_adm0":"Deutschland",
    "qs_pg:name_adm1":"Nordrhein-Westfalen",
    "qs_pg:photos":109,
    "qs_pg:photos_1k":22,
    "qs_pg:photos_9k":1,
    "qs_pg:photos_9r":3,
    "qs_pg:photos_all":109,
    "qs_pg:photos_sr":3,
    "qs_pg:pop_sr":0,
    "qs_pg:qs_pg_placetype":"neighbourhood",
    "qs_pg:qs_pg_placetype_gp":"Suburb",
    "qs_pg:woe_adm0":23424829,
    "wof:lang":[
        "ger"
    ],
    "wof:name":"Coerde",
    "wof:placetype":"neighbourhood"
},
  "geometry": {"coordinates":[7.651624,52.000839],"type":"Point"}
}