{
  "type": "Feature",
  "properties": {
    "gn:admin1_code":"7",
    "gn:admin2_code":"57.0",
    "gn:admin3_code":"5770.0",
    "gn:admin4_code":"5770004.0",
    "gn:asciiname":"Jaegerplatz",
    "gn:country_code":"DE",
    "gn:dem":128,
    "gn:feature_class":"P",
    "gn:feature_code":"PPL",
    "gn:name":"J\u00e4gerplatz",
    "gn:population":0,
    "gn:timezone":"Europe/Berlin",
    "iso:country":"DE",
    "wof:name":"Jaegerplatz",
    "wof:placetype":"neighbourhood"
},
  "geometry": {"coordinates":[8.75019,52.26535],"type":"Point"}
}