{
  "type": "Feature",
  "properties": {
    "gn:admin1_code":"2.0",
    "gn:admin2_code":"094",
    "gn:admin3_code":"9477.0",
    "gn:admin4_code":"9477136.0",
    "gn:asciiname":"Wustenbuchau",
    "gn:country_code":"DE",
    "gn:dem":316,
    "gn:feature_class":"P",
    "gn:feature_code":"PPL",
    "gn:name":"W\u00fcstenbuchau",
    "gn:population":0,
    "gn:timezone":"Europe/Berlin",
    "iso:country":"DE",
    "wof:name":"Wustenbuchau",
    "wof:placetype":"neighbourhood"
},
  "geometry": {"coordinates":[11.34031,50.08179000000001],"type":"Point"}
}