{
  "type": "Feature",
  "properties": {
    "gn:admin1_code":"2",
    "gn:admin2_code":"92.0",
    "gn:admin3_code":"9273.0",
    "gn:admin4_code":"9273172.0",
    "gn:asciiname":"Tollbach",
    "gn:country_code":"DE",
    "gn:dem":419,
    "gn:feature_class":"P",
    "gn:feature_code":"PPL",
    "gn:name":"Tollbach",
    "gn:population":0,
    "gn:timezone":"Europe/Berlin",
    "iso:country":"DE",
    "wof:name":"Tollbach",
    "wof:placetype":"neighbourhood"
},
  "geometry": {"coordinates":[11.88801,48.74279],"type":"Point"}
}