{
  "type": "Feature",
  "properties": {
    "gn:country":"DE",
    "gn:fcode":"PPL",
    "gn:population":0,
    "iso:country":"DE",
    "name:deu_x_preferred":[
        "W\u00f6schbach"
    ],
    "name:eng_x_preferred":[
        "W\u00f6schbach"
    ],
    "name:fra_x_preferred":[
        "W\u00f6schbach"
    ],
    "name:gle_x_preferred":[
        "W\u00f6schbach"
    ],
    "name:nld_x_preferred":[
        "W\u00f6schbach"
    ],
    "qs_pg:aaroncc":"DE",
    "qs_pg:gn_country":"DE",
    "qs_pg:gn_fcode":"PPL",
    "qs_pg:gn_pop":0,
    "qs_pg:name":"W\u00f6schbach",
    "qs_pg:name_adm0":"Deutschland",
    "qs_pg:name_adm1":"Baden-W\u00fcrttemberg",
    "qs_pg:photos_9r":0,
    "qs_pg:photos_sr":0,
    "qs_pg:pop_sr":0,
    "qs_pg:qs_pg_placetype":"locality",
    "qs_pg:qs_pg_placetype_gp":"Town",
    "qs_pg:woe_adm0":23424829,
    "woe:adm0_id":23424829,
    "woe:name_adm0":"Deutschland",
    "woe:name_adm1":"Baden-W\u00fcrttemberg",
    "woe:placetype":"Town",
    "wof:name":"W\u00f6schbach",
    "wof:placetype":"neighbourhood"
},
  "geometry": {"coordinates":[8.56465,49.0027],"type":"Point"}
}