{
  "type": "Feature",
  "properties": {
    "gn:admin1_code":"14",
    "gn:admin2_code":"0.0",
    "gn:admin3_code":"15088.0",
    "gn:admin4_code":"15088265.0",
    "gn:asciiname":"Weidenbach",
    "gn:country_code":"DE",
    "gn:dem":169,
    "gn:feature_class":"P",
    "gn:feature_code":"PPL",
    "gn:name":"Weidenbach",
    "gn:population":0,
    "gn:timezone":"Europe/Berlin",
    "iso:country":"DE",
    "name:ceb_x_preferred":[
        "Weidenbach"
    ],
    "name:deu_x_preferred":[
        "Weidenbach"
    ],
    "name:epo_x_preferred":[
        "Weidenbach"
    ],
    "name:fra_x_preferred":[
        "Weidenbach"
    ],
    "name:ita_x_preferred":[
        "Weidenbach"
    ],
    "name:nld_x_preferred":[
        "Weidenbach"
    ],
    "name:pol_x_preferred":[
        "Weidenbach"
    ],
    "name:rus_x_preferred":[
        "\u0412\u0430\u0439\u0434\u0435\u043d\u0431\u0430\u0445"
    ],
    "name:srp_x_preferred":[
        "\u0412\u0430\u0458\u0434\u0435\u043d\u0431\u0430\u0445"
    ],
    "name:swe_x_preferred":[
        "Weidenbach"
    ],
    "name:vol_x_preferred":[
        "Weidenbach"
    ],
    "wof:name":"Weidenbach",
    "wof:placetype":"neighbourhood"
},
  "geometry": {"coordinates":[11.66667,51.38333],"type":"Point"}
}