{
  "type": "Feature",
  "properties": {
    "gn:admin1_code":"14",
    "gn:admin2_code":"0.0",
    "gn:admin3_code":"15088.0",
    "gn:admin4_code":"15088265.0",
    "gn:asciiname":"Weidenbach",
    "gn:country_code":"DE",
    "gn:dem":169,
    "gn:feature_class":"P",
    "gn:feature_code":"PPL",
    "gn:name":"Weidenbach",
    "gn:population":0,
    "gn:timezone":"Europe/Berlin",
    "iso:country":"DE",
    "wof:name":"Weidenbach",
    "wof:placetype":"neighbourhood"
},
  "geometry": {"coordinates":[11.66667,51.38333],"type":"Point"}
}