{
  "type": "Feature",
  "properties": {
    "gn:admin1_code":"15",
    "gn:admin2_code":"0.0",
    "gn:admin3_code":"16074.0",
    "gn:admin4_code":"16074039.0",
    "gn:asciiname":"Etzdorf",
    "gn:country_code":"DE",
    "gn:dem":304,
    "gn:feature_class":"P",
    "gn:feature_code":"PPL",
    "gn:name":"Etzdorf",
    "gn:population":0,
    "gn:timezone":"Europe/Berlin",
    "iso:country":"DE",
    "wof:name":"Etzdorf",
    "wof:placetype":"neighbourhood"
},
  "geometry": {"coordinates":[11.94294,50.97696],"type":"Point"}
}