{
  "type": "Feature",
  "properties": {
    "gn:admin1_code":"1",
    "gn:admin2_code":"83.0",
    "gn:admin3_code":"8336.0",
    "gn:admin4_code":"8336107.0",
    "gn:asciiname":"Eichholz",
    "gn:country_code":"DE",
    "gn:dem":607,
    "gn:feature_class":"P",
    "gn:feature_code":"PPL",
    "gn:name":"Eichholz",
    "gn:population":0,
    "gn:timezone":"Europe/Berlin",
    "iso:country":"DE",
    "wof:name":"Eichholz",
    "wof:placetype":"neighbourhood"
},
  "geometry": {"coordinates":[7.78206,47.69917],"type":"Point"}
}