{
  "type": "Feature",
  "properties": {
    "gn:admin1_code":"6",
    "gn:admin2_code":"0.0",
    "gn:admin3_code":"3155.0",
    "gn:admin4_code":"3155010.0",
    "gn:asciiname":"Luetgenrode",
    "gn:country_code":"DE",
    "gn:dem":139,
    "gn:feature_class":"P",
    "gn:feature_code":"PPL",
    "gn:name":"L\u00fctgenrode",
    "gn:population":0,
    "gn:timezone":"Europe/Berlin",
    "iso:country":"DE",
    "wof:name":"Luetgenrode",
    "wof:placetype":"neighbourhood"
},
  "geometry": {"coordinates":[9.9119,51.63075],"type":"Point"}
}