{
  "type": "Feature",
  "properties": {
    "gn:country":"DE",
    "gn:fcode":"PPL",
    "gn:population":0,
    "iso:country":"DE",
    "name:deu_x_preferred":[
        "Stubben"
    ],
    "name:epo_x_preferred":[
        "Stubben"
    ],
    "name:fas_x_preferred":[
        "\u0634\u062a\u0648\u0628\u0646"
    ],
    "name:ita_x_preferred":[
        "Stubben"
    ],
    "name:nds_x_preferred":[
        "Stubben"
    ],
    "name:nld_x_preferred":[
        "Stubben"
    ],
    "name:pol_x_preferred":[
        "Stubben"
    ],
    "name:por_x_preferred":[
        "Stubben"
    ],
    "name:ron_x_preferred":[
        "Stubben"
    ],
    "name:rus_x_preferred":[
        "\u0428\u0442\u0443\u0431\u0431\u0435\u043d"
    ],
    "name:srp_x_preferred":[
        "\u0428\u0442\u0443\u0431\u0435\u043d"
    ],
    "name:uzb_x_preferred":[
        "Stubben"
    ],
    "name:vie_x_preferred":[
        "Stubben"
    ],
    "name:vol_x_preferred":[
        "Stubben"
    ],
    "name:war_x_preferred":[
        "Stubben"
    ],
    "name:zho_x_preferred":[
        "\u65bd\u56fe\u672c"
    ],
    "qs_pg:aaroncc":"DE",
    "qs_pg:gn_country":"DE",
    "qs_pg:gn_fcode":"PPL",
    "qs_pg:gn_pop":0,
    "qs_pg:name":"Stubben",
    "qs_pg:name_adm0":"Deutschland",
    "qs_pg:name_adm1":"Freie Hansestadt Bremen",
    "qs_pg:photos":2,
    "qs_pg:photos_1k":1,
    "qs_pg:photos_9k":1,
    "qs_pg:photos_9r":1,
    "qs_pg:photos_all":2,
    "qs_pg:photos_sr":1,
    "qs_pg:pop_sr":0,
    "qs_pg:qs_pg_placetype":"neighbourhood",
    "qs_pg:qs_pg_placetype_gp":"Suburb",
    "qs_pg:woe_adm0":23424829,
    "woe:adm0_id":23424829,
    "woe:name_adm0":"Deutschland",
    "woe:name_adm1":"Freie Hansestadt Bremen",
    "woe:placetype":"Suburb",
    "wof:name":"Stubben",
    "wof:placetype":"neighbourhood"
},
  "geometry": {"coordinates":[8.69408,53.1884],"type":"Point"}
}