{
  "type": "Feature",
  "properties": {
    "gn:admin1_code":"1",
    "gn:admin2_code":"84.0",
    "gn:admin3_code":"8417.0",
    "gn:admin4_code":"8417079.0",
    "gn:asciiname":"Margrethausen",
    "gn:country_code":"DE",
    "gn:dem":702,
    "gn:feature_class":"P",
    "gn:feature_code":"PPL",
    "gn:name":"Margrethausen",
    "gn:population":0,
    "gn:timezone":"Europe/Berlin",
    "iso:country":"DE",
    "name:deu_x_preferred":[
        "Margrethausen"
    ],
    "name:fas_x_preferred":[
        "\u0627\u0648\u0634\u0632\u0646\u0628\u0631\u06af"
    ],
    "name:nld_x_preferred":[
        "Margrethausen"
    ],
    "name:pol_x_preferred":[
        "Margrethausen"
    ],
    "wof:name":"Margrethausen",
    "wof:placetype":"neighbourhood"
},
  "geometry": {"coordinates":[8.96741,48.23073],"type":"Point"}
}