{
  "type": "Feature",
  "properties": {
    "gn:admin1_code":"2.0",
    "gn:admin2_code":"092",
    "gn:admin3_code":"9274.0",
    "gn:admin4_code":"9274184.0",
    "gn:asciiname":"Zeiling",
    "gn:country_code":"DE",
    "gn:dem":480,
    "gn:feature_class":"P",
    "gn:feature_code":"PPL",
    "gn:name":"Zeiling",
    "gn:population":0,
    "gn:timezone":"Europe/Berlin",
    "iso:country":"DE",
    "wof:name":"Zeiling",
    "wof:placetype":"neighbourhood"
},
  "geometry": {"coordinates":[12.38306,48.44005],"type":"Point"}
}