{
  "type": "Feature",
  "properties": {
    "gn:admin1_code":"2",
    "gn:admin2_code":"92.0",
    "gn:admin3_code":"9276.0",
    "gn:admin4_code":"9276148.0",
    "gn:asciiname":"Klautzenbach",
    "gn:country_code":"DE",
    "gn:dem":593,
    "gn:feature_class":"P",
    "gn:feature_code":"PPL",
    "gn:name":"Klautzenbach",
    "gn:population":0,
    "gn:timezone":"Europe/Berlin",
    "iso:country":"DE",
    "wof:name":"Klautzenbach",
    "wof:placetype":"neighbourhood"
},
  "geometry": {"coordinates":[13.22093,49.03258],"type":"Point"}
}