{
  "type": "Feature",
  "properties": {
    "gn:admin1_code":"2",
    "gn:admin2_code":"92.0",
    "gn:admin3_code":"9278.0",
    "gn:admin4_code":"9278123.0",
    "gn:asciiname":"Gross",
    "gn:country_code":"DE",
    "gn:dem":378,
    "gn:feature_class":"P",
    "gn:feature_code":"PPL",
    "gn:name":"Gro\u00df",
    "gn:population":0,
    "gn:timezone":"Europe/Berlin",
    "iso:country":"DE",
    "name:ceb_x_preferred":[
        "Gross"
    ],
    "name:ces_x_preferred":[
        "Gross"
    ],
    "name:deu_x_preferred":[
        "Gro\u00df"
    ],
    "name:fas_x_preferred":[
        "\u06af\u0631\u0648\u0633"
    ],
    "name:fra_x_preferred":[
        "Gross"
    ],
    "name:heb_x_preferred":[
        "\u05d2\u05e8\u05d5\u05e1"
    ],
    "name:ita_x_preferred":[
        "Gross"
    ],
    "name:jpn_x_preferred":[
        "\u30b0\u30ed\u30b9"
    ],
    "name:kaz_x_preferred":[
        "\u0413\u0440\u043e\u0441\u0441"
    ],
    "name:kor_x_preferred":[
        "\uadf8\ub85c\uc2a4"
    ],
    "name:lav_x_preferred":[
        "Gross"
    ],
    "name:pol_x_preferred":[
        "Gro\u00df"
    ],
    "name:por_x_preferred":[
        "Gross"
    ],
    "name:rus_x_preferred":[
        "\u0413\u0440\u043e\u0441\u0441"
    ],
    "name:ukr_x_preferred":[
        "\u0413\u0440\u043e\u0441\u0441"
    ],
    "wof:name":"Gross",
    "wof:placetype":"neighbourhood"
},
  "geometry": {"coordinates":[12.42784,48.82481],"type":"Point"}
}