{
  "type": "Feature",
  "properties": {
    "gn:admin1_code":"2",
    "gn:admin2_code":"92.0",
    "gn:admin3_code":"9278.0",
    "gn:admin4_code":"9278123.0",
    "gn:asciiname":"Gross",
    "gn:country_code":"DE",
    "gn:dem":378,
    "gn:feature_class":"P",
    "gn:feature_code":"PPL",
    "gn:name":"Gro\u00df",
    "gn:population":0,
    "gn:timezone":"Europe/Berlin",
    "iso:country":"DE",
    "wof:name":"Gross",
    "wof:placetype":"neighbourhood"
},
  "geometry": {"coordinates":[12.42784,48.82481],"type":"Point"}
}