{
  "type": "Feature",
  "properties": {
    "gn:admin1_code":"9",
    "gn:admin2_code":"0.0",
    "gn:admin3_code":"10046.0",
    "gn:admin4_code":"10046116.0",
    "gn:asciiname":"Gronig",
    "gn:country_code":"DE",
    "gn:dem":342,
    "gn:feature_class":"P",
    "gn:feature_code":"PPL",
    "gn:name":"Gronig",
    "gn:population":0,
    "gn:timezone":"Europe/Berlin",
    "iso:country":"DE",
    "wof:name":"Gronig",
    "wof:placetype":"neighbourhood"
},
  "geometry": {"coordinates":[7.07058,49.51254],"type":"Point"}
}