{
  "type": "Feature",
  "properties": {
    "gn:admin1_code":"11",
    "gn:admin2_code":"0.0",
    "gn:admin3_code":"12069.0",
    "gn:admin4_code":"12069345.0",
    "gn:asciiname":"Deutsch Bork",
    "gn:country_code":"DE",
    "gn:dem":42,
    "gn:feature_class":"P",
    "gn:feature_code":"PPL",
    "gn:name":"Deutsch Bork",
    "gn:population":0,
    "gn:timezone":"Europe/Berlin",
    "iso:country":"DE",
    "wof:name":"Deutsch Bork",
    "wof:placetype":"neighbourhood"
},
  "geometry": {"coordinates":[12.85453,52.16644],"type":"Point"}
}