{
  "type": "Feature",
  "properties": {
    "gn:admin1_code":"6",
    "gn:admin2_code":"0.0",
    "gn:admin3_code":"3459.0",
    "gn:admin4_code":"3459024.0",
    "gn:asciiname":"Buer",
    "gn:country_code":"DE",
    "gn:dem":106,
    "gn:feature_class":"P",
    "gn:feature_code":"PPL",
    "gn:name":"Buer",
    "gn:population":0,
    "gn:timezone":"Europe/Berlin",
    "iso:country":"DE",
    "name:ceb_x_preferred":[
        "Buer"
    ],
    "name:deu_x_preferred":[
        "Buer"
    ],
    "name:nds_x_preferred":[
        "Buer"
    ],
    "name:nld_x_preferred":[
        "Buer"
    ],
    "wof:name":"Buer",
    "wof:placetype":"neighbourhood"
},
  "geometry": {"coordinates":[8.40302,52.24683],"type":"Point"}
}