{
  "type": "Feature",
  "properties": {
    "gn:admin1_code":"2",
    "gn:admin2_code":"97.0",
    "gn:admin3_code":"9780.0",
    "gn:admin4_code":"9780114.0",
    "gn:asciiname":"Gotzen",
    "gn:country_code":"DE",
    "gn:dem":797,
    "gn:feature_class":"P",
    "gn:feature_code":"PPL",
    "gn:name":"G\u00f6tzen",
    "gn:population":0,
    "gn:timezone":"Europe/Berlin",
    "iso:country":"DE",
    "wof:name":"Gotzen",
    "wof:placetype":"neighbourhood"
},
  "geometry": {"coordinates":[10.39357,47.73119000000001],"type":"Point"}
}