{
  "type": "Feature",
  "properties": {
    "iso:country":"DE",
    "wof:name":"Echarding",
    "wof:placetype":"neighbourhood"
},
  "geometry": {"coordinates":[11.61824837444954,48.12631354066053],"type":"Point"}
}