{
  "type": "Feature",
  "properties": {
    "gn:admin1_code":"11",
    "gn:admin2_code":"0.0",
    "gn:admin3_code":"12064.0",
    "gn:admin4_code":"12064317.0",
    "gn:asciiname":"Eggersdorf",
    "gn:country_code":"DE",
    "gn:dem":76,
    "gn:feature_class":"P",
    "gn:feature_code":"PPL",
    "gn:name":"Eggersdorf",
    "gn:population":0,
    "gn:timezone":"Europe/Berlin",
    "iso:country":"DE",
    "name:bak_x_preferred":[
        "\u042d\u0433\u0433\u0435\u0440\u0441\u0434\u043e\u0440\u0444"
    ],
    "name:ceb_x_preferred":[
        "Eggersdorf"
    ],
    "name:deu_x_preferred":[
        "Eggersdorf"
    ],
    "name:epo_x_preferred":[
        "Eggersdorf"
    ],
    "name:ita_x_preferred":[
        "Eggersdorf"
    ],
    "name:mkd_x_preferred":[
        "\u0415\u0433\u0435\u0440\u0441\u0434\u043e\u0440\u0444"
    ],
    "name:nld_x_preferred":[
        "Eggersdorf"
    ],
    "name:ron_x_preferred":[
        "Eggersdorf"
    ],
    "name:rus_x_preferred":[
        "\u042d\u0433\u0433\u0435\u0440\u0441\u0434\u043e\u0440\u0444"
    ],
    "name:uzb_x_preferred":[
        "Eggersdorf"
    ],
    "name:vol_x_preferred":[
        "Eggersdorf"
    ],
    "wof:name":"Eggersdorf",
    "wof:placetype":"neighbourhood"
},
  "geometry": {"coordinates":[14.10433,52.47575],"type":"Point"}
}