{
  "type": "Feature",
  "properties": {
    "gn:admin1_code":"7",
    "gn:admin2_code":"59.0",
    "gn:admin3_code":"5970.0",
    "gn:admin4_code":"5970016.0",
    "gn:asciiname":"Eichen",
    "gn:country_code":"DE",
    "gn:dem":321,
    "gn:feature_class":"P",
    "gn:feature_code":"PPL",
    "gn:name":"Eichen",
    "gn:population":0,
    "gn:timezone":"Europe/Berlin",
    "iso:country":"DE",
    "wof:name":"Eichen",
    "wof:placetype":"neighbourhood"
},
  "geometry": {"coordinates":[7.88255,50.90608],"type":"Point"}
}