{
  "type": "Feature",
  "properties": {
    "gn:admin1_code":"10",
    "gn:admin2_code":"0.0",
    "gn:admin3_code":"1053.0",
    "gn:admin4_code":"1053113.0",
    "gn:asciiname":"Gross Schretstaken",
    "gn:country_code":"DE",
    "gn:dem":50,
    "gn:feature_class":"P",
    "gn:feature_code":"PPL",
    "gn:name":"Gro\u00df Schretstaken",
    "gn:population":0,
    "gn:timezone":"Europe/Berlin",
    "iso:country":"DE",
    "name:und_x_variant":[
        "Gro\u00df Schretstaken"
    ],
    "wof:name":"Gross Schretstaken",
    "wof:placetype":"neighbourhood"
},
  "geometry": {"coordinates":[10.54584,53.58551],"type":"Point"}
}