{
  "type": "Feature",
  "properties": {
    "gn:admin1_code":"6",
    "gn:admin2_code":"0.0",
    "gn:admin3_code":"3251.0",
    "gn:admin4_code":"3251011.0",
    "gn:asciiname":"Wehrkamp",
    "gn:country_code":"DE",
    "gn:dem":43,
    "gn:feature_class":"P",
    "gn:feature_code":"PPL",
    "gn:name":"Wehrkamp",
    "gn:population":0,
    "gn:timezone":"Europe/Berlin",
    "iso:country":"DE",
    "wof:name":"Wehrkamp",
    "wof:placetype":"neighbourhood"
},
  "geometry": {"coordinates":[8.45226,52.63348000000001],"type":"Point"}
}