{
  "type": "Feature",
  "properties": {
    "gn:admin1_code":"2",
    "gn:admin2_code":"92.0",
    "gn:admin3_code":"9276.0",
    "gn:admin4_code":"9276120.0",
    "gn:asciiname":"Oberried",
    "gn:country_code":"DE",
    "gn:dem":601,
    "gn:feature_class":"P",
    "gn:feature_code":"PPL",
    "gn:name":"Oberried",
    "gn:population":0,
    "gn:timezone":"Europe/Berlin",
    "iso:country":"DE",
    "name:als_x_preferred":[
        "Oberried"
    ],
    "name:ceb_x_preferred":[
        "Oberried"
    ],
    "name:deu_x_preferred":[
        "Oberried"
    ],
    "name:epo_x_preferred":[
        "Oberried"
    ],
    "name:fra_x_preferred":[
        "Oberried"
    ],
    "name:ita_x_preferred":[
        "Oberried"
    ],
    "name:nld_x_preferred":[
        "Oberried"
    ],
    "name:pol_x_preferred":[
        "Oberried"
    ],
    "name:swe_x_preferred":[
        "Oberried"
    ],
    "wof:name":"Oberried",
    "wof:placetype":"neighbourhood"
},
  "geometry": {"coordinates":[13.04051,49.10152],"type":"Point"}
}