{
  "type": "Feature",
  "properties": {
    "gn:admin1_code":"1",
    "gn:admin2_code":"81.0",
    "gn:admin3_code":"8126.0",
    "gn:admin4_code":"8126066.0",
    "gn:asciiname":"Moglingen",
    "gn:country_code":"DE",
    "gn:dem":177,
    "gn:feature_class":"P",
    "gn:feature_code":"PPL",
    "gn:name":"M\u00f6glingen",
    "gn:population":0,
    "gn:timezone":"Europe/Berlin",
    "iso:country":"DE",
    "wof:name":"Moglingen",
    "wof:placetype":"neighbourhood"
},
  "geometry": {"coordinates":[9.43284,49.24618],"type":"Point"}
}