{
  "type": "Feature",
  "properties": {
    "gn:admin1_code":"13",
    "gn:admin2_code":"0.0",
    "gn:admin3_code":"14626.0",
    "gn:admin4_code":"14626250.0",
    "gn:asciiname":"Sagarlugk",
    "gn:country_code":"DE",
    "gn:dem":113,
    "gn:feature_class":"P",
    "gn:feature_code":"PPL",
    "gn:name":"Sagarlugk",
    "gn:population":0,
    "gn:timezone":"Europe/Berlin",
    "iso:country":"DE",
    "wof:name":"Sagarlugk",
    "wof:placetype":"neighbourhood"
},
  "geometry": {"coordinates":[14.76667,51.51667],"type":"Point"}
}