{
  "type": "Feature",
  "properties": {
    "gn:admin1_code":"11",
    "gn:admin2_code":"0.0",
    "gn:admin3_code":"12065.0",
    "gn:admin4_code":"12065256.0",
    "gn:asciiname":"Schmachtenhagen Ost",
    "gn:country_code":"DE",
    "gn:dem":55,
    "gn:feature_class":"P",
    "gn:feature_code":"PPL",
    "gn:name":"Schmachtenhagen Ost",
    "gn:population":0,
    "gn:timezone":"Europe/Berlin",
    "iso:country":"DE",
    "wof:name":"Schmachtenhagen Ost",
    "wof:placetype":"neighbourhood"
},
  "geometry": {"coordinates":[13.3476,52.75331],"type":"Point"}
}