{
  "type": "Feature",
  "properties": {
    "gn:admin1_code":"2",
    "gn:admin2_code":"91.0",
    "gn:admin3_code":"9187.0",
    "gn:admin4_code":"9187113.0",
    "gn:asciiname":"Unterratting",
    "gn:country_code":"DE",
    "gn:dem":571,
    "gn:feature_class":"P",
    "gn:feature_code":"PPL",
    "gn:name":"Unterratting",
    "gn:population":0,
    "gn:timezone":"Europe/Berlin",
    "iso:country":"DE",
    "wof:name":"Unterratting",
    "wof:placetype":"neighbourhood"
},
  "geometry": {"coordinates":[12.29767,47.97654],"type":"Point"}
}