{
  "type": "Feature",
  "properties": {
    "gn:population":1307,
    "iso:country":"DE",
    "name:ceb_x_preferred":[
        "Taufkirchen"
    ],
    "name:deu_x_preferred":[
        "Taufkirchen"
    ],
    "name:epo_x_preferred":[
        "Taufkirchen"
    ],
    "name:fra_x_preferred":[
        "Taufkirchen"
    ],
    "name:hbs_x_preferred":[
        "Taufkirchen"
    ],
    "name:hye_x_preferred":[
        "\u0539\u0561\u0578\u0582\u0586\u056f\u056b\u0580\u056d\u0565\u0576"
    ],
    "name:ita_x_preferred":[
        "Taufkirchen"
    ],
    "name:lmo_x_preferred":[
        "Taufkirchen"
    ],
    "name:nld_x_preferred":[
        "Taufkirchen"
    ],
    "name:pol_x_preferred":[
        "Taufkirchen"
    ],
    "name:ron_x_preferred":[
        "Taufkirchen"
    ],
    "name:rus_x_preferred":[
        "\u0422\u0430\u0443\u0444\u043a\u0438\u0440\u0445\u0435\u043d"
    ],
    "name:srp_x_preferred":[
        "\u0422\u0430\u0443\u0444\u043a\u0438\u0440\u0445\u0435\u043d"
    ],
    "name:zho_x_preferred":[
        "\u9676\u592b\u57fa\u5c14\u5174"
    ],
    "qs:a0":"Bundesrepublik Deutschland",
    "qs:a1":"*Bayern",
    "qs:a1r":"0",
    "qs:a2":"M\u00fchldorf a. Inn",
    "qs:adm0":"Bundesrepublik Deutschland",
    "qs:la_lc":"*",
    "qs:level":"locality",
    "qs:loc":"Taufkirchen",
    "qs:loc_alt":"Taufkirchen",
    "qs:pop":0,
    "qs:type":"buffered point",
    "wd:wordcount":32,
    "wof:lang":[
        "ger"
    ],
    "wof:name":"Taufkirchen",
    "wof:placetype":"locality",
    "wof:population":1307
},
  "geometry": {"coordinates":[12.449217,48.146733],"type":"Point"}
}