{
  "type": "Feature",
  "properties": {
    "gn:admin1_code":"14.0",
    "gn:admin2_code":"00",
    "gn:admin3_code":"15081.0",
    "gn:admin4_code":"15081135.0",
    "gn:asciiname":"Zienau",
    "gn:country_code":"DE",
    "gn:dem":52,
    "gn:feature_class":"P",
    "gn:feature_code":"PPL",
    "gn:name":"Zienau",
    "gn:population":0,
    "gn:timezone":"Europe/Berlin",
    "iso:country":"DE",
    "wof:name":"Zienau",
    "wof:placetype":"neighbourhood"
},
  "geometry": {"coordinates":[11.42747,52.51728000000001],"type":"Point"}
}