{
  "type": "Feature",
  "properties": {
    "gn:admin1_code":"11",
    "gn:admin2_code":"0.0",
    "gn:admin3_code":"12067.0",
    "gn:admin4_code":"12067493.0",
    "gn:asciiname":"Goersdorf",
    "gn:country_code":"DE",
    "gn:dem":71,
    "gn:feature_class":"P",
    "gn:feature_code":"PPL",
    "gn:name":"G\u00f6rsdorf",
    "gn:population":0,
    "gn:timezone":"Europe/Berlin",
    "iso:country":"DE",
    "wof:name":"Goersdorf",
    "wof:placetype":"neighbourhood"
},
  "geometry": {"coordinates":[14.09055,52.15106],"type":"Point"}
}