{
  "type": "Feature",
  "properties": {
    "gn:admin1_code":"2",
    "gn:admin2_code":"93.0",
    "gn:admin3_code":"9375.0",
    "gn:admin4_code":"9375148.0",
    "gn:asciiname":"Lautersee",
    "gn:country_code":"DE",
    "gn:dem":532,
    "gn:feature_class":"P",
    "gn:feature_code":"PPL",
    "gn:name":"Lautersee",
    "gn:population":0,
    "gn:timezone":"Europe/Berlin",
    "iso:country":"DE",
    "name:bar_x_preferred":[
        "Lautersee"
    ],
    "name:ceb_x_preferred":[
        "Lauter See"
    ],
    "name:dan_x_preferred":[
        "Lautersee"
    ],
    "name:deu_x_preferred":[
        "Lautersee"
    ],
    "name:nld_x_preferred":[
        "Lautersee"
    ],
    "name:spa_x_preferred":[
        "Lago Lauter"
    ],
    "name:vie_x_preferred":[
        "Lautersee"
    ],
    "wof:name":"Lautersee",
    "wof:placetype":"neighbourhood"
},
  "geometry": {"coordinates":[11.77418,48.9977],"type":"Point"}
}