{
  "type": "Feature",
  "properties": {
    "gn:admin1_code":"15",
    "gn:admin2_code":"0.0",
    "gn:admin3_code":"16073.0",
    "gn:admin4_code":"16073028.0",
    "gn:asciiname":"Sommersdorf",
    "gn:country_code":"DE",
    "gn:dem":541,
    "gn:feature_class":"P",
    "gn:feature_code":"PPL",
    "gn:name":"Sommersdorf",
    "gn:population":0,
    "gn:timezone":"Europe/Berlin",
    "iso:country":"DE",
    "name:bak_x_preferred":[
        "\u0417\u043e\u043c\u043c\u0435\u0440\u0441\u0434\u043e\u0440\u0444"
    ],
    "name:ceb_x_preferred":[
        "Sommersdorf"
    ],
    "name:deu_x_preferred":[
        "Sommersdorf"
    ],
    "name:epo_x_preferred":[
        "Sommersdorf"
    ],
    "name:fas_x_preferred":[
        "\u0633\u0648\u0645\u0631\u0633\u062f\u0648\u0631\u0641"
    ],
    "name:fra_x_preferred":[
        "Sommersdorf"
    ],
    "name:hun_x_preferred":[
        "Sommersdorf"
    ],
    "name:ita_x_preferred":[
        "Sommersdorf"
    ],
    "name:kaz_x_preferred":[
        "\u0417\u043e\u043c\u043c\u0435\u0440\u0441\u0434\u043e\u0440\u0444"
    ],
    "name:kir_x_preferred":[
        "\u0417\u043e\u043c\u043c\u0435\u0440\u0441\u0434\u043e\u0440\u0444"
    ],
    "name:mkd_x_preferred":[
        "\u0417\u043e\u043c\u0435\u0440\u0441\u0434\u043e\u0440\u0444"
    ],
    "name:msa_x_preferred":[
        "Sommersdorf"
    ],
    "name:nld_x_preferred":[
        "Sommersdorf"
    ],
    "name:pol_x_preferred":[
        "Sommersdorf"
    ],
    "name:ron_x_preferred":[
        "Sommersdorf"
    ],
    "name:rus_x_preferred":[
        "\u0417\u043e\u043c\u043c\u0435\u0440\u0441\u0434\u043e\u0440\u0444"
    ],
    "name:spa_x_preferred":[
        "Sommersdorf"
    ],
    "name:srp_x_preferred":[
        "\u0417\u043e\u043c\u0435\u0440\u0441\u0434\u043e\u0440\u0444"
    ],
    "name:ukr_x_preferred":[
        "\u0417\u043e\u043c\u043c\u0435\u0440\u0441\u0434\u043e\u0440\u0444"
    ],
    "name:uzb_x_preferred":[
        "Sommersdorf"
    ],
    "name:vie_x_preferred":[
        "Sommersdorf"
    ],
    "name:vol_x_preferred":[
        "Sommersdorf"
    ],
    "name:war_x_preferred":[
        "Sommersdorf"
    ],
    "name:zho_x_preferred":[
        "\u7d22\u9ed8\u65af\u591a\u592b"
    ],
    "wof:name":"Sommersdorf",
    "wof:placetype":"neighbourhood"
},
  "geometry": {"coordinates":[11.27295,50.52083],"type":"Point"}
}