{
  "type": "Feature",
  "properties": {
    "gn:admin1_code":"5",
    "gn:admin2_code":"65.0",
    "gn:admin3_code":"6531.0",
    "gn:admin4_code":"6531016.0",
    "gn:asciiname":"Lindenstruth",
    "gn:country_code":"DE",
    "gn:dem":226,
    "gn:feature_class":"P",
    "gn:feature_code":"PPL",
    "gn:name":"Lindenstruth",
    "gn:population":0,
    "gn:timezone":"Europe/Berlin",
    "iso:country":"DE",
    "wof:name":"Lindenstruth",
    "wof:placetype":"neighbourhood"
},
  "geometry": {"coordinates":[8.8564,50.59302],"type":"Point"}
}