{
  "type": "Feature",
  "properties": {
    "gn:country":"DE",
    "gn:fcode":"PPL",
    "gn:population":300,
    "iso:country":"DE",
    "name:bak_x_preferred":[
        "\u0412\u0430\u043d\u043d\u0435\u0444\u0435\u043b\u044c\u0434"
    ],
    "name:ceb_x_preferred":[
        "Wannefeld"
    ],
    "name:deu_x_preferred":[
        "Wannefeld"
    ],
    "name:epo_x_preferred":[
        "Wannefeld"
    ],
    "name:fas_x_preferred":[
        "\u0648\u0627\u0646\u0641\u0644\u062f"
    ],
    "name:ita_x_preferred":[
        "Wannefeld"
    ],
    "name:kaz_x_preferred":[
        "\u0412\u0430\u043d\u043d\u0435\u0444\u0435\u043b\u044c\u0434"
    ],
    "name:kir_x_preferred":[
        "\u0412\u0430\u043d\u043d\u0435\u0444\u0435\u043b\u044c\u0434"
    ],
    "name:nld_x_preferred":[
        "Wannefeld"
    ],
    "name:ron_x_preferred":[
        "Wannefeld"
    ],
    "name:rus_x_preferred":[
        "\u0412\u0430\u043d\u043d\u0435\u0444\u0435\u043b\u044c\u0434"
    ],
    "name:uzb_x_preferred":[
        "Wannefeld"
    ],
    "name:vie_x_preferred":[
        "Wannefeld"
    ],
    "name:vol_x_preferred":[
        "Wannefeld"
    ],
    "qs_pg:aaroncc":"DE",
    "qs_pg:gn_country":"DE",
    "qs_pg:gn_fcode":"PPL",
    "qs_pg:gn_pop":300,
    "qs_pg:name":"Wannefeld",
    "qs_pg:name_adm0":"Deutschland",
    "qs_pg:name_adm1":"Sachsen-Anhalt",
    "qs_pg:photos_9r":0,
    "qs_pg:photos_sr":0,
    "qs_pg:pop_sr":2,
    "qs_pg:qs_pg_placetype":"locality",
    "qs_pg:qs_pg_placetype_gp":"Town",
    "qs_pg:woe_adm0":23424829,
    "woe:adm0_id":23424829,
    "woe:name_adm0":"Deutschland",
    "woe:name_adm1":"Sachsen-Anhalt",
    "woe:placetype":"Town",
    "wof:name":"Wannefeld",
    "wof:placetype":"neighbourhood",
    "wof:population":300
},
  "geometry": {"coordinates":[11.44856,52.43862],"type":"Point"}
}