{
  "type": "Feature",
  "properties": {
    "gn:admin1_code":"6",
    "gn:admin2_code":"0.0",
    "gn:admin3_code":"3102.0",
    "gn:admin4_code":"3102000.0",
    "gn:asciiname":"Lesse",
    "gn:country_code":"DE",
    "gn:dem":100,
    "gn:feature_class":"P",
    "gn:feature_code":"PPL",
    "gn:name":"Lesse",
    "gn:population":0,
    "gn:timezone":"Europe/Berlin",
    "iso:country":"DE",
    "name:bel_x_preferred":[
        "\u041b\u0435\u0441"
    ],
    "name:cat_x_preferred":[
        "Lesse"
    ],
    "name:ceb_x_preferred":[
        "Lesse"
    ],
    "name:chv_x_preferred":[
        "\u041b\u0435\u0441"
    ],
    "name:deu_x_preferred":[
        "Lesse"
    ],
    "name:est_x_preferred":[
        "Lesse'i j\u00f5gi"
    ],
    "name:fra_x_preferred":[
        "Lesse"
    ],
    "name:hye_x_preferred":[
        "\u053c\u0565\u057d"
    ],
    "name:lit_x_preferred":[
        "Lesas"
    ],
    "name:ltz_x_preferred":[
        "Lesse"
    ],
    "name:nld_x_preferred":[
        "Lesse"
    ],
    "name:nno_x_preferred":[
        "Lesse"
    ],
    "name:por_x_preferred":[
        "Lesse"
    ],
    "name:rus_x_preferred":[
        "\u041b\u0435\u0441"
    ],
    "name:spa_x_preferred":[
        "Lesse"
    ],
    "name:swe_x_preferred":[
        "Lesse"
    ],
    "name:zho_x_preferred":[
        "\u83b1\u65af"
    ],
    "wof:name":"Lesse",
    "wof:placetype":"neighbourhood"
},
  "geometry": {"coordinates":[10.25831,52.16161],"type":"Point"}
}