{
  "type": "Feature",
  "properties": {
    "gn:admin1_code":"8",
    "gn:admin2_code":"0.0",
    "gn:admin3_code":"7232.0",
    "gn:admin4_code":"7232296.0",
    "gn:asciiname":"Tafel",
    "gn:country_code":"DE",
    "gn:dem":531,
    "gn:feature_class":"P",
    "gn:feature_code":"PPL",
    "gn:name":"Tafel",
    "gn:population":0,
    "gn:timezone":"Europe/Berlin",
    "iso:country":"DE",
    "wof:name":"Tafel",
    "wof:placetype":"neighbourhood"
},
  "geometry": {"coordinates":[6.41303,50.21782],"type":"Point"}
}