{
  "type": "Feature",
  "properties": {
    "gn:admin1_code":"6",
    "gn:admin2_code":"0.0",
    "gn:admin3_code":"3461.0",
    "gn:admin4_code":"3461004.0",
    "gn:asciiname":"Oberhoerne",
    "gn:country_code":"DE",
    "gn:dem":-2,
    "gn:feature_class":"P",
    "gn:feature_code":"PPL",
    "gn:name":"Oberh\u00f6rne",
    "gn:population":0,
    "gn:timezone":"Europe/Berlin",
    "iso:country":"DE",
    "wof:name":"Oberhoerne",
    "wof:placetype":"neighbourhood"
},
  "geometry": {"coordinates":[8.3409,53.24764],"type":"Point"}
}