{
  "type": "Feature",
  "properties": {
    "gn:admin1_code":"11",
    "gn:admin2_code":"0.0",
    "gn:admin3_code":"12062.0",
    "gn:admin4_code":"12062128.0",
    "gn:asciiname":"Kleinroessen",
    "gn:country_code":"DE",
    "gn:dem":82,
    "gn:feature_class":"P",
    "gn:feature_code":"PPL",
    "gn:name":"Kleinr\u00f6ssen",
    "gn:population":0,
    "gn:timezone":"Europe/Berlin",
    "iso:country":"DE",
    "wof:name":"Kleinroessen",
    "wof:placetype":"neighbourhood"
},
  "geometry": {"coordinates":[13.26427,51.6437],"type":"Point"}
}