{
  "type": "Feature",
  "properties": {
    "gn:admin1_code":"11",
    "gn:admin2_code":"0.0",
    "gn:admin3_code":"12073.0",
    "gn:admin4_code":"12073578.0",
    "gn:asciiname":"Falkenwalde",
    "gn:country_code":"DE",
    "gn:dem":79,
    "gn:feature_class":"P",
    "gn:feature_code":"PPL",
    "gn:name":"Falkenwalde",
    "gn:population":0,
    "gn:timezone":"Europe/Berlin",
    "iso:country":"DE",
    "wof:name":"Falkenwalde",
    "wof:placetype":"neighbourhood"
},
  "geometry": {"coordinates":[14.00542,53.26711],"type":"Point"}
}