{
  "type": "Feature",
  "properties": {
    "gn:admin1_code":"11",
    "gn:admin2_code":"0.0",
    "gn:admin3_code":"12072.0",
    "gn:admin4_code":"12072232.0",
    "gn:asciiname":"Lindenberg",
    "gn:country_code":"DE",
    "gn:dem":58,
    "gn:feature_class":"P",
    "gn:feature_code":"PPL",
    "gn:name":"Lindenberg",
    "gn:population":0,
    "gn:timezone":"Europe/Berlin",
    "iso:country":"DE",
    "name:ceb_x_preferred":[
        "Lindenberg"
    ],
    "name:deu_x_preferred":[
        "Lindenberg"
    ],
    "name:epo_x_preferred":[
        "Lindenberg"
    ],
    "name:fas_x_preferred":[
        "\u0644\u06cc\u0646\u062f\u0646\u0628\u0631\u06af"
    ],
    "name:fra_x_preferred":[
        "Lindenberg"
    ],
    "name:ita_x_preferred":[
        "Lindenberg"
    ],
    "name:lav_x_preferred":[
        "Lindenberg"
    ],
    "name:mkd_x_preferred":[
        "\u041b\u0438\u043d\u0434\u0435\u043d\u0431\u0435\u0440\u0433"
    ],
    "name:nld_x_preferred":[
        "Lindenberg"
    ],
    "name:pol_x_preferred":[
        "Lindenberg"
    ],
    "name:ron_x_preferred":[
        "Lindenberg"
    ],
    "name:rus_x_preferred":[
        "\u041b\u0438\u043d\u0434\u0435\u043d\u0431\u0435\u0440\u0433"
    ],
    "name:swe_x_preferred":[
        "Lindenberg"
    ],
    "name:vol_x_preferred":[
        "Lindenberg"
    ],
    "wof:name":"Lindenberg",
    "wof:placetype":"neighbourhood"
},
  "geometry": {"coordinates":[13.15702,52.0634],"type":"Point"}
}