{
  "type": "Feature",
  "properties": {
    "gn:admin1_code":"11",
    "gn:admin2_code":"0.0",
    "gn:admin3_code":"12063.0",
    "gn:admin4_code":"12063148.0",
    "gn:asciiname":"Tremmen",
    "gn:country_code":"DE",
    "gn:dem":35,
    "gn:feature_class":"P",
    "gn:feature_code":"PPL",
    "gn:name":"Tremmen",
    "gn:population":0,
    "gn:timezone":"Europe/Berlin",
    "iso:country":"DE",
    "name:ceb_x_preferred":[
        "Tremmen"
    ],
    "name:deu_x_preferred":[
        "Tremmen"
    ],
    "name:fas_x_preferred":[
        "\u062a\u0631\u0645\u0646"
    ],
    "wof:name":"Tremmen",
    "wof:placetype":"neighbourhood"
},
  "geometry": {"coordinates":[12.81813,52.53053000000001],"type":"Point"}
}