{
  "type": "Feature",
  "properties": {
    "gn:admin1_code":"14",
    "gn:admin2_code":"0.0",
    "gn:admin3_code":"15088.0",
    "gn:admin4_code":"15088319.0",
    "gn:asciiname":"Naundorf",
    "gn:country_code":"DE",
    "gn:dem":175,
    "gn:feature_class":"P",
    "gn:feature_code":"PPL",
    "gn:name":"Naundorf",
    "gn:population":0,
    "gn:timezone":"Europe/Berlin",
    "iso:country":"DE",
    "name:ceb_x_preferred":[
        "Naundorf"
    ],
    "name:deu_x_preferred":[
        "Naundorf"
    ],
    "name:epo_x_preferred":[
        "Naundorf"
    ],
    "name:fra_x_preferred":[
        "Naundorf"
    ],
    "name:hsb_x_preferred":[
        "Naundorf"
    ],
    "name:ita_x_preferred":[
        "Naundorf"
    ],
    "name:mkd_x_preferred":[
        "\u041d\u0430\u0443\u043d\u0434\u043e\u0440\u0444"
    ],
    "name:nld_x_preferred":[
        "Naundorf"
    ],
    "name:pol_x_preferred":[
        "Naundorf"
    ],
    "name:rus_x_preferred":[
        "\u041d\u0430\u0443\u043d\u0434\u043e\u0440\u0444"
    ],
    "name:srp_x_preferred":[
        "\u041d\u0430\u0443\u043d\u0434\u043e\u0440\u0444"
    ],
    "name:swe_x_preferred":[
        "Naundorf"
    ],
    "wof:name":"Naundorf",
    "wof:placetype":"neighbourhood"
},
  "geometry": {"coordinates":[11.73557,51.55374000000001],"type":"Point"}
}