{
  "type": "Feature",
  "properties": {
    "gn:admin1_code":"1",
    "gn:admin2_code":"83.0",
    "gn:admin3_code":"8317.0",
    "gn:admin4_code":"8317121.0",
    "gn:asciiname":"Untertal",
    "gn:country_code":"DE",
    "gn:dem":233,
    "gn:feature_class":"P",
    "gn:feature_code":"PPLL",
    "gn:name":"Untertal",
    "gn:population":0,
    "gn:timezone":"Europe/Berlin",
    "iso:country":"DE",
    "name:deu_x_preferred":[
        "Untertal"
    ],
    "wof:name":"Untertal",
    "wof:placetype":"neighbourhood"
},
  "geometry": {"coordinates":[7.9551,48.27952],"type":"Point"}
}