{
  "type": "Feature",
  "properties": {
    "gn:admin1_code":"10",
    "gn:admin2_code":"0.0",
    "gn:admin3_code":"1051.0",
    "gn:admin4_code":"1051074.0",
    "gn:asciiname":"Hesel",
    "gn:country_code":"DE",
    "gn:dem":1,
    "gn:feature_class":"P",
    "gn:feature_code":"PPL",
    "gn:name":"Hesel",
    "gn:population":0,
    "gn:timezone":"Europe/Berlin",
    "iso:country":"DE",
    "name:ceb_x_preferred":[
        "Hesel"
    ],
    "name:dan_x_preferred":[
        "Hesel"
    ],
    "name:deu_x_preferred":[
        "Hesel"
    ],
    "name:epo_x_preferred":[
        "Hesel"
    ],
    "name:est_x_preferred":[
        "Hesel"
    ],
    "name:eus_x_preferred":[
        "Hesel"
    ],
    "name:fas_x_preferred":[
        "\u0647\u0632\u0644"
    ],
    "name:fra_x_preferred":[
        "Hesel"
    ],
    "name:hun_x_preferred":[
        "Hesel"
    ],
    "name:ita_x_preferred":[
        "Hesel"
    ],
    "name:kaz_x_preferred":[
        "\u0425\u0435\u0437\u0435\u043b\u044c"
    ],
    "name:kir_x_preferred":[
        "\u0425\u0435\u0437\u0435\u043b\u044c"
    ],
    "name:lat_x_preferred":[
        "Hesel"
    ],
    "name:msa_x_preferred":[
        "Hesel"
    ],
    "name:nds_x_preferred":[
        "Hesel"
    ],
    "name:nld_x_preferred":[
        "Hesel"
    ],
    "name:pol_x_preferred":[
        "Hesel"
    ],
    "name:por_x_preferred":[
        "Hesel"
    ],
    "name:ron_x_preferred":[
        "Hesel"
    ],
    "name:rus_x_preferred":[
        "\u0425\u0435\u0437\u0435\u043b\u044c"
    ],
    "name:spa_x_preferred":[
        "Hesel"
    ],
    "name:srp_x_preferred":[
        "\u0425\u0435\u0441\u0435\u043b"
    ],
    "name:swe_x_preferred":[
        "Hesel"
    ],
    "name:ukr_x_preferred":[
        "\u0413\u0435\u0437\u0435\u043b\u044c"
    ],
    "name:uzb_x_preferred":[
        "Hesel"
    ],
    "name:vie_x_preferred":[
        "Hesel"
    ],
    "name:vol_x_preferred":[
        "Hesel"
    ],
    "name:war_x_preferred":[
        "Hesel"
    ],
    "name:zho_x_preferred":[
        "\u9ed1\u745f\u5c14"
    ],
    "wof:name":"Hesel",
    "wof:placetype":"neighbourhood"
},
  "geometry": {"coordinates":[9.10171,54.10786],"type":"Point"}
}