{
  "type": "Feature",
  "properties": {
    "gn:admin1_code":"2",
    "gn:admin2_code":"91.0",
    "gn:admin3_code":"9171.0",
    "gn:admin4_code":"9171118.0",
    "gn:asciiname":"Kemerting",
    "gn:country_code":"DE",
    "gn:dem":364,
    "gn:feature_class":"P",
    "gn:feature_code":"PPL",
    "gn:name":"Kemerting",
    "gn:population":0,
    "gn:timezone":"Europe/Berlin",
    "iso:country":"DE",
    "wof:name":"Kemerting",
    "wof:placetype":"neighbourhood"
},
  "geometry": {"coordinates":[12.85254,48.20431],"type":"Point"}
}