{
  "type": "Feature",
  "properties": {
    "gn:admin1_code":"2",
    "gn:admin2_code":"93.0",
    "gn:admin3_code":"9374.0",
    "gn:admin4_code":"9374165.0",
    "gn:asciiname":"Ottenrieth",
    "gn:country_code":"DE",
    "gn:dem":556,
    "gn:feature_class":"P",
    "gn:feature_code":"PPL",
    "gn:name":"Ottenrieth",
    "gn:population":0,
    "gn:timezone":"Europe/Berlin",
    "iso:country":"DE",
    "wof:name":"Ottenrieth",
    "wof:placetype":"neighbourhood"
},
  "geometry": {"coordinates":[12.31494,49.6844],"type":"Point"}
}