{
  "type": "Feature",
  "properties": {
    "gn:admin1_code":"13.0",
    "gn:admin2_code":"0.0",
    "gn:admin3_code":"14628.0",
    "gn:admin4_code":"14628360.0",
    "gn:asciiname":"Amtshainersdorf",
    "gn:country_code":"DE",
    "gn:dem":255,
    "gn:feature_class":"P",
    "gn:feature_code":"PPL",
    "gn:name":"Amtshainersdorf",
    "gn:population":0,
    "gn:timezone":"Europe/Berlin",
    "iso:country":"DE",
    "wof:name":"Amtshainersdorf",
    "wof:placetype":"neighbourhood"
},
  "geometry": {"coordinates":[14.23822,50.9675],"type":"Point"}
}