{
  "type": "Feature",
  "properties": {
    "gn:admin1_code":"7",
    "gn:admin2_code":"57.0",
    "gn:admin3_code":"5762.0",
    "gn:admin4_code":"5762012.0",
    "gn:asciiname":"Luetgeneder",
    "gn:country_code":"DE",
    "gn:dem":182,
    "gn:feature_class":"P",
    "gn:feature_code":"PPL",
    "gn:name":"L\u00fctgeneder",
    "gn:population":0,
    "gn:timezone":"Europe/Berlin",
    "iso:country":"DE",
    "wof:name":"Luetgeneder",
    "wof:placetype":"neighbourhood"
},
  "geometry": {"coordinates":[9.20259,51.54121],"type":"Point"}
}