{
  "type": "Feature",
  "properties": {
    "gn:admin1_code":"7.0",
    "gn:admin2_code":"059",
    "gn:admin3_code":"5958.0",
    "gn:admin4_code":"5958040.0",
    "gn:asciiname":"Werpe",
    "gn:country_code":"DE",
    "gn:dem":446,
    "gn:feature_class":"P",
    "gn:feature_code":"PPL",
    "gn:name":"Werpe",
    "gn:population":0,
    "gn:timezone":"Europe/Berlin",
    "iso:country":"DE",
    "name:deu_x_preferred":[
        "Werpe"
    ],
    "name:fas_x_preferred":[
        "\u0648\u0631\u067e\u0647"
    ],
    "wof:name":"Werpe",
    "wof:placetype":"neighbourhood"
},
  "geometry": {"coordinates":[8.25045,51.15539],"type":"Point"}
}