{
  "type": "Feature",
  "properties": {
    "gn:admin1_code":"7",
    "gn:admin2_code":"55.0",
    "gn:admin3_code":"5558.0",
    "gn:admin4_code":"5558008.0",
    "gn:asciiname":"Langenhorst",
    "gn:country_code":"DE",
    "gn:dem":91,
    "gn:feature_class":"P",
    "gn:feature_code":"PPLL",
    "gn:name":"Langenhorst",
    "gn:population":0,
    "gn:timezone":"Europe/Berlin",
    "iso:country":"DE",
    "wof:name":"Langenhorst",
    "wof:placetype":"neighbourhood"
},
  "geometry": {"coordinates":[7.36476,51.9975],"type":"Point"}
}