{
  "type": "Feature",
  "properties": {
    "gn:admin1_code":"5",
    "gn:admin2_code":"65.0",
    "gn:admin3_code":"6533.0",
    "gn:admin4_code":"6533008.0",
    "gn:asciiname":"Nauheim",
    "gn:country_code":"DE",
    "gn:dem":202,
    "gn:feature_class":"P",
    "gn:feature_code":"PPL",
    "gn:name":"Nauheim",
    "gn:population":0,
    "gn:timezone":"Europe/Berlin",
    "iso:country":"DE",
    "name:ceb_x_preferred":[
        "Nauheim"
    ],
    "name:deu_x_preferred":[
        "Nauheim"
    ],
    "name:epo_x_preferred":[
        "Nauheim"
    ],
    "name:eus_x_preferred":[
        "Nauheim"
    ],
    "name:fas_x_preferred":[
        "\u0646\u0627\u0648\u0647\u0627\u06cc\u0645"
    ],
    "name:fra_x_preferred":[
        "Nauheim"
    ],
    "name:hun_x_preferred":[
        "Nauheim"
    ],
    "name:ita_x_preferred":[
        "Nauheim"
    ],
    "name:jpn_x_preferred":[
        "\u30ca\u30a6\u30cf\u30a4\u30e0"
    ],
    "name:kaz_x_preferred":[
        "\u041d\u0430\u0443\u0445\u0430\u0439\u043c"
    ],
    "name:kir_x_preferred":[
        "\u041d\u0430\u0443\u0445\u0430\u0439\u043c"
    ],
    "name:msa_x_preferred":[
        "Nauheim"
    ],
    "name:nld_x_preferred":[
        "Nauheim"
    ],
    "name:pol_x_preferred":[
        "Nauheim"
    ],
    "name:ron_x_preferred":[
        "Nauheim"
    ],
    "name:rus_x_preferred":[
        "\u041d\u0430\u0443\u0445\u0430\u0439\u043c"
    ],
    "name:spa_x_preferred":[
        "Nauheim"
    ],
    "name:srp_x_preferred":[
        "\u041d\u0430\u0443\u0445\u0430\u0458\u043c"
    ],
    "name:ukr_x_preferred":[
        "\u041d\u0430\u0443\u0433\u0430\u0439\u043c"
    ],
    "name:uzb_x_preferred":[
        "Nauheim"
    ],
    "name:vol_x_preferred":[
        "Nauheim"
    ],
    "name:war_x_preferred":[
        "Nauheim"
    ],
    "name:zho_x_preferred":[
        "\u7459\u6d77\u59c6"
    ],
    "wof:name":"Nauheim",
    "wof:placetype":"neighbourhood"
},
  "geometry": {"coordinates":[8.13625,50.34469],"type":"Point"}
}