{
  "type": "Feature",
  "properties": {
    "gn:gn_country":"DE",
    "gn:gn_fcode":"PPLA4",
    "gn:gn_pop":531,
    "gn:population":531,
    "iso:country":"DE",
    "name:baq_x_preferred":[
        "Rascheid"
    ],
    "name:dut_x_preferred":[
        "Rascheid"
    ],
    "name:eng_x_preferred":[
        "Rascheid"
    ],
    "name:epo_x_preferred":[
        "Rascheid"
    ],
    "name:fre_x_preferred":[
        "Rascheid"
    ],
    "name:ger_x_preferred":[
        "Rascheid"
    ],
    "name:hun_x_preferred":[
        "Rascheid"
    ],
    "name:ita_x_preferred":[
        "Rascheid"
    ],
    "name:jpn_x_preferred":[
        "\u30e9\u30b7\u30e3\u30a4\u30c8"
    ],
    "name:kaz_x_preferred":[
        "\u0420\u0430\u0448\u0430\u0439\u0434"
    ],
    "name:kir_x_preferred":[
        "\u0420\u0430\u0448\u0430\u0439\u0434"
    ],
    "name:may_x_preferred":[
        "Rascheid"
    ],
    "name:per_x_preferred":[
        "\u0631\u0627\u0634\u0627\u06cc\u062f"
    ],
    "name:pol_x_preferred":[
        "Rascheid"
    ],
    "name:por_x_preferred":[
        "Rascheid"
    ],
    "name:rum_x_preferred":[
        "Rascheid"
    ],
    "name:rus_x_preferred":[
        "\u0420\u0430\u0448\u0430\u0439\u0434"
    ],
    "name:srp_x_preferred":[
        "\u0420\u0430\u0448\u0430\u0458\u0434"
    ],
    "name:ukr_x_preferred":[
        "\u0420\u0430\u0448\u0430\u0439\u0434"
    ],
    "name:uzb_x_preferred":[
        "Rascheid"
    ],
    "name:vie_x_preferred":[
        "Rascheid"
    ],
    "name:vol_x_preferred":[
        "Rascheid"
    ],
    "name:war_x_preferred":[
        "Rascheid"
    ],
    "qs_pg:aaroncc":"DE",
    "qs_pg:gn_country":"DE",
    "qs_pg:gn_fcode":"PPLA4",
    "qs_pg:gn_pop":531,
    "qs_pg:name":"Rascheid",
    "qs_pg:photos_9r":0,
    "qs_pg:photos_sr":0,
    "qs_pg:pop_sr":2,
    "qs_pg:qs_pg_placetype":"locality",
    "wof:name":"Rascheid",
    "wof:placetype":"locality",
    "wof:population":531
},
  "geometry": {"coordinates":[6.93333,49.71667],"type":"Point"}
}