{
  "type": "Feature",
  "properties": {
    "gn:admin1_code":"1.0",
    "gn:admin2_code":"81.0",
    "gn:admin3_code":"8136.0",
    "gn:admin4_code":"8136088.0",
    "gn:asciiname":"Arlesberg",
    "gn:country_code":"DE",
    "gn:dem":625,
    "gn:feature_class":"P",
    "gn:feature_code":"PPL",
    "gn:name":"Arlesberg",
    "gn:population":0,
    "gn:timezone":"Europe/Berlin",
    "iso:country":"DE",
    "wof:name":"Arlesberg",
    "wof:placetype":"neighbourhood"
},
  "geometry": {"coordinates":[10.19184,48.84871],"type":"Point"}
}