{
  "type": "Feature",
  "properties": {
    "gn:admin1_code":"13.0",
    "gn:admin2_code":"0.0",
    "gn:admin3_code":"14521.0",
    "gn:admin4_code":"14521170.0",
    "gn:asciiname":"Blauenthal",
    "gn:country_code":"DE",
    "gn:dem":489,
    "gn:feature_class":"P",
    "gn:feature_code":"PPL",
    "gn:name":"Blauenthal",
    "gn:population":0,
    "gn:timezone":"Europe/Berlin",
    "iso:country":"DE",
    "wof:name":"Blauenthal",
    "wof:placetype":"neighbourhood"
},
  "geometry": {"coordinates":[12.6263,50.51211],"type":"Point"}
}