{
  "type": "Feature",
  "properties": {
    "gn:admin1_code":"12",
    "gn:admin2_code":"0.0",
    "gn:admin3_code":"13076.0",
    "gn:admin4_code":"13076121.0",
    "gn:asciiname":"Muehlenbeck",
    "gn:country_code":"DE",
    "gn:dem":47,
    "gn:feature_class":"P",
    "gn:feature_code":"PPL",
    "gn:name":"M\u00fchlenbeck",
    "gn:population":0,
    "gn:timezone":"Europe/Berlin",
    "iso:country":"DE",
    "wof:name":"Muehlenbeck",
    "wof:placetype":"neighbourhood"
},
  "geometry": {"coordinates":[11.24979,53.52611],"type":"Point"}
}