{
  "type": "Feature",
  "properties": {
    "gn:admin1_code":"2",
    "gn:admin2_code":"91.0",
    "gn:admin3_code":"9173.0",
    "gn:admin4_code":"9173131.0",
    "gn:asciiname":"Petern",
    "gn:country_code":"DE",
    "gn:dem":729,
    "gn:feature_class":"P",
    "gn:feature_code":"PPL",
    "gn:name":"Petern",
    "gn:population":0,
    "gn:timezone":"Europe/Berlin",
    "iso:country":"DE",
    "wof:name":"Petern",
    "wof:placetype":"neighbourhood"
},
  "geometry": {"coordinates":[11.50344,47.61375],"type":"Point"}
}