{
  "type": "Feature",
  "properties": {
    "gn:admin1_code":"8",
    "gn:admin2_code":"0.0",
    "gn:admin3_code":"7335.0",
    "gn:admin4_code":"7335043.0",
    "gn:asciiname":"Poerrbach",
    "gn:country_code":"DE",
    "gn:dem":274,
    "gn:feature_class":"P",
    "gn:feature_code":"PPL",
    "gn:name":"P\u00f6rrbach",
    "gn:population":0,
    "gn:timezone":"Europe/Berlin",
    "iso:country":"DE",
    "wof:name":"Poerrbach",
    "wof:placetype":"neighbourhood"
},
  "geometry": {"coordinates":[7.59746,49.50628],"type":"Point"}
}