{
  "type": "Feature",
  "properties": {
    "gn:admin1_code":"15",
    "gn:admin2_code":"0.0",
    "gn:admin3_code":"16077.0",
    "gn:admin4_code":"16077043.0",
    "gn:asciiname":"Grossstoebnitz",
    "gn:country_code":"DE",
    "gn:dem":200,
    "gn:feature_class":"P",
    "gn:feature_code":"PPL",
    "gn:name":"Gro\u00dfst\u00f6bnitz",
    "gn:population":0,
    "gn:timezone":"Europe/Berlin",
    "iso:country":"DE",
    "wof:name":"Grossstoebnitz",
    "wof:placetype":"neighbourhood"
},
  "geometry": {"coordinates":[12.38832,50.92156],"type":"Point"}
}