{
  "type": "Feature",
  "properties": {
    "gn:admin1_code":"6",
    "gn:admin2_code":"0.0",
    "gn:admin3_code":"3151.0",
    "gn:admin4_code":"3151008.0",
    "gn:asciiname":"Lessien",
    "gn:country_code":"DE",
    "gn:dem":74,
    "gn:feature_class":"P",
    "gn:feature_code":"PPL",
    "gn:name":"Lessien",
    "gn:population":0,
    "gn:timezone":"Europe/Berlin",
    "iso:country":"DE",
    "wof:name":"Lessien",
    "wof:placetype":"neighbourhood"
},
  "geometry": {"coordinates":[10.75656,52.56873],"type":"Point"}
}