{
  "type": "Feature",
  "properties": {
    "gn:admin1_code":"15",
    "gn:admin2_code":"0.0",
    "gn:admin3_code":"16062.0",
    "gn:admin4_code":"16062063.0",
    "gn:asciiname":"Grosswechsungen",
    "gn:country_code":"DE",
    "gn:dem":201,
    "gn:feature_class":"P",
    "gn:feature_code":"PPL",
    "gn:name":"Gro\u00dfwechsungen",
    "gn:population":0,
    "gn:timezone":"Europe/Berlin",
    "iso:country":"DE",
    "name:und_x_variant":[
        "Gro\u00dfwechsungen"
    ],
    "wof:name":"Grosswechsungen",
    "wof:placetype":"neighbourhood"
},
  "geometry": {"coordinates":[10.69008,51.49263],"type":"Point"}
}