{
  "type": "Feature",
  "properties": {
    "gn:admin1_code":"10",
    "gn:admin2_code":"0.0",
    "gn:admin3_code":"1059.0",
    "gn:admin4_code":"1059005.0",
    "gn:asciiname":"Kleinsee",
    "gn:country_code":"DE",
    "gn:dem":-4,
    "gn:feature_class":"P",
    "gn:feature_code":"PPL",
    "gn:name":"Kleinsee",
    "gn:population":0,
    "gn:timezone":"Europe/Berlin",
    "iso:country":"DE",
    "name:deu_x_preferred":[
        "Kleinsee"
    ],
    "wof:name":"Kleinsee",
    "wof:placetype":"neighbourhood"
},
  "geometry": {"coordinates":[9.33333,54.38333000000001],"type":"Point"}
}