{
  "type": "Feature",
  "properties": {
    "gn:admin1_code":"2.0",
    "gn:admin2_code":"091",
    "gn:admin3_code":"9173.0",
    "gn:admin4_code":"9173135.0",
    "gn:asciiname":"Winkel",
    "gn:country_code":"DE",
    "gn:dem":718,
    "gn:feature_class":"P",
    "gn:feature_code":"PPL",
    "gn:name":"Winkel",
    "gn:population":0,
    "gn:timezone":"Europe/Berlin",
    "iso:country":"DE",
    "wof:name":"Winkel",
    "wof:placetype":"neighbourhood"
},
  "geometry": {"coordinates":[11.59908,47.63856],"type":"Point"}
}