{
  "type": "Feature",
  "properties": {
    "iso:country":"DE",
    "name:deu_x_preferred":[
        "Rumeln"
    ],
    "name:unk_x_variant":[
        "Rumeln"
    ],
    "qs:gn_adm0_cc":"DE",
    "qs:gn_local":2934691,
    "qs:local_max":4851,
    "qs:local_sum":11005,
    "qs:localhoods":24,
    "qs:name":"Rumeln",
    "qs:name_adm0":"Deutschland",
    "qs:name_adm1":"Nordrhein-Westfalen",
    "qs:name_adm2":"Stadtkreis Duisburg",
    "qs:name_lau":"Rumeln-Kaldenhausen",
    "qs:name_local":"Duisburg",
    "qs:photo_max":56,
    "qs:photo_sum":81,
    "qs:placetype":"Suburb",
    "qs:quad_count":9,
    "qs:woe_adm0":23424829,
    "qs:woe_adm1":2345487,
    "qs:woe_adm2":12596956,
    "qs:woe_lau":26822245,
    "qs:woe_local":645877,
    "qs:woe_ver":"7.10.0",
    "wof:lang":[
        "ger"
    ],
    "wof:name":"Rumeln",
    "wof:placetype":"neighbourhood"
},
  "geometry": {"coordinates":[6.667677,51.400287],"type":"Point"}
}