{
  "type": "Feature",
  "properties": {
    "gn:admin1_code":"15",
    "gn:admin2_code":"0.0",
    "gn:admin3_code":"16064.0",
    "gn:admin4_code":"16064074.0",
    "gn:asciiname":"Gute Hoffnung",
    "gn:country_code":"DE",
    "gn:dem":440,
    "gn:feature_class":"P",
    "gn:feature_code":"PPL",
    "gn:name":"Gute Hoffnung",
    "gn:population":0,
    "gn:timezone":"Europe/Berlin",
    "iso:country":"DE",
    "wof:name":"Gute Hoffnung",
    "wof:placetype":"neighbourhood"
},
  "geometry": {"coordinates":[10.28333,51.15],"type":"Point"}
}