{
  "type": "Feature",
  "properties": {
    "gn:admin1_code":"2",
    "gn:admin2_code":"94.0",
    "gn:admin3_code":"9462.0",
    "gn:admin4_code":"9462000.0",
    "gn:asciiname":"Schupfenschlag",
    "gn:country_code":"DE",
    "gn:dem":381,
    "gn:feature_class":"P",
    "gn:feature_code":"PPL",
    "gn:name":"Schupfenschlag",
    "gn:population":0,
    "gn:timezone":"Europe/Berlin",
    "iso:country":"DE",
    "wof:name":"Schupfenschlag",
    "wof:placetype":"neighbourhood"
},
  "geometry": {"coordinates":[11.59333,49.97259],"type":"Point"}
}