{
  "type": "Feature",
  "properties": {
    "gn:admin1_code":"1",
    "gn:admin2_code":"81.0",
    "gn:admin3_code":"8117.0",
    "gn:admin4_code":"8117016.0",
    "gn:asciiname":"Unterdrackenstein",
    "gn:country_code":"DE",
    "gn:dem":644,
    "gn:feature_class":"P",
    "gn:feature_code":"PPL",
    "gn:name":"Unterdrackenstein",
    "gn:population":0,
    "gn:timezone":"Europe/Berlin",
    "iso:country":"DE",
    "wof:name":"Unterdrackenstein",
    "wof:placetype":"neighbourhood"
},
  "geometry": {"coordinates":[9.66827,48.55856],"type":"Point"}
}