{
  "type": "Feature",
  "properties": {
    "gn:admin1_code":"6",
    "gn:admin2_code":"0.0",
    "gn:admin3_code":"3251.0",
    "gn:admin4_code":"3251037.0",
    "gn:asciiname":"Lehmkuhl",
    "gn:country_code":"DE",
    "gn:dem":14,
    "gn:feature_class":"P",
    "gn:feature_code":"PPL",
    "gn:name":"Lehmkuhl",
    "gn:population":0,
    "gn:timezone":"Europe/Berlin",
    "iso:country":"DE",
    "wof:name":"Lehmkuhl",
    "wof:placetype":"neighbourhood"
},
  "geometry": {"coordinates":[8.68985,52.97747],"type":"Point"}
}