{
  "type": "Feature",
  "properties": {
    "gn:admin1_code":"1.0",
    "gn:admin2_code":"081",
    "gn:admin3_code":"8128.0",
    "gn:admin4_code":"8128039.0",
    "gn:asciiname":"Wessental",
    "gn:country_code":"DE",
    "gn:dem":241,
    "gn:feature_class":"P",
    "gn:feature_code":"PPL",
    "gn:name":"Wessental",
    "gn:population":0,
    "gn:timezone":"Europe/Berlin",
    "iso:country":"DE",
    "name:und_x_variant":[
        "Wessenthal",
        "Wessental"
    ],
    "wof:name":"Wessental",
    "wof:placetype":"neighbourhood"
},
  "geometry": {"coordinates":[9.41141,49.73014000000001],"type":"Point"}
}