{
  "type": "Feature",
  "properties": {
    "iso:country":"DE",
    "name:ceb_x_preferred":[
        "Ekel"
    ],
    "name:deu_x_preferred":[
        "Ekel"
    ],
    "name:swe_x_preferred":[
        "Ekel"
    ],
    "wof:name":"Ekel",
    "wof:placetype":"neighbourhood"
},
  "geometry": {"coordinates":[6.93163134103215,51.62833468033314],"type":"Point"}
}