{
  "type": "Feature",
  "properties": {
    "gn:admin1_code":"7.0",
    "gn:admin2_code":"57.0",
    "gn:admin3_code":"5766.0",
    "gn:admin4_code":"5766020.0",
    "gn:asciiname":"Barkhausen",
    "gn:country_code":"DE",
    "gn:dem":207,
    "gn:feature_class":"P",
    "gn:feature_code":"PPL",
    "gn:name":"Barkhausen",
    "gn:population":0,
    "gn:timezone":"Europe/Berlin",
    "iso:country":"DE",
    "name:deu_x_preferred":[
        "Barkhausen"
    ],
    "name:nds_x_preferred":[
        "Barkhausen"
    ],
    "name:nld_x_preferred":[
        "Barkhausen"
    ],
    "name:rus_x_preferred":[
        "\u0411\u0430\u0440\u043a\u0433\u0430\u0443\u0437\u0435\u043d"
    ],
    "wof:name":"Barkhausen",
    "wof:placetype":"neighbourhood"
},
  "geometry": {"coordinates":[8.93317,51.97484],"type":"Point"}
}