{
  "type": "Feature",
  "properties": {
    "gn:admin1_code":"13",
    "gn:admin2_code":"0.0",
    "gn:admin3_code":"14729.0",
    "gn:admin4_code":"14729245.0",
    "gn:asciiname":"Frauwalde",
    "gn:country_code":"DE",
    "gn:dem":146,
    "gn:feature_class":"P",
    "gn:feature_code":"PPL",
    "gn:name":"Frauwalde",
    "gn:population":0,
    "gn:timezone":"Europe/Berlin",
    "iso:country":"DE",
    "wof:name":"Frauwalde",
    "wof:placetype":"neighbourhood"
},
  "geometry": {"coordinates":[12.92336,51.40317],"type":"Point"}
}