{
  "type": "Feature",
  "properties": {
    "gn:admin1_code":"6",
    "gn:admin2_code":"0.0",
    "gn:admin3_code":"3241.0",
    "gn:admin4_code":"3241010.0",
    "gn:asciiname":"Brink",
    "gn:country_code":"DE",
    "gn:dem":55,
    "gn:feature_class":"P",
    "gn:feature_code":"PPL",
    "gn:name":"Brink",
    "gn:population":0,
    "gn:timezone":"Europe/Berlin",
    "iso:country":"DE",
    "name:deu_x_preferred":[
        "Brink"
    ],
    "name:fin_x_preferred":[
        "Brink"
    ],
    "name:fra_x_preferred":[
        "Brink"
    ],
    "name:nds_x_preferred":[
        "Brink"
    ],
    "name:nld_x_preferred":[
        "Brink"
    ],
    "name:pol_x_preferred":[
        "Brink"
    ],
    "name:rus_x_preferred":[
        "\u0411\u0440\u0438\u043d\u043a"
    ],
    "name:swe_x_preferred":[
        "Brink"
    ],
    "wof:name":"Brink",
    "wof:placetype":"neighbourhood"
},
  "geometry": {"coordinates":[9.73333,52.43333000000001],"type":"Point"}
}