{
  "type": "Feature",
  "properties": {
    "gn:gn_country":"DE",
    "gn:gn_fcode":"PPLA4",
    "gn:gn_pop":144,
    "gn:population":144,
    "iso:country":"DE",
    "name:baq_x_preferred":[
        "Welkenbach"
    ],
    "name:chi_x_preferred":[
        "\u97e6\u5c14\u80af\u5df4\u8d6b"
    ],
    "name:dut_x_preferred":[
        "Welkenbach"
    ],
    "name:eng_x_preferred":[
        "Welkenbach"
    ],
    "name:epo_x_preferred":[
        "Welkenbach"
    ],
    "name:fre_x_preferred":[
        "Welkenbach"
    ],
    "name:ger_x_preferred":[
        "Welkenbach"
    ],
    "name:hun_x_preferred":[
        "Welkenbach"
    ],
    "name:ita_x_preferred":[
        "Welkenbach"
    ],
    "name:jpn_x_preferred":[
        "\u30f4\u30a7\u30eb\u30b1\u30f3\u30d0\u30c3\u30cf"
    ],
    "name:kaz_x_preferred":[
        "\u0412\u0435\u043b\u044c\u043a\u0435\u043d\u0431\u0430\u0445"
    ],
    "name:kir_x_preferred":[
        "\u0412\u0435\u043b\u044c\u043a\u0435\u043d\u0431\u0430\u0445"
    ],
    "name:may_x_preferred":[
        "Welkenbach"
    ],
    "name:per_x_preferred":[
        "\u0648\u0644\u06a9\u0646\u0628\u0627\u062e"
    ],
    "name:pol_x_preferred":[
        "Welkenbach"
    ],
    "name:por_x_preferred":[
        "Welkenbach"
    ],
    "name:rum_x_preferred":[
        "Welkenbach"
    ],
    "name:rus_x_preferred":[
        "\u0412\u0435\u043b\u044c\u043a\u0435\u043d\u0431\u0430\u0445"
    ],
    "name:srp_x_preferred":[
        "\u0412\u0435\u043b\u043a\u0435\u043d\u0431\u0430\u0445"
    ],
    "name:ukr_x_preferred":[
        "\u0412\u0435\u043b\u044c\u043a\u0435\u043d\u0431\u0430\u0445"
    ],
    "name:uzb_x_preferred":[
        "Welkenbach"
    ],
    "name:vie_x_preferred":[
        "Welkenbach"
    ],
    "name:vol_x_preferred":[
        "Welkenbach"
    ],
    "name:war_x_preferred":[
        "Welkenbach"
    ],
    "qs_pg:aaroncc":"DE",
    "qs_pg:gn_country":"DE",
    "qs_pg:gn_fcode":"PPLA4",
    "qs_pg:gn_pop":144,
    "qs_pg:name":"Welkenbach",
    "qs_pg:photos_9r":0,
    "qs_pg:photos_sr":0,
    "qs_pg:pop_sr":1,
    "qs_pg:qs_pg_placetype":"locality",
    "wof:name":"Welkenbach",
    "wof:placetype":"locality",
    "wof:population":144
},
  "geometry": {"coordinates":[7.73333,50.63333],"type":"Point"}
}