{
  "type": "Feature",
  "properties": {
    "gn:admin1_code":"5.0",
    "gn:admin2_code":"65.0",
    "gn:admin3_code":"6532.0",
    "gn:admin4_code":"6532006.0",
    "gn:asciiname":"Beilstein",
    "gn:country_code":"DE",
    "gn:dem":306,
    "gn:feature_class":"P",
    "gn:feature_code":"PPL",
    "gn:name":"Beilstein",
    "gn:population":0,
    "gn:timezone":"Europe/Berlin",
    "iso:country":"DE",
    "name:ceb_x_preferred":[
        "Beilstein"
    ],
    "name:deu_x_preferred":[
        "Beilstein"
    ],
    "name:epo_x_preferred":[
        "Beilstein"
    ],
    "name:fra_x_preferred":[
        "Beilstein"
    ],
    "name:hun_x_preferred":[
        "Beilstein"
    ],
    "name:ita_x_preferred":[
        "Beilstein"
    ],
    "name:jpn_x_preferred":[
        "\u30d0\u30a4\u30eb\u30b7\u30e5\u30bf\u30a4\u30f3"
    ],
    "name:nld_x_preferred":[
        "Beilstein"
    ],
    "name:pol_x_preferred":[
        "Beilstein"
    ],
    "name:rus_x_preferred":[
        "\u0411\u0430\u0439\u043b\u044c\u0448\u0442\u0430\u0439\u043d"
    ],
    "name:srp_x_preferred":[
        "\u0411\u0430\u0458\u043b\u0448\u0442\u0430\u0458\u043d"
    ],
    "name:swe_x_preferred":[
        "Beilstein"
    ],
    "name:vol_x_preferred":[
        "Beilstein"
    ],
    "wof:name":"Beilstein",
    "wof:placetype":"neighbourhood"
},
  "geometry": {"coordinates":[8.35069,50.74796],"type":"Point"}
}