{
  "type": "Feature",
  "properties": {
    "gn:admin1_code":"11.0",
    "gn:admin2_code":"00",
    "gn:admin3_code":"12071.0",
    "gn:admin4_code":"12071392.0",
    "gn:asciiname":"Wolfshain",
    "gn:country_code":"DE",
    "gn:dem":133,
    "gn:feature_class":"P",
    "gn:feature_code":"PPL",
    "gn:name":"Wolfshain",
    "gn:population":0,
    "gn:timezone":"Europe/Berlin",
    "iso:country":"DE",
    "wof:name":"Wolfshain",
    "wof:placetype":"neighbourhood"
},
  "geometry": {"coordinates":[14.58896,51.57989],"type":"Point"}
}