{
  "type": "Feature",
  "properties": {
    "gn:admin1_code":"2",
    "gn:admin2_code":"92.0",
    "gn:admin3_code":"9271.0",
    "gn:admin4_code":"9271122.0",
    "gn:asciiname":"Horpolding",
    "gn:country_code":"DE",
    "gn:dem":438,
    "gn:feature_class":"P",
    "gn:feature_code":"PPL",
    "gn:name":"H\u00f6rpolding",
    "gn:population":0,
    "gn:timezone":"Europe/Berlin",
    "iso:country":"DE",
    "name:und_x_variant":[
        "Hieberding",
        "H\u00f6rpolting",
        "H\u00f6rpolding"
    ],
    "wof:name":"Horpolding",
    "wof:placetype":"neighbourhood"
},
  "geometry": {"coordinates":[12.94661,48.87699],"type":"Point"}
}