{
  "type": "Feature",
  "properties": {
    "gn:admin1_code":"1",
    "gn:admin2_code":"83.0",
    "gn:admin3_code":"8316.0",
    "gn:admin4_code":"8316014.0",
    "gn:asciiname":"Mussbach",
    "gn:country_code":"DE",
    "gn:dem":382,
    "gn:feature_class":"P",
    "gn:feature_code":"PPL",
    "gn:name":"Mu\u00dfbach",
    "gn:population":0,
    "gn:timezone":"Europe/Berlin",
    "iso:country":"DE",
    "wof:name":"Mussbach",
    "wof:placetype":"neighbourhood"
},
  "geometry": {"coordinates":[7.97572,48.12751],"type":"Point"}
}