{
  "type": "Feature",
  "properties": {
    "gn:admin1_code":"11.0",
    "gn:admin2_code":"00",
    "gn:admin3_code":"12071.0",
    "gn:admin4_code":"12071244.0",
    "gn:asciiname":"Wiesendorf",
    "gn:country_code":"DE",
    "gn:dem":66,
    "gn:feature_class":"P",
    "gn:feature_code":"PPL",
    "gn:name":"Wiesendorf",
    "gn:population":0,
    "gn:timezone":"Europe/Berlin",
    "iso:country":"DE",
    "name:dsb_x_preferred":[
        "Nase\u0144ce"
    ],
    "wof:name":"Wiesendorf",
    "wof:placetype":"neighbourhood"
},
  "geometry": {"coordinates":[14.14724,51.7291],"type":"Point"}
}