{
  "type": "Feature",
  "properties": {
    "gn:admin1_code":"13",
    "gn:admin2_code":"0.0",
    "gn:admin3_code":"14612.0",
    "gn:admin4_code":"14612000.0",
    "gn:asciiname":"Doelzschen",
    "gn:country_code":"DE",
    "gn:dem":225,
    "gn:feature_class":"P",
    "gn:feature_code":"PPL",
    "gn:name":"D\u00f6lzschen",
    "gn:population":0,
    "gn:timezone":"Europe/Berlin",
    "iso:country":"DE",
    "name:deu_x_colloquial":[
        "Doelzschen",
        "Dolzschen"
    ],
    "name:deu_x_preferred":[
        "D\u00f6lzschen"
    ],
    "name:eng_x_preferred":[
        "D\u00f6lzschen"
    ],
    "qs:gn_local":0,
    "qs:local_max":13108,
    "qs:local_sum":52556,
    "qs:localhoods":61,
    "qs:name":"D\u00f6lzschen",
    "qs:name_adm0":"Deutschland",
    "qs:name_adm1":"Sachsen",
    "qs:name_adm2":"Kreisfreie Stadt Dresden",
    "qs:name_lau":"Stadtteil Plauen",
    "qs:name_local":"Dresden",
    "qs:photo_max":6,
    "qs:photo_sum":17,
    "qs:placetype":"Suburb",
    "qs:quad_count":6,
    "qs:woe_adm0":23424829,
    "qs:woe_adm1":2345493,
    "qs:woe_adm2":12596943,
    "qs:woe_lau":26822144,
    "qs:woe_local":645686,
    "qs:woe_ver":"7.10.0",
    "wof:lang":[
        "ger"
    ],
    "wof:name":"Doelzschen",
    "wof:placetype":"neighbourhood"
},
  "geometry": {"coordinates":[13.685831,51.02443],"type":"Point"}
}