{
  "type": "Feature",
  "properties": {
    "gn:admin1_code":"5",
    "gn:admin2_code":"64.0",
    "gn:admin3_code":"6440.0",
    "gn:admin4_code":"6440007.0",
    "gn:asciiname":"Oberflorstadt",
    "gn:country_code":"DE",
    "gn:dem":131,
    "gn:feature_class":"P",
    "gn:feature_code":"PPL",
    "gn:name":"Oberflorstadt",
    "gn:population":0,
    "gn:timezone":"Europe/Berlin",
    "iso:country":"DE",
    "wof:name":"Oberflorstadt",
    "wof:placetype":"neighbourhood"
},
  "geometry": {"coordinates":[8.87474,50.32585],"type":"Point"}
}