{
  "type": "Feature",
  "properties": {
    "gn:admin1_code":"1.0",
    "gn:admin2_code":"81.0",
    "gn:admin3_code":"8127.0",
    "gn:admin4_code":"8127101.0",
    "gn:asciiname":"Bergertshofen",
    "gn:country_code":"DE",
    "gn:dem":460,
    "gn:feature_class":"P",
    "gn:feature_code":"PPL",
    "gn:name":"Bergertshofen",
    "gn:population":0,
    "gn:timezone":"Europe/Berlin",
    "iso:country":"DE",
    "wof:name":"Bergertshofen",
    "wof:placetype":"neighbourhood"
},
  "geometry": {"coordinates":[10.21356,49.15392],"type":"Point"}
}