{
  "type": "Feature",
  "properties": {
    "gn:admin1_code":"1",
    "gn:admin2_code":"83.0",
    "gn:admin3_code":"8315.0",
    "gn:admin4_code":"8315102.0",
    "gn:asciiname":"Oberschwarzhalden",
    "gn:country_code":"DE",
    "gn:dem":929,
    "gn:feature_class":"P",
    "gn:feature_code":"PPL",
    "gn:name":"Oberschwarzhalden",
    "gn:population":0,
    "gn:timezone":"Europe/Berlin",
    "iso:country":"DE",
    "wof:name":"Oberschwarzhalden",
    "wof:placetype":"neighbourhood"
},
  "geometry": {"coordinates":[8.18489,47.7877],"type":"Point"}
}