{
  "type": "Feature",
  "properties": {
    "gn:admin1_code":"2",
    "gn:admin2_code":"95.0",
    "gn:admin3_code":"9574.0",
    "gn:admin4_code":"9574160.0",
    "gn:asciiname":"Lunkenreuth",
    "gn:country_code":"DE",
    "gn:dem":453,
    "gn:feature_class":"P",
    "gn:feature_code":"PPL",
    "gn:name":"Lunkenreuth",
    "gn:population":0,
    "gn:timezone":"Europe/Berlin",
    "iso:country":"DE",
    "wof:name":"Lunkenreuth",
    "wof:placetype":"neighbourhood"
},
  "geometry": {"coordinates":[11.48333,49.63333],"type":"Point"}
}