{
  "type": "Feature",
  "properties": {
    "gn:admin1_code":"2",
    "gn:admin2_code":"96.0",
    "gn:admin3_code":"9671.0",
    "gn:admin4_code":"9671143.0",
    "gn:asciiname":"Molkenberg",
    "gn:country_code":"DE",
    "gn:dem":341,
    "gn:feature_class":"P",
    "gn:feature_code":"PPL",
    "gn:name":"Molkenberg",
    "gn:population":0,
    "gn:timezone":"Europe/Berlin",
    "iso:country":"DE",
    "wof:name":"Molkenberg",
    "wof:placetype":"neighbourhood"
},
  "geometry": {"coordinates":[9.12703,50.0647],"type":"Point"}
}