{
  "type": "Feature",
  "properties": {
    "gn:admin1_code":"1",
    "gn:admin2_code":"81.0",
    "gn:admin3_code":"8127.0",
    "gn:admin4_code":"8127014.0",
    "gn:asciiname":"Eichelberg",
    "gn:country_code":"DE",
    "gn:dem":426,
    "gn:feature_class":"P",
    "gn:feature_code":"PPL",
    "gn:name":"Eichelberg",
    "gn:population":0,
    "gn:timezone":"Europe/Berlin",
    "iso:country":"DE",
    "wof:name":"Eichelberg",
    "wof:placetype":"neighbourhood"
},
  "geometry": {"coordinates":[10.08408,49.08736],"type":"Point"}
}