{
  "type": "Feature",
  "properties": {
    "gn:admin1_code":"7",
    "gn:admin2_code":"59.0",
    "gn:admin3_code":"5974.0",
    "gn:admin4_code":"5974004.0",
    "gn:asciiname":"Robringhausen",
    "gn:country_code":"DE",
    "gn:dem":183,
    "gn:feature_class":"P",
    "gn:feature_code":"PPL",
    "gn:name":"Robringhausen",
    "gn:population":0,
    "gn:timezone":"Europe/Berlin",
    "iso:country":"DE",
    "wof:name":"Robringhausen",
    "wof:placetype":"neighbourhood"
},
  "geometry": {"coordinates":[8.27214,51.55614],"type":"Point"}
}