{
  "type": "Feature",
  "properties": {
    "gn:admin1_code":"2",
    "gn:admin2_code":"93.0",
    "gn:admin3_code":"9373.0",
    "gn:admin4_code":"9373151.0",
    "gn:asciiname":"Grunstaude",
    "gn:country_code":"DE",
    "gn:dem":557,
    "gn:feature_class":"P",
    "gn:feature_code":"PPL",
    "gn:name":"Gr\u00fcnstaude",
    "gn:population":0,
    "gn:timezone":"Europe/Berlin",
    "iso:country":"DE",
    "wof:name":"Grunstaude",
    "wof:placetype":"neighbourhood"
},
  "geometry": {"coordinates":[11.74181,49.10405],"type":"Point"}
}