{
  "type": "Feature",
  "properties": {
    "gn:admin1_code":"1",
    "gn:admin2_code":"83.0",
    "gn:admin3_code":"8337.0",
    "gn:admin4_code":"8337038.0",
    "gn:asciiname":"Gunnetsmattle",
    "gn:country_code":"DE",
    "gn:dem":730,
    "gn:feature_class":"P",
    "gn:feature_code":"PPL",
    "gn:name":"G\u00fcnnetsm\u00e4ttle",
    "gn:population":0,
    "gn:timezone":"Europe/Berlin",
    "iso:country":"DE",
    "name:und_x_variant":[
        "G\u00fcnnetsm\u00e4ltle",
        "G\u00fcnnetsm\u00e4ttle"
    ],
    "wof:name":"Gunnetsmattle",
    "wof:placetype":"neighbourhood"
},
  "geometry": {"coordinates":[8.06396,47.6439],"type":"Point"}
}