{
  "type": "Feature",
  "properties": {
    "gn:admin1_code":"5",
    "gn:admin2_code":"65.0",
    "gn:admin3_code":"6535.0",
    "gn:admin4_code":"6535002.0",
    "gn:asciiname":"Ruhlkirchen",
    "gn:country_code":"DE",
    "gn:dem":254,
    "gn:feature_class":"P",
    "gn:feature_code":"PPL",
    "gn:name":"Ruhlkirchen",
    "gn:population":0,
    "gn:timezone":"Europe/Berlin",
    "iso:country":"DE",
    "wof:name":"Ruhlkirchen",
    "wof:placetype":"neighbourhood"
},
  "geometry": {"coordinates":[9.18451,50.79437],"type":"Point"}
}