{
  "type": "Feature",
  "properties": {
    "gn:admin1_code":"2",
    "gn:admin2_code":"93.0",
    "gn:admin3_code":"9375.0",
    "gn:admin4_code":"9375156.0",
    "gn:asciiname":"Karolinenhutte",
    "gn:cc2":"DE",
    "gn:country_code":"DE",
    "gn:dem":354,
    "gn:feature_class":"P",
    "gn:feature_code":"PPL",
    "gn:name":"Karolinenh\u00fctte",
    "gn:population":0,
    "gn:timezone":"Europe/Berlin",
    "iso:country":"DE",
    "name:und_x_variant":[
        "Carolineh\u00fctte"
    ],
    "wof:name":"Karolinenhutte",
    "wof:placetype":"neighbourhood"
},
  "geometry": {"coordinates":[11.92145,49.1863],"type":"Point"}
}