{
  "type": "Feature",
  "properties": {
    "gn:gn_country":"DE",
    "gn:gn_fcode":"PPLA4",
    "gn:gn_pop":256,
    "gn:population":256,
    "iso:country":"DE",
    "name:bak_x_preferred":[
        "\u042d\u0441\u0431\u0430\u0445"
    ],
    "name:baq_x_preferred":[
        "E\u00dfbach"
    ],
    "name:chi_x_preferred":[
        "\u57c3\u65af\u5df4\u8d6b"
    ],
    "name:dut_x_preferred":[
        "E\u00dfbach"
    ],
    "name:eng_x_preferred":[
        "E\u00dfbach"
    ],
    "name:epo_x_preferred":[
        "E\u00dfbach"
    ],
    "name:fre_x_preferred":[
        "E\u00dfbach"
    ],
    "name:ger_x_preferred":[
        "E\u00dfbach"
    ],
    "name:hun_x_preferred":[
        "E\u00dfbach"
    ],
    "name:ita_x_preferred":[
        "E\u00dfbach"
    ],
    "name:mac_x_preferred":[
        "\u0415\u0441\u0431\u0430\u0445"
    ],
    "name:may_x_preferred":[
        "E\u00dfbach"
    ],
    "name:per_x_preferred":[
        "\u0627\u0633\u0628\u0627\u062e"
    ],
    "name:pol_x_preferred":[
        "E\u00dfbach"
    ],
    "name:por_x_preferred":[
        "E\u00dfbach"
    ],
    "name:rum_x_preferred":[
        "E\u00dfbach"
    ],
    "name:rus_x_preferred":[
        "\u042d\u0441\u0431\u0430\u0445"
    ],
    "name:srp_x_preferred":[
        "\u0415\u0441\u0431\u0430\u0445"
    ],
    "name:ukr_x_preferred":[
        "\u0415\u0441\u0431\u0430\u0445"
    ],
    "name:uzb_x_preferred":[
        "E\u00dfbach"
    ],
    "name:vie_x_preferred":[
        "E\u00dfbach"
    ],
    "name:vol_x_preferred":[
        "E\u00dfbach"
    ],
    "name:war_x_preferred":[
        "E\u00dfbach"
    ],
    "qs_pg:aaroncc":"DE",
    "qs_pg:gn_country":"DE",
    "qs_pg:gn_fcode":"PPLA4",
    "qs_pg:gn_pop":256,
    "qs_pg:name":"E\u00dfbach",
    "qs_pg:photos_9r":0,
    "qs_pg:photos_sr":0,
    "qs_pg:pop_sr":2,
    "qs_pg:qs_pg_placetype":"locality",
    "wof:name":"E\u00dfbach",
    "wof:placetype":"locality",
    "wof:population":256
},
  "geometry": {"coordinates":[11.68333,50.58333],"type":"Point"}
}