{
  "type": "Feature",
  "properties": {
    "gn:admin1_code":"7.0",
    "gn:admin2_code":"57.0",
    "gn:admin3_code":"5762.0",
    "gn:admin4_code":"5762016.0",
    "gn:asciiname":"Auenhausen",
    "gn:country_code":"DE",
    "gn:dem":287,
    "gn:feature_class":"P",
    "gn:feature_code":"PPL",
    "gn:name":"Auenhausen",
    "gn:population":0,
    "gn:timezone":"Europe/Berlin",
    "iso:country":"DE",
    "wof:name":"Auenhausen",
    "wof:placetype":"neighbourhood"
},
  "geometry": {"coordinates":[9.21101,51.64827],"type":"Point"}
}