{
  "type": "Feature",
  "properties": {
    "gn:admin1_code":"1",
    "gn:admin2_code":"81.0",
    "gn:admin3_code":"8127.0",
    "gn:admin4_code":"8127013.0",
    "gn:asciiname":"Hinterwald",
    "gn:country_code":"DE",
    "gn:dem":484,
    "gn:feature_class":"P",
    "gn:feature_code":"PPL",
    "gn:name":"Hinterwald",
    "gn:population":0,
    "gn:timezone":"Europe/Berlin",
    "iso:country":"DE",
    "name:ces_x_preferred":[
        "Hinterw\u00e4lder"
    ],
    "name:deu_x_preferred":[
        "Hinterw\u00e4lder-Rind"
    ],
    "name:fra_x_preferred":[
        "Hinterw\u00e4lder"
    ],
    "name:vie_x_preferred":[
        "B\u00f2 Hinterwald"
    ],
    "wof:name":"Hinterwald",
    "wof:placetype":"neighbourhood"
},
  "geometry": {"coordinates":[9.99052,48.98057],"type":"Point"}
}