{
  "type": "Feature",
  "properties": {
    "gn:admin1_code":"5",
    "gn:admin2_code":"66.0",
    "gn:admin3_code":"6636.0",
    "gn:admin4_code":"6636016.0",
    "gn:asciiname":"Gertenbach",
    "gn:country_code":"DE",
    "gn:dem":139,
    "gn:feature_class":"P",
    "gn:feature_code":"PPL",
    "gn:name":"Gertenbach",
    "gn:population":0,
    "gn:timezone":"Europe/Berlin",
    "iso:country":"DE",
    "wof:name":"Gertenbach",
    "wof:placetype":"neighbourhood"
},
  "geometry": {"coordinates":[9.8053,51.37834],"type":"Point"}
}