{
  "type": "Feature",
  "properties": {
    "gn:admin1_code":"12",
    "gn:admin2_code":"0.0",
    "gn:admin3_code":"13071.0",
    "gn:admin4_code":"13071101.0",
    "gn:asciiname":"Hoppenberg",
    "gn:country_code":"DE",
    "gn:dem":81,
    "gn:feature_class":"P",
    "gn:feature_code":"PPL",
    "gn:name":"Hoppenberg",
    "gn:population":0,
    "gn:timezone":"Europe/Berlin",
    "iso:country":"DE",
    "wof:name":"Hoppenberg",
    "wof:placetype":"neighbourhood"
},
  "geometry": {"coordinates":[12.91644,53.55709],"type":"Point"}
}