{
  "type": "Feature",
  "properties": {
    "iso:country":"DE",
    "name:ceb_x_preferred":[
        "D\u00f6se"
    ],
    "name:deu_x_preferred":[
        "D\u00f6se"
    ],
    "name:deu_x_variant":[
        "Doos"
    ],
    "name:eng_x_preferred":[
        "Doos-Muggenhof"
    ],
    "name:eng_x_variant":[
        "Doos-Muggenhof"
    ],
    "name:nds_x_preferred":[
        "D\u00f6\u00f6s"
    ],
    "name:unk_x_variant":[
        "Doos-Muggenhof",
        "Doos"
    ],
    "qs:gn_adm0_cc":"DE",
    "qs:gn_fcode":"PPLX",
    "qs:gn_local":2861650,
    "qs:gn_nam_loc":"nurnberg",
    "qs:gn_namadm1":"02",
    "qs:gn_name":"Doos",
    "qs:local_max":6346,
    "qs:local_sum":25338,
    "qs:localhoods":37,
    "qs:name":"Doos",
    "qs:name_adm0":"Deutschland",
    "qs:name_adm1":"Bayern",
    "qs:name_adm2":"Stadtkreis N\u00fcrnberg",
    "qs:name_en":"Doos-Muggenhof",
    "qs:name_lau":"Stadtteil Westliche Au\u00dfenstadt",
    "qs:name_local":"N\u00fcrnberg",
    "qs:photo_max":50,
    "qs:photo_sum":171,
    "qs:placetype":"Suburb",
    "qs:quad_count":18,
    "qs:woe_adm0":23424829,
    "qs:woe_adm1":2345482,
    "qs:woe_adm2":12596973,
    "qs:woe_lau":26823116,
    "qs:woe_local":680564,
    "qs:woe_ver":"7.10.0",
    "wof:lang":[
        "ger"
    ],
    "wof:name":"Doos",
    "wof:placetype":"neighbourhood"
},
  "geometry": {"coordinates":[11.019203,49.462033],"type":"Point"}
}