{
  "type": "Feature",
  "properties": {
    "gn:admin1_code":"14.0",
    "gn:admin2_code":"0.0",
    "gn:admin3_code":"15085.0",
    "gn:admin4_code":"15085040.0",
    "gn:asciiname":"Asmusstedt",
    "gn:country_code":"DE",
    "gn:dem":160,
    "gn:feature_class":"P",
    "gn:feature_code":"PPL",
    "gn:name":"Asmusstedt",
    "gn:population":0,
    "gn:timezone":"Europe/Berlin",
    "iso:country":"DE",
    "name:und_x_variant":[
        "Vorwerk Asmusstedt"
    ],
    "wof:name":"Asmusstedt",
    "wof:placetype":"neighbourhood"
},
  "geometry": {"coordinates":[11.23895,51.74313],"type":"Point"}
}