{
  "type": "Feature",
  "properties": {
    "gn:admin1_code":"2",
    "gn:admin2_code":"92.0",
    "gn:admin3_code":"9273.0",
    "gn:admin4_code":"9273137.0",
    "gn:asciiname":"Hohenpfahl",
    "gn:country_code":"DE",
    "gn:dem":355,
    "gn:feature_class":"P",
    "gn:feature_code":"PPL",
    "gn:name":"Hohenpfahl",
    "gn:population":0,
    "gn:timezone":"Europe/Berlin",
    "iso:country":"DE",
    "wof:name":"Hohenpfahl",
    "wof:placetype":"neighbourhood"
},
  "geometry": {"coordinates":[11.87321,48.90981],"type":"Point"}
}