{
  "type": "Feature",
  "properties": {
    "gn:admin1_code":"6",
    "gn:admin2_code":"0.0",
    "gn:admin3_code":"3452.0",
    "gn:admin4_code":"3452003.0",
    "gn:asciiname":"Holzdorf",
    "gn:country_code":"DE",
    "gn:dem":1,
    "gn:feature_class":"P",
    "gn:feature_code":"PPL",
    "gn:name":"Holzdorf",
    "gn:population":0,
    "gn:timezone":"Europe/Berlin",
    "iso:country":"DE",
    "name:ceb_x_preferred":[
        "Holzdorf"
    ],
    "name:dan_x_preferred":[
        "Holttorp"
    ],
    "name:deu_x_preferred":[
        "Holzdorf"
    ],
    "name:epo_x_preferred":[
        "Holzdorf"
    ],
    "name:eus_x_preferred":[
        "Holzdorf"
    ],
    "name:fas_x_preferred":[
        "\u0647\u0648\u0644\u062a\u0633\u062f\u0648\u0631\u0641"
    ],
    "name:fra_x_preferred":[
        "Holzdorf"
    ],
    "name:hun_x_preferred":[
        "Holzdorf"
    ],
    "name:ita_x_preferred":[
        "Holzdorf"
    ],
    "name:kaz_x_preferred":[
        "\u0425\u043e\u043b\u044c\u0446\u0434\u043e\u0440\u0444"
    ],
    "name:kir_x_preferred":[
        "\u0425\u043e\u043b\u044c\u0446\u0434\u043e\u0440\u0444"
    ],
    "name:mkd_x_preferred":[
        "\u0425\u043e\u043b\u0446\u0434\u043e\u0440\u0444"
    ],
    "name:msa_x_preferred":[
        "Holzdorf"
    ],
    "name:nld_x_preferred":[
        "Holzdorf"
    ],
    "name:pol_x_preferred":[
        "Holzdorf"
    ],
    "name:por_x_preferred":[
        "Holzdorf"
    ],
    "name:ron_x_preferred":[
        "Holzdorf"
    ],
    "name:rus_x_preferred":[
        "\u0425\u043e\u043b\u044c\u0446\u0434\u043e\u0440\u0444"
    ],
    "name:spa_x_preferred":[
        "Holzdorf"
    ],
    "name:srp_x_preferred":[
        "\u0425\u043e\u043b\u0446\u0434\u043e\u0440\u0444"
    ],
    "name:tur_x_preferred":[
        "Holzdorf"
    ],
    "name:ukr_x_preferred":[
        "\u0413\u043e\u043b\u044c\u0446\u0434\u043e\u0440\u0444"
    ],
    "name:uzb_x_preferred":[
        "Holzdorf"
    ],
    "name:vie_x_preferred":[
        "Holzdorf"
    ],
    "name:vol_x_preferred":[
        "Holzdorf"
    ],
    "name:war_x_preferred":[
        "Holzdorf"
    ],
    "name:zho_x_preferred":[
        "\u970d\u5c14\u8328\u591a\u592b"
    ],
    "wof:name":"Holzdorf",
    "wof:placetype":"neighbourhood"
},
  "geometry": {"coordinates":[7.30278,53.58621],"type":"Point"}
}