{
  "type": "Feature",
  "properties": {
    "gn:admin1_code":"15",
    "gn:admin2_code":"0.0",
    "gn:admin3_code":"16065.0",
    "gn:admin4_code":"16065067.0",
    "gn:asciiname":"Immenrode",
    "gn:country_code":"DE",
    "gn:dem":402,
    "gn:feature_class":"P",
    "gn:feature_code":"PPL",
    "gn:name":"Immenrode",
    "gn:population":0,
    "gn:timezone":"Europe/Berlin",
    "iso:country":"DE",
    "name:und_x_variant":[
        "Immenroda",
        "Immenrode"
    ],
    "wof:name":"Immenrode",
    "wof:placetype":"neighbourhood"
},
  "geometry": {"coordinates":[10.73467,51.36712],"type":"Point"}
}