{
  "type": "Feature",
  "properties": {
    "gn:admin1_code":"2",
    "gn:admin2_code":"94.0",
    "gn:admin3_code":"9477.0",
    "gn:admin4_code":"9477139.0",
    "gn:asciiname":"Oberpollitz",
    "gn:country_code":"DE",
    "gn:dem":529,
    "gn:feature_class":"P",
    "gn:feature_code":"PPL",
    "gn:name":"Oberp\u00f6llitz",
    "gn:population":0,
    "gn:timezone":"Europe/Berlin",
    "iso:country":"DE",
    "wof:name":"Oberpollitz",
    "wof:placetype":"neighbourhood"
},
  "geometry": {"coordinates":[11.64324,50.09673],"type":"Point"}
}