{
  "type": "Feature",
  "properties": {
    "gn:admin1_code":"13",
    "gn:admin2_code":"0.0",
    "gn:admin3_code":"14523.0",
    "gn:admin4_code":"14523245.0",
    "gn:asciiname":"Sachsengrund",
    "gn:country_code":"DE",
    "gn:dem":768,
    "gn:feature_class":"P",
    "gn:feature_code":"PPL",
    "gn:name":"Sachsengrund",
    "gn:population":0,
    "gn:timezone":"Europe/Berlin",
    "iso:country":"DE",
    "wof:name":"Sachsengrund",
    "wof:placetype":"neighbourhood"
},
  "geometry": {"coordinates":[12.53313,50.41743],"type":"Point"}
}