{
  "type": "Feature",
  "properties": {
    "gn:admin1_code":"13",
    "gn:admin2_code":"0.0",
    "gn:admin3_code":"14729.0",
    "gn:admin4_code":"14729320.0",
    "gn:asciiname":"Hain",
    "gn:country_code":"DE",
    "gn:dem":116,
    "gn:feature_class":"P",
    "gn:feature_code":"PPL",
    "gn:name":"Hain",
    "gn:population":0,
    "gn:timezone":"Europe/Berlin",
    "iso:country":"DE",
    "name:ceb_x_preferred":[
        "Hain"
    ],
    "name:deu_x_preferred":[
        "Hain"
    ],
    "name:est_x_preferred":[
        "Hain"
    ],
    "name:fra_x_preferred":[
        "Hain"
    ],
    "name:hun_x_preferred":[
        "Hain"
    ],
    "name:nld_x_preferred":[
        "Hain"
    ],
    "name:pol_x_preferred":[
        "Hain"
    ],
    "name:swe_x_preferred":[
        "Hain"
    ],
    "name:tgl_x_preferred":[
        "Hain"
    ],
    "wof:name":"Hain",
    "wof:placetype":"neighbourhood"
},
  "geometry": {"coordinates":[12.45,51.16667],"type":"Point"}
}