{
  "type": "Feature",
  "properties": {
    "gn:admin1_code":"2",
    "gn:admin2_code":"92.0",
    "gn:admin3_code":"9278.0",
    "gn:admin4_code":"9278139.0",
    "gn:asciiname":"Steinburg",
    "gn:country_code":"DE",
    "gn:dem":347,
    "gn:feature_class":"P",
    "gn:feature_code":"PPL",
    "gn:name":"Steinburg",
    "gn:population":0,
    "gn:timezone":"Europe/Berlin",
    "iso:country":"DE",
    "name:cat_x_preferred":[
        "Steinburg"
    ],
    "name:ceb_x_preferred":[
        "Kreis Steinburg"
    ],
    "name:dan_x_preferred":[
        "Kreis Steinburg"
    ],
    "name:deu_x_preferred":[
        "Kreis Steinburg"
    ],
    "name:epo_x_preferred":[
        "Distrikto Steinburg"
    ],
    "name:fas_x_preferred":[
        "\u0627\u0634\u062a\u0627\u06cc\u0646\u0628\u0648\u0631\u06af"
    ],
    "name:fin_x_preferred":[
        "Steinburg"
    ],
    "name:frr_x_preferred":[
        "Kris Steinborj"
    ],
    "name:ile_x_preferred":[
        "Subdistrict Steinburg"
    ],
    "name:ind_x_preferred":[
        "Steinburg"
    ],
    "name:kat_x_preferred":[
        "\u10e8\u10e2\u10d0\u10d8\u10dc\u10d1\u10e3\u10e0\u10d2\u10d8\u10e1 \u10e0\u10d0\u10d8\u10dd\u10dc\u10d8"
    ],
    "name:kaz_x_preferred":[
        "\u0428\u0442\u0430\u0439\u043d\u0431\u0443\u0440\u0433"
    ],
    "name:mkd_x_preferred":[
        "\u0428\u0442\u0430\u0458\u043d\u0431\u0443\u0440\u0433"
    ],
    "name:msa_x_preferred":[
        "Steinburg"
    ],
    "name:nds_x_preferred":[
        "Kreis Steenborg"
    ],
    "name:nld_x_preferred":[
        "Kreis Steinburg"
    ],
    "name:nor_x_preferred":[
        "Kreis Steinburg"
    ],
    "name:pnb_x_preferred":[
        "\u0633\u0679\u0627\u0626\u0646\u0628\u0631\u06af"
    ],
    "name:pol_x_preferred":[
        "Powiat Steinburg"
    ],
    "name:por_x_preferred":[
        "Steinburg"
    ],
    "name:ron_x_preferred":[
        "Steinburg"
    ],
    "name:rus_x_preferred":[
        "\u0428\u0442\u0430\u0439\u043d\u0431\u0443\u0440\u0433"
    ],
    "name:stq_x_preferred":[
        "Kring Steinburg"
    ],
    "name:swe_x_preferred":[
        "Kreis Steinburg"
    ],
    "name:tur_x_preferred":[
        "Steinburg"
    ],
    "name:ukr_x_preferred":[
        "\u0428\u0442\u0430\u0439\u043d\u0431\u0443\u0440\u0433"
    ],
    "name:uzb_x_preferred":[
        "Steinburg"
    ],
    "name:vie_x_preferred":[
        "Steinburg"
    ],
    "name:war_x_preferred":[
        "Steinburg"
    ],
    "name:zho_x_preferred":[
        "\u65bd\u6cf0\u56e0\u5821\u53bf"
    ],
    "wof:name":"Steinburg",
    "wof:placetype":"neighbourhood"
},
  "geometry": {"coordinates":[12.73968,48.96295],"type":"Point"}
}