{
  "type": "Feature",
  "properties": {
    "gn:admin1_code":"12",
    "gn:admin2_code":"0.0",
    "gn:admin3_code":"13071.0",
    "gn:admin4_code":"13071068.0",
    "gn:asciiname":"Goddin",
    "gn:country_code":"DE",
    "gn:dem":74,
    "gn:feature_class":"P",
    "gn:feature_code":"PPL",
    "gn:name":"Goddin",
    "gn:population":0,
    "gn:timezone":"Europe/Berlin",
    "iso:country":"DE",
    "wof:name":"Goddin",
    "wof:placetype":"neighbourhood"
},
  "geometry": {"coordinates":[13.02504,53.66702],"type":"Point"}
}