{
  "type": "Feature",
  "properties": {
    "gn:admin1_code":"13",
    "gn:admin2_code":"0.0",
    "gn:admin3_code":"14627.0",
    "gn:admin4_code":"14627230.0",
    "gn:asciiname":"Neupochra",
    "gn:country_code":"DE",
    "gn:dem":103,
    "gn:feature_class":"P",
    "gn:feature_code":"PPL",
    "gn:name":"Neupochra",
    "gn:population":0,
    "gn:timezone":"Europe/Berlin",
    "iso:country":"DE",
    "wof:name":"Neupochra",
    "wof:placetype":"neighbourhood"
},
  "geometry": {"coordinates":[13.21957,51.31631],"type":"Point"}
}