{
  "type": "Feature",
  "properties": {
    "gn:admin1_code":"2",
    "gn:admin2_code":"92.0",
    "gn:admin3_code":"9272.0",
    "gn:admin4_code":"9272120.0",
    "gn:asciiname":"Schlag",
    "gn:country_code":"DE",
    "gn:dem":598,
    "gn:feature_class":"P",
    "gn:feature_code":"PPL",
    "gn:name":"Schlag",
    "gn:population":0,
    "gn:timezone":"Europe/Berlin",
    "iso:country":"DE",
    "wof:name":"Schlag",
    "wof:placetype":"neighbourhood"
},
  "geometry": {"coordinates":[13.39353,48.84955],"type":"Point"}
}