{
  "type": "Feature",
  "properties": {
    "gn:admin1_code":"11.0",
    "gn:admin2_code":"0.0",
    "gn:admin3_code":"12071.0",
    "gn:admin4_code":"12071294.0",
    "gn:asciiname":"Bahren",
    "gn:country_code":"DE",
    "gn:dem":96,
    "gn:feature_class":"P",
    "gn:feature_code":"PPL",
    "gn:name":"Bahren",
    "gn:population":0,
    "gn:timezone":"Europe/Berlin",
    "iso:country":"DE",
    "wof:name":"Bahren",
    "wof:placetype":"neighbourhood"
},
  "geometry": {"coordinates":[14.74949,51.63741],"type":"Point"}
}