{
  "type": "Feature",
  "properties": {
    "gn:admin1_code":"2",
    "gn:admin2_code":"93.0",
    "gn:admin3_code":"9374.0",
    "gn:admin4_code":"9374155.0",
    "gn:asciiname":"Naslitz",
    "gn:country_code":"DE",
    "gn:dem":456,
    "gn:feature_class":"P",
    "gn:feature_code":"PPL",
    "gn:name":"Naslitz",
    "gn:population":0,
    "gn:timezone":"Europe/Berlin",
    "iso:country":"DE",
    "wof:name":"Naslitz",
    "wof:placetype":"neighbourhood"
},
  "geometry": {"coordinates":[11.70667,49.80107],"type":"Point"}
}