{
  "type": "Feature",
  "properties": {
    "gn:admin1_code":"15",
    "gn:admin2_code":"0.0",
    "gn:admin3_code":"16074.0",
    "gn:admin4_code":"16074012.0",
    "gn:asciiname":"Nickelsdorf",
    "gn:country_code":"DE",
    "gn:dem":270,
    "gn:feature_class":"P",
    "gn:feature_code":"PPL",
    "gn:name":"Nickelsdorf",
    "gn:population":0,
    "gn:timezone":"Europe/Berlin",
    "iso:country":"DE",
    "name:ceb_x_preferred":[
        "Nickelsdorf"
    ],
    "name:ces_x_preferred":[
        "Nickelsdorf"
    ],
    "name:deu_x_preferred":[
        "Nickelsdorf"
    ],
    "name:epo_x_preferred":[
        "Nickelsdorf"
    ],
    "name:fas_x_preferred":[
        "\u0646\u06cc\u06a9\u0644\u0632\u062f\u0648\u0631\u0641"
    ],
    "name:fra_x_preferred":[
        "Nickelsdorf"
    ],
    "name:hun_x_preferred":[
        "Mikl\u00f3shalma"
    ],
    "name:ita_x_preferred":[
        "Nickelsdorf"
    ],
    "name:kaz_x_preferred":[
        "\u041d\u0438\u043a\u043a\u0435\u043b\u044c\u0441\u0434\u043e\u0440\u0444"
    ],
    "name:nld_x_preferred":[
        "Nickelsdorf"
    ],
    "name:pol_x_preferred":[
        "Nickelsdorf"
    ],
    "name:por_x_preferred":[
        "Nickelsdorf"
    ],
    "name:ron_x_preferred":[
        "Nickelsdorf"
    ],
    "name:rus_x_preferred":[
        "\u041d\u0438\u043a\u043a\u0435\u043b\u044c\u0441\u0434\u043e\u0440\u0444"
    ],
    "name:slk_x_preferred":[
        "Nickelsdorf"
    ],
    "name:spa_x_preferred":[
        "Nickelsdorf"
    ],
    "name:swe_x_preferred":[
        "Nickelsdorf"
    ],
    "name:ukr_x_preferred":[
        "\u041d\u0456\u043a\u0435\u043b\u044c\u0441\u0434\u043e\u0440\u0444"
    ],
    "name:uzb_x_preferred":[
        "Nickelsdorf"
    ],
    "name:vol_x_preferred":[
        "Nickelsdorf"
    ],
    "name:war_x_preferred":[
        "Nickelsdorf"
    ],
    "name:zho_x_preferred":[
        "\u5c3c\u514b\u5c14\u65af\u591a\u592b"
    ],
    "wof:name":"Nickelsdorf",
    "wof:placetype":"neighbourhood"
},
  "geometry": {"coordinates":[12.00549,50.97787],"type":"Point"}
}