{
  "type": "Feature",
  "properties": {
    "gn:admin1_code":"15",
    "gn:admin2_code":"0.0",
    "gn:admin3_code":"16074.0",
    "gn:admin4_code":"16074012.0",
    "gn:asciiname":"Nickelsdorf",
    "gn:country_code":"DE",
    "gn:dem":270,
    "gn:feature_class":"P",
    "gn:feature_code":"PPL",
    "gn:name":"Nickelsdorf",
    "gn:population":0,
    "gn:timezone":"Europe/Berlin",
    "iso:country":"DE",
    "wof:name":"Nickelsdorf",
    "wof:placetype":"neighbourhood"
},
  "geometry": {"coordinates":[12.00549,50.97787],"type":"Point"}
}