{
  "type": "Feature",
  "properties": {
    "gn:admin1_code":"2",
    "gn:admin2_code":"95.0",
    "gn:admin3_code":"9571.0",
    "gn:admin4_code":"9571226.0",
    "gn:asciiname":"Lanzendorf",
    "gn:country_code":"DE",
    "gn:dem":392,
    "gn:feature_class":"P",
    "gn:feature_code":"PPL",
    "gn:name":"Lanzendorf",
    "gn:population":0,
    "gn:timezone":"Europe/Berlin",
    "iso:country":"DE",
    "name:ceb_x_preferred":[
        "Lanzendorf"
    ],
    "name:deu_x_preferred":[
        "Lanzendorf"
    ],
    "name:epo_x_preferred":[
        "Lanzendorf"
    ],
    "name:fas_x_preferred":[
        "\u0644\u0627\u0646\u062a\u0633\u0646\u062f\u0648\u0631\u0641"
    ],
    "name:fra_x_preferred":[
        "Lanzendorf"
    ],
    "name:hun_x_preferred":[
        "Lanzendorf"
    ],
    "name:ita_x_preferred":[
        "Lanzendorf"
    ],
    "name:nld_x_preferred":[
        "Lanzendorf"
    ],
    "name:pol_x_preferred":[
        "Lanzendorf"
    ],
    "name:por_x_preferred":[
        "Lanzendorf"
    ],
    "name:rus_x_preferred":[
        "\u041b\u0430\u043d\u0446\u0435\u043d\u0434\u043e\u0440\u0444"
    ],
    "name:slk_x_preferred":[
        "Lanzendorf"
    ],
    "name:spa_x_preferred":[
        "Lanzendorf"
    ],
    "name:swe_x_preferred":[
        "Lanzendorf"
    ],
    "name:uzb_x_preferred":[
        "Lanzendorf"
    ],
    "name:vie_x_preferred":[
        "Lanzendorf"
    ],
    "name:vol_x_preferred":[
        "Lanzendorf"
    ],
    "name:war_x_preferred":[
        "Lanzendorf"
    ],
    "name:zho_x_preferred":[
        "\u5170\u5c91\u591a\u592b"
    ],
    "wof:name":"Lanzendorf",
    "wof:placetype":"neighbourhood"
},
  "geometry": {"coordinates":[10.88372,49.29927],"type":"Point"}
}