{
  "type": "Feature",
  "properties": {
    "gn:admin1_code":"2",
    "gn:admin2_code":"91.0",
    "gn:admin3_code":"9177.0",
    "gn:admin4_code":"9177113.0",
    "gn:asciiname":"Gugging",
    "gn:country_code":"DE",
    "gn:dem":509,
    "gn:feature_class":"P",
    "gn:feature_code":"PPL",
    "gn:name":"Gugging",
    "gn:population":0,
    "gn:timezone":"Europe/Berlin",
    "iso:country":"DE",
    "wof:name":"Gugging",
    "wof:placetype":"neighbourhood"
},
  "geometry": {"coordinates":[11.99544,48.28485],"type":"Point"}
}