{
  "type": "Feature",
  "properties": {
    "gn:admin1_code":"2",
    "gn:admin2_code":"94.0",
    "gn:admin3_code":"9474.0",
    "gn:admin4_code":"9474140.0",
    "gn:asciiname":"Oberrusselbach",
    "gn:country_code":"DE",
    "gn:dem":475,
    "gn:feature_class":"P",
    "gn:feature_code":"PPL",
    "gn:name":"Oberr\u00fcsselbach",
    "gn:population":0,
    "gn:timezone":"Europe/Berlin",
    "iso:country":"DE",
    "wof:name":"Oberrusselbach",
    "wof:placetype":"neighbourhood"
},
  "geometry": {"coordinates":[11.27232,49.61221],"type":"Point"}
}