{
  "type": "Feature",
  "properties": {
    "gn:admin1_code":"6.0",
    "gn:admin2_code":"0.0",
    "gn:admin3_code":"3460.0",
    "gn:admin4_code":"3460002.0",
    "gn:asciiname":"Bexadde",
    "gn:country_code":"DE",
    "gn:dem":99,
    "gn:feature_class":"P",
    "gn:feature_code":"PPL",
    "gn:name":"Bexadde",
    "gn:population":0,
    "gn:timezone":"Europe/Berlin",
    "iso:country":"DE",
    "wof:name":"Bexadde",
    "wof:placetype":"neighbourhood"
},
  "geometry": {"coordinates":[8.17005,52.52719],"type":"Point"}
}