{
  "type": "Feature",
  "properties": {
    "gn:admin1_code":"15",
    "gn:admin2_code":"0.0",
    "gn:admin3_code":"16071.0",
    "gn:admin4_code":"16071059.0",
    "gn:asciiname":"Nauendorf",
    "gn:country_code":"DE",
    "gn:dem":335,
    "gn:feature_class":"P",
    "gn:feature_code":"PPLA4",
    "gn:name":"Nauendorf",
    "gn:population":0,
    "gn:timezone":"Europe/Berlin",
    "iso:country":"DE",
    "wof:name":"Nauendorf",
    "wof:placetype":"locality"
},
  "geometry": {"coordinates":[11.18108,50.89453],"type":"Point"}
}