{
  "type": "Feature",
  "properties": {
    "gn:admin1_code":"2.0",
    "gn:admin2_code":"95.0",
    "gn:admin3_code":"9571.0",
    "gn:admin4_code":"9571193.0",
    "gn:asciiname":"Bettenfeld",
    "gn:country_code":"DE",
    "gn:dem":417,
    "gn:feature_class":"P",
    "gn:feature_code":"PPL",
    "gn:name":"Bettenfeld",
    "gn:population":0,
    "gn:timezone":"Europe/Berlin",
    "iso:country":"DE",
    "name:ceb_x_preferred":[
        "Bettenfeld"
    ],
    "name:deu_x_preferred":[
        "Bettenfeld"
    ],
    "name:epo_x_preferred":[
        "Bettenfeld"
    ],
    "name:eus_x_preferred":[
        "Bettenfeld"
    ],
    "name:fas_x_preferred":[
        "\u0628\u062a\u0646\u0641\u0644\u062f"
    ],
    "name:fra_x_preferred":[
        "Bettenfeld"
    ],
    "name:hun_x_preferred":[
        "Bettenfeld"
    ],
    "name:ita_x_preferred":[
        "Bettenfeld"
    ],
    "name:kaz_x_preferred":[
        "\u0411\u0435\u0442\u0442\u0435\u043d\u0444\u0435\u043b\u044c\u0434"
    ],
    "name:kir_x_preferred":[
        "\u0411\u0435\u0442\u0442\u0435\u043d\u0444\u0435\u043b\u044c\u0434"
    ],
    "name:msa_x_preferred":[
        "Bettenfeld"
    ],
    "name:nld_x_preferred":[
        "Bettenfeld"
    ],
    "name:pol_x_preferred":[
        "Bettenfeld"
    ],
    "name:por_x_preferred":[
        "Bettenfeld"
    ],
    "name:ron_x_preferred":[
        "Bettenfeld"
    ],
    "name:rus_x_preferred":[
        "\u0411\u0435\u0442\u0442\u0435\u043d\u0444\u0435\u043b\u044c\u0434"
    ],
    "name:spa_x_preferred":[
        "Bettenfeld"
    ],
    "name:srp_x_preferred":[
        "\u0411\u0435\u0442\u0435\u043d\u0444\u0435\u043b\u0434"
    ],
    "name:ukr_x_preferred":[
        "\u0411\u0435\u0442\u0442\u0435\u043d\u0444\u0435\u043b\u044c\u0434"
    ],
    "name:uzb_x_preferred":[
        "Bettenfeld"
    ],
    "name:vie_x_preferred":[
        "Bettenfeld"
    ],
    "name:vol_x_preferred":[
        "Bettenfeld"
    ],
    "name:war_x_preferred":[
        "Bettenfeld"
    ],
    "name:zho_x_preferred":[
        "\u8d1d\u6ed5\u8d39\u5c14\u5fb7"
    ],
    "wof:name":"Bettenfeld",
    "wof:placetype":"neighbourhood"
},
  "geometry": {"coordinates":[10.12844,49.34049],"type":"Point"}
}