{
  "type": "Feature",
  "properties": {
    "gn:admin1_code":"10",
    "gn:admin2_code":"0.0",
    "gn:admin3_code":"1057.0",
    "gn:admin4_code":"1057091.0",
    "gn:asciiname":"Klausdorf",
    "gn:country_code":"DE",
    "gn:dem":6,
    "gn:feature_class":"P",
    "gn:feature_code":"PPL",
    "gn:name":"Klausdorf",
    "gn:population":6047,
    "gn:timezone":"Europe/Berlin",
    "iso:country":"DE",
    "name:ceb_x_preferred":[
        "Klausdorf"
    ],
    "name:deu_x_preferred":[
        "Klausdorf"
    ],
    "name:epo_x_preferred":[
        "Klausdorf"
    ],
    "name:fas_x_preferred":[
        "\u06a9\u0644\u0627\u0648\u0633\u062f\u0648\u0631\u0641"
    ],
    "name:mkd_x_preferred":[
        "\u041a\u043b\u0430\u0443\u0441\u0434\u043e\u0440\u0444"
    ],
    "name:nld_x_preferred":[
        "Klausdorf"
    ],
    "name:ron_x_preferred":[
        "Klausdorf"
    ],
    "name:rus_x_preferred":[
        "\u041a\u043b\u0430\u0443\u0441\u0434\u043e\u0440\u0444"
    ],
    "name:spa_x_preferred":[
        "Klausdorf"
    ],
    "name:tur_x_preferred":[
        "Klausdorf"
    ],
    "name:uzb_x_preferred":[
        "Klausdorf"
    ],
    "name:vol_x_preferred":[
        "Klausdorf"
    ],
    "wof:name":"Klausdorf",
    "wof:placetype":"neighbourhood",
    "wof:population":6047
},
  "geometry": {"coordinates":[10.21372,54.30899],"type":"Point"}
}