{
  "type": "Feature",
  "properties": {
    "gn:admin1_code":"10",
    "gn:admin2_code":"0.0",
    "gn:admin3_code":"1057.0",
    "gn:admin4_code":"1057091.0",
    "gn:asciiname":"Klausdorf",
    "gn:country_code":"DE",
    "gn:dem":6,
    "gn:feature_class":"P",
    "gn:feature_code":"PPL",
    "gn:name":"Klausdorf",
    "gn:population":6047,
    "gn:timezone":"Europe/Berlin",
    "iso:country":"DE",
    "wof:name":"Klausdorf",
    "wof:placetype":"neighbourhood",
    "wof:population":6047
},
  "geometry": {"coordinates":[10.21372,54.30899],"type":"Point"}
}