{
  "type": "Feature",
  "properties": {
    "iso:country":"DE",
    "wof:name":"Flingern Nord",
    "wof:placetype":"neighbourhood"
},
  "geometry": {"coordinates":[6.81435943684232,51.23039481425689],"type":"Point"}
}