{
  "type": "Feature",
  "properties": {
    "gn:admin1_code":"2",
    "gn:admin2_code":"97.0",
    "gn:admin3_code":"9776.0",
    "gn:admin4_code":"9776112.0",
    "gn:asciiname":"Schmalenberg",
    "gn:country_code":"DE",
    "gn:dem":644,
    "gn:feature_class":"P",
    "gn:feature_code":"PPL",
    "gn:name":"Schmalenberg",
    "gn:population":0,
    "gn:timezone":"Europe/Berlin",
    "iso:country":"DE",
    "name:ceb_x_preferred":[
        "Schmalenberg"
    ],
    "name:deu_x_preferred":[
        "Schmalenberg"
    ],
    "name:epo_x_preferred":[
        "Schmalenberg"
    ],
    "name:eus_x_preferred":[
        "Schmalenberg"
    ],
    "name:fas_x_preferred":[
        "\u0634\u0645\u0627\u0644\u0646\u0628\u0631\u06af"
    ],
    "name:fra_x_preferred":[
        "Schmalenberg"
    ],
    "name:hun_x_preferred":[
        "Schmalenberg"
    ],
    "name:ita_x_preferred":[
        "Schmalenberg"
    ],
    "name:msa_x_preferred":[
        "Schmalenberg"
    ],
    "name:nld_x_preferred":[
        "Schmalenberg"
    ],
    "name:pol_x_preferred":[
        "Schmalenberg"
    ],
    "name:por_x_preferred":[
        "Schmalenberg"
    ],
    "name:ron_x_preferred":[
        "Schmalenberg"
    ],
    "name:rus_x_preferred":[
        "\u0428\u043c\u0430\u043b\u0435\u043d\u0431\u0435\u0440\u0433"
    ],
    "name:spa_x_preferred":[
        "Schmalenberg"
    ],
    "name:srp_x_preferred":[
        "\u0428\u043c\u0430\u043b\u0435\u043d\u0431\u0435\u0440\u0433"
    ],
    "name:ukr_x_preferred":[
        "\u0428\u043c\u0430\u043b\u0435\u043d\u0431\u0435\u0440\u0433"
    ],
    "name:uzb_x_preferred":[
        "Schmalenberg"
    ],
    "name:vie_x_preferred":[
        "Schmalenberg"
    ],
    "name:vol_x_preferred":[
        "Schmalenberg"
    ],
    "name:war_x_preferred":[
        "Schmalenberg"
    ],
    "wof:name":"Schmalenberg",
    "wof:placetype":"neighbourhood"
},
  "geometry": {"coordinates":[9.96667,47.65],"type":"Point"}
}