{
  "type": "Feature",
  "properties": {
    "gn:admin1_code":"2",
    "gn:admin2_code":"94.0",
    "gn:admin3_code":"9478.0",
    "gn:admin4_code":"9478145.0",
    "gn:asciiname":"Lettenreuth",
    "gn:country_code":"DE",
    "gn:dem":291,
    "gn:feature_class":"P",
    "gn:feature_code":"PPL",
    "gn:name":"Lettenreuth",
    "gn:population":0,
    "gn:timezone":"Europe/Berlin",
    "iso:country":"DE",
    "wof:name":"Lettenreuth",
    "wof:placetype":"neighbourhood"
},
  "geometry": {"coordinates":[11.15919,50.17607],"type":"Point"}
}