{
  "type": "Feature",
  "properties": {
    "gn:admin1_code":"1",
    "gn:admin2_code":"84.0",
    "gn:admin3_code":"8436.0",
    "gn:admin4_code":"8436064.0",
    "gn:asciiname":"Mariatal",
    "gn:country_code":"DE",
    "gn:dem":427,
    "gn:feature_class":"P",
    "gn:feature_code":"PPL",
    "gn:name":"Mariatal",
    "gn:population":0,
    "gn:timezone":"Europe/Berlin",
    "iso:country":"DE",
    "wof:name":"Mariatal",
    "wof:placetype":"neighbourhood"
},
  "geometry": {"coordinates":[9.59552,47.75426],"type":"Point"}
}