{
  "type": "Feature",
  "properties": {
    "iso:country":"DE",
    "name:ces_x_preferred":[
        "Kamp"
    ],
    "name:dan_x_preferred":[
        "Kamp"
    ],
    "name:deu_x_preferred":[
        "Kamp"
    ],
    "name:fra_x_preferred":[
        "Kamp"
    ],
    "name:ita_x_preferred":[
        "Kamp"
    ],
    "name:lit_x_preferred":[
        "Kampas"
    ],
    "name:nor_x_preferred":[
        "Kamp"
    ],
    "name:pol_x_preferred":[
        "Kamp"
    ],
    "name:swe_x_preferred":[
        "Kamp"
    ],
    "name:zho_x_preferred":[
        "\u574e\u666e\u6cb3"
    ],
    "qs_pg:aaroncc":"DE",
    "qs_pg:name":"Kamp",
    "qs_pg:name_adm0":"Deutschland",
    "qs_pg:name_adm1":"Niedersachsen",
    "qs_pg:photos":183,
    "qs_pg:photos_1k":37,
    "qs_pg:photos_9k":1,
    "qs_pg:photos_9r":4,
    "qs_pg:photos_all":183,
    "qs_pg:photos_sr":4,
    "qs_pg:pop_sr":0,
    "qs_pg:qs_pg_placetype":"locality",
    "qs_pg:qs_pg_placetype_gp":"Town",
    "qs_pg:woe_adm0":23424829,
    "woe:adm0_id":23424829,
    "woe:name_adm0":"Deutschland",
    "woe:name_adm1":"Niedersachsen",
    "woe:placetype":"Town",
    "wof:name":"Kamp",
    "wof:placetype":"neighbourhood"
},
  "geometry": {"coordinates":[8.465913,52.224927],"type":"Point"}
}