{
  "type": "Feature",
  "properties": {
    "gn:admin1_code":"6",
    "gn:admin2_code":"0.0",
    "gn:admin3_code":"3241.0",
    "gn:admin4_code":"3241005.0",
    "gn:asciiname":"Frielingen",
    "gn:country_code":"DE",
    "gn:dem":48,
    "gn:feature_class":"P",
    "gn:feature_code":"PPL",
    "gn:name":"Frielingen",
    "gn:population":0,
    "gn:timezone":"Europe/Berlin",
    "iso:country":"DE",
    "name:nds_x_preferred":[
        "Frielje"
    ],
    "name:nds_x_variant":[
        "Frielingen"
    ],
    "wof:name":"Frielingen",
    "wof:placetype":"neighbourhood"
},
  "geometry": {"coordinates":[9.52777,52.46029],"type":"Point"}
}