{
  "type": "Feature",
  "properties": {
    "gn:admin1_code":"2",
    "gn:asciiname":"Heilig Kreuz",
    "gn:country_code":"DE",
    "gn:dem":363,
    "gn:feature_class":"P",
    "gn:feature_code":"PPL",
    "gn:name":"Heilig Kreuz",
    "gn:population":0,
    "gn:timezone":"Europe/Berlin",
    "iso:country":"DE",
    "wof:name":"Heilig Kreuz",
    "wof:placetype":"neighbourhood"
},
  "geometry": {"coordinates":[12.81667,48.15],"type":"Point"}
}