{
  "type": "Feature",
  "properties": {
    "gn:admin1_code":"6",
    "gn:admin2_code":"0.0",
    "gn:admin3_code":"3457.0",
    "gn:admin4_code":"3457021.0",
    "gn:asciiname":"Holthusen",
    "gn:country_code":"DE",
    "gn:dem":5,
    "gn:feature_class":"P",
    "gn:feature_code":"PPL",
    "gn:name":"Holthusen",
    "gn:population":0,
    "gn:timezone":"Europe/Berlin",
    "iso:country":"DE",
    "name:deu_x_preferred":[
        "Holthusen"
    ],
    "name:epo_x_preferred":[
        "Holthusen"
    ],
    "name:fas_x_preferred":[
        "\u0647\u0648\u0644\u062a\u0648\u0632\u0646"
    ],
    "name:fra_x_preferred":[
        "Holthusen"
    ],
    "name:hun_x_preferred":[
        "Holthusen"
    ],
    "name:ita_x_preferred":[
        "Holthusen"
    ],
    "name:kaz_x_preferred":[
        "\u0425\u043e\u043b\u044c\u0442\u0443\u0437\u0435\u043d"
    ],
    "name:kir_x_preferred":[
        "\u0425\u043e\u043b\u044c\u0442\u0443\u0437\u0435\u043d"
    ],
    "name:mkd_x_preferred":[
        "\u0425\u043e\u043b\u0442\u0443\u0437\u0435\u043d"
    ],
    "name:msa_x_preferred":[
        "Holthusen"
    ],
    "name:nld_x_preferred":[
        "Holthusen"
    ],
    "name:pol_x_preferred":[
        "Holthusen"
    ],
    "name:ron_x_preferred":[
        "Holthusen"
    ],
    "name:rus_x_preferred":[
        "\u0425\u043e\u043b\u044c\u0442\u0443\u0437\u0435\u043d"
    ],
    "name:spa_x_preferred":[
        "Holthusen"
    ],
    "name:srp_x_preferred":[
        "\u0425\u043e\u043b\u0442\u0443\u0441\u0435\u043d"
    ],
    "name:ukr_x_preferred":[
        "\u0413\u043e\u043b\u044c\u0442\u0443\u0437\u0435\u043d"
    ],
    "name:uzb_x_preferred":[
        "Holthusen"
    ],
    "name:vie_x_preferred":[
        "Holthusen"
    ],
    "name:vol_x_preferred":[
        "Holthusen"
    ],
    "name:war_x_preferred":[
        "Holthusen"
    ],
    "name:zho_x_preferred":[
        "\u970d\u5c14\u7279\u80e1\u68ee"
    ],
    "wof:name":"Holthusen",
    "wof:placetype":"neighbourhood"
},
  "geometry": {"coordinates":[7.31256,53.15389],"type":"Point"}
}