{
  "type": "Feature",
  "properties": {
    "gn:admin1_code":"9",
    "gn:admin2_code":"0.0",
    "gn:admin3_code":"10043.0",
    "gn:admin4_code":"10043112.0",
    "gn:asciiname":"Gennweiler",
    "gn:country_code":"DE",
    "gn:dem":294,
    "gn:feature_class":"P",
    "gn:feature_code":"PPL",
    "gn:name":"Gennweiler",
    "gn:population":0,
    "gn:timezone":"Europe/Berlin",
    "iso:country":"DE",
    "wof:name":"Gennweiler",
    "wof:placetype":"neighbourhood"
},
  "geometry": {"coordinates":[7.05843,49.37075],"type":"Point"}
}