{
  "type": "Feature",
  "properties": {
    "gn:admin1_code":"6",
    "gn:admin2_code":"0.0",
    "gn:admin3_code":"3254.0",
    "gn:admin4_code":"3254032.0",
    "gn:asciiname":"Gross Himstedt",
    "gn:country_code":"DE",
    "gn:dem":111,
    "gn:feature_class":"P",
    "gn:feature_code":"PPL",
    "gn:name":"Gro\u00df Himstedt",
    "gn:population":0,
    "gn:timezone":"Europe/Berlin",
    "iso:country":"DE",
    "wof:name":"Gross Himstedt",
    "wof:placetype":"neighbourhood"
},
  "geometry": {"coordinates":[10.20166,52.18635],"type":"Point"}
}