{
  "type": "Feature",
  "properties": {
    "gn:admin1_code":"5",
    "gn:admin2_code":"66.0",
    "gn:admin3_code":"6631.0",
    "gn:admin4_code":"6631006.0",
    "gn:asciiname":"Sulzhof",
    "gn:country_code":"DE",
    "gn:dem":303,
    "gn:feature_class":"P",
    "gn:feature_code":"PPL",
    "gn:name":"Sulzhof",
    "gn:population":0,
    "gn:timezone":"Europe/Berlin",
    "iso:country":"DE",
    "wof:name":"Sulzhof",
    "wof:placetype":"neighbourhood"
},
  "geometry": {"coordinates":[9.66179,50.49652],"type":"Point"}
}