{
  "type": "Feature",
  "properties": {
    "gn:admin1_code":"11",
    "gn:admin2_code":"0.0",
    "gn:admin3_code":"12067.0",
    "gn:admin4_code":"12067072.0",
    "gn:asciiname":"Briesen",
    "gn:country_code":"DE",
    "gn:dem":42,
    "gn:feature_class":"P",
    "gn:feature_code":"PPL",
    "gn:name":"Briesen",
    "gn:population":2374,
    "gn:timezone":"Europe/Berlin",
    "iso:country":"DE",
    "name:ceb_x_preferred":[
        "Briesen"
    ],
    "name:deu_x_preferred":[
        "Briesen"
    ],
    "name:epo_x_preferred":[
        "Briesen"
    ],
    "name:fra_x_preferred":[
        "Briesen"
    ],
    "name:hun_x_preferred":[
        "Briesen"
    ],
    "name:ita_x_preferred":[
        "Briesen"
    ],
    "name:nld_x_preferred":[
        "Briesen"
    ],
    "name:pol_x_preferred":[
        "Briesen"
    ],
    "name:srp_x_preferred":[
        "\u0411\u0440\u0438\u0437\u0435\u043d"
    ],
    "name:swe_x_preferred":[
        "Briesen"
    ],
    "wof:name":"Briesen",
    "wof:placetype":"neighbourhood",
    "wof:population":2374
},
  "geometry": {"coordinates":[14.27804,52.34383],"type":"Point"}
}