{
  "type": "Feature",
  "properties": {
    "gn:admin1_code":"2.0",
    "gn:admin2_code":"91.0",
    "gn:admin3_code":"9188.0",
    "gn:admin4_code":"9188113.0",
    "gn:asciiname":"Bachhausen",
    "gn:country_code":"DE",
    "gn:dem":635,
    "gn:feature_class":"P",
    "gn:feature_code":"PPL",
    "gn:name":"Bachhausen",
    "gn:population":0,
    "gn:timezone":"Europe/Berlin",
    "iso:country":"DE",
    "wof:name":"Bachhausen",
    "wof:placetype":"neighbourhood"
},
  "geometry": {"coordinates":[11.3887,47.95677],"type":"Point"}
}