{
  "type": "Feature",
  "properties": {
    "gn:admin1_code":"11",
    "gn:admin2_code":"0.0",
    "gn:admin3_code":"12061.0",
    "gn:admin4_code":"12061320.0",
    "gn:asciiname":"Stossdorfer See",
    "gn:country_code":"DE",
    "gn:dem":60,
    "gn:feature_class":"P",
    "gn:feature_code":"PPL",
    "gn:name":"Sto\u00dfdorfer See",
    "gn:population":0,
    "gn:timezone":"Europe/Berlin",
    "iso:country":"DE",
    "wof:name":"Stossdorfer See",
    "wof:placetype":"neighbourhood"
},
  "geometry": {"coordinates":[13.81667,51.83333],"type":"Point"}
}