{
  "type": "Feature",
  "properties": {
    "gn:admin1_code":"7",
    "gn:admin2_code":"55.0",
    "gn:admin3_code":"5558.0",
    "gn:admin4_code":"5558016.0",
    "gn:asciiname":"Hausduelmen",
    "gn:country_code":"DE",
    "gn:dem":50,
    "gn:feature_class":"P",
    "gn:feature_code":"PPL",
    "gn:name":"Hausd\u00fclmen",
    "gn:population":0,
    "gn:timezone":"Europe/Berlin",
    "iso:country":"DE",
    "wof:name":"Hausduelmen",
    "wof:placetype":"neighbourhood"
},
  "geometry": {"coordinates":[7.25607,51.81],"type":"Point"}
}