{
  "type": "Feature",
  "properties": {
    "iso:country":"DE",
    "wof:name":"Vahrenwald",
    "wof:placetype":"neighbourhood"
},
  "geometry": {"coordinates":[9.73337942539296,52.39648899268169],"type":"Point"}
}