{
  "type": "Feature",
  "properties": {
    "gn:admin1_code":"2.0",
    "gn:admin2_code":"097",
    "gn:admin3_code":"9777.0",
    "gn:admin4_code":"9777159.0",
    "gn:asciiname":"Weissbach",
    "gn:country_code":"DE",
    "gn:dem":877,
    "gn:feature_class":"P",
    "gn:feature_code":"PPL",
    "gn:name":"Wei\u00dfbach",
    "gn:population":0,
    "gn:timezone":"Europe/Berlin",
    "iso:country":"DE",
    "name:ceb_x_preferred":[
        "Wei\u00dfbach"
    ],
    "name:deu_x_preferred":[
        "Wei\u00dfbach"
    ],
    "name:epo_x_preferred":[
        "Wei\u00dfbach"
    ],
    "name:fra_x_preferred":[
        "Wei\u00dfbach"
    ],
    "name:ita_x_preferred":[
        "Wei\u00dfbach"
    ],
    "name:nld_x_preferred":[
        "Wei\u00dfbach"
    ],
    "name:pol_x_preferred":[
        "Wei\u00dfbach"
    ],
    "name:rus_x_preferred":[
        "\u0412\u0430\u0439\u0441\u0431\u0430\u0445"
    ],
    "name:srp_x_preferred":[
        "\u0412\u0430\u0458\u0441\u0431\u0430\u0445"
    ],
    "name:swe_x_preferred":[
        "Wei\u00dfbach"
    ],
    "name:vol_x_preferred":[
        "Wei\u00dfbach"
    ],
    "wof:name":"Weissbach",
    "wof:placetype":"neighbourhood"
},
  "geometry": {"coordinates":[10.55443,47.59441],"type":"Point"}
}