{
  "type": "Feature",
  "properties": {
    "gn:admin1_code":"1",
    "gn:admin2_code":"84.0",
    "gn:admin3_code":"8415.0",
    "gn:admin4_code":"8415034.0",
    "gn:asciiname":"Munzdorf",
    "gn:country_code":"DE",
    "gn:dem":694,
    "gn:feature_class":"P",
    "gn:feature_code":"PPL",
    "gn:name":"M\u00fcnzdorf",
    "gn:population":0,
    "gn:timezone":"Europe/Berlin",
    "iso:country":"DE",
    "wof:name":"Munzdorf",
    "wof:placetype":"neighbourhood"
},
  "geometry": {"coordinates":[9.47888,48.30837],"type":"Point"}
}