{
  "type": "Feature",
  "properties": {
    "gn:admin1_code":"2.0",
    "gn:admin2_code":"091",
    "gn:admin3_code":"9187.0",
    "gn:admin4_code":"9187177.0",
    "gn:asciiname":"Westerndorf",
    "gn:country_code":"DE",
    "gn:dem":475,
    "gn:feature_class":"P",
    "gn:feature_code":"PPL",
    "gn:name":"Westerndorf",
    "gn:population":0,
    "gn:timezone":"Europe/Berlin",
    "iso:country":"DE",
    "wof:name":"Westerndorf",
    "wof:placetype":"neighbourhood"
},
  "geometry": {"coordinates":[12.16161,47.85591],"type":"Point"}
}