{
  "type": "Feature",
  "properties": {
    "gn:admin1_code":"1",
    "gn:admin2_code":"83.0",
    "gn:admin3_code":"8316.0",
    "gn:admin4_code":"8316054.0",
    "gn:asciiname":"Schillingerberg",
    "gn:country_code":"DE",
    "gn:dem":622,
    "gn:feature_class":"P",
    "gn:feature_code":"PPL",
    "gn:name":"Schillingerberg",
    "gn:population":0,
    "gn:timezone":"Europe/Berlin",
    "iso:country":"DE",
    "wof:name":"Schillingerberg",
    "wof:placetype":"neighbourhood"
},
  "geometry": {"coordinates":[7.96096,48.16755],"type":"Point"}
}