{
  "type": "Feature",
  "properties": {
    "gn:admin1_code":"2",
    "gn:admin2_code":"97.0",
    "gn:admin3_code":"9774.0",
    "gn:admin4_code":"9774150.0",
    "gn:asciiname":"Hohenraunau",
    "gn:country_code":"DE",
    "gn:dem":559,
    "gn:feature_class":"P",
    "gn:feature_code":"PPL",
    "gn:name":"Hohenraunau",
    "gn:population":0,
    "gn:timezone":"Europe/Berlin",
    "iso:country":"DE",
    "wof:name":"Hohenraunau",
    "wof:placetype":"neighbourhood"
},
  "geometry": {"coordinates":[10.36619,48.21601],"type":"Point"}
}