{
  "type": "Feature",
  "properties": {
    "gn:admin1_code":"15",
    "gn:admin2_code":"0.0",
    "gn:admin3_code":"16065.0",
    "gn:admin4_code":"16065054.0",
    "gn:asciiname":"Sachsenburg",
    "gn:country_code":"DE",
    "gn:dem":134,
    "gn:feature_class":"P",
    "gn:feature_code":"PPL",
    "gn:name":"Sachsenburg",
    "gn:population":0,
    "gn:timezone":"Europe/Berlin",
    "iso:country":"DE",
    "wof:name":"Sachsenburg",
    "wof:placetype":"neighbourhood"
},
  "geometry": {"coordinates":[11.16282,51.28802],"type":"Point"}
}