{
  "type": "Feature",
  "properties": {
    "gn:admin1_code":"15",
    "gn:admin2_code":"0.0",
    "gn:admin3_code":"16065.0",
    "gn:admin4_code":"16065054.0",
    "gn:asciiname":"Sachsenburg",
    "gn:country_code":"DE",
    "gn:dem":134,
    "gn:feature_class":"P",
    "gn:feature_code":"PPL",
    "gn:name":"Sachsenburg",
    "gn:population":0,
    "gn:timezone":"Europe/Berlin",
    "iso:country":"DE",
    "name:ceb_x_preferred":[
        "Sachsenburg"
    ],
    "name:deu_x_preferred":[
        "Sachsenburg"
    ],
    "name:epo_x_preferred":[
        "Sachsenburg"
    ],
    "name:fas_x_preferred":[
        "\u0634\u0627\u06a9\u0633\u0646\u0628\u0631\u06af"
    ],
    "name:fra_x_preferred":[
        "Sachsenburg"
    ],
    "name:fur_x_preferred":[
        "Sachsenburg"
    ],
    "name:hun_x_preferred":[
        "Sachsenburg"
    ],
    "name:ita_x_preferred":[
        "Sachsenburg"
    ],
    "name:kaz_x_preferred":[
        "\u0417\u0430\u043a\u0441\u0435\u043d\u0431\u0443\u0440\u0433"
    ],
    "name:nld_x_preferred":[
        "Sachsenburg"
    ],
    "name:pol_x_preferred":[
        "Sachsenburg"
    ],
    "name:por_x_preferred":[
        "Sachsenburg"
    ],
    "name:rus_x_preferred":[
        "\u0417\u0430\u043a\u0441\u0435\u043d\u0431\u0443\u0440\u0433"
    ],
    "name:slk_x_preferred":[
        "Sachsenburg"
    ],
    "name:spa_x_preferred":[
        "Sachsenburg"
    ],
    "name:swe_x_preferred":[
        "Sachsenburg"
    ],
    "name:urd_x_preferred":[
        "\u0633\u0686\u0633\u0646\u0628\u0631\u06af"
    ],
    "name:uzb_x_preferred":[
        "Sachsenburg"
    ],
    "name:vie_x_preferred":[
        "Sachsenburg"
    ],
    "name:vol_x_preferred":[
        "Sachsenburg"
    ],
    "name:war_x_preferred":[
        "Sachsenburg"
    ],
    "name:zho_x_preferred":[
        "\u8428\u514b\u68ee\u5821"
    ],
    "wof:name":"Sachsenburg",
    "wof:placetype":"neighbourhood"
},
  "geometry": {"coordinates":[11.16282,51.28802],"type":"Point"}
}