{
  "type": "Feature",
  "properties": {
    "gn:admin1_code":"1",
    "gn:admin2_code":"83.0",
    "gn:admin3_code":"8337.0",
    "gn:admin4_code":"8337090.0",
    "gn:asciiname":"Schweikhof",
    "gn:country_code":"DE",
    "gn:dem":702,
    "gn:feature_class":"P",
    "gn:feature_code":"PPL",
    "gn:name":"Schweikhof",
    "gn:population":0,
    "gn:timezone":"Europe/Berlin",
    "iso:country":"DE",
    "wof:name":"Schweikhof",
    "wof:placetype":"neighbourhood"
},
  "geometry": {"coordinates":[7.98375,47.59641],"type":"Point"}
}