{
  "type": "Feature",
  "properties": {
    "gn:admin1_code":"6.0",
    "gn:admin2_code":"00",
    "gn:admin3_code":"3257.0",
    "gn:admin4_code":"3257003.0",
    "gn:asciiname":"Wiersen",
    "gn:country_code":"DE",
    "gn:dem":119,
    "gn:feature_class":"P",
    "gn:feature_code":"PPL",
    "gn:name":"Wiersen",
    "gn:population":0,
    "gn:timezone":"Europe/Berlin",
    "iso:country":"DE",
    "wof:name":"Wiersen",
    "wof:placetype":"neighbourhood"
},
  "geometry": {"coordinates":[9.30696,52.2669],"type":"Point"}
}