{
  "type": "Feature",
  "properties": {
    "gn:admin1_code":"10",
    "gn:admin2_code":"0.0",
    "gn:admin3_code":"1056.0",
    "gn:admin4_code":"1056035.0",
    "gn:asciiname":"UEberstoer",
    "gn:country_code":"DE",
    "gn:dem":13,
    "gn:feature_class":"P",
    "gn:feature_code":"PPL",
    "gn:name":"\u00dcberst\u00f6r",
    "gn:population":0,
    "gn:timezone":"Europe/Berlin",
    "iso:country":"DE",
    "wof:name":"UEberstoer",
    "wof:placetype":"neighbourhood"
},
  "geometry": {"coordinates":[9.77252,53.83793000000001],"type":"Point"}
}