{
  "type": "Feature",
  "properties": {
    "iso:country":"DE",
    "name:ceb_x_preferred":[
        "Bockum"
    ],
    "name:deu_x_preferred":[
        "Bockum"
    ],
    "name:epo_x_preferred":[
        "Bockum"
    ],
    "name:fas_x_preferred":[
        "\u0628\u0648\u06a9\u0648\u0645"
    ],
    "wof:name":"Bockum",
    "wof:placetype":"neighbourhood"
},
  "geometry": {"coordinates":[6.61522008688098,51.34538258872123],"type":"Point"}
}