{
  "type": "Feature",
  "properties": {
    "gn:admin1_code":"7",
    "gn:admin2_code":"51.0",
    "gn:admin3_code":"5124.0",
    "gn:admin4_code":"5124000.0",
    "gn:asciiname":"Heidt",
    "gn:country_code":"DE",
    "gn:dem":289,
    "gn:feature_class":"P",
    "gn:feature_code":"PPL",
    "gn:name":"Heidt",
    "gn:population":0,
    "gn:timezone":"Europe/Berlin",
    "iso:country":"DE",
    "wof:name":"Heidt",
    "wof:placetype":"neighbourhood"
},
  "geometry": {"coordinates":[7.18748,51.21587],"type":"Point"}
}