{
  "type": "Feature",
  "properties": {
    "gn:admin1_code":"2.0",
    "gn:admin2_code":"091",
    "gn:admin3_code":"9182.0",
    "gn:admin4_code":"9182123.0",
    "gn:asciiname":"Wendling",
    "gn:country_code":"DE",
    "gn:dem":700,
    "gn:feature_class":"P",
    "gn:feature_code":"PPL",
    "gn:name":"Wendling",
    "gn:population":0,
    "gn:timezone":"Europe/Berlin",
    "iso:country":"DE",
    "name:ceb_x_preferred":[
        "Wendling"
    ],
    "name:deu_x_preferred":[
        "Wendling"
    ],
    "name:fas_x_preferred":[
        "\u0648\u0646\u062f\u0644\u06cc\u0646\u06af"
    ],
    "name:fra_x_preferred":[
        "Wendling"
    ],
    "name:hun_x_preferred":[
        "Wendling"
    ],
    "name:ita_x_preferred":[
        "Wendling"
    ],
    "name:kaz_x_preferred":[
        "\u0412\u0435\u043d\u0434\u043b\u0438\u043d\u0433"
    ],
    "name:nld_x_preferred":[
        "Wendling"
    ],
    "name:pol_x_preferred":[
        "Wendling"
    ],
    "name:por_x_preferred":[
        "Wendling"
    ],
    "name:rus_x_preferred":[
        "\u0412\u0435\u043d\u0434\u043b\u0438\u043d\u0433"
    ],
    "name:slk_x_preferred":[
        "Wendling"
    ],
    "name:spa_x_preferred":[
        "Wendling"
    ],
    "name:swe_x_preferred":[
        "Wendling"
    ],
    "name:uzb_x_preferred":[
        "Wendling"
    ],
    "name:vol_x_preferred":[
        "Wendling"
    ],
    "name:war_x_preferred":[
        "Wendling"
    ],
    "name:zho_x_preferred":[
        "\u6e29\u5fb7\u7075"
    ],
    "wof:name":"Wendling",
    "wof:placetype":"neighbourhood"
},
  "geometry": {"coordinates":[11.9006,47.82653],"type":"Point"}
}