{
  "type": "Feature",
  "properties": {
    "gn:population":1462,
    "iso:country":"DE",
    "name:deu_x_preferred":[
        "Niederneisen"
    ],
    "name:epo_x_preferred":[
        "Niederneisen"
    ],
    "name:eus_x_preferred":[
        "Niederneisen"
    ],
    "name:fra_x_preferred":[
        "Niederneisen"
    ],
    "name:hbs_x_preferred":[
        "Niederneisen"
    ],
    "name:hun_x_preferred":[
        "Niederneisen"
    ],
    "name:ita_x_preferred":[
        "Niederneisen"
    ],
    "name:kaz_x_preferred":[
        "\u041d\u0438\u0434\u0435\u0440\u043d\u0430\u0439\u0437\u0435\u043d"
    ],
    "name:kir_x_preferred":[
        "\u041d\u0438\u0434\u0435\u0440\u043d\u0430\u0439\u0437\u0435\u043d"
    ],
    "name:msa_x_preferred":[
        "Niederneisen"
    ],
    "name:nld_x_preferred":[
        "Niederneisen"
    ],
    "name:pol_x_preferred":[
        "Niederneisen"
    ],
    "name:por_x_preferred":[
        "Niederneisen"
    ],
    "name:ron_x_preferred":[
        "Niederneisen"
    ],
    "name:rus_x_preferred":[
        "\u041d\u0438\u0434\u0435\u0440\u043d\u0430\u0439\u0437\u0435\u043d"
    ],
    "name:srp_x_preferred":[
        "\u041d\u0438\u0434\u0435\u0440\u043d\u0430\u0458\u0437\u0435\u043d"
    ],
    "name:uzb_x_preferred":[
        "Niederneisen"
    ],
    "name:vie_x_preferred":[
        "Niederneisen"
    ],
    "name:vol_x_preferred":[
        "Niederneisen"
    ],
    "name:war_x_preferred":[
        "Niederneisen"
    ],
    "name:zho_x_preferred":[
        "\u4e0b\u5948\u68ee"
    ],
    "qs:a0":"Bundesrepublik Deutschland",
    "qs:a1":"*Rheinland-Pfalz",
    "qs:a1r":"0",
    "qs:a2":"Rhein-Lahn-Kreis",
    "qs:adm0":"Bundesrepublik Deutschland",
    "qs:la_lc":"*",
    "qs:level":"locality",
    "qs:loc":"Niederneisen",
    "qs:loc_alt":"Niederneisen",
    "qs:pop":0,
    "qs:type":"buffered point",
    "wd:wordcount":30,
    "wof:name":"Niederneisen",
    "wof:placetype":"locality",
    "wof:population":1462
},
  "geometry": {"coordinates":[8.051827,50.329361],"type":"Point"}
}