{
  "type": "Feature",
  "properties": {
    "gn:admin1_code":"7.0",
    "gn:admin2_code":"53.0",
    "gn:admin3_code":"5382.0",
    "gn:admin4_code":"5382036.0",
    "gn:asciiname":"Amtsknechtswahn",
    "gn:country_code":"DE",
    "gn:dem":194,
    "gn:feature_class":"P",
    "gn:feature_code":"PPL",
    "gn:name":"Amtsknechtswahn",
    "gn:population":0,
    "gn:timezone":"Europe/Berlin",
    "iso:country":"DE",
    "name:und_x_variant":[
        "Amtknechtswahn",
        "Amtsknechtswahn"
    ],
    "wof:name":"Amtsknechtswahn",
    "wof:placetype":"neighbourhood"
},
  "geometry": {"coordinates":[7.40515,50.89339],"type":"Point"}
}