{
  "type": "Feature",
  "properties": {
    "gn:admin1_code":"2.0",
    "gn:admin2_code":"094",
    "gn:admin3_code":"9473.0",
    "gn:admin4_code":"9473144.0",
    "gn:asciiname":"Wiesenfeld",
    "gn:country_code":"DE",
    "gn:dem":308,
    "gn:feature_class":"P",
    "gn:feature_code":"PPL",
    "gn:name":"Wiesenfeld",
    "gn:population":0,
    "gn:timezone":"Europe/Berlin",
    "iso:country":"DE",
    "name:ceb_x_preferred":[
        "Wiesenfeld"
    ],
    "name:deu_x_preferred":[
        "Wiesenfeld"
    ],
    "name:epo_x_preferred":[
        "Wiesenfeld"
    ],
    "name:nld_x_preferred":[
        "Wiesenfeld"
    ],
    "name:pol_x_preferred":[
        "Wiesenfeld"
    ],
    "name:swe_x_preferred":[
        "Wiesenfeld"
    ],
    "wof:name":"Wiesenfeld",
    "wof:placetype":"neighbourhood"
},
  "geometry": {"coordinates":[10.90701,50.29992],"type":"Point"}
}