{
  "type": "Feature",
  "properties": {
    "gn:admin1_code":"1.0",
    "gn:admin2_code":"81.0",
    "gn:admin3_code":"8136.0",
    "gn:admin4_code":"8136002.0",
    "gn:asciiname":"Borrat",
    "gn:country_code":"DE",
    "gn:dem":490,
    "gn:feature_class":"P",
    "gn:feature_code":"PPL",
    "gn:name":"B\u00f6rrat",
    "gn:population":0,
    "gn:timezone":"Europe/Berlin",
    "iso:country":"DE",
    "wof:name":"Borrat",
    "wof:placetype":"neighbourhood"
},
  "geometry": {"coordinates":[9.93885,48.88615],"type":"Point"}
}