{
  "type": "Feature",
  "properties": {
    "gn:admin1_code":"1",
    "gn:admin2_code":"81.0",
    "gn:admin3_code":"8119.0",
    "gn:admin4_code":"8119044.0",
    "gn:asciiname":"Eulenhofle",
    "gn:country_code":"DE",
    "gn:dem":365,
    "gn:feature_class":"P",
    "gn:feature_code":"PPL",
    "gn:name":"Eulenh\u00f6fle",
    "gn:population":0,
    "gn:timezone":"Europe/Berlin",
    "iso:country":"DE",
    "wof:name":"Eulenhofle",
    "wof:placetype":"neighbourhood"
},
  "geometry": {"coordinates":[9.57012,48.97182],"type":"Point"}
}