{
  "type": "Feature",
  "properties": {
    "gn:admin1_code":"7.0",
    "gn:admin2_code":"59.0",
    "gn:admin3_code":"5978.0",
    "gn:admin4_code":"5978012.0",
    "gn:asciiname":"Bausenhagen",
    "gn:country_code":"DE",
    "gn:dem":194,
    "gn:feature_class":"P",
    "gn:feature_code":"PPL",
    "gn:name":"Bausenhagen",
    "gn:population":0,
    "gn:timezone":"Europe/Berlin",
    "iso:country":"DE",
    "name:deu_x_preferred":[
        "Bausenhagen"
    ],
    "name:fas_x_preferred":[
        "\u0628\u0627\u0648\u0632\u0646\u0647\u0627\u06af\u0646"
    ],
    "wof:name":"Bausenhagen",
    "wof:placetype":"neighbourhood"
},
  "geometry": {"coordinates":[7.8039,51.50628],"type":"Point"}
}