{
  "type": "Feature",
  "properties": {
    "gn:admin1_code":"6",
    "gn:admin2_code":"0.0",
    "gn:admin3_code":"3453.0",
    "gn:admin4_code":"3453011.0",
    "gn:asciiname":"Wachtum",
    "gn:country_code":"DE",
    "gn:dem":36,
    "gn:feature_class":"P",
    "gn:feature_code":"PPL",
    "gn:name":"Wachtum",
    "gn:population":0,
    "gn:timezone":"Europe/Berlin",
    "iso:country":"DE",
    "name:ceb_x_preferred":[
        "Wachtum"
    ],
    "name:fra_x_preferred":[
        "Wachtum"
    ],
    "name:nld_x_preferred":[
        "Wachtum"
    ],
    "wof:name":"Wachtum",
    "wof:placetype":"neighbourhood"
},
  "geometry": {"coordinates":[7.7153,52.79037],"type":"Point"}
}