{
  "type": "Feature",
  "properties": {
    "gn:admin1_code":"13.0",
    "gn:admin2_code":"0.0",
    "gn:admin3_code":"14625.0",
    "gn:admin4_code":"14625140.0",
    "gn:asciiname":"Beigut",
    "gn:country_code":"DE",
    "gn:dem":284,
    "gn:feature_class":"P",
    "gn:feature_code":"PPL",
    "gn:name":"Beigut",
    "gn:population":0,
    "gn:timezone":"Europe/Berlin",
    "iso:country":"DE",
    "wof:name":"Beigut",
    "wof:placetype":"neighbourhood"
},
  "geometry": {"coordinates":[14.12662,51.1329],"type":"Point"}
}