{
  "type": "Feature",
  "properties": {
    "gn:admin1_code":"2.0",
    "gn:admin2_code":"092",
    "gn:admin3_code":"9278.0",
    "gn:admin4_code":"9278197.0",
    "gn:asciiname":"Zinzenzell",
    "gn:country_code":"DE",
    "gn:dem":651,
    "gn:feature_class":"P",
    "gn:feature_code":"PPL",
    "gn:name":"Zinzenzell",
    "gn:population":0,
    "gn:timezone":"Europe/Berlin",
    "iso:country":"DE",
    "name:bar_x_preferred":[
        "Zinznzej"
    ],
    "name:deu_x_preferred":[
        "Zinzenzell"
    ],
    "name:fas_x_preferred":[
        "\u0633\u06cc\u0646\u0632\u0646\u0633\u0644"
    ],
    "wof:name":"Zinzenzell",
    "wof:placetype":"neighbourhood"
},
  "geometry": {"coordinates":[12.57916,49.07753],"type":"Point"}
}