{
  "type": "Feature",
  "properties": {
    "gn:admin1_code":"2",
    "gn:admin2_code":"92.0",
    "gn:admin3_code":"9272.0",
    "gn:admin4_code":"9272149.0",
    "gn:asciiname":"Luisenfels",
    "gn:country_code":"DE",
    "gn:dem":779,
    "gn:feature_class":"P",
    "gn:feature_code":"PPL",
    "gn:name":"Luisenfels",
    "gn:population":0,
    "gn:timezone":"Europe/Berlin",
    "iso:country":"DE",
    "wof:name":"Luisenfels",
    "wof:placetype":"neighbourhood"
},
  "geometry": {"coordinates":[13.35226,48.91022],"type":"Point"}
}