{
  "type": "Feature",
  "properties": {
    "gn:admin1_code":"5.0",
    "gn:admin2_code":"65.0",
    "gn:admin3_code":"6534.0",
    "gn:admin4_code":"6534014.0",
    "gn:asciiname":"Bortshausen",
    "gn:country_code":"DE",
    "gn:dem":199,
    "gn:feature_class":"P",
    "gn:feature_code":"PPL",
    "gn:name":"Bortshausen",
    "gn:population":0,
    "gn:timezone":"Europe/Berlin",
    "iso:country":"DE",
    "name:ceb_x_preferred":[
        "Bortshausen"
    ],
    "name:deu_x_preferred":[
        "Bortshausen"
    ],
    "name:fas_x_preferred":[
        "\u0628\u0648\u0631\u062a\u0633\u0647\u0627\u0648\u0632\u0646"
    ],
    "name:nld_x_preferred":[
        "Bortshausen"
    ],
    "wof:name":"Bortshausen",
    "wof:placetype":"neighbourhood"
},
  "geometry": {"coordinates":[8.77541,50.75108],"type":"Point"}
}