{
  "type": "Feature",
  "properties": {
    "gn:admin1_code":"1",
    "gn:admin2_code":"83.0",
    "gn:admin3_code":"8336.0",
    "gn:admin4_code":"8336081.0",
    "gn:asciiname":"Schweigmatt",
    "gn:country_code":"DE",
    "gn:dem":715,
    "gn:feature_class":"P",
    "gn:feature_code":"PPL",
    "gn:name":"Schweigmatt",
    "gn:population":0,
    "gn:timezone":"Europe/Berlin",
    "iso:country":"DE",
    "name:deu_x_preferred":[
        "Schweigmatt"
    ],
    "wof:name":"Schweigmatt",
    "wof:placetype":"neighbourhood"
},
  "geometry": {"coordinates":[7.88236,47.68092],"type":"Point"}
}