{
  "type": "Feature",
  "properties": {
    "gn:admin1_code":"15",
    "gn:admin2_code":"0.0",
    "gn:admin3_code":"16061.0",
    "gn:admin4_code":"16061045.0",
    "gn:asciiname":"Kalteneber",
    "gn:country_code":"DE",
    "gn:dem":456,
    "gn:feature_class":"P",
    "gn:feature_code":"PPL",
    "gn:name":"Kalteneber",
    "gn:population":0,
    "gn:timezone":"Europe/Berlin",
    "iso:country":"DE",
    "wof:name":"Kalteneber",
    "wof:placetype":"neighbourhood"
},
  "geometry": {"coordinates":[10.13748,51.31882],"type":"Point"}
}