{
  "type": "Feature",
  "properties": {
    "gn:admin1_code":"2.0",
    "gn:admin2_code":"095",
    "gn:admin3_code":"9571.0",
    "gn:admin4_code":"9571218.0",
    "gn:asciiname":"Wornitzhofen",
    "gn:country_code":"DE",
    "gn:dem":439,
    "gn:feature_class":"P",
    "gn:feature_code":"PPL",
    "gn:name":"W\u00f6rnitzhofen",
    "gn:population":0,
    "gn:timezone":"Europe/Berlin",
    "iso:country":"DE",
    "wof:name":"Wornitzhofen",
    "wof:placetype":"neighbourhood"
},
  "geometry": {"coordinates":[10.4516,49.04561],"type":"Point"}
}