{
  "type": "Feature",
  "properties": {
    "gn:admin1_code":"2",
    "gn:admin2_code":"91.0",
    "gn:admin3_code":"9171.0",
    "gn:admin4_code":"9171113.0",
    "gn:asciiname":"Thalhausen",
    "gn:country_code":"DE",
    "gn:dem":440,
    "gn:feature_class":"P",
    "gn:feature_code":"PPL",
    "gn:name":"Thalhausen",
    "gn:population":0,
    "gn:timezone":"Europe/Berlin",
    "iso:country":"DE",
    "name:ceb_x_preferred":[
        "Thalhausen"
    ],
    "name:deu_x_preferred":[
        "Thalhausen"
    ],
    "name:epo_x_preferred":[
        "Thalhausen"
    ],
    "name:eus_x_preferred":[
        "Thalhausen"
    ],
    "name:fas_x_preferred":[
        "\u062a\u0627\u0644\u0647\u0627\u0648\u0632\u0646"
    ],
    "name:fra_x_preferred":[
        "Thalhausen"
    ],
    "name:hun_x_preferred":[
        "Thalhausen"
    ],
    "name:ita_x_preferred":[
        "Thalhausen"
    ],
    "name:msa_x_preferred":[
        "Thalhausen"
    ],
    "name:nld_x_preferred":[
        "Thalhausen"
    ],
    "name:pol_x_preferred":[
        "Thalhausen"
    ],
    "name:por_x_preferred":[
        "Thalhausen"
    ],
    "name:ron_x_preferred":[
        "Thalhausen"
    ],
    "name:rus_x_preferred":[
        "\u0422\u0430\u043b\u044c\u0445\u0430\u0443\u0437\u0435\u043d"
    ],
    "name:spa_x_preferred":[
        "Thalhausen"
    ],
    "name:srp_x_preferred":[
        "\u0422\u0430\u043b\u0445\u0430\u0443\u0437\u0435\u043d"
    ],
    "name:ukr_x_preferred":[
        "\u0422\u0430\u043b\u044c\u0433\u0430\u0443\u0437\u0435\u043d"
    ],
    "name:uzb_x_preferred":[
        "Thalhausen"
    ],
    "name:vie_x_preferred":[
        "Thalhausen"
    ],
    "name:vol_x_preferred":[
        "Thalhausen"
    ],
    "name:war_x_preferred":[
        "Thalhausen"
    ],
    "name:zho_x_preferred":[
        "\u5854\u5c14\u8c6a\u68ee"
    ],
    "wof:name":"Thalhausen",
    "wof:placetype":"neighbourhood"
},
  "geometry": {"coordinates":[12.74447,48.16798],"type":"Point"}
}