{
  "type": "Feature",
  "properties": {
    "gn:admin1_code":"1",
    "gn:admin2_code":"81.0",
    "gn:admin3_code":"8136.0",
    "gn:admin4_code":"8136065.0",
    "gn:asciiname":"Lindach",
    "gn:country_code":"DE",
    "gn:dem":463,
    "gn:feature_class":"P",
    "gn:feature_code":"PPL",
    "gn:name":"Lindach",
    "gn:population":0,
    "gn:timezone":"Europe/Berlin",
    "iso:country":"DE",
    "name:chv_x_preferred":[
        "\u041b\u0438\u043d\u0434\u0430\u0445"
    ],
    "name:deu_x_preferred":[
        "Lindach"
    ],
    "wof:name":"Lindach",
    "wof:placetype":"neighbourhood"
},
  "geometry": {"coordinates":[9.81731,48.83193],"type":"Point"}
}