{
  "type": "Feature",
  "properties": {
    "gn:country":"DE",
    "gn:fcode":"PPL",
    "gn:population":0,
    "iso:country":"DE",
    "name:ceb_x_preferred":[
        "Hohenkirchen"
    ],
    "name:deu_x_preferred":[
        "Hohenkirchen"
    ],
    "name:epo_x_preferred":[
        "Hohenkirchen"
    ],
    "name:fas_x_preferred":[
        "\u0647\u0648\u0647\u0646\u06a9\u06cc\u0631\u0634\u0646"
    ],
    "name:fra_x_preferred":[
        "Hohenkirchen"
    ],
    "name:hun_x_preferred":[
        "Hohenkirchen"
    ],
    "name:ita_x_preferred":[
        "Hohenkirchen"
    ],
    "name:kaz_x_preferred":[
        "\u0425\u043e\u044d\u043d\u043a\u0438\u0440\u0445\u0435\u043d"
    ],
    "name:kir_x_preferred":[
        "\u0425\u043e\u044d\u043d\u043a\u0438\u0440\u0445\u0435\u043d"
    ],
    "name:mkd_x_preferred":[
        "\u0425\u043e\u0435\u043d\u043a\u0438\u0440\u0445\u0435\u043d"
    ],
    "name:msa_x_preferred":[
        "Hohenkirchen"
    ],
    "name:nld_x_preferred":[
        "Hohenkirchen"
    ],
    "name:pol_x_preferred":[
        "Hohenkirchen"
    ],
    "name:por_x_preferred":[
        "Hohenkirchen"
    ],
    "name:ron_x_preferred":[
        "Hohenkirchen"
    ],
    "name:rus_x_preferred":[
        "\u0425\u043e\u044d\u043d\u043a\u0438\u0440\u0445\u0435\u043d"
    ],
    "name:spa_x_preferred":[
        "Hohenkirchen"
    ],
    "name:srp_x_preferred":[
        "\u0425\u043e\u0435\u043d\u043a\u0438\u0440\u0445\u0435\u043d"
    ],
    "name:ukr_x_preferred":[
        "\u0413\u043e\u0435\u043d\u043a\u0456\u0440\u0445\u0435\u043d"
    ],
    "name:und_x_variant":[
        "Hoher R\u00fccken"
    ],
    "name:uzb_x_preferred":[
        "Hohenkirchen"
    ],
    "name:vie_x_preferred":[
        "Hohenkirchen"
    ],
    "name:vol_x_preferred":[
        "Hohenkirchen"
    ],
    "name:war_x_preferred":[
        "Hohenkirchen"
    ],
    "name:zho_x_preferred":[
        "\u970d\u6069\u57fa\u5174"
    ],
    "qs_pg:aaroncc":"DE",
    "qs_pg:gn_country":"DE",
    "qs_pg:gn_fcode":"PPL",
    "qs_pg:gn_pop":0,
    "qs_pg:name":"Hohenkirchen",
    "qs_pg:name_adm0":"Deutschland",
    "qs_pg:name_adm1":"Niedersachsen",
    "qs_pg:photos_9r":0,
    "qs_pg:photos_sr":0,
    "qs_pg:pop_sr":0,
    "qs_pg:qs_pg_placetype":"locality",
    "qs_pg:qs_pg_placetype_gp":"Town",
    "qs_pg:woe_adm0":23424829,
    "woe:adm0_id":23424829,
    "woe:name_adm0":"Deutschland",
    "woe:name_adm1":"Niedersachsen",
    "woe:placetype":"Town",
    "wof:name":"Hohenkirchen",
    "wof:placetype":"neighbourhood"
},
  "geometry": {"coordinates":[7.9174,53.6626],"type":"Point"}
}