{
  "type": "Feature",
  "properties": {
    "gn:admin1_code":"2.0",
    "gn:admin2_code":"92.0",
    "gn:admin3_code":"9272.0",
    "gn:admin4_code":"9272128.0",
    "gn:asciiname":"Barnreuth",
    "gn:country_code":"DE",
    "gn:dem":550,
    "gn:feature_class":"P",
    "gn:feature_code":"PPL",
    "gn:name":"B\u00e4rnreuth",
    "gn:population":0,
    "gn:timezone":"Europe/Berlin",
    "iso:country":"DE",
    "wof:name":"Barnreuth",
    "wof:placetype":"neighbourhood"
},
  "geometry": {"coordinates":[13.29955,48.85455],"type":"Point"}
}