{
  "type": "Feature",
  "properties": {
    "iso:country":"DE",
    "oa:elevation_ft":"814",
    "oa:type":"small_airport",
    "woe:hierarchy":{
        "country_id":23424829,
        "county_id":12596774,
        "localadmin_id":12636111,
        "planet_id":1,
        "state_id":2345482
    },
    "wof:name":"Sportflugplatz Ochsenfurt",
    "wof:placetype":"campus"
},
  "geometry": {"coordinates":[10.0715,49.674167],"type":"Point"}
}