{
  "type": "Feature",
  "properties": {
    "iso:country":"DE",
    "name:deu_x_preferred":[
        "Flugplatz Ochsenfurt"
    ],
    "name:eng_x_preferred":[
        "Ochsenfurt Airport"
    ],
    "name:eng_x_variant":[
        "EDGJ",
        "Ochsenfurt airfield"
    ],
    "name:fin_x_preferred":[
        "Ochsenfurts flygplats"
    ],
    "name:fra_x_preferred":[
        "Ochsenfurts flygplats"
    ],
    "name:ind_x_preferred":[
        "Ochsenfurts flygplats"
    ],
    "name:ita_x_preferred":[
        "Ochsenfurts flygplats"
    ],
    "name:msa_x_preferred":[
        "Lapangan Terbang Ochsenfurt"
    ],
    "name:nld_x_preferred":[
        "Ochsenfurts flygplats"
    ],
    "name:por_x_preferred":[
        "Ochsenfurts flygplats"
    ],
    "name:spa_x_preferred":[
        "Ochsenfurts flygplats"
    ],
    "name:swe_x_preferred":[
        "Ochsenfurts flygplats"
    ],
    "oa:elevation_ft":"814",
    "oa:type":"small_airport",
    "woe:hierarchy":{
        "country_id":23424829,
        "county_id":12596774,
        "localadmin_id":12636111,
        "planet_id":1,
        "state_id":2345482
    },
    "wof:name":"Sportflugplatz Ochsenfurt",
    "wof:placetype":"campus"
},
  "geometry": {"coordinates":[10.0715,49.674167],"type":"Point"}
}