{
  "type": "Feature",
  "properties": {
    "gn:admin1_code":"2.0",
    "gn:admin2_code":"91.0",
    "gn:admin3_code":"9189.0",
    "gn:admin4_code":"9189154.0",
    "gn:asciiname":"Anning",
    "gn:country_code":"DE",
    "gn:dem":524,
    "gn:feature_class":"P",
    "gn:feature_code":"PPL",
    "gn:name":"Anning",
    "gn:population":0,
    "gn:timezone":"Europe/Berlin",
    "iso:country":"DE",
    "name:ceb_x_preferred":[
        "Anning"
    ],
    "name:deu_x_preferred":[
        "Anning"
    ],
    "name:fra_x_preferred":[
        "Anning"
    ],
    "name:nds_x_preferred":[
        "Anning"
    ],
    "name:nld_x_preferred":[
        "Anning"
    ],
    "name:nor_x_preferred":[
        "Anning"
    ],
    "name:rus_x_preferred":[
        "\u0410\u043d\u044c\u043d\u0438\u043d"
    ],
    "name:swe_x_preferred":[
        "Anning"
    ],
    "name:vie_x_preferred":[
        "An Ninh"
    ],
    "wof:name":"Anning",
    "wof:placetype":"neighbourhood"
},
  "geometry": {"coordinates":[12.56481,47.98542],"type":"Point"}
}