{
  "type": "Feature",
  "properties": {
    "gn:admin1_code":"11",
    "gn:admin2_code":"0.0",
    "gn:admin3_code":"12067.0",
    "gn:admin4_code":"12067438.0",
    "gn:asciiname":"Bremsdorfer Muehle",
    "gn:country_code":"DE",
    "gn:dem":63,
    "gn:feature_class":"P",
    "gn:feature_code":"PPL",
    "gn:name":"Bremsdorfer M\u00fchle",
    "gn:population":0,
    "gn:timezone":"Europe/Berlin",
    "iso:country":"DE",
    "wof:name":"Bremsdorfer Muehle",
    "wof:placetype":"neighbourhood"
},
  "geometry": {"coordinates":[14.46213,52.13544],"type":"Point"}
}