{
  "type": "Feature",
  "properties": {
    "iso:country":"DE",
    "name:deu_x_preferred":[
        "Broich"
    ],
    "name:nld_x_preferred":[
        "Broich"
    ],
    "name:pol_x_preferred":[
        "Broich"
    ],
    "name:rus_x_preferred":[
        "\u0411\u0440\u043e\u0439\u0445"
    ],
    "name:unk_x_variant":[
        "Broich"
    ],
    "qs:gn_adm0_cc":"DE",
    "qs:gn_fcode":"PPLX",
    "qs:gn_local":2867838,
    "qs:gn_nam_loc":"M\u00fclheim an der Ruhr, Nordrhein-Westfalen, DE",
    "qs:gn_namadm1":"07",
    "qs:gn_name":"Broich",
    "qs:local_max":6349,
    "qs:local_sum":9575,
    "qs:localhoods":14,
    "qs:name":"Broich",
    "qs:name_adm0":"Deutschland",
    "qs:name_adm1":"Nordrhein-Westfalen",
    "qs:name_adm2":"Stadtkreis M\u00fclheim an der Ruhr",
    "qs:name_lau":"Stadtteil M\u00fclheim an der Ruhr",
    "qs:name_local":"Stadtteil M\u00fclheim an der Ruhr",
    "qs:photo_max":5921,
    "qs:photo_sum":6349,
    "qs:placetype":"Suburb",
    "qs:quad_count":29,
    "qs:woe_adm0":23424829,
    "qs:woe_adm1":2345487,
    "qs:woe_adm2":12597066,
    "qs:woe_lau":28350219,
    "qs:woe_local":28350219,
    "qs:woe_ver":"7.10.0",
    "wd:wordcount":151,
    "wof:lang":[
        "ger"
    ],
    "wof:name":"Broich",
    "wof:placetype":"neighbourhood"
},
  "geometry": {"coordinates":[6.861359,51.425357],"type":"Point"}
}