{
  "type": "Feature",
  "properties": {
    "iso:country":"DE",
    "name:deu_x_preferred":[
        "Oberholtorf"
    ],
    "name:unk_x_variant":[
        "Oberholtorf"
    ],
    "qs:gn_adm0_cc":"DE",
    "qs:gn_local":2946447,
    "qs:gn_nam_loc":"bonn",
    "qs:gn_namadm1":"07",
    "qs:local_max":6309,
    "qs:local_sum":17418,
    "qs:localhoods":14,
    "qs:name":"Oberholtorf",
    "qs:name_adm0":"Deutschland",
    "qs:name_adm1":"Nordrhein-Westfalen",
    "qs:name_adm2":"Stadtkreis Bonn",
    "qs:name_lau":"Stadtteil Holtorf",
    "qs:name_local":"Bonn",
    "qs:photo_max":60,
    "qs:photo_sum":418,
    "qs:placetype":"Suburb",
    "qs:quad_count":50,
    "qs:woe_adm0":23424829,
    "qs:woe_adm1":2345487,
    "qs:woe_adm2":12597065,
    "qs:woe_lau":26822011,
    "qs:woe_local":640161,
    "qs:woe_ver":"7.10.0",
    "wof:lang":[
        "ger"
    ],
    "wof:name":"Oberholtorf",
    "wof:placetype":"neighbourhood"
},
  "geometry": {"coordinates":[7.186922,50.724377],"type":"Point"}
}