{
  "type": "Feature",
  "properties": {
    "gn:admin1_code":"13",
    "gn:admin2_code":"0.0",
    "gn:admin3_code":"14521.0",
    "gn:admin4_code":"14521510.0",
    "gn:asciiname":"Oberscheibe",
    "gn:country_code":"DE",
    "gn:dem":601,
    "gn:feature_class":"P",
    "gn:feature_code":"PPL",
    "gn:name":"Oberscheibe",
    "gn:population":0,
    "gn:timezone":"Europe/Berlin",
    "iso:country":"DE",
    "wof:name":"Oberscheibe",
    "wof:placetype":"neighbourhood"
},
  "geometry": {"coordinates":[12.89382,50.53518],"type":"Point"}
}