{
  "type": "Feature",
  "properties": {
    "gn:admin1_code":"2",
    "gn:admin2_code":"94.0",
    "gn:admin3_code":"9472.0",
    "gn:admin4_code":"9472167.0",
    "gn:asciiname":"Schobertsreuth",
    "gn:country_code":"DE",
    "gn:dem":445,
    "gn:feature_class":"P",
    "gn:feature_code":"PPL",
    "gn:name":"Schobertsreuth",
    "gn:population":0,
    "gn:timezone":"Europe/Berlin",
    "iso:country":"DE",
    "wof:name":"Schobertsreuth",
    "wof:placetype":"neighbourhood"
},
  "geometry": {"coordinates":[11.47579,49.89097],"type":"Point"}
}