{
  "type": "Feature",
  "properties": {
    "gn:admin1_code":"13",
    "gn:admin2_code":"0.0",
    "gn:admin3_code":"14521.0",
    "gn:admin4_code":"14521150.0",
    "gn:asciiname":"Neue Haeuser",
    "gn:country_code":"DE",
    "gn:dem":456,
    "gn:feature_class":"P",
    "gn:feature_code":"PPL",
    "gn:name":"Neue H\u00e4user",
    "gn:population":0,
    "gn:timezone":"Europe/Berlin",
    "iso:country":"DE",
    "wof:name":"Neue Haeuser",
    "wof:placetype":"neighbourhood"
},
  "geometry": {"coordinates":[13.01974,50.68283],"type":"Point"}
}