{
  "type": "Feature",
  "properties": {
    "gn:admin1_code":"13",
    "gn:admin2_code":"0.0",
    "gn:admin3_code":"14627.0",
    "gn:admin4_code":"14627040.0",
    "gn:asciiname":"Sageritz",
    "gn:country_code":"DE",
    "gn:dem":112,
    "gn:feature_class":"P",
    "gn:feature_code":"PPL",
    "gn:name":"Sageritz",
    "gn:population":0,
    "gn:timezone":"Europe/Berlin",
    "iso:country":"DE",
    "wof:name":"Sageritz",
    "wof:placetype":"neighbourhood"
},
  "geometry": {"coordinates":[13.38255,51.32064],"type":"Point"}
}