{
  "type": "Feature",
  "properties": {
    "gn:admin1_code":"1",
    "gn:admin2_code":"84.0",
    "gn:admin3_code":"8426.0",
    "gn:admin4_code":"8426008.0",
    "gn:asciiname":"Waldhausen",
    "gn:country_code":"DE",
    "gn:dem":540,
    "gn:feature_class":"P",
    "gn:feature_code":"PPL",
    "gn:name":"Waldhausen",
    "gn:population":0,
    "gn:timezone":"Europe/Berlin",
    "iso:country":"DE",
    "name:ces_x_preferred":[
        "Waldhausen"
    ],
    "name:deu_x_preferred":[
        "Waldhausen"
    ],
    "name:epo_x_preferred":[
        "Waldhausen"
    ],
    "name:fas_x_preferred":[
        "\u0648\u0627\u0644\u062f\u0647\u0648\u0633\u0646"
    ],
    "name:fra_x_preferred":[
        "Waldhausen"
    ],
    "name:hun_x_preferred":[
        "Waldhausen"
    ],
    "name:ita_x_preferred":[
        "Waldhausen"
    ],
    "name:kaz_x_preferred":[
        "\u0425\u0438\u0440\u0448\u0435\u043d\u0448\u043b\u0430\u0433"
    ],
    "name:nld_x_preferred":[
        "Waldhausen"
    ],
    "name:pol_x_preferred":[
        "Waldhausen"
    ],
    "name:por_x_preferred":[
        "Waldhausen"
    ],
    "name:rus_x_preferred":[
        "\u0412\u0430\u043b\u044c\u0434\u0445\u0430\u0443\u0437\u0435\u043d"
    ],
    "name:slk_x_preferred":[
        "Waldhausen"
    ],
    "name:spa_x_preferred":[
        "Waldhausen"
    ],
    "name:uzb_x_preferred":[
        "Waldhausen"
    ],
    "name:vol_x_preferred":[
        "Waldhausen"
    ],
    "name:war_x_preferred":[
        "Waldhausen"
    ],
    "name:zho_x_preferred":[
        "\u74e6\u5c14\u5fb7\u8c6a\u68ee"
    ],
    "wof:name":"Waldhausen",
    "wof:placetype":"neighbourhood"
},
  "geometry": {"coordinates":[9.43764,48.12628],"type":"Point"}
}