{
  "type": "Feature",
  "properties": {
    "gn:admin1_code":"1",
    "gn:admin2_code":"84.0",
    "gn:admin3_code":"8436.0",
    "gn:admin4_code":"8436064.0",
    "gn:asciiname":"Eschau",
    "gn:country_code":"DE",
    "gn:dem":518,
    "gn:feature_class":"P",
    "gn:feature_code":"PPL",
    "gn:name":"Eschau",
    "gn:population":0,
    "gn:timezone":"Europe/Berlin",
    "iso:country":"DE",
    "name:bar_x_preferred":[
        "Eschau"
    ],
    "name:dan_x_preferred":[
        "Eschau"
    ],
    "name:deu_x_preferred":[
        "Eschau"
    ],
    "name:epo_x_preferred":[
        "Eschau"
    ],
    "name:fas_x_preferred":[
        "\u0627\u0634\u0627\u0626\u0648"
    ],
    "name:fra_x_preferred":[
        "Eschau"
    ],
    "name:hun_x_preferred":[
        "Eschau"
    ],
    "name:hye_x_preferred":[
        "\u0537\u0577\u0561\u0578\u0582"
    ],
    "name:ind_x_preferred":[
        "Eschau"
    ],
    "name:ita_x_preferred":[
        "Eschau"
    ],
    "name:jpn_x_preferred":[
        "\u30a8\u30c3\u30b7\u30e3\u30a6"
    ],
    "name:kaz_x_preferred":[
        "\u042d\u0448\u0430\u0443"
    ],
    "name:kir_x_preferred":[
        "\u042d\u0448\u0430\u0443"
    ],
    "name:lmo_x_preferred":[
        "Eschau"
    ],
    "name:msa_x_preferred":[
        "Eschau"
    ],
    "name:nld_x_preferred":[
        "Eschau"
    ],
    "name:pol_x_preferred":[
        "Eschau"
    ],
    "name:por_x_preferred":[
        "Eschau"
    ],
    "name:ron_x_preferred":[
        "Eschau"
    ],
    "name:rus_x_preferred":[
        "\u042d\u0448\u0430\u0443"
    ],
    "name:srp_x_preferred":[
        "\u0415\u0448\u0430\u0443"
    ],
    "name:ukr_x_preferred":[
        "\u0415\u0448\u0430\u0443"
    ],
    "name:uzb_x_preferred":[
        "Eschau"
    ],
    "name:vol_x_preferred":[
        "Eschau"
    ],
    "name:war_x_preferred":[
        "Eschau"
    ],
    "wof:name":"Eschau",
    "wof:placetype":"neighbourhood"
},
  "geometry": {"coordinates":[9.5304,47.77359000000001],"type":"Point"}
}