{
  "type": "Feature",
  "properties": {
    "gn:admin1_code":"2",
    "gn:admin2_code":"94.0",
    "gn:admin3_code":"9475.0",
    "gn:admin4_code":"9475161.0",
    "gn:asciiname":"Schwesendorf",
    "gn:country_code":"DE",
    "gn:dem":548,
    "gn:feature_class":"P",
    "gn:feature_code":"PPL",
    "gn:name":"Schwesendorf",
    "gn:population":0,
    "gn:timezone":"Europe/Berlin",
    "iso:country":"DE",
    "wof:name":"Schwesendorf",
    "wof:placetype":"neighbourhood"
},
  "geometry": {"coordinates":[12.07054,50.30409],"type":"Point"}
}