{
  "type": "Feature",
  "properties": {
    "gn:admin1_code":"1",
    "gn:admin2_code":"83.0",
    "gn:admin3_code":"8326.0",
    "gn:admin4_code":"8326020.0",
    "gn:asciiname":"Oberlehmannsgrund",
    "gn:country_code":"DE",
    "gn:dem":974,
    "gn:feature_class":"P",
    "gn:feature_code":"PPL",
    "gn:name":"Oberlehmannsgrund",
    "gn:population":0,
    "gn:timezone":"Europe/Berlin",
    "iso:country":"DE",
    "wof:name":"Oberlehmannsgrund",
    "wof:placetype":"neighbourhood"
},
  "geometry": {"coordinates":[8.13191,48.05408],"type":"Point"}
}