{
  "type": "Feature",
  "properties": {
    "gn:admin1_code":"8",
    "gn:admin2_code":"0.0",
    "gn:admin3_code":"7132.0",
    "gn:admin4_code":"7132054.0",
    "gn:asciiname":"Oberhoevels",
    "gn:country_code":"DE",
    "gn:dem":217,
    "gn:feature_class":"P",
    "gn:feature_code":"PPL",
    "gn:name":"Oberh\u00f6vels",
    "gn:population":0,
    "gn:timezone":"Europe/Berlin",
    "iso:country":"DE",
    "wof:name":"Oberhoevels",
    "wof:placetype":"neighbourhood"
},
  "geometry": {"coordinates":[7.77996,50.79772],"type":"Point"}
}