{
  "type": "Feature",
  "properties": {
    "gn:admin1_code":"1",
    "gn:admin2_code":"81.0",
    "gn:admin3_code":"8118.0",
    "gn:admin4_code":"8118021.0",
    "gn:asciiname":"Holzweiler Hof",
    "gn:country_code":"DE",
    "gn:dem":269,
    "gn:feature_class":"P",
    "gn:feature_code":"PPL",
    "gn:name":"Holzweiler Hof",
    "gn:population":0,
    "gn:timezone":"Europe/Berlin",
    "iso:country":"DE",
    "wof:name":"Holzweiler Hof",
    "wof:placetype":"neighbourhood"
},
  "geometry": {"coordinates":[9.25009,49.0118],"type":"Point"}
}