{
  "type": "Feature",
  "properties": {
    "gn:admin1_code":"11",
    "gn:admin2_code":"0.0",
    "gn:admin3_code":"12068.0",
    "gn:admin4_code":"12068280.0",
    "gn:asciiname":"Siedlung Werbellinsee",
    "gn:country_code":"DE",
    "gn:dem":50,
    "gn:feature_class":"P",
    "gn:feature_code":"PPL",
    "gn:name":"Siedlung Werbellinsee",
    "gn:population":0,
    "gn:timezone":"Europe/Berlin",
    "iso:country":"DE",
    "wof:name":"Siedlung Werbellinsee",
    "wof:placetype":"neighbourhood"
},
  "geometry": {"coordinates":[12.94189,52.92691],"type":"Point"}
}