{
  "type": "Feature",
  "properties": {
    "gn:admin1_code":"1",
    "gn:admin2_code":"81.0",
    "gn:admin3_code":"8117.0",
    "gn:admin4_code":"8117010.0",
    "gn:asciiname":"Schnittlingen",
    "gn:country_code":"DE",
    "gn:dem":652,
    "gn:feature_class":"P",
    "gn:feature_code":"PPL",
    "gn:name":"Schnittlingen",
    "gn:population":0,
    "gn:timezone":"Europe/Berlin",
    "iso:country":"DE",
    "wof:name":"Schnittlingen",
    "wof:placetype":"neighbourhood"
},
  "geometry": {"coordinates":[9.87568,48.67464],"type":"Point"}
}