{
  "type": "Feature",
  "properties": {
    "gn:admin1_code":"5",
    "gn:admin2_code":"64.0",
    "gn:admin3_code":"6437.0",
    "gn:admin4_code":"6437007.0",
    "gn:asciiname":"Ober Gersprenz",
    "gn:country_code":"DE",
    "gn:dem":190,
    "gn:feature_class":"P",
    "gn:feature_code":"PPL",
    "gn:name":"Ober Gersprenz",
    "gn:population":0,
    "gn:timezone":"Europe/Berlin",
    "iso:country":"DE",
    "wof:name":"Ober Gersprenz",
    "wof:placetype":"neighbourhood"
},
  "geometry": {"coordinates":[8.86667,49.73333],"type":"Point"}
}