{
  "type": "Feature",
  "properties": {
    "gn:admin1_code":"13",
    "gn:admin2_code":"0.0",
    "gn:admin3_code":"14523.0",
    "gn:admin4_code":"14523120.0",
    "gn:asciiname":"Spitzhaeuschen",
    "gn:country_code":"DE",
    "gn:dem":540,
    "gn:feature_class":"P",
    "gn:feature_code":"PPL",
    "gn:name":"Spitzh\u00e4uschen",
    "gn:population":0,
    "gn:timezone":"Europe/Berlin",
    "iso:country":"DE",
    "wof:name":"Spitzhaeuschen",
    "wof:placetype":"neighbourhood"
},
  "geometry": {"coordinates":[12.36776,50.48627000000001],"type":"Point"}
}