{
  "type": "Feature",
  "properties": {
    "gn:admin1_code":"2",
    "gn:admin2_code":"92.0",
    "gn:admin3_code":"9273.0",
    "gn:admin4_code":"9273159.0",
    "gn:asciiname":"Rothenbugl",
    "gn:country_code":"DE",
    "gn:dem":518,
    "gn:feature_class":"P",
    "gn:feature_code":"PPL",
    "gn:name":"Rothenb\u00fcgl",
    "gn:population":0,
    "gn:timezone":"Europe/Berlin",
    "iso:country":"DE",
    "wof:name":"Rothenbugl",
    "wof:placetype":"neighbourhood"
},
  "geometry": {"coordinates":[11.84232,48.98146],"type":"Point"}
}