{
  "type": "Feature",
  "properties": {
    "gn:admin1_code":"2.0",
    "gn:admin2_code":"094",
    "gn:admin3_code":"9475.0",
    "gn:admin4_code":"9475142.0",
    "gn:asciiname":"Wolbersbach",
    "gn:country_code":"DE",
    "gn:dem":568,
    "gn:feature_class":"P",
    "gn:feature_code":"PPL",
    "gn:name":"W\u00f6lbersbach",
    "gn:population":0,
    "gn:timezone":"Europe/Berlin",
    "iso:country":"DE",
    "wof:name":"Wolbersbach",
    "wof:placetype":"neighbourhood"
},
  "geometry": {"coordinates":[11.84559,50.22399],"type":"Point"}
}