{
  "type": "Feature",
  "properties": {
    "gn:admin1_code":"7",
    "gn:admin2_code":"53.0",
    "gn:admin3_code":"5370.0",
    "gn:admin4_code":"5370012.0",
    "gn:asciiname":"Immendorf",
    "gn:country_code":"DE",
    "gn:dem":107,
    "gn:feature_class":"P",
    "gn:feature_code":"PPL",
    "gn:name":"Immendorf",
    "gn:population":0,
    "gn:timezone":"Europe/Berlin",
    "iso:country":"DE",
    "wof:name":"Immendorf",
    "wof:placetype":"neighbourhood"
},
  "geometry": {"coordinates":[6.17306,50.95135],"type":"Point"}
}