{
  "type": "Feature",
  "properties": {
    "gn:admin1_code":"2",
    "gn:admin2_code":"94.0",
    "gn:admin3_code":"9473.0",
    "gn:admin4_code":"9473134.0",
    "gn:asciiname":"Roth am Forst",
    "gn:country_code":"DE",
    "gn:dem":295,
    "gn:feature_class":"P",
    "gn:feature_code":"PPL",
    "gn:name":"Roth am Forst",
    "gn:population":0,
    "gn:timezone":"Europe/Berlin",
    "iso:country":"DE",
    "name:und_x_variant":[
        "Roth",
        "Roth am Forst"
    ],
    "wof:name":"Roth am Forst",
    "wof:placetype":"neighbourhood"
},
  "geometry": {"coordinates":[11.01086,50.22178],"type":"Point"}
}