{
  "type": "Feature",
  "properties": {
    "gn:admin1_code":"2",
    "gn:admin2_code":"95.0",
    "gn:admin3_code":"9573.0",
    "gn:admin4_code":"9573127.0",
    "gn:asciiname":"Eckershof",
    "gn:country_code":"DE",
    "gn:dem":352,
    "gn:feature_class":"P",
    "gn:feature_code":"PPL",
    "gn:name":"Eckershof",
    "gn:population":0,
    "gn:timezone":"Europe/Berlin",
    "iso:country":"DE",
    "wof:name":"Eckershof",
    "wof:placetype":"neighbourhood"
},
  "geometry": {"coordinates":[10.98831,49.38935],"type":"Point"}
}