{
  "type": "Feature",
  "properties": {
    "gn:admin1_code":"5.0",
    "gn:admin2_code":"66.0",
    "gn:admin3_code":"6635.0",
    "gn:admin4_code":"6635004.0",
    "gn:asciiname":"Berghofen",
    "gn:country_code":"DE",
    "gn:dem":323,
    "gn:feature_class":"P",
    "gn:feature_code":"PPL",
    "gn:name":"Berghofen",
    "gn:population":0,
    "gn:timezone":"Europe/Berlin",
    "iso:country":"DE",
    "wof:name":"Berghofen",
    "wof:placetype":"neighbourhood"
},
  "geometry": {"coordinates":[8.67225,51.00468],"type":"Point"}
}