{
  "type": "Feature",
  "properties": {
    "gn:admin1_code":"7",
    "gn:admin2_code":"53.0",
    "gn:admin3_code":"5334.0",
    "gn:admin4_code":"5334028.0",
    "gn:asciiname":"Rollesbroich",
    "gn:country_code":"DE",
    "gn:dem":504,
    "gn:feature_class":"P",
    "gn:feature_code":"PPL",
    "gn:name":"Rollesbroich",
    "gn:population":0,
    "gn:timezone":"Europe/Berlin",
    "iso:country":"DE",
    "wof:name":"Rollesbroich",
    "wof:placetype":"neighbourhood"
},
  "geometry": {"coordinates":[6.31618,50.63054],"type":"Point"}
}