{
  "type": "Feature",
  "properties": {
    "gn:admin1_code":"2",
    "gn:admin2_code":"96.0",
    "gn:admin3_code":"9675.0",
    "gn:admin4_code":"9675150.0",
    "gn:asciiname":"Enheim",
    "gn:country_code":"DE",
    "gn:dem":289,
    "gn:feature_class":"P",
    "gn:feature_code":"PPL",
    "gn:name":"Enheim",
    "gn:population":0,
    "gn:timezone":"Europe/Berlin",
    "iso:country":"DE",
    "wof:name":"Enheim",
    "wof:placetype":"neighbourhood"
},
  "geometry": {"coordinates":[10.13746,49.63262],"type":"Point"}
}