{
  "type": "Feature",
  "properties": {
    "gn:admin1_code":"10",
    "gn:admin2_code":"0.0",
    "gn:admin3_code":"1057.0",
    "gn:admin4_code":"1057007.0",
    "gn:asciiname":"Kakoehl",
    "gn:country_code":"DE",
    "gn:dem":52,
    "gn:feature_class":"P",
    "gn:feature_code":"PPL",
    "gn:name":"Kak\u00f6hl",
    "gn:population":0,
    "gn:timezone":"Europe/Berlin",
    "iso:country":"DE",
    "wof:name":"Kakoehl",
    "wof:placetype":"neighbourhood"
},
  "geometry": {"coordinates":[10.67785,54.28176],"type":"Point"}
}