{
  "type": "Feature",
  "properties": {
    "iso:country":"DE",
    "name:deu_x_colloquial":[
        "Suder Vorstadt",
        "Sueder Vorstadt"
    ],
    "name:deu_x_preferred":[
        "S\u00fcdervorstadt"
    ],
    "name:deu_x_variant":[
        "S\u00fcder Vorstadt"
    ],
    "name:eng_x_preferred":[
        "S\u00fcder Vorstadt"
    ],
    "name:unk_x_variant":[
        "S\u00fcder Vorstadt"
    ],
    "qs:gn_adm0_cc":"DE",
    "qs:gn_local":2944388,
    "qs:local_max":10591,
    "qs:local_sum":29027,
    "qs:localhoods":40,
    "qs:name":"S\u00fcder Vorstadt",
    "qs:name_adm0":"Deutschland",
    "qs:name_adm1":"Freie Hansestadt Bremen",
    "qs:name_adm2":"Stadtkreis Bremen",
    "qs:name_lau":"Stadtteil Neustadt",
    "qs:name_local":"Bremen",
    "qs:photo_max":74,
    "qs:photo_sum":370,
    "qs:placetype":"Suburb",
    "qs:quad_count":23,
    "qs:woe_adm0":23424829,
    "qs:woe_adm1":2345483,
    "qs:woe_adm2":12597033,
    "qs:woe_lau":26822051,
    "qs:woe_local":641142,
    "qs:woe_ver":"7.10.0",
    "wof:lang":[
        "ger"
    ],
    "wof:name":"Suedervorstadt",
    "wof:placetype":"neighbourhood"
},
  "geometry": {"coordinates":[8.792675,53.064177],"type":"Point"}
}