{
  "type": "Feature",
  "properties": {
    "gn:admin1_code":"11.0",
    "gn:admin2_code":"0.0",
    "gn:admin3_code":"12063.0",
    "gn:admin4_code":"12063189.0",
    "gn:asciiname":"Bahnitz",
    "gn:country_code":"DE",
    "gn:dem":30,
    "gn:feature_class":"P",
    "gn:feature_code":"PPL",
    "gn:name":"Bahnitz",
    "gn:population":0,
    "gn:timezone":"Europe/Berlin",
    "iso:country":"DE",
    "wof:name":"Bahnitz",
    "wof:placetype":"neighbourhood"
},
  "geometry": {"coordinates":[12.40423,52.49444],"type":"Point"}
}