{
  "type": "Feature",
  "properties": {
    "gn:admin1_code":"15.0",
    "gn:admin2_code":"00",
    "gn:admin3_code":"16062.0",
    "gn:admin4_code":"16062065.0",
    "gn:asciiname":"Wiegersdorf",
    "gn:country_code":"DE",
    "gn:dem":253,
    "gn:feature_class":"P",
    "gn:feature_code":"PPL",
    "gn:name":"Wiegersdorf",
    "gn:population":0,
    "gn:timezone":"Europe/Berlin",
    "iso:country":"DE",
    "name:gml_x_preferred":[
        "Wigradisdorp [a. 1240]"
    ],
    "wof:name":"Wiegersdorf",
    "wof:placetype":"neighbourhood"
},
  "geometry": {"coordinates":[10.79156,51.57624000000001],"type":"Point"}
}