{
  "type": "Feature",
  "properties": {
    "gn:admin1_code":"2",
    "gn:admin2_code":"94.0",
    "gn:admin3_code":"9479.0",
    "gn:admin4_code":"9479159.0",
    "gn:asciiname":"Kaiserhammer",
    "gn:country_code":"DE",
    "gn:dem":511,
    "gn:feature_class":"P",
    "gn:feature_code":"PPL",
    "gn:name":"Kaiserhammer",
    "gn:population":0,
    "gn:timezone":"Europe/Berlin",
    "iso:country":"DE",
    "wof:name":"Kaiserhammer",
    "wof:placetype":"neighbourhood"
},
  "geometry": {"coordinates":[12.08015,50.12837],"type":"Point"}
}