{
  "type": "Feature",
  "properties": {
    "gn:admin1_code":"2.0",
    "gn:admin2_code":"091",
    "gn:admin3_code":"9173.0",
    "gn:admin4_code":"9173137.0",
    "gn:asciiname":"Wimpasing",
    "gn:country_code":"DE",
    "gn:dem":639,
    "gn:feature_class":"P",
    "gn:feature_code":"PPL",
    "gn:name":"Wimpasing",
    "gn:population":0,
    "gn:timezone":"Europe/Berlin",
    "iso:country":"DE",
    "wof:name":"Wimpasing",
    "wof:placetype":"neighbourhood"
},
  "geometry": {"coordinates":[11.34441,47.90516],"type":"Point"}
}