{
  "type": "Feature",
  "properties": {
    "gn:admin1_code":"2",
    "gn:admin2_code":"95.0",
    "gn:admin3_code":"9576.0",
    "gn:admin4_code":"9576143.0",
    "gn:asciiname":"Eckersmuhlen",
    "gn:country_code":"DE",
    "gn:dem":350,
    "gn:feature_class":"P",
    "gn:feature_code":"PPL",
    "gn:name":"Eckersm\u00fchlen",
    "gn:population":0,
    "gn:timezone":"Europe/Berlin",
    "iso:country":"DE",
    "wof:name":"Eckersmuhlen",
    "wof:placetype":"neighbourhood"
},
  "geometry": {"coordinates":[11.14469,49.21754],"type":"Point"}
}