{
  "type": "Feature",
  "properties": {
    "gn:admin1_code":"8",
    "gn:admin2_code":"0.0",
    "gn:admin3_code":"7233.0",
    "gn:admin4_code":"7233035.0",
    "gn:asciiname":"Glaadt",
    "gn:country_code":"DE",
    "gn:dem":444,
    "gn:feature_class":"P",
    "gn:feature_code":"PPL",
    "gn:name":"Glaadt",
    "gn:population":0,
    "gn:timezone":"Europe/Berlin",
    "iso:country":"DE",
    "wof:name":"Glaadt",
    "wof:placetype":"neighbourhood"
},
  "geometry": {"coordinates":[6.57058,50.35109],"type":"Point"}
}