{
  "type": "Feature",
  "properties": {
    "gn:admin1_code":"15",
    "gn:admin2_code":"0.0",
    "gn:admin3_code":"16074.0",
    "gn:admin4_code":"16074085.0",
    "gn:asciiname":"Mennewitz",
    "gn:country_code":"DE",
    "gn:dem":275,
    "gn:feature_class":"P",
    "gn:feature_code":"PPL",
    "gn:name":"Mennewitz",
    "gn:population":0,
    "gn:timezone":"Europe/Berlin",
    "iso:country":"DE",
    "wof:name":"Mennewitz",
    "wof:placetype":"neighbourhood"
},
  "geometry": {"coordinates":[11.70027,50.90265],"type":"Point"}
}