{
  "type": "Feature",
  "properties": {
    "gn:admin1_code":"1",
    "gn:admin2_code":"81.0",
    "gn:admin3_code":"8136.0",
    "gn:admin4_code":"8136024.0",
    "gn:asciiname":"Mulfingen",
    "gn:country_code":"DE",
    "gn:dem":399,
    "gn:feature_class":"P",
    "gn:feature_code":"PPL",
    "gn:name":"Mulfingen",
    "gn:population":0,
    "gn:timezone":"Europe/Berlin",
    "iso:country":"DE",
    "name:als_x_preferred":[
        "Mulfingen"
    ],
    "name:deu_x_preferred":[
        "Mulfingen"
    ],
    "name:epo_x_preferred":[
        "Mulfingen"
    ],
    "name:eus_x_preferred":[
        "Mulfingen"
    ],
    "name:fas_x_preferred":[
        "\u0645\u0648\u0644\u0641\u06cc\u0646\u06af\u0646"
    ],
    "name:fra_x_preferred":[
        "Mulfingen"
    ],
    "name:hun_x_preferred":[
        "Mulfingen"
    ],
    "name:ita_x_preferred":[
        "Mulfingen"
    ],
    "name:jpn_x_preferred":[
        "\u30e0\u30eb\u30d5\u30a3\u30f3\u30b2\u30f3"
    ],
    "name:lat_x_preferred":[
        "Mulfingen"
    ],
    "name:lmo_x_preferred":[
        "Mulfingen"
    ],
    "name:msa_x_preferred":[
        "Mulfingen"
    ],
    "name:nld_x_preferred":[
        "Mulfingen"
    ],
    "name:pol_x_preferred":[
        "Mulfingen"
    ],
    "name:por_x_preferred":[
        "Mulfingen"
    ],
    "name:ron_x_preferred":[
        "Mulfingen"
    ],
    "name:rus_x_preferred":[
        "\u041c\u0443\u043b\u044c\u0444\u0438\u043d\u0433\u0435\u043d"
    ],
    "name:srp_x_preferred":[
        "\u041c\u0443\u043b\u0444\u0438\u043d\u0433\u0435\u043d"
    ],
    "name:ukr_x_preferred":[
        "\u041c\u0443\u043b\u044c\u0444\u0456\u043d\u0433\u0435\u043d"
    ],
    "name:uzb_x_preferred":[
        "Mulfingen"
    ],
    "name:vol_x_preferred":[
        "Mulfingen"
    ],
    "name:war_x_preferred":[
        "Mulfingen"
    ],
    "name:zho_x_preferred":[
        "\u7a46\u5c14\u82ac\u6839"
    ],
    "wof:name":"Mulfingen",
    "wof:placetype":"neighbourhood"
},
  "geometry": {"coordinates":[9.88995,48.84938],"type":"Point"}
}