{
  "type": "Feature",
  "properties": {
    "gn:admin1_code":"11",
    "gn:admin2_code":"0.0",
    "gn:admin3_code":"12070.0",
    "gn:admin4_code":"12070280.0",
    "gn:asciiname":"Schmolde",
    "gn:country_code":"DE",
    "gn:dem":117,
    "gn:feature_class":"P",
    "gn:feature_code":"PPL",
    "gn:name":"Schmolde",
    "gn:population":0,
    "gn:timezone":"Europe/Berlin",
    "iso:country":"DE",
    "wof:name":"Schmolde",
    "wof:placetype":"neighbourhood"
},
  "geometry": {"coordinates":[12.28084,53.28361],"type":"Point"}
}