{
  "type": "Feature",
  "properties": {
    "gn:admin1_code":"5",
    "gn:admin2_code":"65.0",
    "gn:admin3_code":"6531.0",
    "gn:admin4_code":"6531013.0",
    "gn:asciiname":"Salzboeden",
    "gn:country_code":"DE",
    "gn:dem":185,
    "gn:feature_class":"P",
    "gn:feature_code":"PPL",
    "gn:name":"Salzb\u00f6den",
    "gn:population":0,
    "gn:timezone":"Europe/Berlin",
    "iso:country":"DE",
    "wof:name":"Salzboeden",
    "wof:placetype":"neighbourhood"
},
  "geometry": {"coordinates":[8.68402,50.68366],"type":"Point"}
}