{
  "type": "Feature",
  "properties": {
    "gn:admin1_code":"6",
    "gn:admin2_code":"0.0",
    "gn:admin3_code":"3360.0",
    "gn:admin4_code":"3360001.0",
    "gn:asciiname":"Secklendorf",
    "gn:country_code":"DE",
    "gn:dem":64,
    "gn:feature_class":"P",
    "gn:feature_code":"PPL",
    "gn:name":"Secklendorf",
    "gn:population":0,
    "gn:timezone":"Europe/Berlin",
    "iso:country":"DE",
    "wof:name":"Secklendorf",
    "wof:placetype":"neighbourhood"
},
  "geometry": {"coordinates":[10.60112,53.10794],"type":"Point"}
}