{
  "type": "Feature",
  "properties": {
    "iso:country":"DE",
    "oa:elevation_ft":"341",
    "oa:type":"small_airport",
    "woe:hierarchy":{
        "country_id":23424829,
        "county_id":12596936,
        "localadmin_id":12626299,
        "planet_id":1,
        "state_id":2345494
    },
    "wof:name":"Merseburg Airport",
    "wof:placetype":"campus"
},
  "geometry": {"coordinates":[11.95055556,51.36194444],"type":"Point"}
}