{
  "type": "Feature",
  "properties": {
    "iso:country":"DE",
    "name:deu_x_preferred":[
        "Flugplatz Merseburg"
    ],
    "name:eng_x_preferred":[
        "Merseburg Aerodrome"
    ],
    "name:eng_x_variant":[
        "EDAM",
        "Merseburg airfield"
    ],
    "name:msa_x_preferred":[
        "Lapangan Terbang Merseburg"
    ],
    "oa:elevation_ft":"341",
    "oa:type":"small_airport",
    "woe:hierarchy":{
        "country_id":23424829,
        "county_id":12596936,
        "localadmin_id":12626299,
        "planet_id":1,
        "state_id":2345494
    },
    "wof:name":"Merseburg Airport",
    "wof:placetype":"campus"
},
  "geometry": {"coordinates":[11.950556,51.361944],"type":"Point"}
}