{
  "type": "Feature",
  "properties": {
    "gn:admin1_code":"7",
    "gn:admin2_code":"53.0",
    "gn:admin3_code":"5334.0",
    "gn:admin4_code":"5334016.0",
    "gn:asciiname":"Hofstadt",
    "gn:cc2":"DE",
    "gn:country_code":"DE",
    "gn:dem":134,
    "gn:feature_class":"P",
    "gn:feature_code":"PPL",
    "gn:name":"Hofstadt",
    "gn:population":0,
    "gn:timezone":"Europe/Berlin",
    "iso:country":"DE",
    "name:und_x_variant":[
        "Merkstein Hofstadt"
    ],
    "wof:name":"Hofstadt",
    "wof:placetype":"neighbourhood"
},
  "geometry": {"coordinates":[6.09033,50.89973],"type":"Point"}
}