{
  "type": "Feature",
  "properties": {
    "gn:admin1_code":"2",
    "gn:admin2_code":"96.0",
    "gn:admin3_code":"9674.0",
    "gn:admin4_code":"9674147.0",
    "gn:asciiname":"Sailershausen",
    "gn:country_code":"DE",
    "gn:dem":349,
    "gn:feature_class":"P",
    "gn:feature_code":"PPL",
    "gn:name":"Sailershausen",
    "gn:population":0,
    "gn:timezone":"Europe/Berlin",
    "iso:country":"DE",
    "wof:name":"Sailershausen",
    "wof:placetype":"neighbourhood"
},
  "geometry": {"coordinates":[10.45129,50.05922],"type":"Point"}
}