{
  "type": "Feature",
  "properties": {
    "gn:admin1_code":"2",
    "gn:admin2_code":"91.0",
    "gn:admin3_code":"9183.0",
    "gn:admin4_code":"9183114.0",
    "gn:asciiname":"Eiching",
    "gn:country_code":"DE",
    "gn:dem":467,
    "gn:feature_class":"P",
    "gn:feature_code":"PPL",
    "gn:name":"Eiching",
    "gn:population":0,
    "gn:timezone":"Europe/Berlin",
    "iso:country":"DE",
    "wof:name":"Eiching",
    "wof:placetype":"neighbourhood"
},
  "geometry": {"coordinates":[12.34546,48.30501],"type":"Point"}
}