{
  "type": "Feature",
  "properties": {
    "gn:admin1_code":"1",
    "gn:admin2_code":"81.0",
    "gn:admin3_code":"8125.0",
    "gn:admin4_code":"8125058.0",
    "gn:asciiname":"Schluchtern",
    "gn:country_code":"DE",
    "gn:dem":183,
    "gn:feature_class":"P",
    "gn:feature_code":"PPL",
    "gn:name":"Schluchtern",
    "gn:population":0,
    "gn:timezone":"Europe/Berlin",
    "iso:country":"DE",
    "wof:name":"Schluchtern",
    "wof:placetype":"neighbourhood"
},
  "geometry": {"coordinates":[9.10187,49.1471],"type":"Point"}
}