{
  "type": "Feature",
  "properties": {
    "iso:country":"DE",
    "wof:name":"Ludenberg",
    "wof:placetype":"neighbourhood"
},
  "geometry": {"coordinates":[6.86251045306919,51.25559494608485],"type":"Point"}
}