{
  "type": "Feature",
  "properties": {
    "gn:admin1_code":"8",
    "gn:admin2_code":"0.0",
    "gn:admin3_code":"7137.0",
    "gn:admin4_code":"7137049.0",
    "gn:asciiname":"Waldesch",
    "gn:country_code":"DE",
    "gn:dem":509,
    "gn:feature_class":"P",
    "gn:feature_code":"PPL",
    "gn:name":"Waldesch",
    "gn:population":0,
    "gn:timezone":"Europe/Berlin",
    "iso:country":"DE",
    "wof:name":"Waldesch",
    "wof:placetype":"neighbourhood"
},
  "geometry": {"coordinates":[7.14983,50.36779],"type":"Point"}
}