{
  "type": "Feature",
  "properties": {
    "gn:admin1_code":"8",
    "gn:admin2_code":"0.0",
    "gn:admin3_code":"7137.0",
    "gn:admin4_code":"7137049.0",
    "gn:asciiname":"Waldesch",
    "gn:country_code":"DE",
    "gn:dem":509,
    "gn:feature_class":"P",
    "gn:feature_code":"PPL",
    "gn:name":"Waldesch",
    "gn:population":0,
    "gn:timezone":"Europe/Berlin",
    "iso:country":"DE",
    "name:ceb_x_preferred":[
        "Waldesch"
    ],
    "name:deu_x_preferred":[
        "Waldesch"
    ],
    "name:epo_x_preferred":[
        "Waldesch"
    ],
    "name:eus_x_preferred":[
        "Waldesch"
    ],
    "name:fas_x_preferred":[
        "\u0648\u0627\u0644\u062f\u0634"
    ],
    "name:fra_x_preferred":[
        "Waldesch"
    ],
    "name:hun_x_preferred":[
        "Waldesch"
    ],
    "name:ita_x_preferred":[
        "Waldesch"
    ],
    "name:kaz_x_preferred":[
        "\u0412\u0430\u043b\u044c\u0434\u0435\u0448"
    ],
    "name:kir_x_preferred":[
        "\u0412\u0430\u043b\u044c\u0434\u0435\u0448"
    ],
    "name:msa_x_preferred":[
        "Waldesch"
    ],
    "name:nld_x_preferred":[
        "Waldesch"
    ],
    "name:pol_x_preferred":[
        "Waldesch"
    ],
    "name:por_x_preferred":[
        "Waldesch"
    ],
    "name:ron_x_preferred":[
        "Waldesch"
    ],
    "name:rus_x_preferred":[
        "\u0412\u0430\u043b\u044c\u0434\u0435\u0448"
    ],
    "name:spa_x_preferred":[
        "Waldesch"
    ],
    "name:srp_x_preferred":[
        "\u0412\u0430\u043b\u0434\u0435\u0448"
    ],
    "name:swe_x_preferred":[
        "Waldesch"
    ],
    "name:ukr_x_preferred":[
        "\u0412\u0430\u043b\u044c\u0434\u0435\u0448"
    ],
    "name:uzb_x_preferred":[
        "Waldesch"
    ],
    "name:vie_x_preferred":[
        "Waldesch"
    ],
    "name:vol_x_preferred":[
        "Waldesch"
    ],
    "name:war_x_preferred":[
        "Waldesch"
    ],
    "name:zho_x_preferred":[
        "\u74e6\u5c14\u5fb7\u57c3\u65bd"
    ],
    "wof:name":"Waldesch",
    "wof:placetype":"neighbourhood"
},
  "geometry": {"coordinates":[7.14983,50.36779],"type":"Point"}
}