{
  "type": "Feature",
  "properties": {
    "gn:admin1_code":"2",
    "gn:admin2_code":"94.0",
    "gn:admin3_code":"9471.0",
    "gn:admin4_code":"9471159.0",
    "gn:asciiname":"Kremmeldorf",
    "gn:country_code":"DE",
    "gn:dem":316,
    "gn:feature_class":"P",
    "gn:feature_code":"PPL",
    "gn:name":"Kremmeldorf",
    "gn:population":0,
    "gn:timezone":"Europe/Berlin",
    "iso:country":"DE",
    "wof:name":"Kremmeldorf",
    "wof:placetype":"neighbourhood"
},
  "geometry": {"coordinates":[11.01291,49.93694],"type":"Point"}
}