{
  "type": "Feature",
  "properties": {
    "gn:admin1_code":"2",
    "gn:admin2_code":"91.0",
    "gn:admin3_code":"9183.0",
    "gn:admin4_code":"9183129.0",
    "gn:asciiname":"Grafing",
    "gn:country_code":"DE",
    "gn:dem":431,
    "gn:feature_class":"P",
    "gn:feature_code":"PPL",
    "gn:name":"Grafing",
    "gn:population":0,
    "gn:timezone":"Europe/Berlin",
    "iso:country":"DE",
    "name:ara_x_preferred":[
        "\u063a\u0631\u0627\u0641\u064a\u0646\u063a"
    ],
    "name:ceb_x_preferred":[
        "Grafing b.M\u00fcnchen"
    ],
    "name:kir_x_preferred":[
        "\u0413\u0440\u0430\u0444\u0438\u043d\u0433-\u041c\u044e\u043d\u0445\u0435\u043d"
    ],
    "name:msa_x_preferred":[
        "Grafing"
    ],
    "name:por_x_preferred":[
        "Grafing"
    ],
    "name:rus_x_preferred":[
        "\u0413\u0440\u0430\u0444\u0438\u043d\u0433-\u0431\u0430\u0439-\u041c\u044e\u043d\u0445\u0435\u043d"
    ],
    "name:spa_x_preferred":[
        "Grafing"
    ],
    "name:swe_x_preferred":[
        "Grafing"
    ],
    "name:ukr_x_preferred":[
        "\u0413\u0440\u0430\u0444\u0456\u043d\u0433"
    ],
    "name:war_x_preferred":[
        "Grafing"
    ],
    "name:zho_x_preferred":[
        "\u683c\u62c9\u82ac"
    ],
    "wof:name":"Grafing",
    "wof:placetype":"neighbourhood"
},
  "geometry": {"coordinates":[12.56416,48.38779],"type":"Point"}
}