{
  "type": "Feature",
  "properties": {
    "gn:admin1_code":"2",
    "gn:admin2_code":"95.0",
    "gn:admin3_code":"9577.0",
    "gn:admin4_code":"9577141.0",
    "gn:asciiname":"Goppersdorf",
    "gn:country_code":"DE",
    "gn:dem":445,
    "gn:feature_class":"P",
    "gn:feature_code":"PPL",
    "gn:name":"G\u00f6ppersdorf",
    "gn:population":0,
    "gn:timezone":"Europe/Berlin",
    "iso:country":"DE",
    "wof:name":"Goppersdorf",
    "wof:placetype":"neighbourhood"
},
  "geometry": {"coordinates":[11.02431,49.0864],"type":"Point"}
}