{
  "type": "Feature",
  "properties": {
    "gn:admin1_code":"2",
    "gn:admin2_code":"95.0",
    "gn:admin3_code":"9576.0",
    "gn:admin4_code":"9576142.0",
    "gn:asciiname":"Prunst",
    "gn:country_code":"DE",
    "gn:dem":402,
    "gn:feature_class":"P",
    "gn:feature_code":"PPL",
    "gn:name":"Pr\u00fcnst",
    "gn:population":0,
    "gn:timezone":"Europe/Berlin",
    "iso:country":"DE",
    "wof:name":"Prunst",
    "wof:placetype":"neighbourhood"
},
  "geometry": {"coordinates":[10.91157,49.32102],"type":"Point"}
}