{
  "type": "Feature",
  "properties": {
    "gn:admin1_code":"2",
    "gn:admin2_code":"91.0",
    "gn:admin3_code":"9187.0",
    "gn:admin4_code":"9187163.0",
    "gn:asciiname":"Inzenham",
    "gn:country_code":"DE",
    "gn:dem":508,
    "gn:feature_class":"P",
    "gn:feature_code":"PPL",
    "gn:name":"Inzenham",
    "gn:population":0,
    "gn:timezone":"Europe/Berlin",
    "iso:country":"DE",
    "wof:name":"Inzenham",
    "wof:placetype":"neighbourhood"
},
  "geometry": {"coordinates":[12.22838,47.88069],"type":"Point"}
}