{
  "type": "Feature",
  "properties": {
    "gn:admin1_code":"13",
    "gn:admin2_code":"0.0",
    "gn:admin3_code":"14522.0",
    "gn:admin4_code":"14522440.0",
    "gn:asciiname":"Hartha",
    "gn:country_code":"DE",
    "gn:dem":420,
    "gn:feature_class":"P",
    "gn:feature_code":"PPL",
    "gn:name":"Hartha",
    "gn:population":0,
    "gn:timezone":"Europe/Berlin",
    "iso:country":"DE",
    "wof:name":"Hartha",
    "wof:placetype":"neighbourhood"
},
  "geometry": {"coordinates":[13.18059,50.90335],"type":"Point"}
}