{
  "type": "Feature",
  "properties": {
    "gn:admin1_code":"10",
    "gn:admin2_code":"0.0",
    "gn:admin3_code":"1059.0",
    "gn:admin4_code":"1059109.0",
    "gn:asciiname":"Esgrusschauby",
    "gn:country_code":"DE",
    "gn:dem":43,
    "gn:feature_class":"P",
    "gn:feature_code":"PPL",
    "gn:name":"Esgrusschauby",
    "gn:population":0,
    "gn:timezone":"Europe/Berlin",
    "iso:country":"DE",
    "wof:name":"Esgrusschauby",
    "wof:placetype":"neighbourhood"
},
  "geometry": {"coordinates":[9.80882,54.70963],"type":"Point"}
}