{
  "type": "Feature",
  "properties": {
    "gn:admin1_code":"7",
    "gn:admin2_code":"53.0",
    "gn:admin3_code":"5378.0",
    "gn:admin4_code":"5378024.0",
    "gn:asciiname":"Unterauel",
    "gn:country_code":"DE",
    "gn:dem":97,
    "gn:feature_class":"P",
    "gn:feature_code":"PPL",
    "gn:name":"Unterauel",
    "gn:population":0,
    "gn:timezone":"Europe/Berlin",
    "iso:country":"DE",
    "wof:name":"Unterauel",
    "wof:placetype":"neighbourhood"
},
  "geometry": {"coordinates":[7.20464,50.94153],"type":"Point"}
}