{
  "type": "Feature",
  "properties": {
    "gn:admin1_code":"7",
    "gn:admin2_code":"55.0",
    "gn:admin3_code":"5558.0",
    "gn:admin4_code":"5558032.0",
    "gn:asciiname":"Gladbeck",
    "gn:country_code":"DE",
    "gn:dem":96,
    "gn:feature_class":"P",
    "gn:feature_code":"PPL",
    "gn:name":"Gladbeck",
    "gn:population":0,
    "gn:timezone":"Europe/Berlin",
    "iso:country":"DE",
    "name:ara_x_preferred":[
        "\u063a\u0644\u0627\u062f\u0628\u064a\u0643"
    ],
    "name:azb_x_preferred":[
        "\u0642\u0644\u0627\u062f\u0628\u06a9"
    ],
    "name:aze_x_preferred":[
        "Qladbek"
    ],
    "name:bel_x_preferred":[
        "\u0413\u043b\u0430\u0434\u0431\u0435\u043a"
    ],
    "name:ces_x_preferred":[
        "Gladbeck"
    ],
    "name:dan_x_preferred":[
        "Gladbeck"
    ],
    "name:deu_x_preferred":[
        "Gladbeck"
    ],
    "name:epo_x_preferred":[
        "Gladbeck"
    ],
    "name:est_x_preferred":[
        "Gladbeck"
    ],
    "name:eus_x_preferred":[
        "Gladbeck"
    ],
    "name:fas_x_preferred":[
        "\u06af\u0644\u0627\u062f\u0628\u06a9"
    ],
    "name:fin_x_preferred":[
        "Gladbeck"
    ],
    "name:fra_x_preferred":[
        "Gladbeck"
    ],
    "name:hun_x_preferred":[
        "Gladbeck"
    ],
    "name:ita_x_preferred":[
        "Gladbeck"
    ],
    "name:kaz_x_preferred":[
        "\u0413\u043b\u0430\u0434\u0431\u0435\u043a"
    ],
    "name:kir_x_preferred":[
        "\u0413\u043b\u0430\u0434\u0431\u0435\u043a"
    ],
    "name:kor_x_preferred":[
        "\uae00\ub77c\ud2b8\ubca0\ud06c"
    ],
    "name:lim_x_preferred":[
        "Gladbeck"
    ],
    "name:msa_x_preferred":[
        "Gladbeck"
    ],
    "name:nds_x_preferred":[
        "Gladbeck"
    ],
    "name:nld_x_preferred":[
        "Gladbeck"
    ],
    "name:nno_x_preferred":[
        "Gladbeck"
    ],
    "name:nor_x_preferred":[
        "Gladbeck"
    ],
    "name:pol_x_preferred":[
        "Gladbeck"
    ],
    "name:por_x_preferred":[
        "Gladbeck"
    ],
    "name:ron_x_preferred":[
        "Gladbeck"
    ],
    "name:rus_x_preferred":[
        "\u0413\u043b\u0430\u0434\u0431\u0435\u043a"
    ],
    "name:spa_x_preferred":[
        "Gladbeck"
    ],
    "name:srp_x_preferred":[
        "\u0413\u043b\u0430\u0434\u0431\u0435\u043a"
    ],
    "name:swa_x_preferred":[
        "Gladbeck"
    ],
    "name:swe_x_preferred":[
        "Gladbeck"
    ],
    "name:tat_x_preferred":[
        "\u0413\u043b\u0430\u0434\u0431\u0435\u043a"
    ],
    "name:tur_x_preferred":[
        "Gladbeck"
    ],
    "name:ukr_x_preferred":[
        "\u0413\u043b\u0430\u0434\u0431\u0435\u043a"
    ],
    "name:uzb_x_preferred":[
        "Gladbeck"
    ],
    "name:vol_x_preferred":[
        "Gladbeck"
    ],
    "name:war_x_preferred":[
        "Gladbeck"
    ],
    "name:zho_x_preferred":[
        "\u683c\u62c9\u5fb7\u8c9d\u514b"
    ],
    "wof:name":"Gladbeck",
    "wof:placetype":"neighbourhood"
},
  "geometry": {"coordinates":[7.28211,51.91595],"type":"Point"}
}