{
  "type": "Feature",
  "properties": {
    "gn:admin1_code":"12",
    "gn:admin2_code":"0.0",
    "gn:admin3_code":"13076.0",
    "gn:admin4_code":"13076020.0",
    "gn:asciiname":"Keez",
    "gn:country_code":"DE",
    "gn:dem":26,
    "gn:feature_class":"P",
    "gn:feature_code":"PPL",
    "gn:name":"Keez",
    "gn:population":0,
    "gn:timezone":"Europe/Berlin",
    "iso:country":"DE",
    "wof:name":"Keez",
    "wof:placetype":"neighbourhood"
},
  "geometry": {"coordinates":[11.6425,53.73363000000001],"type":"Point"}
}