{
  "type": "Feature",
  "properties": {
    "gn:admin1_code":"14",
    "gn:admin2_code":"0.0",
    "gn:admin3_code":"15082.0",
    "gn:admin4_code":"15082301.0",
    "gn:asciiname":"Klein Leipzig",
    "gn:country_code":"DE",
    "gn:dem":85,
    "gn:feature_class":"P",
    "gn:feature_code":"PPL",
    "gn:name":"Klein Leipzig",
    "gn:population":0,
    "gn:timezone":"Europe/Berlin",
    "iso:country":"DE",
    "wof:name":"Klein Leipzig",
    "wof:placetype":"neighbourhood"
},
  "geometry": {"coordinates":[12.20956,51.71966],"type":"Point"}
}