{
  "type": "Feature",
  "properties": {
    "gn:admin1_code":"11",
    "gn:admin2_code":"0.0",
    "gn:admin3_code":"12067.0",
    "gn:admin4_code":"12067413.0",
    "gn:asciiname":"Kolpin",
    "gn:country_code":"DE",
    "gn:dem":44,
    "gn:feature_class":"P",
    "gn:feature_code":"PPL",
    "gn:name":"Kolpin",
    "gn:population":0,
    "gn:timezone":"Europe/Berlin",
    "iso:country":"DE",
    "name:und_x_variant":[
        "Colpin",
        "Kolpin"
    ],
    "wof:name":"Kolpin",
    "wof:placetype":"neighbourhood"
},
  "geometry": {"coordinates":[13.98495,52.29296],"type":"Point"}
}