{
  "type": "Feature",
  "properties": {
    "gn:admin1_code":"15",
    "gn:admin2_code":"0.0",
    "gn:admin3_code":"16065.0",
    "gn:admin4_code":"16065031.0",
    "gn:asciiname":"Lundershausen",
    "gn:country_code":"DE",
    "gn:dem":172,
    "gn:feature_class":"P",
    "gn:feature_code":"PPL",
    "gn:name":"Lundershausen",
    "gn:population":0,
    "gn:timezone":"Europe/Berlin",
    "iso:country":"DE",
    "wof:name":"Lundershausen",
    "wof:placetype":"neighbourhood"
},
  "geometry": {"coordinates":[11.26675,51.26759000000001],"type":"Point"}
}