{
  "type": "Feature",
  "properties": {
    "gn:admin1_code":"12",
    "gn:admin2_code":"0.0",
    "gn:admin3_code":"13072.0",
    "gn:admin4_code":"13072027.0",
    "gn:asciiname":"Sabel",
    "gn:country_code":"DE",
    "gn:dem":34,
    "gn:feature_class":"P",
    "gn:feature_code":"PPL",
    "gn:name":"Sabel",
    "gn:population":0,
    "gn:timezone":"Europe/Berlin",
    "iso:country":"DE",
    "name:deu_x_preferred":[
        "Sabel"
    ],
    "name:jpn_x_preferred":[
        "\u30b7\u30df\u30bf\u30fc"
    ],
    "name:nld_x_preferred":[
        "Sabel"
    ],
    "name:scn_x_preferred":[
        "Scimitarra"
    ],
    "wof:name":"Sabel",
    "wof:placetype":"neighbourhood"
},
  "geometry": {"coordinates":[12.21354,53.94659],"type":"Point"}
}