{
  "type": "Feature",
  "properties": {
    "gn:admin1_code":"14",
    "gn:admin2_code":"0.0",
    "gn:admin3_code":"15083.0",
    "gn:admin4_code":"15083230.0",
    "gn:asciiname":"Hasselburg",
    "gn:country_code":"DE",
    "gn:dem":98,
    "gn:feature_class":"P",
    "gn:feature_code":"PPL",
    "gn:name":"Hasselburg",
    "gn:population":0,
    "gn:timezone":"Europe/Berlin",
    "iso:country":"DE",
    "wof:name":"Hasselburg",
    "wof:placetype":"neighbourhood"
},
  "geometry": {"coordinates":[11.26648,52.32611],"type":"Point"}
}