{
  "type": "Feature",
  "properties": {
    "gn:admin1_code":"2",
    "gn:admin2_code":"96.0",
    "gn:admin3_code":"9675.0",
    "gn:admin4_code":"9675179.0",
    "gn:asciiname":"Huttenheim",
    "gn:country_code":"DE",
    "gn:dem":284,
    "gn:feature_class":"P",
    "gn:feature_code":"PPL",
    "gn:name":"H\u00fcttenheim",
    "gn:population":0,
    "gn:timezone":"Europe/Berlin",
    "iso:country":"DE",
    "name:als_x_preferred":[
        "H\u00fcttenheim"
    ],
    "name:ara_x_preferred":[
        "\u0647\u0648\u062a\u064a\u0646\u0647\u064a\u0645"
    ],
    "name:cat_x_preferred":[
        "Huttenheim"
    ],
    "name:ceb_x_preferred":[
        "Huttenheim"
    ],
    "name:deu_x_preferred":[
        "Huttenheim"
    ],
    "name:eus_x_preferred":[
        "Huttenheim"
    ],
    "name:fra_x_preferred":[
        "Huttenheim"
    ],
    "name:hun_x_preferred":[
        "Huttenheim"
    ],
    "name:hye_x_preferred":[
        "\u0548\u0582\u0569\u0565\u0576\u0561\u0575\u0574"
    ],
    "name:ita_x_preferred":[
        "Huttenheim"
    ],
    "name:kaz_x_preferred":[
        "\u042e\u0442\u0442\u0435\u043d\u0430\u0439\u043c"
    ],
    "name:lat_x_preferred":[
        "Huttenheim"
    ],
    "name:msa_x_preferred":[
        "Huttenheim"
    ],
    "name:nld_x_preferred":[
        "Huttenheim"
    ],
    "name:oci_x_preferred":[
        "Huttenheim"
    ],
    "name:pfl_x_preferred":[
        "H\u00fcttenheim"
    ],
    "name:pms_x_preferred":[
        "Huttenheim"
    ],
    "name:pol_x_preferred":[
        "Huttenheim"
    ],
    "name:por_x_preferred":[
        "Huttenheim"
    ],
    "name:ron_x_preferred":[
        "Huttenheim"
    ],
    "name:rus_x_preferred":[
        "\u042e\u0442\u0442\u0435\u043d\u0430\u0439\u043c"
    ],
    "name:slk_x_preferred":[
        "Huttenheim"
    ],
    "name:slv_x_preferred":[
        "Huttenheim"
    ],
    "name:spa_x_preferred":[
        "Huttenheim"
    ],
    "name:swe_x_preferred":[
        "Huttenheim"
    ],
    "name:ukr_x_preferred":[
        "\u042e\u0442\u0442\u0435\u043d\u0430\u0439\u043c"
    ],
    "name:uzb_x_preferred":[
        "Huttenheim"
    ],
    "name:vie_x_preferred":[
        "Huttenheim"
    ],
    "name:vol_x_preferred":[
        "Huttenheim"
    ],
    "name:war_x_preferred":[
        "Huttenheim"
    ],
    "name:zho_x_preferred":[
        "\u4e8e\u7279\u5948\u59c6"
    ],
    "wof:name":"Huttenheim",
    "wof:placetype":"neighbourhood"
},
  "geometry": {"coordinates":[10.2578,49.64807],"type":"Point"}
}