{
  "type": "Feature",
  "properties": {
    "gn:admin1_code":"2",
    "gn:admin2_code":"91.0",
    "gn:admin3_code":"9183.0",
    "gn:admin4_code":"9183127.0",
    "gn:asciiname":"Langenstegham",
    "gn:country_code":"DE",
    "gn:dem":415,
    "gn:feature_class":"P",
    "gn:feature_code":"PPL",
    "gn:name":"Langenstegham",
    "gn:population":0,
    "gn:timezone":"Europe/Berlin",
    "iso:country":"DE",
    "name:und_x_variant":[
        "Langen",
        "Langenstegham"
    ],
    "wof:name":"Langenstegham",
    "wof:placetype":"neighbourhood"
},
  "geometry": {"coordinates":[12.46941,48.28358],"type":"Point"}
}