{
  "type": "Feature",
  "properties": {
    "gn:admin1_code":"12",
    "gn:admin2_code":"0.0",
    "gn:admin3_code":"13073.0",
    "gn:admin4_code":"13073001.0",
    "gn:asciiname":"Pantlitz",
    "gn:country_code":"DE",
    "gn:dem":19,
    "gn:feature_class":"P",
    "gn:feature_code":"PPL",
    "gn:name":"Pantlitz",
    "gn:population":0,
    "gn:timezone":"Europe/Berlin",
    "iso:country":"DE",
    "wof:name":"Pantlitz",
    "wof:placetype":"neighbourhood"
},
  "geometry": {"coordinates":[12.55441,54.22538],"type":"Point"}
}