{
  "type": "Feature",
  "properties": {
    "iso:country":"DE",
    "name:deu_x_preferred":[
        "\u00dcckesdorf"
    ],
    "wof:name":"Ueckesdorf",
    "wof:placetype":"neighbourhood"
},
  "geometry": {"coordinates":[7.06728142053447,50.69282186181456],"type":"Point"}
}