{
  "type": "Feature",
  "properties": {
    "gn:admin1_code":"2",
    "gn:admin2_code":"92.0",
    "gn:admin3_code":"9278.0",
    "gn:admin4_code":"9278134.0",
    "gn:asciiname":"Felling",
    "gn:country_code":"DE",
    "gn:dem":423,
    "gn:feature_class":"P",
    "gn:feature_code":"PPL",
    "gn:name":"Felling",
    "gn:population":0,
    "gn:timezone":"Europe/Berlin",
    "iso:country":"DE",
    "name:ces_x_preferred":[
        "K\u00e1cen\u00ed"
    ],
    "name:deu_x_preferred":[
        "F\u00e4lltechnik"
    ],
    "name:est_x_preferred":[
        "Langetamine"
    ],
    "name:spa_x_preferred":[
        "Tala"
    ],
    "wof:name":"Felling",
    "wof:placetype":"neighbourhood"
},
  "geometry": {"coordinates":[12.69178,48.9925],"type":"Point"}
}