{
  "type": "Feature",
  "properties": {
    "gn:admin1_code":"8",
    "gn:admin2_code":"0.0",
    "gn:admin3_code":"7340.0",
    "gn:admin4_code":"7340228.0",
    "gn:asciiname":"Niederhausen",
    "gn:country_code":"DE",
    "gn:dem":252,
    "gn:feature_class":"P",
    "gn:feature_code":"PPL",
    "gn:name":"Niederhausen",
    "gn:population":0,
    "gn:timezone":"Europe/Berlin",
    "iso:country":"DE",
    "name:ara_x_preferred":[
        "\u0646\u064a\u062f\u0631\u0647\u0627\u0648\u0632\u0646"
    ],
    "name:ceb_x_preferred":[
        "Niederhausen"
    ],
    "name:deu_x_preferred":[
        "Niederhausen"
    ],
    "name:epo_x_preferred":[
        "Niederhausen"
    ],
    "name:eus_x_preferred":[
        "Niederhausen"
    ],
    "name:fas_x_preferred":[
        "\u0646\u06cc\u062f\u0631\u0647\u0627\u0648\u0632\u0646"
    ],
    "name:fra_x_preferred":[
        "Niederhausen"
    ],
    "name:hun_x_preferred":[
        "Niederhausen"
    ],
    "name:ita_x_preferred":[
        "Niederhausen"
    ],
    "name:kaz_x_preferred":[
        "\u041d\u0438\u0434\u0435\u0440\u0445\u0430\u0443\u0437\u0435\u043d"
    ],
    "name:kir_x_preferred":[
        "\u041d\u0438\u0434\u0435\u0440\u0445\u0430\u0443\u0437\u0435\u043d"
    ],
    "name:msa_x_preferred":[
        "Niederhausen"
    ],
    "name:nld_x_preferred":[
        "Niederhausen"
    ],
    "name:pol_x_preferred":[
        "Niederhausen"
    ],
    "name:por_x_preferred":[
        "Niederhausen"
    ],
    "name:ron_x_preferred":[
        "Niederhausen"
    ],
    "name:rus_x_preferred":[
        "\u041d\u0438\u0434\u0435\u0440\u0445\u0430\u0443\u0437\u0435\u043d"
    ],
    "name:spa_x_preferred":[
        "Niederhausen"
    ],
    "name:srp_x_preferred":[
        "\u041d\u0438\u0434\u0435\u0440\u0445\u0430\u0443\u0437\u0435\u043d"
    ],
    "name:ukr_x_preferred":[
        "\u041d\u0456\u0434\u0435\u0440\u0433\u0430\u0443\u0437\u0435\u043d"
    ],
    "name:uzb_x_preferred":[
        "Niederhausen"
    ],
    "name:vie_x_preferred":[
        "Niederhausen"
    ],
    "name:vol_x_preferred":[
        "Niederhausen"
    ],
    "name:war_x_preferred":[
        "Niederhausen"
    ],
    "name:zho_x_preferred":[
        "\u5c3c\u5fb7\u8c6a\u68ee"
    ],
    "wof:name":"Niederhausen",
    "wof:placetype":"neighbourhood"
},
  "geometry": {"coordinates":[7.463,49.29524],"type":"Point"}
}