{
  "type": "Feature",
  "properties": {
    "gn:admin1_code":"8",
    "gn:admin2_code":"0.0",
    "gn:admin3_code":"7340.0",
    "gn:admin4_code":"7340228.0",
    "gn:asciiname":"Niederhausen",
    "gn:country_code":"DE",
    "gn:dem":252,
    "gn:feature_class":"P",
    "gn:feature_code":"PPL",
    "gn:name":"Niederhausen",
    "gn:population":0,
    "gn:timezone":"Europe/Berlin",
    "iso:country":"DE",
    "wof:name":"Niederhausen",
    "wof:placetype":"neighbourhood"
},
  "geometry": {"coordinates":[7.463,49.29524],"type":"Point"}
}