{
  "type": "Feature",
  "properties": {
    "gn:admin1_code":"1",
    "gn:admin2_code":"84.0",
    "gn:admin3_code":"8435.0",
    "gn:admin4_code":"8435057.0",
    "gn:asciiname":"Herrgottsweiler",
    "gn:country_code":"DE",
    "gn:dem":568,
    "gn:feature_class":"P",
    "gn:feature_code":"PPL",
    "gn:name":"Herrgottsweiler",
    "gn:population":0,
    "gn:timezone":"Europe/Berlin",
    "iso:country":"DE",
    "wof:name":"Herrgottsweiler",
    "wof:placetype":"locality"
},
  "geometry": {"coordinates":[9.61667,47.68333],"type":"Point"}
}