{
  "type": "Feature",
  "properties": {
    "gn:admin1_code":"14",
    "gn:admin2_code":"0.0",
    "gn:admin3_code":"15084.0",
    "gn:admin4_code":"15084590.0",
    "gn:asciiname":"Streckau",
    "gn:country_code":"DE",
    "gn:dem":173,
    "gn:feature_class":"P",
    "gn:feature_code":"PPL",
    "gn:name":"Streckau",
    "gn:population":0,
    "gn:timezone":"Europe/Berlin",
    "iso:country":"DE",
    "wof:name":"Streckau",
    "wof:placetype":"neighbourhood"
},
  "geometry": {"coordinates":[12.08313,51.08317],"type":"Point"}
}