{
  "type": "Feature",
  "properties": {
    "gn:admin1_code":"2",
    "gn:admin2_code":"94.0",
    "gn:admin3_code":"9472.0",
    "gn:admin4_code":"9472199.0",
    "gn:asciiname":"Lankendorf",
    "gn:country_code":"DE",
    "gn:dem":528,
    "gn:feature_class":"P",
    "gn:feature_code":"PPL",
    "gn:name":"Lankendorf",
    "gn:population":0,
    "gn:timezone":"Europe/Berlin",
    "iso:country":"DE",
    "wof:name":"Lankendorf",
    "wof:placetype":"neighbourhood"
},
  "geometry": {"coordinates":[11.68631,49.93801],"type":"Point"}
}