{
  "type": "Feature",
  "properties": {
    "iso:country":"DE",
    "name:ger_x_variant":[
        "Zentral"
    ],
    "wof:name":"Central",
    "wof:placetype":"neighbourhood"
},
  "geometry": {"coordinates":[7.07624954771591,51.19266941177171],"type":"Point"}
}