{
  "type": "Feature",
  "properties": {
    "gn:admin1_code":"7",
    "gn:admin2_code":"57.0",
    "gn:admin3_code":"5758.0",
    "gn:admin4_code":"5758020.0",
    "gn:asciiname":"Klosterheide",
    "gn:country_code":"DE",
    "gn:dem":106,
    "gn:feature_class":"P",
    "gn:feature_code":"PPLL",
    "gn:name":"Klosterheide",
    "gn:population":0,
    "gn:timezone":"Europe/Berlin",
    "iso:country":"DE",
    "wof:name":"Klosterheide",
    "wof:placetype":"neighbourhood"
},
  "geometry": {"coordinates":[8.6138,52.23906],"type":"Point"}
}