{
  "type": "Feature",
  "properties": {
    "gn:admin1_code":"6.0",
    "gn:admin2_code":"0.0",
    "gn:admin3_code":"3241.0",
    "gn:admin4_code":"3241017.0",
    "gn:asciiname":"Sedemuender",
    "gn:country_code":"DE",
    "gn:dem":118,
    "gn:feature_class":"P",
    "gn:feature_code":"PPL",
    "gn:name":"Sedem\u00fcnder",
    "gn:population":0,
    "gn:timezone":"Europe/Berlin",
    "iso:country":"DE",
    "name:gml_x_preferred":[
        "Sedemunde [a. 1237]"
    ],
    "name:osx_x_preferred":[
        "Sidenun [< a. 1007]"
    ],
    "wof:name":"Sedemuender",
    "wof:placetype":"neighbourhood"
},
  "geometry": {"coordinates":[9.52257,52.18688],"type":"Point"}
}