{
  "type": "Feature",
  "properties": {
    "gn:admin1_code":"2",
    "gn:admin2_code":"91.0",
    "gn:admin3_code":"9187.0",
    "gn:admin4_code":"9187120.0",
    "gn:asciiname":"Griessenbach",
    "gn:country_code":"DE",
    "gn:dem":477,
    "gn:feature_class":"P",
    "gn:feature_code":"PPL",
    "gn:name":"Grie\u00dfenbach",
    "gn:population":0,
    "gn:timezone":"Europe/Berlin",
    "iso:country":"DE",
    "wof:name":"Griessenbach",
    "wof:placetype":"neighbourhood"
},
  "geometry": {"coordinates":[12.10829,47.73676],"type":"Point"}
}