{
  "type": "Feature",
  "properties": {
    "gn:population":2021,
    "iso:country":"DE",
    "name:arm_x_preferred":[
        "\u0555\u0586\u057f\u0565\u0580\u0577\u057e\u0561\u0576\u0563"
    ],
    "name:baq_x_preferred":[
        "Ofterschwang"
    ],
    "name:chi_x_preferred":[
        "\u5965\u592b\u7279\u5c14\u65bd\u65fa"
    ],
    "name:deu_x_preferred":[
        "Ofterschwang"
    ],
    "name:dut_x_preferred":[
        "Ofterschwang"
    ],
    "name:eng_x_preferred":[
        "Ofterschwang"
    ],
    "name:epo_x_preferred":[
        "Ofterschwang"
    ],
    "name:eus_x_preferred":[
        "Ofterschwang"
    ],
    "name:fra_x_preferred":[
        "Ofterschwang"
    ],
    "name:fre_x_preferred":[
        "Ofterschwang"
    ],
    "name:ger_x_preferred":[
        "Ofterschwang"
    ],
    "name:gsw_x_preferred":[
        "Ofterschwang"
    ],
    "name:hbs_x_preferred":[
        "Ofterschwang"
    ],
    "name:hun_x_preferred":[
        "Ofterschwang"
    ],
    "name:hye_x_preferred":[
        "\u0555\u0586\u057f\u0565\u0580\u0577\u057e\u0561\u0576\u0563"
    ],
    "name:ind_x_preferred":[
        "Ofterschwang"
    ],
    "name:ita_x_preferred":[
        "Ofterschwang"
    ],
    "name:kaz_x_preferred":[
        "\u041e\u0444\u0442\u0435\u0440\u0448\u0432\u0430\u043d\u0433"
    ],
    "name:kir_x_preferred":[
        "\u041e\u0444\u0442\u0435\u0440\u0448\u0432\u0430\u043d\u0433"
    ],
    "name:lmo_x_preferred":[
        "Ofterschwang"
    ],
    "name:may_x_preferred":[
        "Ofterschwang"
    ],
    "name:msa_x_preferred":[
        "Ofterschwang"
    ],
    "name:nan_x_preferred":[
        "Ofterschwang"
    ],
    "name:nld_x_preferred":[
        "Ofterschwang"
    ],
    "name:per_x_preferred":[
        "\u0627\u0648\u0641\u062a\u0631\u0634\u0648\u0627\u0646\u06af"
    ],
    "name:pol_x_preferred":[
        "Ofterschwang"
    ],
    "name:ron_x_preferred":[
        "Ofterschwang"
    ],
    "name:rum_x_preferred":[
        "Ofterschwang"
    ],
    "name:rus_x_preferred":[
        "\u041e\u0444\u0442\u0435\u0440\u0448\u0432\u0430\u043d\u0433"
    ],
    "name:srp_x_preferred":[
        "\u041e\u0444\u0442\u0435\u0440\u0448\u0432\u0430\u043d\u0433"
    ],
    "name:swe_x_preferred":[
        "Ofterschwang"
    ],
    "name:ukr_x_preferred":[
        "\u041e\u0444\u0442\u0435\u0440\u0448\u0432\u0430\u043d\u0433"
    ],
    "name:uzb_x_preferred":[
        "Ofterschwang"
    ],
    "name:vie_x_preferred":[
        "Ofterschwang"
    ],
    "name:vol_x_preferred":[
        "Ofterschwang"
    ],
    "name:war_x_preferred":[
        "Ofterschwang"
    ],
    "name:zho_min_nan_x_preferred":[
        "Ofterschwang"
    ],
    "name:zho_x_preferred":[
        "\u5965\u592b\u7279\u5c14\u65bd\u65fa"
    ],
    "qs:a0":"Bundesrepublik Deutschland",
    "qs:a1":"*Bayern",
    "qs:a1r":"0",
    "qs:a2":"Oberallg\u00e4u",
    "qs:adm0":"Bundesrepublik Deutschland",
    "qs:la_lc":"*",
    "qs:level":"locality",
    "qs:loc":"Ofterschwang",
    "qs:loc_alt":"Ofterschwang",
    "qs:pop":0,
    "qs:type":"buffered point",
    "wd:wordcount":320,
    "wof:name":"Ofterschwang",
    "wof:placetype":"locality",
    "wof:population":2021
},
  "geometry": {"coordinates":[10.235488,47.496286],"type":"Point"}
}