{
  "type": "Feature",
  "properties": {
    "gn:admin1_code":"11.0",
    "gn:admin2_code":"00",
    "gn:admin3_code":"12066.0",
    "gn:admin4_code":"12066320.0",
    "gn:asciiname":"Wuestenhain",
    "gn:country_code":"DE",
    "gn:dem":69,
    "gn:feature_class":"P",
    "gn:feature_code":"PPL",
    "gn:name":"W\u00fcstenhain",
    "gn:population":0,
    "gn:timezone":"Europe/Berlin",
    "iso:country":"DE",
    "name:dsb_x_preferred":[
        "Hu\u0161ta\u0144"
    ],
    "wof:name":"Wuestenhain",
    "wof:placetype":"neighbourhood"
},
  "geometry": {"coordinates":[14.1216,51.71787],"type":"Point"}
}