{
  "type": "Feature",
  "properties": {
    "gn:admin1_code":"6",
    "gn:admin2_code":"0.0",
    "gn:admin3_code":"3159.0",
    "gn:admin4_code":"3159017.0",
    "gn:asciiname":"Volkmarshausen",
    "gn:country_code":"DE",
    "gn:dem":134,
    "gn:feature_class":"P",
    "gn:feature_code":"PPL",
    "gn:name":"Volkmarshausen",
    "gn:population":0,
    "gn:timezone":"Europe/Berlin",
    "iso:country":"DE",
    "wof:name":"Volkmarshausen",
    "wof:placetype":"neighbourhood"
},
  "geometry": {"coordinates":[9.66219,51.44385],"type":"Point"}
}