{
  "type": "Feature",
  "properties": {
    "gn:admin1_code":"12",
    "gn:admin2_code":"0.0",
    "gn:admin3_code":"13071.0",
    "gn:admin4_code":"13071080.0",
    "gn:asciiname":"Dalmsdorf",
    "gn:country_code":"DE",
    "gn:dem":67,
    "gn:feature_class":"P",
    "gn:feature_code":"PPL",
    "gn:name":"Dalmsdorf",
    "gn:population":0,
    "gn:timezone":"Europe/Berlin",
    "iso:country":"DE",
    "wof:name":"Dalmsdorf",
    "wof:placetype":"neighbourhood"
},
  "geometry": {"coordinates":[12.93039,53.42231999999999],"type":"Point"}
}