{
  "type": "Feature",
  "properties": {
    "gn:admin1_code":"2",
    "gn:admin2_code":"95.0",
    "gn:admin3_code":"9571.0",
    "gn:admin4_code":"9571205.0",
    "gn:asciiname":"Ellwingshofen",
    "gn:country_code":"DE",
    "gn:dem":414,
    "gn:feature_class":"P",
    "gn:feature_code":"PPL",
    "gn:name":"Ellwingshofen",
    "gn:population":0,
    "gn:timezone":"Europe/Berlin",
    "iso:country":"DE",
    "wof:name":"Ellwingshofen",
    "wof:placetype":"neighbourhood"
},
  "geometry": {"coordinates":[10.20669,49.43081],"type":"Point"}
}