{
  "type": "Feature",
  "properties": {
    "gn:admin1_code":"12",
    "gn:admin2_code":"0.0",
    "gn:admin3_code":"13072.0",
    "gn:admin4_code":"13072019.0",
    "gn:asciiname":"Steinfeld",
    "gn:country_code":"DE",
    "gn:dem":46,
    "gn:feature_class":"P",
    "gn:feature_code":"PPL",
    "gn:name":"Steinfeld",
    "gn:population":0,
    "gn:timezone":"Europe/Berlin",
    "iso:country":"DE",
    "name:ceb_x_preferred":[
        "Steinfeld"
    ],
    "name:ces_x_preferred":[
        "Steinfeld"
    ],
    "name:deu_x_preferred":[
        "Steinfeld"
    ],
    "name:epo_x_preferred":[
        "Steinfeld"
    ],
    "name:eus_x_preferred":[
        "Steinfeld"
    ],
    "name:fra_x_preferred":[
        "Steinfeld"
    ],
    "name:ita_x_preferred":[
        "Steinfeld"
    ],
    "name:jpn_x_preferred":[
        "\u30b7\u30e5\u30bf\u30a4\u30f3\u30d5\u30a7\u30eb\u30c8"
    ],
    "name:lmo_x_preferred":[
        "Steinfeld"
    ],
    "name:mkd_x_preferred":[
        "\u0428\u0442\u0430\u0458\u043d\u0444\u0435\u043b\u0434"
    ],
    "name:nds_x_preferred":[
        "Steenfeld"
    ],
    "name:nld_x_preferred":[
        "Steinfeld"
    ],
    "name:pol_x_preferred":[
        "Steinfeld"
    ],
    "name:rus_x_preferred":[
        "\u0428\u0442\u0430\u0439\u043d\u0444\u0435\u043b\u044c\u0434"
    ],
    "name:spa_x_preferred":[
        "Steinfeld"
    ],
    "name:srp_x_preferred":[
        "\u0428\u0442\u0430\u0458\u043d\u0444\u0435\u043b\u0434"
    ],
    "name:swe_x_preferred":[
        "Steinfeld"
    ],
    "name:vol_x_preferred":[
        "Steinfeld"
    ],
    "wof:name":"Steinfeld",
    "wof:placetype":"neighbourhood"
},
  "geometry": {"coordinates":[12.30975,54.10813],"type":"Point"}
}