{
  "type": "Feature",
  "properties": {
    "gn:admin1_code":"7",
    "gn:admin2_code":"53.0",
    "gn:admin3_code":"5374.0",
    "gn:admin4_code":"5374024.0",
    "gn:asciiname":"Dannenberg",
    "gn:country_code":"DE",
    "gn:dem":440,
    "gn:feature_class":"P",
    "gn:feature_code":"PPL",
    "gn:name":"Dannenberg",
    "gn:population":0,
    "gn:timezone":"Europe/Berlin",
    "iso:country":"DE",
    "name:ceb_x_preferred":[
        "Dannenberg"
    ],
    "name:deu_x_preferred":[
        "Dannenberg"
    ],
    "name:est_x_preferred":[
        "Dannenberg"
    ],
    "name:lav_x_preferred":[
        "Dannenbergs"
    ],
    "name:nds_x_preferred":[
        "Dannenberg"
    ],
    "name:nld_x_preferred":[
        "Dannenberg"
    ],
    "name:pol_x_preferred":[
        "Dannenberg"
    ],
    "name:rus_x_preferred":[
        "\u0414\u0430\u043d\u043d\u0435\u043d\u0431\u0435\u0440\u0433"
    ],
    "wof:name":"Dannenberg",
    "wof:placetype":"neighbourhood"
},
  "geometry": {"coordinates":[7.59893,51.07506],"type":"Point"}
}