{
  "type": "Feature",
  "properties": {
    "gn:gn_country":"DE",
    "gn:gn_fcode":"PPLA4",
    "gn:gn_pop":516,
    "gn:population":516,
    "iso:country":"DE",
    "name:baq_x_preferred":[
        "Kalt"
    ],
    "name:chi_x_preferred":[
        "\u5361\u5c14\u7279"
    ],
    "name:dut_x_preferred":[
        "Kalt"
    ],
    "name:eng_x_preferred":[
        "Kalt"
    ],
    "name:epo_x_preferred":[
        "Kalt"
    ],
    "name:fre_x_preferred":[
        "Kalt"
    ],
    "name:ger_x_preferred":[
        "Kalt"
    ],
    "name:hun_x_preferred":[
        "Kalt"
    ],
    "name:ita_x_preferred":[
        "Kalt"
    ],
    "name:jpn_x_preferred":[
        "\u30ab\u30eb\u30c8"
    ],
    "name:kaz_x_preferred":[
        "\u041a\u0430\u043b\u044c\u0442"
    ],
    "name:kir_x_preferred":[
        "\u041a\u0430\u043b\u044c\u0442"
    ],
    "name:may_x_preferred":[
        "Kalt"
    ],
    "name:pol_x_preferred":[
        "Kalt"
    ],
    "name:por_x_preferred":[
        "Kalt"
    ],
    "name:rum_x_preferred":[
        "Kalt"
    ],
    "name:rus_x_preferred":[
        "\u041a\u0430\u043b\u044c\u0442"
    ],
    "name:srp_x_preferred":[
        "\u041a\u0430\u043b\u0442"
    ],
    "name:ukr_x_preferred":[
        "\u041a\u0430\u043b\u044c\u0442"
    ],
    "name:uzb_x_preferred":[
        "Kalt"
    ],
    "name:vie_x_preferred":[
        "Kalt"
    ],
    "name:vol_x_preferred":[
        "Kalt"
    ],
    "name:war_x_preferred":[
        "Kalt"
    ],
    "qs_pg:aaroncc":"DE",
    "qs_pg:gn_country":"DE",
    "qs_pg:gn_fcode":"PPLA4",
    "qs_pg:gn_pop":516,
    "qs_pg:name":"Kalt",
    "qs_pg:photos_9r":0,
    "qs_pg:photos_sr":0,
    "qs_pg:pop_sr":2,
    "qs_pg:qs_pg_placetype":"locality",
    "wof:name":"Kalt",
    "wof:placetype":"locality",
    "wof:population":516
},
  "geometry": {"coordinates":[7.39466,50.26729],"type":"Point"}
}