{
  "type": "Feature",
  "properties": {
    "gn:admin1_code":"7",
    "gn:admin2_code":"51.0",
    "gn:admin3_code":"5170.0",
    "gn:admin4_code":"5170024.0",
    "gn:asciiname":"Utfort",
    "gn:country_code":"DE",
    "gn:dem":28,
    "gn:feature_class":"P",
    "gn:feature_code":"PPL",
    "gn:name":"Utfort",
    "gn:population":0,
    "gn:timezone":"Europe/Berlin",
    "iso:country":"DE",
    "wof:name":"Utfort",
    "wof:placetype":"neighbourhood"
},
  "geometry": {"coordinates":[6.62733,51.47099],"type":"Point"}
}