{
  "type": "Feature",
  "properties": {
    "gn:admin1_code":"1",
    "gn:admin2_code":"83.0",
    "gn:admin3_code":"8311.0",
    "gn:admin4_code":"8311000.0",
    "gn:asciiname":"Lehen",
    "gn:country_code":"DE",
    "gn:dem":234,
    "gn:feature_class":"P",
    "gn:feature_code":"PPL",
    "gn:name":"Lehen",
    "gn:population":0,
    "gn:timezone":"Europe/Berlin",
    "iso:country":"DE",
    "name:bar_x_preferred":[
        "Lehen"
    ],
    "name:deu_x_preferred":[
        "Lehen"
    ],
    "wof:name":"Lehen",
    "wof:placetype":"neighbourhood"
},
  "geometry": {"coordinates":[7.80606,48.01496],"type":"Point"}
}