{
  "type": "Feature",
  "properties": {
    "gn:admin1_code":"2",
    "gn:admin2_code":"91.0",
    "gn:admin3_code":"9178.0",
    "gn:admin4_code":"9178124.0",
    "gn:asciiname":"Weihenstephan",
    "gn:country_code":"DE",
    "gn:dem":443,
    "gn:feature_class":"P",
    "gn:feature_code":"PPL",
    "gn:name":"Weihenstephan",
    "gn:population":0,
    "gn:timezone":"Europe/Berlin",
    "iso:country":"DE",
    "name:deu_x_preferred":[
        "Weihenstephan"
    ],
    "name:ell_x_preferred":[
        "\u0392\u03ac\u03b9\u03b5\u03bd\u03c3\u03c4\u03b5\u03c6\u03b1\u03bd"
    ],
    "name:epo_x_preferred":[
        "Weihenstephan"
    ],
    "wof:name":"Weihenstephan",
    "wof:placetype":"neighbourhood"
},
  "geometry": {"coordinates":[11.73758,48.39294],"type":"Point"}
}