{
  "type": "Feature",
  "properties": {
    "gn:admin1_code":"2.0",
    "gn:admin2_code":"91.0",
    "gn:admin3_code":"9183.0",
    "gn:admin4_code":"9183127.0",
    "gn:asciiname":"Amering",
    "gn:country_code":"DE",
    "gn:dem":443,
    "gn:feature_class":"P",
    "gn:feature_code":"PPL",
    "gn:name":"Amering",
    "gn:population":0,
    "gn:timezone":"Europe/Berlin",
    "iso:country":"DE",
    "name:ceb_x_preferred":[
        "Amering"
    ],
    "name:deu_x_preferred":[
        "Amering"
    ],
    "name:fas_x_preferred":[
        "\u0627\u0645\u0631\u06cc\u0646\u06af"
    ],
    "name:fra_x_preferred":[
        "Amering"
    ],
    "name:ita_x_preferred":[
        "Amering"
    ],
    "name:kaz_x_preferred":[
        "\u0410\u043c\u0435\u0440\u0438\u043d\u0433"
    ],
    "name:nld_x_preferred":[
        "Amering"
    ],
    "name:por_x_preferred":[
        "Amering"
    ],
    "name:rus_x_preferred":[
        "\u0410\u043c\u0435\u0440\u0438\u043d\u0433"
    ],
    "name:slk_x_preferred":[
        "Amering"
    ],
    "name:swe_x_preferred":[
        "Amering"
    ],
    "name:uzb_x_preferred":[
        "Amering"
    ],
    "name:vie_x_preferred":[
        "Amering"
    ],
    "name:vol_x_preferred":[
        "Amering"
    ],
    "name:war_x_preferred":[
        "Amering"
    ],
    "name:zho_x_preferred":[
        "\u963f\u6885\u7075"
    ],
    "wof:name":"Amering",
    "wof:placetype":"neighbourhood"
},
  "geometry": {"coordinates":[12.46993,48.30575],"type":"Point"}
}