{
  "type": "Feature",
  "properties": {
    "gn:admin1_code":"2.0",
    "gn:admin2_code":"92.0",
    "gn:admin3_code":"9275.0",
    "gn:admin4_code":"9275156.0",
    "gn:asciiname":"Kropfmuhl",
    "gn:country_code":"DE",
    "gn:dem":713,
    "gn:feature_class":"P",
    "gn:feature_code":"PPL",
    "gn:name":"Kropfm\u00fchl",
    "gn:population":0,
    "gn:timezone":"Europe/Berlin",
    "iso:country":"DE",
    "wof:name":"Kropfmuhl",
    "wof:placetype":"neighbourhood"
},
  "geometry": {"coordinates":[13.73333,48.61667],"type":"Point"}
}