{
  "type": "Feature",
  "properties": {
    "gn:admin1_code":"5",
    "gn:admin2_code":"65.0",
    "gn:admin3_code":"6534.0",
    "gn:admin4_code":"6534004.0",
    "gn:asciiname":"Engelbach",
    "gn:country_code":"DE",
    "gn:dem":299,
    "gn:feature_class":"P",
    "gn:feature_code":"PPL",
    "gn:name":"Engelbach",
    "gn:population":0,
    "gn:timezone":"Europe/Berlin",
    "iso:country":"DE",
    "wof:name":"Engelbach",
    "wof:placetype":"neighbourhood"
},
  "geometry": {"coordinates":[8.60839,50.92429],"type":"Point"}
}