{
  "type": "Feature",
  "properties": {
    "gn:admin1_code":"13",
    "gn:admin2_code":"0.0",
    "gn:admin3_code":"14522.0",
    "gn:admin4_code":"14522200.0",
    "gn:asciiname":"Neuwaltersdorf",
    "gn:country_code":"DE",
    "gn:dem":538,
    "gn:feature_class":"P",
    "gn:feature_code":"PPL",
    "gn:name":"Neuwaltersdorf",
    "gn:population":0,
    "gn:timezone":"Europe/Berlin",
    "iso:country":"DE",
    "wof:name":"Neuwaltersdorf",
    "wof:placetype":"neighbourhood"
},
  "geometry": {"coordinates":[13.31667,50.78333],"type":"Point"}
}