{
  "type": "Feature",
  "properties": {
    "gn:admin1_code":"8",
    "gn:admin2_code":"0.0",
    "gn:admin3_code":"7233.0",
    "gn:admin4_code":"7233501.0",
    "gn:asciiname":"Neunkirchen",
    "gn:country_code":"DE",
    "gn:dem":434,
    "gn:feature_class":"P",
    "gn:feature_code":"PPL",
    "gn:name":"Neunkirchen",
    "gn:population":0,
    "gn:timezone":"Europe/Berlin",
    "iso:country":"DE",
    "name:bos_x_preferred":[
        "Neunkirchen"
    ],
    "name:ceb_x_preferred":[
        "Neunkirchen"
    ],
    "name:ces_x_preferred":[
        "Neunkirchen"
    ],
    "name:deu_x_preferred":[
        "Neunkirchen"
    ],
    "name:epo_x_preferred":[
        "Neunkirchen"
    ],
    "name:fin_x_preferred":[
        "Neunkirchen"
    ],
    "name:fra_x_preferred":[
        "Neunkirchen"
    ],
    "name:hun_x_preferred":[
        "Neunkirchen"
    ],
    "name:hye_x_preferred":[
        "\u0546\u0578\u0575\u0576\u056f\u056b\u0580\u056d\u0565\u0576"
    ],
    "name:ita_x_preferred":[
        "Neunkirchen"
    ],
    "name:jpn_x_preferred":[
        "\u30ce\u30a4\u30f3\u30ad\u30eb\u30d2\u30a7\u30f3"
    ],
    "name:kaz_x_preferred":[
        "\u041d\u043e\u0439\u043d\u043a\u0438\u0440\u0445\u0435\u043d"
    ],
    "name:lmo_x_preferred":[
        "Neunkirchen"
    ],
    "name:nds_x_preferred":[
        "Neenkark"
    ],
    "name:nld_x_preferred":[
        "Neunkirchen"
    ],
    "name:nor_x_preferred":[
        "Neunkirchen"
    ],
    "name:pol_x_preferred":[
        "Neunkirchen"
    ],
    "name:por_x_preferred":[
        "Neunkirchen"
    ],
    "name:ron_x_preferred":[
        "Neunkirchen"
    ],
    "name:rus_x_preferred":[
        "\u041d\u043e\u0439\u043d\u043a\u0438\u0440\u0445\u0435\u043d"
    ],
    "name:slk_x_preferred":[
        "Neunkirchen"
    ],
    "name:spa_x_preferred":[
        "Neunkirchen"
    ],
    "name:srp_x_preferred":[
        "\u041d\u043e\u0458\u043d\u043a\u0438\u0440\u0445\u0435\u043d"
    ],
    "name:swe_x_preferred":[
        "Neunkirchen"
    ],
    "name:ukr_x_preferred":[
        "\u041d\u043e\u0439\u043d\u043a\u0456\u0440\u0445\u0435\u043d"
    ],
    "name:vol_x_preferred":[
        "Neunkirchen"
    ],
    "name:zho_x_preferred":[
        "\u8afe\u56e0\u57fa\u8208"
    ],
    "wof:name":"Neunkirchen",
    "wof:placetype":"neighbourhood"
},
  "geometry": {"coordinates":[6.79441,50.20323],"type":"Point"}
}