{
  "type": "Feature",
  "properties": {
    "gn:admin1_code":"2",
    "gn:admin2_code":"95.0",
    "gn:admin3_code":"9574.0",
    "gn:admin4_code":"9574157.0",
    "gn:asciiname":"Unterlindelburg",
    "gn:country_code":"DE",
    "gn:dem":410,
    "gn:feature_class":"P",
    "gn:feature_code":"PPL",
    "gn:name":"Unterlindelburg",
    "gn:population":0,
    "gn:timezone":"Europe/Berlin",
    "iso:country":"DE",
    "wof:name":"Unterlindelburg",
    "wof:placetype":"neighbourhood"
},
  "geometry": {"coordinates":[11.27849,49.33245],"type":"Point"}
}