{
  "type": "Feature",
  "properties": {
    "gn:admin1_code":"6.0",
    "gn:admin2_code":"0.0",
    "gn:admin3_code":"3352.0",
    "gn:admin4_code":"3352055.0",
    "gn:asciiname":"Bielenberg",
    "gn:country_code":"DE",
    "gn:dem":4,
    "gn:feature_class":"P",
    "gn:feature_code":"PPL",
    "gn:name":"Bielenberg",
    "gn:population":0,
    "gn:timezone":"Europe/Berlin",
    "iso:country":"DE",
    "name:und_x_variant":[
        "Am Bielenberge",
        "Bielenberg"
    ],
    "wof:name":"Bielenberg",
    "wof:placetype":"neighbourhood"
},
  "geometry": {"coordinates":[8.76632,53.73356],"type":"Point"}
}