{
  "type": "Feature",
  "properties": {
    "gn:admin1_code":"5",
    "gn:admin2_code":"65.0",
    "gn:admin3_code":"6535.0",
    "gn:admin4_code":"6535009.0",
    "gn:asciiname":"Ober Ofleiden",
    "gn:country_code":"DE",
    "gn:dem":209,
    "gn:feature_class":"P",
    "gn:feature_code":"PPL",
    "gn:name":"Ober Ofleiden",
    "gn:population":0,
    "gn:timezone":"Europe/Berlin",
    "iso:country":"DE",
    "wof:name":"Ober Ofleiden",
    "wof:placetype":"neighbourhood"
},
  "geometry": {"coordinates":[8.98258,50.73414],"type":"Point"}
}