{
  "type": "Feature",
  "properties": {
    "gn:population":4516,
    "iso:country":"DE",
    "name:arm_x_preferred":[
        "\u0554\u0575\u0578\u0576\u056b\u0563\u057d\u0574\u0578\u057d"
    ],
    "name:baq_x_preferred":[
        "K\u00f6nigsmoos"
    ],
    "name:ceb_x_preferred":[
        "K\u00f6nigsmoos"
    ],
    "name:chi_x_preferred":[
        "\u514b\u5c3c\u683c\u65af\u83ab\u65af"
    ],
    "name:dan_x_preferred":[
        "K\u00f6nigsmoos"
    ],
    "name:deu_x_preferred":[
        "K\u00f6nigsmoos"
    ],
    "name:dut_x_preferred":[
        "K\u00f6nigsmoos"
    ],
    "name:eng_x_preferred":[
        "K\u00f6nigsmoos"
    ],
    "name:epo_x_preferred":[
        "K\u00f6nigsmoos"
    ],
    "name:eus_x_preferred":[
        "K\u00f6nigsmoos"
    ],
    "name:fas_x_preferred":[
        "\u06a9\u0648\u0646\u06cc\u06af\u0633\u0645\u0648\u0633"
    ],
    "name:fra_x_preferred":[
        "K\u00f6nigsmoos"
    ],
    "name:fre_x_preferred":[
        "K\u00f6nigsmoos"
    ],
    "name:ger_x_preferred":[
        "K\u00f6nigsmoos"
    ],
    "name:hun_x_preferred":[
        "K\u00f6nigsmoos"
    ],
    "name:hye_x_preferred":[
        "\u0554\u0575\u0578\u0576\u056b\u0563\u057d\u0574\u0578\u057d"
    ],
    "name:ind_x_preferred":[
        "K\u00f6nigsmoos"
    ],
    "name:ita_x_preferred":[
        "K\u00f6nigsmoos"
    ],
    "name:jpn_x_preferred":[
        "\u30b1\u30fc\u30cb\u30d2\u30b9\u30e2\u30fc\u30b9"
    ],
    "name:lmo_x_preferred":[
        "K\u00f6nigsmoos"
    ],
    "name:may_x_preferred":[
        "K\u00f6nigsmoos"
    ],
    "name:nan_x_preferred":[
        "K\u00f6nigsmoos"
    ],
    "name:per_x_preferred":[
        "\u06a9\u0648\u0646\u06cc\u06af\u0633\u0645\u0648\u0633"
    ],
    "name:pol_x_preferred":[
        "K\u00f6nigsmoos"
    ],
    "name:por_x_preferred":[
        "K\u00f6nigsmoos"
    ],
    "name:rum_x_preferred":[
        "K\u00f6nigsmoos"
    ],
    "name:rus_x_preferred":[
        "\u041a\u0451\u043d\u0438\u0433\u0441\u043c\u043e\u0441"
    ],
    "name:srp_x_preferred":[
        "\u041a\u0435\u043d\u0438\u0433\u0441\u043c\u043e\u0441"
    ],
    "name:ukr_x_preferred":[
        "\u041a\u0435\u043d\u0456\u0433\u0441\u043c\u043e\u0441"
    ],
    "name:uzb_x_preferred":[
        "K\u00f6nigsmoos"
    ],
    "name:vie_x_preferred":[
        "K\u00f6nigsmoos"
    ],
    "name:vol_x_preferred":[
        "K\u00f6nigsmoos"
    ],
    "name:war_x_preferred":[
        "K\u00f6nigsmoos"
    ],
    "qs:a0":"Bundesrepublik Deutschland",
    "qs:a1":"*Bayern",
    "qs:a1r":"0",
    "qs:a2":"Neuburg-Schrobenhausen",
    "qs:adm0":"Bundesrepublik Deutschland",
    "qs:la_lc":"*",
    "qs:level":"locality",
    "qs:loc":"K\u00f6nigsmoos",
    "qs:loc_alt":"Koenigsmoos",
    "qs:pop":0,
    "qs:type":"buffered point",
    "wd:wordcount":35,
    "wof:name":"K\u00f6nigsmoos",
    "wof:placetype":"locality",
    "wof:population":4516
},
  "geometry": {"coordinates":[11.183441,48.640252],"type":"Point"}
}