{
  "type": "Feature",
  "properties": {
    "gn:admin1_code":"5",
    "gn:admin2_code":"66.0",
    "gn:admin3_code":"6631.0",
    "gn:admin4_code":"6631004.0",
    "gn:asciiname":"Schmalnau",
    "gn:country_code":"DE",
    "gn:dem":351,
    "gn:feature_class":"P",
    "gn:feature_code":"PPL",
    "gn:name":"Schmalnau",
    "gn:population":0,
    "gn:timezone":"Europe/Berlin",
    "iso:country":"DE",
    "name:deu_x_preferred":[
        "Schmalnau"
    ],
    "wof:name":"Schmalnau",
    "wof:placetype":"neighbourhood"
},
  "geometry": {"coordinates":[9.79294,50.45351],"type":"Point"}
}