{
  "type": "Feature",
  "properties": {
    "gn:admin1_code":"7",
    "gn:admin2_code":"53.0",
    "gn:admin3_code":"5378.0",
    "gn:admin4_code":"5378024.0",
    "gn:asciiname":"Mittelauel",
    "gn:country_code":"DE",
    "gn:dem":105,
    "gn:feature_class":"P",
    "gn:feature_code":"PPL",
    "gn:name":"Mittelauel",
    "gn:population":0,
    "gn:timezone":"Europe/Berlin",
    "iso:country":"DE",
    "wof:name":"Mittelauel",
    "wof:placetype":"neighbourhood"
},
  "geometry": {"coordinates":[7.2107,50.94476],"type":"Point"}
}