{
  "type": "Feature",
  "properties": {
    "gn:admin1_code":"6",
    "gn:admin2_code":"0.0",
    "gn:admin3_code":"3459.0",
    "gn:admin4_code":"3459022.0",
    "gn:asciiname":"Hilter",
    "gn:country_code":"DE",
    "gn:dem":124,
    "gn:feature_class":"P",
    "gn:feature_code":"PPL",
    "gn:name":"Hilter",
    "gn:population":10173,
    "gn:timezone":"Europe/Berlin",
    "iso:country":"DE",
    "name:ceb_x_preferred":[
        "Hilter"
    ],
    "name:est_x_preferred":[
        "Hilter"
    ],
    "name:fas_x_preferred":[
        "\u0647\u06cc\u0644\u062a\u0631"
    ],
    "name:jpn_x_preferred":[
        "\u30d2\u30eb\u30bf\u30fc\u30fb\u30a2\u30e0\u30fb\u30c8\u30a4\u30c8\u30d6\u30eb\u30ac\u30fc\u30fb\u30f4\u30a1\u30eb\u30c8"
    ],
    "name:kaz_x_preferred":[
        "\u0425\u0438\u043b\u044c\u0442\u0435\u0440-\u0430\u043c-\u0422\u043e\u0439\u0442\u043e\u0431\u0443\u0440\u0433\u0435\u0440-\u0412\u0430\u043b\u044c\u0434"
    ],
    "name:kir_x_preferred":[
        "\u0425\u0438\u043b\u044c\u0442\u0435\u0440-\u0430\u043c-\u0422\u043e\u0439\u0442\u043e\u0431\u0443\u0440\u0433\u0435\u0440-\u0412\u0430\u043b\u044c\u0434"
    ],
    "name:msa_x_preferred":[
        "Hilter"
    ],
    "name:rus_x_preferred":[
        "\u0425\u0438\u043b\u044c\u0442\u0435\u0440-\u0430\u043c-\u0422\u043e\u0439\u0442\u043e\u0431\u0443\u0440\u0433\u0435\u0440-\u0412\u0430\u043b\u044c\u0434"
    ],
    "name:ukr_x_preferred":[
        "\u0413\u0456\u043b\u044c\u0442\u0435\u0440"
    ],
    "name:vie_x_preferred":[
        "Hilter"
    ],
    "name:war_x_preferred":[
        "Hilter"
    ],
    "name:zho_x_preferred":[
        "\u6761\u987f\u5821\u6797\u5c71\u9e93\u5e0c\u7279\u5c14"
    ],
    "wof:name":"Hilter",
    "wof:placetype":"neighbourhood",
    "wof:population":10173
},
  "geometry": {"coordinates":[8.14715,52.13573],"type":"Point"}
}