{
  "type": "Feature",
  "properties": {
    "gn:admin1_code":"7",
    "gn:admin2_code":"57.0",
    "gn:admin3_code":"5770.0",
    "gn:admin4_code":"5770028.0",
    "gn:asciiname":"Lahde",
    "gn:country_code":"DE",
    "gn:dem":43,
    "gn:feature_class":"P",
    "gn:feature_code":"PPL",
    "gn:name":"Lahde",
    "gn:population":0,
    "gn:timezone":"Europe/Berlin",
    "iso:country":"DE",
    "name:fin_x_preferred":[
        "L\u00e4hde"
    ],
    "wof:name":"Lahde",
    "wof:placetype":"neighbourhood"
},
  "geometry": {"coordinates":[8.99954,52.37058],"type":"Point"}
}