{
  "type": "Feature",
  "properties": {
    "gn:admin1_code":"6",
    "gn:admin2_code":"0.0",
    "gn:admin3_code":"3157.0",
    "gn:admin4_code":"3157006.0",
    "gn:asciiname":"Stederdorf",
    "gn:country_code":"DE",
    "gn:dem":72,
    "gn:feature_class":"P",
    "gn:feature_code":"PPL",
    "gn:name":"Stederdorf",
    "gn:population":0,
    "gn:timezone":"Europe/Berlin",
    "iso:country":"DE",
    "name:nds_x_preferred":[
        "Stie'erdorp"
    ],
    "wof:name":"Stederdorf",
    "wof:placetype":"neighbourhood"
},
  "geometry": {"coordinates":[10.24647,52.34981],"type":"Point"}
}