{
  "type": "Feature",
  "properties": {
    "gn:admin1_code":"1",
    "gn:admin2_code":"82.0",
    "gn:admin3_code":"8236.0",
    "gn:admin4_code":"8236043.0",
    "gn:asciiname":"Waldrennach",
    "gn:country_code":"DE",
    "gn:dem":551,
    "gn:feature_class":"P",
    "gn:feature_code":"PPL",
    "gn:name":"Waldrennach",
    "gn:population":0,
    "gn:timezone":"Europe/Berlin",
    "iso:country":"DE",
    "wof:name":"Waldrennach",
    "wof:placetype":"neighbourhood"
},
  "geometry": {"coordinates":[8.61087,48.83299],"type":"Point"}
}