{
  "type": "Feature",
  "properties": {
    "gn:gn_country":"DE",
    "gn:gn_fcode":"PPLA4",
    "gn:gn_pop":509,
    "gn:population":509,
    "iso:country":"DE",
    "name:chi_x_preferred":[
        "\u963f\u5c14\u7279\u6797"
    ],
    "name:dut_x_preferred":[
        "Alt Tellin"
    ],
    "name:eng_x_preferred":[
        "Alt Tellin"
    ],
    "name:epo_x_preferred":[
        "Alt Tellin"
    ],
    "name:fas_x_preferred":[
        "\u0627\u0644\u062a \u062a\u0644\u06cc\u0646"
    ],
    "name:fre_x_preferred":[
        "Alt Tellin"
    ],
    "name:ger_x_preferred":[
        "Alt Tellin"
    ],
    "name:hun_x_preferred":[
        "Alt Tellin"
    ],
    "name:ita_x_preferred":[
        "Alt Tellin"
    ],
    "name:kaz_x_preferred":[
        "\u0410\u043b\u044c\u0442-\u0422\u0435\u043b\u043b\u0438\u043d"
    ],
    "name:kir_x_preferred":[
        "\u0410\u043b\u044c\u0442-\u0422\u0435\u043b\u043b\u0438\u043d"
    ],
    "name:mac_x_preferred":[
        "\u0410\u043b\u0442 \u0422\u0435\u043b\u0438\u043d"
    ],
    "name:may_x_preferred":[
        "Alt Tellin"
    ],
    "name:mkd_x_preferred":[
        "\u0410\u043b\u0442 \u0422\u0435\u043b\u0438\u043d"
    ],
    "name:per_x_preferred":[
        "\u0627\u0644\u062a \u062a\u0644\u06cc\u0646"
    ],
    "name:pol_x_preferred":[
        "Alt Tellin"
    ],
    "name:rum_x_preferred":[
        "Alt Tellin"
    ],
    "name:rus_x_preferred":[
        "\u0410\u043b\u044c\u0442-\u0422\u0435\u043b\u043b\u0438\u043d"
    ],
    "name:srp_x_preferred":[
        "\u0410\u043b\u0442 \u0422\u0435\u043b\u0438\u043d"
    ],
    "name:ukr_x_preferred":[
        "\u0410\u043b\u044c\u0442-\u0422\u0435\u043b\u043b\u0456\u043d"
    ],
    "name:uzb_x_preferred":[
        "Alt Tellin"
    ],
    "name:vie_x_preferred":[
        "Alt Tellin"
    ],
    "name:vol_x_preferred":[
        "Alt Tellin"
    ],
    "name:war_x_preferred":[
        "Alt Tellin"
    ],
    "name:zho_x_preferred":[
        "\u963f\u5c14\u7279\u6797"
    ],
    "qs_pg:aaroncc":"DE",
    "qs_pg:gn_country":"DE",
    "qs_pg:gn_fcode":"PPLA4",
    "qs_pg:gn_pop":509,
    "qs_pg:name":"Alt Tellin",
    "qs_pg:name_adm0":"Deutschland",
    "qs_pg:name_adm1":"Mecklenburg-Vorpommern",
    "qs_pg:photos_9r":0,
    "qs_pg:photos_sr":0,
    "qs_pg:pop_sr":2,
    "qs_pg:qs_pg_placetype":"locality",
    "qs_pg:qs_pg_placetype_gp":"Town",
    "qs_pg:woe_adm0":23424829,
    "woe:adm0_id":23424829,
    "woe:name_adm0":"Deutschland",
    "woe:name_adm1":"Mecklenburg-Vorpommern",
    "woe:placetype":"Town",
    "wof:name":"Alt Tellin",
    "wof:placetype":"locality",
    "wof:population":509
},
  "geometry": {"coordinates":[13.25,53.85],"type":"Point"}
}