{
  "type": "Feature",
  "properties": {
    "gn:admin1_code":"13",
    "gn:admin2_code":"0.0",
    "gn:admin3_code":"14521.0",
    "gn:admin4_code":"14521530.0",
    "gn:asciiname":"Priesterhaeuser",
    "gn:country_code":"DE",
    "gn:dem":541,
    "gn:feature_class":"P",
    "gn:feature_code":"PPL",
    "gn:name":"Priesterh\u00e4user",
    "gn:population":0,
    "gn:timezone":"Europe/Berlin",
    "iso:country":"DE",
    "wof:name":"Priesterhaeuser",
    "wof:placetype":"neighbourhood"
},
  "geometry": {"coordinates":[12.62264,50.57883],"type":"Point"}
}