{
  "type": "Feature",
  "properties": {
    "gn:country":"DE",
    "gn:fcode":"PPL",
    "gn:population":0,
    "iso:country":"DE",
    "name:ara_x_preferred":[
        "\u0641\u0627\u064a\u0633\u0643\u064a\u0631\u0634\u0646"
    ],
    "name:cat_x_preferred":[
        "Weiskirchen"
    ],
    "name:ceb_x_preferred":[
        "Weiskirchen"
    ],
    "name:deu_x_preferred":[
        "Weiskirchen"
    ],
    "name:epo_x_preferred":[
        "Weiskirchen"
    ],
    "name:eus_x_preferred":[
        "Weiskirchen"
    ],
    "name:fas_x_preferred":[
        "\u0648\u0627\u06cc\u0633 \u06a9\u06cc\u0631\u0634\u0646"
    ],
    "name:fra_x_preferred":[
        "Weiskirchen"
    ],
    "name:hun_x_preferred":[
        "Weiskirchen"
    ],
    "name:ita_x_preferred":[
        "Weiskirchen"
    ],
    "name:kaz_x_preferred":[
        "\u0412\u0430\u0439\u0441\u043a\u0438\u0440\u0445\u0435\u043d"
    ],
    "name:kir_x_preferred":[
        "\u0412\u0430\u0439\u0441\u043a\u0438\u0440\u0445\u0435\u043d"
    ],
    "name:msa_x_preferred":[
        "Weiskirchen"
    ],
    "name:nld_x_preferred":[
        "Weiskirchen"
    ],
    "name:pol_x_preferred":[
        "Weiskirchen"
    ],
    "name:por_x_preferred":[
        "Weiskirchen"
    ],
    "name:ron_x_preferred":[
        "Weiskirchen"
    ],
    "name:rus_x_preferred":[
        "\u0412\u0430\u0439\u0441\u043a\u0438\u0440\u0445\u0435\u043d"
    ],
    "name:spa_x_preferred":[
        "Weiskirchen"
    ],
    "name:srp_x_preferred":[
        "\u0412\u0430\u0458\u0441\u043a\u0438\u0440\u0445\u0435\u043d"
    ],
    "name:ukr_x_preferred":[
        "\u0412\u0430\u0439\u0441\u043a\u0456\u0440\u0445\u0435\u043d"
    ],
    "name:uzb_x_preferred":[
        "Weiskirchen"
    ],
    "name:vie_x_preferred":[
        "Weiskirchen"
    ],
    "name:vol_x_preferred":[
        "Weiskirchen"
    ],
    "name:war_x_preferred":[
        "Weiskirchen"
    ],
    "name:zho_x_preferred":[
        "\u9b4f\u65af\u57fa\u5174"
    ],
    "qs_pg:aaroncc":"DE",
    "qs_pg:gn_country":"DE",
    "qs_pg:gn_fcode":"PPL",
    "qs_pg:gn_pop":0,
    "qs_pg:name":"Weiskirchen",
    "qs_pg:name_adm0":"Deutschland",
    "qs_pg:name_adm1":"Hessen",
    "qs_pg:photos":82,
    "qs_pg:photos_1k":17,
    "qs_pg:photos_9k":1,
    "qs_pg:photos_9r":3,
    "qs_pg:photos_all":82,
    "qs_pg:photos_sr":3,
    "qs_pg:pop_sr":0,
    "qs_pg:qs_pg_placetype":"locality",
    "qs_pg:qs_pg_placetype_gp":"Town",
    "qs_pg:woe_adm0":23424829,
    "woe:adm0_id":23424829,
    "woe:name_adm0":"Deutschland",
    "woe:name_adm1":"Hessen",
    "woe:placetype":"Town",
    "wof:name":"Weiskirchen",
    "wof:placetype":"neighbourhood"
},
  "geometry": {"coordinates":[8.88817,50.05272],"type":"Point"}
}