{
  "type": "Feature",
  "properties": {
    "gn:admin1_code":"12",
    "gn:admin2_code":"0.0",
    "gn:admin3_code":"13073.0",
    "gn:admin4_code":"13073095.0",
    "gn:asciiname":"Freesenort",
    "gn:country_code":"DE",
    "gn:dem":3,
    "gn:feature_class":"P",
    "gn:feature_code":"PPL",
    "gn:name":"Freesenort",
    "gn:population":0,
    "gn:timezone":"Europe/Berlin",
    "iso:country":"DE",
    "wof:name":"Freesenort",
    "wof:placetype":"neighbourhood"
},
  "geometry": {"coordinates":[13.12557,54.44529],"type":"Point"}
}