{
  "type": "Feature",
  "properties": {
    "iso:country":"DE",
    "wof:name":"Wiesenau",
    "wof:placetype":"neighbourhood"
},
  "geometry": {"coordinates":[8.63285877128581,50.16451067412555],"type":"Point"}
}