{
  "type": "Feature",
  "properties": {
    "iso:country":"DE",
    "name:ceb_x_preferred":[
        "Wiesenau"
    ],
    "name:deu_x_preferred":[
        "Wiesenau"
    ],
    "name:epo_x_preferred":[
        "Wiesenau"
    ],
    "name:eus_x_preferred":[
        "Wiesenau"
    ],
    "name:fas_x_preferred":[
        "\u0648\u06cc\u0632\u0646\u0627\u0648"
    ],
    "name:fra_x_preferred":[
        "Wiesenau"
    ],
    "name:hun_x_preferred":[
        "Wiesenau"
    ],
    "name:hye_x_preferred":[
        "\u054e\u056b\u0566\u0565\u0576\u0561\u0578\u0582"
    ],
    "name:ita_x_preferred":[
        "Wiesenau"
    ],
    "name:kaz_x_preferred":[
        "\u0412\u0438\u0437\u0435\u043d\u0430\u0443"
    ],
    "name:kir_x_preferred":[
        "\u0412\u0438\u0437\u0435\u043d\u0430\u0443"
    ],
    "name:mkd_x_preferred":[
        "\u0412\u0438\u0437\u0435\u043d\u0430\u0443"
    ],
    "name:msa_x_preferred":[
        "Wiesenau"
    ],
    "name:nld_x_preferred":[
        "Wiesenau"
    ],
    "name:pol_x_preferred":[
        "Wiesenau"
    ],
    "name:ron_x_preferred":[
        "Wiesenau"
    ],
    "name:rus_x_preferred":[
        "\u0412\u0438\u0437\u0435\u043d\u0430\u0443"
    ],
    "name:spa_x_preferred":[
        "Wiesenau"
    ],
    "name:srp_x_preferred":[
        "\u0412\u0438\u0437\u0435\u043d\u0430\u0443"
    ],
    "name:ukr_x_preferred":[
        "\u0412\u0456\u0437\u0435\u043d\u0430\u0443"
    ],
    "name:uzb_x_preferred":[
        "Wiesenau"
    ],
    "name:vol_x_preferred":[
        "Wiesenau"
    ],
    "name:war_x_preferred":[
        "Wiesenau"
    ],
    "name:zho_x_preferred":[
        "\u7ef4\u585e\u7459"
    ],
    "wof:name":"Wiesenau",
    "wof:placetype":"neighbourhood"
},
  "geometry": {"coordinates":[8.63285877128581,50.16451067412555],"type":"Point"}
}