{
  "type": "Feature",
  "properties": {
    "gn:admin1_code":"1.0",
    "gn:admin2_code":"084",
    "gn:admin3_code":"8415.0",
    "gn:admin4_code":"8415053.0",
    "gn:asciiname":"Wittsteig",
    "gn:country_code":"DE",
    "gn:dem":607,
    "gn:feature_class":"P",
    "gn:feature_code":"PPL",
    "gn:name":"Wittsteig",
    "gn:population":0,
    "gn:timezone":"Europe/Berlin",
    "iso:country":"DE",
    "wof:name":"Wittsteig",
    "wof:placetype":"neighbourhood"
},
  "geometry": {"coordinates":[9.50652,48.31998],"type":"Point"}
}