{
  "type": "Feature",
  "properties": {
    "gn:admin1_code":"2",
    "gn:admin2_code":"96.0",
    "gn:admin3_code":"9672.0",
    "gn:admin4_code":"9672149.0",
    "gn:asciiname":"Singenrain",
    "gn:country_code":"DE",
    "gn:dem":496,
    "gn:feature_class":"P",
    "gn:feature_code":"PPL",
    "gn:name":"Singenrain",
    "gn:population":0,
    "gn:timezone":"Europe/Berlin",
    "iso:country":"DE",
    "wof:name":"Singenrain",
    "wof:placetype":"neighbourhood"
},
  "geometry": {"coordinates":[9.88614,50.25434],"type":"Point"}
}