{
  "type": "Feature",
  "properties": {
    "iso:country":"DE",
    "wof:name":"Stadtgarten",
    "wof:placetype":"neighbourhood"
},
  "geometry": {"coordinates":[7.23407533235298,51.54416906679841],"type":"Point"}
}