{
  "type": "Feature",
  "properties": {
    "gn:admin1_code":"2",
    "gn:admin2_code":"94.0",
    "gn:admin3_code":"9475.0",
    "gn:admin4_code":"9475136.0",
    "gn:asciiname":"Oberweissenbach",
    "gn:country_code":"DE",
    "gn:dem":638,
    "gn:feature_class":"P",
    "gn:feature_code":"PPL",
    "gn:name":"Oberwei\u00dfenbach",
    "gn:population":0,
    "gn:timezone":"Europe/Berlin",
    "iso:country":"DE",
    "wof:name":"Oberweissenbach",
    "wof:placetype":"neighbourhood"
},
  "geometry": {"coordinates":[11.69304,50.23447],"type":"Point"}
}