{
  "type": "Feature",
  "properties": {
    "gn:country":"DE",
    "gn:fcode":"PPL",
    "gn:population":0,
    "iso:country":"DE",
    "name:ceb_x_preferred":[
        "Assmannshausen"
    ],
    "name:deu_x_preferred":[
        "Assmannshausen"
    ],
    "name:fas_x_preferred":[
        "\u0622\u0633\u0633\u0645\u0627\u0646\u0633\u0647\u0627\u0648\u0632\u0646"
    ],
    "name:fra_x_preferred":[
        "Assmannshausen"
    ],
    "name:nld_x_preferred":[
        "Assmannshausen"
    ],
    "name:ron_x_preferred":[
        "Assmannshausen"
    ],
    "name:zho_x_preferred":[
        "\u963f\u65af\u66fc\u65af\u8c6a\u68ee"
    ],
    "qs_pg:aaroncc":"DE",
    "qs_pg:gn_country":"DE",
    "qs_pg:gn_fcode":"PPL",
    "qs_pg:gn_pop":0,
    "qs_pg:name":"Assmannshausen",
    "qs_pg:name_adm0":"Deutschland",
    "qs_pg:name_adm1":"Hessen",
    "qs_pg:photos":655,
    "qs_pg:photos_1k":133,
    "qs_pg:photos_9k":3,
    "qs_pg:photos_9r":5,
    "qs_pg:photos_all":655,
    "qs_pg:photos_sr":8,
    "qs_pg:pop_sr":0,
    "qs_pg:qs_pg_placetype":"locality",
    "qs_pg:qs_pg_placetype_gp":"Town",
    "qs_pg:woe_adm0":23424829,
    "woe:adm0_id":23424829,
    "woe:name_adm0":"Deutschland",
    "woe:name_adm1":"Hessen",
    "woe:placetype":"Town",
    "wof:name":"Assmannshausen",
    "wof:placetype":"neighbourhood"
},
  "geometry": {"coordinates":[7.86716,49.98986],"type":"Point"}
}