{
  "type": "Feature",
  "properties": {
    "gn:admin1_code":"1.0",
    "gn:admin2_code":"081",
    "gn:admin3_code":"8127.0",
    "gn:admin4_code":"8127009.0",
    "gn:asciiname":"Winterberg",
    "gn:country_code":"DE",
    "gn:dem":340,
    "gn:feature_class":"P",
    "gn:feature_code":"PPL",
    "gn:name":"Winterberg",
    "gn:population":0,
    "gn:timezone":"Europe/Berlin",
    "iso:country":"DE",
    "wof:name":"Winterberg",
    "wof:placetype":"neighbourhood"
},
  "geometry": {"coordinates":[9.78504,49.25251],"type":"Point"}
}