{
  "type": "Feature",
  "properties": {
    "gn:admin1_code":"2",
    "gn:admin2_code":"94.0",
    "gn:admin3_code":"9475.0",
    "gn:admin4_code":"9475168.0",
    "gn:asciiname":"Schwingen",
    "gn:country_code":"DE",
    "gn:dem":528,
    "gn:feature_class":"P",
    "gn:feature_code":"PPL",
    "gn:name":"Schwingen",
    "gn:population":0,
    "gn:timezone":"Europe/Berlin",
    "iso:country":"DE",
    "wof:name":"Schwingen",
    "wof:placetype":"neighbourhood"
},
  "geometry": {"coordinates":[11.9448,50.23271],"type":"Point"}
}