{
  "type": "Feature",
  "properties": {
    "gn:admin1_code":"2",
    "gn:admin2_code":"94.0",
    "gn:admin3_code":"9475.0",
    "gn:admin4_code":"9475168.0",
    "gn:asciiname":"Schwingen",
    "gn:country_code":"DE",
    "gn:dem":528,
    "gn:feature_class":"P",
    "gn:feature_code":"PPL",
    "gn:name":"Schwingen",
    "gn:population":0,
    "gn:timezone":"Europe/Berlin",
    "iso:country":"DE",
    "name:als_x_preferred":[
        "Schwingen"
    ],
    "name:bre_x_preferred":[
        "Schwingen"
    ],
    "name:ces_x_preferred":[
        "Schwingen"
    ],
    "name:dan_x_preferred":[
        "Schwingen"
    ],
    "name:deu_x_preferred":[
        "Schwingen"
    ],
    "name:epo_x_preferred":[
        "\u015cvingo"
    ],
    "name:fra_x_preferred":[
        "Lutte suisse"
    ],
    "name:ita_x_preferred":[
        "Lotta svizzera"
    ],
    "name:jpn_x_preferred":[
        "\u30b7\u30e5\u30f4\u30a3\u30f3\u30b2\u30f3"
    ],
    "name:nld_x_preferred":[
        "Schwingen"
    ],
    "name:rus_x_preferred":[
        "\u0428\u0432\u0438\u043d\u0433\u0435\u043d"
    ],
    "name:spa_x_preferred":[
        "Schwingen"
    ],
    "name:swe_x_preferred":[
        "Schwingen"
    ],
    "name:tur_x_preferred":[
        "Schwingen"
    ],
    "wof:name":"Schwingen",
    "wof:placetype":"neighbourhood"
},
  "geometry": {"coordinates":[11.9448,50.23271],"type":"Point"}
}