{
  "type": "Feature",
  "properties": {
    "gn:admin1_code":"2",
    "gn:admin2_code":"92.0",
    "gn:admin3_code":"9279.0",
    "gn:admin4_code":"9279135.0",
    "gn:asciiname":"Pirka",
    "gn:country_code":"DE",
    "gn:dem":463,
    "gn:feature_class":"P",
    "gn:feature_code":"PPL",
    "gn:name":"Pirka",
    "gn:population":0,
    "gn:timezone":"Europe/Berlin",
    "iso:country":"DE",
    "name:ceb_x_preferred":[
        "Pirka"
    ],
    "name:deu_x_preferred":[
        "Pirka"
    ],
    "name:fas_x_preferred":[
        "\u067e\u06cc\u0631\u06a9\u0627"
    ],
    "name:fra_x_preferred":[
        "Pirka"
    ],
    "name:ita_x_preferred":[
        "Pirka"
    ],
    "name:kaz_x_preferred":[
        "\u041f\u0438\u0440\u043a\u0430"
    ],
    "name:nld_x_preferred":[
        "Pirka"
    ],
    "name:rus_x_preferred":[
        "\u041f\u0438\u0440\u043a\u0430"
    ],
    "name:slk_x_preferred":[
        "Pirka"
    ],
    "name:swe_x_preferred":[
        "Pirka"
    ],
    "name:uzb_x_preferred":[
        "Pirka"
    ],
    "name:vie_x_preferred":[
        "Pirka"
    ],
    "name:vol_x_preferred":[
        "Pirka"
    ],
    "name:war_x_preferred":[
        "Pirka"
    ],
    "name:zho_x_preferred":[
        "\u76ae\u5c14\u5361"
    ],
    "wof:name":"Pirka",
    "wof:placetype":"neighbourhood"
},
  "geometry": {"coordinates":[12.68197,48.52983],"type":"Point"}
}