{
  "type": "Feature",
  "properties": {
    "gn:admin1_code":"2",
    "gn:admin2_code":"92.0",
    "gn:admin3_code":"9274.0",
    "gn:admin4_code":"9274179.0",
    "gn:asciiname":"Mollersdorf",
    "gn:country_code":"DE",
    "gn:dem":497,
    "gn:feature_class":"P",
    "gn:feature_code":"PPL",
    "gn:name":"M\u00f6llersdorf",
    "gn:population":0,
    "gn:timezone":"Europe/Berlin",
    "iso:country":"DE",
    "wof:name":"Mollersdorf",
    "wof:placetype":"neighbourhood"
},
  "geometry": {"coordinates":[12.43409,48.4616],"type":"Point"}
}