{
  "type": "Feature",
  "properties": {
    "gn:admin1_code":"7",
    "gn:admin2_code":"51.0",
    "gn:admin3_code":"5120.0",
    "gn:admin4_code":"5120000.0",
    "gn:asciiname":"Grund",
    "gn:country_code":"DE",
    "gn:dem":224,
    "gn:feature_class":"P",
    "gn:feature_code":"PPL",
    "gn:name":"Grund",
    "gn:population":0,
    "gn:timezone":"Europe/Berlin",
    "iso:country":"DE",
    "name:ceb_x_preferred":[
        "Grund"
    ],
    "name:ces_x_preferred":[
        "Grund"
    ],
    "name:dan_x_preferred":[
        "Grund"
    ],
    "name:deu_x_preferred":[
        "Grund"
    ],
    "name:epo_x_preferred":[
        "Grund"
    ],
    "name:fas_x_preferred":[
        "\u06af\u0631\u0648\u0646\u062f"
    ],
    "name:hun_x_preferred":[
        "Grund"
    ],
    "name:isl_x_preferred":[
        "Grund"
    ],
    "name:ita_x_preferred":[
        "Grund"
    ],
    "name:nld_x_preferred":[
        "Grund"
    ],
    "name:pol_x_preferred":[
        "Grund"
    ],
    "name:swe_x_preferred":[
        "Grund"
    ],
    "wof:name":"Grund",
    "wof:placetype":"neighbourhood"
},
  "geometry": {"coordinates":[7.1853,51.20614000000001],"type":"Point"}
}