{
  "type": "Feature",
  "properties": {
    "gn:admin1_code":"13",
    "gn:admin2_code":"0.0",
    "gn:admin3_code":"14625.0",
    "gn:admin4_code":"14625190.0",
    "gn:asciiname":"Mehltheuer",
    "gn:country_code":"DE",
    "gn:dem":337,
    "gn:feature_class":"P",
    "gn:feature_code":"PPL",
    "gn:name":"Mehltheuer",
    "gn:population":0,
    "gn:timezone":"Europe/Berlin",
    "iso:country":"DE",
    "name:bak_x_preferred":[
        "\u041c\u0435\u043b\u044c\u0442\u043e\u0439\u0435\u0440"
    ],
    "name:ceb_x_preferred":[
        "Mehltheuer"
    ],
    "name:deu_x_preferred":[
        "Mehltheuer"
    ],
    "name:epo_x_preferred":[
        "Mehltheuer"
    ],
    "name:fas_x_preferred":[
        "\u0645\u0647\u0644\u062a\u0648\u06cc\u0631"
    ],
    "name:fra_x_preferred":[
        "Mehltheuer"
    ],
    "name:hsb_x_preferred":[
        "Lubjenc"
    ],
    "name:ita_x_preferred":[
        "Mehltheuer"
    ],
    "name:mkd_x_preferred":[
        "\u041c\u0435\u043b\u0442\u043e\u0458\u0435\u0440"
    ],
    "name:nld_x_preferred":[
        "Mehltheuer"
    ],
    "name:pol_x_preferred":[
        "Mehltheuer"
    ],
    "name:ron_x_preferred":[
        "Mehltheuer"
    ],
    "name:rus_x_preferred":[
        "\u041c\u0435\u043b\u044c\u0442\u043e\u0439\u0435\u0440"
    ],
    "name:srp_x_preferred":[
        "\u041c\u0435\u043b\u0442\u043e\u0458\u0435\u0440"
    ],
    "name:uzb_x_preferred":[
        "Mehltheuer"
    ],
    "name:vie_x_preferred":[
        "Mehltheuer"
    ],
    "name:vol_x_preferred":[
        "Mehltheuer"
    ],
    "name:war_x_preferred":[
        "Mehltheuer"
    ],
    "wof:name":"Mehltheuer",
    "wof:placetype":"neighbourhood"
},
  "geometry": {"coordinates":[14.47696,51.14073],"type":"Point"}
}