{
  "type": "Feature",
  "properties": {
    "iso:country":"DE",
    "name:als_x_preferred":[
        "Heimersdorf"
    ],
    "name:bug_x_preferred":[
        "Heimersdorf"
    ],
    "name:cat_x_preferred":[
        "Heimersdorf"
    ],
    "name:ceb_x_preferred":[
        "Heimersdorf"
    ],
    "name:ces_x_preferred":[
        "Heimersdorf"
    ],
    "name:deu_x_preferred":[
        "Heimersdorf"
    ],
    "name:eus_x_preferred":[
        "Heimersdorf"
    ],
    "name:fra_x_preferred":[
        "Heimersdorf"
    ],
    "name:hun_x_preferred":[
        "Heimersdorf"
    ],
    "name:ita_x_preferred":[
        "Heimersdorf"
    ],
    "name:kaz_x_preferred":[
        "\u0415\u043c\u0435\u0440\u0441\u0434\u043e\u0440\u0444"
    ],
    "name:lat_x_preferred":[
        "Heimersdorf"
    ],
    "name:msa_x_preferred":[
        "Heimersdorf"
    ],
    "name:nld_x_preferred":[
        "Heimersdorf"
    ],
    "name:oci_x_preferred":[
        "Heimersdorf"
    ],
    "name:pfl_x_preferred":[
        "Heimersdorf"
    ],
    "name:pms_x_preferred":[
        "Heimersdorf"
    ],
    "name:pol_x_preferred":[
        "Heimersdorf"
    ],
    "name:por_x_preferred":[
        "Heimersdorf"
    ],
    "name:ron_x_preferred":[
        "Heimersdorf"
    ],
    "name:rus_x_preferred":[
        "\u042d\u043c\u0435\u0440\u0441\u0434\u043e\u0440\u0444"
    ],
    "name:slk_x_preferred":[
        "Heimersdorf"
    ],
    "name:slv_x_preferred":[
        "Heimersdorf"
    ],
    "name:spa_x_preferred":[
        "Heimersdorf"
    ],
    "name:srp_x_preferred":[
        "\u0425\u0430\u0458\u043c\u0435\u0440\u0437\u0434\u043e\u0440\u0444"
    ],
    "name:swe_x_preferred":[
        "Heimersdorf"
    ],
    "name:ukr_x_preferred":[
        "\u0415\u043c\u0435\u0440\u0441\u0434\u043e\u0440\u0444"
    ],
    "name:uzb_x_preferred":[
        "Heimersdorf"
    ],
    "name:vie_x_preferred":[
        "Heimersdorf"
    ],
    "name:vol_x_preferred":[
        "Heimersdorf"
    ],
    "name:war_x_preferred":[
        "Heimersdorf"
    ],
    "name:zho_x_preferred":[
        "\u827e\u9ed8\u65af\u591a\u592b"
    ],
    "wof:name":"Heimersdorf",
    "wof:placetype":"neighbourhood"
},
  "geometry": {"coordinates":[6.89891591789258,51.00654350630764],"type":"Point"}
}