{
  "type": "Feature",
  "properties": {
    "iso:country":"DE",
    "wof:name":"Heimersdorf",
    "wof:placetype":"neighbourhood"
},
  "geometry": {"coordinates":[6.89891591789258,51.00654350630764],"type":"Point"}
}