{
  "type": "Feature",
  "properties": {
    "gn:admin1_code":"7.0",
    "gn:admin2_code":"59.0",
    "gn:admin3_code":"5974.0",
    "gn:admin4_code":"5974020.0",
    "gn:asciiname":"Boenninghausen",
    "gn:country_code":"DE",
    "gn:dem":93,
    "gn:feature_class":"P",
    "gn:feature_code":"PPL",
    "gn:name":"B\u00f6nninghausen",
    "gn:population":0,
    "gn:timezone":"Europe/Berlin",
    "iso:country":"DE",
    "wof:name":"Boenninghausen",
    "wof:placetype":"neighbourhood"
},
  "geometry": {"coordinates":[8.47369,51.66285],"type":"Point"}
}