{
  "type": "Feature",
  "properties": {
    "gn:admin1_code":"6",
    "gn:admin2_code":"0.0",
    "gn:admin3_code":"3159.0",
    "gn:admin4_code":"3159026.0",
    "gn:asciiname":"Marke",
    "gn:country_code":"DE",
    "gn:dem":239,
    "gn:feature_class":"P",
    "gn:feature_code":"PPL",
    "gn:name":"Marke",
    "gn:population":0,
    "gn:timezone":"Europe/Berlin",
    "iso:country":"DE",
    "name:als_x_preferred":[
        "Marke"
    ],
    "name:ceb_x_preferred":[
        "Marke"
    ],
    "name:deu_x_preferred":[
        "Marke"
    ],
    "name:fry_x_preferred":[
        "Marke"
    ],
    "name:lit_x_preferred":[
        "Mark\u0117"
    ],
    "name:nld_x_preferred":[
        "Marke"
    ],
    "name:pol_x_preferred":[
        "Marke"
    ],
    "name:rus_x_preferred":[
        "\u041c\u0430\u0440\u043a\u0435"
    ],
    "name:swe_x_preferred":[
        "Marke"
    ],
    "wof:name":"Marke",
    "wof:placetype":"neighbourhood"
},
  "geometry": {"coordinates":[10.12258,51.72137],"type":"Point"}
}