{
  "type": "Feature",
  "properties": {
    "gn:admin1_code":"14.0",
    "gn:admin2_code":"00",
    "gn:admin3_code":"15085.0",
    "gn:admin4_code":"15085110.0",
    "gn:asciiname":"Wieserode",
    "gn:country_code":"DE",
    "gn:dem":253,
    "gn:feature_class":"P",
    "gn:feature_code":"PPL",
    "gn:name":"Wieserode",
    "gn:population":0,
    "gn:timezone":"Europe/Berlin",
    "iso:country":"DE",
    "wof:name":"Wieserode",
    "wof:placetype":"neighbourhood"
},
  "geometry": {"coordinates":[11.33286,51.68493],"type":"Point"}
}