{
  "type": "Feature",
  "properties": {
    "gn:country":"DE",
    "gn:fcode":"PPL",
    "gn:population":252,
    "iso:country":"DE",
    "name:ara_x_preferred":[
        "\u0634\u0645\u064a\u062f\u062a\u0641\u0622\u064a\u0644\u0631"
    ],
    "name:ceb_x_preferred":[
        "Schmittweiler"
    ],
    "name:deu_x_preferred":[
        "Schmittweiler"
    ],
    "name:epo_x_preferred":[
        "Schmittweiler"
    ],
    "name:eus_x_preferred":[
        "Schmittweiler"
    ],
    "name:fas_x_preferred":[
        "\u0634\u0645\u06cc\u062a\u0648\u0627\u06cc\u0644\u0631"
    ],
    "name:fra_x_preferred":[
        "Schmittweiler"
    ],
    "name:hun_x_preferred":[
        "Schmittweiler"
    ],
    "name:ita_x_preferred":[
        "Schmittweiler"
    ],
    "name:msa_x_preferred":[
        "Schmittweiler"
    ],
    "name:nld_x_preferred":[
        "Schmittweiler"
    ],
    "name:pol_x_preferred":[
        "Schmittweiler"
    ],
    "name:por_x_preferred":[
        "Schmittweiler"
    ],
    "name:ron_x_preferred":[
        "Schmittweiler"
    ],
    "name:rus_x_preferred":[
        "\u0428\u043c\u0438\u0442\u0432\u0430\u0439\u043b\u0435\u0440"
    ],
    "name:spa_x_preferred":[
        "Schmittweiler"
    ],
    "name:srp_x_preferred":[
        "\u0428\u043c\u0438\u0442\u0432\u0430\u0458\u043b\u0435\u0440"
    ],
    "name:ukr_x_preferred":[
        "\u0428\u043c\u0456\u0442\u0442\u0432\u0430\u0439\u043b\u0435\u0440"
    ],
    "name:uzb_x_preferred":[
        "Schmittweiler"
    ],
    "name:vie_x_preferred":[
        "Schmittweiler"
    ],
    "name:vol_x_preferred":[
        "Schmittweiler"
    ],
    "name:war_x_preferred":[
        "Schmittweiler"
    ],
    "name:zho_x_preferred":[
        "\u65bd\u7c73\u7279\u97e6\u52d2"
    ],
    "qs_pg:aaroncc":"DE",
    "qs_pg:gn_country":"DE",
    "qs_pg:gn_fcode":"PPL",
    "qs_pg:gn_pop":252,
    "qs_pg:name":"Schmittweiler",
    "qs_pg:name_adm0":"Deutschland",
    "qs_pg:name_adm1":"Rheinland-Pfalz",
    "qs_pg:photos_9r":0,
    "qs_pg:photos_sr":0,
    "qs_pg:pop_sr":2,
    "qs_pg:qs_pg_placetype":"locality",
    "qs_pg:qs_pg_placetype_gp":"Town",
    "qs_pg:woe_adm0":23424829,
    "woe:adm0_id":23424829,
    "woe:name_adm0":"Deutschland",
    "woe:name_adm1":"Rheinland-Pfalz",
    "woe:placetype":"Town",
    "wof:name":"Schmittweiler",
    "wof:placetype":"neighbourhood",
    "wof:population":252
},
  "geometry": {"coordinates":[7.33784,49.41019],"type":"Point"}
}