{
  "type": "Feature",
  "properties": {
    "gn:admin1_code":"8.0",
    "gn:admin2_code":"00",
    "gn:admin3_code":"7143.0",
    "gn:admin4_code":"7143256.0",
    "gn:asciiname":"Weissenberg",
    "gn:country_code":"DE",
    "gn:dem":574,
    "gn:feature_class":"P",
    "gn:feature_code":"PPL",
    "gn:name":"Wei\u00dfenberg",
    "gn:population":0,
    "gn:timezone":"Europe/Berlin",
    "iso:country":"DE",
    "name:ceb_x_preferred":[
        "Weissenberg"
    ],
    "name:fin_x_preferred":[
        "Weissenberg"
    ],
    "name:fra_x_preferred":[
        "Weissenberg"
    ],
    "name:pol_x_preferred":[
        "Weissenberg"
    ],
    "name:swe_x_preferred":[
        "Weissenberg"
    ],
    "wof:name":"Weissenberg",
    "wof:placetype":"neighbourhood"
},
  "geometry": {"coordinates":[8.10642,50.68459],"type":"Point"}
}