{
  "type": "Feature",
  "properties": {
    "gn:admin1_code":"15.0",
    "gn:admin2_code":"0.0",
    "gn:admin3_code":"16063.0",
    "gn:admin4_code":"16063032.0",
    "gn:asciiname":"Borsch",
    "gn:country_code":"DE",
    "gn:dem":286,
    "gn:feature_class":"P",
    "gn:feature_code":"PPL",
    "gn:name":"Borsch",
    "gn:population":0,
    "gn:timezone":"Europe/Berlin",
    "iso:country":"DE",
    "wof:name":"Borsch",
    "wof:placetype":"neighbourhood"
},
  "geometry": {"coordinates":[9.96522,50.73368],"type":"Point"}
}