{
  "type": "Feature",
  "properties": {
    "gn:country":"DE",
    "gn:fcode":"PPL",
    "gn:population":0,
    "iso:country":"DE",
    "name:azb_x_preferred":[
        "\u0647\u0648\u0648"
    ],
    "name:bar_x_preferred":[
        "Hove"
    ],
    "name:ceb_x_preferred":[
        "Hove"
    ],
    "name:ces_x_preferred":[
        "Hove"
    ],
    "name:deu_x_preferred":[
        "Hove"
    ],
    "name:epo_x_preferred":[
        "Hove"
    ],
    "name:est_x_preferred":[
        "Hove"
    ],
    "name:fas_x_preferred":[
        "\u0647\u0648\u0648"
    ],
    "name:fra_x_preferred":[
        "Hove"
    ],
    "name:hin_x_preferred":[
        "\u0939\u094b\u0935"
    ],
    "name:ita_x_preferred":[
        "Hove"
    ],
    "name:nld_x_preferred":[
        "Hove"
    ],
    "name:pol_x_preferred":[
        "Hove"
    ],
    "name:por_x_preferred":[
        "Hove"
    ],
    "name:ron_x_preferred":[
        "Hove"
    ],
    "name:rus_x_preferred":[
        "\u0425\u043e\u0432"
    ],
    "name:spa_x_preferred":[
        "Hove"
    ],
    "name:srp_x_preferred":[
        "\u0425\u043e\u0443\u0432"
    ],
    "name:swe_x_preferred":[
        "Hove"
    ],
    "name:urd_x_preferred":[
        "\u06c1\u0648\u0648"
    ],
    "name:war_x_preferred":[
        "Hove"
    ],
    "name:zho_x_preferred":[
        "\u970d\u592b"
    ],
    "qs_pg:aaroncc":"DE",
    "qs_pg:gn_country":"DE",
    "qs_pg:gn_fcode":"PPL",
    "qs_pg:gn_pop":0,
    "qs_pg:name":"Hove",
    "qs_pg:name_adm0":"Deutschland",
    "qs_pg:name_adm1":"Nordrhein-Westfalen",
    "qs_pg:photos":9,
    "qs_pg:photos_1k":2,
    "qs_pg:photos_9k":1,
    "qs_pg:photos_9r":1,
    "qs_pg:photos_all":9,
    "qs_pg:photos_sr":1,
    "qs_pg:pop_sr":0,
    "qs_pg:qs_pg_placetype":"neighbourhood",
    "qs_pg:qs_pg_placetype_gp":"Suburb",
    "qs_pg:woe_adm0":23424829,
    "woe:adm0_id":23424829,
    "woe:name_adm0":"Deutschland",
    "woe:name_adm1":"Nordrhein-Westfalen",
    "woe:placetype":"Suburb",
    "wof:name":"Hove",
    "wof:placetype":"neighbourhood"
},
  "geometry": {"coordinates":[6.43333,51.13333],"type":"Point"}
}