{
  "type": "Feature",
  "properties": {
    "gn:admin1_code":"1",
    "gn:admin2_code":"82.0",
    "gn:admin3_code":"8216.0",
    "gn:admin4_code":"8216007.0",
    "gn:asciiname":"Oberhatzenweier",
    "gn:country_code":"DE",
    "gn:dem":132,
    "gn:feature_class":"P",
    "gn:feature_code":"PPL",
    "gn:name":"Oberhatzenweier",
    "gn:population":0,
    "gn:timezone":"Europe/Berlin",
    "iso:country":"DE",
    "wof:name":"Oberhatzenweier",
    "wof:placetype":"neighbourhood"
},
  "geometry": {"coordinates":[8.11667,48.68333],"type":"Point"}
}