{
  "type": "Feature",
  "properties": {
    "gn:admin1_code":"5.0",
    "gn:admin2_code":"066",
    "gn:admin3_code":"6631.0",
    "gn:admin4_code":"6631009.0",
    "gn:asciiname":"Winnenhof",
    "gn:country_code":"DE",
    "gn:dem":349,
    "gn:feature_class":"P",
    "gn:feature_code":"PPL",
    "gn:name":"Winnenhof",
    "gn:population":0,
    "gn:timezone":"Europe/Berlin",
    "iso:country":"DE",
    "wof:name":"Winnenhof",
    "wof:placetype":"neighbourhood"
},
  "geometry": {"coordinates":[9.57673,50.52811],"type":"Point"}
}