{
  "type": "Feature",
  "properties": {
    "gn:admin1_code":"10",
    "gn:admin2_code":"0.0",
    "gn:admin3_code":"1051.0",
    "gn:admin4_code":"1051100.0",
    "gn:asciiname":"Krim",
    "gn:cc2":"DE",
    "gn:country_code":"DE",
    "gn:dem":1,
    "gn:feature_class":"P",
    "gn:feature_code":"PPLL",
    "gn:name":"Krim",
    "gn:population":0,
    "gn:timezone":"Europe/Berlin",
    "iso:country":"DE",
    "name:bak_x_preferred":[
        "\u04a0\u044b\u0440\u044b\u043c"
    ],
    "name:bul_x_preferred":[
        "\u041a\u0440\u0438\u043c"
    ],
    "name:bxr_x_preferred":[
        "\u041a\u0440\u044b\u043c"
    ],
    "name:ceb_x_preferred":[
        "Krim"
    ],
    "name:deu_x_preferred":[
        "Krim"
    ],
    "name:dsb_x_preferred":[
        "Krim"
    ],
    "name:fra_x_preferred":[
        "Krim"
    ],
    "name:heb_x_preferred":[
        "\u05e7\u05e8\u05d9\u05dd"
    ],
    "name:hsb_x_preferred":[
        "Krim"
    ],
    "name:ind_x_preferred":[
        "Krim"
    ],
    "name:jpn_x_preferred":[
        "\u30af\u30ea\u30e0"
    ],
    "name:kaz_x_preferred":[
        "\u049a\u044b\u0440\u044b\u043c"
    ],
    "name:nld_x_preferred":[
        "Krim"
    ],
    "name:nno_x_preferred":[
        "Krim"
    ],
    "name:nor_x_preferred":[
        "Krim"
    ],
    "name:rus_x_preferred":[
        "\u041a\u0440\u044b\u043c"
    ],
    "name:slv_x_preferred":[
        "Krim"
    ],
    "name:srp_x_preferred":[
        "\u041a\u0440\u0438\u043c"
    ],
    "name:swe_x_preferred":[
        "Krim"
    ],
    "name:tat_x_preferred":[
        "\u041a\u044b\u0440\u044b\u043c"
    ],
    "name:ukr_x_preferred":[
        "\u041a\u0440\u0438\u043c"
    ],
    "name:und_x_variant":[
        "Krimm"
    ],
    "name:vep_x_preferred":[
        "Krim"
    ],
    "wof:name":"Krim",
    "wof:placetype":"neighbourhood"
},
  "geometry": {"coordinates":[9.25,54.23333],"type":"Point"}
}