{
  "type": "Feature",
  "properties": {
    "gn:admin1_code":"1.0",
    "gn:admin2_code":"84.0",
    "gn:admin3_code":"8415.0",
    "gn:admin4_code":"8415061.0",
    "gn:asciiname":"Alteburg",
    "gn:country_code":"DE",
    "gn:dem":505,
    "gn:feature_class":"P",
    "gn:feature_code":"PPL",
    "gn:name":"Alteburg",
    "gn:population":0,
    "gn:timezone":"Europe/Berlin",
    "iso:country":"DE",
    "wof:name":"Alteburg",
    "wof:placetype":"neighbourhood"
},
  "geometry": {"coordinates":[9.15337,48.46194000000001],"type":"Point"}
}