{
  "type": "Feature",
  "properties": {
    "gn:admin1_code":"10",
    "gn:admin2_code":"0.0",
    "gn:admin3_code":"1053.0",
    "gn:admin4_code":"1053041.0",
    "gn:asciiname":"Sankt Hubertus",
    "gn:country_code":"DE",
    "gn:dem":15,
    "gn:feature_class":"P",
    "gn:feature_code":"PPL",
    "gn:name":"Sankt Hubertus",
    "gn:population":0,
    "gn:timezone":"Europe/Berlin",
    "iso:country":"DE",
    "wof:name":"Sankt Hubertus",
    "wof:placetype":"neighbourhood"
},
  "geometry": {"coordinates":[10.72952,53.82021],"type":"Point"}
}