{
  "type": "Feature",
  "properties": {
    "gn:admin1_code":"2",
    "gn:admin2_code":"92.0",
    "gn:admin3_code":"9274.0",
    "gn:admin4_code":"9274156.0",
    "gn:asciiname":"Thalham",
    "gn:country_code":"DE",
    "gn:dem":446,
    "gn:feature_class":"P",
    "gn:feature_code":"PPL",
    "gn:name":"Thalham",
    "gn:population":0,
    "gn:timezone":"Europe/Berlin",
    "iso:country":"DE",
    "wof:name":"Thalham",
    "wof:placetype":"neighbourhood"
},
  "geometry": {"coordinates":[12.33447,48.58879],"type":"Point"}
}