{
  "type": "Feature",
  "properties": {
    "gn:admin1_code":"11",
    "gn:admin2_code":"0.0",
    "gn:admin3_code":"12066.0",
    "gn:admin4_code":"12066052.0",
    "gn:asciiname":"Klein Mehssow",
    "gn:country_code":"DE",
    "gn:dem":83,
    "gn:feature_class":"P",
    "gn:feature_code":"PPL",
    "gn:name":"Klein Meh\u00dfow",
    "gn:population":0,
    "gn:timezone":"Europe/Berlin",
    "iso:country":"DE",
    "wof:name":"Klein Mehssow",
    "wof:placetype":"neighbourhood"
},
  "geometry": {"coordinates":[13.85032,51.73889000000001],"type":"Point"}
}