{
  "type": "Feature",
  "properties": {
    "gn:admin1_code":"2",
    "gn:admin2_code":"94.0",
    "gn:admin3_code":"9477.0",
    "gn:admin4_code":"9477136.0",
    "gn:asciiname":"Friedrichsberg",
    "gn:country_code":"DE",
    "gn:dem":341,
    "gn:feature_class":"P",
    "gn:feature_code":"PPL",
    "gn:name":"Friedrichsberg",
    "gn:population":0,
    "gn:timezone":"Europe/Berlin",
    "iso:country":"DE",
    "wof:name":"Friedrichsberg",
    "wof:placetype":"neighbourhood"
},
  "geometry": {"coordinates":[11.32057,50.10661],"type":"Point"}
}