{
  "type": "Feature",
  "properties": {
    "gn:admin1_code":"2",
    "gn:admin2_code":"91.0",
    "gn:admin3_code":"9171.0",
    "gn:admin4_code":"9171116.0",
    "gn:asciiname":"Fernreith",
    "gn:country_code":"DE",
    "gn:dem":510,
    "gn:feature_class":"P",
    "gn:feature_code":"PPL",
    "gn:name":"Fernreith",
    "gn:population":0,
    "gn:timezone":"Europe/Berlin",
    "iso:country":"DE",
    "wof:name":"Fernreith",
    "wof:placetype":"neighbourhood"
},
  "geometry": {"coordinates":[12.61468,48.0912],"type":"Point"}
}