{
  "type": "Feature",
  "properties": {
    "gn:admin1_code":"1",
    "gn:admin2_code":"84.0",
    "gn:admin3_code":"8426.0",
    "gn:admin4_code":"8426014.0",
    "gn:asciiname":"Otterswang",
    "gn:country_code":"DE",
    "gn:dem":565,
    "gn:feature_class":"P",
    "gn:feature_code":"PPL",
    "gn:name":"Otterswang",
    "gn:population":0,
    "gn:timezone":"Europe/Berlin",
    "iso:country":"DE",
    "wof:name":"Otterswang",
    "wof:placetype":"neighbourhood"
},
  "geometry": {"coordinates":[9.64387,47.97739],"type":"Point"}
}