{
  "type": "Feature",
  "properties": {
    "gn:gn_country":"DE",
    "gn:gn_fcode":"PPLA4",
    "gn:gn_pop":167,
    "gn:population":167,
    "iso:country":"DE",
    "name:baq_x_preferred":[
        "Leidenborn"
    ],
    "name:chi_x_preferred":[
        "\u83b1\u767b\u535a\u5c14\u6069"
    ],
    "name:dut_x_preferred":[
        "Leidenborn"
    ],
    "name:eng_x_preferred":[
        "Leidenborn"
    ],
    "name:epo_x_preferred":[
        "Leidenborn"
    ],
    "name:fre_x_preferred":[
        "Leidenborn"
    ],
    "name:ger_x_preferred":[
        "Leidenborn"
    ],
    "name:hun_x_preferred":[
        "Leidenborn"
    ],
    "name:ita_x_preferred":[
        "Leidenborn"
    ],
    "name:jpn_x_preferred":[
        "\u30e9\u30a4\u30c7\u30f3\u30dc\u30eb\u30f3"
    ],
    "name:may_x_preferred":[
        "Leidenborn"
    ],
    "name:per_x_preferred":[
        "\u0644\u0627\u06cc\u062f\u0646\u0628\u0648\u0631\u0646"
    ],
    "name:pol_x_preferred":[
        "Leidenborn"
    ],
    "name:por_x_preferred":[
        "Leidenborn"
    ],
    "name:rum_x_preferred":[
        "Leidenborn"
    ],
    "name:rus_x_preferred":[
        "\u041b\u0430\u0439\u0434\u0435\u043d\u0431\u043e\u0440\u043d"
    ],
    "name:srp_x_preferred":[
        "\u041b\u0430\u0458\u0434\u0435\u043d\u0431\u043e\u0440\u043d"
    ],
    "name:ukr_x_preferred":[
        "\u041b\u044f\u0439\u0434\u0435\u043d\u0431\u043e\u0440\u043d"
    ],
    "name:uzb_x_preferred":[
        "Leidenborn"
    ],
    "name:vie_x_preferred":[
        "Leidenborn"
    ],
    "name:vol_x_preferred":[
        "Leidenborn"
    ],
    "name:war_x_preferred":[
        "Leidenborn"
    ],
    "qs_pg:aaroncc":"DE",
    "qs_pg:gn_country":"DE",
    "qs_pg:gn_fcode":"PPLA4",
    "qs_pg:gn_pop":167,
    "qs_pg:name":"Leidenborn",
    "qs_pg:photos_9r":0,
    "qs_pg:photos_sr":0,
    "qs_pg:pop_sr":1,
    "qs_pg:qs_pg_placetype":"locality",
    "wof:name":"Leidenborn",
    "wof:placetype":"locality",
    "wof:population":167
},
  "geometry": {"coordinates":[6.21667,50.13333],"type":"Point"}
}