{
  "type": "Feature",
  "properties": {
    "gn:admin1_code":"1.0",
    "gn:admin2_code":"081",
    "gn:admin3_code":"8136.0",
    "gn:admin4_code":"8136075.0",
    "gn:asciiname":"Zipplingen",
    "gn:country_code":"DE",
    "gn:dem":501,
    "gn:feature_class":"P",
    "gn:feature_code":"PPL",
    "gn:name":"Zipplingen",
    "gn:population":0,
    "gn:timezone":"Europe/Berlin",
    "iso:country":"DE",
    "wof:name":"Zipplingen",
    "wof:placetype":"neighbourhood"
},
  "geometry": {"coordinates":[10.40586,48.92271],"type":"Point"}
}