{
  "type": "Feature",
  "properties": {
    "gn:admin1_code":"13",
    "gn:asciiname":"Neuwelzow",
    "gn:country_code":"DE",
    "gn:dem":123,
    "gn:feature_class":"P",
    "gn:feature_code":"PPL",
    "gn:name":"Neuwelzow",
    "gn:population":0,
    "gn:timezone":"Europe/Berlin",
    "iso:country":"DE",
    "wof:name":"Neuwelzow",
    "wof:placetype":"neighbourhood"
},
  "geometry": {"coordinates":[14.16667,51.58333],"type":"Point"}
}