{
  "type": "Feature",
  "properties": {
    "gn:admin1_code":"11.0",
    "gn:admin2_code":"00",
    "gn:admin3_code":"12073.0",
    "gn:admin4_code":"12073579.0",
    "gn:asciiname":"Wilsickow",
    "gn:country_code":"DE",
    "gn:dem":33,
    "gn:feature_class":"P",
    "gn:feature_code":"PPL",
    "gn:name":"Wilsickow",
    "gn:population":0,
    "gn:timezone":"Europe/Berlin",
    "iso:country":"DE",
    "wof:name":"Wilsickow",
    "wof:placetype":"neighbourhood"
},
  "geometry": {"coordinates":[13.86267,53.4845],"type":"Point"}
}