{
  "type": "Feature",
  "properties": {
    "gn:admin1_code":"15",
    "gn:asciiname":"Trebesberg",
    "gn:country_code":"DE",
    "gn:dem":545,
    "gn:feature_class":"P",
    "gn:feature_code":"PPL",
    "gn:name":"Trebesberg",
    "gn:population":0,
    "gn:timezone":"Europe/Berlin",
    "iso:country":"DE",
    "wof:name":"Trebesberg",
    "wof:placetype":"neighbourhood"
},
  "geometry": {"coordinates":[11.34699,50.29669000000001],"type":"Point"}
}