{
  "type": "Feature",
  "properties": {
    "gn:admin1_code":"1",
    "gn:admin2_code":"84.0",
    "gn:admin3_code":"8437.0",
    "gn:admin4_code":"8437076.0",
    "gn:asciiname":"Granheim",
    "gn:country_code":"DE",
    "gn:dem":580,
    "gn:feature_class":"P",
    "gn:feature_code":"PPL",
    "gn:name":"Granheim",
    "gn:population":0,
    "gn:timezone":"Europe/Berlin",
    "iso:country":"DE",
    "wof:name":"Granheim",
    "wof:placetype":"neighbourhood"
},
  "geometry": {"coordinates":[9.34095,48.02621],"type":"Point"}
}