{
  "type": "Feature",
  "properties": {
    "gn:admin1_code":"11",
    "gn:admin2_code":"0.0",
    "gn:admin3_code":"12070.0",
    "gn:admin4_code":"12070222.0",
    "gn:asciiname":"Buckow",
    "gn:country_code":"DE",
    "gn:dem":93,
    "gn:feature_class":"P",
    "gn:feature_code":"PPL",
    "gn:name":"Buckow",
    "gn:population":0,
    "gn:timezone":"Europe/Berlin",
    "iso:country":"DE",
    "name:azb_x_preferred":[
        "\u0628\u0648\u06a9\u0648"
    ],
    "name:ceb_x_preferred":[
        "Buckow"
    ],
    "name:dan_x_preferred":[
        "Buckow"
    ],
    "name:deu_x_preferred":[
        "Buckow"
    ],
    "name:epo_x_preferred":[
        "Buckow"
    ],
    "name:fas_x_preferred":[
        "\u0628\u0648\u06a9\u0648"
    ],
    "name:fra_x_preferred":[
        "Buckow"
    ],
    "name:hun_x_preferred":[
        "Buckow"
    ],
    "name:hye_x_preferred":[
        "\u0532\u0578\u0582\u056f\u0578\u057e"
    ],
    "name:ita_x_preferred":[
        "Buckow"
    ],
    "name:lav_x_preferred":[
        "Bukova"
    ],
    "name:mkd_x_preferred":[
        "\u0411\u0443\u043a\u043e\u0432"
    ],
    "name:msa_x_preferred":[
        "Buckow"
    ],
    "name:nld_x_preferred":[
        "Buckow"
    ],
    "name:pol_x_preferred":[
        "Buckow"
    ],
    "name:ron_x_preferred":[
        "Buckow"
    ],
    "name:rus_x_preferred":[
        "\u0411\u0443\u043a\u043a\u043e\u0432"
    ],
    "name:spa_x_preferred":[
        "Buckow"
    ],
    "name:srp_x_preferred":[
        "\u0411\u0443\u043a\u043e\u0432"
    ],
    "name:swe_x_preferred":[
        "Buckow"
    ],
    "name:szl_x_preferred":[
        "Buckow"
    ],
    "name:tur_x_preferred":[
        "Buckow"
    ],
    "name:ukr_x_preferred":[
        "\u0411\u0443\u043a\u043e\u0432"
    ],
    "name:uzb_x_preferred":[
        "Buckow"
    ],
    "name:vie_x_preferred":[
        "Buckow"
    ],
    "name:vol_x_preferred":[
        "Buckow"
    ],
    "name:war_x_preferred":[
        "Buckow"
    ],
    "wof:name":"Buckow",
    "wof:placetype":"neighbourhood"
},
  "geometry": {"coordinates":[12.15888,53.25319],"type":"Point"}
}