{
  "type": "Feature",
  "properties": {
    "gn:admin1_code":"13",
    "gn:admin2_code":"0.0",
    "gn:admin3_code":"14625.0",
    "gn:admin4_code":"14625420.0",
    "gn:asciiname":"Trado",
    "gn:country_code":"DE",
    "gn:dem":136,
    "gn:feature_class":"P",
    "gn:feature_code":"PPL",
    "gn:name":"Trado",
    "gn:population":0,
    "gn:timezone":"Europe/Berlin",
    "iso:country":"DE",
    "name:hsb_x_preferred":[
        "Tradow"
    ],
    "name:nld_x_preferred":[
        "Trado"
    ],
    "wof:name":"Trado",
    "wof:placetype":"neighbourhood"
},
  "geometry": {"coordinates":[14.20159,51.33996],"type":"Point"}
}