{
  "type": "Feature",
  "properties": {
    "gn:admin1_code":"2",
    "gn:admin2_code":"93.0",
    "gn:admin3_code":"9372.0",
    "gn:admin4_code":"9372116.0",
    "gn:asciiname":"Oberhaid",
    "gn:country_code":"DE",
    "gn:dem":433,
    "gn:feature_class":"P",
    "gn:feature_code":"PPL",
    "gn:name":"Oberhaid",
    "gn:population":0,
    "gn:timezone":"Europe/Berlin",
    "iso:country":"DE",
    "name:ara_x_preferred":[
        "\u0623\u0648\u0628\u0631\u0647\u0622\u064a\u062f"
    ],
    "name:deu_x_preferred":[
        "Oberhaid"
    ],
    "name:epo_x_preferred":[
        "Oberhaid"
    ],
    "name:eus_x_preferred":[
        "Oberhaid"
    ],
    "name:fas_x_preferred":[
        "\u0627\u0648\u0628\u0631\u0647\u0627\u06cc\u062f"
    ],
    "name:fra_x_preferred":[
        "Oberhaid"
    ],
    "name:hun_x_preferred":[
        "Oberhaid"
    ],
    "name:hye_x_preferred":[
        "\u0555\u0562\u0565\u0580\u0570\u0561\u0575\u0564"
    ],
    "name:ita_x_preferred":[
        "Oberhaid"
    ],
    "name:jpn_x_preferred":[
        "\u30aa\u30fc\u30d0\u30fc\u30cf\u30a4\u30c8"
    ],
    "name:kaz_x_preferred":[
        "\u041e\u0431\u0435\u0440\u0445\u0430\u0439\u0434"
    ],
    "name:lmo_x_preferred":[
        "Oberhaid"
    ],
    "name:msa_x_preferred":[
        "Oberhaid"
    ],
    "name:nld_x_preferred":[
        "Oberhaid"
    ],
    "name:pol_x_preferred":[
        "Oberhaid"
    ],
    "name:por_x_preferred":[
        "Oberhaid"
    ],
    "name:ron_x_preferred":[
        "Oberhaid"
    ],
    "name:rus_x_preferred":[
        "\u041e\u0431\u0435\u0440\u0445\u0430\u0439\u0434"
    ],
    "name:spa_x_preferred":[
        "Oberhaid"
    ],
    "name:srp_x_preferred":[
        "\u041e\u0431\u0435\u0440\u0445\u0430\u0458\u0434"
    ],
    "name:ukr_x_preferred":[
        "\u041e\u0431\u0435\u0440\u0433\u0430\u0439\u0434"
    ],
    "name:uzb_x_preferred":[
        "Oberhaid"
    ],
    "name:vol_x_preferred":[
        "Oberhaid"
    ],
    "name:war_x_preferred":[
        "Oberhaid"
    ],
    "name:zho_x_preferred":[
        "\u4e0a\u6d77\u5fb7"
    ],
    "wof:name":"Oberhaid",
    "wof:placetype":"neighbourhood"
},
  "geometry": {"coordinates":[12.7003,49.15888],"type":"Point"}
}