{
  "type": "Feature",
  "properties": {
    "gn:admin1_code":"15",
    "gn:admin2_code":"0.0",
    "gn:admin3_code":"16071.0",
    "gn:admin4_code":"16071008.0",
    "gn:asciiname":"Egendorf",
    "gn:country_code":"DE",
    "gn:dem":376,
    "gn:feature_class":"P",
    "gn:feature_code":"PPL",
    "gn:name":"Egendorf",
    "gn:population":0,
    "gn:timezone":"Europe/Berlin",
    "iso:country":"DE",
    "wof:name":"Egendorf",
    "wof:placetype":"neighbourhood"
},
  "geometry": {"coordinates":[11.3669,50.86323],"type":"Point"}
}