{
  "type": "Feature",
  "properties": {
    "gn:admin1_code":"2",
    "gn:admin2_code":"92.0",
    "gn:admin3_code":"9274.0",
    "gn:admin4_code":"9274134.0",
    "gn:asciiname":"Helmsau",
    "gn:country_code":"DE",
    "gn:dem":498,
    "gn:feature_class":"P",
    "gn:feature_code":"PPL",
    "gn:name":"Helmsau",
    "gn:population":0,
    "gn:timezone":"Europe/Berlin",
    "iso:country":"DE",
    "wof:name":"Helmsau",
    "wof:placetype":"neighbourhood"
},
  "geometry": {"coordinates":[12.3069,48.50691],"type":"Point"}
}