{
  "type": "Feature",
  "properties": {
    "gn:admin1_code":"2",
    "gn:admin2_code":"91.0",
    "gn:admin3_code":"9183.0",
    "gn:admin4_code":"9183140.0",
    "gn:asciiname":"Heberding",
    "gn:country_code":"DE",
    "gn:dem":566,
    "gn:feature_class":"P",
    "gn:feature_code":"PPL",
    "gn:name":"Heberding",
    "gn:population":0,
    "gn:timezone":"Europe/Berlin",
    "iso:country":"DE",
    "wof:name":"Heberding",
    "wof:placetype":"neighbourhood"
},
  "geometry": {"coordinates":[12.26403,48.2052],"type":"Point"}
}