{
  "type": "Feature",
  "properties": {
    "gn:admin1_code":"1",
    "gn:admin2_code":"81.0",
    "gn:admin3_code":"8126.0",
    "gn:admin4_code":"8126086.0",
    "gn:asciiname":"Crispenhofen",
    "gn:country_code":"DE",
    "gn:dem":257,
    "gn:feature_class":"P",
    "gn:feature_code":"PPL",
    "gn:name":"Crispenhofen",
    "gn:population":0,
    "gn:timezone":"Europe/Berlin",
    "iso:country":"DE",
    "wof:name":"Crispenhofen",
    "wof:placetype":"neighbourhood"
},
  "geometry": {"coordinates":[9.5978,49.31623],"type":"Point"}
}