{
  "type": "Feature",
  "properties": {
    "iso:country":"DE",
    "name:deu_x_preferred":[
        "Espen"
    ],
    "name:eng_x_preferred":[
        "Espey"
    ],
    "name:eng_x_variant":[
        "Espey"
    ],
    "name:unk_x_variant":[
        "Espen"
    ],
    "qs:gn_fcode":"PPLX",
    "qs:gn_local":0,
    "qs:gn_namadm1":"07",
    "qs:gn_name":"Espen",
    "qs:local_max":481,
    "qs:local_sum":2047,
    "qs:localhoods":11,
    "qs:name":"Espen",
    "qs:name_adm0":"Deutschland",
    "qs:name_adm1":"Nordrhein-Westfalen",
    "qs:name_adm2":"Ennepe-Ruhr-Kreis",
    "qs:name_en":"Espey",
    "qs:name_lau":"Stadtteil Witten",
    "qs:name_local":"Stadtteil Witten",
    "qs:photo_max":156,
    "qs:photo_sum":206,
    "qs:placetype":"Suburb",
    "qs:quad_count":11,
    "qs:woe_adm0":23424829,
    "qs:woe_adm1":2345487,
    "qs:woe_adm2":12596887,
    "qs:woe_lau":28350222,
    "qs:woe_local":28350222,
    "qs:woe_ver":"7.10.0",
    "wof:lang":[
        "ger"
    ],
    "wof:name":"Espen",
    "wof:placetype":"neighbourhood"
},
  "geometry": {"coordinates":[7.305809,51.438239],"type":"Point"}
}