{
  "type": "Feature",
  "properties": {
    "gn:admin1_code":"13",
    "gn:admin2_code":"0.0",
    "gn:admin3_code":"14729.0",
    "gn:admin4_code":"14729170.0",
    "gn:asciiname":"Kleinpriesligk",
    "gn:country_code":"DE",
    "gn:dem":138,
    "gn:feature_class":"P",
    "gn:feature_code":"PPL",
    "gn:name":"Kleinpriesligk",
    "gn:population":0,
    "gn:timezone":"Europe/Berlin",
    "iso:country":"DE",
    "name:und_x_variant":[
        "Kleinprie\u00dfligk",
        "Kleinpriesligk"
    ],
    "wof:name":"Kleinpriesligk",
    "wof:placetype":"neighbourhood"
},
  "geometry": {"coordinates":[12.2434,51.11293],"type":"Point"}
}