{
  "type": "Feature",
  "properties": {
    "gn:admin1_code":"13",
    "gn:admin2_code":"0.0",
    "gn:admin3_code":"14625.0",
    "gn:admin4_code":"14625490.0",
    "gn:asciiname":"Brohna",
    "gn:country_code":"DE",
    "gn:dem":155,
    "gn:feature_class":"P",
    "gn:feature_code":"PPL",
    "gn:name":"Brohna",
    "gn:population":0,
    "gn:timezone":"Europe/Berlin",
    "iso:country":"DE",
    "name:hsb_x_preferred":[
        "Bronjo"
    ],
    "wof:name":"Brohna",
    "wof:placetype":"neighbourhood"
},
  "geometry": {"coordinates":[14.39724,51.25305],"type":"Point"}
}