{
  "type": "Feature",
  "properties": {
    "gn:admin1_code":"15.0",
    "gn:admin2_code":"00",
    "gn:admin3_code":"16066.0",
    "gn:admin4_code":"16066064.0",
    "gn:asciiname":"Zillbach",
    "gn:country_code":"DE",
    "gn:dem":351,
    "gn:feature_class":"P",
    "gn:feature_code":"PPL",
    "gn:name":"Zillbach",
    "gn:population":0,
    "gn:timezone":"Europe/Berlin",
    "iso:country":"DE",
    "wof:name":"Zillbach",
    "wof:placetype":"neighbourhood"
},
  "geometry": {"coordinates":[10.29759,50.70574000000001],"type":"Point"}
}