{
  "type": "Feature",
  "properties": {
    "gn:admin1_code":"8",
    "gn:admin2_code":"0.0",
    "gn:admin3_code":"7143.0",
    "gn:admin4_code":"7143203.0",
    "gn:asciiname":"Etzelbach",
    "gn:country_code":"DE",
    "gn:dem":408,
    "gn:feature_class":"P",
    "gn:feature_code":"PPL",
    "gn:name":"Etzelbach",
    "gn:population":0,
    "gn:timezone":"Europe/Berlin",
    "iso:country":"DE",
    "wof:name":"Etzelbach",
    "wof:placetype":"neighbourhood"
},
  "geometry": {"coordinates":[7.86861,50.53547],"type":"Point"}
}