{
  "type": "Feature",
  "properties": {
    "gn:admin1_code":"10.0",
    "gn:admin2_code":"0.0",
    "gn:admin3_code":"1053.0",
    "gn:admin4_code":"1053097.0",
    "gn:asciiname":"Sandfelde",
    "gn:country_code":"DE",
    "gn:dem":8,
    "gn:feature_class":"P",
    "gn:feature_code":"PPL",
    "gn:name":"Sandfelde",
    "gn:population":0,
    "gn:timezone":"Europe/Berlin",
    "iso:country":"DE",
    "wof:name":"Sandfelde",
    "wof:placetype":"neighbourhood"
},
  "geometry": {"coordinates":[10.63333,53.66667],"type":"Point"}
}