{
  "type": "Feature",
  "properties": {
    "gn:admin1_code":"7",
    "gn:admin2_code":"53.0",
    "gn:admin3_code":"5382.0",
    "gn:admin4_code":"5382052.0",
    "gn:asciiname":"Obersaurenbach",
    "gn:country_code":"DE",
    "gn:dem":235,
    "gn:feature_class":"P",
    "gn:feature_code":"PPL",
    "gn:name":"Obersaurenbach",
    "gn:population":0,
    "gn:timezone":"Europe/Berlin",
    "iso:country":"DE",
    "wof:name":"Obersaurenbach",
    "wof:placetype":"neighbourhood"
},
  "geometry": {"coordinates":[7.47434,50.85694],"type":"Point"}
}