{
  "type": "Feature",
  "properties": {
    "gn:admin1_code":"10",
    "gn:admin2_code":"0.0",
    "gn:admin3_code":"1061.0",
    "gn:admin4_code":"1061041.0",
    "gn:asciiname":"Espe",
    "gn:country_code":"DE",
    "gn:dem":-4,
    "gn:feature_class":"P",
    "gn:feature_code":"PPL",
    "gn:name":"Espe",
    "gn:population":0,
    "gn:timezone":"Europe/Berlin",
    "iso:country":"DE",
    "name:ceb_x_preferred":[
        "Espe"
    ],
    "name:dan_x_preferred":[
        "Espe"
    ],
    "name:deu_x_preferred":[
        "Espe"
    ],
    "name:nld_x_preferred":[
        "Espe"
    ],
    "name:swe_x_preferred":[
        "Espe"
    ],
    "wof:name":"Espe",
    "wof:placetype":"neighbourhood"
},
  "geometry": {"coordinates":[9.58333,53.85],"type":"Point"}
}