{
  "type": "Feature",
  "properties": {
    "gn:admin1_code":"1",
    "gn:admin2_code":"81.0",
    "gn:admin3_code":"8125.0",
    "gn:admin4_code":"8125008.0",
    "gn:asciiname":"Schmidhausen",
    "gn:country_code":"DE",
    "gn:dem":258,
    "gn:feature_class":"P",
    "gn:feature_code":"PPL",
    "gn:name":"Schmidhausen",
    "gn:population":0,
    "gn:timezone":"Europe/Berlin",
    "iso:country":"DE",
    "wof:name":"Schmidhausen",
    "wof:placetype":"neighbourhood"
},
  "geometry": {"coordinates":[9.33055,49.04158],"type":"Point"}
}