{
  "type": "Feature",
  "properties": {
    "iso:country":"DE",
    "wof:name":"Ostheim-Nord",
    "wof:placetype":"neighbourhood"
},
  "geometry": {"coordinates":[7.04486529444856,50.93164669202206],"type":"Point"}
}