{
  "type": "Feature",
  "properties": {
    "gn:admin1_code":"2",
    "gn:admin2_code":"97.0",
    "gn:admin3_code":"9771.0",
    "gn:admin4_code":"9771113.0",
    "gn:asciiname":"Matzenberg",
    "gn:country_code":"DE",
    "gn:dem":488,
    "gn:feature_class":"P",
    "gn:feature_code":"PPL",
    "gn:name":"Matzenberg",
    "gn:population":0,
    "gn:timezone":"Europe/Berlin",
    "iso:country":"DE",
    "wof:name":"Matzenberg",
    "wof:placetype":"neighbourhood"
},
  "geometry": {"coordinates":[11.14116,48.40412],"type":"Point"}
}