{
  "type": "Feature",
  "properties": {
    "gn:admin1_code":"7",
    "gn:admin2_code":"53.0",
    "gn:admin3_code":"5366.0",
    "gn:admin4_code":"5366028.0",
    "gn:asciiname":"Glehn",
    "gn:country_code":"DE",
    "gn:dem":291,
    "gn:feature_class":"P",
    "gn:feature_code":"PPL",
    "gn:name":"Glehn",
    "gn:population":0,
    "gn:timezone":"Europe/Berlin",
    "iso:country":"DE",
    "name:deu_x_preferred":[
        "Glehn"
    ],
    "name:est_x_preferred":[
        "Glehn"
    ],
    "name:nld_x_preferred":[
        "Glehn"
    ],
    "name:rus_x_preferred":[
        "\u0413\u043b\u0435\u043d"
    ],
    "wof:name":"Glehn",
    "wof:placetype":"neighbourhood"
},
  "geometry": {"coordinates":[6.5942,50.60347],"type":"Point"}
}