{
  "type": "Feature",
  "properties": {
    "gn:admin1_code":"6",
    "gn:admin2_code":"0.0",
    "gn:admin3_code":"3354.0",
    "gn:admin4_code":"3354023.0",
    "gn:asciiname":"Vasenthien",
    "gn:country_code":"DE",
    "gn:dem":18,
    "gn:feature_class":"P",
    "gn:feature_code":"PPL",
    "gn:name":"Vasenthien",
    "gn:population":0,
    "gn:timezone":"Europe/Berlin",
    "iso:country":"DE",
    "name:und_x_variant":[
        "Vasenthin",
        "Vasenthien"
    ],
    "wof:name":"Vasenthien",
    "wof:placetype":"neighbourhood"
},
  "geometry": {"coordinates":[11.26754,52.98998],"type":"Point"}
}