{
  "type": "Feature",
  "properties": {
    "gn:admin1_code":"1",
    "gn:admin2_code":"81.0",
    "gn:admin3_code":"8119.0",
    "gn:admin4_code":"8119006.0",
    "gn:asciiname":"Rottmannsberg",
    "gn:country_code":"DE",
    "gn:dem":479,
    "gn:feature_class":"P",
    "gn:feature_code":"PPL",
    "gn:name":"Rottmannsberg",
    "gn:population":0,
    "gn:timezone":"Europe/Berlin",
    "iso:country":"DE",
    "wof:name":"Rottmannsberg",
    "wof:placetype":"neighbourhood"
},
  "geometry": {"coordinates":[9.53336,48.9523],"type":"Point"}
}