{
  "type": "Feature",
  "properties": {
    "gn:admin1_code":"7",
    "gn:admin2_code":"55.0",
    "gn:admin3_code":"5566.0",
    "gn:admin4_code":"5566024.0",
    "gn:asciiname":"Haltern",
    "gn:country_code":"DE",
    "gn:dem":73,
    "gn:feature_class":"P",
    "gn:feature_code":"PPL",
    "gn:name":"Haltern",
    "gn:population":0,
    "gn:timezone":"Europe/Berlin",
    "iso:country":"DE",
    "wof:name":"Haltern",
    "wof:placetype":"neighbourhood"
},
  "geometry": {"coordinates":[7.26743,52.12077],"type":"Point"}
}