{
  "type": "Feature",
  "properties": {
    "gn:admin1_code":"10.0",
    "gn:admin2_code":"0.0",
    "gn:admin3_code":"1058.0",
    "gn:admin4_code":"1058121.0",
    "gn:asciiname":"Borghorst",
    "gn:country_code":"DE",
    "gn:dem":17,
    "gn:feature_class":"P",
    "gn:feature_code":"PPL",
    "gn:name":"Borghorst",
    "gn:population":0,
    "gn:timezone":"Europe/Berlin",
    "iso:country":"DE",
    "wof:name":"Borghorst",
    "wof:placetype":"neighbourhood"
},
  "geometry": {"coordinates":[9.97695,54.43668],"type":"Point"}
}