{
  "type": "Feature",
  "properties": {
    "gn:admin1_code":"2.0",
    "gn:admin2_code":"96.0",
    "gn:admin3_code":"9675.0",
    "gn:admin4_code":"9675158.0",
    "gn:asciiname":"Altenschonbach",
    "gn:country_code":"DE",
    "gn:dem":289,
    "gn:feature_class":"P",
    "gn:feature_code":"PPL",
    "gn:name":"Altensch\u00f6nbach",
    "gn:population":0,
    "gn:timezone":"Europe/Berlin",
    "iso:country":"DE",
    "wof:name":"Altenschonbach",
    "wof:placetype":"neighbourhood"
},
  "geometry": {"coordinates":[10.39857,49.8237],"type":"Point"}
}