{
  "type": "Feature",
  "properties": {
    "gn:admin1_code":"6",
    "gn:admin2_code":"0.0",
    "gn:admin3_code":"3251.0",
    "gn:admin4_code":"3251025.0",
    "gn:asciiname":"Marl",
    "gn:country_code":"DE",
    "gn:dem":41,
    "gn:feature_class":"P",
    "gn:feature_code":"PPLA4",
    "gn:name":"Marl",
    "gn:population":570,
    "gn:timezone":"Europe/Berlin",
    "iso:country":"DE",
    "wof:name":"Marl",
    "wof:placetype":"locality",
    "wof:population":570
},
  "geometry": {"coordinates":[8.36667,52.48333],"type":"Point"}
}