{
  "type": "Feature",
  "properties": {
    "gn:admin1_code":"6.0",
    "gn:admin2_code":"0.0",
    "gn:admin3_code":"3456.0",
    "gn:admin4_code":"3456001.0",
    "gn:asciiname":"Bardenhorst",
    "gn:country_code":"DE",
    "gn:dem":28,
    "gn:feature_class":"P",
    "gn:feature_code":"PPL",
    "gn:name":"Bardenhorst",
    "gn:population":0,
    "gn:timezone":"Europe/Berlin",
    "iso:country":"DE",
    "wof:name":"Bardenhorst",
    "wof:placetype":"neighbourhood"
},
  "geometry": {"coordinates":[7.08333,52.35],"type":"Point"}
}