{
  "type": "Feature",
  "properties": {
    "gn:admin1_code":"9",
    "gn:admin2_code":"0.0",
    "gn:admin3_code":"10046.0",
    "gn:admin4_code":"10046118.0",
    "gn:asciiname":"Lindscheid",
    "gn:country_code":"DE",
    "gn:dem":312,
    "gn:feature_class":"P",
    "gn:feature_code":"PPL",
    "gn:name":"Lindscheid",
    "gn:population":0,
    "gn:timezone":"Europe/Berlin",
    "iso:country":"DE",
    "wof:name":"Lindscheid",
    "wof:placetype":"neighbourhood"
},
  "geometry": {"coordinates":[6.92657,49.4907],"type":"Point"}
}