{
  "type": "Feature",
  "properties": {
    "iso:country":"DE",
    "name:deu_x_preferred":[
        "H\u00f6fles"
    ],
    "wof:name":"Hoefles",
    "wof:placetype":"neighbourhood"
},
  "geometry": {"coordinates":[11.02951809664102,49.48966561537383],"type":"Point"}
}