{
  "type": "Feature",
  "properties": {
    "gn:admin1_code":"13",
    "gn:admin2_code":"0.0",
    "gn:admin3_code":"14729.0",
    "gn:admin4_code":"14729430.0",
    "gn:asciiname":"Ruessen",
    "gn:country_code":"DE",
    "gn:dem":136,
    "gn:feature_class":"P",
    "gn:feature_code":"PPL",
    "gn:name":"R\u00fcssen",
    "gn:population":0,
    "gn:timezone":"Europe/Berlin",
    "iso:country":"DE",
    "wof:name":"Ruessen",
    "wof:placetype":"neighbourhood"
},
  "geometry": {"coordinates":[12.30579,51.18858],"type":"Point"}
}