{
  "type": "Feature",
  "properties": {
    "gn:admin1_code":"7.0",
    "gn:admin2_code":"53.0",
    "gn:admin3_code":"5334.0",
    "gn:admin4_code":"5334032.0",
    "gn:asciiname":"Breinigerheide",
    "gn:country_code":"DE",
    "gn:dem":277,
    "gn:feature_class":"P",
    "gn:feature_code":"PPL",
    "gn:name":"Breinigerheide",
    "gn:population":0,
    "gn:timezone":"Europe/Berlin",
    "iso:country":"DE",
    "wof:name":"Breinigerheide",
    "wof:placetype":"neighbourhood"
},
  "geometry": {"coordinates":[6.21526,50.73224],"type":"Point"}
}