{
  "type": "Feature",
  "properties": {
    "gn:admin1_code":"7.0",
    "gn:admin2_code":"59.0",
    "gn:admin3_code":"5966.0",
    "gn:admin4_code":"5966028.0",
    "gn:asciiname":"Altenhof",
    "gn:country_code":"DE",
    "gn:dem":388,
    "gn:feature_class":"P",
    "gn:feature_code":"PPL",
    "gn:name":"Altenhof",
    "gn:population":0,
    "gn:timezone":"Europe/Berlin",
    "iso:country":"DE",
    "name:ceb_x_preferred":[
        "Altenhof"
    ],
    "name:deu_x_preferred":[
        "Altenhof"
    ],
    "name:epo_x_preferred":[
        "Altenhof"
    ],
    "name:eus_x_preferred":[
        "Altenhof"
    ],
    "name:fra_x_preferred":[
        "Altenhof"
    ],
    "name:ita_x_preferred":[
        "Altenhof"
    ],
    "name:mkd_x_preferred":[
        "\u0410\u043b\u0442\u0435\u043d\u0445\u043e\u0444"
    ],
    "name:nld_x_preferred":[
        "Altenhof"
    ],
    "name:pol_x_preferred":[
        "Altenhof"
    ],
    "name:rus_x_preferred":[
        "\u0410\u043b\u044c\u0442\u0435\u043d\u0445\u043e\u0444"
    ],
    "name:srp_x_preferred":[
        "\u0410\u043b\u0442\u0435\u043d\u0445\u043e\u0444"
    ],
    "name:swe_x_preferred":[
        "Altenhof"
    ],
    "name:vol_x_preferred":[
        "Altenhof"
    ],
    "wof:name":"Altenhof",
    "wof:placetype":"neighbourhood"
},
  "geometry": {"coordinates":[7.90104,50.96194000000001],"type":"Point"}
}