{
  "type": "Feature",
  "properties": {
    "gn:admin1_code":"13",
    "gn:admin2_code":"0.0",
    "gn:admin3_code":"14625.0",
    "gn:admin4_code":"14625490.0",
    "gn:asciiname":"Coelln",
    "gn:country_code":"DE",
    "gn:dem":200,
    "gn:feature_class":"P",
    "gn:feature_code":"PPL",
    "gn:name":"C\u00f6lln",
    "gn:population":0,
    "gn:timezone":"Europe/Berlin",
    "iso:country":"DE",
    "name:hsb_x_preferred":[
        "Chelno"
    ],
    "wof:name":"Coelln",
    "wof:placetype":"neighbourhood"
},
  "geometry": {"coordinates":[14.38977,51.22608],"type":"Point"}
}