{
  "type": "Feature",
  "properties": {
    "gn:admin1_code":"7.0",
    "gn:admin2_code":"53.0",
    "gn:admin3_code":"5374.0",
    "gn:admin4_code":"5374032.0",
    "gn:asciiname":"Bonekamp",
    "gn:country_code":"DE",
    "gn:dem":240,
    "gn:feature_class":"P",
    "gn:feature_code":"PPLL",
    "gn:name":"Bonekamp",
    "gn:population":0,
    "gn:timezone":"Europe/Berlin",
    "iso:country":"DE",
    "wof:name":"Bonekamp",
    "wof:placetype":"neighbourhood"
},
  "geometry": {"coordinates":[7.55,50.91667],"type":"Point"}
}