{
  "type": "Feature",
  "properties": {
    "gn:admin1_code":"10.0",
    "gn:admin2_code":"00",
    "gn:admin3_code":"1054.0",
    "gn:admin4_code":"1054157.0",
    "gn:asciiname":"Wisch",
    "gn:country_code":"DE",
    "gn:dem":1,
    "gn:feature_class":"P",
    "gn:feature_code":"PPLA4",
    "gn:name":"Wisch",
    "gn:population":0,
    "gn:timezone":"Europe/Berlin",
    "iso:country":"DE",
    "wof:name":"Wisch",
    "wof:placetype":"locality"
},
  "geometry": {"coordinates":[9.15,54.41667],"type":"Point"}
}