{
  "type": "Feature",
  "properties": {
    "gn:admin1_code":"13",
    "gn:admin2_code":"0.0",
    "gn:admin3_code":"14729.0",
    "gn:admin4_code":"14729160.0",
    "gn:asciiname":"Markroehlitz",
    "gn:country_code":"DE",
    "gn:dem":218,
    "gn:feature_class":"P",
    "gn:feature_code":"PPL",
    "gn:name":"Markr\u00f6hlitz",
    "gn:population":0,
    "gn:timezone":"Europe/Berlin",
    "iso:country":"DE",
    "wof:name":"Markroehlitz",
    "wof:placetype":"neighbourhood"
},
  "geometry": {"coordinates":[12.86667,51.21667],"type":"Point"}
}