{
  "type": "Feature",
  "properties": {
    "gn:gn_country":"DE",
    "gn:gn_fcode":"PPLA4",
    "gn:gn_pop":1057,
    "gn:population":1057,
    "iso:country":"DE",
    "name:baq_x_preferred":[
        "M\u00fcschenbach"
    ],
    "name:chi_x_preferred":[
        "\u7c73\u7533\u5df4\u8d6b"
    ],
    "name:dut_x_preferred":[
        "M\u00fcschenbach"
    ],
    "name:eng_x_preferred":[
        "M\u00fcschenbach"
    ],
    "name:epo_x_preferred":[
        "M\u00fcschenbach"
    ],
    "name:fre_x_preferred":[
        "M\u00fcschenbach"
    ],
    "name:ger_x_preferred":[
        "M\u00fcschenbach"
    ],
    "name:hun_x_preferred":[
        "M\u00fcschenbach"
    ],
    "name:ita_x_preferred":[
        "M\u00fcschenbach"
    ],
    "name:jpn_x_preferred":[
        "\u30df\u30e5\u30b7\u30a7\u30f3\u30d0\u30c3\u30cf"
    ],
    "name:may_x_preferred":[
        "M\u00fcschenbach"
    ],
    "name:per_x_preferred":[
        "\u0645\u0648\u0634\u0646\u0628\u0627\u062e"
    ],
    "name:pol_x_preferred":[
        "M\u00fcschenbach"
    ],
    "name:por_x_preferred":[
        "M\u00fcschenbach"
    ],
    "name:rum_x_preferred":[
        "M\u00fcschenbach"
    ],
    "name:rus_x_preferred":[
        "\u041c\u044e\u0448\u0435\u043d\u0431\u0430\u0445"
    ],
    "name:srp_x_preferred":[
        "\u041c\u0438\u0448\u0435\u043d\u0431\u0430\u0445"
    ],
    "name:ukr_x_preferred":[
        "\u041c\u044e\u0448\u0435\u043d\u0431\u0430\u0445"
    ],
    "name:uzb_x_preferred":[
        "M\u00fcschenbach"
    ],
    "name:vie_x_preferred":[
        "M\u00fcschenbach"
    ],
    "name:vol_x_preferred":[
        "M\u00fcschenbach"
    ],
    "name:war_x_preferred":[
        "M\u00fcschenbach"
    ],
    "qs_pg:aaroncc":"DE",
    "qs_pg:gn_country":"DE",
    "qs_pg:gn_fcode":"PPLA4",
    "qs_pg:gn_pop":1057,
    "qs_pg:name":"M\u00fcschenbach",
    "qs_pg:photos_9r":0,
    "qs_pg:photos_sr":0,
    "qs_pg:pop_sr":3,
    "qs_pg:qs_pg_placetype":"locality",
    "wof:name":"M\u00fcschenbach",
    "wof:placetype":"locality",
    "wof:population":1057
},
  "geometry": {"coordinates":[7.78333,50.68333],"type":"Point"}
}