{
  "type": "Feature",
  "properties": {
    "gn:admin1_code":"8",
    "gn:admin2_code":"0.0",
    "gn:admin3_code":"7231.0",
    "gn:admin4_code":"7231070.0",
    "gn:asciiname":"Pilmeroth",
    "gn:country_code":"DE",
    "gn:dem":432,
    "gn:feature_class":"P",
    "gn:feature_code":"PPL",
    "gn:name":"Pilmeroth",
    "gn:population":0,
    "gn:timezone":"Europe/Berlin",
    "iso:country":"DE",
    "wof:name":"Pilmeroth",
    "wof:placetype":"neighbourhood"
},
  "geometry": {"coordinates":[7.15121,49.89782],"type":"Point"}
}