{
  "type": "Feature",
  "properties": {
    "gn:admin1_code":"7",
    "gn:admin2_code":"51.0",
    "gn:admin3_code":"5124.0",
    "gn:admin4_code":"5124000.0",
    "gn:asciiname":"Obensiebeneick",
    "gn:country_code":"DE",
    "gn:dem":238,
    "gn:feature_class":"P",
    "gn:feature_code":"PPLL",
    "gn:name":"Obensiebeneick",
    "gn:population":0,
    "gn:timezone":"Europe/Berlin",
    "iso:country":"DE",
    "wof:name":"Obensiebeneick",
    "wof:placetype":"neighbourhood"
},
  "geometry": {"coordinates":[7.14023,51.28704000000001],"type":"Point"}
}