{
  "type": "Feature",
  "properties": {
    "gn:admin1_code":"7",
    "gn:admin2_code":"57.0",
    "gn:admin3_code":"5754.0",
    "gn:admin4_code":"5754016.0",
    "gn:asciiname":"Rheda",
    "gn:country_code":"DE",
    "gn:dem":67,
    "gn:feature_class":"P",
    "gn:feature_code":"PPLL",
    "gn:name":"Rheda",
    "gn:population":0,
    "gn:timezone":"Europe/Berlin",
    "iso:country":"DE",
    "name:bar_x_preferred":[
        "Rheda"
    ],
    "name:deu_x_preferred":[
        "Rheda"
    ],
    "name:nld_x_preferred":[
        "Rheda"
    ],
    "name:rus_x_preferred":[
        "\u0420\u0435\u0434\u0430"
    ],
    "wof:name":"Rheda",
    "wof:placetype":"neighbourhood"
},
  "geometry": {"coordinates":[8.2054,51.98193],"type":"Point"}
}