{
  "type": "Feature",
  "properties": {
    "gn:admin1_code":"6.0",
    "gn:admin2_code":"00",
    "gn:admin3_code":"3451.0",
    "gn:admin4_code":"3451008.0",
    "gn:asciiname":"Wemkendorf",
    "gn:country_code":"DE",
    "gn:dem":18,
    "gn:feature_class":"P",
    "gn:feature_code":"PPL",
    "gn:name":"Wemkendorf",
    "gn:population":0,
    "gn:timezone":"Europe/Berlin",
    "iso:country":"DE",
    "wof:name":"Wemkendorf",
    "wof:placetype":"neighbourhood"
},
  "geometry": {"coordinates":[8.14753,53.26239],"type":"Point"}
}