{
  "type": "Feature",
  "properties": {
    "gn:admin1_code":"2",
    "gn:admin2_code":"92.0",
    "gn:admin3_code":"9275.0",
    "gn:admin4_code":"9275146.0",
    "gn:asciiname":"Steinbuchl",
    "gn:country_code":"DE",
    "gn:dem":442,
    "gn:feature_class":"P",
    "gn:feature_code":"PPL",
    "gn:name":"Steinb\u00fcchl",
    "gn:population":0,
    "gn:timezone":"Europe/Berlin",
    "iso:country":"DE",
    "wof:name":"Steinbuchl",
    "wof:placetype":"neighbourhood"
},
  "geometry": {"coordinates":[13.50479,48.6116],"type":"Point"}
}