{
  "type": "Feature",
  "properties": {
    "gn:admin1_code":"2",
    "gn:admin2_code":"92.0",
    "gn:admin3_code":"9278.0",
    "gn:admin4_code":"9278149.0",
    "gn:asciiname":"Fahrndorf",
    "gn:country_code":"DE",
    "gn:dem":315,
    "gn:feature_class":"P",
    "gn:feature_code":"PPL",
    "gn:name":"Fahrndorf",
    "gn:population":0,
    "gn:timezone":"Europe/Berlin",
    "iso:country":"DE",
    "wof:name":"Fahrndorf",
    "wof:placetype":"neighbourhood"
},
  "geometry": {"coordinates":[12.79876,48.83701],"type":"Point"}
}