{
  "type": "Feature",
  "properties": {
    "iso:country":"DE",
    "name:deu_x_preferred":[
        "Untert\u00fcrkheim"
    ],
    "wof:name":"Untertuerkheim",
    "wof:placetype":"neighbourhood"
},
  "geometry": {"coordinates":[9.2552393436729,48.78089069397468],"type":"Point"}
}