{
  "type": "Feature",
  "properties": {
    "gn:admin1_code":"7",
    "gn:admin2_code":"53.0",
    "gn:admin3_code":"5382.0",
    "gn:admin4_code":"5382048.0",
    "gn:asciiname":"Ramershoven",
    "gn:country_code":"DE",
    "gn:dem":160,
    "gn:feature_class":"P",
    "gn:feature_code":"PPL",
    "gn:name":"Ramershoven",
    "gn:population":0,
    "gn:timezone":"Europe/Berlin",
    "iso:country":"DE",
    "wof:name":"Ramershoven",
    "wof:placetype":"neighbourhood"
},
  "geometry": {"coordinates":[6.96559,50.64249],"type":"Point"}
}