{
  "type": "Feature",
  "properties": {
    "gn:admin1_code":"13",
    "gn:admin2_code":"0.0",
    "gn:admin3_code":"14729.0",
    "gn:admin4_code":"14729190.0",
    "gn:asciiname":"Roedgen",
    "gn:country_code":"DE",
    "gn:dem":87,
    "gn:feature_class":"P",
    "gn:feature_code":"PPL",
    "gn:name":"R\u00f6dgen",
    "gn:population":0,
    "gn:timezone":"Europe/Berlin",
    "iso:country":"DE",
    "name:cat_x_preferred":[
        "Roedgen"
    ],
    "name:ceb_x_preferred":[
        "Roedgen"
    ],
    "name:fra_x_preferred":[
        "Roedgen"
    ],
    "name:ltz_x_preferred":[
        "Riedgen"
    ],
    "name:nld_x_preferred":[
        "Roedgen"
    ],
    "name:pol_x_preferred":[
        "Roedgen"
    ],
    "name:swe_x_preferred":[
        "Roedgen"
    ],
    "wof:name":"Roedgen",
    "wof:placetype":"neighbourhood"
},
  "geometry": {"coordinates":[12.4671,51.2411],"type":"Point"}
}