{
  "type": "Feature",
  "properties": {
    "gn:admin1_code":"12",
    "gn:admin2_code":"0.0",
    "gn:admin3_code":"13074.0",
    "gn:admin4_code":"13074007.0",
    "gn:asciiname":"Friedrichsdorf",
    "gn:country_code":"DE",
    "gn:dem":22,
    "gn:feature_class":"P",
    "gn:feature_code":"PPL",
    "gn:name":"Friedrichsdorf",
    "gn:population":0,
    "gn:timezone":"Europe/Berlin",
    "iso:country":"DE",
    "name:afr_x_preferred":[
        "Friedrichsdorf"
    ],
    "name:ara_x_preferred":[
        "\u0641\u0631\u064a\u062f\u0631\u064a\u0634\u0633\u062f\u0648\u0631\u0641"
    ],
    "name:azb_x_preferred":[
        "\u0641\u0631\u06cc\u062f\u0631\u06cc\u0634\u0632\u062f\u0648\u0631\u0641"
    ],
    "name:ceb_x_preferred":[
        "Friedrichsdorf"
    ],
    "name:deu_x_preferred":[
        "Friedrichsdorf"
    ],
    "name:epo_x_preferred":[
        "Friedrichsdorf"
    ],
    "name:fas_x_preferred":[
        "\u0641\u0631\u06cc\u062f\u0631\u06cc\u0634\u0632\u062f\u0648\u0631\u0641"
    ],
    "name:fra_x_preferred":[
        "Friedrichsdorf"
    ],
    "name:hun_x_preferred":[
        "Friedrichsdorf"
    ],
    "name:ita_x_preferred":[
        "Friedrichsdorf"
    ],
    "name:jpn_x_preferred":[
        "\u30d5\u30ea\u30fc\u30c9\u30ea\u30d2\u30b9\u30c9\u30eb\u30d5"
    ],
    "name:msa_x_preferred":[
        "Friedrichsdorf"
    ],
    "name:nld_x_preferred":[
        "Friedrichsdorf"
    ],
    "name:pcd_x_preferred":[
        "Friedrichsdorf"
    ],
    "name:pol_x_preferred":[
        "Friedrichsdorf"
    ],
    "name:ron_x_preferred":[
        "Friedrichsdorf"
    ],
    "name:rus_x_preferred":[
        "\u0424\u0440\u0438\u0434\u0440\u0438\u0445\u0441\u0434\u043e\u0440\u0444"
    ],
    "name:spa_x_preferred":[
        "Friedrichsdorf"
    ],
    "name:srp_x_preferred":[
        "\u0424\u0440\u0438\u0434\u0440\u0438\u0445\u0441\u0434\u043e\u0440\u0444"
    ],
    "name:swa_x_preferred":[
        "Friedrichsdorf"
    ],
    "name:tur_x_preferred":[
        "Friedrichsdorf"
    ],
    "name:ukr_x_preferred":[
        "\u0424\u0440\u0456\u0434\u0440\u0456\u0445\u0441\u0434\u043e\u0440\u0444"
    ],
    "name:uzb_x_preferred":[
        "Friedrichsdorf"
    ],
    "name:vol_x_preferred":[
        "Friedrichsdorf"
    ],
    "name:war_x_preferred":[
        "Friedrichsdorf"
    ],
    "name:zho_x_preferred":[
        "\u8153\u7279\u70c8\u65af\u591a\u592b"
    ],
    "wof:name":"Friedrichsdorf",
    "wof:placetype":"neighbourhood"
},
  "geometry": {"coordinates":[11.56249,53.98491],"type":"Point"}
}