{
  "type": "Feature",
  "properties": {
    "gn:admin1_code":"12",
    "gn:admin2_code":"0.0",
    "gn:admin3_code":"13074.0",
    "gn:admin4_code":"13074007.0",
    "gn:asciiname":"Friedrichsdorf",
    "gn:country_code":"DE",
    "gn:dem":22,
    "gn:feature_class":"P",
    "gn:feature_code":"PPL",
    "gn:name":"Friedrichsdorf",
    "gn:population":0,
    "gn:timezone":"Europe/Berlin",
    "iso:country":"DE",
    "wof:name":"Friedrichsdorf",
    "wof:placetype":"neighbourhood"
},
  "geometry": {"coordinates":[11.56249,53.98491],"type":"Point"}
}