{
  "type": "Feature",
  "properties": {
    "gn:admin1_code":"2",
    "gn:admin2_code":"93.0",
    "gn:admin3_code":"9376.0",
    "gn:admin4_code":"9376167.0",
    "gn:asciiname":"Waldhauser",
    "gn:country_code":"DE",
    "gn:dem":699,
    "gn:feature_class":"P",
    "gn:feature_code":"PPL",
    "gn:name":"Waldh\u00e4user",
    "gn:population":0,
    "gn:timezone":"Europe/Berlin",
    "iso:country":"DE",
    "wof:name":"Waldhauser",
    "wof:placetype":"neighbourhood"
},
  "geometry": {"coordinates":[12.63817,49.51508],"type":"Point"}
}