{
  "type": "Feature",
  "properties": {
    "iso:country":"DE",
    "name:ger_x_variant":[
        "Unter-Gerresheim"
    ],
    "wof:name":"H\u00fcttenviertel",
    "wof:placetype":"neighbourhood"
},
  "geometry": {"coordinates":[6.86201692661054,51.226309910826],"type":"Point"}
}