{
  "type": "Feature",
  "properties": {
    "gn:admin1_code":"7",
    "gn:admin2_code":"53.0",
    "gn:admin3_code":"5382.0",
    "gn:admin4_code":"5382028.0",
    "gn:asciiname":"Hoven",
    "gn:country_code":"DE",
    "gn:dem":205,
    "gn:feature_class":"P",
    "gn:feature_code":"PPL",
    "gn:name":"Hoven",
    "gn:population":0,
    "gn:timezone":"Europe/Berlin",
    "iso:country":"DE",
    "wof:name":"Hoven",
    "wof:placetype":"neighbourhood"
},
  "geometry": {"coordinates":[7.24493,50.91644],"type":"Point"}
}