{
  "type": "Feature",
  "properties": {
    "gn:admin1_code":"2",
    "gn:admin2_code":"95.0",
    "gn:admin3_code":"9575.0",
    "gn:admin4_code":"9575118.0",
    "gn:asciiname":"Hanbach",
    "gn:country_code":"DE",
    "gn:dem":288,
    "gn:feature_class":"P",
    "gn:feature_code":"PPL",
    "gn:name":"Hanbach",
    "gn:population":0,
    "gn:timezone":"Europe/Berlin",
    "iso:country":"DE",
    "wof:name":"Hanbach",
    "wof:placetype":"neighbourhood"
},
  "geometry": {"coordinates":[10.5878,49.60588],"type":"Point"}
}