{
  "type": "Feature",
  "properties": {
    "gn:admin1_code":"7",
    "gn:admin2_code":"59.0",
    "gn:admin3_code":"5962.0",
    "gn:admin4_code":"5962036.0",
    "gn:asciiname":"Ihne",
    "gn:country_code":"DE",
    "gn:dem":374,
    "gn:feature_class":"P",
    "gn:feature_code":"PPL",
    "gn:name":"Ihne",
    "gn:population":0,
    "gn:timezone":"Europe/Berlin",
    "iso:country":"DE",
    "name:chv_x_preferred":[
        "\u0418\u043d\u0435"
    ],
    "name:deu_x_preferred":[
        "Ihne"
    ],
    "wof:name":"Ihne",
    "wof:placetype":"neighbourhood"
},
  "geometry": {"coordinates":[7.7793,51.10845],"type":"Point"}
}