{
  "type": "Feature",
  "properties": {
    "gn:gn_country":"DE",
    "gn:gn_fcode":"PPLA4",
    "gn:gn_pop":698,
    "gn:population":698,
    "iso:country":"DE",
    "name:chi_x_preferred":[
        "\u7b56\u5c14\u79d1"
    ],
    "name:deu_x_preferred":[
        "Z\u00f6lkow"
    ],
    "name:dut_x_preferred":[
        "Z\u00f6lkow"
    ],
    "name:eng_x_preferred":[
        "Z\u00f6lkow"
    ],
    "name:epo_x_preferred":[
        "Z\u00f6lkow"
    ],
    "name:fre_x_preferred":[
        "Z\u00f6lkow"
    ],
    "name:ger_x_preferred":[
        "Z\u00f6lkow"
    ],
    "name:hun_x_preferred":[
        "Z\u00f6lkow"
    ],
    "name:ita_x_preferred":[
        "Z\u00f6lkow"
    ],
    "name:kaz_x_preferred":[
        "\u0426\u0451\u043b\u044c\u043a\u043e\u0432"
    ],
    "name:kir_x_preferred":[
        "\u0426\u04e9\u043b\u044c\u043a\u043e\u0432"
    ],
    "name:mac_x_preferred":[
        "\u0426\u0435\u043b\u043a\u043e\u0432"
    ],
    "name:may_x_preferred":[
        "Z\u00f6lkow"
    ],
    "name:per_x_preferred":[
        "\u062a\u0633\u0648\u0644\u06a9\u0648\u0648"
    ],
    "name:pol_x_preferred":[
        "Z\u00f6lkow"
    ],
    "name:por_x_preferred":[
        "Z\u00f6lkow"
    ],
    "name:rum_x_preferred":[
        "Z\u00f6lkow"
    ],
    "name:rus_x_preferred":[
        "\u0426\u0451\u043b\u044c\u043a\u043e\u0432"
    ],
    "name:srp_x_preferred":[
        "\u0426\u0435\u043b\u043a\u043e\u0432"
    ],
    "name:tgl_x_preferred":[
        "Z\u00f6lkow"
    ],
    "name:ukr_x_preferred":[
        "\u0426\u0435\u043b\u044c\u043a\u043e\u0432"
    ],
    "name:uzb_x_preferred":[
        "Z\u00f6lkow"
    ],
    "name:vie_x_preferred":[
        "Z\u00f6lkow"
    ],
    "name:vol_x_preferred":[
        "Z\u00f6lkow"
    ],
    "name:war_x_preferred":[
        "Z\u00f6lkow"
    ],
    "qs_pg:aaroncc":"DE",
    "qs_pg:gn_country":"DE",
    "qs_pg:gn_fcode":"PPLA4",
    "qs_pg:gn_pop":698,
    "qs_pg:name":"Z\u00f6lkow",
    "qs_pg:photos_9r":0,
    "qs_pg:photos_sr":0,
    "qs_pg:pop_sr":2,
    "qs_pg:qs_pg_placetype":"locality",
    "wof:name":"Z\u00f6lkow",
    "wof:placetype":"locality",
    "wof:population":698
},
  "geometry": {"coordinates":[11.8206,53.56325],"type":"Point"}
}