{
  "type": "Feature",
  "properties": {
    "gn:country":"DE",
    "gn:fcode":"PPL",
    "gn:population":0,
    "iso:country":"DE",
    "name:als_x_preferred":[
        "Rohr"
    ],
    "name:cat_x_preferred":[
        "Rohr"
    ],
    "name:ceb_x_preferred":[
        "Rohr"
    ],
    "name:deu_x_preferred":[
        "Rohr"
    ],
    "name:epo_x_preferred":[
        "Rohr"
    ],
    "name:fra_x_preferred":[
        "Rohr"
    ],
    "name:hye_x_preferred":[
        "\u054c\u0578\u0570\u0580"
    ],
    "name:ita_x_preferred":[
        "Rohr"
    ],
    "name:kir_x_preferred":[
        "\u0420\u043e\u0440"
    ],
    "name:lmo_x_preferred":[
        "Rohr"
    ],
    "name:nds_x_preferred":[
        "Rohr"
    ],
    "name:nld_x_preferred":[
        "Rohr"
    ],
    "name:pms_x_preferred":[
        "Rohr"
    ],
    "name:pol_x_preferred":[
        "Rohr"
    ],
    "name:por_x_preferred":[
        "Rohr"
    ],
    "name:rus_x_preferred":[
        "\u0420\u043e\u0440"
    ],
    "name:spa_x_preferred":[
        "Rohr"
    ],
    "name:swe_x_preferred":[
        "Rohr"
    ],
    "name:vol_x_preferred":[
        "Rohr"
    ],
    "qs_pg:aaroncc":"DE",
    "qs_pg:gn_country":"DE",
    "qs_pg:gn_fcode":"PPL",
    "qs_pg:gn_pop":0,
    "qs_pg:name":"Rohr",
    "qs_pg:name_adm0":"Deutschland",
    "qs_pg:name_adm1":"Nordrhein-Westfalen",
    "qs_pg:photos":90,
    "qs_pg:photos_1k":18,
    "qs_pg:photos_9k":1,
    "qs_pg:photos_9r":3,
    "qs_pg:photos_all":90,
    "qs_pg:photos_sr":3,
    "qs_pg:pop_sr":0,
    "qs_pg:qs_pg_placetype":"locality",
    "qs_pg:qs_pg_placetype_gp":"Town",
    "qs_pg:woe_adm0":23424829,
    "woe:adm0_id":23424829,
    "woe:name_adm0":"Deutschland",
    "woe:name_adm1":"Nordrhein-Westfalen",
    "woe:placetype":"Town",
    "wof:name":"Rohr",
    "wof:placetype":"neighbourhood"
},
  "geometry": {"coordinates":[6.73268,50.45298],"type":"Point"}
}