{
  "type": "Feature",
  "properties": {
    "gn:admin1_code":"2",
    "gn:admin2_code":"94.0",
    "gn:admin3_code":"9474.0",
    "gn:admin4_code":"9474138.0",
    "gn:asciiname":"Gorbitz",
    "gn:country_code":"DE",
    "gn:dem":488,
    "gn:feature_class":"P",
    "gn:feature_code":"PPL",
    "gn:name":"G\u00f6rbitz",
    "gn:population":0,
    "gn:timezone":"Europe/Berlin",
    "iso:country":"DE",
    "name:ceb_x_preferred":[
        "Gorbitz"
    ],
    "name:deu_x_preferred":[
        "Gorbitz"
    ],
    "name:fas_x_preferred":[
        "\u06af\u0648\u0631\u0628\u06cc\u062a\u0633"
    ],
    "name:ita_x_preferred":[
        "Gorbitz"
    ],
    "name:swe_x_preferred":[
        "Gorbitz"
    ],
    "wof:name":"Gorbitz",
    "wof:placetype":"neighbourhood"
},
  "geometry": {"coordinates":[11.30939,49.64959],"type":"Point"}
}