{
  "type": "Feature",
  "properties": {
    "gn:country":"DE",
    "gn:fcode":"PPL",
    "gn:population":0,
    "iso:country":"DE",
    "qs_pg:aaroncc":"DE",
    "qs_pg:gn_country":"DE",
    "qs_pg:gn_fcode":"PPL",
    "qs_pg:gn_pop":0,
    "qs_pg:name":"Ragow",
    "qs_pg:name_adm0":"Deutschland",
    "qs_pg:name_adm1":"Bundesland Brandenburg",
    "qs_pg:photos":673,
    "qs_pg:photos_1k":136,
    "qs_pg:photos_9k":3,
    "qs_pg:photos_9r":5,
    "qs_pg:photos_all":673,
    "qs_pg:photos_sr":8,
    "qs_pg:pop_sr":0,
    "qs_pg:qs_pg_placetype":"locality",
    "qs_pg:qs_pg_placetype_gp":"Town",
    "qs_pg:woe_adm0":23424829,
    "woe:adm0_id":23424829,
    "woe:name_adm0":"Deutschland",
    "woe:name_adm1":"Bundesland Brandenburg",
    "woe:placetype":"Town",
    "wof:name":"Ragow",
    "wof:placetype":"neighbourhood"
},
  "geometry": {"coordinates":[13.54446,52.28657],"type":"Point"}
}