{
  "type": "Feature",
  "properties": {
    "gn:admin1_code":"7.0",
    "gn:admin2_code":"059",
    "gn:admin3_code":"5962.0",
    "gn:admin4_code":"5962020.0",
    "gn:asciiname":"Weisse Ahe",
    "gn:country_code":"DE",
    "gn:dem":344,
    "gn:feature_class":"P",
    "gn:feature_code":"PPL",
    "gn:name":"Wei\u00dfe Ahe",
    "gn:population":0,
    "gn:timezone":"Europe/Berlin",
    "iso:country":"DE",
    "name:und_x_variant":[
        "Ahe",
        "Wei\u00dfe Ahe"
    ],
    "wof:name":"Weisse Ahe",
    "wof:placetype":"neighbourhood"
},
  "geometry": {"coordinates":[7.78727,51.17665],"type":"Point"}
}