{
  "type": "Feature",
  "properties": {
    "gn:admin1_code":"1.0",
    "gn:admin2_code":"82.0",
    "gn:admin3_code":"8216.0",
    "gn:admin4_code":"8216007.0",
    "gn:asciiname":"Waldsteg",
    "gn:country_code":"DE",
    "gn:dem":249,
    "gn:feature_class":"P",
    "gn:feature_code":"PPL",
    "gn:name":"Waldsteg",
    "gn:population":0,
    "gn:timezone":"Europe/Berlin",
    "iso:country":"DE",
    "wof:name":"Waldsteg",
    "wof:placetype":"neighbourhood"
},
  "geometry": {"coordinates":[8.14446,48.65836],"type":"Point"}
}