{
  "type": "Feature",
  "properties": {
    "gn:admin1_code":"5",
    "gn:admin2_code":"66.0",
    "gn:admin3_code":"6631.0",
    "gn:admin4_code":"6631020.0",
    "gn:asciiname":"Steinhaus",
    "gn:country_code":"DE",
    "gn:dem":296,
    "gn:feature_class":"P",
    "gn:feature_code":"PPL",
    "gn:name":"Steinhaus",
    "gn:population":0,
    "gn:timezone":"Europe/Berlin",
    "iso:country":"DE",
    "name:ceb_x_preferred":[
        "Steinhaus"
    ],
    "name:deu_x_preferred":[
        "Steinhaus"
    ],
    "name:epo_x_preferred":[
        "Steinhaus"
    ],
    "name:fra_x_preferred":[
        "Steinhaus"
    ],
    "name:ita_x_preferred":[
        "Steinhaus"
    ],
    "name:nld_x_preferred":[
        "Steinhaus"
    ],
    "name:pol_x_preferred":[
        "Steinhaus"
    ],
    "name:swe_x_preferred":[
        "Steinhaus"
    ],
    "name:ukr_x_preferred":[
        "\u0428\u0442\u0435\u0439\u043d\u0433\u0430\u0443\u0437"
    ],
    "wof:name":"Steinhaus",
    "wof:placetype":"neighbourhood"
},
  "geometry": {"coordinates":[9.74676,50.59473],"type":"Point"}
}