{
  "type": "Feature",
  "properties": {
    "gn:admin1_code":"10.0",
    "gn:admin2_code":"0.0",
    "gn:admin3_code":"1056.0",
    "gn:admin4_code":"1056048.0",
    "gn:asciiname":"Ahrenlohe",
    "gn:country_code":"DE",
    "gn:dem":15,
    "gn:feature_class":"P",
    "gn:feature_code":"PPL",
    "gn:name":"Ahrenlohe",
    "gn:population":0,
    "gn:timezone":"Europe/Berlin",
    "iso:country":"DE",
    "wof:name":"Ahrenlohe",
    "wof:placetype":"neighbourhood"
},
  "geometry": {"coordinates":[9.74682,53.71286],"type":"Point"}
}