{
  "type": "Feature",
  "properties": {
    "gn:admin1_code":"1",
    "gn:admin2_code":"83.0",
    "gn:admin3_code":"8327.0",
    "gn:admin4_code":"8327038.0",
    "gn:asciiname":"Neuhausen ob Eck",
    "gn:cc2":"DE",
    "gn:country_code":"DE",
    "gn:dem":767,
    "gn:feature_class":"P",
    "gn:feature_code":"PPLA4",
    "gn:name":"Neuhausen ob Eck",
    "gn:population":0,
    "gn:timezone":"Europe/Berlin",
    "iso:country":"DE",
    "name:rus_x_preferred":[
        "\u041d\u043e\u0439\u0445\u0430\u0443\u0437\u0435\u043d-\u043e\u0431-\u042d\u043a\u043a"
    ],
    "name:srp_x_preferred":[
        "\u041d\u043e\u0458\u0445\u0430\u0443\u0437\u0435\u043d \u043e\u0431 \u0415\u043a"
    ],
    "name:und_x_variant":[
        "Neuhausen"
    ],
    "name:zho_x_preferred":[
        "\u8bfa\u4f0a\u8c6a\u68ee\u5965\u5e03\u57c3\u514b"
    ],
    "wof:name":"Neuhausen ob Eck",
    "wof:placetype":"locality"
},
  "geometry": {"coordinates":[8.92759,47.97257000000001],"type":"Point"}
}