{
  "type": "Feature",
  "properties": {
    "gn:admin1_code":"13",
    "gn:admin2_code":"0.0",
    "gn:admin3_code":"14522.0",
    "gn:admin4_code":"14522580.0",
    "gn:asciiname":"Seitenhain",
    "gn:country_code":"DE",
    "gn:dem":236,
    "gn:feature_class":"P",
    "gn:feature_code":"PPL",
    "gn:name":"Seitenhain",
    "gn:population":0,
    "gn:timezone":"Europe/Berlin",
    "iso:country":"DE",
    "wof:name":"Seitenhain",
    "wof:placetype":"neighbourhood"
},
  "geometry": {"coordinates":[12.80526,50.98651],"type":"Point"}
}