{
  "type": "Feature",
  "properties": {
    "gn:admin1_code":"2",
    "gn:admin2_code":"91.0",
    "gn:admin3_code":"9175.0",
    "gn:admin4_code":"9175119.0",
    "gn:asciiname":"Lauterbach",
    "gn:country_code":"DE",
    "gn:dem":487,
    "gn:feature_class":"P",
    "gn:feature_code":"PPL",
    "gn:name":"Lauterbach",
    "gn:population":0,
    "gn:timezone":"Europe/Berlin",
    "iso:country":"DE",
    "name:ceb_x_preferred":[
        "Lauterbach"
    ],
    "name:chv_x_preferred":[
        "\u041b\u0430\u0443\u0442\u0435\u0440\u0431\u0430\u0445"
    ],
    "name:deu_x_preferred":[
        "Lauterbach"
    ],
    "name:epo_x_preferred":[
        "Lauterbach"
    ],
    "name:fra_x_preferred":[
        "Lauterbach"
    ],
    "name:heb_x_preferred":[
        "\u05dc\u05d5\u05d9\u05d8\u05e8\u05d1\u05da"
    ],
    "name:hun_x_preferred":[
        "Lauterbach"
    ],
    "name:ita_x_preferred":[
        "Lauterbach"
    ],
    "name:jpn_x_preferred":[
        "\u30e9\u30a6\u30bf\u30fc\u30d0\u30c3\u30cf"
    ],
    "name:nld_x_preferred":[
        "Lauterbach"
    ],
    "name:nor_x_preferred":[
        "Lauterbach"
    ],
    "name:pol_x_preferred":[
        "Lauterbach"
    ],
    "name:ron_x_preferred":[
        "Lauterbach"
    ],
    "name:rus_x_preferred":[
        "\u041b\u0430\u0443\u0442\u0435\u0440\u0431\u0430\u0445"
    ],
    "name:srp_x_preferred":[
        "\u041b\u0430\u0443\u0442\u0435\u0440\u0431\u0430\u0445"
    ],
    "name:swe_x_preferred":[
        "Lauterbach"
    ],
    "name:vol_x_preferred":[
        "Lauterbach"
    ],
    "wof:name":"Lauterbach",
    "wof:placetype":"neighbourhood"
},
  "geometry": {"coordinates":[12.05526,48.04825],"type":"Point"}
}