{
  "type": "Feature",
  "properties": {
    "iso:country":"DE",
    "name:cat_x_preferred":[
        "Sankt Georg"
    ],
    "name:ceb_x_preferred":[
        "St. Georg"
    ],
    "name:deu_x_preferred":[
        "Sankt Georg"
    ],
    "name:deu_x_variant":[
        "St. Georg"
    ],
    "name:eng_x_preferred":[
        "St. Georg"
    ],
    "name:fas_x_preferred":[
        "\u0634\u062a. \u06af\u0648\u0631\u06af"
    ],
    "name:fra_x_preferred":[
        "Hamburg-Sankt Georg"
    ],
    "name:ger_x_variant":[
        "St. Georg"
    ],
    "name:heb_x_preferred":[
        "\u05e1\u05e0\u05d8 \u05d2\u05d0\u05d5\u05e8\u05d2"
    ],
    "name:hun_x_preferred":[
        "St. Georg"
    ],
    "name:hye_x_preferred":[
        "\u054d\u0578\u0582\u0580\u0562 \u0533\u0587\u0578\u0580\u0563"
    ],
    "name:ita_x_preferred":[
        "St. Georg"
    ],
    "name:lat_x_preferred":[
        "Hamburg-St. Georg"
    ],
    "name:mkd_x_preferred":[
        "\u0417\u0430\u043d\u043a\u0442 \u0413\u0435\u043e\u0440\u0433"
    ],
    "name:nld_x_preferred":[
        "St. Georg"
    ],
    "name:nob_x_preferred":[
        "St. Georg"
    ],
    "name:pol_x_preferred":[
        "St. Georg"
    ],
    "name:rus_x_preferred":[
        "\u0421\u0435\u043d\u0442-\u0413\u0435\u043e\u0440\u0433"
    ],
    "name:spa_x_preferred":[
        "Sankt Georg"
    ],
    "name:swe_x_preferred":[
        "Hamburg-St. Georg"
    ],
    "name:urd_x_preferred":[
        "\u0633\u06cc\u0646\u0679 \u062c\u0627\u0631\u062c\u060c \u06c1\u06cc\u0645\u0628\u0631\u06af"
    ],
    "name:urd_x_variant":[
        "\u0633\u06cc\u0646\u0679 \u062c\u0627\u0631\u062c"
    ],
    "wof:name":"Sankt Georg",
    "wof:placetype":"neighbourhood"
},
  "geometry": {"coordinates":[10.01533261842867,53.55516907091135],"type":"Point"}
}