{
  "type": "Feature",
  "properties": {
    "gn:admin1_code":"12",
    "gn:admin2_code":"0.0",
    "gn:admin3_code":"13074.0",
    "gn:admin4_code":"13074093.0",
    "gn:asciiname":"Rodenberg",
    "gn:country_code":"DE",
    "gn:dem":9,
    "gn:feature_class":"P",
    "gn:feature_code":"PPL",
    "gn:name":"Rodenberg",
    "gn:population":0,
    "gn:timezone":"Europe/Berlin",
    "iso:country":"DE",
    "name:ara_x_preferred":[
        "\u0631\u0648\u062f\u0646\u0628\u0631\u063a"
    ],
    "name:azb_x_preferred":[
        "\u0631\u062f\u0646\u0628\u0631\u0642"
    ],
    "name:ceb_x_preferred":[
        "Rodenberg"
    ],
    "name:dan_x_preferred":[
        "Rodenberg"
    ],
    "name:deu_x_preferred":[
        "Rodenberg"
    ],
    "name:epo_x_preferred":[
        "Rodenberg"
    ],
    "name:est_x_preferred":[
        "Rodenberg"
    ],
    "name:eus_x_preferred":[
        "Rodenberg"
    ],
    "name:fas_x_preferred":[
        "\u0631\u062f\u0646\u0628\u0631\u06af"
    ],
    "name:fra_x_preferred":[
        "Rodenberg"
    ],
    "name:heb_x_preferred":[
        "\u05e8\u05d5\u05d3\u05e0\u05d1\u05e8\u05d2"
    ],
    "name:hun_x_preferred":[
        "Rodenberg"
    ],
    "name:ita_x_preferred":[
        "Rodenberg"
    ],
    "name:jpn_x_preferred":[
        "\u30ed\u30fc\u30c7\u30f3\u30d9\u30eb\u30af"
    ],
    "name:kaz_x_preferred":[
        "\u0420\u043e\u0434\u0435\u043d\u0431\u0435\u0440\u0433"
    ],
    "name:kir_x_preferred":[
        "\u0420\u043e\u0434\u0435\u043d\u0431\u0435\u0440\u0433"
    ],
    "name:mkd_x_preferred":[
        "\u0420\u043e\u0434\u0435\u043d\u0431\u0435\u0440\u0433"
    ],
    "name:msa_x_preferred":[
        "Rodenberg"
    ],
    "name:nld_x_preferred":[
        "Rodenberg"
    ],
    "name:pol_x_preferred":[
        "Rodenberg"
    ],
    "name:por_x_preferred":[
        "Rodenberg"
    ],
    "name:ron_x_preferred":[
        "Rodenberg"
    ],
    "name:rus_x_preferred":[
        "\u0420\u043e\u0434\u0435\u043d\u0431\u0435\u0440\u0433"
    ],
    "name:spa_x_preferred":[
        "Rodenberg"
    ],
    "name:srp_x_preferred":[
        "\u0420\u043e\u0434\u0435\u043d\u0431\u0435\u0440\u0433"
    ],
    "name:swe_x_preferred":[
        "Rodenberg"
    ],
    "name:ukr_x_preferred":[
        "\u0420\u043e\u0434\u0435\u043d\u0431\u0435\u0440\u0433"
    ],
    "name:uzb_x_preferred":[
        "Rodenberg"
    ],
    "name:vol_x_preferred":[
        "Rodenberg"
    ],
    "name:war_x_preferred":[
        "Rodenberg"
    ],
    "name:zho_x_preferred":[
        "\u7f57\u767b\u8d1d\u683c"
    ],
    "wof:name":"Rodenberg",
    "wof:placetype":"neighbourhood"
},
  "geometry": {"coordinates":[11.02163,53.87474],"type":"Point"}
}