{
  "type": "Feature",
  "properties": {
    "gn:admin1_code":"2.0",
    "gn:admin2_code":"97.0",
    "gn:admin3_code":"9780.0",
    "gn:admin4_code":"9780114.0",
    "gn:asciiname":"Bogenried",
    "gn:country_code":"DE",
    "gn:dem":722,
    "gn:feature_class":"P",
    "gn:feature_code":"PPL",
    "gn:name":"Bogenried",
    "gn:population":0,
    "gn:timezone":"Europe/Berlin",
    "iso:country":"DE",
    "wof:name":"Bogenried",
    "wof:placetype":"neighbourhood"
},
  "geometry": {"coordinates":[10.3909,47.75398],"type":"Point"}
}