{
  "type": "Feature",
  "properties": {
    "gn:admin1_code":"6",
    "gn:admin2_code":"0.0",
    "gn:admin3_code":"3360.0",
    "gn:admin4_code":"3360004.0",
    "gn:asciiname":"Eitzen Eins",
    "gn:country_code":"DE",
    "gn:dem":32,
    "gn:feature_class":"P",
    "gn:feature_code":"PPL",
    "gn:name":"Eitzen Eins",
    "gn:population":0,
    "gn:timezone":"Europe/Berlin",
    "iso:country":"DE",
    "name:und_x_variant":[
        "Eitzen",
        "Eitzen Eins"
    ],
    "wof:name":"Eitzen Eins",
    "wof:placetype":"neighbourhood"
},
  "geometry": {"coordinates":[10.43093,53.13509000000001],"type":"Point"}
}