{
  "type": "Feature",
  "properties": {
    "gn:admin1_code":"11",
    "gn:admin2_code":"0.0",
    "gn:admin3_code":"12060.0",
    "gn:admin4_code":"12060100.0",
    "gn:asciiname":"Neuhaus",
    "gn:country_code":"DE",
    "gn:dem":79,
    "gn:feature_class":"P",
    "gn:feature_code":"PPL",
    "gn:name":"Neuhaus",
    "gn:population":0,
    "gn:timezone":"Europe/Berlin",
    "iso:country":"DE",
    "wof:name":"Neuhaus",
    "wof:placetype":"neighbourhood"
},
  "geometry": {"coordinates":[13.77737,52.99929],"type":"Point"}
}