{
  "type": "Feature",
  "properties": {
    "gn:admin1_code":"12",
    "gn:admin2_code":"0.0",
    "gn:admin3_code":"13074.0",
    "gn:admin4_code":"13074033.0",
    "gn:asciiname":"Steinmannshagen",
    "gn:country_code":"DE",
    "gn:dem":53,
    "gn:feature_class":"P",
    "gn:feature_code":"PPL",
    "gn:name":"Steinmannshagen",
    "gn:population":0,
    "gn:timezone":"Europe/Berlin",
    "iso:country":"DE",
    "wof:name":"Steinmannshagen",
    "wof:placetype":"neighbourhood"
},
  "geometry": {"coordinates":[11.0236,53.70838000000001],"type":"Point"}
}