{
  "type": "Feature",
  "properties": {
    "gn:admin1_code":"2.0",
    "gn:admin2_code":"93.0",
    "gn:admin3_code":"9377.0",
    "gn:admin4_code":"9377118.0",
    "gn:asciiname":"Barnhohe",
    "gn:country_code":"DE",
    "gn:dem":623,
    "gn:feature_class":"P",
    "gn:feature_code":"PPL",
    "gn:name":"B\u00e4rnh\u00f6he",
    "gn:population":0,
    "gn:timezone":"Europe/Berlin",
    "iso:country":"DE",
    "wof:name":"Barnhohe",
    "wof:placetype":"neighbourhood"
},
  "geometry": {"coordinates":[12.0681,49.88876],"type":"Point"}
}