{
  "type": "Feature",
  "properties": {
    "gn:admin1_code":"7",
    "gn:admin2_code":"53.0",
    "gn:admin3_code":"5382.0",
    "gn:admin4_code":"5382052.0",
    "gn:asciiname":"Juenkersfeld",
    "gn:country_code":"DE",
    "gn:dem":183,
    "gn:feature_class":"P",
    "gn:feature_code":"PPL",
    "gn:name":"J\u00fcnkersfeld",
    "gn:population":0,
    "gn:timezone":"Europe/Berlin",
    "iso:country":"DE",
    "wof:name":"Juenkersfeld",
    "wof:placetype":"neighbourhood"
},
  "geometry": {"coordinates":[7.42624,50.84472],"type":"Point"}
}