{
  "type": "Feature",
  "properties": {
    "iso:country":"DE",
    "name:deu_x_preferred":[
        "Stahmeln"
    ],
    "name:unk_x_variant":[
        "Stahmeln"
    ],
    "qs:gn_adm0_cc":"DE",
    "qs:gn_fcode":"PPL",
    "qs:gn_local":2879139,
    "qs:gn_nam_loc":"Leipzig, Kreisfreie Stadt Leipzig, Sachsen, DE",
    "qs:gn_namadm1":"13",
    "qs:gn_name":"Stahmeln",
    "qs:local_max":18559,
    "qs:local_sum":46030,
    "qs:localhoods":28,
    "qs:name":"Stahmeln",
    "qs:name_adm0":"Deutschland",
    "qs:name_adm1":"Sachsen",
    "qs:name_adm2":"Kreisfreie Stadt Leipzig",
    "qs:name_lau":"Stadtteil Wahren",
    "qs:name_local":"Leipzig",
    "qs:photo_max":170,
    "qs:photo_sum":258,
    "qs:placetype":"Suburb",
    "qs:quad_count":12,
    "qs:woe_adm0":23424829,
    "qs:woe_adm1":2345493,
    "qs:woe_adm2":12596753,
    "qs:woe_lau":26822873,
    "qs:woe_local":671072,
    "qs:woe_ver":"7.10.0",
    "wof:lang":[
        "ger"
    ],
    "wof:name":"Stahmeln",
    "wof:placetype":"neighbourhood"
},
  "geometry": {"coordinates":[12.299678,51.378442],"type":"Point"}
}