{
  "type": "Feature",
  "properties": {
    "iso:country":"DE",
    "name:bpy_x_preferred":[
        "\u09b0\u09be\u09a5"
    ],
    "name:ceb_x_preferred":[
        "Rath"
    ],
    "name:ces_x_preferred":[
        "Rath"
    ],
    "name:deu_x_preferred":[
        "Rath"
    ],
    "name:fra_x_preferred":[
        "Rath"
    ],
    "name:hun_x_preferred":[
        "R\u00e1th"
    ],
    "name:ita_x_preferred":[
        "Rath"
    ],
    "name:msa_x_preferred":[
        "Rath"
    ],
    "name:nld_x_preferred":[
        "Rath"
    ],
    "name:pol_x_preferred":[
        "Rath"
    ],
    "name:swe_x_preferred":[
        "Rath"
    ],
    "name:unk_x_variant":[
        "Rath"
    ],
    "name:vie_x_preferred":[
        "Rath"
    ],
    "qs:gn_fcode":"PPLX",
    "qs:gn_local":0,
    "qs:gn_namadm1":"07",
    "qs:gn_name":"Rath",
    "qs:local_max":1159,
    "qs:local_sum":2186,
    "qs:localhoods":16,
    "qs:name":"Rath",
    "qs:name_adm0":"Deutschland",
    "qs:name_adm1":"Nordrhein-Westfalen",
    "qs:name_adm2":"Stadtkreis Remscheid",
    "qs:name_lau":"Stadtteil Remscheid",
    "qs:name_local":"Stadtteil Remscheid",
    "qs:photo_max":1,
    "qs:photo_sum":1,
    "qs:placetype":"Suburb",
    "qs:quad_count":1,
    "qs:woe_adm0":23424829,
    "qs:woe_adm1":2345487,
    "qs:woe_adm2":12597081,
    "qs:woe_lau":28350224,
    "qs:woe_local":28350224,
    "qs:woe_ver":"7.10.0",
    "wd:wordcount":393,
    "wof:lang":[
        "ger"
    ],
    "wof:name":"Rath",
    "wof:placetype":"neighbourhood"
},
  "geometry": {"coordinates":[7.176819,51.181065],"type":"Point"}
}