{
  "type": "Feature",
  "properties": {
    "gn:admin1_code":"14",
    "gn:admin2_code":"0.0",
    "gn:admin3_code":"15084.0",
    "gn:admin4_code":"15084013.0",
    "gn:asciiname":"Pretzsch",
    "gn:country_code":"DE",
    "gn:dem":247,
    "gn:feature_class":"P",
    "gn:feature_code":"PPL",
    "gn:name":"Pretzsch",
    "gn:population":167,
    "gn:timezone":"Europe/Berlin",
    "iso:country":"DE",
    "wof:name":"Pretzsch",
    "wof:placetype":"neighbourhood",
    "wof:population":167
},
  "geometry": {"coordinates":[11.94631,51.09439],"type":"Point"}
}