{
  "type": "Feature",
  "properties": {
    "gn:admin1_code":"14",
    "gn:admin2_code":"0.0",
    "gn:admin3_code":"15084.0",
    "gn:admin4_code":"15084013.0",
    "gn:asciiname":"Pretzsch",
    "gn:country_code":"DE",
    "gn:dem":247,
    "gn:feature_class":"P",
    "gn:feature_code":"PPL",
    "gn:name":"Pretzsch",
    "gn:population":167,
    "gn:timezone":"Europe/Berlin",
    "iso:country":"DE",
    "name:bak_x_preferred":[
        "\u041f\u0440\u0435\u0446\u0448"
    ],
    "name:deu_x_preferred":[
        "Pretzsch"
    ],
    "name:epo_x_preferred":[
        "Pretzsch"
    ],
    "name:fas_x_preferred":[
        "\u067e\u0631\u0686"
    ],
    "name:ita_x_preferred":[
        "Pretzsch"
    ],
    "name:kaz_x_preferred":[
        "\u041f\u0440\u0435\u0446\u0448"
    ],
    "name:kir_x_preferred":[
        "\u041f\u0440\u0435\u0446\u0448"
    ],
    "name:mkd_x_preferred":[
        "\u041f\u0440\u0435\u0446\u0448"
    ],
    "name:nld_x_preferred":[
        "Pretzsch"
    ],
    "name:pol_x_preferred":[
        "Pretzsch"
    ],
    "name:ron_x_preferred":[
        "Pretzsch"
    ],
    "name:rus_x_preferred":[
        "\u041f\u0440\u0435\u0447"
    ],
    "name:uzb_x_preferred":[
        "Pretzsch"
    ],
    "name:vie_x_preferred":[
        "Pretzsch"
    ],
    "wof:name":"Pretzsch",
    "wof:placetype":"neighbourhood",
    "wof:population":167
},
  "geometry": {"coordinates":[11.94631,51.09439],"type":"Point"}
}