{
  "type": "Feature",
  "properties": {
    "gn:admin1_code":"14",
    "gn:admin2_code":"0.0",
    "gn:admin3_code":"15084.0",
    "gn:admin4_code":"15084315.0",
    "gn:asciiname":"Stoesswitz",
    "gn:country_code":"DE",
    "gn:dem":117,
    "gn:feature_class":"P",
    "gn:feature_code":"PPL",
    "gn:name":"St\u00f6\u00dfwitz",
    "gn:population":0,
    "gn:timezone":"Europe/Berlin",
    "iso:country":"DE",
    "wof:name":"Stoesswitz",
    "wof:placetype":"neighbourhood"
},
  "geometry": {"coordinates":[12.09339,51.21974],"type":"Point"}
}