{
  "type": "Feature",
  "properties": {
    "gn:admin1_code":"15.0",
    "gn:admin2_code":"00",
    "gn:admin3_code":"16067.0",
    "gn:admin4_code":"16067083.0",
    "gn:asciiname":"Wipperoda",
    "gn:country_code":"DE",
    "gn:dem":340,
    "gn:feature_class":"P",
    "gn:feature_code":"PPL",
    "gn:name":"Wipperoda",
    "gn:population":0,
    "gn:timezone":"Europe/Berlin",
    "iso:country":"DE",
    "wof:name":"Wipperoda",
    "wof:placetype":"neighbourhood"
},
  "geometry": {"coordinates":[10.66151,50.87221],"type":"Point"}
}