{
  "type": "Feature",
  "properties": {
    "gn:admin1_code":"2",
    "gn:admin2_code":"91.0",
    "gn:admin3_code":"9183.0",
    "gn:admin4_code":"9183132.0",
    "gn:asciiname":"Geiselharting",
    "gn:country_code":"DE",
    "gn:dem":463,
    "gn:feature_class":"P",
    "gn:feature_code":"PPL",
    "gn:name":"Geiselharting",
    "gn:population":0,
    "gn:timezone":"Europe/Berlin",
    "iso:country":"DE",
    "wof:name":"Geiselharting",
    "wof:placetype":"neighbourhood"
},
  "geometry": {"coordinates":[12.41462,48.31516],"type":"Point"}
}