{
  "type": "Feature",
  "properties": {
    "gn:gn_country":"DE",
    "gn:gn_fcode":"PPLA4",
    "gn:gn_pop":985,
    "gn:population":985,
    "iso:country":"DE",
    "name:arm_x_preferred":[
        "\u0555\u0562\u0565\u0580\u0577\u0575\u0578\u0576\u0565\u0563"
    ],
    "name:baq_x_preferred":[
        "Obersch\u00f6negg"
    ],
    "name:chi_x_preferred":[
        "\u4e0a\u820d\u5185\u683c"
    ],
    "name:cze_x_preferred":[
        "Obersch\u00f6negg"
    ],
    "name:dut_x_preferred":[
        "Obersch\u00f6negg"
    ],
    "name:eng_x_preferred":[
        "Obersch\u00f6negg"
    ],
    "name:epo_x_preferred":[
        "Obersch\u00f6negg"
    ],
    "name:fre_x_preferred":[
        "Obersch\u00f6negg"
    ],
    "name:ger_x_preferred":[
        "Obersch\u00f6negg"
    ],
    "name:gsw_x_preferred":[
        "Obersch\u00f6negg"
    ],
    "name:hun_x_preferred":[
        "Obersch\u00f6negg"
    ],
    "name:hye_x_preferred":[
        "\u0555\u0562\u0565\u0580\u0577\u0575\u0578\u0576\u0565\u0563"
    ],
    "name:ita_x_preferred":[
        "Obersch\u00f6negg"
    ],
    "name:kaz_x_preferred":[
        "\u041e\u0431\u0435\u0440\u0448\u0451\u043d\u0435\u0433"
    ],
    "name:kir_x_preferred":[
        "\u041e\u0431\u0435\u0440\u0448\u04e9\u043d\u0435\u0433"
    ],
    "name:lmo_x_preferred":[
        "Obersch\u00f6negg"
    ],
    "name:may_x_preferred":[
        "Obersch\u00f6negg"
    ],
    "name:nan_x_preferred":[
        "Obersch\u00f6negg"
    ],
    "name:per_x_preferred":[
        "\u0627\u0648\u0628\u0631\u0634\u0648\u0646\u06af"
    ],
    "name:pol_x_preferred":[
        "Obersch\u00f6negg"
    ],
    "name:rum_x_preferred":[
        "Obersch\u00f6negg"
    ],
    "name:rus_x_preferred":[
        "\u041e\u0431\u0435\u0440\u0448\u0451\u043d\u0435\u0433"
    ],
    "name:srp_x_preferred":[
        "\u041e\u0431\u0435\u0440\u0448\u0435\u043d\u0435\u0433"
    ],
    "name:ukr_x_preferred":[
        "\u041e\u0431\u0435\u0440\u0448\u0435\u043d\u0435\u0433\u0433"
    ],
    "name:uzb_x_preferred":[
        "Obersch\u00f6negg"
    ],
    "name:vie_x_preferred":[
        "Obersch\u00f6negg"
    ],
    "name:vol_x_preferred":[
        "Obersch\u00f6negg"
    ],
    "name:war_x_preferred":[
        "Obersch\u00f6negg"
    ],
    "name:zho_x_preferred":[
        "\u4e0a\u820d\u5185\u683c"
    ],
    "qs_pg:aaroncc":"DE",
    "qs_pg:gn_country":"DE",
    "qs_pg:gn_fcode":"PPLA4",
    "qs_pg:gn_pop":985,
    "qs_pg:name":"Obersch\u00f6negg",
    "qs_pg:photos_9r":0,
    "qs_pg:photos_sr":0,
    "qs_pg:pop_sr":2,
    "qs_pg:qs_pg_placetype":"locality",
    "wof:name":"Obersch\u00f6negg",
    "wof:placetype":"locality",
    "wof:population":985
},
  "geometry": {"coordinates":[10.29848,48.10846],"type":"Point"}
}