{
  "type": "Feature",
  "properties": {
    "gn:admin1_code":"5",
    "gn:admin2_code":"66.0",
    "gn:admin3_code":"6635.0",
    "gn:admin4_code":"6635015.0",
    "gn:asciiname":"Goldhausen",
    "gn:country_code":"DE",
    "gn:dem":490,
    "gn:feature_class":"P",
    "gn:feature_code":"PPL",
    "gn:name":"Goldhausen",
    "gn:population":0,
    "gn:timezone":"Europe/Berlin",
    "iso:country":"DE",
    "wof:name":"Goldhausen",
    "wof:placetype":"neighbourhood"
},
  "geometry": {"coordinates":[8.81782,51.24709],"type":"Point"}
}