{
  "type": "Feature",
  "properties": {
    "gn:admin1_code":"5",
    "gn:admin2_code":"64.0",
    "gn:admin3_code":"6435.0",
    "gn:admin4_code":"6435025.0",
    "gn:asciiname":"Gundhelm",
    "gn:country_code":"DE",
    "gn:dem":400,
    "gn:feature_class":"P",
    "gn:feature_code":"PPL",
    "gn:name":"Gundhelm",
    "gn:population":0,
    "gn:timezone":"Europe/Berlin",
    "iso:country":"DE",
    "wof:name":"Gundhelm",
    "wof:placetype":"neighbourhood"
},
  "geometry": {"coordinates":[9.63449,50.36503],"type":"Point"}
}