{
  "type": "Feature",
  "properties": {
    "gn:gn_country":"DE",
    "gn:gn_fcode":"PPLA4",
    "gn:gn_pop":79,
    "gn:population":79,
    "iso:country":"DE",
    "name:baq_x_preferred":[
        "Oberstedem"
    ],
    "name:chi_x_preferred":[
        "\u4e0a\u65af\u7279\u5fb7\u59c6"
    ],
    "name:dut_x_preferred":[
        "Oberstedem"
    ],
    "name:eng_x_preferred":[
        "Oberstedem"
    ],
    "name:epo_x_preferred":[
        "Oberstedem"
    ],
    "name:fre_x_preferred":[
        "Oberstedem"
    ],
    "name:ger_x_preferred":[
        "Oberstedem"
    ],
    "name:hun_x_preferred":[
        "Oberstedem"
    ],
    "name:ita_x_preferred":[
        "Oberstedem"
    ],
    "name:jpn_x_preferred":[
        "\u30aa\u30fc\u30d0\u30fc\u30b9\u30c6\u30a3\u30c7\u30e0"
    ],
    "name:may_x_preferred":[
        "Oberstedem"
    ],
    "name:per_x_preferred":[
        "\u0627\u0648\u0628\u0631\u0634\u062a\u062f\u0645"
    ],
    "name:pol_x_preferred":[
        "Oberstedem"
    ],
    "name:por_x_preferred":[
        "Oberstedem"
    ],
    "name:rum_x_preferred":[
        "Oberstedem"
    ],
    "name:rus_x_preferred":[
        "\u041e\u0431\u0435\u0440\u0441\u0442\u0435\u0434\u0435\u043c"
    ],
    "name:srp_x_preferred":[
        "\u041e\u0431\u0435\u0440\u0441\u0442\u0435\u0434\u0435\u043c"
    ],
    "name:ukr_x_preferred":[
        "\u041e\u0431\u0435\u0440\u0441\u0442\u0435\u0434\u0435\u043c"
    ],
    "name:uzb_x_preferred":[
        "Oberstedem"
    ],
    "name:vie_x_preferred":[
        "Oberstedem"
    ],
    "name:vol_x_preferred":[
        "Oberstedem"
    ],
    "name:war_x_preferred":[
        "Oberstedem"
    ],
    "qs_pg:aaroncc":"DE",
    "qs_pg:gn_country":"DE",
    "qs_pg:gn_fcode":"PPLA4",
    "qs_pg:gn_pop":79,
    "qs_pg:name":"Oberstedem",
    "qs_pg:photos_9r":0,
    "qs_pg:photos_sr":0,
    "qs_pg:pop_sr":1,
    "qs_pg:qs_pg_placetype":"locality",
    "wof:name":"Oberstedem",
    "wof:placetype":"locality",
    "wof:population":79
},
  "geometry": {"coordinates":[6.51667,49.93333],"type":"Point"}
}