{
  "type": "Feature",
  "properties": {
    "gn:admin1_code":"10",
    "gn:admin2_code":"0.0",
    "gn:admin3_code":"1051.0",
    "gn:admin4_code":"1051027.0",
    "gn:asciiname":"Elpersbuettelerdonn",
    "gn:country_code":"DE",
    "gn:dem":5,
    "gn:feature_class":"P",
    "gn:feature_code":"PPLL",
    "gn:name":"Elpersb\u00fcttelerdonn",
    "gn:population":0,
    "gn:timezone":"Europe/Berlin",
    "iso:country":"DE",
    "wof:name":"Elpersbuettelerdonn",
    "wof:placetype":"neighbourhood"
},
  "geometry": {"coordinates":[9.0742,54.06469],"type":"Point"}
}