{
  "type": "Feature",
  "properties": {
    "gn:gn_country":"DE",
    "gn:gn_fcode":"PPLA4",
    "gn:gn_pop":507,
    "gn:population":507,
    "iso:country":"DE",
    "name:baq_x_preferred":[
        "Winnemark"
    ],
    "name:chi_x_preferred":[
        "\u7ef4\u5185\u9a6c\u5c14\u514b"
    ],
    "name:dan_x_preferred":[
        "Vindemark"
    ],
    "name:dut_x_preferred":[
        "Winnemark"
    ],
    "name:eng_x_preferred":[
        "Winnemark"
    ],
    "name:epo_x_preferred":[
        "Winnemark"
    ],
    "name:fre_x_preferred":[
        "Winnemark"
    ],
    "name:ger_x_preferred":[
        "Winnemark"
    ],
    "name:hun_x_preferred":[
        "Winnemark"
    ],
    "name:ita_x_preferred":[
        "Winnemark"
    ],
    "name:mac_x_preferred":[
        "\u0412\u0438\u043d\u0435\u043c\u0430\u0440\u043a"
    ],
    "name:may_x_preferred":[
        "Winnemark"
    ],
    "name:per_x_preferred":[
        "\u0648\u06cc\u0646\u0645\u0627\u0631\u06a9"
    ],
    "name:pol_x_preferred":[
        "Winnemark"
    ],
    "name:por_x_preferred":[
        "Winnemark"
    ],
    "name:rum_x_preferred":[
        "Winnemark"
    ],
    "name:rus_x_preferred":[
        "\u0412\u0438\u043d\u043d\u0435\u043c\u0430\u0440\u043a"
    ],
    "name:srp_x_preferred":[
        "\u0412\u0438\u043d\u0435\u043c\u0430\u0440\u043a"
    ],
    "name:tur_x_preferred":[
        "Winnemark"
    ],
    "name:ukr_x_preferred":[
        "\u0412\u0456\u043d\u043d\u0435\u043c\u0430\u0440\u043a"
    ],
    "name:uzb_x_preferred":[
        "Winnemark"
    ],
    "name:vie_x_preferred":[
        "Winnemark"
    ],
    "name:vol_x_preferred":[
        "Winnemark"
    ],
    "name:war_x_preferred":[
        "Winnemark"
    ],
    "qs_pg:aaroncc":"DE",
    "qs_pg:gn_country":"DE",
    "qs_pg:gn_fcode":"PPLA4",
    "qs_pg:gn_pop":507,
    "qs_pg:name":"Winnemark",
    "qs_pg:photos_9r":0,
    "qs_pg:photos_sr":0,
    "qs_pg:pop_sr":2,
    "qs_pg:qs_pg_placetype":"locality",
    "wof:name":"Winnemark",
    "wof:placetype":"locality",
    "wof:population":507
},
  "geometry": {"coordinates":[9.91667,54.61667],"type":"Point"}
}