{
  "type": "Feature",
  "properties": {
    "iso:country":"DE",
    "wof:name":"Hoisten",
    "wof:placetype":"neighbourhood"
},
  "geometry": {"coordinates":[6.69990640878778,51.14310675244799],"type":"Point"}
}