{
  "type": "Feature",
  "properties": {
    "gn:admin1_code":"7",
    "gn:admin2_code":"59.0",
    "gn:admin3_code":"5962.0",
    "gn:admin4_code":"5962040.0",
    "gn:asciiname":"Stucken",
    "gn:country_code":"DE",
    "gn:dem":181,
    "gn:feature_class":"P",
    "gn:feature_code":"PPL",
    "gn:name":"Stucken",
    "gn:population":0,
    "gn:timezone":"Europe/Berlin",
    "iso:country":"DE",
    "wof:name":"Stucken",
    "wof:placetype":"neighbourhood"
},
  "geometry": {"coordinates":[7.75,51.43333],"type":"Point"}
}