{
  "type": "Feature",
  "properties": {
    "gn:admin1_code":"2",
    "gn:admin2_code":"91.0",
    "gn:admin3_code":"9173.0",
    "gn:admin4_code":"9173147.0",
    "gn:asciiname":"Nantwein",
    "gn:cc2":"DE",
    "gn:country_code":"DE",
    "gn:dem":578,
    "gn:feature_class":"P",
    "gn:feature_code":"PPL",
    "gn:name":"Nantwein",
    "gn:population":0,
    "gn:timezone":"Europe/Berlin",
    "iso:country":"DE",
    "name:und_x_variant":[
        "Nantweirn"
    ],
    "wof:name":"Nantwein",
    "wof:placetype":"neighbourhood"
},
  "geometry": {"coordinates":[11.43497,47.91433],"type":"Point"}
}