{
  "type": "Feature",
  "properties": {
    "gn:admin1_code":"5",
    "gn:admin2_code":"64.0",
    "gn:admin3_code":"6437.0",
    "gn:admin4_code":"6437013.0",
    "gn:asciiname":"Ober-Kainsbach",
    "gn:country_code":"DE",
    "gn:dem":283,
    "gn:feature_class":"P",
    "gn:feature_code":"PPL",
    "gn:name":"Ober-Kainsbach",
    "gn:population":0,
    "gn:timezone":"Europe/Berlin",
    "iso:country":"DE",
    "wof:name":"Ober-Kainsbach",
    "wof:placetype":"neighbourhood"
},
  "geometry": {"coordinates":[8.90186,49.72452],"type":"Point"}
}