{
  "type": "Feature",
  "properties": {
    "gn:admin1_code":"2",
    "gn:admin2_code":"97.0",
    "gn:admin3_code":"9773.0",
    "gn:admin4_code":"9773153.0",
    "gn:asciiname":"Obermedlingen",
    "gn:country_code":"DE",
    "gn:dem":444,
    "gn:feature_class":"P",
    "gn:feature_code":"PPL",
    "gn:name":"Obermedlingen",
    "gn:population":0,
    "gn:timezone":"Europe/Berlin",
    "iso:country":"DE",
    "wof:name":"Obermedlingen",
    "wof:placetype":"neighbourhood"
},
  "geometry": {"coordinates":[10.31852,48.56755],"type":"Point"}
}