{
  "type": "Feature",
  "properties": {
    "iso:country":"DE",
    "name:deu_x_preferred":[
        "H\u00fcbben"
    ],
    "wof:name":"Huebbern",
    "wof:placetype":"neighbourhood"
},
  "geometry": {"coordinates":[7.04301159687965,51.1651429111938],"type":"Point"}
}