{
  "type": "Feature",
  "properties": {
    "gn:admin1_code":"7",
    "gn:admin2_code":"59.0",
    "gn:admin3_code":"5974.0",
    "gn:admin4_code":"5974048.0",
    "gn:asciiname":"Fahnen",
    "gn:country_code":"DE",
    "gn:dem":76,
    "gn:feature_class":"P",
    "gn:feature_code":"PPL",
    "gn:name":"Fahnen",
    "gn:population":0,
    "gn:timezone":"Europe/Berlin",
    "iso:country":"DE",
    "wof:name":"Fahnen",
    "wof:placetype":"neighbourhood"
},
  "geometry": {"coordinates":[8.01775,51.60888],"type":"Point"}
}