{
  "type": "Feature",
  "properties": {
    "gn:admin1_code":"1.0",
    "gn:admin2_code":"84.0",
    "gn:admin3_code":"8437.0",
    "gn:admin4_code":"8437086.0",
    "gn:asciiname":"Bachhaupten",
    "gn:country_code":"DE",
    "gn:dem":644,
    "gn:feature_class":"P",
    "gn:feature_code":"PPL",
    "gn:name":"Bachhaupten",
    "gn:population":0,
    "gn:timezone":"Europe/Berlin",
    "iso:country":"DE",
    "wof:name":"Bachhaupten",
    "wof:placetype":"neighbourhood"
},
  "geometry": {"coordinates":[9.42887,47.98246],"type":"Point"}
}