{
  "type": "Feature",
  "properties": {
    "gn:admin1_code":"11",
    "gn:admin2_code":"0.0",
    "gn:admin3_code":"12071.0",
    "gn:admin4_code":"12071057.0",
    "gn:asciiname":"Leuthen",
    "gn:country_code":"DE",
    "gn:dem":81,
    "gn:feature_class":"P",
    "gn:feature_code":"PPL",
    "gn:name":"Leuthen",
    "gn:population":0,
    "gn:timezone":"Europe/Berlin",
    "iso:country":"DE",
    "name:deu_x_preferred":[
        "Leuthen"
    ],
    "name:ukr_x_preferred":[
        "\u041b\u0435\u0439\u0442\u0435\u043d"
    ],
    "name:und_x_variant":[
        "Leuthen-Wintdorf"
    ],
    "name:vie_x_preferred":[
        "Leuthen"
    ],
    "wof:name":"Leuthen",
    "wof:placetype":"neighbourhood"
},
  "geometry": {"coordinates":[14.24715,51.69602],"type":"Point"}
}