{
  "type": "Feature",
  "properties": {
    "gn:country":"DE",
    "gn:fcode":"PPL",
    "gn:population":560,
    "iso:country":"DE",
    "name:bak_x_preferred":[
        "\u042d\u043a\u0441\u0434\u043e\u0440\u0444"
    ],
    "name:ceb_x_preferred":[
        "Exdorf"
    ],
    "name:deu_x_preferred":[
        "Exdorf"
    ],
    "name:epo_x_preferred":[
        "Exdorf"
    ],
    "name:nld_x_preferred":[
        "Exdorf"
    ],
    "name:ron_x_preferred":[
        "Exdorf"
    ],
    "name:rus_x_preferred":[
        "\u042d\u043a\u0441\u0434\u043e\u0440\u0444"
    ],
    "name:uzb_x_preferred":[
        "Exdorf"
    ],
    "name:vol_x_preferred":[
        "Exdorf"
    ],
    "qs_pg:aaroncc":"DE",
    "qs_pg:gn_country":"DE",
    "qs_pg:gn_fcode":"PPL",
    "qs_pg:gn_pop":560,
    "qs_pg:name":"Exdorf",
    "qs_pg:name_adm0":"Deutschland",
    "qs_pg:name_adm1":"Th\u00fcringen",
    "qs_pg:photos_9r":0,
    "qs_pg:photos_sr":0,
    "qs_pg:pop_sr":2,
    "qs_pg:qs_pg_placetype":"locality",
    "qs_pg:qs_pg_placetype_gp":"Town",
    "qs_pg:woe_adm0":23424829,
    "woe:adm0_id":23424829,
    "woe:name_adm0":"Deutschland",
    "woe:name_adm1":"Th\u00fcringen",
    "woe:placetype":"Town",
    "wof:name":"Exdorf",
    "wof:placetype":"neighbourhood",
    "wof:population":560
},
  "geometry": {"coordinates":[10.54241,50.45718],"type":"Point"}
}