{
  "type": "Feature",
  "properties": {
    "gn:admin1_code":"2.0",
    "gn:admin2_code":"97.0",
    "gn:admin3_code":"9778.0",
    "gn:admin4_code":"9778134.0",
    "gn:asciiname":"Aspach",
    "gn:country_code":"DE",
    "gn:dem":577,
    "gn:feature_class":"P",
    "gn:feature_code":"PPL",
    "gn:name":"Aspach",
    "gn:population":0,
    "gn:timezone":"Europe/Berlin",
    "iso:country":"DE",
    "name:als_x_preferred":[
        "Aspach"
    ],
    "name:bre_x_preferred":[
        "Aspach"
    ],
    "name:ceb_x_preferred":[
        "Aspach"
    ],
    "name:ces_x_preferred":[
        "Aspach"
    ],
    "name:deu_x_preferred":[
        "Aspach"
    ],
    "name:epo_x_preferred":[
        "Aspach"
    ],
    "name:est_x_preferred":[
        "Aspach"
    ],
    "name:eus_x_preferred":[
        "Aspach"
    ],
    "name:fra_x_preferred":[
        "Aspach"
    ],
    "name:ita_x_preferred":[
        "Aspach"
    ],
    "name:jpn_x_preferred":[
        "\u30a2\u30b9\u30d1\u30c3\u30cf"
    ],
    "name:ltz_x_preferred":[
        "Aspach"
    ],
    "name:nds_x_preferred":[
        "Aspach"
    ],
    "name:nld_x_preferred":[
        "Aspach"
    ],
    "name:oci_x_preferred":[
        "Aspach"
    ],
    "name:pms_x_preferred":[
        "Aspach"
    ],
    "name:pol_x_preferred":[
        "Aspach"
    ],
    "name:por_x_preferred":[
        "Aspach"
    ],
    "name:rus_x_preferred":[
        "\u0410\u0441\u043f\u0430\u0445"
    ],
    "name:slk_x_preferred":[
        "Aspach"
    ],
    "name:spa_x_preferred":[
        "Aspach"
    ],
    "name:srp_x_preferred":[
        "\u0410\u0441\u043f\u0430\u0445"
    ],
    "name:swe_x_preferred":[
        "Aspach"
    ],
    "name:vol_x_preferred":[
        "Aspach"
    ],
    "wof:name":"Aspach",
    "wof:placetype":"neighbourhood"
},
  "geometry": {"coordinates":[10.50894,48.18165],"type":"Point"}
}