{
  "type": "Feature",
  "properties": {
    "gn:country":"DE",
    "gn:fcode":"PPL",
    "gn:population":855,
    "iso:country":"DE",
    "name:ceb_x_preferred":[
        "Remplin"
    ],
    "name:deu_x_preferred":[
        "Remplin"
    ],
    "name:epo_x_preferred":[
        "Remplin"
    ],
    "name:fas_x_preferred":[
        "\u0631\u0645\u067e\u0644\u06cc\u0646"
    ],
    "name:kaz_x_preferred":[
        "\u0420\u0435\u043c\u043f\u043b\u0438\u043d"
    ],
    "name:kir_x_preferred":[
        "\u0420\u0435\u043c\u043f\u043b\u0438\u043d"
    ],
    "name:nld_x_preferred":[
        "Remplin"
    ],
    "name:ron_x_preferred":[
        "Remplin"
    ],
    "name:rus_x_preferred":[
        "\u0420\u0435\u043c\u043f\u043b\u0438\u043d"
    ],
    "name:spa_x_preferred":[
        "Remplin"
    ],
    "name:uzb_x_preferred":[
        "Remplin"
    ],
    "name:vol_x_preferred":[
        "Remplin"
    ],
    "qs_pg:aaroncc":"DE",
    "qs_pg:gn_country":"DE",
    "qs_pg:gn_fcode":"PPL",
    "qs_pg:gn_pop":855,
    "qs_pg:name":"Remplin",
    "qs_pg:name_adm0":"Deutschland",
    "qs_pg:name_adm1":"Mecklenburg-Vorpommern",
    "qs_pg:photos_9k":1,
    "qs_pg:photos_9r":1,
    "qs_pg:photos_all":10,
    "qs_pg:photos_sr":0,
    "qs_pg:pop_sr":2,
    "qs_pg:qs_pg_placetype":"locality",
    "qs_pg:qs_pg_placetype_gp":"Town",
    "qs_pg:woe_adm0":23424829,
    "woe:adm0_id":23424829,
    "woe:name_adm0":"Deutschland",
    "woe:name_adm1":"Mecklenburg-Vorpommern",
    "woe:placetype":"Town",
    "wof:name":"Remplin",
    "wof:placetype":"neighbourhood",
    "wof:population":855
},
  "geometry": {"coordinates":[12.69705,53.75388],"type":"Point"}
}