{
  "type": "Feature",
  "properties": {
    "gn:admin1_code":"15",
    "gn:admin2_code":"0.0",
    "gn:admin3_code":"16061.0",
    "gn:admin4_code":"16061113.0",
    "gn:asciiname":"Misserode",
    "gn:country_code":"DE",
    "gn:dem":311,
    "gn:feature_class":"P",
    "gn:feature_code":"PPL",
    "gn:name":"Misserode",
    "gn:population":0,
    "gn:timezone":"Europe/Berlin",
    "iso:country":"DE",
    "wof:name":"Misserode",
    "wof:placetype":"neighbourhood"
},
  "geometry": {"coordinates":[10.1342,51.25504],"type":"Point"}
}