{
  "type": "Feature",
  "properties": {
    "gn:admin1_code":"2",
    "gn:admin2_code":"91.0",
    "gn:admin3_code":"9182.0",
    "gn:admin4_code":"9182125.0",
    "gn:asciiname":"Thalhammer",
    "gn:country_code":"DE",
    "gn:dem":752,
    "gn:feature_class":"P",
    "gn:feature_code":"PPL",
    "gn:name":"Thalhammer",
    "gn:population":0,
    "gn:timezone":"Europe/Berlin",
    "iso:country":"DE",
    "wof:name":"Thalhammer",
    "wof:placetype":"neighbourhood"
},
  "geometry": {"coordinates":[11.80987,47.78058],"type":"Point"}
}