{
  "type": "Feature",
  "properties": {
    "gn:admin1_code":"6",
    "gn:admin2_code":"0.0",
    "gn:admin3_code":"3454.0",
    "gn:admin4_code":"3454028.0",
    "gn:asciiname":"Grumsmuehlen",
    "gn:country_code":"DE",
    "gn:dem":26,
    "gn:feature_class":"P",
    "gn:feature_code":"PPL",
    "gn:name":"Grumsm\u00fchlen",
    "gn:population":0,
    "gn:timezone":"Europe/Berlin",
    "iso:country":"DE",
    "wof:name":"Grumsmuehlen",
    "wof:placetype":"neighbourhood"
},
  "geometry": {"coordinates":[7.43472,52.53991],"type":"Point"}
}