{
  "type": "Feature",
  "properties": {
    "gn:admin1_code":"12.0",
    "gn:admin2_code":"0.0",
    "gn:admin3_code":"13074.0",
    "gn:admin4_code":"13074026.0",
    "gn:asciiname":"Barendorf",
    "gn:country_code":"DE",
    "gn:dem":100,
    "gn:feature_class":"P",
    "gn:feature_code":"PPL",
    "gn:name":"Barendorf",
    "gn:population":0,
    "gn:timezone":"Europe/Berlin",
    "iso:country":"DE",
    "name:ceb_x_preferred":[
        "Barendorf"
    ],
    "name:dan_x_preferred":[
        "Barendorf"
    ],
    "name:deu_x_preferred":[
        "Barendorf"
    ],
    "name:epo_x_preferred":[
        "Barendorf"
    ],
    "name:est_x_preferred":[
        "Barendorf"
    ],
    "name:eus_x_preferred":[
        "Barendorf"
    ],
    "name:fas_x_preferred":[
        "\u0628\u0627\u0631\u0646\u062f\u0648\u0631\u0641"
    ],
    "name:fra_x_preferred":[
        "Barendorf"
    ],
    "name:hun_x_preferred":[
        "Barendorf"
    ],
    "name:ita_x_preferred":[
        "Barendorf"
    ],
    "name:kaz_x_preferred":[
        "\u0411\u0430\u0440\u0435\u043d\u0434\u043e\u0440\u0444"
    ],
    "name:kir_x_preferred":[
        "\u0411\u0430\u0440\u0435\u043d\u0434\u043e\u0440\u0444"
    ],
    "name:lat_x_preferred":[
        "Barendorf"
    ],
    "name:msa_x_preferred":[
        "Barendorf"
    ],
    "name:nld_x_preferred":[
        "Barendorf"
    ],
    "name:pol_x_preferred":[
        "Barendorf"
    ],
    "name:por_x_preferred":[
        "Barendorf"
    ],
    "name:ron_x_preferred":[
        "Barendorf"
    ],
    "name:rus_x_preferred":[
        "\u0411\u0430\u0440\u0435\u043d\u0434\u043e\u0440\u0444"
    ],
    "name:spa_x_preferred":[
        "Barendorf"
    ],
    "name:srp_x_preferred":[
        "\u0411\u0430\u0440\u0435\u043d\u0434\u043e\u0440\u0444"
    ],
    "name:ukr_x_preferred":[
        "\u0411\u0430\u0440\u0435\u043d\u0434\u043e\u0440\u0444"
    ],
    "name:uzb_x_preferred":[
        "Barendorf"
    ],
    "name:vie_x_preferred":[
        "Barendorf"
    ],
    "name:vol_x_preferred":[
        "Barendorf"
    ],
    "name:war_x_preferred":[
        "Barendorf"
    ],
    "name:zho_x_preferred":[
        "\u5df4\u4f26\u591a\u592b"
    ],
    "wof:name":"Barendorf",
    "wof:placetype":"neighbourhood"
},
  "geometry": {"coordinates":[11.28371,53.87497],"type":"Point"}
}