{
  "type": "Feature",
  "properties": {
    "gn:country":"DE",
    "gn:fcode":"PPL",
    "gn:population":0,
    "iso:country":"DE",
    "name:als_x_preferred":[
        "F\u00fcrstenau"
    ],
    "name:ceb_x_preferred":[
        "F\u00fcrstenau"
    ],
    "name:deu_x_preferred":[
        "F\u00fcrstenau"
    ],
    "name:epo_x_preferred":[
        "F\u00fcrstenau"
    ],
    "name:eus_x_preferred":[
        "F\u00fcrstenau"
    ],
    "name:fra_x_preferred":[
        "F\u00fcrstenau"
    ],
    "name:ita_x_preferred":[
        "F\u00fcrstenau"
    ],
    "name:nds_x_preferred":[
        "F\u00fcrstenau"
    ],
    "name:nld_x_preferred":[
        "F\u00fcrstenau"
    ],
    "name:pol_x_preferred":[
        "F\u00fcrstenau"
    ],
    "name:rus_x_preferred":[
        "\u0424\u044e\u0440\u0441\u0442\u0435\u043d\u0430\u0443"
    ],
    "name:spa_x_preferred":[
        "F\u00fcrstenau"
    ],
    "name:swe_x_preferred":[
        "F\u00fcrstenau"
    ],
    "name:vol_x_preferred":[
        "F\u00fcrstenau"
    ],
    "qs_pg:aaroncc":"DE",
    "qs_pg:gn_country":"DE",
    "qs_pg:gn_fcode":"PPL",
    "qs_pg:gn_pop":0,
    "qs_pg:name":"F\u00fcrstenau",
    "qs_pg:name_adm0":"Deutschland",
    "qs_pg:name_adm1":"Nordrhein-Westfalen",
    "qs_pg:photos":25,
    "qs_pg:photos_1k":5,
    "qs_pg:photos_9k":1,
    "qs_pg:photos_9r":1,
    "qs_pg:photos_all":25,
    "qs_pg:photos_sr":1,
    "qs_pg:pop_sr":0,
    "qs_pg:qs_pg_placetype":"locality",
    "qs_pg:qs_pg_placetype_gp":"Town",
    "qs_pg:woe_adm0":23424829,
    "woe:adm0_id":23424829,
    "woe:name_adm0":"Deutschland",
    "woe:name_adm1":"Nordrhein-Westfalen",
    "woe:placetype":"Town",
    "wof:name":"F\u00fcrstenau",
    "wof:placetype":"neighbourhood"
},
  "geometry": {"coordinates":[9.31864,51.83026],"type":"Point"}
}