{
  "type": "Feature",
  "properties": {
    "gn:admin1_code":"8",
    "gn:admin2_code":"0.0",
    "gn:admin3_code":"7232.0",
    "gn:admin4_code":"7232113.0",
    "gn:asciiname":"Bruderholz",
    "gn:country_code":"DE",
    "gn:dem":486,
    "gn:feature_class":"P",
    "gn:feature_code":"PPL",
    "gn:name":"Bruderholz",
    "gn:population":0,
    "gn:timezone":"Europe/Berlin",
    "iso:country":"DE",
    "wof:name":"Bruderholz",
    "wof:placetype":"neighbourhood"
},
  "geometry": {"coordinates":[6.58972,50.08642],"type":"Point"}
}