{
  "type": "Feature",
  "properties": {
    "gn:admin1_code":"6",
    "gn:admin2_code":"0.0",
    "gn:admin3_code":"3352.0",
    "gn:admin4_code":"3352036.0",
    "gn:asciiname":"Varrel",
    "gn:country_code":"DE",
    "gn:dem":8,
    "gn:feature_class":"P",
    "gn:feature_code":"PPL",
    "gn:name":"Varrel",
    "gn:population":0,
    "gn:timezone":"Europe/Berlin",
    "iso:country":"DE",
    "name:dan_x_preferred":[
        "Varrel"
    ],
    "name:deu_x_preferred":[
        "Varrel"
    ],
    "name:epo_x_preferred":[
        "Varrel"
    ],
    "name:est_x_preferred":[
        "Varrel"
    ],
    "name:eus_x_preferred":[
        "Varrel"
    ],
    "name:fra_x_preferred":[
        "Varrel"
    ],
    "name:hun_x_preferred":[
        "Varrel"
    ],
    "name:hye_x_preferred":[
        "\u0556\u0561\u0580\u0565\u056c"
    ],
    "name:ita_x_preferred":[
        "Varrel"
    ],
    "name:kaz_x_preferred":[
        "\u0424\u0430\u0440\u0440\u0435\u043b\u044c"
    ],
    "name:kir_x_preferred":[
        "\u0424\u0430\u0440\u0440\u0435\u043b\u044c"
    ],
    "name:msa_x_preferred":[
        "Varrel"
    ],
    "name:nds_x_preferred":[
        "Varrel"
    ],
    "name:nld_x_preferred":[
        "Varrel"
    ],
    "name:pol_x_preferred":[
        "Varrel"
    ],
    "name:por_x_preferred":[
        "Varrel"
    ],
    "name:ron_x_preferred":[
        "Varrel"
    ],
    "name:rus_x_preferred":[
        "\u0424\u0430\u0440\u0440\u0435\u043b\u044c"
    ],
    "name:spa_x_preferred":[
        "Varrel"
    ],
    "name:srp_x_preferred":[
        "\u0424\u0430\u0440\u0435\u043b"
    ],
    "name:ukr_x_preferred":[
        "\u0424\u0430\u0440\u0440\u0435\u043b\u044c"
    ],
    "name:uzb_x_preferred":[
        "Varrel"
    ],
    "name:vie_x_preferred":[
        "Varrel"
    ],
    "name:vol_x_preferred":[
        "Varrel"
    ],
    "name:war_x_preferred":[
        "Varrel"
    ],
    "name:zho_x_preferred":[
        "\u6cd5\u52d2\u5c14"
    ],
    "wof:name":"Varrel",
    "wof:placetype":"neighbourhood"
},
  "geometry": {"coordinates":[9.0546,53.67779],"type":"Point"}
}