{
  "type": "Feature",
  "properties": {
    "iso:country":"DE",
    "name:ara_x_preferred":[
        "\u0633\u064a\u062a\u0627\u0631\u062f"
    ],
    "name:aze_x_preferred":[
        "Sittard"
    ],
    "name:cat_x_preferred":[
        "Sittard"
    ],
    "name:ceb_x_preferred":[
        "Sittard"
    ],
    "name:deu_x_preferred":[
        "Sittard"
    ],
    "name:epo_x_preferred":[
        "Sittard"
    ],
    "name:fas_x_preferred":[
        "\u0633\u06cc\u062a\u0627\u0631\u062f"
    ],
    "name:fra_x_preferred":[
        "Sittard"
    ],
    "name:hrv_x_preferred":[
        "Sittard"
    ],
    "name:ita_x_preferred":[
        "Sittard"
    ],
    "name:kor_x_preferred":[
        "\uc2dc\ud0c0\ub974\ud2b8"
    ],
    "name:lim_x_preferred":[
        "Zittert"
    ],
    "name:lit_x_preferred":[
        "Sitardas"
    ],
    "name:nds_x_preferred":[
        "Sittard"
    ],
    "name:nld_x_preferred":[
        "Sittard"
    ],
    "name:nor_x_preferred":[
        "Sittard"
    ],
    "name:pol_x_preferred":[
        "Sittard"
    ],
    "name:spa_x_preferred":[
        "Sittard"
    ],
    "name:sqi_x_preferred":[
        "Sittard"
    ],
    "name:swe_x_preferred":[
        "Sittard"
    ],
    "name:szl_x_preferred":[
        "Sittard"
    ],
    "name:tur_x_preferred":[
        "Sittard"
    ],
    "name:ukr_x_preferred":[
        "\u0421\u0456\u0442\u0442\u0430\u0440\u0434"
    ],
    "name:zho_x_preferred":[
        "\u932b\u5854\u5fb7"
    ],
    "wof:name":"Sittard",
    "wof:placetype":"neighbourhood"
},
  "geometry": {"coordinates":[6.35651195652936,51.13664450917297],"type":"Point"}
}