{
  "type": "Feature",
  "properties": {
    "iso:country":"DE",
    "wof:name":"Sittard",
    "wof:placetype":"neighbourhood"
},
  "geometry": {"coordinates":[6.35651195652936,51.13664450917297],"type":"Point"}
}