{
  "type": "Feature",
  "properties": {
    "gn:gn_country":"DE",
    "gn:gn_fcode":"PPLA4",
    "gn:gn_pop":333,
    "gn:population":333,
    "iso:country":"DE",
    "name:baq_x_preferred":[
        "Eisenschmitt"
    ],
    "name:chi_x_preferred":[
        "\u827e\u68ee\u65bd\u7c73\u7279"
    ],
    "name:dut_x_preferred":[
        "Eisenschmitt"
    ],
    "name:eng_x_preferred":[
        "Eisenschmitt"
    ],
    "name:epo_x_preferred":[
        "Eisenschmitt"
    ],
    "name:fre_x_preferred":[
        "Eisenschmitt"
    ],
    "name:ger_x_preferred":[
        "Eisenschmitt"
    ],
    "name:hun_x_preferred":[
        "Eisenschmitt"
    ],
    "name:ita_x_preferred":[
        "Eisenschmitt"
    ],
    "name:jpn_x_preferred":[
        "\u30a2\u30a4\u30bc\u30f3\u30b7\u30e5\u30df\u30c3\u30c8"
    ],
    "name:kaz_x_preferred":[
        "\u0410\u0439\u0437\u0435\u043d\u0448\u043c\u0438\u0442"
    ],
    "name:kir_x_preferred":[
        "\u0410\u0439\u0437\u0435\u043d\u0448\u043c\u0438\u0442"
    ],
    "name:may_x_preferred":[
        "Eisenschmitt"
    ],
    "name:per_x_preferred":[
        "\u0627\u06cc\u0632\u0646\u0634\u0645\u06cc\u062a"
    ],
    "name:pol_x_preferred":[
        "Eisenschmitt"
    ],
    "name:por_x_preferred":[
        "Eisenschmitt"
    ],
    "name:rum_x_preferred":[
        "Eisenschmitt"
    ],
    "name:rus_x_preferred":[
        "\u0410\u0439\u0437\u0435\u043d\u0448\u043c\u0438\u0442"
    ],
    "name:srp_x_preferred":[
        "\u0410\u0458\u0437\u0435\u043d\u0448\u043c\u0438\u0442"
    ],
    "name:ukr_x_preferred":[
        "\u0410\u0439\u0437\u0435\u043d\u0448\u043c\u0456\u0442\u0442"
    ],
    "name:uzb_x_preferred":[
        "Eisenschmitt"
    ],
    "name:vie_x_preferred":[
        "Eisenschmitt"
    ],
    "name:vol_x_preferred":[
        "Eisenschmitt"
    ],
    "name:war_x_preferred":[
        "Eisenschmitt"
    ],
    "qs_pg:aaroncc":"DE",
    "qs_pg:gn_country":"DE",
    "qs_pg:gn_fcode":"PPLA4",
    "qs_pg:gn_pop":333,
    "qs_pg:name":"Eisenschmitt",
    "qs_pg:photos_9r":0,
    "qs_pg:photos_sr":0,
    "qs_pg:pop_sr":2,
    "qs_pg:qs_pg_placetype":"locality",
    "wof:name":"Eisenschmitt",
    "wof:placetype":"locality",
    "wof:population":333
},
  "geometry": {"coordinates":[6.71667,50.05],"type":"Point"}
}