{
  "type": "Feature",
  "properties": {
    "gn:admin1_code":"6",
    "gn:admin2_code":"0.0",
    "gn:admin3_code":"3359.0",
    "gn:admin4_code":"3359005.0",
    "gn:asciiname":"Stuehkamp",
    "gn:country_code":"DE",
    "gn:dem":32,
    "gn:feature_class":"P",
    "gn:feature_code":"PPL",
    "gn:name":"St\u00fchkamp",
    "gn:population":0,
    "gn:timezone":"Europe/Berlin",
    "iso:country":"DE",
    "wof:name":"Stuehkamp",
    "wof:placetype":"neighbourhood"
},
  "geometry": {"coordinates":[9.4429,53.46632],"type":"Point"}
}