{
  "type": "Feature",
  "properties": {
    "gn:admin1_code":"5.0",
    "gn:admin2_code":"064",
    "gn:admin3_code":"6439.0",
    "gn:admin4_code":"6439015.0",
    "gn:asciiname":"Wingsbach",
    "gn:country_code":"DE",
    "gn:dem":392,
    "gn:feature_class":"P",
    "gn:feature_code":"PPL",
    "gn:name":"Wingsbach",
    "gn:population":0,
    "gn:timezone":"Europe/Berlin",
    "iso:country":"DE",
    "wof:name":"Wingsbach",
    "wof:placetype":"neighbourhood"
},
  "geometry": {"coordinates":[8.14854,50.16618],"type":"Point"}
}