{
  "type": "Feature",
  "properties": {
    "gn:admin1_code":"6.0",
    "gn:admin2_code":"0.0",
    "gn:admin3_code":"3358.0",
    "gn:admin4_code":"3358009.0",
    "gn:asciiname":"Bosse",
    "gn:country_code":"DE",
    "gn:dem":20,
    "gn:feature_class":"P",
    "gn:feature_code":"PPL",
    "gn:name":"Bosse",
    "gn:population":0,
    "gn:timezone":"Europe/Berlin",
    "iso:country":"DE",
    "name:deu_x_preferred":[
        "Bosse"
    ],
    "name:fra_x_preferred":[
        "Bosse"
    ],
    "name:ita_x_preferred":[
        "Bosse"
    ],
    "name:nds_x_preferred":[
        "Bosse"
    ],
    "name:rus_x_preferred":[
        "\u0411\u043e\u0441\u0441\u0435"
    ],
    "name:swe_x_preferred":[
        "Bosse"
    ],
    "name:ukr_x_preferred":[
        "\u0411\u043e\u0441\u0441\u0435"
    ],
    "wof:name":"Bosse",
    "wof:placetype":"neighbourhood"
},
  "geometry": {"coordinates":[9.45356,52.76341],"type":"Point"}
}