{
  "type": "Feature",
  "properties": {
    "gn:admin1_code":"7",
    "gn:admin2_code":"51.0",
    "gn:admin3_code":"5170.0",
    "gn:admin4_code":"5170032.0",
    "gn:asciiname":"Wallach",
    "gn:country_code":"DE",
    "gn:dem":23,
    "gn:feature_class":"P",
    "gn:feature_code":"PPL",
    "gn:name":"Wallach",
    "gn:population":0,
    "gn:timezone":"Europe/Berlin",
    "iso:country":"DE",
    "wof:name":"Wallach",
    "wof:placetype":"neighbourhood"
},
  "geometry": {"coordinates":[6.57227,51.59612],"type":"Point"}
}