{
  "type": "Feature",
  "properties": {
    "gn:admin1_code":"1",
    "gn:admin2_code":"83.0",
    "gn:admin3_code":"8317.0",
    "gn:admin4_code":"8317089.0",
    "gn:asciiname":"Vordere Allmend",
    "gn:country_code":"DE",
    "gn:dem":240,
    "gn:feature_class":"P",
    "gn:feature_code":"PPLL",
    "gn:name":"Vordere Allmend",
    "gn:population":0,
    "gn:timezone":"Europe/Berlin",
    "iso:country":"DE",
    "wof:name":"Vordere Allmend",
    "wof:placetype":"neighbourhood"
},
  "geometry": {"coordinates":[8.09128,48.50982],"type":"Point"}
}