{
  "type": "Feature",
  "properties": {
    "gn:admin1_code":"6",
    "gn:admin2_code":"0.0",
    "gn:admin3_code":"3462.0",
    "gn:admin4_code":"3462005.0",
    "gn:asciiname":"Etzel",
    "gn:country_code":"DE",
    "gn:dem":2,
    "gn:feature_class":"P",
    "gn:feature_code":"PPL",
    "gn:name":"Etzel",
    "gn:population":0,
    "gn:timezone":"Europe/Berlin",
    "iso:country":"DE",
    "name:deu_x_preferred":[
        "Etzel"
    ],
    "name:fra_x_preferred":[
        "Etzel"
    ],
    "name:ita_x_preferred":[
        "Etzel"
    ],
    "name:nds_x_preferred":[
        "Etzel"
    ],
    "name:nld_x_preferred":[
        "Etzel"
    ],
    "name:pol_x_preferred":[
        "Etzel"
    ],
    "name:rus_x_preferred":[
        "\u042d\u0442\u0446\u0435\u043b\u044c"
    ],
    "name:swe_x_preferred":[
        "Etzel"
    ],
    "wof:name":"Etzel",
    "wof:placetype":"neighbourhood"
},
  "geometry": {"coordinates":[7.90305,53.46623],"type":"Point"}
}