{
  "type": "Feature",
  "properties": {
    "iso:country":"DE",
    "name:ceb_x_preferred":[
        "Weiden"
    ],
    "name:ces_x_preferred":[
        "Weiden"
    ],
    "name:deu_x_preferred":[
        "Weiden"
    ],
    "name:epo_x_preferred":[
        "Weiden"
    ],
    "name:fra_x_preferred":[
        "Weiden"
    ],
    "name:ita_x_preferred":[
        "Weiden"
    ],
    "name:nld_x_preferred":[
        "Weiden"
    ],
    "name:pol_x_preferred":[
        "Weiden"
    ],
    "name:rus_x_preferred":[
        "\u0412\u0430\u0439\u0434\u0435\u043d"
    ],
    "name:srp_x_preferred":[
        "\u0412\u0430\u0458\u0434\u0435\u043d"
    ],
    "name:swe_x_preferred":[
        "Weiden"
    ],
    "wof:name":"Weiden",
    "wof:placetype":"neighbourhood"
},
  "geometry": {"coordinates":[6.83774721646114,50.93817381089153],"type":"Point"}
}