{
  "type": "Feature",
  "properties": {
    "gn:admin1_code":"2.0",
    "gn:admin2_code":"91.0",
    "gn:admin3_code":"9173.0",
    "gn:admin4_code":"9173134.0",
    "gn:asciiname":"Boschhof",
    "gn:country_code":"DE",
    "gn:dem":587,
    "gn:feature_class":"P",
    "gn:feature_code":"PPL",
    "gn:name":"Boschhof",
    "gn:population":0,
    "gn:timezone":"Europe/Berlin",
    "iso:country":"DE",
    "wof:name":"Boschhof",
    "wof:placetype":"neighbourhood"
},
  "geometry": {"coordinates":[11.41127,47.80976],"type":"Point"}
}