{
  "type": "Feature",
  "properties": {
    "gn:admin1_code":"11.0",
    "gn:admin2_code":"0.0",
    "gn:admin3_code":"12065.0",
    "gn:admin4_code":"12065084.0",
    "gn:asciiname":"Pian",
    "gn:country_code":"DE",
    "gn:dem":55,
    "gn:feature_class":"P",
    "gn:feature_code":"PPL",
    "gn:name":"Pian",
    "gn:population":0,
    "gn:timezone":"Europe/Berlin",
    "iso:country":"DE",
    "name:ceb_x_preferred":[
        "Pian"
    ],
    "name:deu_x_preferred":[
        "Pian"
    ],
    "name:fra_x_preferred":[
        "Pian"
    ],
    "name:ita_x_preferred":[
        "Pian"
    ],
    "name:por_x_preferred":[
        "Pian"
    ],
    "name:spa_x_preferred":[
        "Pian"
    ],
    "name:srp_x_preferred":[
        "Pjan"
    ],
    "name:swe_x_preferred":[
        "Pian"
    ],
    "wof:name":"Pian",
    "wof:placetype":"neighbourhood"
},
  "geometry": {"coordinates":[13.24408,53.18568000000001],"type":"Point"}
}