{
  "type": "Feature",
  "properties": {
    "gn:admin1_code":"2",
    "gn:admin2_code":"94.0",
    "gn:admin3_code":"9479.0",
    "gn:admin4_code":"9479152.0",
    "gn:asciiname":"Hausellohe",
    "gn:country_code":"DE",
    "gn:dem":581,
    "gn:feature_class":"P",
    "gn:feature_code":"PPL",
    "gn:name":"H\u00e4usellohe",
    "gn:population":0,
    "gn:timezone":"Europe/Berlin",
    "iso:country":"DE",
    "wof:name":"Hausellohe",
    "wof:placetype":"neighbourhood"
},
  "geometry": {"coordinates":[12.17911,50.15452],"type":"Point"}
}