{
  "type": "Feature",
  "properties": {
    "gn:admin1_code":"8",
    "gn:admin2_code":"0.0",
    "gn:admin3_code":"7133.0",
    "gn:admin4_code":"7133046.0",
    "gn:asciiname":"Sankt Johannisberg",
    "gn:country_code":"DE",
    "gn:dem":279,
    "gn:feature_class":"P",
    "gn:feature_code":"PPL",
    "gn:name":"Sankt Johannisberg",
    "gn:population":0,
    "gn:timezone":"Europe/Berlin",
    "iso:country":"DE",
    "wof:name":"Sankt Johannisberg",
    "wof:placetype":"neighbourhood"
},
  "geometry": {"coordinates":[7.49643,49.79825],"type":"Point"}
}