{
  "type": "Feature",
  "properties": {
    "iso:country":"DE",
    "wof:name":"Beuel-Ost",
    "wof:placetype":"neighbourhood"
},
  "geometry": {"coordinates":[7.13548824196223,50.73910571230888],"type":"Point"}
}