{
  "type": "Feature",
  "properties": {
    "gn:admin1_code":"2",
    "gn:admin2_code":"97.0",
    "gn:admin3_code":"9772.0",
    "gn:admin4_code":"9772115.0",
    "gn:asciiname":"Hennhofen",
    "gn:country_code":"DE",
    "gn:dem":444,
    "gn:feature_class":"P",
    "gn:feature_code":"PPL",
    "gn:name":"Hennhofen",
    "gn:population":0,
    "gn:timezone":"Europe/Berlin",
    "iso:country":"DE",
    "wof:name":"Hennhofen",
    "wof:placetype":"neighbourhood"
},
  "geometry": {"coordinates":[10.58773,48.47406],"type":"Point"}
}