{
  "type": "Feature",
  "properties": {
    "gn:admin1_code":"10",
    "gn:admin2_code":"0.0",
    "gn:admin3_code":"1058.0",
    "gn:admin4_code":"1058121.0",
    "gn:asciiname":"Stubbendorf",
    "gn:country_code":"DE",
    "gn:dem":21,
    "gn:feature_class":"P",
    "gn:feature_code":"PPL",
    "gn:name":"Stubbendorf",
    "gn:population":0,
    "gn:timezone":"Europe/Berlin",
    "iso:country":"DE",
    "name:ceb_x_preferred":[
        "Stubbendorf"
    ],
    "name:deu_x_preferred":[
        "Stubbendorf"
    ],
    "name:epo_x_preferred":[
        "Stubbendorf"
    ],
    "name:fas_x_preferred":[
        "\u0634\u062a\u0648\u0628\u0646\u062f\u0648\u0631\u0641"
    ],
    "name:fra_x_preferred":[
        "Stubbendorf"
    ],
    "name:hun_x_preferred":[
        "Stubbendorf"
    ],
    "name:ita_x_preferred":[
        "Stubbendorf"
    ],
    "name:mkd_x_preferred":[
        "\u0428\u0442\u0443\u0431\u0435\u043d\u0434\u043e\u0440\u0444"
    ],
    "name:msa_x_preferred":[
        "Stubbendorf"
    ],
    "name:nld_x_preferred":[
        "Stubbendorf"
    ],
    "name:pol_x_preferred":[
        "Stubbendorf"
    ],
    "name:ron_x_preferred":[
        "Stubbendorf"
    ],
    "name:rus_x_preferred":[
        "\u0428\u0442\u0443\u0431\u0431\u0435\u043d\u0434\u043e\u0440\u0444"
    ],
    "name:spa_x_preferred":[
        "Stubbendorf"
    ],
    "name:srp_x_preferred":[
        "\u0428\u0442\u0443\u0431\u0435\u043d\u0434\u043e\u0440\u0444"
    ],
    "name:ukr_x_preferred":[
        "\u0428\u0442\u0443\u0431\u0431\u0435\u043d\u0434\u043e\u0440\u0444"
    ],
    "name:uzb_x_preferred":[
        "Stubbendorf"
    ],
    "name:vie_x_preferred":[
        "Stubbendorf"
    ],
    "name:vol_x_preferred":[
        "Stubbendorf"
    ],
    "name:war_x_preferred":[
        "Stubbendorf"
    ],
    "name:zho_x_preferred":[
        "\u65bd\u56fe\u672c\u591a\u592b"
    ],
    "wof:name":"Stubbendorf",
    "wof:placetype":"neighbourhood"
},
  "geometry": {"coordinates":[10.01974,54.44371999999999],"type":"Point"}
}