{
  "type": "Feature",
  "properties": {
    "gn:admin1_code":"15",
    "gn:admin2_code":"0.0",
    "gn:admin3_code":"16063.0",
    "gn:admin4_code":"16063066.0",
    "gn:asciiname":"Heiligenstein",
    "gn:country_code":"DE",
    "gn:dem":327,
    "gn:feature_class":"P",
    "gn:feature_code":"PPL",
    "gn:name":"Heiligenstein",
    "gn:population":0,
    "gn:timezone":"Europe/Berlin",
    "iso:country":"DE",
    "name:als_x_preferred":[
        "Heiligenstein"
    ],
    "name:ara_x_preferred":[
        "\u0647\u064a\u0644\u064a\u063a\u064a\u0646\u0633\u062a\u064a\u0646"
    ],
    "name:azb_x_preferred":[
        "\u0647\u0627\u06cc\u0644\u06cc\u0642\u0646\u0634\u062a\u0627\u06cc\u0646"
    ],
    "name:cat_x_preferred":[
        "Heiligenstein"
    ],
    "name:ceb_x_preferred":[
        "Heiligenstein"
    ],
    "name:deu_x_preferred":[
        "Heiligenstein"
    ],
    "name:eus_x_preferred":[
        "Heiligenstein"
    ],
    "name:fas_x_preferred":[
        "\u0647\u0627\u06cc\u0644\u06cc\u06af\u0646\u0634\u062a\u0627\u06cc\u0646"
    ],
    "name:fin_x_preferred":[
        "Heiligenstein"
    ],
    "name:fra_x_preferred":[
        "Heiligenstein"
    ],
    "name:hun_x_preferred":[
        "Heiligenstein"
    ],
    "name:hye_x_preferred":[
        "\u0531\u0575\u056c\u056b\u0563\u0565\u0576\u057d\u057f\u0565\u0576"
    ],
    "name:ita_x_preferred":[
        "Heiligenstein"
    ],
    "name:kaz_x_preferred":[
        "\u0410\u0439\u043b\u0438\u0433\u0435\u043d\u0441\u0442\u0435\u043d"
    ],
    "name:lat_x_preferred":[
        "Heiligenstein"
    ],
    "name:mlg_x_preferred":[
        "Heiligenstein"
    ],
    "name:msa_x_preferred":[
        "Heiligenstein"
    ],
    "name:nld_x_preferred":[
        "Heiligenstein"
    ],
    "name:oci_x_preferred":[
        "Heiligenstein"
    ],
    "name:pfl_x_preferred":[
        "Heiligenstein"
    ],
    "name:pms_x_preferred":[
        "Heiligenstein"
    ],
    "name:pol_x_preferred":[
        "Heiligenstein"
    ],
    "name:por_x_preferred":[
        "Heiligenstein"
    ],
    "name:ron_x_preferred":[
        "Heiligenstein"
    ],
    "name:rus_x_preferred":[
        "\u0410\u0439\u043b\u0438\u0433\u0435\u043d\u0441\u0442\u0435\u043d"
    ],
    "name:slk_x_preferred":[
        "Heiligenstein"
    ],
    "name:slv_x_preferred":[
        "Heiligenstein"
    ],
    "name:spa_x_preferred":[
        "Heiligenstein"
    ],
    "name:srp_x_preferred":[
        "\u0425\u0430\u0458\u043b\u0438\u0433\u0435\u043d\u0448\u0442\u0430\u0458\u043d"
    ],
    "name:swe_x_preferred":[
        "Heiligenstein"
    ],
    "name:ukr_x_preferred":[
        "\u0410\u0439\u043b\u0456\u0433\u0435\u043d\u0441\u0442\u0435\u043d"
    ],
    "name:uzb_x_preferred":[
        "Heiligenstein"
    ],
    "name:vie_x_preferred":[
        "Heiligenstein"
    ],
    "name:vol_x_preferred":[
        "Heiligenstein"
    ],
    "name:war_x_preferred":[
        "Heiligenstein"
    ],
    "name:zho_x_preferred":[
        "\u827e\u5229\u6839\u4ec0\u6cf0\u56e0"
    ],
    "wof:name":"Heiligenstein",
    "wof:placetype":"neighbourhood"
},
  "geometry": {"coordinates":[10.38905,50.91384],"type":"Point"}
}