{
  "type": "Feature",
  "properties": {
    "gn:admin1_code":"13",
    "gn:admin2_code":"0.0",
    "gn:admin3_code":"14628.0",
    "gn:admin4_code":"14628380.0",
    "gn:asciiname":"Oberhelmsdorf",
    "gn:country_code":"DE",
    "gn:dem":236,
    "gn:feature_class":"P",
    "gn:feature_code":"PPL",
    "gn:name":"Oberhelmsdorf",
    "gn:population":0,
    "gn:timezone":"Europe/Berlin",
    "iso:country":"DE",
    "wof:name":"Oberhelmsdorf",
    "wof:placetype":"neighbourhood"
},
  "geometry": {"coordinates":[14.04284,51.04161],"type":"Point"}
}