{
  "type": "Feature",
  "properties": {
    "gn:admin1_code":"6",
    "gn:admin2_code":"0.0",
    "gn:admin3_code":"3462.0",
    "gn:admin4_code":"3462019.0",
    "gn:asciiname":"Leerhafe",
    "gn:country_code":"DE",
    "gn:dem":5,
    "gn:feature_class":"P",
    "gn:feature_code":"PPL",
    "gn:name":"Leerhafe",
    "gn:population":0,
    "gn:timezone":"Europe/Berlin",
    "iso:country":"DE",
    "wof:name":"Leerhafe",
    "wof:placetype":"neighbourhood"
},
  "geometry": {"coordinates":[7.78103,53.5289],"type":"Point"}
}