{
  "type": "Feature",
  "properties": {
    "gn:admin1_code":"6",
    "gn:admin2_code":"0.0",
    "gn:admin3_code":"3154.0",
    "gn:admin4_code":"3154013.0",
    "gn:asciiname":"Glentorf",
    "gn:cc2":"DE",
    "gn:country_code":"DE",
    "gn:dem":100,
    "gn:feature_class":"P",
    "gn:feature_code":"PPL",
    "gn:name":"Glentorf",
    "gn:population":0,
    "gn:timezone":"Europe/Berlin",
    "iso:country":"DE",
    "name:und_x_variant":[
        "Glendorf",
        "Glentorf"
    ],
    "wof:name":"Glentorf",
    "wof:placetype":"neighbourhood"
},
  "geometry": {"coordinates":[10.80179,52.32674],"type":"Point"}
}