{
  "type": "Feature",
  "properties": {
    "gn:admin1_code":"5",
    "gn:admin2_code":"66.0",
    "gn:admin3_code":"6631.0",
    "gn:admin4_code":"6631010.0",
    "gn:asciiname":"Wachtkueppel",
    "gn:country_code":"DE",
    "gn:dem":646,
    "gn:feature_class":"P",
    "gn:feature_code":"PPL",
    "gn:name":"Wachtk\u00fcppel",
    "gn:population":0,
    "gn:timezone":"Europe/Berlin",
    "iso:country":"DE",
    "wof:name":"Wachtkueppel",
    "wof:placetype":"neighbourhood"
},
  "geometry": {"coordinates":[9.88764,50.46887],"type":"Point"}
}