{
  "type": "Feature",
  "properties": {
    "gn:admin1_code":"11",
    "gn:admin2_code":"0.0",
    "gn:admin3_code":"12072.0",
    "gn:admin4_code":"12072312.0",
    "gn:asciiname":"Gottow",
    "gn:country_code":"DE",
    "gn:dem":49,
    "gn:feature_class":"P",
    "gn:feature_code":"PPL",
    "gn:name":"Gottow",
    "gn:population":0,
    "gn:timezone":"Europe/Berlin",
    "iso:country":"DE",
    "wof:name":"Gottow",
    "wof:placetype":"neighbourhood"
},
  "geometry": {"coordinates":[13.26535,52.0918],"type":"Point"}
}