{
  "type": "Feature",
  "properties": {
    "gn:admin1_code":"7",
    "gn:admin2_code":"59.0",
    "gn:admin3_code":"5978.0",
    "gn:admin4_code":"5978008.0",
    "gn:asciiname":"Osterboenen",
    "gn:country_code":"DE",
    "gn:dem":83,
    "gn:feature_class":"P",
    "gn:feature_code":"PPL",
    "gn:name":"Osterb\u00f6nen",
    "gn:population":0,
    "gn:timezone":"Europe/Berlin",
    "iso:country":"DE",
    "wof:name":"Osterboenen",
    "wof:placetype":"neighbourhood"
},
  "geometry": {"coordinates":[7.8027,51.61226],"type":"Point"}
}