{
  "type": "Feature",
  "properties": {
    "gn:admin1_code":"2.0",
    "gn:admin2_code":"91.0",
    "gn:admin3_code":"9176.0",
    "gn:admin4_code":"9176161.0",
    "gn:asciiname":"Appertshofen",
    "gn:country_code":"DE",
    "gn:dem":485,
    "gn:feature_class":"P",
    "gn:feature_code":"PPL",
    "gn:name":"Appertshofen",
    "gn:population":0,
    "gn:timezone":"Europe/Berlin",
    "iso:country":"DE",
    "wof:name":"Appertshofen",
    "wof:placetype":"neighbourhood"
},
  "geometry": {"coordinates":[11.46231,48.87235],"type":"Point"}
}