{
  "type": "Feature",
  "properties": {
    "gn:admin1_code":"15",
    "gn:admin2_code":"0.0",
    "gn:admin3_code":"16076.0",
    "gn:admin4_code":"16076008.0",
    "gn:asciiname":"Groitschen",
    "gn:country_code":"DE",
    "gn:dem":246,
    "gn:feature_class":"P",
    "gn:feature_code":"PPL",
    "gn:name":"Groitschen",
    "gn:population":0,
    "gn:timezone":"Europe/Berlin",
    "iso:country":"DE",
    "wof:name":"Groitschen",
    "wof:placetype":"neighbourhood"
},
  "geometry": {"coordinates":[12.16918,50.92254000000001],"type":"Point"}
}