{
  "type": "Feature",
  "properties": {
    "gn:admin1_code":"1",
    "gn:admin2_code":"83.0",
    "gn:admin3_code":"8335.0",
    "gn:admin4_code":"8335035.0",
    "gn:asciiname":"Dietlishof",
    "gn:country_code":"DE",
    "gn:dem":457,
    "gn:feature_class":"P",
    "gn:feature_code":"PPL",
    "gn:name":"Dietlishof",
    "gn:population":0,
    "gn:timezone":"Europe/Berlin",
    "iso:country":"DE",
    "name:und_x_variant":[
        "Dietlishofen",
        "Dietlishof"
    ],
    "wof:name":"Dietlishof",
    "wof:placetype":"neighbourhood"
},
  "geometry": {"coordinates":[8.77849,47.75593],"type":"Point"}
}