{
  "type": "Feature",
  "properties": {
    "gn:admin1_code":"2",
    "gn:admin2_code":"92.0",
    "gn:admin3_code":"9277.0",
    "gn:admin4_code":"9277142.0",
    "gn:asciiname":"Ehrnstorf",
    "gn:country_code":"DE",
    "gn:dem":338,
    "gn:feature_class":"P",
    "gn:feature_code":"PPL",
    "gn:name":"Ehrnstorf",
    "gn:population":0,
    "gn:timezone":"Europe/Berlin",
    "iso:country":"DE",
    "name:und_x_variant":[
        "Ehrnsdorf",
        "Ehrnstorf"
    ],
    "wof:name":"Ehrnstorf",
    "wof:placetype":"neighbourhood"
},
  "geometry": {"coordinates":[12.97891,48.60304],"type":"Point"}
}