{
  "type": "Feature",
  "properties": {
    "gn:admin1_code":"2",
    "gn:admin2_code":"92.0",
    "gn:admin3_code":"9278.0",
    "gn:admin4_code":"9278179.0",
    "gn:asciiname":"Eggerszell",
    "gn:country_code":"DE",
    "gn:dem":485,
    "gn:feature_class":"P",
    "gn:feature_code":"PPL",
    "gn:name":"Eggerszell",
    "gn:population":0,
    "gn:timezone":"Europe/Berlin",
    "iso:country":"DE",
    "wof:name":"Eggerszell",
    "wof:placetype":"neighbourhood"
},
  "geometry": {"coordinates":[12.61832,49.02338],"type":"Point"}
}