{
  "type": "Feature",
  "properties": {
    "gn:admin1_code":"7",
    "gn:admin2_code":"53.0",
    "gn:admin3_code":"5358.0",
    "gn:admin4_code":"5358060.0",
    "gn:asciiname":"Froitzheim",
    "gn:country_code":"DE",
    "gn:dem":189,
    "gn:feature_class":"P",
    "gn:feature_code":"PPL",
    "gn:name":"Froitzheim",
    "gn:population":0,
    "gn:timezone":"Europe/Berlin",
    "iso:country":"DE",
    "wof:name":"Froitzheim",
    "wof:placetype":"neighbourhood"
},
  "geometry": {"coordinates":[6.57547,50.71316],"type":"Point"}
}