{
  "type": "Feature",
  "properties": {
    "gn:country":"DE",
    "gn:fcode":"PPLA4",
    "gn:population":162,
    "iso:country":"DE",
    "name:bak_x_preferred":[
        "\u0411\u0440\u0430\u0439\u0442\u0435\u043d\u0445\u0430\u0439\u043d"
    ],
    "name:ceb_x_preferred":[
        "Breitenhain"
    ],
    "name:che_x_preferred":[
        "\u0411\u0440\u0430\u0439\u0442\u0435\u043d\u0445\u0430\u0439\u043d"
    ],
    "name:deu_x_preferred":[
        "Breitenhain"
    ],
    "name:eng_x_preferred":[
        "Breitenhain"
    ],
    "name:epo_x_preferred":[
        "Breitenhain"
    ],
    "name:fas_x_preferred":[
        "\u0628\u0631\u0627\u06cc\u062a\u0646\u0647\u0627\u06cc\u0646"
    ],
    "name:fra_x_preferred":[
        "Breitenhain"
    ],
    "name:ita_x_preferred":[
        "Breitenhain"
    ],
    "name:kaz_x_preferred":[
        "\u0411\u0440\u0430\u0439\u0442\u0435\u043d\u0445\u0430\u0439\u043d"
    ],
    "name:kir_x_preferred":[
        "\u0411\u0440\u0430\u0439\u0442\u0435\u043d\u0445\u0430\u0439\u043d"
    ],
    "name:nld_x_preferred":[
        "Breitenhain"
    ],
    "name:por_x_preferred":[
        "Breitenhain"
    ],
    "name:ron_x_preferred":[
        "Breitenhain"
    ],
    "name:rus_x_preferred":[
        "\u0411\u0440\u0430\u0439\u0442\u0435\u043d\u0445\u0430\u0439\u043d"
    ],
    "name:srp_x_preferred":[
        "\u0411\u0440\u0430\u0458\u0442\u0435\u043d\u0445\u0430\u0458\u043d"
    ],
    "name:tat_x_preferred":[
        "\u0411\u0440\u0430\u0439\u0442\u0435\u043d\u0445\u0430\u0439\u043d"
    ],
    "name:uzb_x_preferred":[
        "Breitenhain"
    ],
    "name:vol_x_preferred":[
        "Breitenhain"
    ],
    "name:war_x_preferred":[
        "Breitenhain"
    ],
    "qs_pg:aaroncc":"DE",
    "qs_pg:gn_country":"DE",
    "qs_pg:gn_fcode":"PPLA4",
    "qs_pg:gn_pop":162,
    "qs_pg:name":"Breitenhain",
    "qs_pg:photos_9r":0,
    "qs_pg:photos_sr":0,
    "qs_pg:pop_sr":1,
    "qs_pg:qs_pg_placetype":"locality",
    "wof:name":"Breitenhain",
    "wof:placetype":"neighbourhood",
    "wof:population":162
},
  "geometry": {"coordinates":[11.73333,50.76667],"type":"Point"}
}