{
  "type": "Feature",
  "properties": {
    "gn:admin1_code":"2",
    "gn:admin2_code":"97.0",
    "gn:admin3_code":"9774.0",
    "gn:admin4_code":"9774198.0",
    "gn:asciiname":"Hellersberg",
    "gn:country_code":"DE",
    "gn:dem":570,
    "gn:feature_class":"P",
    "gn:feature_code":"PPL",
    "gn:name":"Hellersberg",
    "gn:population":0,
    "gn:timezone":"Europe/Berlin",
    "iso:country":"DE",
    "wof:name":"Hellersberg",
    "wof:placetype":"neighbourhood"
},
  "geometry": {"coordinates":[10.52861,48.26361],"type":"Point"}
}