{
  "type": "Feature",
  "properties": {
    "gn:admin1_code":"2",
    "gn:admin2_code":"91.0",
    "gn:admin3_code":"9189.0",
    "gn:admin4_code":"9189134.0",
    "gn:asciiname":"Harpfetsham",
    "gn:country_code":"DE",
    "gn:dem":572,
    "gn:feature_class":"P",
    "gn:feature_code":"PPLL",
    "gn:name":"Harpfetsham",
    "gn:population":0,
    "gn:timezone":"Europe/Berlin",
    "iso:country":"DE",
    "wof:name":"Harpfetsham",
    "wof:placetype":"neighbourhood"
},
  "geometry": {"coordinates":[12.66465,47.98966],"type":"Point"}
}