{
  "type": "Feature",
  "properties": {
    "iso:country":"DE",
    "name:deu_x_preferred":[
        "Vaalserquartier"
    ],
    "name:eng_x_preferred":[
        "Vaalserquartier"
    ],
    "name:fra_x_preferred":[
        "Vaalserquartier"
    ],
    "name:nld_x_preferred":[
        "Vaalserquartier"
    ],
    "name:und_x_variant":[
        "Vaelserquartier"
    ],
    "qs:gn_adm0_cc":"DE",
    "qs:gn_fcode":"PPL",
    "qs:gn_local":0,
    "qs:gn_namadm1":"07",
    "qs:gn_name":"Vaalserquartier",
    "qs:local_max":7923,
    "qs:local_sum":22653,
    "qs:localhoods":31,
    "qs:name":"Vaalserquartier",
    "qs:name_adm0":"Deutschland",
    "qs:name_adm1":"Nordrhein-Westfalen",
    "qs:name_adm2":"Stadtkreis Aachen",
    "qs:name_lau":"Stadtteil Laurensberg",
    "qs:name_local":"Aachen",
    "qs:photo_max":112,
    "qs:photo_sum":1083,
    "qs:placetype":"Suburb",
    "qs:quad_count":60,
    "qs:woe_adm0":23424829,
    "qs:woe_adm1":2345487,
    "qs:woe_adm2":20071103,
    "qs:woe_lau":26821834,
    "qs:woe_local":633175,
    "qs:woe_ver":"7.10.0",
    "wof:lang":[
        "ger"
    ],
    "wof:name":"Vaalserquartier",
    "wof:placetype":"neighbourhood"
},
  "geometry": {"coordinates":[6.05741,50.774459],"type":"Point"}
}