{
  "type": "Feature",
  "properties": {
    "gn:admin1_code":"5",
    "gn:admin2_code":"65.0",
    "gn:admin3_code":"6533.0",
    "gn:admin4_code":"6533006.0",
    "gn:asciiname":"Malmeneich",
    "gn:country_code":"DE",
    "gn:dem":252,
    "gn:feature_class":"P",
    "gn:feature_code":"PPL",
    "gn:name":"Malmeneich",
    "gn:population":0,
    "gn:timezone":"Europe/Berlin",
    "iso:country":"DE",
    "name:deu_x_preferred":[
        "Malmeneich"
    ],
    "wof:name":"Malmeneich",
    "wof:placetype":"neighbourhood"
},
  "geometry": {"coordinates":[7.99519,50.44046],"type":"Point"}
}