{
  "type": "Feature",
  "properties": {
    "gn:admin1_code":"2",
    "gn:admin2_code":"91.0",
    "gn:admin3_code":"9190.0",
    "gn:admin4_code":"9190152.0",
    "gn:asciiname":"Oppenried",
    "gn:country_code":"DE",
    "gn:dem":632,
    "gn:feature_class":"P",
    "gn:feature_code":"PPL",
    "gn:name":"Oppenried",
    "gn:population":0,
    "gn:timezone":"Europe/Berlin",
    "iso:country":"DE",
    "wof:name":"Oppenried",
    "wof:placetype":"neighbourhood"
},
  "geometry": {"coordinates":[11.25863,47.82846],"type":"Point"}
}