{
  "type": "Feature",
  "properties": {
    "gn:admin1_code":"13",
    "gn:admin2_code":"0.0",
    "gn:admin3_code":"14628.0",
    "gn:admin4_code":"14628300.0",
    "gn:asciiname":"Luebau",
    "gn:country_code":"DE",
    "gn:dem":325,
    "gn:feature_class":"P",
    "gn:feature_code":"PPL",
    "gn:name":"L\u00fcbau",
    "gn:population":0,
    "gn:timezone":"Europe/Berlin",
    "iso:country":"DE",
    "wof:name":"Luebau",
    "wof:placetype":"neighbourhood"
},
  "geometry": {"coordinates":[13.61963,50.95361],"type":"Point"}
}