{
  "type": "Feature",
  "properties": {
    "gn:admin1_code":"2",
    "gn:admin2_code":"91.0",
    "gn:admin3_code":"9177.0",
    "gn:admin4_code":"9177123.0",
    "gn:asciiname":"Mittbach",
    "gn:country_code":"DE",
    "gn:dem":624,
    "gn:feature_class":"P",
    "gn:feature_code":"PPL",
    "gn:name":"Mittbach",
    "gn:population":0,
    "gn:timezone":"Europe/Berlin",
    "iso:country":"DE",
    "wof:name":"Mittbach",
    "wof:placetype":"neighbourhood"
},
  "geometry": {"coordinates":[12.02977,48.16414],"type":"Point"}
}