{
  "type": "Feature",
  "properties": {
    "gn:admin1_code":"13",
    "gn:admin2_code":"0.0",
    "gn:admin3_code":"14522.0",
    "gn:admin4_code":"14522200.0",
    "gn:asciiname":"Mittelsaida",
    "gn:country_code":"DE",
    "gn:dem":514,
    "gn:feature_class":"P",
    "gn:feature_code":"PPL",
    "gn:name":"Mittelsaida",
    "gn:population":0,
    "gn:timezone":"Europe/Berlin",
    "iso:country":"DE",
    "wof:name":"Mittelsaida",
    "wof:placetype":"neighbourhood"
},
  "geometry": {"coordinates":[13.30395,50.76365],"type":"Point"}
}