{
  "type": "Feature",
  "properties": {
    "gn:admin1_code":"1",
    "gn:admin2_code":"81.0",
    "gn:admin3_code":"8117.0",
    "gn:admin4_code":"8117007.0",
    "gn:asciiname":"Oberbohringen",
    "gn:country_code":"DE",
    "gn:dem":721,
    "gn:feature_class":"P",
    "gn:feature_code":"PPL",
    "gn:name":"Oberb\u00f6hringen",
    "gn:population":0,
    "gn:timezone":"Europe/Berlin",
    "iso:country":"DE",
    "wof:name":"Oberbohringen",
    "wof:placetype":"neighbourhood"
},
  "geometry": {"coordinates":[9.78075,48.6177],"type":"Point"}
}