{
  "type": "Feature",
  "properties": {
    "gn:admin1_code":"2",
    "gn:admin2_code":"95.0",
    "gn:admin3_code":"9571.0",
    "gn:admin4_code":"9571165.0",
    "gn:asciiname":"Trachenhofstatt",
    "gn:country_code":"DE",
    "gn:dem":403,
    "gn:feature_class":"P",
    "gn:feature_code":"PPL",
    "gn:name":"Trachenh\u00f6fstatt",
    "gn:population":0,
    "gn:timezone":"Europe/Berlin",
    "iso:country":"DE",
    "wof:name":"Trachenhofstatt",
    "wof:placetype":"neighbourhood"
},
  "geometry": {"coordinates":[10.84363,49.32223],"type":"Point"}
}