{
  "type": "Feature",
  "properties": {
    "gn:admin1_code":"13",
    "gn:admin2_code":"0.0",
    "gn:admin3_code":"14626.0",
    "gn:admin4_code":"14626190.0",
    "gn:asciiname":"Jerchwitz",
    "gn:country_code":"DE",
    "gn:dem":202,
    "gn:feature_class":"P",
    "gn:feature_code":"PPL",
    "gn:name":"Jerchwitz",
    "gn:population":0,
    "gn:timezone":"Europe/Berlin",
    "iso:country":"DE",
    "name:hsb_x_preferred":[
        "Jerchecy"
    ],
    "wof:name":"Jerchwitz",
    "wof:placetype":"neighbourhood"
},
  "geometry": {"coordinates":[14.69153,51.23349],"type":"Point"}
}