{
  "type": "Feature",
  "properties": {
    "gn:admin1_code":"2",
    "gn:admin2_code":"91.0",
    "gn:admin3_code":"9190.0",
    "gn:admin4_code":"9190133.0",
    "gn:asciiname":"Erbenschwang",
    "gn:country_code":"DE",
    "gn:dem":761,
    "gn:feature_class":"P",
    "gn:feature_code":"PPL",
    "gn:name":"Erbenschwang",
    "gn:population":0,
    "gn:timezone":"Europe/Berlin",
    "iso:country":"DE",
    "wof:name":"Erbenschwang",
    "wof:placetype":"neighbourhood"
},
  "geometry": {"coordinates":[10.80161,47.80627],"type":"Point"}
}