{
  "type": "Feature",
  "properties": {
    "gn:admin1_code":"6",
    "gn:admin2_code":"0.0",
    "gn:admin3_code":"3457.0",
    "gn:admin4_code":"3457014.0",
    "gn:asciiname":"Jheringsfehn",
    "gn:country_code":"DE",
    "gn:dem":1,
    "gn:feature_class":"P",
    "gn:feature_code":"PPL",
    "gn:name":"Jheringsfehn",
    "gn:population":0,
    "gn:timezone":"Europe/Berlin",
    "iso:country":"DE",
    "name:deu_x_preferred":[
        "Jheringsfehn"
    ],
    "name:fra_x_preferred":[
        "Jheringsfehn"
    ],
    "name:nld_x_preferred":[
        "Jheringsfehn"
    ],
    "name:und_x_variant":[
        "Iheringsfehn"
    ],
    "wof:name":"Jheringsfehn",
    "wof:placetype":"neighbourhood"
},
  "geometry": {"coordinates":[7.51834,53.31816],"type":"Point"}
}