{
  "type": "Feature",
  "properties": {
    "gn:admin1_code":"10",
    "gn:admin2_code":"0.0",
    "gn:admin3_code":"1056.0",
    "gn:admin4_code":"1056041.0",
    "gn:asciiname":"Himmelmoor",
    "gn:country_code":"DE",
    "gn:dem":17,
    "gn:feature_class":"P",
    "gn:feature_code":"PPL",
    "gn:name":"Himmelmoor",
    "gn:population":0,
    "gn:timezone":"Europe/Berlin",
    "iso:country":"DE",
    "wof:name":"Himmelmoor",
    "wof:placetype":"neighbourhood"
},
  "geometry": {"coordinates":[9.86988,53.74694],"type":"Point"}
}