{
  "type": "Feature",
  "properties": {
    "gn:admin1_code":"14",
    "gn:admin2_code":"0.0",
    "gn:admin3_code":"15090.0",
    "gn:admin4_code":"15090270.0",
    "gn:asciiname":"Faehrkrug",
    "gn:country_code":"DE",
    "gn:dem":28,
    "gn:feature_class":"P",
    "gn:feature_code":"PPL",
    "gn:name":"F\u00e4hrkrug",
    "gn:population":0,
    "gn:timezone":"Europe/Berlin",
    "iso:country":"DE",
    "wof:name":"Faehrkrug",
    "wof:placetype":"neighbourhood"
},
  "geometry": {"coordinates":[12.02951,52.78522],"type":"Point"}
}