{
  "type": "Feature",
  "properties": {
    "gn:admin1_code":"2",
    "gn:admin2_code":"92.0",
    "gn:admin3_code":"9274.0",
    "gn:admin4_code":"9274146.0",
    "gn:asciiname":"Hohenberg",
    "gn:country_code":"DE",
    "gn:dem":497,
    "gn:feature_class":"P",
    "gn:feature_code":"PPL",
    "gn:name":"H\u00f6henberg",
    "gn:population":0,
    "gn:timezone":"Europe/Berlin",
    "iso:country":"DE",
    "wof:name":"Hohenberg",
    "wof:placetype":"neighbourhood"
},
  "geometry": {"coordinates":[12.19626,48.50053],"type":"Point"}
}