{
  "type": "Feature",
  "properties": {
    "gn:admin1_code":"11",
    "gn:admin2_code":"0.0",
    "gn:admin3_code":"12071.0",
    "gn:admin4_code":"12071341.0",
    "gn:asciiname":"Saccassne",
    "gn:country_code":"DE",
    "gn:dem":55,
    "gn:feature_class":"P",
    "gn:feature_code":"PPL",
    "gn:name":"Saccassne",
    "gn:population":0,
    "gn:timezone":"Europe/Berlin",
    "iso:country":"DE",
    "name:dsb_x_preferred":[
        "Zakazna"
    ],
    "wof:name":"Saccassne",
    "wof:placetype":"neighbourhood"
},
  "geometry": {"coordinates":[14.19721,51.8651],"type":"Point"}
}