{
  "type": "Feature",
  "properties": {
    "gn:admin1_code":"7",
    "gn:admin2_code":"53.0",
    "gn:admin3_code":"5382.0",
    "gn:admin4_code":"5382020.0",
    "gn:asciiname":"Driesch",
    "gn:country_code":"DE",
    "gn:dem":173,
    "gn:feature_class":"P",
    "gn:feature_code":"PPL",
    "gn:name":"Driesch",
    "gn:population":0,
    "gn:timezone":"Europe/Berlin",
    "iso:country":"DE",
    "wof:name":"Driesch",
    "wof:placetype":"neighbourhood"
},
  "geometry": {"coordinates":[7.34256,50.78575],"type":"Point"}
}