{
  "type": "Feature",
  "properties": {
    "gn:admin1_code":"2.0",
    "gn:admin2_code":"092",
    "gn:admin3_code":"9279.0",
    "gn:admin4_code":"9279134.0",
    "gn:asciiname":"Wimbach",
    "gn:country_code":"DE",
    "gn:dem":452,
    "gn:feature_class":"P",
    "gn:feature_code":"PPL",
    "gn:name":"Wimbach",
    "gn:population":0,
    "gn:timezone":"Europe/Berlin",
    "iso:country":"DE",
    "name:ceb_x_preferred":[
        "Wimbach"
    ],
    "name:deu_x_preferred":[
        "Wimbach"
    ],
    "name:epo_x_preferred":[
        "Wimbach"
    ],
    "name:eus_x_preferred":[
        "Wimbach"
    ],
    "name:fas_x_preferred":[
        "\u0648\u06cc\u0645\u0628\u0627\u062e"
    ],
    "name:fra_x_preferred":[
        "Wimbach"
    ],
    "name:hun_x_preferred":[
        "Wimbach"
    ],
    "name:ita_x_preferred":[
        "Wimbach"
    ],
    "name:kaz_x_preferred":[
        "\u0412\u0438\u043c\u0431\u0430\u0445"
    ],
    "name:kir_x_preferred":[
        "\u0412\u0438\u043c\u0431\u0430\u0445"
    ],
    "name:msa_x_preferred":[
        "Wimbach"
    ],
    "name:nld_x_preferred":[
        "Wimbach"
    ],
    "name:pol_x_preferred":[
        "Wimbach"
    ],
    "name:por_x_preferred":[
        "Wimbach"
    ],
    "name:ron_x_preferred":[
        "Wimbach"
    ],
    "name:rus_x_preferred":[
        "\u0412\u0438\u043c\u0431\u0430\u0445"
    ],
    "name:spa_x_preferred":[
        "Wimbach"
    ],
    "name:srp_x_preferred":[
        "\u0412\u0438\u043c\u0431\u0430\u0445"
    ],
    "name:ukr_x_preferred":[
        "\u0412\u0456\u043c\u0431\u0430\u0445"
    ],
    "name:uzb_x_preferred":[
        "Wimbach"
    ],
    "name:vie_x_preferred":[
        "Wimbach"
    ],
    "name:vol_x_preferred":[
        "Wimbach"
    ],
    "name:war_x_preferred":[
        "Wimbach"
    ],
    "name:zho_x_preferred":[
        "\u6e29\u5df4\u8d6b"
    ],
    "wof:name":"Wimbach",
    "wof:placetype":"neighbourhood"
},
  "geometry": {"coordinates":[12.62674,48.54914],"type":"Point"}
}