{
  "type": "Feature",
  "properties": {
    "gn:admin1_code":"13",
    "gn:admin2_code":"0.0",
    "gn:admin3_code":"14729.0",
    "gn:admin4_code":"14729330.0",
    "gn:asciiname":"Grossbuch",
    "gn:country_code":"DE",
    "gn:dem":159,
    "gn:feature_class":"P",
    "gn:feature_code":"PPL",
    "gn:name":"Gro\u00dfbuch",
    "gn:population":0,
    "gn:timezone":"Europe/Berlin",
    "iso:country":"DE",
    "wof:name":"Grossbuch",
    "wof:placetype":"neighbourhood"
},
  "geometry": {"coordinates":[12.64198,51.20051],"type":"Point"}
}