{
  "type": "Feature",
  "properties": {
    "iso:country":"DE",
    "wof:name":"Niederbrich",
    "wof:placetype":"neighbourhood"
},
  "geometry": {"coordinates":[6.59479503030067,51.3177497601298],"type":"Point"}
}