{
  "type": "Feature",
  "properties": {
    "gn:admin1_code":"2",
    "gn:admin2_code":"96.0",
    "gn:admin3_code":"9673.0",
    "gn:admin4_code":"9673182.0",
    "gn:asciiname":"Volkershausen",
    "gn:country_code":"DE",
    "gn:dem":405,
    "gn:feature_class":"P",
    "gn:feature_code":"PPL",
    "gn:name":"V\u00f6lkershausen",
    "gn:population":0,
    "gn:timezone":"Europe/Berlin",
    "iso:country":"DE",
    "wof:name":"Volkershausen",
    "wof:placetype":"neighbourhood"
},
  "geometry": {"coordinates":[10.27654,50.48991],"type":"Point"}
}