{
  "type": "Feature",
  "properties": {
    "gn:admin1_code":"6",
    "gn:admin2_code":"0.0",
    "gn:admin3_code":"3357.0",
    "gn:admin4_code":"3357016.0",
    "gn:asciiname":"Schwarze Flage",
    "gn:country_code":"DE",
    "gn:dem":7,
    "gn:feature_class":"P",
    "gn:feature_code":"PPL",
    "gn:name":"Schwarze Flage",
    "gn:population":0,
    "gn:timezone":"Europe/Berlin",
    "iso:country":"DE",
    "wof:name":"Schwarze Flage",
    "wof:placetype":"neighbourhood"
},
  "geometry": {"coordinates":[9.0662,53.43591],"type":"Point"}
}