{
  "type": "Feature",
  "properties": {
    "gn:admin1_code":"7",
    "gn:admin2_code":"51.0",
    "gn:admin3_code":"5116.0",
    "gn:admin4_code":"5116000.0",
    "gn:asciiname":"Genhuelsen",
    "gn:country_code":"DE",
    "gn:dem":83,
    "gn:feature_class":"P",
    "gn:feature_code":"PPL",
    "gn:name":"Genh\u00fclsen",
    "gn:population":0,
    "gn:timezone":"Europe/Berlin",
    "iso:country":"DE",
    "wof:name":"Genhuelsen",
    "wof:placetype":"neighbourhood"
},
  "geometry": {"coordinates":[6.39988,51.15502],"type":"Point"}
}