{
  "type": "Feature",
  "properties": {
    "gn:admin1_code":"13.0",
    "gn:admin2_code":"00",
    "gn:admin3_code":"14522.0",
    "gn:admin4_code":"14522500.0",
    "gn:asciiname":"Weinsdorf",
    "gn:country_code":"DE",
    "gn:dem":291,
    "gn:feature_class":"P",
    "gn:feature_code":"PPL",
    "gn:name":"Weinsdorf",
    "gn:population":0,
    "gn:timezone":"Europe/Berlin",
    "iso:country":"DE",
    "wof:name":"Weinsdorf",
    "wof:placetype":"neighbourhood"
},
  "geometry": {"coordinates":[13.02256,50.99656],"type":"Point"}
}