{
  "type": "Feature",
  "properties": {
    "gn:admin1_code":"1.0",
    "gn:admin2_code":"82.0",
    "gn:admin3_code":"8237.0",
    "gn:admin4_code":"8237045.0",
    "gn:asciiname":"Ausserer Vogelsberg",
    "gn:country_code":"DE",
    "gn:dem":677,
    "gn:feature_class":"P",
    "gn:feature_code":"PPL",
    "gn:name":"\u00c4u\u00dferer Vogelsberg",
    "gn:population":0,
    "gn:timezone":"Europe/Berlin",
    "iso:country":"DE",
    "wof:name":"Ausserer Vogelsberg",
    "wof:placetype":"locality"
},
  "geometry": {"coordinates":[8.45113,48.38729],"type":"Point"}
}