{
  "type": "Feature",
  "properties": {
    "gn:admin1_code":"1",
    "gn:admin2_code":"82.0",
    "gn:admin3_code":"8236.0",
    "gn:admin4_code":"8236040.0",
    "gn:asciiname":"Enzberg",
    "gn:country_code":"DE",
    "gn:dem":256,
    "gn:feature_class":"P",
    "gn:feature_code":"PPL",
    "gn:name":"Enzberg",
    "gn:population":0,
    "gn:timezone":"Europe/Berlin",
    "iso:country":"DE",
    "wof:name":"Enzberg",
    "wof:placetype":"neighbourhood"
},
  "geometry": {"coordinates":[8.80012,48.93594],"type":"Point"}
}