{
  "type": "Feature",
  "properties": {
    "gn:admin1_code":"11",
    "gn:admin2_code":"0.0",
    "gn:admin3_code":"12067.0",
    "gn:admin4_code":"12067493.0",
    "gn:asciiname":"Falkenberg",
    "gn:country_code":"DE",
    "gn:dem":68,
    "gn:feature_class":"P",
    "gn:feature_code":"PPL",
    "gn:name":"Falkenberg",
    "gn:population":0,
    "gn:timezone":"Europe/Berlin",
    "iso:country":"DE",
    "name:ara_x_preferred":[
        "\u0641\u0627\u0644\u0643\u0646\u0628\u0631\u063a"
    ],
    "name:bul_x_preferred":[
        "\u0424\u0430\u043b\u043a\u0435\u043d\u0431\u0435\u0440\u0438"
    ],
    "name:cat_x_preferred":[
        "Falkenberg"
    ],
    "name:ceb_x_preferred":[
        "Falkenberg"
    ],
    "name:dan_x_preferred":[
        "Falkenberg"
    ],
    "name:deu_x_preferred":[
        "Falkenberg"
    ],
    "name:est_x_preferred":[
        "Falkenberg"
    ],
    "name:fao_x_preferred":[
        "Falkenberg"
    ],
    "name:fas_x_preferred":[
        "\u0641\u0644\u06a9\u0646\u0628\u06cc"
    ],
    "name:fin_x_preferred":[
        "Falkenbergin kunta"
    ],
    "name:fra_x_preferred":[
        "Falkenberg"
    ],
    "name:glg_x_preferred":[
        "Falkenberg"
    ],
    "name:hrv_x_preferred":[
        "Falkenberg"
    ],
    "name:ind_x_preferred":[
        "Falkenberg"
    ],
    "name:isl_x_preferred":[
        "Falkenberg"
    ],
    "name:ita_x_preferred":[
        "Falkenberg"
    ],
    "name:jpn_x_preferred":[
        "\u30d5\u30a1\u30eb\u30b1\u30f3\u30d9\u30ea"
    ],
    "name:kor_x_preferred":[
        "\ud314\ucf04\ubca0\ub9ac"
    ],
    "name:lit_x_preferred":[
        "Falkenbergas"
    ],
    "name:min_x_preferred":[
        "Falkenberg"
    ],
    "name:nld_x_preferred":[
        "Falkenberg"
    ],
    "name:nno_x_preferred":[
        "Falkenberg"
    ],
    "name:nor_x_preferred":[
        "Falkenberg"
    ],
    "name:pol_x_preferred":[
        "Falkenberg"
    ],
    "name:por_x_preferred":[
        "Falkenberg"
    ],
    "name:ron_x_preferred":[
        "Falkenberg"
    ],
    "name:rus_x_preferred":[
        "\u0424\u0430\u043b\u044c\u043a\u0435\u043d\u0431\u0435\u0440\u0433"
    ],
    "name:spa_x_preferred":[
        "Falkenberg"
    ],
    "name:sqi_x_preferred":[
        "Falkenberg"
    ],
    "name:srp_x_preferred":[
        "\u0424\u0430\u043b\u043a\u0435\u043d\u0431\u0435\u0440\u0433"
    ],
    "name:swa_x_preferred":[
        "Falkenberg"
    ],
    "name:swe_x_preferred":[
        "Falkenberg"
    ],
    "name:tur_x_preferred":[
        "Falkenberg"
    ],
    "name:ukr_x_preferred":[
        "\u0424\u0430\u043b\u044c\u043a\u0435\u043d\u0431\u0435\u0440\u0433"
    ],
    "name:urd_x_preferred":[
        "\u0641\u0627\u0644\u06a9\u06cc\u0646\u0628\u06cc\u0631\u06af"
    ],
    "name:vol_x_preferred":[
        "Falkenberg"
    ],
    "name:zho_x_preferred":[
        "\u6cd5\u5c14\u80af\u8d1d\u91cc"
    ],
    "wof:name":"Falkenberg",
    "wof:placetype":"neighbourhood"
},
  "geometry": {"coordinates":[14.12966,52.16041],"type":"Point"}
}