{
  "type": "Feature",
  "properties": {
    "gn:admin1_code":"2",
    "gn:admin2_code":"92.0",
    "gn:admin3_code":"9273.0",
    "gn:admin4_code":"9273166.0",
    "gn:asciiname":"Oberteuerting",
    "gn:country_code":"DE",
    "gn:dem":391,
    "gn:feature_class":"P",
    "gn:feature_code":"PPL",
    "gn:name":"Oberteuerting",
    "gn:population":0,
    "gn:timezone":"Europe/Berlin",
    "iso:country":"DE",
    "wof:name":"Oberteuerting",
    "wof:placetype":"neighbourhood"
},
  "geometry": {"coordinates":[11.90046,48.85598],"type":"Point"}
}