{
  "type": "Feature",
  "properties": {
    "gn:admin1_code":"7",
    "gn:asciiname":"Nievelstein",
    "gn:cc2":"DE",
    "gn:country_code":"DE",
    "gn:dem":128,
    "gn:feature_class":"P",
    "gn:feature_code":"PPL",
    "gn:name":"Nievelstein",
    "gn:population":0,
    "gn:timezone":"Europe/Berlin",
    "iso:country":"DE",
    "name:und_x_variant":[
        "Merkstein Nievelstein",
        "Nievelstein"
    ],
    "wof:name":"Nievelstein",
    "wof:placetype":"neighbourhood"
},
  "geometry": {"coordinates":[6.06667,50.88333],"type":"Point"}
}