{
  "type": "Feature",
  "properties": {
    "gn:admin1_code":"5.0",
    "gn:admin2_code":"064",
    "gn:admin3_code":"6433.0",
    "gn:admin4_code":"6433003.0",
    "gn:asciiname":"Worfelden",
    "gn:country_code":"DE",
    "gn:dem":101,
    "gn:feature_class":"P",
    "gn:feature_code":"PPL",
    "gn:name":"Worfelden",
    "gn:population":0,
    "gn:timezone":"Europe/Berlin",
    "iso:country":"DE",
    "wof:name":"Worfelden",
    "wof:placetype":"neighbourhood"
},
  "geometry": {"coordinates":[8.55194,49.92834000000001],"type":"Point"}
}