{
  "type": "Feature",
  "properties": {
    "gn:admin1_code":"15",
    "gn:admin2_code":"0.0",
    "gn:admin3_code":"16069.0",
    "gn:admin4_code":"16069012.0",
    "gn:asciiname":"Waffenrod",
    "gn:country_code":"DE",
    "gn:dem":647,
    "gn:feature_class":"P",
    "gn:feature_code":"PPL",
    "gn:name":"Waffenrod",
    "gn:population":0,
    "gn:timezone":"Europe/Berlin",
    "iso:country":"DE",
    "wof:name":"Waffenrod",
    "wof:placetype":"neighbourhood"
},
  "geometry": {"coordinates":[10.91213,50.47597],"type":"Point"}
}