{
  "type": "Feature",
  "properties": {
    "gn:admin1_code":"7",
    "gn:admin2_code":"57.0",
    "gn:admin3_code":"5770.0",
    "gn:admin4_code":"5770004.0",
    "gn:asciiname":"Schmalenbeck",
    "gn:country_code":"DE",
    "gn:dem":87,
    "gn:feature_class":"P",
    "gn:feature_code":"PPL",
    "gn:name":"Schmalenbeck",
    "gn:population":0,
    "gn:timezone":"Europe/Berlin",
    "iso:country":"DE",
    "wof:name":"Schmalenbeck",
    "wof:placetype":"neighbourhood"
},
  "geometry": {"coordinates":[8.75944,52.24844],"type":"Point"}
}