{
  "type": "Feature",
  "properties": {
    "gn:admin1_code":"2",
    "gn:admin2_code":"94.0",
    "gn:admin3_code":"9472.0",
    "gn:admin4_code":"9472111.0",
    "gn:asciiname":"Poppendorf",
    "gn:country_code":"DE",
    "gn:dem":429,
    "gn:feature_class":"P",
    "gn:feature_code":"PPL",
    "gn:name":"Poppendorf",
    "gn:population":0,
    "gn:timezone":"Europe/Berlin",
    "iso:country":"DE",
    "name:deu_x_preferred":[
        "Poppendorf"
    ],
    "name:epo_x_preferred":[
        "Poppendorf"
    ],
    "name:fas_x_preferred":[
        "\u067e\u0648\u067e\u0646\u062f\u0648\u0631\u0641"
    ],
    "name:fra_x_preferred":[
        "Poppendorf"
    ],
    "name:hun_x_preferred":[
        "Poppendorf"
    ],
    "name:ita_x_preferred":[
        "Poppendorf"
    ],
    "name:mkd_x_preferred":[
        "\u041f\u043e\u043f\u0435\u043d\u0434\u043e\u0440\u0444"
    ],
    "name:msa_x_preferred":[
        "Poppendorf"
    ],
    "name:nld_x_preferred":[
        "Poppendorf"
    ],
    "name:pol_x_preferred":[
        "Poppendorf"
    ],
    "name:ron_x_preferred":[
        "Poppendorf"
    ],
    "name:rus_x_preferred":[
        "\u041f\u043e\u043f\u043f\u0435\u043d\u0434\u043e\u0440\u0444"
    ],
    "name:spa_x_preferred":[
        "Poppendorf"
    ],
    "name:srp_x_preferred":[
        "\u041f\u043e\u043f\u0435\u043d\u0434\u043e\u0440\u0444"
    ],
    "name:ukr_x_preferred":[
        "\u041f\u043e\u043f\u043f\u0435\u043d\u0434\u043e\u0440\u0444"
    ],
    "name:uzb_x_preferred":[
        "Poppendorf"
    ],
    "name:vie_x_preferred":[
        "Poppendorf"
    ],
    "name:vol_x_preferred":[
        "Poppendorf"
    ],
    "name:war_x_preferred":[
        "Poppendorf"
    ],
    "name:zho_x_preferred":[
        "\u6ce2\u5f6d\u591a\u592b"
    ],
    "wof:name":"Poppendorf",
    "wof:placetype":"neighbourhood"
},
  "geometry": {"coordinates":[11.4493,49.83138],"type":"Point"}
}