{
  "type": "Feature",
  "properties": {
    "gn:admin1_code":"7",
    "gn:admin2_code":"57.0",
    "gn:admin3_code":"5758.0",
    "gn:admin4_code":"5758004.0",
    "gn:asciiname":"Uhlenbrock",
    "gn:country_code":"DE",
    "gn:dem":68,
    "gn:feature_class":"P",
    "gn:feature_code":"PPL",
    "gn:name":"Uhlenbrock",
    "gn:population":0,
    "gn:timezone":"Europe/Berlin",
    "iso:country":"DE",
    "wof:name":"Uhlenbrock",
    "wof:placetype":"neighbourhood"
},
  "geometry": {"coordinates":[8.54295,52.19716],"type":"Point"}
}