{
  "type": "Feature",
  "properties": {
    "gn:admin1_code":"6",
    "gn:admin2_code":"0.0",
    "gn:admin3_code":"3158.0",
    "gn:admin4_code":"3158027.0",
    "gn:asciiname":"Kueblingen",
    "gn:country_code":"DE",
    "gn:dem":116,
    "gn:feature_class":"P",
    "gn:feature_code":"PPL",
    "gn:name":"K\u00fcblingen",
    "gn:population":0,
    "gn:timezone":"Europe/Berlin",
    "iso:country":"DE",
    "wof:name":"Kueblingen",
    "wof:placetype":"neighbourhood"
},
  "geometry": {"coordinates":[10.78737,52.14603],"type":"Point"}
}