{
  "type": "Feature",
  "properties": {
    "gn:admin1_code":"2",
    "gn:admin2_code":"97.0",
    "gn:admin3_code":"9777.0",
    "gn:admin4_code":"9777152.0",
    "gn:asciiname":"Hausen",
    "gn:country_code":"DE",
    "gn:dem":741,
    "gn:feature_class":"P",
    "gn:feature_code":"PPL",
    "gn:name":"Hausen",
    "gn:population":0,
    "gn:timezone":"Europe/Berlin",
    "iso:country":"DE",
    "name:als_x_preferred":[
        "Hausen"
    ],
    "name:ceb_x_preferred":[
        "Hausen"
    ],
    "name:dan_x_preferred":[
        "Hausen"
    ],
    "name:deu_x_preferred":[
        "Hausen"
    ],
    "name:epo_x_preferred":[
        "Hausen"
    ],
    "name:fin_x_preferred":[
        "Hausen"
    ],
    "name:fra_x_preferred":[
        "Hausen"
    ],
    "name:hun_x_preferred":[
        "Hausen"
    ],
    "name:hye_x_preferred":[
        "\u0540\u0561\u0578\u0582\u0566\u0565\u0576"
    ],
    "name:ita_x_preferred":[
        "Hausen"
    ],
    "name:jpn_x_preferred":[
        "\u30cf\u30a6\u30bc\u30f3"
    ],
    "name:lmo_x_preferred":[
        "Hausen"
    ],
    "name:nds_x_preferred":[
        "Hausen"
    ],
    "name:nld_x_preferred":[
        "Hausen"
    ],
    "name:pol_x_preferred":[
        "Hausen"
    ],
    "name:por_x_preferred":[
        "Hausen"
    ],
    "name:rus_x_preferred":[
        "\u0425\u0430\u0443\u0437\u0435\u043d"
    ],
    "name:spa_x_preferred":[
        "Hausen"
    ],
    "name:swe_x_preferred":[
        "Hausen"
    ],
    "name:ukr_x_preferred":[
        "\u0413\u0430\u0443\u0437\u0435\u043d"
    ],
    "name:vol_x_preferred":[
        "Hausen"
    ],
    "wof:name":"Hausen",
    "wof:placetype":"neighbourhood"
},
  "geometry": {"coordinates":[10.66933,47.8775],"type":"Point"}
}