{
  "type": "Feature",
  "properties": {
    "gn:admin1_code":"2",
    "gn:admin2_code":"94.0",
    "gn:admin3_code":"9479.0",
    "gn:admin4_code":"9479111.0",
    "gn:asciiname":"Kleinwendern",
    "gn:country_code":"DE",
    "gn:dem":610,
    "gn:feature_class":"P",
    "gn:feature_code":"PPL",
    "gn:name":"Kleinwendern",
    "gn:population":0,
    "gn:timezone":"Europe/Berlin",
    "iso:country":"DE",
    "wof:name":"Kleinwendern",
    "wof:placetype":"neighbourhood"
},
  "geometry": {"coordinates":[12.01883,50.00078],"type":"Point"}
}