{
  "type": "Feature",
  "properties": {
    "gn:admin1_code":"2",
    "gn:admin2_code":"91.0",
    "gn:admin3_code":"9186.0",
    "gn:admin4_code":"9186125.0",
    "gn:asciiname":"Unterwengen",
    "gn:country_code":"DE",
    "gn:dem":467,
    "gn:feature_class":"P",
    "gn:feature_code":"PPL",
    "gn:name":"Unterwengen",
    "gn:population":0,
    "gn:timezone":"Europe/Berlin",
    "iso:country":"DE",
    "wof:name":"Unterwengen",
    "wof:placetype":"neighbourhood"
},
  "geometry": {"coordinates":[11.38038,48.52134],"type":"Point"}
}