{
  "type": "Feature",
  "properties": {
    "gn:admin1_code":"15.0",
    "gn:admin2_code":"00",
    "gn:admin3_code":"16074.0",
    "gn:admin4_code":"16074086.0",
    "gn:asciiname":"Zinna",
    "gn:country_code":"DE",
    "gn:dem":273,
    "gn:feature_class":"P",
    "gn:feature_code":"PPL",
    "gn:name":"Zinna",
    "gn:population":0,
    "gn:timezone":"Europe/Berlin",
    "iso:country":"DE",
    "name:bak_x_preferred":[
        "\u0426\u0438\u043d\u043d\u0430"
    ],
    "name:ceb_x_preferred":[
        "Zinna"
    ],
    "name:deu_x_preferred":[
        "Zinna"
    ],
    "name:epo_x_preferred":[
        "Zinna"
    ],
    "name:fas_x_preferred":[
        "\u062a\u0633\u06cc\u0646\u0627"
    ],
    "name:fra_x_preferred":[
        "Zinna"
    ],
    "name:ita_x_preferred":[
        "Zinna"
    ],
    "name:mkd_x_preferred":[
        "\u0426\u0438\u043d\u0430"
    ],
    "name:msa_x_preferred":[
        "Zinna"
    ],
    "name:nld_x_preferred":[
        "Zinna"
    ],
    "name:pol_x_preferred":[
        "Zinna"
    ],
    "name:ron_x_preferred":[
        "Zinna"
    ],
    "name:rus_x_preferred":[
        "\u0426\u0438\u043d\u043d\u0430"
    ],
    "name:srp_x_preferred":[
        "\u0426\u0438\u043d\u0430"
    ],
    "name:ukr_x_preferred":[
        "\u0426\u0438\u043d\u043d\u0430"
    ],
    "name:uzb_x_preferred":[
        "Zinna"
    ],
    "name:vie_x_preferred":[
        "Zinna"
    ],
    "name:vol_x_preferred":[
        "Zinna"
    ],
    "name:war_x_preferred":[
        "Zinna"
    ],
    "wof:name":"Zinna",
    "wof:placetype":"neighbourhood"
},
  "geometry": {"coordinates":[11.73335,50.92105],"type":"Point"}
}