{
  "type": "Feature",
  "properties": {
    "gn:admin1_code":"7",
    "gn:admin2_code":"59.0",
    "gn:admin3_code":"5958.0",
    "gn:admin4_code":"5958032.0",
    "gn:asciiname":"Galilaea",
    "gn:country_code":"DE",
    "gn:dem":268,
    "gn:feature_class":"P",
    "gn:feature_code":"PPL",
    "gn:name":"Galil\u00e4a",
    "gn:population":0,
    "gn:timezone":"Europe/Berlin",
    "iso:country":"DE",
    "wof:name":"Galilaea",
    "wof:placetype":"neighbourhood"
},
  "geometry": {"coordinates":[8.25373,51.35551],"type":"Point"}
}