{
  "type": "Feature",
  "properties": {
    "gn:admin1_code":"2",
    "gn:admin2_code":"91.0",
    "gn:admin3_code":"9189.0",
    "gn:admin4_code":"9189119.0",
    "gn:asciiname":"Tettenmoos",
    "gn:country_code":"DE",
    "gn:dem":570,
    "gn:feature_class":"P",
    "gn:feature_code":"PPL",
    "gn:name":"Tettenmoos",
    "gn:population":0,
    "gn:timezone":"Europe/Berlin",
    "iso:country":"DE",
    "wof:name":"Tettenmoos",
    "wof:placetype":"neighbourhood"
},
  "geometry": {"coordinates":[12.57921,47.86471],"type":"Point"}
}