{
  "type": "Feature",
  "properties": {
    "gn:admin1_code":"11",
    "gn:admin2_code":"0.0",
    "gn:admin3_code":"12064.0",
    "gn:admin4_code":"12064340.0",
    "gn:asciiname":"Neufriedland",
    "gn:country_code":"DE",
    "gn:dem":4,
    "gn:feature_class":"P",
    "gn:feature_code":"PPL",
    "gn:name":"Neufriedland",
    "gn:population":0,
    "gn:timezone":"Europe/Berlin",
    "iso:country":"DE",
    "wof:name":"Neufriedland",
    "wof:placetype":"neighbourhood"
},
  "geometry": {"coordinates":[14.23244,52.64463000000001],"type":"Point"}
}