{
  "type": "Feature",
  "properties": {
    "gn:admin1_code":"1",
    "gn:admin2_code":"82.0",
    "gn:admin3_code":"8237.0",
    "gn:admin4_code":"8237074.0",
    "gn:asciiname":"Vesperweiler",
    "gn:country_code":"DE",
    "gn:dem":550,
    "gn:feature_class":"P",
    "gn:feature_code":"PPL",
    "gn:name":"Vesperweiler",
    "gn:population":0,
    "gn:timezone":"Europe/Berlin",
    "iso:country":"DE",
    "wof:name":"Vesperweiler",
    "wof:placetype":"neighbourhood"
},
  "geometry": {"coordinates":[8.56792,48.49603],"type":"Point"}
}