{
  "type": "Feature",
  "properties": {
    "gn:country":"DE",
    "gn:fcode":"PPL",
    "gn:population":0,
    "iso:country":"DE",
    "name:bar_x_preferred":[
        "Wiam"
    ],
    "name:cat_x_preferred":[
        "Riu W\u00fcrm"
    ],
    "name:ceb_x_preferred":[
        "W\u00fcrm"
    ],
    "name:ces_x_preferred":[
        "W\u00fcrm"
    ],
    "name:chv_x_preferred":[
        "\u0412\u044e\u0440\u043c"
    ],
    "name:dan_x_preferred":[
        "W\u00fcrm"
    ],
    "name:deu_x_preferred":[
        "W\u00fcrm"
    ],
    "name:fra_x_preferred":[
        "W\u00fcrm"
    ],
    "name:hun_x_preferred":[
        "W\u00fcrm"
    ],
    "name:ita_x_preferred":[
        "W\u00fcrm"
    ],
    "name:nld_x_preferred":[
        "W\u00fcrm"
    ],
    "name:nno_x_preferred":[
        "W\u00fcrm"
    ],
    "name:oci_x_preferred":[
        "W\u00fcrm"
    ],
    "name:rus_x_preferred":[
        "\u0412\u044e\u0440\u043c"
    ],
    "name:spa_x_preferred":[
        "R\u00edo W\u00fcrm"
    ],
    "name:vie_x_preferred":[
        "S\u00f4ng W\u00fcrm"
    ],
    "qs_pg:aaroncc":"DE",
    "qs_pg:gn_country":"DE",
    "qs_pg:gn_fcode":"PPL",
    "qs_pg:gn_pop":0,
    "qs_pg:name":"W\u00fcrm",
    "qs_pg:name_adm0":"Deutschland",
    "qs_pg:name_adm1":"Baden-W\u00fcrttemberg",
    "qs_pg:photos":56,
    "qs_pg:photos_1k":11,
    "qs_pg:photos_9k":1,
    "qs_pg:photos_9r":2,
    "qs_pg:photos_all":56,
    "qs_pg:photos_sr":2,
    "qs_pg:pop_sr":0,
    "qs_pg:qs_pg_placetype":"locality",
    "qs_pg:qs_pg_placetype_gp":"Town",
    "qs_pg:woe_adm0":23424829,
    "woe:adm0_id":23424829,
    "woe:name_adm0":"Deutschland",
    "woe:name_adm1":"Baden-W\u00fcrttemberg",
    "woe:placetype":"Town",
    "wof:name":"W\u00fcrm",
    "wof:placetype":"neighbourhood"
},
  "geometry": {"coordinates":[8.73624,48.85776],"type":"Point"}
}