{
  "type": "Feature",
  "properties": {
    "gn:admin1_code":"1",
    "gn:admin2_code":"84.0",
    "gn:admin3_code":"8435.0",
    "gn:admin4_code":"8435047.0",
    "gn:asciiname":"Hohenbodman",
    "gn:country_code":"DE",
    "gn:dem":665,
    "gn:feature_class":"P",
    "gn:feature_code":"PPL",
    "gn:name":"Hohenbodman",
    "gn:population":0,
    "gn:timezone":"Europe/Berlin",
    "iso:country":"DE",
    "name:und_x_variant":[
        "Hohenbodmann",
        "Hohenbodman"
    ],
    "wof:name":"Hohenbodman",
    "wof:placetype":"neighbourhood"
},
  "geometry": {"coordinates":[9.20972,47.82387],"type":"Point"}
}