{
  "type": "Feature",
  "properties": {
    "gn:admin1_code":"2",
    "gn:admin2_code":"97.0",
    "gn:admin3_code":"9773.0",
    "gn:admin4_code":"9773137.0",
    "gn:asciiname":"Unterbechingen",
    "gn:country_code":"DE",
    "gn:dem":466,
    "gn:feature_class":"P",
    "gn:feature_code":"PPL",
    "gn:name":"Unterbechingen",
    "gn:population":0,
    "gn:timezone":"Europe/Berlin",
    "iso:country":"DE",
    "wof:name":"Unterbechingen",
    "wof:placetype":"neighbourhood"
},
  "geometry": {"coordinates":[10.36062,48.61668],"type":"Point"}
}