{
  "type": "Feature",
  "properties": {
    "gn:country":"DE",
    "gn:fcode":"PPL",
    "gn:population":279,
    "iso:country":"DE",
    "name:bak_x_preferred":[
        "\u041a\u0430\u0442\u0435\u043d\u0434\u043e\u0440\u0444"
    ],
    "name:ceb_x_preferred":[
        "Kathendorf"
    ],
    "name:deu_x_preferred":[
        "Kathendorf"
    ],
    "name:epo_x_preferred":[
        "Kathendorf"
    ],
    "name:fas_x_preferred":[
        "\u06a9\u0627\u062a\u0646\u062f\u0648\u0631\u0641"
    ],
    "name:ita_x_preferred":[
        "Kathendorf"
    ],
    "name:kaz_x_preferred":[
        "\u041a\u0430\u0442\u0435\u043d\u0434\u043e\u0440\u0444"
    ],
    "name:kir_x_preferred":[
        "\u041a\u0430\u0442\u0435\u043d\u0434\u043e\u0440\u0444"
    ],
    "name:mkd_x_preferred":[
        "\u041a\u0430\u0442\u0435\u043d\u0434\u043e\u0440\u0444"
    ],
    "name:nld_x_preferred":[
        "Kathendorf"
    ],
    "name:pol_x_preferred":[
        "Kathendorf"
    ],
    "name:ron_x_preferred":[
        "Kathendorf"
    ],
    "name:rus_x_preferred":[
        "\u041a\u0430\u0442\u0435\u043d\u0434\u043e\u0440\u0444"
    ],
    "name:uzb_x_preferred":[
        "Kathendorf"
    ],
    "name:vie_x_preferred":[
        "Kathendorf"
    ],
    "name:vol_x_preferred":[
        "Kathendorf"
    ],
    "qs_pg:aaroncc":"DE",
    "qs_pg:gn_country":"DE",
    "qs_pg:gn_fcode":"PPL",
    "qs_pg:gn_pop":279,
    "qs_pg:name":"Kathendorf",
    "qs_pg:name_adm0":"Deutschland",
    "qs_pg:name_adm1":"Sachsen-Anhalt",
    "qs_pg:photos_9r":0,
    "qs_pg:photos_sr":0,
    "qs_pg:pop_sr":2,
    "qs_pg:qs_pg_placetype":"locality",
    "qs_pg:qs_pg_placetype_gp":"Town",
    "qs_pg:woe_adm0":23424829,
    "woe:adm0_id":23424829,
    "woe:name_adm0":"Deutschland",
    "woe:name_adm1":"Sachsen-Anhalt",
    "woe:placetype":"Town",
    "wof:name":"Kathendorf",
    "wof:placetype":"neighbourhood",
    "wof:population":279
},
  "geometry": {"coordinates":[11.13464,52.39802],"type":"Point"}
}