{
  "type": "Feature",
  "properties": {
    "iso:country":"DE",
    "name:ceb_x_preferred":[
        "Eller"
    ],
    "name:deu_x_preferred":[
        "Eller"
    ],
    "name:fra_x_preferred":[
        "Eller"
    ],
    "name:ita_x_preferred":[
        "Eller"
    ],
    "name:nds_x_preferred":[
        "Eller"
    ],
    "name:pol_x_preferred":[
        "Eller"
    ],
    "name:swe_x_preferred":[
        "Eller"
    ],
    "wof:name":"Eller",
    "wof:placetype":"neighbourhood"
},
  "geometry": {"coordinates":[6.84053569209681,51.2013694409036],"type":"Point"}
}