{
  "type": "Feature",
  "properties": {
    "iso:country":"DE",
    "wof:name":"Eller",
    "wof:placetype":"neighbourhood"
},
  "geometry": {"coordinates":[6.84053569209681,51.2013694409036],"type":"Point"}
}