{
  "type": "Feature",
  "properties": {
    "gn:country":"DE",
    "gn:fcode":"PPL",
    "gn:population":350,
    "iso:country":"DE",
    "name:bak_x_preferred":[
        "\u0413\u0438\u043a\u043a\u0430\u0443"
    ],
    "name:ceb_x_preferred":[
        "Gieckau"
    ],
    "name:che_x_preferred":[
        "\u0413\u0438\u043a\u043a\u0430\u0443"
    ],
    "name:deu_x_preferred":[
        "Gieckau"
    ],
    "name:eng_x_preferred":[
        "Gieckau"
    ],
    "name:epo_x_preferred":[
        "Gieckau"
    ],
    "name:fas_x_preferred":[
        "\u06af\u06cc\u06a9\u0627\u0648"
    ],
    "name:fra_x_preferred":[
        "Gieckau"
    ],
    "name:gle_x_preferred":[
        "Gieckau"
    ],
    "name:ita_x_preferred":[
        "Gieckau"
    ],
    "name:kaz_x_preferred":[
        "\u0413\u0438\u043a\u043a\u0430\u0443"
    ],
    "name:kir_x_preferred":[
        "\u0413\u0438\u043a\u043a\u0430\u0443"
    ],
    "name:nld_x_preferred":[
        "Gieckau"
    ],
    "name:ron_x_preferred":[
        "Gieckau"
    ],
    "name:rus_x_preferred":[
        "\u0413\u0438\u043a\u043a\u0430\u0443"
    ],
    "name:tat_x_preferred":[
        "\u0413\u0438\u043a\u043a\u0430\u0443"
    ],
    "name:uzb_x_preferred":[
        "Gieckau"
    ],
    "name:vie_x_preferred":[
        "Gieckau"
    ],
    "name:vol_x_preferred":[
        "Gieckau"
    ],
    "qs_pg:aaroncc":"DE",
    "qs_pg:gn_country":"DE",
    "qs_pg:gn_fcode":"PPL",
    "qs_pg:gn_pop":350,
    "qs_pg:name":"Gieckau",
    "qs_pg:name_adm0":"Deutschland",
    "qs_pg:name_adm1":"Sachsen-Anhalt",
    "qs_pg:photos_9k":1,
    "qs_pg:photos_9r":1,
    "qs_pg:photos_all":1,
    "qs_pg:photos_sr":0,
    "qs_pg:pop_sr":2,
    "qs_pg:qs_pg_placetype":"locality",
    "qs_pg:qs_pg_placetype_gp":"Town",
    "qs_pg:woe_adm0":23424829,
    "woe:adm0_id":23424829,
    "woe:name_adm0":"Deutschland",
    "woe:name_adm1":"Sachsen-Anhalt",
    "woe:placetype":"Town",
    "wof:name":"Gieckau",
    "wof:placetype":"neighbourhood",
    "wof:population":350
},
  "geometry": {"coordinates":[11.88377,51.13396],"type":"Point"}
}