{
  "type": "Feature",
  "properties": {
    "gn:admin1_code":"2",
    "gn:admin2_code":"91.0",
    "gn:admin3_code":"9190.0",
    "gn:admin4_code":"9190140.0",
    "gn:asciiname":"Luttenbach",
    "gn:country_code":"DE",
    "gn:dem":770,
    "gn:feature_class":"P",
    "gn:feature_code":"PPL",
    "gn:name":"Luttenbach",
    "gn:population":0,
    "gn:timezone":"Europe/Berlin",
    "iso:country":"DE",
    "wof:name":"Luttenbach",
    "wof:placetype":"neighbourhood"
},
  "geometry": {"coordinates":[10.89731,47.76874],"type":"Point"}
}