{
  "type": "Feature",
  "properties": {
    "gn:admin1_code":"2",
    "gn:admin2_code":"93.0",
    "gn:admin3_code":"9377.0",
    "gn:admin4_code":"9377146.0",
    "gn:asciiname":"Liebenstein",
    "gn:country_code":"DE",
    "gn:dem":514,
    "gn:feature_class":"P",
    "gn:feature_code":"PPL",
    "gn:name":"Liebenstein",
    "gn:population":0,
    "gn:timezone":"Europe/Berlin",
    "iso:country":"DE",
    "name:bak_x_preferred":[
        "\u041b\u0438\u0431\u0435\u043d\u0448\u0442\u0430\u0439\u043d"
    ],
    "name:ceb_x_preferred":[
        "Liebenstein"
    ],
    "name:deu_x_preferred":[
        "Liebenstein"
    ],
    "name:epo_x_preferred":[
        "Liebenstein"
    ],
    "name:eus_x_preferred":[
        "Liebenstein"
    ],
    "name:fas_x_preferred":[
        "\u0644\u06cc\u0628\u0646\u0634\u062a\u0627\u06cc\u0646"
    ],
    "name:fra_x_preferred":[
        "Liebenstein"
    ],
    "name:hun_x_preferred":[
        "Liebenstein"
    ],
    "name:ita_x_preferred":[
        "Liebenstein"
    ],
    "name:kaz_x_preferred":[
        "\u041b\u0438\u0431\u0435\u043d\u0448\u0442\u0430\u0439\u043d"
    ],
    "name:kir_x_preferred":[
        "\u041b\u0438\u0431\u0435\u043d\u0448\u0442\u0430\u0439\u043d"
    ],
    "name:mkd_x_preferred":[
        "\u041b\u0438\u0431\u0435\u043d\u0448\u0442\u0430\u0458\u043d"
    ],
    "name:msa_x_preferred":[
        "Liebenstein"
    ],
    "name:nld_x_preferred":[
        "Liebenstein"
    ],
    "name:pol_x_preferred":[
        "Liebenstein"
    ],
    "name:por_x_preferred":[
        "Liebenstein"
    ],
    "name:ron_x_preferred":[
        "Liebenstein"
    ],
    "name:rus_x_preferred":[
        "\u041b\u0438\u0431\u0435\u043d\u0448\u0442\u0430\u0439\u043d"
    ],
    "name:spa_x_preferred":[
        "Liebenstein"
    ],
    "name:srp_x_preferred":[
        "\u041b\u0438\u0431\u0435\u043d\u0448\u0442\u0430\u0458\u043d"
    ],
    "name:ukr_x_preferred":[
        "\u041b\u0456\u0431\u0435\u043d\u0448\u0442\u0430\u0439\u043d"
    ],
    "name:uzb_x_preferred":[
        "Liebenstein"
    ],
    "name:vie_x_preferred":[
        "Liebenstein"
    ],
    "name:vol_x_preferred":[
        "Liebenstein"
    ],
    "name:war_x_preferred":[
        "Liebenstein"
    ],
    "name:zho_x_preferred":[
        "\u5229\u672c\u65bd\u6cf0\u56e0"
    ],
    "wof:name":"Liebenstein",
    "wof:placetype":"neighbourhood"
},
  "geometry": {"coordinates":[12.33391,49.83191],"type":"Point"}
}