{
  "type": "Feature",
  "properties": {
    "gn:admin1_code":"2",
    "gn:admin2_code":"91.0",
    "gn:admin3_code":"9188.0",
    "gn:admin4_code":"9188124.0",
    "gn:asciiname":"Rausch",
    "gn:country_code":"DE",
    "gn:dem":583,
    "gn:feature_class":"P",
    "gn:feature_code":"PPL",
    "gn:name":"Rausch",
    "gn:population":0,
    "gn:timezone":"Europe/Berlin",
    "iso:country":"DE",
    "name:ceb_x_preferred":[
        "Rausch"
    ],
    "name:deu_x_preferred":[
        "Rausch"
    ],
    "name:epo_x_preferred":[
        "Rausch"
    ],
    "name:fra_x_preferred":[
        "Rausch"
    ],
    "name:ita_x_preferred":[
        "Rausch"
    ],
    "name:pol_x_preferred":[
        "Rausch"
    ],
    "name:rus_x_preferred":[
        "\u0420\u0430\u0443\u0448"
    ],
    "name:swe_x_preferred":[
        "Rausch"
    ],
    "name:ukr_x_preferred":[
        "\u0420\u0430\u0443\u0448"
    ],
    "wof:name":"Rausch",
    "wof:placetype":"neighbourhood"
},
  "geometry": {"coordinates":[11.15859,48.01272],"type":"Point"}
}