{
  "type": "Feature",
  "properties": {
    "gn:admin1_code":"2",
    "gn:admin2_code":"93.0",
    "gn:admin3_code":"9376.0",
    "gn:admin4_code":"9376117.0",
    "gn:asciiname":"Mogendorf",
    "gn:country_code":"DE",
    "gn:dem":379,
    "gn:feature_class":"P",
    "gn:feature_code":"PPL",
    "gn:name":"M\u00f6gendorf",
    "gn:population":0,
    "gn:timezone":"Europe/Berlin",
    "iso:country":"DE",
    "name:ara_x_preferred":[
        "\u0645\u0648\u063a\u0646\u062f\u0648\u0631\u0641"
    ],
    "name:ceb_x_preferred":[
        "Mogendorf"
    ],
    "name:deu_x_preferred":[
        "Mogendorf"
    ],
    "name:epo_x_preferred":[
        "Mogendorf"
    ],
    "name:eus_x_preferred":[
        "Mogendorf"
    ],
    "name:fas_x_preferred":[
        "\u0645\u0648\u06af\u0646\u062f\u0648\u0631\u0641"
    ],
    "name:fra_x_preferred":[
        "Mogendorf"
    ],
    "name:hun_x_preferred":[
        "Mogendorf"
    ],
    "name:ita_x_preferred":[
        "Mogendorf"
    ],
    "name:msa_x_preferred":[
        "Mogendorf"
    ],
    "name:nld_x_preferred":[
        "Mogendorf"
    ],
    "name:pol_x_preferred":[
        "Mogendorf"
    ],
    "name:por_x_preferred":[
        "Mogendorf"
    ],
    "name:ron_x_preferred":[
        "Mogendorf"
    ],
    "name:rus_x_preferred":[
        "\u041c\u043e\u0433\u0435\u043d\u0434\u043e\u0440\u0444"
    ],
    "name:srp_x_preferred":[
        "\u041c\u043e\u0433\u0435\u043d\u0434\u043e\u0440\u0444"
    ],
    "name:ukr_x_preferred":[
        "\u041c\u043e\u0433\u0435\u043d\u0434\u043e\u0440\u0444"
    ],
    "name:uzb_x_preferred":[
        "Mogendorf"
    ],
    "name:vol_x_preferred":[
        "Mogendorf"
    ],
    "name:war_x_preferred":[
        "Mogendorf"
    ],
    "name:zho_x_preferred":[
        "\u83ab\u6839\u591a\u592b"
    ],
    "wof:name":"Mogendorf",
    "wof:placetype":"neighbourhood"
},
  "geometry": {"coordinates":[12.2948,49.26222],"type":"Point"}
}