{
  "type": "Feature",
  "properties": {
    "gn:admin1_code":"2",
    "gn:admin2_code":"93.0",
    "gn:admin3_code":"9371.0",
    "gn:admin4_code":"9371120.0",
    "gn:asciiname":"Gotzenod",
    "gn:country_code":"DE",
    "gn:dem":458,
    "gn:feature_class":"P",
    "gn:feature_code":"PPL",
    "gn:name":"G\u00f6tzen\u00f6d",
    "gn:population":0,
    "gn:timezone":"Europe/Berlin",
    "iso:country":"DE",
    "wof:name":"Gotzenod",
    "wof:placetype":"neighbourhood"
},
  "geometry": {"coordinates":[11.96037,49.36453],"type":"Point"}
}