{
  "type": "Feature",
  "properties": {
    "gn:admin1_code":"12",
    "gn:admin2_code":"0.0",
    "gn:admin3_code":"13074.0",
    "gn:admin4_code":"13074023.0",
    "gn:asciiname":"Warnkenhagen",
    "gn:country_code":"DE",
    "gn:dem":59,
    "gn:feature_class":"P",
    "gn:feature_code":"PPL",
    "gn:name":"Warnkenhagen",
    "gn:population":0,
    "gn:timezone":"Europe/Berlin",
    "iso:country":"DE",
    "name:deu_x_preferred":[
        "Warnkenhagen"
    ],
    "name:epo_x_preferred":[
        "Warnkenhagen"
    ],
    "name:fas_x_preferred":[
        "\u0648\u0627\u0631\u0646\u06a9\u0646\u0647\u0627\u06af\u0646"
    ],
    "name:fra_x_preferred":[
        "Warnkenhagen"
    ],
    "name:hun_x_preferred":[
        "Warnkenhagen"
    ],
    "name:ita_x_preferred":[
        "Warnkenhagen"
    ],
    "name:mkd_x_preferred":[
        "\u0412\u0430\u0440\u043d\u043a\u0435\u043d\u0445\u0430\u0433\u0435\u043d"
    ],
    "name:msa_x_preferred":[
        "Warnkenhagen"
    ],
    "name:nld_x_preferred":[
        "Warnkenhagen"
    ],
    "name:pol_x_preferred":[
        "Warnkenhagen"
    ],
    "name:ron_x_preferred":[
        "Warnkenhagen"
    ],
    "name:rus_x_preferred":[
        "\u0412\u0430\u0440\u043d\u043a\u0435\u043d\u0445\u0430\u0433\u0435\u043d"
    ],
    "name:spa_x_preferred":[
        "Warnkenhagen"
    ],
    "name:srp_x_preferred":[
        "\u0412\u0430\u0440\u043d\u043a\u0435\u043d\u0445\u0430\u0433\u0435\u043d"
    ],
    "name:ukr_x_preferred":[
        "\u0412\u0430\u0440\u043d\u043a\u0435\u043d\u0433\u0430\u0433\u0435\u043d"
    ],
    "name:uzb_x_preferred":[
        "Warnkenhagen"
    ],
    "name:vie_x_preferred":[
        "Warnkenhagen"
    ],
    "name:vol_x_preferred":[
        "Warnkenhagen"
    ],
    "name:war_x_preferred":[
        "Warnkenhagen"
    ],
    "name:zho_x_preferred":[
        "\u74e6\u6069\u80af\u54c8\u6839"
    ],
    "wof:name":"Warnkenhagen",
    "wof:placetype":"neighbourhood"
},
  "geometry": {"coordinates":[11.78026,53.92112],"type":"Point"}
}