{
  "type": "Feature",
  "properties": {
    "gn:admin1_code":"2.0",
    "gn:admin2_code":"92.0",
    "gn:admin3_code":"9279.0",
    "gn:admin4_code":"9279134.0",
    "gn:asciiname":"Atzmannsberg",
    "gn:country_code":"DE",
    "gn:dem":440,
    "gn:feature_class":"P",
    "gn:feature_code":"PPL",
    "gn:name":"Atzmannsberg",
    "gn:population":0,
    "gn:timezone":"Europe/Berlin",
    "iso:country":"DE",
    "wof:name":"Atzmannsberg",
    "wof:placetype":"neighbourhood"
},
  "geometry": {"coordinates":[12.62683,48.59427],"type":"Point"}
}