{
  "type": "Feature",
  "properties": {
    "gn:admin1_code":"2.0",
    "gn:admin2_code":"92.0",
    "gn:admin3_code":"9272.0",
    "gn:admin4_code":"9272141.0",
    "gn:asciiname":"Auggenthal",
    "gn:country_code":"DE",
    "gn:dem":481,
    "gn:feature_class":"P",
    "gn:feature_code":"PPL",
    "gn:name":"Auggenthal",
    "gn:population":0,
    "gn:timezone":"Europe/Berlin",
    "iso:country":"DE",
    "wof:name":"Auggenthal",
    "wof:placetype":"neighbourhood"
},
  "geometry": {"coordinates":[13.50109,48.77202],"type":"Point"}
}