{
  "type": "Feature",
  "properties": {
    "gn:gn_country":"DE",
    "gn:gn_fcode":"PPLX",
    "gn:gn_pop":0,
    "iso:country":"DE",
    "name:ceb_x_preferred":[
        "Winden"
    ],
    "name:deu_x_preferred":[
        "Winden"
    ],
    "name:epo_x_preferred":[
        "Winden"
    ],
    "name:fra_x_preferred":[
        "Winden"
    ],
    "name:ita_x_preferred":[
        "Winden"
    ],
    "name:nld_x_preferred":[
        "Winden"
    ],
    "name:pol_x_preferred":[
        "Winden"
    ],
    "name:rus_x_preferred":[
        "\u0412\u0438\u043d\u0434\u0435\u043d"
    ],
    "name:srp_x_preferred":[
        "\u0412\u0438\u043d\u0434\u0438"
    ],
    "name:swe_x_preferred":[
        "Winden"
    ],
    "qs_pg:aaroncc":"DE",
    "qs_pg:gn_country":"DE",
    "qs_pg:gn_fcode":"PPLX",
    "qs_pg:gn_pop":0,
    "qs_pg:name":"Winden",
    "qs_pg:name_adm0":"Deutschland",
    "qs_pg:name_adm1":"Bayern",
    "qs_pg:photos":4,
    "qs_pg:photos_1k":1,
    "qs_pg:photos_9k":1,
    "qs_pg:photos_9r":1,
    "qs_pg:photos_all":4,
    "qs_pg:photos_sr":1,
    "qs_pg:pop_sr":0,
    "qs_pg:qs_pg_placetype":"neighbourhood",
    "qs_pg:qs_pg_placetype_gp":"Suburb",
    "qs_pg:woe_adm0":23424829,
    "woe:adm0_id":23424829,
    "woe:name_adm0":"Deutschland",
    "woe:name_adm1":"Bayern",
    "woe:placetype":"Suburb",
    "wof:name":"Winden",
    "wof:placetype":"neighbourhood"
},
  "geometry": {"coordinates":[11.38895,48.70157],"type":"Point"}
}