{
  "type": "Feature",
  "properties": {
    "gn:admin1_code":"2",
    "gn:admin2_code":"93.0",
    "gn:admin3_code":"9377.0",
    "gn:admin4_code":"9377149.0",
    "gn:asciiname":"Reuth bei Erbendorf",
    "gn:country_code":"DE",
    "gn:dem":485,
    "gn:feature_class":"P",
    "gn:feature_code":"PPL",
    "gn:name":"Reuth bei Erbendorf",
    "gn:population":0,
    "gn:timezone":"Europe/Berlin",
    "iso:country":"DE",
    "name:deu_x_preferred":[
        "Reuth bei Erbendorf"
    ],
    "name:epo_x_preferred":[
        "Reuth apud Erbendorf"
    ],
    "name:eus_x_preferred":[
        "Reuth bei Erbendorf"
    ],
    "name:fas_x_preferred":[
        "\u0631\u0648\u06cc\u062a \u0628\u0627\u06cc \u0631\u0628\u0646\u062f\u0648\u0631\u0641"
    ],
    "name:fra_x_preferred":[
        "Reuth bei Erbendorf"
    ],
    "name:hun_x_preferred":[
        "Reuth bei Erbendorf"
    ],
    "name:hye_x_preferred":[
        "\u054c\u0578\u0575\u0569 \u0537\u0580\u0562\u0565\u0576\u0564\u0578\u0580\u0586"
    ],
    "name:ita_x_preferred":[
        "Reuth bei Erbendorf"
    ],
    "name:kaz_x_preferred":[
        "\u0420\u043e\u0439\u0442-\u042d\u0440\u0431\u0435\u043d\u0434\u043e\u0440\u0444"
    ],
    "name:kir_x_preferred":[
        "\u0420\u043e\u0439\u0442-\u042d\u0440\u0431\u0435\u043d\u0434\u043e\u0440\u0444"
    ],
    "name:lmo_x_preferred":[
        "Reuth bei Erbendorf"
    ],
    "name:msa_x_preferred":[
        "Reuth bei Erbendorf"
    ],
    "name:nld_x_preferred":[
        "Reuth bei Erbendorf"
    ],
    "name:pol_x_preferred":[
        "Reuth bei Erbendorf"
    ],
    "name:ron_x_preferred":[
        "Reuth bei Erbendorf"
    ],
    "name:rus_x_preferred":[
        "\u0420\u043e\u0439\u0442-\u042d\u0440\u0431\u0435\u043d\u0434\u043e\u0440\u0444"
    ],
    "name:rus_x_variant":[
        "\u0420\u043e\u0439\u0442-\u0431\u0430\u0439-\u042d\u0440\u0431\u0435\u043d\u0434\u043e\u0440\u0444"
    ],
    "name:spa_x_preferred":[
        "Reuth bei Erbendorf"
    ],
    "name:srp_x_preferred":[
        "\u0420\u043e\u0458\u0442 \u0431\u0430\u0458 \u0415\u0440\u0431\u0435\u043d\u0434\u043e\u0440\u0444"
    ],
    "name:ukr_x_preferred":[
        "\u0420\u043e\u0439\u0442-\u0431\u0430\u0439-\u0415\u0440\u0431\u0435\u043d\u0434\u043e\u0440\u0444"
    ],
    "name:uzb_x_preferred":[
        "Reuth bei Erbendorf"
    ],
    "name:vie_x_preferred":[
        "Reuth bei Erbendorf"
    ],
    "name:vol_x_preferred":[
        "Reuth bei Erbendorf"
    ],
    "name:war_x_preferred":[
        "Reuth bei Erbendorf"
    ],
    "name:zho_x_preferred":[
        "\u57c3\u5c14\u672c\u591a\u592b\u9644\u8fd1\u7f57\u4f0a\u7279"
    ],
    "wof:name":"Reuth bei Erbendorf",
    "wof:placetype":"neighbourhood"
},
  "geometry": {"coordinates":[12.12136,49.84378],"type":"Point"}
}