{
  "type": "Feature",
  "properties": {
    "gn:admin1_code":"7",
    "gn:admin2_code":"53.0",
    "gn:admin3_code":"5366.0",
    "gn:admin4_code":"5366044.0",
    "gn:asciiname":"Niederelvenich",
    "gn:country_code":"DE",
    "gn:dem":151,
    "gn:feature_class":"P",
    "gn:feature_code":"PPL",
    "gn:name":"Niederelvenich",
    "gn:population":0,
    "gn:timezone":"Europe/Berlin",
    "iso:country":"DE",
    "wof:name":"Niederelvenich",
    "wof:placetype":"neighbourhood"
},
  "geometry": {"coordinates":[6.7152,50.7055],"type":"Point"}
}