{
  "type": "Feature",
  "properties": {
    "gn:admin1_code":"15",
    "gn:admin2_code":"0.0",
    "gn:admin3_code":"16065.0",
    "gn:admin4_code":"16065067.0",
    "gn:asciiname":"Grossberndten",
    "gn:country_code":"DE",
    "gn:dem":396,
    "gn:feature_class":"P",
    "gn:feature_code":"PPL",
    "gn:name":"Gro\u00dfberndten",
    "gn:population":0,
    "gn:timezone":"Europe/Berlin",
    "iso:country":"DE",
    "wof:name":"Grossberndten",
    "wof:placetype":"neighbourhood"
},
  "geometry": {"coordinates":[10.70103,51.35897],"type":"Point"}
}