{
  "type": "Feature",
  "properties": {
    "gn:admin1_code":"11",
    "gn:admin2_code":"0.0",
    "gn:admin3_code":"12070.0",
    "gn:admin4_code":"12070316.0",
    "gn:asciiname":"Kuckuk",
    "gn:country_code":"DE",
    "gn:dem":77,
    "gn:feature_class":"P",
    "gn:feature_code":"PPL",
    "gn:name":"Kuckuk",
    "gn:population":0,
    "gn:timezone":"Europe/Berlin",
    "iso:country":"DE",
    "name:und_x_variant":[
        "Kuckuck",
        "Kukuk",
        "Kuckuk"
    ],
    "wof:name":"Kuckuk",
    "wof:placetype":"neighbourhood"
},
  "geometry": {"coordinates":[12.26299,53.20014000000001],"type":"Point"}
}