{
  "type": "Feature",
  "properties": {
    "gn:admin1_code":"1",
    "gn:admin2_code":"81.0",
    "gn:admin3_code":"8125.0",
    "gn:admin4_code":"8125038.0",
    "gn:asciiname":"Eibensbach",
    "gn:country_code":"DE",
    "gn:dem":269,
    "gn:feature_class":"P",
    "gn:feature_code":"PPL",
    "gn:name":"Eibensbach",
    "gn:population":0,
    "gn:timezone":"Europe/Berlin",
    "iso:country":"DE",
    "wof:name":"Eibensbach",
    "wof:placetype":"neighbourhood"
},
  "geometry": {"coordinates":[8.99121,49.04712],"type":"Point"}
}