{
  "type": "Feature",
  "properties": {
    "iso:country":"DE",
    "name:deu_x_colloquial":[
        "Moenkhof",
        "Monkhof"
    ],
    "name:deu_x_preferred":[
        "M\u00f6nkhof"
    ],
    "name:unk_x_variant":[
        "M\u00f6nkhof"
    ],
    "qs:gn_adm0_cc":"DE",
    "qs:gn_local":2875601,
    "qs:local_max":2963,
    "qs:local_sum":12788,
    "qs:localhoods":32,
    "qs:name":"M\u00f6nkhof",
    "qs:name_adm0":"Deutschland",
    "qs:name_adm1":"Schleswig-Holstein",
    "qs:name_adm2":"Stadtkreis L\u00fcbeck",
    "qs:name_lau":"Stadtteil St. J\u00fcrgen",
    "qs:name_local":"L\u00fcbeck",
    "qs:photo_max":23,
    "qs:photo_sum":95,
    "qs:placetype":"Suburb",
    "qs:quad_count":17,
    "qs:woe_adm0":23424829,
    "qs:woe_adm1":2345490,
    "qs:woe_adm2":12597082,
    "qs:woe_lau":26822944,
    "qs:woe_local":672826,
    "qs:woe_ver":"7.10.0",
    "wof:lang":[
        "ger"
    ],
    "wof:name":"M\u00f6nkhof",
    "wof:placetype":"neighbourhood"
},
  "geometry": {"coordinates":[10.700607,53.835308],"type":"Point"}
}