{
  "type": "Feature",
  "properties": {
    "gn:admin1_code":"2",
    "gn:admin2_code":"93.0",
    "gn:admin3_code":"9374.0",
    "gn:admin4_code":"9374121.0",
    "gn:asciiname":"Fehrsdorf",
    "gn:country_code":"DE",
    "gn:dem":513,
    "gn:feature_class":"P",
    "gn:feature_code":"PPL",
    "gn:name":"Fehrsdorf",
    "gn:population":0,
    "gn:timezone":"Europe/Berlin",
    "iso:country":"DE",
    "wof:name":"Fehrsdorf",
    "wof:placetype":"neighbourhood"
},
  "geometry": {"coordinates":[12.23793,49.70013],"type":"Point"}
}