{
  "type": "Feature",
  "properties": {
    "gn:admin1_code":"1",
    "gn:admin2_code":"84.0",
    "gn:admin3_code":"8426.0",
    "gn:admin4_code":"8426021.0",
    "gn:asciiname":"Mettenberg",
    "gn:country_code":"DE",
    "gn:dem":602,
    "gn:feature_class":"P",
    "gn:feature_code":"PPL",
    "gn:name":"Mettenberg",
    "gn:population":0,
    "gn:timezone":"Europe/Berlin",
    "iso:country":"DE",
    "name:deu_x_preferred":[
        "M\u00e4ttenberg"
    ],
    "name:fin_x_preferred":[
        "M\u00e4ttenberg"
    ],
    "name:heb_x_preferred":[
        "\u05de\u05d8\u05e0\u05d1\u05e8\u05d2"
    ],
    "name:kat_x_preferred":[
        "\u10db\u10d4\u10e2\u10d4\u10dc\u10d1\u10d4\u10e0\u10d2\u10d8"
    ],
    "name:nno_x_preferred":[
        "M\u00e4ttenberg"
    ],
    "name:pol_x_preferred":[
        "M\u00e4ttenberg"
    ],
    "name:zho_x_preferred":[
        "\u6885\u6ed5\u5c71"
    ],
    "wof:name":"Mettenberg",
    "wof:placetype":"neighbourhood"
},
  "geometry": {"coordinates":[9.82258,48.11309],"type":"Point"}
}