{
  "type": "Feature",
  "properties": {
    "gn:admin1_code":"6.0",
    "gn:admin2_code":"0.0",
    "gn:admin3_code":"3458.0",
    "gn:admin4_code":"3458007.0",
    "gn:asciiname":"Hespenbusch",
    "gn:country_code":"DE",
    "gn:dem":30,
    "gn:feature_class":"P",
    "gn:feature_code":"PPL",
    "gn:name":"Hespenbusch",
    "gn:population":0,
    "gn:timezone":"Europe/Berlin",
    "iso:country":"DE",
    "name:deu_x_preferred":[
        "Hespenbusch"
    ],
    "wof:name":"Hespenbusch",
    "wof:placetype":"neighbourhood"
},
  "geometry": {"coordinates":[8.3059,52.93566],"type":"Point"}
}