{
  "type": "Feature",
  "properties": {
    "gn:admin1_code":"7",
    "gn:admin2_code":"55.0",
    "gn:admin3_code":"5566.0",
    "gn:admin4_code":"5566024.0",
    "gn:asciiname":"Leer",
    "gn:country_code":"DE",
    "gn:dem":74,
    "gn:feature_class":"P",
    "gn:feature_code":"PPL",
    "gn:name":"Leer",
    "gn:population":0,
    "gn:timezone":"Europe/Berlin",
    "iso:country":"DE",
    "name:afr_x_preferred":[
        "Leer"
    ],
    "name:ara_x_preferred":[
        "\u0644\u064a\u0631"
    ],
    "name:azb_x_preferred":[
        "\u0644\u0631"
    ],
    "name:ceb_x_preferred":[
        "Leer"
    ],
    "name:ces_x_preferred":[
        "Leer"
    ],
    "name:dan_x_preferred":[
        "Leer"
    ],
    "name:deu_x_preferred":[
        "Leer"
    ],
    "name:epo_x_preferred":[
        "Leer"
    ],
    "name:est_x_preferred":[
        "Leer"
    ],
    "name:eus_x_preferred":[
        "Leer"
    ],
    "name:fas_x_preferred":[
        "\u0644\u0631"
    ],
    "name:fra_x_preferred":[
        "Leer"
    ],
    "name:fry_x_preferred":[
        "Lier"
    ],
    "name:hun_x_preferred":[
        "Leer"
    ],
    "name:ita_x_preferred":[
        "Leer"
    ],
    "name:jpn_x_preferred":[
        "\u30ec\u30fc\u30a2"
    ],
    "name:kaz_x_preferred":[
        "\u041b\u0435\u0440"
    ],
    "name:lat_x_preferred":[
        "Leri"
    ],
    "name:msa_x_preferred":[
        "Leer"
    ],
    "name:nds_x_preferred":[
        "Leer"
    ],
    "name:nld_x_preferred":[
        "Leer"
    ],
    "name:pol_x_preferred":[
        "Leer"
    ],
    "name:por_x_preferred":[
        "Leer"
    ],
    "name:ron_x_preferred":[
        "Leer"
    ],
    "name:rus_x_preferred":[
        "\u041b\u0435\u0440"
    ],
    "name:spa_x_preferred":[
        "Leer"
    ],
    "name:srp_x_preferred":[
        "\u041b\u0435\u0440"
    ],
    "name:stq_x_preferred":[
        "Lier"
    ],
    "name:swe_x_preferred":[
        "Leer"
    ],
    "name:tur_x_preferred":[
        "Leer"
    ],
    "name:ukr_x_preferred":[
        "\u041b\u0435\u0440"
    ],
    "name:uzb_x_preferred":[
        "Leer"
    ],
    "name:vie_x_preferred":[
        "Leer"
    ],
    "name:vol_x_preferred":[
        "Leer"
    ],
    "name:war_x_preferred":[
        "Leer"
    ],
    "wof:name":"Leer",
    "wof:placetype":"neighbourhood"
},
  "geometry": {"coordinates":[7.29492,52.11399],"type":"Point"}
}