{
  "type": "Feature",
  "properties": {
    "gn:admin1_code":"6",
    "gn:admin2_code":"0.0",
    "gn:admin3_code":"3254.0",
    "gn:admin4_code":"3254045.0",
    "gn:asciiname":"Sellenstedt",
    "gn:country_code":"DE",
    "gn:dem":181,
    "gn:feature_class":"P",
    "gn:feature_code":"PPL",
    "gn:name":"Sellenstedt",
    "gn:population":0,
    "gn:timezone":"Europe/Berlin",
    "iso:country":"DE",
    "name:nds_x_preferred":[
        "Sellenstie"
    ],
    "name:nds_x_variant":[
        "Sellstie"
    ],
    "wof:name":"Sellenstedt",
    "wof:placetype":"neighbourhood"
},
  "geometry": {"coordinates":[9.93473,52.01426],"type":"Point"}
}