{
  "type": "Feature",
  "properties": {
    "gn:admin1_code":"2",
    "gn:admin2_code":"95.0",
    "gn:admin3_code":"9577.0",
    "gn:admin4_code":"9577172.0",
    "gn:asciiname":"Dornhausen",
    "gn:country_code":"DE",
    "gn:dem":427,
    "gn:feature_class":"P",
    "gn:feature_code":"PPL",
    "gn:name":"Dornhausen",
    "gn:population":0,
    "gn:timezone":"Europe/Berlin",
    "iso:country":"DE",
    "wof:name":"Dornhausen",
    "wof:placetype":"neighbourhood"
},
  "geometry": {"coordinates":[10.81944,49.08695],"type":"Point"}
}