{
  "type": "Feature",
  "properties": {
    "gn:admin1_code":"5",
    "gn:admin2_code":"64.0",
    "gn:admin3_code":"6436.0",
    "gn:admin4_code":"6436010.0",
    "gn:asciiname":"Niederhofheim",
    "gn:country_code":"DE",
    "gn:dem":172,
    "gn:feature_class":"P",
    "gn:feature_code":"PPL",
    "gn:name":"Niederhofheim",
    "gn:population":0,
    "gn:timezone":"Europe/Berlin",
    "iso:country":"DE",
    "wof:name":"Niederhofheim",
    "wof:placetype":"neighbourhood"
},
  "geometry": {"coordinates":[8.48563,50.12886],"type":"Point"}
}