{
  "type": "Feature",
  "properties": {
    "iso:country":"DE",
    "name:deu_x_preferred":[
        "Neu-M\u00fcngersdorf"
    ],
    "wof:name":"Neu-Muengersdorf",
    "wof:placetype":"neighbourhood"
},
  "geometry": {"coordinates":[6.8581749305968,50.94250056760657],"type":"Point"}
}