{
  "type": "Feature",
  "properties": {
    "gn:admin1_code":"15",
    "gn:admin2_code":"0.0",
    "gn:admin3_code":"16069.0",
    "gn:admin4_code":"16069058.0",
    "gn:asciiname":"Schwarzbach",
    "gn:country_code":"DE",
    "gn:dem":463,
    "gn:feature_class":"P",
    "gn:feature_code":"PPL",
    "gn:name":"Schwarzbach",
    "gn:population":0,
    "gn:timezone":"Europe/Berlin",
    "iso:country":"DE",
    "name:ceb_x_preferred":[
        "Schwarzbach"
    ],
    "name:ces_x_preferred":[
        "Schwartzbach"
    ],
    "name:deu_x_preferred":[
        "Schwarzbach"
    ],
    "name:epo_x_preferred":[
        "Schwarzbach"
    ],
    "name:fra_x_preferred":[
        "Schwarzbach"
    ],
    "name:ita_x_preferred":[
        "Schwarzbach"
    ],
    "name:nld_x_preferred":[
        "Schwarzbach"
    ],
    "name:pol_x_preferred":[
        "Schwarzbach"
    ],
    "name:rus_x_preferred":[
        "\u0428\u0432\u0430\u0440\u0446\u0431\u0430\u0445"
    ],
    "name:swe_x_preferred":[
        "Schwarzbach"
    ],
    "name:vol_x_preferred":[
        "Schwarzbach"
    ],
    "wof:name":"Schwarzbach",
    "wof:placetype":"neighbourhood"
},
  "geometry": {"coordinates":[10.82879,50.48199],"type":"Point"}
}