{
  "type": "Feature",
  "properties": {
    "gn:admin1_code":"2",
    "gn:admin2_code":"93.0",
    "gn:admin3_code":"9372.0",
    "gn:admin4_code":"9372178.0",
    "gn:asciiname":"Oberhaiderberg",
    "gn:country_code":"DE",
    "gn:dem":868,
    "gn:feature_class":"P",
    "gn:feature_code":"PPL",
    "gn:name":"Oberhaiderberg",
    "gn:population":0,
    "gn:timezone":"Europe/Berlin",
    "iso:country":"DE",
    "wof:name":"Oberhaiderberg",
    "wof:placetype":"neighbourhood"
},
  "geometry": {"coordinates":[13.12849,49.16711],"type":"Point"}
}