{
  "type": "Feature",
  "properties": {
    "gn:admin1_code":"1",
    "gn:admin2_code":"81.0",
    "gn:admin3_code":"8136.0",
    "gn:admin4_code":"8136027.0",
    "gn:asciiname":"Seelach",
    "gn:country_code":"DE",
    "gn:dem":559,
    "gn:feature_class":"P",
    "gn:feature_code":"PPL",
    "gn:name":"Seelach",
    "gn:population":0,
    "gn:timezone":"Europe/Berlin",
    "iso:country":"DE",
    "wof:name":"Seelach",
    "wof:placetype":"neighbourhood"
},
  "geometry": {"coordinates":[9.72625,48.91943],"type":"Point"}
}