{
  "type": "Feature",
  "properties": {
    "gn:admin1_code":"2",
    "gn:admin2_code":"92.0",
    "gn:admin3_code":"9277.0",
    "gn:admin4_code":"9277119.0",
    "gn:asciiname":"Diepoltskirchen",
    "gn:country_code":"DE",
    "gn:dem":443,
    "gn:feature_class":"P",
    "gn:feature_code":"PPL",
    "gn:name":"Diepoltskirchen",
    "gn:population":0,
    "gn:timezone":"Europe/Berlin",
    "iso:country":"DE",
    "name:deu_x_preferred":[
        "Diepoltskirchen"
    ],
    "wof:name":"Diepoltskirchen",
    "wof:placetype":"neighbourhood"
},
  "geometry": {"coordinates":[12.71007,48.48138],"type":"Point"}
}