{
  "type": "Feature",
  "properties": {
    "gn:admin1_code":"14",
    "gn:admin2_code":"0.0",
    "gn:admin3_code":"15088.0",
    "gn:admin4_code":"15088100.0",
    "gn:asciiname":"Unterfarnstaedt",
    "gn:country_code":"DE",
    "gn:dem":173,
    "gn:feature_class":"P",
    "gn:feature_code":"PPL",
    "gn:name":"Unterfarnst\u00e4dt",
    "gn:population":0,
    "gn:timezone":"Europe/Berlin",
    "iso:country":"DE",
    "wof:name":"Unterfarnstaedt",
    "wof:placetype":"neighbourhood"
},
  "geometry": {"coordinates":[11.58628,51.42872],"type":"Point"}
}