{
  "type": "Feature",
  "properties": {
    "gn:admin1_code":"7",
    "gn:admin2_code":"53.0",
    "gn:admin3_code":"5378.0",
    "gn:admin4_code":"5378008.0",
    "gn:asciiname":"Grosshamberg",
    "gn:country_code":"DE",
    "gn:dem":118,
    "gn:feature_class":"P",
    "gn:feature_code":"PPL",
    "gn:name":"Gro\u00dfhamberg",
    "gn:population":0,
    "gn:timezone":"Europe/Berlin",
    "iso:country":"DE",
    "wof:name":"Grosshamberg",
    "wof:placetype":"neighbourhood"
},
  "geometry": {"coordinates":[7.06881,51.07777],"type":"Point"}
}