{
  "type": "Feature",
  "properties": {
    "gn:admin1_code":"2.0",
    "gn:admin2_code":"096",
    "gn:admin3_code":"9677.0",
    "gn:admin4_code":"9677135.0",
    "gn:asciiname":"Windheim",
    "gn:country_code":"DE",
    "gn:dem":161,
    "gn:feature_class":"P",
    "gn:feature_code":"PPL",
    "gn:name":"Windheim",
    "gn:population":0,
    "gn:timezone":"Europe/Berlin",
    "iso:country":"DE",
    "wof:name":"Windheim",
    "wof:placetype":"neighbourhood"
},
  "geometry": {"coordinates":[9.58132,49.88065],"type":"Point"}
}