{
  "type": "Feature",
  "properties": {
    "gn:admin1_code":"2.0",
    "gn:admin2_code":"97.0",
    "gn:admin3_code":"9780.0",
    "gn:admin4_code":"9780137.0",
    "gn:asciiname":"Acker",
    "gn:country_code":"DE",
    "gn:dem":870,
    "gn:feature_class":"P",
    "gn:feature_code":"PPL",
    "gn:name":"Acker",
    "gn:population":0,
    "gn:timezone":"Europe/Berlin",
    "iso:country":"DE",
    "name:ces_x_preferred":[
        "Acker"
    ],
    "name:deu_x_preferred":[
        "Acker"
    ],
    "name:heb_x_preferred":[
        "\u05d0\u05e7\u05e8"
    ],
    "wof:name":"Acker",
    "wof:placetype":"neighbourhood"
},
  "geometry": {"coordinates":[10.35664,47.60982],"type":"Point"}
}