{
  "type": "Feature",
  "properties": {
    "iso:country":"DE",
    "name:deu_x_preferred":[
        "Alt Bartelsdorf"
    ],
    "name:unk_x_variant":[
        "Alt Bartelsdorf"
    ],
    "qs:gn_adm0_cc":"DE",
    "qs:gn_local":2844588,
    "qs:gn_nam_loc":"rostock",
    "qs:gn_namadm1":"12",
    "qs:local_max":6613,
    "qs:local_sum":19240,
    "qs:localhoods":23,
    "qs:name":"Alt Bartelsdorf",
    "qs:name_adm0":"Deutschland",
    "qs:name_adm1":"Mecklenburg-Vorpommern",
    "qs:name_adm2":"Stadtkreis Rostock",
    "qs:name_lau":"Stadtteil Stadtmitte",
    "qs:name_local":"Rostock",
    "qs:photo_max":1,
    "qs:photo_sum":1,
    "qs:placetype":"Suburb",
    "qs:quad_count":1,
    "qs:woe_adm0":23424829,
    "qs:woe_adm1":2345492,
    "qs:woe_adm2":12597074,
    "qs:woe_lau":26823183,
    "qs:woe_local":689776,
    "qs:woe_ver":"7.10.0",
    "wof:lang":[
        "ger"
    ],
    "wof:name":"Alt Bartelsdorf",
    "wof:placetype":"neighbourhood"
},
  "geometry": {"coordinates":[12.192078,54.096451],"type":"Point"}
}