{
  "type": "Feature",
  "properties": {
    "gn:admin1_code":"14",
    "gn:admin2_code":"0.0",
    "gn:admin3_code":"15088.0",
    "gn:admin4_code":"15088319.0",
    "gn:asciiname":"Quillschina",
    "gn:country_code":"DE",
    "gn:dem":103,
    "gn:feature_class":"P",
    "gn:feature_code":"PPL",
    "gn:name":"Quillschina",
    "gn:population":0,
    "gn:timezone":"Europe/Berlin",
    "iso:country":"DE",
    "wof:name":"Quillschina",
    "wof:placetype":"neighbourhood"
},
  "geometry": {"coordinates":[11.80964,51.52014000000001],"type":"Point"}
}