{
  "type": "Feature",
  "properties": {
    "gn:admin1_code":"7",
    "gn:admin2_code":"57.0",
    "gn:admin3_code":"5766.0",
    "gn:admin4_code":"5766016.0",
    "gn:asciiname":"Kleinenmarpe",
    "gn:country_code":"DE",
    "gn:dem":145,
    "gn:feature_class":"P",
    "gn:feature_code":"PPL",
    "gn:name":"Kleinenmarpe",
    "gn:population":0,
    "gn:timezone":"Europe/Berlin",
    "iso:country":"DE",
    "wof:name":"Kleinenmarpe",
    "wof:placetype":"neighbourhood"
},
  "geometry": {"coordinates":[8.99454,51.96971],"type":"Point"}
}