{
  "type": "Feature",
  "properties": {
    "gn:admin1_code":"2",
    "gn:admin2_code":"95.0",
    "gn:admin3_code":"9571.0",
    "gn:admin4_code":"9571114.0",
    "gn:asciiname":"Eyerlohe",
    "gn:country_code":"DE",
    "gn:dem":425,
    "gn:feature_class":"P",
    "gn:feature_code":"PPL",
    "gn:name":"Eyerlohe",
    "gn:population":0,
    "gn:timezone":"Europe/Berlin",
    "iso:country":"DE",
    "wof:name":"Eyerlohe",
    "wof:placetype":"neighbourhood"
},
  "geometry": {"coordinates":[10.42098,49.267],"type":"Point"}
}