{
  "type": "Feature",
  "properties": {
    "gn:admin1_code":"13",
    "gn:admin2_code":"0.0",
    "gn:admin3_code":"14521.0",
    "gn:admin4_code":"14521495.0",
    "gn:asciiname":"Kalk",
    "gn:country_code":"DE",
    "gn:dem":611,
    "gn:feature_class":"P",
    "gn:feature_code":"PPL",
    "gn:name":"Kalk",
    "gn:population":0,
    "gn:timezone":"Europe/Berlin",
    "iso:country":"DE",
    "name:ceb_x_preferred":[
        "Kalk"
    ],
    "name:dan_x_preferred":[
        "Kalk"
    ],
    "name:deu_x_preferred":[
        "Kalk"
    ],
    "name:nor_x_preferred":[
        "Kalk"
    ],
    "name:pol_x_preferred":[
        "Kalk"
    ],
    "name:swe_x_preferred":[
        "Kalk"
    ],
    "name:und_x_variant":[
        "Kalkwerk"
    ],
    "wof:name":"Kalk",
    "wof:placetype":"neighbourhood"
},
  "geometry": {"coordinates":[13.17386,50.70076],"type":"Point"}
}