{
  "type": "Feature",
  "properties": {
    "gn:admin1_code":"1",
    "gn:admin2_code":"83.0",
    "gn:admin3_code":"8315.0",
    "gn:admin4_code":"8315094.0",
    "gn:asciiname":"In der Spirzen",
    "gn:country_code":"DE",
    "gn:dem":706,
    "gn:feature_class":"P",
    "gn:feature_code":"PPLL",
    "gn:name":"In der Spirzen",
    "gn:population":0,
    "gn:timezone":"Europe/Berlin",
    "iso:country":"DE",
    "wof:name":"In der Spirzen",
    "wof:placetype":"neighbourhood"
},
  "geometry": {"coordinates":[8.06703,47.97266],"type":"Point"}
}