{
  "type": "Feature",
  "properties": {
    "gn:admin1_code":"2",
    "gn:admin2_code":"95.0",
    "gn:admin3_code":"9577.0",
    "gn:admin4_code":"9577136.0",
    "gn:asciiname":"Schweina",
    "gn:country_code":"DE",
    "gn:dem":418,
    "gn:feature_class":"P",
    "gn:feature_code":"PPL",
    "gn:name":"Schweina",
    "gn:population":0,
    "gn:timezone":"Europe/Berlin",
    "iso:country":"DE",
    "name:bak_x_preferred":[
        "\u0428\u0432\u0430\u0439\u043d\u0430"
    ],
    "name:ceb_x_preferred":[
        "Schweina"
    ],
    "name:deu_x_preferred":[
        "Schweina"
    ],
    "name:epo_x_preferred":[
        "Schweina"
    ],
    "name:fas_x_preferred":[
        "\u0634\u0648\u0627\u06cc\u0646\u0627"
    ],
    "name:ita_x_preferred":[
        "Schweina"
    ],
    "name:kaz_x_preferred":[
        "\u0428\u0432\u0430\u0439\u043d\u0430"
    ],
    "name:kir_x_preferred":[
        "\u0428\u0432\u0430\u0439\u043d\u0430"
    ],
    "name:msa_x_preferred":[
        "Schweina"
    ],
    "name:nld_x_preferred":[
        "Schweina"
    ],
    "name:pol_x_preferred":[
        "Schweina"
    ],
    "name:por_x_preferred":[
        "Schweina"
    ],
    "name:ron_x_preferred":[
        "Schweina"
    ],
    "name:rus_x_preferred":[
        "\u0428\u0432\u0430\u0439\u043d\u0430"
    ],
    "name:srp_x_preferred":[
        "\u0428\u0432\u0430\u0458\u043d\u0430"
    ],
    "name:uzb_x_preferred":[
        "Schweina"
    ],
    "name:vie_x_preferred":[
        "Schweina"
    ],
    "name:vol_x_preferred":[
        "Schweina"
    ],
    "name:war_x_preferred":[
        "Schweina"
    ],
    "name:zho_x_preferred":[
        "\u65bd\u97e6\u7eb3"
    ],
    "wof:name":"Schweina",
    "wof:placetype":"neighbourhood"
},
  "geometry": {"coordinates":[10.7111,49.12887],"type":"Point"}
}