{
  "type": "Feature",
  "properties": {
    "gn:admin1_code":"13",
    "gn:admin2_code":"0.0",
    "gn:admin3_code":"14524.0",
    "gn:admin4_code":"14524180.0",
    "gn:asciiname":"Herrnsdorf",
    "gn:country_code":"DE",
    "gn:dem":224,
    "gn:feature_class":"P",
    "gn:feature_code":"PPL",
    "gn:name":"Herrnsdorf",
    "gn:population":0,
    "gn:timezone":"Europe/Berlin",
    "iso:country":"DE",
    "wof:name":"Herrnsdorf",
    "wof:placetype":"neighbourhood"
},
  "geometry": {"coordinates":[12.66145,50.89586],"type":"Point"}
}