{
  "type": "Feature",
  "properties": {
    "gn:admin1_code":"1.0",
    "gn:admin2_code":"84.0",
    "gn:admin3_code":"8435.0",
    "gn:admin4_code":"8435029.0",
    "gn:asciiname":"Berg",
    "gn:country_code":"DE",
    "gn:dem":451,
    "gn:feature_class":"P",
    "gn:feature_code":"PPL",
    "gn:name":"Berg",
    "gn:population":0,
    "gn:timezone":"Europe/Berlin",
    "iso:country":"DE",
    "wof:name":"Berg",
    "wof:placetype":"neighbourhood"
},
  "geometry": {"coordinates":[9.60504,47.60855],"type":"Point"}
}