{
  "type": "Feature",
  "properties": {
    "gn:admin1_code":"1",
    "gn:admin2_code":"83.0",
    "gn:admin3_code":"8317.0",
    "gn:admin4_code":"8317098.0",
    "gn:asciiname":"Ramsbachle",
    "gn:country_code":"DE",
    "gn:dem":324,
    "gn:feature_class":"P",
    "gn:feature_code":"PPLL",
    "gn:name":"Ramsb\u00e4chle",
    "gn:population":0,
    "gn:timezone":"Europe/Berlin",
    "iso:country":"DE",
    "wof:name":"Ramsbachle",
    "wof:placetype":"neighbourhood"
},
  "geometry": {"coordinates":[8.15882,48.50146],"type":"Point"}
}