{
  "type": "Feature",
  "properties": {
    "gn:admin1_code":"2.0",
    "gn:admin2_code":"093",
    "gn:admin3_code":"9372.0",
    "gn:admin4_code":"9372171.0",
    "gn:asciiname":"Zillendorf",
    "gn:country_code":"DE",
    "gn:dem":509,
    "gn:feature_class":"P",
    "gn:feature_code":"PPL",
    "gn:name":"Zillendorf",
    "gn:population":0,
    "gn:timezone":"Europe/Berlin",
    "iso:country":"DE",
    "wof:name":"Zillendorf",
    "wof:placetype":"neighbourhood"
},
  "geometry": {"coordinates":[12.66776,49.35088],"type":"Point"}
}