{
  "type": "Feature",
  "properties": {
    "gn:admin1_code":"6",
    "gn:admin2_code":"0.0",
    "gn:admin3_code":"3257.0",
    "gn:admin4_code":"3257003.0",
    "gn:asciiname":"Kathrinhagen",
    "gn:country_code":"DE",
    "gn:dem":143,
    "gn:feature_class":"P",
    "gn:feature_code":"PPL",
    "gn:name":"Kathrinhagen",
    "gn:population":0,
    "gn:timezone":"Europe/Berlin",
    "iso:country":"DE",
    "wof:name":"Kathrinhagen",
    "wof:placetype":"neighbourhood"
},
  "geometry": {"coordinates":[9.20362,52.23747],"type":"Point"}
}