{
  "type": "Feature",
  "properties": {
    "gn:admin1_code":"1.0",
    "gn:admin2_code":"81.0",
    "gn:admin3_code":"8136.0",
    "gn:admin4_code":"8136066.0",
    "gn:asciiname":"Beutenhof",
    "gn:country_code":"DE",
    "gn:dem":476,
    "gn:feature_class":"P",
    "gn:feature_code":"PPL",
    "gn:name":"Beutenhof",
    "gn:population":0,
    "gn:timezone":"Europe/Berlin",
    "iso:country":"DE",
    "wof:name":"Beutenhof",
    "wof:placetype":"locality"
},
  "geometry": {"coordinates":[9.74734,48.87393],"type":"Point"}
}