{
  "type": "Feature",
  "properties": {
    "gn:admin1_code":"15",
    "gn:admin2_code":"0.0",
    "gn:admin3_code":"16074.0",
    "gn:admin4_code":"16074089.0",
    "gn:asciiname":"Leuchtenburg",
    "gn:country_code":"DE",
    "gn:dem":388,
    "gn:feature_class":"P",
    "gn:feature_code":"PPL",
    "gn:name":"Leuchtenburg",
    "gn:population":0,
    "gn:timezone":"Europe/Berlin",
    "iso:country":"DE",
    "wof:name":"Leuchtenburg",
    "wof:placetype":"neighbourhood"
},
  "geometry": {"coordinates":[11.61259,50.80406],"type":"Point"}
}