{
  "type": "Feature",
  "properties": {
    "gn:admin1_code":"13",
    "gn:admin2_code":"0.0",
    "gn:admin3_code":"14521.0",
    "gn:admin4_code":"14521380.0",
    "gn:asciiname":"Neukirchberg",
    "gn:country_code":"DE",
    "gn:dem":412,
    "gn:feature_class":"P",
    "gn:feature_code":"PPL",
    "gn:name":"Neukirchberg",
    "gn:population":0,
    "gn:timezone":"Europe/Berlin",
    "iso:country":"DE",
    "wof:name":"Neukirchberg",
    "wof:placetype":"neighbourhood"
},
  "geometry": {"coordinates":[12.76182,50.74722],"type":"Point"}
}