{
  "type": "Feature",
  "properties": {
    "gn:admin1_code":"2",
    "gn:admin2_code":"95.0",
    "gn:admin3_code":"9575.0",
    "gn:admin4_code":"9575152.0",
    "gn:asciiname":"Vockenroth",
    "gn:country_code":"DE",
    "gn:dem":377,
    "gn:feature_class":"P",
    "gn:feature_code":"PPL",
    "gn:name":"Vockenroth",
    "gn:population":0,
    "gn:timezone":"Europe/Berlin",
    "iso:country":"DE",
    "wof:name":"Vockenroth",
    "wof:placetype":"neighbourhood"
},
  "geometry": {"coordinates":[10.63015,49.46422000000001],"type":"Point"}
}