{
  "type": "Feature",
  "properties": {
    "gn:admin1_code":"2",
    "gn:admin2_code":"92.0",
    "gn:admin3_code":"9275.0",
    "gn:admin4_code":"9275156.0",
    "gn:asciiname":"Polzod",
    "gn:country_code":"DE",
    "gn:dem":548,
    "gn:feature_class":"P",
    "gn:feature_code":"PPL",
    "gn:name":"P\u00f6lz\u00f6d",
    "gn:population":0,
    "gn:timezone":"Europe/Berlin",
    "iso:country":"DE",
    "wof:name":"Polzod",
    "wof:placetype":"neighbourhood"
},
  "geometry": {"coordinates":[13.72913,48.5757],"type":"Point"}
}