{
  "type": "Feature",
  "properties": {
    "gn:admin1_code":"2",
    "gn:admin2_code":"92.0",
    "gn:admin3_code":"9277.0",
    "gn:admin4_code":"9277111.0",
    "gn:asciiname":"Wabach",
    "gn:country_code":"DE",
    "gn:dem":395,
    "gn:feature_class":"P",
    "gn:feature_code":"PPL",
    "gn:name":"Wabach",
    "gn:population":0,
    "gn:timezone":"Europe/Berlin",
    "iso:country":"DE",
    "wof:name":"Wabach",
    "wof:placetype":"neighbourhood"
},
  "geometry": {"coordinates":[12.78185,48.53815],"type":"Point"}
}