{
  "type": "Feature",
  "properties": {
    "gn:admin1_code":"14",
    "gn:admin2_code":"0.0",
    "gn:admin3_code":"15088.0",
    "gn:admin4_code":"15088205.0",
    "gn:asciiname":"Horburg",
    "gn:country_code":"DE",
    "gn:dem":92,
    "gn:feature_class":"P",
    "gn:feature_code":"PPL",
    "gn:name":"Horburg",
    "gn:population":0,
    "gn:timezone":"Europe/Berlin",
    "iso:country":"DE",
    "wof:name":"Horburg",
    "wof:placetype":"neighbourhood"
},
  "geometry": {"coordinates":[12.17263,51.36612],"type":"Point"}
}