{
  "type": "Feature",
  "properties": {
    "gn:admin1_code":"1",
    "gn:admin2_code":"83.0",
    "gn:admin3_code":"8335.0",
    "gn:admin4_code":"8335075.0",
    "gn:asciiname":"Schlatt unter Krahen",
    "gn:country_code":"DE",
    "gn:dem":448,
    "gn:feature_class":"P",
    "gn:feature_code":"PPL",
    "gn:name":"Schlatt unter Kr\u00e4hen",
    "gn:population":0,
    "gn:timezone":"Europe/Berlin",
    "iso:country":"DE",
    "name:und_x_variant":[
        "Schlatt",
        "Schlatt unter Kr\u00e4hen"
    ],
    "wof:name":"Schlatt unter Krahen",
    "wof:placetype":"neighbourhood"
},
  "geometry": {"coordinates":[8.8366,47.80527],"type":"Point"}
}