{
  "type": "Feature",
  "properties": {
    "gn:admin1_code":"7",
    "gn:admin2_code":"51.0",
    "gn:admin3_code":"5166.0",
    "gn:admin4_code":"5166012.0",
    "gn:asciiname":"Haag",
    "gn:country_code":"DE",
    "gn:dem":42,
    "gn:feature_class":"P",
    "gn:feature_code":"PPL",
    "gn:name":"Haag",
    "gn:population":0,
    "gn:timezone":"Europe/Berlin",
    "iso:country":"DE",
    "name:bos_x_preferred":[
        "Haag"
    ],
    "name:ceb_x_preferred":[
        "Haag"
    ],
    "name:ces_x_preferred":[
        "Haag"
    ],
    "name:deu_x_preferred":[
        "Haag"
    ],
    "name:epo_x_preferred":[
        "Haag"
    ],
    "name:fra_x_preferred":[
        "Haag"
    ],
    "name:hun_x_preferred":[
        "Haag"
    ],
    "name:hye_x_preferred":[
        "\u0540\u0561\u0563"
    ],
    "name:ita_x_preferred":[
        "Haag"
    ],
    "name:kaz_x_preferred":[
        "\u0425\u0430\u0433"
    ],
    "name:lav_x_preferred":[
        "H\u0101ga"
    ],
    "name:nld_x_preferred":[
        "Haag"
    ],
    "name:pol_x_preferred":[
        "Haag"
    ],
    "name:por_x_preferred":[
        "Haag"
    ],
    "name:rus_x_preferred":[
        "\u0425\u0430\u0433"
    ],
    "name:swe_x_preferred":[
        "Haag"
    ],
    "name:vol_x_preferred":[
        "Haag"
    ],
    "wof:name":"Haag",
    "wof:placetype":"neighbourhood"
},
  "geometry": {"coordinates":[6.48134,51.41236],"type":"Point"}
}