{
  "type": "Feature",
  "properties": {
    "gn:admin1_code":"5",
    "gn:admin2_code":"65.0",
    "gn:admin3_code":"6532.0",
    "gn:admin4_code":"6532006.0",
    "gn:asciiname":"Eibach",
    "gn:country_code":"DE",
    "gn:dem":294,
    "gn:feature_class":"P",
    "gn:feature_code":"PPL",
    "gn:name":"Eibach",
    "gn:population":0,
    "gn:timezone":"Europe/Berlin",
    "iso:country":"DE",
    "name:deu_x_preferred":[
        "Eibach"
    ],
    "name:ita_x_preferred":[
        "Eibach"
    ],
    "name:nld_x_preferred":[
        "Eibach"
    ],
    "wof:name":"Eibach",
    "wof:placetype":"neighbourhood"
},
  "geometry": {"coordinates":[8.32463,50.74605],"type":"Point"}
}