{
  "type": "Feature",
  "properties": {
    "gn:admin1_code":"2.0",
    "gn:admin2_code":"093",
    "gn:admin3_code":"9371.0",
    "gn:admin4_code":"9371119.0",
    "gn:asciiname":"Weissenberg",
    "gn:country_code":"DE",
    "gn:dem":453,
    "gn:feature_class":"P",
    "gn:feature_code":"PPL",
    "gn:name":"Wei\u00dfenberg",
    "gn:population":0,
    "gn:timezone":"Europe/Berlin",
    "iso:country":"DE",
    "name:ceb_x_preferred":[
        "Weissenberg"
    ],
    "name:fin_x_preferred":[
        "Weissenberg"
    ],
    "name:fra_x_preferred":[
        "Weissenberg"
    ],
    "name:pol_x_preferred":[
        "Weissenberg"
    ],
    "name:swe_x_preferred":[
        "Weissenberg"
    ],
    "wof:name":"Weissenberg",
    "wof:placetype":"neighbourhood"
},
  "geometry": {"coordinates":[11.7267,49.57755],"type":"Point"}
}