{
  "type": "Feature",
  "properties": {
    "gn:admin1_code":"8",
    "gn:admin2_code":"0.0",
    "gn:admin3_code":"7131.0",
    "gn:admin4_code":"7131006.0",
    "gn:asciiname":"Oberbreisig",
    "gn:country_code":"DE",
    "gn:dem":116,
    "gn:feature_class":"P",
    "gn:feature_code":"PPL",
    "gn:name":"Oberbreisig",
    "gn:population":0,
    "gn:timezone":"Europe/Berlin",
    "iso:country":"DE",
    "wof:name":"Oberbreisig",
    "wof:placetype":"neighbourhood"
},
  "geometry": {"coordinates":[7.27739,50.50079],"type":"Point"}
}