{
  "type": "Feature",
  "properties": {
    "gn:admin1_code":"1.0",
    "gn:admin2_code":"84.0",
    "gn:admin3_code":"8436.0",
    "gn:admin4_code":"8436013.0",
    "gn:asciiname":"Aichach",
    "gn:country_code":"DE",
    "gn:dem":545,
    "gn:feature_class":"P",
    "gn:feature_code":"PPL",
    "gn:name":"Aichach",
    "gn:population":0,
    "gn:timezone":"Europe/Berlin",
    "iso:country":"DE",
    "name:als_x_preferred":[
        "Aichach"
    ],
    "name:ara_x_preferred":[
        "\u0622\u064a\u0634\u0627\u062e"
    ],
    "name:azb_x_preferred":[
        "\u0622\u06cc\u0634\u0627\u062e"
    ],
    "name:aze_x_preferred":[
        "Ayxax"
    ],
    "name:bar_x_preferred":[
        "Aichach"
    ],
    "name:bel_x_preferred":[
        "\u0410\u0439\u0445\u0430\u0445"
    ],
    "name:bul_x_preferred":[
        "\u0410\u0439\u0445\u0430\u0445"
    ],
    "name:cat_x_preferred":[
        "Aichach"
    ],
    "name:ceb_x_preferred":[
        "Aichach"
    ],
    "name:dan_x_preferred":[
        "Aichach"
    ],
    "name:deu_x_preferred":[
        "Aichach"
    ],
    "name:ell_x_preferred":[
        "\u0386\u03b9\u03c7\u03b1\u03c7"
    ],
    "name:epo_x_preferred":[
        "Aichach"
    ],
    "name:fas_x_preferred":[
        "\u0622\u06cc\u0634\u0627\u062e"
    ],
    "name:fra_x_preferred":[
        "Aichach"
    ],
    "name:fry_x_preferred":[
        "Aichach"
    ],
    "name:hrv_x_preferred":[
        "Aichach"
    ],
    "name:hun_x_preferred":[
        "Aichach"
    ],
    "name:hye_x_preferred":[
        "\u0531\u0575\u056d\u0561\u056d"
    ],
    "name:ind_x_preferred":[
        "Aichach"
    ],
    "name:ita_x_preferred":[
        "Aichach"
    ],
    "name:jpn_x_preferred":[
        "\u30a2\u30a4\u30d2\u30e3\u30c3\u30cf"
    ],
    "name:kir_x_preferred":[
        "\u0410\u0439\u0445\u0430\u0445"
    ],
    "name:lat_x_preferred":[
        "Aichach"
    ],
    "name:lmo_x_preferred":[
        "Aichach"
    ],
    "name:msa_x_preferred":[
        "Aichach"
    ],
    "name:nld_x_preferred":[
        "Aichach"
    ],
    "name:pnb_x_preferred":[
        "\u0627\u06cc\u0686\u0627\u062e"
    ],
    "name:pol_x_preferred":[
        "Aichach"
    ],
    "name:por_x_preferred":[
        "Aichach"
    ],
    "name:ron_x_preferred":[
        "Aichach"
    ],
    "name:rus_x_preferred":[
        "\u0410\u0439\u0445\u0430\u0445"
    ],
    "name:spa_x_preferred":[
        "Aichach"
    ],
    "name:srp_x_preferred":[
        "\u0410\u0458\u0445\u0430\u0445"
    ],
    "name:swe_x_preferred":[
        "Aichach"
    ],
    "name:tur_x_preferred":[
        "Aichach"
    ],
    "name:ukr_x_preferred":[
        "\u0410\u0439\u0445\u0430\u0445"
    ],
    "name:uzb_x_preferred":[
        "Aichach"
    ],
    "name:vie_x_preferred":[
        "Aichach"
    ],
    "name:vol_x_preferred":[
        "Aichach"
    ],
    "name:war_x_preferred":[
        "Aichach"
    ],
    "name:zho_x_preferred":[
        "\u827e\u590f\u8d6b"
    ],
    "wof:name":"Aichach",
    "wof:placetype":"neighbourhood"
},
  "geometry": {"coordinates":[9.57882,47.83934],"type":"Point"}
}