{
  "type": "Feature",
  "properties": {
    "gn:admin1_code":"1.0",
    "gn:admin2_code":"84.0",
    "gn:admin3_code":"8436.0",
    "gn:admin4_code":"8436013.0",
    "gn:asciiname":"Aichach",
    "gn:country_code":"DE",
    "gn:dem":545,
    "gn:feature_class":"P",
    "gn:feature_code":"PPL",
    "gn:name":"Aichach",
    "gn:population":0,
    "gn:timezone":"Europe/Berlin",
    "iso:country":"DE",
    "wof:name":"Aichach",
    "wof:placetype":"neighbourhood"
},
  "geometry": {"coordinates":[9.57882,47.83934],"type":"Point"}
}