{
  "type": "Feature",
  "properties": {
    "gn:admin1_code":"6",
    "gn:admin2_code":"0.0",
    "gn:admin3_code":"3454.0",
    "gn:admin4_code":"3454035.0",
    "gn:asciiname":"Ruehle",
    "gn:country_code":"DE",
    "gn:dem":19,
    "gn:feature_class":"P",
    "gn:feature_code":"PPL",
    "gn:name":"R\u00fchle",
    "gn:population":0,
    "gn:timezone":"Europe/Berlin",
    "iso:country":"DE",
    "wof:name":"Ruehle",
    "wof:placetype":"neighbourhood"
},
  "geometry": {"coordinates":[7.24578,52.66943000000001],"type":"Point"}
}