{
  "type": "Feature",
  "properties": {
    "gn:admin1_code":"1.0",
    "gn:admin2_code":"83.0",
    "gn:admin3_code":"8316.0",
    "gn:admin4_code":"8316056.0",
    "gn:asciiname":"Biehl",
    "gn:country_code":"DE",
    "gn:dem":347,
    "gn:feature_class":"P",
    "gn:feature_code":"PPL",
    "gn:name":"Biehl",
    "gn:population":0,
    "gn:timezone":"Europe/Berlin",
    "iso:country":"DE",
    "wof:name":"Biehl",
    "wof:placetype":"neighbourhood"
},
  "geometry": {"coordinates":[7.99696,48.105],"type":"Point"}
}