{
  "type": "Feature",
  "properties": {
    "gn:admin1_code":"11",
    "gn:admin2_code":"0.0",
    "gn:admin3_code":"12062.0",
    "gn:admin4_code":"12062372.0",
    "gn:asciiname":"Kahla",
    "gn:country_code":"DE",
    "gn:dem":96,
    "gn:feature_class":"P",
    "gn:feature_code":"PPL",
    "gn:name":"Kahla",
    "gn:population":0,
    "gn:timezone":"Europe/Berlin",
    "iso:country":"DE",
    "wof:name":"Kahla",
    "wof:placetype":"neighbourhood"
},
  "geometry": {"coordinates":[13.56629,51.46781],"type":"Point"}
}