{
  "type": "Feature",
  "properties": {
    "gn:admin1_code":"6.0",
    "gn:admin2_code":"0.0",
    "gn:admin3_code":"3357.0",
    "gn:admin4_code":"3357016.0",
    "gn:asciiname":"Unter Barkhausen",
    "gn:country_code":"DE",
    "gn:dem":9,
    "gn:feature_class":"P",
    "gn:feature_code":"PPL",
    "gn:name":"Unter Barkhausen",
    "gn:population":0,
    "gn:timezone":"Europe/Berlin",
    "iso:country":"DE",
    "wof:name":"Unter Barkhausen",
    "wof:placetype":"neighbourhood"
},
  "geometry": {"coordinates":[9.01987,53.38008000000001],"type":"Point"}
}