{
  "type": "Feature",
  "properties": {
    "iso:country":"DE",
    "name:deu_x_preferred":[
        "Bulmke"
    ],
    "name:unk_x_variant":[
        "Bulmke"
    ],
    "qs:gn_adm0_cc":"DE",
    "qs:gn_fcode":"PPLX",
    "qs:gn_local":2921466,
    "qs:gn_nam_loc":"gelsenkirchen",
    "qs:gn_namadm1":"07",
    "qs:gn_name":"Bulmke",
    "qs:local_max":11550,
    "qs:local_sum":26487,
    "qs:localhoods":6,
    "qs:name":"Bulmke",
    "qs:name_adm0":"Deutschland",
    "qs:name_adm1":"Nordrhein-Westfalen",
    "qs:name_adm2":"Stadtkreis Gelsenkirchen",
    "qs:name_lau":"Stadtteil Schalke",
    "qs:name_local":"Gelsenkirchen",
    "qs:photo_max":1240,
    "qs:photo_sum":5681,
    "qs:placetype":"Suburb",
    "qs:quad_count":52,
    "qs:woe_adm0":23424829,
    "qs:woe_adm1":2345487,
    "qs:woe_adm2":12597080,
    "qs:woe_lau":26822454,
    "qs:woe_local":652038,
    "qs:woe_ver":"7.10.0",
    "wof:lang":[
        "ger"
    ],
    "wof:name":"Bulmke",
    "wof:placetype":"neighbourhood"
},
  "geometry": {"coordinates":[7.090409,51.513651],"type":"Point"}
}