{
  "type": "Feature",
  "properties": {
    "gn:admin1_code":"13",
    "gn:admin2_code":"0.0",
    "gn:admin3_code":"14521.0",
    "gn:admin4_code":"14521180.0",
    "gn:asciiname":"Schwarzbach",
    "gn:country_code":"DE",
    "gn:dem":525,
    "gn:feature_class":"P",
    "gn:feature_code":"PPL",
    "gn:name":"Schwarzbach",
    "gn:population":0,
    "gn:timezone":"Europe/Berlin",
    "iso:country":"DE",
    "wof:name":"Schwarzbach",
    "wof:placetype":"neighbourhood"
},
  "geometry": {"coordinates":[12.86638,50.5614],"type":"Point"}
}