{
  "type": "Feature",
  "properties": {
    "gn:admin1_code":"6",
    "gn:admin2_code":"0.0",
    "gn:admin3_code":"3458.0",
    "gn:admin4_code":"3458003.0",
    "gn:asciiname":"Hesterhoege",
    "gn:country_code":"DE",
    "gn:dem":36,
    "gn:feature_class":"P",
    "gn:feature_code":"PPL",
    "gn:name":"Hesterh\u00f6ge",
    "gn:population":0,
    "gn:timezone":"Europe/Berlin",
    "iso:country":"DE",
    "wof:name":"Hesterhoege",
    "wof:placetype":"neighbourhood"
},
  "geometry": {"coordinates":[8.36667,52.95],"type":"Point"}
}