{
  "type": "Feature",
  "properties": {
    "gn:admin1_code":"7",
    "gn:admin2_code":"53.0",
    "gn:admin3_code":"5374.0",
    "gn:admin4_code":"5374016.0",
    "gn:asciiname":"Kurzfeld",
    "gn:country_code":"DE",
    "gn:dem":309,
    "gn:feature_class":"P",
    "gn:feature_code":"PPL",
    "gn:name":"Kurzfeld",
    "gn:population":0,
    "gn:timezone":"Europe/Berlin",
    "iso:country":"DE",
    "wof:name":"Kurzfeld",
    "wof:placetype":"neighbourhood"
},
  "geometry": {"coordinates":[7.28388,51.13221],"type":"Point"}
}