{
  "type": "Feature",
  "properties": {
    "gn:admin1_code":"1.0",
    "gn:admin2_code":"084",
    "gn:admin3_code":"8425.0",
    "gn:admin4_code":"8425141.0",
    "gn:asciiname":"Ziegelhutte",
    "gn:country_code":"DE",
    "gn:dem":639,
    "gn:feature_class":"P",
    "gn:feature_code":"PPL",
    "gn:name":"Ziegelh\u00fctte",
    "gn:population":0,
    "gn:timezone":"Europe/Berlin",
    "iso:country":"DE",
    "wof:name":"Ziegelhutte",
    "wof:placetype":"neighbourhood"
},
  "geometry": {"coordinates":[9.86667,48.46667],"type":"Point"}
}