{
  "type": "Feature",
  "properties": {
    "gn:admin1_code":"13",
    "gn:admin2_code":"0.0",
    "gn:admin3_code":"14729.0",
    "gn:admin4_code":"14729270.0",
    "gn:asciiname":"Schkeitbar",
    "gn:country_code":"DE",
    "gn:dem":132,
    "gn:feature_class":"P",
    "gn:feature_code":"PPL",
    "gn:name":"Schkeitbar",
    "gn:population":0,
    "gn:timezone":"Europe/Berlin",
    "iso:country":"DE",
    "wof:name":"Schkeitbar",
    "wof:placetype":"neighbourhood"
},
  "geometry": {"coordinates":[12.22212,51.25354],"type":"Point"}
}