{
  "type": "Feature",
  "properties": {
    "gn:gn_country":"DE",
    "gn:gn_fcode":"PPLA4",
    "gn:gn_pop":52,
    "gn:population":52,
    "iso:country":"DE",
    "name:baq_x_preferred":[
        "Muxerath"
    ],
    "name:chi_x_preferred":[
        "\u7a46\u514b\u585e\u62c9\u7279"
    ],
    "name:dut_x_preferred":[
        "Muxerath"
    ],
    "name:eng_x_preferred":[
        "Muxerath"
    ],
    "name:epo_x_preferred":[
        "Muxerath"
    ],
    "name:fre_x_preferred":[
        "Muxerath"
    ],
    "name:ger_x_preferred":[
        "Muxerath"
    ],
    "name:hun_x_preferred":[
        "Muxerath"
    ],
    "name:ita_x_preferred":[
        "Muxerath"
    ],
    "name:jpn_x_preferred":[
        "\u30e0\u30af\u30bb\u30e9\u30fc\u30c8"
    ],
    "name:may_x_preferred":[
        "Muxerath"
    ],
    "name:per_x_preferred":[
        "\u0645\u0648\u06a9\u0633\u0631\u0627\u062a"
    ],
    "name:pol_x_preferred":[
        "Muxerath"
    ],
    "name:por_x_preferred":[
        "Muxerath"
    ],
    "name:rum_x_preferred":[
        "Muxerath"
    ],
    "name:rus_x_preferred":[
        "\u041c\u0443\u043a\u0441\u0435\u0440\u0430\u0442"
    ],
    "name:srp_x_preferred":[
        "\u041c\u0443\u043a\u0441\u0435\u0440\u0430\u0442"
    ],
    "name:ukr_x_preferred":[
        "\u041c\u0443\u043a\u0441\u0435\u0440\u0430\u0442"
    ],
    "name:uzb_x_preferred":[
        "Muxerath"
    ],
    "name:vie_x_preferred":[
        "Muxerath"
    ],
    "name:vol_x_preferred":[
        "Muxerath"
    ],
    "name:war_x_preferred":[
        "Muxerath"
    ],
    "qs_pg:aaroncc":"DE",
    "qs_pg:gn_country":"DE",
    "qs_pg:gn_fcode":"PPLA4",
    "qs_pg:gn_pop":52,
    "qs_pg:name":"Muxerath",
    "qs_pg:photos_9r":0,
    "qs_pg:photos_sr":0,
    "qs_pg:pop_sr":1,
    "qs_pg:qs_pg_placetype":"locality",
    "wof:name":"Muxerath",
    "wof:placetype":"locality",
    "wof:population":52
},
  "geometry": {"coordinates":[6.26667,49.98333],"type":"Point"}
}