{
  "type": "Feature",
  "properties": {
    "gn:admin1_code":"1",
    "gn:admin2_code":"83.0",
    "gn:admin3_code":"8315.0",
    "gn:admin4_code":"8315084.0",
    "gn:asciiname":"Hornegrund",
    "gn:country_code":"DE",
    "gn:dem":1140,
    "gn:feature_class":"P",
    "gn:feature_code":"PPLL",
    "gn:name":"H\u00f6rnegrund",
    "gn:population":0,
    "gn:timezone":"Europe/Berlin",
    "iso:country":"DE",
    "wof:name":"Hornegrund",
    "wof:placetype":"neighbourhood"
},
  "geometry": {"coordinates":[7.91667,47.91667],"type":"Point"}
}