{
  "type": "Feature",
  "properties": {
    "gn:admin1_code":"2",
    "gn:admin2_code":"92.0",
    "gn:admin3_code":"9273.0",
    "gn:admin4_code":"9273152.0",
    "gn:asciiname":"Niederulrain",
    "gn:country_code":"DE",
    "gn:dem":363,
    "gn:feature_class":"P",
    "gn:feature_code":"PPL",
    "gn:name":"Niederulrain",
    "gn:population":0,
    "gn:timezone":"Europe/Berlin",
    "iso:country":"DE",
    "wof:name":"Niederulrain",
    "wof:placetype":"neighbourhood"
},
  "geometry": {"coordinates":[11.79765,48.80214],"type":"Point"}
}