{
  "type": "Feature",
  "properties": {
    "gn:admin1_code":"2.0",
    "gn:admin2_code":"91.0",
    "gn:admin3_code":"9172.0",
    "gn:admin4_code":"9172117.0",
    "gn:asciiname":"Wasserer Moos",
    "gn:country_code":"DE",
    "gn:dem":614,
    "gn:feature_class":"P",
    "gn:feature_code":"PPL",
    "gn:name":"Wasserer Moos",
    "gn:population":0,
    "gn:timezone":"Europe/Berlin",
    "iso:country":"DE",
    "wof:name":"Wasserer Moos",
    "wof:placetype":"neighbourhood"
},
  "geometry": {"coordinates":[12.9641,47.63707],"type":"Point"}
}