{
  "type": "Feature",
  "properties": {
    "gn:admin1_code":"2.0",
    "gn:admin2_code":"091",
    "gn:admin3_code":"9182.0",
    "gn:admin4_code":"9182114.0",
    "gn:asciiname":"Wornsmuhl",
    "gn:country_code":"DE",
    "gn:dem":694,
    "gn:feature_class":"P",
    "gn:feature_code":"PPL",
    "gn:name":"W\u00f6rnsm\u00fchl",
    "gn:population":0,
    "gn:timezone":"Europe/Berlin",
    "iso:country":"DE",
    "wof:name":"Wornsmuhl",
    "wof:placetype":"neighbourhood"
},
  "geometry": {"coordinates":[11.90716,47.76737],"type":"Point"}
}