{
  "type": "Feature",
  "properties": {
    "gn:gn_country":"DE",
    "gn:gn_fcode":"PPLA4",
    "gn:gn_pop":234,
    "gn:population":234,
    "iso:country":"DE",
    "name:bak_x_preferred":[
        "\u0425\u0438\u043b\u044c\u0431\u0435\u0440\u0441\u0434\u043e\u0440\u0444"
    ],
    "name:baq_x_preferred":[
        "Hilbersdorf"
    ],
    "name:chi_x_preferred":[
        "\u5e0c\u5c14\u8d1d\u5c14\u65af\u591a\u592b"
    ],
    "name:dut_x_preferred":[
        "Hilbersdorf"
    ],
    "name:eng_x_preferred":[
        "Hilbersdorf"
    ],
    "name:epo_x_preferred":[
        "Hilbersdorf"
    ],
    "name:fre_x_preferred":[
        "Hilbersdorf"
    ],
    "name:ger_x_preferred":[
        "Hilbersdorf"
    ],
    "name:hun_x_preferred":[
        "Hilbersdorf"
    ],
    "name:ita_x_preferred":[
        "Hilbersdorf"
    ],
    "name:mac_x_preferred":[
        "\u0425\u0438\u043b\u0431\u0435\u0440\u0441\u0434\u043e\u0440\u0444"
    ],
    "name:may_x_preferred":[
        "Hilbersdorf"
    ],
    "name:per_x_preferred":[
        "\u0647\u06cc\u0644\u0628\u0631\u0633\u062f\u0648\u0631\u0641"
    ],
    "name:pol_x_preferred":[
        "Hilbersdorf"
    ],
    "name:por_x_preferred":[
        "Hilbersdorf"
    ],
    "name:rum_x_preferred":[
        "Hilbersdorf"
    ],
    "name:rus_x_preferred":[
        "\u0425\u0438\u043b\u044c\u0431\u0435\u0440\u0441\u0434\u043e\u0440\u0444"
    ],
    "name:srp_x_preferred":[
        "\u0425\u0438\u043b\u0431\u0435\u0440\u0441\u0434\u043e\u0440\u0444"
    ],
    "name:ukr_x_preferred":[
        "\u0413\u0456\u043b\u044c\u0431\u0435\u0440\u0441\u0434\u043e\u0440\u0444"
    ],
    "name:uzb_x_preferred":[
        "Hilbersdorf"
    ],
    "name:vol_x_preferred":[
        "Hilbersdorf"
    ],
    "name:war_x_preferred":[
        "Hilbersdorf"
    ],
    "qs_pg:aaroncc":"DE",
    "qs_pg:gn_country":"DE",
    "qs_pg:gn_fcode":"PPLA4",
    "qs_pg:gn_pop":234,
    "qs_pg:name":"Hilbersdorf",
    "qs_pg:photos_9r":0,
    "qs_pg:photos_sr":0,
    "qs_pg:pop_sr":2,
    "qs_pg:qs_pg_placetype":"locality",
    "wof:name":"Hilbersdorf",
    "wof:placetype":"locality",
    "wof:population":234
},
  "geometry": {"coordinates":[12.15,50.81667],"type":"Point"}
}