{
  "type": "Feature",
  "properties": {
    "iso:country":"DE",
    "wof:name":"Bettikum",
    "wof:placetype":"neighbourhood"
},
  "geometry": {"coordinates":[6.71472651512134,51.14584395775174],"type":"Point"}
}