{
  "type": "Feature",
  "properties": {
    "gn:admin1_code":"2",
    "gn:admin2_code":"93.0",
    "gn:admin3_code":"9377.0",
    "gn:admin4_code":"9377133.0",
    "gn:asciiname":"Rothenhof",
    "gn:country_code":"DE",
    "gn:dem":599,
    "gn:feature_class":"P",
    "gn:feature_code":"PPL",
    "gn:name":"Rothenhof",
    "gn:population":0,
    "gn:timezone":"Europe/Berlin",
    "iso:country":"DE",
    "wof:name":"Rothenhof",
    "wof:placetype":"neighbourhood"
},
  "geometry": {"coordinates":[11.93856,49.90095],"type":"Point"}
}