{
  "type": "Feature",
  "properties": {
    "gn:admin1_code":"7.0",
    "gn:admin2_code":"59.0",
    "gn:admin3_code":"5962.0",
    "gn:admin4_code":"5962012.0",
    "gn:asciiname":"Ahe",
    "gn:country_code":"DE",
    "gn:dem":337,
    "gn:feature_class":"P",
    "gn:feature_code":"PPL",
    "gn:name":"Ahe",
    "gn:population":0,
    "gn:timezone":"Europe/Berlin",
    "iso:country":"DE",
    "name:cat_x_preferred":[
        "Ahe"
    ],
    "name:ceb_x_preferred":[
        "Atoll Ahe"
    ],
    "name:ces_x_preferred":[
        "Ahe"
    ],
    "name:deu_x_preferred":[
        "Ahe"
    ],
    "name:epo_x_preferred":[
        "Ahe"
    ],
    "name:fas_x_preferred":[
        "\u0627\u0647\u0647"
    ],
    "name:fin_x_preferred":[
        "Ahe"
    ],
    "name:fra_x_preferred":[
        "Ahe"
    ],
    "name:glg_x_preferred":[
        "Atol Ahe"
    ],
    "name:hun_x_preferred":[
        "Ahe"
    ],
    "name:ita_x_preferred":[
        "Ahe"
    ],
    "name:lit_x_preferred":[
        "Ahe"
    ],
    "name:mrj_x_preferred":[
        "\u0410\u0445\u0435"
    ],
    "name:nld_x_preferred":[
        "Ahe"
    ],
    "name:rus_x_preferred":[
        "\u0410\u0445\u0435"
    ],
    "name:slk_x_preferred":[
        "Ahe"
    ],
    "name:spa_x_preferred":[
        "Ahe"
    ],
    "name:swa_x_preferred":[
        "Ahe"
    ],
    "name:tah_x_preferred":[
        "Ahe"
    ],
    "wof:name":"Ahe",
    "wof:placetype":"neighbourhood"
},
  "geometry": {"coordinates":[7.44515,51.21233],"type":"Point"}
}