{
  "type": "Feature",
  "properties": {
    "gn:admin1_code":"1",
    "gn:admin2_code":"83.0",
    "gn:admin3_code":"8326.0",
    "gn:admin4_code":"8326060.0",
    "gn:asciiname":"Vordertal",
    "gn:country_code":"DE",
    "gn:dem":766,
    "gn:feature_class":"P",
    "gn:feature_code":"PPLL",
    "gn:name":"Vordertal",
    "gn:population":0,
    "gn:timezone":"Europe/Berlin",
    "iso:country":"DE",
    "wof:name":"Vordertal",
    "wof:placetype":"neighbourhood"
},
  "geometry": {"coordinates":[8.28287,48.13253],"type":"Point"}
}