{
  "type": "Feature",
  "properties": {
    "gn:admin1_code":"2.0",
    "gn:admin2_code":"91.0",
    "gn:admin3_code":"9185.0",
    "gn:admin4_code":"9185149.0",
    "gn:asciiname":"Bergen",
    "gn:country_code":"DE",
    "gn:dem":422,
    "gn:feature_class":"P",
    "gn:feature_code":"PPL",
    "gn:name":"Bergen",
    "gn:population":0,
    "gn:timezone":"Europe/Berlin",
    "iso:country":"DE",
    "wof:name":"Bergen",
    "wof:placetype":"neighbourhood"
},
  "geometry": {"coordinates":[11.14387,48.78397],"type":"Point"}
}