{
  "type": "Feature",
  "properties": {
    "gn:admin1_code":"13",
    "gn:admin2_code":"0.0",
    "gn:admin3_code":"14626.0",
    "gn:admin4_code":"14626060.0",
    "gn:asciiname":"Kringelsdorf",
    "gn:country_code":"DE",
    "gn:dem":133,
    "gn:feature_class":"P",
    "gn:feature_code":"PPL",
    "gn:name":"Kringelsdorf",
    "gn:population":0,
    "gn:timezone":"Europe/Berlin",
    "iso:country":"DE",
    "name:hsb_x_preferred":[
        "Krynhelecy"
    ],
    "wof:name":"Kringelsdorf",
    "wof:placetype":"neighbourhood"
},
  "geometry": {"coordinates":[14.6079,51.38787],"type":"Point"}
}