{
  "type": "Feature",
  "properties": {
    "gn:country":"DE",
    "gn:fcode":"PPL",
    "gn:population":415,
    "iso:country":"DE",
    "name:bak_x_preferred":[
        "\u0411\u0440\u0451\u043a\u043a\u0430\u0443"
    ],
    "name:ceb_x_preferred":[
        "Br\u00f6ckau"
    ],
    "name:che_x_preferred":[
        "\u0411\u0440\u043e\u044c\u043a\u043a\u0430\u0443"
    ],
    "name:deu_x_preferred":[
        "Br\u00f6ckau"
    ],
    "name:eng_x_preferred":[
        "Br\u00f6ckau"
    ],
    "name:epo_x_preferred":[
        "Br\u00f6ckau"
    ],
    "name:fas_x_preferred":[
        "\u0628\u0631\u0648\u06a9\u0627\u0648"
    ],
    "name:fra_x_preferred":[
        "Br\u00f6ckau"
    ],
    "name:gle_x_preferred":[
        "Br\u00f6ckau"
    ],
    "name:ita_x_preferred":[
        "Br\u00f6ckau"
    ],
    "name:kaz_x_preferred":[
        "\u0411\u0440\u0451\u043a\u043a\u0430\u0443"
    ],
    "name:kir_x_preferred":[
        "\u0411\u0440\u04e9\u043a\u043a\u0430\u0443"
    ],
    "name:mkd_x_preferred":[
        "\u0411\u0440\u0435\u043a\u0430\u0443"
    ],
    "name:nld_x_preferred":[
        "Br\u00f6ckau"
    ],
    "name:ron_x_preferred":[
        "Br\u00f6ckau"
    ],
    "name:rus_x_preferred":[
        "\u0411\u0440\u0451\u043a\u043a\u0430\u0443"
    ],
    "name:tat_x_preferred":[
        "\u0411\u0440\u0451\u043a\u043a\u0430\u0443"
    ],
    "name:uzb_x_preferred":[
        "Br\u00f6ckau"
    ],
    "name:vie_x_preferred":[
        "Br\u00f6ckau"
    ],
    "name:vol_x_preferred":[
        "Br\u00f6ckau"
    ],
    "qs_pg:aaroncc":"DE",
    "qs_pg:gn_country":"DE",
    "qs_pg:gn_fcode":"PPL",
    "qs_pg:gn_pop":415,
    "qs_pg:name":"Br\u00f6ckau",
    "qs_pg:name_adm0":"Deutschland",
    "qs_pg:name_adm1":"Sachsen-Anhalt",
    "qs_pg:photos_9r":0,
    "qs_pg:photos_sr":0,
    "qs_pg:pop_sr":2,
    "qs_pg:qs_pg_placetype":"locality",
    "qs_pg:qs_pg_placetype_gp":"Town",
    "qs_pg:woe_adm0":23424829,
    "woe:adm0_id":23424829,
    "woe:name_adm0":"Deutschland",
    "woe:name_adm1":"Sachsen-Anhalt",
    "woe:placetype":"Town",
    "wof:name":"Br\u00f6ckau",
    "wof:placetype":"neighbourhood",
    "wof:population":415
},
  "geometry": {"coordinates":[12.2129,50.96359],"type":"Point"}
}