{
  "type": "Feature",
  "properties": {
    "gn:admin1_code":"11",
    "gn:admin2_code":"0.0",
    "gn:admin3_code":"12069.0",
    "gn:admin4_code":"12069696.0",
    "gn:asciiname":"Grebs",
    "gn:country_code":"DE",
    "gn:dem":62,
    "gn:feature_class":"P",
    "gn:feature_code":"PPL",
    "gn:name":"Grebs",
    "gn:population":0,
    "gn:timezone":"Europe/Berlin",
    "iso:country":"DE",
    "wof:name":"Grebs",
    "wof:placetype":"neighbourhood"
},
  "geometry": {"coordinates":[12.39324,52.25383],"type":"Point"}
}