{
  "type": "Feature",
  "properties": {
    "gn:admin1_code":"11",
    "gn:admin2_code":"0.0",
    "gn:admin3_code":"12072.0",
    "gn:admin4_code":"12072055.0",
    "gn:asciiname":"Liebsdorf",
    "gn:country_code":"DE",
    "gn:dem":76,
    "gn:feature_class":"P",
    "gn:feature_code":"PPL",
    "gn:name":"Liebsdorf",
    "gn:population":0,
    "gn:timezone":"Europe/Berlin",
    "iso:country":"DE",
    "name:als_x_preferred":[
        "Liebsdorf"
    ],
    "name:bug_x_preferred":[
        "Liebsdorf"
    ],
    "name:cat_x_preferred":[
        "Liebsdorf"
    ],
    "name:ceb_x_preferred":[
        "Liebsdorf"
    ],
    "name:deu_x_preferred":[
        "Liebsdorf"
    ],
    "name:eus_x_preferred":[
        "Liebsdorf"
    ],
    "name:fra_x_preferred":[
        "Liebsdorf"
    ],
    "name:hun_x_preferred":[
        "Liebsdorf"
    ],
    "name:ita_x_preferred":[
        "Liebsdorf"
    ],
    "name:kaz_x_preferred":[
        "\u041b\u0438\u0431\u0441\u0434\u043e\u0440\u0444"
    ],
    "name:lat_x_preferred":[
        "Liebsdorf"
    ],
    "name:msa_x_preferred":[
        "Liebsdorf"
    ],
    "name:nld_x_preferred":[
        "Liebsdorf"
    ],
    "name:oci_x_preferred":[
        "Liebsdorf"
    ],
    "name:pfl_x_preferred":[
        "Liebsdorf"
    ],
    "name:pms_x_preferred":[
        "Liebsdorf"
    ],
    "name:pol_x_preferred":[
        "Liebsdorf"
    ],
    "name:por_x_preferred":[
        "Liebsdorf"
    ],
    "name:ron_x_preferred":[
        "Liebsdorf"
    ],
    "name:rus_x_preferred":[
        "\u041b\u0438\u0431\u0441\u0434\u043e\u0440\u0444"
    ],
    "name:slk_x_preferred":[
        "Liebsdorf"
    ],
    "name:slv_x_preferred":[
        "Liebsdorf"
    ],
    "name:spa_x_preferred":[
        "Liebsdorf"
    ],
    "name:swe_x_preferred":[
        "Liebsdorf"
    ],
    "name:ukr_x_preferred":[
        "\u041b\u0456\u0431\u0441\u0434\u043e\u0440\u0444"
    ],
    "name:uzb_x_preferred":[
        "Liebsdorf"
    ],
    "name:vie_x_preferred":[
        "Liebsdorf"
    ],
    "name:vol_x_preferred":[
        "Liebsdorf"
    ],
    "name:war_x_preferred":[
        "Liebsdorf"
    ],
    "name:zho_x_preferred":[
        "\u5229\u5e03\u65af\u591a\u592b"
    ],
    "wof:name":"Liebsdorf",
    "wof:placetype":"neighbourhood"
},
  "geometry": {"coordinates":[13.503,51.90821],"type":"Point"}
}