{
  "type": "Feature",
  "properties": {
    "gn:admin1_code":"11",
    "gn:admin2_code":"0.0",
    "gn:admin3_code":"12072.0",
    "gn:admin4_code":"12072055.0",
    "gn:asciiname":"Liebsdorf",
    "gn:country_code":"DE",
    "gn:dem":76,
    "gn:feature_class":"P",
    "gn:feature_code":"PPL",
    "gn:name":"Liebsdorf",
    "gn:population":0,
    "gn:timezone":"Europe/Berlin",
    "iso:country":"DE",
    "wof:name":"Liebsdorf",
    "wof:placetype":"neighbourhood"
},
  "geometry": {"coordinates":[13.503,51.90821],"type":"Point"}
}