{
  "type": "Feature",
  "properties": {
    "iso:country":"DE",
    "name:deu_x_preferred":[
        "Neustadt"
    ],
    "name:unk_x_variant":[
        "Neustadt"
    ],
    "qs:gn_adm0_cc":"DE",
    "qs:gn_fcode":"PPL",
    "qs:gn_local":2940132,
    "qs:gn_namadm1":"13",
    "qs:gn_name":"Naustadt",
    "qs:local_max":1030,
    "qs:local_sum":1761,
    "qs:localhoods":9,
    "qs:name":"Neustadt",
    "qs:name_adm0":"Deutschland",
    "qs:name_adm1":"Sachsen",
    "qs:name_adm2":"Kreisfreie Stadt Chemnitz",
    "qs:name_lau":"Stadtteil Sch\u00f6nau",
    "qs:name_local":"Chemnitz",
    "qs:photo_max":336,
    "qs:photo_sum":1030,
    "qs:placetype":"Suburb",
    "qs:quad_count":73,
    "qs:woe_adm0":23424829,
    "qs:woe_adm1":2345493,
    "qs:woe_adm2":12596812,
    "qs:woe_lau":26822073,
    "qs:woe_local":643134,
    "qs:woe_ver":"7.10.0",
    "wd:wordcount":497,
    "wof:lang":[
        "ger"
    ],
    "wof:name":"Neustadt",
    "wof:placetype":"neighbourhood"
},
  "geometry": {"coordinates":[12.905317,50.824395],"type":"Point"}
}