{
  "type": "Feature",
  "properties": {
    "iso:country":"DE",
    "name:bre_x_preferred":[
        "Neustadt"
    ],
    "name:cat_x_preferred":[
        "Neustadt"
    ],
    "name:ceb_x_preferred":[
        "Neustadt"
    ],
    "name:dan_x_preferred":[
        "Neustadt"
    ],
    "name:deu_x_preferred":[
        "Neustadt"
    ],
    "name:epo_x_preferred":[
        "Neustadt"
    ],
    "name:fas_x_preferred":[
        "\u0646\u0648\u06cc\u200c\u0627\u0634\u062a\u0627\u062a"
    ],
    "name:fin_x_preferred":[
        "Neustadt"
    ],
    "name:fra_x_preferred":[
        "Neustadt"
    ],
    "name:heb_x_preferred":[
        "\u05e0\u05d5\u05d9\u05e9\u05d8\u05d0\u05d3\u05d8"
    ],
    "name:ita_x_preferred":[
        "Neustadt"
    ],
    "name:jpn_x_preferred":[
        "\u30ce\u30a4\u30b7\u30e5\u30bf\u30c3\u30c8"
    ],
    "name:lmo_x_preferred":[
        "Neustadt"
    ],
    "name:mkd_x_preferred":[
        "\u041d\u043e\u0458\u0448\u0442\u0430\u0442"
    ],
    "name:nds_x_preferred":[
        "Neustadt"
    ],
    "name:nld_x_preferred":[
        "Neustadt"
    ],
    "name:nor_x_preferred":[
        "Neustadt"
    ],
    "name:pol_x_preferred":[
        "Neustadt"
    ],
    "name:por_x_preferred":[
        "Neustadt"
    ],
    "name:ron_x_preferred":[
        "Neustadt"
    ],
    "name:rus_x_preferred":[
        "\u041d\u043e\u0439\u0448\u0442\u0430\u0434\u0442"
    ],
    "name:spa_x_preferred":[
        "Neustadt"
    ],
    "name:swe_x_preferred":[
        "Neustadt"
    ],
    "name:ukr_x_preferred":[
        "\u041d\u043e\u0439\u0448\u0442\u0430\u0434\u0442"
    ],
    "name:unk_x_variant":[
        "Neustadt"
    ],
    "name:vol_x_preferred":[
        "Neustadt"
    ],
    "qs:gn_adm0_cc":"DE",
    "qs:gn_fcode":"PPL",
    "qs:gn_local":2940132,
    "qs:gn_namadm1":"13",
    "qs:gn_name":"Naustadt",
    "qs:local_max":1030,
    "qs:local_sum":1761,
    "qs:localhoods":9,
    "qs:name":"Neustadt",
    "qs:name_adm0":"Deutschland",
    "qs:name_adm1":"Sachsen",
    "qs:name_adm2":"Kreisfreie Stadt Chemnitz",
    "qs:name_lau":"Stadtteil Sch\u00f6nau",
    "qs:name_local":"Chemnitz",
    "qs:photo_max":336,
    "qs:photo_sum":1030,
    "qs:placetype":"Suburb",
    "qs:quad_count":73,
    "qs:woe_adm0":23424829,
    "qs:woe_adm1":2345493,
    "qs:woe_adm2":12596812,
    "qs:woe_lau":26822073,
    "qs:woe_local":643134,
    "qs:woe_ver":"7.10.0",
    "wd:wordcount":497,
    "wof:lang":[
        "ger"
    ],
    "wof:name":"Neustadt",
    "wof:placetype":"neighbourhood"
},
  "geometry": {"coordinates":[12.905317,50.824395],"type":"Point"}
}