{
  "type": "Feature",
  "properties": {
    "gn:admin1_code":"5",
    "gn:admin2_code":"64.0",
    "gn:admin3_code":"6439.0",
    "gn:admin4_code":"6439016.0",
    "gn:asciiname":"Reinborn",
    "gn:country_code":"DE",
    "gn:dem":415,
    "gn:feature_class":"P",
    "gn:feature_code":"PPL",
    "gn:name":"Reinborn",
    "gn:population":0,
    "gn:timezone":"Europe/Berlin",
    "iso:country":"DE",
    "wof:name":"Reinborn",
    "wof:placetype":"neighbourhood"
},
  "geometry": {"coordinates":[8.35598,50.26199],"type":"Point"}
}