{
  "type": "Feature",
  "properties": {
    "gn:admin1_code":"10",
    "gn:admin2_code":"0.0",
    "gn:admin3_code":"1057.0",
    "gn:admin4_code":"1057046.0",
    "gn:asciiname":"Trent",
    "gn:country_code":"DE",
    "gn:dem":43,
    "gn:feature_class":"P",
    "gn:feature_code":"PPL",
    "gn:name":"Trent",
    "gn:population":0,
    "gn:timezone":"Europe/Berlin",
    "iso:country":"DE",
    "name:bre_x_preferred":[
        "Trent"
    ],
    "name:cat_x_preferred":[
        "Trent"
    ],
    "name:ceb_x_preferred":[
        "Trent"
    ],
    "name:dan_x_preferred":[
        "Trent"
    ],
    "name:deu_x_preferred":[
        "Trent"
    ],
    "name:ell_x_preferred":[
        "\u03a4\u03c1\u03b5\u03bd\u03c4"
    ],
    "name:epo_x_preferred":[
        "Trent"
    ],
    "name:fas_x_preferred":[
        "\u062a\u0631\u0646\u062a"
    ],
    "name:fra_x_preferred":[
        "Trent"
    ],
    "name:hin_x_preferred":[
        "\u091f\u094d\u0930\u0947\u0902\u091f"
    ],
    "name:hrv_x_preferred":[
        "Trent"
    ],
    "name:hun_x_preferred":[
        "Trent"
    ],
    "name:hye_x_preferred":[
        "\u0539\u0580\u0565\u0576\u0569"
    ],
    "name:ita_x_preferred":[
        "Trent"
    ],
    "name:kor_x_preferred":[
        "\ud2b8\ub80c\ud2b8"
    ],
    "name:lat_x_preferred":[
        "Trent"
    ],
    "name:lit_x_preferred":[
        "Trentas"
    ],
    "name:nld_x_preferred":[
        "Trent"
    ],
    "name:nor_x_preferred":[
        "Trent"
    ],
    "name:pol_x_preferred":[
        "Trent"
    ],
    "name:por_x_preferred":[
        "Trent"
    ],
    "name:rus_x_preferred":[
        "\u0422\u0440\u0435\u043d\u0442"
    ],
    "name:spa_x_preferred":[
        "Trent"
    ],
    "name:srp_x_preferred":[
        "\u0422\u0440\u0435\u043d\u0442"
    ],
    "name:swe_x_preferred":[
        "Trent"
    ],
    "name:ukr_x_preferred":[
        "\u0422\u0440\u0435\u043d\u0442"
    ],
    "name:urd_x_preferred":[
        "\u0679\u0631\u06cc\u0646\u0679"
    ],
    "name:vie_x_preferred":[
        "S\u00f4ng Trent"
    ],
    "wof:name":"Trent",
    "wof:placetype":"neighbourhood"
},
  "geometry": {"coordinates":[10.36854,54.2059],"type":"Point"}
}