{
  "type": "Feature",
  "properties": {
    "gn:admin1_code":"2",
    "gn:admin2_code":"93.0",
    "gn:admin3_code":"9374.0",
    "gn:admin4_code":"9374123.0",
    "gn:asciiname":"Rehberg",
    "gn:country_code":"DE",
    "gn:dem":631,
    "gn:feature_class":"P",
    "gn:feature_code":"PPL",
    "gn:name":"Rehberg",
    "gn:population":0,
    "gn:timezone":"Europe/Berlin",
    "iso:country":"DE",
    "name:ceb_x_preferred":[
        "Rehberg"
    ],
    "name:deu_x_preferred":[
        "Rehberg"
    ],
    "name:epo_x_preferred":[
        "Rehberg"
    ],
    "name:fra_x_preferred":[
        "Rehberg"
    ],
    "name:pol_x_preferred":[
        "Rehberg"
    ],
    "name:swe_x_preferred":[
        "Rehberg"
    ],
    "wof:name":"Rehberg",
    "wof:placetype":"neighbourhood"
},
  "geometry": {"coordinates":[12.39978,49.69791],"type":"Point"}
}