{
  "type": "Feature",
  "properties": {
    "gn:admin1_code":"2",
    "gn:admin2_code":"94.0",
    "gn:admin3_code":"9472.0",
    "gn:admin4_code":"9472197.0",
    "gn:asciiname":"Hubenberg",
    "gn:country_code":"DE",
    "gn:dem":465,
    "gn:feature_class":"P",
    "gn:feature_code":"PPL",
    "gn:name":"Hubenberg",
    "gn:population":0,
    "gn:timezone":"Europe/Berlin",
    "iso:country":"DE",
    "wof:name":"Hubenberg",
    "wof:placetype":"neighbourhood"
},
  "geometry": {"coordinates":[11.30764,49.84747],"type":"Point"}
}