{
  "type": "Feature",
  "properties": {
    "gn:admin1_code":"13",
    "gn:admin2_code":"0.0",
    "gn:admin3_code":"14521.0",
    "gn:admin4_code":"14521030.0",
    "gn:asciiname":"Niederpfannenstiel",
    "gn:country_code":"DE",
    "gn:dem":372,
    "gn:feature_class":"P",
    "gn:feature_code":"PPL",
    "gn:name":"Niederpfannenstiel",
    "gn:population":0,
    "gn:timezone":"Europe/Berlin",
    "iso:country":"DE",
    "wof:name":"Niederpfannenstiel",
    "wof:placetype":"neighbourhood"
},
  "geometry": {"coordinates":[12.71814,50.58297],"type":"Point"}
}