{
  "type": "Feature",
  "properties": {
    "gn:admin1_code":"10",
    "gn:admin2_code":"0.0",
    "gn:admin3_code":"1057.0",
    "gn:admin4_code":"1057069.0",
    "gn:asciiname":"Schoenboeken",
    "gn:country_code":"DE",
    "gn:dem":47,
    "gn:feature_class":"P",
    "gn:feature_code":"PPL",
    "gn:name":"Sch\u00f6nb\u00f6ken",
    "gn:population":0,
    "gn:timezone":"Europe/Berlin",
    "iso:country":"DE",
    "wof:name":"Schoenboeken",
    "wof:placetype":"neighbourhood"
},
  "geometry": {"coordinates":[10.19625,54.08198],"type":"Point"}
}