{
  "type": "Feature",
  "properties": {
    "gn:admin1_code":"11.0",
    "gn:admin2_code":"0.0",
    "gn:admin3_code":"12051.0",
    "gn:admin4_code":"12051000.0",
    "gn:asciiname":"Hohenstuecken",
    "gn:country_code":"DE",
    "gn:dem":32,
    "gn:feature_class":"P",
    "gn:feature_code":"PPL",
    "gn:name":"Hohenst\u00fccken",
    "gn:population":0,
    "gn:timezone":"Europe/Berlin",
    "iso:country":"DE",
    "wof:name":"Hohenstuecken",
    "wof:placetype":"neighbourhood"
},
  "geometry": {"coordinates":[12.52956,52.42823],"type":"Point"}
}