{
  "type": "Feature",
  "properties": {
    "gn:admin1_code":"1",
    "gn:admin2_code":"84.0",
    "gn:admin3_code":"8436.0",
    "gn:admin4_code":"8436094.0",
    "gn:asciiname":"Oberharprechts",
    "gn:country_code":"DE",
    "gn:dem":679,
    "gn:feature_class":"P",
    "gn:feature_code":"PPL",
    "gn:name":"Oberharprechts",
    "gn:population":0,
    "gn:timezone":"Europe/Berlin",
    "iso:country":"DE",
    "wof:name":"Oberharprechts",
    "wof:placetype":"neighbourhood"
},
  "geometry": {"coordinates":[9.98821,47.71169],"type":"Point"}
}