{
  "type": "Feature",
  "properties": {
    "gn:admin1_code":"1.0",
    "gn:admin2_code":"83.0",
    "gn:admin3_code":"8316.0",
    "gn:admin4_code":"8316055.0",
    "gn:asciiname":"Braunhofe",
    "gn:country_code":"DE",
    "gn:dem":393,
    "gn:feature_class":"P",
    "gn:feature_code":"PPL",
    "gn:name":"Braunh\u00f6fe",
    "gn:population":0,
    "gn:timezone":"Europe/Berlin",
    "iso:country":"DE",
    "wof:name":"Braunhofe",
    "wof:placetype":"neighbourhood"
},
  "geometry": {"coordinates":[8.04755,48.14651],"type":"Point"}
}