{
  "type": "Feature",
  "properties": {
    "gn:admin1_code":"2",
    "gn:admin2_code":"97.0",
    "gn:admin3_code":"9763.0",
    "gn:admin4_code":"9763000.0",
    "gn:asciiname":"Reinharts",
    "gn:country_code":"DE",
    "gn:dem":725,
    "gn:feature_class":"P",
    "gn:feature_code":"PPL",
    "gn:name":"Reinharts",
    "gn:population":0,
    "gn:timezone":"Europe/Berlin",
    "iso:country":"DE",
    "wof:name":"Reinharts",
    "wof:placetype":"neighbourhood"
},
  "geometry": {"coordinates":[10.33678,47.74097],"type":"Point"}
}