{
  "type": "Feature",
  "properties": {
    "gn:admin1_code":"2",
    "gn:admin2_code":"92.0",
    "gn:admin3_code":"9275.0",
    "gn:admin4_code":"9275126.0",
    "gn:asciiname":"Oberkummering",
    "gn:country_code":"DE",
    "gn:dem":543,
    "gn:feature_class":"P",
    "gn:feature_code":"PPL",
    "gn:name":"Oberk\u00fcmmering",
    "gn:population":0,
    "gn:timezone":"Europe/Berlin",
    "iso:country":"DE",
    "wof:name":"Oberkummering",
    "wof:placetype":"neighbourhood"
},
  "geometry": {"coordinates":[13.5783,48.65582],"type":"Point"}
}