{
  "type": "Feature",
  "properties": {
    "gn:admin1_code":"7",
    "gn:admin2_code":"53.0",
    "gn:admin3_code":"5374.0",
    "gn:admin4_code":"5374048.0",
    "gn:asciiname":"Hueckhausen",
    "gn:country_code":"DE",
    "gn:dem":201,
    "gn:feature_class":"P",
    "gn:feature_code":"PPL",
    "gn:name":"H\u00fcckhausen",
    "gn:population":0,
    "gn:timezone":"Europe/Berlin",
    "iso:country":"DE",
    "wof:name":"Hueckhausen",
    "wof:placetype":"neighbourhood"
},
  "geometry": {"coordinates":[7.50206,50.97302],"type":"Point"}
}