{
  "type": "Feature",
  "properties": {
    "gn:admin1_code":"14",
    "gn:admin2_code":"0.0",
    "gn:admin3_code":"15085.0",
    "gn:admin4_code":"15085185.0",
    "gn:asciiname":"Schlanstedt",
    "gn:country_code":"DE",
    "gn:dem":91,
    "gn:feature_class":"P",
    "gn:feature_code":"PPL",
    "gn:name":"Schlanstedt",
    "gn:population":0,
    "gn:timezone":"Europe/Berlin",
    "iso:country":"DE",
    "wof:name":"Schlanstedt",
    "wof:placetype":"neighbourhood"
},
  "geometry": {"coordinates":[11.03096,52.01225],"type":"Point"}
}