{
  "type": "Feature",
  "properties": {
    "gn:admin1_code":"2.0",
    "gn:admin2_code":"091",
    "gn:admin3_code":"9171.0",
    "gn:admin4_code":"9171118.0",
    "gn:asciiname":"Winklham",
    "gn:country_code":"DE",
    "gn:dem":359,
    "gn:feature_class":"P",
    "gn:feature_code":"PPL",
    "gn:name":"Winklham",
    "gn:population":0,
    "gn:timezone":"Europe/Berlin",
    "iso:country":"DE",
    "wof:name":"Winklham",
    "wof:placetype":"neighbourhood"
},
  "geometry": {"coordinates":[12.902,48.22029000000001],"type":"Point"}
}