{
  "type": "Feature",
  "properties": {
    "gn:admin1_code":"2.0",
    "gn:admin2_code":"92.0",
    "gn:admin3_code":"9278.0",
    "gn:admin4_code":"9278197.0",
    "gn:asciiname":"Bogenroith",
    "gn:country_code":"DE",
    "gn:dem":636,
    "gn:feature_class":"P",
    "gn:feature_code":"PPL",
    "gn:name":"Bogenroith",
    "gn:population":0,
    "gn:timezone":"Europe/Berlin",
    "iso:country":"DE",
    "wof:name":"Bogenroith",
    "wof:placetype":"neighbourhood"
},
  "geometry": {"coordinates":[12.52596,49.03764],"type":"Point"}
}