{
  "type": "Feature",
  "properties": {
    "gn:admin1_code":"6",
    "gn:admin2_code":"0.0",
    "gn:admin3_code":"3158.0",
    "gn:admin4_code":"3158031.0",
    "gn:asciiname":"Warle",
    "gn:country_code":"DE",
    "gn:dem":108,
    "gn:feature_class":"P",
    "gn:feature_code":"PPL",
    "gn:name":"Warle",
    "gn:population":0,
    "gn:timezone":"Europe/Berlin",
    "iso:country":"DE",
    "wof:name":"Warle",
    "wof:placetype":"neighbourhood"
},
  "geometry": {"coordinates":[10.81295,52.11557],"type":"Point"}
}