{
  "type": "Feature",
  "properties": {
    "gn:admin1_code":"11",
    "gn:admin2_code":"0.0",
    "gn:admin3_code":"12068.0",
    "gn:admin4_code":"12068181.0",
    "gn:asciiname":"Liebenthal",
    "gn:country_code":"DE",
    "gn:dem":73,
    "gn:feature_class":"P",
    "gn:feature_code":"PPL",
    "gn:name":"Liebenthal",
    "gn:population":0,
    "gn:timezone":"Europe/Berlin",
    "iso:country":"DE",
    "name:ceb_x_preferred":[
        "Liebenthal"
    ],
    "name:ces_x_preferred":[
        "Liebenthal"
    ],
    "name:deu_x_preferred":[
        "Liebenthal"
    ],
    "name:fra_x_preferred":[
        "Liebenthal"
    ],
    "name:ita_x_preferred":[
        "Liebenthal"
    ],
    "name:nld_x_preferred":[
        "Liebenthal"
    ],
    "name:pol_x_preferred":[
        "Liebenthal"
    ],
    "name:swe_x_preferred":[
        "Liebenthal"
    ],
    "wof:name":"Liebenthal",
    "wof:placetype":"neighbourhood"
},
  "geometry": {"coordinates":[12.40391,53.13956],"type":"Point"}
}