{
  "type": "Feature",
  "properties": {
    "gn:admin1_code":"2.0",
    "gn:admin2_code":"092",
    "gn:admin3_code":"9275.0",
    "gn:admin4_code":"9275146.0",
    "gn:asciiname":"Willhartsberg",
    "gn:country_code":"DE",
    "gn:dem":436,
    "gn:feature_class":"P",
    "gn:feature_code":"PPL",
    "gn:name":"Willhartsberg",
    "gn:population":0,
    "gn:timezone":"Europe/Berlin",
    "iso:country":"DE",
    "wof:name":"Willhartsberg",
    "wof:placetype":"neighbourhood"
},
  "geometry": {"coordinates":[13.50704,48.6336],"type":"Point"}
}