{
  "type": "Feature",
  "properties": {
    "gn:admin1_code":"10",
    "gn:admin2_code":"0.0",
    "gn:admin3_code":"1057.0",
    "gn:admin4_code":"1057062.0",
    "gn:asciiname":"Wakendorf",
    "gn:country_code":"DE",
    "gn:dem":28,
    "gn:feature_class":"P",
    "gn:feature_code":"PPL",
    "gn:name":"Wakendorf",
    "gn:population":0,
    "gn:timezone":"Europe/Berlin",
    "iso:country":"DE",
    "name:deu_x_preferred":[
        "Wakendorf"
    ],
    "name:fra_x_preferred":[
        "Wakendorf"
    ],
    "name:ita_x_preferred":[
        "Wakendorf"
    ],
    "name:mkd_x_preferred":[
        "\u0412\u0430\u043a\u0435\u043d\u0434\u043e\u0440\u0444"
    ],
    "name:rus_x_preferred":[
        "\u0412\u0430\u043a\u0435\u043d\u0434\u043e\u0440\u0444"
    ],
    "wof:name":"Wakendorf",
    "wof:placetype":"neighbourhood"
},
  "geometry": {"coordinates":[10.29762,54.25198],"type":"Point"}
}