{
  "type": "Feature",
  "properties": {
    "gn:admin1_code":"11",
    "gn:admin2_code":"0.0",
    "gn:admin3_code":"12069.0",
    "gn:admin4_code":"12069306.0",
    "gn:asciiname":"Rotscherlinde",
    "gn:country_code":"DE",
    "gn:dem":65,
    "gn:feature_class":"P",
    "gn:feature_code":"PPL",
    "gn:name":"Rotscherlinde",
    "gn:population":0,
    "gn:timezone":"Europe/Berlin",
    "iso:country":"DE",
    "wof:name":"Rotscherlinde",
    "wof:placetype":"neighbourhood"
},
  "geometry": {"coordinates":[12.60227,52.33469],"type":"Point"}
}