{
  "type": "Feature",
  "properties": {
    "gn:admin1_code":"1",
    "gn:admin2_code":"82.0",
    "gn:admin3_code":"8237.0",
    "gn:admin4_code":"8237004.0",
    "gn:asciiname":"Surrbach",
    "gn:country_code":"DE",
    "gn:dem":613,
    "gn:feature_class":"P",
    "gn:feature_code":"PPL",
    "gn:name":"Surrbach",
    "gn:population":0,
    "gn:timezone":"Europe/Berlin",
    "iso:country":"DE",
    "wof:name":"Surrbach",
    "wof:placetype":"neighbourhood"
},
  "geometry": {"coordinates":[8.38445,48.4964],"type":"Point"}
}