{
  "type": "Feature",
  "properties": {
    "gn:admin1_code":"7",
    "gn:admin2_code":"57.0",
    "gn:admin3_code":"5758.0",
    "gn:admin4_code":"5758036.0",
    "gn:asciiname":"Kipshagen",
    "gn:country_code":"DE",
    "gn:dem":179,
    "gn:feature_class":"P",
    "gn:feature_code":"PPLL",
    "gn:name":"Kipshagen",
    "gn:population":0,
    "gn:timezone":"Europe/Berlin",
    "iso:country":"DE",
    "wof:name":"Kipshagen",
    "wof:placetype":"neighbourhood"
},
  "geometry": {"coordinates":[8.74653,52.13263],"type":"Point"}
}