{
  "type": "Feature",
  "properties": {
    "gn:admin1_code":"15",
    "gn:admin2_code":"0.0",
    "gn:admin3_code":"16068.0",
    "gn:admin4_code":"16068004.0",
    "gn:asciiname":"Dueppel",
    "gn:country_code":"DE",
    "gn:dem":253,
    "gn:feature_class":"P",
    "gn:feature_code":"PPL",
    "gn:name":"D\u00fcppel",
    "gn:population":0,
    "gn:timezone":"Europe/Berlin",
    "iso:country":"DE",
    "wof:name":"Dueppel",
    "wof:placetype":"neighbourhood"
},
  "geometry": {"coordinates":[11.08182,51.3041],"type":"Point"}
}