{
  "type": "Feature",
  "properties": {
    "gn:admin1_code":"2",
    "gn:admin2_code":"91.0",
    "gn:admin3_code":"9178.0",
    "gn:admin4_code":"9178137.0",
    "gn:asciiname":"Grandlmiltach",
    "gn:country_code":"DE",
    "gn:dem":467,
    "gn:feature_class":"P",
    "gn:feature_code":"PPL",
    "gn:name":"Grandlmiltach",
    "gn:population":0,
    "gn:timezone":"Europe/Berlin",
    "iso:country":"DE",
    "wof:name":"Grandlmiltach",
    "wof:placetype":"neighbourhood"
},
  "geometry": {"coordinates":[11.56468,48.39666],"type":"Point"}
}