{
  "type": "Feature",
  "properties": {
    "gn:admin1_code":"7",
    "gn:admin2_code":"51.0",
    "gn:admin3_code":"5170.0",
    "gn:admin4_code":"5170020.0",
    "gn:asciiname":"Noppick",
    "gn:country_code":"DE",
    "gn:dem":28,
    "gn:feature_class":"P",
    "gn:feature_code":"PPLL",
    "gn:name":"Noppick",
    "gn:population":0,
    "gn:timezone":"Europe/Berlin",
    "iso:country":"DE",
    "wof:name":"Noppick",
    "wof:placetype":"neighbourhood"
},
  "geometry": {"coordinates":[6.46679,51.50131],"type":"Point"}
}