{
  "type": "Feature",
  "properties": {
    "gn:admin1_code":"7",
    "gn:admin2_code":"59.0",
    "gn:admin3_code":"5958.0",
    "gn:admin4_code":"5958044.0",
    "gn:asciiname":"Hoevel",
    "gn:country_code":"DE",
    "gn:dem":359,
    "gn:feature_class":"P",
    "gn:feature_code":"PPL",
    "gn:name":"H\u00f6vel",
    "gn:population":0,
    "gn:timezone":"Europe/Berlin",
    "iso:country":"DE",
    "name:deu_x_preferred":[
        "H\u00f6vel"
    ],
    "name:nld_x_preferred":[
        "H\u00f6vel"
    ],
    "wof:name":"Hoevel",
    "wof:placetype":"neighbourhood"
},
  "geometry": {"coordinates":[7.92605,51.36918],"type":"Point"}
}