{
  "type": "Feature",
  "properties": {
    "gn:admin1_code":"2",
    "gn:admin2_code":"96.0",
    "gn:admin3_code":"9676.0",
    "gn:admin4_code":"9676121.0",
    "gn:asciiname":"Ruck",
    "gn:country_code":"DE",
    "gn:dem":155,
    "gn:feature_class":"P",
    "gn:feature_code":"PPL",
    "gn:name":"R\u00fcck",
    "gn:population":0,
    "gn:timezone":"Europe/Berlin",
    "iso:country":"DE",
    "name:deu_x_preferred":[
        "Ruck"
    ],
    "name:fra_x_preferred":[
        "Ruck"
    ],
    "name:ita_x_preferred":[
        "Ruck"
    ],
    "name:nds_x_preferred":[
        "Ruck"
    ],
    "name:pol_x_preferred":[
        "Ruck"
    ],
    "wof:name":"Ruck",
    "wof:placetype":"neighbourhood"
},
  "geometry": {"coordinates":[9.21306,49.82977],"type":"Point"}
}