{
  "type": "Feature",
  "properties": {
    "gn:admin1_code":"7",
    "gn:admin2_code":"57.0",
    "gn:admin3_code":"5766.0",
    "gn:admin4_code":"5766040.0",
    "gn:asciiname":"Massbruch",
    "gn:country_code":"DE",
    "gn:dem":122,
    "gn:feature_class":"P",
    "gn:feature_code":"PPLL",
    "gn:name":"Ma\u00dfbruch",
    "gn:population":0,
    "gn:timezone":"Europe/Berlin",
    "iso:country":"DE",
    "wof:name":"Massbruch",
    "wof:placetype":"neighbourhood"
},
  "geometry": {"coordinates":[8.80324,52.00056],"type":"Point"}
}