{
  "type": "Feature",
  "properties": {
    "iso:country":"DE",
    "name:deu_x_preferred":[
        "Gerasm\u00fchle"
    ],
    "wof:name":"Gerasmuehle",
    "wof:placetype":"neighbourhood"
},
  "geometry": {"coordinates":[11.0246114398149,49.39424209209297],"type":"Point"}
}