{
  "type": "Feature",
  "properties": {
    "iso:country":"DE",
    "name:cat_x_preferred":[
        "Steilshoop"
    ],
    "name:deu_x_preferred":[
        "Steilshoop"
    ],
    "name:eng_x_preferred":[
        "Steilshoop"
    ],
    "name:fra_x_preferred":[
        "Steilshoop"
    ],
    "name:hun_x_preferred":[
        "Steilshoop"
    ],
    "name:ita_x_preferred":[
        "Steilshoop"
    ],
    "name:lat_x_preferred":[
        "Hamburg-Steilshoop"
    ],
    "name:nld_x_preferred":[
        "Steilshoop"
    ],
    "name:oci_x_preferred":[
        "Steilshoop"
    ],
    "name:pol_x_preferred":[
        "Steilshoop"
    ],
    "name:rus_x_preferred":[
        "\u0428\u0442\u0430\u0439\u043b\u044c\u0441\u0445\u043e\u043e\u043f"
    ],
    "name:spa_x_preferred":[
        "Steilshoop"
    ],
    "wof:name":"Steilshoop",
    "wof:placetype":"neighbourhood"
},
  "geometry": {"coordinates":[10.05488620930133,53.61079621857305],"type":"Point"}
}