{
  "type": "Feature",
  "properties": {
    "gn:admin1_code":"5",
    "gn:admin2_code":"66.0",
    "gn:admin3_code":"6632.0",
    "gn:admin4_code":"6632014.0",
    "gn:asciiname":"Salzberg",
    "gn:country_code":"DE",
    "gn:dem":385,
    "gn:feature_class":"P",
    "gn:feature_code":"PPL",
    "gn:name":"Salzberg",
    "gn:population":0,
    "gn:timezone":"Europe/Berlin",
    "iso:country":"DE",
    "name:ceb_x_preferred":[
        "Salzberg"
    ],
    "name:deu_x_preferred":[
        "Salzberg"
    ],
    "name:swe_x_preferred":[
        "Salzberg"
    ],
    "wof:name":"Salzberg",
    "wof:placetype":"neighbourhood"
},
  "geometry": {"coordinates":[9.50428,50.90323],"type":"Point"}
}