{
  "type": "Feature",
  "properties": {
    "gn:admin1_code":"2",
    "gn:admin2_code":"91.0",
    "gn:admin3_code":"9189.0",
    "gn:admin4_code":"9189157.0",
    "gn:asciiname":"Lindach",
    "gn:country_code":"DE",
    "gn:dem":560,
    "gn:feature_class":"P",
    "gn:feature_code":"PPL",
    "gn:name":"Lindach",
    "gn:population":0,
    "gn:timezone":"Europe/Berlin",
    "iso:country":"DE",
    "name:chv_x_preferred":[
        "\u041b\u0438\u043d\u0434\u0430\u0445"
    ],
    "name:deu_x_preferred":[
        "Lindach"
    ],
    "wof:name":"Lindach",
    "wof:placetype":"neighbourhood"
},
  "geometry": {"coordinates":[12.57746,48.00365],"type":"Point"}
}