{
  "type": "Feature",
  "properties": {
    "gn:admin1_code":"6",
    "gn:admin2_code":"0.0",
    "gn:admin3_code":"3354.0",
    "gn:admin4_code":"3354015.0",
    "gn:asciiname":"Kriwitz",
    "gn:country_code":"DE",
    "gn:dem":24,
    "gn:feature_class":"P",
    "gn:feature_code":"PPL",
    "gn:name":"Kriwitz",
    "gn:population":0,
    "gn:timezone":"Europe/Berlin",
    "iso:country":"DE",
    "wof:name":"Kriwitz",
    "wof:placetype":"neighbourhood"
},
  "geometry": {"coordinates":[11.29028,52.90051999999999],"type":"Point"}
}