{
  "type": "Feature",
  "properties": {
    "gn:admin1_code":"13",
    "gn:admin2_code":"0.0",
    "gn:admin3_code":"14522.0",
    "gn:admin4_code":"14522120.0",
    "gn:asciiname":"Crossen",
    "gn:country_code":"DE",
    "gn:dem":263,
    "gn:feature_class":"P",
    "gn:feature_code":"PPL",
    "gn:name":"Crossen",
    "gn:population":0,
    "gn:timezone":"Europe/Berlin",
    "iso:country":"DE",
    "name:deu_x_preferred":[
        "Crossen"
    ],
    "name:fra_x_preferred":[
        "Crossen"
    ],
    "name:ita_x_preferred":[
        "Crossen"
    ],
    "name:pol_x_preferred":[
        "Crossen"
    ],
    "wof:name":"Crossen",
    "wof:placetype":"neighbourhood"
},
  "geometry": {"coordinates":[12.92746,51.0329],"type":"Point"}
}