{
  "type": "Feature",
  "properties": {
    "gn:admin1_code":"11",
    "gn:admin2_code":"0.0",
    "gn:admin3_code":"12072.0",
    "gn:admin4_code":"12072014.0",
    "gn:asciiname":"Horstwalde",
    "gn:country_code":"DE",
    "gn:dem":53,
    "gn:feature_class":"P",
    "gn:feature_code":"PPL",
    "gn:name":"Horstwalde",
    "gn:population":0,
    "gn:timezone":"Europe/Berlin",
    "iso:country":"DE",
    "name:und_x_variant":[
        "Neuhof",
        "Horstwalde"
    ],
    "wof:name":"Horstwalde",
    "wof:placetype":"neighbourhood"
},
  "geometry": {"coordinates":[13.40706,52.0835],"type":"Point"}
}