{
  "type": "Feature",
  "properties": {
    "gn:admin1_code":"12.0",
    "gn:admin2_code":"0.0",
    "gn:admin3_code":"13073.0",
    "gn:admin4_code":"13073017.0",
    "gn:asciiname":"Dierhagen Dorf",
    "gn:country_code":"DE",
    "gn:dem":2,
    "gn:feature_class":"P",
    "gn:feature_code":"PPL",
    "gn:name":"Dierhagen Dorf",
    "gn:population":0,
    "gn:timezone":"Europe/Berlin",
    "iso:country":"DE",
    "wof:name":"Dierhagen Dorf",
    "wof:placetype":"neighbourhood"
},
  "geometry": {"coordinates":[12.35876,54.28978000000001],"type":"Point"}
}