{
  "type": "Feature",
  "properties": {
    "gn:admin1_code":"1",
    "gn:admin2_code":"82.0",
    "gn:admin3_code":"8216.0",
    "gn:admin4_code":"8216015.0",
    "gn:asciiname":"Ottenau",
    "gn:country_code":"DE",
    "gn:dem":186,
    "gn:feature_class":"P",
    "gn:feature_code":"PPL",
    "gn:name":"Ottenau",
    "gn:population":0,
    "gn:timezone":"Europe/Berlin",
    "iso:country":"DE",
    "wof:name":"Ottenau",
    "wof:placetype":"neighbourhood"
},
  "geometry": {"coordinates":[8.34214,48.79386],"type":"Point"}
}