{
  "type": "Feature",
  "properties": {
    "gn:admin1_code":"7",
    "gn:admin2_code":"57.0",
    "gn:admin3_code":"5770.0",
    "gn:admin4_code":"5770008.0",
    "gn:asciiname":"Kurzenhuelsen",
    "gn:country_code":"DE",
    "gn:dem":54,
    "gn:feature_class":"P",
    "gn:feature_code":"PPL",
    "gn:name":"Kurzenh\u00fclsen",
    "gn:population":0,
    "gn:timezone":"Europe/Berlin",
    "iso:country":"DE",
    "wof:name":"Kurzenhuelsen",
    "wof:placetype":"neighbourhood"
},
  "geometry": {"coordinates":[8.56969,52.36066],"type":"Point"}
}