{
  "type": "Feature",
  "properties": {
    "gn:admin1_code":"5.0",
    "gn:admin2_code":"66.0",
    "gn:admin3_code":"6632.0",
    "gn:admin4_code":"6632018.0",
    "gn:asciiname":"Atzelrode",
    "gn:country_code":"DE",
    "gn:dem":293,
    "gn:feature_class":"P",
    "gn:feature_code":"PPL",
    "gn:name":"Atzelrode",
    "gn:population":0,
    "gn:timezone":"Europe/Berlin",
    "iso:country":"DE",
    "wof:name":"Atzelrode",
    "wof:placetype":"neighbourhood"
},
  "geometry": {"coordinates":[9.68216,50.98775],"type":"Point"}
}