{
  "type": "Feature",
  "properties": {
    "gn:admin1_code":"2",
    "gn:admin2_code":"96.0",
    "gn:admin3_code":"9677.0",
    "gn:admin4_code":"9677203.0",
    "gn:asciiname":"Duttenbrunn",
    "gn:country_code":"DE",
    "gn:dem":282,
    "gn:feature_class":"P",
    "gn:feature_code":"PPL",
    "gn:name":"Duttenbrunn",
    "gn:population":0,
    "gn:timezone":"Europe/Berlin",
    "iso:country":"DE",
    "wof:name":"Duttenbrunn",
    "wof:placetype":"neighbourhood"
},
  "geometry": {"coordinates":[9.71901,49.90242],"type":"Point"}
}