{
  "type": "Feature",
  "properties": {
    "gn:admin1_code":"12",
    "gn:admin2_code":"0.0",
    "gn:admin3_code":"13076.0",
    "gn:admin4_code":"13076055.0",
    "gn:asciiname":"Granzin",
    "gn:country_code":"DE",
    "gn:dem":66,
    "gn:feature_class":"P",
    "gn:feature_code":"PPL",
    "gn:name":"Granzin",
    "gn:population":0,
    "gn:timezone":"Europe/Berlin",
    "iso:country":"DE",
    "name:ceb_x_preferred":[
        "Granzin"
    ],
    "name:deu_x_preferred":[
        "Granzin"
    ],
    "name:epo_x_preferred":[
        "Granzin"
    ],
    "name:fas_x_preferred":[
        "\u06af\u0631\u0627\u0646\u062a\u0633\u06cc\u0646"
    ],
    "name:fra_x_preferred":[
        "Granzin"
    ],
    "name:hun_x_preferred":[
        "Granzin"
    ],
    "name:ita_x_preferred":[
        "Granzin"
    ],
    "name:kaz_x_preferred":[
        "\u0413\u0440\u0430\u043d\u0446\u0438\u043d"
    ],
    "name:kir_x_preferred":[
        "\u0413\u0440\u0430\u043d\u0446\u0438\u043d"
    ],
    "name:mkd_x_preferred":[
        "\u0413\u0440\u0430\u043d\u0446\u0438\u043d"
    ],
    "name:msa_x_preferred":[
        "Granzin"
    ],
    "name:nld_x_preferred":[
        "Granzin"
    ],
    "name:pol_x_preferred":[
        "Granzin"
    ],
    "name:por_x_preferred":[
        "Granzin"
    ],
    "name:ron_x_preferred":[
        "Granzin"
    ],
    "name:rus_x_preferred":[
        "\u0413\u0440\u0430\u043d\u0446\u0438\u043d"
    ],
    "name:spa_x_preferred":[
        "Granzin"
    ],
    "name:srp_x_preferred":[
        "\u0413\u0440\u0430\u043d\u0446\u0438\u043d"
    ],
    "name:tgl_x_preferred":[
        "Granzin"
    ],
    "name:ukr_x_preferred":[
        "\u0413\u0440\u0430\u043d\u0446\u0438\u043d"
    ],
    "name:uzb_x_preferred":[
        "Granzin"
    ],
    "name:vie_x_preferred":[
        "Granzin"
    ],
    "name:vol_x_preferred":[
        "Granzin"
    ],
    "name:war_x_preferred":[
        "Granzin"
    ],
    "name:zho_x_preferred":[
        "\u683c\u5170\u94a6"
    ],
    "wof:name":"Granzin",
    "wof:placetype":"neighbourhood"
},
  "geometry": {"coordinates":[10.83994,53.46483000000001],"type":"Point"}
}