{
  "type": "Feature",
  "properties": {
    "gn:admin1_code":"5",
    "gn:admin2_code":"66.0",
    "gn:admin3_code":"6636.0",
    "gn:admin4_code":"6636012.0",
    "gn:asciiname":"Hetzerode",
    "gn:country_code":"DE",
    "gn:dem":314,
    "gn:feature_class":"P",
    "gn:feature_code":"PPL",
    "gn:name":"Hetzerode",
    "gn:population":0,
    "gn:timezone":"Europe/Berlin",
    "iso:country":"DE",
    "wof:name":"Hetzerode",
    "wof:placetype":"neighbourhood"
},
  "geometry": {"coordinates":[9.80999,51.13414],"type":"Point"}
}