{
  "type": "Feature",
  "properties": {
    "gn:admin1_code":"14.0",
    "gn:admin2_code":"0.0",
    "gn:admin3_code":"15082.0",
    "gn:admin4_code":"15082377.0",
    "gn:asciiname":"Breesen",
    "gn:country_code":"DE",
    "gn:dem":79,
    "gn:feature_class":"P",
    "gn:feature_code":"PPL",
    "gn:name":"Breesen",
    "gn:population":0,
    "gn:timezone":"Europe/Berlin",
    "iso:country":"DE",
    "name:ceb_x_preferred":[
        "Breesen"
    ],
    "name:deu_x_preferred":[
        "Breesen"
    ],
    "name:epo_x_preferred":[
        "Breesen"
    ],
    "name:fas_x_preferred":[
        "\u0628\u0631\u06cc\u0632\u0646"
    ],
    "name:fra_x_preferred":[
        "Breesen"
    ],
    "name:hun_x_preferred":[
        "Breesen"
    ],
    "name:ita_x_preferred":[
        "Breesen"
    ],
    "name:mkd_x_preferred":[
        "\u0411\u0440\u0435\u0437\u0435\u043d"
    ],
    "name:msa_x_preferred":[
        "Breesen"
    ],
    "name:nld_x_preferred":[
        "Breesen"
    ],
    "name:pol_x_preferred":[
        "Breesen"
    ],
    "name:ron_x_preferred":[
        "Breesen"
    ],
    "name:rus_x_preferred":[
        "\u0411\u0440\u0435\u0437\u0435\u043d"
    ],
    "name:spa_x_preferred":[
        "Breesen"
    ],
    "name:srp_x_preferred":[
        "\u0411\u0440\u0435\u0441\u0435\u043d"
    ],
    "name:ukr_x_preferred":[
        "\u0411\u0440\u0435\u0437\u0435\u043d"
    ],
    "name:vie_x_preferred":[
        "Breesen"
    ],
    "name:vol_x_preferred":[
        "Breesen"
    ],
    "name:war_x_preferred":[
        "Breesen"
    ],
    "name:zho_x_preferred":[
        "\u5e03\u96f7\u68ee"
    ],
    "wof:name":"Breesen",
    "wof:placetype":"neighbourhood"
},
  "geometry": {"coordinates":[12.06688,51.74025],"type":"Point"}
}