{
  "type": "Feature",
  "properties": {
    "gn:admin1_code":"2.0",
    "gn:admin2_code":"91.0",
    "gn:admin3_code":"9173.0",
    "gn:admin4_code":"9173123.0",
    "gn:asciiname":"Blocken",
    "gn:country_code":"DE",
    "gn:dem":622,
    "gn:feature_class":"P",
    "gn:feature_code":"PPL",
    "gn:name":"Bl\u00f6cken",
    "gn:population":0,
    "gn:timezone":"Europe/Berlin",
    "iso:country":"DE",
    "wof:name":"Blocken",
    "wof:placetype":"neighbourhood"
},
  "geometry": {"coordinates":[11.43694,47.83471],"type":"Point"}
}