{
  "type": "Feature",
  "properties": {
    "gn:admin1_code":"10.0",
    "gn:admin2_code":"0.0",
    "gn:admin3_code":"1058.0",
    "gn:admin4_code":"1058070.0",
    "gn:asciiname":"Huy",
    "gn:country_code":"DE",
    "gn:dem":2,
    "gn:feature_class":"P",
    "gn:feature_code":"PPLL",
    "gn:name":"Huy",
    "gn:population":0,
    "gn:timezone":"Europe/Berlin",
    "iso:country":"DE",
    "name:afr_x_preferred":[
        "Hoei"
    ],
    "name:ara_x_preferred":[
        "\u0647\u0648\u064a"
    ],
    "name:bre_x_preferred":[
        "Huy"
    ],
    "name:cat_x_preferred":[
        "Huy"
    ],
    "name:ces_x_preferred":[
        "Huy"
    ],
    "name:dan_x_preferred":[
        "Huy"
    ],
    "name:deu_x_preferred":[
        "Huy"
    ],
    "name:epo_x_preferred":[
        "Huy"
    ],
    "name:eus_x_preferred":[
        "Huy"
    ],
    "name:fas_x_preferred":[
        "\u0627\u0648\u06cc\u06cc"
    ],
    "name:fin_x_preferred":[
        "Huy"
    ],
    "name:fra_x_preferred":[
        "Huy"
    ],
    "name:heb_x_preferred":[
        "\u05d0\u05d5\u05d0\u05d9"
    ],
    "name:ile_x_preferred":[
        "Huy"
    ],
    "name:ita_x_preferred":[
        "Huy"
    ],
    "name:jpn_x_preferred":[
        "\u30e6\u30a4"
    ],
    "name:lim_x_preferred":[
        "Hoei"
    ],
    "name:ltz_x_preferred":[
        "Huy"
    ],
    "name:nld_x_preferred":[
        "Hoei"
    ],
    "name:nno_x_preferred":[
        "Huy"
    ],
    "name:nor_x_preferred":[
        "Huy"
    ],
    "name:oci_x_preferred":[
        "Huy"
    ],
    "name:pcd_x_preferred":[
        "Huy"
    ],
    "name:pol_x_preferred":[
        "Huy"
    ],
    "name:por_x_preferred":[
        "Huy"
    ],
    "name:ron_x_preferred":[
        "Huy"
    ],
    "name:slk_x_preferred":[
        "Huy"
    ],
    "name:spa_x_preferred":[
        "Huy"
    ],
    "name:swe_x_preferred":[
        "Huy"
    ],
    "name:tur_x_preferred":[
        "Huy"
    ],
    "name:vie_x_preferred":[
        "Huy"
    ],
    "name:vol_x_preferred":[
        "Huy"
    ],
    "name:war_x_preferred":[
        "Huy"
    ],
    "wof:name":"Huy",
    "wof:placetype":"neighbourhood"
},
  "geometry": {"coordinates":[9.51667,54.21666999999999],"type":"Point"}
}