{
  "type": "Feature",
  "properties": {
    "gn:admin1_code":"2",
    "gn:admin2_code":"93.0",
    "gn:admin3_code":"9363.0",
    "gn:admin4_code":"9363000.0",
    "gn:asciiname":"Odenthal",
    "gn:country_code":"DE",
    "gn:dem":544,
    "gn:feature_class":"P",
    "gn:feature_code":"PPL",
    "gn:name":"\u00d6denthal",
    "gn:population":0,
    "gn:timezone":"Europe/Berlin",
    "iso:country":"DE",
    "name:bul_x_preferred":[
        "\u041e\u0434\u0435\u043d\u0442\u0430\u043b"
    ],
    "name:ceb_x_preferred":[
        "Odenthal"
    ],
    "name:deu_x_preferred":[
        "Odenthal"
    ],
    "name:epo_x_preferred":[
        "Odenthal"
    ],
    "name:eus_x_preferred":[
        "Odenthal"
    ],
    "name:fas_x_preferred":[
        "\u0627\u0648\u062f\u0646\u062a\u0627\u0644"
    ],
    "name:fra_x_preferred":[
        "Odenthal"
    ],
    "name:hun_x_preferred":[
        "Odenthal"
    ],
    "name:ita_x_preferred":[
        "Odenthal"
    ],
    "name:kaz_x_preferred":[
        "\u041e\u0434\u0435\u043d\u0442\u0430\u043b\u044c"
    ],
    "name:kir_x_preferred":[
        "\u041e\u0434\u0435\u043d\u0442\u0430\u043b\u044c"
    ],
    "name:lim_x_preferred":[
        "Odenthal"
    ],
    "name:msa_x_preferred":[
        "Odenthal"
    ],
    "name:nld_x_preferred":[
        "Odenthal"
    ],
    "name:pol_x_preferred":[
        "Odenthal"
    ],
    "name:por_x_preferred":[
        "Odenthal"
    ],
    "name:ron_x_preferred":[
        "Odenthal"
    ],
    "name:rus_x_preferred":[
        "\u041e\u0434\u0435\u043d\u0442\u0430\u043b\u044c"
    ],
    "name:sco_x_preferred":[
        "Odenthal"
    ],
    "name:spa_x_preferred":[
        "Odenthal"
    ],
    "name:srp_x_preferred":[
        "\u041e\u0434\u0435\u043d\u0442\u0430\u043b"
    ],
    "name:ukr_x_preferred":[
        "\u041e\u0434\u0435\u043d\u0442\u0430\u043b\u044c"
    ],
    "name:uzb_x_preferred":[
        "Odenthal"
    ],
    "name:vie_x_preferred":[
        "Odenthal"
    ],
    "name:vol_x_preferred":[
        "Odenthal"
    ],
    "name:war_x_preferred":[
        "Odenthal"
    ],
    "name:zho_x_preferred":[
        "\u5965\u767b\u5854\u5c14"
    ],
    "wof:name":"Odenthal",
    "wof:placetype":"neighbourhood"
},
  "geometry": {"coordinates":[12.23911,49.64432],"type":"Point"}
}