{
  "type": "Feature",
  "properties": {
    "gn:admin1_code":"13",
    "gn:admin2_code":"0.0",
    "gn:admin3_code":"14625.0",
    "gn:admin4_code":"14625110.0",
    "gn:asciiname":"Preuschwitz",
    "gn:country_code":"DE",
    "gn:dem":203,
    "gn:feature_class":"P",
    "gn:feature_code":"PPL",
    "gn:name":"Preuschwitz",
    "gn:population":0,
    "gn:timezone":"Europe/Berlin",
    "iso:country":"DE",
    "name:hsb_x_preferred":[
        "P\u0159i\u0161ecy"
    ],
    "wof:name":"Preuschwitz",
    "wof:placetype":"neighbourhood"
},
  "geometry": {"coordinates":[14.40872,51.15832],"type":"Point"}
}