{
  "type": "Feature",
  "properties": {
    "gn:admin1_code":"2.0",
    "gn:admin2_code":"93.0",
    "gn:admin3_code":"9376.0",
    "gn:admin4_code":"9376173.0",
    "gn:asciiname":"Atzenhof",
    "gn:country_code":"DE",
    "gn:dem":447,
    "gn:feature_class":"P",
    "gn:feature_code":"PPL",
    "gn:name":"Atzenhof",
    "gn:population":0,
    "gn:timezone":"Europe/Berlin",
    "iso:country":"DE",
    "wof:name":"Atzenhof",
    "wof:placetype":"neighbourhood"
},
  "geometry": {"coordinates":[12.26825,49.5134],"type":"Point"}
}