{
  "type": "Feature",
  "properties": {
    "gn:admin1_code":"15",
    "gn:admin2_code":"0.0",
    "gn:admin3_code":"16076.0",
    "gn:admin4_code":"16076022.0",
    "gn:asciiname":"Raasdorf",
    "gn:country_code":"DE",
    "gn:dem":349,
    "gn:feature_class":"P",
    "gn:feature_code":"PPL",
    "gn:name":"Raasdorf",
    "gn:population":0,
    "gn:timezone":"Europe/Berlin",
    "iso:country":"DE",
    "name:ceb_x_preferred":[
        "Raasdorf"
    ],
    "name:ces_x_preferred":[
        "Raasdorf"
    ],
    "name:deu_x_preferred":[
        "Raasdorf"
    ],
    "name:epo_x_preferred":[
        "Raasdorf"
    ],
    "name:fas_x_preferred":[
        "\u0631\u0627\u0633\u062f\u0648\u0631\u0641"
    ],
    "name:fra_x_preferred":[
        "Raasdorf"
    ],
    "name:hun_x_preferred":[
        "Raasdorf"
    ],
    "name:ita_x_preferred":[
        "Raasdorf"
    ],
    "name:kaz_x_preferred":[
        "\u0420\u0430\u0441\u0434\u043e\u0440\u0444"
    ],
    "name:nld_x_preferred":[
        "Raasdorf"
    ],
    "name:pol_x_preferred":[
        "Raasdorf"
    ],
    "name:por_x_preferred":[
        "Raasdorf"
    ],
    "name:rus_x_preferred":[
        "\u0420\u0430\u0441\u0434\u043e\u0440\u0444"
    ],
    "name:slk_x_preferred":[
        "Raasdorf"
    ],
    "name:spa_x_preferred":[
        "Raasdorf"
    ],
    "name:swe_x_preferred":[
        "Raasdorf"
    ],
    "name:szl_x_preferred":[
        "Raasdorf"
    ],
    "name:und_x_variant":[
        "Greiz-Raasdorf"
    ],
    "name:uzb_x_preferred":[
        "Raasdorf"
    ],
    "name:vie_x_preferred":[
        "Raasdorf"
    ],
    "name:vol_x_preferred":[
        "Raasdorf"
    ],
    "name:war_x_preferred":[
        "Raasdorf"
    ],
    "name:zho_x_preferred":[
        "\u62c9\u65af\u591a\u592b"
    ],
    "wof:name":"Raasdorf",
    "wof:placetype":"neighbourhood"
},
  "geometry": {"coordinates":[12.23944,50.66516],"type":"Point"}
}