{
  "type": "Feature",
  "properties": {
    "gn:admin1_code":"15",
    "gn:admin2_code":"0.0",
    "gn:admin3_code":"16076.0",
    "gn:admin4_code":"16076022.0",
    "gn:asciiname":"Raasdorf",
    "gn:country_code":"DE",
    "gn:dem":349,
    "gn:feature_class":"P",
    "gn:feature_code":"PPL",
    "gn:name":"Raasdorf",
    "gn:population":0,
    "gn:timezone":"Europe/Berlin",
    "iso:country":"DE",
    "name:und_x_variant":[
        "Greiz-Raasdorf",
        "Raasdorf"
    ],
    "wof:name":"Raasdorf",
    "wof:placetype":"neighbourhood"
},
  "geometry": {"coordinates":[12.23944,50.66516],"type":"Point"}
}