{
  "type": "Feature",
  "properties": {
    "gn:admin1_code":"9",
    "gn:admin2_code":"0.0",
    "gn:admin3_code":"10042.0",
    "gn:admin4_code":"10042114.0",
    "gn:asciiname":"Nohn",
    "gn:country_code":"DE",
    "gn:dem":305,
    "gn:feature_class":"P",
    "gn:feature_code":"PPL",
    "gn:name":"Nohn",
    "gn:population":0,
    "gn:timezone":"Europe/Berlin",
    "iso:country":"DE",
    "name:ceb_x_preferred":[
        "Nohn"
    ],
    "name:deu_x_preferred":[
        "Nohn"
    ],
    "name:epo_x_preferred":[
        "Nohn"
    ],
    "name:eus_x_preferred":[
        "Nohn"
    ],
    "name:fra_x_preferred":[
        "Nohn"
    ],
    "name:hun_x_preferred":[
        "Nohn"
    ],
    "name:ita_x_preferred":[
        "Nohn"
    ],
    "name:msa_x_preferred":[
        "Nohn"
    ],
    "name:nld_x_preferred":[
        "Nohn"
    ],
    "name:pol_x_preferred":[
        "Nohn"
    ],
    "name:por_x_preferred":[
        "Nohn"
    ],
    "name:ron_x_preferred":[
        "Nohn"
    ],
    "name:rus_x_preferred":[
        "\u041d\u043e\u043d"
    ],
    "name:spa_x_preferred":[
        "Nohn"
    ],
    "name:srp_x_preferred":[
        "\u041d\u043e\u043d"
    ],
    "name:ukr_x_preferred":[
        "\u041d\u043e\u043d"
    ],
    "name:uzb_x_preferred":[
        "Nohn"
    ],
    "name:vie_x_preferred":[
        "Nohn"
    ],
    "name:vol_x_preferred":[
        "Nohn"
    ],
    "name:war_x_preferred":[
        "Nohn"
    ],
    "name:zho_x_preferred":[
        "\u8bfa\u6069"
    ],
    "wof:name":"Nohn",
    "wof:placetype":"neighbourhood"
},
  "geometry": {"coordinates":[6.54236,49.4843],"type":"Point"}
}