{
  "type": "Feature",
  "properties": {
    "gn:admin1_code":"8",
    "gn:admin2_code":"0.0",
    "gn:admin3_code":"7233.0",
    "gn:admin4_code":"7233084.0",
    "gn:asciiname":"Oberwinkel",
    "gn:country_code":"DE",
    "gn:dem":381,
    "gn:feature_class":"P",
    "gn:feature_code":"PPL",
    "gn:name":"Oberwinkel",
    "gn:population":0,
    "gn:timezone":"Europe/Berlin",
    "iso:country":"DE",
    "wof:name":"Oberwinkel",
    "wof:placetype":"neighbourhood"
},
  "geometry": {"coordinates":[6.94234,50.14621],"type":"Point"}
}