{
  "type": "Feature",
  "properties": {
    "gn:admin1_code":"15",
    "gn:admin2_code":"0.0",
    "gn:admin3_code":"16072.0",
    "gn:admin4_code":"16072015.0",
    "gn:asciiname":"Goersdorf",
    "gn:country_code":"DE",
    "gn:dem":420,
    "gn:feature_class":"P",
    "gn:feature_code":"PPL",
    "gn:name":"G\u00f6rsdorf",
    "gn:population":0,
    "gn:timezone":"Europe/Berlin",
    "iso:country":"DE",
    "wof:name":"Goersdorf",
    "wof:placetype":"neighbourhood"
},
  "geometry": {"coordinates":[10.96076,50.37931],"type":"Point"}
}