{
  "type": "Feature",
  "properties": {
    "gn:admin1_code":"12",
    "gn:admin2_code":"0.0",
    "gn:admin3_code":"13071.0",
    "gn:admin4_code":"13071102.0",
    "gn:asciiname":"Moelln",
    "gn:country_code":"DE",
    "gn:dem":51,
    "gn:feature_class":"P",
    "gn:feature_code":"PPL",
    "gn:name":"M\u00f6lln",
    "gn:population":604,
    "gn:timezone":"Europe/Berlin",
    "iso:country":"DE",
    "wof:name":"Moelln",
    "wof:placetype":"neighbourhood",
    "wof:population":604
},
  "geometry": {"coordinates":[13.08529,53.59021],"type":"Point"}
}