{
  "type": "Feature",
  "properties": {
    "gn:admin1_code":"2",
    "gn:admin2_code":"97.0",
    "gn:admin3_code":"9772.0",
    "gn:admin4_code":"9772111.0",
    "gn:asciiname":"Kruichen",
    "gn:country_code":"DE",
    "gn:dem":481,
    "gn:feature_class":"P",
    "gn:feature_code":"PPL",
    "gn:name":"Kruichen",
    "gn:population":0,
    "gn:timezone":"Europe/Berlin",
    "iso:country":"DE",
    "wof:name":"Kruichen",
    "wof:placetype":"neighbourhood"
},
  "geometry": {"coordinates":[10.69553,48.43239000000001],"type":"Point"}
}