{
  "type": "Feature",
  "properties": {
    "gn:admin1_code":"5.0",
    "gn:admin2_code":"064",
    "gn:admin3_code":"6440.0",
    "gn:admin4_code":"6440018.0",
    "gn:asciiname":"Ziegenberg",
    "gn:country_code":"DE",
    "gn:dem":247,
    "gn:feature_class":"P",
    "gn:feature_code":"PPL",
    "gn:name":"Ziegenberg",
    "gn:population":0,
    "gn:timezone":"Europe/Berlin",
    "iso:country":"DE",
    "name:ceb_x_preferred":[
        "Ziegenberg"
    ],
    "name:deu_x_preferred":[
        "Ziegenberg"
    ],
    "name:swe_x_preferred":[
        "Ziegenberg"
    ],
    "name:und_x_variant":[
        "Langenhain-Ziegenberg"
    ],
    "wof:name":"Ziegenberg",
    "wof:placetype":"neighbourhood"
},
  "geometry": {"coordinates":[8.63195,50.36628],"type":"Point"}
}