{
  "type": "Feature",
  "properties": {
    "gn:admin1_code":"1",
    "gn:admin2_code":"83.0",
    "gn:admin3_code":"8336.0",
    "gn:admin4_code":"8336087.0",
    "gn:asciiname":"Geschwend",
    "gn:country_code":"DE",
    "gn:dem":587,
    "gn:feature_class":"P",
    "gn:feature_code":"PPL",
    "gn:name":"Geschwend",
    "gn:population":0,
    "gn:timezone":"Europe/Berlin",
    "iso:country":"DE",
    "wof:name":"Geschwend",
    "wof:placetype":"neighbourhood"
},
  "geometry": {"coordinates":[7.9396,47.80416],"type":"Point"}
}