{
  "type": "Feature",
  "properties": {
    "gn:gn_country":"DE",
    "gn:gn_fcode":"PPLA4",
    "gn:gn_pop":405,
    "gn:population":405,
    "iso:country":"DE",
    "name:baq_x_preferred":[
        "Uhler"
    ],
    "name:chi_x_preferred":[
        "\u4e4c\u83b1\u5c14"
    ],
    "name:dut_x_preferred":[
        "Uhler"
    ],
    "name:eng_x_preferred":[
        "Uhler"
    ],
    "name:epo_x_preferred":[
        "Uhler"
    ],
    "name:fre_x_preferred":[
        "Uhler"
    ],
    "name:ger_x_preferred":[
        "Uhler"
    ],
    "name:hun_x_preferred":[
        "Uhler"
    ],
    "name:ita_x_preferred":[
        "Uhler"
    ],
    "name:jpn_x_preferred":[
        "\u30a6\u30fc\u30e9\u30fc"
    ],
    "name:per_x_preferred":[
        "\u0627\u0648\u0647\u0644\u0631"
    ],
    "name:pol_x_preferred":[
        "Uhler"
    ],
    "name:por_x_preferred":[
        "Uhler"
    ],
    "name:rum_x_preferred":[
        "Uhler"
    ],
    "name:rus_x_preferred":[
        "\u0423\u043b\u0435\u0440"
    ],
    "name:srp_x_preferred":[
        "\u0423\u043b\u0435\u0440"
    ],
    "name:ukr_x_preferred":[
        "\u0423\u043b\u0435\u0440"
    ],
    "name:uzb_x_preferred":[
        "Uhler"
    ],
    "name:vie_x_preferred":[
        "Uhler"
    ],
    "name:vol_x_preferred":[
        "Uhler"
    ],
    "name:war_x_preferred":[
        "Uhler"
    ],
    "qs_pg:aaroncc":"DE",
    "qs_pg:gn_country":"DE",
    "qs_pg:gn_fcode":"PPLA4",
    "qs_pg:gn_pop":405,
    "qs_pg:name":"Uhler",
    "qs_pg:photos_9r":0,
    "qs_pg:photos_sr":0,
    "qs_pg:pop_sr":2,
    "qs_pg:qs_pg_placetype":"locality",
    "wof:name":"Uhler",
    "wof:placetype":"locality",
    "wof:population":405
},
  "geometry": {"coordinates":[7.43333,50.08333],"type":"Point"}
}