{
  "type": "Feature",
  "properties": {
    "gn:gn_country":"DE",
    "gn:gn_fcode":"PPL",
    "gn:gn_pop":0,
    "iso:country":"DE",
    "name:deu_x_preferred":[
        "Stiddien"
    ],
    "name:unk_x_variant":[
        "Stiddien"
    ],
    "qs:gn_adm0_cc":"DE",
    "qs:gn_fcode":"PPL",
    "qs:gn_local":2945024,
    "qs:gn_namadm1":"06",
    "qs:gn_name":"Stiddien",
    "qs:local_max":1853,
    "qs:local_sum":10764,
    "qs:localhoods":34,
    "qs:name":"Stiddien",
    "qs:name_adm0":"Deutschland",
    "qs:name_adm1":"Niedersachsen",
    "qs:name_adm2":"Stadtkreis Braunschweig",
    "qs:name_lau":"Timmerlah-Geitelde-Stiddien",
    "qs:name_local":"Braunschweig",
    "qs:photo_max":10,
    "qs:photo_sum":28,
    "qs:placetype":"Suburb",
    "qs:quad_count":12,
    "qs:woe_adm0":23424829,
    "qs:woe_adm1":2345486,
    "qs:woe_adm2":12596719,
    "qs:woe_lau":26822042,
    "qs:woe_local":640831,
    "qs:woe_ver":"7.10.0",
    "qs_pg:aaroncc":"DE",
    "qs_pg:gn_country":"DE",
    "qs_pg:gn_fcode":"PPL",
    "qs_pg:gn_pop":0,
    "qs_pg:name":"Stiddien",
    "qs_pg:name_adm0":"Deutschland",
    "qs_pg:name_adm1":"Niedersachsen",
    "qs_pg:photos":28,
    "qs_pg:photos_1k":6,
    "qs_pg:photos_9k":1,
    "qs_pg:photos_9r":2,
    "qs_pg:photos_all":28,
    "qs_pg:photos_sr":2,
    "qs_pg:pop_sr":0,
    "qs_pg:qs_pg_placetype":"neighbourhood",
    "qs_pg:qs_pg_placetype_gp":"Suburb",
    "qs_pg:woe_adm0":23424829,
    "wof:lang":[
        "ger"
    ],
    "wof:name":"Stiddien",
    "wof:placetype":"neighbourhood"
},
  "geometry": {"coordinates":[10.455649,52.233204],"type":"Point"}
}