{
  "type": "Feature",
  "properties": {
    "gn:admin1_code":"13",
    "gn:admin2_code":"0.0",
    "gn:admin3_code":"14521.0",
    "gn:admin4_code":"14521110.0",
    "gn:asciiname":"Oberglobenstein",
    "gn:country_code":"DE",
    "gn:dem":566,
    "gn:feature_class":"P",
    "gn:feature_code":"PPL",
    "gn:name":"Oberglobenstein",
    "gn:population":0,
    "gn:timezone":"Europe/Berlin",
    "iso:country":"DE",
    "wof:name":"Oberglobenstein",
    "wof:placetype":"neighbourhood"
},
  "geometry": {"coordinates":[12.78551,50.49674],"type":"Point"}
}