{
  "type": "Feature",
  "properties": {
    "gn:admin1_code":"10",
    "gn:admin2_code":"0.0",
    "gn:admin3_code":"1058.0",
    "gn:admin4_code":"1058005.0",
    "gn:asciiname":"Stift",
    "gn:country_code":"DE",
    "gn:dem":27,
    "gn:feature_class":"P",
    "gn:feature_code":"PPL",
    "gn:name":"Stift",
    "gn:population":0,
    "gn:timezone":"Europe/Berlin",
    "iso:country":"DE",
    "name:deu_x_preferred":[
        "Stift"
    ],
    "name:epo_x_preferred":[
        "Kolegiato"
    ],
    "name:fra_x_preferred":[
        "Stift"
    ],
    "name:nld_x_preferred":[
        "Sticht"
    ],
    "name:nor_x_preferred":[
        "Kirkestift"
    ],
    "wof:name":"Stift",
    "wof:placetype":"neighbourhood"
},
  "geometry": {"coordinates":[10.13224,54.38551999999999],"type":"Point"}
}