{
  "type": "Feature",
  "properties": {
    "gn:admin1_code":"6.0",
    "gn:admin2_code":"0.0",
    "gn:admin3_code":"3353.0",
    "gn:admin4_code":"3353009.0",
    "gn:asciiname":"Sudermuehlen",
    "gn:country_code":"DE",
    "gn:dem":60,
    "gn:feature_class":"P",
    "gn:feature_code":"PPL",
    "gn:name":"Suderm\u00fchlen",
    "gn:population":0,
    "gn:timezone":"Europe/Berlin",
    "iso:country":"DE",
    "name:nds_x_preferred":[
        "Su\u2019m\u00f6hlen"
    ],
    "wof:name":"Sudermuehlen",
    "wof:placetype":"neighbourhood"
},
  "geometry": {"coordinates":[10.03061,53.19212],"type":"Point"}
}