{
  "type": "Feature",
  "properties": {
    "gn:admin1_code":"6.0",
    "gn:admin2_code":"00",
    "gn:admin3_code":"3352.0",
    "gn:admin4_code":"3352038.0",
    "gn:asciiname":"Westerihlienworth",
    "gn:country_code":"DE",
    "gn:dem":-2,
    "gn:feature_class":"P",
    "gn:feature_code":"PPL",
    "gn:name":"Westerihlienworth",
    "gn:population":0,
    "gn:timezone":"Europe/Berlin",
    "iso:country":"DE",
    "wof:name":"Westerihlienworth",
    "wof:placetype":"neighbourhood"
},
  "geometry": {"coordinates":[8.91667,53.75],"type":"Point"}
}