{
  "type": "Feature",
  "properties": {
    "iso:country":"DE",
    "wof:name":"Heideviertel",
    "wof:placetype":"neighbourhood"
},
  "geometry": {"coordinates":[9.81800852681215,52.37934211178725],"type":"Point"}
}