{
  "type": "Feature",
  "properties": {
    "gn:admin1_code":"12",
    "gn:admin2_code":"0.0",
    "gn:admin3_code":"13072.0",
    "gn:admin4_code":"13072063.0",
    "gn:asciiname":"Mamerow",
    "gn:cc2":"DE",
    "gn:country_code":"DE",
    "gn:dem":49,
    "gn:feature_class":"P",
    "gn:feature_code":"PPL",
    "gn:name":"Mamerow",
    "gn:population":0,
    "gn:timezone":"Europe/Berlin",
    "iso:country":"DE",
    "name:und_x_variant":[
        "Mamerow Dorf"
    ],
    "wof:name":"Mamerow",
    "wof:placetype":"neighbourhood"
},
  "geometry": {"coordinates":[12.43378,53.73226],"type":"Point"}
}