{
  "type": "Feature",
  "properties": {
    "gn:admin1_code":"5",
    "gn:admin2_code":"64.0",
    "gn:admin3_code":"6432.0",
    "gn:admin4_code":"6432022.0",
    "gn:asciiname":"Stettbach",
    "gn:country_code":"DE",
    "gn:dem":292,
    "gn:feature_class":"P",
    "gn:feature_code":"PPL",
    "gn:name":"Stettbach",
    "gn:population":0,
    "gn:timezone":"Europe/Berlin",
    "iso:country":"DE",
    "wof:name":"Stettbach",
    "wof:placetype":"neighbourhood"
},
  "geometry": {"coordinates":[8.67639,49.74833],"type":"Point"}
}