{
  "type": "Feature",
  "properties": {
    "gn:admin1_code":"7.0",
    "gn:admin2_code":"55.0",
    "gn:admin3_code":"5558.0",
    "gn:admin4_code":"5558016.0",
    "gn:asciiname":"Boernste",
    "gn:country_code":"DE",
    "gn:dem":65,
    "gn:feature_class":"P",
    "gn:feature_code":"PPL",
    "gn:name":"B\u00f6rnste",
    "gn:population":0,
    "gn:timezone":"Europe/Berlin",
    "iso:country":"DE",
    "wof:name":"Boernste",
    "wof:placetype":"neighbourhood"
},
  "geometry": {"coordinates":[7.23583,51.84014000000001],"type":"Point"}
}