{
  "type": "Feature",
  "properties": {
    "gn:admin1_code":"7",
    "gn:admin2_code":"59.0",
    "gn:admin3_code":"5962.0",
    "gn:admin4_code":"5962012.0",
    "gn:asciiname":"Schwenke",
    "gn:country_code":"DE",
    "gn:dem":392,
    "gn:feature_class":"P",
    "gn:feature_code":"PPLL",
    "gn:name":"Schwenke",
    "gn:population":0,
    "gn:timezone":"Europe/Berlin",
    "iso:country":"DE",
    "name:deu_x_preferred":[
        "Schwenke"
    ],
    "name:fra_x_preferred":[
        "Schwenke"
    ],
    "name:spa_x_preferred":[
        "Schwenke"
    ],
    "wof:name":"Schwenke",
    "wof:placetype":"neighbourhood"
},
  "geometry": {"coordinates":[7.43749,51.19149],"type":"Point"}
}