{
  "type": "Feature",
  "properties": {
    "gn:admin1_code":"5.0",
    "gn:admin2_code":"066",
    "gn:admin3_code":"6636.0",
    "gn:admin4_code":"6636016.0",
    "gn:asciiname":"Werleshausen",
    "gn:country_code":"DE",
    "gn:dem":145,
    "gn:feature_class":"P",
    "gn:feature_code":"PPL",
    "gn:name":"Werleshausen",
    "gn:population":0,
    "gn:timezone":"Europe/Berlin",
    "iso:country":"DE",
    "name:deu_x_preferred":[
        "Werleshausen"
    ],
    "name:fas_x_preferred":[
        "\u0648\u0631\u0644\u0633\u0647\u0627\u0648\u0632\u0646"
    ],
    "wof:name":"Werleshausen",
    "wof:placetype":"neighbourhood"
},
  "geometry": {"coordinates":[9.91545,51.32494000000001],"type":"Point"}
}