{
  "type": "Feature",
  "properties": {
    "gn:admin1_code":"15",
    "gn:admin2_code":"0.0",
    "gn:admin3_code":"16052.0",
    "gn:admin4_code":"16052000.0",
    "gn:asciiname":"Niebra",
    "gn:country_code":"DE",
    "gn:dem":301,
    "gn:feature_class":"P",
    "gn:feature_code":"PPL",
    "gn:name":"Niebra",
    "gn:population":0,
    "gn:timezone":"Europe/Berlin",
    "iso:country":"DE",
    "wof:name":"Niebra",
    "wof:placetype":"neighbourhood"
},
  "geometry": {"coordinates":[12.11386,50.81989],"type":"Point"}
}