{
  "type": "Feature",
  "properties": {
    "gn:admin1_code":"2",
    "gn:admin2_code":"96.0",
    "gn:admin3_code":"9675.0",
    "gn:admin4_code":"9675139.0",
    "gn:asciiname":"Monchsondheim",
    "gn:country_code":"DE",
    "gn:dem":270,
    "gn:feature_class":"P",
    "gn:feature_code":"PPL",
    "gn:name":"M\u00f6nchsondheim",
    "gn:population":0,
    "gn:timezone":"Europe/Berlin",
    "iso:country":"DE",
    "wof:name":"Monchsondheim",
    "wof:placetype":"neighbourhood"
},
  "geometry": {"coordinates":[10.27873,49.66721],"type":"Point"}
}