{
  "type": "Feature",
  "properties": {
    "gn:admin1_code":"1",
    "gn:admin2_code":"84.0",
    "gn:admin3_code":"8436.0",
    "gn:admin4_code":"8436094.0",
    "gn:asciiname":"Obervorholz",
    "gn:country_code":"DE",
    "gn:dem":738,
    "gn:feature_class":"P",
    "gn:feature_code":"PPL",
    "gn:name":"Obervorholz",
    "gn:population":0,
    "gn:timezone":"Europe/Berlin",
    "iso:country":"DE",
    "wof:name":"Obervorholz",
    "wof:placetype":"neighbourhood"
},
  "geometry": {"coordinates":[9.96667,47.66667],"type":"Point"}
}