{
  "type": "Feature",
  "properties": {
    "gn:admin1_code":"2",
    "gn:admin2_code":"91.0",
    "gn:admin3_code":"9172.0",
    "gn:admin4_code":"9172131.0",
    "gn:asciiname":"Melleck",
    "gn:country_code":"DE",
    "gn:dem":606,
    "gn:feature_class":"P",
    "gn:feature_code":"PPL",
    "gn:name":"Melleck",
    "gn:population":0,
    "gn:timezone":"Europe/Berlin",
    "iso:country":"DE",
    "wof:name":"Melleck",
    "wof:placetype":"neighbourhood"
},
  "geometry": {"coordinates":[12.7604,47.67205],"type":"Point"}
}