{
  "type": "Feature",
  "properties": {
    "gn:admin1_code":"2",
    "gn:admin2_code":"91.0",
    "gn:admin3_code":"9176.0",
    "gn:admin4_code":"9176114.0",
    "gn:asciiname":"Hirschberg",
    "gn:country_code":"DE",
    "gn:dem":502,
    "gn:feature_class":"P",
    "gn:feature_code":"PPL",
    "gn:name":"Hirschberg",
    "gn:population":0,
    "gn:timezone":"Europe/Berlin",
    "iso:country":"DE",
    "name:cat_x_preferred":[
        "Hirschberg"
    ],
    "name:ceb_x_preferred":[
        "Hirschberg"
    ],
    "name:ces_x_preferred":[
        "Hirschberg"
    ],
    "name:deu_x_preferred":[
        "Hirschberg"
    ],
    "name:epo_x_preferred":[
        "Hirschberg"
    ],
    "name:est_x_preferred":[
        "Hirschberg"
    ],
    "name:fas_x_preferred":[
        "\u0647\u06cc\u0631\u0634\u0628\u0631\u06af"
    ],
    "name:fra_x_preferred":[
        "Hirschberg"
    ],
    "name:heb_x_preferred":[
        "\u05d4\u05d9\u05e8\u05e9\u05d1\u05e8\u05d2"
    ],
    "name:ita_x_preferred":[
        "Hirschberg"
    ],
    "name:jpn_x_preferred":[
        "\u30d2\u30eb\u30b7\u30e5\u30d9\u30eb\u30af"
    ],
    "name:nld_x_preferred":[
        "Hirschberg"
    ],
    "name:pol_x_preferred":[
        "Hirschberg"
    ],
    "name:por_x_preferred":[
        "Hirschberg"
    ],
    "name:rus_x_preferred":[
        "\u0425\u0438\u0440\u0448\u0431\u0435\u0440\u0433"
    ],
    "name:spa_x_preferred":[
        "Hirschberg"
    ],
    "name:swe_x_preferred":[
        "Hirschberg"
    ],
    "name:vol_x_preferred":[
        "Hirschberg"
    ],
    "wof:name":"Hirschberg",
    "wof:placetype":"neighbourhood"
},
  "geometry": {"coordinates":[11.45428,49.03663],"type":"Point"}
}