{
  "type": "Feature",
  "properties": {
    "gn:admin1_code":"2",
    "gn:admin2_code":"93.0",
    "gn:admin3_code":"9374.0",
    "gn:admin4_code":"9374122.0",
    "gn:asciiname":"Hildweinsreuth",
    "gn:country_code":"DE",
    "gn:dem":707,
    "gn:feature_class":"P",
    "gn:feature_code":"PPL",
    "gn:name":"Hildweinsreuth",
    "gn:population":0,
    "gn:timezone":"Europe/Berlin",
    "iso:country":"DE",
    "wof:name":"Hildweinsreuth",
    "wof:placetype":"neighbourhood"
},
  "geometry": {"coordinates":[12.35765,49.75768],"type":"Point"}
}