{
  "type": "Feature",
  "properties": {
    "gn:admin1_code":"1",
    "gn:admin2_code":"84.0",
    "gn:admin3_code":"8437.0",
    "gn:admin4_code":"8437044.0",
    "gn:asciiname":"Mieterkingen",
    "gn:country_code":"DE",
    "gn:dem":584,
    "gn:feature_class":"P",
    "gn:feature_code":"PPL",
    "gn:name":"Mieterkingen",
    "gn:population":0,
    "gn:timezone":"Europe/Berlin",
    "iso:country":"DE",
    "wof:name":"Mieterkingen",
    "wof:placetype":"neighbourhood"
},
  "geometry": {"coordinates":[9.45129,48.05002],"type":"Point"}
}