{
  "type": "Feature",
  "properties": {
    "gn:admin1_code":"14.0",
    "gn:admin2_code":"00",
    "gn:admin3_code":"15081.0",
    "gn:admin4_code":"15081105.0",
    "gn:asciiname":"Wuellmersen",
    "gn:country_code":"DE",
    "gn:dem":66,
    "gn:feature_class":"P",
    "gn:feature_code":"PPL",
    "gn:name":"W\u00fcllmersen",
    "gn:population":0,
    "gn:timezone":"Europe/Berlin",
    "iso:country":"DE",
    "wof:name":"Wuellmersen",
    "wof:placetype":"neighbourhood"
},
  "geometry": {"coordinates":[10.94347,52.72507],"type":"Point"}
}