{
  "type": "Feature",
  "properties": {
    "gn:admin1_code":"2",
    "gn:admin2_code":"91.0",
    "gn:admin3_code":"9183.0",
    "gn:admin4_code":"9183135.0",
    "gn:asciiname":"Deutenheim",
    "gn:country_code":"DE",
    "gn:dem":463,
    "gn:feature_class":"P",
    "gn:feature_code":"PPL",
    "gn:name":"Deutenheim",
    "gn:population":0,
    "gn:timezone":"Europe/Berlin",
    "iso:country":"DE",
    "wof:name":"Deutenheim",
    "wof:placetype":"neighbourhood"
},
  "geometry": {"coordinates":[12.29439,48.24937],"type":"Point"}
}