{
  "type": "Feature",
  "properties": {
    "gn:admin1_code":"1",
    "gn:admin2_code":"84.0",
    "gn:admin3_code":"8435.0",
    "gn:admin4_code":"8435066.0",
    "gn:asciiname":"Oberuhldingen",
    "gn:country_code":"DE",
    "gn:dem":418,
    "gn:feature_class":"P",
    "gn:feature_code":"PPL",
    "gn:name":"Oberuhldingen",
    "gn:population":0,
    "gn:timezone":"Europe/Berlin",
    "iso:country":"DE",
    "wof:name":"Oberuhldingen",
    "wof:placetype":"neighbourhood"
},
  "geometry": {"coordinates":[9.25,47.73333],"type":"Point"}
}