{
  "type": "Feature",
  "properties": {
    "iso:country":"DE",
    "name:deu_x_preferred":[
        "Altenhagen"
    ],
    "name:deu_x_variant":[
        "Altenhagen (Celle)",
        "Celle-Altenhagen"
    ],
    "name:nds_x_preferred":[
        "Olenhagen"
    ],
    "name:nds_x_variant":[
        "o\u02d0l\u0259nh\u0254\u02d0\u0263\u0259n",
        "\u014dl\u0259nh\u01fb\u0292\u0259n",
        "\u014cl\u2019nh\u00e5\u011f\u0115n"
    ],
    "name:unk_x_variant":[
        "Altenhagen"
    ],
    "qs:gn_fcode":"PPL",
    "qs:gn_local":0,
    "qs:gn_namadm1":"06",
    "qs:gn_name":"Altenhagen",
    "qs:local_max":122,
    "qs:local_sum":398,
    "qs:localhoods":10,
    "qs:name":"Altenhagen",
    "qs:name_adm0":"Deutschland",
    "qs:name_adm1":"Niedersachsen",
    "qs:name_adm2":"Stadtkreis Salzgitter",
    "qs:name_lau":"Stadtteil Lichtenberg",
    "qs:name_local":"Salzgitter",
    "qs:photo_max":7,
    "qs:photo_sum":14,
    "qs:placetype":"Suburb",
    "qs:quad_count":4,
    "qs:woe_adm0":23424829,
    "qs:woe_adm1":2345486,
    "qs:woe_adm2":12596994,
    "qs:woe_lau":26823239,
    "qs:woe_local":690863,
    "qs:woe_ver":"7.10.0",
    "wof:lang":[
        "ger"
    ],
    "wof:name":"Altenhagen",
    "wof:placetype":"neighbourhood"
},
  "geometry": {"coordinates":[10.283988,52.11783],"type":"Point"}
}