{
  "type": "Feature",
  "properties": {
    "gn:country":"DE",
    "gn:fcode":"PPL",
    "gn:population":299,
    "iso:country":"DE",
    "name:bak_x_preferred":[
        "\u0425\u043e\u044d\u043d\u0442\u0440\u0430\u043c"
    ],
    "name:ceb_x_preferred":[
        "Hohentramm"
    ],
    "name:che_x_preferred":[
        "\u0425\u043e\u044d\u043d\u0442\u0440\u0430\u043c"
    ],
    "name:deu_x_preferred":[
        "Hohentramm"
    ],
    "name:eng_x_preferred":[
        "Hohentramm"
    ],
    "name:epo_x_preferred":[
        "Hohentramm"
    ],
    "name:fas_x_preferred":[
        "\u0647\u0648\u0647\u0646\u062a\u0631\u0627\u0645"
    ],
    "name:fra_x_preferred":[
        "Hohentramm"
    ],
    "name:gle_x_preferred":[
        "Hohentramm"
    ],
    "name:kaz_x_preferred":[
        "\u0425\u043e\u044d\u043d\u0442\u0440\u0430\u043c"
    ],
    "name:kir_x_preferred":[
        "\u0425\u043e\u044d\u043d\u0442\u0440\u0430\u043c"
    ],
    "name:nld_x_preferred":[
        "Hohentramm"
    ],
    "name:ron_x_preferred":[
        "Hohentramm"
    ],
    "name:rus_x_preferred":[
        "\u0425\u043e\u044d\u043d\u0442\u0440\u0430\u043c"
    ],
    "name:tat_x_preferred":[
        "\u0425\u043e\u044d\u043d\u0442\u0440\u0430\u043c"
    ],
    "name:uzb_x_preferred":[
        "Hohentramm"
    ],
    "name:vol_x_preferred":[
        "Hohentramm"
    ],
    "qs_pg:aaroncc":"DE",
    "qs_pg:gn_country":"DE",
    "qs_pg:gn_fcode":"PPL",
    "qs_pg:gn_pop":299,
    "qs_pg:name":"Hohentramm",
    "qs_pg:name_adm0":"Deutschland",
    "qs_pg:name_adm1":"Sachsen-Anhalt",
    "qs_pg:photos_9r":0,
    "qs_pg:photos_sr":0,
    "qs_pg:pop_sr":2,
    "qs_pg:qs_pg_placetype":"locality",
    "qs_pg:qs_pg_placetype_gp":"Town",
    "qs_pg:woe_adm0":23424829,
    "woe:adm0_id":23424829,
    "woe:name_adm0":"Deutschland",
    "woe:name_adm1":"Sachsen-Anhalt",
    "woe:placetype":"Town",
    "wof:name":"Hohentramm",
    "wof:placetype":"neighbourhood",
    "wof:population":299
},
  "geometry": {"coordinates":[11.14607,52.70826],"type":"Point"}
}