{
  "type": "Feature",
  "properties": {
    "gn:admin1_code":"6",
    "gn:admin2_code":"0.0",
    "gn:admin3_code":"3257.0",
    "gn:admin4_code":"3257016.0",
    "gn:asciiname":"Mathe",
    "gn:country_code":"DE",
    "gn:dem":56,
    "gn:feature_class":"P",
    "gn:feature_code":"PPL",
    "gn:name":"Mathe",
    "gn:population":0,
    "gn:timezone":"Europe/Berlin",
    "iso:country":"DE",
    "name:deu_x_preferred":[
        "Mathe"
    ],
    "wof:name":"Mathe",
    "wof:placetype":"neighbourhood"
},
  "geometry": {"coordinates":[9.37346,52.36586],"type":"Point"}
}