{
  "type": "Feature",
  "properties": {
    "gn:admin1_code":"7",
    "gn:admin2_code":"59.0",
    "gn:admin3_code":"5958.0",
    "gn:admin4_code":"5958040.0",
    "gn:asciiname":"Dornheim",
    "gn:country_code":"DE",
    "gn:dem":506,
    "gn:feature_class":"P",
    "gn:feature_code":"PPL",
    "gn:name":"Dornheim",
    "gn:population":0,
    "gn:timezone":"Europe/Berlin",
    "iso:country":"DE",
    "name:bak_x_preferred":[
        "\u0414\u043e\u0440\u043d\u0445\u0430\u0439\u043c"
    ],
    "name:ceb_x_preferred":[
        "Dornheim"
    ],
    "name:deu_x_preferred":[
        "Dornheim"
    ],
    "name:epo_x_preferred":[
        "Dornheim"
    ],
    "name:eus_x_preferred":[
        "Dornheim"
    ],
    "name:fas_x_preferred":[
        "\u062f\u0648\u0631\u0646\u0647\u0627\u06cc\u0645"
    ],
    "name:fra_x_preferred":[
        "Dornheim"
    ],
    "name:glg_x_preferred":[
        "Dornheim"
    ],
    "name:hun_x_preferred":[
        "Dornheim"
    ],
    "name:ita_x_preferred":[
        "Dornheim"
    ],
    "name:mkd_x_preferred":[
        "\u0414\u043e\u0440\u043d\u0445\u0430\u0458\u043c"
    ],
    "name:msa_x_preferred":[
        "Dornheim"
    ],
    "name:nld_x_preferred":[
        "Dornheim"
    ],
    "name:pol_x_preferred":[
        "Dornheim"
    ],
    "name:por_x_preferred":[
        "Dornheim"
    ],
    "name:ron_x_preferred":[
        "Dornheim"
    ],
    "name:rus_x_preferred":[
        "\u0414\u043e\u0440\u043d\u0445\u0430\u0439\u043c"
    ],
    "name:spa_x_preferred":[
        "Dornheim"
    ],
    "name:srp_x_preferred":[
        "\u0414\u043e\u0440\u043d\u0445\u0430\u0458\u043c"
    ],
    "name:ukr_x_preferred":[
        "\u0414\u043e\u0440\u043d\u0433\u0430\u0439\u043c"
    ],
    "name:uzb_x_preferred":[
        "Dornheim"
    ],
    "name:vie_x_preferred":[
        "Dornheim"
    ],
    "name:vol_x_preferred":[
        "Dornheim"
    ],
    "name:war_x_preferred":[
        "Dornheim"
    ],
    "name:zho_x_preferred":[
        "\u591a\u6069\u6d77\u59c6"
    ],
    "wof:name":"Dornheim",
    "wof:placetype":"neighbourhood"
},
  "geometry": {"coordinates":[8.33706,51.24788],"type":"Point"}
}