{
  "type": "Feature",
  "properties": {
    "gn:admin1_code":"7",
    "gn:admin2_code":"59.0",
    "gn:admin3_code":"5962.0",
    "gn:admin4_code":"5962036.0",
    "gn:asciiname":"Hahnenbecke",
    "gn:country_code":"DE",
    "gn:dem":433,
    "gn:feature_class":"P",
    "gn:feature_code":"PPLL",
    "gn:name":"Hahnenbecke",
    "gn:population":0,
    "gn:timezone":"Europe/Berlin",
    "iso:country":"DE",
    "wof:name":"Hahnenbecke",
    "wof:placetype":"neighbourhood"
},
  "geometry": {"coordinates":[7.62743,51.11034],"type":"Point"}
}