{
  "type": "Feature",
  "properties": {
    "gn:admin1_code":"14.0",
    "gn:admin2_code":"0.0",
    "gn:admin3_code":"15084.0",
    "gn:admin4_code":"15084133.0",
    "gn:asciiname":"Bernsdorf",
    "gn:country_code":"DE",
    "gn:dem":260,
    "gn:feature_class":"P",
    "gn:feature_code":"PPL",
    "gn:name":"Bernsdorf",
    "gn:population":0,
    "gn:timezone":"Europe/Berlin",
    "iso:country":"DE",
    "name:bak_x_preferred":[
        "\u0411\u0435\u0440\u043d\u0441\u0434\u043e\u0440\u0444"
    ],
    "name:ceb_x_preferred":[
        "Bernsdorf"
    ],
    "name:deu_x_preferred":[
        "Bernsdorf"
    ],
    "name:epo_x_preferred":[
        "Bernsdorf"
    ],
    "name:est_x_preferred":[
        "Bernsdorf"
    ],
    "name:fra_x_preferred":[
        "Bernsdorf"
    ],
    "name:ita_x_preferred":[
        "Bernsdorf"
    ],
    "name:kaz_x_preferred":[
        "\u0411\u0435\u0440\u043d\u0441\u0434\u043e\u0440\u0444"
    ],
    "name:mkd_x_preferred":[
        "\u0411\u0435\u0440\u043d\u0441\u0434\u043e\u0440\u0444"
    ],
    "name:nld_x_preferred":[
        "Bernsdorf"
    ],
    "name:pol_x_preferred":[
        "Bernsdorf"
    ],
    "name:rus_x_preferred":[
        "\u0411\u0435\u0440\u043d\u0441\u0434\u043e\u0440\u0444"
    ],
    "wof:name":"Bernsdorf",
    "wof:placetype":"neighbourhood"
},
  "geometry": {"coordinates":[11.48592,51.21758],"type":"Point"}
}