{
  "type": "Feature",
  "properties": {
    "iso:country":"DE",
    "wof:name":"Brooktorkai/Ericus",
    "wof:placetype":"neighbourhood"
},
  "geometry": {"coordinates":[10.00161393518302,53.54486634300878],"type":"Point"}
}