{
  "type": "Feature",
  "properties": {
    "gn:country":"DE",
    "gn:fcode":"PPL",
    "gn:population":193,
    "iso:country":"DE",
    "name:bul_x_preferred":[
        "\u0413\u043e\u0441\u043f\u043e\u0434\u0441\u0442\u0432\u043e \u0412\u0435\u0440\u043b\u0435"
    ],
    "name:deu_x_preferred":[
        "Herrschaft Werle"
    ],
    "name:fra_x_preferred":[
        "Mecklembourg-Werle"
    ],
    "name:mkd_x_preferred":[
        "\u0413\u043e\u0441\u043f\u043e\u0434\u0441\u0442\u0432\u043e \u0412\u0435\u0440\u043b\u0435"
    ],
    "name:pol_x_preferred":[
        "Werle"
    ],
    "name:rus_x_preferred":[
        "\u0412\u0435\u0440\u043b\u0435"
    ],
    "name:swe_x_preferred":[
        "Werle"
    ],
    "qs_pg:aaroncc":"DE",
    "qs_pg:gn_country":"DE",
    "qs_pg:gn_fcode":"PPL",
    "qs_pg:gn_pop":193,
    "qs_pg:name":"Werle",
    "qs_pg:name_adm0":"Deutschland",
    "qs_pg:name_adm1":"Mecklenburg-Vorpommern",
    "qs_pg:photos_9r":0,
    "qs_pg:photos_sr":0,
    "qs_pg:pop_sr":1,
    "qs_pg:qs_pg_placetype":"locality",
    "qs_pg:qs_pg_placetype_gp":"Town",
    "qs_pg:woe_adm0":23424829,
    "woe:adm0_id":23424829,
    "woe:name_adm0":"Deutschland",
    "woe:name_adm1":"Mecklenburg-Vorpommern",
    "woe:placetype":"Town",
    "wof:name":"Werle",
    "wof:placetype":"neighbourhood",
    "wof:population":193
},
  "geometry": {"coordinates":[12.09337,53.8924],"type":"Point"}
}