{
  "type": "Feature",
  "properties": {
    "gn:admin1_code":"5",
    "gn:admin2_code":"64.0",
    "gn:admin3_code":"6439.0",
    "gn:admin4_code":"6439004.0",
    "gn:asciiname":"Marienthal",
    "gn:country_code":"DE",
    "gn:dem":229,
    "gn:feature_class":"P",
    "gn:feature_code":"PPL",
    "gn:name":"Marienthal",
    "gn:population":0,
    "gn:timezone":"Europe/Berlin",
    "iso:country":"DE",
    "name:ceb_x_preferred":[
        "Marienthal"
    ],
    "name:deu_x_preferred":[
        "Marienthal"
    ],
    "name:fin_x_preferred":[
        "Marienthal"
    ],
    "name:fra_x_preferred":[
        "Marienthal"
    ],
    "name:ita_x_preferred":[
        "Marienthal"
    ],
    "name:nld_x_preferred":[
        "Marienthal"
    ],
    "name:pol_x_preferred":[
        "Marienthal"
    ],
    "name:swe_x_preferred":[
        "Marienthal"
    ],
    "wof:name":"Marienthal",
    "wof:placetype":"neighbourhood"
},
  "geometry": {"coordinates":[7.95285,50.0054],"type":"Point"}
}