{
  "type": "Feature",
  "properties": {
    "gn:admin1_code":"12",
    "gn:admin2_code":"0.0",
    "gn:admin3_code":"13076.0",
    "gn:admin4_code":"13076040.0",
    "gn:asciiname":"Penzlin",
    "gn:country_code":"DE",
    "gn:dem":65,
    "gn:feature_class":"P",
    "gn:feature_code":"PPL",
    "gn:name":"Penzlin",
    "gn:population":0,
    "gn:timezone":"Europe/Berlin",
    "iso:country":"DE",
    "name:ara_x_preferred":[
        "\u0628\u0646\u062a\u0633\u0644\u064a\u0646"
    ],
    "name:azb_x_preferred":[
        "\u067e\u0646\u062a\u0633\u0644\u06cc\u0646"
    ],
    "name:ceb_x_preferred":[
        "Penzlin"
    ],
    "name:deu_x_preferred":[
        "Penzlin"
    ],
    "name:epo_x_preferred":[
        "Penzlin"
    ],
    "name:fas_x_preferred":[
        "\u067e\u0646\u062a\u0633\u0644\u06cc\u0646"
    ],
    "name:fra_x_preferred":[
        "Penzlin"
    ],
    "name:hun_x_preferred":[
        "Penzlin"
    ],
    "name:ita_x_preferred":[
        "Penzlin"
    ],
    "name:lav_x_preferred":[
        "Pencl\u012bne"
    ],
    "name:mkd_x_preferred":[
        "\u041f\u0435\u043d\u0446\u043b\u0438\u043d"
    ],
    "name:msa_x_preferred":[
        "Penzlin"
    ],
    "name:nld_x_preferred":[
        "Penzlin"
    ],
    "name:pol_x_preferred":[
        "Penzlin"
    ],
    "name:por_x_preferred":[
        "Penzlin"
    ],
    "name:ron_x_preferred":[
        "Penzlin"
    ],
    "name:rus_x_preferred":[
        "\u041f\u0435\u043d\u0446\u043b\u0438\u043d"
    ],
    "name:spa_x_preferred":[
        "Penzlin"
    ],
    "name:srp_x_preferred":[
        "\u041f\u0435\u043d\u0446\u043b\u0438\u043d"
    ],
    "name:swe_x_preferred":[
        "Penzlin"
    ],
    "name:ukr_x_preferred":[
        "\u041f\u0435\u043d\u0446\u043b\u0456\u043d"
    ],
    "name:uzb_x_preferred":[
        "Penzlin"
    ],
    "name:vie_x_preferred":[
        "Penzlin"
    ],
    "name:vol_x_preferred":[
        "Penzlin"
    ],
    "name:war_x_preferred":[
        "Penzlin"
    ],
    "name:zho_x_preferred":[
        "\u5f6d\u8328\u6797"
    ],
    "wof:name":"Penzlin",
    "wof:placetype":"neighbourhood"
},
  "geometry": {"coordinates":[12.16427,53.52336999999999],"type":"Point"}
}