{
  "type": "Feature",
  "properties": {
    "gn:admin1_code":"12",
    "gn:admin2_code":"0.0",
    "gn:admin3_code":"13073.0",
    "gn:admin4_code":"13073080.0",
    "gn:asciiname":"Clementelvitz",
    "gn:cc2":"DE",
    "gn:country_code":"DE",
    "gn:dem":75,
    "gn:feature_class":"P",
    "gn:feature_code":"PPL",
    "gn:name":"Clementelvitz",
    "gn:population":0,
    "gn:timezone":"Europe/Berlin",
    "iso:country":"DE",
    "name:und_x_variant":[
        "Klementelvitz"
    ],
    "wof:name":"Clementelvitz",
    "wof:placetype":"neighbourhood"
},
  "geometry": {"coordinates":[13.59077,54.52068000000001],"type":"Point"}
}