{
  "type": "Feature",
  "properties": {
    "gn:admin1_code":"10",
    "gn:admin2_code":"0.0",
    "gn:admin3_code":"1061.0",
    "gn:admin4_code":"1061110.0",
    "gn:asciiname":"Rosskopp",
    "gn:country_code":"DE",
    "gn:dem":-1,
    "gn:feature_class":"P",
    "gn:feature_code":"PPL",
    "gn:name":"Ro\u00dfkopp",
    "gn:population":0,
    "gn:timezone":"Europe/Berlin",
    "iso:country":"DE",
    "wof:name":"Rosskopp",
    "wof:placetype":"neighbourhood"
},
  "geometry": {"coordinates":[9.35574,53.85834000000001],"type":"Point"}
}