{
  "type": "Feature",
  "properties": {
    "gn:admin1_code":"1",
    "gn:admin2_code":"84.0",
    "gn:admin3_code":"8437.0",
    "gn:admin4_code":"8437059.0",
    "gn:asciiname":"Engelswies",
    "gn:country_code":"DE",
    "gn:dem":670,
    "gn:feature_class":"P",
    "gn:feature_code":"PPL",
    "gn:name":"Engelswies",
    "gn:population":0,
    "gn:timezone":"Europe/Berlin",
    "iso:country":"DE",
    "wof:name":"Engelswies",
    "wof:placetype":"neighbourhood"
},
  "geometry": {"coordinates":[9.13462,48.04268],"type":"Point"}
}