{
  "type": "Feature",
  "properties": {
    "gn:gn_country":"DE",
    "gn:gn_fcode":"PPLA4",
    "gn:gn_pop":95,
    "gn:population":95,
    "iso:country":"DE",
    "name:baq_x_preferred":[
        "Br\u00fccktal"
    ],
    "name:chi_x_preferred":[
        "\u5e03\u5415\u514b\u5854\u5c14"
    ],
    "name:dut_x_preferred":[
        "Br\u00fccktal"
    ],
    "name:eng_x_preferred":[
        "Br\u00fccktal"
    ],
    "name:epo_x_preferred":[
        "Br\u00fccktal"
    ],
    "name:fre_x_preferred":[
        "Br\u00fccktal"
    ],
    "name:ger_x_preferred":[
        "Br\u00fccktal"
    ],
    "name:hun_x_preferred":[
        "Br\u00fccktal"
    ],
    "name:ita_x_preferred":[
        "Br\u00fccktal"
    ],
    "name:jpn_x_preferred":[
        "\u30d6\u30ea\u30e5\u30c3\u30af\u30bf\u30fc\u30eb"
    ],
    "name:kaz_x_preferred":[
        "\u0411\u0440\u044e\u043a\u0442\u0430\u043b\u044c"
    ],
    "name:kir_x_preferred":[
        "\u0411\u0440\u04af\u043a\u0442\u0430\u043b\u044c"
    ],
    "name:may_x_preferred":[
        "Br\u00fccktal"
    ],
    "name:per_x_preferred":[
        "\u0628\u0631\u0648\u06a9\u062a\u0627\u0644"
    ],
    "name:pol_x_preferred":[
        "Br\u00fccktal"
    ],
    "name:por_x_preferred":[
        "Br\u00fccktal"
    ],
    "name:rum_x_preferred":[
        "Br\u00fccktal"
    ],
    "name:rus_x_preferred":[
        "\u0411\u0440\u044e\u043a\u0442\u0430\u043b\u044c"
    ],
    "name:spa_x_preferred":[
        "Br\u00fccktal"
    ],
    "name:srp_x_preferred":[
        "\u0411\u0440\u0438\u043a\u0442\u0430\u043b"
    ],
    "name:ukr_x_preferred":[
        "\u0411\u0440\u044e\u043a\u0442\u0430\u043b\u044c"
    ],
    "name:unk_x_variant":[
        "Br\u00fcck"
    ],
    "name:uzb_x_preferred":[
        "Br\u00fccktal"
    ],
    "name:vie_x_preferred":[
        "Br\u00fccktal"
    ],
    "name:vol_x_preferred":[
        "Br\u00fccktal"
    ],
    "name:war_x_preferred":[
        "Br\u00fccktal"
    ],
    "qs_pg:aaroncc":"DE",
    "qs_pg:gn_country":"DE",
    "qs_pg:gn_fcode":"PPLA4",
    "qs_pg:gn_pop":95,
    "qs_pg:name":"Br\u00fccktal",
    "qs_pg:photos_9r":0,
    "qs_pg:photos_sr":0,
    "qs_pg:pop_sr":1,
    "qs_pg:qs_pg_placetype":"locality",
    "wof:name":"Br\u00fccktal",
    "wof:placetype":"locality",
    "wof:population":95
},
  "geometry": {"coordinates":[6.98333,50.31667],"type":"Point"}
}