{
  "type": "Feature",
  "properties": {
    "gn:admin1_code":"1",
    "gn:admin2_code":"81.0",
    "gn:admin3_code":"8127.0",
    "gn:admin4_code":"8127032.0",
    "gn:asciiname":"Unterweiler",
    "gn:country_code":"DE",
    "gn:dem":469,
    "gn:feature_class":"P",
    "gn:feature_code":"PPL",
    "gn:name":"Unterweiler",
    "gn:population":0,
    "gn:timezone":"Europe/Berlin",
    "iso:country":"DE",
    "wof:name":"Unterweiler",
    "wof:placetype":"neighbourhood"
},
  "geometry": {"coordinates":[9.94126,49.27285],"type":"Point"}
}