{
  "type": "Feature",
  "properties": {
    "gn:admin1_code":"13",
    "gn:admin2_code":"0.0",
    "gn:admin3_code":"14625.0",
    "gn:admin4_code":"14625290.0",
    "gn:asciiname":"Gross Kunitz",
    "gn:country_code":"DE",
    "gn:dem":331,
    "gn:feature_class":"P",
    "gn:feature_code":"PPL",
    "gn:name":"Gro\u00df Kunitz",
    "gn:population":0,
    "gn:timezone":"Europe/Berlin",
    "iso:country":"DE",
    "name:hsb_x_preferred":[
        "Ch\u00f3jnica"
    ],
    "name:und_x_variant":[
        "Gro\u00df Kunitz"
    ],
    "wof:name":"Gross Kunitz",
    "wof:placetype":"neighbourhood"
},
  "geometry": {"coordinates":[14.48533,51.12775],"type":"Point"}
}