{
  "type": "Feature",
  "properties": {
    "gn:admin1_code":"2",
    "gn:admin2_code":"91.0",
    "gn:admin3_code":"9183.0",
    "gn:admin4_code":"9183119.0",
    "gn:asciiname":"Stauden",
    "gn:country_code":"DE",
    "gn:dem":596,
    "gn:feature_class":"P",
    "gn:feature_code":"PPL",
    "gn:name":"Stauden",
    "gn:population":0,
    "gn:timezone":"Europe/Berlin",
    "iso:country":"DE",
    "wof:name":"Stauden",
    "wof:placetype":"neighbourhood"
},
  "geometry": {"coordinates":[12.1229,48.16992],"type":"Point"}
}