{
  "type": "Feature",
  "properties": {
    "gn:admin1_code":"2",
    "gn:admin2_code":"91.0",
    "gn:admin3_code":"9175.0",
    "gn:admin4_code":"9175115.0",
    "gn:asciiname":"Reitgesing",
    "gn:country_code":"DE",
    "gn:dem":571,
    "gn:feature_class":"P",
    "gn:feature_code":"PPL",
    "gn:name":"Reitgesing",
    "gn:population":0,
    "gn:timezone":"Europe/Berlin",
    "iso:country":"DE",
    "wof:name":"Reitgesing",
    "wof:placetype":"neighbourhood"
},
  "geometry": {"coordinates":[11.9345,48.06431],"type":"Point"}
}