{
  "type": "Feature",
  "properties": {
    "gn:admin1_code":"7.0",
    "gn:admin2_code":"55.0",
    "gn:admin3_code":"5566.0",
    "gn:admin4_code":"5566076.0",
    "gn:asciiname":"Feldkante",
    "gn:country_code":"DE",
    "gn:dem":46,
    "gn:feature_class":"P",
    "gn:feature_code":"PPL",
    "gn:name":"Feldkante",
    "gn:population":0,
    "gn:timezone":"Europe/Berlin",
    "iso:country":"DE",
    "wof:name":"Feldkante",
    "wof:placetype":"neighbourhood"
},
  "geometry": {"coordinates":[7.54263,52.24006],"type":"Point"}
}