{
  "type": "Feature",
  "properties": {
    "gn:admin1_code":"2.0",
    "gn:admin2_code":"91.0",
    "gn:admin3_code":"9175.0",
    "gn:admin4_code":"9175113.0",
    "gn:asciiname":"Berganger",
    "gn:country_code":"DE",
    "gn:dem":547,
    "gn:feature_class":"P",
    "gn:feature_code":"PPL",
    "gn:name":"Berganger",
    "gn:population":0,
    "gn:timezone":"Europe/Berlin",
    "iso:country":"DE",
    "wof:name":"Berganger",
    "wof:placetype":"neighbourhood"
},
  "geometry": {"coordinates":[11.91682,47.97964],"type":"Point"}
}