{
  "type": "Feature",
  "properties": {
    "gn:country":"DE",
    "gn:fcode":"PPL",
    "gn:population":919,
    "iso:country":"DE",
    "name:bak_x_preferred":[
        "\u0414\u043e\u0440\u043d\u0431\u0443\u0440\u0433"
    ],
    "name:deu_x_preferred":[
        "Dornburg"
    ],
    "name:epo_x_preferred":[
        "Dornburg"
    ],
    "name:fas_x_preferred":[
        "\u062f\u0648\u0631\u0646\u0628\u0648\u0631\u06af"
    ],
    "name:kaz_x_preferred":[
        "\u0414\u043e\u0440\u043d\u0431\u0443\u0440\u0433"
    ],
    "name:kir_x_preferred":[
        "\u0414\u043e\u0440\u043d\u0431\u0443\u0440\u0433"
    ],
    "name:mkd_x_preferred":[
        "\u0414\u043e\u0440\u043d\u0431\u0443\u0440\u0433"
    ],
    "name:nld_x_preferred":[
        "Dornburg/Saale"
    ],
    "name:por_x_preferred":[
        "Dornburg/Saale"
    ],
    "name:rus_x_preferred":[
        "\u0414\u043e\u0440\u043d\u0431\u0443\u0440\u0433"
    ],
    "name:und_x_variant":[
        "Dornburg /Saale"
    ],
    "name:uzb_x_preferred":[
        "Dornburg/Saale"
    ],
    "name:vol_x_preferred":[
        "Dornburg/Saale"
    ],
    "qs_pg:aaroncc":"DE",
    "qs_pg:gn_country":"DE",
    "qs_pg:gn_fcode":"PPL",
    "qs_pg:gn_pop":919,
    "qs_pg:name":"Dornburg",
    "qs_pg:name_adm0":"Deutschland",
    "qs_pg:name_adm1":"Th\u00fcringen",
    "qs_pg:photos":38,
    "qs_pg:photos_1k":8,
    "qs_pg:photos_9k":1,
    "qs_pg:photos_9r":2,
    "qs_pg:photos_all":38,
    "qs_pg:photos_sr":2,
    "qs_pg:pop_sr":2,
    "qs_pg:qs_pg_placetype":"locality",
    "qs_pg:qs_pg_placetype_gp":"Town",
    "qs_pg:woe_adm0":23424829,
    "woe:adm0_id":23424829,
    "woe:name_adm0":"Deutschland",
    "woe:name_adm1":"Th\u00fcringen",
    "woe:placetype":"Town",
    "wof:name":"Dornburg",
    "wof:placetype":"neighbourhood",
    "wof:population":919
},
  "geometry": {"coordinates":[11.6633,51.00736],"type":"Point"}
}