{
  "type": "Feature",
  "properties": {
    "gn:admin1_code":"1.0",
    "gn:admin2_code":"81.0",
    "gn:admin3_code":"8119.0",
    "gn:admin4_code":"8119075.0",
    "gn:asciiname":"Bartenbach",
    "gn:country_code":"DE",
    "gn:dem":278,
    "gn:feature_class":"P",
    "gn:feature_code":"PPL",
    "gn:name":"Bartenbach",
    "gn:population":0,
    "gn:timezone":"Europe/Berlin",
    "iso:country":"DE",
    "wof:name":"Bartenbach",
    "wof:placetype":"neighbourhood"
},
  "geometry": {"coordinates":[9.53382,48.99661],"type":"Point"}
}