{
  "type": "Feature",
  "properties": {
    "gn:admin1_code":"12.0",
    "gn:admin2_code":"00",
    "gn:admin3_code":"13076.0",
    "gn:admin4_code":"13076164.0",
    "gn:asciiname":"Woeten",
    "gn:country_code":"DE",
    "gn:dem":62,
    "gn:feature_class":"P",
    "gn:feature_code":"PPL",
    "gn:name":"Woeten",
    "gn:population":0,
    "gn:timezone":"Europe/Berlin",
    "iso:country":"DE",
    "wof:name":"Woeten",
    "wof:placetype":"neighbourhood"
},
  "geometry": {"coordinates":[11.8891,53.53011],"type":"Point"}
}