{
  "type": "Feature",
  "properties": {
    "gn:admin1_code":"8",
    "gn:admin2_code":"0.0",
    "gn:admin3_code":"7138.0",
    "gn:admin4_code":"7138080.0",
    "gn:asciiname":"Oberelles",
    "gn:country_code":"DE",
    "gn:dem":251,
    "gn:feature_class":"P",
    "gn:feature_code":"PPL",
    "gn:name":"Oberelles",
    "gn:population":0,
    "gn:timezone":"Europe/Berlin",
    "iso:country":"DE",
    "wof:name":"Oberelles",
    "wof:placetype":"neighbourhood"
},
  "geometry": {"coordinates":[7.38778,50.67745],"type":"Point"}
}