{
  "type": "Feature",
  "properties": {
    "gn:admin1_code":"2",
    "gn:admin2_code":"91.0",
    "gn:admin3_code":"9187.0",
    "gn:admin4_code":"9187168.0",
    "gn:asciiname":"Gansbach",
    "gn:country_code":"DE",
    "gn:dem":596,
    "gn:feature_class":"P",
    "gn:feature_code":"PPL",
    "gn:name":"G\u00e4nsbach",
    "gn:population":0,
    "gn:timezone":"Europe/Berlin",
    "iso:country":"DE",
    "name:deu_x_preferred":[
        "Gansbach"
    ],
    "wof:name":"Gansbach",
    "wof:placetype":"neighbourhood"
},
  "geometry": {"coordinates":[12.3102,47.86995],"type":"Point"}
}