{
  "type": "Feature",
  "properties": {
    "gn:admin1_code":"2.0",
    "gn:admin2_code":"095",
    "gn:admin3_code":"9577.0",
    "gn:admin4_code":"9577127.0",
    "gn:asciiname":"Wollmetzhofen",
    "gn:country_code":"DE",
    "gn:dem":449,
    "gn:feature_class":"P",
    "gn:feature_code":"PPL",
    "gn:name":"W\u00f6llmetzhofen",
    "gn:population":0,
    "gn:timezone":"Europe/Berlin",
    "iso:country":"DE",
    "wof:name":"Wollmetzhofen",
    "wof:placetype":"neighbourhood"
},
  "geometry": {"coordinates":[11.04499,49.07215],"type":"Point"}
}