{
  "type": "Feature",
  "properties": {
    "gn:admin1_code":"14",
    "gn:admin2_code":"0.0",
    "gn:admin3_code":"15084.0",
    "gn:admin4_code":"15084315.0",
    "gn:asciiname":"Kleingoerschen",
    "gn:country_code":"DE",
    "gn:dem":145,
    "gn:feature_class":"P",
    "gn:feature_code":"PPL",
    "gn:name":"Kleing\u00f6rschen",
    "gn:population":0,
    "gn:timezone":"Europe/Berlin",
    "iso:country":"DE",
    "name:deu_x_preferred":[
        "Kleing\u00f6rschen"
    ],
    "wof:name":"Kleingoerschen",
    "wof:placetype":"neighbourhood"
},
  "geometry": {"coordinates":[12.18583,51.22324],"type":"Point"}
}