{
  "type": "Feature",
  "properties": {
    "gn:admin1_code":"2",
    "gn:admin2_code":"91.0",
    "gn:admin3_code":"9181.0",
    "gn:admin4_code":"9181132.0",
    "gn:asciiname":"Oberbergen",
    "gn:country_code":"DE",
    "gn:dem":612,
    "gn:feature_class":"P",
    "gn:feature_code":"PPL",
    "gn:name":"Oberbergen",
    "gn:population":0,
    "gn:timezone":"Europe/Berlin",
    "iso:country":"DE",
    "wof:name":"Oberbergen",
    "wof:placetype":"neighbourhood"
},
  "geometry": {"coordinates":[10.93603,48.09132],"type":"Point"}
}