{
  "type": "Feature",
  "properties": {
    "gn:admin1_code":"2",
    "gn:admin2_code":"96.0",
    "gn:admin3_code":"9677.0",
    "gn:admin4_code":"9677131.0",
    "gn:asciiname":"Kleingemunden",
    "gn:country_code":"DE",
    "gn:dem":178,
    "gn:feature_class":"P",
    "gn:feature_code":"PPL",
    "gn:name":"Kleingem\u00fcnden",
    "gn:population":0,
    "gn:timezone":"Europe/Berlin",
    "iso:country":"DE",
    "wof:name":"Kleingemunden",
    "wof:placetype":"neighbourhood"
},
  "geometry": {"coordinates":[9.70394,50.06363],"type":"Point"}
}