{
  "type": "Feature",
  "properties": {
    "gn:admin1_code":"12.0",
    "gn:admin2_code":"00",
    "gn:admin3_code":"13071.0",
    "gn:admin4_code":"13071158.0",
    "gn:asciiname":"Wodarg",
    "gn:country_code":"DE",
    "gn:dem":39,
    "gn:feature_class":"P",
    "gn:feature_code":"PPL",
    "gn:name":"Wodarg",
    "gn:population":0,
    "gn:timezone":"Europe/Berlin",
    "iso:country":"DE",
    "wof:name":"Wodarg",
    "wof:placetype":"neighbourhood"
},
  "geometry": {"coordinates":[13.35148,53.74333000000001],"type":"Point"}
}