{
  "type": "Feature",
  "properties": {
    "gn:admin1_code":"5",
    "gn:admin2_code":"65.0",
    "gn:admin3_code":"6532.0",
    "gn:admin4_code":"6532023.0",
    "gn:asciiname":"Niedergirmes",
    "gn:country_code":"DE",
    "gn:dem":153,
    "gn:feature_class":"P",
    "gn:feature_code":"PPL",
    "gn:name":"Niedergirmes",
    "gn:population":0,
    "gn:timezone":"Europe/Berlin",
    "iso:country":"DE",
    "wof:name":"Niedergirmes",
    "wof:placetype":"neighbourhood"
},
  "geometry": {"coordinates":[8.50202,50.57251],"type":"Point"}
}