{
  "type": "Feature",
  "properties": {
    "gn:admin1_code":"9.0",
    "gn:admin2_code":"0.0",
    "gn:admin3_code":"10042.0",
    "gn:admin4_code":"10042116.0",
    "gn:asciiname":"Biel",
    "gn:country_code":"DE",
    "gn:dem":283,
    "gn:feature_class":"P",
    "gn:feature_code":"PPL",
    "gn:name":"Biel",
    "gn:population":0,
    "gn:timezone":"Europe/Berlin",
    "iso:country":"DE",
    "name:ben_x_preferred":[
        "\u09ac\u09bf\u09df\u09c7\u09b2"
    ],
    "name:hin_x_preferred":[
        "\u092c\u0940\u0932"
    ],
    "name:urd_x_preferred":[
        "\u0628\u0627\u0626\u06cc\u0644"
    ],
    "name:vie_x_preferred":[
        "Biel"
    ],
    "wof:name":"Biel",
    "wof:placetype":"neighbourhood"
},
  "geometry": {"coordinates":[6.86345,49.50598],"type":"Point"}
}