{
  "type": "Feature",
  "properties": {
    "gn:admin1_code":"2",
    "gn:admin2_code":"97.0",
    "gn:admin3_code":"9771.0",
    "gn:admin4_code":"9771113.0",
    "gn:asciiname":"Obermauerbach",
    "gn:country_code":"DE",
    "gn:dem":520,
    "gn:feature_class":"P",
    "gn:feature_code":"PPL",
    "gn:name":"Obermauerbach",
    "gn:population":0,
    "gn:timezone":"Europe/Berlin",
    "iso:country":"DE",
    "wof:name":"Obermauerbach",
    "wof:placetype":"neighbourhood"
},
  "geometry": {"coordinates":[11.18558,48.4296],"type":"Point"}
}