{
  "type": "Feature",
  "properties": {
    "gn:admin1_code":"6",
    "gn:admin2_code":"0.0",
    "gn:admin3_code":"3256.0",
    "gn:admin4_code":"3256001.0",
    "gn:asciiname":"Buchhorst",
    "gn:country_code":"DE",
    "gn:dem":26,
    "gn:feature_class":"P",
    "gn:feature_code":"PPL",
    "gn:name":"Buchhorst",
    "gn:population":0,
    "gn:timezone":"Europe/Berlin",
    "iso:country":"DE",
    "name:und_x_variant":[
        "Buchorst",
        "Buchhorst"
    ],
    "wof:name":"Buchhorst",
    "wof:placetype":"neighbourhood"
},
  "geometry": {"coordinates":[9.17057,52.69657],"type":"Point"}
}