{
  "type": "Feature",
  "properties": {
    "gn:admin1_code":"6",
    "gn:admin2_code":"0.0",
    "gn:admin3_code":"3256.0",
    "gn:admin4_code":"3256001.0",
    "gn:asciiname":"Buchhorst",
    "gn:country_code":"DE",
    "gn:dem":26,
    "gn:feature_class":"P",
    "gn:feature_code":"PPL",
    "gn:name":"Buchhorst",
    "gn:population":0,
    "gn:timezone":"Europe/Berlin",
    "iso:country":"DE",
    "name:ceb_x_preferred":[
        "Buchhorst"
    ],
    "name:dan_x_preferred":[
        "Buchhorst"
    ],
    "name:deu_x_preferred":[
        "Buchhorst"
    ],
    "name:epo_x_preferred":[
        "Buchhorst"
    ],
    "name:eus_x_preferred":[
        "Buchhorst"
    ],
    "name:fas_x_preferred":[
        "\u0628\u0648\u062e\u0647\u0648\u0631\u0634\u062a"
    ],
    "name:fra_x_preferred":[
        "Buchhorst"
    ],
    "name:hun_x_preferred":[
        "Buchhorst"
    ],
    "name:ita_x_preferred":[
        "Buchhorst"
    ],
    "name:mkd_x_preferred":[
        "\u0411\u0443\u0445\u043e\u0440\u0441\u0442"
    ],
    "name:msa_x_preferred":[
        "Buchhorst"
    ],
    "name:nld_x_preferred":[
        "Buchhorst"
    ],
    "name:pol_x_preferred":[
        "Buchhorst"
    ],
    "name:por_x_preferred":[
        "Buchhorst"
    ],
    "name:ron_x_preferred":[
        "Buchhorst"
    ],
    "name:rus_x_preferred":[
        "\u0411\u0443\u0445\u0445\u043e\u0440\u0441\u0442"
    ],
    "name:spa_x_preferred":[
        "Buchhorst"
    ],
    "name:srp_x_preferred":[
        "\u0411\u0443\u0445\u043e\u0440\u0441\u0442"
    ],
    "name:szl_x_preferred":[
        "Buchhorst"
    ],
    "name:tur_x_preferred":[
        "Buchhorst"
    ],
    "name:ukr_x_preferred":[
        "\u0411\u0443\u0445\u0433\u043e\u0440\u0441\u0442"
    ],
    "name:und_x_variant":[
        "Buchorst"
    ],
    "name:uzb_x_preferred":[
        "Buchhorst"
    ],
    "name:vie_x_preferred":[
        "Buchhorst"
    ],
    "name:vol_x_preferred":[
        "Buchhorst"
    ],
    "name:war_x_preferred":[
        "Buchhorst"
    ],
    "name:zho_x_preferred":[
        "\u5e03\u8d6b\u970d\u65af\u7279"
    ],
    "wof:name":"Buchhorst",
    "wof:placetype":"neighbourhood"
},
  "geometry": {"coordinates":[9.17057,52.69657],"type":"Point"}
}