{
  "type": "Feature",
  "properties": {
    "gn:admin1_code":"2",
    "gn:admin2_code":"92.0",
    "gn:admin3_code":"9278.0",
    "gn:admin4_code":"9278184.0",
    "gn:asciiname":"Mitterberg",
    "gn:country_code":"DE",
    "gn:dem":621,
    "gn:feature_class":"P",
    "gn:feature_code":"PPLL",
    "gn:name":"Mitterberg",
    "gn:population":0,
    "gn:timezone":"Europe/Berlin",
    "iso:country":"DE",
    "name:cat_x_preferred":[
        "Mitterberg"
    ],
    "name:ceb_x_preferred":[
        "Mitterberg"
    ],
    "name:deu_x_preferred":[
        "Mitterberg"
    ],
    "name:fas_x_preferred":[
        "\u0645\u06cc\u062a\u0631\u0628\u0631\u06af"
    ],
    "name:fra_x_preferred":[
        "Mitterberg"
    ],
    "name:ita_x_preferred":[
        "Mitterberg"
    ],
    "name:nld_x_preferred":[
        "Mitterberg"
    ],
    "name:slk_x_preferred":[
        "Mitterberg"
    ],
    "name:swe_x_preferred":[
        "Mitterberg"
    ],
    "name:war_x_preferred":[
        "Mitterberg"
    ],
    "name:zho_x_preferred":[
        "\u7c73\u7279\u8d1d\u683c"
    ],
    "wof:name":"Mitterberg",
    "wof:placetype":"neighbourhood"
},
  "geometry": {"coordinates":[12.80153,48.99222],"type":"Point"}
}