{
  "type": "Feature",
  "properties": {
    "iso:country":"DE",
    "name:deu_x_preferred":[
        "K\u00f6ln-Porz"
    ],
    "name:fas_x_preferred":[
        "\u067e\u0648\u0631\u062a\u0633"
    ],
    "name:lat_x_preferred":[
        "K\u00f6ln-Porz"
    ],
    "name:pol_x_preferred":[
        "Porz"
    ],
    "name:ron_x_preferred":[
        "K\u00f6ln-Porz"
    ],
    "wof:name":"Porz",
    "wof:placetype":"neighbourhood"
},
  "geometry": {"coordinates":[7.06569355199864,50.88387472932173],"type":"Point"}
}