{
  "type": "Feature",
  "properties": {
    "gn:admin1_code":"1.0",
    "gn:admin2_code":"083",
    "gn:admin3_code":"8335.0",
    "gn:admin4_code":"8335022.0",
    "gn:asciiname":"Zimmerholz",
    "gn:country_code":"DE",
    "gn:dem":584,
    "gn:feature_class":"P",
    "gn:feature_code":"PPL",
    "gn:name":"Zimmerholz",
    "gn:population":0,
    "gn:timezone":"Europe/Berlin",
    "iso:country":"DE",
    "wof:name":"Zimmerholz",
    "wof:placetype":"neighbourhood"
},
  "geometry": {"coordinates":[8.74055,47.86801],"type":"Point"}
}