{
  "type": "Feature",
  "properties": {
    "gn:admin1_code":"6",
    "gn:admin2_code":"0.0",
    "gn:admin3_code":"3361.0",
    "gn:admin4_code":"3361002.0",
    "gn:asciiname":"Neddernhude",
    "gn:country_code":"DE",
    "gn:dem":13,
    "gn:feature_class":"P",
    "gn:feature_code":"PPL",
    "gn:name":"Neddernhude",
    "gn:population":0,
    "gn:timezone":"Europe/Berlin",
    "iso:country":"DE",
    "wof:name":"Neddernhude",
    "wof:placetype":"neighbourhood"
},
  "geometry": {"coordinates":[9.18392,52.92081999999999],"type":"Point"}
}