{
  "type": "Feature",
  "properties": {
    "gn:admin1_code":"10",
    "gn:admin2_code":"0.0",
    "gn:admin3_code":"1061.0",
    "gn:admin4_code":"1061097.0",
    "gn:asciiname":"Kammerhorst",
    "gn:country_code":"DE",
    "gn:dem":28,
    "gn:feature_class":"P",
    "gn:feature_code":"PPL",
    "gn:name":"Kammerhorst",
    "gn:population":0,
    "gn:timezone":"Europe/Berlin",
    "iso:country":"DE",
    "wof:name":"Kammerhorst",
    "wof:placetype":"neighbourhood"
},
  "geometry": {"coordinates":[9.48333,54.06667],"type":"Point"}
}