{
  "type": "Feature",
  "properties": {
    "gn:admin1_code":"13",
    "gn:admin2_code":"0.0",
    "gn:admin3_code":"14627.0",
    "gn:admin4_code":"14627200.0",
    "gn:asciiname":"Nauleis",
    "gn:country_code":"DE",
    "gn:dem":147,
    "gn:feature_class":"P",
    "gn:feature_code":"PPL",
    "gn:name":"Nauleis",
    "gn:population":0,
    "gn:timezone":"Europe/Berlin",
    "iso:country":"DE",
    "wof:name":"Nauleis",
    "wof:placetype":"neighbourhood"
},
  "geometry": {"coordinates":[13.58222,51.24901],"type":"Point"}
}