{
  "type": "Feature",
  "properties": {
    "gn:admin1_code":"2.0",
    "gn:admin2_code":"093",
    "gn:admin3_code":"9373.0",
    "gn:admin4_code":"9373112.0",
    "gn:asciiname":"Wolfersthal",
    "gn:country_code":"DE",
    "gn:dem":477,
    "gn:feature_class":"P",
    "gn:feature_code":"PPL",
    "gn:name":"Wolfersthal",
    "gn:population":0,
    "gn:timezone":"Europe/Berlin",
    "iso:country":"DE",
    "wof:name":"Wolfersthal",
    "wof:placetype":"neighbourhood"
},
  "geometry": {"coordinates":[11.49445,49.14416],"type":"Point"}
}