{
  "type": "Feature",
  "properties": {
    "gn:admin1_code":"1",
    "gn:admin2_code":"84.0",
    "gn:admin3_code":"8416.0",
    "gn:admin4_code":"8416041.0",
    "gn:asciiname":"Buhl",
    "gn:country_code":"DE",
    "gn:dem":338,
    "gn:feature_class":"P",
    "gn:feature_code":"PPL",
    "gn:name":"B\u00fchl",
    "gn:population":0,
    "gn:timezone":"Europe/Berlin",
    "iso:country":"DE",
    "name:ces_x_preferred":[
        "B\u00fchl"
    ],
    "name:deu_x_preferred":[
        "B\u00fchl"
    ],
    "name:nld_x_preferred":[
        "B\u00fchl"
    ],
    "wof:name":"Buhl",
    "wof:placetype":"neighbourhood"
},
  "geometry": {"coordinates":[8.99888,48.48333],"type":"Point"}
}