{
  "type": "Feature",
  "properties": {
    "gn:admin1_code":"2.0",
    "gn:admin2_code":"91.0",
    "gn:admin3_code":"9183.0",
    "gn:admin4_code":"9183136.0",
    "gn:asciiname":"Annabrunn",
    "gn:country_code":"DE",
    "gn:dem":384,
    "gn:feature_class":"P",
    "gn:feature_code":"PPL",
    "gn:name":"Annabrunn",
    "gn:population":0,
    "gn:timezone":"Europe/Berlin",
    "iso:country":"DE",
    "wof:name":"Annabrunn",
    "wof:placetype":"neighbourhood"
},
  "geometry": {"coordinates":[12.50924,48.23003],"type":"Point"}
}