{
  "type": "Feature",
  "properties": {
    "gn:admin1_code":"10",
    "gn:admin2_code":"0.0",
    "gn:admin3_code":"1054.0",
    "gn:admin4_code":"1054002.0",
    "gn:asciiname":"Klein Ahrenshoeft",
    "gn:country_code":"DE",
    "gn:dem":5,
    "gn:feature_class":"P",
    "gn:feature_code":"PPL",
    "gn:name":"Klein Ahrensh\u00f6ft",
    "gn:population":0,
    "gn:timezone":"Europe/Berlin",
    "iso:country":"DE",
    "wof:name":"Klein Ahrenshoeft",
    "wof:placetype":"neighbourhood"
},
  "geometry": {"coordinates":[9.06667,54.56667],"type":"Point"}
}