{
  "type": "Feature",
  "properties": {
    "gn:admin1_code":"1.0",
    "gn:admin2_code":"81.0",
    "gn:admin3_code":"8136.0",
    "gn:admin4_code":"8136061.0",
    "gn:asciiname":"Birkenlohe",
    "gn:country_code":"DE",
    "gn:dem":451,
    "gn:feature_class":"P",
    "gn:feature_code":"PPL",
    "gn:name":"Birkenlohe",
    "gn:population":0,
    "gn:timezone":"Europe/Berlin",
    "iso:country":"DE",
    "wof:name":"Birkenlohe",
    "wof:placetype":"neighbourhood"
},
  "geometry": {"coordinates":[9.78182,48.90651],"type":"Point"}
}