{
  "type": "Feature",
  "properties": {
    "gn:admin1_code":"5",
    "gn:admin2_code":"65.0",
    "gn:admin3_code":"6532.0",
    "gn:admin4_code":"6532005.0",
    "gn:asciiname":"Ewersbach",
    "gn:country_code":"DE",
    "gn:dem":350,
    "gn:feature_class":"P",
    "gn:feature_code":"PPL",
    "gn:name":"Ewersbach",
    "gn:population":0,
    "gn:timezone":"Europe/Berlin",
    "iso:country":"DE",
    "name:und_x_variant":[
        "Bergebersbach",
        "Ewersbach"
    ],
    "wof:name":"Ewersbach",
    "wof:placetype":"neighbourhood"
},
  "geometry": {"coordinates":[8.31156,50.83395],"type":"Point"}
}