{
  "type": "Feature",
  "properties": {
    "gn:admin1_code":"15",
    "gn:admin2_code":"0.0",
    "gn:admin3_code":"16061.0",
    "gn:admin4_code":"16061035.0",
    "gn:asciiname":"Doeringsdorf",
    "gn:country_code":"DE",
    "gn:dem":326,
    "gn:feature_class":"P",
    "gn:feature_code":"PPL",
    "gn:name":"D\u00f6ringsdorf",
    "gn:population":0,
    "gn:timezone":"Europe/Berlin",
    "iso:country":"DE",
    "name:und_x_variant":[
        "D\u00f6ringsdorf"
    ],
    "wof:name":"Doeringsdorf",
    "wof:placetype":"neighbourhood"
},
  "geometry": {"coordinates":[10.16394,51.21578],"type":"Point"}
}