{
  "type": "Feature",
  "properties": {
    "gn:admin1_code":"2.0",
    "gn:admin2_code":"94.0",
    "gn:admin3_code":"9477.0",
    "gn:admin4_code":"9477124.0",
    "gn:asciiname":"Krumme Fohre",
    "gn:country_code":"DE",
    "gn:dem":362,
    "gn:feature_class":"P",
    "gn:feature_code":"PPL",
    "gn:name":"Krumme Fohre",
    "gn:population":0,
    "gn:timezone":"Europe/Berlin",
    "iso:country":"DE",
    "wof:name":"Krumme Fohre",
    "wof:placetype":"neighbourhood"
},
  "geometry": {"coordinates":[11.38194,50.0544],"type":"Point"}
}