{
  "type": "Feature",
  "properties": {
    "gn:admin1_code":"2",
    "gn:admin2_code":"92.0",
    "gn:admin3_code":"9279.0",
    "gn:admin4_code":"9279122.0",
    "gn:asciiname":"Niederhocking",
    "gn:country_code":"DE",
    "gn:dem":386,
    "gn:feature_class":"P",
    "gn:feature_code":"PPL",
    "gn:name":"Niederh\u00f6cking",
    "gn:population":0,
    "gn:timezone":"Europe/Berlin",
    "iso:country":"DE",
    "wof:name":"Niederhocking",
    "wof:placetype":"neighbourhood"
},
  "geometry": {"coordinates":[12.67565,48.65469],"type":"Point"}
}