{
  "type": "Feature",
  "properties": {
    "iso:country":"DE",
    "name:deu_x_preferred":[
        "Mundenheim"
    ],
    "qs:gn_adm0_cc":"DE",
    "qs:gn_fcode":"PPLX",
    "qs:gn_local":2875376,
    "qs:gn_nam_loc":"Ludwigshafen am Rhein, Rheinland-Pfalz, DE",
    "qs:gn_namadm1":"08",
    "qs:gn_name":"Mundenheim",
    "qs:local_max":1675,
    "qs:local_sum":3883,
    "qs:localhoods":9,
    "qs:name":"Mundenheim",
    "qs:name_adm0":"Deutschland",
    "qs:name_adm1":"Rheinland-Pfalz",
    "qs:name_adm2":"Stadtkreis Ludwigshafen am Rhein",
    "qs:name_lau":"Stadtteil Ludwigshafen am Rhein",
    "qs:name_local":"Stadtteil Ludwigshafen am Rhein",
    "qs:photo_max":236,
    "qs:photo_sum":1675,
    "qs:placetype":"Suburb",
    "qs:quad_count":98,
    "qs:woe_adm0":23424829,
    "qs:woe_adm1":2345488,
    "qs:woe_adm2":12597103,
    "qs:woe_lau":28350228,
    "qs:woe_local":28350228,
    "qs:woe_ver":"7.10.0",
    "wof:lang":[
        "ger"
    ],
    "wof:name":"Mundenheim",
    "wof:placetype":"neighbourhood"
},
  "geometry": {"coordinates":[8.450714,49.479862],"type":"Point"}
}