{
  "type": "Feature",
  "properties": {
    "gn:admin1_code":"2",
    "gn:admin2_code":"91.0",
    "gn:admin3_code":"9176.0",
    "gn:admin4_code":"9176166.0",
    "gn:asciiname":"Hard",
    "gn:country_code":"DE",
    "gn:dem":518,
    "gn:feature_class":"P",
    "gn:feature_code":"PPL",
    "gn:name":"Hard",
    "gn:population":0,
    "gn:timezone":"Europe/Berlin",
    "iso:country":"DE",
    "name:ceb_x_preferred":[
        "Hard"
    ],
    "name:deu_x_preferred":[
        "Hard"
    ],
    "name:fra_x_preferred":[
        "Hard"
    ],
    "name:ita_x_preferred":[
        "Hard"
    ],
    "name:nld_x_preferred":[
        "Hard"
    ],
    "name:nno_x_preferred":[
        "Hardleik"
    ],
    "name:nor_x_preferred":[
        "Hardhet"
    ],
    "name:pol_x_preferred":[
        "Hard"
    ],
    "name:por_x_preferred":[
        "Hard"
    ],
    "name:ron_x_preferred":[
        "Hard"
    ],
    "name:swe_x_preferred":[
        "Hard"
    ],
    "name:ukr_x_preferred":[
        "Hard"
    ],
    "wof:name":"Hard",
    "wof:placetype":"neighbourhood"
},
  "geometry": {"coordinates":[11.12644,48.81976],"type":"Point"}
}