{
  "type": "Feature",
  "properties": {
    "gn:admin1_code":"2.0",
    "gn:admin2_code":"95.0",
    "gn:admin3_code":"9571.0",
    "gn:admin4_code":"9571190.0",
    "gn:asciiname":"Adelmannssitz",
    "gn:country_code":"DE",
    "gn:dem":371,
    "gn:feature_class":"P",
    "gn:feature_code":"PPL",
    "gn:name":"Adelmannssitz",
    "gn:population":0,
    "gn:timezone":"Europe/Berlin",
    "iso:country":"DE",
    "name:und_x_variant":[
        "Adelmannsitz",
        "Adelmannssitz"
    ],
    "wof:name":"Adelmannssitz",
    "wof:placetype":"neighbourhood"
},
  "geometry": {"coordinates":[10.69641,49.33208],"type":"Point"}
}