{
  "type": "Feature",
  "properties": {
    "gn:gn_country":"DE",
    "gn:gn_fcode":"PPLA4",
    "gn:gn_pop":903,
    "gn:population":903,
    "iso:country":"DE",
    "name:baq_x_preferred":[
        "Wonsheim"
    ],
    "name:chi_x_preferred":[
        "\u7fc1\u65af\u6d77\u59c6"
    ],
    "name:dut_x_preferred":[
        "Wonsheim"
    ],
    "name:eng_x_preferred":[
        "Wonsheim"
    ],
    "name:epo_x_preferred":[
        "Wonsheim"
    ],
    "name:fre_x_preferred":[
        "Wonsheim"
    ],
    "name:ger_x_preferred":[
        "Wonsheim"
    ],
    "name:hun_x_preferred":[
        "Wonsheim"
    ],
    "name:ita_x_preferred":[
        "Wonsheim"
    ],
    "name:jpn_x_preferred":[
        "\u30f4\u30a9\u30f3\u30b9\u30cf\u30a4\u30e0"
    ],
    "name:kaz_x_preferred":[
        "\u0412\u043e\u043d\u0441\u0445\u0430\u0439\u043c"
    ],
    "name:kir_x_preferred":[
        "\u0412\u043e\u043d\u0441\u0445\u0430\u0439\u043c"
    ],
    "name:may_x_preferred":[
        "Wonsheim"
    ],
    "name:per_x_preferred":[
        "\u0648\u0648\u0646\u0633\u0647\u0627\u06cc\u0645"
    ],
    "name:pol_x_preferred":[
        "Wonsheim"
    ],
    "name:por_x_preferred":[
        "Wonsheim"
    ],
    "name:rum_x_preferred":[
        "Wonsheim"
    ],
    "name:rus_x_preferred":[
        "\u0412\u043e\u043d\u0441\u0445\u0430\u0439\u043c"
    ],
    "name:srp_x_preferred":[
        "\u0412\u043e\u043d\u0441\u0445\u0430\u0458\u043c"
    ],
    "name:ukr_x_preferred":[
        "\u0412\u043e\u043d\u0441\u0433\u0430\u0439\u043c"
    ],
    "name:uzb_x_preferred":[
        "Wonsheim"
    ],
    "name:vie_x_preferred":[
        "Wonsheim"
    ],
    "name:vol_x_preferred":[
        "Wonsheim"
    ],
    "name:war_x_preferred":[
        "Wonsheim"
    ],
    "qs_pg:aaroncc":"DE",
    "qs_pg:gn_country":"DE",
    "qs_pg:gn_fcode":"PPLA4",
    "qs_pg:gn_pop":903,
    "qs_pg:name":"Wonsheim",
    "qs_pg:photos_9r":0,
    "qs_pg:photos_sr":0,
    "qs_pg:pop_sr":2,
    "qs_pg:qs_pg_placetype":"locality",
    "wof:name":"Wonsheim",
    "wof:placetype":"locality",
    "wof:population":903
},
  "geometry": {"coordinates":[7.96667,49.78333],"type":"Point"}
}