{
  "type": "Feature",
  "properties": {
    "gn:admin1_code":"2.0",
    "gn:admin2_code":"095",
    "gn:admin3_code":"9571.0",
    "gn:admin4_code":"9571200.0",
    "gn:asciiname":"Zwernberg",
    "gn:country_code":"DE",
    "gn:dem":452,
    "gn:feature_class":"P",
    "gn:feature_code":"PPL",
    "gn:name":"Zwernberg",
    "gn:population":0,
    "gn:timezone":"Europe/Berlin",
    "iso:country":"DE",
    "wof:name":"Zwernberg",
    "wof:placetype":"neighbourhood"
},
  "geometry": {"coordinates":[10.27742,49.11279],"type":"Point"}
}