{
  "type": "Feature",
  "properties": {
    "gn:admin1_code":"2",
    "gn:admin2_code":"94.0",
    "gn:admin3_code":"9474.0",
    "gn:admin4_code":"9474154.0",
    "gn:asciiname":"Rosenbach",
    "gn:country_code":"DE",
    "gn:dem":309,
    "gn:feature_class":"P",
    "gn:feature_code":"PPL",
    "gn:name":"Rosenbach",
    "gn:population":0,
    "gn:timezone":"Europe/Berlin",
    "iso:country":"DE",
    "name:bak_x_preferred":[
        "\u0420\u043e\u0437\u0435\u043d\u0431\u0430\u0445"
    ],
    "name:ceb_x_preferred":[
        "Rosenbach"
    ],
    "name:deu_x_preferred":[
        "Rosenbach"
    ],
    "name:epo_x_preferred":[
        "Rosenbach"
    ],
    "name:est_x_preferred":[
        "Rosenbach"
    ],
    "name:fra_x_preferred":[
        "Rosenbach"
    ],
    "name:ita_x_preferred":[
        "Rosenbach"
    ],
    "name:mkd_x_preferred":[
        "\u0420\u043e\u0437\u0435\u043d\u0431\u0430\u0445"
    ],
    "name:nor_x_preferred":[
        "Rosenbach"
    ],
    "name:pol_x_preferred":[
        "Rosenbach"
    ],
    "name:rus_x_preferred":[
        "\u0420\u043e\u0437\u0435\u043d\u0431\u0430\u0445"
    ],
    "name:swe_x_preferred":[
        "Rosenbach"
    ],
    "wof:name":"Rosenbach",
    "wof:placetype":"neighbourhood"
},
  "geometry": {"coordinates":[11.0943,49.60682],"type":"Point"}
}