{
  "type": "Feature",
  "properties": {
    "gn:admin1_code":"10",
    "gn:admin2_code":"0.0",
    "gn:admin3_code":"1059.0",
    "gn:admin4_code":"1059079.0",
    "gn:asciiname":"Esperstoftfeld",
    "gn:country_code":"DE",
    "gn:dem":10,
    "gn:feature_class":"P",
    "gn:feature_code":"PPLL",
    "gn:name":"Esperstoftfeld",
    "gn:population":0,
    "gn:timezone":"Europe/Berlin",
    "iso:country":"DE",
    "wof:name":"Esperstoftfeld",
    "wof:placetype":"neighbourhood"
},
  "geometry": {"coordinates":[9.38466,54.56546],"type":"Point"}
}