{
  "type": "Feature",
  "properties": {
    "gn:admin1_code":"5.0",
    "gn:admin2_code":"64.0",
    "gn:admin3_code":"6433.0",
    "gn:admin4_code":"6433014.0",
    "gn:asciiname":"Astheim",
    "gn:country_code":"DE",
    "gn:dem":88,
    "gn:feature_class":"P",
    "gn:feature_code":"PPL",
    "gn:name":"Astheim",
    "gn:population":0,
    "gn:timezone":"Europe/Berlin",
    "iso:country":"DE",
    "wof:name":"Astheim",
    "wof:placetype":"neighbourhood"
},
  "geometry": {"coordinates":[8.38167,49.93556],"type":"Point"}
}