{
  "type": "Feature",
  "properties": {
    "gn:gn_country":"DE",
    "gn:gn_fcode":"PPLA4",
    "gn:gn_pop":247,
    "gn:population":247,
    "iso:country":"DE",
    "name:baq_x_preferred":[
        "Heckenbach"
    ],
    "name:chi_x_preferred":[
        "\u9ed1\u80af\u5df4\u8d6b"
    ],
    "name:dut_x_preferred":[
        "Heckenbach"
    ],
    "name:eng_x_preferred":[
        "Heckenbach"
    ],
    "name:epo_x_preferred":[
        "Heckenbach"
    ],
    "name:fre_x_preferred":[
        "Heckenbach"
    ],
    "name:ger_x_preferred":[
        "Heckenbach"
    ],
    "name:hun_x_preferred":[
        "Heckenbach"
    ],
    "name:ita_x_preferred":[
        "Heckenbach"
    ],
    "name:jpn_x_preferred":[
        "\u30d8\u30c3\u30b1\u30f3\u30d0\u30c3\u30cf"
    ],
    "name:kaz_x_preferred":[
        "\u0425\u0435\u043a\u043a\u0435\u043d\u0431\u0430\u0445"
    ],
    "name:kir_x_preferred":[
        "\u0425\u0435\u043a\u043a\u0435\u043d\u0431\u0430\u0445"
    ],
    "name:may_x_preferred":[
        "Heckenbach"
    ],
    "name:per_x_preferred":[
        "\u0647\u06a9\u0646\u0628\u0627\u062e"
    ],
    "name:pol_x_preferred":[
        "Heckenbach"
    ],
    "name:por_x_preferred":[
        "Heckenbach"
    ],
    "name:rum_x_preferred":[
        "Heckenbach"
    ],
    "name:rus_x_preferred":[
        "\u0425\u0435\u043a\u043a\u0435\u043d\u0431\u0430\u0445"
    ],
    "name:srp_x_preferred":[
        "\u0425\u0435\u043a\u0435\u043d\u0431\u0430\u0445"
    ],
    "name:ukr_x_preferred":[
        "\u0413\u0435\u043a\u043a\u0435\u043d\u0431\u0430\u0445"
    ],
    "name:uzb_x_preferred":[
        "Heckenbach"
    ],
    "name:vie_x_preferred":[
        "Heckenbach"
    ],
    "name:vol_x_preferred":[
        "Heckenbach"
    ],
    "name:war_x_preferred":[
        "Heckenbach"
    ],
    "qs_pg:aaroncc":"DE",
    "qs_pg:gn_country":"DE",
    "qs_pg:gn_fcode":"PPLA4",
    "qs_pg:gn_pop":247,
    "qs_pg:name":"Heckenbach",
    "qs_pg:photos_9r":0,
    "qs_pg:photos_sr":0,
    "qs_pg:pop_sr":2,
    "qs_pg:qs_pg_placetype":"locality",
    "wof:name":"Heckenbach",
    "wof:placetype":"locality",
    "wof:population":247
},
  "geometry": {"coordinates":[7.05,50.46667],"type":"Point"}
}