{
  "type": "Feature",
  "properties": {
    "gn:admin1_code":"6",
    "gn:admin2_code":"0.0",
    "gn:admin3_code":"3354.0",
    "gn:admin4_code":"3354002.0",
    "gn:asciiname":"Sachau",
    "gn:country_code":"DE",
    "gn:dem":29,
    "gn:feature_class":"P",
    "gn:feature_code":"PPL",
    "gn:name":"Sachau",
    "gn:population":0,
    "gn:timezone":"Europe/Berlin",
    "iso:country":"DE",
    "name:ceb_x_preferred":[
        "Sachau"
    ],
    "name:deu_x_preferred":[
        "Sachau"
    ],
    "name:epo_x_preferred":[
        "Sachau"
    ],
    "name:fas_x_preferred":[
        "\u0632\u0627\u062e\u0627\u0626\u0648"
    ],
    "name:ita_x_preferred":[
        "Sachau"
    ],
    "name:kaz_x_preferred":[
        "\u0417\u0430\u0445\u0430\u0443"
    ],
    "name:nld_x_preferred":[
        "Sachau"
    ],
    "name:pol_x_preferred":[
        "Sachau"
    ],
    "name:ron_x_preferred":[
        "Sachau"
    ],
    "name:rus_x_preferred":[
        "\u0417\u0430\u0445\u0430\u0443"
    ],
    "name:srp_x_preferred":[
        "\u0417\u0430\u0445\u0430\u0443"
    ],
    "name:urd_x_preferred":[
        "\u0633\u0686\u0648"
    ],
    "name:uzb_x_preferred":[
        "Sachau"
    ],
    "name:vie_x_preferred":[
        "Sachau"
    ],
    "name:vol_x_preferred":[
        "Sachau"
    ],
    "name:war_x_preferred":[
        "Sachau"
    ],
    "wof:name":"Sachau",
    "wof:placetype":"neighbourhood"
},
  "geometry": {"coordinates":[10.9956,52.949],"type":"Point"}
}