{
  "type": "Feature",
  "properties": {
    "gn:admin1_code":"15",
    "gn:admin2_code":"0.0",
    "gn:admin3_code":"16073.0",
    "gn:admin4_code":"16073106.0",
    "gn:asciiname":"Steinsdorf",
    "gn:country_code":"DE",
    "gn:dem":527,
    "gn:feature_class":"P",
    "gn:feature_code":"PPL",
    "gn:name":"Steinsdorf",
    "gn:population":0,
    "gn:timezone":"Europe/Berlin",
    "iso:country":"DE",
    "name:bak_x_preferred":[
        "\u0428\u0442\u0430\u0439\u043d\u0441\u0434\u043e\u0440\u0444"
    ],
    "name:ceb_x_preferred":[
        "Steinsdorf"
    ],
    "name:deu_x_preferred":[
        "Steinsdorf"
    ],
    "name:epo_x_preferred":[
        "Steinsdorf"
    ],
    "name:fas_x_preferred":[
        "\u0634\u062a\u0627\u06cc\u0646\u0633\u062f\u0648\u0631\u0641"
    ],
    "name:fra_x_preferred":[
        "Steinsdorf"
    ],
    "name:ita_x_preferred":[
        "Steinsdorf"
    ],
    "name:kaz_x_preferred":[
        "\u0428\u0442\u0430\u0439\u043d\u0441\u0434\u043e\u0440\u0444"
    ],
    "name:kir_x_preferred":[
        "\u0428\u0442\u0430\u0439\u043d\u0441\u0434\u043e\u0440\u0444"
    ],
    "name:mkd_x_preferred":[
        "\u0428\u0442\u0430\u0458\u043d\u0441\u0434\u043e\u0440\u0444"
    ],
    "name:msa_x_preferred":[
        "Steinsdorf"
    ],
    "name:nld_x_preferred":[
        "Steinsdorf"
    ],
    "name:pol_x_preferred":[
        "Steinsdorf"
    ],
    "name:por_x_preferred":[
        "Steinsdorf"
    ],
    "name:ron_x_preferred":[
        "Steinsdorf"
    ],
    "name:rus_x_preferred":[
        "\u0428\u0442\u0430\u0439\u043d\u0441\u0434\u043e\u0440\u0444"
    ],
    "name:srp_x_preferred":[
        "\u0428\u0442\u0430\u0458\u043d\u0441\u0434\u043e\u0440\u0444"
    ],
    "name:uzb_x_preferred":[
        "Steinsdorf"
    ],
    "name:vie_x_preferred":[
        "Steinsdorf"
    ],
    "name:vol_x_preferred":[
        "Steinsdorf"
    ],
    "name:war_x_preferred":[
        "Steinsdorf"
    ],
    "name:zho_x_preferred":[
        "\u65bd\u6cf0\u56e0\u65af\u591a\u592b"
    ],
    "wof:name":"Steinsdorf",
    "wof:placetype":"neighbourhood"
},
  "geometry": {"coordinates":[11.49436,50.58476],"type":"Point"}
}