{
  "type": "Feature",
  "properties": {
    "gn:admin1_code":"2",
    "gn:admin2_code":"97.0",
    "gn:admin3_code":"9778.0",
    "gn:admin4_code":"9778144.0",
    "gn:asciiname":"Ittelsburg",
    "gn:country_code":"DE",
    "gn:dem":722,
    "gn:feature_class":"P",
    "gn:feature_code":"PPL",
    "gn:name":"Ittelsburg",
    "gn:population":0,
    "gn:timezone":"Europe/Berlin",
    "iso:country":"DE",
    "name:und_x_variant":[
        "Jttelsburg",
        "Ittelsburg"
    ],
    "wof:name":"Ittelsburg",
    "wof:placetype":"neighbourhood"
},
  "geometry": {"coordinates":[10.27223,47.87207],"type":"Point"}
}