{
  "type": "Feature",
  "properties": {
    "gn:admin1_code":"6",
    "gn:admin2_code":"0.0",
    "gn:admin3_code":"3254.0",
    "gn:admin4_code":"3254043.0",
    "gn:asciiname":"Nienstedt",
    "gn:country_code":"DE",
    "gn:dem":131,
    "gn:feature_class":"P",
    "gn:feature_code":"PPL",
    "gn:name":"Nienstedt",
    "gn:population":0,
    "gn:timezone":"Europe/Berlin",
    "iso:country":"DE",
    "name:bak_x_preferred":[
        "\u041d\u0438\u0435\u043d\u0448\u0442\u0435\u0434\u0442"
    ],
    "name:ceb_x_preferred":[
        "Nienstedt"
    ],
    "name:deu_x_preferred":[
        "Nienstedt"
    ],
    "name:epo_x_preferred":[
        "Nienstedt"
    ],
    "name:fas_x_preferred":[
        "\u0646\u0627\u06cc\u0646\u0634\u062a"
    ],
    "name:ita_x_preferred":[
        "Nienstedt"
    ],
    "name:kaz_x_preferred":[
        "\u041d\u0438\u0435\u043d\u0448\u0442\u0435\u0434\u0442"
    ],
    "name:kir_x_preferred":[
        "\u041d\u0438\u0435\u043d\u0448\u0442\u0435\u0434\u0442"
    ],
    "name:mkd_x_preferred":[
        "\u041d\u0438\u043d\u0448\u0442\u0435\u0442"
    ],
    "name:nld_x_preferred":[
        "Nienstedt"
    ],
    "name:ron_x_preferred":[
        "Nienstedt"
    ],
    "name:rus_x_preferred":[
        "\u041d\u0438\u0435\u043d\u0448\u0442\u0435\u0434\u0442"
    ],
    "name:uzb_x_preferred":[
        "Nienstedt"
    ],
    "name:vie_x_preferred":[
        "Nienstedt"
    ],
    "name:vol_x_preferred":[
        "Nienstedt"
    ],
    "wof:name":"Nienstedt",
    "wof:placetype":"neighbourhood"
},
  "geometry": {"coordinates":[9.86565,52.0751],"type":"Point"}
}