{
  "type": "Feature",
  "properties": {
    "gn:admin1_code":"12.0",
    "gn:admin2_code":"0.0",
    "gn:admin3_code":"13071.0",
    "gn:admin4_code":"13071110.0",
    "gn:asciiname":"Kalkhorst",
    "gn:country_code":"DE",
    "gn:dem":66,
    "gn:feature_class":"P",
    "gn:feature_code":"PPL",
    "gn:name":"Kalkhorst",
    "gn:population":0,
    "gn:timezone":"Europe/Berlin",
    "iso:country":"DE",
    "name:deu_x_preferred":[
        "Kalkhorst"
    ],
    "name:epo_x_preferred":[
        "Kalkhorst"
    ],
    "name:fas_x_preferred":[
        "\u06a9\u0627\u0644\u06a9\u0647\u0648\u0631\u0634\u062a"
    ],
    "name:fra_x_preferred":[
        "Kalkhorst"
    ],
    "name:hun_x_preferred":[
        "Kalkhorst"
    ],
    "name:ita_x_preferred":[
        "Kalkhorst"
    ],
    "name:kaz_x_preferred":[
        "\u041a\u0430\u043b\u044c\u043a\u0445\u043e\u0440\u0441\u0442"
    ],
    "name:kir_x_preferred":[
        "\u041a\u0430\u043b\u044c\u043a\u0445\u043e\u0440\u0441\u0442"
    ],
    "name:mkd_x_preferred":[
        "\u041a\u0430\u043b\u043a\u0445\u043e\u0440\u0441\u0442"
    ],
    "name:msa_x_preferred":[
        "Kalkhorst"
    ],
    "name:nld_x_preferred":[
        "Kalkhorst"
    ],
    "name:pol_x_preferred":[
        "Kalkhorst"
    ],
    "name:por_x_preferred":[
        "Kalkhorst"
    ],
    "name:ron_x_preferred":[
        "Kalkhorst"
    ],
    "name:rus_x_preferred":[
        "\u041a\u0430\u043b\u044c\u043a\u0445\u043e\u0440\u0441\u0442"
    ],
    "name:spa_x_preferred":[
        "Kalkhorst"
    ],
    "name:srp_x_preferred":[
        "\u041a\u0430\u043b\u043a\u0445\u043e\u0440\u0441\u0442"
    ],
    "name:swe_x_preferred":[
        "Kalkhorst"
    ],
    "name:ukr_x_preferred":[
        "\u041a\u0430\u043b\u044c\u043a\u0433\u043e\u0440\u0441\u0442"
    ],
    "name:uzb_x_preferred":[
        "Kalkhorst"
    ],
    "name:vie_x_preferred":[
        "Kalkhorst"
    ],
    "name:vol_x_preferred":[
        "Kalkhorst"
    ],
    "name:war_x_preferred":[
        "Kalkhorst"
    ],
    "name:zho_x_preferred":[
        "\u5361\u5c14\u514b\u970d\u65af\u7279"
    ],
    "wof:name":"Kalkhorst",
    "wof:placetype":"neighbourhood"
},
  "geometry": {"coordinates":[13.06772,53.33574],"type":"Point"}
}