{
  "type": "Feature",
  "properties": {
    "iso:country":"DE",
    "name:deu_x_preferred":[
        "Katernberg"
    ],
    "qs:gn_adm0_cc":"DE",
    "qs:gn_fcode":"PPLX",
    "qs:gn_local":2805753,
    "qs:gn_nam_loc":"wuppertal",
    "qs:gn_namadm1":"07",
    "qs:gn_name":"Katernberg",
    "qs:local_max":2358,
    "qs:local_sum":9442,
    "qs:localhoods":28,
    "qs:name":"Katernberg",
    "qs:name_adm0":"Deutschland",
    "qs:name_adm1":"Nordrhein-Westfalen",
    "qs:name_adm2":"Stadtkreis Wuppertal",
    "qs:name_lau":"Stadtteil Beek",
    "qs:name_local":"Wuppertal",
    "qs:photo_max":76,
    "qs:photo_sum":153,
    "qs:placetype":"Suburb",
    "qs:quad_count":17,
    "qs:woe_adm0":23424829,
    "qs:woe_adm1":2345487,
    "qs:woe_adm2":12597064,
    "qs:woe_lau":26823380,
    "qs:woe_local":708228,
    "qs:woe_ver":"7.10.0",
    "wof:lang":[
        "ger"
    ],
    "wof:name":"Katernberg",
    "wof:placetype":"neighbourhood"
},
  "geometry": {"coordinates":[7.116294,51.274883],"type":"Point"}
}