{
  "type": "Feature",
  "properties": {
    "iso:country":"DE",
    "name:deu_x_preferred":[
        "Tackh\u00fctte"
    ],
    "wof:name":"Tackhuette",
    "wof:placetype":"neighbourhood"
},
  "geometry": {"coordinates":[6.48055166890312,51.17198730343065],"type":"Point"}
}