{
  "type": "Feature",
  "properties": {
    "gn:admin1_code":"13",
    "gn:admin2_code":"0.0",
    "gn:admin3_code":"14523.0",
    "gn:admin4_code":"14523420.0",
    "gn:asciiname":"Lottengruen",
    "gn:country_code":"DE",
    "gn:dem":525,
    "gn:feature_class":"P",
    "gn:feature_code":"PPL",
    "gn:name":"Lottengr\u00fcn",
    "gn:population":0,
    "gn:timezone":"Europe/Berlin",
    "iso:country":"DE",
    "wof:name":"Lottengruen",
    "wof:placetype":"neighbourhood"
},
  "geometry": {"coordinates":[12.23906,50.44552],"type":"Point"}
}