{
  "type": "Feature",
  "properties": {
    "gn:admin1_code":"15",
    "gn:admin2_code":"0.0",
    "gn:admin3_code":"16071.0",
    "gn:admin4_code":"16071095.0",
    "gn:asciiname":"Schwabsdorf",
    "gn:country_code":"DE",
    "gn:dem":253,
    "gn:feature_class":"P",
    "gn:feature_code":"PPL",
    "gn:name":"Schwabsdorf",
    "gn:population":0,
    "gn:timezone":"Europe/Berlin",
    "iso:country":"DE",
    "name:gml_x_preferred":[
        "S\u016da\u016dirstorp [a. 1223]"
    ],
    "wof:name":"Schwabsdorf",
    "wof:placetype":"neighbourhood"
},
  "geometry": {"coordinates":[11.42893,50.99027],"type":"Point"}
}