{
  "type": "Feature",
  "properties": {
    "gn:admin1_code":"2",
    "gn:admin2_code":"92.0",
    "gn:admin3_code":"9279.0",
    "gn:admin4_code":"9279113.0",
    "gn:asciiname":"Unterfrauenholz",
    "gn:country_code":"DE",
    "gn:dem":411,
    "gn:feature_class":"P",
    "gn:feature_code":"PPLL",
    "gn:name":"Unterfrauenholz",
    "gn:population":0,
    "gn:timezone":"Europe/Berlin",
    "iso:country":"DE",
    "wof:name":"Unterfrauenholz",
    "wof:placetype":"neighbourhood"
},
  "geometry": {"coordinates":[12.84119,48.67491],"type":"Point"}
}