{
  "type": "Feature",
  "properties": {
    "iso:country":"DE",
    "wof:name":"Lerchenau-Ost",
    "wof:placetype":"neighbourhood"
},
  "geometry": {"coordinates":[11.55043494387533,48.19907905672757],"type":"Point"}
}