{
  "type": "Feature",
  "properties": {
    "gn:admin1_code":"13",
    "gn:admin2_code":"0.0",
    "gn:admin3_code":"14628.0",
    "gn:admin4_code":"14628130.0",
    "gn:asciiname":"Oberschlottwitz",
    "gn:country_code":"DE",
    "gn:dem":257,
    "gn:feature_class":"P",
    "gn:feature_code":"PPL",
    "gn:name":"Oberschlottwitz",
    "gn:population":0,
    "gn:timezone":"Europe/Berlin",
    "iso:country":"DE",
    "wof:name":"Oberschlottwitz",
    "wof:placetype":"neighbourhood"
},
  "geometry": {"coordinates":[13.81531,50.87492],"type":"Point"}
}