{
  "type": "Feature",
  "properties": {
    "gn:admin1_code":"2",
    "gn:admin2_code":"91.0",
    "gn:admin3_code":"9187.0",
    "gn:admin4_code":"9187114.0",
    "gn:asciiname":"Grattenbach",
    "gn:country_code":"DE",
    "gn:dem":701,
    "gn:feature_class":"P",
    "gn:feature_code":"PPL",
    "gn:name":"Grattenbach",
    "gn:population":0,
    "gn:timezone":"Europe/Berlin",
    "iso:country":"DE",
    "wof:name":"Grattenbach",
    "wof:placetype":"neighbourhood"
},
  "geometry": {"coordinates":[12.28988,47.72013],"type":"Point"}
}