{
  "type": "Feature",
  "properties": {
    "gn:admin1_code":"2",
    "gn:admin2_code":"91.0",
    "gn:admin3_code":"9176.0",
    "gn:admin4_code":"9176126.0",
    "gn:asciiname":"Lippertshofen",
    "gn:country_code":"DE",
    "gn:dem":421,
    "gn:feature_class":"P",
    "gn:feature_code":"PPL",
    "gn:name":"Lippertshofen",
    "gn:population":0,
    "gn:timezone":"Europe/Berlin",
    "iso:country":"DE",
    "wof:name":"Lippertshofen",
    "wof:placetype":"neighbourhood"
},
  "geometry": {"coordinates":[11.3566,48.83544000000001],"type":"Point"}
}