{
  "type": "Feature",
  "properties": {
    "gn:admin1_code":"1",
    "gn:admin2_code":"84.0",
    "gn:admin3_code":"8425.0",
    "gn:admin4_code":"8425050.0",
    "gn:asciiname":"Obergriesingen",
    "gn:country_code":"DE",
    "gn:dem":522,
    "gn:feature_class":"P",
    "gn:feature_code":"PPL",
    "gn:name":"Obergriesingen",
    "gn:population":0,
    "gn:timezone":"Europe/Berlin",
    "iso:country":"DE",
    "wof:name":"Obergriesingen",
    "wof:placetype":"neighbourhood"
},
  "geometry": {"coordinates":[9.77549,48.26303],"type":"Point"}
}