{
  "type": "Feature",
  "properties": {
    "gn:admin1_code":"2",
    "gn:admin2_code":"93.0",
    "gn:admin3_code":"9372.0",
    "gn:admin4_code":"9372116.0",
    "gn:asciiname":"Hanzing",
    "gn:country_code":"DE",
    "gn:dem":442,
    "gn:feature_class":"P",
    "gn:feature_code":"PPL",
    "gn:name":"Hanzing",
    "gn:population":0,
    "gn:timezone":"Europe/Berlin",
    "iso:country":"DE",
    "wof:name":"Hanzing",
    "wof:placetype":"neighbourhood"
},
  "geometry": {"coordinates":[12.67938,49.1668],"type":"Point"}
}