{
  "type": "Feature",
  "properties": {
    "gn:admin1_code":"7",
    "gn:admin2_code":"53.0",
    "gn:admin3_code":"5382.0",
    "gn:admin4_code":"5382040.0",
    "gn:asciiname":"Rippert",
    "gn:country_code":"DE",
    "gn:dem":192,
    "gn:feature_class":"P",
    "gn:feature_code":"PPL",
    "gn:name":"Rippert",
    "gn:population":0,
    "gn:timezone":"Europe/Berlin",
    "iso:country":"DE",
    "wof:name":"Rippert",
    "wof:placetype":"neighbourhood"
},
  "geometry": {"coordinates":[7.30416,50.87168],"type":"Point"}
}