{
  "type": "Feature",
  "properties": {
    "gn:admin1_code":"12",
    "gn:admin2_code":"0.0",
    "gn:admin3_code":"13074.0",
    "gn:admin4_code":"13074029.0",
    "gn:asciiname":"Torisdorf",
    "gn:country_code":"DE",
    "gn:dem":46,
    "gn:feature_class":"P",
    "gn:feature_code":"PPL",
    "gn:name":"Torisdorf",
    "gn:population":0,
    "gn:timezone":"Europe/Berlin",
    "iso:country":"DE",
    "wof:name":"Torisdorf",
    "wof:placetype":"neighbourhood"
},
  "geometry": {"coordinates":[10.95914,53.80539],"type":"Point"}
}