{
  "type": "Feature",
  "properties": {
    "gn:admin1_code":"7.0",
    "gn:admin2_code":"57.0",
    "gn:admin3_code":"5774.0",
    "gn:admin4_code":"5774020.0",
    "gn:asciiname":"Auf der Kanneword",
    "gn:country_code":"DE",
    "gn:dem":98,
    "gn:feature_class":"P",
    "gn:feature_code":"PPLL",
    "gn:name":"Auf der Kanneword",
    "gn:population":0,
    "gn:timezone":"Europe/Berlin",
    "iso:country":"DE",
    "wof:name":"Auf der Kanneword",
    "wof:placetype":"neighbourhood"
},
  "geometry": {"coordinates":[8.60055,51.80161],"type":"Point"}
}