{
  "type": "Feature",
  "properties": {
    "gn:admin1_code":"5",
    "gn:admin2_code":"64.0",
    "gn:admin3_code":"6437.0",
    "gn:admin4_code":"6437003.0",
    "gn:asciiname":"Wallbach",
    "gn:country_code":"DE",
    "gn:dem":257,
    "gn:feature_class":"P",
    "gn:feature_code":"PPL",
    "gn:name":"Wallbach",
    "gn:population":0,
    "gn:timezone":"Europe/Berlin",
    "iso:country":"DE",
    "name:als_x_preferred":[
        "Wallbach"
    ],
    "name:ceb_x_preferred":[
        "Wallbach"
    ],
    "name:deu_x_preferred":[
        "Wallbach"
    ],
    "name:epo_x_preferred":[
        "Wallbach"
    ],
    "name:eus_x_preferred":[
        "Wallbach"
    ],
    "name:ita_x_preferred":[
        "Wallbach"
    ],
    "name:lmo_x_preferred":[
        "Wallbach"
    ],
    "name:nld_x_preferred":[
        "Wallbach"
    ],
    "name:pol_x_preferred":[
        "Wallbach"
    ],
    "name:rus_x_preferred":[
        "\u0412\u0430\u043b\u044c\u0431\u0430\u0445"
    ],
    "name:sco_x_preferred":[
        "Wallbach"
    ],
    "name:spa_x_preferred":[
        "Wallbach"
    ],
    "name:swe_x_preferred":[
        "Wallbach"
    ],
    "name:vol_x_preferred":[
        "Wallbach"
    ],
    "wof:name":"Wallbach",
    "wof:placetype":"neighbourhood"
},
  "geometry": {"coordinates":[8.91161,49.76258],"type":"Point"}
}