{
  "type": "Feature",
  "properties": {
    "gn:admin1_code":"2.0",
    "gn:admin2_code":"91.0",
    "gn:admin3_code":"9171.0",
    "gn:admin4_code":"9171111.0",
    "gn:asciiname":"Baumanngutl",
    "gn:country_code":"DE",
    "gn:dem":401,
    "gn:feature_class":"P",
    "gn:feature_code":"PPL",
    "gn:name":"Baumanng\u00fctl",
    "gn:population":0,
    "gn:timezone":"Europe/Berlin",
    "iso:country":"DE",
    "wof:name":"Baumanngutl",
    "wof:placetype":"neighbourhood"
},
  "geometry": {"coordinates":[12.63298,48.23036],"type":"Point"}
}