{
  "type": "Feature",
  "properties": {
    "gn:admin1_code":"1.0",
    "gn:admin2_code":"83.0",
    "gn:admin3_code":"8335.0",
    "gn:admin4_code":"8335080.0",
    "gn:asciiname":"Beuren am Ried",
    "gn:cc2":"DE",
    "gn:country_code":"DE",
    "gn:dem":491,
    "gn:feature_class":"P",
    "gn:feature_code":"PPL",
    "gn:name":"Beuren am Ried",
    "gn:population":0,
    "gn:timezone":"Europe/Berlin",
    "iso:country":"DE",
    "name:und_x_variant":[
        "Beuren"
    ],
    "wof:name":"Beuren am Ried",
    "wof:placetype":"neighbourhood"
},
  "geometry": {"coordinates":[8.69637,47.79863],"type":"Point"}
}