{
  "type": "Feature",
  "properties": {
    "gn:gn_country":"DE",
    "gn:gn_fcode":"PPLA4",
    "gn:gn_pop":254,
    "gn:population":254,
    "iso:country":"DE",
    "name:baq_x_preferred":[
        "Krempdorf"
    ],
    "name:chi_x_preferred":[
        "\u514b\u4f26\u666e\u591a\u5c14\u592b"
    ],
    "name:dan_x_preferred":[
        "Krempdorf"
    ],
    "name:dut_x_preferred":[
        "Krempdorf"
    ],
    "name:eng_x_preferred":[
        "Krempdorf"
    ],
    "name:epo_x_preferred":[
        "Krempdorf"
    ],
    "name:fre_x_preferred":[
        "Krempdorf"
    ],
    "name:ger_x_preferred":[
        "Krempdorf"
    ],
    "name:hun_x_preferred":[
        "Krempdorf"
    ],
    "name:ita_x_preferred":[
        "Krempdorf"
    ],
    "name:kaz_x_preferred":[
        "\u041a\u0440\u0435\u043c\u043f\u0434\u043e\u0440\u0444"
    ],
    "name:kir_x_preferred":[
        "\u041a\u0440\u0435\u043c\u043f\u0434\u043e\u0440\u0444"
    ],
    "name:mac_x_preferred":[
        "\u041a\u0440\u0435\u043c\u043f\u0434\u043e\u0440\u0444"
    ],
    "name:may_x_preferred":[
        "Krempdorf"
    ],
    "name:per_x_preferred":[
        "\u06a9\u0631\u0645\u067e\u062f\u0648\u0631\u0641"
    ],
    "name:pol_x_preferred":[
        "Krempdorf"
    ],
    "name:por_x_preferred":[
        "Krempdorf"
    ],
    "name:rum_x_preferred":[
        "Krempdorf"
    ],
    "name:rus_x_preferred":[
        "\u041a\u0440\u0435\u043c\u043f\u0434\u043e\u0440\u0444"
    ],
    "name:srp_x_preferred":[
        "\u041a\u0440\u0435\u043c\u043f\u0434\u043e\u0440\u0444"
    ],
    "name:tur_x_preferred":[
        "Krempdorf"
    ],
    "name:ukr_x_preferred":[
        "\u041a\u0440\u0435\u043c\u043f\u0434\u043e\u0440\u0444"
    ],
    "name:uzb_x_preferred":[
        "Krempdorf"
    ],
    "name:vie_x_preferred":[
        "Krempdorf"
    ],
    "name:vol_x_preferred":[
        "Krempdorf"
    ],
    "name:war_x_preferred":[
        "Krempdorf"
    ],
    "qs_pg:aaroncc":"DE",
    "qs_pg:gn_country":"DE",
    "qs_pg:gn_fcode":"PPLA4",
    "qs_pg:gn_pop":254,
    "qs_pg:name":"Krempdorf",
    "qs_pg:photos_9r":0,
    "qs_pg:photos_sr":0,
    "qs_pg:pop_sr":2,
    "qs_pg:qs_pg_placetype":"locality",
    "wof:name":"Krempdorf",
    "wof:placetype":"locality",
    "wof:population":254
},
  "geometry": {"coordinates":[9.46667,53.83333],"type":"Point"}
}