{
  "type": "Feature",
  "properties": {
    "gn:admin1_code":"6",
    "gn:admin2_code":"0.0",
    "gn:admin3_code":"3454.0",
    "gn:admin4_code":"3454032.0",
    "gn:asciiname":"Schepsdorf",
    "gn:country_code":"DE",
    "gn:dem":24,
    "gn:feature_class":"P",
    "gn:feature_code":"PPL",
    "gn:name":"Schepsdorf",
    "gn:population":0,
    "gn:timezone":"Europe/Berlin",
    "iso:country":"DE",
    "wof:name":"Schepsdorf",
    "wof:placetype":"neighbourhood"
},
  "geometry": {"coordinates":[7.28815,52.51031],"type":"Point"}
}