{
  "type": "Feature",
  "properties": {
    "gn:admin1_code":"2",
    "gn:admin2_code":"93.0",
    "gn:admin3_code":"9373.0",
    "gn:admin4_code":"9373156.0",
    "gn:asciiname":"Pruppach",
    "gn:country_code":"DE",
    "gn:dem":402,
    "gn:feature_class":"P",
    "gn:feature_code":"PPL",
    "gn:name":"Pruppach",
    "gn:population":0,
    "gn:timezone":"Europe/Berlin",
    "iso:country":"DE",
    "wof:name":"Pruppach",
    "wof:placetype":"neighbourhood"
},
  "geometry": {"coordinates":[11.23635,49.28141],"type":"Point"}
}