{
  "type": "Feature",
  "properties": {
    "gn:admin1_code":"10",
    "gn:admin2_code":"0.0",
    "gn:admin3_code":"1059.0",
    "gn:admin4_code":"1059149.0",
    "gn:asciiname":"Nordlinnaufeld",
    "gn:country_code":"DE",
    "gn:dem":8,
    "gn:feature_class":"P",
    "gn:feature_code":"PPL",
    "gn:name":"Nordlinnaufeld",
    "gn:population":0,
    "gn:timezone":"Europe/Berlin",
    "iso:country":"DE",
    "wof:name":"Nordlinnaufeld",
    "wof:placetype":"neighbourhood"
},
  "geometry": {"coordinates":[9.15,54.71666999999999],"type":"Point"}
}