{
  "type": "Feature",
  "properties": {
    "gn:admin1_code":"6",
    "gn:admin2_code":"0.0",
    "gn:admin3_code":"3251.0",
    "gn:admin4_code":"3251038.0",
    "gn:asciiname":"Eitzen",
    "gn:country_code":"DE",
    "gn:dem":53,
    "gn:feature_class":"P",
    "gn:feature_code":"PPL",
    "gn:name":"Eitzen",
    "gn:population":0,
    "gn:timezone":"Europe/Berlin",
    "iso:country":"DE",
    "name:deu_x_preferred":[
        "Eitzen"
    ],
    "wof:name":"Eitzen",
    "wof:placetype":"neighbourhood"
},
  "geometry": {"coordinates":[8.87675,52.80296],"type":"Point"}
}