{
  "type": "Feature",
  "properties": {
    "gn:admin1_code":"15.0",
    "gn:admin2_code":"0.0",
    "gn:admin3_code":"16066.0",
    "gn:admin4_code":"16066074.0",
    "gn:asciiname":"Auwallenburg",
    "gn:country_code":"DE",
    "gn:dem":370,
    "gn:feature_class":"P",
    "gn:feature_code":"PPL",
    "gn:name":"Auwallenburg",
    "gn:population":0,
    "gn:timezone":"Europe/Berlin",
    "iso:country":"DE",
    "wof:name":"Auwallenburg",
    "wof:placetype":"neighbourhood"
},
  "geometry": {"coordinates":[10.41528,50.78737],"type":"Point"}
}