{
  "type": "Feature",
  "properties": {
    "gn:admin1_code":"2",
    "gn:admin2_code":"91.0",
    "gn:admin3_code":"9187.0",
    "gn:admin4_code":"9187122.0",
    "gn:asciiname":"Unterholzham",
    "gn:country_code":"DE",
    "gn:dem":510,
    "gn:feature_class":"P",
    "gn:feature_code":"PPL",
    "gn:name":"Unterholzham",
    "gn:population":0,
    "gn:timezone":"Europe/Berlin",
    "iso:country":"DE",
    "wof:name":"Unterholzham",
    "wof:placetype":"neighbourhood"
},
  "geometry": {"coordinates":[11.93253,47.9214],"type":"Point"}
}