{
  "type": "Feature",
  "properties": {
    "gn:admin1_code":"2",
    "gn:admin2_code":"97.0",
    "gn:admin3_code":"9778.0",
    "gn:admin4_code":"9778173.0",
    "gn:asciiname":"Katzenhirn",
    "gn:country_code":"DE",
    "gn:dem":628,
    "gn:feature_class":"P",
    "gn:feature_code":"PPL",
    "gn:name":"Katzenhirn",
    "gn:population":0,
    "gn:timezone":"Europe/Berlin",
    "iso:country":"DE",
    "wof:name":"Katzenhirn",
    "wof:placetype":"neighbourhood"
},
  "geometry": {"coordinates":[10.53064,48.03789],"type":"Point"}
}