{
  "type": "Feature",
  "properties": {
    "gn:admin1_code":"13.0",
    "gn:admin2_code":"0.0",
    "gn:admin3_code":"14524.0",
    "gn:admin4_code":"14524180.0",
    "gn:asciiname":"Braeunsdorf",
    "gn:country_code":"DE",
    "gn:dem":308,
    "gn:feature_class":"P",
    "gn:feature_code":"PPL",
    "gn:name":"Br\u00e4unsdorf",
    "gn:population":0,
    "gn:timezone":"Europe/Berlin",
    "iso:country":"DE",
    "wof:name":"Braeunsdorf",
    "wof:placetype":"neighbourhood"
},
  "geometry": {"coordinates":[12.70861,50.87159000000001],"type":"Point"}
}