{
  "type": "Feature",
  "properties": {
    "gn:admin1_code":"6.0",
    "gn:admin2_code":"00",
    "gn:admin3_code":"3455.0",
    "gn:admin4_code":"3455026.0",
    "gn:asciiname":"Winkelsheidermoor",
    "gn:country_code":"DE",
    "gn:dem":1,
    "gn:feature_class":"P",
    "gn:feature_code":"PPLL",
    "gn:name":"Winkelsheidermoor",
    "gn:population":0,
    "gn:timezone":"Europe/Berlin",
    "iso:country":"DE",
    "wof:name":"Winkelsheidermoor",
    "wof:placetype":"neighbourhood"
},
  "geometry": {"coordinates":[8.09718,53.39945],"type":"Point"}
}