{
  "type": "Feature",
  "properties": {
    "gn:admin1_code":"2",
    "gn:admin2_code":"92.0",
    "gn:admin3_code":"9276.0",
    "gn:admin4_code":"9276111.0",
    "gn:asciiname":"Hienhardt",
    "gn:country_code":"DE",
    "gn:dem":621,
    "gn:feature_class":"P",
    "gn:feature_code":"PPLL",
    "gn:name":"Hienhardt",
    "gn:population":0,
    "gn:timezone":"Europe/Berlin",
    "iso:country":"DE",
    "wof:name":"Hienhardt",
    "wof:placetype":"neighbourhood"
},
  "geometry": {"coordinates":[12.93441,48.96735],"type":"Point"}
}