{
  "type": "Feature",
  "properties": {
    "gn:admin1_code":"2",
    "gn:admin2_code":"91.0",
    "gn:admin3_code":"9189.0",
    "gn:admin4_code":"9189145.0",
    "gn:asciiname":"Wagenau",
    "gn:country_code":"DE",
    "gn:dem":692,
    "gn:feature_class":"P",
    "gn:feature_code":"PPLL",
    "gn:name":"Wagenau",
    "gn:population":0,
    "gn:timezone":"Europe/Berlin",
    "iso:country":"DE",
    "wof:name":"Wagenau",
    "wof:placetype":"neighbourhood"
},
  "geometry": {"coordinates":[12.72472,47.79161],"type":"Point"}
}