{
  "type": "Feature",
  "properties": {
    "gn:admin1_code":"13",
    "gn:admin2_code":"0.0",
    "gn:admin3_code":"14626.0",
    "gn:admin4_code":"14626580.0",
    "gn:asciiname":"Diehsa",
    "gn:country_code":"DE",
    "gn:dem":166,
    "gn:feature_class":"P",
    "gn:feature_code":"PPL",
    "gn:name":"Diehsa",
    "gn:population":0,
    "gn:timezone":"Europe/Berlin",
    "iso:country":"DE",
    "name:hsb_x_preferred":[
        "D\u017a\u011b\u017ee"
    ],
    "name:und_x_variant":[
        "Altmarkt",
        "Diehsa"
    ],
    "wof:name":"Diehsa",
    "wof:placetype":"neighbourhood"
},
  "geometry": {"coordinates":[14.7663,51.24476],"type":"Point"}
}