{
  "type": "Feature",
  "properties": {
    "gn:admin1_code":"11.0",
    "gn:admin2_code":"0.0",
    "gn:admin3_code":"12060.0",
    "gn:admin4_code":"12060192.0",
    "gn:asciiname":"Albertshof",
    "gn:country_code":"DE",
    "gn:dem":74,
    "gn:feature_class":"P",
    "gn:feature_code":"PPL",
    "gn:name":"Albertshof",
    "gn:population":0,
    "gn:timezone":"Europe/Berlin",
    "iso:country":"DE",
    "wof:name":"Albertshof",
    "wof:placetype":"neighbourhood"
},
  "geometry": {"coordinates":[13.65944,52.69792],"type":"Point"}
}