{
  "type": "Feature",
  "properties": {
    "gn:admin1_code":"13",
    "gn:admin2_code":"0.0",
    "gn:admin3_code":"14627.0",
    "gn:admin4_code":"14627230.0",
    "gn:asciiname":"Poppitz",
    "gn:country_code":"DE",
    "gn:dem":103,
    "gn:feature_class":"P",
    "gn:feature_code":"PPL",
    "gn:name":"Poppitz",
    "gn:population":0,
    "gn:timezone":"Europe/Berlin",
    "iso:country":"DE",
    "name:bre_x_preferred":[
        "Poppitz"
    ],
    "name:deu_x_preferred":[
        "Poppitz"
    ],
    "name:fra_x_preferred":[
        "Poppitz"
    ],
    "wof:name":"Poppitz",
    "wof:placetype":"neighbourhood"
},
  "geometry": {"coordinates":[13.32401,51.29096],"type":"Point"}
}