{
  "type": "Feature",
  "properties": {
    "gn:admin1_code":"13",
    "gn:admin2_code":"0.0",
    "gn:admin3_code":"14730.0",
    "gn:admin4_code":"14730110.0",
    "gn:asciiname":"Hainichen",
    "gn:country_code":"DE",
    "gn:dem":99,
    "gn:feature_class":"P",
    "gn:feature_code":"PPL",
    "gn:name":"Hainichen",
    "gn:population":0,
    "gn:timezone":"Europe/Berlin",
    "iso:country":"DE",
    "name:ceb_x_preferred":[
        "Hainichen"
    ],
    "name:deu_x_preferred":[
        "Hainichen"
    ],
    "name:fra_x_preferred":[
        "Hainichen"
    ],
    "name:mkd_x_preferred":[
        "\u0425\u0430\u0458\u043d\u0438\u0445\u0435\u043d"
    ],
    "name:nld_x_preferred":[
        "Hainichen"
    ],
    "name:pol_x_preferred":[
        "Hainichen"
    ],
    "name:rus_x_preferred":[
        "\u0425\u0430\u0439\u043d\u0438\u0445\u0435\u043d"
    ],
    "name:vol_x_preferred":[
        "Hainichen"
    ],
    "wof:name":"Hainichen",
    "wof:placetype":"neighbourhood"
},
  "geometry": {"coordinates":[12.61517,51.48346],"type":"Point"}
}