{
  "type": "Feature",
  "properties": {
    "gn:admin1_code":"7.0",
    "gn:admin2_code":"053",
    "gn:admin3_code":"5374.0",
    "gn:admin4_code":"5374012.0",
    "gn:asciiname":"Wuerden",
    "gn:country_code":"DE",
    "gn:dem":302,
    "gn:feature_class":"P",
    "gn:feature_code":"PPL",
    "gn:name":"W\u00fcrden",
    "gn:population":0,
    "gn:timezone":"Europe/Berlin",
    "iso:country":"DE",
    "wof:name":"Wuerden",
    "wof:placetype":"neighbourhood"
},
  "geometry": {"coordinates":[7.44387,51.03385],"type":"Point"}
}