{
  "type": "Feature",
  "properties": {
    "gn:admin1_code":"2",
    "gn:admin2_code":"97.0",
    "gn:admin3_code":"9780.0",
    "gn:admin4_code":"9780140.0",
    "gn:asciiname":"Sulzbrunn",
    "gn:country_code":"DE",
    "gn:dem":846,
    "gn:feature_class":"P",
    "gn:feature_code":"PPL",
    "gn:name":"Sulzbrunn",
    "gn:population":0,
    "gn:timezone":"Europe/Berlin",
    "iso:country":"DE",
    "name:und_x_variant":[
        "Jodbad Sulzbrunn",
        "Sulzbrunn"
    ],
    "wof:name":"Sulzbrunn",
    "wof:placetype":"neighbourhood"
},
  "geometry": {"coordinates":[10.38512,47.67059],"type":"Point"}
}