{
  "type": "Feature",
  "properties": {
    "iso:country":"DE",
    "qs_pg:aaroncc":"DE",
    "qs_pg:name":"Slek",
    "qs_pg:name_adm0":"Nederland",
    "qs_pg:name_adm1":"Limburg",
    "qs_pg:photos":3,
    "qs_pg:photos_1k":1,
    "qs_pg:photos_9k":1,
    "qs_pg:photos_9r":1,
    "qs_pg:photos_all":3,
    "qs_pg:photos_sr":1,
    "qs_pg:pop_sr":0,
    "qs_pg:qs_pg_placetype":"locality",
    "qs_pg:qs_pg_placetype_gp":"Town",
    "qs_pg:woe_adm0":23424909,
    "woe:adm0_id":23424909,
    "woe:name_adm0":"Nederland",
    "woe:name_adm1":"Limburg",
    "woe:placetype":"Town",
    "wof:name":"Slek",
    "wof:placetype":"neighbourhood"
},
  "geometry": {"coordinates":[5.902333,51.059],"type":"Point"}
}