{
  "type": "Feature",
  "properties": {
    "gn:admin1_code":"2",
    "gn:admin2_code":"94.0",
    "gn:admin3_code":"9473.0",
    "gn:admin4_code":"9473151.0",
    "gn:asciiname":"Furth am Berg",
    "gn:country_code":"DE",
    "gn:dem":313,
    "gn:feature_class":"P",
    "gn:feature_code":"PPL",
    "gn:name":"F\u00fcrth am Berg",
    "gn:population":0,
    "gn:timezone":"Europe/Berlin",
    "iso:country":"DE",
    "name:und_x_variant":[
        "F\u00fcrth",
        "F\u00fcrth am Berg"
    ],
    "wof:name":"Furth am Berg",
    "wof:placetype":"neighbourhood"
},
  "geometry": {"coordinates":[11.16016,50.27762],"type":"Point"}
}