{
  "type": "Feature",
  "properties": {
    "gn:admin1_code":"1",
    "gn:admin2_code":"81.0",
    "gn:admin3_code":"8135.0",
    "gn:admin4_code":"8135010.0",
    "gn:asciiname":"Wagenhofen",
    "gn:country_code":"DE",
    "gn:dem":504,
    "gn:feature_class":"P",
    "gn:feature_code":"PPL",
    "gn:name":"Wagenhofen",
    "gn:population":0,
    "gn:timezone":"Europe/Berlin",
    "iso:country":"DE",
    "wof:name":"Wagenhofen",
    "wof:placetype":"neighbourhood"
},
  "geometry": {"coordinates":[10.44381,48.68061],"type":"Point"}
}