{
  "type": "Feature",
  "properties": {
    "gn:admin1_code":"2",
    "gn:admin2_code":"93.0",
    "gn:admin3_code":"9372.0",
    "gn:admin4_code":"9372137.0",
    "gn:asciiname":"Traidersdorf",
    "gn:country_code":"DE",
    "gn:dem":489,
    "gn:feature_class":"P",
    "gn:feature_code":"PPL",
    "gn:name":"Traidersdorf",
    "gn:population":0,
    "gn:timezone":"Europe/Berlin",
    "iso:country":"DE",
    "wof:name":"Traidersdorf",
    "wof:placetype":"neighbourhood"
},
  "geometry": {"coordinates":[12.92782,49.15392],"type":"Point"}
}