{
  "type": "Feature",
  "properties": {
    "gn:admin1_code":"14.0",
    "gn:admin2_code":"0.0",
    "gn:admin3_code":"15084.0",
    "gn:admin4_code":"15084133.0",
    "gn:asciiname":"Borgau",
    "gn:country_code":"DE",
    "gn:dem":263,
    "gn:feature_class":"P",
    "gn:feature_code":"PPL",
    "gn:name":"Borgau",
    "gn:population":0,
    "gn:timezone":"Europe/Berlin",
    "iso:country":"DE",
    "wof:name":"Borgau",
    "wof:placetype":"neighbourhood"
},
  "geometry": {"coordinates":[11.52228,51.1791],"type":"Point"}
}