{
  "type": "Feature",
  "properties": {
    "gn:admin1_code":"2",
    "gn:admin2_code":"92.0",
    "gn:admin3_code":"9274.0",
    "gn:admin4_code":"9274135.0",
    "gn:asciiname":"Sommerau",
    "gn:country_code":"DE",
    "gn:dem":428,
    "gn:feature_class":"P",
    "gn:feature_code":"PPLL",
    "gn:name":"Sommerau",
    "gn:population":0,
    "gn:timezone":"Europe/Berlin",
    "iso:country":"DE",
    "wof:name":"Sommerau",
    "wof:placetype":"neighbourhood"
},
  "geometry": {"coordinates":[12.43723,48.51666],"type":"Point"}
}