{
  "type": "Feature",
  "properties": {
    "gn:admin1_code":"2",
    "gn:admin2_code":"92.0",
    "gn:admin3_code":"9274.0",
    "gn:admin4_code":"9274135.0",
    "gn:asciiname":"Sommerau",
    "gn:country_code":"DE",
    "gn:dem":428,
    "gn:feature_class":"P",
    "gn:feature_code":"PPLL",
    "gn:name":"Sommerau",
    "gn:population":0,
    "gn:timezone":"Europe/Berlin",
    "iso:country":"DE",
    "name:ceb_x_preferred":[
        "Sommerau"
    ],
    "name:deu_x_preferred":[
        "Sommerau"
    ],
    "name:eus_x_preferred":[
        "Sommerau"
    ],
    "name:fas_x_preferred":[
        "\u0633\u0648\u0645\u0631\u0627\u0648"
    ],
    "name:fra_x_preferred":[
        "Sommerau"
    ],
    "name:hun_x_preferred":[
        "Sommerau"
    ],
    "name:ita_x_preferred":[
        "Sommerau"
    ],
    "name:kat_x_preferred":[
        "\u10d6\u10dd\u10db\u10d4\u10e0\u10d0\u10e3"
    ],
    "name:msa_x_preferred":[
        "Sommerau"
    ],
    "name:nld_x_preferred":[
        "Sommerau"
    ],
    "name:pol_x_preferred":[
        "Sommerau"
    ],
    "name:por_x_preferred":[
        "Sommerau"
    ],
    "name:ron_x_preferred":[
        "Sommerau"
    ],
    "name:rus_x_preferred":[
        "\u0417\u043e\u043c\u043c\u0435\u0440\u0430\u0443"
    ],
    "name:spa_x_preferred":[
        "Sommerau"
    ],
    "name:srp_x_preferred":[
        "\u0417\u043e\u043c\u0435\u0440\u0430\u0443"
    ],
    "name:ukr_x_preferred":[
        "\u0417\u043e\u043c\u043c\u0435\u0440\u0430\u0443"
    ],
    "name:uzb_x_preferred":[
        "Sommerau"
    ],
    "name:vie_x_preferred":[
        "Sommerau"
    ],
    "name:vol_x_preferred":[
        "Sommerau"
    ],
    "name:war_x_preferred":[
        "Sommerau"
    ],
    "name:zho_x_preferred":[
        "\u7d22\u9ed8\u52b3"
    ],
    "wof:name":"Sommerau",
    "wof:placetype":"neighbourhood"
},
  "geometry": {"coordinates":[12.43723,48.51666],"type":"Point"}
}