{
  "type": "Feature",
  "properties": {
    "gn:gn_country":"DE",
    "gn:gn_fcode":"PPLA4",
    "gn:gn_pop":311,
    "gn:population":311,
    "iso:country":"DE",
    "name:baq_x_preferred":[
        "Tellig"
    ],
    "name:chi_x_preferred":[
        "\u7279\u5229\u5e0c"
    ],
    "name:dut_x_preferred":[
        "Tellig"
    ],
    "name:eng_x_preferred":[
        "Tellig"
    ],
    "name:epo_x_preferred":[
        "Tellig"
    ],
    "name:fre_x_preferred":[
        "Tellig"
    ],
    "name:ger_x_preferred":[
        "Tellig"
    ],
    "name:hun_x_preferred":[
        "Tellig"
    ],
    "name:ita_x_preferred":[
        "Tellig"
    ],
    "name:jpn_x_preferred":[
        "\u30c6\u30ea\u30d2"
    ],
    "name:may_x_preferred":[
        "Tellig"
    ],
    "name:per_x_preferred":[
        "\u062a\u0644\u06cc\u06af"
    ],
    "name:pol_x_preferred":[
        "Tellig"
    ],
    "name:por_x_preferred":[
        "Tellig"
    ],
    "name:rum_x_preferred":[
        "Tellig"
    ],
    "name:rus_x_preferred":[
        "\u0422\u0435\u043b\u043b\u0438\u0433"
    ],
    "name:srp_x_preferred":[
        "\u0422\u0435\u043b\u0438\u0433"
    ],
    "name:ukr_x_preferred":[
        "\u0422\u0435\u043b\u043b\u0456\u0433"
    ],
    "name:uzb_x_preferred":[
        "Tellig"
    ],
    "name:vie_x_preferred":[
        "Tellig"
    ],
    "name:vol_x_preferred":[
        "Tellig"
    ],
    "name:war_x_preferred":[
        "Tellig"
    ],
    "qs_pg:aaroncc":"DE",
    "qs_pg:gn_country":"DE",
    "qs_pg:gn_fcode":"PPLA4",
    "qs_pg:gn_pop":311,
    "qs_pg:name":"Tellig",
    "qs_pg:photos_9r":0,
    "qs_pg:photos_sr":0,
    "qs_pg:pop_sr":2,
    "qs_pg:qs_pg_placetype":"locality",
    "wof:name":"Tellig",
    "wof:placetype":"locality",
    "wof:population":311
},
  "geometry": {"coordinates":[7.25,50.03333],"type":"Point"}
}