{
  "type": "Feature",
  "properties": {
    "gn:admin1_code":"2",
    "gn:admin2_code":"91.0",
    "gn:admin3_code":"9183.0",
    "gn:admin4_code":"9183136.0",
    "gn:asciiname":"Furth",
    "gn:country_code":"DE",
    "gn:dem":414,
    "gn:feature_class":"P",
    "gn:feature_code":"PPL",
    "gn:name":"Furth",
    "gn:population":0,
    "gn:timezone":"Europe/Berlin",
    "iso:country":"DE",
    "name:cat_x_preferred":[
        "Furth"
    ],
    "name:ceb_x_preferred":[
        "Furth"
    ],
    "name:deu_x_preferred":[
        "Furth"
    ],
    "name:epo_x_preferred":[
        "Furth"
    ],
    "name:fra_x_preferred":[
        "Furth"
    ],
    "name:ita_x_preferred":[
        "Furth"
    ],
    "name:nld_x_preferred":[
        "Furth"
    ],
    "name:pol_x_preferred":[
        "Furth"
    ],
    "name:rus_x_preferred":[
        "\u0424\u0443\u0440\u0442"
    ],
    "name:srp_x_preferred":[
        "\u0424\u0443\u0440\u0442"
    ],
    "name:swe_x_preferred":[
        "Furth"
    ],
    "wof:name":"Furth",
    "wof:placetype":"neighbourhood"
},
  "geometry": {"coordinates":[12.51159,48.20557],"type":"Point"}
}