{
  "type": "Feature",
  "properties": {
    "gn:country":"DE",
    "gn:fcode":"PPL",
    "gn:population":1457,
    "iso:country":"DE",
    "name:bak_x_preferred":[
        "\u0424\u0438\u043d\u0441\u0442\u0435\u0440\u0431\u0435\u0440\u0433\u0435\u043d"
    ],
    "name:ceb_x_preferred":[
        "Finsterbergen"
    ],
    "name:deu_x_preferred":[
        "Finsterbergen"
    ],
    "name:epo_x_preferred":[
        "Finsterbergen"
    ],
    "name:fas_x_preferred":[
        "\u0641\u06cc\u0646\u0634\u062a\u0631\u0628\u0631\u06af\u0646"
    ],
    "name:mkd_x_preferred":[
        "\u0424\u0438\u043d\u0441\u0442\u0435\u0440\u0431\u0435\u0440\u0433\u0435\u043d"
    ],
    "name:nld_x_preferred":[
        "Finsterbergen"
    ],
    "name:por_x_preferred":[
        "Finsterbergen"
    ],
    "name:ron_x_preferred":[
        "Finsterbergen"
    ],
    "name:rus_x_preferred":[
        "\u0424\u0438\u043d\u0441\u0442\u0435\u0440\u0431\u0435\u0440\u0433\u0435\u043d"
    ],
    "name:uzb_x_preferred":[
        "Finsterbergen"
    ],
    "name:vol_x_preferred":[
        "Finsterbergen"
    ],
    "qs_pg:aaroncc":"DE",
    "qs_pg:gn_country":"DE",
    "qs_pg:gn_fcode":"PPL",
    "qs_pg:gn_pop":1457,
    "qs_pg:name":"Finsterbergen",
    "qs_pg:name_adm0":"Deutschland",
    "qs_pg:name_adm1":"Th\u00fcringen",
    "qs_pg:photos":19,
    "qs_pg:photos_1k":4,
    "qs_pg:photos_9k":1,
    "qs_pg:photos_9r":1,
    "qs_pg:photos_all":19,
    "qs_pg:photos_sr":1,
    "qs_pg:pop_sr":3,
    "qs_pg:qs_pg_placetype":"locality",
    "qs_pg:qs_pg_placetype_gp":"Town",
    "qs_pg:woe_adm0":23424829,
    "woe:adm0_id":23424829,
    "woe:name_adm0":"Deutschland",
    "woe:name_adm1":"Th\u00fcringen",
    "woe:placetype":"Town",
    "wof:name":"Finsterbergen",
    "wof:placetype":"neighbourhood",
    "wof:population":1457
},
  "geometry": {"coordinates":[10.58916,50.83464],"type":"Point"}
}