{
  "type": "Feature",
  "properties": {
    "gn:admin1_code":"11",
    "gn:admin2_code":"0.0",
    "gn:admin3_code":"12066.0",
    "gn:admin4_code":"12066296.0",
    "gn:asciiname":"Wandelhof",
    "gn:country_code":"DE",
    "gn:dem":99,
    "gn:feature_class":"P",
    "gn:feature_code":"PPL",
    "gn:name":"Wandelhof",
    "gn:population":0,
    "gn:timezone":"Europe/Berlin",
    "iso:country":"DE",
    "wof:name":"Wandelhof",
    "wof:placetype":"neighbourhood"
},
  "geometry": {"coordinates":[13.84988,51.47473],"type":"Point"}
}