{
  "type": "Feature",
  "properties": {
    "gn:admin1_code":"1",
    "gn:admin2_code":"83.0",
    "gn:admin3_code":"8337.0",
    "gn:admin4_code":"8337097.0",
    "gn:asciiname":"Niedermuhle",
    "gn:country_code":"DE",
    "gn:dem":607,
    "gn:feature_class":"P",
    "gn:feature_code":"PPL",
    "gn:name":"Niederm\u00fchle",
    "gn:population":0,
    "gn:timezone":"Europe/Berlin",
    "iso:country":"DE",
    "wof:name":"Niedermuhle",
    "wof:placetype":"neighbourhood"
},
  "geometry": {"coordinates":[8.12014,47.67948],"type":"Point"}
}