{
  "type": "Feature",
  "properties": {
    "gn:gn_country":"DE",
    "gn:gn_fcode":"PPLA4",
    "gn:gn_pop":236,
    "gn:population":236,
    "iso:country":"DE",
    "qs_pg:aaroncc":"DE",
    "qs_pg:gn_country":"DE",
    "qs_pg:gn_fcode":"PPLA4",
    "qs_pg:gn_pop":236,
    "qs_pg:name":"D\u00f6britschen",
    "qs_pg:photos_9r":0,
    "qs_pg:photos_sr":0,
    "qs_pg:pop_sr":2,
    "qs_pg:qs_pg_placetype":"locality",
    "wof:name":"D\u00f6britschen",
    "wof:placetype":"locality",
    "wof:population":236
},
  "geometry": {"coordinates":[11.47599,50.91921],"type":"Point"}
}