{
  "type": "Feature",
  "properties": {
    "gn:admin1_code":"2.0",
    "gn:admin2_code":"91.0",
    "gn:admin3_code":"9183.0",
    "gn:admin4_code":"9183126.0",
    "gn:asciiname":"Brand",
    "gn:country_code":"DE",
    "gn:dem":549,
    "gn:feature_class":"P",
    "gn:feature_code":"PPL",
    "gn:name":"Brand",
    "gn:population":0,
    "gn:timezone":"Europe/Berlin",
    "iso:country":"DE",
    "wof:name":"Brand",
    "wof:placetype":"neighbourhood"
},
  "geometry": {"coordinates":[12.14772,48.15359],"type":"Point"}
}