{
  "type": "Feature",
  "properties": {
    "gn:admin1_code":"7",
    "gn:admin2_code":"59.0",
    "gn:admin3_code":"5958.0",
    "gn:admin4_code":"5958032.0",
    "gn:asciiname":"Loellinghausen",
    "gn:country_code":"DE",
    "gn:dem":332,
    "gn:feature_class":"P",
    "gn:feature_code":"PPL",
    "gn:name":"L\u00f6llinghausen",
    "gn:population":0,
    "gn:timezone":"Europe/Berlin",
    "iso:country":"DE",
    "wof:name":"Loellinghausen",
    "wof:placetype":"neighbourhood"
},
  "geometry": {"coordinates":[8.32888,51.31091],"type":"Point"}
}