{
  "type": "Feature",
  "properties": {
    "gn:admin1_code":"5",
    "gn:admin2_code":"64.0",
    "gn:admin3_code":"6434.0",
    "gn:admin4_code":"6434006.0",
    "gn:asciiname":"Schoenberg",
    "gn:country_code":"DE",
    "gn:dem":254,
    "gn:feature_class":"P",
    "gn:feature_code":"PPL",
    "gn:name":"Sch\u00f6nberg",
    "gn:population":0,
    "gn:timezone":"Europe/Berlin",
    "iso:country":"DE",
    "name:nld_x_preferred":[
        "Sch\u00f6nberg"
    ],
    "wof:name":"Schoenberg",
    "wof:placetype":"neighbourhood"
},
  "geometry": {"coordinates":[8.5221,50.18483],"type":"Point"}
}