{
  "type": "Feature",
  "properties": {
    "gn:admin1_code":"10",
    "gn:admin2_code":"0.0",
    "gn:admin3_code":"1058.0",
    "gn:admin4_code":"1058005.0",
    "gn:asciiname":"Knoop",
    "gn:country_code":"DE",
    "gn:dem":18,
    "gn:feature_class":"P",
    "gn:feature_code":"PPL",
    "gn:name":"Knoop",
    "gn:population":0,
    "gn:timezone":"Europe/Berlin",
    "iso:country":"DE",
    "wof:name":"Knoop",
    "wof:placetype":"neighbourhood"
},
  "geometry": {"coordinates":[10.10192,54.37483],"type":"Point"}
}