{
  "type": "Feature",
  "properties": {
    "gn:admin1_code":"12",
    "gn:admin2_code":"0.0",
    "gn:admin3_code":"13073.0",
    "gn:admin4_code":"13073063.0",
    "gn:asciiname":"Volkshagen",
    "gn:country_code":"DE",
    "gn:dem":13,
    "gn:feature_class":"P",
    "gn:feature_code":"PPL",
    "gn:name":"Volkshagen",
    "gn:population":0,
    "gn:timezone":"Europe/Berlin",
    "iso:country":"DE",
    "wof:name":"Volkshagen",
    "wof:placetype":"neighbourhood"
},
  "geometry": {"coordinates":[13.32441,54.4296],"type":"Point"}
}