{
  "type": "Feature",
  "properties": {
    "gn:admin1_code":"2",
    "gn:admin2_code":"97.0",
    "gn:admin3_code":"9773.0",
    "gn:admin4_code":"9773125.0",
    "gn:asciiname":"Steinheim",
    "gn:country_code":"DE",
    "gn:dem":419,
    "gn:feature_class":"P",
    "gn:feature_code":"PPL",
    "gn:name":"Steinheim",
    "gn:population":0,
    "gn:timezone":"Europe/Berlin",
    "iso:country":"DE",
    "name:ceb_x_preferred":[
        "Steinheim"
    ],
    "name:deu_x_preferred":[
        "Steinheim"
    ],
    "name:epo_x_preferred":[
        "Steinheim"
    ],
    "name:fin_x_preferred":[
        "Steinheim"
    ],
    "name:fra_x_preferred":[
        "Steinheim"
    ],
    "name:hun_x_preferred":[
        "Steinheim"
    ],
    "name:ltz_x_preferred":[
        "Steinheim"
    ],
    "name:nld_x_preferred":[
        "Steinheim"
    ],
    "name:pol_x_preferred":[
        "Steinheim"
    ],
    "name:por_x_preferred":[
        "Steinheim"
    ],
    "name:ron_x_preferred":[
        "Steinheim"
    ],
    "name:swe_x_preferred":[
        "Steinheim"
    ],
    "wof:name":"Steinheim",
    "wof:placetype":"neighbourhood"
},
  "geometry": {"coordinates":[10.53726,48.59534],"type":"Point"}
}