{
  "type": "Feature",
  "properties": {
    "gn:admin1_code":"1",
    "gn:admin2_code":"84.0",
    "gn:admin3_code":"8417.0",
    "gn:admin4_code":"8417002.0",
    "gn:asciiname":"Durrwangen",
    "gn:country_code":"DE",
    "gn:dem":573,
    "gn:feature_class":"P",
    "gn:feature_code":"PPL",
    "gn:name":"D\u00fcrrwangen",
    "gn:population":0,
    "gn:timezone":"Europe/Berlin",
    "iso:country":"DE",
    "wof:name":"Durrwangen",
    "wof:placetype":"neighbourhood"
},
  "geometry": {"coordinates":[8.88742,48.24062],"type":"Point"}
}