{
  "type": "Feature",
  "properties": {
    "gn:admin1_code":"6.0",
    "gn:admin2_code":"0.0",
    "gn:admin3_code":"3358.0",
    "gn:admin4_code":"3358003.0",
    "gn:asciiname":"Altenwahlingen",
    "gn:country_code":"DE",
    "gn:dem":21,
    "gn:feature_class":"P",
    "gn:feature_code":"PPL",
    "gn:name":"Altenwahlingen",
    "gn:population":0,
    "gn:timezone":"Europe/Berlin",
    "iso:country":"DE",
    "wof:name":"Altenwahlingen",
    "wof:placetype":"neighbourhood"
},
  "geometry": {"coordinates":[9.4285,52.79581],"type":"Point"}
}