{
  "type": "Feature",
  "properties": {
    "gn:admin1_code":"2",
    "gn:admin2_code":"91.0",
    "gn:admin3_code":"9187.0",
    "gn:admin4_code":"9187116.0",
    "gn:asciiname":"Neudeck",
    "gn:country_code":"DE",
    "gn:dem":498,
    "gn:feature_class":"P",
    "gn:feature_code":"PPL",
    "gn:name":"Neudeck",
    "gn:population":0,
    "gn:timezone":"Europe/Berlin",
    "iso:country":"DE",
    "name:deu_x_preferred":[
        "Neudeck"
    ],
    "wof:name":"Neudeck",
    "wof:placetype":"neighbourhood"
},
  "geometry": {"coordinates":[12.24106,48.06985],"type":"Point"}
}