{
  "type": "Feature",
  "properties": {
    "iso:country":"DE",
    "name:deu_x_preferred":[
        "Flugplatz Bad Gandersheim"
    ],
    "name:eng_x_preferred":[
        "Bad Gandersheim Airport"
    ],
    "name:eng_x_variant":[
        "EDVA",
        "Bad Gandersheim airfield"
    ],
    "name:fas_x_preferred":[
        "\u0641\u0631\u0648\u062f\u06af\u0627\u0647 \u0628\u0627\u062f \u06af\u0627\u0646\u062f\u0631\u0632\u0647\u0627\u06cc\u0645"
    ],
    "name:mkd_x_preferred":[
        "\u0410\u0435\u0440\u043e\u0434\u0440\u043e\u043c \u0411\u0430\u0434 \u0413\u0430\u043d\u0434\u0435\u0440\u0441\u0445\u0430\u0458\u043c"
    ],
    "name:msa_x_preferred":[
        "Lapangan Terbang Bad Gandersheim"
    ],
    "name:nld_x_preferred":[
        "Vliegveld Bad Gandersheim"
    ],
    "name:pol_x_preferred":[
        "Lotnisko Bad Gandersheim"
    ],
    "name:tgk_x_preferred":[
        "\u0424\u0443\u0440\u0443\u0434\u0433\u043e\u04b3\u0438 \u0431\u043e\u0434 \u0433\u043e\u043d\u0434\u0440\u0437\u04b3\u043e\u0438\u043c"
    ],
    "oa:elevation_ft":"791",
    "oa:type":"small_airport",
    "woe:hierarchy":{
        "country_id":23424829,
        "county_id":12596705,
        "localadmin_id":12630391,
        "planet_id":1,
        "state_id":2345486
    },
    "wof:name":"Flugplatz Bad Gandersheim",
    "wof:placetype":"campus"
},
  "geometry": {"coordinates":[10.027778,51.854167],"type":"Point"}
}