{
  "type": "Feature",
  "properties": {
    "iso:country":"DE",
    "oa:elevation_ft":"791",
    "oa:type":"small_airport",
    "woe:hierarchy":{
        "country_id":23424829,
        "county_id":12596705,
        "localadmin_id":12630391,
        "planet_id":1,
        "state_id":2345486
    },
    "wof:name":"Flugplatz Bad Gandersheim",
    "wof:placetype":"campus"
},
  "geometry": {"coordinates":[10.027777777778,51.854166666667],"type":"Point"}
}