{
  "type": "Feature",
  "properties": {
    "gn:admin1_code":"2",
    "gn:admin2_code":"92.0",
    "gn:admin3_code":"9275.0",
    "gn:admin4_code":"9275153.0",
    "gn:asciiname":"Hanzing",
    "gn:country_code":"DE",
    "gn:dem":538,
    "gn:feature_class":"P",
    "gn:feature_code":"PPL",
    "gn:name":"Hanzing",
    "gn:population":0,
    "gn:timezone":"Europe/Berlin",
    "iso:country":"DE",
    "wof:name":"Hanzing",
    "wof:placetype":"neighbourhood"
},
  "geometry": {"coordinates":[13.66467,48.55593],"type":"Point"}
}