{
  "type": "Feature",
  "properties": {
    "iso:country":"DE",
    "wof:name":"Rondorf",
    "wof:placetype":"neighbourhood"
},
  "geometry": {"coordinates":[6.95475973266434,50.87364741864121],"type":"Point"}
}