{
  "type": "Feature",
  "properties": {
    "gn:admin1_code":"1.0",
    "gn:admin2_code":"83.0",
    "gn:admin3_code":"8317.0",
    "gn:admin4_code":"8317129.0",
    "gn:asciiname":"Bei der Kirche",
    "gn:country_code":"DE",
    "gn:dem":269,
    "gn:feature_class":"P",
    "gn:feature_code":"PPLL",
    "gn:name":"Bei der Kirche",
    "gn:population":0,
    "gn:timezone":"Europe/Berlin",
    "iso:country":"DE",
    "wof:name":"Bei der Kirche",
    "wof:placetype":"neighbourhood"
},
  "geometry": {"coordinates":[8.01722,48.2748],"type":"Point"}
}