{
  "type": "Feature",
  "properties": {
    "gn:admin1_code":"6",
    "gn:admin2_code":"0.0",
    "gn:admin3_code":"3155.0",
    "gn:admin4_code":"3155013.0",
    "gn:asciiname":"Erzhausen",
    "gn:country_code":"DE",
    "gn:dem":104,
    "gn:feature_class":"P",
    "gn:feature_code":"PPL",
    "gn:name":"Erzhausen",
    "gn:population":0,
    "gn:timezone":"Europe/Berlin",
    "iso:country":"DE",
    "name:dan_x_preferred":[
        "Erzhausen"
    ],
    "name:deu_x_preferred":[
        "Erzhausen"
    ],
    "name:epo_x_preferred":[
        "Erzhausen"
    ],
    "name:eus_x_preferred":[
        "Erzhausen"
    ],
    "name:fas_x_preferred":[
        "\u0627\u0631\u062a\u0633\u0647\u0627\u0648\u0632\u0646"
    ],
    "name:fra_x_preferred":[
        "Erzhausen"
    ],
    "name:hun_x_preferred":[
        "Erzhausen"
    ],
    "name:ita_x_preferred":[
        "Erzhausen"
    ],
    "name:jpn_x_preferred":[
        "\u30a8\u30eb\u30c4\u30cf\u30a6\u30bc\u30f3"
    ],
    "name:msa_x_preferred":[
        "Erzhausen"
    ],
    "name:nld_x_preferred":[
        "Erzhausen"
    ],
    "name:pol_x_preferred":[
        "Erzhausen"
    ],
    "name:ron_x_preferred":[
        "Erzhausen"
    ],
    "name:rus_x_preferred":[
        "\u042d\u0440\u0446\u0445\u0430\u0443\u0437\u0435\u043d"
    ],
    "name:spa_x_preferred":[
        "Erzhausen"
    ],
    "name:srp_x_preferred":[
        "\u0415\u0440\u0446\u0445\u0430\u0443\u0437\u0435\u043d"
    ],
    "name:ukr_x_preferred":[
        "\u0415\u0440\u0446\u0433\u0430\u0443\u0437\u0435\u043d"
    ],
    "name:uzb_x_preferred":[
        "Erzhausen"
    ],
    "name:vol_x_preferred":[
        "Erzhausen"
    ],
    "name:war_x_preferred":[
        "Erzhausen"
    ],
    "name:zho_x_preferred":[
        "\u57c3\u5c14\u8328\u8c6a\u68ee"
    ],
    "wof:name":"Erzhausen",
    "wof:placetype":"neighbourhood"
},
  "geometry": {"coordinates":[9.92967,51.89151],"type":"Point"}
}