{
  "type": "Feature",
  "properties": {
    "gn:admin1_code":"6",
    "gn:admin2_code":"0.0",
    "gn:admin3_code":"3455.0",
    "gn:admin4_code":"3455026.0",
    "gn:asciiname":"Rosenberg",
    "gn:country_code":"DE",
    "gn:dem":6,
    "gn:feature_class":"P",
    "gn:feature_code":"PPLL",
    "gn:name":"Rosenberg",
    "gn:population":0,
    "gn:timezone":"Europe/Berlin",
    "iso:country":"DE",
    "wof:name":"Rosenberg",
    "wof:placetype":"neighbourhood"
},
  "geometry": {"coordinates":[8.11532,53.34144000000001],"type":"Point"}
}