{
  "type": "Feature",
  "properties": {
    "gn:admin1_code":"6",
    "gn:admin2_code":"0.0",
    "gn:admin3_code":"3455.0",
    "gn:admin4_code":"3455026.0",
    "gn:asciiname":"Rosenberg",
    "gn:country_code":"DE",
    "gn:dem":6,
    "gn:feature_class":"P",
    "gn:feature_code":"PPLL",
    "gn:name":"Rosenberg",
    "gn:population":0,
    "gn:timezone":"Europe/Berlin",
    "iso:country":"DE",
    "name:cat_x_preferred":[
        "Rosenberg"
    ],
    "name:ceb_x_preferred":[
        "Rosenberg"
    ],
    "name:ces_x_preferred":[
        "Rosenberg"
    ],
    "name:deu_x_preferred":[
        "Rosenberg"
    ],
    "name:epo_x_preferred":[
        "Rosenberg"
    ],
    "name:fas_x_preferred":[
        "\u0631\u0648\u0632\u0646\u0628\u0631\u06af"
    ],
    "name:fin_x_preferred":[
        "Rosenberg"
    ],
    "name:fra_x_preferred":[
        "Rosenberg"
    ],
    "name:heb_x_preferred":[
        "\u05e8\u05d5\u05d6\u05e0\u05d1\u05e8\u05d2"
    ],
    "name:hun_x_preferred":[
        "Rosenberg"
    ],
    "name:ita_x_preferred":[
        "Rosenberg"
    ],
    "name:jpn_x_preferred":[
        "\u30ed\u30fc\u30bc\u30f3\u30d9\u30eb\u30af"
    ],
    "name:kor_x_preferred":[
        "\ub85c\uc820\ubc84\uadf8"
    ],
    "name:lav_x_preferred":[
        "Rozenbergs"
    ],
    "name:lmo_x_preferred":[
        "Rosenberg"
    ],
    "name:nld_x_preferred":[
        "Rosenberg"
    ],
    "name:pol_x_preferred":[
        "Rosenberg"
    ],
    "name:por_x_preferred":[
        "Rosenberg"
    ],
    "name:ron_x_preferred":[
        "Rosenberg"
    ],
    "name:rus_x_preferred":[
        "\u0420\u043e\u0437\u0435\u043d\u0431\u0435\u0440\u0433"
    ],
    "name:slv_x_preferred":[
        "Rosenberg"
    ],
    "name:spa_x_preferred":[
        "Rosenberg"
    ],
    "name:swe_x_preferred":[
        "Rosenberg"
    ],
    "name:ukr_x_preferred":[
        "\u0420\u043e\u0437\u0435\u043d\u0431\u0435\u0440\u0433"
    ],
    "name:vol_x_preferred":[
        "Rosenberg"
    ],
    "wof:name":"Rosenberg",
    "wof:placetype":"neighbourhood"
},
  "geometry": {"coordinates":[8.11532,53.34144000000001],"type":"Point"}
}