{
  "type": "Feature",
  "properties": {
    "gn:admin1_code":"2",
    "gn:admin2_code":"91.0",
    "gn:admin3_code":"9178.0",
    "gn:admin4_code":"9178132.0",
    "gn:asciiname":"Sankt Alban",
    "gn:country_code":"DE",
    "gn:dem":465,
    "gn:feature_class":"P",
    "gn:feature_code":"PPL",
    "gn:name":"Sankt Alban",
    "gn:population":0,
    "gn:timezone":"Europe/Berlin",
    "iso:country":"DE",
    "name:ceb_x_preferred":[
        "Sankt Alban"
    ],
    "name:deu_x_preferred":[
        "Sankt Alban"
    ],
    "name:epo_x_preferred":[
        "Sankt Alban"
    ],
    "name:eus_x_preferred":[
        "Sankt Alban"
    ],
    "name:fas_x_preferred":[
        "\u0632\u0627\u0646\u06a9\u062a \u0622\u0644\u0628\u0627\u0646"
    ],
    "name:fra_x_preferred":[
        "Sankt Alban"
    ],
    "name:hun_x_preferred":[
        "Sankt Alban"
    ],
    "name:ita_x_preferred":[
        "Sankt Alban"
    ],
    "name:msa_x_preferred":[
        "Sankt Alban"
    ],
    "name:nld_x_preferred":[
        "Sankt Alban"
    ],
    "name:pol_x_preferred":[
        "Sankt Alban"
    ],
    "name:por_x_preferred":[
        "Sankt Alban"
    ],
    "name:ron_x_preferred":[
        "Sankt Alban"
    ],
    "name:rus_x_preferred":[
        "\u0421\u0430\u043d\u043a\u0442-\u0410\u043b\u044c\u0431\u0430\u043d"
    ],
    "name:spa_x_preferred":[
        "Sankt Alban"
    ],
    "name:srp_x_preferred":[
        "\u0421\u0430\u043d\u043a\u0442 \u0410\u043b\u0431\u0430\u043d"
    ],
    "name:ukr_x_preferred":[
        "\u0417\u0430\u043d\u043a\u0442-\u0410\u043b\u044c\u0431\u0430\u043d"
    ],
    "name:uzb_x_preferred":[
        "Sankt Alban"
    ],
    "name:vie_x_preferred":[
        "Sankt Alban"
    ],
    "name:vol_x_preferred":[
        "Sankt Alban"
    ],
    "name:war_x_preferred":[
        "Sankt Alban"
    ],
    "name:zho_x_preferred":[
        "\u5723\u963f\u5c14\u73ed"
    ],
    "wof:name":"Sankt Alban",
    "wof:placetype":"neighbourhood"
},
  "geometry": {"coordinates":[11.8448,48.55209],"type":"Point"}
}