{
  "type": "Feature",
  "properties": {
    "gn:admin1_code":"2",
    "gn:admin2_code":"95.0",
    "gn:admin3_code":"9572.0",
    "gn:admin4_code":"9572133.0",
    "gn:asciiname":"Obermembach",
    "gn:country_code":"DE",
    "gn:dem":327,
    "gn:feature_class":"P",
    "gn:feature_code":"PPL",
    "gn:name":"Obermembach",
    "gn:population":0,
    "gn:timezone":"Europe/Berlin",
    "iso:country":"DE",
    "wof:name":"Obermembach",
    "wof:placetype":"neighbourhood"
},
  "geometry": {"coordinates":[10.88385,49.60576],"type":"Point"}
}