{
  "type": "Feature",
  "properties": {
    "gn:admin1_code":"7.0",
    "gn:admin2_code":"57.0",
    "gn:admin3_code":"5770.0",
    "gn:admin4_code":"5770028.0",
    "gn:asciiname":"Borstel",
    "gn:country_code":"DE",
    "gn:dem":50,
    "gn:feature_class":"P",
    "gn:feature_code":"PPL",
    "gn:name":"Borstel",
    "gn:population":0,
    "gn:timezone":"Europe/Berlin",
    "iso:country":"DE",
    "name:ceb_x_preferred":[
        "Borstel"
    ],
    "name:dan_x_preferred":[
        "Borstel"
    ],
    "name:deu_x_preferred":[
        "Borstel"
    ],
    "name:epo_x_preferred":[
        "Borstel"
    ],
    "name:eus_x_preferred":[
        "Borstel"
    ],
    "name:fra_x_preferred":[
        "Borstel"
    ],
    "name:hun_x_preferred":[
        "Borstel"
    ],
    "name:ita_x_preferred":[
        "Borstel"
    ],
    "name:mkd_x_preferred":[
        "\u0411\u043e\u0440\u0441\u0442\u0435\u043b"
    ],
    "name:nds_x_preferred":[
        "Borstel"
    ],
    "name:nld_x_preferred":[
        "Borstel"
    ],
    "name:pol_x_preferred":[
        "Borstel"
    ],
    "name:rus_x_preferred":[
        "\u0411\u043e\u0440\u0441\u0442\u0435\u043b\u044c"
    ],
    "name:srp_x_preferred":[
        "\u0411\u043e\u0440\u0441\u0442\u0435\u043b"
    ],
    "name:swe_x_preferred":[
        "Borstel"
    ],
    "name:vol_x_preferred":[
        "Borstel"
    ],
    "wof:name":"Borstel",
    "wof:placetype":"neighbourhood"
},
  "geometry": {"coordinates":[9.07368,52.35694],"type":"Point"}
}