{
  "type": "Feature",
  "properties": {
    "gn:admin1_code":"7.0",
    "gn:admin2_code":"55.0",
    "gn:admin3_code":"5558.0",
    "gn:admin4_code":"5558008.0",
    "gn:asciiname":"Osthellen",
    "gn:country_code":"DE",
    "gn:dem":101,
    "gn:feature_class":"P",
    "gn:feature_code":"PPL",
    "gn:name":"Osthellen",
    "gn:population":0,
    "gn:timezone":"Europe/Berlin",
    "iso:country":"DE",
    "wof:name":"Osthellen",
    "wof:placetype":"neighbourhood"
},
  "geometry": {"coordinates":[7.25378,51.97123],"type":"Point"}
}