{
  "type": "Feature",
  "properties": {
    "iso:country":"DE",
    "name:deu_x_preferred":[
        "S\u00fcdfeldmark"
    ],
    "wof:name":"Suedfeldmark",
    "wof:placetype":"neighbourhood"
},
  "geometry": {"coordinates":[7.14868805947078,51.48863876051678],"type":"Point"}
}