{
  "type": "Feature",
  "properties": {
    "gn:admin1_code":"7",
    "gn:admin2_code":"57.0",
    "gn:admin3_code":"5758.0",
    "gn:admin4_code":"5758028.0",
    "gn:asciiname":"Stukenhoefen",
    "gn:country_code":"DE",
    "gn:dem":103,
    "gn:feature_class":"P",
    "gn:feature_code":"PPL",
    "gn:name":"Stukenh\u00f6fen",
    "gn:population":0,
    "gn:timezone":"Europe/Berlin",
    "iso:country":"DE",
    "wof:name":"Stukenhoefen",
    "wof:placetype":"neighbourhood"
},
  "geometry": {"coordinates":[8.52048,52.25608],"type":"Point"}
}