{
  "type": "Feature",
  "properties": {
    "gn:country":"DE",
    "gn:fcode":"PPL",
    "gn:population":0,
    "iso:country":"DE",
    "name:als_x_preferred":[
        "Lahr/Schwarzwald"
    ],
    "name:ara_x_preferred":[
        "\u0644\u0627\u0631"
    ],
    "name:azb_x_preferred":[
        "\u0644\u0627\u0631"
    ],
    "name:bul_x_preferred":[
        "\u041b\u0430\u0440"
    ],
    "name:ceb_x_preferred":[
        "Lahr"
    ],
    "name:deu_x_preferred":[
        "Lahr/Schwarzwald"
    ],
    "name:epo_x_preferred":[
        "Lahr"
    ],
    "name:eus_x_preferred":[
        "Lahr"
    ],
    "name:fas_x_preferred":[
        "\u0644\u0627\u0631"
    ],
    "name:fra_x_preferred":[
        "Lahr/Schwarzwald"
    ],
    "name:hrv_x_preferred":[
        "Lahr"
    ],
    "name:hun_x_preferred":[
        "Lahr"
    ],
    "name:ita_x_preferred":[
        "Lahr/Schwarzwald"
    ],
    "name:lat_x_preferred":[
        "Lahr"
    ],
    "name:lmo_x_preferred":[
        "Lahr/Schwarzwald"
    ],
    "name:msa_x_preferred":[
        "Lahr"
    ],
    "name:nld_x_preferred":[
        "Lahr/Schwarzwald"
    ],
    "name:pol_x_preferred":[
        "Lahr/Schwarzwald"
    ],
    "name:por_x_preferred":[
        "Lahr"
    ],
    "name:ron_x_preferred":[
        "Lahr/Schwarzwald"
    ],
    "name:rus_x_preferred":[
        "\u041b\u0430\u0440"
    ],
    "name:spa_x_preferred":[
        "Lahr"
    ],
    "name:srp_x_preferred":[
        "\u041b\u0430\u0440"
    ],
    "name:swa_x_preferred":[
        "Lahr"
    ],
    "name:swe_x_preferred":[
        "Lahr"
    ],
    "name:tat_x_preferred":[
        "\u041b\u0430\u0440"
    ],
    "name:tur_x_preferred":[
        "Lahr"
    ],
    "name:ukr_x_preferred":[
        "\u041b\u0430\u0440"
    ],
    "name:uzb_x_preferred":[
        "Lahr"
    ],
    "name:vol_x_preferred":[
        "Lahr/Schwarzwald"
    ],
    "name:war_x_preferred":[
        "Lahr"
    ],
    "name:zho_x_preferred":[
        "\u9ed1\u6797\u5c71\u533a\u62c9\u5c14"
    ],
    "qs_pg:aaroncc":"DE",
    "qs_pg:gn_country":"DE",
    "qs_pg:gn_fcode":"PPL",
    "qs_pg:gn_pop":0,
    "qs_pg:name":"Lahr",
    "qs_pg:name_adm0":"Deutschland",
    "qs_pg:name_adm1":"Nordrhein-Westfalen",
    "qs_pg:photos":85,
    "qs_pg:photos_1k":17,
    "qs_pg:photos_9k":1,
    "qs_pg:photos_9r":3,
    "qs_pg:photos_all":85,
    "qs_pg:photos_sr":3,
    "qs_pg:pop_sr":0,
    "qs_pg:qs_pg_placetype":"locality",
    "qs_pg:qs_pg_placetype_gp":"Town",
    "qs_pg:woe_adm0":23424829,
    "woe:adm0_id":23424829,
    "woe:name_adm0":"Deutschland",
    "woe:name_adm1":"Nordrhein-Westfalen",
    "woe:placetype":"Town",
    "wof:name":"Lahr",
    "wof:placetype":"neighbourhood"
},
  "geometry": {"coordinates":[8.13256,50.5095],"type":"Point"}
}