{
  "type": "Feature",
  "properties": {
    "gn:admin1_code":"11.0",
    "gn:admin2_code":"0.0",
    "gn:admin3_code":"12064.0",
    "gn:admin4_code":"12064044.0",
    "gn:asciiname":"Altkietz",
    "gn:country_code":"DE",
    "gn:dem":4,
    "gn:feature_class":"P",
    "gn:feature_code":"PPL",
    "gn:name":"Altkietz",
    "gn:population":0,
    "gn:timezone":"Europe/Berlin",
    "iso:country":"DE",
    "wof:name":"Altkietz",
    "wof:placetype":"neighbourhood"
},
  "geometry": {"coordinates":[14.02611,52.78859],"type":"Point"}
}