{
  "type": "Feature",
  "properties": {
    "gn:admin1_code":"12",
    "gn:admin2_code":"0.0",
    "gn:admin3_code":"13075.0",
    "gn:admin4_code":"13075031.0",
    "gn:asciiname":"Hasenkrug",
    "gn:country_code":"DE",
    "gn:dem":10,
    "gn:feature_class":"P",
    "gn:feature_code":"PPL",
    "gn:name":"Hasenkrug",
    "gn:population":0,
    "gn:timezone":"Europe/Berlin",
    "iso:country":"DE",
    "name:ceb_x_preferred":[
        "Hasenkrug"
    ],
    "name:dan_x_preferred":[
        "Hasenkrug"
    ],
    "name:deu_x_preferred":[
        "Hasenkrug"
    ],
    "name:epo_x_preferred":[
        "Hasenkrug"
    ],
    "name:eus_x_preferred":[
        "Hasenkrug"
    ],
    "name:fas_x_preferred":[
        "\u0647\u0627\u0632\u0646\u06a9\u0631\u0648\u06af"
    ],
    "name:fra_x_preferred":[
        "Hasenkrug"
    ],
    "name:hun_x_preferred":[
        "Hasenkrug"
    ],
    "name:ind_x_preferred":[
        "Hasenkrug"
    ],
    "name:ita_x_preferred":[
        "Hasenkrug"
    ],
    "name:mkd_x_preferred":[
        "\u0425\u0430\u0437\u0435\u043d\u043a\u0440\u0443\u0433"
    ],
    "name:msa_x_preferred":[
        "Hasenkrug"
    ],
    "name:nld_x_preferred":[
        "Hasenkrug"
    ],
    "name:pol_x_preferred":[
        "Hasenkrug"
    ],
    "name:por_x_preferred":[
        "Hasenkrug"
    ],
    "name:ron_x_preferred":[
        "Hasenkrug"
    ],
    "name:rus_x_preferred":[
        "\u0425\u0430\u0437\u0435\u043d\u043a\u0440\u0443\u0433"
    ],
    "name:spa_x_preferred":[
        "Hasenkrug"
    ],
    "name:srp_x_preferred":[
        "\u0425\u0430\u0437\u0435\u043d\u043a\u0440\u0443\u0433"
    ],
    "name:tur_x_preferred":[
        "Hasenkrug"
    ],
    "name:ukr_x_preferred":[
        "\u0413\u0430\u0437\u0435\u043d\u043a\u0440\u0443\u0433"
    ],
    "name:uzb_x_preferred":[
        "Hasenkrug"
    ],
    "name:vie_x_preferred":[
        "Hasenkrug"
    ],
    "name:vol_x_preferred":[
        "Hasenkrug"
    ],
    "name:war_x_preferred":[
        "Hasenkrug"
    ],
    "name:zho_x_preferred":[
        "\u54c8\u68ee\u514b\u9c81\u683c"
    ],
    "wof:name":"Hasenkrug",
    "wof:placetype":"neighbourhood"
},
  "geometry": {"coordinates":[14.0472,53.65333],"type":"Point"}
}