{
  "type": "Feature",
  "properties": {
    "gn:admin1_code":"1",
    "gn:admin2_code":"81.0",
    "gn:admin3_code":"8119.0",
    "gn:admin4_code":"8119087.0",
    "gn:asciiname":"Sinzenburg",
    "gn:country_code":"DE",
    "gn:dem":382,
    "gn:feature_class":"P",
    "gn:feature_code":"PPL",
    "gn:name":"Sinzenburg",
    "gn:population":0,
    "gn:timezone":"Europe/Berlin",
    "iso:country":"DE",
    "wof:name":"Sinzenburg",
    "wof:placetype":"neighbourhood"
},
  "geometry": {"coordinates":[9.34606,49.0001],"type":"Point"}
}