{
  "type": "Feature",
  "properties": {
    "gn:admin1_code":"5.0",
    "gn:admin2_code":"66.0",
    "gn:admin3_code":"6633.0",
    "gn:admin4_code":"6633028.0",
    "gn:asciiname":"Altenhasungen",
    "gn:country_code":"DE",
    "gn:dem":282,
    "gn:feature_class":"P",
    "gn:feature_code":"PPL",
    "gn:name":"Altenhasungen",
    "gn:population":0,
    "gn:timezone":"Europe/Berlin",
    "iso:country":"DE",
    "wof:name":"Altenhasungen",
    "wof:placetype":"neighbourhood"
},
  "geometry": {"coordinates":[9.23135,51.33908],"type":"Point"}
}