{
  "type": "Feature",
  "properties": {
    "gn:admin1_code":"2",
    "gn:admin2_code":"92.0",
    "gn:admin3_code":"9276.0",
    "gn:admin4_code":"9276111.0",
    "gn:asciiname":"Kogl",
    "gn:country_code":"DE",
    "gn:dem":673,
    "gn:feature_class":"P",
    "gn:feature_code":"PPL",
    "gn:name":"Kogl",
    "gn:population":0,
    "gn:timezone":"Europe/Berlin",
    "iso:country":"DE",
    "name:deu_x_preferred":[
        "Kogl"
    ],
    "name:ita_x_preferred":[
        "Kogl"
    ],
    "wof:name":"Kogl",
    "wof:placetype":"neighbourhood"
},
  "geometry": {"coordinates":[12.92839,48.99718],"type":"Point"}
}