{
  "type": "Feature",
  "properties": {
    "iso:country":"DE",
    "name:deu_x_preferred":[
        "Hardtberg"
    ],
    "name:eng_x_preferred":[
        "Hardtberg"
    ],
    "name:epo_x_preferred":[
        "Hardtberg"
    ],
    "name:fra_x_preferred":[
        "Hardtberg"
    ],
    "name:hye_x_preferred":[
        "\u0540\u0561\u0580\u057f\u0562\u0568\u0580\u0581"
    ],
    "name:ita_x_preferred":[
        "Hardtberg"
    ],
    "name:kat_x_preferred":[
        "\u10f0\u10d0\u10e0\u10d3\u10e2\u10d1\u10d4\u10e0\u10d2\u10d8"
    ],
    "name:nld_x_preferred":[
        "Hardtberg"
    ],
    "name:ron_x_preferred":[
        "Hardtberg"
    ],
    "name:tur_x_preferred":[
        "Hardtberg"
    ],
    "qs:gn_adm0_cc":"DE",
    "qs:gn_local":2946447,
    "qs:gn_nam_loc":"bonn",
    "qs:gn_namadm1":"07",
    "qs:local_max":6309,
    "qs:local_sum":17418,
    "qs:localhoods":14,
    "qs:name":"Hardtberg",
    "qs:name_adm0":"Deutschland",
    "qs:name_adm1":"Nordrhein-Westfalen",
    "qs:name_adm2":"Stadtkreis Bonn",
    "qs:name_lau":"Stadtteil Lengsdorf",
    "qs:name_local":"Bonn",
    "qs:photo_max":44,
    "qs:photo_sum":202,
    "qs:placetype":"Suburb",
    "qs:quad_count":38,
    "qs:woe_adm0":23424829,
    "qs:woe_adm1":2345487,
    "qs:woe_adm2":12597065,
    "qs:woe_lau":26821969,
    "qs:woe_local":640161,
    "qs:woe_ver":"7.10.0",
    "wd:wordcount":78,
    "wof:lang":[
        "ger"
    ],
    "wof:name":"Hardtberg",
    "wof:placetype":"neighbourhood"
},
  "geometry": {"coordinates":[7.054253,50.705609],"type":"Point"}
}