{
  "type": "Feature",
  "properties": {
    "gn:admin1_code":"6.0",
    "gn:admin2_code":"00",
    "gn:admin3_code":"3454.0",
    "gn:admin4_code":"3454057.0",
    "gn:asciiname":"Wieste",
    "gn:country_code":"DE",
    "gn:dem":32,
    "gn:feature_class":"P",
    "gn:feature_code":"PPL",
    "gn:name":"Wieste",
    "gn:population":0,
    "gn:timezone":"Europe/Berlin",
    "iso:country":"DE",
    "name:ceb_x_preferred":[
        "Wieste"
    ],
    "name:chv_x_preferred":[
        "\u0412\u0438\u0441\u0442\u0435"
    ],
    "name:deu_x_preferred":[
        "Wieste"
    ],
    "name:nds_x_preferred":[
        "Wiest"
    ],
    "name:rus_x_preferred":[
        "\u0412\u0438\u0441\u0442\u0435"
    ],
    "wof:name":"Wieste",
    "wof:placetype":"neighbourhood"
},
  "geometry": {"coordinates":[7.66477,52.81101999999999],"type":"Point"}
}