{
  "type": "Feature",
  "properties": {
    "iso:country":"DE",
    "name:deu_x_preferred":[
        "Pl\u00f6sen"
    ],
    "wof:name":"Ploesen",
    "wof:placetype":"neighbourhood"
},
  "geometry": {"coordinates":[12.43581056100566,51.3833552012897],"type":"Point"}
}