{
  "type": "Feature",
  "properties": {
    "gn:admin1_code":"2",
    "gn:admin2_code":"97.0",
    "gn:admin3_code":"9771.0",
    "gn:admin4_code":"9771162.0",
    "gn:asciiname":"Kuhnhausen",
    "gn:country_code":"DE",
    "gn:dem":532,
    "gn:feature_class":"P",
    "gn:feature_code":"PPL",
    "gn:name":"K\u00fchnhausen",
    "gn:population":0,
    "gn:timezone":"Europe/Berlin",
    "iso:country":"DE",
    "wof:name":"Kuhnhausen",
    "wof:placetype":"neighbourhood"
},
  "geometry": {"coordinates":[11.28013,48.452],"type":"Point"}
}