{
  "type": "Feature",
  "properties": {
    "gn:admin1_code":"14.0",
    "gn:admin2_code":"0.0",
    "gn:admin3_code":"15083.0",
    "gn:admin4_code":"15083535.0",
    "gn:asciiname":"Belsdorf",
    "gn:country_code":"DE",
    "gn:dem":124,
    "gn:feature_class":"P",
    "gn:feature_code":"PPL",
    "gn:name":"Belsdorf",
    "gn:population":0,
    "gn:timezone":"Europe/Berlin",
    "iso:country":"DE",
    "name:bak_x_preferred":[
        "\u0411\u0435\u043b\u044c\u0441\u0434\u043e\u0440\u0444"
    ],
    "name:ceb_x_preferred":[
        "Belsdorf"
    ],
    "name:deu_x_preferred":[
        "Belsdorf"
    ],
    "name:epo_x_preferred":[
        "Belsdorf"
    ],
    "name:fas_x_preferred":[
        "\u0628\u0644\u0633\u062f\u0648\u0631\u0641"
    ],
    "name:ita_x_preferred":[
        "Belsdorf"
    ],
    "name:kaz_x_preferred":[
        "\u0411\u0435\u043b\u044c\u0441\u0434\u043e\u0440\u0444"
    ],
    "name:kir_x_preferred":[
        "\u0411\u0435\u043b\u044c\u0441\u0434\u043e\u0440\u0444"
    ],
    "name:nds_x_preferred":[
        "Belsd\u00f6rp"
    ],
    "name:nds_x_variant":[
        "Belsdorp"
    ],
    "name:nld_x_preferred":[
        "Belsdorf"
    ],
    "name:ron_x_preferred":[
        "Belsdorf"
    ],
    "name:rus_x_preferred":[
        "\u0411\u0435\u043b\u044c\u0441\u0434\u043e\u0440\u0444"
    ],
    "name:uzb_x_preferred":[
        "Belsdorf"
    ],
    "name:vie_x_preferred":[
        "Belsdorf"
    ],
    "name:vol_x_preferred":[
        "Belsdorf"
    ],
    "wof:name":"Belsdorf",
    "wof:placetype":"neighbourhood"
},
  "geometry": {"coordinates":[11.15413,52.19614],"type":"Point"}
}