{
  "type": "Feature",
  "properties": {
    "gn:admin1_code":"15",
    "gn:admin2_code":"0.0",
    "gn:admin3_code":"16063.0",
    "gn:admin4_code":"16063062.0",
    "gn:asciiname":"Lenders",
    "gn:country_code":"DE",
    "gn:dem":556,
    "gn:feature_class":"P",
    "gn:feature_code":"PPL",
    "gn:name":"Lenders",
    "gn:population":0,
    "gn:timezone":"Europe/Berlin",
    "iso:country":"DE",
    "wof:name":"Lenders",
    "wof:placetype":"neighbourhood"
},
  "geometry": {"coordinates":[10.061,50.72279],"type":"Point"}
}