{
  "type": "Feature",
  "properties": {
    "gn:admin1_code":"14.0",
    "gn:admin2_code":"00",
    "gn:admin3_code":"15083.0",
    "gn:admin4_code":"15083411.0",
    "gn:asciiname":"Wolfsdorf",
    "gn:country_code":"DE",
    "gn:dem":76,
    "gn:feature_class":"P",
    "gn:feature_code":"PPL",
    "gn:name":"Wolfsdorf",
    "gn:population":0,
    "gn:timezone":"Europe/Berlin",
    "iso:country":"DE",
    "wof:name":"Wolfsdorf",
    "wof:placetype":"neighbourhood"
},
  "geometry": {"coordinates":[11.06667,52.35],"type":"Point"}
}