{
  "type": "Feature",
  "properties": {
    "gn:admin1_code":"5",
    "gn:admin2_code":"65.0",
    "gn:admin3_code":"6533.0",
    "gn:admin4_code":"6533005.0",
    "gn:asciiname":"Waldmannshausen",
    "gn:country_code":"DE",
    "gn:dem":207,
    "gn:feature_class":"P",
    "gn:feature_code":"PPL",
    "gn:name":"Waldmannshausen",
    "gn:population":0,
    "gn:timezone":"Europe/Berlin",
    "iso:country":"DE",
    "wof:name":"Waldmannshausen",
    "wof:placetype":"neighbourhood"
},
  "geometry": {"coordinates":[8.05533,50.51359],"type":"Point"}
}