{
  "type": "Feature",
  "properties": {
    "gn:admin1_code":"5",
    "gn:admin2_code":"65.0",
    "gn:admin3_code":"6531.0",
    "gn:admin4_code":"6531011.0",
    "gn:asciiname":"Langsdorf",
    "gn:country_code":"DE",
    "gn:dem":166,
    "gn:feature_class":"P",
    "gn:feature_code":"PPL",
    "gn:name":"Langsdorf",
    "gn:population":0,
    "gn:timezone":"Europe/Berlin",
    "iso:country":"DE",
    "name:deu_x_preferred":[
        "Langsdorf"
    ],
    "name:nds_x_preferred":[
        "Langsdorf"
    ],
    "name:nld_x_preferred":[
        "Langsdorf"
    ],
    "name:pol_x_preferred":[
        "Langsdorff"
    ],
    "name:rus_x_preferred":[
        "\u041b\u0430\u043d\u0433\u0441\u0434\u043e\u0440\u0444"
    ],
    "name:swe_x_preferred":[
        "Langsdorf"
    ],
    "wof:name":"Langsdorf",
    "wof:placetype":"neighbourhood"
},
  "geometry": {"coordinates":[8.85464,50.49399],"type":"Point"}
}