{
  "type": "Feature",
  "properties": {
    "gn:admin1_code":"12.0",
    "gn:admin2_code":"0.0",
    "gn:admin3_code":"13073.0",
    "gn:admin4_code":"13073089.0",
    "gn:asciiname":"Boltenhagen",
    "gn:cc2":"DE",
    "gn:country_code":"DE",
    "gn:dem":15,
    "gn:feature_class":"P",
    "gn:feature_code":"PPL",
    "gn:name":"Boltenhagen",
    "gn:population":0,
    "gn:timezone":"Europe/Berlin",
    "iso:country":"DE",
    "name:ceb_x_preferred":[
        "Boltenhagen"
    ],
    "name:deu_x_preferred":[
        "Boltenhagen"
    ],
    "name:epo_x_preferred":[
        "Boltenhagen"
    ],
    "name:fas_x_preferred":[
        "\u0628\u0648\u0644\u062a\u0646\u0647\u0627\u06af\u0646"
    ],
    "name:fra_x_preferred":[
        "Boltenhagen"
    ],
    "name:hun_x_preferred":[
        "Boltenhagen"
    ],
    "name:ita_x_preferred":[
        "Boltenhagen"
    ],
    "name:lit_x_preferred":[
        "Boltenhagenas"
    ],
    "name:mkd_x_preferred":[
        "\u0411\u043e\u043b\u0442\u0435\u043d\u0445\u0430\u0433\u0435\u043d"
    ],
    "name:msa_x_preferred":[
        "Boltenhagen"
    ],
    "name:nld_x_preferred":[
        "Boltenhagen"
    ],
    "name:pol_x_preferred":[
        "Boltenhagen"
    ],
    "name:por_x_preferred":[
        "Boltenhagen"
    ],
    "name:ron_x_preferred":[
        "Boltenhagen"
    ],
    "name:rus_x_preferred":[
        "\u0411\u043e\u043b\u044c\u0442\u0435\u043d\u0445\u0430\u0433\u0435\u043d"
    ],
    "name:spa_x_preferred":[
        "Boltenhagen"
    ],
    "name:srp_x_preferred":[
        "\u0411\u043e\u043b\u0442\u0435\u043d\u0445\u0430\u0433\u0435\u043d"
    ],
    "name:swe_x_preferred":[
        "Boltenhagen"
    ],
    "name:ukr_x_preferred":[
        "\u0411\u043e\u043b\u044c\u0442\u0435\u043d\u0433\u0430\u0433\u0435\u043d"
    ],
    "name:und_x_variant":[
        "Adlig Boltenhagen",
        "Adelig Boltenhagen",
        "Allodial Boltenhagen"
    ],
    "name:uzb_x_preferred":[
        "Boltenhagen"
    ],
    "name:vie_x_preferred":[
        "Boltenhagen"
    ],
    "name:vol_x_preferred":[
        "Boltenhagen"
    ],
    "name:war_x_preferred":[
        "Boltenhagen"
    ],
    "name:zho_x_preferred":[
        "\u535a\u5c14\u6ed5\u54c8\u6839"
    ],
    "wof:name":"Boltenhagen",
    "wof:placetype":"neighbourhood"
},
  "geometry": {"coordinates":[13.07776,54.07445],"type":"Point"}
}