{
  "type": "Feature",
  "properties": {
    "gn:admin1_code":"15",
    "gn:admin2_code":"0.0",
    "gn:admin3_code":"16073.0",
    "gn:admin4_code":"16073105.0",
    "gn:asciiname":"Teichroeda",
    "gn:country_code":"DE",
    "gn:dem":251,
    "gn:feature_class":"P",
    "gn:feature_code":"PPL",
    "gn:name":"Teichr\u00f6da",
    "gn:population":0,
    "gn:timezone":"Europe/Berlin",
    "iso:country":"DE",
    "wof:name":"Teichroeda",
    "wof:placetype":"neighbourhood"
},
  "geometry": {"coordinates":[11.30473,50.75596],"type":"Point"}
}