{
  "type": "Feature",
  "properties": {
    "gn:admin1_code":"1.0",
    "gn:admin2_code":"83.0",
    "gn:admin3_code":"8316.0",
    "gn:admin4_code":"8316056.0",
    "gn:asciiname":"Batzenhausle",
    "gn:country_code":"DE",
    "gn:dem":257,
    "gn:feature_class":"P",
    "gn:feature_code":"PPL",
    "gn:name":"Batzenh\u00e4usle",
    "gn:population":0,
    "gn:timezone":"Europe/Berlin",
    "iso:country":"DE",
    "wof:name":"Batzenhausle",
    "wof:placetype":"neighbourhood"
},
  "geometry": {"coordinates":[7.937,48.08712],"type":"Point"}
}