{
  "type": "Feature",
  "properties": {
    "gn:gn_country":"DE",
    "gn:gn_fcode":"PPLX",
    "gn:gn_pop":0,
    "iso:country":"DE",
    "name:ceb_x_preferred":[
        "Altstadt"
    ],
    "name:deu_x_preferred":[
        "Frankfurt-Altstadt"
    ],
    "name:eng_x_preferred":[
        "Altstadt"
    ],
    "name:fas_x_preferred":[
        "\u0627\u0644\u062a\u0633\u062a\u0627\u062f"
    ],
    "name:fra_x_preferred":[
        "Altstadt"
    ],
    "name:nld_x_preferred":[
        "Frankfurt-Altstadt"
    ],
    "name:nob_x_preferred":[
        "Frankfurt-Altstadt"
    ],
    "name:nor_x_preferred":[
        "Frankfurt-Altstadt"
    ],
    "name:pol_x_preferred":[
        "Altstadt"
    ],
    "name:zho_x_preferred":[
        "\u6cd5\u5170\u514b\u798f\u8001\u57ce"
    ],
    "qs_pg:aaroncc":"DE",
    "qs_pg:gn_country":"DE",
    "qs_pg:gn_fcode":"PPLX",
    "qs_pg:gn_pop":0,
    "qs_pg:name":"Stadtteil Altstadt",
    "qs_pg:name_adm0":"Deutschland",
    "qs_pg:name_adm1":"Hessen",
    "qs_pg:photos_9k":174,
    "qs_pg:photos_9r":23,
    "qs_pg:photos_all":39292,
    "qs_pg:photos_sr":0,
    "qs_pg:pop_sr":0,
    "qs_pg:qs_pg_placetype":"neighbourhood",
    "qs_pg:qs_pg_placetype_gp":"LocalAdmin",
    "qs_pg:woe_adm0":23424829,
    "woe:adm0_id":23424829,
    "woe:name_adm0":"Deutschland",
    "woe:name_adm1":"Hessen",
    "woe:placetype":"LocalAdmin",
    "wof:name":"Stadtteil Altstadt",
    "wof:placetype":"neighbourhood"
},
  "geometry": {"coordinates":[8.68255,50.11029],"type":"Point"}
}