{
  "type": "Feature",
  "properties": {
    "gn:admin1_code":"1.0",
    "gn:admin2_code":"82.0",
    "gn:admin3_code":"8216.0",
    "gn:admin4_code":"8216041.0",
    "gn:asciiname":"Breithurst",
    "gn:country_code":"DE",
    "gn:dem":130,
    "gn:feature_class":"P",
    "gn:feature_code":"PPL",
    "gn:name":"Breithurst",
    "gn:population":0,
    "gn:timezone":"Europe/Berlin",
    "iso:country":"DE",
    "wof:name":"Breithurst",
    "wof:placetype":"neighbourhood"
},
  "geometry": {"coordinates":[8.07942,48.68435],"type":"Point"}
}