{
  "type": "Feature",
  "properties": {
    "gn:admin1_code":"12",
    "gn:admin2_code":"0.0",
    "gn:admin3_code":"13071.0",
    "gn:admin4_code":"13071033.0",
    "gn:asciiname":"Luettenhagen",
    "gn:country_code":"DE",
    "gn:dem":126,
    "gn:feature_class":"P",
    "gn:feature_code":"PPL",
    "gn:name":"L\u00fcttenhagen",
    "gn:population":0,
    "gn:timezone":"Europe/Berlin",
    "iso:country":"DE",
    "wof:name":"Luettenhagen",
    "wof:placetype":"neighbourhood"
},
  "geometry": {"coordinates":[13.38591,53.33859],"type":"Point"}
}