{
  "type": "Feature",
  "properties": {
    "gn:admin1_code":"2",
    "gn:admin2_code":"92.0",
    "gn:admin3_code":"9275.0",
    "gn:admin4_code":"9275143.0",
    "gn:asciiname":"Neugertsham",
    "gn:country_code":"DE",
    "gn:dem":373,
    "gn:feature_class":"P",
    "gn:feature_code":"PPL",
    "gn:name":"Neugertsham",
    "gn:population":0,
    "gn:timezone":"Europe/Berlin",
    "iso:country":"DE",
    "wof:name":"Neugertsham",
    "wof:placetype":"neighbourhood"
},
  "geometry": {"coordinates":[13.15312,48.3908],"type":"Point"}
}