{
  "type": "Feature",
  "properties": {
    "iso:country":"DE",
    "name:deu_x_preferred":[
        "Herzogenried"
    ],
    "name:eng_x_preferred":[
        "Herzogenried"
    ],
    "wof:name":"Herzogenried",
    "wof:placetype":"neighbourhood"
},
  "geometry": {"coordinates":[8.47744526207703,49.50643603023838],"type":"Point"}
}