{
  "type": "Feature",
  "properties": {
    "gn:admin1_code":"2",
    "gn:admin2_code":"94.0",
    "gn:admin3_code":"9471.0",
    "gn:admin4_code":"9471208.0",
    "gn:asciiname":"Feigendorf",
    "gn:country_code":"DE",
    "gn:dem":281,
    "gn:feature_class":"P",
    "gn:feature_code":"PPL",
    "gn:name":"Feigendorf",
    "gn:population":0,
    "gn:timezone":"Europe/Berlin",
    "iso:country":"DE",
    "wof:name":"Feigendorf",
    "wof:placetype":"neighbourhood"
},
  "geometry": {"coordinates":[10.74734,49.88721],"type":"Point"}
}