{
  "type": "Feature",
  "properties": {
    "gn:admin1_code":"2",
    "gn:admin2_code":"92.0",
    "gn:admin3_code":"9272.0",
    "gn:admin4_code":"9272128.0",
    "gn:asciiname":"Lungdorf",
    "gn:country_code":"DE",
    "gn:dem":596,
    "gn:feature_class":"P",
    "gn:feature_code":"PPL",
    "gn:name":"Lungdorf",
    "gn:population":0,
    "gn:timezone":"Europe/Berlin",
    "iso:country":"DE",
    "wof:name":"Lungdorf",
    "wof:placetype":"neighbourhood"
},
  "geometry": {"coordinates":[13.27217,48.86663],"type":"Point"}
}