{
  "type": "Feature",
  "properties": {
    "gn:admin1_code":"13",
    "gn:admin2_code":"0.0",
    "gn:admin3_code":"14521.0",
    "gn:admin4_code":"14521310.0",
    "gn:asciiname":"Seifersdorf",
    "gn:country_code":"DE",
    "gn:dem":397,
    "gn:feature_class":"P",
    "gn:feature_code":"PPL",
    "gn:name":"Seifersdorf",
    "gn:population":0,
    "gn:timezone":"Europe/Berlin",
    "iso:country":"DE",
    "name:und_x_variant":[
        "Leukersdorf-Seifersdorf",
        "Seifersdorf"
    ],
    "wof:name":"Seifersdorf",
    "wof:placetype":"neighbourhood"
},
  "geometry": {"coordinates":[12.79876,50.76269],"type":"Point"}
}