{
  "type": "Feature",
  "properties": {
    "gn:admin1_code":"2.0",
    "gn:admin2_code":"95.0",
    "gn:admin3_code":"9571.0",
    "gn:admin4_code":"9571145.0",
    "gn:asciiname":"Aichau",
    "gn:country_code":"DE",
    "gn:dem":472,
    "gn:feature_class":"P",
    "gn:feature_code":"PPL",
    "gn:name":"Aichau",
    "gn:population":0,
    "gn:timezone":"Europe/Berlin",
    "iso:country":"DE",
    "wof:name":"Aichau",
    "wof:placetype":"neighbourhood"
},
  "geometry": {"coordinates":[10.42393,49.18547],"type":"Point"}
}