{
  "type": "Feature",
  "properties": {
    "gn:admin1_code":"8",
    "gn:admin2_code":"0.0",
    "gn:admin3_code":"7131.0",
    "gn:admin4_code":"7131077.0",
    "gn:asciiname":"Loehndorf",
    "gn:country_code":"DE",
    "gn:dem":169,
    "gn:feature_class":"P",
    "gn:feature_code":"PPL",
    "gn:name":"L\u00f6hndorf",
    "gn:population":0,
    "gn:timezone":"Europe/Berlin",
    "iso:country":"DE",
    "wof:name":"Loehndorf",
    "wof:placetype":"neighbourhood"
},
  "geometry": {"coordinates":[7.20167,50.52968],"type":"Point"}
}