{
  "type": "Feature",
  "properties": {
    "gn:admin1_code":"2",
    "gn:admin2_code":"94.0",
    "gn:admin3_code":"9479.0",
    "gn:admin4_code":"9479152.0",
    "gn:asciiname":"Unterweissenbach",
    "gn:country_code":"DE",
    "gn:dem":529,
    "gn:feature_class":"P",
    "gn:feature_code":"PPL",
    "gn:name":"Unterwei\u00dfenbach",
    "gn:population":0,
    "gn:timezone":"Europe/Berlin",
    "iso:country":"DE",
    "wof:name":"Unterweissenbach",
    "wof:placetype":"neighbourhood"
},
  "geometry": {"coordinates":[12.10378,50.15885],"type":"Point"}
}