{
  "type": "Feature",
  "properties": {
    "gn:admin1_code":"13",
    "gn:admin2_code":"0.0",
    "gn:admin3_code":"14522.0",
    "gn:admin4_code":"14522140.0",
    "gn:asciiname":"Neue Sorge",
    "gn:country_code":"DE",
    "gn:dem":296,
    "gn:feature_class":"P",
    "gn:feature_code":"PPL",
    "gn:name":"Neue Sorge",
    "gn:population":0,
    "gn:timezone":"Europe/Berlin",
    "iso:country":"DE",
    "name:deu_x_preferred":[
        "Neue Sorge"
    ],
    "name:pol_x_preferred":[
        "Neue Sorge"
    ],
    "wof:name":"Neue Sorge",
    "wof:placetype":"neighbourhood"
},
  "geometry": {"coordinates":[13.0703,50.84855],"type":"Point"}
}