{
  "type": "Feature",
  "properties": {
    "gn:admin1_code":"6.0",
    "gn:admin2_code":"0.0",
    "gn:admin3_code":"3252.0",
    "gn:admin4_code":"3252003.0",
    "gn:asciiname":"Baarsen",
    "gn:country_code":"DE",
    "gn:dem":342,
    "gn:feature_class":"P",
    "gn:feature_code":"PPL",
    "gn:name":"Baarsen",
    "gn:population":0,
    "gn:timezone":"Europe/Berlin",
    "iso:country":"DE",
    "wof:name":"Baarsen",
    "wof:placetype":"neighbourhood"
},
  "geometry": {"coordinates":[9.32224,51.94522],"type":"Point"}
}