{
  "type": "Feature",
  "properties": {
    "gn:admin1_code":"2",
    "gn:admin2_code":"92.0",
    "gn:admin3_code":"9276.0",
    "gn:admin4_code":"9276134.0",
    "gn:asciiname":"Tradweging",
    "gn:country_code":"DE",
    "gn:dem":660,
    "gn:feature_class":"P",
    "gn:feature_code":"PPL",
    "gn:name":"Tradweging",
    "gn:population":0,
    "gn:timezone":"Europe/Berlin",
    "iso:country":"DE",
    "wof:name":"Tradweging",
    "wof:placetype":"neighbourhood"
},
  "geometry": {"coordinates":[12.9517,49.01839],"type":"Point"}
}