{
  "type": "Feature",
  "properties": {
    "gn:admin1_code":"5",
    "gn:admin2_code":"64.0",
    "gn:admin3_code":"6431.0",
    "gn:admin4_code":"6431002.0",
    "gn:asciiname":"Langwaden",
    "gn:country_code":"DE",
    "gn:dem":95,
    "gn:feature_class":"P",
    "gn:feature_code":"PPL",
    "gn:name":"Langwaden",
    "gn:population":0,
    "gn:timezone":"Europe/Berlin",
    "iso:country":"DE",
    "wof:name":"Langwaden",
    "wof:placetype":"neighbourhood"
},
  "geometry": {"coordinates":[8.55195,49.71917],"type":"Point"}
}