{
  "type": "Feature",
  "properties": {
    "gn:admin1_code":"11",
    "gn:admin2_code":"0.0",
    "gn:admin3_code":"12068.0",
    "gn:admin4_code":"12068117.0",
    "gn:asciiname":"Langen",
    "gn:country_code":"DE",
    "gn:dem":38,
    "gn:feature_class":"P",
    "gn:feature_code":"PPL",
    "gn:name":"Langen",
    "gn:population":0,
    "gn:timezone":"Europe/Berlin",
    "iso:country":"DE",
    "name:ceb_x_preferred":[
        "Langen"
    ],
    "name:deu_x_preferred":[
        "Langen"
    ],
    "name:epo_x_preferred":[
        "Langen"
    ],
    "name:eus_x_preferred":[
        "Langen"
    ],
    "name:fas_x_preferred":[
        "\u0644\u0627\u0646\u06af\u0646"
    ],
    "name:fra_x_preferred":[
        "Langen"
    ],
    "name:hun_x_preferred":[
        "Langen"
    ],
    "name:ita_x_preferred":[
        "Langen"
    ],
    "name:jpn_x_preferred":[
        "\u30e9\u30f3\u30b2\u30f3"
    ],
    "name:nds_x_preferred":[
        "Langen"
    ],
    "name:nld_x_preferred":[
        "Langen"
    ],
    "name:nor_x_preferred":[
        "Langen"
    ],
    "name:pol_x_preferred":[
        "Langen"
    ],
    "name:rus_x_preferred":[
        "\u041b\u0430\u043d\u0433\u0435\u043d"
    ],
    "name:spa_x_preferred":[
        "Langen"
    ],
    "name:srp_x_preferred":[
        "\u041b\u0430\u043d\u0433\u0435\u043d"
    ],
    "name:swe_x_preferred":[
        "Langen"
    ],
    "name:vol_x_preferred":[
        "Langen"
    ],
    "wof:name":"Langen",
    "wof:placetype":"neighbourhood"
},
  "geometry": {"coordinates":[12.80663,52.8399],"type":"Point"}
}