{
  "type": "Feature",
  "properties": {
    "gn:gn_country":"DE",
    "gn:gn_fcode":"PPLA4",
    "gn:gn_pop":972,
    "gn:population":972,
    "iso:country":"DE",
    "name:arm_x_preferred":[
        "\u0532\u0578\u0582\u0576\u0564\u0578\u0580\u0586"
    ],
    "name:baq_x_preferred":[
        "Bundorf"
    ],
    "name:dan_x_preferred":[
        "Bundorf"
    ],
    "name:dut_x_preferred":[
        "Bundorf"
    ],
    "name:eng_x_preferred":[
        "Bundorf"
    ],
    "name:epo_x_preferred":[
        "Bundorf"
    ],
    "name:fre_x_preferred":[
        "Bundorf"
    ],
    "name:ger_x_preferred":[
        "Bundorf"
    ],
    "name:hun_x_preferred":[
        "Bundorf"
    ],
    "name:hye_x_preferred":[
        "\u0532\u0578\u0582\u0576\u0564\u0578\u0580\u0586"
    ],
    "name:ind_x_preferred":[
        "Bundorf"
    ],
    "name:ita_x_preferred":[
        "Bundorf"
    ],
    "name:kaz_x_preferred":[
        "\u0411\u0443\u043d\u0434\u043e\u0440\u0444"
    ],
    "name:kir_x_preferred":[
        "\u0411\u0443\u043d\u0434\u043e\u0440\u0444"
    ],
    "name:lat_x_preferred":[
        "Bundorf"
    ],
    "name:lmo_x_preferred":[
        "Bundorf"
    ],
    "name:may_x_preferred":[
        "Bundorf"
    ],
    "name:nan_x_preferred":[
        "Bundorf"
    ],
    "name:pol_x_preferred":[
        "Bundorf"
    ],
    "name:por_x_preferred":[
        "Bundorf"
    ],
    "name:rum_x_preferred":[
        "Bundorf"
    ],
    "name:rus_x_preferred":[
        "\u0411\u0443\u043d\u0434\u043e\u0440\u0444"
    ],
    "name:srp_x_preferred":[
        "\u0411\u0443\u043d\u0434\u043e\u0440\u0444"
    ],
    "name:ukr_x_preferred":[
        "\u0411\u0443\u043d\u0434\u043e\u0440\u0444"
    ],
    "name:uzb_x_preferred":[
        "Bundorf"
    ],
    "name:vie_x_preferred":[
        "Bundorf"
    ],
    "name:vol_x_preferred":[
        "Bundorf"
    ],
    "name:war_x_preferred":[
        "Bundorf"
    ],
    "qs_pg:aaroncc":"DE",
    "qs_pg:gn_country":"DE",
    "qs_pg:gn_fcode":"PPLA4",
    "qs_pg:gn_pop":972,
    "qs_pg:name":"Bundorf",
    "qs_pg:photos_9r":0,
    "qs_pg:photos_sr":0,
    "qs_pg:pop_sr":2,
    "qs_pg:qs_pg_placetype":"locality",
    "wof:name":"Bundorf",
    "wof:placetype":"locality",
    "wof:population":972
},
  "geometry": {"coordinates":[10.51667,50.21667],"type":"Point"}
}