{
  "type": "Feature",
  "properties": {
    "gn:admin1_code":"2",
    "gn:admin2_code":"94.0",
    "gn:admin3_code":"9475.0",
    "gn:admin4_code":"9475189.0",
    "gn:asciiname":"Grosslosnitz",
    "gn:country_code":"DE",
    "gn:dem":565,
    "gn:feature_class":"P",
    "gn:feature_code":"PPL",
    "gn:name":"Gro\u00dflosnitz",
    "gn:population":0,
    "gn:timezone":"Europe/Berlin",
    "iso:country":"DE",
    "name:und_x_variant":[
        "Gro\u00df Lossnitz",
        "Gro\u00dflosnitz"
    ],
    "wof:name":"Grosslosnitz",
    "wof:placetype":"neighbourhood"
},
  "geometry": {"coordinates":[11.80425,50.15363],"type":"Point"}
}