{
  "type": "Feature",
  "properties": {
    "iso:country":"DE",
    "wof:name":"Frohnhausen",
    "wof:placetype":"neighbourhood"
},
  "geometry": {"coordinates":[6.97169079069131,51.4464479343062],"type":"Point"}
}