{
  "type": "Feature",
  "properties": {
    "gn:admin1_code":"8.0",
    "gn:admin2_code":"0.0",
    "gn:admin3_code":"7143.0",
    "gn:admin4_code":"7143277.0",
    "gn:asciiname":"Bach",
    "gn:country_code":"DE",
    "gn:dem":497,
    "gn:feature_class":"P",
    "gn:feature_code":"PPL",
    "gn:name":"Bach",
    "gn:population":0,
    "gn:timezone":"Europe/Berlin",
    "iso:country":"DE",
    "wof:name":"Bach",
    "wof:placetype":"neighbourhood"
},
  "geometry": {"coordinates":[7.99036,50.65645],"type":"Point"}
}