{
  "type": "Feature",
  "properties": {
    "gn:admin1_code":"2",
    "gn:admin2_code":"92.0",
    "gn:admin3_code":"9272.0",
    "gn:admin4_code":"9272141.0",
    "gn:asciiname":"Lobenstein",
    "gn:country_code":"DE",
    "gn:dem":501,
    "gn:feature_class":"P",
    "gn:feature_code":"PPL",
    "gn:name":"Lobenstein",
    "gn:population":0,
    "gn:timezone":"Europe/Berlin",
    "iso:country":"DE",
    "name:ceb_x_preferred":[
        "Lobenstein"
    ],
    "name:deu_x_preferred":[
        "Lobenstein"
    ],
    "name:swe_x_preferred":[
        "Lobenstein"
    ],
    "wof:name":"Lobenstein",
    "wof:placetype":"neighbourhood"
},
  "geometry": {"coordinates":[13.52644,48.7677],"type":"Point"}
}