{
  "type": "Feature",
  "properties": {
    "gn:admin1_code":"2",
    "gn:admin2_code":"94.0",
    "gn:admin3_code":"9477.0",
    "gn:admin4_code":"9477157.0",
    "gn:asciiname":"Felkendorf",
    "gn:country_code":"DE",
    "gn:dem":430,
    "gn:feature_class":"P",
    "gn:feature_code":"PPL",
    "gn:name":"Felkendorf",
    "gn:population":0,
    "gn:timezone":"Europe/Berlin",
    "iso:country":"DE",
    "wof:name":"Felkendorf",
    "wof:placetype":"neighbourhood"
},
  "geometry": {"coordinates":[11.41296,49.99825],"type":"Point"}
}