{
  "type": "Feature",
  "properties": {
    "gn:admin1_code":"2",
    "gn:admin2_code":"97.0",
    "gn:admin3_code":"9780.0",
    "gn:admin4_code":"9780112.0",
    "gn:asciiname":"Strobels",
    "gn:country_code":"DE",
    "gn:dem":753,
    "gn:feature_class":"P",
    "gn:feature_code":"PPL",
    "gn:name":"Strobels",
    "gn:population":0,
    "gn:timezone":"Europe/Berlin",
    "iso:country":"DE",
    "wof:name":"Strobels",
    "wof:placetype":"neighbourhood"
},
  "geometry": {"coordinates":[10.20048,47.81308],"type":"Point"}
}