{
  "type": "Feature",
  "properties": {
    "gn:admin1_code":"7.0",
    "gn:admin2_code":"59.0",
    "gn:admin3_code":"5962.0",
    "gn:admin4_code":"5962016.0",
    "gn:asciiname":"Apricke",
    "gn:country_code":"DE",
    "gn:dem":313,
    "gn:feature_class":"P",
    "gn:feature_code":"PPL",
    "gn:name":"Apricke",
    "gn:population":0,
    "gn:timezone":"Europe/Berlin",
    "iso:country":"DE",
    "wof:name":"Apricke",
    "wof:placetype":"neighbourhood"
},
  "geometry": {"coordinates":[7.80962,51.39102000000001],"type":"Point"}
}