{
  "type": "Feature",
  "properties": {
    "gn:admin1_code":"2",
    "gn:admin2_code":"91.0",
    "gn:admin3_code":"9177.0",
    "gn:admin4_code":"9177137.0",
    "gn:asciiname":"Gansberg",
    "gn:country_code":"DE",
    "gn:dem":569,
    "gn:feature_class":"P",
    "gn:feature_code":"PPL",
    "gn:name":"G\u00e4nsberg",
    "gn:population":0,
    "gn:timezone":"Europe/Berlin",
    "iso:country":"DE",
    "wof:name":"Gansberg",
    "wof:placetype":"neighbourhood"
},
  "geometry": {"coordinates":[12.18785,48.22103],"type":"Point"}
}