{
  "type": "Feature",
  "properties": {
    "gn:admin1_code":"8",
    "gn:admin2_code":"0.0",
    "gn:admin3_code":"7313.0",
    "gn:admin4_code":"7313000.0",
    "gn:asciiname":"Moerzheim",
    "gn:country_code":"DE",
    "gn:dem":199,
    "gn:feature_class":"P",
    "gn:feature_code":"PPL",
    "gn:name":"M\u00f6rzheim",
    "gn:population":0,
    "gn:timezone":"Europe/Berlin",
    "iso:country":"DE",
    "wof:name":"Moerzheim",
    "wof:placetype":"neighbourhood"
},
  "geometry": {"coordinates":[8.07664,49.16792],"type":"Point"}
}