{
  "type": "Feature",
  "properties": {
    "iso:country":"DE",
    "name:afr_x_preferred":[
        "Dorp"
    ],
    "name:deu_x_preferred":[
        "Dorp"
    ],
    "name:fra_x_preferred":[
        "Dorp"
    ],
    "name:nds_x_preferred":[
        "Dorp"
    ],
    "name:nld_x_preferred":[
        "Dorp"
    ],
    "name:unk_x_variant":[
        "Dorp"
    ],
    "qs:gn_adm0_cc":"DE",
    "qs:gn_fcode":"PPL",
    "qs:gn_local":2934246,
    "qs:gn_namadm1":"07",
    "qs:gn_name":"Dorp",
    "qs:local_max":9824,
    "qs:local_sum":24688,
    "qs:localhoods":8,
    "qs:name":"Dorp",
    "qs:name_adm0":"Deutschland",
    "qs:name_adm1":"Nordrhein-Westfalen",
    "qs:name_adm2":"Stadtkreis D\u00fcsseldorf",
    "qs:name_lau":"Stadtteil Hubbelrath",
    "qs:name_local":"D\u00fcsseldorf",
    "qs:photo_max":7,
    "qs:photo_sum":84,
    "qs:placetype":"Suburb",
    "qs:quad_count":32,
    "qs:woe_adm0":23424829,
    "qs:woe_adm1":2345487,
    "qs:woe_adm2":12596700,
    "qs:woe_lau":26822292,
    "qs:woe_local":646099,
    "qs:woe_ver":"7.10.0",
    "wd:wordcount":31,
    "wof:lang":[
        "ger"
    ],
    "wof:name":"Dorp",
    "wof:placetype":"neighbourhood"
},
  "geometry": {"coordinates":[6.922388,51.256067],"type":"Point"}
}