{
  "type": "Feature",
  "properties": {
    "gn:admin1_code":"6",
    "gn:admin2_code":"0.0",
    "gn:admin3_code":"3158.0",
    "gn:admin4_code":"3158031.0",
    "gn:asciiname":"Watzum",
    "gn:country_code":"DE",
    "gn:dem":111,
    "gn:feature_class":"P",
    "gn:feature_code":"PPL",
    "gn:name":"Watzum",
    "gn:population":0,
    "gn:timezone":"Europe/Berlin",
    "iso:country":"DE",
    "wof:name":"Watzum",
    "wof:placetype":"neighbourhood"
},
  "geometry": {"coordinates":[10.78119,52.1141],"type":"Point"}
}