{
  "type": "Feature",
  "properties": {
    "gn:admin1_code":"6",
    "gn:admin2_code":"0.0",
    "gn:admin3_code":"3459.0",
    "gn:admin4_code":"3459012.0",
    "gn:asciiname":"Schelenburg",
    "gn:country_code":"DE",
    "gn:dem":100,
    "gn:feature_class":"P",
    "gn:feature_code":"PPL",
    "gn:name":"Schelenburg",
    "gn:population":0,
    "gn:timezone":"Europe/Berlin",
    "iso:country":"DE",
    "name:deu_x_preferred":[
        "Schelenburg"
    ],
    "wof:name":"Schelenburg",
    "wof:placetype":"neighbourhood"
},
  "geometry": {"coordinates":[8.23333,52.28333],"type":"Point"}
}