{
  "type": "Feature",
  "properties": {
    "gn:admin1_code":"2",
    "gn:admin2_code":"91.0",
    "gn:admin3_code":"9174.0",
    "gn:admin4_code":"9174115.0",
    "gn:asciiname":"Pullhausen",
    "gn:country_code":"DE",
    "gn:dem":506,
    "gn:feature_class":"P",
    "gn:feature_code":"PPL",
    "gn:name":"Pullhausen",
    "gn:population":0,
    "gn:timezone":"Europe/Berlin",
    "iso:country":"DE",
    "wof:name":"Pullhausen",
    "wof:placetype":"neighbourhood"
},
  "geometry": {"coordinates":[11.4048,48.28482],"type":"Point"}
}