{
  "type": "Feature",
  "properties": {
    "gn:country":"DE",
    "gn:fcode":"PPL",
    "gn:population":706,
    "iso:country":"DE",
    "name:bak_x_preferred":[
        "\u0424\u0438\u0448\u0431\u0435\u043a"
    ],
    "name:ceb_x_preferred":[
        "Fischbeck"
    ],
    "name:che_x_preferred":[
        "\u0424\u0438\u0448\u0431\u0435\u043a"
    ],
    "name:deu_x_preferred":[
        "Fischbeck"
    ],
    "name:eng_x_preferred":[
        "Fischbeck"
    ],
    "name:epo_x_preferred":[
        "Fischbeck"
    ],
    "name:fas_x_preferred":[
        "\u0641\u06cc\u0634\u0628\u06a9"
    ],
    "name:fra_x_preferred":[
        "Fischbeck"
    ],
    "name:gle_x_preferred":[
        "Fischbeck"
    ],
    "name:ita_x_preferred":[
        "Fischbeck"
    ],
    "name:kaz_x_preferred":[
        "\u0424\u0438\u0448\u0431\u0435\u043a"
    ],
    "name:kir_x_preferred":[
        "\u0424\u0438\u0448\u0431\u0435\u043a"
    ],
    "name:mkd_x_preferred":[
        "\u0424\u0438\u0448\u0431\u0435\u043a"
    ],
    "name:nld_x_preferred":[
        "Fischbeck"
    ],
    "name:ron_x_preferred":[
        "Fischbeck"
    ],
    "name:rus_x_preferred":[
        "\u0424\u0438\u0448\u0431\u0435\u043a"
    ],
    "name:swe_x_preferred":[
        "Fischbeck"
    ],
    "name:tat_x_preferred":[
        "\u0424\u0438\u0448\u0431\u0435\u043a"
    ],
    "name:uzb_x_preferred":[
        "Fischbeck"
    ],
    "name:vie_x_preferred":[
        "Fischbeck"
    ],
    "name:vol_x_preferred":[
        "Fischbeck"
    ],
    "name:zho_x_preferred":[
        "\u8d39\u65bd\u8d1d\u514b"
    ],
    "qs_pg:aaroncc":"DE",
    "qs_pg:gn_country":"DE",
    "qs_pg:gn_fcode":"PPL",
    "qs_pg:gn_pop":706,
    "qs_pg:name":"Fischbeck",
    "qs_pg:name_adm0":"Deutschland",
    "qs_pg:name_adm1":"Sachsen-Anhalt",
    "qs_pg:photos_9r":0,
    "qs_pg:photos_sr":0,
    "qs_pg:pop_sr":2,
    "qs_pg:qs_pg_placetype":"locality",
    "qs_pg:qs_pg_placetype_gp":"Town",
    "qs_pg:woe_adm0":23424829,
    "woe:adm0_id":23424829,
    "woe:name_adm0":"Deutschland",
    "woe:name_adm1":"Sachsen-Anhalt",
    "woe:placetype":"Town",
    "wof:name":"Fischbeck",
    "wof:placetype":"neighbourhood",
    "wof:population":706
},
  "geometry": {"coordinates":[12.01677,52.53986],"type":"Point"}
}