{
  "type": "Feature",
  "properties": {
    "gn:admin1_code":"6",
    "gn:admin2_code":"0.0",
    "gn:admin3_code":"3460.0",
    "gn:admin4_code":"3460001.0",
    "gn:asciiname":"Hausstette",
    "gn:country_code":"DE",
    "gn:dem":32,
    "gn:feature_class":"P",
    "gn:feature_code":"PPL",
    "gn:name":"Hausstette",
    "gn:population":0,
    "gn:timezone":"Europe/Berlin",
    "iso:country":"DE",
    "wof:name":"Hausstette",
    "wof:placetype":"locality"
},
  "geometry": {"coordinates":[8.12881,52.73325],"type":"Point"}
}