{
  "type": "Feature",
  "properties": {
    "gn:country":"DE",
    "gn:fcode":"PPL",
    "gn:population":0,
    "iso:country":"DE",
    "name:ceb_x_preferred":[
        "H\u00f6rsten"
    ],
    "name:dan_x_preferred":[
        "H\u00f6rsten"
    ],
    "name:deu_x_preferred":[
        "H\u00f6rsten"
    ],
    "name:epo_x_preferred":[
        "H\u00f6rsten"
    ],
    "name:eus_x_preferred":[
        "H\u00f6rsten"
    ],
    "name:fas_x_preferred":[
        "\u0647\u0648\u0631\u0634\u062a\u0646"
    ],
    "name:fra_x_preferred":[
        "H\u00f6rsten"
    ],
    "name:hun_x_preferred":[
        "H\u00f6rsten"
    ],
    "name:ita_x_preferred":[
        "H\u00f6rsten"
    ],
    "name:kaz_x_preferred":[
        "\u0425\u0451\u0440\u0441\u0442\u0435\u043d"
    ],
    "name:kir_x_preferred":[
        "\u0425\u04e9\u0440\u0441\u0442\u0435\u043d"
    ],
    "name:mkd_x_preferred":[
        "\u0425\u0435\u0440\u0441\u0442\u0435\u043d"
    ],
    "name:msa_x_preferred":[
        "H\u00f6rsten"
    ],
    "name:nld_x_preferred":[
        "H\u00f6rsten"
    ],
    "name:pol_x_preferred":[
        "H\u00f6rsten"
    ],
    "name:por_x_preferred":[
        "H\u00f6rsten"
    ],
    "name:ron_x_preferred":[
        "H\u00f6rsten"
    ],
    "name:rus_x_preferred":[
        "\u0425\u0451\u0440\u0441\u0442\u0435\u043d"
    ],
    "name:spa_x_preferred":[
        "H\u00f6rsten"
    ],
    "name:srp_x_preferred":[
        "\u0425\u0435\u0440\u0441\u0442\u0435\u043d"
    ],
    "name:tur_x_preferred":[
        "H\u00f6rsten"
    ],
    "name:ukr_x_preferred":[
        "\u0413\u0435\u0440\u0441\u0442\u0435\u043d"
    ],
    "name:uzb_x_preferred":[
        "H\u00f6rsten"
    ],
    "name:vie_x_preferred":[
        "H\u00f6rsten"
    ],
    "name:vol_x_preferred":[
        "H\u00f6rsten"
    ],
    "name:war_x_preferred":[
        "H\u00f6rsten"
    ],
    "name:zho_x_preferred":[
        "\u8d6b\u5c14\u65af\u6ed5"
    ],
    "qs_pg:aaroncc":"DE",
    "qs_pg:gn_country":"DE",
    "qs_pg:gn_fcode":"PPL",
    "qs_pg:gn_pop":0,
    "qs_pg:name":"H\u00f6rsten",
    "qs_pg:name_adm0":"Deutschland",
    "qs_pg:name_adm1":"Niedersachsen",
    "qs_pg:photos_9k":1,
    "qs_pg:photos_9r":1,
    "qs_pg:photos_all":4,
    "qs_pg:photos_sr":0,
    "qs_pg:pop_sr":0,
    "qs_pg:qs_pg_placetype":"locality",
    "qs_pg:qs_pg_placetype_gp":"Town",
    "qs_pg:woe_adm0":23424829,
    "woe:adm0_id":23424829,
    "woe:name_adm0":"Deutschland",
    "woe:name_adm1":"Niedersachsen",
    "woe:placetype":"Town",
    "wof:name":"H\u00f6rsten",
    "wof:placetype":"neighbourhood"
},
  "geometry": {"coordinates":[10.06277,53.41113],"type":"Point"}
}