{
  "type": "Feature",
  "properties": {
    "iso:country":"DE",
    "name:deu_x_preferred":[
        "Schriefersm\u00fchle"
    ],
    "wof:name":"Schriefersmuehle",
    "wof:placetype":"neighbourhood"
},
  "geometry": {"coordinates":[6.3396605228797,51.13628546913445],"type":"Point"}
}