{
  "type": "Feature",
  "properties": {
    "gn:admin1_code":"1.0",
    "gn:admin2_code":"082",
    "gn:admin3_code":"8215.0",
    "gn:admin4_code":"8215089.0",
    "gn:asciiname":"Woessingen",
    "gn:country_code":"DE",
    "gn:dem":182,
    "gn:feature_class":"P",
    "gn:feature_code":"PPL",
    "gn:name":"W\u00f6ssingen",
    "gn:population":3781,
    "gn:timezone":"Europe/Berlin",
    "iso:country":"DE",
    "wof:name":"Woessingen",
    "wof:placetype":"neighbourhood",
    "wof:population":3781
},
  "geometry": {"coordinates":[8.60754,49.01205],"type":"Point"}
}