{
  "type": "Feature",
  "properties": {
    "iso:country":"DE",
    "name:deu_x_colloquial":[
        "Hassley"
    ],
    "name:deu_x_preferred":[
        "Ha\u00dfley"
    ],
    "name:unk_x_variant":[
        "Ha\u00dfley"
    ],
    "qs:gn_fcode":"PPLX",
    "qs:gn_local":0,
    "qs:gn_namadm1":"07",
    "qs:gn_name":"Ha\u00dfley",
    "qs:local_max":1328,
    "qs:local_sum":3650,
    "qs:localhoods":22,
    "qs:name":"Ha\u00dfley",
    "qs:name_adm0":"Deutschland",
    "qs:name_adm1":"Nordrhein-Westfalen",
    "qs:name_adm2":"Stadtkreis Hagen",
    "qs:name_lau":"Stadtteil Hohenlimburg",
    "qs:name_local":"Hagen",
    "qs:photo_max":5,
    "qs:photo_sum":16,
    "qs:placetype":"Suburb",
    "qs:quad_count":7,
    "qs:woe_adm0":23424829,
    "qs:woe_adm1":2345487,
    "qs:woe_adm2":12596856,
    "qs:woe_lau":26822477,
    "qs:woe_local":656385,
    "qs:woe_ver":"7.10.0",
    "wof:lang":[
        "ger"
    ],
    "wof:name":"Ha\u00dfley",
    "wof:placetype":"neighbourhood"
},
  "geometry": {"coordinates":[7.524605,51.35506],"type":"Point"}
}