{
  "type": "Feature",
  "properties": {
    "gn:admin1_code":"7.0",
    "gn:admin2_code":"51.0",
    "gn:admin3_code":"5170.0",
    "gn:admin4_code":"5170008.0",
    "gn:asciiname":"Bruch",
    "gn:country_code":"DE",
    "gn:dem":30,
    "gn:feature_class":"P",
    "gn:feature_code":"PPL",
    "gn:name":"Bruch",
    "gn:population":0,
    "gn:timezone":"Europe/Berlin",
    "iso:country":"DE",
    "name:ceb_x_preferred":[
        "Bruch"
    ],
    "name:deu_x_preferred":[
        "Bruch"
    ],
    "name:epo_x_preferred":[
        "Bruch"
    ],
    "name:fra_x_preferred":[
        "Bruch"
    ],
    "name:ita_x_preferred":[
        "Bruch"
    ],
    "name:ltz_x_preferred":[
        "Bruch"
    ],
    "name:nld_x_preferred":[
        "Bruch"
    ],
    "name:pol_x_preferred":[
        "Bruch"
    ],
    "name:por_x_preferred":[
        "Bruch"
    ],
    "name:rus_x_preferred":[
        "\u0411\u0440\u0443\u0445"
    ],
    "name:spa_x_preferred":[
        "Bruch"
    ],
    "name:srp_x_preferred":[
        "\u0411\u0440\u0438\u0448"
    ],
    "name:swe_x_preferred":[
        "Bruch"
    ],
    "wof:name":"Bruch",
    "wof:placetype":"neighbourhood"
},
  "geometry": {"coordinates":[6.72844,51.57718],"type":"Point"}
}