{
  "type": "Feature",
  "properties": {
    "gn:admin1_code":"6",
    "gn:admin2_code":"0.0",
    "gn:admin3_code":"3102.0",
    "gn:admin4_code":"3102000.0",
    "gn:asciiname":"Calbecht",
    "gn:country_code":"DE",
    "gn:dem":121,
    "gn:feature_class":"P",
    "gn:feature_code":"PPL",
    "gn:name":"Calbecht",
    "gn:population":0,
    "gn:timezone":"Europe/Berlin",
    "iso:country":"DE",
    "wof:name":"Calbecht",
    "wof:placetype":"neighbourhood"
},
  "geometry": {"coordinates":[10.38191,52.09027],"type":"Point"}
}