{
  "type": "Feature",
  "properties": {
    "gn:admin1_code":"1",
    "gn:admin2_code":"83.0",
    "gn:admin3_code":"8337.0",
    "gn:admin4_code":"8337049.0",
    "gn:asciiname":"Rutte",
    "gn:country_code":"DE",
    "gn:dem":891,
    "gn:feature_class":"P",
    "gn:feature_code":"PPL",
    "gn:name":"R\u00fctte",
    "gn:population":0,
    "gn:timezone":"Europe/Berlin",
    "iso:country":"DE",
    "wof:name":"Rutte",
    "wof:placetype":"neighbourhood"
},
  "geometry": {"coordinates":[7.98923,47.67186],"type":"Point"}
}