{
  "type": "Feature",
  "properties": {
    "gn:admin1_code":"14",
    "gn:admin2_code":"0.0",
    "gn:admin3_code":"15090.0",
    "gn:admin4_code":"15090415.0",
    "gn:asciiname":"Meierbusch",
    "gn:country_code":"DE",
    "gn:dem":24,
    "gn:feature_class":"P",
    "gn:feature_code":"PPL",
    "gn:name":"Meierbusch",
    "gn:population":0,
    "gn:timezone":"Europe/Berlin",
    "iso:country":"DE",
    "wof:name":"Meierbusch",
    "wof:placetype":"neighbourhood"
},
  "geometry": {"coordinates":[11.81913,52.79739],"type":"Point"}
}