{
  "type": "Feature",
  "properties": {
    "gn:admin1_code":"6",
    "gn:admin2_code":"0.0",
    "gn:admin3_code":"3352.0",
    "gn:admin4_code":"3352059.0",
    "gn:asciiname":"Seebeck",
    "gn:country_code":"DE",
    "gn:dem":12,
    "gn:feature_class":"P",
    "gn:feature_code":"PPL",
    "gn:name":"Seebeck",
    "gn:population":0,
    "gn:timezone":"Europe/Berlin",
    "iso:country":"DE",
    "name:cat_x_preferred":[
        "Seebek"
    ],
    "name:ceb_x_preferred":[
        "Seebeck"
    ],
    "name:deu_x_preferred":[
        "Seebeck"
    ],
    "name:nds_x_preferred":[
        "Seebeck"
    ],
    "name:rus_x_preferred":[
        "\u0417\u0435\u0435\u0431\u0435\u043a"
    ],
    "name:swe_x_preferred":[
        "Seebeck"
    ],
    "wof:name":"Seebeck",
    "wof:placetype":"neighbourhood"
},
  "geometry": {"coordinates":[8.79091,53.39295],"type":"Point"}
}