{
  "type": "Feature",
  "properties": {
    "gn:admin1_code":"8",
    "gn:admin2_code":"0.0",
    "gn:admin3_code":"7333.0",
    "gn:admin4_code":"7333503.0",
    "gn:asciiname":"Kupferschmelz",
    "gn:country_code":"DE",
    "gn:dem":236,
    "gn:feature_class":"P",
    "gn:feature_code":"PPL",
    "gn:name":"Kupferschmelz",
    "gn:population":0,
    "gn:timezone":"Europe/Berlin",
    "iso:country":"DE",
    "wof:name":"Kupferschmelz",
    "wof:placetype":"neighbourhood"
},
  "geometry": {"coordinates":[7.84876,49.57578],"type":"Point"}
}