{
  "type": "Feature",
  "properties": {
    "gn:admin1_code":"6",
    "gn:admin2_code":"0.0",
    "gn:admin3_code":"3453.0",
    "gn:admin4_code":"3453007.0",
    "gn:asciiname":"Klauen",
    "gn:country_code":"DE",
    "gn:dem":5,
    "gn:feature_class":"P",
    "gn:feature_code":"PPL",
    "gn:name":"Klauen",
    "gn:population":0,
    "gn:timezone":"Europe/Berlin",
    "iso:country":"DE",
    "wof:name":"Klauen",
    "wof:placetype":"neighbourhood"
},
  "geometry": {"coordinates":[7.85,53.01667],"type":"Point"}
}