{
  "type": "Feature",
  "properties": {
    "gn:admin1_code":"2.0",
    "gn:admin2_code":"95.0",
    "gn:admin3_code":"9572.0",
    "gn:admin4_code":"9572111.0",
    "gn:asciiname":"Aisch",
    "gn:country_code":"DE",
    "gn:dem":274,
    "gn:feature_class":"P",
    "gn:feature_code":"PPL",
    "gn:name":"Aisch",
    "gn:population":0,
    "gn:timezone":"Europe/Berlin",
    "iso:country":"DE",
    "name:ceb_x_preferred":[
        "Aisch"
    ],
    "name:dan_x_preferred":[
        "Aisch"
    ],
    "name:deu_x_preferred":[
        "Aisch"
    ],
    "name:fas_x_preferred":[
        "\u0622\u06cc\u0634"
    ],
    "name:pol_x_preferred":[
        "Aisch"
    ],
    "name:rus_x_preferred":[
        "\u0410\u0439\u0448"
    ],
    "wof:name":"Aisch",
    "wof:placetype":"neighbourhood"
},
  "geometry": {"coordinates":[10.88848,49.72176],"type":"Point"}
}