{
  "type": "Feature",
  "properties": {
    "gn:admin1_code":"2.0",
    "gn:admin2_code":"91.0",
    "gn:admin3_code":"9185.0",
    "gn:admin4_code":"9185140.0",
    "gn:asciiname":"Bofzheim",
    "gn:country_code":"DE",
    "gn:dem":371,
    "gn:feature_class":"P",
    "gn:feature_code":"PPL",
    "gn:name":"Bofzheim",
    "gn:population":0,
    "gn:timezone":"Europe/Berlin",
    "iso:country":"DE",
    "wof:name":"Bofzheim",
    "wof:placetype":"neighbourhood"
},
  "geometry": {"coordinates":[11.37855,48.68702],"type":"Point"}
}