{
  "type": "Feature",
  "properties": {
    "gn:admin1_code":"2",
    "gn:admin2_code":"92.0",
    "gn:admin3_code":"9275.0",
    "gn:admin4_code":"9275154.0",
    "gn:asciiname":"Giglmohrn",
    "gn:country_code":"DE",
    "gn:dem":390,
    "gn:feature_class":"P",
    "gn:feature_code":"PPL",
    "gn:name":"Giglm\u00f6hrn",
    "gn:population":0,
    "gn:timezone":"Europe/Berlin",
    "iso:country":"DE",
    "name:und_x_variant":[
        "Giglm\u00f6hren",
        "Giglm\u00f6hrn"
    ],
    "wof:name":"Giglmohrn",
    "wof:placetype":"neighbourhood"
},
  "geometry": {"coordinates":[13.26693,48.59047],"type":"Point"}
}