{
  "type": "Feature",
  "properties": {
    "gn:admin1_code":"5",
    "gn:admin2_code":"66.0",
    "gn:admin3_code":"6631.0",
    "gn:admin4_code":"6631009.0",
    "gn:asciiname":"Glaeserzell",
    "gn:country_code":"DE",
    "gn:dem":246,
    "gn:feature_class":"P",
    "gn:feature_code":"PPL",
    "gn:name":"Gl\u00e4serzell",
    "gn:population":0,
    "gn:timezone":"Europe/Berlin",
    "iso:country":"DE",
    "wof:name":"Glaeserzell",
    "wof:placetype":"neighbourhood"
},
  "geometry": {"coordinates":[9.64405,50.58105],"type":"Point"}
}