{
  "type": "Feature",
  "properties": {
    "gn:admin1_code":"2",
    "gn:admin2_code":"97.0",
    "gn:admin3_code":"9776.0",
    "gn:admin4_code":"9776124.0",
    "gn:asciiname":"Happareute",
    "gn:country_code":"DE",
    "gn:dem":657,
    "gn:feature_class":"P",
    "gn:feature_code":"PPL",
    "gn:name":"Happareute",
    "gn:population":0,
    "gn:timezone":"Europe/Berlin",
    "iso:country":"DE",
    "wof:name":"Happareute",
    "wof:placetype":"neighbourhood"
},
  "geometry": {"coordinates":[9.95253,47.63766],"type":"Point"}
}