{
  "type": "Feature",
  "properties": {
    "iso:country":"DE",
    "name:deu_x_preferred":[
        "Wittlaer"
    ],
    "name:ita_x_preferred":[
        "Wittlaer"
    ],
    "name:pol_x_preferred":[
        "Wittlaer"
    ],
    "name:rus_x_preferred":[
        "\u0414\u044e\u0441\u0441\u0435\u043b\u044c\u0434\u043e\u0440\u0444-\u0412\u0438\u0442\u0442\u043b\u0430\u0440"
    ],
    "wof:name":"Wittlaer",
    "wof:placetype":"neighbourhood"
},
  "geometry": {"coordinates":[6.74260313203768,51.32149192592684],"type":"Point"}
}