{
  "type": "Feature",
  "properties": {
    "gn:admin1_code":"6",
    "gn:admin2_code":"0.0",
    "gn:admin3_code":"3454.0",
    "gn:admin4_code":"3454018.0",
    "gn:asciiname":"Haar",
    "gn:country_code":"DE",
    "gn:dem":17,
    "gn:feature_class":"P",
    "gn:feature_code":"PPL",
    "gn:name":"Haar",
    "gn:population":0,
    "gn:timezone":"Europe/Berlin",
    "iso:country":"DE",
    "wof:name":"Haar",
    "wof:placetype":"neighbourhood"
},
  "geometry": {"coordinates":[7.13461,52.79592],"type":"Point"}
}