{
  "type": "Feature",
  "properties": {
    "gn:admin1_code":"7",
    "gn:admin2_code":"55.0",
    "gn:admin3_code":"5566.0",
    "gn:admin4_code":"5566024.0",
    "gn:asciiname":"Eismann",
    "gn:country_code":"DE",
    "gn:dem":80,
    "gn:feature_class":"P",
    "gn:feature_code":"PPL",
    "gn:name":"Eismann",
    "gn:population":0,
    "gn:timezone":"Europe/Berlin",
    "iso:country":"DE",
    "wof:name":"Eismann",
    "wof:placetype":"neighbourhood"
},
  "geometry": {"coordinates":[7.26667,52.11667],"type":"Point"}
}