{
  "type": "Feature",
  "properties": {
    "gn:admin1_code":"7",
    "gn:admin2_code":"53.0",
    "gn:admin3_code":"5314.0",
    "gn:admin4_code":"5314000.0",
    "gn:asciiname":"Schwarz Rheindorf",
    "gn:country_code":"DE",
    "gn:dem":60,
    "gn:feature_class":"P",
    "gn:feature_code":"PPL",
    "gn:name":"Schwarz Rheindorf",
    "gn:population":0,
    "gn:timezone":"Europe/Berlin",
    "iso:country":"DE",
    "name:und_x_variant":[
        "Schwarzrheindorf/Vilich-Rheindorf",
        "Schwarz Rheindorf"
    ],
    "wof:name":"Schwarz Rheindorf",
    "wof:placetype":"neighbourhood"
},
  "geometry": {"coordinates":[7.11643,50.75074],"type":"Point"}
}