{
  "type": "Feature",
  "properties": {
    "gn:admin1_code":"2",
    "gn:admin2_code":"95.0",
    "gn:admin3_code":"9577.0",
    "gn:admin4_code":"9577158.0",
    "gn:asciiname":"Ochsenhart",
    "gn:country_code":"DE",
    "gn:dem":547,
    "gn:feature_class":"P",
    "gn:feature_code":"PPL",
    "gn:name":"Ochsenhart",
    "gn:population":0,
    "gn:timezone":"Europe/Berlin",
    "iso:country":"DE",
    "wof:name":"Ochsenhart",
    "wof:placetype":"neighbourhood"
},
  "geometry": {"coordinates":[11.04727,48.9137],"type":"Point"}
}