{
  "type": "Feature",
  "properties": {
    "gn:admin1_code":"8",
    "gn:admin2_code":"0.0",
    "gn:admin3_code":"7132.0",
    "gn:admin4_code":"7132054.0",
    "gn:asciiname":"Niederhoevels",
    "gn:country_code":"DE",
    "gn:dem":167,
    "gn:feature_class":"P",
    "gn:feature_code":"PPL",
    "gn:name":"Niederh\u00f6vels",
    "gn:population":0,
    "gn:timezone":"Europe/Berlin",
    "iso:country":"DE",
    "wof:name":"Niederhoevels",
    "wof:placetype":"locality"
},
  "geometry": {"coordinates":[7.78639,50.78687],"type":"Point"}
}