{
  "type": "Feature",
  "properties": {
    "gn:admin1_code":"2",
    "gn:admin2_code":"91.0",
    "gn:admin3_code":"9179.0",
    "gn:admin4_code":"9179113.0",
    "gn:asciiname":"Germannsberg",
    "gn:country_code":"DE",
    "gn:dem":603,
    "gn:feature_class":"P",
    "gn:feature_code":"PPL",
    "gn:name":"Germannsberg",
    "gn:population":0,
    "gn:timezone":"Europe/Berlin",
    "iso:country":"DE",
    "wof:name":"Germannsberg",
    "wof:placetype":"neighbourhood"
},
  "geometry": {"coordinates":[11.26713,48.14024000000001],"type":"Point"}
}