{
  "type": "Feature",
  "properties": {
    "gn:admin1_code":"6.0",
    "gn:admin2_code":"0.0",
    "gn:admin3_code":"3359.0",
    "gn:admin4_code":"3359008.0",
    "gn:asciiname":"Bredenbeck",
    "gn:country_code":"DE",
    "gn:dem":23,
    "gn:feature_class":"P",
    "gn:feature_code":"PPL",
    "gn:name":"Bredenbeck",
    "gn:population":0,
    "gn:timezone":"Europe/Berlin",
    "iso:country":"DE",
    "wof:name":"Bredenbeck",
    "wof:placetype":"neighbourhood"
},
  "geometry": {"coordinates":[9.34663,53.43957],"type":"Point"}
}