{
  "type": "Feature",
  "properties": {
    "gn:admin1_code":"13",
    "gn:admin2_code":"0.0",
    "gn:admin3_code":"14522.0",
    "gn:admin4_code":"14522280.0",
    "gn:asciiname":"Leupahn",
    "gn:country_code":"DE",
    "gn:dem":218,
    "gn:feature_class":"P",
    "gn:feature_code":"PPL",
    "gn:name":"Leupahn",
    "gn:population":0,
    "gn:timezone":"Europe/Berlin",
    "iso:country":"DE",
    "wof:name":"Leupahn",
    "wof:placetype":"neighbourhood"
},
  "geometry": {"coordinates":[12.75945,51.09854],"type":"Point"}
}