{
  "type": "Feature",
  "properties": {
    "iso:country":"DE",
    "wof:name":"Podemus",
    "wof:placetype":"neighbourhood"
},
  "geometry": {"coordinates":[13.62634007803552,51.05997259878607],"type":"Point"}
}