{
  "type": "Feature",
  "properties": {
    "gn:admin1_code":"7",
    "gn:admin2_code":"57.0",
    "gn:admin3_code":"5754.0",
    "gn:admin4_code":"5754052.0",
    "gn:asciiname":"Isingdorf",
    "gn:country_code":"DE",
    "gn:dem":177,
    "gn:feature_class":"P",
    "gn:feature_code":"PPLL",
    "gn:name":"Isingdorf",
    "gn:population":0,
    "gn:timezone":"Europe/Berlin",
    "iso:country":"DE",
    "wof:name":"Isingdorf",
    "wof:placetype":"neighbourhood"
},
  "geometry": {"coordinates":[8.42857,52.0564],"type":"Point"}
}