{
  "type": "Feature",
  "properties": {
    "iso:country":"DE",
    "wof:name":"Pongs",
    "wof:placetype":"neighbourhood"
},
  "geometry": {"coordinates":[6.4114293196712,51.16402206055404],"type":"Point"}
}