{
  "type": "Feature",
  "properties": {
    "gn:admin1_code":"15",
    "gn:admin2_code":"0.0",
    "gn:admin3_code":"16073.0",
    "gn:admin4_code":"16073079.0",
    "gn:asciiname":"Taubenbach",
    "gn:country_code":"DE",
    "gn:dem":653,
    "gn:feature_class":"P",
    "gn:feature_code":"PPL",
    "gn:name":"Taubenbach",
    "gn:population":0,
    "gn:timezone":"Europe/Berlin",
    "iso:country":"DE",
    "wof:name":"Taubenbach",
    "wof:placetype":"neighbourhood"
},
  "geometry": {"coordinates":[11.22649,50.52823],"type":"Point"}
}