{
  "type": "Feature",
  "properties": {
    "gn:admin1_code":"13",
    "gn:admin2_code":"0.0",
    "gn:admin3_code":"14625.0",
    "gn:admin4_code":"14625500.0",
    "gn:asciiname":"Graenze",
    "gn:country_code":"DE",
    "gn:dem":151,
    "gn:feature_class":"P",
    "gn:feature_code":"PPL",
    "gn:name":"Gr\u00e4nze",
    "gn:population":0,
    "gn:timezone":"Europe/Berlin",
    "iso:country":"DE",
    "name:hsb_x_preferred":[
        "Hra\u0144ca"
    ],
    "wof:name":"Graenze",
    "wof:placetype":"neighbourhood"
},
  "geometry": {"coordinates":[14.2391,51.27429],"type":"Point"}
}