{
  "type": "Feature",
  "properties": {
    "gn:admin1_code":"2",
    "gn:admin2_code":"95.0",
    "gn:admin3_code":"9575.0",
    "gn:admin4_code":"9575125.0",
    "gn:asciiname":"Gottelhof",
    "gn:country_code":"DE",
    "gn:dem":341,
    "gn:feature_class":"P",
    "gn:feature_code":"PPL",
    "gn:name":"G\u00f6ttelh\u00f6f",
    "gn:population":0,
    "gn:timezone":"Europe/Berlin",
    "iso:country":"DE",
    "wof:name":"Gottelhof",
    "wof:placetype":"neighbourhood"
},
  "geometry": {"coordinates":[10.69313,49.60203],"type":"Point"}
}