{
  "type": "Feature",
  "properties": {
    "gn:admin1_code":"9",
    "gn:admin2_code":"0.0",
    "gn:admin3_code":"10041.0",
    "gn:admin4_code":"10041100.0",
    "gn:asciiname":"Jaegersfreude",
    "gn:country_code":"DE",
    "gn:dem":217,
    "gn:feature_class":"P",
    "gn:feature_code":"PPL",
    "gn:name":"J\u00e4gersfreude",
    "gn:population":0,
    "gn:timezone":"Europe/Berlin",
    "iso:country":"DE",
    "wof:name":"Jaegersfreude",
    "wof:placetype":"neighbourhood"
},
  "geometry": {"coordinates":[7.00599,49.26555],"type":"Point"}
}