{
  "type": "Feature",
  "properties": {
    "gn:admin1_code":"13.0",
    "gn:admin2_code":"0.0",
    "gn:admin3_code":"14627.0",
    "gn:admin4_code":"14627220.0",
    "gn:asciiname":"Berbisdorf",
    "gn:country_code":"DE",
    "gn:dem":157,
    "gn:feature_class":"P",
    "gn:feature_code":"PPL",
    "gn:name":"Berbisdorf",
    "gn:population":0,
    "gn:timezone":"Europe/Berlin",
    "iso:country":"DE",
    "wof:name":"Berbisdorf",
    "wof:placetype":"neighbourhood"
},
  "geometry": {"coordinates":[13.72261,51.18946],"type":"Point"}
}