{
  "type": "Feature",
  "properties": {
    "gn:gn_country":"DE",
    "gn:gn_fcode":"PPLA4",
    "gn:gn_pop":148,
    "gn:population":148,
    "iso:country":"DE",
    "name:baq_x_preferred":[
        "Oberweiler"
    ],
    "name:chi_x_preferred":[
        "\u4e0a\u9b4f\u83b1\u5c14"
    ],
    "name:dut_x_preferred":[
        "Oberweiler"
    ],
    "name:eng_x_preferred":[
        "Oberweiler"
    ],
    "name:epo_x_preferred":[
        "Oberweiler"
    ],
    "name:fre_x_preferred":[
        "Oberweiler"
    ],
    "name:ger_x_preferred":[
        "Oberweiler"
    ],
    "name:hun_x_preferred":[
        "Oberweiler"
    ],
    "name:ita_x_preferred":[
        "Oberweiler"
    ],
    "name:jpn_x_preferred":[
        "\u30aa\u30fc\u30d0\u30fc\u30f4\u30a1\u30a4\u30e9\u30fc"
    ],
    "name:may_x_preferred":[
        "Oberweiler"
    ],
    "name:per_x_preferred":[
        "\u0627\u0648\u0628\u0631\u0648\u0627\u06cc\u0644\u0631"
    ],
    "name:pol_x_preferred":[
        "Oberweiler"
    ],
    "name:por_x_preferred":[
        "Oberweiler"
    ],
    "name:rum_x_preferred":[
        "Oberweiler"
    ],
    "name:rus_x_preferred":[
        "\u041e\u0431\u0435\u0440\u0432\u0430\u0439\u043b\u0435\u0440"
    ],
    "name:srp_x_preferred":[
        "\u041e\u0431\u0435\u0440\u0432\u0430\u0458\u043b\u0435\u0440"
    ],
    "name:ukr_x_preferred":[
        "\u041e\u0431\u0435\u0440\u0432\u0430\u0439\u043b\u0435\u0440"
    ],
    "name:uzb_x_preferred":[
        "Oberweiler"
    ],
    "name:vie_x_preferred":[
        "Oberweiler"
    ],
    "name:vol_x_preferred":[
        "Oberweiler"
    ],
    "name:war_x_preferred":[
        "Oberweiler"
    ],
    "qs_pg:aaroncc":"DE",
    "qs_pg:gn_country":"DE",
    "qs_pg:gn_fcode":"PPLA4",
    "qs_pg:gn_pop":148,
    "qs_pg:name":"Oberweiler",
    "qs_pg:photos_9r":0,
    "qs_pg:photos_sr":0,
    "qs_pg:pop_sr":1,
    "qs_pg:qs_pg_placetype":"locality",
    "wof:name":"Oberweiler",
    "wof:placetype":"locality",
    "wof:population":148
},
  "geometry": {"coordinates":[6.45,50.05],"type":"Point"}
}