{
  "type": "Feature",
  "properties": {
    "gn:admin1_code":"1",
    "gn:admin2_code":"81.0",
    "gn:admin3_code":"8127.0",
    "gn:admin4_code":"8127014.0",
    "gn:asciiname":"Heinkenbusch",
    "gn:country_code":"DE",
    "gn:dem":436,
    "gn:feature_class":"P",
    "gn:feature_code":"PPL",
    "gn:name":"Heinkenbusch",
    "gn:population":0,
    "gn:timezone":"Europe/Berlin",
    "iso:country":"DE",
    "wof:name":"Heinkenbusch",
    "wof:placetype":"neighbourhood"
},
  "geometry": {"coordinates":[9.98333,49.15],"type":"Point"}
}