{
  "type": "Feature",
  "properties": {
    "gn:admin1_code":"14",
    "gn:admin2_code":"0.0",
    "gn:admin3_code":"15084.0",
    "gn:admin4_code":"15084012.0",
    "gn:asciiname":"Burghessler",
    "gn:country_code":"DE",
    "gn:dem":184,
    "gn:feature_class":"P",
    "gn:feature_code":"PPL",
    "gn:name":"Burghe\u00dfler",
    "gn:population":0,
    "gn:timezone":"Europe/Berlin",
    "iso:country":"DE",
    "wof:name":"Burghessler",
    "wof:placetype":"neighbourhood"
},
  "geometry": {"coordinates":[11.65087,51.1594],"type":"Point"}
}