{
  "type": "Feature",
  "properties": {
    "gn:admin1_code":"15.0",
    "gn:admin2_code":"00",
    "gn:admin3_code":"16066.0",
    "gn:admin4_code":"16066042.0",
    "gn:asciiname":"Welkershausen",
    "gn:country_code":"DE",
    "gn:dem":364,
    "gn:feature_class":"P",
    "gn:feature_code":"PPL",
    "gn:name":"Welkershausen",
    "gn:population":0,
    "gn:timezone":"Europe/Berlin",
    "iso:country":"DE",
    "wof:name":"Welkershausen",
    "wof:placetype":"neighbourhood"
},
  "geometry": {"coordinates":[10.42278,50.5944],"type":"Point"}
}