{
  "type": "Feature",
  "properties": {
    "gn:admin1_code":"13",
    "gn:admin2_code":"0.0",
    "gn:admin3_code":"14522.0",
    "gn:admin4_code":"14522510.0",
    "gn:asciiname":"Otzdorf",
    "gn:country_code":"DE",
    "gn:dem":258,
    "gn:feature_class":"P",
    "gn:feature_code":"PPL",
    "gn:name":"Otzdorf",
    "gn:population":0,
    "gn:timezone":"Europe/Berlin",
    "iso:country":"DE",
    "wof:name":"Otzdorf",
    "wof:placetype":"neighbourhood"
},
  "geometry": {"coordinates":[13.10339,51.06653],"type":"Point"}
}