{
  "type": "Feature",
  "properties": {
    "gn:admin1_code":"1.0",
    "gn:admin2_code":"082",
    "gn:admin3_code":"8237.0",
    "gn:admin4_code":"8237024.0",
    "gn:asciiname":"Wiesenstetten",
    "gn:country_code":"DE",
    "gn:dem":529,
    "gn:feature_class":"P",
    "gn:feature_code":"PPL",
    "gn:name":"Wiesenstetten",
    "gn:population":0,
    "gn:timezone":"Europe/Berlin",
    "iso:country":"DE",
    "wof:name":"Wiesenstetten",
    "wof:placetype":"neighbourhood"
},
  "geometry": {"coordinates":[8.74812,48.39889],"type":"Point"}
}