{
  "type": "Feature",
  "properties": {
    "gn:admin1_code":"2",
    "gn:admin2_code":"96.0",
    "gn:admin3_code":"9674.0",
    "gn:admin4_code":"9674164.0",
    "gn:asciiname":"Unfinden",
    "gn:country_code":"DE",
    "gn:dem":285,
    "gn:feature_class":"P",
    "gn:feature_code":"PPL",
    "gn:name":"Unfinden",
    "gn:population":0,
    "gn:timezone":"Europe/Berlin",
    "iso:country":"DE",
    "wof:name":"Unfinden",
    "wof:placetype":"neighbourhood"
},
  "geometry": {"coordinates":[10.56819,50.09303],"type":"Point"}
}