{
  "type": "Feature",
  "properties": {
    "gn:admin1_code":"1",
    "gn:admin2_code":"82.0",
    "gn:admin3_code":"8226.0",
    "gn:admin4_code":"8226006.0",
    "gn:asciiname":"Vorstadtel",
    "gn:country_code":"DE",
    "gn:dem":152,
    "gn:feature_class":"P",
    "gn:feature_code":"PPL",
    "gn:name":"Vorst\u00e4dtel",
    "gn:population":0,
    "gn:timezone":"Europe/Berlin",
    "iso:country":"DE",
    "wof:name":"Vorstadtel",
    "wof:placetype":"neighbourhood"
},
  "geometry": {"coordinates":[8.78333,49.35],"type":"Point"}
}