{
  "type": "Feature",
  "properties": {
    "gn:admin1_code":"6",
    "gn:admin2_code":"0.0",
    "gn:admin3_code":"3457.0",
    "gn:admin4_code":"3457011.0",
    "gn:asciiname":"Holtlander Nuecke",
    "gn:country_code":"DE",
    "gn:dem":10,
    "gn:feature_class":"P",
    "gn:feature_code":"PPLL",
    "gn:name":"Holtlander N\u00fccke",
    "gn:population":0,
    "gn:timezone":"Europe/Berlin",
    "iso:country":"DE",
    "wof:name":"Holtlander Nuecke",
    "wof:placetype":"neighbourhood"
},
  "geometry": {"coordinates":[7.57244,53.28295],"type":"Point"}
}