{
  "type": "Feature",
  "properties": {
    "gn:admin1_code":"10",
    "gn:admin2_code":"0.0",
    "gn:admin3_code":"1059.0",
    "gn:admin4_code":"1059132.0",
    "gn:asciiname":"Stieglund",
    "gn:country_code":"DE",
    "gn:dem":26,
    "gn:feature_class":"P",
    "gn:feature_code":"PPL",
    "gn:name":"Stieglund",
    "gn:population":0,
    "gn:timezone":"Europe/Berlin",
    "iso:country":"DE",
    "wof:name":"Stieglund",
    "wof:placetype":"neighbourhood"
},
  "geometry": {"coordinates":[9.23313,54.63889],"type":"Point"}
}