{
  "type": "Feature",
  "properties": {
    "gn:admin1_code":"5.0",
    "gn:admin2_code":"065",
    "gn:admin3_code":"6534.0",
    "gn:admin4_code":"6534008.0",
    "gn:asciiname":"Wermertshausen",
    "gn:country_code":"DE",
    "gn:dem":352,
    "gn:feature_class":"P",
    "gn:feature_code":"PPL",
    "gn:name":"Wermertshausen",
    "gn:population":0,
    "gn:timezone":"Europe/Berlin",
    "iso:country":"DE",
    "wof:name":"Wermertshausen",
    "wof:placetype":"neighbourhood"
},
  "geometry": {"coordinates":[8.90552,50.69634],"type":"Point"}
}