{
  "type": "Feature",
  "properties": {
    "gn:admin1_code":"7.0",
    "gn:admin2_code":"51.0",
    "gn:admin3_code":"5170.0",
    "gn:admin4_code":"5170024.0",
    "gn:asciiname":"Bornheim",
    "gn:country_code":"DE",
    "gn:dem":25,
    "gn:feature_class":"P",
    "gn:feature_code":"PPL",
    "gn:name":"Bornheim",
    "gn:population":0,
    "gn:timezone":"Europe/Berlin",
    "iso:country":"DE",
    "name:ceb_x_preferred":[
        "Bornheim"
    ],
    "name:deu_x_preferred":[
        "Bornheim"
    ],
    "name:epo_x_preferred":[
        "Bornheim"
    ],
    "name:eus_x_preferred":[
        "Bornheim"
    ],
    "name:fra_x_preferred":[
        "Bornheim"
    ],
    "name:ita_x_preferred":[
        "Bornheim"
    ],
    "name:nld_x_preferred":[
        "Bornheim"
    ],
    "name:pol_x_preferred":[
        "Bornheim"
    ],
    "name:por_x_preferred":[
        "Bornheim"
    ],
    "name:ron_x_preferred":[
        "Bornheim"
    ],
    "name:sco_x_preferred":[
        "Bornheim"
    ],
    "name:tat_x_preferred":[
        "\u0411\u043e\u0440\u043d\u04bb\u0430\u0439\u043c"
    ],
    "name:vol_x_preferred":[
        "Bornheim"
    ],
    "wof:name":"Bornheim",
    "wof:placetype":"neighbourhood"
},
  "geometry": {"coordinates":[6.63293,51.49204],"type":"Point"}
}