{
  "type": "Feature",
  "properties": {
    "gn:admin1_code":"2",
    "gn:admin2_code":"92.0",
    "gn:admin3_code":"9275.0",
    "gn:admin4_code":"9275154.0",
    "gn:asciiname":"Haid",
    "gn:country_code":"DE",
    "gn:dem":373,
    "gn:feature_class":"P",
    "gn:feature_code":"PPLL",
    "gn:name":"Haid",
    "gn:population":0,
    "gn:timezone":"Europe/Berlin",
    "iso:country":"DE",
    "name:deu_x_preferred":[
        "Haid"
    ],
    "wof:name":"Haid",
    "wof:placetype":"neighbourhood"
},
  "geometry": {"coordinates":[13.28674,48.60143],"type":"Point"}
}