{
  "type": "Feature",
  "properties": {
    "gn:admin1_code":"9",
    "gn:admin2_code":"0.0",
    "gn:admin3_code":"10042.0",
    "gn:admin4_code":"10042114.0",
    "gn:asciiname":"Tuensdorf",
    "gn:country_code":"DE",
    "gn:dem":367,
    "gn:feature_class":"P",
    "gn:feature_code":"PPL",
    "gn:name":"T\u00fcnsdorf",
    "gn:population":0,
    "gn:timezone":"Europe/Berlin",
    "iso:country":"DE",
    "wof:name":"Tuensdorf",
    "wof:placetype":"neighbourhood"
},
  "geometry": {"coordinates":[6.49687,49.47471],"type":"Point"}
}