{
  "type": "Feature",
  "properties": {
    "gn:admin1_code":"2",
    "gn:admin2_code":"91.0",
    "gn:admin3_code":"9190.0",
    "gn:admin4_code":"9190136.0",
    "gn:asciiname":"Habaching",
    "gn:country_code":"DE",
    "gn:dem":671,
    "gn:feature_class":"P",
    "gn:feature_code":"PPL",
    "gn:name":"Habaching",
    "gn:population":0,
    "gn:timezone":"Europe/Berlin",
    "iso:country":"DE",
    "wof:name":"Habaching",
    "wof:placetype":"neighbourhood"
},
  "geometry": {"coordinates":[11.25414,47.72879],"type":"Point"}
}