{
  "type": "Feature",
  "properties": {
    "gn:admin1_code":"1",
    "gn:admin2_code":"83.0",
    "gn:admin3_code":"8327.0",
    "gn:admin4_code":"8327018.0",
    "gn:asciiname":"Kirchen",
    "gn:country_code":"DE",
    "gn:dem":676,
    "gn:feature_class":"P",
    "gn:feature_code":"PPL",
    "gn:name":"Kirchen",
    "gn:population":0,
    "gn:timezone":"Europe/Berlin",
    "iso:country":"DE",
    "name:ara_x_preferred":[
        "\u0643\u064a\u0631\u0634\u0646"
    ],
    "name:azb_x_preferred":[
        "\u06a9\u06cc\u0631\u0634\u0646"
    ],
    "name:deu_x_preferred":[
        "Kirchen"
    ],
    "name:epo_x_preferred":[
        "Kirchen"
    ],
    "name:fas_x_preferred":[
        "\u06a9\u06cc\u0631\u0634\u0646"
    ],
    "name:fra_x_preferred":[
        "Kirchen"
    ],
    "name:hun_x_preferred":[
        "Kirchen"
    ],
    "name:ita_x_preferred":[
        "Kirchen"
    ],
    "name:jpn_x_preferred":[
        "\u30ad\u30eb\u30d2\u30a7\u30f3"
    ],
    "name:kaz_x_preferred":[
        "\u041a\u0438\u0440\u0445\u0435\u043d"
    ],
    "name:kir_x_preferred":[
        "\u041a\u0438\u0440\u0445\u0435\u043d"
    ],
    "name:lat_x_preferred":[
        "Chiricheim"
    ],
    "name:msa_x_preferred":[
        "Kirchen"
    ],
    "name:nld_x_preferred":[
        "Kirchen"
    ],
    "name:pol_x_preferred":[
        "Kirchen"
    ],
    "name:por_x_preferred":[
        "Kirchen"
    ],
    "name:ron_x_preferred":[
        "Kirchen"
    ],
    "name:rus_x_preferred":[
        "\u041a\u0438\u0440\u0445\u0435\u043d"
    ],
    "name:spa_x_preferred":[
        "Kirchen"
    ],
    "name:srp_x_preferred":[
        "\u041a\u0438\u0440\u0445\u0435\u043d"
    ],
    "name:ukr_x_preferred":[
        "\u041a\u0456\u0440\u0445\u0435\u043d"
    ],
    "name:uzb_x_preferred":[
        "Kirchen"
    ],
    "name:vie_x_preferred":[
        "Kirchen"
    ],
    "name:vol_x_preferred":[
        "Kirchen"
    ],
    "name:war_x_preferred":[
        "Kirchen"
    ],
    "name:zho_x_preferred":[
        "\u9521\u683c\u6cb3\u7554\u57fa\u5174"
    ],
    "wof:name":"Kirchen",
    "wof:placetype":"neighbourhood"
},
  "geometry": {"coordinates":[8.67179,47.90893],"type":"Point"}
}