{
  "type": "Feature",
  "properties": {
    "gn:admin1_code":"14",
    "gn:admin2_code":"0.0",
    "gn:admin3_code":"15084.0",
    "gn:admin4_code":"15084130.0",
    "gn:asciiname":"Oelsen",
    "gn:cc2":"DE",
    "gn:country_code":"DE",
    "gn:dem":198,
    "gn:feature_class":"P",
    "gn:feature_code":"PPL",
    "gn:name":"Oelsen",
    "gn:population":0,
    "gn:timezone":"Europe/Berlin",
    "iso:country":"DE",
    "name:und_x_variant":[
        "\u00d6lsen",
        "Oelsen"
    ],
    "wof:name":"Oelsen",
    "wof:placetype":"neighbourhood"
},
  "geometry": {"coordinates":[12.24718,51.03319000000001],"type":"Point"}
}