{
  "type": "Feature",
  "properties": {
    "iso:country":"DE",
    "name:deu_x_preferred":[
        "Wanne-S\u00fcd"
    ],
    "wof:name":"Wanne-Sued",
    "wof:placetype":"neighbourhood"
},
  "geometry": {"coordinates":[7.172277205556,51.52658615771869],"type":"Point"}
}