{
  "type": "Feature",
  "properties": {
    "gn:admin1_code":"7",
    "gn:admin2_code":"59.0",
    "gn:admin3_code":"5958.0",
    "gn:admin4_code":"5958016.0",
    "gn:asciiname":"Obersalwey",
    "gn:country_code":"DE",
    "gn:dem":365,
    "gn:feature_class":"P",
    "gn:feature_code":"PPL",
    "gn:name":"Obersalwey",
    "gn:population":0,
    "gn:timezone":"Europe/Berlin",
    "iso:country":"DE",
    "wof:name":"Obersalwey",
    "wof:placetype":"neighbourhood"
},
  "geometry": {"coordinates":[8.09742,51.24826],"type":"Point"}
}