{
  "type": "Feature",
  "properties": {
    "gn:admin1_code":"10",
    "gn:admin2_code":"0.0",
    "gn:admin3_code":"1058.0",
    "gn:admin4_code":"1058084.0",
    "gn:asciiname":"Fellhorst",
    "gn:country_code":"DE",
    "gn:dem":31,
    "gn:feature_class":"P",
    "gn:feature_code":"PPL",
    "gn:name":"Fellhorst",
    "gn:population":0,
    "gn:timezone":"Europe/Berlin",
    "iso:country":"DE",
    "wof:name":"Fellhorst",
    "wof:placetype":"neighbourhood"
},
  "geometry": {"coordinates":[9.67711,54.45782],"type":"Point"}
}