{
  "type": "Feature",
  "properties": {
    "gn:admin1_code":"2",
    "gn:admin2_code":"96.0",
    "gn:admin3_code":"9676.0",
    "gn:admin4_code":"9676123.0",
    "gn:asciiname":"Unteraulenbach",
    "gn:country_code":"DE",
    "gn:dem":193,
    "gn:feature_class":"P",
    "gn:feature_code":"PPL",
    "gn:name":"Unteraulenbach",
    "gn:population":0,
    "gn:timezone":"Europe/Berlin",
    "iso:country":"DE",
    "wof:name":"Unteraulenbach",
    "wof:placetype":"neighbourhood"
},
  "geometry": {"coordinates":[9.27839,49.83724],"type":"Point"}
}