{
  "type": "Feature",
  "properties": {
    "gn:admin1_code":"2",
    "gn:admin2_code":"91.0",
    "gn:admin3_code":"9178.0",
    "gn:admin4_code":"9178157.0",
    "gn:asciiname":"Siechendorf",
    "gn:country_code":"DE",
    "gn:dem":442,
    "gn:feature_class":"P",
    "gn:feature_code":"PPL",
    "gn:name":"Siechendorf",
    "gn:population":0,
    "gn:timezone":"Europe/Berlin",
    "iso:country":"DE",
    "wof:name":"Siechendorf",
    "wof:placetype":"neighbourhood"
},
  "geometry": {"coordinates":[11.73728,48.46442],"type":"Point"}
}