{
  "type": "Feature",
  "properties": {
    "gn:admin1_code":"1",
    "gn:admin2_code":"84.0",
    "gn:admin3_code":"8417.0",
    "gn:admin4_code":"8417002.0",
    "gn:asciiname":"Engstlatt",
    "gn:country_code":"DE",
    "gn:dem":514,
    "gn:feature_class":"P",
    "gn:feature_code":"PPL",
    "gn:name":"Engstlatt",
    "gn:population":0,
    "gn:timezone":"Europe/Berlin",
    "iso:country":"DE",
    "wof:name":"Engstlatt",
    "wof:placetype":"neighbourhood"
},
  "geometry": {"coordinates":[8.87412,48.30072],"type":"Point"}
}