{
  "type": "Feature",
  "properties": {
    "gn:admin1_code":"15",
    "gn:admin2_code":"0.0",
    "gn:admin3_code":"16052.0",
    "gn:admin4_code":"16052000.0",
    "gn:asciiname":"Hermsdorf",
    "gn:country_code":"DE",
    "gn:dem":290,
    "gn:feature_class":"P",
    "gn:feature_code":"PPL",
    "gn:name":"Hermsdorf",
    "gn:population":0,
    "gn:timezone":"Europe/Berlin",
    "iso:country":"DE",
    "name:ceb_x_preferred":[
        "Hermsdorf"
    ],
    "name:ces_x_preferred":[
        "Hermsdorf"
    ],
    "name:deu_x_preferred":[
        "Hermsdorf"
    ],
    "name:epo_x_preferred":[
        "Hermsdorf"
    ],
    "name:fra_x_preferred":[
        "Hermsdorf"
    ],
    "name:ita_x_preferred":[
        "Hermsdorf"
    ],
    "name:kir_x_preferred":[
        "\u0425\u0435\u0440\u043c\u0441\u0434\u043e\u0440\u0444"
    ],
    "name:mkd_x_preferred":[
        "\u0425\u0435\u0440\u043c\u0441\u0434\u043e\u0440\u0444"
    ],
    "name:nld_x_preferred":[
        "Hermsdorf"
    ],
    "name:pol_x_preferred":[
        "Hermsdorf"
    ],
    "name:por_x_preferred":[
        "Hermsdorf"
    ],
    "name:rus_x_preferred":[
        "\u0425\u0435\u0440\u043c\u0441\u0434\u043e\u0440\u0444"
    ],
    "name:swe_x_preferred":[
        "Hermsdorf"
    ],
    "name:vol_x_preferred":[
        "Hermsdorf"
    ],
    "wof:name":"Hermsdorf",
    "wof:placetype":"neighbourhood"
},
  "geometry": {"coordinates":[12.15286,50.96327],"type":"Point"}
}