{
  "type": "Feature",
  "properties": {
    "gn:admin1_code":"2",
    "gn:admin2_code":"95.0",
    "gn:admin3_code":"9575.0",
    "gn:admin4_code":"9575125.0",
    "gn:asciiname":"Rappoldshofen",
    "gn:country_code":"DE",
    "gn:dem":287,
    "gn:feature_class":"P",
    "gn:feature_code":"PPL",
    "gn:name":"Rappoldshofen",
    "gn:population":0,
    "gn:timezone":"Europe/Berlin",
    "iso:country":"DE",
    "wof:name":"Rappoldshofen",
    "wof:placetype":"neighbourhood"
},
  "geometry": {"coordinates":[10.66893,49.62344],"type":"Point"}
}