{
  "type": "Feature",
  "properties": {
    "gn:admin1_code":"2",
    "gn:admin2_code":"97.0",
    "gn:admin3_code":"9780.0",
    "gn:admin4_code":"9780132.0",
    "gn:asciiname":"Tronsberg",
    "gn:country_code":"DE",
    "gn:dem":863,
    "gn:feature_class":"P",
    "gn:feature_code":"PPL",
    "gn:name":"Tronsberg",
    "gn:population":0,
    "gn:timezone":"Europe/Berlin",
    "iso:country":"DE",
    "wof:name":"Tronsberg",
    "wof:placetype":"neighbourhood"
},
  "geometry": {"coordinates":[10.05117,47.56261],"type":"Point"}
}