{
  "type": "Feature",
  "properties": {
    "gn:admin1_code":"7",
    "gn:admin2_code":"57.0",
    "gn:admin3_code":"5762.0",
    "gn:admin4_code":"5762036.0",
    "gn:asciiname":"Calenberg",
    "gn:country_code":"DE",
    "gn:dem":223,
    "gn:feature_class":"P",
    "gn:feature_code":"PPL",
    "gn:name":"Calenberg",
    "gn:population":0,
    "gn:timezone":"Europe/Berlin",
    "iso:country":"DE",
    "name:deu_x_preferred":[
        "Calenberg"
    ],
    "name:est_x_preferred":[
        "Calenberg"
    ],
    "name:ita_x_preferred":[
        "Calenberg"
    ],
    "name:und_x_variant":[
        "Kalenberg"
    ],
    "wof:name":"Calenberg",
    "wof:placetype":"neighbourhood"
},
  "geometry": {"coordinates":[9.16417,51.4658],"type":"Point"}
}