{
  "type": "Feature",
  "properties": {
    "gn:admin1_code":"3.0",
    "gn:admin2_code":"0.0",
    "gn:admin3_code":"4011.0",
    "gn:admin4_code":"4011000.0",
    "gn:asciiname":"Industriehaefen",
    "gn:country_code":"DE",
    "gn:dem":4,
    "gn:feature_class":"P",
    "gn:feature_code":"PPL",
    "gn:name":"Industrieh\u00e4fen",
    "gn:population":0,
    "gn:timezone":"Europe/Berlin",
    "iso:country":"DE",
    "wof:name":"Industriehaefen",
    "wof:placetype":"neighbourhood"
},
  "geometry": {"coordinates":[8.73259,53.1219],"type":"Point"}
}