{
  "type": "Feature",
  "properties": {
    "gn:country":"DE",
    "gn:fcode":"PPL",
    "gn:population":0,
    "iso:country":"DE",
    "name:als_x_preferred":[
        "Deutsch"
    ],
    "name:cat_x_preferred":[
        "Deutsch"
    ],
    "name:ces_x_preferred":[
        "Deutsch"
    ],
    "name:deu_x_preferred":[
        "Deutsch"
    ],
    "name:fra_x_preferred":[
        "Deutsch"
    ],
    "name:heb_x_preferred":[
        "\u05d3\u05d5\u05d9\u05d8\u05e9"
    ],
    "name:hun_x_preferred":[
        "Deutsch"
    ],
    "name:ita_x_preferred":[
        "Deutsch"
    ],
    "name:jpn_x_preferred":[
        "\u30c9\u30a4\u30c3\u30c1\u30e5"
    ],
    "name:kor_x_preferred":[
        "\ub3c4\uc774\uce58"
    ],
    "name:nld_x_preferred":[
        "Deutsch"
    ],
    "name:pol_x_preferred":[
        "Deutsch"
    ],
    "name:por_x_preferred":[
        "Deutsch"
    ],
    "name:ron_x_preferred":[
        "Deutsch"
    ],
    "name:rus_x_preferred":[
        "\u0414\u043e\u0439\u0447"
    ],
    "name:spa_x_preferred":[
        "Deutsch"
    ],
    "name:swe_x_preferred":[
        "Deutsch"
    ],
    "name:tha_x_preferred":[
        "Deutsch"
    ],
    "name:zho_x_preferred":[
        "\u5fb7\u610f\u5fd7"
    ],
    "qs_pg:aaroncc":"DE",
    "qs_pg:gn_country":"DE",
    "qs_pg:gn_fcode":"PPL",
    "qs_pg:gn_pop":0,
    "qs_pg:name":"Deutsch",
    "qs_pg:name_adm0":"Deutschland",
    "qs_pg:name_adm1":"Sachsen-Anhalt",
    "qs_pg:photos_9r":0,
    "qs_pg:photos_sr":0,
    "qs_pg:pop_sr":0,
    "qs_pg:qs_pg_placetype":"locality",
    "qs_pg:qs_pg_placetype_gp":"Town",
    "qs_pg:woe_adm0":23424829,
    "woe:adm0_id":23424829,
    "woe:name_adm0":"Deutschland",
    "woe:name_adm1":"Sachsen-Anhalt",
    "woe:placetype":"Town",
    "wof:name":"Deutsch",
    "wof:placetype":"neighbourhood"
},
  "geometry": {"coordinates":[11.58625,52.96515],"type":"Point"}
}