{
  "type": "Feature",
  "properties": {
    "gn:admin1_code":"11",
    "gn:admin2_code":"0.0",
    "gn:admin3_code":"12067.0",
    "gn:admin4_code":"12067426.0",
    "gn:asciiname":"Klein Rietz",
    "gn:country_code":"DE",
    "gn:dem":65,
    "gn:feature_class":"P",
    "gn:feature_code":"PPL",
    "gn:name":"Klein Rietz",
    "gn:population":0,
    "gn:timezone":"Europe/Berlin",
    "iso:country":"DE",
    "wof:name":"Klein Rietz",
    "wof:placetype":"neighbourhood"
},
  "geometry": {"coordinates":[14.19119,52.20914000000001],"type":"Point"}
}