{
  "type": "Feature",
  "properties": {
    "gn:admin1_code":"10.0",
    "gn:admin2_code":"00",
    "gn:admin3_code":"1055.0",
    "gn:admin4_code":"1055035.0",
    "gn:asciiname":"Wilmsdorf",
    "gn:country_code":"DE",
    "gn:dem":4,
    "gn:feature_class":"P",
    "gn:feature_code":"PPL",
    "gn:name":"Wilmsdorf",
    "gn:population":0,
    "gn:timezone":"Europe/Berlin",
    "iso:country":"DE",
    "wof:name":"Wilmsdorf",
    "wof:placetype":"neighbourhood"
},
  "geometry": {"coordinates":[10.7843,53.95667],"type":"Point"}
}