{
  "type": "Feature",
  "properties": {
    "iso:country":"DE",
    "wof:name":"Hellerberge",
    "wof:placetype":"neighbourhood"
},
  "geometry": {"coordinates":[13.74317000895005,51.09694623699545],"type":"Point"}
}