{
  "type": "Feature",
  "properties": {
    "gn:admin1_code":"6",
    "gn:admin2_code":"0.0",
    "gn:admin3_code":"3356.0",
    "gn:admin4_code":"3356002.0",
    "gn:asciiname":"Otterstein",
    "gn:country_code":"DE",
    "gn:dem":6,
    "gn:feature_class":"P",
    "gn:feature_code":"PPL",
    "gn:name":"Otterstein",
    "gn:population":0,
    "gn:timezone":"Europe/Berlin",
    "iso:country":"DE",
    "wof:name":"Otterstein",
    "wof:placetype":"neighbourhood"
},
  "geometry": {"coordinates":[8.97445,53.21403000000001],"type":"Point"}
}