{
  "type": "Feature",
  "properties": {
    "gn:admin1_code":"2",
    "gn:admin2_code":"92.0",
    "gn:admin3_code":"9277.0",
    "gn:admin4_code":"9277114.0",
    "gn:asciiname":"Ed",
    "gn:country_code":"DE",
    "gn:dem":418,
    "gn:feature_class":"P",
    "gn:feature_code":"PPL",
    "gn:name":"Ed",
    "gn:population":0,
    "gn:timezone":"Europe/Berlin",
    "iso:country":"DE",
    "wof:name":"Ed",
    "wof:placetype":"neighbourhood"
},
  "geometry": {"coordinates":[13.02905,48.48647],"type":"Point"}
}