{
  "type": "Feature",
  "properties": {
    "gn:admin1_code":"13",
    "gn:admin2_code":"0.0",
    "gn:admin3_code":"14522.0",
    "gn:admin4_code":"14522360.0",
    "gn:asciiname":"Thalheim",
    "gn:country_code":"DE",
    "gn:dem":248,
    "gn:feature_class":"P",
    "gn:feature_code":"PPL",
    "gn:name":"Thalheim",
    "gn:population":0,
    "gn:timezone":"Europe/Berlin",
    "iso:country":"DE",
    "name:als_x_preferred":[
        "Thalheim"
    ],
    "name:ceb_x_preferred":[
        "Thalheim"
    ],
    "name:deu_x_preferred":[
        "Thalheim"
    ],
    "name:epo_x_preferred":[
        "Thalheim"
    ],
    "name:fra_x_preferred":[
        "Thalheim"
    ],
    "name:ita_x_preferred":[
        "Thalheim"
    ],
    "name:nld_x_preferred":[
        "Thalheim"
    ],
    "name:pol_x_preferred":[
        "Thalheim"
    ],
    "name:swe_x_preferred":[
        "Thalheim"
    ],
    "wof:name":"Thalheim",
    "wof:placetype":"neighbourhood"
},
  "geometry": {"coordinates":[12.88318,51.0016],"type":"Point"}
}