{
  "type": "Feature",
  "properties": {
    "gn:admin1_code":"13",
    "gn:admin2_code":"0.0",
    "gn:admin3_code":"14730.0",
    "gn:admin4_code":"14730100.0",
    "gn:asciiname":"Sueptitz",
    "gn:country_code":"DE",
    "gn:dem":101,
    "gn:feature_class":"P",
    "gn:feature_code":"PPL",
    "gn:name":"S\u00fcptitz",
    "gn:population":0,
    "gn:timezone":"Europe/Berlin",
    "iso:country":"DE",
    "name:deu_x_preferred":[
        "S\u00fcptitz"
    ],
    "wof:name":"Sueptitz",
    "wof:placetype":"neighbourhood"
},
  "geometry": {"coordinates":[12.9269,51.56556],"type":"Point"}
}