{
  "type": "Feature",
  "properties": {
    "gn:admin1_code":"5.0",
    "gn:admin2_code":"64.0",
    "gn:admin3_code":"6437.0",
    "gn:admin4_code":"6437011.0",
    "gn:asciiname":"Bremhof",
    "gn:country_code":"DE",
    "gn:dem":392,
    "gn:feature_class":"P",
    "gn:feature_code":"PPL",
    "gn:name":"Bremhof",
    "gn:population":0,
    "gn:timezone":"Europe/Berlin",
    "iso:country":"DE",
    "wof:name":"Bremhof",
    "wof:placetype":"neighbourhood"
},
  "geometry": {"coordinates":[9.1106,49.73163],"type":"Point"}
}