{
  "type": "Feature",
  "properties": {
    "gn:gn_country":"DE",
    "gn:gn_fcode":"PPLA4",
    "gn:gn_pop":208,
    "gn:population":208,
    "iso:country":"DE",
    "name:baq_x_preferred":[
        "Agethorst"
    ],
    "name:chi_x_preferred":[
        "\u963f\u683c\u6258\u5c14\u65af\u7279"
    ],
    "name:dan_x_preferred":[
        "Agethorst"
    ],
    "name:dut_x_preferred":[
        "Agethorst"
    ],
    "name:eng_x_preferred":[
        "Agethorst"
    ],
    "name:epo_x_preferred":[
        "Agethorst"
    ],
    "name:fre_x_preferred":[
        "Agethorst"
    ],
    "name:ger_x_preferred":[
        "Agethorst"
    ],
    "name:hun_x_preferred":[
        "Agethorst"
    ],
    "name:ita_x_preferred":[
        "Agethorst"
    ],
    "name:kaz_x_preferred":[
        "\u0410\u0433\u0435\u0442\u043e\u0440\u0441\u0442"
    ],
    "name:kir_x_preferred":[
        "\u0410\u0433\u0435\u0442\u043e\u0440\u0441\u0442"
    ],
    "name:mac_x_preferred":[
        "\u0410\u0433\u0435\u0442\u0445\u043e\u0440\u0441\u0442"
    ],
    "name:may_x_preferred":[
        "Agethorst"
    ],
    "name:nob_x_preferred":[
        "Agethorst"
    ],
    "name:per_x_preferred":[
        "\u0627\u06cc\u062c\u062a\u0627\u0631\u0633\u062a"
    ],
    "name:pol_x_preferred":[
        "Agethorst"
    ],
    "name:por_x_preferred":[
        "Agethorst"
    ],
    "name:rum_x_preferred":[
        "Agethorst"
    ],
    "name:rus_x_preferred":[
        "\u0410\u0433\u0435\u0442\u043e\u0440\u0441\u0442"
    ],
    "name:spa_x_preferred":[
        "Agethorst"
    ],
    "name:srp_x_preferred":[
        "\u0410\u0433\u0435\u0442\u043e\u0440\u0441\u0442"
    ],
    "name:tur_x_preferred":[
        "Agethorst"
    ],
    "name:ukr_x_preferred":[
        "\u0410\u0433\u0435\u0442\u043e\u0440\u0441\u0442"
    ],
    "name:urd_x_preferred":[
        "\u0627\u06cc\u062c \u062a\u06be\u0627\u0631\u0633\u0679"
    ],
    "name:uzb_x_preferred":[
        "Agethorst"
    ],
    "name:vie_x_preferred":[
        "Agethorst"
    ],
    "name:vol_x_preferred":[
        "Agethorst"
    ],
    "name:war_x_preferred":[
        "Agethorst"
    ],
    "qs_pg:aaroncc":"DE",
    "qs_pg:gn_country":"DE",
    "qs_pg:gn_fcode":"PPLA4",
    "qs_pg:gn_pop":208,
    "qs_pg:name":"Agethorst",
    "qs_pg:photos_9r":0,
    "qs_pg:photos_sr":0,
    "qs_pg:pop_sr":2,
    "qs_pg:qs_pg_placetype":"locality",
    "wof:name":"Agethorst",
    "wof:placetype":"locality",
    "wof:population":208
},
  "geometry": {"coordinates":[9.4359,54.01947],"type":"Point"}
}