{
  "type": "Feature",
  "properties": {
    "gn:admin1_code":"13",
    "gn:admin2_code":"0.0",
    "gn:admin3_code":"14625.0",
    "gn:admin4_code":"14625570.0",
    "gn:asciiname":"Burghammer",
    "gn:country_code":"DE",
    "gn:dem":117,
    "gn:feature_class":"P",
    "gn:feature_code":"PPL",
    "gn:name":"Burghammer",
    "gn:population":0,
    "gn:timezone":"Europe/Berlin",
    "iso:country":"DE",
    "name:hsb_x_preferred":[
        "B\u00f3rkhamor"
    ],
    "wof:name":"Burghammer",
    "wof:placetype":"neighbourhood"
},
  "geometry": {"coordinates":[14.37151,51.47581],"type":"Point"}
}