{
  "type": "Feature",
  "properties": {
    "gn:admin1_code":"11",
    "gn:admin2_code":"0.0",
    "gn:admin3_code":"12068.0",
    "gn:admin4_code":"12068353.0",
    "gn:asciiname":"Paulshorst",
    "gn:country_code":"DE",
    "gn:dem":68,
    "gn:feature_class":"P",
    "gn:feature_code":"PPL",
    "gn:name":"Paulshorst",
    "gn:population":0,
    "gn:timezone":"Europe/Berlin",
    "iso:country":"DE",
    "wof:name":"Paulshorst",
    "wof:placetype":"neighbourhood"
},
  "geometry": {"coordinates":[12.91531,53.11522],"type":"Point"}
}