{
  "type": "Feature",
  "properties": {
    "iso:country":"DE",
    "wof:name":"Siebeneick",
    "wof:placetype":"neighbourhood"
},
  "geometry": {"coordinates":[7.11712643367018,51.29178352876587],"type":"Point"}
}