{
  "type": "Feature",
  "properties": {
    "gn:admin1_code":"11",
    "gn:admin2_code":"0.0",
    "gn:admin3_code":"12063.0",
    "gn:admin4_code":"12063212.0",
    "gn:asciiname":"Damme",
    "gn:country_code":"DE",
    "gn:dem":31,
    "gn:feature_class":"P",
    "gn:feature_code":"PPL",
    "gn:name":"Damme",
    "gn:population":0,
    "gn:timezone":"Europe/Berlin",
    "iso:country":"DE",
    "name:ara_x_preferred":[
        "\u062f\u0627\u0645\u0647"
    ],
    "name:bre_x_preferred":[
        "Damme"
    ],
    "name:bul_x_preferred":[
        "\u0414\u0430\u043c\u0435"
    ],
    "name:cat_x_preferred":[
        "Damme"
    ],
    "name:deu_x_preferred":[
        "Damme"
    ],
    "name:epo_x_preferred":[
        "Damme"
    ],
    "name:eus_x_preferred":[
        "Damme"
    ],
    "name:fas_x_preferred":[
        "\u062f\u0645"
    ],
    "name:fra_x_preferred":[
        "Damme"
    ],
    "name:ita_x_preferred":[
        "Damme"
    ],
    "name:jpn_x_preferred":[
        "\u30c0\u30f3\u30e1"
    ],
    "name:kor_x_preferred":[
        "\ub2e4\uba38"
    ],
    "name:lat_x_preferred":[
        "Dammum"
    ],
    "name:lim_x_preferred":[
        "Damme"
    ],
    "name:ltz_x_preferred":[
        "Damme"
    ],
    "name:nld_x_preferred":[
        "Damme"
    ],
    "name:nor_x_preferred":[
        "Damme"
    ],
    "name:oci_x_preferred":[
        "Damme"
    ],
    "name:pol_x_preferred":[
        "Damme"
    ],
    "name:por_x_preferred":[
        "Damme"
    ],
    "name:ron_x_preferred":[
        "Damme"
    ],
    "name:rus_x_preferred":[
        "\u0414\u0430\u043c\u043c\u0435"
    ],
    "name:slk_x_preferred":[
        "Damme"
    ],
    "name:spa_x_preferred":[
        "Damme"
    ],
    "name:swe_x_preferred":[
        "Damme"
    ],
    "name:vie_x_preferred":[
        "Damme"
    ],
    "name:vls_x_preferred":[
        "Damme"
    ],
    "name:vol_x_preferred":[
        "Damme"
    ],
    "name:war_x_preferred":[
        "Damme"
    ],
    "name:zea_x_preferred":[
        "Damme"
    ],
    "wof:name":"Damme",
    "wof:placetype":"neighbourhood"
},
  "geometry": {"coordinates":[12.56888,52.61565],"type":"Point"}
}