{
  "type": "Feature",
  "properties": {
    "gn:admin1_code":"2",
    "gn:admin2_code":"91.0",
    "gn:admin3_code":"9178.0",
    "gn:admin4_code":"9178120.0",
    "gn:asciiname":"Hollern",
    "gn:country_code":"DE",
    "gn:dem":470,
    "gn:feature_class":"P",
    "gn:feature_code":"PPL",
    "gn:name":"Hollern",
    "gn:population":0,
    "gn:timezone":"Europe/Berlin",
    "iso:country":"DE",
    "name:deu_x_preferred":[
        "Hollern"
    ],
    "wof:name":"Hollern",
    "wof:placetype":"neighbourhood"
},
  "geometry": {"coordinates":[11.59446,48.29008],"type":"Point"}
}