{
  "type": "Feature",
  "properties": {
    "gn:admin1_code":"2",
    "gn:admin2_code":"94.0",
    "gn:admin3_code":"9471.0",
    "gn:admin4_code":"9471151.0",
    "gn:asciiname":"Voitmannsdorf",
    "gn:country_code":"DE",
    "gn:dem":426,
    "gn:feature_class":"P",
    "gn:feature_code":"PPL",
    "gn:name":"Voitmannsdorf",
    "gn:population":0,
    "gn:timezone":"Europe/Berlin",
    "iso:country":"DE",
    "wof:name":"Voitmannsdorf",
    "wof:placetype":"neighbourhood"
},
  "geometry": {"coordinates":[11.20399,49.92876],"type":"Point"}
}