{
  "type": "Feature",
  "properties": {
    "gn:admin1_code":"14.0",
    "gn:admin2_code":"0.0",
    "gn:admin3_code":"15083.0",
    "gn:admin4_code":"15083415.0",
    "gn:asciiname":"Beckendorf-Neindorf",
    "gn:country_code":"DE",
    "gn:dem":130,
    "gn:feature_class":"P",
    "gn:feature_code":"PPL",
    "gn:name":"Beckendorf-Neindorf",
    "gn:population":0,
    "gn:timezone":"Europe/Berlin",
    "iso:country":"DE",
    "wof:name":"Beckendorf-Neindorf",
    "wof:placetype":"neighbourhood"
},
  "geometry": {"coordinates":[11.15559,52.09262],"type":"Point"}
}