{
  "type": "Feature",
  "properties": {
    "gn:admin1_code":"2.0",
    "gn:admin2_code":"91.0",
    "gn:admin3_code":"9183.0",
    "gn:admin4_code":"9183123.0",
    "gn:asciiname":"Asen",
    "gn:country_code":"DE",
    "gn:dem":585,
    "gn:feature_class":"P",
    "gn:feature_code":"PPL",
    "gn:name":"Asen",
    "gn:population":0,
    "gn:timezone":"Europe/Berlin",
    "iso:country":"DE",
    "name:bul_x_preferred":[
        "\u0410\u0441\u0435\u043d"
    ],
    "name:ceb_x_preferred":[
        "Asen"
    ],
    "name:deu_x_preferred":[
        "Asen"
    ],
    "name:fra_x_preferred":[
        "Asen"
    ],
    "name:ita_x_preferred":[
        "Asen"
    ],
    "name:nld_x_preferred":[
        "Asen"
    ],
    "name:swe_x_preferred":[
        "Asen"
    ],
    "name:vie_x_preferred":[
        "Asen"
    ],
    "wof:name":"Asen",
    "wof:placetype":"neighbourhood"
},
  "geometry": {"coordinates":[12.20195,48.18074],"type":"Point"}
}