{
  "type": "Feature",
  "properties": {
    "gn:admin1_code":"14",
    "gn:admin2_code":"0.0",
    "gn:admin3_code":"15084.0",
    "gn:admin4_code":"15084235.0",
    "gn:asciiname":"Moednitz",
    "gn:country_code":"DE",
    "gn:dem":142,
    "gn:feature_class":"P",
    "gn:feature_code":"PPL",
    "gn:name":"M\u00f6dnitz",
    "gn:population":0,
    "gn:timezone":"Europe/Berlin",
    "iso:country":"DE",
    "wof:name":"Moednitz",
    "wof:placetype":"neighbourhood"
},
  "geometry": {"coordinates":[12.14246,51.17208],"type":"Point"}
}