{
  "type": "Feature",
  "properties": {
    "gn:admin1_code":"2",
    "gn:admin2_code":"95.0",
    "gn:admin3_code":"9571.0",
    "gn:admin4_code":"9571115.0",
    "gn:asciiname":"Voggendorf",
    "gn:country_code":"DE",
    "gn:dem":424,
    "gn:feature_class":"P",
    "gn:feature_code":"PPL",
    "gn:name":"Voggendorf",
    "gn:population":0,
    "gn:timezone":"Europe/Berlin",
    "iso:country":"DE",
    "wof:name":"Voggendorf",
    "wof:placetype":"neighbourhood"
},
  "geometry": {"coordinates":[10.59228,49.16358],"type":"Point"}
}