{
  "type": "Feature",
  "properties": {
    "gn:admin1_code":"7",
    "gn:admin2_code":"57.0",
    "gn:admin3_code":"5770.0",
    "gn:admin4_code":"5770044.0",
    "gn:asciiname":"Stelle",
    "gn:country_code":"DE",
    "gn:dem":52,
    "gn:feature_class":"P",
    "gn:feature_code":"PPLL",
    "gn:name":"Stelle",
    "gn:population":0,
    "gn:timezone":"Europe/Berlin",
    "iso:country":"DE",
    "name:ceb_x_preferred":[
        "Stelle"
    ],
    "name:deu_x_preferred":[
        "Stelle"
    ],
    "name:est_x_preferred":[
        "Stelle"
    ],
    "name:ita_x_preferred":[
        "Stelle"
    ],
    "name:nld_x_preferred":[
        "Stelle"
    ],
    "name:pol_x_preferred":[
        "Stelle"
    ],
    "name:swe_x_preferred":[
        "Stelle"
    ],
    "name:vol_x_preferred":[
        "Stelle"
    ],
    "wof:name":"Stelle",
    "wof:placetype":"neighbourhood"
},
  "geometry": {"coordinates":[8.46667,52.43333000000001],"type":"Point"}
}