{
  "type": "Feature",
  "properties": {
    "gn:admin1_code":"11",
    "gn:admin2_code":"0.0",
    "gn:admin3_code":"12066.0",
    "gn:admin4_code":"12066008.0",
    "gn:asciiname":"Feldschaenke",
    "gn:country_code":"DE",
    "gn:dem":101,
    "gn:feature_class":"P",
    "gn:feature_code":"PPL",
    "gn:name":"Feldsch\u00e4nke",
    "gn:population":0,
    "gn:timezone":"Europe/Berlin",
    "iso:country":"DE",
    "wof:name":"Feldschaenke",
    "wof:placetype":"neighbourhood"
},
  "geometry": {"coordinates":[14.06667,51.66667],"type":"Point"}
}