{
  "type": "Feature",
  "properties": {
    "gn:admin1_code":"7.0",
    "gn:admin2_code":"053",
    "gn:admin3_code":"5382.0",
    "gn:admin4_code":"5382040.0",
    "gn:asciiname":"Wiescheid",
    "gn:country_code":"DE",
    "gn:dem":214,
    "gn:feature_class":"P",
    "gn:feature_code":"PPL",
    "gn:name":"Wiescheid",
    "gn:population":0,
    "gn:timezone":"Europe/Berlin",
    "iso:country":"DE",
    "wof:name":"Wiescheid",
    "wof:placetype":"neighbourhood"
},
  "geometry": {"coordinates":[7.32518,50.82473],"type":"Point"}
}