{
  "type": "Feature",
  "properties": {
    "iso:country":"DE",
    "wof:name":"Lahe",
    "wof:placetype":"neighbourhood"
},
  "geometry": {"coordinates":[9.82647715900285,52.41886420565709],"type":"Point"}
}