{
  "type": "Feature",
  "properties": {
    "iso:country":"DE",
    "name:deu_x_preferred":[
        "Lahe"
    ],
    "name:est_x_preferred":[
        "Lahe"
    ],
    "name:hye_x_preferred":[
        "\u053c\u0561\u0570\u0565"
    ],
    "name:sco_x_preferred":[
        "Lahe"
    ],
    "name:ukr_x_preferred":[
        "\u041b\u0430\u0433\u0435"
    ],
    "name:vol_x_preferred":[
        "Lahe"
    ],
    "wof:name":"Lahe",
    "wof:placetype":"neighbourhood"
},
  "geometry": {"coordinates":[9.82647715900285,52.41886420565709],"type":"Point"}
}