{
  "type": "Feature",
  "properties": {
    "gn:admin1_code":"5",
    "gn:admin2_code":"64.0",
    "gn:admin3_code":"6431.0",
    "gn:admin4_code":"6431017.0",
    "gn:asciiname":"Voeckelsbach",
    "gn:country_code":"DE",
    "gn:dem":309,
    "gn:feature_class":"P",
    "gn:feature_code":"PPL",
    "gn:name":"V\u00f6ckelsbach",
    "gn:population":0,
    "gn:timezone":"Europe/Berlin",
    "iso:country":"DE",
    "wof:name":"Voeckelsbach",
    "wof:placetype":"neighbourhood"
},
  "geometry": {"coordinates":[8.7706,49.5679],"type":"Point"}
}