{
  "type": "Feature",
  "properties": {
    "gn:admin1_code":"1.0",
    "gn:admin2_code":"083",
    "gn:admin3_code":"8335.0",
    "gn:admin4_code":"8335079.0",
    "gn:asciiname":"Zizenhausen",
    "gn:country_code":"DE",
    "gn:dem":528,
    "gn:feature_class":"P",
    "gn:feature_code":"PPL",
    "gn:name":"Zizenhausen",
    "gn:population":0,
    "gn:timezone":"Europe/Berlin",
    "iso:country":"DE",
    "wof:name":"Zizenhausen",
    "wof:placetype":"neighbourhood"
},
  "geometry": {"coordinates":[9.00393,47.87405],"type":"Point"}
}