{
  "type": "Feature",
  "properties": {
    "gn:admin1_code":"2",
    "gn:admin2_code":"97.0",
    "gn:admin3_code":"9780.0",
    "gn:admin4_code":"9780120.0",
    "gn:asciiname":"Hermannsberg",
    "gn:country_code":"DE",
    "gn:dem":797,
    "gn:feature_class":"P",
    "gn:feature_code":"PPL",
    "gn:name":"Hermannsberg",
    "gn:population":0,
    "gn:timezone":"Europe/Berlin",
    "iso:country":"DE",
    "name:ceb_x_preferred":[
        "Hermannsberg"
    ],
    "name:deu_x_preferred":[
        "Hermannsberg"
    ],
    "name:epo_x_preferred":[
        "Hermannsberg"
    ],
    "name:swe_x_preferred":[
        "Hermannsberg"
    ],
    "wof:name":"Hermannsberg",
    "wof:placetype":"neighbourhood"
},
  "geometry": {"coordinates":[10.3752,47.70443],"type":"Point"}
}