{
  "type": "Feature",
  "properties": {
    "gn:admin1_code":"2",
    "gn:admin2_code":"91.0",
    "gn:admin3_code":"9187.0",
    "gn:admin4_code":"9187131.0",
    "gn:asciiname":"Kirnstein",
    "gn:country_code":"DE",
    "gn:dem":475,
    "gn:feature_class":"P",
    "gn:feature_code":"PPL",
    "gn:name":"Kirnstein",
    "gn:population":0,
    "gn:timezone":"Europe/Berlin",
    "iso:country":"DE",
    "wof:name":"Kirnstein",
    "wof:placetype":"neighbourhood"
},
  "geometry": {"coordinates":[12.15493,47.69289000000001],"type":"Point"}
}