{
  "type": "Feature",
  "properties": {
    "gn:admin1_code":"8",
    "gn:admin2_code":"0.0",
    "gn:admin3_code":"7138.0",
    "gn:admin4_code":"7138045.0",
    "gn:asciiname":"Huellenberg",
    "gn:country_code":"DE",
    "gn:dem":193,
    "gn:feature_class":"P",
    "gn:feature_code":"PPL",
    "gn:name":"H\u00fcllenberg",
    "gn:population":0,
    "gn:timezone":"Europe/Berlin",
    "iso:country":"DE",
    "wof:name":"Huellenberg",
    "wof:placetype":"neighbourhood"
},
  "geometry": {"coordinates":[7.41216,50.45248],"type":"Point"}
}