{
  "type": "Feature",
  "properties": {
    "gn:admin1_code":"5",
    "gn:admin2_code":"65.0",
    "gn:admin3_code":"6534.0",
    "gn:admin4_code":"6534010.0",
    "gn:asciiname":"Kehlnbach",
    "gn:country_code":"DE",
    "gn:dem":277,
    "gn:feature_class":"P",
    "gn:feature_code":"PPL",
    "gn:name":"Kehlnbach",
    "gn:population":0,
    "gn:timezone":"Europe/Berlin",
    "iso:country":"DE",
    "wof:name":"Kehlnbach",
    "wof:placetype":"neighbourhood"
},
  "geometry": {"coordinates":[8.56416,50.77035],"type":"Point"}
}