{
  "type": "Feature",
  "properties": {
    "gn:admin1_code":"2",
    "gn:admin2_code":"93.0",
    "gn:admin3_code":"9372.0",
    "gn:admin4_code":"9372135.0",
    "gn:asciiname":"Thenhof",
    "gn:country_code":"DE",
    "gn:dem":526,
    "gn:feature_class":"P",
    "gn:feature_code":"PPL",
    "gn:name":"Thenhof",
    "gn:population":0,
    "gn:timezone":"Europe/Berlin",
    "iso:country":"DE",
    "wof:name":"Thenhof",
    "wof:placetype":"neighbourhood"
},
  "geometry": {"coordinates":[12.95752,49.19769],"type":"Point"}
}