{
  "type": "Feature",
  "properties": {
    "gn:admin1_code":"2",
    "gn:admin2_code":"91.0",
    "gn:admin3_code":"9171.0",
    "gn:admin4_code":"9171119.0",
    "gn:asciiname":"Dosham",
    "gn:country_code":"DE",
    "gn:dem":471,
    "gn:feature_class":"P",
    "gn:feature_code":"PPL",
    "gn:name":"D\u00f6sham",
    "gn:population":0,
    "gn:timezone":"Europe/Berlin",
    "iso:country":"DE",
    "wof:name":"Dosham",
    "wof:placetype":"neighbourhood"
},
  "geometry": {"coordinates":[12.69461,48.13352],"type":"Point"}
}