{
  "type": "Feature",
  "properties": {
    "gn:admin1_code":"6.0",
    "gn:admin2_code":"0.0",
    "gn:admin3_code":"3151.0",
    "gn:admin4_code":"3151006.0",
    "gn:asciiname":"Allerbuettel",
    "gn:country_code":"DE",
    "gn:dem":59,
    "gn:elevation":"60.0",
    "gn:feature_class":"P",
    "gn:feature_code":"PPL",
    "gn:name":"Allerb\u00fcttel",
    "gn:population":776,
    "gn:timezone":"Europe/Berlin",
    "iso:country":"DE",
    "wof:name":"Allerbuettel",
    "wof:placetype":"neighbourhood",
    "wof:population":776
},
  "geometry": {"coordinates":[10.63889,52.42074],"type":"Point"}
}