{
  "type": "Feature",
  "properties": {
    "gn:country":"DE",
    "gn:fcode":"PPL",
    "gn:population":0,
    "iso:country":"DE",
    "name:deu_x_preferred":[
        "Osterheide"
    ],
    "name:est_x_preferred":[
        "Osterheide"
    ],
    "name:fas_x_preferred":[
        "\u0627\u0648\u0634\u062a\u0631\u0647\u0627\u06cc\u062f\u0647"
    ],
    "name:ita_x_preferred":[
        "Osterheide"
    ],
    "name:msa_x_preferred":[
        "Osterheide"
    ],
    "name:nld_x_preferred":[
        "Osterheide"
    ],
    "name:pol_x_preferred":[
        "Osterheide"
    ],
    "name:por_x_preferred":[
        "Osterheide"
    ],
    "name:ron_x_preferred":[
        "Osterheide"
    ],
    "name:ukr_x_preferred":[
        "\u041e\u0441\u0442\u0435\u0440\u0433\u0430\u0439\u0434\u0435"
    ],
    "name:war_x_preferred":[
        "Osterheide"
    ],
    "name:zho_x_preferred":[
        "\u5965\u65af\u7279\u8d56\u5fb7"
    ],
    "qs_pg:aaroncc":"DE",
    "qs_pg:gn_country":"DE",
    "qs_pg:gn_fcode":"PPL",
    "qs_pg:gn_pop":0,
    "qs_pg:name":"Osterheide",
    "qs_pg:name_adm0":"Deutschland",
    "qs_pg:name_adm1":"Nordrhein-Westfalen",
    "qs_pg:photos":80,
    "qs_pg:photos_1k":16,
    "qs_pg:photos_9k":1,
    "qs_pg:photos_9r":3,
    "qs_pg:photos_all":80,
    "qs_pg:photos_sr":3,
    "qs_pg:pop_sr":0,
    "qs_pg:qs_pg_placetype":"locality",
    "qs_pg:qs_pg_placetype_gp":"Town",
    "qs_pg:woe_adm0":23424829,
    "woe:adm0_id":23424829,
    "woe:name_adm0":"Deutschland",
    "woe:name_adm1":"Nordrhein-Westfalen",
    "woe:placetype":"Town",
    "wof:name":"Osterheide",
    "wof:placetype":"neighbourhood"
},
  "geometry": {"coordinates":[8.71336,51.97864],"type":"Point"}
}