{
  "type": "Feature",
  "properties": {
    "gn:admin1_code":"2",
    "gn:admin2_code":"92.0",
    "gn:admin3_code":"9271.0",
    "gn:admin4_code":"9271119.0",
    "gn:asciiname":"Simmling",
    "gn:country_code":"DE",
    "gn:dem":439,
    "gn:feature_class":"P",
    "gn:feature_code":"PPLL",
    "gn:name":"Simmling",
    "gn:population":0,
    "gn:timezone":"Europe/Berlin",
    "iso:country":"DE",
    "wof:name":"Simmling",
    "wof:placetype":"neighbourhood"
},
  "geometry": {"coordinates":[12.98567,48.83229],"type":"Point"}
}