{
  "type": "Feature",
  "properties": {
    "gn:admin1_code":"11",
    "gn:admin2_code":"0.0",
    "gn:admin3_code":"12068.0",
    "gn:admin4_code":"12068468.0",
    "gn:asciiname":"Randow",
    "gn:country_code":"DE",
    "gn:dem":73,
    "gn:feature_class":"P",
    "gn:feature_code":"PPL",
    "gn:name":"Randow",
    "gn:population":0,
    "gn:timezone":"Europe/Berlin",
    "iso:country":"DE",
    "name:ceb_x_preferred":[
        "Randow"
    ],
    "name:deu_x_preferred":[
        "Randow"
    ],
    "name:mkd_x_preferred":[
        "\u0420\u0430\u043d\u0434\u043e\u0432"
    ],
    "name:nld_x_preferred":[
        "Randow"
    ],
    "name:pol_x_preferred":[
        "Randow"
    ],
    "wof:name":"Randow",
    "wof:placetype":"neighbourhood"
},
  "geometry": {"coordinates":[12.55566,53.19565],"type":"Point"}
}