{
  "type": "Feature",
  "properties": {
    "gn:admin1_code":"2.0",
    "gn:admin2_code":"096",
    "gn:admin3_code":"9678.0",
    "gn:admin4_code":"9678181.0",
    "gn:asciiname":"Wettringen",
    "gn:country_code":"DE",
    "gn:dem":302,
    "gn:feature_class":"P",
    "gn:feature_code":"PPL",
    "gn:name":"Wettringen",
    "gn:population":0,
    "gn:timezone":"Europe/Berlin",
    "iso:country":"DE",
    "wof:name":"Wettringen",
    "wof:placetype":"neighbourhood"
},
  "geometry": {"coordinates":[10.41482,50.1681],"type":"Point"}
}