{
  "type": "Feature",
  "properties": {
    "gn:admin1_code":"7",
    "gn:admin2_code":"59.0",
    "gn:admin3_code":"5978.0",
    "gn:admin4_code":"5978024.0",
    "gn:asciiname":"Lippholthausen",
    "gn:country_code":"DE",
    "gn:dem":70,
    "gn:feature_class":"P",
    "gn:feature_code":"PPL",
    "gn:name":"Lippholthausen",
    "gn:population":0,
    "gn:timezone":"Europe/Berlin",
    "iso:country":"DE",
    "name:und_x_variant":[
        "Lippoltshausen",
        "Lippholthausen"
    ],
    "wof:name":"Lippholthausen",
    "wof:placetype":"neighbourhood"
},
  "geometry": {"coordinates":[7.48114,51.61384],"type":"Point"}
}