{
  "type": "Feature",
  "properties": {
    "gn:admin1_code":"13",
    "gn:admin2_code":"0.0",
    "gn:admin3_code":"14626.0",
    "gn:admin4_code":"14626270.0",
    "gn:asciiname":"Lehdehaeuser",
    "gn:country_code":"DE",
    "gn:dem":355,
    "gn:feature_class":"P",
    "gn:feature_code":"PPL",
    "gn:name":"Lehdeh\u00e4user",
    "gn:population":0,
    "gn:timezone":"Europe/Berlin",
    "iso:country":"DE",
    "wof:name":"Lehdehaeuser",
    "wof:placetype":"neighbourhood"
},
  "geometry": {"coordinates":[14.58259,51.07947],"type":"Point"}
}