{
  "type": "Feature",
  "properties": {
    "iso:country":"DE",
    "qs_pg:aaroncc":"DE",
    "qs_pg:name":"Clausmoorhof",
    "qs_pg:name_adm0":"Deutschland",
    "qs_pg:name_adm1":"Niedersachsen",
    "qs_pg:photos":39,
    "qs_pg:photos_1k":8,
    "qs_pg:photos_9k":1,
    "qs_pg:photos_9r":2,
    "qs_pg:photos_all":39,
    "qs_pg:photos_sr":2,
    "qs_pg:pop_sr":0,
    "qs_pg:qs_pg_placetype":"locality",
    "qs_pg:qs_pg_placetype_gp":"Town",
    "qs_pg:woe_adm0":23424829,
    "woe:adm0_id":23424829,
    "woe:name_adm0":"Deutschland",
    "woe:name_adm1":"Niedersachsen",
    "woe:placetype":"Town",
    "wof:name":"Clausmoorhof",
    "wof:placetype":"neighbourhood"
},
  "geometry": {"coordinates":[10.617756,52.45308],"type":"Point"}
}