{
  "type": "Feature",
  "properties": {
    "gn:admin1_code":"2",
    "gn:admin2_code":"92.0",
    "gn:admin3_code":"9277.0",
    "gn:admin4_code":"9277119.0",
    "gn:asciiname":"Sparod",
    "gn:country_code":"DE",
    "gn:dem":441,
    "gn:feature_class":"P",
    "gn:feature_code":"PPL",
    "gn:name":"Spar\u00f6d",
    "gn:population":0,
    "gn:timezone":"Europe/Berlin",
    "iso:country":"DE",
    "wof:name":"Sparod",
    "wof:placetype":"neighbourhood"
},
  "geometry": {"coordinates":[12.71167,48.49646],"type":"Point"}
}