{
  "type": "Feature",
  "properties": {
    "gn:country":"DE",
    "gn:fcode":"PPL",
    "gn:population":684,
    "iso:country":"DE",
    "name:bak_x_preferred":[
        "\u0420\u0438\u043f\u043f\u0430\u0445"
    ],
    "name:ceb_x_preferred":[
        "Rippach"
    ],
    "name:deu_x_preferred":[
        "Rippach"
    ],
    "name:epo_x_preferred":[
        "Rippach"
    ],
    "name:fas_x_preferred":[
        "\u0631\u06cc\u067e\u0627\u062e"
    ],
    "name:ita_x_preferred":[
        "Rippach"
    ],
    "name:kaz_x_preferred":[
        "\u0420\u0438\u043f\u043f\u0430\u0445"
    ],
    "name:kir_x_preferred":[
        "\u0420\u0438\u043f\u043f\u0430\u0445"
    ],
    "name:mkd_x_preferred":[
        "\u0420\u0438\u043f\u0430\u0445"
    ],
    "name:nld_x_preferred":[
        "Rippach"
    ],
    "name:ron_x_preferred":[
        "Rippach"
    ],
    "name:rus_x_preferred":[
        "\u0420\u0438\u043f\u043f\u0430\u0445"
    ],
    "name:uzb_x_preferred":[
        "Rippach"
    ],
    "name:vie_x_preferred":[
        "Rippach"
    ],
    "name:vol_x_preferred":[
        "Rippach"
    ],
    "qs_pg:aaroncc":"DE",
    "qs_pg:gn_country":"DE",
    "qs_pg:gn_fcode":"PPL",
    "qs_pg:gn_pop":684,
    "qs_pg:name":"Rippach",
    "qs_pg:name_adm0":"Deutschland",
    "qs_pg:name_adm1":"Sachsen-Anhalt",
    "qs_pg:photos_9r":0,
    "qs_pg:photos_sr":0,
    "qs_pg:pop_sr":2,
    "qs_pg:qs_pg_placetype":"locality",
    "qs_pg:qs_pg_placetype_gp":"Town",
    "qs_pg:woe_adm0":23424829,
    "woe:adm0_id":23424829,
    "woe:name_adm0":"Deutschland",
    "woe:name_adm1":"Sachsen-Anhalt",
    "woe:placetype":"Town",
    "wof:name":"Rippach",
    "wof:placetype":"neighbourhood",
    "wof:population":684
},
  "geometry": {"coordinates":[12.06336,51.2266],"type":"Point"}
}