{
  "type": "Feature",
  "properties": {
    "gn:admin1_code":"2",
    "gn:admin2_code":"91.0",
    "gn:admin3_code":"9187.0",
    "gn:admin4_code":"9187167.0",
    "gn:asciiname":"Gogging",
    "gn:country_code":"DE",
    "gn:dem":505,
    "gn:feature_class":"P",
    "gn:feature_code":"PPL",
    "gn:name":"G\u00f6gging",
    "gn:population":0,
    "gn:timezone":"Europe/Berlin",
    "iso:country":"DE",
    "wof:name":"Gogging",
    "wof:placetype":"neighbourhood"
},
  "geometry": {"coordinates":[12.19723,47.82704],"type":"Point"}
}