{
  "type": "Feature",
  "properties": {
    "gn:admin1_code":"7",
    "gn:admin2_code":"59.0",
    "gn:admin3_code":"5978.0",
    "gn:admin4_code":"5978036.0",
    "gn:asciiname":"Ringebrauck",
    "gn:country_code":"DE",
    "gn:dem":116,
    "gn:feature_class":"P",
    "gn:feature_code":"PPL",
    "gn:name":"Ringebrauck",
    "gn:population":0,
    "gn:timezone":"Europe/Berlin",
    "iso:country":"DE",
    "wof:name":"Ringebrauck",
    "wof:placetype":"neighbourhood"
},
  "geometry": {"coordinates":[7.65407,51.51189],"type":"Point"}
}