{
  "type": "Feature",
  "properties": {
    "gn:admin1_code":"7.0",
    "gn:admin2_code":"51.0",
    "gn:admin3_code":"5158.0",
    "gn:admin4_code":"5158032.0",
    "gn:asciiname":"Bonsfeld",
    "gn:country_code":"DE",
    "gn:dem":109,
    "gn:feature_class":"P",
    "gn:feature_code":"PPL",
    "gn:name":"Bonsfeld",
    "gn:population":0,
    "gn:timezone":"Europe/Berlin",
    "iso:country":"DE",
    "wof:name":"Bonsfeld",
    "wof:placetype":"neighbourhood"
},
  "geometry": {"coordinates":[7.13064,51.36337],"type":"Point"}
}