{
  "type": "Feature",
  "properties": {
    "gn:admin1_code":"5.0",
    "gn:admin2_code":"066",
    "gn:admin3_code":"6636.0",
    "gn:admin4_code":"6636016.0",
    "gn:asciiname":"Ziegenhagen",
    "gn:country_code":"DE",
    "gn:dem":208,
    "gn:feature_class":"P",
    "gn:feature_code":"PPL",
    "gn:name":"Ziegenhagen",
    "gn:population":0,
    "gn:timezone":"Europe/Berlin",
    "iso:country":"DE",
    "wof:name":"Ziegenhagen",
    "wof:placetype":"neighbourhood"
},
  "geometry": {"coordinates":[9.75755,51.36647],"type":"Point"}
}