{
  "type": "Feature",
  "properties": {
    "gn:admin1_code":"6",
    "gn:admin2_code":"0.0",
    "gn:admin3_code":"3460.0",
    "gn:admin4_code":"3460005.0",
    "gn:asciiname":"Dersaburg",
    "gn:country_code":"DE",
    "gn:dem":91,
    "gn:feature_class":"P",
    "gn:feature_code":"PPL",
    "gn:name":"Dersaburg",
    "gn:population":0,
    "gn:timezone":"Europe/Berlin",
    "iso:country":"DE",
    "wof:name":"Dersaburg",
    "wof:placetype":"neighbourhood"
},
  "geometry": {"coordinates":[8.17846,52.55424],"type":"Point"}
}