{
  "type": "Feature",
  "properties": {
    "iso:country":"DE",
    "name:deu_x_preferred":[
        "Flugplatz Schweinfurt-S\u00fcd"
    ],
    "name:eng_x_preferred":[
        "Schweinfurt-S\u00fcd Airport"
    ],
    "name:eng_x_variant":[
        "EDFS",
        "Schweinfurt-S\u00fcd airfield"
    ],
    "name:msa_x_preferred":[
        "Lapangan Terbang Schweinfurt Sud"
    ],
    "oa:elevation_ft":"686",
    "oa:type":"small_airport",
    "woe:hierarchy":{
        "country_id":23424829,
        "county_id":12596732,
        "localadmin_id":12635420,
        "planet_id":1,
        "state_id":2345482
    },
    "wof:name":"Segelflugplatz Schweinfurt-s\u00fcd",
    "wof:placetype":"campus"
},
  "geometry": {"coordinates":[10.2494,50.0111],"type":"Point"}
}