{
  "type": "Feature",
  "properties": {
    "iso:country":"DE",
    "oa:elevation_ft":"686",
    "oa:type":"small_airport",
    "woe:hierarchy":{
        "country_id":23424829,
        "county_id":12596732,
        "localadmin_id":12635420,
        "planet_id":1,
        "state_id":2345482
    },
    "wof:name":"Segelflugplatz Schweinfurt-s\u00fcd",
    "wof:placetype":"campus"
},
  "geometry": {"coordinates":[10.2494,50.0111],"type":"Point"}
}