{
  "type": "Feature",
  "properties": {
    "gn:admin1_code":"6",
    "gn:admin2_code":"0.0",
    "gn:admin3_code":"3460.0",
    "gn:admin4_code":"3460006.0",
    "gn:asciiname":"Moorkamp",
    "gn:country_code":"DE",
    "gn:dem":30,
    "gn:feature_class":"P",
    "gn:feature_code":"PPL",
    "gn:name":"Moorkamp",
    "gn:population":0,
    "gn:timezone":"Europe/Berlin",
    "iso:country":"DE",
    "wof:name":"Moorkamp",
    "wof:placetype":"neighbourhood"
},
  "geometry": {"coordinates":[8.21726,52.67136],"type":"Point"}
}