{
  "type": "Feature",
  "properties": {
    "gn:admin1_code":"1",
    "gn:admin2_code":"83.0",
    "gn:admin3_code":"8326.0",
    "gn:admin4_code":"8326017.0",
    "gn:asciiname":"Obertal",
    "gn:country_code":"DE",
    "gn:dem":962,
    "gn:feature_class":"P",
    "gn:feature_code":"PPLL",
    "gn:name":"Obertal",
    "gn:population":0,
    "gn:timezone":"Europe/Berlin",
    "iso:country":"DE",
    "wof:name":"Obertal",
    "wof:placetype":"neighbourhood"
},
  "geometry": {"coordinates":[8.26689,48.09584],"type":"Point"}
}