{
  "type": "Feature",
  "properties": {
    "gn:admin1_code":"5.0",
    "gn:admin2_code":"066",
    "gn:admin3_code":"6636.0",
    "gn:admin4_code":"6636011.0",
    "gn:asciiname":"Wichmannshausen",
    "gn:country_code":"DE",
    "gn:dem":209,
    "gn:feature_class":"P",
    "gn:feature_code":"PPL",
    "gn:name":"Wichmannshausen",
    "gn:population":0,
    "gn:timezone":"Europe/Berlin",
    "iso:country":"DE",
    "wof:name":"Wichmannshausen",
    "wof:placetype":"neighbourhood"
},
  "geometry": {"coordinates":[9.97159,51.10851],"type":"Point"}
}