{
  "type": "Feature",
  "properties": {
    "gn:admin1_code":"15",
    "gn:admin2_code":"0.0",
    "gn:admin3_code":"16077.0",
    "gn:admin4_code":"16077042.0",
    "gn:asciiname":"Untermolbitz",
    "gn:country_code":"DE",
    "gn:dem":171,
    "gn:feature_class":"P",
    "gn:feature_code":"PPL",
    "gn:name":"Untermolbitz",
    "gn:population":0,
    "gn:timezone":"Europe/Berlin",
    "iso:country":"DE",
    "wof:name":"Untermolbitz",
    "wof:placetype":"neighbourhood"
},
  "geometry": {"coordinates":[12.40586,51.01204],"type":"Point"}
}