{
  "type": "Feature",
  "properties": {
    "gn:admin1_code":"2",
    "gn:admin2_code":"92.0",
    "gn:admin3_code":"9274.0",
    "gn:admin4_code":"9274128.0",
    "gn:asciiname":"Oberrohrenbach",
    "gn:country_code":"DE",
    "gn:dem":425,
    "gn:feature_class":"P",
    "gn:feature_code":"PPL",
    "gn:name":"Oberr\u00f6hrenbach",
    "gn:population":0,
    "gn:timezone":"Europe/Berlin",
    "iso:country":"DE",
    "wof:name":"Oberrohrenbach",
    "wof:placetype":"neighbourhood"
},
  "geometry": {"coordinates":[12.25797,48.65748],"type":"Point"}
}