{
  "type": "Feature",
  "properties": {
    "gn:admin1_code":"10",
    "gn:admin2_code":"0.0",
    "gn:admin3_code":"1061.0",
    "gn:admin4_code":"1061037.0",
    "gn:asciiname":"Moorhufen",
    "gn:country_code":"DE",
    "gn:dem":-1,
    "gn:feature_class":"P",
    "gn:feature_code":"PPL",
    "gn:name":"Moorhufen",
    "gn:population":0,
    "gn:timezone":"Europe/Berlin",
    "iso:country":"DE",
    "name:und_x_variant":[
        "Moorhofen",
        "Moorhufen"
    ],
    "wof:name":"Moorhufen",
    "wof:placetype":"neighbourhood"
},
  "geometry": {"coordinates":[9.52189,53.76872],"type":"Point"}
}