{
  "type": "Feature",
  "properties": {
    "gn:admin1_code":"2",
    "gn:admin2_code":"92.0",
    "gn:admin3_code":"9273.0",
    "gn:admin4_code":"9273125.0",
    "gn:asciiname":"Dietenhofen",
    "gn:country_code":"DE",
    "gn:dem":385,
    "gn:feature_class":"P",
    "gn:feature_code":"PPL",
    "gn:name":"Dietenhofen",
    "gn:population":0,
    "gn:timezone":"Europe/Berlin",
    "iso:country":"DE",
    "name:ara_x_preferred":[
        "\u062f\u064a\u062a\u064a\u0646\u0647\u0648\u0641\u0646"
    ],
    "name:ceb_x_preferred":[
        "Dietenhofen"
    ],
    "name:dan_x_preferred":[
        "Dietenhofen"
    ],
    "name:deu_x_preferred":[
        "Dietenhofen"
    ],
    "name:epo_x_preferred":[
        "Dietenhofen"
    ],
    "name:eus_x_preferred":[
        "Dietenhofen"
    ],
    "name:fas_x_preferred":[
        "\u062f\u06cc\u062a\u0646\u0647\u0648\u0641\u0646"
    ],
    "name:fra_x_preferred":[
        "Dietenhofen"
    ],
    "name:hun_x_preferred":[
        "Dietenhofen"
    ],
    "name:hye_x_preferred":[
        "\u0534\u056b\u057f\u0565\u0576\u0570\u0578\u0586\u0565\u0576"
    ],
    "name:ind_x_preferred":[
        "Dietenhofen"
    ],
    "name:ita_x_preferred":[
        "Dietenhofen"
    ],
    "name:jpn_x_preferred":[
        "\u30c7\u30a3\u30fc\u30c6\u30f3\u30db\u30fc\u30d5\u30a7\u30f3"
    ],
    "name:kaz_x_preferred":[
        "\u0414\u0438\u0442\u0435\u043d\u0445\u043e\u0444\u0435\u043d"
    ],
    "name:kir_x_preferred":[
        "\u0414\u0438\u0442\u0435\u043d\u0445\u043e\u0444\u0435\u043d"
    ],
    "name:lmo_x_preferred":[
        "Dietenhofen"
    ],
    "name:msa_x_preferred":[
        "Dietenhofen"
    ],
    "name:nld_x_preferred":[
        "Dietenhofen"
    ],
    "name:pol_x_preferred":[
        "Dietenhofen"
    ],
    "name:por_x_preferred":[
        "Dietenhofen"
    ],
    "name:ron_x_preferred":[
        "Dietenhofen"
    ],
    "name:rus_x_preferred":[
        "\u0414\u0438\u0442\u0435\u043d\u0445\u043e\u0444\u0435\u043d"
    ],
    "name:spa_x_preferred":[
        "Dietenhofen"
    ],
    "name:srp_x_preferred":[
        "\u0414\u0438\u0442\u0435\u043d\u0445\u043e\u0444\u0435\u043d"
    ],
    "name:ukr_x_preferred":[
        "\u0414\u0456\u0442\u0435\u043d\u0433\u043e\u0444\u0435\u043d"
    ],
    "name:uzb_x_preferred":[
        "Dietenhofen"
    ],
    "name:vie_x_preferred":[
        "Dietenhofen"
    ],
    "name:vol_x_preferred":[
        "Dietenhofen"
    ],
    "name:war_x_preferred":[
        "Dietenhofen"
    ],
    "name:zho_x_preferred":[
        "\u8fea\u6ed5\u970d\u82ac"
    ],
    "wof:name":"Dietenhofen",
    "wof:placetype":"neighbourhood"
},
  "geometry": {"coordinates":[12.01457,48.84782],"type":"Point"}
}