{
  "type": "Feature",
  "properties": {
    "iso:country":"DE",
    "wof:name":"Ronsdorf-Mitte/Nord",
    "wof:placetype":"neighbourhood"
},
  "geometry": {"coordinates":[7.19580460436077,51.23256014197641],"type":"Point"}
}