{
  "type": "Feature",
  "properties": {
    "gn:admin1_code":"1",
    "gn:admin2_code":"83.0",
    "gn:admin3_code":"8316.0",
    "gn:admin4_code":"8316014.0",
    "gn:asciiname":"Oberspitzenbach",
    "gn:country_code":"DE",
    "gn:dem":583,
    "gn:feature_class":"P",
    "gn:feature_code":"PPL",
    "gn:name":"Oberspitzenbach",
    "gn:population":0,
    "gn:timezone":"Europe/Berlin",
    "iso:country":"DE",
    "wof:name":"Oberspitzenbach",
    "wof:placetype":"neighbourhood"
},
  "geometry": {"coordinates":[7.9886,48.17598],"type":"Point"}
}