{
  "type": "Feature",
  "properties": {
    "gn:admin1_code":"5",
    "gn:admin2_code":"65.0",
    "gn:admin3_code":"6534.0",
    "gn:admin4_code":"6534011.0",
    "gn:asciiname":"Langenstein",
    "gn:country_code":"DE",
    "gn:dem":252,
    "gn:feature_class":"P",
    "gn:feature_code":"PPL",
    "gn:name":"Langenstein",
    "gn:population":0,
    "gn:timezone":"Europe/Berlin",
    "iso:country":"DE",
    "wof:name":"Langenstein",
    "wof:placetype":"locality"
},
  "geometry": {"coordinates":[8.95864,50.83191],"type":"Point"}
}