{
  "type": "Feature",
  "properties": {
    "gn:admin1_code":"15.0",
    "gn:admin2_code":"0.0",
    "gn:admin3_code":"16066.0",
    "gn:admin4_code":"16066063.0",
    "gn:asciiname":"Asbach",
    "gn:country_code":"DE",
    "gn:dem":345,
    "gn:feature_class":"P",
    "gn:feature_code":"PPL",
    "gn:name":"Asbach",
    "gn:population":0,
    "gn:timezone":"Europe/Berlin",
    "iso:country":"DE",
    "name:ceb_x_preferred":[
        "Asbach"
    ],
    "name:deu_x_preferred":[
        "Asbach"
    ],
    "name:epo_x_preferred":[
        "Asbach"
    ],
    "name:eus_x_preferred":[
        "Asbach"
    ],
    "name:fra_x_preferred":[
        "Asbach"
    ],
    "name:ita_x_preferred":[
        "Asbach"
    ],
    "name:jpn_x_preferred":[
        "\u30a2\u30b9\u30d0\u30c3\u30cf"
    ],
    "name:nld_x_preferred":[
        "Asbach"
    ],
    "name:pol_x_preferred":[
        "Asbach"
    ],
    "name:rus_x_preferred":[
        "\u0410\u0441\u0431\u0430\u0445"
    ],
    "name:srp_x_preferred":[
        "\u0410\u0441\u0431\u0430\u0445"
    ],
    "wof:name":"Asbach",
    "wof:placetype":"neighbourhood"
},
  "geometry": {"coordinates":[10.48869,50.72599],"type":"Point"}
}