{
  "type": "Feature",
  "properties": {
    "gn:admin1_code":"2",
    "gn:admin2_code":"92.0",
    "gn:admin3_code":"9277.0",
    "gn:admin4_code":"9277145.0",
    "gn:asciiname":"Kottigstelzham",
    "gn:country_code":"DE",
    "gn:dem":487,
    "gn:feature_class":"P",
    "gn:feature_code":"PPL",
    "gn:name":"Kottigstelzham",
    "gn:population":0,
    "gn:timezone":"Europe/Berlin",
    "iso:country":"DE",
    "wof:name":"Kottigstelzham",
    "wof:placetype":"neighbourhood"
},
  "geometry": {"coordinates":[12.95082,48.28726],"type":"Point"}
}