{
  "type": "Feature",
  "properties": {
    "gn:admin1_code":"1",
    "gn:admin2_code":"83.0",
    "gn:admin3_code":"8336.0",
    "gn:admin4_code":"8336045.0",
    "gn:asciiname":"Riedlingen",
    "gn:country_code":"DE",
    "gn:dem":311,
    "gn:feature_class":"P",
    "gn:feature_code":"PPL",
    "gn:name":"Riedlingen",
    "gn:population":0,
    "gn:timezone":"Europe/Berlin",
    "iso:country":"DE",
    "wof:name":"Riedlingen",
    "wof:placetype":"neighbourhood"
},
  "geometry": {"coordinates":[7.63457,47.71583],"type":"Point"}
}