{
  "type": "Feature",
  "properties": {
    "gn:admin1_code":"13",
    "gn:admin2_code":"0.0",
    "gn:admin3_code":"14523.0",
    "gn:admin4_code":"14523310.0",
    "gn:asciiname":"Wallengruen",
    "gn:country_code":"DE",
    "gn:dem":411,
    "gn:feature_class":"P",
    "gn:feature_code":"PPL",
    "gn:name":"Wallengr\u00fcn",
    "gn:population":0,
    "gn:timezone":"Europe/Berlin",
    "iso:country":"DE",
    "wof:name":"Wallengruen",
    "wof:placetype":"neighbourhood"
},
  "geometry": {"coordinates":[11.97796,50.598],"type":"Point"}
}