{
  "type": "Feature",
  "properties": {
    "gn:admin1_code":"7.0",
    "gn:admin2_code":"059",
    "gn:admin3_code":"5962.0",
    "gn:admin4_code":"5962040.0",
    "gn:asciiname":"Werringsen",
    "gn:country_code":"DE",
    "gn:dem":231,
    "gn:feature_class":"P",
    "gn:feature_code":"PPL",
    "gn:name":"Werringsen",
    "gn:population":0,
    "gn:timezone":"Europe/Berlin",
    "iso:country":"DE",
    "wof:name":"Werringsen",
    "wof:placetype":"neighbourhood"
},
  "geometry": {"coordinates":[7.83946,51.45657],"type":"Point"}
}