{
  "type": "Feature",
  "properties": {
    "gn:gn_country":"DE",
    "gn:gn_fcode":"PPLA4",
    "gn:gn_pop":245,
    "gn:population":245,
    "iso:country":"DE",
    "name:arm_x_preferred":[
        "\u054e\u0575\u0578\u0580\u0576\u0565\u0580\u057d\u0562\u0565\u0580\u0563"
    ],
    "name:baq_x_preferred":[
        "W\u00f6rnersberg"
    ],
    "name:cat_x_preferred":[
        "W\u00f6rnersberg"
    ],
    "name:dut_x_preferred":[
        "W\u00f6rnersberg"
    ],
    "name:eng_x_preferred":[
        "W\u00f6rnersberg"
    ],
    "name:epo_x_preferred":[
        "W\u00f6rnersberg"
    ],
    "name:fre_x_preferred":[
        "W\u00f6rnersberg"
    ],
    "name:ger_x_preferred":[
        "W\u00f6rnersberg"
    ],
    "name:gsw_x_preferred":[
        "W\u00f6rnersberg"
    ],
    "name:hun_x_preferred":[
        "W\u00f6rnersberg"
    ],
    "name:ita_x_preferred":[
        "W\u00f6rnersberg"
    ],
    "name:kaz_x_preferred":[
        "\u0412\u0451\u0440\u043d\u0435\u0440\u0441\u0431\u0435\u0440\u0433"
    ],
    "name:kir_x_preferred":[
        "\u0412\u0451\u0440\u043d\u0435\u0440\u0441\u0431\u0435\u0440\u0433"
    ],
    "name:lat_x_preferred":[
        "W\u00f6rnersberg"
    ],
    "name:lmo_x_preferred":[
        "W\u00f6rnersberg"
    ],
    "name:may_x_preferred":[
        "W\u00f6rnersberg"
    ],
    "name:nan_x_preferred":[
        "W\u00f6rnersberg"
    ],
    "name:oci_x_preferred":[
        "W\u00f6rnersberg"
    ],
    "name:per_x_preferred":[
        "\u0648\u0648\u0631\u0646\u0631\u0633\u0628\u0631\u06af"
    ],
    "name:pol_x_preferred":[
        "W\u00f6rnersberg"
    ],
    "name:por_x_preferred":[
        "W\u00f6rnersberg"
    ],
    "name:rum_x_preferred":[
        "W\u00f6rnersberg"
    ],
    "name:rus_x_preferred":[
        "\u0412\u0451\u0440\u043d\u0435\u0440\u0441\u0431\u0435\u0440\u0433"
    ],
    "name:spa_x_preferred":[
        "W\u00f6rnersberg"
    ],
    "name:srp_x_preferred":[
        "\u0412\u0435\u0440\u043d\u0435\u0440\u0441\u0431\u0435\u0440\u0433"
    ],
    "name:ukr_x_preferred":[
        "\u0412\u0435\u0440\u043d\u0435\u0440\u0441\u0431\u0435\u0440\u0433"
    ],
    "name:uzb_x_preferred":[
        "W\u00f6rnersberg"
    ],
    "name:vie_x_preferred":[
        "W\u00f6rnersberg"
    ],
    "name:vol_x_preferred":[
        "W\u00f6rnersberg"
    ],
    "name:war_x_preferred":[
        "W\u00f6rnersberg"
    ],
    "qs_pg:aaroncc":"DE",
    "qs_pg:gn_country":"DE",
    "qs_pg:gn_fcode":"PPLA4",
    "qs_pg:gn_pop":245,
    "qs_pg:name":"W\u00f6rnersberg",
    "qs_pg:name_adm0":"Deutschland",
    "qs_pg:name_adm1":"Baden-W\u00fcrttemberg",
    "qs_pg:photos_9r":0,
    "qs_pg:photos_sr":0,
    "qs_pg:pop_sr":2,
    "qs_pg:qs_pg_placetype":"locality",
    "qs_pg:qs_pg_placetype_gp":"Town",
    "qs_pg:woe_adm0":23424829,
    "woe:adm0_id":23424829,
    "woe:name_adm0":"Deutschland",
    "woe:name_adm1":"Baden-W\u00fcrttemberg",
    "woe:placetype":"Town",
    "wof:name":"W\u00f6rnersberg",
    "wof:placetype":"locality",
    "wof:population":245
},
  "geometry": {"coordinates":[8.56667,48.56667],"type":"Point"}
}