{
  "type": "Feature",
  "properties": {
    "gn:admin1_code":"2.0",
    "gn:admin2_code":"097",
    "gn:admin3_code":"9773.0",
    "gn:admin4_code":"9773111.0",
    "gn:asciiname":"Windhausen",
    "gn:country_code":"DE",
    "gn:dem":464,
    "gn:feature_class":"P",
    "gn:feature_code":"PPL",
    "gn:name":"Windhausen",
    "gn:population":0,
    "gn:timezone":"Europe/Berlin",
    "iso:country":"DE",
    "wof:name":"Windhausen",
    "wof:placetype":"neighbourhood"
},
  "geometry": {"coordinates":[10.44611,48.49033],"type":"Point"}
}