{
  "type": "Feature",
  "properties": {
    "gn:admin1_code":"1",
    "gn:admin2_code":"81.0",
    "gn:admin3_code":"8111.0",
    "gn:admin4_code":"8111000.0",
    "gn:asciiname":"Moehringen",
    "gn:country_code":"DE",
    "gn:dem":423,
    "gn:feature_class":"P",
    "gn:feature_code":"PPL",
    "gn:name":"M\u00f6hringen",
    "gn:population":0,
    "gn:timezone":"Europe/Berlin",
    "iso:country":"DE",
    "wof:name":"Moehringen",
    "wof:placetype":"neighbourhood"
},
  "geometry": {"coordinates":[9.15187,48.72634],"type":"Point"}
}