{
  "type": "Feature",
  "properties": {
    "gn:admin1_code":"11.0",
    "gn:admin2_code":"0.0",
    "gn:admin3_code":"12073.0",
    "gn:admin4_code":"12073008.0",
    "gn:asciiname":"Blumberger Muehle",
    "gn:country_code":"DE",
    "gn:dem":39,
    "gn:feature_class":"P",
    "gn:feature_code":"PPL",
    "gn:name":"Blumberger M\u00fchle",
    "gn:population":0,
    "gn:timezone":"Europe/Berlin",
    "iso:country":"DE",
    "wof:name":"Blumberger Muehle",
    "wof:placetype":"neighbourhood"
},
  "geometry": {"coordinates":[13.96431,53.03605],"type":"Point"}
}