{
  "type": "Feature",
  "properties": {
    "gn:admin1_code":"7",
    "gn:admin2_code":"53.0",
    "gn:admin3_code":"5370.0",
    "gn:admin4_code":"5370012.0",
    "gn:asciiname":"Hochheid",
    "gn:country_code":"DE",
    "gn:dem":89,
    "gn:feature_class":"P",
    "gn:feature_code":"PPL",
    "gn:name":"Hochheid",
    "gn:population":0,
    "gn:timezone":"Europe/Berlin",
    "iso:country":"DE",
    "wof:name":"Hochheid",
    "wof:placetype":"neighbourhood"
},
  "geometry": {"coordinates":[6.12931,50.98746],"type":"Point"}
}