{
  "type": "Feature",
  "properties": {
    "gn:admin1_code":"7",
    "gn:admin2_code":"53.0",
    "gn:admin3_code":"5378.0",
    "gn:admin4_code":"5378012.0",
    "gn:asciiname":"Weiden",
    "gn:country_code":"DE",
    "gn:dem":249,
    "gn:feature_class":"P",
    "gn:feature_code":"PPL",
    "gn:name":"Weiden",
    "gn:population":0,
    "gn:timezone":"Europe/Berlin",
    "iso:country":"DE",
    "name:ceb_x_preferred":[
        "Weiden"
    ],
    "name:ces_x_preferred":[
        "Weiden"
    ],
    "name:deu_x_preferred":[
        "Weiden"
    ],
    "name:epo_x_preferred":[
        "Weiden"
    ],
    "name:fra_x_preferred":[
        "Weiden"
    ],
    "name:ita_x_preferred":[
        "Weiden"
    ],
    "name:nld_x_preferred":[
        "Weiden"
    ],
    "name:pol_x_preferred":[
        "Weiden"
    ],
    "name:rus_x_preferred":[
        "\u0412\u0430\u0439\u0434\u0435\u043d"
    ],
    "name:srp_x_preferred":[
        "\u0412\u0430\u0458\u0434\u0435\u043d"
    ],
    "name:swe_x_preferred":[
        "Weiden"
    ],
    "wof:name":"Weiden",
    "wof:placetype":"neighbourhood"
},
  "geometry": {"coordinates":[7.2425,51.06247000000001],"type":"Point"}
}