{
  "type": "Feature",
  "properties": {
    "gn:admin1_code":"15",
    "gn:admin2_code":"0.0",
    "gn:admin3_code":"16073.0",
    "gn:admin4_code":"16073049.0",
    "gn:asciiname":"Geiersthal",
    "gn:country_code":"DE",
    "gn:dem":542,
    "gn:feature_class":"P",
    "gn:feature_code":"PPL",
    "gn:name":"Geiersthal",
    "gn:population":0,
    "gn:timezone":"Europe/Berlin",
    "iso:country":"DE",
    "name:ara_x_preferred":[
        "\u063a\u0622\u064a\u0631\u0633\u062a\u0622\u0644"
    ],
    "name:ceb_x_preferred":[
        "Geiersthal"
    ],
    "name:deu_x_preferred":[
        "Geiersthal"
    ],
    "name:epo_x_preferred":[
        "Geiersthal"
    ],
    "name:eus_x_preferred":[
        "Geiersthal"
    ],
    "name:fas_x_preferred":[
        "\u06af\u0627\u06cc\u0631\u0633\u062a\u0627\u0644"
    ],
    "name:fra_x_preferred":[
        "Geiersthal"
    ],
    "name:hun_x_preferred":[
        "Geiersthal"
    ],
    "name:hye_x_preferred":[
        "\u0533\u0561\u0575\u0565\u0580\u057d\u0569\u0561\u056c"
    ],
    "name:ita_x_preferred":[
        "Geiersthal"
    ],
    "name:lmo_x_preferred":[
        "Geiersthal"
    ],
    "name:msa_x_preferred":[
        "Geiersthal"
    ],
    "name:nld_x_preferred":[
        "Geiersthal"
    ],
    "name:pol_x_preferred":[
        "Geiersthal"
    ],
    "name:por_x_preferred":[
        "Geiersthal"
    ],
    "name:ron_x_preferred":[
        "Geiersthal"
    ],
    "name:rus_x_preferred":[
        "\u0413\u0430\u0439\u0435\u0440\u0441\u0442\u0430\u043b\u044c"
    ],
    "name:spa_x_preferred":[
        "Geiersthal"
    ],
    "name:srp_x_preferred":[
        "\u0413\u0430\u0458\u0435\u0440\u0441\u0442\u0430\u043b"
    ],
    "name:ukr_x_preferred":[
        "\u0413\u0430\u0454\u0440\u0441\u0442\u0430\u043b\u044c"
    ],
    "name:uzb_x_preferred":[
        "Geiersthal"
    ],
    "name:vie_x_preferred":[
        "Geiersthal"
    ],
    "name:vol_x_preferred":[
        "Geiersthal"
    ],
    "name:war_x_preferred":[
        "Geiersthal"
    ],
    "name:zho_x_preferred":[
        "\u76d6\u57c3\u5c14\u65af\u5854\u5c14"
    ],
    "wof:name":"Geiersthal",
    "wof:placetype":"neighbourhood"
},
  "geometry": {"coordinates":[11.18562,50.53956],"type":"Point"}
}