{
  "type": "Feature",
  "properties": {
    "gn:admin1_code":"8",
    "gn:admin2_code":"0.0",
    "gn:admin3_code":"7137.0",
    "gn:admin4_code":"7137223.0",
    "gn:asciiname":"Oberspay",
    "gn:country_code":"DE",
    "gn:dem":73,
    "gn:feature_class":"P",
    "gn:feature_code":"PPL",
    "gn:name":"Oberspay",
    "gn:population":0,
    "gn:timezone":"Europe/Berlin",
    "iso:country":"DE",
    "wof:name":"Oberspay",
    "wof:placetype":"neighbourhood"
},
  "geometry": {"coordinates":[7.64611,50.25217],"type":"Point"}
}