{
  "type": "Feature",
  "properties": {
    "gn:admin1_code":"2",
    "gn:admin2_code":"94.0",
    "gn:admin3_code":"9478.0",
    "gn:admin4_code":"9478120.0",
    "gn:asciiname":"Peusenhof",
    "gn:country_code":"DE",
    "gn:dem":310,
    "gn:feature_class":"P",
    "gn:feature_code":"PPL",
    "gn:name":"Peusenhof",
    "gn:population":0,
    "gn:timezone":"Europe/Berlin",
    "iso:country":"DE",
    "wof:name":"Peusenhof",
    "wof:placetype":"neighbourhood"
},
  "geometry": {"coordinates":[10.99444,50.02084],"type":"Point"}
}