{
  "type": "Feature",
  "properties": {
    "gn:admin1_code":"6.0",
    "gn:admin2_code":"0.0",
    "gn:admin3_code":"3251.0",
    "gn:admin4_code":"3251042.0",
    "gn:asciiname":"Abbentheren",
    "gn:country_code":"DE",
    "gn:dem":51,
    "gn:feature_class":"P",
    "gn:feature_code":"PPL",
    "gn:name":"Abbentheren",
    "gn:population":0,
    "gn:timezone":"Europe/Berlin",
    "iso:country":"DE",
    "wof:name":"Abbentheren",
    "wof:placetype":"neighbourhood"
},
  "geometry": {"coordinates":[8.5417,52.81049],"type":"Point"}
}