{
  "type": "Feature",
  "properties": {
    "iso:country":"DE",
    "wof:name":"Sittardheide",
    "wof:placetype":"neighbourhood"
},
  "geometry": {"coordinates":[6.3493880058014,51.13703944999062],"type":"Point"}
}