{
  "type": "Feature",
  "properties": {
    "gn:admin1_code":"2",
    "gn:admin2_code":"94.0",
    "gn:admin3_code":"9475.0",
    "gn:admin4_code":"9475154.0",
    "gn:asciiname":"Rabenreuth",
    "gn:country_code":"DE",
    "gn:dem":654,
    "gn:feature_class":"P",
    "gn:feature_code":"PPL",
    "gn:name":"Rabenreuth",
    "gn:population":0,
    "gn:timezone":"Europe/Berlin",
    "iso:country":"DE",
    "wof:name":"Rabenreuth",
    "wof:placetype":"neighbourhood"
},
  "geometry": {"coordinates":[11.77186,50.22909],"type":"Point"}
}