{
  "type": "Feature",
  "properties": {
    "iso:country":"DE",
    "wof:name":"Unterrath",
    "wof:placetype":"neighbourhood"
},
  "geometry": {"coordinates":[6.78717073945345,51.27515495343645],"type":"Point"}
}