{
  "type": "Feature",
  "properties": {
    "gn:country":"DE",
    "gn:fcode":"PPL",
    "gn:population":0,
    "iso:country":"DE",
    "name:bos_x_preferred":[
        "Feldkirchen"
    ],
    "name:ceb_x_preferred":[
        "Feldkirchen"
    ],
    "name:deu_x_preferred":[
        "Feldkirchen"
    ],
    "name:epo_x_preferred":[
        "Feldkirchen"
    ],
    "name:fra_x_preferred":[
        "Feldkirchen"
    ],
    "name:ita_x_preferred":[
        "Feldkirchen"
    ],
    "name:kir_x_preferred":[
        "\u0424\u0435\u043b\u044c\u0434\u043a\u0438\u0440\u0445\u0435\u043d"
    ],
    "name:nld_x_preferred":[
        "Feldkirchen"
    ],
    "name:pol_x_preferred":[
        "Feldkirchen"
    ],
    "name:ron_x_preferred":[
        "Feldkirchen"
    ],
    "name:rus_x_preferred":[
        "\u0424\u0435\u043b\u044c\u0434\u043a\u0438\u0440\u0445\u0435\u043d"
    ],
    "name:slk_x_preferred":[
        "Feldkirchen"
    ],
    "name:srp_x_preferred":[
        "\u0424\u0435\u043b\u0434\u043a\u0438\u0440\u0445\u0435\u043d"
    ],
    "name:swe_x_preferred":[
        "Feldkirchen"
    ],
    "name:und_x_variant":[
        "Feldkirchen/Rhein"
    ],
    "qs_pg:aaroncc":"DE",
    "qs_pg:gn_country":"DE",
    "qs_pg:gn_fcode":"PPL",
    "qs_pg:gn_pop":0,
    "qs_pg:name":"Feldkirchen",
    "qs_pg:name_adm0":"Deutschland",
    "qs_pg:name_adm1":"Rheinland-Pfalz",
    "qs_pg:photos":32,
    "qs_pg:photos_1k":6,
    "qs_pg:photos_9k":1,
    "qs_pg:photos_9r":2,
    "qs_pg:photos_all":32,
    "qs_pg:photos_sr":2,
    "qs_pg:pop_sr":0,
    "qs_pg:qs_pg_placetype":"locality",
    "qs_pg:qs_pg_placetype_gp":"Town",
    "qs_pg:woe_adm0":23424829,
    "woe:adm0_id":23424829,
    "woe:name_adm0":"Deutschland",
    "woe:name_adm1":"Rheinland-Pfalz",
    "woe:placetype":"Town",
    "wof:name":"Feldkirchen",
    "wof:placetype":"neighbourhood"
},
  "geometry": {"coordinates":[7.42562,50.45244],"type":"Point"}
}