{
  "type": "Feature",
  "properties": {
    "gn:admin1_code":"1",
    "gn:admin2_code":"83.0",
    "gn:admin3_code":"8326.0",
    "gn:admin4_code":"8326068.0",
    "gn:asciiname":"Vorderlangenbach",
    "gn:country_code":"DE",
    "gn:dem":854,
    "gn:feature_class":"P",
    "gn:feature_code":"PPLL",
    "gn:name":"Vorderlangenbach",
    "gn:population":0,
    "gn:timezone":"Europe/Berlin",
    "iso:country":"DE",
    "wof:name":"Vorderlangenbach",
    "wof:placetype":"neighbourhood"
},
  "geometry": {"coordinates":[8.29942,48.06305],"type":"Point"}
}