{
  "type": "Feature",
  "properties": {
    "gn:admin1_code":"2",
    "gn:admin2_code":"93.0",
    "gn:admin3_code":"9372.0",
    "gn:admin4_code":"9372161.0",
    "gn:asciiname":"Raubersried",
    "gn:country_code":"DE",
    "gn:dem":434,
    "gn:feature_class":"P",
    "gn:feature_code":"PPL",
    "gn:name":"Raubersried",
    "gn:population":0,
    "gn:timezone":"Europe/Berlin",
    "iso:country":"DE",
    "wof:name":"Raubersried",
    "wof:placetype":"neighbourhood"
},
  "geometry": {"coordinates":[12.4719,49.26816],"type":"Point"}
}