{
  "type": "Feature",
  "properties": {
    "gn:admin1_code":"2",
    "gn:admin2_code":"97.0",
    "gn:admin3_code":"9780.0",
    "gn:admin4_code":"9780122.0",
    "gn:asciiname":"Staudach",
    "gn:country_code":"DE",
    "gn:dem":715,
    "gn:feature_class":"P",
    "gn:feature_code":"PPL",
    "gn:name":"Staudach",
    "gn:population":0,
    "gn:timezone":"Europe/Berlin",
    "iso:country":"DE",
    "wof:name":"Staudach",
    "wof:placetype":"neighbourhood"
},
  "geometry": {"coordinates":[10.34635,47.77271],"type":"Point"}
}