{
  "type": "Feature",
  "properties": {
    "gn:admin1_code":"2",
    "gn:admin2_code":"91.0",
    "gn:admin3_code":"9174.0",
    "gn:admin4_code":"9174147.0",
    "gn:asciiname":"Oberdorf",
    "gn:country_code":"DE",
    "gn:dem":522,
    "gn:feature_class":"P",
    "gn:feature_code":"PPL",
    "gn:name":"Oberdorf",
    "gn:population":0,
    "gn:timezone":"Europe/Berlin",
    "iso:country":"DE",
    "name:als_x_preferred":[
        "Oberdorf"
    ],
    "name:bre_x_preferred":[
        "Oberdorf"
    ],
    "name:ceb_x_preferred":[
        "Oberdorf"
    ],
    "name:deu_x_preferred":[
        "Oberdorf"
    ],
    "name:epo_x_preferred":[
        "Oberdorf"
    ],
    "name:eus_x_preferred":[
        "Oberdorf"
    ],
    "name:fra_x_preferred":[
        "Oberdorf"
    ],
    "name:ita_x_preferred":[
        "Oberdorf"
    ],
    "name:kor_x_preferred":[
        "\uc624\ubc84\ub3c4\ub974\ud504"
    ],
    "name:nld_x_preferred":[
        "Oberdorf"
    ],
    "name:pms_x_preferred":[
        "Oberdorf"
    ],
    "name:pol_x_preferred":[
        "Oberdorf"
    ],
    "name:por_x_preferred":[
        "Oberdorf"
    ],
    "name:ron_x_preferred":[
        "Oberdorf"
    ],
    "name:rus_x_preferred":[
        "\u041e\u0431\u0435\u0440\u0434\u043e\u0440\u0444"
    ],
    "name:spa_x_preferred":[
        "Oberdorf"
    ],
    "name:swe_x_preferred":[
        "Oberdorf"
    ],
    "wof:name":"Oberdorf",
    "wof:placetype":"neighbourhood"
},
  "geometry": {"coordinates":[11.30832,48.44022],"type":"Point"}
}