{
  "type": "Feature",
  "properties": {
    "gn:admin1_code":"8",
    "gn:admin2_code":"0.0",
    "gn:admin3_code":"7138.0",
    "gn:admin4_code":"7138065.0",
    "gn:asciiname":"Lache",
    "gn:country_code":"DE",
    "gn:dem":132,
    "gn:feature_class":"P",
    "gn:feature_code":"PPL",
    "gn:name":"Lache",
    "gn:population":0,
    "gn:timezone":"Europe/Berlin",
    "iso:country":"DE",
    "name:pol_x_preferred":[
        "Lache"
    ],
    "wof:name":"Lache",
    "wof:placetype":"neighbourhood"
},
  "geometry": {"coordinates":[7.42084,50.5644],"type":"Point"}
}