{
  "type": "Feature",
  "properties": {
    "gn:admin1_code":"9",
    "gn:admin2_code":"0.0",
    "gn:admin3_code":"10042.0",
    "gn:admin4_code":"10042115.0",
    "gn:asciiname":"Oberleuken",
    "gn:country_code":"DE",
    "gn:dem":355,
    "gn:feature_class":"P",
    "gn:feature_code":"PPL",
    "gn:name":"Oberleuken",
    "gn:population":0,
    "gn:timezone":"Europe/Berlin",
    "iso:country":"DE",
    "wof:name":"Oberleuken",
    "wof:placetype":"neighbourhood"
},
  "geometry": {"coordinates":[6.46692,49.50616],"type":"Point"}
}