{
  "type": "Feature",
  "properties": {
    "gn:admin1_code":"2",
    "gn:admin2_code":"92.0",
    "gn:admin3_code":"9275.0",
    "gn:admin4_code":"9275146.0",
    "gn:asciiname":"Englboldsdorf",
    "gn:country_code":"DE",
    "gn:dem":447,
    "gn:feature_class":"P",
    "gn:feature_code":"PPL",
    "gn:name":"Englboldsdorf",
    "gn:population":0,
    "gn:timezone":"Europe/Berlin",
    "iso:country":"DE",
    "wof:name":"Englboldsdorf",
    "wof:placetype":"neighbourhood"
},
  "geometry": {"coordinates":[13.47055,48.64266],"type":"Point"}
}