{
  "type": "Feature",
  "properties": {
    "gn:admin1_code":"9",
    "gn:admin2_code":"0.0",
    "gn:admin3_code":"10042.0",
    "gn:admin4_code":"10042116.0",
    "gn:asciiname":"Krettnich",
    "gn:country_code":"DE",
    "gn:dem":305,
    "gn:feature_class":"P",
    "gn:feature_code":"PPL",
    "gn:name":"Krettnich",
    "gn:population":0,
    "gn:timezone":"Europe/Berlin",
    "iso:country":"DE",
    "wof:name":"Krettnich",
    "wof:placetype":"neighbourhood"
},
  "geometry": {"coordinates":[6.94364,49.52496],"type":"Point"}
}