{
  "type": "Feature",
  "properties": {
    "gn:admin1_code":"13.0",
    "gn:admin2_code":"00",
    "gn:admin3_code":"14729.0",
    "gn:admin4_code":"14729080.0",
    "gn:asciiname":"Zschetzsch",
    "gn:country_code":"DE",
    "gn:dem":140,
    "gn:feature_class":"P",
    "gn:feature_code":"PPL",
    "gn:name":"Zschetzsch",
    "gn:population":0,
    "gn:timezone":"Europe/Berlin",
    "iso:country":"DE",
    "wof:name":"Zschetzsch",
    "wof:placetype":"neighbourhood"
},
  "geometry": {"coordinates":[12.78333,51.15],"type":"Point"}
}