{
  "type": "Feature",
  "properties": {
    "gn:admin1_code":"14",
    "gn:admin2_code":"0.0",
    "gn:admin3_code":"15084.0",
    "gn:admin4_code":"15084445.0",
    "gn:asciiname":"Possenhain",
    "gn:country_code":"DE",
    "gn:dem":155,
    "gn:feature_class":"P",
    "gn:feature_code":"PPL",
    "gn:name":"Possenhain",
    "gn:population":0,
    "gn:timezone":"Europe/Berlin",
    "iso:country":"DE",
    "wof:name":"Possenhain",
    "wof:placetype":"neighbourhood"
},
  "geometry": {"coordinates":[11.89753,51.15859],"type":"Point"}
}