{
  "type": "Feature",
  "properties": {
    "gn:admin1_code":"2",
    "gn:admin2_code":"95.0",
    "gn:admin3_code":"9577.0",
    "gn:admin4_code":"9577173.0",
    "gn:asciiname":"Oberheumodern",
    "gn:country_code":"DE",
    "gn:dem":519,
    "gn:feature_class":"P",
    "gn:feature_code":"PPL",
    "gn:name":"Oberheum\u00f6dern",
    "gn:population":0,
    "gn:timezone":"Europe/Berlin",
    "iso:country":"DE",
    "wof:name":"Oberheumodern",
    "wof:placetype":"neighbourhood"
},
  "geometry": {"coordinates":[10.85417,48.95358],"type":"Point"}
}