{
  "type": "Feature",
  "properties": {
    "gn:admin1_code":"2",
    "gn:admin2_code":"92.0",
    "gn:admin3_code":"9276.0",
    "gn:admin4_code":"9276121.0",
    "gn:asciiname":"Dorfl",
    "gn:country_code":"DE",
    "gn:dem":637,
    "gn:feature_class":"P",
    "gn:feature_code":"PPL",
    "gn:name":"D\u00f6rfl",
    "gn:population":0,
    "gn:timezone":"Europe/Berlin",
    "iso:country":"DE",
    "wof:name":"Dorfl",
    "wof:placetype":"neighbourhood"
},
  "geometry": {"coordinates":[13.30161,48.99469000000001],"type":"Point"}
}