{
  "type": "Feature",
  "properties": {
    "gn:admin1_code":"6.0",
    "gn:admin2_code":"0.0",
    "gn:admin3_code":"3159.0",
    "gn:admin4_code":"3159003.0",
    "gn:asciiname":"Bartolfelde",
    "gn:country_code":"DE",
    "gn:dem":309,
    "gn:feature_class":"P",
    "gn:feature_code":"PPL",
    "gn:name":"Bartolfelde",
    "gn:population":0,
    "gn:timezone":"Europe/Berlin",
    "iso:country":"DE",
    "wof:name":"Bartolfelde",
    "wof:placetype":"neighbourhood"
},
  "geometry": {"coordinates":[10.45788,51.5964],"type":"Point"}
}