{
  "type": "Feature",
  "properties": {
    "gn:admin1_code":"15",
    "gn:admin2_code":"0.0",
    "gn:admin3_code":"16064.0",
    "gn:admin4_code":"16064055.0",
    "gn:asciiname":"Eigenrieden",
    "gn:country_code":"DE",
    "gn:dem":464,
    "gn:feature_class":"P",
    "gn:feature_code":"PPL",
    "gn:name":"Eigenrieden",
    "gn:population":0,
    "gn:timezone":"Europe/Berlin",
    "iso:country":"DE",
    "wof:name":"Eigenrieden",
    "wof:placetype":"neighbourhood"
},
  "geometry": {"coordinates":[10.32621,51.20967],"type":"Point"}
}