{
  "type": "Feature",
  "properties": {
    "gn:admin1_code":"12.0",
    "gn:admin2_code":"00",
    "gn:admin3_code":"13073.0",
    "gn:admin4_code":"13073101.0",
    "gn:asciiname":"Woldenitz",
    "gn:country_code":"DE",
    "gn:dem":3,
    "gn:feature_class":"P",
    "gn:feature_code":"PPL",
    "gn:name":"Woldenitz",
    "gn:population":0,
    "gn:timezone":"Europe/Berlin",
    "iso:country":"DE",
    "wof:name":"Woldenitz",
    "wof:placetype":"neighbourhood"
},
  "geometry": {"coordinates":[13.29998,54.5817],"type":"Point"}
}