{
  "type": "Feature",
  "properties": {
    "gn:admin1_code":"1",
    "gn:admin2_code":"84.0",
    "gn:admin3_code":"8426.0",
    "gn:admin4_code":"8426134.0",
    "gn:asciiname":"Ingerkingen",
    "gn:country_code":"DE",
    "gn:dem":518,
    "gn:feature_class":"P",
    "gn:feature_code":"PPL",
    "gn:name":"Ingerkingen",
    "gn:population":0,
    "gn:timezone":"Europe/Berlin",
    "iso:country":"DE",
    "wof:name":"Ingerkingen",
    "wof:placetype":"neighbourhood"
},
  "geometry": {"coordinates":[9.7707,48.19894],"type":"Point"}
}