{
  "type": "Feature",
  "properties": {
    "gn:admin1_code":"7",
    "gn:admin2_code":"53.0",
    "gn:admin3_code":"5370.0",
    "gn:admin4_code":"5370028.0",
    "gn:asciiname":"Stegh",
    "gn:country_code":"DE",
    "gn:dem":115,
    "gn:feature_class":"P",
    "gn:feature_code":"PPL",
    "gn:name":"Stegh",
    "gn:population":0,
    "gn:timezone":"Europe/Berlin",
    "iso:country":"DE",
    "wof:name":"Stegh",
    "wof:placetype":"neighbourhood"
},
  "geometry": {"coordinates":[6.12006,50.93497],"type":"Point"}
}