{
  "type": "Feature",
  "properties": {
    "gn:admin1_code":"12.0",
    "gn:admin2_code":"00",
    "gn:admin3_code":"13071.0",
    "gn:admin4_code":"13071164.0",
    "gn:asciiname":"Wilhelmshoehe",
    "gn:country_code":"DE",
    "gn:dem":109,
    "gn:feature_class":"P",
    "gn:feature_code":"PPL",
    "gn:name":"Wilhelmsh\u00f6he",
    "gn:population":0,
    "gn:timezone":"Europe/Berlin",
    "iso:country":"DE",
    "wof:name":"Wilhelmshoehe",
    "wof:placetype":"neighbourhood"
},
  "geometry": {"coordinates":[13.55141,53.48174],"type":"Point"}
}