{
  "type": "Feature",
  "properties": {
    "gn:admin1_code":"8",
    "gn:admin2_code":"0.0",
    "gn:admin3_code":"7235.0",
    "gn:admin4_code":"7235093.0",
    "gn:asciiname":"Schmelz",
    "gn:country_code":"DE",
    "gn:dem":530,
    "gn:feature_class":"P",
    "gn:feature_code":"PPL",
    "gn:name":"Schmelz",
    "gn:population":0,
    "gn:timezone":"Europe/Berlin",
    "iso:country":"DE",
    "name:cat_x_preferred":[
        "Schmelz"
    ],
    "name:ceb_x_preferred":[
        "Schmelz"
    ],
    "name:deu_x_preferred":[
        "Schmelz"
    ],
    "name:epo_x_preferred":[
        "Schmelz"
    ],
    "name:eus_x_preferred":[
        "Schmelz"
    ],
    "name:fas_x_preferred":[
        "\u0627\u0634\u0645\u0644\u062a\u0633"
    ],
    "name:fra_x_preferred":[
        "Schmelz"
    ],
    "name:hun_x_preferred":[
        "Schmelz"
    ],
    "name:ita_x_preferred":[
        "Schmelz"
    ],
    "name:kaz_x_preferred":[
        "\u0428\u043c\u0435\u043b\u044c\u0446"
    ],
    "name:kir_x_preferred":[
        "\u0428\u043c\u0435\u043b\u044c\u0446"
    ],
    "name:msa_x_preferred":[
        "Schmelz"
    ],
    "name:nld_x_preferred":[
        "Schmelz"
    ],
    "name:pol_x_preferred":[
        "Schmelz"
    ],
    "name:por_x_preferred":[
        "Schmelz"
    ],
    "name:ron_x_preferred":[
        "Schmelz"
    ],
    "name:rus_x_preferred":[
        "\u0428\u043c\u0435\u043b\u044c\u0446"
    ],
    "name:spa_x_preferred":[
        "Schmelz"
    ],
    "name:srp_x_preferred":[
        "\u0428\u043c\u0435\u043b\u0446"
    ],
    "name:ukr_x_preferred":[
        "\u0428\u043c\u0435\u043b\u044c\u0446"
    ],
    "name:uzb_x_preferred":[
        "Schmelz"
    ],
    "name:vie_x_preferred":[
        "Schmelz"
    ],
    "name:vol_x_preferred":[
        "Schmelz"
    ],
    "name:war_x_preferred":[
        "Schmelz"
    ],
    "name:zho_x_preferred":[
        "\u65bd\u6885\u5c14\u8328"
    ],
    "wof:name":"Schmelz",
    "wof:placetype":"neighbourhood"
},
  "geometry": {"coordinates":[7.01169,49.64067],"type":"Point"}
}