{
  "type": "Feature",
  "properties": {
    "gn:country":"DE",
    "gn:fcode":"PPL",
    "gn:population":2000,
    "iso:country":"DE",
    "name:frs_x_preferred":[
        "Fedderwarn"
    ],
    "name:gmh_x_preferred":[
        "Fatruwerde [a. 1155]"
    ],
    "name:gml_x_preferred":[
        "Ffedderwurden in Frisia [a. 1420]"
    ],
    "name:ofs_x_preferred":[
        "*Fa\u00ferwur\u00fe-"
    ],
    "qs_pg:aaroncc":"DE",
    "qs_pg:gn_country":"DE",
    "qs_pg:gn_fcode":"PPL",
    "qs_pg:gn_pop":2000,
    "qs_pg:name":"Fedderwarden",
    "qs_pg:name_adm0":"Deutschland",
    "qs_pg:name_adm1":"Niedersachsen",
    "qs_pg:photos_9k":1,
    "qs_pg:photos_9r":1,
    "qs_pg:photos_all":1,
    "qs_pg:photos_sr":0,
    "qs_pg:pop_sr":3,
    "qs_pg:qs_pg_placetype":"locality",
    "qs_pg:qs_pg_placetype_gp":"Town",
    "qs_pg:woe_adm0":23424829,
    "woe:adm0_id":23424829,
    "woe:name_adm0":"Deutschland",
    "woe:name_adm1":"Niedersachsen",
    "woe:placetype":"Town",
    "wof:name":"Fedderwarden",
    "wof:placetype":"neighbourhood",
    "wof:population":2000
},
  "geometry": {"coordinates":[8.04371,53.56142],"type":"Point"}
}