{
  "type": "Feature",
  "properties": {
    "gn:admin1_code":"15",
    "gn:admin2_code":"0.0",
    "gn:admin3_code":"16075.0",
    "gn:admin4_code":"16075085.0",
    "gn:asciiname":"Juedewein",
    "gn:country_code":"DE",
    "gn:dem":241,
    "gn:feature_class":"P",
    "gn:feature_code":"PPL",
    "gn:name":"J\u00fcdewein",
    "gn:population":0,
    "gn:timezone":"Europe/Berlin",
    "iso:country":"DE",
    "wof:name":"Juedewein",
    "wof:placetype":"neighbourhood"
},
  "geometry": {"coordinates":[11.59152,50.70077],"type":"Point"}
}