{
  "type": "Feature",
  "properties": {
    "gn:admin1_code":"2",
    "gn:admin2_code":"97.0",
    "gn:admin3_code":"9774.0",
    "gn:admin4_code":"9774135.0",
    "gn:asciiname":"Riedhausen bei Gunzburg",
    "gn:country_code":"DE",
    "gn:dem":446,
    "gn:feature_class":"P",
    "gn:feature_code":"PPL",
    "gn:name":"Riedhausen bei G\u00fcnzburg",
    "gn:population":0,
    "gn:timezone":"Europe/Berlin",
    "iso:country":"DE",
    "wof:name":"Riedhausen bei Gunzburg",
    "wof:placetype":"neighbourhood"
},
  "geometry": {"coordinates":[10.25187,48.50773],"type":"Point"}
}