{
  "type": "Feature",
  "properties": {
    "gn:admin1_code":"5",
    "gn:admin2_code":"66.0",
    "gn:admin3_code":"6632.0",
    "gn:admin4_code":"6632008.0",
    "gn:asciiname":"Muesenbach",
    "gn:country_code":"DE",
    "gn:dem":227,
    "gn:feature_class":"P",
    "gn:feature_code":"PPL",
    "gn:name":"M\u00fcsenbach",
    "gn:population":0,
    "gn:timezone":"Europe/Berlin",
    "iso:country":"DE",
    "wof:name":"Muesenbach",
    "wof:placetype":"neighbourhood"
},
  "geometry": {"coordinates":[9.70559,50.79021],"type":"Point"}
}