{
  "type": "Feature",
  "properties": {
    "gn:admin1_code":"7",
    "gn:admin2_code":"53.0",
    "gn:admin3_code":"5362.0",
    "gn:admin4_code":"5362036.0",
    "gn:asciiname":"Stommelerbusch",
    "gn:country_code":"DE",
    "gn:dem":45,
    "gn:feature_class":"P",
    "gn:feature_code":"PPL",
    "gn:name":"Stommelerbusch",
    "gn:population":0,
    "gn:timezone":"Europe/Berlin",
    "iso:country":"DE",
    "wof:name":"Stommelerbusch",
    "wof:placetype":"neighbourhood"
},
  "geometry": {"coordinates":[6.77324,51.04647],"type":"Point"}
}