{
  "type": "Feature",
  "properties": {
    "gn:admin1_code":"2.0",
    "gn:admin2_code":"91.0",
    "gn:admin3_code":"9188.0",
    "gn:admin4_code":"9188120.0",
    "gn:asciiname":"Grubmuhl",
    "gn:country_code":"DE",
    "gn:dem":575,
    "gn:feature_class":"P",
    "gn:feature_code":"PPL",
    "gn:name":"Grubm\u00fchl",
    "gn:population":0,
    "gn:timezone":"Europe/Berlin",
    "iso:country":"DE",
    "wof:name":"Grubmuhl",
    "wof:placetype":"neighbourhood"
},
  "geometry": {"coordinates":[11.38733,48.07991],"type":"Point"}
}