{
  "type": "Feature",
  "properties": {
    "gn:admin1_code":"12",
    "gn:admin2_code":"0.0",
    "gn:admin3_code":"13072.0",
    "gn:admin4_code":"13072085.0",
    "gn:asciiname":"Gaarzerhof",
    "gn:country_code":"DE",
    "gn:dem":3,
    "gn:feature_class":"P",
    "gn:feature_code":"PPL",
    "gn:name":"Gaarzerhof",
    "gn:population":0,
    "gn:timezone":"Europe/Berlin",
    "iso:country":"DE",
    "wof:name":"Gaarzerhof",
    "wof:placetype":"neighbourhood"
},
  "geometry": {"coordinates":[11.63066,54.09932],"type":"Point"}
}