{
  "type": "Feature",
  "properties": {
    "gn:admin1_code":"13",
    "gn:admin2_code":"0.0",
    "gn:admin3_code":"14729.0",
    "gn:admin4_code":"14729140.0",
    "gn:asciiname":"Linda",
    "gn:cc2":"DE",
    "gn:country_code":"DE",
    "gn:dem":220,
    "gn:feature_class":"P",
    "gn:feature_code":"PPL",
    "gn:name":"Linda",
    "gn:population":0,
    "gn:timezone":"Europe/Berlin",
    "iso:country":"DE",
    "name:und_x_variant":[
        "Jahnshain-Linda"
    ],
    "wof:name":"Linda",
    "wof:placetype":"neighbourhood"
},
  "geometry": {"coordinates":[12.62432,50.99761],"type":"Point"}
}