{
  "type": "Feature",
  "properties": {
    "gn:admin1_code":"13",
    "gn:admin2_code":"0.0",
    "gn:admin3_code":"14729.0",
    "gn:admin4_code":"14729140.0",
    "gn:asciiname":"Linda",
    "gn:cc2":"DE",
    "gn:country_code":"DE",
    "gn:dem":220,
    "gn:feature_class":"P",
    "gn:feature_code":"PPL",
    "gn:name":"Linda",
    "gn:population":0,
    "gn:timezone":"Europe/Berlin",
    "iso:country":"DE",
    "name:ceb_x_preferred":[
        "Linda"
    ],
    "name:ces_x_preferred":[
        "Linda"
    ],
    "name:deu_x_preferred":[
        "Linda"
    ],
    "name:epo_x_preferred":[
        "Linda"
    ],
    "name:est_x_preferred":[
        "Linda"
    ],
    "name:fin_x_preferred":[
        "Linda"
    ],
    "name:fra_x_preferred":[
        "Linda"
    ],
    "name:heb_x_preferred":[
        "\u05dc\u05d9\u05e0\u05d3\u05d4"
    ],
    "name:hsb_x_preferred":[
        "Linda"
    ],
    "name:hun_x_preferred":[
        "Linda"
    ],
    "name:ita_x_preferred":[
        "Linda"
    ],
    "name:jpn_x_preferred":[
        "\u30ea\u30f3\u30c0"
    ],
    "name:nld_x_preferred":[
        "Linda"
    ],
    "name:pol_x_preferred":[
        "Linda"
    ],
    "name:por_x_preferred":[
        "Linda"
    ],
    "name:ron_x_preferred":[
        "Linda"
    ],
    "name:rus_x_preferred":[
        "\u041b\u0438\u043d\u0434\u0430"
    ],
    "name:spa_x_preferred":[
        "Linda"
    ],
    "name:ukr_x_preferred":[
        "\u041b\u0456\u043d\u0434\u0430"
    ],
    "name:und_x_variant":[
        "Jahnshain-Linda"
    ],
    "name:vie_x_preferred":[
        "Linda"
    ],
    "wof:name":"Linda",
    "wof:placetype":"neighbourhood"
},
  "geometry": {"coordinates":[12.62432,50.99761],"type":"Point"}
}