{
  "type": "Feature",
  "properties": {
    "gn:admin1_code":"11.0",
    "gn:admin2_code":"00",
    "gn:admin3_code":"12068.0",
    "gn:admin4_code":"12068353.0",
    "gn:asciiname":"Zuehlen",
    "gn:country_code":"DE",
    "gn:dem":71,
    "gn:feature_class":"P",
    "gn:feature_code":"PPL",
    "gn:name":"Z\u00fchlen",
    "gn:population":0,
    "gn:timezone":"Europe/Berlin",
    "iso:country":"DE",
    "wof:name":"Zuehlen",
    "wof:placetype":"neighbourhood"
},
  "geometry": {"coordinates":[12.81804,53.07484],"type":"Point"}
}