{
  "type": "Feature",
  "properties": {
    "gn:admin1_code":"6",
    "gn:admin2_code":"0.0",
    "gn:admin3_code":"3451.0",
    "gn:admin4_code":"3451001.0",
    "gn:asciiname":"Godensholterfeld",
    "gn:country_code":"DE",
    "gn:dem":2,
    "gn:feature_class":"P",
    "gn:feature_code":"PPL",
    "gn:name":"Godensholterfeld",
    "gn:population":0,
    "gn:timezone":"Europe/Berlin",
    "iso:country":"DE",
    "wof:name":"Godensholterfeld",
    "wof:placetype":"neighbourhood"
},
  "geometry": {"coordinates":[7.83802,53.18983000000001],"type":"Point"}
}