{
  "type": "Feature",
  "properties": {
    "gn:admin1_code":"15.0",
    "gn:admin2_code":"0.0",
    "gn:admin3_code":"16064.0",
    "gn:admin4_code":"16064066.0",
    "gn:asciiname":"Grabe",
    "gn:country_code":"DE",
    "gn:dem":199,
    "gn:feature_class":"P",
    "gn:feature_code":"PPL",
    "gn:name":"Grabe",
    "gn:population":0,
    "gn:timezone":"Europe/Berlin",
    "iso:country":"DE",
    "name:bos_x_preferred":[
        "Grabe"
    ],
    "name:ceb_x_preferred":[
        "Grabe"
    ],
    "name:deu_x_preferred":[
        "Grabe"
    ],
    "name:hrv_x_preferred":[
        "Grabe"
    ],
    "name:nld_x_preferred":[
        "Grabe"
    ],
    "name:slv_x_preferred":[
        "Grabe"
    ],
    "name:srp_x_preferred":[
        "\u0413\u0440\u0430\u0431\u0435"
    ],
    "name:swe_x_preferred":[
        "Grabe"
    ],
    "wof:name":"Grabe",
    "wof:placetype":"neighbourhood"
},
  "geometry": {"coordinates":[10.53851,51.22727],"type":"Point"}
}