{
  "type": "Feature",
  "properties": {
    "gn:admin1_code":"12",
    "gn:admin2_code":"0.0",
    "gn:admin3_code":"13072.0",
    "gn:admin4_code":"13072045.0",
    "gn:asciiname":"Goerzhausen",
    "gn:country_code":"DE",
    "gn:dem":82,
    "gn:feature_class":"P",
    "gn:feature_code":"PPL",
    "gn:name":"G\u00f6rzhausen",
    "gn:population":0,
    "gn:timezone":"Europe/Berlin",
    "iso:country":"DE",
    "wof:name":"Goerzhausen",
    "wof:placetype":"neighbourhood"
},
  "geometry": {"coordinates":[12.52245,53.70217],"type":"Point"}
}