{
  "type": "Feature",
  "properties": {
    "iso:country":"DE",
    "name:ces_x_preferred":[
        "Helfenberg"
    ],
    "name:deu_x_preferred":[
        "Helfenberg"
    ],
    "name:fas_x_preferred":[
        "\u0647\u0644\u0641\u0646\u0628\u0631\u06af"
    ],
    "name:fra_x_preferred":[
        "Helfenberg"
    ],
    "name:hun_x_preferred":[
        "Helfenberg"
    ],
    "name:ita_x_preferred":[
        "Helfenberg"
    ],
    "name:kaz_x_preferred":[
        "\u0425\u0435\u043b\u044c\u0444\u0435\u043d\u0431\u0435\u0440\u0433"
    ],
    "name:nld_x_preferred":[
        "Helfenberg"
    ],
    "name:pol_x_preferred":[
        "Helfenberg"
    ],
    "name:por_x_preferred":[
        "Helfenberg"
    ],
    "name:rus_x_preferred":[
        "\u0425\u0435\u043b\u044c\u0444\u0435\u043d\u0431\u0435\u0440\u0433"
    ],
    "name:slk_x_preferred":[
        "Helfenberg"
    ],
    "name:spa_x_preferred":[
        "Helfenberg"
    ],
    "name:uzb_x_preferred":[
        "Helfenberg"
    ],
    "name:vol_x_preferred":[
        "Helfenberg"
    ],
    "name:war_x_preferred":[
        "Helfenberg"
    ],
    "name:zho_x_preferred":[
        "\u9ed1\u82ac\u8d1d\u683c"
    ],
    "wof:name":"Helfenberg",
    "wof:placetype":"neighbourhood"
},
  "geometry": {"coordinates":[13.86626558327598,51.03596076951808],"type":"Point"}
}