{
  "type": "Feature",
  "properties": {
    "iso:country":"DE",
    "wof:name":"Helfenberg",
    "wof:placetype":"neighbourhood"
},
  "geometry": {"coordinates":[13.86626558327598,51.03596076951808],"type":"Point"}
}