{
  "type": "Feature",
  "properties": {
    "gn:gn_country":"DE",
    "gn:gn_fcode":"PPLA4",
    "gn:gn_pop":434,
    "gn:population":434,
    "iso:country":"DE",
    "name:baq_x_preferred":[
        "Hergenroth"
    ],
    "name:chi_x_preferred":[
        "\u9ed1\u5c14\u6839\u7f57\u7279"
    ],
    "name:dut_x_preferred":[
        "Hergenroth"
    ],
    "name:eng_x_preferred":[
        "Hergenroth"
    ],
    "name:epo_x_preferred":[
        "Hergenroth"
    ],
    "name:fre_x_preferred":[
        "Hergenroth"
    ],
    "name:ger_x_preferred":[
        "Hergenroth"
    ],
    "name:hun_x_preferred":[
        "Hergenroth"
    ],
    "name:ita_x_preferred":[
        "Hergenroth"
    ],
    "name:jpn_x_preferred":[
        "\u30d8\u30eb\u30b2\u30f3\u30ed\u30fc\u30c8"
    ],
    "name:kaz_x_preferred":[
        "\u0425\u0435\u0440\u0433\u0435\u043d\u0440\u043e\u0442"
    ],
    "name:kir_x_preferred":[
        "\u0425\u0435\u0440\u0433\u0435\u043d\u0440\u043e\u0442"
    ],
    "name:may_x_preferred":[
        "Hergenroth"
    ],
    "name:per_x_preferred":[
        "\u0647\u0631\u06af\u0646\u0631\u0648\u062a"
    ],
    "name:pol_x_preferred":[
        "Hergenroth"
    ],
    "name:por_x_preferred":[
        "Hergenroth"
    ],
    "name:rum_x_preferred":[
        "Hergenroth"
    ],
    "name:rus_x_preferred":[
        "\u0425\u0435\u0440\u0433\u0435\u043d\u0440\u043e\u0442"
    ],
    "name:srp_x_preferred":[
        "\u0425\u0435\u0440\u0433\u0435\u043d\u0440\u043e\u0442"
    ],
    "name:ukr_x_preferred":[
        "\u0413\u0435\u0440\u0433\u0435\u043d\u0440\u043e\u0442"
    ],
    "name:uzb_x_preferred":[
        "Hergenroth"
    ],
    "name:vie_x_preferred":[
        "Hergenroth"
    ],
    "name:vol_x_preferred":[
        "Hergenroth"
    ],
    "name:war_x_preferred":[
        "Hergenroth"
    ],
    "qs_pg:aaroncc":"DE",
    "qs_pg:gn_country":"DE",
    "qs_pg:gn_fcode":"PPLA4",
    "qs_pg:gn_pop":434,
    "qs_pg:name":"Hergenroth",
    "qs_pg:photos_9r":0,
    "qs_pg:photos_sr":0,
    "qs_pg:pop_sr":2,
    "qs_pg:qs_pg_placetype":"locality",
    "wof:name":"Hergenroth",
    "wof:placetype":"locality",
    "wof:population":434
},
  "geometry": {"coordinates":[7.96667,50.58333],"type":"Point"}
}