{
  "type": "Feature",
  "properties": {
    "gn:admin1_code":"2",
    "gn:admin2_code":"94.0",
    "gn:admin3_code":"9472.0",
    "gn:admin4_code":"9472154.0",
    "gn:asciiname":"Hainbach",
    "gn:country_code":"DE",
    "gn:dem":417,
    "gn:feature_class":"P",
    "gn:feature_code":"PPL",
    "gn:name":"Hainbach",
    "gn:population":0,
    "gn:timezone":"Europe/Berlin",
    "iso:country":"DE",
    "name:ceb_x_preferred":[
        "Hainbach"
    ],
    "name:deu_x_preferred":[
        "Hainbach"
    ],
    "name:epo_x_preferred":[
        "Hainbach"
    ],
    "name:rus_x_preferred":[
        "\u0425\u0430\u0439\u043d\u0431\u0430\u0445"
    ],
    "name:swe_x_preferred":[
        "Hainbach"
    ],
    "wof:name":"Hainbach",
    "wof:placetype":"neighbourhood"
},
  "geometry": {"coordinates":[11.33669,49.9105],"type":"Point"}
}