{
  "type": "Feature",
  "properties": {
    "gn:admin1_code":"2",
    "gn:admin2_code":"92.0",
    "gn:admin3_code":"9278.0",
    "gn:admin4_code":"9278129.0",
    "gn:asciiname":"Hiening",
    "gn:country_code":"DE",
    "gn:dem":630,
    "gn:feature_class":"P",
    "gn:feature_code":"PPL",
    "gn:name":"Hiening",
    "gn:population":0,
    "gn:timezone":"Europe/Berlin",
    "iso:country":"DE",
    "wof:name":"Hiening",
    "wof:placetype":"neighbourhood"
},
  "geometry": {"coordinates":[12.73995,49.04528],"type":"Point"}
}