{
  "type": "Feature",
  "properties": {
    "gn:admin1_code":"11",
    "gn:admin2_code":"0.0",
    "gn:admin3_code":"12073.0",
    "gn:admin4_code":"12073579.0",
    "gn:asciiname":"Fahrenholz",
    "gn:country_code":"DE",
    "gn:dem":90,
    "gn:feature_class":"P",
    "gn:feature_code":"PPL",
    "gn:name":"Fahrenholz",
    "gn:population":0,
    "gn:timezone":"Europe/Berlin",
    "iso:country":"DE",
    "wof:name":"Fahrenholz",
    "wof:placetype":"neighbourhood"
},
  "geometry": {"coordinates":[13.75014,53.45668000000001],"type":"Point"}
}