{
  "type": "Feature",
  "properties": {
    "gn:admin1_code":"2",
    "gn:admin2_code":"91.0",
    "gn:admin3_code":"9182.0",
    "gn:admin4_code":"9182119.0",
    "gn:asciiname":"Freudenreich",
    "gn:country_code":"DE",
    "gn:dem":767,
    "gn:feature_class":"P",
    "gn:feature_code":"PPL",
    "gn:name":"Freudenreich",
    "gn:population":0,
    "gn:timezone":"Europe/Berlin",
    "iso:country":"DE",
    "wof:name":"Freudenreich",
    "wof:placetype":"neighbourhood"
},
  "geometry": {"coordinates":[11.81923,47.75421],"type":"Point"}
}