{
  "type": "Feature",
  "properties": {
    "gn:admin1_code":"2",
    "gn:admin2_code":"91.0",
    "gn:admin3_code":"9187.0",
    "gn:admin4_code":"9187150.0",
    "gn:asciiname":"Pullach",
    "gn:country_code":"DE",
    "gn:dem":474,
    "gn:feature_class":"P",
    "gn:feature_code":"PPL",
    "gn:name":"Pullach",
    "gn:population":0,
    "gn:timezone":"Europe/Berlin",
    "iso:country":"DE",
    "wof:name":"Pullach",
    "wof:placetype":"neighbourhood"
},
  "geometry": {"coordinates":[12.01458,47.84842],"type":"Point"}
}