{
  "type": "Feature",
  "properties": {
    "gn:admin1_code":"2",
    "gn:admin2_code":"91.0",
    "gn:admin3_code":"9187.0",
    "gn:admin4_code":"9187150.0",
    "gn:asciiname":"Pullach",
    "gn:country_code":"DE",
    "gn:dem":474,
    "gn:feature_class":"P",
    "gn:feature_code":"PPL",
    "gn:name":"Pullach",
    "gn:population":0,
    "gn:timezone":"Europe/Berlin",
    "iso:country":"DE",
    "name:ara_x_preferred":[
        "\u0628\u0648\u0644\u0622\u062e"
    ],
    "name:eus_x_preferred":[
        "Pullach"
    ],
    "name:fas_x_preferred":[
        "\u067e\u0648\u0644\u0627\u062e"
    ],
    "name:hye_x_preferred":[
        "\u053b\u0566\u0561\u0580\u0569\u0561\u056c\u056b \u054a\u0578\u0582\u056c\u0561\u056d"
    ],
    "name:ind_x_preferred":[
        "Pullach"
    ],
    "name:jpn_x_preferred":[
        "\u30d7\u30e9\u30c3\u30cf\u30fb\u30a4\u30e0\u30fb\u30a4\u30fc\u30b6\u30eb\u30bf\u30fc\u30eb"
    ],
    "name:kaz_x_preferred":[
        "\u041f\u0443\u043b\u043b\u0430\u0445-\u0438\u043c-\u0418\u0437\u0430\u0440\u0442\u0430\u043b\u044c"
    ],
    "name:kir_x_preferred":[
        "\u041f\u0443\u043b\u043b\u0430\u0445-\u0438\u043c-\u0418\u0437\u0430\u0440\u0442\u0430\u043b\u044c"
    ],
    "name:msa_x_preferred":[
        "Pullach"
    ],
    "name:por_x_preferred":[
        "Pullach"
    ],
    "name:rus_x_preferred":[
        "\u041f\u0443\u043b\u043b\u0430\u0445-\u0438\u043c-\u0418\u0437\u0430\u0440\u0442\u0430\u043b\u044c"
    ],
    "name:spa_x_preferred":[
        "Pullach"
    ],
    "name:ukr_x_preferred":[
        "\u041f\u0443\u043b\u043b\u0430\u0445"
    ],
    "name:war_x_preferred":[
        "Pullach"
    ],
    "wof:name":"Pullach",
    "wof:placetype":"neighbourhood"
},
  "geometry": {"coordinates":[12.01458,47.84842],"type":"Point"}
}