{
  "type": "Feature",
  "properties": {
    "gn:admin1_code":"15",
    "gn:admin2_code":"0.0",
    "gn:admin3_code":"16070.0",
    "gn:admin4_code":"16070056.0",
    "gn:asciiname":"Doellstedt",
    "gn:country_code":"DE",
    "gn:dem":412,
    "gn:feature_class":"P",
    "gn:feature_code":"PPL",
    "gn:name":"D\u00f6llstedt",
    "gn:population":0,
    "gn:timezone":"Europe/Berlin",
    "iso:country":"DE",
    "wof:name":"Doellstedt",
    "wof:placetype":"neighbourhood"
},
  "geometry": {"coordinates":[11.14191,50.76472],"type":"Point"}
}