{
  "type": "Feature",
  "properties": {
    "iso:country":"DE",
    "wof:name":"Uellendahl-Ost",
    "wof:placetype":"neighbourhood"
},
  "geometry": {"coordinates":[7.16685103754664,51.28448319807794],"type":"Point"}
}