{
  "type": "Feature",
  "properties": {
    "gn:admin1_code":"7.0",
    "gn:admin2_code":"53.0",
    "gn:admin3_code":"5378.0",
    "gn:admin4_code":"5378032.0",
    "gn:asciiname":"Bergstadt",
    "gn:country_code":"DE",
    "gn:dem":275,
    "gn:feature_class":"P",
    "gn:feature_code":"PPL",
    "gn:name":"Bergstadt",
    "gn:population":0,
    "gn:timezone":"Europe/Berlin",
    "iso:country":"DE",
    "name:ceb_x_preferred":[
        "Bergstadt"
    ],
    "name:deu_x_preferred":[
        "Bergstadt"
    ],
    "name:swe_x_preferred":[
        "Bergstadt"
    ],
    "wof:name":"Bergstadt",
    "wof:placetype":"neighbourhood"
},
  "geometry": {"coordinates":[7.27776,51.1061],"type":"Point"}
}