{
  "type": "Feature",
  "properties": {
    "gn:admin1_code":"15.0",
    "gn:admin2_code":"00",
    "gn:admin3_code":"16075.0",
    "gn:admin4_code":"16075054.0",
    "gn:asciiname":"Wildhaus",
    "gn:country_code":"DE",
    "gn:dem":394,
    "gn:feature_class":"P",
    "gn:feature_code":"PPL",
    "gn:name":"Wildhaus",
    "gn:population":0,
    "gn:timezone":"Europe/Berlin",
    "iso:country":"DE",
    "wof:name":"Wildhaus",
    "wof:placetype":"neighbourhood"
},
  "geometry": {"coordinates":[11.68333,50.75],"type":"Point"}
}