{
  "type": "Feature",
  "properties": {
    "gn:admin1_code":"15.0",
    "gn:admin2_code":"00",
    "gn:admin3_code":"16075.0",
    "gn:admin4_code":"16075054.0",
    "gn:asciiname":"Wildhaus",
    "gn:country_code":"DE",
    "gn:dem":394,
    "gn:feature_class":"P",
    "gn:feature_code":"PPL",
    "gn:name":"Wildhaus",
    "gn:population":0,
    "gn:timezone":"Europe/Berlin",
    "iso:country":"DE",
    "name:cat_x_preferred":[
        "Wildhaus"
    ],
    "name:ceb_x_preferred":[
        "Wildhaus"
    ],
    "name:cym_x_preferred":[
        "Wildhaus"
    ],
    "name:deu_x_preferred":[
        "Wildhaus"
    ],
    "name:epo_x_preferred":[
        "Wildhaus"
    ],
    "name:fra_x_preferred":[
        "Wildhaus"
    ],
    "name:ita_x_preferred":[
        "Wildhaus"
    ],
    "name:kaz_x_preferred":[
        "\u0412\u0438\u043b\u044c\u0434\u0445\u0430\u0443\u0441"
    ],
    "name:nld_x_preferred":[
        "Wildhaus"
    ],
    "name:pms_x_preferred":[
        "Wildhaus"
    ],
    "name:pnb_x_preferred":[
        "\u0648\u0627\u0626\u0644\u0688\u06c1\u0627\u0624\u0633"
    ],
    "name:pol_x_preferred":[
        "Wildhaus"
    ],
    "name:por_x_preferred":[
        "Wildhaus"
    ],
    "name:ron_x_preferred":[
        "Wildhaus"
    ],
    "name:rus_x_preferred":[
        "\u0412\u0438\u043b\u044c\u0434\u0445\u0430\u0443\u0441"
    ],
    "name:spa_x_preferred":[
        "Wildhaus"
    ],
    "name:uzb_x_preferred":[
        "Wildhaus"
    ],
    "name:vol_x_preferred":[
        "Wildhaus"
    ],
    "wof:name":"Wildhaus",
    "wof:placetype":"neighbourhood"
},
  "geometry": {"coordinates":[11.68333,50.75],"type":"Point"}
}