{
  "type": "Feature",
  "properties": {
    "gn:admin1_code":"6",
    "gn:admin2_code":"0.0",
    "gn:admin3_code":"3157.0",
    "gn:admin4_code":"3157007.0",
    "gn:asciiname":"Koechingen",
    "gn:country_code":"DE",
    "gn:dem":80,
    "gn:feature_class":"P",
    "gn:feature_code":"PPL",
    "gn:name":"K\u00f6chingen",
    "gn:population":0,
    "gn:timezone":"Europe/Berlin",
    "iso:country":"DE",
    "name:gml_x_preferred":[
        "Cogginge [~ a. 1200]"
    ],
    "name:nds_x_preferred":[
        "K\u00f6chich"
    ],
    "name:nds_x_variant":[
        "K\u00f6chig"
    ],
    "name:osx_x_preferred":[
        "Cochigghe"
    ],
    "wof:name":"Koechingen",
    "wof:placetype":"neighbourhood"
},
  "geometry": {"coordinates":[10.36783,52.2402],"type":"Point"}
}