{
  "type": "Feature",
  "properties": {
    "gn:admin1_code":"2",
    "gn:admin2_code":"91.0",
    "gn:admin3_code":"9180.0",
    "gn:admin4_code":"9180127.0",
    "gn:asciiname":"Kleinaschau",
    "gn:country_code":"DE",
    "gn:dem":625,
    "gn:feature_class":"P",
    "gn:feature_code":"PPL",
    "gn:name":"Kleinaschau",
    "gn:population":0,
    "gn:timezone":"Europe/Berlin",
    "iso:country":"DE",
    "wof:name":"Kleinaschau",
    "wof:placetype":"neighbourhood"
},
  "geometry": {"coordinates":[11.20556,47.63616],"type":"Point"}
}