{
  "type": "Feature",
  "properties": {
    "gn:admin1_code":"10",
    "gn:admin2_code":"0.0",
    "gn:admin3_code":"1060.0",
    "gn:admin4_code":"1060075.0",
    "gn:asciiname":"Kembs",
    "gn:country_code":"DE",
    "gn:dem":39,
    "gn:feature_class":"P",
    "gn:feature_code":"PPL",
    "gn:name":"Kembs",
    "gn:population":0,
    "gn:timezone":"Europe/Berlin",
    "iso:country":"DE",
    "name:als_x_preferred":[
        "Kembs"
    ],
    "name:bug_x_preferred":[
        "Kembs"
    ],
    "name:cat_x_preferred":[
        "Kembs"
    ],
    "name:ceb_x_preferred":[
        "Kembs"
    ],
    "name:deu_x_preferred":[
        "Kembs"
    ],
    "name:eus_x_preferred":[
        "Kembs"
    ],
    "name:fra_x_preferred":[
        "Kembs"
    ],
    "name:hun_x_preferred":[
        "Kembs"
    ],
    "name:ita_x_preferred":[
        "Kembs"
    ],
    "name:kaz_x_preferred":[
        "\u041a\u0435\u043c\u0431\u0441"
    ],
    "name:lat_x_preferred":[
        "Cambetis"
    ],
    "name:msa_x_preferred":[
        "Kembs"
    ],
    "name:nld_x_preferred":[
        "Kembs"
    ],
    "name:oci_x_preferred":[
        "Kembs"
    ],
    "name:pfl_x_preferred":[
        "Kembs"
    ],
    "name:pms_x_preferred":[
        "Kembs"
    ],
    "name:pol_x_preferred":[
        "Kembs"
    ],
    "name:por_x_preferred":[
        "Kembs"
    ],
    "name:ron_x_preferred":[
        "Kembs"
    ],
    "name:rus_x_preferred":[
        "\u041a\u0435\u043c\u0431\u0441"
    ],
    "name:slk_x_preferred":[
        "Kembs"
    ],
    "name:slv_x_preferred":[
        "Kembs"
    ],
    "name:spa_x_preferred":[
        "Kembs"
    ],
    "name:srp_x_preferred":[
        "\u041a\u0435\u043c\u0431\u0441"
    ],
    "name:swe_x_preferred":[
        "Kembs"
    ],
    "name:ukr_x_preferred":[
        "\u041a\u0435\u043c\u0431\u0441"
    ],
    "name:uzb_x_preferred":[
        "Kembs"
    ],
    "name:vie_x_preferred":[
        "Kembs"
    ],
    "name:vol_x_preferred":[
        "Kembs"
    ],
    "name:war_x_preferred":[
        "Kembs"
    ],
    "name:zho_x_preferred":[
        "\u51ef\u59c6\u65af"
    ],
    "wof:name":"Kembs",
    "wof:placetype":"neighbourhood"
},
  "geometry": {"coordinates":[10.42454,54.07183000000001],"type":"Point"}
}