{
  "type": "Feature",
  "properties": {
    "gn:admin1_code":"5",
    "gn:admin2_code":"65.0",
    "gn:admin3_code":"6532.0",
    "gn:admin4_code":"6532008.0",
    "gn:asciiname":"Dreisbach",
    "gn:country_code":"DE",
    "gn:dem":238,
    "gn:feature_class":"P",
    "gn:feature_code":"PPL",
    "gn:name":"Dreisbach",
    "gn:population":0,
    "gn:timezone":"Europe/Berlin",
    "iso:country":"DE",
    "name:ceb_x_preferred":[
        "Dreisbach"
    ],
    "name:deu_x_preferred":[
        "Dreisbach"
    ],
    "name:pol_x_preferred":[
        "Dreisbach"
    ],
    "name:rus_x_preferred":[
        "\u0414\u0440\u0430\u0439\u0441\u0431\u0430\u0445"
    ],
    "name:swe_x_preferred":[
        "Dreisbach"
    ],
    "wof:name":"Dreisbach",
    "wof:placetype":"neighbourhood"
},
  "geometry": {"coordinates":[8.39304,50.65068],"type":"Point"}
}