{
  "type": "Feature",
  "properties": {
    "gn:admin1_code":"13",
    "gn:admin2_code":"0.0",
    "gn:admin3_code":"14625.0",
    "gn:admin4_code":"14625240.0",
    "gn:asciiname":"Klein Neida",
    "gn:country_code":"DE",
    "gn:dem":123,
    "gn:feature_class":"P",
    "gn:feature_code":"PPL",
    "gn:name":"Klein Neida",
    "gn:population":0,
    "gn:timezone":"Europe/Berlin",
    "iso:country":"DE",
    "name:hsb_x_preferred":[
        "Ma\u0142a Nydej"
    ],
    "name:und_x_variant":[
        "Kolonie Klein Weidau",
        "Klein Neida"
    ],
    "wof:name":"Klein Neida",
    "wof:placetype":"neighbourhood"
},
  "geometry": {"coordinates":[14.23191,51.42914],"type":"Point"}
}