{
  "type": "Feature",
  "properties": {
    "gn:gn_country":"DE",
    "gn:gn_fcode":"PPLA4",
    "gn:gn_pop":1008,
    "gn:population":1008,
    "iso:country":"DE",
    "name:baq_x_preferred":[
        "Gro\u00dfholbach"
    ],
    "name:chi_x_preferred":[
        "\u5927\u970d\u5c14\u5df4\u8d6b"
    ],
    "name:dut_x_preferred":[
        "Gro\u00dfholbach"
    ],
    "name:eng_x_preferred":[
        "Gro\u00dfholbach"
    ],
    "name:epo_x_preferred":[
        "Gro\u00dfholbach"
    ],
    "name:fre_x_preferred":[
        "Gro\u00dfholbach"
    ],
    "name:ger_x_preferred":[
        "Gro\u00dfholbach"
    ],
    "name:hun_x_preferred":[
        "Gro\u00dfholbach"
    ],
    "name:ita_x_preferred":[
        "Gro\u00dfholbach"
    ],
    "name:jpn_x_preferred":[
        "\u30b0\u30ed\u30fc\u30b9\u30db\u30eb\u30d0\u30c3\u30cf"
    ],
    "name:may_x_preferred":[
        "Gro\u00dfholbach"
    ],
    "name:per_x_preferred":[
        "\u06af\u0631\u0648\u0633\u0647\u0648\u0644\u0628\u0627\u062e"
    ],
    "name:pol_x_preferred":[
        "Gro\u00dfholbach"
    ],
    "name:por_x_preferred":[
        "Gro\u00dfholbach"
    ],
    "name:rum_x_preferred":[
        "Gro\u00dfholbach"
    ],
    "name:rus_x_preferred":[
        "\u0413\u0440\u043e\u0441\u0445\u043e\u043b\u044c\u0431\u0430\u0445"
    ],
    "name:srp_x_preferred":[
        "\u0413\u0440\u043e\u0441\u0445\u043e\u043b\u0431\u0430\u0445"
    ],
    "name:ukr_x_preferred":[
        "\u0413\u0440\u043e\u0441\u0433\u043e\u043b\u044c\u0431\u0430\u0445"
    ],
    "name:uzb_x_preferred":[
        "Gro\u00dfholbach"
    ],
    "name:vie_x_preferred":[
        "Gro\u00dfholbach"
    ],
    "name:vol_x_preferred":[
        "Gro\u00dfholbach"
    ],
    "name:war_x_preferred":[
        "Gro\u00dfholbach"
    ],
    "qs_pg:aaroncc":"DE",
    "qs_pg:gn_country":"DE",
    "qs_pg:gn_fcode":"PPLA4",
    "qs_pg:gn_pop":1008,
    "qs_pg:name":"Gro\u00dfholbach",
    "qs_pg:photos_9r":0,
    "qs_pg:photos_sr":0,
    "qs_pg:pop_sr":3,
    "qs_pg:qs_pg_placetype":"locality",
    "wof:name":"Gro\u00dfholbach",
    "wof:placetype":"locality",
    "wof:population":1008
},
  "geometry": {"coordinates":[7.88333,50.45],"type":"Point"}
}