{
  "type": "Feature",
  "properties": {
    "gn:admin1_code":"6",
    "gn:admin2_code":"0.0",
    "gn:admin3_code":"3157.0",
    "gn:admin4_code":"3157006.0",
    "gn:asciiname":"Hofschwicheldt",
    "gn:cc2":"DE",
    "gn:country_code":"DE",
    "gn:dem":78,
    "gn:feature_class":"P",
    "gn:feature_code":"PPL",
    "gn:name":"Hofschwicheldt",
    "gn:population":0,
    "gn:timezone":"Europe/Berlin",
    "iso:country":"DE",
    "name:und_x_variant":[
        "Hofschwichelt"
    ],
    "wof:name":"Hofschwicheldt",
    "wof:placetype":"neighbourhood"
},
  "geometry": {"coordinates":[10.14278,52.28969],"type":"Point"}
}