{
  "type": "Feature",
  "properties": {
    "gn:admin1_code":"7",
    "gn:admin2_code":"53.0",
    "gn:admin3_code":"5378.0",
    "gn:admin4_code":"5378012.0",
    "gn:asciiname":"Gross Klev",
    "gn:country_code":"DE",
    "gn:dem":262,
    "gn:feature_class":"P",
    "gn:feature_code":"PPL",
    "gn:name":"Gro\u00df Klev",
    "gn:population":0,
    "gn:timezone":"Europe/Berlin",
    "iso:country":"DE",
    "wof:name":"Gross Klev",
    "wof:placetype":"neighbourhood"
},
  "geometry": {"coordinates":[7.23333,51.06667],"type":"Point"}
}