{
  "type": "Feature",
  "properties": {
    "gn:admin1_code":"14",
    "gn:admin2_code":"0.0",
    "gn:admin3_code":"15089.0",
    "gn:admin4_code":"15089055.0",
    "gn:asciiname":"Schwarz",
    "gn:country_code":"DE",
    "gn:dem":57,
    "gn:feature_class":"P",
    "gn:feature_code":"PPL",
    "gn:name":"Schwarz",
    "gn:population":0,
    "gn:timezone":"Europe/Berlin",
    "iso:country":"DE",
    "name:bel_x_preferred":[
        "\u0428\u0432\u0430\u0440\u0446"
    ],
    "name:ceb_x_preferred":[
        "Schwarz"
    ],
    "name:ces_x_preferred":[
        "Schwarz"
    ],
    "name:deu_x_preferred":[
        "Schwarz"
    ],
    "name:fin_x_preferred":[
        "Schwarz"
    ],
    "name:fra_x_preferred":[
        "Schwarz"
    ],
    "name:heb_x_preferred":[
        "\u05e9\u05d5\u05d5\u05e8\u05e5"
    ],
    "name:ita_x_preferred":[
        "Schwarz"
    ],
    "name:jpn_x_preferred":[
        "\u30b7\u30e5\u30ef\u30eb\u30c4"
    ],
    "name:kor_x_preferred":[
        "\uc288\ubc14\ub974\uce20"
    ],
    "name:lit_x_preferred":[
        "Schwarz"
    ],
    "name:nld_x_preferred":[
        "Schwarz"
    ],
    "name:pol_x_preferred":[
        "Schwarz"
    ],
    "name:por_x_preferred":[
        "Schwarz"
    ],
    "name:rus_x_preferred":[
        "\u0428\u0432\u0430\u0440\u0446"
    ],
    "name:spa_x_preferred":[
        "Schwarz"
    ],
    "name:swe_x_preferred":[
        "Schwarz"
    ],
    "name:ukr_x_preferred":[
        "\u0428\u0432\u0430\u0440\u0446"
    ],
    "wof:name":"Schwarz",
    "wof:placetype":"neighbourhood"
},
  "geometry": {"coordinates":[11.79368,51.89068],"type":"Point"}
}