{
  "type": "Feature",
  "properties": {
    "gn:admin1_code":"2",
    "gn:admin2_code":"94.0",
    "gn:admin3_code":"9475.0",
    "gn:admin4_code":"9475169.0",
    "gn:asciiname":"Thiemitz",
    "gn:country_code":"DE",
    "gn:dem":489,
    "gn:feature_class":"P",
    "gn:feature_code":"PPL",
    "gn:name":"Thiemitz",
    "gn:population":0,
    "gn:timezone":"Europe/Berlin",
    "iso:country":"DE",
    "wof:name":"Thiemitz",
    "wof:placetype":"neighbourhood"
},
  "geometry": {"coordinates":[11.58595,50.29656],"type":"Point"}
}