{
  "type": "Feature",
  "properties": {
    "gn:admin1_code":"2.0",
    "gn:admin2_code":"092",
    "gn:admin3_code":"9279.0",
    "gn:admin4_code":"9279134.0",
    "gn:asciiname":"Wildprechting",
    "gn:country_code":"DE",
    "gn:dem":443,
    "gn:feature_class":"P",
    "gn:feature_code":"PPL",
    "gn:name":"Wildprechting",
    "gn:population":0,
    "gn:timezone":"Europe/Berlin",
    "iso:country":"DE",
    "wof:name":"Wildprechting",
    "wof:placetype":"neighbourhood"
},
  "geometry": {"coordinates":[12.63634,48.49163],"type":"Point"}
}