{
  "type": "Feature",
  "properties": {
    "iso:country":"DE",
    "name:deu_x_preferred":[
        "Mockau-S\u00fcd"
    ],
    "wof:name":"Mockau-Sued",
    "wof:placetype":"neighbourhood"
},
  "geometry": {"coordinates":[12.40800140394703,51.36971130456368],"type":"Point"}
}