{
  "type": "Feature",
  "properties": {
    "gn:admin1_code":"15",
    "gn:admin2_code":"0.0",
    "gn:admin3_code":"16074.0",
    "gn:admin4_code":"16074077.0",
    "gn:asciiname":"Hellborn",
    "gn:country_code":"DE",
    "gn:dem":320,
    "gn:feature_class":"P",
    "gn:feature_code":"PPL",
    "gn:name":"Hellborn",
    "gn:population":0,
    "gn:timezone":"Europe/Berlin",
    "iso:country":"DE",
    "name:fra_x_preferred":[
        "Hellborn"
    ],
    "name:rus_x_preferred":[
        "\u041f\u043e\u0440\u043e\u0436\u0434\u0435\u043d\u0438\u0435 \u0430\u0434\u0430"
    ],
    "wof:name":"Hellborn",
    "wof:placetype":"neighbourhood"
},
  "geometry": {"coordinates":[11.87497,50.81305],"type":"Point"}
}