{
  "type": "Feature",
  "properties": {
    "gn:admin1_code":"13",
    "gn:admin2_code":"0.0",
    "gn:admin3_code":"14521.0",
    "gn:admin4_code":"14521060.0",
    "gn:asciiname":"Oberbarenstein",
    "gn:country_code":"DE",
    "gn:dem":757,
    "gn:feature_class":"P",
    "gn:feature_code":"PPL",
    "gn:name":"Oberb\u00e4renstein",
    "gn:population":0,
    "gn:timezone":"Europe/Berlin",
    "iso:country":"DE",
    "wof:name":"Oberbarenstein",
    "wof:placetype":"neighbourhood"
},
  "geometry": {"coordinates":[13.0267,50.49967],"type":"Point"}
}