{
  "type": "Feature",
  "properties": {
    "gn:admin1_code":"2",
    "gn:admin2_code":"91.0",
    "gn:admin3_code":"9190.0",
    "gn:admin4_code":"9190157.0",
    "gn:asciiname":"Tollern",
    "gn:country_code":"DE",
    "gn:dem":560,
    "gn:feature_class":"P",
    "gn:feature_code":"PPL",
    "gn:name":"T\u00f6llern",
    "gn:population":0,
    "gn:timezone":"Europe/Berlin",
    "iso:country":"DE",
    "wof:name":"Tollern",
    "wof:placetype":"neighbourhood"
},
  "geometry": {"coordinates":[11.15086,47.85164],"type":"Point"}
}