{
  "type": "Feature",
  "properties": {
    "gn:admin1_code":"2",
    "gn:admin2_code":"91.0",
    "gn:admin3_code":"9186.0",
    "gn:admin4_code":"9186122.0",
    "gn:asciiname":"Engelbrechtsmunster",
    "gn:country_code":"DE",
    "gn:dem":377,
    "gn:feature_class":"P",
    "gn:feature_code":"PPL",
    "gn:name":"Engelbrechtsm\u00fcnster",
    "gn:population":0,
    "gn:timezone":"Europe/Berlin",
    "iso:country":"DE",
    "name:und_x_variant":[
        "Engelbrechtsm\u00fcnster"
    ],
    "wof:name":"Engelbrechtsmunster",
    "wof:placetype":"neighbourhood"
},
  "geometry": {"coordinates":[11.63371,48.6937],"type":"Point"}
}