{
  "type": "Feature",
  "properties": {
    "gn:gn_country":"DE",
    "gn:gn_fcode":"PPLA4",
    "gn:gn_pop":388,
    "gn:population":388,
    "iso:country":"DE",
    "name:baq_x_preferred":[
        "Endsch\u00fctz"
    ],
    "name:chi_x_preferred":[
        "\u6069\u8328\u8bb8\u8328"
    ],
    "name:dut_x_preferred":[
        "Endsch\u00fctz"
    ],
    "name:eng_x_preferred":[
        "Endsch\u00fctz"
    ],
    "name:epo_x_preferred":[
        "Endsch\u00fctz"
    ],
    "name:fre_x_preferred":[
        "Endsch\u00fctz"
    ],
    "name:ger_x_preferred":[
        "Endsch\u00fctz"
    ],
    "name:hun_x_preferred":[
        "Endsch\u00fctz"
    ],
    "name:ita_x_preferred":[
        "Endsch\u00fctz"
    ],
    "name:kaz_x_preferred":[
        "\u042d\u043d\u0434\u0448\u044e\u0446"
    ],
    "name:kir_x_preferred":[
        "\u042d\u043d\u0434\u0448\u044e\u0446"
    ],
    "name:mac_x_preferred":[
        "\u0415\u043d\u0434\u0448\u0438\u0446"
    ],
    "name:may_x_preferred":[
        "Endsch\u00fctz"
    ],
    "name:per_x_preferred":[
        "\u0627\u0646\u062f\u0634\u0648\u062a\u0633"
    ],
    "name:pol_x_preferred":[
        "Endsch\u00fctz"
    ],
    "name:por_x_preferred":[
        "Endsch\u00fctz"
    ],
    "name:rum_x_preferred":[
        "Endsch\u00fctz"
    ],
    "name:rus_x_preferred":[
        "\u042d\u043d\u0434\u0448\u044e\u0446"
    ],
    "name:srp_x_preferred":[
        "\u0415\u043d\u0434\u0448\u0438\u0446"
    ],
    "name:ukr_x_preferred":[
        "\u0415\u043d\u0434\u0448\u044e\u0446"
    ],
    "name:uzb_x_preferred":[
        "Endsch\u00fctz"
    ],
    "name:vol_x_preferred":[
        "Endsch\u00fctz"
    ],
    "name:war_x_preferred":[
        "Endsch\u00fctz"
    ],
    "qs_pg:aaroncc":"DE",
    "qs_pg:gn_country":"DE",
    "qs_pg:gn_fcode":"PPLA4",
    "qs_pg:gn_pop":388,
    "qs_pg:name":"Endsch\u00fctz",
    "qs_pg:photos_9r":0,
    "qs_pg:photos_sr":0,
    "qs_pg:pop_sr":2,
    "qs_pg:qs_pg_placetype":"locality",
    "wof:name":"Endsch\u00fctz",
    "wof:placetype":"locality",
    "wof:population":388
},
  "geometry": {"coordinates":[12.13333,50.78333],"type":"Point"}
}