{
  "type": "Feature",
  "properties": {
    "gn:admin1_code":"11",
    "gn:admin2_code":"0.0",
    "gn:admin3_code":"12068.0",
    "gn:admin4_code":"12068468.0",
    "gn:asciiname":"Neu Coelln",
    "gn:cc2":"DE",
    "gn:country_code":"DE",
    "gn:dem":84,
    "gn:feature_class":"P",
    "gn:feature_code":"PPL",
    "gn:name":"Neu C\u00f6lln",
    "gn:population":0,
    "gn:timezone":"Europe/Berlin",
    "iso:country":"DE",
    "name:und_x_variant":[
        "Neuk\u00f6lln"
    ],
    "wof:name":"Neu Coelln",
    "wof:placetype":"neighbourhood"
},
  "geometry": {"coordinates":[12.37885,53.27435],"type":"Point"}
}