{
  "type": "Feature",
  "properties": {
    "gn:admin1_code":"15.0",
    "gn:admin2_code":"0.0",
    "gn:admin3_code":"16073.0",
    "gn:admin4_code":"16073094.0",
    "gn:asciiname":"Quelitz",
    "gn:country_code":"DE",
    "gn:dem":356,
    "gn:feature_class":"P",
    "gn:feature_code":"PPL",
    "gn:name":"Quelitz",
    "gn:population":0,
    "gn:timezone":"Europe/Berlin",
    "iso:country":"DE",
    "wof:name":"Quelitz",
    "wof:placetype":"neighbourhood"
},
  "geometry": {"coordinates":[11.17557,50.60758],"type":"Point"}
}