{
  "type": "Feature",
  "properties": {
    "gn:admin1_code":"10",
    "gn:admin2_code":"0.0",
    "gn:admin3_code":"1062.0",
    "gn:admin4_code":"1062016.0",
    "gn:asciiname":"Fischbek",
    "gn:country_code":"DE",
    "gn:dem":31,
    "gn:feature_class":"P",
    "gn:feature_code":"PPL",
    "gn:name":"Fischbek",
    "gn:population":0,
    "gn:timezone":"Europe/Berlin",
    "iso:country":"DE",
    "wof:name":"Fischbek",
    "wof:placetype":"neighbourhood"
},
  "geometry": {"coordinates":[10.28706,53.76387],"type":"Point"}
}