{
  "type": "Feature",
  "properties": {
    "gn:admin1_code":"6.0",
    "gn:admin2_code":"00",
    "gn:admin3_code":"3401.0",
    "gn:admin4_code":"3401000.0",
    "gn:asciiname":"Wiekhorn",
    "gn:country_code":"DE",
    "gn:dem":11,
    "gn:feature_class":"P",
    "gn:feature_code":"PPL",
    "gn:name":"Wiekhorn",
    "gn:population":0,
    "gn:timezone":"Europe/Berlin",
    "iso:country":"DE",
    "wof:name":"Wiekhorn",
    "wof:placetype":"neighbourhood"
},
  "geometry": {"coordinates":[8.63333,53.03333000000001],"type":"Point"}
}