{
  "type": "Feature",
  "properties": {
    "gn:admin1_code":"2",
    "gn:admin2_code":"91.0",
    "gn:admin3_code":"9176.0",
    "gn:admin4_code":"9176114.0",
    "gn:asciiname":"Paulushofen",
    "gn:country_code":"DE",
    "gn:dem":507,
    "gn:feature_class":"P",
    "gn:feature_code":"PPL",
    "gn:name":"Paulushofen",
    "gn:population":0,
    "gn:timezone":"Europe/Berlin",
    "iso:country":"DE",
    "wof:name":"Paulushofen",
    "wof:placetype":"neighbourhood"
},
  "geometry": {"coordinates":[11.50037,49.01102],"type":"Point"}
}