{
  "type": "Feature",
  "properties": {
    "gn:admin1_code":"2",
    "gn:admin2_code":"94.0",
    "gn:admin3_code":"9477.0",
    "gn:admin4_code":"9477139.0",
    "gn:asciiname":"Mittelpollitz",
    "gn:country_code":"DE",
    "gn:dem":503,
    "gn:feature_class":"P",
    "gn:feature_code":"PPL",
    "gn:name":"Mittelp\u00f6llitz",
    "gn:population":0,
    "gn:timezone":"Europe/Berlin",
    "iso:country":"DE",
    "wof:name":"Mittelpollitz",
    "wof:placetype":"neighbourhood"
},
  "geometry": {"coordinates":[11.63289,50.09679000000001],"type":"Point"}
}