{
  "type": "Feature",
  "properties": {
    "gn:admin1_code":"12",
    "gn:admin2_code":"0.0",
    "gn:admin3_code":"13071.0",
    "gn:admin4_code":"13071159.0",
    "gn:asciiname":"Strasen",
    "gn:country_code":"DE",
    "gn:dem":58,
    "gn:feature_class":"P",
    "gn:feature_code":"PPL",
    "gn:name":"Strasen",
    "gn:population":0,
    "gn:timezone":"Europe/Berlin",
    "iso:country":"DE",
    "wof:name":"Strasen",
    "wof:placetype":"neighbourhood"
},
  "geometry": {"coordinates":[12.99353,53.20801],"type":"Point"}
}