{
  "type": "Feature",
  "properties": {
    "gn:gn_country":"DE",
    "gn:gn_fcode":"PPL",
    "gn:gn_pop":0,
    "iso:country":"DE",
    "name:ben_x_preferred":[
        "\u0995\u09c8\u09b2\u09be\u09b0\u09be\u09b8"
    ],
    "name:bpy_x_preferred":[
        "\u0995\u09c8\u09b2\u09be\u09b0\u09be\u09b8"
    ],
    "name:ceb_x_preferred":[
        "Eich"
    ],
    "name:ceb_x_variant":[
        "Kail\u0101ras"
    ],
    "name:deu_x_preferred":[
        "Eich"
    ],
    "name:epo_x_preferred":[
        "Eich"
    ],
    "name:fra_x_preferred":[
        "Eich"
    ],
    "name:ita_x_preferred":[
        "Eich"
    ],
    "name:ita_x_variant":[
        "Kailaras"
    ],
    "name:msa_x_preferred":[
        "Kailaras"
    ],
    "name:new_x_preferred":[
        "\u0915\u0948\u0932\u093e\u0930\u093e\u0938"
    ],
    "name:nld_x_preferred":[
        "Eich"
    ],
    "name:nld_x_variant":[
        "Kailaras"
    ],
    "name:pol_x_preferred":[
        "Eich"
    ],
    "name:por_x_preferred":[
        "Kailaras"
    ],
    "name:spa_x_preferred":[
        "Kailaras"
    ],
    "name:swe_x_preferred":[
        "Kail\u0101ras"
    ],
    "name:unk_x_variant":[
        "Eich"
    ],
    "name:vie_x_preferred":[
        "Kailaras"
    ],
    "name:vol_x_preferred":[
        "Eich"
    ],
    "name:zho_x_preferred":[
        "\u51ef\u62c9\u62c9\u65af"
    ],
    "qs:gn_fcode":"PPL",
    "qs:gn_local":0,
    "qs:gn_namadm1":"07",
    "qs:gn_name":"Eich",
    "qs:local_max":7923,
    "qs:local_sum":22653,
    "qs:localhoods":31,
    "qs:name":"Eich",
    "qs:name_adm0":"Deutschland",
    "qs:name_adm1":"Nordrhein-Westfalen",
    "qs:name_adm2":"Stadtkreis Aachen",
    "qs:name_lau":"Stadtteil Hahn",
    "qs:name_local":"Aachen",
    "qs:photo_max":291,
    "qs:photo_sum":370,
    "qs:placetype":"Suburb",
    "qs:quad_count":5,
    "qs:woe_adm0":23424829,
    "qs:woe_adm1":2345487,
    "qs:woe_adm2":20071103,
    "qs:woe_lau":26821835,
    "qs:woe_local":633175,
    "qs:woe_ver":"7.10.0",
    "qs_pg:aaroncc":"DE",
    "qs_pg:gn_country":"DE",
    "qs_pg:gn_fcode":"PPL",
    "qs_pg:gn_pop":0,
    "qs_pg:name":"Eich",
    "qs_pg:name_adm0":"Deutschland",
    "qs_pg:name_adm1":"Nordrhein-Westfalen",
    "qs_pg:photos":373,
    "qs_pg:photos_1k":76,
    "qs_pg:photos_9k":2,
    "qs_pg:photos_9r":5,
    "qs_pg:photos_all":373,
    "qs_pg:photos_sr":6,
    "qs_pg:pop_sr":0,
    "qs_pg:qs_pg_placetype":"neighbourhood",
    "qs_pg:qs_pg_placetype_gp":"Suburb",
    "qs_pg:woe_adm0":23424829,
    "wof:lang":[
        "ger"
    ],
    "wof:name":"Eich",
    "wof:placetype":"neighbourhood"
},
  "geometry": {"coordinates":[6.118063,50.719086],"type":"Point"}
}