{
  "type": "Feature",
  "properties": {
    "gn:admin1_code":"7.0",
    "gn:admin2_code":"053",
    "gn:admin3_code":"5374.0",
    "gn:admin4_code":"5374040.0",
    "gn:asciiname":"Wildbergerhuette",
    "gn:country_code":"DE",
    "gn:dem":316,
    "gn:feature_class":"P",
    "gn:feature_code":"PPL",
    "gn:name":"Wildbergerh\u00fctte",
    "gn:population":0,
    "gn:timezone":"Europe/Berlin",
    "iso:country":"DE",
    "name:deu_x_preferred":[
        "Wildbergerh\u00fctte"
    ],
    "wof:name":"Wildbergerhuette",
    "wof:placetype":"neighbourhood"
},
  "geometry": {"coordinates":[7.75023,50.93857],"type":"Point"}
}