{
  "type": "Feature",
  "properties": {
    "iso:country":"DE",
    "name:deu_x_preferred":[
        "Gneversdorf"
    ],
    "name:unk_x_variant":[
        "Gneversdorf"
    ],
    "qs:gn_adm0_cc":"DE",
    "qs:gn_fcode":"PPL",
    "qs:gn_local":2875601,
    "qs:gn_namadm1":"12",
    "qs:gn_name":"Gersdorf",
    "qs:local_max":2963,
    "qs:local_sum":12788,
    "qs:localhoods":32,
    "qs:name":"Gneversdorf",
    "qs:name_adm0":"Deutschland",
    "qs:name_adm1":"Schleswig-Holstein",
    "qs:name_adm2":"Stadtkreis L\u00fcbeck",
    "qs:name_lau":"Stadtteil Travem\u00fcnde",
    "qs:name_local":"L\u00fcbeck",
    "qs:photo_max":7,
    "qs:photo_sum":24,
    "qs:placetype":"Suburb",
    "qs:quad_count":11,
    "qs:woe_adm0":23424829,
    "qs:woe_adm1":2345490,
    "qs:woe_adm2":12597082,
    "qs:woe_lau":26822951,
    "qs:woe_local":672826,
    "qs:woe_ver":"7.10.0",
    "wof:lang":[
        "ger"
    ],
    "wof:name":"Gneversdorf",
    "wof:placetype":"neighbourhood"
},
  "geometry": {"coordinates":[10.847168,53.96201],"type":"Point"}
}