{
  "type": "Feature",
  "properties": {
    "gn:admin1_code":"13",
    "gn:admin2_code":"0.0",
    "gn:admin3_code":"14628.0",
    "gn:admin4_code":"14628110.0",
    "gn:asciiname":"Saalhausen",
    "gn:country_code":"DE",
    "gn:dem":254,
    "gn:feature_class":"P",
    "gn:feature_code":"PPL",
    "gn:name":"Saalhausen",
    "gn:population":0,
    "gn:timezone":"Europe/Berlin",
    "iso:country":"DE",
    "wof:name":"Saalhausen",
    "wof:placetype":"neighbourhood"
},
  "geometry": {"coordinates":[13.61726,51.01193],"type":"Point"}
}