{
  "type": "Feature",
  "properties": {
    "gn:admin1_code":"11.0",
    "gn:admin2_code":"0.0",
    "gn:admin3_code":"12071.0",
    "gn:admin4_code":"12071301.0",
    "gn:asciiname":"Braesinchen",
    "gn:country_code":"DE",
    "gn:dem":85,
    "gn:feature_class":"P",
    "gn:feature_code":"PPL",
    "gn:name":"Br\u00e4sinchen",
    "gn:population":0,
    "gn:timezone":"Europe/Berlin",
    "iso:country":"DE",
    "name:dsb_x_preferred":[
        "Brjazynka"
    ],
    "wof:name":"Braesinchen",
    "wof:placetype":"neighbourhood"
},
  "geometry": {"coordinates":[14.40081,51.66275],"type":"Point"}
}