{
  "type": "Feature",
  "properties": {
    "gn:admin1_code":"2",
    "gn:admin2_code":"92.0",
    "gn:admin3_code":"9271.0",
    "gn:admin4_code":"9271152.0",
    "gn:asciiname":"Hasreit",
    "gn:country_code":"DE",
    "gn:dem":398,
    "gn:feature_class":"P",
    "gn:feature_code":"PPL",
    "gn:name":"Hasreit",
    "gn:population":0,
    "gn:timezone":"Europe/Berlin",
    "iso:country":"DE",
    "wof:name":"Hasreit",
    "wof:placetype":"neighbourhood"
},
  "geometry": {"coordinates":[12.86096,48.66961],"type":"Point"}
}