{
  "type": "Feature",
  "properties": {
    "gn:admin1_code":"1",
    "gn:admin2_code":"81.0",
    "gn:admin3_code":"8125.0",
    "gn:admin4_code":"8125107.0",
    "gn:asciiname":"Finsterrot",
    "gn:country_code":"DE",
    "gn:dem":486,
    "gn:feature_class":"P",
    "gn:feature_code":"PPL",
    "gn:name":"Finsterrot",
    "gn:population":0,
    "gn:timezone":"Europe/Berlin",
    "iso:country":"DE",
    "wof:name":"Finsterrot",
    "wof:placetype":"neighbourhood"
},
  "geometry": {"coordinates":[9.49299,49.08906],"type":"Point"}
}