{
  "type": "Feature",
  "properties": {
    "gn:admin1_code":"10.0",
    "gn:admin2_code":"0.0",
    "gn:admin3_code":"1061.0",
    "gn:admin4_code":"1061119.0",
    "gn:asciiname":"Achterhoern",
    "gn:country_code":"DE",
    "gn:dem":-2,
    "gn:feature_class":"P",
    "gn:feature_code":"PPLL",
    "gn:name":"Achterh\u00f6rn",
    "gn:population":0,
    "gn:timezone":"Europe/Berlin",
    "iso:country":"DE",
    "wof:name":"Achterhoern",
    "wof:placetype":"neighbourhood"
},
  "geometry": {"coordinates":[9.29932,53.96349],"type":"Point"}
}