{
  "type": "Feature",
  "properties": {
    "gn:admin1_code":"2",
    "gn:admin2_code":"92.0",
    "gn:admin3_code":"9278.0",
    "gn:admin4_code":"9278113.0",
    "gn:asciiname":"Geltolfing",
    "gn:country_code":"DE",
    "gn:dem":339,
    "gn:feature_class":"P",
    "gn:feature_code":"PPL",
    "gn:name":"Geltolfing",
    "gn:population":0,
    "gn:timezone":"Europe/Berlin",
    "iso:country":"DE",
    "wof:name":"Geltolfing",
    "wof:placetype":"locality"
},
  "geometry": {"coordinates":[12.60591,48.83543],"type":"Point"}
}