{
  "type": "Feature",
  "properties": {
    "gn:admin1_code":"10",
    "gn:admin2_code":"0.0",
    "gn:admin3_code":"1053.0",
    "gn:admin4_code":"1053062.0",
    "gn:asciiname":"Niendorf",
    "gn:country_code":"DE",
    "gn:dem":40,
    "gn:feature_class":"P",
    "gn:feature_code":"PPL",
    "gn:name":"Niendorf",
    "gn:population":0,
    "gn:timezone":"Europe/Berlin",
    "iso:country":"DE",
    "name:cat_x_preferred":[
        "Niendorf"
    ],
    "name:ceb_x_preferred":[
        "Niendorf"
    ],
    "name:deu_x_preferred":[
        "Niendorf"
    ],
    "name:epo_x_preferred":[
        "Niendorf"
    ],
    "name:fra_x_preferred":[
        "Niendorf"
    ],
    "name:ita_x_preferred":[
        "Niendorf"
    ],
    "name:mkd_x_preferred":[
        "\u041d\u0438\u043d\u0434\u043e\u0440\u0444"
    ],
    "name:nds_x_preferred":[
        "Niendorf"
    ],
    "name:nld_x_preferred":[
        "Niendorf"
    ],
    "name:pol_x_preferred":[
        "Niendorf"
    ],
    "name:rus_x_preferred":[
        "\u041d\u0438\u043d\u0434\u043e\u0440\u0444"
    ],
    "name:swe_x_preferred":[
        "Niendorf"
    ],
    "name:zho_x_preferred":[
        "\u5b81\u591a\u592b"
    ],
    "wof:name":"Niendorf",
    "wof:placetype":"neighbourhood"
},
  "geometry": {"coordinates":[10.93174,53.65288],"type":"Point"}
}