{
  "type": "Feature",
  "properties": {
    "gn:admin1_code":"12",
    "gn:admin2_code":"0.0",
    "gn:admin3_code":"13071.0",
    "gn:admin4_code":"13071054.0",
    "gn:asciiname":"Klein Daberkow",
    "gn:country_code":"DE",
    "gn:dem":100,
    "gn:feature_class":"P",
    "gn:feature_code":"PPL",
    "gn:name":"Klein Daberkow",
    "gn:population":0,
    "gn:timezone":"Europe/Berlin",
    "iso:country":"DE",
    "wof:name":"Klein Daberkow",
    "wof:placetype":"neighbourhood"
},
  "geometry": {"coordinates":[13.65552,53.53558],"type":"Point"}
}