{
  "type": "Feature",
  "properties": {
    "gn:admin1_code":"2.0",
    "gn:admin2_code":"097",
    "gn:admin3_code":"9773.0",
    "gn:admin4_code":"9773117.0",
    "gn:asciiname":"Zoltingen",
    "gn:country_code":"DE",
    "gn:dem":509,
    "gn:feature_class":"P",
    "gn:feature_code":"PPL",
    "gn:name":"Zoltingen",
    "gn:population":0,
    "gn:timezone":"Europe/Berlin",
    "iso:country":"DE",
    "wof:name":"Zoltingen",
    "wof:placetype":"neighbourhood"
},
  "geometry": {"coordinates":[10.51838,48.72364],"type":"Point"}
}