{
  "type": "Feature",
  "properties": {
    "gn:admin1_code":"1",
    "gn:admin2_code":"84.0",
    "gn:admin3_code":"8426.0",
    "gn:admin4_code":"8426100.0",
    "gn:asciiname":"Dietenberg",
    "gn:country_code":"DE",
    "gn:dem":674,
    "gn:feature_class":"P",
    "gn:feature_code":"PPL",
    "gn:name":"Dietenberg",
    "gn:population":0,
    "gn:timezone":"Europe/Berlin",
    "iso:country":"DE",
    "wof:name":"Dietenberg",
    "wof:placetype":"neighbourhood"
},
  "geometry": {"coordinates":[9.98219,47.9787],"type":"Point"}
}