{
  "type": "Feature",
  "properties": {
    "iso:country":"DE",
    "name:deu_x_preferred":[
        "Hordel"
    ],
    "name:tur_x_preferred":[
        "Bochum-Hordel"
    ],
    "wof:name":"Hordel",
    "wof:placetype":"neighbourhood"
},
  "geometry": {"coordinates":[7.17266344384849,51.4993619697778],"type":"Point"}
}