{
  "type": "Feature",
  "properties": {
    "iso:country":"DE",
    "wof:name":"Hordel",
    "wof:placetype":"neighbourhood"
},
  "geometry": {"coordinates":[7.17266344384849,51.4993619697778],"type":"Point"}
}