{
  "type": "Feature",
  "properties": {
    "gn:admin1_code":"13",
    "gn:admin2_code":"0.0",
    "gn:admin3_code":"14522.0",
    "gn:admin4_code":"14522190.0",
    "gn:asciiname":"Hilmsdorf",
    "gn:country_code":"DE",
    "gn:dem":275,
    "gn:feature_class":"P",
    "gn:feature_code":"PPL",
    "gn:name":"Hilmsdorf",
    "gn:population":0,
    "gn:timezone":"Europe/Berlin",
    "iso:country":"DE",
    "wof:name":"Hilmsdorf",
    "wof:placetype":"neighbourhood"
},
  "geometry": {"coordinates":[12.93333,51.06667],"type":"Point"}
}