{
  "type": "Feature",
  "properties": {
    "gn:admin1_code":"8",
    "gn:admin2_code":"0.0",
    "gn:admin3_code":"7138.0",
    "gn:admin4_code":"7138077.0",
    "gn:asciiname":"Schweifeld",
    "gn:country_code":"DE",
    "gn:dem":296,
    "gn:feature_class":"P",
    "gn:feature_code":"PPL",
    "gn:name":"Schweifeld",
    "gn:population":0,
    "gn:timezone":"Europe/Berlin",
    "iso:country":"DE",
    "name:deu_x_preferred":[
        "Schweifeld"
    ],
    "wof:name":"Schweifeld",
    "wof:placetype":"neighbourhood"
},
  "geometry": {"coordinates":[7.3175,50.63176],"type":"Point"}
}