{
  "type": "Feature",
  "properties": {
    "gn:admin1_code":"2",
    "gn:admin2_code":"95.0",
    "gn:admin3_code":"9576.0",
    "gn:admin4_code":"9576121.0",
    "gn:asciiname":"Petersgmund",
    "gn:country_code":"DE",
    "gn:dem":360,
    "gn:feature_class":"P",
    "gn:feature_code":"PPL",
    "gn:name":"Petersgm\u00fcnd",
    "gn:population":0,
    "gn:timezone":"Europe/Berlin",
    "iso:country":"DE",
    "wof:name":"Petersgmund",
    "wof:placetype":"neighbourhood"
},
  "geometry": {"coordinates":[11.02507,49.18643],"type":"Point"}
}