{
  "type": "Feature",
  "properties": {
    "gn:admin1_code":"5",
    "gn:admin2_code":"64.0",
    "gn:admin3_code":"6439.0",
    "gn:admin4_code":"6439014.0",
    "gn:asciiname":"Georgenborn",
    "gn:country_code":"DE",
    "gn:dem":375,
    "gn:feature_class":"P",
    "gn:feature_code":"PPL",
    "gn:name":"Georgenborn",
    "gn:population":0,
    "gn:timezone":"Europe/Berlin",
    "iso:country":"DE",
    "name:deu_x_preferred":[
        "Georgenborn"
    ],
    "wof:name":"Georgenborn",
    "wof:placetype":"neighbourhood"
},
  "geometry": {"coordinates":[8.12558,50.08864000000001],"type":"Point"}
}