{
  "type": "Feature",
  "properties": {
    "gn:admin1_code":"2",
    "gn:admin2_code":"93.0",
    "gn:admin3_code":"9374.0",
    "gn:admin4_code":"9374133.0",
    "gn:asciiname":"Unterwildenau",
    "gn:country_code":"DE",
    "gn:dem":383,
    "gn:feature_class":"P",
    "gn:feature_code":"PPL",
    "gn:name":"Unterwildenau",
    "gn:population":0,
    "gn:timezone":"Europe/Berlin",
    "iso:country":"DE",
    "wof:name":"Unterwildenau",
    "wof:placetype":"neighbourhood"
},
  "geometry": {"coordinates":[12.13528,49.59913],"type":"Point"}
}