{
  "type": "Feature",
  "properties": {
    "gn:admin1_code":"14",
    "gn:admin2_code":"0.0",
    "gn:admin3_code":"15083.0",
    "gn:admin4_code":"15083270.0",
    "gn:asciiname":"Papenberg",
    "gn:country_code":"DE",
    "gn:dem":76,
    "gn:feature_class":"P",
    "gn:feature_code":"PPL",
    "gn:name":"Papenberg",
    "gn:population":0,
    "gn:timezone":"Europe/Berlin",
    "iso:country":"DE",
    "wof:name":"Papenberg",
    "wof:placetype":"neighbourhood"
},
  "geometry": {"coordinates":[11.38116,52.29103],"type":"Point"}
}