{
  "type": "Feature",
  "properties": {
    "gn:country":"DE",
    "gn:fcode":"PPL",
    "gn:population":0,
    "iso:country":"DE",
    "name:dan_x_preferred":[
        "Sahlenburg"
    ],
    "name:deu_x_preferred":[
        "Sahlenburg"
    ],
    "name:nds_x_preferred":[
        "Sahlenborg"
    ],
    "name:nld_x_preferred":[
        "Sahlenburg"
    ],
    "name:pol_x_preferred":[
        "Sahlenburg"
    ],
    "qs_pg:aaroncc":"DE",
    "qs_pg:gn_country":"DE",
    "qs_pg:gn_fcode":"PPL",
    "qs_pg:gn_pop":0,
    "qs_pg:name":"Sahlenburg",
    "qs_pg:name_adm0":"Deutschland",
    "qs_pg:name_adm1":"Niedersachsen",
    "qs_pg:photos":279,
    "qs_pg:photos_1k":57,
    "qs_pg:photos_9k":1,
    "qs_pg:photos_9r":4,
    "qs_pg:photos_all":279,
    "qs_pg:photos_sr":5,
    "qs_pg:pop_sr":0,
    "qs_pg:qs_pg_placetype":"locality",
    "qs_pg:qs_pg_placetype_gp":"Town",
    "qs_pg:woe_adm0":23424829,
    "woe:adm0_id":23424829,
    "woe:name_adm0":"Deutschland",
    "woe:name_adm1":"Niedersachsen",
    "woe:placetype":"Town",
    "wof:name":"Sahlenburg",
    "wof:placetype":"neighbourhood"
},
  "geometry": {"coordinates":[8.62669,53.86186],"type":"Point"}
}