{
  "type": "Feature",
  "properties": {
    "gn:admin1_code":"2",
    "gn:admin2_code":"92.0",
    "gn:admin3_code":"9275.0",
    "gn:admin4_code":"9275159.0",
    "gn:asciiname":"Desching",
    "gn:country_code":"DE",
    "gn:dem":408,
    "gn:feature_class":"P",
    "gn:feature_code":"PPLL",
    "gn:name":"Desching",
    "gn:population":0,
    "gn:timezone":"Europe/Berlin",
    "iso:country":"DE",
    "wof:name":"Desching",
    "wof:placetype":"neighbourhood"
},
  "geometry": {"coordinates":[13.25698,48.65332],"type":"Point"}
}