{
  "type": "Feature",
  "properties": {
    "gn:admin1_code":"6.0",
    "gn:admin2_code":"00",
    "gn:admin3_code":"3351.0",
    "gn:admin4_code":"3351004.0",
    "gn:asciiname":"Widdernhausen",
    "gn:country_code":"DE",
    "gn:dem":81,
    "gn:feature_class":"P",
    "gn:feature_code":"PPL",
    "gn:name":"Widdernhausen",
    "gn:population":0,
    "gn:timezone":"Europe/Berlin",
    "iso:country":"DE",
    "wof:name":"Widdernhausen",
    "wof:placetype":"neighbourhood"
},
  "geometry": {"coordinates":[9.98056,52.8568],"type":"Point"}
}