{
  "type": "Feature",
  "properties": {
    "gn:admin1_code":"7",
    "gn:admin2_code":"59.0",
    "gn:admin3_code":"5974.0",
    "gn:admin4_code":"5974008.0",
    "gn:asciiname":"Opmuenden",
    "gn:country_code":"DE",
    "gn:dem":129,
    "gn:feature_class":"P",
    "gn:feature_code":"PPL",
    "gn:name":"Opm\u00fcnden",
    "gn:population":0,
    "gn:timezone":"Europe/Berlin",
    "iso:country":"DE",
    "wof:name":"Opmuenden",
    "wof:placetype":"neighbourhood"
},
  "geometry": {"coordinates":[8.16189,51.56015],"type":"Point"}
}