{
  "type": "Feature",
  "properties": {
    "iso:country":"DE",
    "name:deu_x_colloquial":[
        "Stuenz",
        "Stunz"
    ],
    "name:deu_x_preferred":[
        "St\u00fcnz"
    ],
    "name:eng_x_preferred":[
        "St\u00fcnz"
    ],
    "qs:gn_adm0_cc":"DE",
    "qs:gn_fcode":"PPL",
    "qs:gn_local":2879139,
    "qs:gn_nam_loc":"Leipzig, Kreisfreie Stadt Leipzig, Sachsen, DE",
    "qs:gn_namadm1":"13",
    "qs:gn_name":"St\u00fcnz",
    "qs:local_max":18559,
    "qs:local_sum":46030,
    "qs:localhoods":28,
    "qs:name":"St\u00fcnz",
    "qs:name_adm0":"Deutschland",
    "qs:name_adm1":"Sachsen",
    "qs:name_adm2":"Kreisfreie Stadt Leipzig",
    "qs:name_lau":"Sellerhausen-St\u00fcnz",
    "qs:name_local":"Leipzig",
    "qs:photo_max":42,
    "qs:photo_sum":272,
    "qs:placetype":"Suburb",
    "qs:quad_count":31,
    "qs:woe_adm0":23424829,
    "qs:woe_adm1":2345493,
    "qs:woe_adm2":12596753,
    "qs:woe_lau":26822914,
    "qs:woe_local":671072,
    "qs:woe_ver":"7.10.0",
    "wof:lang":[
        "ger"
    ],
    "wof:name":"Stuenz",
    "wof:placetype":"neighbourhood"
},
  "geometry": {"coordinates":[12.433472,51.340843],"type":"Point"}
}