{
  "type": "Feature",
  "properties": {
    "gn:admin1_code":"1",
    "gn:admin2_code":"82.0",
    "gn:admin3_code":"8237.0",
    "gn:admin4_code":"8237054.0",
    "gn:asciiname":"Herzogsweiler",
    "gn:country_code":"DE",
    "gn:dem":673,
    "gn:feature_class":"P",
    "gn:feature_code":"PPL",
    "gn:name":"Herzogsweiler",
    "gn:population":0,
    "gn:timezone":"Europe/Berlin",
    "iso:country":"DE",
    "wof:name":"Herzogsweiler",
    "wof:placetype":"neighbourhood"
},
  "geometry": {"coordinates":[8.53329,48.50899],"type":"Point"}
}