{
  "type": "Feature",
  "properties": {
    "gn:admin1_code":"7.0",
    "gn:admin2_code":"53.0",
    "gn:admin3_code":"5374.0",
    "gn:admin4_code":"5374052.0",
    "gn:asciiname":"Jaegerhof",
    "gn:country_code":"DE",
    "gn:dem":339,
    "gn:feature_class":"P",
    "gn:feature_code":"PPL",
    "gn:name":"J\u00e4gerhof",
    "gn:population":0,
    "gn:timezone":"Europe/Berlin",
    "iso:country":"DE",
    "wof:name":"Jaegerhof",
    "wof:placetype":"locality"
},
  "geometry": {"coordinates":[7.43137,51.10433],"type":"Point"}
}