{
  "type": "Feature",
  "properties": {
    "gn:admin1_code":"6",
    "gn:admin2_code":"0.0",
    "gn:admin3_code":"3462.0",
    "gn:admin4_code":"3462005.0",
    "gn:asciiname":"Langstrasse",
    "gn:country_code":"DE",
    "gn:dem":4,
    "gn:feature_class":"P",
    "gn:feature_code":"PPL",
    "gn:name":"Langstra\u00dfe",
    "gn:population":0,
    "gn:timezone":"Europe/Berlin",
    "iso:country":"DE",
    "name:deu_x_preferred":[
        "Langstrasse"
    ],
    "name:lat_x_preferred":[
        "Langstrasse"
    ],
    "wof:name":"Langstrasse",
    "wof:placetype":"neighbourhood"
},
  "geometry": {"coordinates":[7.87244,53.50255],"type":"Point"}
}