{
  "type": "Feature",
  "properties": {
    "gn:admin1_code":"13",
    "gn:admin2_code":"0.0",
    "gn:admin3_code":"14730.0",
    "gn:admin4_code":"14730080.0",
    "gn:asciiname":"Paschwitz",
    "gn:country_code":"DE",
    "gn:dem":119,
    "gn:feature_class":"P",
    "gn:feature_code":"PPL",
    "gn:name":"Paschwitz",
    "gn:population":0,
    "gn:timezone":"Europe/Berlin",
    "iso:country":"DE",
    "wof:name":"Paschwitz",
    "wof:placetype":"neighbourhood"
},
  "geometry": {"coordinates":[12.72217,51.46524],"type":"Point"}
}