{
  "type": "Feature",
  "properties": {
    "gn:admin1_code":"13",
    "gn:admin2_code":"0.0",
    "gn:admin3_code":"14625.0",
    "gn:admin4_code":"14625230.0",
    "gn:asciiname":"Pommritz",
    "gn:country_code":"DE",
    "gn:dem":234,
    "gn:feature_class":"P",
    "gn:feature_code":"PPL",
    "gn:name":"Pommritz",
    "gn:population":0,
    "gn:timezone":"Europe/Berlin",
    "iso:country":"DE",
    "name:hsb_x_preferred":[
        "Pomorcy"
    ],
    "wof:name":"Pommritz",
    "wof:placetype":"neighbourhood"
},
  "geometry": {"coordinates":[14.56788,51.16122],"type":"Point"}
}