{
  "type": "Feature",
  "properties": {
    "gn:admin1_code":"1",
    "gn:admin2_code":"84.0",
    "gn:admin3_code":"8436.0",
    "gn:admin4_code":"8436009.0",
    "gn:asciiname":"Oberurbach",
    "gn:country_code":"DE",
    "gn:dem":633,
    "gn:feature_class":"P",
    "gn:feature_code":"PPL",
    "gn:name":"Oberurbach",
    "gn:population":0,
    "gn:timezone":"Europe/Berlin",
    "iso:country":"DE",
    "wof:name":"Oberurbach",
    "wof:placetype":"neighbourhood"
},
  "geometry": {"coordinates":[9.7689,47.87743],"type":"Point"}
}