{
  "type": "Feature",
  "properties": {
    "gn:admin1_code":"2",
    "gn:admin2_code":"97.0",
    "gn:admin3_code":"9780.0",
    "gn:admin4_code":"9780146.0",
    "gn:asciiname":"Pfaffenried",
    "gn:country_code":"DE",
    "gn:dem":830,
    "gn:feature_class":"P",
    "gn:feature_code":"PPL",
    "gn:name":"Pfaffenried",
    "gn:population":0,
    "gn:timezone":"Europe/Berlin",
    "iso:country":"DE",
    "wof:name":"Pfaffenried",
    "wof:placetype":"neighbourhood"
},
  "geometry": {"coordinates":[10.2457,47.74052],"type":"Point"}
}