{
  "type": "Feature",
  "properties": {
    "gn:admin1_code":"13.0",
    "gn:admin2_code":"00",
    "gn:admin3_code":"14627.0",
    "gn:admin4_code":"14627260.0",
    "gn:asciiname":"Wilschwitz",
    "gn:country_code":"DE",
    "gn:dem":145,
    "gn:feature_class":"P",
    "gn:feature_code":"PPL",
    "gn:name":"Wilschwitz",
    "gn:population":0,
    "gn:timezone":"Europe/Berlin",
    "iso:country":"DE",
    "wof:name":"Wilschwitz",
    "wof:placetype":"neighbourhood"
},
  "geometry": {"coordinates":[13.21282,51.22486],"type":"Point"}
}