{
  "type": "Feature",
  "properties": {
    "gn:admin1_code":"13",
    "gn:admin2_code":"0.0",
    "gn:admin3_code":"14625.0",
    "gn:admin4_code":"14625030.0",
    "gn:asciiname":"Grossgrabe",
    "gn:country_code":"DE",
    "gn:dem":141,
    "gn:feature_class":"P",
    "gn:feature_code":"PPL",
    "gn:name":"Gro\u00dfgrabe",
    "gn:population":0,
    "gn:timezone":"Europe/Berlin",
    "iso:country":"DE",
    "wof:name":"Grossgrabe",
    "wof:placetype":"neighbourhood"
},
  "geometry": {"coordinates":[14.01789,51.34777],"type":"Point"}
}