{
  "type": "Feature",
  "properties": {
    "gn:admin1_code":"2",
    "gn:admin2_code":"91.0",
    "gn:admin3_code":"9177.0",
    "gn:admin4_code":"9177115.0",
    "gn:asciiname":"Landersdorf",
    "gn:country_code":"DE",
    "gn:dem":498,
    "gn:feature_class":"P",
    "gn:feature_code":"PPL",
    "gn:name":"Landersdorf",
    "gn:population":0,
    "gn:timezone":"Europe/Berlin",
    "iso:country":"DE",
    "wof:name":"Landersdorf",
    "wof:placetype":"neighbourhood"
},
  "geometry": {"coordinates":[12.08741,48.29106],"type":"Point"}
}