{
  "type": "Feature",
  "properties": {
    "gn:admin1_code":"2",
    "gn:admin2_code":"93.0",
    "gn:admin3_code":"9377.0",
    "gn:admin4_code":"9377149.0",
    "gn:asciiname":"Josephshof",
    "gn:country_code":"DE",
    "gn:dem":505,
    "gn:feature_class":"P",
    "gn:feature_code":"PPL",
    "gn:name":"Josephshof",
    "gn:population":0,
    "gn:timezone":"Europe/Berlin",
    "iso:country":"DE",
    "wof:name":"Josephshof",
    "wof:placetype":"neighbourhood"
},
  "geometry": {"coordinates":[12.1495,49.84982],"type":"Point"}
}