{
  "type": "Feature",
  "properties": {
    "gn:admin1_code":"1.0",
    "gn:admin2_code":"081",
    "gn:admin3_code":"8127.0",
    "gn:admin4_code":"8127014.0",
    "gn:asciiname":"Wittau",
    "gn:country_code":"DE",
    "gn:dem":424,
    "gn:feature_class":"P",
    "gn:feature_code":"PPL",
    "gn:name":"Wittau",
    "gn:population":0,
    "gn:timezone":"Europe/Berlin",
    "iso:country":"DE",
    "wof:name":"Wittau",
    "wof:placetype":"neighbourhood"
},
  "geometry": {"coordinates":[10.10794,49.11613],"type":"Point"}
}