{
  "type": "Feature",
  "properties": {
    "gn:admin1_code":"11",
    "gn:admin2_code":"0.0",
    "gn:admin3_code":"12061.0",
    "gn:admin4_code":"12061510.0",
    "gn:asciiname":"Leibsch",
    "gn:country_code":"DE",
    "gn:dem":46,
    "gn:feature_class":"P",
    "gn:feature_code":"PPL",
    "gn:name":"Leibsch",
    "gn:population":0,
    "gn:timezone":"Europe/Berlin",
    "iso:country":"DE",
    "name:deu_x_preferred":[
        "Leibsch"
    ],
    "name:eus_x_preferred":[
        "Leibsch"
    ],
    "name:und_x_variant":[
        "Lubu\u0161"
    ],
    "wof:name":"Leibsch",
    "wof:placetype":"neighbourhood"
},
  "geometry": {"coordinates":[13.87581,52.08066],"type":"Point"}
}