{
  "type": "Feature",
  "properties": {
    "gn:admin1_code":"2.0",
    "gn:admin2_code":"95.0",
    "gn:admin3_code":"9575.0",
    "gn:admin4_code":"9575146.0",
    "gn:asciiname":"Wustphul",
    "gn:country_code":"DE",
    "gn:dem":344,
    "gn:feature_class":"P",
    "gn:feature_code":"PPL",
    "gn:name":"W\u00fcstph\u00fcl",
    "gn:population":0,
    "gn:timezone":"Europe/Berlin",
    "iso:country":"DE",
    "wof:name":"Wustphul",
    "wof:placetype":"neighbourhood"
},
  "geometry": {"coordinates":[10.32299,49.56898],"type":"Point"}
}