{
  "type": "Feature",
  "properties": {
    "gn:admin1_code":"5.0",
    "gn:admin2_code":"64.0",
    "gn:admin3_code":"6439.0",
    "gn:admin4_code":"6439002.0",
    "gn:asciiname":"Adolphseck",
    "gn:country_code":"DE",
    "gn:dem":300,
    "gn:feature_class":"P",
    "gn:feature_code":"PPL",
    "gn:name":"Adolphseck",
    "gn:population":0,
    "gn:timezone":"Europe/Berlin",
    "iso:country":"DE",
    "wof:name":"Adolphseck",
    "wof:placetype":"neighbourhood"
},
  "geometry": {"coordinates":[8.07838,50.16181],"type":"Point"}
}