{
  "type": "Feature",
  "properties": {
    "iso:country":"DE",
    "name:deu_x_preferred":[
        "Gohlis-S\u00fcd"
    ],
    "wof:name":"Gohlis-Sued",
    "wof:placetype":"neighbourhood"
},
  "geometry": {"coordinates":[12.36182447031262,51.36163734624824],"type":"Point"}
}