{
  "type": "Feature",
  "properties": {
    "gn:admin1_code":"2",
    "gn:admin2_code":"92.0",
    "gn:admin3_code":"9263.0",
    "gn:admin4_code":"9263000.0",
    "gn:asciiname":"Hofstetten",
    "gn:country_code":"DE",
    "gn:dem":319,
    "gn:feature_class":"P",
    "gn:feature_code":"PPLL",
    "gn:name":"Hofstetten",
    "gn:population":0,
    "gn:timezone":"Europe/Berlin",
    "iso:country":"DE",
    "wof:name":"Hofstetten",
    "wof:placetype":"neighbourhood"
},
  "geometry": {"coordinates":[12.62394,48.88948],"type":"Point"}
}