{
  "type": "Feature",
  "properties": {
    "gn:admin1_code":"6",
    "gn:admin2_code":"0.0",
    "gn:admin3_code":"3354.0",
    "gn:admin4_code":"3354019.0",
    "gn:asciiname":"Katemin",
    "gn:cc2":"DE",
    "gn:country_code":"DE",
    "gn:dem":15,
    "gn:feature_class":"P",
    "gn:feature_code":"PPL",
    "gn:name":"Katemin",
    "gn:population":0,
    "gn:timezone":"Europe/Berlin",
    "iso:country":"DE",
    "name:und_x_variant":[
        "Kateman",
        "Katemin"
    ],
    "wof:name":"Katemin",
    "wof:placetype":"neighbourhood"
},
  "geometry": {"coordinates":[10.87481,53.2322],"type":"Point"}
}