{
  "type": "Feature",
  "properties": {
    "gn:admin1_code":"2",
    "gn:admin2_code":"97.0",
    "gn:admin3_code":"9779.0",
    "gn:admin4_code":"9779117.0",
    "gn:asciiname":"Dornstadt",
    "gn:country_code":"DE",
    "gn:dem":438,
    "gn:feature_class":"P",
    "gn:feature_code":"PPL",
    "gn:name":"Dornstadt",
    "gn:population":0,
    "gn:timezone":"Europe/Berlin",
    "iso:country":"DE",
    "name:als_x_preferred":[
        "Dornstadt"
    ],
    "name:ceb_x_preferred":[
        "Dornstadt"
    ],
    "name:deu_x_preferred":[
        "Dornstadt"
    ],
    "name:epo_x_preferred":[
        "Dornstadt"
    ],
    "name:eus_x_preferred":[
        "Dornstadt"
    ],
    "name:fas_x_preferred":[
        "\u062f\u0648\u0631\u0646\u0634\u062a\u0627\u062a"
    ],
    "name:fra_x_preferred":[
        "Dornstadt"
    ],
    "name:hun_x_preferred":[
        "Dornstadt"
    ],
    "name:hye_x_preferred":[
        "\u0534\u0578\u0580\u0576\u0577\u057f\u0561\u0564\u057f"
    ],
    "name:ita_x_preferred":[
        "Dornstadt"
    ],
    "name:kat_x_preferred":[
        "\u10d3\u10dd\u10e0\u10dc\u10e8\u10e2\u10d0\u10d3\u10e2\u10d8"
    ],
    "name:kaz_x_preferred":[
        "\u0414\u043e\u0440\u043d\u0448\u0442\u0430\u0434\u0442"
    ],
    "name:kir_x_preferred":[
        "\u0414\u043e\u0440\u043d\u0448\u0442\u0430\u0434\u0442"
    ],
    "name:lat_x_preferred":[
        "Dornstadt"
    ],
    "name:lmo_x_preferred":[
        "Dornstadt"
    ],
    "name:msa_x_preferred":[
        "Dornstadt"
    ],
    "name:nld_x_preferred":[
        "Dornstadt"
    ],
    "name:pol_x_preferred":[
        "Dornstadt"
    ],
    "name:por_x_preferred":[
        "Dornstadt"
    ],
    "name:ron_x_preferred":[
        "Dornstadt"
    ],
    "name:rus_x_preferred":[
        "\u0414\u043e\u0440\u043d\u0448\u0442\u0430\u0434\u0442"
    ],
    "name:spa_x_preferred":[
        "Dornstadt"
    ],
    "name:srp_x_preferred":[
        "\u0414\u043e\u0440\u043d\u0448\u0442\u0430\u0442"
    ],
    "name:ukr_x_preferred":[
        "\u0414\u043e\u0440\u043d\u0448\u0442\u0430\u0434\u0442"
    ],
    "name:uzb_x_preferred":[
        "Dornstadt"
    ],
    "name:vol_x_preferred":[
        "Dornstadt"
    ],
    "name:war_x_preferred":[
        "Dornstadt"
    ],
    "name:zho_x_preferred":[
        "\u591a\u6069\u65bd\u5854\u7279"
    ],
    "wof:name":"Dornstadt",
    "wof:placetype":"neighbourhood"
},
  "geometry": {"coordinates":[10.584,49.0023],"type":"Point"}
}