{
  "type": "Feature",
  "properties": {
    "gn:admin1_code":"2",
    "gn:admin2_code":"94.0",
    "gn:admin3_code":"9475.0",
    "gn:admin4_code":"9475141.0",
    "gn:asciiname":"Lamitz",
    "gn:country_code":"DE",
    "gn:dem":516,
    "gn:feature_class":"P",
    "gn:feature_code":"PPL",
    "gn:name":"Lamitz",
    "gn:population":0,
    "gn:timezone":"Europe/Berlin",
    "iso:country":"DE",
    "name:deu_x_preferred":[
        "Lamitz"
    ],
    "wof:name":"Lamitz",
    "wof:placetype":"neighbourhood"
},
  "geometry": {"coordinates":[11.82455,50.38105],"type":"Point"}
}