{
  "type": "Feature",
  "properties": {
    "gn:admin1_code":"2.0",
    "gn:admin2_code":"91.0",
    "gn:admin3_code":"9181.0",
    "gn:admin4_code":"9181144.0",
    "gn:asciiname":"Achselschwang",
    "gn:country_code":"DE",
    "gn:dem":595,
    "gn:feature_class":"P",
    "gn:feature_code":"PPL",
    "gn:name":"Achselschwang",
    "gn:population":0,
    "gn:timezone":"Europe/Berlin",
    "iso:country":"DE",
    "wof:name":"Achselschwang",
    "wof:placetype":"neighbourhood"
},
  "geometry": {"coordinates":[11.05144,48.03474],"type":"Point"}
}