{
  "type": "Feature",
  "properties": {
    "gn:country":"DE",
    "gn:fcode":"PPL",
    "gn:population":183,
    "iso:country":"DE",
    "name:bak_x_preferred":[
        "\u0422\u0438\u043b\u044c\u0431\u0435\u0440"
    ],
    "name:ceb_x_preferred":[
        "Thielbeer"
    ],
    "name:deu_x_preferred":[
        "Thielbeer"
    ],
    "name:epo_x_preferred":[
        "Thielbeer"
    ],
    "name:fas_x_preferred":[
        "\u062a\u06cc\u0644\u0628\u0631"
    ],
    "name:ita_x_preferred":[
        "Thielbeer"
    ],
    "name:kaz_x_preferred":[
        "\u0422\u0438\u043b\u044c\u0431\u0435\u0440"
    ],
    "name:kir_x_preferred":[
        "\u0422\u0438\u043b\u044c\u0431\u0435\u0440"
    ],
    "name:nld_x_preferred":[
        "Thielbeer"
    ],
    "name:ron_x_preferred":[
        "Thielbeer"
    ],
    "name:rus_x_preferred":[
        "\u0422\u0438\u043b\u044c\u0431\u0435\u0440"
    ],
    "name:uzb_x_preferred":[
        "Thielbeer"
    ],
    "name:vie_x_preferred":[
        "Thielbeer"
    ],
    "name:vol_x_preferred":[
        "Thielbeer"
    ],
    "qs_pg:aaroncc":"DE",
    "qs_pg:gn_country":"DE",
    "qs_pg:gn_fcode":"PPL",
    "qs_pg:gn_pop":183,
    "qs_pg:name":"Thielbeer",
    "qs_pg:name_adm0":"Deutschland",
    "qs_pg:name_adm1":"Sachsen-Anhalt",
    "qs_pg:photos_9r":0,
    "qs_pg:photos_sr":0,
    "qs_pg:pop_sr":1,
    "qs_pg:qs_pg_placetype":"locality",
    "qs_pg:qs_pg_placetype_gp":"Town",
    "qs_pg:woe_adm0":23424829,
    "woe:adm0_id":23424829,
    "woe:name_adm0":"Deutschland",
    "woe:name_adm1":"Sachsen-Anhalt",
    "woe:placetype":"Town",
    "wof:name":"Thielbeer",
    "wof:placetype":"neighbourhood",
    "wof:population":183
},
  "geometry": {"coordinates":[11.48236,52.8465],"type":"Point"}
}