{
  "type": "Feature",
  "properties": {
    "gn:admin1_code":"7.0",
    "gn:admin2_code":"051",
    "gn:admin3_code":"5170.0",
    "gn:admin4_code":"5170020.0",
    "gn:asciiname":"Wickrath",
    "gn:country_code":"DE",
    "gn:dem":26,
    "gn:feature_class":"P",
    "gn:feature_code":"PPLL",
    "gn:name":"Wickrath",
    "gn:population":0,
    "gn:timezone":"Europe/Berlin",
    "iso:country":"DE",
    "wof:name":"Wickrath",
    "wof:placetype":"neighbourhood"
},
  "geometry": {"coordinates":[6.48903,51.48304],"type":"Point"}
}