{
  "type": "Feature",
  "properties": {
    "gn:admin1_code":"1",
    "gn:admin2_code":"83.0",
    "gn:admin3_code":"8315.0",
    "gn:admin4_code":"8315014.0",
    "gn:asciiname":"Gutighofen",
    "gn:country_code":"DE",
    "gn:dem":285,
    "gn:feature_class":"P",
    "gn:feature_code":"PPL",
    "gn:name":"G\u00fctighofen",
    "gn:population":0,
    "gn:timezone":"Europe/Berlin",
    "iso:country":"DE",
    "wof:name":"Gutighofen",
    "wof:placetype":"neighbourhood"
},
  "geometry": {"coordinates":[7.7713,47.91784000000001],"type":"Point"}
}