{
  "type": "Feature",
  "properties": {
    "gn:admin1_code":"15",
    "gn:admin2_code":"0.0",
    "gn:admin3_code":"16063.0",
    "gn:admin4_code":"16063092.0",
    "gn:asciiname":"Eichrodt",
    "gn:country_code":"DE",
    "gn:dem":235,
    "gn:feature_class":"P",
    "gn:feature_code":"PPL",
    "gn:name":"Eichrodt",
    "gn:population":0,
    "gn:timezone":"Europe/Berlin",
    "iso:country":"DE",
    "name:deu_x_preferred":[
        "Eichrodt"
    ],
    "wof:name":"Eichrodt",
    "wof:placetype":"neighbourhood"
},
  "geometry": {"coordinates":[10.38359,50.95881],"type":"Point"}
}