{
  "type": "Feature",
  "properties": {
    "gn:admin1_code":"1",
    "gn:admin2_code":"81.0",
    "gn:admin3_code":"8126.0",
    "gn:admin4_code":"8126085.0",
    "gn:asciiname":"Streithof",
    "gn:country_code":"DE",
    "gn:dem":493,
    "gn:feature_class":"P",
    "gn:feature_code":"PPL",
    "gn:name":"Streithof",
    "gn:population":0,
    "gn:timezone":"Europe/Berlin",
    "iso:country":"DE",
    "wof:name":"Streithof",
    "wof:placetype":"neighbourhood"
},
  "geometry": {"coordinates":[9.63042,49.18389000000001],"type":"Point"}
}