{
  "type": "Feature",
  "properties": {
    "gn:admin1_code":"7",
    "gn:admin2_code":"57.0",
    "gn:admin3_code":"5770.0",
    "gn:admin4_code":"5770036.0",
    "gn:asciiname":"Landwehr",
    "gn:country_code":"DE",
    "gn:dem":78,
    "gn:feature_class":"P",
    "gn:feature_code":"PPL",
    "gn:name":"Landwehr",
    "gn:population":0,
    "gn:timezone":"Europe/Berlin",
    "iso:country":"DE",
    "name:ces_x_preferred":[
        "Zem\u011bbrana"
    ],
    "name:deu_x_preferred":[
        "Landwehr"
    ],
    "name:eus_x_preferred":[
        "Landwehr"
    ],
    "name:fra_x_preferred":[
        "Landwehr"
    ],
    "name:hun_x_preferred":[
        "Honv\u00e9ds\u00e9g"
    ],
    "name:ita_x_preferred":[
        "Landwehr"
    ],
    "name:jpn_x_preferred":[
        "\u30e9\u30f3\u30c8\u30f4\u30a7\u30fc\u30a2"
    ],
    "name:kaz_x_preferred":[
        "\u041b\u0430\u043d\u0434\u0432\u0435\u0440"
    ],
    "name:kir_x_preferred":[
        "\u041b\u0430\u043d\u0434\u0432\u0435\u0440"
    ],
    "name:kor_x_preferred":[
        "\ub780\ud2b8\ubca0\uc5b4"
    ],
    "name:lit_x_preferred":[
        "Landveras"
    ],
    "name:nld_x_preferred":[
        "Landweer"
    ],
    "name:pol_x_preferred":[
        "Landwehra"
    ],
    "name:por_x_preferred":[
        "Landwehr"
    ],
    "name:ron_x_preferred":[
        "Landwehr"
    ],
    "name:rus_x_preferred":[
        "\u041b\u0430\u043d\u0434\u0432\u0435\u0440"
    ],
    "name:spa_x_preferred":[
        "Landwehr"
    ],
    "name:srp_x_preferred":[
        "\u041b\u0430\u043d\u0434\u0432\u0435\u0440"
    ],
    "name:ukr_x_preferred":[
        "\u041b\u0430\u043d\u0434\u0432\u0435\u0440"
    ],
    "wof:name":"Landwehr",
    "wof:placetype":"neighbourhood"
},
  "geometry": {"coordinates":[8.51582,52.29125],"type":"Point"}
}