{
  "type": "Feature",
  "properties": {
    "gn:admin1_code":"11.0",
    "gn:admin2_code":"0.0",
    "gn:admin3_code":"12071.0",
    "gn:admin4_code":"12071057.0",
    "gn:asciiname":"Auras",
    "gn:country_code":"DE",
    "gn:dem":106,
    "gn:feature_class":"P",
    "gn:feature_code":"PPL",
    "gn:name":"Auras",
    "gn:population":0,
    "gn:timezone":"Europe/Berlin",
    "iso:country":"DE",
    "name:dsb_x_preferred":[
        "Huraz"
    ],
    "wof:name":"Auras",
    "wof:placetype":"neighbourhood"
},
  "geometry": {"coordinates":[14.28479,51.66571],"type":"Point"}
}