{
  "type": "Feature",
  "properties": {
    "gn:admin1_code":"12",
    "gn:admin2_code":"0.0",
    "gn:admin3_code":"13072.0",
    "gn:admin4_code":"13072042.0",
    "gn:asciiname":"Langensee",
    "gn:country_code":"DE",
    "gn:dem":9,
    "gn:feature_class":"P",
    "gn:feature_code":"PPL",
    "gn:name":"Langensee",
    "gn:population":0,
    "gn:timezone":"Europe/Berlin",
    "iso:country":"DE",
    "name:als_x_preferred":[
        "Langensee"
    ],
    "name:deu_x_preferred":[
        "Langensee"
    ],
    "wof:name":"Langensee",
    "wof:placetype":"neighbourhood"
},
  "geometry": {"coordinates":[12.03315,53.80879],"type":"Point"}
}