{
  "type": "Feature",
  "properties": {
    "iso:country":"DE",
    "name:deu_x_preferred":[
        "Reuschenberg"
    ],
    "qs:gn_fcode":"PPL",
    "qs:gn_local":0,
    "qs:gn_namadm1":"07",
    "qs:gn_name":"Reuschenberg",
    "qs:local_max":1202,
    "qs:local_sum":3714,
    "qs:localhoods":18,
    "qs:name":"Reuschenberg",
    "qs:name_adm0":"Deutschland",
    "qs:name_adm1":"Nordrhein-Westfalen",
    "qs:name_adm2":"Landkreis Neuss",
    "qs:name_lau":"Stadtteil Neuss",
    "qs:name_local":"Stadtteil Neuss",
    "qs:photo_max":12,
    "qs:photo_sum":30,
    "qs:placetype":"Suburb",
    "qs:quad_count":11,
    "qs:woe_adm0":23424829,
    "qs:woe_adm1":2345487,
    "qs:woe_adm2":12596955,
    "qs:woe_lau":26823111,
    "qs:woe_local":26823111,
    "qs:woe_ver":"7.10.0",
    "wof:lang":[
        "ger"
    ],
    "wof:name":"Reuschenberg",
    "wof:placetype":"neighbourhood"
},
  "geometry": {"coordinates":[6.684151,51.169285],"type":"Point"}
}