{
  "type": "Feature",
  "properties": {
    "gn:admin1_code":"10",
    "gn:admin2_code":"0.0",
    "gn:admin3_code":"1061.0",
    "gn:admin4_code":"1061018.0",
    "gn:asciiname":"Gross Arentsee",
    "gn:country_code":"DE",
    "gn:dem":-2,
    "gn:feature_class":"P",
    "gn:feature_code":"PPLL",
    "gn:name":"Gro\u00df Arentsee",
    "gn:population":0,
    "gn:timezone":"Europe/Berlin",
    "iso:country":"DE",
    "wof:name":"Gross Arentsee",
    "wof:placetype":"neighbourhood"
},
  "geometry": {"coordinates":[9.29612,53.87615],"type":"Point"}
}