{
  "type": "Feature",
  "properties": {
    "gn:admin1_code":"5",
    "gn:admin2_code":"66.0",
    "gn:admin3_code":"6634.0",
    "gn:admin4_code":"6634011.0",
    "gn:asciiname":"Voelkershain",
    "gn:country_code":"DE",
    "gn:dem":298,
    "gn:feature_class":"P",
    "gn:feature_code":"PPL",
    "gn:name":"V\u00f6lkershain",
    "gn:population":0,
    "gn:timezone":"Europe/Berlin",
    "iso:country":"DE",
    "wof:name":"Voelkershain",
    "wof:placetype":"neighbourhood"
},
  "geometry": {"coordinates":[9.47658,50.97116],"type":"Point"}
}