{
  "type": "Feature",
  "properties": {
    "gn:admin1_code":"6.0",
    "gn:admin2_code":"00",
    "gn:admin3_code":"3459.0",
    "gn:admin4_code":"3459005.0",
    "gn:asciiname":"Winkelsetten",
    "gn:country_code":"DE",
    "gn:dem":75,
    "gn:feature_class":"P",
    "gn:feature_code":"PPL",
    "gn:name":"Winkelsetten",
    "gn:population":0,
    "gn:timezone":"Europe/Berlin",
    "iso:country":"DE",
    "wof:name":"Winkelsetten",
    "wof:placetype":"neighbourhood"
},
  "geometry": {"coordinates":[8.08091,52.08749],"type":"Point"}
}