{
  "type": "Feature",
  "properties": {
    "gn:admin1_code":"2.0",
    "gn:admin2_code":"92.0",
    "gn:admin3_code":"9271.0",
    "gn:admin4_code":"9271140.0",
    "gn:asciiname":"Aschenau",
    "gn:country_code":"DE",
    "gn:dem":320,
    "gn:feature_class":"P",
    "gn:feature_code":"PPLL",
    "gn:name":"Aschenau",
    "gn:population":0,
    "gn:timezone":"Europe/Berlin",
    "iso:country":"DE",
    "wof:name":"Aschenau",
    "wof:placetype":"neighbourhood"
},
  "geometry": {"coordinates":[12.84412,48.88126],"type":"Point"}
}