{
  "type": "Feature",
  "properties": {
    "gn:admin1_code":"13",
    "gn:admin2_code":"0.0",
    "gn:admin3_code":"14625.0",
    "gn:admin4_code":"14625330.0",
    "gn:asciiname":"Litschen",
    "gn:country_code":"DE",
    "gn:dem":127,
    "gn:feature_class":"P",
    "gn:feature_code":"PPL",
    "gn:name":"Litschen",
    "gn:population":0,
    "gn:timezone":"Europe/Berlin",
    "iso:country":"DE",
    "name:hsb_x_preferred":[
        "Z\u0142y\u010din"
    ],
    "wof:name":"Litschen",
    "wof:placetype":"neighbourhood"
},
  "geometry": {"coordinates":[14.40827,51.36782],"type":"Point"}
}