{
  "type": "Feature",
  "properties": {
    "gn:admin1_code":"13",
    "gn:admin2_code":"0.0",
    "gn:admin3_code":"14729.0",
    "gn:admin4_code":"14729410.0",
    "gn:asciiname":"Dehnitz",
    "gn:country_code":"DE",
    "gn:dem":118,
    "gn:feature_class":"P",
    "gn:feature_code":"PPL",
    "gn:name":"Dehnitz",
    "gn:population":0,
    "gn:timezone":"Europe/Berlin",
    "iso:country":"DE",
    "wof:name":"Dehnitz",
    "wof:placetype":"neighbourhood"
},
  "geometry": {"coordinates":[12.73436,51.35013],"type":"Point"}
}