{
  "type": "Feature",
  "properties": {
    "iso:country":"DE",
    "name:ceb_x_preferred":[
        "Nienhagen"
    ],
    "name:deu_x_preferred":[
        "Nienhagen"
    ],
    "name:epo_x_preferred":[
        "Nienhagen"
    ],
    "name:est_x_preferred":[
        "Nienhagen"
    ],
    "name:eus_x_preferred":[
        "Nienhagen"
    ],
    "name:fra_x_preferred":[
        "Nienhagen"
    ],
    "name:hun_x_preferred":[
        "Nienhagen"
    ],
    "name:ita_x_preferred":[
        "Nienhagen"
    ],
    "name:mkd_x_preferred":[
        "\u041d\u0438\u043d\u0445\u0430\u0433\u0435\u043d"
    ],
    "name:nds_x_preferred":[
        "Nienhagen"
    ],
    "name:nld_x_preferred":[
        "Nienhagen"
    ],
    "name:pol_x_preferred":[
        "Nienhagen"
    ],
    "name:rus_x_preferred":[
        "\u041d\u0438\u043d\u0445\u0430\u0433\u0435\u043d"
    ],
    "name:srp_x_preferred":[
        "\u041d\u0438\u043d\u0445\u0430\u0433\u0435\u043d"
    ],
    "name:swe_x_preferred":[
        "Nienhagen"
    ],
    "name:vol_x_preferred":[
        "Nienhagen"
    ],
    "qs_pg:aaroncc":"DE",
    "qs_pg:name":"Nienhagen",
    "qs_pg:name_adm0":"Deutschland",
    "qs_pg:name_adm1":"Mecklenburg-Vorpommern",
    "qs_pg:photos":2,
    "qs_pg:photos_1k":1,
    "qs_pg:photos_9k":1,
    "qs_pg:photos_9r":1,
    "qs_pg:photos_all":2,
    "qs_pg:photos_sr":1,
    "qs_pg:pop_sr":0,
    "qs_pg:qs_pg_placetype":"neighbourhood",
    "qs_pg:qs_pg_placetype_gp":"Suburb",
    "qs_pg:woe_adm0":23424829,
    "woe:adm0_id":23424829,
    "woe:name_adm0":"Deutschland",
    "woe:name_adm1":"Mecklenburg-Vorpommern",
    "woe:placetype":"Suburb",
    "wof:name":"Nienhagen",
    "wof:placetype":"neighbourhood"
},
  "geometry": {"coordinates":[12.17434,54.14869],"type":"Point"}
}