{
  "type": "Feature",
  "properties": {
    "gn:country":"DE",
    "gn:fcode":"PPL",
    "gn:population":0,
    "iso:country":"DE",
    "name:ceb_x_preferred":[
        "Hamberge"
    ],
    "name:dan_x_preferred":[
        "Hamberge"
    ],
    "name:deu_x_preferred":[
        "Hamberge"
    ],
    "name:epo_x_preferred":[
        "Hamberge"
    ],
    "name:eus_x_preferred":[
        "Hamberge"
    ],
    "name:fas_x_preferred":[
        "\u0647\u0627\u0645\u0628\u0631\u06af\u0647"
    ],
    "name:fra_x_preferred":[
        "Hamberge"
    ],
    "name:hun_x_preferred":[
        "Hamberge"
    ],
    "name:ita_x_preferred":[
        "Hamberge"
    ],
    "name:mkd_x_preferred":[
        "\u0425\u0430\u043c\u0431\u0435\u0440\u0433\u0435"
    ],
    "name:msa_x_preferred":[
        "Hamberge"
    ],
    "name:nld_x_preferred":[
        "Hamberge"
    ],
    "name:pol_x_preferred":[
        "Hamberge"
    ],
    "name:por_x_preferred":[
        "Hamberge"
    ],
    "name:ron_x_preferred":[
        "Hamberge"
    ],
    "name:rus_x_preferred":[
        "\u0425\u0430\u043c\u0431\u0435\u0440\u0433\u0435"
    ],
    "name:spa_x_preferred":[
        "Hamberge"
    ],
    "name:srp_x_preferred":[
        "\u0425\u0430\u043c\u0431\u0435\u0440\u0433\u0435"
    ],
    "name:tur_x_preferred":[
        "Hamberge"
    ],
    "name:ukr_x_preferred":[
        "\u0413\u0430\u043c\u0431\u0435\u0440\u0433\u0435"
    ],
    "name:uzb_x_preferred":[
        "Hamberge"
    ],
    "name:vie_x_preferred":[
        "Hamberge"
    ],
    "name:vol_x_preferred":[
        "Hamberge"
    ],
    "name:war_x_preferred":[
        "Hamberge"
    ],
    "name:zho_x_preferred":[
        "\u6c49\u8d1d\u683c"
    ],
    "qs_pg:aaroncc":"DE",
    "qs_pg:gn_country":"DE",
    "qs_pg:gn_fcode":"PPL",
    "qs_pg:gn_pop":0,
    "qs_pg:name":"Hamberge",
    "qs_pg:name_adm0":"Deutschland",
    "qs_pg:name_adm1":"Mecklenburg-Vorpommern",
    "qs_pg:photos":15,
    "qs_pg:photos_1k":3,
    "qs_pg:photos_9k":1,
    "qs_pg:photos_9r":1,
    "qs_pg:photos_all":15,
    "qs_pg:photos_sr":1,
    "qs_pg:pop_sr":0,
    "qs_pg:qs_pg_placetype":"locality",
    "qs_pg:qs_pg_placetype_gp":"Town",
    "qs_pg:woe_adm0":23424829,
    "woe:adm0_id":23424829,
    "woe:name_adm0":"Deutschland",
    "woe:name_adm1":"Mecklenburg-Vorpommern",
    "woe:placetype":"Town",
    "wof:name":"Hamberge",
    "wof:placetype":"neighbourhood"
},
  "geometry": {"coordinates":[11.2339,53.87512],"type":"Point"}
}