{
  "type": "Feature",
  "properties": {
    "iso:country":"DE",
    "name:deu_x_preferred":[
        "Maxau"
    ],
    "name:deu_x_variant":[
        "Moxau"
    ],
    "name:unk_x_variant":[
        "Moxau",
        "Maxau"
    ],
    "qs:gn_adm0_cc":"DE",
    "qs:gn_fcode":"PPLX",
    "qs:gn_local":2892794,
    "qs:gn_namadm1":"01",
    "qs:gn_name":"Maxau",
    "qs:local_max":5751,
    "qs:local_sum":18066,
    "qs:localhoods":10,
    "qs:name":"Maxau",
    "qs:name_adm0":"Deutschland",
    "qs:name_adm1":"Baden-W\u00fcrttemberg",
    "qs:name_adm2":"Stadtkreis Karlsruhe",
    "qs:name_lau":"Stadtteil Knielingen",
    "qs:name_local":"Karlsruhe",
    "qs:photo_max":138,
    "qs:photo_sum":2636,
    "qs:placetype":"Suburb",
    "qs:quad_count":164,
    "qs:woe_adm0":23424829,
    "qs:woe_adm1":2345481,
    "qs:woe_adm2":20071085,
    "qs:woe_lau":26822679,
    "qs:woe_local":664942,
    "qs:woe_ver":"7.10.0",
    "wof:lang":[
        "ger"
    ],
    "wof:name":"Maxau",
    "wof:placetype":"neighbourhood"
},
  "geometry": {"coordinates":[8.317995,49.032784],"type":"Point"}
}