{
  "type": "Feature",
  "properties": {
    "gn:admin1_code":"7",
    "gn:admin2_code":"51.0",
    "gn:admin3_code":"5158.0",
    "gn:admin4_code":"5158004.0",
    "gn:asciiname":"Neandertal",
    "gn:country_code":"DE",
    "gn:dem":102,
    "gn:feature_class":"P",
    "gn:feature_code":"PPL",
    "gn:name":"Neandertal",
    "gn:population":0,
    "gn:timezone":"Europe/Berlin",
    "iso:country":"DE",
    "name:und_x_variant":[
        "Neanderthal",
        "Neandertal"
    ],
    "wof:name":"Neandertal",
    "wof:placetype":"neighbourhood"
},
  "geometry": {"coordinates":[6.95091,51.22712],"type":"Point"}
}