{
  "type": "Feature",
  "properties": {
    "gn:admin1_code":"14",
    "gn:admin2_code":"0.0",
    "gn:admin3_code":"15082.0",
    "gn:admin4_code":"15082377.0",
    "gn:asciiname":"Kleinweissandt",
    "gn:country_code":"DE",
    "gn:dem":79,
    "gn:feature_class":"P",
    "gn:feature_code":"PPL",
    "gn:name":"Kleinwei\u00dfandt",
    "gn:population":0,
    "gn:timezone":"Europe/Berlin",
    "iso:country":"DE",
    "name:und_x_variant":[
        "Kleinwei\u00dfand",
        "Kleinwei\u00dfandt"
    ],
    "wof:name":"Kleinweissandt",
    "wof:placetype":"neighbourhood"
},
  "geometry": {"coordinates":[12.06087,51.67902],"type":"Point"}
}