{
  "type": "Feature",
  "properties": {
    "gn:admin1_code":"2",
    "gn:admin2_code":"97.0",
    "gn:admin3_code":"9772.0",
    "gn:admin4_code":"9772149.0",
    "gn:asciiname":"Lager Lechfeld",
    "gn:country_code":"DE",
    "gn:dem":553,
    "gn:feature_class":"P",
    "gn:feature_code":"PPL",
    "gn:name":"Lager Lechfeld",
    "gn:population":0,
    "gn:timezone":"Europe/Berlin",
    "iso:country":"DE",
    "name:und_x_variant":[
        "Lechfeld",
        "Lager Lechfeld"
    ],
    "wof:name":"Lager Lechfeld",
    "wof:placetype":"neighbourhood"
},
  "geometry": {"coordinates":[10.84368,48.17989],"type":"Point"}
}