{
  "type": "Feature",
  "properties": {
    "gn:admin1_code":"11",
    "gn:admin2_code":"0.0",
    "gn:admin3_code":"12068.0",
    "gn:admin4_code":"12068426.0",
    "gn:asciiname":"Rohrlack",
    "gn:country_code":"DE",
    "gn:dem":43,
    "gn:feature_class":"P",
    "gn:feature_code":"PPL",
    "gn:name":"Rohrlack",
    "gn:population":0,
    "gn:timezone":"Europe/Berlin",
    "iso:country":"DE",
    "wof:name":"Rohrlack",
    "wof:placetype":"neighbourhood"
},
  "geometry": {"coordinates":[12.60372,52.85141],"type":"Point"}
}