{
  "type": "Feature",
  "properties": {
    "gn:admin1_code":"8.0",
    "gn:admin2_code":"0.0",
    "gn:admin3_code":"7134.0",
    "gn:admin4_code":"7134058.0",
    "gn:asciiname":"Boeschweiler",
    "gn:country_code":"DE",
    "gn:dem":358,
    "gn:feature_class":"P",
    "gn:feature_code":"PPL",
    "gn:name":"B\u00f6schweiler",
    "gn:population":0,
    "gn:timezone":"Europe/Berlin",
    "iso:country":"DE",
    "wof:name":"Boeschweiler",
    "wof:placetype":"neighbourhood"
},
  "geometry": {"coordinates":[7.20901,49.6841],"type":"Point"}
}