{
  "type": "Feature",
  "properties": {
    "gn:admin1_code":"7",
    "gn:admin2_code":"53.0",
    "gn:admin3_code":"5334.0",
    "gn:admin4_code":"5334028.0",
    "gn:asciiname":"Strauch",
    "gn:country_code":"DE",
    "gn:dem":535,
    "gn:feature_class":"P",
    "gn:feature_code":"PPL",
    "gn:name":"Strauch",
    "gn:population":0,
    "gn:timezone":"Europe/Berlin",
    "iso:country":"DE",
    "name:deu_x_preferred":[
        "Strauch"
    ],
    "name:epo_x_preferred":[
        "Strauch"
    ],
    "name:fra_x_preferred":[
        "Strauch"
    ],
    "name:pol_x_preferred":[
        "Strauch"
    ],
    "name:rus_x_preferred":[
        "\u0428\u0442\u0440\u0430\u0443\u0445"
    ],
    "wof:name":"Strauch",
    "wof:placetype":"neighbourhood"
},
  "geometry": {"coordinates":[6.33525,50.62382],"type":"Point"}
}