{
  "type": "Feature",
  "properties": {
    "gn:admin1_code":"1.0",
    "gn:admin2_code":"83.0",
    "gn:admin3_code":"8337.0",
    "gn:admin4_code":"8337090.0",
    "gn:asciiname":"Ruttehof",
    "gn:country_code":"DE",
    "gn:dem":867,
    "gn:feature_class":"P",
    "gn:feature_code":"PPL",
    "gn:name":"R\u00fcttehof",
    "gn:population":0,
    "gn:timezone":"Europe/Berlin",
    "iso:country":"DE",
    "wof:name":"Ruttehof",
    "wof:placetype":"neighbourhood"
},
  "geometry": {"coordinates":[7.94805,47.63913],"type":"Point"}
}