{
  "type": "Feature",
  "properties": {
    "iso:country":"DE",
    "name:deu_x_preferred":[
        "Flugplatz Ebern-Sendelbach"
    ],
    "name:eng_x_preferred":[
        "Ebern-Sendelbach Airport"
    ],
    "name:eng_x_variant":[
        "EDQR",
        "Ebern-Sendelbach airfield"
    ],
    "name:msa_x_preferred":[
        "Lapangan Terbang Ebern-Sendelbach"
    ],
    "oa:elevation_ft":"827",
    "oa:type":"small_airport",
    "woe:hierarchy":{
        "country_id":23424829,
        "county_id":12596756,
        "localadmin_id":12635247,
        "planet_id":1,
        "state_id":2345482
    },
    "wof:name":"Sportflugplatz Ebern-sendelbach",
    "wof:placetype":"campus"
},
  "geometry": {"coordinates":[10.822778,50.039722],"type":"Point"}
}