{
  "type": "Feature",
  "properties": {
    "gn:admin1_code":"14.0",
    "gn:admin2_code":"00",
    "gn:admin3_code":"15081.0",
    "gn:admin4_code":"15081135.0",
    "gn:asciiname":"Werder",
    "gn:country_code":"DE",
    "gn:dem":58,
    "gn:feature_class":"P",
    "gn:feature_code":"PPL",
    "gn:name":"Werder",
    "gn:population":0,
    "gn:timezone":"Europe/Berlin",
    "iso:country":"DE",
    "name:ceb_x_preferred":[
        "Werder"
    ],
    "name:deu_x_preferred":[
        "Werder"
    ],
    "name:epo_x_preferred":[
        "Werder"
    ],
    "name:fra_x_preferred":[
        "Werder"
    ],
    "name:hrv_x_preferred":[
        "Werder"
    ],
    "name:ita_x_preferred":[
        "Werder"
    ],
    "name:mkd_x_preferred":[
        "\u0412\u0435\u0440\u0434\u0435\u0440"
    ],
    "name:nds_x_preferred":[
        "Werder"
    ],
    "name:nld_x_preferred":[
        "Werder"
    ],
    "name:pol_x_preferred":[
        "Werder"
    ],
    "name:rus_x_preferred":[
        "\u0412\u0435\u0440\u0434\u0435\u0440"
    ],
    "name:srp_x_preferred":[
        "\u0412\u0435\u0440\u0434\u0435\u0440"
    ],
    "name:swe_x_preferred":[
        "Werder"
    ],
    "name:ukr_x_preferred":[
        "\u0412\u0435\u0440\u0434\u0435\u0440"
    ],
    "name:vol_x_preferred":[
        "Werder"
    ],
    "wof:name":"Werder",
    "wof:placetype":"neighbourhood"
},
  "geometry": {"coordinates":[11.15706,52.43607],"type":"Point"}
}