{
  "type": "Feature",
  "properties": {
    "gn:admin1_code":"1",
    "gn:admin2_code":"81.0",
    "gn:admin3_code":"8128.0",
    "gn:admin4_code":"8128014.0",
    "gn:asciiname":"Kupprichhausen",
    "gn:country_code":"DE",
    "gn:dem":281,
    "gn:feature_class":"P",
    "gn:feature_code":"PPL",
    "gn:name":"Kupprichhausen",
    "gn:population":0,
    "gn:timezone":"Europe/Berlin",
    "iso:country":"DE",
    "name:und_x_variant":[
        "Kupprichausen",
        "Kupprichhausen"
    ],
    "wof:name":"Kupprichhausen",
    "wof:placetype":"locality"
},
  "geometry": {"coordinates":[9.62095,49.52682],"type":"Point"}
}