{
  "type": "Feature",
  "properties": {
    "gn:admin1_code":"15",
    "gn:admin2_code":"0.0",
    "gn:admin3_code":"16054.0",
    "gn:admin4_code":"16054000.0",
    "gn:asciiname":"Heidersbach",
    "gn:country_code":"DE",
    "gn:dem":603,
    "gn:feature_class":"P",
    "gn:feature_code":"PPL",
    "gn:name":"Heidersbach",
    "gn:population":0,
    "gn:timezone":"Europe/Berlin",
    "iso:country":"DE",
    "wof:name":"Heidersbach",
    "wof:placetype":"neighbourhood"
},
  "geometry": {"coordinates":[10.73333,50.63669],"type":"Point"}
}