{
  "type": "Feature",
  "properties": {
    "gn:country":"DE",
    "gn:fcode":"PPL",
    "gn:population":316,
    "iso:country":"DE",
    "name:ceb_x_preferred":[
        "Dohndorf"
    ],
    "name:eng_x_preferred":[
        "Dohndorf"
    ],
    "name:nld_x_preferred":[
        "Dohndorf"
    ],
    "qs_pg:aaroncc":"DE",
    "qs_pg:gn_country":"DE",
    "qs_pg:gn_fcode":"PPL",
    "qs_pg:gn_pop":316,
    "qs_pg:name":"Dohndorf",
    "qs_pg:name_adm0":"Deutschland",
    "qs_pg:name_adm1":"Sachsen-Anhalt",
    "qs_pg:photos_9r":0,
    "qs_pg:photos_sr":0,
    "qs_pg:pop_sr":2,
    "qs_pg:qs_pg_placetype":"locality",
    "qs_pg:qs_pg_placetype_gp":"Town",
    "qs_pg:woe_adm0":23424829,
    "woe:adm0_id":23424829,
    "woe:name_adm0":"Deutschland",
    "woe:name_adm1":"Sachsen-Anhalt",
    "woe:placetype":"Town",
    "wof:name":"Dohndorf",
    "wof:placetype":"neighbourhood",
    "wof:population":316
},
  "geometry": {"coordinates":[11.87352,51.72551],"type":"Point"}
}