{
  "type": "Feature",
  "properties": {
    "gn:admin1_code":"13",
    "gn:admin2_code":"0.0",
    "gn:admin3_code":"14625.0",
    "gn:admin4_code":"14625040.0",
    "gn:asciiname":"Grossdrebnitz",
    "gn:country_code":"DE",
    "gn:dem":308,
    "gn:feature_class":"P",
    "gn:feature_code":"PPL",
    "gn:name":"Gro\u00dfdrebnitz",
    "gn:population":0,
    "gn:timezone":"Europe/Berlin",
    "iso:country":"DE",
    "wof:name":"Grossdrebnitz",
    "wof:placetype":"neighbourhood"
},
  "geometry": {"coordinates":[14.15674,51.0901],"type":"Point"}
}