{
  "type": "Feature",
  "properties": {
    "gn:admin1_code":"13",
    "gn:admin2_code":"0.0",
    "gn:admin3_code":"14625.0",
    "gn:admin4_code":"14625040.0",
    "gn:asciiname":"Grossdrebnitz",
    "gn:country_code":"DE",
    "gn:dem":308,
    "gn:feature_class":"P",
    "gn:feature_code":"PPL",
    "gn:name":"Gro\u00dfdrebnitz",
    "gn:population":0,
    "gn:timezone":"Europe/Berlin",
    "iso:country":"DE",
    "name:ceb_x_preferred":[
        "Gro\u00dfdrebnitz"
    ],
    "name:deu_x_preferred":[
        "Gro\u00dfdrebnitz"
    ],
    "name:eus_x_preferred":[
        "Gro\u00dfdrebnitz"
    ],
    "name:fas_x_preferred":[
        "\u06af\u0631\u0648\u0633\u062f\u0631\u0628\u0646\u06cc\u062a\u0633"
    ],
    "name:fra_x_preferred":[
        "Gro\u00dfdrebnitz"
    ],
    "name:hsb_x_preferred":[
        "Drjewnica"
    ],
    "name:nld_x_preferred":[
        "Gro\u00dfdrebnitz"
    ],
    "wof:name":"Grossdrebnitz",
    "wof:placetype":"neighbourhood"
},
  "geometry": {"coordinates":[14.15674,51.0901],"type":"Point"}
}