{
  "type": "Feature",
  "properties": {
    "gn:admin1_code":"1",
    "gn:admin2_code":"83.0",
    "gn:admin3_code":"8337.0",
    "gn:admin4_code":"8337090.0",
    "gn:asciiname":"Hennenmatt",
    "gn:country_code":"DE",
    "gn:dem":751,
    "gn:feature_class":"P",
    "gn:feature_code":"PPLL",
    "gn:name":"Hennenmatt",
    "gn:population":0,
    "gn:timezone":"Europe/Berlin",
    "iso:country":"DE",
    "wof:name":"Hennenmatt",
    "wof:placetype":"neighbourhood"
},
  "geometry": {"coordinates":[7.99055,47.62571],"type":"Point"}
}