{
  "type": "Feature",
  "properties": {
    "gn:admin1_code":"5.0",
    "gn:admin2_code":"65.0",
    "gn:admin3_code":"6535.0",
    "gn:admin4_code":"6535001.0",
    "gn:asciiname":"Berfa",
    "gn:country_code":"DE",
    "gn:dem":308,
    "gn:feature_class":"P",
    "gn:feature_code":"PPL",
    "gn:name":"Berfa",
    "gn:population":0,
    "gn:timezone":"Europe/Berlin",
    "iso:country":"DE",
    "name:deu_x_preferred":[
        "Berf"
    ],
    "wof:name":"Berfa",
    "wof:placetype":"neighbourhood"
},
  "geometry": {"coordinates":[9.35958,50.77308],"type":"Point"}
}