{
  "type": "Feature",
  "properties": {
    "gn:country":"DE",
    "gn:fcode":"PPL",
    "gn:population":0,
    "iso:country":"DE",
    "name:ceb_x_preferred":[
        "Gem\u00fcnd"
    ],
    "name:deu_x_preferred":[
        "Gem\u00fcnd"
    ],
    "name:epo_x_preferred":[
        "Gem\u00fcnd"
    ],
    "name:eus_x_preferred":[
        "Gem\u00fcnd"
    ],
    "name:fas_x_preferred":[
        "\u06af\u0645\u0648\u0646\u062f"
    ],
    "name:fra_x_preferred":[
        "Gem\u00fcnd"
    ],
    "name:hun_x_preferred":[
        "Gem\u00fcnd"
    ],
    "name:ita_x_preferred":[
        "Gem\u00fcnd"
    ],
    "name:msa_x_preferred":[
        "Gem\u00fcnd"
    ],
    "name:nld_x_preferred":[
        "Gem\u00fcnd"
    ],
    "name:pol_x_preferred":[
        "Gem\u00fcnd"
    ],
    "name:por_x_preferred":[
        "Gem\u00fcnd"
    ],
    "name:ron_x_preferred":[
        "Gem\u00fcnd"
    ],
    "name:rus_x_preferred":[
        "\u0413\u0435\u043c\u044e\u043d\u0434"
    ],
    "name:spa_x_preferred":[
        "Gem\u00fcnd"
    ],
    "name:srp_x_preferred":[
        "\u0413\u0435\u043c\u0438\u043d\u0434"
    ],
    "name:ukr_x_preferred":[
        "\u0413\u0435\u043c\u044e\u043d\u0434"
    ],
    "name:uzb_x_preferred":[
        "Gem\u00fcnd"
    ],
    "name:vie_x_preferred":[
        "Gem\u00fcnd"
    ],
    "name:vol_x_preferred":[
        "Gem\u00fcnd"
    ],
    "name:war_x_preferred":[
        "Gem\u00fcnd"
    ],
    "name:zho_x_preferred":[
        "\u76d6\u660e\u5fb7"
    ],
    "qs_pg:aaroncc":"DE",
    "qs_pg:gn_country":"DE",
    "qs_pg:gn_fcode":"PPL",
    "qs_pg:gn_pop":0,
    "qs_pg:name":"Gem\u00fcnd",
    "qs_pg:name_adm0":"Deutschland",
    "qs_pg:name_adm1":"Nordrhein-Westfalen",
    "qs_pg:photos":171,
    "qs_pg:photos_1k":35,
    "qs_pg:photos_9k":1,
    "qs_pg:photos_9r":4,
    "qs_pg:photos_all":171,
    "qs_pg:photos_sr":4,
    "qs_pg:pop_sr":0,
    "qs_pg:qs_pg_placetype":"locality",
    "qs_pg:qs_pg_placetype_gp":"Town",
    "qs_pg:woe_adm0":23424829,
    "woe:adm0_id":23424829,
    "woe:name_adm0":"Deutschland",
    "woe:name_adm1":"Nordrhein-Westfalen",
    "woe:placetype":"Town",
    "wof:name":"Gem\u00fcnd",
    "wof:placetype":"neighbourhood"
},
  "geometry": {"coordinates":[6.50136,50.572],"type":"Point"}
}