{
  "type": "Feature",
  "properties": {
    "gn:admin1_code":"1",
    "gn:admin2_code":"83.0",
    "gn:admin3_code":"8326.0",
    "gn:admin4_code":"8326003.0",
    "gn:asciiname":"Hochemmingen",
    "gn:country_code":"DE",
    "gn:dem":778,
    "gn:feature_class":"P",
    "gn:feature_code":"PPL",
    "gn:name":"Hochemmingen",
    "gn:population":0,
    "gn:timezone":"Europe/Berlin",
    "iso:country":"DE",
    "wof:name":"Hochemmingen",
    "wof:placetype":"neighbourhood"
},
  "geometry": {"coordinates":[8.56815,48.02965],"type":"Point"}
}