{
  "type": "Feature",
  "properties": {
    "gn:admin1_code":"2.0",
    "gn:admin2_code":"091",
    "gn:admin3_code":"9163.0",
    "gn:admin4_code":"9163000.0",
    "gn:asciiname":"Wernhardsberg",
    "gn:country_code":"DE",
    "gn:dem":459,
    "gn:feature_class":"P",
    "gn:feature_code":"PPL",
    "gn:name":"Wernhardsberg",
    "gn:population":0,
    "gn:timezone":"Europe/Berlin",
    "iso:country":"DE",
    "wof:name":"Wernhardsberg",
    "wof:placetype":"neighbourhood"
},
  "geometry": {"coordinates":[12.1059,47.88141],"type":"Point"}
}