{
  "type": "Feature",
  "properties": {
    "gn:admin1_code":"2",
    "gn:admin2_code":"93.0",
    "gn:admin3_code":"9375.0",
    "gn:admin4_code":"9375175.0",
    "gn:asciiname":"Rammelstein",
    "gn:country_code":"DE",
    "gn:dem":446,
    "gn:feature_class":"P",
    "gn:feature_code":"PPL",
    "gn:name":"Rammelstein",
    "gn:population":0,
    "gn:timezone":"Europe/Berlin",
    "iso:country":"DE",
    "wof:name":"Rammelstein",
    "wof:placetype":"neighbourhood"
},
  "geometry": {"coordinates":[11.92316,49.00837],"type":"Point"}
}