{
  "type": "Feature",
  "properties": {
    "gn:admin1_code":"6.0",
    "gn:admin2_code":"0.0",
    "gn:admin3_code":"3451.0",
    "gn:admin4_code":"3451002.0",
    "gn:asciiname":"Altenkamp",
    "gn:country_code":"DE",
    "gn:dem":8,
    "gn:feature_class":"P",
    "gn:feature_code":"PPL",
    "gn:name":"Altenkamp",
    "gn:population":0,
    "gn:timezone":"Europe/Berlin",
    "iso:country":"DE",
    "name:und_x_variant":[
        "Hinter dem alten Kamp",
        "Altenkamp"
    ],
    "wof:name":"Altenkamp",
    "wof:placetype":"neighbourhood"
},
  "geometry": {"coordinates":[7.9741,53.18165],"type":"Point"}
}