{
  "type": "Feature",
  "properties": {
    "gn:admin1_code":"6",
    "gn:admin2_code":"0.0",
    "gn:admin3_code":"3241.0",
    "gn:admin4_code":"3241003.0",
    "gn:asciiname":"Sorgensen",
    "gn:country_code":"DE",
    "gn:dem":54,
    "gn:feature_class":"P",
    "gn:feature_code":"PPL",
    "gn:name":"Sorgensen",
    "gn:population":0,
    "gn:timezone":"Europe/Berlin",
    "iso:country":"DE",
    "name:nds_x_preferred":[
        "Sornsen"
    ],
    "wof:name":"Sorgensen",
    "wof:placetype":"neighbourhood"
},
  "geometry": {"coordinates":[10.02711,52.4608],"type":"Point"}
}