{
  "type": "Feature",
  "properties": {
    "gn:admin1_code":"2",
    "gn:admin2_code":"97.0",
    "gn:admin3_code":"9780.0",
    "gn:admin4_code":"9780128.0",
    "gn:asciiname":"Treffisried",
    "gn:country_code":"DE",
    "gn:dem":897,
    "gn:feature_class":"P",
    "gn:feature_code":"PPL",
    "gn:name":"Treffisried",
    "gn:population":0,
    "gn:timezone":"Europe/Berlin",
    "iso:country":"DE",
    "wof:name":"Treffisried",
    "wof:placetype":"neighbourhood"
},
  "geometry": {"coordinates":[10.41667,47.66667],"type":"Point"}
}