{
  "type": "Feature",
  "properties": {
    "gn:admin1_code":"13.0",
    "gn:admin2_code":"0.0",
    "gn:admin3_code":"14729.0",
    "gn:admin4_code":"14729320.0",
    "gn:asciiname":"Bergisdorf",
    "gn:country_code":"DE",
    "gn:dem":156,
    "gn:feature_class":"P",
    "gn:feature_code":"PPL",
    "gn:name":"Bergisdorf",
    "gn:population":0,
    "gn:timezone":"Europe/Berlin",
    "iso:country":"DE",
    "name:bak_x_preferred":[
        "\u0411\u0435\u0440\u0433\u0438\u0441\u0434\u043e\u0440\u0444"
    ],
    "name:ceb_x_preferred":[
        "Bergisdorf"
    ],
    "name:deu_x_preferred":[
        "Bergisdorf"
    ],
    "name:epo_x_preferred":[
        "Bergisdorf"
    ],
    "name:fas_x_preferred":[
        "\u0628\u0631\u06af\u06cc\u0633\u062f\u0648\u0631\u0641"
    ],
    "name:kaz_x_preferred":[
        "\u0411\u0435\u0440\u0433\u0438\u0441\u0434\u043e\u0440\u0444"
    ],
    "name:kir_x_preferred":[
        "\u0411\u0435\u0440\u0433\u0438\u0441\u0434\u043e\u0440\u0444"
    ],
    "name:mkd_x_preferred":[
        "\u0411\u0435\u0440\u0433\u0438\u0441\u0434\u043e\u0440\u0444"
    ],
    "name:nld_x_preferred":[
        "Bergisdorf"
    ],
    "name:ron_x_preferred":[
        "Bergisdorf"
    ],
    "name:rus_x_preferred":[
        "\u0411\u0435\u0440\u0433\u0438\u0441\u0434\u043e\u0440\u0444"
    ],
    "name:uzb_x_preferred":[
        "Bergisdorf"
    ],
    "name:vie_x_preferred":[
        "Bergisdorf"
    ],
    "name:vol_x_preferred":[
        "Bergisdorf"
    ],
    "wof:name":"Bergisdorf",
    "wof:placetype":"neighbourhood"
},
  "geometry": {"coordinates":[12.43333,51.13333],"type":"Point"}
}