{
  "type": "Feature",
  "properties": {
    "gn:admin1_code":"13.0",
    "gn:admin2_code":"0.0",
    "gn:admin3_code":"14729.0",
    "gn:admin4_code":"14729320.0",
    "gn:asciiname":"Bergisdorf",
    "gn:country_code":"DE",
    "gn:dem":156,
    "gn:feature_class":"P",
    "gn:feature_code":"PPL",
    "gn:name":"Bergisdorf",
    "gn:population":0,
    "gn:timezone":"Europe/Berlin",
    "iso:country":"DE",
    "wof:name":"Bergisdorf",
    "wof:placetype":"neighbourhood"
},
  "geometry": {"coordinates":[12.43333,51.13333],"type":"Point"}
}