{
  "type": "Feature",
  "properties": {
    "gn:admin1_code":"2",
    "gn:admin2_code":"93.0",
    "gn:admin3_code":"9374.0",
    "gn:admin4_code":"9374162.0",
    "gn:asciiname":"Fiedlbuhl",
    "gn:country_code":"DE",
    "gn:dem":564,
    "gn:feature_class":"P",
    "gn:feature_code":"PPL",
    "gn:name":"Fiedlb\u00fchl",
    "gn:population":0,
    "gn:timezone":"Europe/Berlin",
    "iso:country":"DE",
    "wof:name":"Fiedlbuhl",
    "wof:placetype":"neighbourhood"
},
  "geometry": {"coordinates":[12.34486,49.63723],"type":"Point"}
}