{
  "type": "Feature",
  "properties": {
    "gn:admin1_code":"8.0",
    "gn:admin2_code":"00",
    "gn:admin3_code":"7335.0",
    "gn:admin4_code":"7335029.0",
    "gn:asciiname":"Woersbach",
    "gn:country_code":"DE",
    "gn:dem":340,
    "gn:feature_class":"P",
    "gn:feature_code":"PPL",
    "gn:name":"W\u00f6rsbach",
    "gn:population":0,
    "gn:timezone":"Europe/Berlin",
    "iso:country":"DE",
    "wof:name":"Woersbach",
    "wof:placetype":"neighbourhood"
},
  "geometry": {"coordinates":[7.66941,49.55705],"type":"Point"}
}