{
  "type": "Feature",
  "properties": {
    "gn:admin1_code":"12",
    "gn:admin2_code":"0.0",
    "gn:admin3_code":"13073.0",
    "gn:admin4_code":"13073078.0",
    "gn:asciiname":"Vorwerk",
    "gn:country_code":"DE",
    "gn:dem":13,
    "gn:feature_class":"P",
    "gn:feature_code":"PPL",
    "gn:name":"Vorwerk",
    "gn:population":0,
    "gn:timezone":"Europe/Berlin",
    "iso:country":"DE",
    "name:ceb_x_preferred":[
        "Vorwerk"
    ],
    "name:deu_x_preferred":[
        "Vorwerk"
    ],
    "name:fra_x_preferred":[
        "Vorwerk"
    ],
    "name:ita_x_preferred":[
        "Vorwerk"
    ],
    "name:nld_x_preferred":[
        "Vorwerk"
    ],
    "name:pol_x_preferred":[
        "Vorwerk"
    ],
    "wof:name":"Vorwerk",
    "wof:placetype":"neighbourhood"
},
  "geometry": {"coordinates":[13.54228,54.51749],"type":"Point"}
}