{
  "type": "Feature",
  "properties": {
    "gn:admin1_code":"14",
    "gn:admin2_code":"0.0",
    "gn:admin3_code":"15001.0",
    "gn:admin4_code":"15001000.0",
    "gn:asciiname":"Poetnitz",
    "gn:country_code":"DE",
    "gn:dem":63,
    "gn:feature_class":"P",
    "gn:feature_code":"PPL",
    "gn:name":"P\u00f6tnitz",
    "gn:population":0,
    "gn:timezone":"Europe/Berlin",
    "iso:country":"DE",
    "wof:name":"Poetnitz",
    "wof:placetype":"neighbourhood"
},
  "geometry": {"coordinates":[12.28603,51.82072],"type":"Point"}
}