{
  "type": "Feature",
  "properties": {
    "gn:admin1_code":"7",
    "gn:admin2_code":"53.0",
    "gn:admin3_code":"5366.0",
    "gn:admin4_code":"5366028.0",
    "gn:asciiname":"Vussem",
    "gn:country_code":"DE",
    "gn:dem":304,
    "gn:feature_class":"P",
    "gn:feature_code":"PPL",
    "gn:name":"Vussem",
    "gn:population":0,
    "gn:timezone":"Europe/Berlin",
    "iso:country":"DE",
    "wof:name":"Vussem",
    "wof:placetype":"neighbourhood"
},
  "geometry": {"coordinates":[6.66453,50.56704000000001],"type":"Point"}
}