{
  "type": "Feature",
  "properties": {
    "gn:admin1_code":"1",
    "gn:admin2_code":"83.0",
    "gn:admin3_code":"8317.0",
    "gn:admin4_code":"8317039.0",
    "gn:asciiname":"Sulzbach",
    "gn:country_code":"DE",
    "gn:dem":329,
    "gn:feature_class":"P",
    "gn:feature_code":"PPLL",
    "gn:name":"Sulzbach",
    "gn:population":0,
    "gn:timezone":"Europe/Berlin",
    "iso:country":"DE",
    "name:als_x_preferred":[
        "Sulzbach"
    ],
    "name:bul_x_preferred":[
        "\u0417\u0443\u043b\u0446\u0431\u0430\u0445"
    ],
    "name:cat_x_preferred":[
        "Sulzbach"
    ],
    "name:ceb_x_preferred":[
        "Sulzbach"
    ],
    "name:deu_x_preferred":[
        "Sulzbach"
    ],
    "name:epo_x_preferred":[
        "Sulzbach"
    ],
    "name:fra_x_preferred":[
        "Sulzbach"
    ],
    "name:ita_x_preferred":[
        "Sulzbach"
    ],
    "name:kaz_x_preferred":[
        "\u0417\u0443\u043b\u044c\u0446\u0431\u0430\u0445"
    ],
    "name:nld_x_preferred":[
        "Sulzbach"
    ],
    "name:pol_x_preferred":[
        "Sulzbach"
    ],
    "name:por_x_preferred":[
        "Sulzbach"
    ],
    "name:rus_x_preferred":[
        "\u0417\u0443\u043b\u044c\u0446\u0431\u0430\u0445"
    ],
    "name:spa_x_preferred":[
        "Sulzbach"
    ],
    "name:srp_x_preferred":[
        "\u0417\u0443\u043b\u0446\u0431\u0430\u0445"
    ],
    "name:swe_x_preferred":[
        "Sulzbach"
    ],
    "name:vol_x_preferred":[
        "Sulzbach"
    ],
    "wof:name":"Sulzbach",
    "wof:placetype":"neighbourhood"
},
  "geometry": {"coordinates":[8.20145,48.24715],"type":"Point"}
}