{
  "type": "Feature",
  "properties": {
    "gn:admin1_code":"11",
    "gn:admin2_code":"0.0",
    "gn:admin3_code":"12072.0",
    "gn:admin4_code":"12072169.0",
    "gn:asciiname":"Neuheim",
    "gn:country_code":"DE",
    "gn:dem":74,
    "gn:feature_class":"P",
    "gn:feature_code":"PPL",
    "gn:name":"Neuheim",
    "gn:population":0,
    "gn:timezone":"Europe/Berlin",
    "iso:country":"DE",
    "name:als_x_preferred":[
        "Neuheim"
    ],
    "name:cat_x_preferred":[
        "Neuheim"
    ],
    "name:ceb_x_preferred":[
        "Neuheim"
    ],
    "name:chv_x_preferred":[
        "\u041d\u043e\u0439\u0445\u0430\u0439\u043c"
    ],
    "name:deu_x_preferred":[
        "Neuheim"
    ],
    "name:epo_x_preferred":[
        "Neuheim"
    ],
    "name:eus_x_preferred":[
        "Neuheim"
    ],
    "name:fra_x_preferred":[
        "Neuheim"
    ],
    "name:ita_x_preferred":[
        "Neuheim"
    ],
    "name:kaz_x_preferred":[
        "\u041d\u043e\u0439\u0445\u0430\u0439\u043c"
    ],
    "name:lmo_x_preferred":[
        "Neuheim"
    ],
    "name:nld_x_preferred":[
        "Neuheim"
    ],
    "name:nno_x_preferred":[
        "Neuheim"
    ],
    "name:pms_x_preferred":[
        "Neuheim"
    ],
    "name:por_x_preferred":[
        "Neuheim"
    ],
    "name:rus_x_preferred":[
        "\u041d\u043e\u0439\u0445\u0430\u0439\u043c"
    ],
    "name:spa_x_preferred":[
        "Neuheim"
    ],
    "name:sqi_x_preferred":[
        "Neuheim"
    ],
    "name:swe_x_preferred":[
        "Neuheim"
    ],
    "name:und_x_variant":[
        "Dorf Zinna"
    ],
    "name:vol_x_preferred":[
        "Neuheim"
    ],
    "name:war_x_preferred":[
        "Neuheim"
    ],
    "wof:name":"Neuheim",
    "wof:placetype":"neighbourhood"
},
  "geometry": {"coordinates":[13.0583,52.02069],"type":"Point"}
}