{
  "type": "Feature",
  "properties": {
    "gn:admin1_code":"11",
    "gn:admin2_code":"0.0",
    "gn:admin3_code":"12072.0",
    "gn:admin4_code":"12072169.0",
    "gn:asciiname":"Neuheim",
    "gn:country_code":"DE",
    "gn:dem":74,
    "gn:feature_class":"P",
    "gn:feature_code":"PPL",
    "gn:name":"Neuheim",
    "gn:population":0,
    "gn:timezone":"Europe/Berlin",
    "iso:country":"DE",
    "name:und_x_variant":[
        "Dorf Zinna",
        "Neuheim"
    ],
    "wof:name":"Neuheim",
    "wof:placetype":"neighbourhood"
},
  "geometry": {"coordinates":[13.0583,52.02069],"type":"Point"}
}