{
  "type": "Feature",
  "properties": {
    "gn:gn_country":"DE",
    "gn:gn_fcode":"PPL",
    "gn:gn_pop":0,
    "iso:country":"DE",
    "name:chi_x_preferred":[
        "\u6885\u4f26\u5ef7"
    ],
    "name:dut_x_preferred":[
        "Mellenthin"
    ],
    "name:eng_x_preferred":[
        "Mellenthin"
    ],
    "name:epo_x_preferred":[
        "Mellenthin"
    ],
    "name:fre_x_preferred":[
        "Mellenthin"
    ],
    "name:ger_x_preferred":[
        "Mellenthin"
    ],
    "name:hun_x_preferred":[
        "Mellenthin"
    ],
    "name:ita_x_preferred":[
        "Mellenthin"
    ],
    "name:kaz_x_preferred":[
        "\u041c\u0435\u043b\u043b\u0435\u043d\u0442\u0438\u043d"
    ],
    "name:kir_x_preferred":[
        "\u041c\u0435\u043b\u043b\u0435\u043d\u0442\u0438\u043d"
    ],
    "name:mac_x_preferred":[
        "\u041c\u0435\u043b\u0435\u043d\u0442\u0438\u043d"
    ],
    "name:may_x_preferred":[
        "Mellenthin"
    ],
    "name:per_x_preferred":[
        "\u0645\u0644\u0646\u062a\u06cc\u0646"
    ],
    "name:pol_x_preferred":[
        "Mellenthin"
    ],
    "name:por_x_preferred":[
        "Mellenthin"
    ],
    "name:rum_x_preferred":[
        "Mellenthin"
    ],
    "name:rus_x_preferred":[
        "\u041c\u0435\u043b\u043b\u0435\u043d\u0442\u0438\u043d"
    ],
    "name:srp_x_preferred":[
        "\u041c\u0435\u043b\u0435\u043d\u0442\u0438\u043d"
    ],
    "name:ukr_x_preferred":[
        "\u041c\u0435\u043b\u043b\u0435\u043d\u0442\u0456\u043d"
    ],
    "name:uzb_x_preferred":[
        "Mellenthin"
    ],
    "name:vie_x_preferred":[
        "Mellenthin"
    ],
    "name:vol_x_preferred":[
        "Mellenthin"
    ],
    "name:war_x_preferred":[
        "Mellenthin"
    ],
    "qs_pg:aaroncc":"DE",
    "qs_pg:gn_country":"DE",
    "qs_pg:gn_fcode":"PPL",
    "qs_pg:gn_pop":0,
    "qs_pg:name":"Mellenthin",
    "qs_pg:name_adm0":"Deutschland",
    "qs_pg:name_adm1":"Mecklenburg-Vorpommern",
    "qs_pg:photos":123,
    "qs_pg:photos_1k":25,
    "qs_pg:photos_9k":1,
    "qs_pg:photos_9r":3,
    "qs_pg:photos_all":123,
    "qs_pg:photos_sr":3,
    "qs_pg:pop_sr":0,
    "qs_pg:qs_pg_placetype":"locality",
    "qs_pg:qs_pg_placetype_gp":"Town",
    "qs_pg:woe_adm0":23424829,
    "woe:adm0_id":23424829,
    "woe:name_adm0":"Deutschland",
    "woe:name_adm1":"Mecklenburg-Vorpommern",
    "woe:placetype":"Town",
    "wof:name":"Mellenthin",
    "wof:placetype":"locality"
},
  "geometry": {"coordinates":[13.86978,53.85997],"type":"Point"}
}