{
  "type": "Feature",
  "properties": {
    "gn:admin1_code":"11.0",
    "gn:admin2_code":"00",
    "gn:admin3_code":"12061.0",
    "gn:admin4_code":"12061510.0",
    "gn:asciiname":"Wutscherogge",
    "gn:country_code":"DE",
    "gn:dem":50,
    "gn:feature_class":"P",
    "gn:feature_code":"PPL",
    "gn:name":"Wutscherogge",
    "gn:population":0,
    "gn:timezone":"Europe/Berlin",
    "iso:country":"DE",
    "wof:name":"Wutscherogge",
    "wof:placetype":"neighbourhood"
},
  "geometry": {"coordinates":[13.92649,52.13074],"type":"Point"}
}