{
  "type": "Feature",
  "properties": {
    "gn:admin1_code":"12",
    "gn:admin2_code":"0.0",
    "gn:admin3_code":"13071.0",
    "gn:admin4_code":"13071072.0",
    "gn:asciiname":"Neu Kentzlin",
    "gn:country_code":"DE",
    "gn:dem":52,
    "gn:feature_class":"P",
    "gn:feature_code":"PPL",
    "gn:name":"Neu Kentzlin",
    "gn:population":0,
    "gn:timezone":"Europe/Berlin",
    "iso:country":"DE",
    "wof:name":"Neu Kentzlin",
    "wof:placetype":"neighbourhood"
},
  "geometry": {"coordinates":[12.98462,53.76425],"type":"Point"}
}