{
  "type": "Feature",
  "properties": {
    "gn:admin1_code":"5",
    "gn:admin2_code":"66.0",
    "gn:admin3_code":"6631.0",
    "gn:admin4_code":"6631009.0",
    "gn:asciiname":"Bronnzell",
    "gn:cc2":"DE",
    "gn:country_code":"DE",
    "gn:dem":265,
    "gn:feature_class":"P",
    "gn:feature_code":"PPL",
    "gn:name":"Bronnzell",
    "gn:population":0,
    "gn:timezone":"Europe/Berlin",
    "iso:country":"DE",
    "name:und_x_variant":[
        "Bronzell"
    ],
    "wof:name":"Bronnzell",
    "wof:placetype":"neighbourhood"
},
  "geometry": {"coordinates":[9.68041,50.51637],"type":"Point"}
}