{
  "type": "Feature",
  "properties": {
    "gn:admin1_code":"2",
    "gn:admin2_code":"97.0",
    "gn:admin3_code":"9771.0",
    "gn:admin4_code":"9771144.0",
    "gn:asciiname":"Haslangkreit",
    "gn:country_code":"DE",
    "gn:dem":438,
    "gn:feature_class":"P",
    "gn:feature_code":"PPL",
    "gn:name":"Haslangkreit",
    "gn:population":0,
    "gn:timezone":"Europe/Berlin",
    "iso:country":"DE",
    "wof:name":"Haslangkreit",
    "wof:placetype":"neighbourhood"
},
  "geometry": {"coordinates":[11.17552,48.51315],"type":"Point"}
}