{
  "type": "Feature",
  "properties": {
    "gn:admin1_code":"7",
    "gn:admin2_code":"57.0",
    "gn:admin3_code":"5766.0",
    "gn:admin4_code":"5766052.0",
    "gn:asciiname":"Ratsiek",
    "gn:country_code":"DE",
    "gn:dem":160,
    "gn:feature_class":"P",
    "gn:feature_code":"PPL",
    "gn:name":"Ratsiek",
    "gn:population":0,
    "gn:timezone":"Europe/Berlin",
    "iso:country":"DE",
    "wof:name":"Ratsiek",
    "wof:placetype":"neighbourhood"
},
  "geometry": {"coordinates":[9.27212,51.91367],"type":"Point"}
}