{
  "type": "Feature",
  "properties": {
    "gn:admin1_code":"11",
    "gn:admin2_code":"0.0",
    "gn:admin3_code":"12066.0",
    "gn:admin4_code":"12066052.0",
    "gn:asciiname":"Kalkwitz",
    "gn:country_code":"DE",
    "gn:dem":69,
    "gn:feature_class":"P",
    "gn:feature_code":"PPL",
    "gn:name":"Kalkwitz",
    "gn:population":0,
    "gn:timezone":"Europe/Berlin",
    "iso:country":"DE",
    "wof:name":"Kalkwitz",
    "wof:placetype":"neighbourhood"
},
  "geometry": {"coordinates":[13.99124,51.7763],"type":"Point"}
}