{
  "type": "Feature",
  "properties": {
    "gn:admin1_code":"1",
    "gn:admin2_code":"83.0",
    "gn:admin3_code":"8326.0",
    "gn:admin4_code":"8326012.0",
    "gn:asciiname":"Heidenhofen",
    "gn:country_code":"DE",
    "gn:dem":745,
    "gn:feature_class":"P",
    "gn:feature_code":"PPL",
    "gn:name":"Heidenhofen",
    "gn:population":0,
    "gn:timezone":"Europe/Berlin",
    "iso:country":"DE",
    "wof:name":"Heidenhofen",
    "wof:placetype":"neighbourhood"
},
  "geometry": {"coordinates":[8.56417,47.98361],"type":"Point"}
}