{
  "type": "Feature",
  "properties": {
    "gn:admin1_code":"8",
    "gn:admin2_code":"0.0",
    "gn:admin3_code":"7235.0",
    "gn:admin4_code":"7235052.0",
    "gn:asciiname":"Irsch",
    "gn:country_code":"DE",
    "gn:dem":213,
    "gn:feature_class":"P",
    "gn:feature_code":"PPLA4",
    "gn:name":"Irsch",
    "gn:population":1538,
    "gn:timezone":"Europe/Berlin",
    "iso:country":"DE",
    "name:ceb_x_preferred":[
        "Irsch"
    ],
    "name:deu_x_preferred":[
        "Irsch"
    ],
    "name:epo_x_preferred":[
        "Irsch"
    ],
    "name:eus_x_preferred":[
        "Irsch"
    ],
    "name:fas_x_preferred":[
        "\u0627\u06cc\u0631\u0634"
    ],
    "name:fra_x_preferred":[
        "Irsch"
    ],
    "name:hun_x_preferred":[
        "Irsch"
    ],
    "name:ita_x_preferred":[
        "Irsch"
    ],
    "name:kaz_x_preferred":[
        "\u0418\u0440\u0448"
    ],
    "name:kir_x_preferred":[
        "\u0418\u0440\u0448"
    ],
    "name:msa_x_preferred":[
        "Irsch"
    ],
    "name:nld_x_preferred":[
        "Irsch"
    ],
    "name:pol_x_preferred":[
        "Irsch"
    ],
    "name:por_x_preferred":[
        "Irsch"
    ],
    "name:ron_x_preferred":[
        "Irsch"
    ],
    "name:rus_x_preferred":[
        "\u0418\u0440\u0448"
    ],
    "name:spa_x_preferred":[
        "Irsch"
    ],
    "name:srp_x_preferred":[
        "\u0418\u0440\u0448"
    ],
    "name:ukr_x_preferred":[
        "\u0406\u0440\u0448"
    ],
    "name:und_x_variant":[
        "Irisch"
    ],
    "name:uzb_x_preferred":[
        "Irsch"
    ],
    "name:vie_x_preferred":[
        "Irsch"
    ],
    "name:vol_x_preferred":[
        "Irsch"
    ],
    "name:war_x_preferred":[
        "Irsch"
    ],
    "name:zho_x_preferred":[
        "\u4f0a\u5c14\u65bd"
    ],
    "wof:name":"Irsch",
    "wof:placetype":"neighbourhood",
    "wof:population":1538
},
  "geometry": {"coordinates":[6.59547,49.60487],"type":"Point"}
}