{
  "type": "Feature",
  "properties": {
    "gn:admin1_code":"2",
    "gn:admin2_code":"92.0",
    "gn:admin3_code":"9272.0",
    "gn:admin4_code":"9272118.0",
    "gn:asciiname":"Promau",
    "gn:country_code":"DE",
    "gn:dem":707,
    "gn:feature_class":"P",
    "gn:feature_code":"PPL",
    "gn:name":"Promau",
    "gn:population":0,
    "gn:timezone":"Europe/Berlin",
    "iso:country":"DE",
    "wof:name":"Promau",
    "wof:placetype":"neighbourhood"
},
  "geometry": {"coordinates":[13.59016,48.79666],"type":"Point"}
}