{
  "type": "Feature",
  "properties": {
    "gn:admin1_code":"6",
    "gn:admin2_code":"0.0",
    "gn:admin3_code":"3255.0",
    "gn:admin4_code":"3255007.0",
    "gn:asciiname":"Schiesshaus",
    "gn:country_code":"DE",
    "gn:dem":402,
    "gn:feature_class":"P",
    "gn:feature_code":"PPL",
    "gn:name":"Schie\u00dfhaus",
    "gn:population":0,
    "gn:timezone":"Europe/Berlin",
    "iso:country":"DE",
    "wof:name":"Schiesshaus",
    "wof:placetype":"neighbourhood"
},
  "geometry": {"coordinates":[9.56588,51.82299],"type":"Point"}
}