{
  "type": "Feature",
  "properties": {
    "gn:admin1_code":"6",
    "gn:admin2_code":"0.0",
    "gn:admin3_code":"3454.0",
    "gn:admin4_code":"3454002.0",
    "gn:asciiname":"Duisenburg",
    "gn:country_code":"DE",
    "gn:dem":27,
    "gn:feature_class":"P",
    "gn:feature_code":"PPL",
    "gn:name":"Duisenburg",
    "gn:population":0,
    "gn:timezone":"Europe/Berlin",
    "iso:country":"DE",
    "wof:name":"Duisenburg",
    "wof:placetype":"neighbourhood"
},
  "geometry": {"coordinates":[7.42349,52.56257],"type":"Point"}
}