{
  "type": "Feature",
  "properties": {
    "gn:admin1_code":"2.0",
    "gn:admin2_code":"097",
    "gn:admin3_code":"9780.0",
    "gn:admin4_code":"9780132.0",
    "gn:asciiname":"Willis",
    "gn:country_code":"DE",
    "gn:dem":845,
    "gn:feature_class":"P",
    "gn:feature_code":"PPL",
    "gn:name":"Willis",
    "gn:population":0,
    "gn:timezone":"Europe/Berlin",
    "iso:country":"DE",
    "name:ceb_x_preferred":[
        "Willis"
    ],
    "name:ces_x_preferred":[
        "Willis"
    ],
    "name:deu_x_preferred":[
        "Willis"
    ],
    "name:fas_x_preferred":[
        "\u0648\u06cc\u0644\u06cc\u0633"
    ],
    "name:fin_x_preferred":[
        "Willis"
    ],
    "name:fra_x_preferred":[
        "Willis"
    ],
    "name:heb_x_preferred":[
        "\u05d5\u05d9\u05dc\u05d9\u05e1"
    ],
    "name:ita_x_preferred":[
        "Willis"
    ],
    "name:jpn_x_preferred":[
        "\u30a6\u30a3\u30ea\u30b9"
    ],
    "name:kor_x_preferred":[
        "\uc70c\ub9ac\uc2a4"
    ],
    "name:lit_x_preferred":[
        "Willis"
    ],
    "name:nld_x_preferred":[
        "Willis"
    ],
    "name:pol_x_preferred":[
        "Willis"
    ],
    "name:por_x_preferred":[
        "Willis"
    ],
    "name:rus_x_preferred":[
        "\u0423\u0438\u043b\u043b\u0438\u0441"
    ],
    "name:slk_x_preferred":[
        "Willis"
    ],
    "name:srp_x_preferred":[
        "\u0412\u0438\u043b\u0438\u0441"
    ],
    "name:swe_x_preferred":[
        "Willis"
    ],
    "name:ukr_x_preferred":[
        "\u0412\u0456\u043b\u043b\u0456\u0441"
    ],
    "name:urd_x_preferred":[
        "\u0648\u06cc\u0644\u06cc\u0633"
    ],
    "name:vol_x_preferred":[
        "Willis"
    ],
    "wof:name":"Willis",
    "wof:placetype":"neighbourhood"
},
  "geometry": {"coordinates":[10.00371,47.5459],"type":"Point"}
}