{
  "type": "Feature",
  "properties": {
    "gn:admin1_code":"2.0",
    "gn:admin2_code":"097",
    "gn:admin3_code":"9780.0",
    "gn:admin4_code":"9780132.0",
    "gn:asciiname":"Willis",
    "gn:country_code":"DE",
    "gn:dem":845,
    "gn:feature_class":"P",
    "gn:feature_code":"PPL",
    "gn:name":"Willis",
    "gn:population":0,
    "gn:timezone":"Europe/Berlin",
    "iso:country":"DE",
    "wof:name":"Willis",
    "wof:placetype":"neighbourhood"
},
  "geometry": {"coordinates":[10.00371,47.5459],"type":"Point"}
}