{
  "type": "Feature",
  "properties": {
    "gn:admin1_code":"2.0",
    "gn:admin2_code":"97.0",
    "gn:admin3_code":"9776.0",
    "gn:admin4_code":"9776127.0",
    "gn:asciiname":"Balzhofen",
    "gn:country_code":"DE",
    "gn:dem":801,
    "gn:feature_class":"P",
    "gn:feature_code":"PPL",
    "gn:name":"Balzhofen",
    "gn:population":0,
    "gn:timezone":"Europe/Berlin",
    "iso:country":"DE",
    "wof:name":"Balzhofen",
    "wof:placetype":"neighbourhood"
},
  "geometry": {"coordinates":[9.96783,47.58678],"type":"Point"}
}