{
  "type": "Feature",
  "properties": {
    "gn:admin1_code":"1",
    "gn:admin2_code":"82.0",
    "gn:admin3_code":"8215.0",
    "gn:admin4_code":"8215046.0",
    "gn:asciiname":"Volkersbach",
    "gn:country_code":"DE",
    "gn:dem":393,
    "gn:feature_class":"P",
    "gn:feature_code":"PPL",
    "gn:name":"V\u00f6lkersbach",
    "gn:population":0,
    "gn:timezone":"Europe/Berlin",
    "iso:country":"DE",
    "name:deu_x_preferred":[
        "Volkersbach"
    ],
    "wof:name":"Volkersbach",
    "wof:placetype":"neighbourhood"
},
  "geometry": {"coordinates":[8.39355,48.87149],"type":"Point"}
}