{
  "type": "Feature",
  "properties": {
    "gn:country":"DE",
    "gn:fcode":"PPL",
    "gn:population":57,
    "iso:country":"DE",
    "name:bak_x_preferred":[
        "\u041f\u044e\u0433\u0433\u0435\u043d"
    ],
    "name:che_x_preferred":[
        "\u041f\u0443\u044c\u0433\u0433\u0435\u043d"
    ],
    "name:deu_x_preferred":[
        "P\u00fcggen"
    ],
    "name:eng_x_preferred":[
        "P\u00fcggen"
    ],
    "name:epo_x_preferred":[
        "P\u00fcggen"
    ],
    "name:fas_x_preferred":[
        "\u067e\u0648\u06af\u0646"
    ],
    "name:fra_x_preferred":[
        "P\u00fcggen"
    ],
    "name:gle_x_preferred":[
        "P\u00fcggen"
    ],
    "name:ita_x_preferred":[
        "P\u00fcggen"
    ],
    "name:kaz_x_preferred":[
        "\u041f\u044e\u0433\u0433\u0435\u043d"
    ],
    "name:kir_x_preferred":[
        "\u041f\u044e\u0433\u0433\u0435\u043d"
    ],
    "name:nld_x_preferred":[
        "P\u00fcggen"
    ],
    "name:ron_x_preferred":[
        "P\u00fcggen"
    ],
    "name:rus_x_preferred":[
        "\u041f\u044e\u0433\u0433\u0435\u043d"
    ],
    "name:tat_x_preferred":[
        "\u041f\u044e\u0433\u0433\u0435\u043d"
    ],
    "name:uzb_x_preferred":[
        "P\u00fcggen"
    ],
    "name:vol_x_preferred":[
        "P\u00fcggen"
    ],
    "qs_pg:aaroncc":"DE",
    "qs_pg:gn_country":"DE",
    "qs_pg:gn_fcode":"PPL",
    "qs_pg:gn_pop":57,
    "qs_pg:name":"P\u00fcggen",
    "qs_pg:name_adm0":"Deutschland",
    "qs_pg:name_adm1":"Sachsen-Anhalt",
    "qs_pg:photos_9r":0,
    "qs_pg:photos_sr":0,
    "qs_pg:pop_sr":1,
    "qs_pg:qs_pg_placetype":"locality",
    "qs_pg:qs_pg_placetype_gp":"Town",
    "qs_pg:woe_adm0":23424829,
    "woe:adm0_id":23424829,
    "woe:name_adm0":"Deutschland",
    "woe:name_adm1":"Sachsen-Anhalt",
    "woe:placetype":"Town",
    "wof:name":"P\u00fcggen",
    "wof:placetype":"neighbourhood",
    "wof:population":57
},
  "geometry": {"coordinates":[11.05979,52.73291],"type":"Point"}
}