{
  "type": "Feature",
  "properties": {
    "gn:admin1_code":"2",
    "gn:admin2_code":"97.0",
    "gn:admin3_code":"9776.0",
    "gn:admin4_code":"9776116.0",
    "gn:asciiname":"Unterreitnau",
    "gn:country_code":"DE",
    "gn:dem":467,
    "gn:feature_class":"P",
    "gn:feature_code":"PPL",
    "gn:name":"Unterreitnau",
    "gn:population":0,
    "gn:timezone":"Europe/Berlin",
    "iso:country":"DE",
    "wof:name":"Unterreitnau",
    "wof:placetype":"neighbourhood"
},
  "geometry": {"coordinates":[9.66358,47.59161],"type":"Point"}
}