{
  "type": "Feature",
  "properties": {
    "gn:gn_country":"DE",
    "gn:gn_fcode":"PPLA4",
    "gn:gn_pop":466,
    "gn:population":466,
    "iso:country":"DE",
    "name:baq_x_preferred":[
        "Boksee"
    ],
    "name:chi_x_preferred":[
        "\u535a\u514b\u585e"
    ],
    "name:dan_x_preferred":[
        "Boksee"
    ],
    "name:dut_x_preferred":[
        "Boksee"
    ],
    "name:eng_x_preferred":[
        "Boksee"
    ],
    "name:epo_x_preferred":[
        "Boksee"
    ],
    "name:fre_x_preferred":[
        "Boksee"
    ],
    "name:ger_x_preferred":[
        "Boksee"
    ],
    "name:hun_x_preferred":[
        "Boksee"
    ],
    "name:ita_x_preferred":[
        "Boksee"
    ],
    "name:mac_x_preferred":[
        "\u0411\u043e\u043a\u0437\u0435"
    ],
    "name:may_x_preferred":[
        "Boksee"
    ],
    "name:per_x_preferred":[
        "\u0628\u0648\u06a9\u0632\u0647"
    ],
    "name:pol_x_preferred":[
        "Boksee"
    ],
    "name:por_x_preferred":[
        "Boksee"
    ],
    "name:rum_x_preferred":[
        "Boksee"
    ],
    "name:rus_x_preferred":[
        "\u0411\u043e\u043a\u0437\u0435\u0435"
    ],
    "name:spa_x_preferred":[
        "Boksee"
    ],
    "name:srp_x_preferred":[
        "\u0411\u043e\u043a\u0437\u0435"
    ],
    "name:tur_x_preferred":[
        "Boksee"
    ],
    "name:ukr_x_preferred":[
        "\u0411\u043e\u043a\u0437\u0435"
    ],
    "name:uzb_x_preferred":[
        "Boksee"
    ],
    "name:vie_x_preferred":[
        "Boksee"
    ],
    "name:vol_x_preferred":[
        "Boksee"
    ],
    "name:war_x_preferred":[
        "Boksee"
    ],
    "qs_pg:aaroncc":"DE",
    "qs_pg:gn_country":"DE",
    "qs_pg:gn_fcode":"PPLA4",
    "qs_pg:gn_pop":466,
    "qs_pg:name":"Boksee",
    "qs_pg:photos_9r":0,
    "qs_pg:photos_sr":0,
    "qs_pg:pop_sr":2,
    "qs_pg:qs_pg_placetype":"locality",
    "wof:name":"Boksee",
    "wof:placetype":"locality",
    "wof:population":466
},
  "geometry": {"coordinates":[10.13333,54.23333],"type":"Point"}
}