{
  "type": "Feature",
  "properties": {
    "gn:gn_country":"DE",
    "gn:gn_fcode":"PPLA4",
    "gn:gn_pop":136,
    "gn:population":136,
    "iso:country":"DE",
    "name:baq_x_preferred":[
        "Auufer"
    ],
    "name:chi_x_preferred":[
        "\u5965\u4e4c\u8d39\u5c14"
    ],
    "name:dan_x_preferred":[
        "Auufer"
    ],
    "name:dut_x_preferred":[
        "Auufer"
    ],
    "name:eng_x_preferred":[
        "Auufer"
    ],
    "name:epo_x_preferred":[
        "Auufer"
    ],
    "name:fre_x_preferred":[
        "Auufer"
    ],
    "name:ger_x_preferred":[
        "Auufer"
    ],
    "name:hun_x_preferred":[
        "Auufer"
    ],
    "name:ita_x_preferred":[
        "Auufer"
    ],
    "name:mac_x_preferred":[
        "\u0410\u0443\u0444\u0435\u0440"
    ],
    "name:may_x_preferred":[
        "Auufer"
    ],
    "name:per_x_preferred":[
        "\u0627\u0648\u0648\u0641\u0631"
    ],
    "name:pol_x_preferred":[
        "Auufer"
    ],
    "name:por_x_preferred":[
        "Auufer"
    ],
    "name:rum_x_preferred":[
        "Auufer"
    ],
    "name:rus_x_preferred":[
        "\u0410\u0443\u0443\u0444\u0435\u0440"
    ],
    "name:spa_x_preferred":[
        "Auufer"
    ],
    "name:srp_x_preferred":[
        "\u0410\u0443\u0443\u0444\u0435\u0440"
    ],
    "name:tur_x_preferred":[
        "Auufer"
    ],
    "name:ukr_x_preferred":[
        "\u0410\u0443\u0443\u0444\u0435\u0440"
    ],
    "name:uzb_x_preferred":[
        "Auufer"
    ],
    "name:vie_x_preferred":[
        "Auufer"
    ],
    "name:vol_x_preferred":[
        "Auufer"
    ],
    "name:war_x_preferred":[
        "Auufer"
    ],
    "qs_pg:aaroncc":"DE",
    "qs_pg:gn_country":"DE",
    "qs_pg:gn_fcode":"PPLA4",
    "qs_pg:gn_pop":136,
    "qs_pg:name":"Auufer",
    "qs_pg:photos_9r":0,
    "qs_pg:photos_sr":0,
    "qs_pg:pop_sr":1,
    "qs_pg:qs_pg_placetype":"locality",
    "wof:name":"Auufer",
    "wof:placetype":"locality",
    "wof:population":136
},
  "geometry": {"coordinates":[9.68302,53.92416],"type":"Point"}
}