{
  "type": "Feature",
  "properties": {
    "gn:admin1_code":"1.0",
    "gn:admin2_code":"81.0",
    "gn:admin3_code":"8116.0",
    "gn:admin4_code":"8116019.0",
    "gn:asciiname":"Zollberg",
    "gn:country_code":"DE",
    "gn:dem":347,
    "gn:feature_class":"P",
    "gn:feature_code":"PPL",
    "gn:name":"Zollberg",
    "gn:population":0,
    "gn:timezone":"Europe/Berlin",
    "iso:country":"DE",
    "wof:name":"Zollberg",
    "wof:placetype":"neighbourhood"
},
  "geometry": {"coordinates":[9.30066,48.72721],"type":"Point"}
}