{
  "type": "Feature",
  "properties": {
    "gn:admin1_code":"5",
    "gn:admin2_code":"65.0",
    "gn:admin3_code":"6535.0",
    "gn:admin4_code":"6535015.0",
    "gn:asciiname":"Hutzdorf",
    "gn:country_code":"DE",
    "gn:dem":224,
    "gn:feature_class":"P",
    "gn:feature_code":"PPL",
    "gn:name":"Hutzdorf",
    "gn:population":0,
    "gn:timezone":"Europe/Berlin",
    "iso:country":"DE",
    "wof:name":"Hutzdorf",
    "wof:placetype":"neighbourhood"
},
  "geometry": {"coordinates":[9.58102,50.68507],"type":"Point"}
}