{
  "type": "Feature",
  "properties": {
    "gn:admin1_code":"13",
    "gn:admin2_code":"0.0",
    "gn:admin3_code":"14523.0",
    "gn:admin4_code":"14523370.0",
    "gn:asciiname":"Schilbach",
    "gn:country_code":"DE",
    "gn:dem":558,
    "gn:feature_class":"P",
    "gn:feature_code":"PPL",
    "gn:name":"Schilbach",
    "gn:population":0,
    "gn:timezone":"Europe/Berlin",
    "iso:country":"DE",
    "wof:name":"Schilbach",
    "wof:placetype":"neighbourhood"
},
  "geometry": {"coordinates":[12.29815,50.39353],"type":"Point"}
}