{
  "type": "Feature",
  "properties": {
    "gn:admin1_code":"7.0",
    "gn:admin2_code":"057",
    "gn:admin3_code":"5758.0",
    "gn:admin4_code":"5758004.0",
    "gn:asciiname":"Werfen",
    "gn:country_code":"DE",
    "gn:dem":65,
    "gn:feature_class":"P",
    "gn:feature_code":"PPL",
    "gn:name":"Werfen",
    "gn:population":0,
    "gn:timezone":"Europe/Berlin",
    "iso:country":"DE",
    "wof:name":"Werfen",
    "wof:placetype":"neighbourhood"
},
  "geometry": {"coordinates":[8.55406,52.1829],"type":"Point"}
}