{
  "type": "Feature",
  "properties": {
    "gn:admin1_code":"7.0",
    "gn:admin2_code":"057",
    "gn:admin3_code":"5758.0",
    "gn:admin4_code":"5758004.0",
    "gn:asciiname":"Werfen",
    "gn:country_code":"DE",
    "gn:dem":65,
    "gn:feature_class":"P",
    "gn:feature_code":"PPL",
    "gn:name":"Werfen",
    "gn:population":0,
    "gn:timezone":"Europe/Berlin",
    "iso:country":"DE",
    "name:bar_x_preferred":[
        "Werfm"
    ],
    "name:ceb_x_preferred":[
        "Werfen"
    ],
    "name:dan_x_preferred":[
        "Werfen"
    ],
    "name:deu_x_preferred":[
        "Werfen"
    ],
    "name:epo_x_preferred":[
        "Werfen"
    ],
    "name:fin_x_preferred":[
        "Werfen"
    ],
    "name:fra_x_preferred":[
        "Werfen"
    ],
    "name:hun_x_preferred":[
        "Werfen"
    ],
    "name:ita_x_preferred":[
        "Werfen"
    ],
    "name:kaz_x_preferred":[
        "\u0412\u0435\u0440\u0444\u0435\u043d"
    ],
    "name:nld_x_preferred":[
        "Werfen"
    ],
    "name:nno_x_preferred":[
        "Werfen"
    ],
    "name:pol_x_preferred":[
        "Werfen"
    ],
    "name:rus_x_preferred":[
        "\u0412\u0435\u0440\u0444\u0435\u043d"
    ],
    "name:slk_x_preferred":[
        "Werfen"
    ],
    "name:spa_x_preferred":[
        "Werfen"
    ],
    "name:swe_x_preferred":[
        "Werfen"
    ],
    "name:tur_x_preferred":[
        "Werfen"
    ],
    "name:ukr_x_preferred":[
        "\u0412\u0435\u0440\u0444\u0435\u043d"
    ],
    "name:uzb_x_preferred":[
        "Werfen"
    ],
    "name:vol_x_preferred":[
        "Werfen"
    ],
    "name:war_x_preferred":[
        "Werfen"
    ],
    "name:zho_x_preferred":[
        "\u7dad\u723e\u82ac"
    ],
    "wof:name":"Werfen",
    "wof:placetype":"neighbourhood"
},
  "geometry": {"coordinates":[8.55406,52.1829],"type":"Point"}
}