{
  "type": "Feature",
  "properties": {
    "gn:admin1_code":"1",
    "gn:admin2_code":"81.0",
    "gn:admin3_code":"8116.0",
    "gn:admin4_code":"8116037.0",
    "gn:asciiname":"Hegenlohe",
    "gn:country_code":"DE",
    "gn:dem":408,
    "gn:feature_class":"P",
    "gn:feature_code":"PPL",
    "gn:name":"Hegenlohe",
    "gn:population":0,
    "gn:timezone":"Europe/Berlin",
    "iso:country":"DE",
    "wof:name":"Hegenlohe",
    "wof:placetype":"neighbourhood"
},
  "geometry": {"coordinates":[9.47592,48.73369],"type":"Point"}
}