{
  "type": "Feature",
  "properties": {
    "gn:country":"DE",
    "gn:fcode":"PPL",
    "gn:population":829,
    "iso:country":"DE",
    "name:ceb_x_preferred":[
        "Isselbach"
    ],
    "name:deu_x_preferred":[
        "Isselbach"
    ],
    "name:epo_x_preferred":[
        "Isselbach"
    ],
    "name:eus_x_preferred":[
        "Isselbach"
    ],
    "name:fas_x_preferred":[
        "\u0627\u06cc\u0633\u0644\u0628\u0627\u062e"
    ],
    "name:fra_x_preferred":[
        "Isselbach"
    ],
    "name:hun_x_preferred":[
        "Isselbach"
    ],
    "name:ita_x_preferred":[
        "Isselbach"
    ],
    "name:kaz_x_preferred":[
        "\u0418\u0441\u0441\u0435\u043b\u044c\u0431\u0430\u0445"
    ],
    "name:kir_x_preferred":[
        "\u0418\u0441\u0441\u0435\u043b\u044c\u0431\u0430\u0445"
    ],
    "name:msa_x_preferred":[
        "Isselbach"
    ],
    "name:nld_x_preferred":[
        "Isselbach"
    ],
    "name:pol_x_preferred":[
        "Isselbach"
    ],
    "name:por_x_preferred":[
        "Isselbach"
    ],
    "name:ron_x_preferred":[
        "Isselbach"
    ],
    "name:rus_x_preferred":[
        "\u0418\u0441\u0441\u0435\u043b\u044c\u0431\u0430\u0445"
    ],
    "name:spa_x_preferred":[
        "Isselbach"
    ],
    "name:srp_x_preferred":[
        "\u0418\u0441\u0435\u043b\u0431\u0430\u0445"
    ],
    "name:ukr_x_preferred":[
        "\u0406\u0441\u0441\u0435\u043b\u044c\u0431\u0430\u0445"
    ],
    "name:und_x_variant":[
        "Selbach"
    ],
    "name:uzb_x_preferred":[
        "Isselbach"
    ],
    "name:vie_x_preferred":[
        "Isselbach"
    ],
    "name:vol_x_preferred":[
        "Isselbach"
    ],
    "name:war_x_preferred":[
        "Isselbach"
    ],
    "name:zho_x_preferred":[
        "\u4f0a\u745f\u5c14\u5df4\u8d6b"
    ],
    "qs_pg:aaroncc":"DE",
    "qs_pg:gn_country":"DE",
    "qs_pg:gn_fcode":"PPL",
    "qs_pg:gn_pop":829,
    "qs_pg:name":"Isselbach",
    "qs_pg:name_adm0":"Deutschland",
    "qs_pg:name_adm1":"Rheinland-Pfalz",
    "qs_pg:photos_9r":0,
    "qs_pg:photos_sr":0,
    "qs_pg:pop_sr":2,
    "qs_pg:qs_pg_placetype":"locality",
    "qs_pg:qs_pg_placetype_gp":"Town",
    "qs_pg:woe_adm0":23424829,
    "woe:adm0_id":23424829,
    "woe:name_adm0":"Deutschland",
    "woe:name_adm1":"Rheinland-Pfalz",
    "woe:placetype":"Town",
    "wof:name":"Isselbach",
    "wof:placetype":"neighbourhood",
    "wof:population":829
},
  "geometry": {"coordinates":[7.77025,50.74624],"type":"Point"}
}