{
  "type": "Feature",
  "properties": {
    "gn:admin1_code":"6",
    "gn:admin2_code":"0.0",
    "gn:admin3_code":"3453.0",
    "gn:admin4_code":"3453006.0",
    "gn:asciiname":"Felde",
    "gn:country_code":"DE",
    "gn:dem":29,
    "gn:feature_class":"P",
    "gn:feature_code":"PPL",
    "gn:name":"Felde",
    "gn:population":0,
    "gn:timezone":"Europe/Berlin",
    "iso:country":"DE",
    "name:ceb_x_preferred":[
        "Felde"
    ],
    "name:dan_x_preferred":[
        "Felde"
    ],
    "name:deu_x_preferred":[
        "Felde"
    ],
    "name:epo_x_preferred":[
        "Felde"
    ],
    "name:eus_x_preferred":[
        "Felde"
    ],
    "name:fas_x_preferred":[
        "\u0641\u0644\u062f\u0647"
    ],
    "name:fra_x_preferred":[
        "Felde"
    ],
    "name:hun_x_preferred":[
        "Felde"
    ],
    "name:ita_x_preferred":[
        "Felde"
    ],
    "name:kaz_x_preferred":[
        "\u0424\u0435\u043b\u044c\u0434\u0435"
    ],
    "name:kir_x_preferred":[
        "\u0424\u0435\u043b\u044c\u0434\u0435"
    ],
    "name:mkd_x_preferred":[
        "\u0424\u0435\u043b\u0434\u0435"
    ],
    "name:msa_x_preferred":[
        "Felde"
    ],
    "name:nld_x_preferred":[
        "Felde"
    ],
    "name:pol_x_preferred":[
        "Felde"
    ],
    "name:por_x_preferred":[
        "Felde"
    ],
    "name:ron_x_preferred":[
        "Felde"
    ],
    "name:rus_x_preferred":[
        "\u0424\u0435\u043b\u044c\u0434\u0435"
    ],
    "name:spa_x_preferred":[
        "Felde"
    ],
    "name:srp_x_preferred":[
        "\u0424\u0435\u043b\u0434\u0435"
    ],
    "name:tur_x_preferred":[
        "Felde"
    ],
    "name:ukr_x_preferred":[
        "\u0424\u0435\u043b\u044c\u0434\u0435"
    ],
    "name:uzb_x_preferred":[
        "Felde"
    ],
    "name:vie_x_preferred":[
        "Felde"
    ],
    "name:vol_x_preferred":[
        "Felde"
    ],
    "name:war_x_preferred":[
        "Felde"
    ],
    "wof:name":"Felde",
    "wof:placetype":"neighbourhood"
},
  "geometry": {"coordinates":[7.95621,52.73309],"type":"Point"}
}