{
  "type": "Feature",
  "properties": {
    "gn:admin1_code":"2",
    "gn:admin2_code":"93.0",
    "gn:admin3_code":"9376.0",
    "gn:admin4_code":"9376161.0",
    "gn:asciiname":"Waltenhof",
    "gn:country_code":"DE",
    "gn:dem":358,
    "gn:feature_class":"P",
    "gn:feature_code":"PPL",
    "gn:name":"Waltenhof",
    "gn:population":0,
    "gn:timezone":"Europe/Berlin",
    "iso:country":"DE",
    "wof:name":"Waltenhof",
    "wof:placetype":"neighbourhood"
},
  "geometry": {"coordinates":[12.08076,49.26544000000001],"type":"Point"}
}