{
  "type": "Feature",
  "properties": {
    "gn:admin1_code":"1",
    "gn:admin2_code":"81.0",
    "gn:admin3_code":"8136.0",
    "gn:admin4_code":"8136021.0",
    "gn:asciiname":"Hermannsfeld",
    "gn:country_code":"DE",
    "gn:dem":429,
    "gn:feature_class":"P",
    "gn:feature_code":"PPL",
    "gn:name":"Hermannsfeld",
    "gn:population":0,
    "gn:timezone":"Europe/Berlin",
    "iso:country":"DE",
    "wof:name":"Hermannsfeld",
    "wof:placetype":"neighbourhood"
},
  "geometry": {"coordinates":[9.98928,48.81907],"type":"Point"}
}