{
  "type": "Feature",
  "properties": {
    "gn:admin1_code":"12",
    "gn:admin2_code":"0.0",
    "gn:admin3_code":"13073.0",
    "gn:admin4_code":"13073060.0",
    "gn:asciiname":"Obermuetzkow",
    "gn:country_code":"DE",
    "gn:dem":14,
    "gn:feature_class":"P",
    "gn:feature_code":"PPL",
    "gn:name":"Oberm\u00fctzkow",
    "gn:population":0,
    "gn:timezone":"Europe/Berlin",
    "iso:country":"DE",
    "wof:name":"Obermuetzkow",
    "wof:placetype":"neighbourhood"
},
  "geometry": {"coordinates":[12.93134,54.28076],"type":"Point"}
}