{
  "type": "Feature",
  "properties": {
    "gn:admin1_code":"2.0",
    "gn:admin2_code":"094",
    "gn:admin3_code":"9471.0",
    "gn:admin4_code":"9471117.0",
    "gn:asciiname":"Weipelsdorf",
    "gn:country_code":"DE",
    "gn:dem":266,
    "gn:feature_class":"P",
    "gn:feature_code":"PPL",
    "gn:name":"Weipelsdorf",
    "gn:population":0,
    "gn:timezone":"Europe/Berlin",
    "iso:country":"DE",
    "wof:name":"Weipelsdorf",
    "wof:placetype":"neighbourhood"
},
  "geometry": {"coordinates":[10.80605,49.89902],"type":"Point"}
}