{
  "type": "Feature",
  "properties": {
    "gn:admin1_code":"2.0",
    "gn:admin2_code":"094",
    "gn:admin3_code":"9476.0",
    "gn:admin4_code":"9476184.0",
    "gn:asciiname":"Wolfersgrun",
    "gn:country_code":"DE",
    "gn:dem":588,
    "gn:feature_class":"P",
    "gn:feature_code":"PPL",
    "gn:name":"Wolfersgr\u00fcn",
    "gn:population":0,
    "gn:timezone":"Europe/Berlin",
    "iso:country":"DE",
    "wof:name":"Wolfersgrun",
    "wof:placetype":"neighbourhood"
},
  "geometry": {"coordinates":[11.53192,50.30909000000001],"type":"Point"}
}