{
  "type": "Feature",
  "properties": {
    "gn:country":"DE",
    "gn:fcode":"PPLX",
    "gn:population":7500,
    "iso:country":"DE",
    "name:nds_x_preferred":[
        "Garbsen-Mitte"
    ],
    "qs_pg:aaroncc":"DE",
    "qs_pg:gn_country":"DE",
    "qs_pg:gn_fcode":"PPLX",
    "qs_pg:gn_pop":7500,
    "qs_pg:name":"Garbsen-Mitte",
    "qs_pg:photos_9r":0,
    "qs_pg:photos_sr":0,
    "qs_pg:pop_sr":5,
    "qs_pg:qs_pg_placetype":"neighbourhood",
    "wof:name":"Garbsen-Mitte",
    "wof:placetype":"neighbourhood",
    "wof:population":7500
},
  "geometry": {"coordinates":[9.60383,52.42659],"type":"Point"}
}