{
  "type": "Feature",
  "properties": {
    "gn:admin1_code":"14",
    "gn:admin2_code":"0.0",
    "gn:admin3_code":"15088.0",
    "gn:admin4_code":"15088030.0",
    "gn:asciiname":"Goehritz",
    "gn:country_code":"DE",
    "gn:dem":203,
    "gn:feature_class":"P",
    "gn:feature_code":"PPL",
    "gn:name":"G\u00f6hritz",
    "gn:population":0,
    "gn:timezone":"Europe/Berlin",
    "iso:country":"DE",
    "wof:name":"Goehritz",
    "wof:placetype":"neighbourhood"
},
  "geometry": {"coordinates":[11.63128,51.34424],"type":"Point"}
}