{
  "type": "Feature",
  "properties": {
    "gn:admin1_code":"5",
    "gn:admin2_code":"66.0",
    "gn:admin3_code":"6634.0",
    "gn:admin4_code":"6634005.0",
    "gn:asciiname":"Wehren",
    "gn:country_code":"DE",
    "gn:dem":188,
    "gn:feature_class":"P",
    "gn:feature_code":"PPL",
    "gn:name":"Wehren",
    "gn:population":0,
    "gn:timezone":"Europe/Berlin",
    "iso:country":"DE",
    "wof:name":"Wehren",
    "wof:placetype":"neighbourhood"
},
  "geometry": {"coordinates":[9.29584,51.16913],"type":"Point"}
}