{
  "type": "Feature",
  "properties": {
    "gn:admin1_code":"2",
    "gn:admin2_code":"97.0",
    "gn:admin3_code":"9777.0",
    "gn:admin4_code":"9777131.0",
    "gn:asciiname":"Durber",
    "gn:country_code":"DE",
    "gn:dem":814,
    "gn:feature_class":"P",
    "gn:feature_code":"PPL",
    "gn:name":"Durber",
    "gn:population":0,
    "gn:timezone":"Europe/Berlin",
    "iso:country":"DE",
    "wof:name":"Durber",
    "wof:placetype":"neighbourhood"
},
  "geometry": {"coordinates":[10.51349,47.7157],"type":"Point"}
}