{
  "type": "Feature",
  "properties": {
    "gn:admin1_code":"7.0",
    "gn:admin2_code":"53.0",
    "gn:admin3_code":"5382.0",
    "gn:admin4_code":"5382024.0",
    "gn:asciiname":"Bockeroth",
    "gn:country_code":"DE",
    "gn:dem":164,
    "gn:feature_class":"P",
    "gn:feature_code":"PPL",
    "gn:name":"Bockeroth",
    "gn:population":0,
    "gn:timezone":"Europe/Berlin",
    "iso:country":"DE",
    "wof:name":"Bockeroth",
    "wof:placetype":"neighbourhood"
},
  "geometry": {"coordinates":[7.24299,50.72692],"type":"Point"}
}