{
  "type": "Feature",
  "properties": {
    "gn:admin1_code":"6.0",
    "gn:admin2_code":"00",
    "gn:admin3_code":"3454.0",
    "gn:admin4_code":"3454033.0",
    "gn:asciiname":"Westerholt",
    "gn:country_code":"DE",
    "gn:dem":37,
    "gn:feature_class":"P",
    "gn:feature_code":"PPL",
    "gn:name":"Westerholt",
    "gn:population":0,
    "gn:timezone":"Europe/Berlin",
    "iso:country":"DE",
    "name:ceb_x_preferred":[
        "Westerholt"
    ],
    "name:dan_x_preferred":[
        "Westerholt"
    ],
    "name:deu_x_preferred":[
        "Westerholt"
    ],
    "name:epo_x_preferred":[
        "Westerholt"
    ],
    "name:est_x_preferred":[
        "Westerholt"
    ],
    "name:eus_x_preferred":[
        "Westerholt"
    ],
    "name:fas_x_preferred":[
        "\u0648\u0634\u062a\u0631\u0647\u0648\u0644\u062a"
    ],
    "name:fra_x_preferred":[
        "Westerholt"
    ],
    "name:hun_x_preferred":[
        "Westerholt"
    ],
    "name:ita_x_preferred":[
        "Westerholt"
    ],
    "name:kaz_x_preferred":[
        "\u0412\u0435\u0441\u0442\u0435\u0440\u0445\u043e\u043b\u044c\u0442"
    ],
    "name:kir_x_preferred":[
        "\u0412\u0435\u0441\u0442\u0435\u0440\u0445\u043e\u043b\u044c\u0442"
    ],
    "name:lat_x_preferred":[
        "Westerholt"
    ],
    "name:msa_x_preferred":[
        "Westerholt"
    ],
    "name:nld_x_preferred":[
        "Westerholt"
    ],
    "name:pol_x_preferred":[
        "Westerholt"
    ],
    "name:por_x_preferred":[
        "Westerholt"
    ],
    "name:ron_x_preferred":[
        "Westerholt"
    ],
    "name:rus_x_preferred":[
        "\u0412\u0435\u0441\u0442\u0435\u0440\u0445\u043e\u043b\u044c\u0442"
    ],
    "name:spa_x_preferred":[
        "Westerholt"
    ],
    "name:srp_x_preferred":[
        "\u0412\u0435\u0441\u0442\u0435\u0440\u0445\u043e\u043b\u0442"
    ],
    "name:ukr_x_preferred":[
        "\u0412\u0435\u0441\u0442\u0435\u0440\u0433\u043e\u043b\u044c\u0442"
    ],
    "name:uzb_x_preferred":[
        "Westerholt"
    ],
    "name:vol_x_preferred":[
        "Westerholt"
    ],
    "name:war_x_preferred":[
        "Westerholt"
    ],
    "name:zho_x_preferred":[
        "\u97e6\u65af\u7279\u970d\u5c14\u7279"
    ],
    "wof:name":"Westerholt",
    "wof:placetype":"neighbourhood"
},
  "geometry": {"coordinates":[7.63052,52.92246],"type":"Point"}
}