{
  "type": "Feature",
  "properties": {
    "gn:admin1_code":"7",
    "gn:admin2_code":"53.0",
    "gn:admin3_code":"5374.0",
    "gn:admin4_code":"5374052.0",
    "gn:asciiname":"Dreine",
    "gn:country_code":"DE",
    "gn:dem":322,
    "gn:feature_class":"P",
    "gn:feature_code":"PPL",
    "gn:name":"Dreine",
    "gn:population":0,
    "gn:timezone":"Europe/Berlin",
    "iso:country":"DE",
    "wof:name":"Dreine",
    "wof:placetype":"neighbourhood"
},
  "geometry": {"coordinates":[7.42289,51.1355],"type":"Point"}
}