{
  "type": "Feature",
  "properties": {
    "gn:admin1_code":"11",
    "gn:admin2_code":"0.0",
    "gn:admin3_code":"12069.0",
    "gn:admin4_code":"12069306.0",
    "gn:asciiname":"Damsdorf",
    "gn:country_code":"DE",
    "gn:dem":34,
    "gn:feature_class":"P",
    "gn:feature_code":"PPL",
    "gn:name":"Damsdorf",
    "gn:population":0,
    "gn:timezone":"Europe/Berlin",
    "iso:country":"DE",
    "name:ceb_x_preferred":[
        "Damsdorf"
    ],
    "name:dan_x_preferred":[
        "Damsdorf"
    ],
    "name:deu_x_preferred":[
        "Damsdorf"
    ],
    "name:epo_x_preferred":[
        "Damsdorf"
    ],
    "name:eus_x_preferred":[
        "Damsdorf"
    ],
    "name:fas_x_preferred":[
        "\u062f\u0627\u0645\u0633\u062f\u0648\u0631\u0641"
    ],
    "name:fra_x_preferred":[
        "Damsdorf"
    ],
    "name:hun_x_preferred":[
        "Damsdorf"
    ],
    "name:ind_x_preferred":[
        "Damsdorf"
    ],
    "name:ita_x_preferred":[
        "Damsdorf"
    ],
    "name:mkd_x_preferred":[
        "\u0414\u0430\u043c\u0441\u0434\u043e\u0440\u0444"
    ],
    "name:msa_x_preferred":[
        "Damsdorf"
    ],
    "name:nld_x_preferred":[
        "Damsdorf"
    ],
    "name:nor_x_preferred":[
        "Damsdorf"
    ],
    "name:pol_x_preferred":[
        "Damsdorf"
    ],
    "name:por_x_preferred":[
        "Damsdorf"
    ],
    "name:ron_x_preferred":[
        "Damsdorf"
    ],
    "name:rus_x_preferred":[
        "\u0414\u0430\u043c\u0441\u0434\u043e\u0440\u0444"
    ],
    "name:spa_x_preferred":[
        "Damsdorf"
    ],
    "name:srp_x_preferred":[
        "\u0414\u0430\u043c\u0437\u0434\u043e\u0440\u0444"
    ],
    "name:tur_x_preferred":[
        "Damsdorf"
    ],
    "name:ukr_x_preferred":[
        "\u0414\u0430\u043c\u0441\u0434\u043e\u0440\u0444"
    ],
    "name:uzb_x_preferred":[
        "Damsdorf"
    ],
    "name:vie_x_preferred":[
        "Damsdorf"
    ],
    "name:vol_x_preferred":[
        "Damsdorf"
    ],
    "name:war_x_preferred":[
        "Damsdorf"
    ],
    "name:zho_x_preferred":[
        "\u8fbe\u59c6\u65af\u591a\u592b"
    ],
    "wof:name":"Damsdorf",
    "wof:placetype":"neighbourhood"
},
  "geometry": {"coordinates":[12.76137,52.36149],"type":"Point"}
}