{
  "type": "Feature",
  "properties": {
    "gn:admin1_code":"2",
    "gn:admin2_code":"95.0",
    "gn:admin3_code":"9571.0",
    "gn:admin4_code":"9571127.0",
    "gn:asciiname":"Gerersdorf",
    "gn:country_code":"DE",
    "gn:dem":445,
    "gn:feature_class":"P",
    "gn:feature_code":"PPL",
    "gn:name":"Gerersdorf",
    "gn:population":0,
    "gn:timezone":"Europe/Berlin",
    "iso:country":"DE",
    "name:ceb_x_preferred":[
        "Gerersdorf"
    ],
    "name:deu_x_preferred":[
        "Gerersdorf"
    ],
    "name:epo_x_preferred":[
        "Gerersdorf"
    ],
    "name:fas_x_preferred":[
        "\u06af\u0631\u0631\u0633\u062f\u0648\u0631\u0641"
    ],
    "name:fra_x_preferred":[
        "Gerersdorf"
    ],
    "name:hun_x_preferred":[
        "Gerersdorf"
    ],
    "name:ita_x_preferred":[
        "Gerersdorf"
    ],
    "name:kaz_x_preferred":[
        "\u0413\u0435\u0440\u0435\u0440\u0441\u0434\u043e\u0440\u0444"
    ],
    "name:nld_x_preferred":[
        "Gerersdorf"
    ],
    "name:pol_x_preferred":[
        "Gerersdorf"
    ],
    "name:por_x_preferred":[
        "Gerersdorf"
    ],
    "name:rus_x_preferred":[
        "\u0413\u0435\u0440\u0435\u0440\u0441\u0434\u043e\u0440\u0444"
    ],
    "name:slk_x_preferred":[
        "Gerersdorf"
    ],
    "name:spa_x_preferred":[
        "Gerersdorf"
    ],
    "name:swe_x_preferred":[
        "Gerersdorf"
    ],
    "name:uzb_x_preferred":[
        "Gerersdorf"
    ],
    "name:vie_x_preferred":[
        "Gerersdorf"
    ],
    "name:vol_x_preferred":[
        "Gerersdorf"
    ],
    "name:war_x_preferred":[
        "Gerersdorf"
    ],
    "name:zho_x_preferred":[
        "\u683c\u52d2\u5c14\u65af\u591a\u592b"
    ],
    "wof:name":"Gerersdorf",
    "wof:placetype":"neighbourhood"
},
  "geometry": {"coordinates":[10.58514,49.22084],"type":"Point"}
}