{
  "type": "Feature",
  "properties": {
    "gn:admin1_code":"1",
    "gn:admin2_code":"84.0",
    "gn:admin3_code":"8435.0",
    "gn:admin4_code":"8435067.0",
    "gn:asciiname":"Eschle",
    "gn:country_code":"DE",
    "gn:dem":531,
    "gn:feature_class":"P",
    "gn:feature_code":"PPL",
    "gn:name":"Eschle",
    "gn:population":0,
    "gn:timezone":"Europe/Berlin",
    "iso:country":"DE",
    "wof:name":"Eschle",
    "wof:placetype":"neighbourhood"
},
  "geometry": {"coordinates":[9.36667,47.76667],"type":"Point"}
}