{
  "type": "Feature",
  "properties": {
    "gn:country":"DE",
    "gn:fcode":"PPL",
    "gn:population":647,
    "iso:country":"DE",
    "name:ceb_x_preferred":[
        "Prisannewitz"
    ],
    "name:che_x_preferred":[
        "\u041f\u0440\u0438\u0437\u0430\u043d\u043d\u0435\u0432\u0438\u0446"
    ],
    "name:deu_x_preferred":[
        "Prisannewitz"
    ],
    "name:eng_x_preferred":[
        "Prisannewitz"
    ],
    "name:epo_x_preferred":[
        "Prisannewitz"
    ],
    "name:fas_x_preferred":[
        "\u067e\u0631\u06cc\u0632\u0627\u0646\u0648\u06cc\u062a\u0633"
    ],
    "name:fra_x_preferred":[
        "Prisannewitz"
    ],
    "name:nld_x_preferred":[
        "Prisannewitz"
    ],
    "name:ron_x_preferred":[
        "Prisannewitz"
    ],
    "name:rus_x_preferred":[
        "\u041f\u0440\u0438\u0437\u0430\u043d\u043d\u0435\u0432\u0438\u0446"
    ],
    "name:tat_x_preferred":[
        "\u041f\u0440\u0438\u0437\u0430\u043d\u043d\u0435\u0432\u0438\u0446"
    ],
    "name:uzb_x_preferred":[
        "Prisannewitz"
    ],
    "name:vol_x_preferred":[
        "Prisannewitz"
    ],
    "qs_pg:aaroncc":"DE",
    "qs_pg:gn_country":"DE",
    "qs_pg:gn_fcode":"PPL",
    "qs_pg:gn_pop":647,
    "qs_pg:name":"Prisannewitz",
    "qs_pg:name_adm0":"Deutschland",
    "qs_pg:name_adm1":"Mecklenburg-Vorpommern",
    "qs_pg:photos_9r":0,
    "qs_pg:photos_sr":0,
    "qs_pg:pop_sr":2,
    "qs_pg:qs_pg_placetype":"locality",
    "qs_pg:qs_pg_placetype_gp":"Town",
    "qs_pg:woe_adm0":23424829,
    "woe:adm0_id":23424829,
    "woe:name_adm0":"Deutschland",
    "woe:name_adm1":"Mecklenburg-Vorpommern",
    "woe:placetype":"Town",
    "wof:name":"Prisannewitz",
    "wof:placetype":"neighbourhood",
    "wof:population":647
},
  "geometry": {"coordinates":[12.21928,53.98556],"type":"Point"}
}