{
  "type": "Feature",
  "properties": {
    "gn:admin1_code":"6.0",
    "gn:admin2_code":"0.0",
    "gn:admin3_code":"3454.0",
    "gn:admin4_code":"3454041.0",
    "gn:asciiname":"Aschendorf-Moor-Siedlung",
    "gn:country_code":"DE",
    "gn:dem":7,
    "gn:feature_class":"P",
    "gn:feature_code":"PPL",
    "gn:name":"Aschendorf-Moor-Siedlung",
    "gn:population":0,
    "gn:timezone":"Europe/Berlin",
    "iso:country":"DE",
    "name:und_x_variant":[
        "Aschendorf",
        "Aschendorf-Moor-Siedlung"
    ],
    "wof:name":"Aschendorf-Moor-Siedlung",
    "wof:placetype":"neighbourhood"
},
  "geometry": {"coordinates":[7.39947,53.04319],"type":"Point"}
}