{
  "type": "Feature",
  "properties": {
    "gn:admin1_code":"2",
    "gn:admin2_code":"93.0",
    "gn:admin3_code":"9376.0",
    "gn:admin4_code":"9376161.0",
    "gn:asciiname":"Haselbach",
    "gn:country_code":"DE",
    "gn:dem":377,
    "gn:feature_class":"P",
    "gn:feature_code":"PPL",
    "gn:name":"Haselbach",
    "gn:population":0,
    "gn:timezone":"Europe/Berlin",
    "iso:country":"DE",
    "name:ceb_x_preferred":[
        "Haselbach"
    ],
    "name:deu_x_preferred":[
        "Haselbach"
    ],
    "name:epo_x_preferred":[
        "Haselbach"
    ],
    "name:fra_x_preferred":[
        "Haselbach"
    ],
    "name:ita_x_preferred":[
        "Haselbach"
    ],
    "name:nld_x_preferred":[
        "Haselbach"
    ],
    "name:pol_x_preferred":[
        "Haselbach"
    ],
    "name:ron_x_preferred":[
        "Haselbach"
    ],
    "name:rus_x_preferred":[
        "\u0425\u0430\u0437\u0435\u043b\u044c\u0431\u0430\u0445"
    ],
    "name:swe_x_preferred":[
        "Haselbach"
    ],
    "name:vol_x_preferred":[
        "Haselbach"
    ],
    "wof:name":"Haselbach",
    "wof:placetype":"neighbourhood"
},
  "geometry": {"coordinates":[12.03106,49.34246],"type":"Point"}
}