{
  "type": "Feature",
  "properties": {
    "gn:admin1_code":"2",
    "gn:admin2_code":"91.0",
    "gn:admin3_code":"9176.0",
    "gn:admin4_code":"9176164.0",
    "gn:asciiname":"Stadelhofen",
    "gn:country_code":"DE",
    "gn:dem":552,
    "gn:feature_class":"P",
    "gn:feature_code":"PPL",
    "gn:name":"Stadelhofen",
    "gn:population":0,
    "gn:timezone":"Europe/Berlin",
    "iso:country":"DE",
    "wof:name":"Stadelhofen",
    "wof:placetype":"locality"
},
  "geometry": {"coordinates":[11.18872,49.03455],"type":"Point"}
}