{
  "type": "Feature",
  "properties": {
    "iso:country":"DE",
    "name:deu_x_colloquial":[
        "Vode",
        "Voede"
    ],
    "name:deu_x_preferred":[
        "V\u00f6de"
    ],
    "name:hbs_x_preferred":[
        "Bele Vode"
    ],
    "name:hrv_x_preferred":[
        "Bele Vode"
    ],
    "name:nld_x_preferred":[
        "Bele Vode"
    ],
    "name:ron_x_preferred":[
        "Bele Vode"
    ],
    "name:slv_x_preferred":[
        "Bele Vode"
    ],
    "name:ukr_x_preferred":[
        "\u0411\u0435\u043b\u0435 \u0412\u043e\u0434\u0435"
    ],
    "name:unk_x_variant":[
        "V\u00f6de"
    ],
    "qs:gn_fcode":"PPL",
    "qs:gn_local":0,
    "qs:gn_namadm1":"07",
    "qs:gn_name":"Voerde",
    "qs:local_max":1333,
    "qs:local_sum":7580,
    "qs:localhoods":22,
    "qs:name":"V\u00f6de",
    "qs:name_adm0":"Deutschland",
    "qs:name_adm1":"Nordrhein-Westfalen",
    "qs:name_adm2":"Stadtkreis Bochum",
    "qs:name_lau":"Stadtteil Riemke",
    "qs:name_local":"Bochum",
    "qs:photo_max":58,
    "qs:photo_sum":111,
    "qs:placetype":"Suburb",
    "qs:quad_count":15,
    "qs:woe_adm0":23424829,
    "qs:woe_adm1":2345487,
    "qs:woe_adm2":12597004,
    "qs:woe_lau":26821946,
    "qs:woe_local":639679,
    "qs:woe_ver":"7.10.0",
    "wof:lang":[
        "ger"
    ],
    "wof:name":"V\u00f6de",
    "wof:placetype":"neighbourhood"
},
  "geometry": {"coordinates":[7.224353,51.522514],"type":"Point"}
}