{
  "type": "Feature",
  "properties": {
    "gn:admin1_code":"2",
    "gn:admin2_code":"91.0",
    "gn:admin3_code":"9185.0",
    "gn:admin4_code":"9185157.0",
    "gn:asciiname":"Doferhof",
    "gn:country_code":"DE",
    "gn:dem":419,
    "gn:feature_class":"P",
    "gn:feature_code":"PPL",
    "gn:name":"Doferhof",
    "gn:population":0,
    "gn:timezone":"Europe/Berlin",
    "iso:country":"DE",
    "wof:name":"Doferhof",
    "wof:placetype":"neighbourhood"
},
  "geometry": {"coordinates":[11.13699,48.70404],"type":"Point"}
}