{
  "type": "Feature",
  "properties": {
    "gn:admin1_code":"6",
    "gn:admin2_code":"0.0",
    "gn:admin3_code":"3360.0",
    "gn:admin4_code":"3360030.0",
    "gn:asciiname":"Kallenbrock",
    "gn:country_code":"DE",
    "gn:dem":66,
    "gn:feature_class":"P",
    "gn:feature_code":"PPL",
    "gn:name":"Kallenbrock",
    "gn:population":0,
    "gn:timezone":"Europe/Berlin",
    "iso:country":"DE",
    "wof:name":"Kallenbrock",
    "wof:placetype":"neighbourhood"
},
  "geometry": {"coordinates":[10.57262,52.86903],"type":"Point"}
}