{
  "type": "Feature",
  "properties": {
    "gn:gn_country":"DE",
    "gn:gn_fcode":"PPLA4",
    "gn:gn_pop":492,
    "gn:population":492,
    "iso:country":"DE",
    "name:baq_x_preferred":[
        "Birkenbeul"
    ],
    "name:chi_x_preferred":[
        "\u6bd4\u5c14\u80af\u535a\u4f0a\u5c14"
    ],
    "name:dut_x_preferred":[
        "Birkenbeul"
    ],
    "name:eng_x_preferred":[
        "Birkenbeul"
    ],
    "name:epo_x_preferred":[
        "Birkenbeul"
    ],
    "name:fre_x_preferred":[
        "Birkenbeul"
    ],
    "name:ger_x_preferred":[
        "Birkenbeul"
    ],
    "name:hun_x_preferred":[
        "Birkenbeul"
    ],
    "name:ita_x_preferred":[
        "Birkenbeul"
    ],
    "name:jpn_x_preferred":[
        "\u30d3\u30eb\u30b1\u30f3\u30d9\u30a6\u30eb"
    ],
    "name:kaz_x_preferred":[
        "\u0411\u0438\u0440\u043a\u0435\u043d\u0431\u043e\u0439\u043b\u044c"
    ],
    "name:kir_x_preferred":[
        "\u0411\u0438\u0440\u043a\u0435\u043d\u0431\u043e\u0439\u043b\u044c"
    ],
    "name:may_x_preferred":[
        "Birkenbeul"
    ],
    "name:per_x_preferred":[
        "\u0628\u06cc\u0631\u06a9\u0646\u0628\u0644"
    ],
    "name:pol_x_preferred":[
        "Birkenbeul"
    ],
    "name:por_x_preferred":[
        "Birkenbeul"
    ],
    "name:rum_x_preferred":[
        "Birkenbeul"
    ],
    "name:rus_x_preferred":[
        "\u0411\u0438\u0440\u043a\u0435\u043d\u0431\u043e\u0439\u043b\u044c"
    ],
    "name:spa_x_preferred":[
        "Birkenbeul"
    ],
    "name:srp_x_preferred":[
        "\u0411\u0438\u0440\u043a\u0435\u043d\u0431\u043e\u0458\u043b"
    ],
    "name:ukr_x_preferred":[
        "\u0411\u0456\u0440\u043a\u0435\u043d\u0431\u043e\u0439\u043b\u044c"
    ],
    "name:uzb_x_preferred":[
        "Birkenbeul"
    ],
    "name:vie_x_preferred":[
        "Birkenbeul"
    ],
    "name:vol_x_preferred":[
        "Birkenbeul"
    ],
    "name:war_x_preferred":[
        "Birkenbeul"
    ],
    "qs_pg:aaroncc":"DE",
    "qs_pg:gn_country":"DE",
    "qs_pg:gn_fcode":"PPLA4",
    "qs_pg:gn_pop":492,
    "qs_pg:name":"Birkenbeul",
    "qs_pg:photos_9r":0,
    "qs_pg:photos_sr":0,
    "qs_pg:pop_sr":2,
    "qs_pg:qs_pg_placetype":"locality",
    "wof:name":"Birkenbeul",
    "wof:placetype":"locality",
    "wof:population":492
},
  "geometry": {"coordinates":[7.61667,50.73333],"type":"Point"}
}