{
  "type": "Feature",
  "properties": {
    "gn:admin1_code":"7",
    "gn:admin2_code":"59.0",
    "gn:admin3_code":"5958.0",
    "gn:admin4_code":"5958012.0",
    "gn:asciiname":"Scharfenberg",
    "gn:country_code":"DE",
    "gn:dem":437,
    "gn:feature_class":"P",
    "gn:feature_code":"PPL",
    "gn:name":"Scharfenberg",
    "gn:population":0,
    "gn:timezone":"Europe/Berlin",
    "iso:country":"DE",
    "name:ceb_x_preferred":[
        "Scharfenberg"
    ],
    "name:deu_x_preferred":[
        "Scharfenberg"
    ],
    "name:fra_x_preferred":[
        "Scharfenberg"
    ],
    "name:swe_x_preferred":[
        "Scharfenberg"
    ],
    "wof:name":"Scharfenberg",
    "wof:placetype":"neighbourhood"
},
  "geometry": {"coordinates":[8.52942,51.42492],"type":"Point"}
}