{
  "type": "Feature",
  "properties": {
    "gn:admin1_code":"6",
    "gn:admin2_code":"0.0",
    "gn:admin3_code":"3462.0",
    "gn:admin4_code":"3462019.0",
    "gn:asciiname":"Funnixer Neue Mitteldeich",
    "gn:cc2":"DE",
    "gn:country_code":"DE",
    "gn:dem":0,
    "gn:feature_class":"P",
    "gn:feature_code":"PPL",
    "gn:name":"Funnixer Neue Mitteldeich",
    "gn:population":0,
    "gn:timezone":"Europe/Berlin",
    "iso:country":"DE",
    "name:und_x_variant":[
        "Funnixer Neuen-Mitteldeich"
    ],
    "wof:name":"Funnixer Neue Mitteldeich",
    "wof:placetype":"neighbourhood"
},
  "geometry": {"coordinates":[7.79501,53.66707],"type":"Point"}
}