{
  "type": "Feature",
  "properties": {
    "gn:admin1_code":"2",
    "gn:admin2_code":"91.0",
    "gn:admin3_code":"9187.0",
    "gn:admin4_code":"9187122.0",
    "gn:asciiname":"Oberwall",
    "gn:country_code":"DE",
    "gn:dem":550,
    "gn:feature_class":"P",
    "gn:feature_code":"PPL",
    "gn:name":"Oberwall",
    "gn:population":0,
    "gn:timezone":"Europe/Berlin",
    "iso:country":"DE",
    "wof:name":"Oberwall",
    "wof:placetype":"neighbourhood"
},
  "geometry": {"coordinates":[11.94016,47.93699],"type":"Point"}
}