{
  "type": "Feature",
  "properties": {
    "gn:admin1_code":"1",
    "gn:admin2_code":"81.0",
    "gn:admin3_code":"8117.0",
    "gn:admin4_code":"8117007.0",
    "gn:asciiname":"Hausen an der Fils",
    "gn:cc2":"DE",
    "gn:country_code":"DE",
    "gn:dem":462,
    "gn:feature_class":"P",
    "gn:feature_code":"PPL",
    "gn:name":"Hausen an der Fils",
    "gn:population":0,
    "gn:timezone":"Europe/Berlin",
    "iso:country":"DE",
    "name:und_x_variant":[
        "Hausen"
    ],
    "wof:name":"Hausen an der Fils",
    "wof:placetype":"neighbourhood"
},
  "geometry": {"coordinates":[9.76367,48.60738],"type":"Point"}
}