{
  "type": "Feature",
  "properties": {
    "gn:admin1_code":"2",
    "gn:admin2_code":"93.0",
    "gn:admin3_code":"9371.0",
    "gn:admin4_code":"9371122.0",
    "gn:asciiname":"Schleissdorf",
    "gn:country_code":"DE",
    "gn:dem":532,
    "gn:feature_class":"P",
    "gn:feature_code":"PPL",
    "gn:name":"Schlei\u00dfdorf",
    "gn:population":0,
    "gn:timezone":"Europe/Berlin",
    "iso:country":"DE",
    "wof:name":"Schleissdorf",
    "wof:placetype":"neighbourhood"
},
  "geometry": {"coordinates":[12.0241,49.47757],"type":"Point"}
}