{
  "type": "Feature",
  "properties": {
    "gn:admin1_code":"2",
    "gn:admin2_code":"91.0",
    "gn:admin3_code":"9178.0",
    "gn:admin4_code":"9178120.0",
    "gn:asciiname":"Ottenburg",
    "gn:country_code":"DE",
    "gn:dem":471,
    "gn:feature_class":"P",
    "gn:feature_code":"PPL",
    "gn:name":"Ottenburg",
    "gn:population":0,
    "gn:timezone":"Europe/Berlin",
    "iso:country":"DE",
    "name:deu_x_preferred":[
        "Ottenburg"
    ],
    "name:fra_x_preferred":[
        "Ottembourg"
    ],
    "name:nld_x_preferred":[
        "Ottenburg"
    ],
    "wof:name":"Ottenburg",
    "wof:placetype":"neighbourhood"
},
  "geometry": {"coordinates":[11.59641,48.31791],"type":"Point"}
}