{
  "type": "Feature",
  "properties": {
    "gn:admin1_code":"2.0",
    "gn:admin2_code":"93.0",
    "gn:admin3_code":"9377.0",
    "gn:admin4_code":"9377149.0",
    "gn:asciiname":"Roethenbach am Steinwald",
    "gn:country_code":"DE",
    "gn:dem":481,
    "gn:feature_class":"P",
    "gn:feature_code":"PPL",
    "gn:name":"R\u00f6thenbach am Steinwald",
    "gn:population":0,
    "gn:timezone":"Europe/Berlin",
    "iso:country":"DE",
    "wof:name":"Roethenbach am Steinwald",
    "wof:placetype":"neighbourhood"
},
  "geometry": {"coordinates":[12.12689,49.85301],"type":"Point"}
}