{
  "type": "Feature",
  "properties": {
    "gn:admin1_code":"1",
    "gn:admin2_code":"84.0",
    "gn:admin3_code":"8436.0",
    "gn:admin4_code":"8436008.0",
    "gn:asciiname":"Eichbuhl",
    "gn:country_code":"DE",
    "gn:dem":563,
    "gn:feature_class":"P",
    "gn:feature_code":"PPL",
    "gn:name":"Eichb\u00fchl",
    "gn:population":0,
    "gn:timezone":"Europe/Berlin",
    "iso:country":"DE",
    "wof:name":"Eichbuhl",
    "wof:placetype":"neighbourhood"
},
  "geometry": {"coordinates":[9.6707,47.95271],"type":"Point"}
}