{
  "type": "Feature",
  "properties": {
    "gn:admin1_code":"8",
    "gn:admin2_code":"0.0",
    "gn:admin3_code":"7137.0",
    "gn:admin4_code":"7137086.0",
    "gn:asciiname":"Sackenheimerhoefe",
    "gn:country_code":"DE",
    "gn:dem":294,
    "gn:feature_class":"P",
    "gn:feature_code":"PPL",
    "gn:name":"Sackenheimerh\u00f6fe",
    "gn:population":0,
    "gn:timezone":"Europe/Berlin",
    "iso:country":"DE",
    "wof:name":"Sackenheimerhoefe",
    "wof:placetype":"neighbourhood"
},
  "geometry": {"coordinates":[7.41434,50.34249000000001],"type":"Point"}
}