{
  "type": "Feature",
  "properties": {
    "gn:admin1_code":"7.0",
    "gn:admin2_code":"55.0",
    "gn:admin3_code":"5562.0",
    "gn:admin4_code":"5562024.0",
    "gn:asciiname":"Brassert",
    "gn:country_code":"DE",
    "gn:dem":54,
    "gn:feature_class":"P",
    "gn:feature_code":"PPL",
    "gn:name":"Brassert",
    "gn:population":0,
    "gn:timezone":"Europe/Berlin",
    "iso:country":"DE",
    "name:und_x_variant":[
        "Kolonie Brassert",
        "Brassert"
    ],
    "wof:name":"Brassert",
    "wof:placetype":"neighbourhood"
},
  "geometry": {"coordinates":[7.08274,51.66117],"type":"Point"}
}