{
  "type": "Feature",
  "properties": {
    "gn:admin1_code":"11",
    "gn:admin2_code":"0.0",
    "gn:admin3_code":"12068.0",
    "gn:admin4_code":"12068468.0",
    "gn:asciiname":"Eichenfelde",
    "gn:country_code":"DE",
    "gn:dem":70,
    "gn:feature_class":"P",
    "gn:feature_code":"PPL",
    "gn:name":"Eichenfelde",
    "gn:population":0,
    "gn:timezone":"Europe/Berlin",
    "iso:country":"DE",
    "wof:name":"Eichenfelde",
    "wof:placetype":"neighbourhood"
},
  "geometry": {"coordinates":[12.46983,53.21333000000001],"type":"Point"}
}