{
  "type": "Feature",
  "properties": {
    "gn:admin1_code":"5",
    "gn:admin2_code":"64.0",
    "gn:admin3_code":"6435.0",
    "gn:admin4_code":"6435027.0",
    "gn:asciiname":"Geisberg",
    "gn:country_code":"DE",
    "gn:dem":282,
    "gn:feature_class":"P",
    "gn:feature_code":"PPL",
    "gn:name":"Geisberg",
    "gn:population":0,
    "gn:timezone":"Europe/Berlin",
    "iso:country":"DE",
    "wof:name":"Geisberg",
    "wof:placetype":"neighbourhood"
},
  "geometry": {"coordinates":[9.66628,50.31539],"type":"Point"}
}