{
  "type": "Feature",
  "properties": {
    "gn:admin1_code":"1",
    "gn:admin2_code":"84.0",
    "gn:admin3_code":"8436.0",
    "gn:admin4_code":"8436094.0",
    "gn:asciiname":"Stockach",
    "gn:country_code":"DE",
    "gn:dem":663,
    "gn:feature_class":"P",
    "gn:feature_code":"PPL",
    "gn:name":"Stockach",
    "gn:population":0,
    "gn:timezone":"Europe/Berlin",
    "iso:country":"DE",
    "name:als_x_preferred":[
        "Stockach"
    ],
    "name:ara_x_preferred":[
        "\u0634\u062a\u0648\u0643\u0627\u062e"
    ],
    "name:azb_x_preferred":[
        "\u0627\u0634\u062a\u0648\u06a9\u200c\u0622\u062e"
    ],
    "name:ceb_x_preferred":[
        "Stockach"
    ],
    "name:dan_x_preferred":[
        "Stockach"
    ],
    "name:deu_x_preferred":[
        "Stockach"
    ],
    "name:epo_x_preferred":[
        "Stockach"
    ],
    "name:fas_x_preferred":[
        "\u0627\u0634\u062a\u0648\u06a9\u200c\u0622\u062e"
    ],
    "name:fra_x_preferred":[
        "Stockach"
    ],
    "name:hun_x_preferred":[
        "Stockach"
    ],
    "name:ita_x_preferred":[
        "Stockach"
    ],
    "name:kaz_x_preferred":[
        "\u0428\u0442\u043e\u043a\u0430\u0445"
    ],
    "name:kir_x_preferred":[
        "\u0428\u0442\u043e\u043a\u0430\u0445"
    ],
    "name:lat_x_preferred":[
        "Stockach"
    ],
    "name:lmo_x_preferred":[
        "Stockach"
    ],
    "name:msa_x_preferred":[
        "Stockach"
    ],
    "name:nld_x_preferred":[
        "Stockach"
    ],
    "name:pol_x_preferred":[
        "Stockach"
    ],
    "name:por_x_preferred":[
        "Stockach"
    ],
    "name:ron_x_preferred":[
        "Stockach"
    ],
    "name:rus_x_preferred":[
        "\u0428\u0442\u043e\u043a\u0430\u0445"
    ],
    "name:spa_x_preferred":[
        "Stockach"
    ],
    "name:srp_x_preferred":[
        "\u0428\u0442\u043e\u043a\u0430\u0445"
    ],
    "name:swe_x_preferred":[
        "Stockach"
    ],
    "name:ukr_x_preferred":[
        "\u0428\u0442\u043e\u043a\u043a\u0430\u0445"
    ],
    "name:uzb_x_preferred":[
        "Stockach"
    ],
    "name:vol_x_preferred":[
        "Stockach"
    ],
    "name:war_x_preferred":[
        "Stockach"
    ],
    "name:zho_x_preferred":[
        "\u65bd\u6258\u5361\u8d6b"
    ],
    "wof:name":"Stockach",
    "wof:placetype":"neighbourhood"
},
  "geometry": {"coordinates":[9.98333,47.71667],"type":"Point"}
}