{
  "type": "Feature",
  "properties": {
    "gn:admin1_code":"2",
    "gn:admin2_code":"91.0",
    "gn:admin3_code":"9190.0",
    "gn:admin4_code":"9190154.0",
    "gn:asciiname":"Hiebler",
    "gn:country_code":"DE",
    "gn:dem":842,
    "gn:feature_class":"P",
    "gn:feature_code":"PPL",
    "gn:name":"Hiebler",
    "gn:population":0,
    "gn:timezone":"Europe/Berlin",
    "iso:country":"DE",
    "wof:name":"Hiebler",
    "wof:placetype":"neighbourhood"
},
  "geometry": {"coordinates":[10.87934,47.683],"type":"Point"}
}