{
  "type": "Feature",
  "properties": {
    "gn:admin1_code":"7",
    "gn:admin2_code":"57.0",
    "gn:admin3_code":"5770.0",
    "gn:admin4_code":"5770016.0",
    "gn:asciiname":"Holsen",
    "gn:country_code":"DE",
    "gn:dem":125,
    "gn:feature_class":"P",
    "gn:feature_code":"PPL",
    "gn:name":"Holsen",
    "gn:population":0,
    "gn:timezone":"Europe/Berlin",
    "iso:country":"DE",
    "name:msa_x_preferred":[
        "Holsen"
    ],
    "name:nno_x_preferred":[
        "Holsen"
    ],
    "name:nor_x_preferred":[
        "Holsen"
    ],
    "name:pol_x_preferred":[
        "Holsen"
    ],
    "wof:name":"Holsen",
    "wof:placetype":"neighbourhood"
},
  "geometry": {"coordinates":[8.69473,52.28197],"type":"Point"}
}