{
  "type": "Feature",
  "properties": {
    "gn:admin1_code":"6.0",
    "gn:admin2_code":"00",
    "gn:admin3_code":"3354.0",
    "gn:admin4_code":"3354008.0",
    "gn:asciiname":"Zadrau",
    "gn:country_code":"DE",
    "gn:dem":15,
    "gn:feature_class":"P",
    "gn:feature_code":"PPL",
    "gn:name":"Zadrau",
    "gn:population":0,
    "gn:timezone":"Europe/Berlin",
    "iso:country":"DE",
    "wof:name":"Zadrau",
    "wof:placetype":"neighbourhood"
},
  "geometry": {"coordinates":[11.17447,53.04968],"type":"Point"}
}