{
  "type": "Feature",
  "properties": {
    "gn:admin1_code":"2",
    "gn:admin2_code":"91.0",
    "gn:admin3_code":"9171.0",
    "gn:admin4_code":"9171115.0",
    "gn:asciiname":"Steinhausen",
    "gn:country_code":"DE",
    "gn:dem":502,
    "gn:feature_class":"P",
    "gn:feature_code":"PPL",
    "gn:name":"Steinhausen",
    "gn:population":0,
    "gn:timezone":"Europe/Berlin",
    "iso:country":"DE",
    "name:als_x_preferred":[
        "Steinhausen"
    ],
    "name:ceb_x_preferred":[
        "Steinhausen"
    ],
    "name:deu_x_preferred":[
        "Steinhausen"
    ],
    "name:epo_x_preferred":[
        "Steinhausen"
    ],
    "name:eus_x_preferred":[
        "Steinhausen"
    ],
    "name:fra_x_preferred":[
        "Steinhausen"
    ],
    "name:ita_x_preferred":[
        "Steinhausen"
    ],
    "name:nld_x_preferred":[
        "Steinhausen"
    ],
    "name:pol_x_preferred":[
        "Steinhausen"
    ],
    "name:por_x_preferred":[
        "Steinhausen"
    ],
    "name:swe_x_preferred":[
        "Steinhausen"
    ],
    "wof:name":"Steinhausen",
    "wof:placetype":"neighbourhood"
},
  "geometry": {"coordinates":[12.75,48.31667],"type":"Point"}
}