{
  "type": "Feature",
  "properties": {
    "gn:admin1_code":"2",
    "gn:admin2_code":"97.0",
    "gn:admin3_code":"9780.0",
    "gn:admin4_code":"9780116.0",
    "gn:asciiname":"Dietrichs",
    "gn:country_code":"DE",
    "gn:dem":822,
    "gn:feature_class":"P",
    "gn:feature_code":"PPL",
    "gn:name":"Dietrichs",
    "gn:population":0,
    "gn:timezone":"Europe/Berlin",
    "iso:country":"DE",
    "wof:name":"Dietrichs",
    "wof:placetype":"neighbourhood"
},
  "geometry": {"coordinates":[10.2467,47.47943],"type":"Point"}
}