{
  "type": "Feature",
  "properties": {
    "gn:admin1_code":"2",
    "gn:admin2_code":"97.0",
    "gn:admin3_code":"9776.0",
    "gn:admin4_code":"9776127.0",
    "gn:asciiname":"Iringshofen",
    "gn:country_code":"DE",
    "gn:dem":868,
    "gn:feature_class":"P",
    "gn:feature_code":"PPL",
    "gn:name":"Iringshofen",
    "gn:population":0,
    "gn:timezone":"Europe/Berlin",
    "iso:country":"DE",
    "wof:name":"Iringshofen",
    "wof:placetype":"neighbourhood"
},
  "geometry": {"coordinates":[9.9921,47.57257],"type":"Point"}
}