{
  "type": "Feature",
  "properties": {
    "gn:admin1_code":"6",
    "gn:admin2_code":"0.0",
    "gn:admin3_code":"3155.0",
    "gn:admin4_code":"3155011.0",
    "gn:asciiname":"Hoeckelheim",
    "gn:country_code":"DE",
    "gn:dem":123,
    "gn:feature_class":"P",
    "gn:feature_code":"PPL",
    "gn:name":"H\u00f6ckelheim",
    "gn:population":0,
    "gn:timezone":"Europe/Berlin",
    "iso:country":"DE",
    "wof:name":"Hoeckelheim",
    "wof:placetype":"neighbourhood"
},
  "geometry": {"coordinates":[9.96116,51.70104],"type":"Point"}
}