{
  "type": "Feature",
  "properties": {
    "gn:admin1_code":"2",
    "gn:admin2_code":"95.0",
    "gn:admin3_code":"9575.0",
    "gn:admin4_code":"9575124.0",
    "gn:asciiname":"Steinach bei Rothenburg ob der Tauber",
    "gn:country_code":"DE",
    "gn:dem":366,
    "gn:feature_class":"P",
    "gn:feature_code":"PPL",
    "gn:name":"Steinach bei Rothenburg ob der Tauber",
    "gn:population":0,
    "gn:timezone":"Europe/Berlin",
    "iso:country":"DE",
    "name:und_x_variant":[
        "Steinach",
        "Steinach bei Rothenburg ob der Tauber"
    ],
    "wof:name":"Steinach bei Rothenburg ob der Tauber",
    "wof:placetype":"neighbourhood"
},
  "geometry": {"coordinates":[10.27565,49.45275],"type":"Point"}
}