{
  "type": "Feature",
  "properties": {
    "gn:admin1_code":"2",
    "gn:admin2_code":"92.0",
    "gn:admin3_code":"9278.0",
    "gn:admin4_code":"9278146.0",
    "gn:asciiname":"Hausmetting",
    "gn:country_code":"DE",
    "gn:dem":376,
    "gn:feature_class":"P",
    "gn:feature_code":"PPL",
    "gn:name":"Hausmetting",
    "gn:population":0,
    "gn:timezone":"Europe/Berlin",
    "iso:country":"DE",
    "wof:name":"Hausmetting",
    "wof:placetype":"neighbourhood"
},
  "geometry": {"coordinates":[12.45667,48.79822],"type":"Point"}
}