{
  "type": "Feature",
  "properties": {
    "gn:admin1_code":"12",
    "gn:admin2_code":"0.0",
    "gn:admin3_code":"13073.0",
    "gn:admin4_code":"13073003.0",
    "gn:asciiname":"Scharpitz",
    "gn:country_code":"DE",
    "gn:dem":11,
    "gn:feature_class":"P",
    "gn:feature_code":"PPL",
    "gn:name":"Scharpitz",
    "gn:population":0,
    "gn:timezone":"Europe/Berlin",
    "iso:country":"DE",
    "wof:name":"Scharpitz",
    "wof:placetype":"neighbourhood"
},
  "geometry": {"coordinates":[13.15733,54.34185],"type":"Point"}
}