{
  "type": "Feature",
  "properties": {
    "gn:admin1_code":"7.0",
    "gn:admin2_code":"059",
    "gn:admin3_code":"5958.0",
    "gn:admin4_code":"5958016.0",
    "gn:asciiname":"Wenholthausen",
    "gn:country_code":"DE",
    "gn:dem":282,
    "gn:feature_class":"P",
    "gn:feature_code":"PPL",
    "gn:name":"Wenholthausen",
    "gn:population":0,
    "gn:timezone":"Europe/Berlin",
    "iso:country":"DE",
    "wof:name":"Wenholthausen",
    "wof:placetype":"neighbourhood"
},
  "geometry": {"coordinates":[8.18196,51.28513],"type":"Point"}
}