{
  "type": "Feature",
  "properties": {
    "gn:admin1_code":"11",
    "gn:admin2_code":"0.0",
    "gn:admin3_code":"12070.0",
    "gn:admin4_code":"12070149.0",
    "gn:asciiname":"Goerike",
    "gn:country_code":"DE",
    "gn:dem":53,
    "gn:feature_class":"P",
    "gn:feature_code":"PPL",
    "gn:name":"G\u00f6rike",
    "gn:population":0,
    "gn:timezone":"Europe/Berlin",
    "iso:country":"DE",
    "wof:name":"Goerike",
    "wof:placetype":"neighbourhood"
},
  "geometry": {"coordinates":[12.20135,52.94357],"type":"Point"}
}