{
  "type": "Feature",
  "properties": {
    "gn:admin1_code":"7",
    "gn:admin2_code":"53.0",
    "gn:admin3_code":"5366.0",
    "gn:admin4_code":"5366004.0",
    "gn:asciiname":"Kirspenich",
    "gn:country_code":"DE",
    "gn:dem":226,
    "gn:feature_class":"P",
    "gn:feature_code":"PPL",
    "gn:name":"Kirspenich",
    "gn:population":0,
    "gn:timezone":"Europe/Berlin",
    "iso:country":"DE",
    "wof:name":"Kirspenich",
    "wof:placetype":"neighbourhood"
},
  "geometry": {"coordinates":[6.79724,50.60083],"type":"Point"}
}