{
  "type": "Feature",
  "properties": {
    "gn:admin1_code":"14.0",
    "gn:admin2_code":"0.0",
    "gn:admin3_code":"15003.0",
    "gn:admin4_code":"15003000.0",
    "gn:asciiname":"Neu Olvenstedt",
    "gn:country_code":"DE",
    "gn:dem":62,
    "gn:feature_class":"P",
    "gn:feature_code":"PPL",
    "gn:name":"Neu Olvenstedt",
    "gn:population":0,
    "gn:timezone":"Europe/Berlin",
    "iso:country":"DE",
    "wof:name":"Neu Olvenstedt",
    "wof:placetype":"neighbourhood"
},
  "geometry": {"coordinates":[11.58826,52.15124],"type":"Point"}
}