{
  "type": "Feature",
  "properties": {
    "gn:admin1_code":"2",
    "gn:admin2_code":"92.0",
    "gn:admin3_code":"9271.0",
    "gn:admin4_code":"9271111.0",
    "gn:asciiname":"Tabertshausen",
    "gn:country_code":"DE",
    "gn:dem":321,
    "gn:feature_class":"P",
    "gn:feature_code":"PPL",
    "gn:name":"Tabertshausen",
    "gn:population":0,
    "gn:timezone":"Europe/Berlin",
    "iso:country":"DE",
    "wof:name":"Tabertshausen",
    "wof:placetype":"neighbourhood"
},
  "geometry": {"coordinates":[12.87881,48.73457],"type":"Point"}
}