{
  "type": "Feature",
  "properties": {
    "gn:admin1_code":"5.0",
    "gn:admin2_code":"066",
    "gn:admin3_code":"6635.0",
    "gn:admin4_code":"6635008.0",
    "gn:asciiname":"Wethen",
    "gn:country_code":"DE",
    "gn:dem":209,
    "gn:feature_class":"P",
    "gn:feature_code":"PPL",
    "gn:name":"Wethen",
    "gn:population":0,
    "gn:timezone":"Europe/Berlin",
    "iso:country":"DE",
    "wof:name":"Wethen",
    "wof:placetype":"neighbourhood"
},
  "geometry": {"coordinates":[9.07539,51.49154],"type":"Point"}
}