{
  "type": "Feature",
  "properties": {
    "gn:population":1062,
    "iso:country":"DE",
    "name:baq_x_preferred":[
        "Todendorf"
    ],
    "name:ceb_x_preferred":[
        "Todendorf"
    ],
    "name:chi_x_preferred":[
        "\u6258\u767b\u591a\u5c14\u592b"
    ],
    "name:dan_x_preferred":[
        "Todendorf"
    ],
    "name:deu_x_preferred":[
        "Todendorf"
    ],
    "name:dut_x_preferred":[
        "Todendorf"
    ],
    "name:eng_x_preferred":[
        "Todendorf"
    ],
    "name:epo_x_preferred":[
        "Todendorf"
    ],
    "name:eus_x_preferred":[
        "Todendorf"
    ],
    "name:fin_x_preferred":[
        "Todendorf"
    ],
    "name:fra_x_preferred":[
        "Todendorf"
    ],
    "name:fre_x_preferred":[
        "Todendorf"
    ],
    "name:ger_x_preferred":[
        "Todendorf"
    ],
    "name:hbs_x_preferred":[
        "Todendorf"
    ],
    "name:hun_x_preferred":[
        "Todendorf"
    ],
    "name:ita_x_preferred":[
        "Todendorf"
    ],
    "name:jpn_x_preferred":[
        "\u30c8\u30fc\u30c7\u30f3\u30c9\u30eb\u30d5"
    ],
    "name:kaz_x_preferred":[
        "\u0422\u043e\u0434\u0435\u043d\u0434\u043e\u0440\u0444"
    ],
    "name:kir_x_preferred":[
        "\u0422\u043e\u0434\u0435\u043d\u0434\u043e\u0440\u0444"
    ],
    "name:mac_x_preferred":[
        "\u0422\u043e\u0434\u0435\u043d\u0434\u043e\u0440\u0444"
    ],
    "name:may_x_preferred":[
        "Todendorf"
    ],
    "name:mkd_x_preferred":[
        "\u0422\u043e\u0434\u0435\u043d\u0434\u043e\u0440\u0444"
    ],
    "name:msa_x_preferred":[
        "Todendorf"
    ],
    "name:nld_x_preferred":[
        "Todendorf"
    ],
    "name:per_x_preferred":[
        "\u062a\u0648\u062f\u0646\u062f\u0648\u0631\u0641"
    ],
    "name:pol_x_preferred":[
        "Todendorf"
    ],
    "name:por_x_preferred":[
        "Todendorf"
    ],
    "name:ron_x_preferred":[
        "Todendorf"
    ],
    "name:rum_x_preferred":[
        "Todendorf"
    ],
    "name:rus_x_preferred":[
        "\u0422\u043e\u0434\u0435\u043d\u0434\u043e\u0440\u0444"
    ],
    "name:srp_x_preferred":[
        "\u0422\u043e\u0434\u0435\u043d\u0434\u043e\u0440\u0444"
    ],
    "name:swe_x_preferred":[
        "Todendorf"
    ],
    "name:tur_x_preferred":[
        "Todendorf"
    ],
    "name:ukr_x_preferred":[
        "\u0422\u043e\u0434\u0435\u043d\u0434\u043e\u0440\u0444"
    ],
    "name:uzb_x_preferred":[
        "Todendorf"
    ],
    "name:vie_x_preferred":[
        "Todendorf"
    ],
    "name:vol_x_preferred":[
        "Todendorf"
    ],
    "name:war_x_preferred":[
        "Todendorf"
    ],
    "name:zho_x_preferred":[
        "\u6258\u767b\u591a\u592b"
    ],
    "qs:a0":"Bundesrepublik Deutschland",
    "qs:a1":"*Schleswig-Holstein",
    "qs:a1r":"0",
    "qs:a2":"Stormarn",
    "qs:adm0":"Bundesrepublik Deutschland",
    "qs:la_lc":"*",
    "qs:level":"locality",
    "qs:loc":"Todendorf",
    "qs:loc_alt":"Todendorf",
    "qs:pop":0,
    "qs:type":"buffered point",
    "wd:wordcount":35,
    "wof:name":"Todendorf",
    "wof:placetype":"locality",
    "wof:population":1062
},
  "geometry": {"coordinates":[10.349152,53.696649],"type":"Point"}
}