{
  "type": "Feature",
  "properties": {
    "gn:admin1_code":"1",
    "gn:admin2_code":"84.0",
    "gn:admin3_code":"8425.0",
    "gn:admin4_code":"8425033.0",
    "gn:asciiname":"Dettingen",
    "gn:country_code":"DE",
    "gn:dem":503,
    "gn:feature_class":"P",
    "gn:feature_code":"PPL",
    "gn:name":"Dettingen",
    "gn:population":2240,
    "gn:timezone":"Europe/Berlin",
    "iso:country":"DE",
    "name:ceb_x_preferred":[
        "Dettingen"
    ],
    "name:deu_x_preferred":[
        "Dettingen"
    ],
    "name:epo_x_preferred":[
        "Dettingen"
    ],
    "name:fra_x_preferred":[
        "Dettingen"
    ],
    "name:hun_x_preferred":[
        "Dettingen"
    ],
    "name:nld_x_preferred":[
        "Dettingen"
    ],
    "name:pol_x_preferred":[
        "Dettingen"
    ],
    "name:swe_x_preferred":[
        "Dettingen"
    ],
    "wof:name":"Dettingen",
    "wof:placetype":"neighbourhood",
    "wof:population":2240
},
  "geometry": {"coordinates":[9.72161,48.26246],"type":"Point"}
}