{
  "type": "Feature",
  "properties": {
    "gn:admin1_code":"11.0",
    "gn:admin2_code":"00",
    "gn:admin3_code":"12073.0",
    "gn:admin4_code":"12073008.0",
    "gn:asciiname":"Wilmersdorf",
    "gn:country_code":"DE",
    "gn:dem":66,
    "gn:feature_class":"P",
    "gn:feature_code":"PPL",
    "gn:name":"Wilmersdorf",
    "gn:population":0,
    "gn:timezone":"Europe/Berlin",
    "iso:country":"DE",
    "name:bre_x_preferred":[
        "Wilmersdorf"
    ],
    "name:ceb_x_preferred":[
        "Wilmersdorf"
    ],
    "name:dan_x_preferred":[
        "Wilmersdorf"
    ],
    "name:deu_x_preferred":[
        "Berlin-Wilmersdorf"
    ],
    "name:fas_x_preferred":[
        "\u0648\u06cc\u0644\u0645\u0631\u0633\u062f\u0631\u0641"
    ],
    "name:fra_x_preferred":[
        "Berlin-Wilmersdorf"
    ],
    "name:heb_x_preferred":[
        "\u05d5\u05d9\u05dc\u05de\u05e8\u05e1\u05d3\u05d5\u05e8\u05e3"
    ],
    "name:ita_x_preferred":[
        "Wilmersdorf"
    ],
    "name:nld_x_preferred":[
        "Berlin-Wilmersdorf"
    ],
    "name:nor_x_preferred":[
        "Wilmersdorf"
    ],
    "name:pol_x_preferred":[
        "Wilmersdorf"
    ],
    "name:por_x_preferred":[
        "Wilmersdorf"
    ],
    "name:rus_x_preferred":[
        "\u0412\u0438\u043b\u044c\u043c\u0435\u0440\u0441\u0434\u043e\u0440\u0444"
    ],
    "name:swe_x_preferred":[
        "Wilmersdorf"
    ],
    "name:tur_x_preferred":[
        "Wilmersdorf"
    ],
    "name:zho_x_preferred":[
        "\u7ef4\u5c14\u9ed8\u65af\u591a\u592b"
    ],
    "wof:name":"Wilmersdorf",
    "wof:placetype":"neighbourhood"
},
  "geometry": {"coordinates":[13.90612,53.11093],"type":"Point"}
}