{
  "type": "Feature",
  "properties": {
    "gn:admin1_code":"2",
    "gn:admin2_code":"93.0",
    "gn:admin3_code":"9375.0",
    "gn:admin4_code":"9375156.0",
    "gn:asciiname":"Schirndorf",
    "gn:country_code":"DE",
    "gn:dem":347,
    "gn:feature_class":"P",
    "gn:feature_code":"PPL",
    "gn:name":"Schirndorf",
    "gn:population":0,
    "gn:timezone":"Europe/Berlin",
    "iso:country":"DE",
    "wof:name":"Schirndorf",
    "wof:placetype":"neighbourhood"
},
  "geometry": {"coordinates":[11.99089,49.17898],"type":"Point"}
}