{
  "type": "Feature",
  "properties": {
    "gn:admin1_code":"5",
    "gn:admin2_code":"65.0",
    "gn:admin3_code":"6531.0",
    "gn:admin4_code":"6531017.0",
    "gn:asciiname":"Mainzlar",
    "gn:country_code":"DE",
    "gn:dem":197,
    "gn:feature_class":"P",
    "gn:feature_code":"PPL",
    "gn:name":"Mainzlar",
    "gn:population":0,
    "gn:timezone":"Europe/Berlin",
    "iso:country":"DE",
    "wof:name":"Mainzlar",
    "wof:placetype":"neighbourhood"
},
  "geometry": {"coordinates":[8.74579,50.66307000000001],"type":"Point"}
}