{
  "type": "Feature",
  "properties": {
    "gn:admin1_code":"2",
    "gn:admin2_code":"91.0",
    "gn:admin3_code":"9173.0",
    "gn:admin4_code":"9173123.0",
    "gn:asciiname":"Bruckner",
    "gn:country_code":"DE",
    "gn:dem":600,
    "gn:feature_class":"P",
    "gn:feature_code":"PPL",
    "gn:name":"Bruckner",
    "gn:population":0,
    "gn:timezone":"Europe/Berlin",
    "iso:country":"DE",
    "wof:name":"Bruckner",
    "wof:placetype":"neighbourhood"
},
  "geometry": {"coordinates":[11.41299,47.83442],"type":"Point"}
}