{
  "type": "Feature",
  "properties": {
    "gn:admin1_code":"12",
    "gn:admin2_code":"0.0",
    "gn:admin3_code":"13073.0",
    "gn:admin4_code":"13073027.0",
    "gn:asciiname":"Rosengarten",
    "gn:country_code":"DE",
    "gn:dem":5,
    "gn:feature_class":"P",
    "gn:feature_code":"PPL",
    "gn:name":"Rosengarten",
    "gn:population":0,
    "gn:timezone":"Europe/Berlin",
    "iso:country":"DE",
    "name:ceb_x_preferred":[
        "Rosengarten"
    ],
    "name:deu_x_preferred":[
        "Rosengarten"
    ],
    "name:epo_x_preferred":[
        "Rosengarten"
    ],
    "name:fra_x_preferred":[
        "Rosengarten"
    ],
    "name:hun_x_preferred":[
        "Rosengarten"
    ],
    "name:jpn_x_preferred":[
        "\u30ed\u30fc\u30bc\u30f3\u30ac\u30eb\u30c6\u30f3"
    ],
    "name:nld_x_preferred":[
        "Rosengarten"
    ],
    "name:pol_x_preferred":[
        "Rosengarten"
    ],
    "name:por_x_preferred":[
        "Rosengarten"
    ],
    "name:rus_x_preferred":[
        "\u0420\u043e\u0437\u0435\u043d\u0433\u0430\u0440\u0442\u0435\u043d"
    ],
    "name:swe_x_preferred":[
        "Rosengarten"
    ],
    "name:vol_x_preferred":[
        "Rosengarten"
    ],
    "wof:name":"Rosengarten",
    "wof:placetype":"neighbourhood"
},
  "geometry": {"coordinates":[13.38171,54.30836],"type":"Point"}
}