{
  "type": "Feature",
  "properties": {
    "gn:admin1_code":"6",
    "gn:admin2_code":"0.0",
    "gn:admin3_code":"3355.0",
    "gn:admin4_code":"3355025.0",
    "gn:asciiname":"Kovahl",
    "gn:country_code":"DE",
    "gn:dem":72,
    "gn:feature_class":"P",
    "gn:feature_code":"PPL",
    "gn:name":"Kovahl",
    "gn:population":0,
    "gn:timezone":"Europe/Berlin",
    "iso:country":"DE",
    "wof:name":"Kovahl",
    "wof:placetype":"neighbourhood"
},
  "geometry": {"coordinates":[10.85923,53.18293000000001],"type":"Point"}
}