{
  "type": "Feature",
  "properties": {
    "gn:gn_country":"DE",
    "gn:gn_fcode":"PPLA4",
    "gn:gn_pop":600,
    "gn:population":600,
    "iso:country":"DE",
    "name:baq_x_preferred":[
        "Wiesbaum"
    ],
    "name:chi_x_preferred":[
        "\u7ef4\u65af\u9c8d\u59c6"
    ],
    "name:dut_x_preferred":[
        "Wiesbaum"
    ],
    "name:eng_x_preferred":[
        "Wiesbaum"
    ],
    "name:epo_x_preferred":[
        "Wiesbaum"
    ],
    "name:fre_x_preferred":[
        "Wiesbaum"
    ],
    "name:ger_x_preferred":[
        "Wiesbaum"
    ],
    "name:hun_x_preferred":[
        "Wiesbaum"
    ],
    "name:ita_x_preferred":[
        "Wiesbaum"
    ],
    "name:jpn_x_preferred":[
        "\u30f4\u30a3\u30fc\u30b9\u30d0\u30a6\u30e0"
    ],
    "name:kaz_x_preferred":[
        "\u0412\u0438\u0441\u0431\u0430\u0443\u043c"
    ],
    "name:kir_x_preferred":[
        "\u0412\u0438\u0441\u0431\u0430\u0443\u043c"
    ],
    "name:may_x_preferred":[
        "Wiesbaum"
    ],
    "name:per_x_preferred":[
        "\u0648\u06cc\u0633\u0628\u0627\u0648\u0645"
    ],
    "name:pol_x_preferred":[
        "Wiesbaum"
    ],
    "name:por_x_preferred":[
        "Wiesbaum"
    ],
    "name:rum_x_preferred":[
        "Wiesbaum"
    ],
    "name:rus_x_preferred":[
        "\u0412\u0438\u0441\u0431\u0430\u0443\u043c"
    ],
    "name:srp_x_preferred":[
        "\u0412\u0438\u0441\u0431\u0430\u0443\u043c"
    ],
    "name:ukr_x_preferred":[
        "\u0412\u0456\u0441\u0431\u0430\u0443\u043c"
    ],
    "name:uzb_x_preferred":[
        "Wiesbaum"
    ],
    "name:vie_x_preferred":[
        "Wiesbaum"
    ],
    "name:vol_x_preferred":[
        "Wiesbaum"
    ],
    "name:war_x_preferred":[
        "Welcherath"
    ],
    "qs_pg:aaroncc":"DE",
    "qs_pg:gn_country":"DE",
    "qs_pg:gn_fcode":"PPLA4",
    "qs_pg:gn_pop":600,
    "qs_pg:name":"Wiesbaum",
    "qs_pg:photos_9r":0,
    "qs_pg:photos_sr":0,
    "qs_pg:pop_sr":2,
    "qs_pg:qs_pg_placetype":"locality",
    "wof:name":"Wiesbaum",
    "wof:placetype":"locality",
    "wof:population":600
},
  "geometry": {"coordinates":[6.66667,50.33333],"type":"Point"}
}