{
  "type": "Feature",
  "properties": {
    "gn:admin1_code":"13",
    "gn:admin2_code":"0.0",
    "gn:admin3_code":"14729.0",
    "gn:admin4_code":"14729170.0",
    "gn:asciiname":"Kleinstolpen",
    "gn:country_code":"DE",
    "gn:dem":142,
    "gn:feature_class":"P",
    "gn:feature_code":"PPL",
    "gn:name":"Kleinstolpen",
    "gn:population":0,
    "gn:timezone":"Europe/Berlin",
    "iso:country":"DE",
    "wof:name":"Kleinstolpen",
    "wof:placetype":"neighbourhood"
},
  "geometry": {"coordinates":[12.31667,51.13333],"type":"Point"}
}