{
  "type": "Feature",
  "properties": {
    "gn:admin1_code":"9",
    "gn:admin2_code":"0.0",
    "gn:admin3_code":"10043.0",
    "gn:admin4_code":"10043112.0",
    "gn:asciiname":"Huettigweiler",
    "gn:country_code":"DE",
    "gn:dem":289,
    "gn:feature_class":"P",
    "gn:feature_code":"PPL",
    "gn:name":"H\u00fcttigweiler",
    "gn:population":0,
    "gn:timezone":"Europe/Berlin",
    "iso:country":"DE",
    "name:und_x_variant":[
        "H\u00fcttig-Ra\u00dfweiler",
        "H\u00fcttigweiler-Ra\u00dfweiler",
        "H\u00fcttigweiler"
    ],
    "wof:name":"Huettigweiler",
    "wof:placetype":"neighbourhood"
},
  "geometry": {"coordinates":[7.0729,49.38985],"type":"Point"}
}