{
  "type": "Feature",
  "properties": {
    "gn:admin1_code":"2",
    "gn:admin2_code":"94.0",
    "gn:admin3_code":"9477.0",
    "gn:admin4_code":"9477156.0",
    "gn:asciiname":"Romersreuth",
    "gn:country_code":"DE",
    "gn:dem":553,
    "gn:feature_class":"P",
    "gn:feature_code":"PPL",
    "gn:name":"R\u00f6mersreuth",
    "gn:population":0,
    "gn:timezone":"Europe/Berlin",
    "iso:country":"DE",
    "wof:name":"Romersreuth",
    "wof:placetype":"neighbourhood"
},
  "geometry": {"coordinates":[11.52621,50.19778],"type":"Point"}
}