{
  "type": "Feature",
  "properties": {
    "gn:admin1_code":"2.0",
    "gn:admin2_code":"93.0",
    "gn:admin3_code":"9375.0",
    "gn:admin4_code":"9375196.0",
    "gn:asciiname":"Allersdorf",
    "gn:country_code":"DE",
    "gn:dem":402,
    "gn:feature_class":"P",
    "gn:feature_code":"PPL",
    "gn:name":"Allersdorf",
    "gn:population":0,
    "gn:timezone":"Europe/Berlin",
    "iso:country":"DE",
    "wof:name":"Allersdorf",
    "wof:placetype":"neighbourhood"
},
  "geometry": {"coordinates":[12.12778,48.8014],"type":"Point"}
}