{
  "type": "Feature",
  "properties": {
    "gn:admin1_code":"1",
    "gn:admin2_code":"82.0",
    "gn:admin3_code":"8211.0",
    "gn:admin4_code":"8211000.0",
    "gn:asciiname":"Neuweier",
    "gn:country_code":"DE",
    "gn:dem":178,
    "gn:feature_class":"P",
    "gn:feature_code":"PPL",
    "gn:name":"Neuweier",
    "gn:population":0,
    "gn:timezone":"Europe/Berlin",
    "iso:country":"DE",
    "wof:name":"Neuweier",
    "wof:placetype":"neighbourhood"
},
  "geometry": {"coordinates":[8.18372,48.72139],"type":"Point"}
}