{
  "type": "Feature",
  "properties": {
    "gn:admin1_code":"2",
    "gn:admin2_code":"91.0",
    "gn:admin3_code":"9189.0",
    "gn:admin4_code":"9189157.0",
    "gn:asciiname":"Hilling",
    "gn:country_code":"DE",
    "gn:dem":534,
    "gn:feature_class":"P",
    "gn:feature_code":"PPL",
    "gn:name":"Hilling",
    "gn:population":0,
    "gn:timezone":"Europe/Berlin",
    "iso:country":"DE",
    "name:deu_x_preferred":[
        "Dammkultur"
    ],
    "name:fra_x_preferred":[
        "Buttage"
    ],
    "name:hye_x_preferred":[
        "\u0532\u0578\u0582\u056f\u056c\u056b\u0581"
    ],
    "name:ita_x_preferred":[
        "Rincalzatura"
    ],
    "name:nno_x_preferred":[
        "Hypping"
    ],
    "name:nor_x_preferred":[
        "Hyppe"
    ],
    "name:rus_x_preferred":[
        "\u041e\u043a\u0443\u0447\u0438\u0432\u0430\u043d\u0438\u0435"
    ],
    "wof:name":"Hilling",
    "wof:placetype":"neighbourhood"
},
  "geometry": {"coordinates":[12.6075,48.01915],"type":"Point"}
}