{
  "type": "Feature",
  "properties": {
    "gn:admin1_code":"2",
    "gn:admin2_code":"97.0",
    "gn:admin3_code":"9772.0",
    "gn:admin4_code":"9772141.0",
    "gn:asciiname":"Reitenbuch",
    "gn:country_code":"DE",
    "gn:dem":508,
    "gn:feature_class":"P",
    "gn:feature_code":"PPL",
    "gn:name":"Reitenbuch",
    "gn:population":0,
    "gn:timezone":"Europe/Berlin",
    "iso:country":"DE",
    "wof:name":"Reitenbuch",
    "wof:placetype":"neighbourhood"
},
  "geometry": {"coordinates":[10.67389,48.31625],"type":"Point"}
}