{
  "type": "Feature",
  "properties": {
    "gn:admin1_code":"6",
    "gn:admin2_code":"0.0",
    "gn:admin3_code":"3457.0",
    "gn:admin4_code":"3457022.0",
    "gn:asciiname":"Steenfelderkloster",
    "gn:country_code":"DE",
    "gn:dem":1,
    "gn:feature_class":"P",
    "gn:feature_code":"PPL",
    "gn:name":"Steenfelderkloster",
    "gn:population":0,
    "gn:timezone":"Europe/Berlin",
    "iso:country":"DE",
    "wof:name":"Steenfelderkloster",
    "wof:placetype":"neighbourhood"
},
  "geometry": {"coordinates":[7.4314,53.12851],"type":"Point"}
}