{
  "type": "Feature",
  "properties": {
    "gn:admin1_code":"2",
    "gn:admin2_code":"97.0",
    "gn:admin3_code":"9777.0",
    "gn:admin4_code":"9777149.0",
    "gn:asciiname":"Hennenschwang",
    "gn:country_code":"DE",
    "gn:dem":806,
    "gn:feature_class":"P",
    "gn:feature_code":"PPL",
    "gn:name":"Hennenschwang",
    "gn:population":0,
    "gn:timezone":"Europe/Berlin",
    "iso:country":"DE",
    "wof:name":"Hennenschwang",
    "wof:placetype":"neighbourhood"
},
  "geometry": {"coordinates":[10.60604,47.69525],"type":"Point"}
}