{
  "type": "Feature",
  "properties": {
    "gn:admin1_code":"8",
    "gn:admin2_code":"0.0",
    "gn:admin3_code":"7133.0",
    "gn:admin4_code":"7133099.0",
    "gn:asciiname":"Unterhub",
    "gn:country_code":"DE",
    "gn:dem":360,
    "gn:feature_class":"P",
    "gn:feature_code":"PPL",
    "gn:name":"Unterhub",
    "gn:population":0,
    "gn:timezone":"Europe/Berlin",
    "iso:country":"DE",
    "wof:name":"Unterhub",
    "wof:placetype":"neighbourhood"
},
  "geometry": {"coordinates":[7.71541,49.90600000000001],"type":"Point"}
}