{
  "type": "Feature",
  "properties": {
    "gn:admin1_code":"11.0",
    "gn:admin2_code":"0.0",
    "gn:admin3_code":"12064.0",
    "gn:admin4_code":"12064061.0",
    "gn:asciiname":"Bochowsloos",
    "gn:cc2":"DE",
    "gn:country_code":"DE",
    "gn:dem":4,
    "gn:feature_class":"P",
    "gn:feature_code":"PPL",
    "gn:name":"Bochowsloos",
    "gn:population":0,
    "gn:timezone":"Europe/Berlin",
    "iso:country":"DE",
    "name:und_x_variant":[
        "Bochowslos"
    ],
    "wof:name":"Bochowsloos",
    "wof:placetype":"neighbourhood"
},
  "geometry": {"coordinates":[14.1873,52.7102],"type":"Point"}
}