{
  "type": "Feature",
  "properties": {
    "gn:admin1_code":"13",
    "gn:admin2_code":"0.0",
    "gn:admin3_code":"14523.0",
    "gn:admin4_code":"14523330.0",
    "gn:asciiname":"Rentzmuehlenhaeuser",
    "gn:country_code":"DE",
    "gn:dem":310,
    "gn:feature_class":"P",
    "gn:feature_code":"PPL",
    "gn:name":"Rentzm\u00fchlenh\u00e4user",
    "gn:population":0,
    "gn:timezone":"Europe/Berlin",
    "iso:country":"DE",
    "wof:name":"Rentzmuehlenhaeuser",
    "wof:placetype":"neighbourhood"
},
  "geometry": {"coordinates":[12.15965,50.57208],"type":"Point"}
}