{
  "type": "Feature",
  "properties": {
    "gn:admin1_code":"13",
    "gn:admin2_code":"0.0",
    "gn:admin3_code":"14625.0",
    "gn:admin4_code":"14625020.0",
    "gn:asciiname":"Niederuhna",
    "gn:country_code":"DE",
    "gn:dem":196,
    "gn:feature_class":"P",
    "gn:feature_code":"PPL",
    "gn:name":"Niederuhna",
    "gn:population":0,
    "gn:timezone":"Europe/Berlin",
    "iso:country":"DE",
    "name:hsb_x_preferred":[
        "Delni Wunjow"
    ],
    "wof:name":"Niederuhna",
    "wof:placetype":"neighbourhood"
},
  "geometry": {"coordinates":[14.35496,51.20778],"type":"Point"}
}