{
  "type": "Feature",
  "properties": {
    "gn:admin1_code":"1",
    "gn:admin2_code":"81.0",
    "gn:admin3_code":"8118.0",
    "gn:admin4_code":"8118073.0",
    "gn:asciiname":"Horrheim",
    "gn:country_code":"DE",
    "gn:dem":225,
    "gn:feature_class":"P",
    "gn:feature_code":"PPL",
    "gn:name":"Horrheim",
    "gn:population":0,
    "gn:timezone":"Europe/Berlin",
    "iso:country":"DE",
    "wof:name":"Horrheim",
    "wof:placetype":"neighbourhood"
},
  "geometry": {"coordinates":[8.98836,48.97769],"type":"Point"}
}