{
  "type": "Feature",
  "properties": {
    "gn:admin1_code":"2.0",
    "gn:admin2_code":"091",
    "gn:admin3_code":"9177.0",
    "gn:admin4_code":"9177115.0",
    "gn:asciiname":"Zeilhofen",
    "gn:country_code":"DE",
    "gn:dem":457,
    "gn:feature_class":"P",
    "gn:feature_code":"PPL",
    "gn:name":"Zeilhofen",
    "gn:population":0,
    "gn:timezone":"Europe/Berlin",
    "iso:country":"DE",
    "wof:name":"Zeilhofen",
    "wof:placetype":"neighbourhood"
},
  "geometry": {"coordinates":[12.10697,48.28186],"type":"Point"}
}