{
  "type": "Feature",
  "properties": {
    "gn:admin1_code":"2.0",
    "gn:admin2_code":"93.0",
    "gn:admin3_code":"9377.0",
    "gn:admin4_code":"9377117.0",
    "gn:asciiname":"Bodenreuth",
    "gn:country_code":"DE",
    "gn:dem":519,
    "gn:feature_class":"P",
    "gn:feature_code":"PPL",
    "gn:name":"Bodenreuth",
    "gn:population":0,
    "gn:timezone":"Europe/Berlin",
    "iso:country":"DE",
    "wof:name":"Bodenreuth",
    "wof:placetype":"neighbourhood"
},
  "geometry": {"coordinates":[12.22493,49.83561],"type":"Point"}
}