{
  "type": "Feature",
  "properties": {
    "gn:admin1_code":"6",
    "gn:admin2_code":"0.0",
    "gn:admin3_code":"3361.0",
    "gn:admin4_code":"3361005.0",
    "gn:asciiname":"Schaafwinkel",
    "gn:country_code":"DE",
    "gn:dem":44,
    "gn:feature_class":"P",
    "gn:feature_code":"PPL",
    "gn:name":"Schaafwinkel",
    "gn:population":0,
    "gn:timezone":"Europe/Berlin",
    "iso:country":"DE",
    "wof:name":"Schaafwinkel",
    "wof:placetype":"neighbourhood"
},
  "geometry": {"coordinates":[9.45,52.96666999999999],"type":"Point"}
}