{
  "type": "Feature",
  "properties": {
    "gn:admin1_code":"7",
    "gn:admin2_code":"59.0",
    "gn:admin3_code":"5958.0",
    "gn:admin4_code":"5958024.0",
    "gn:asciiname":"Essentho",
    "gn:country_code":"DE",
    "gn:dem":417,
    "gn:feature_class":"P",
    "gn:feature_code":"PPL",
    "gn:name":"Essentho",
    "gn:population":0,
    "gn:timezone":"Europe/Berlin",
    "iso:country":"DE",
    "name:osx_x_preferred":[
        "Asnithi"
    ],
    "wof:name":"Essentho",
    "wof:placetype":"neighbourhood"
},
  "geometry": {"coordinates":[8.83161,51.48041],"type":"Point"}
}