{
  "type": "Feature",
  "properties": {
    "gn:admin1_code":"1",
    "gn:admin2_code":"82.0",
    "gn:admin3_code":"8226.0",
    "gn:admin4_code":"8226032.0",
    "gn:asciiname":"Insultheimerhof",
    "gn:country_code":"DE",
    "gn:dem":97,
    "gn:feature_class":"P",
    "gn:feature_code":"PPL",
    "gn:name":"Insultheimerhof",
    "gn:population":0,
    "gn:timezone":"Europe/Berlin",
    "iso:country":"DE",
    "name:und_x_variant":[
        "Isultheimerhof",
        "Insultheimerhof"
    ],
    "wof:name":"Insultheimerhof",
    "wof:placetype":"neighbourhood"
},
  "geometry": {"coordinates":[8.49998,49.3192],"type":"Point"}
}