{
  "type": "Feature",
  "properties": {
    "gn:admin1_code":"2",
    "gn:admin2_code":"93.0",
    "gn:admin3_code":"9376.0",
    "gn:admin4_code":"9376149.0",
    "gn:asciiname":"Michelsberg",
    "gn:country_code":"DE",
    "gn:dem":397,
    "gn:feature_class":"P",
    "gn:feature_code":"PPL",
    "gn:name":"Michelsberg",
    "gn:population":0,
    "gn:timezone":"Europe/Berlin",
    "iso:country":"DE",
    "name:ceb_x_preferred":[
        "Michelsberg"
    ],
    "name:deu_x_preferred":[
        "Michelsberg"
    ],
    "name:epo_x_preferred":[
        "Michelsberg"
    ],
    "name:ron_x_preferred":[
        "Michelsberg"
    ],
    "name:swe_x_preferred":[
        "Michelsberg"
    ],
    "wof:name":"Michelsberg",
    "wof:placetype":"neighbourhood"
},
  "geometry": {"coordinates":[12.31751,49.18814],"type":"Point"}
}