{
  "type": "Feature",
  "properties": {
    "gn:admin1_code":"6.0",
    "gn:admin2_code":"0.0",
    "gn:admin3_code":"3354.0",
    "gn:admin4_code":"3354022.0",
    "gn:asciiname":"Billerbeck",
    "gn:country_code":"DE",
    "gn:dem":44,
    "gn:feature_class":"P",
    "gn:feature_code":"PPL",
    "gn:name":"Billerbeck",
    "gn:population":0,
    "gn:timezone":"Europe/Berlin",
    "iso:country":"DE",
    "name:ara_x_preferred":[
        "\u0628\u064a\u0644\u0631\u0628\u0643"
    ],
    "name:azb_x_preferred":[
        "\u0628\u06cc\u0644\u0631\u0628\u06a9"
    ],
    "name:ceb_x_preferred":[
        "Billerbeck"
    ],
    "name:deu_x_preferred":[
        "Billerbeck"
    ],
    "name:epo_x_preferred":[
        "Billerbeck"
    ],
    "name:eus_x_preferred":[
        "Billerbeck"
    ],
    "name:fas_x_preferred":[
        "\u0628\u06cc\u0644\u0631\u0628\u06a9"
    ],
    "name:fra_x_preferred":[
        "Billerbeck"
    ],
    "name:hun_x_preferred":[
        "Billerbeck"
    ],
    "name:ita_x_preferred":[
        "Billerbeck"
    ],
    "name:kaz_x_preferred":[
        "\u0411\u0438\u043b\u043b\u0435\u0440\u0431\u0435\u043a"
    ],
    "name:kir_x_preferred":[
        "\u0411\u0438\u043b\u043b\u0435\u0440\u0431\u0435\u043a"
    ],
    "name:lim_x_preferred":[
        "Billerbeck"
    ],
    "name:msa_x_preferred":[
        "Billerbeck"
    ],
    "name:nds_x_preferred":[
        "Billerbi\u00ebk"
    ],
    "name:nld_x_preferred":[
        "Billerbeck"
    ],
    "name:pol_x_preferred":[
        "Billerbeck"
    ],
    "name:por_x_preferred":[
        "Billerbeck"
    ],
    "name:ron_x_preferred":[
        "Billerbeck"
    ],
    "name:rus_x_preferred":[
        "\u0411\u0438\u043b\u043b\u0435\u0440\u0431\u0435\u043a"
    ],
    "name:spa_x_preferred":[
        "Billerbeck"
    ],
    "name:srp_x_preferred":[
        "\u0411\u0438\u043b\u0435\u0440\u0431\u0435\u043a"
    ],
    "name:swe_x_preferred":[
        "Billerbeck"
    ],
    "name:tur_x_preferred":[
        "Billerbeck"
    ],
    "name:ukr_x_preferred":[
        "\u0411\u0456\u043b\u043b\u0435\u0440\u0431\u0435\u043a"
    ],
    "name:uzb_x_preferred":[
        "Billerbeck"
    ],
    "name:vol_x_preferred":[
        "Billerbeck"
    ],
    "name:war_x_preferred":[
        "Billerbeck"
    ],
    "name:zho_x_preferred":[
        "\u6bd4\u52d2\u8d1d\u514b"
    ],
    "wof:name":"Billerbeck",
    "wof:placetype":"neighbourhood"
},
  "geometry": {"coordinates":[10.87355,52.87431],"type":"Point"}
}