{
  "type": "Feature",
  "properties": {
    "gn:admin1_code":"13",
    "gn:admin2_code":"0.0",
    "gn:admin3_code":"14626.0",
    "gn:admin4_code":"14626180.0",
    "gn:asciiname":"Ninive",
    "gn:country_code":"DE",
    "gn:dem":334,
    "gn:feature_class":"P",
    "gn:feature_code":"PPL",
    "gn:name":"Ninive",
    "gn:population":0,
    "gn:timezone":"Europe/Berlin",
    "iso:country":"DE",
    "name:deu_x_preferred":[
        "Ninive"
    ],
    "name:und_x_variant":[
        "Neuoberruppersdorf"
    ],
    "wof:name":"Ninive",
    "wof:placetype":"neighbourhood"
},
  "geometry": {"coordinates":[14.71063,50.99087],"type":"Point"}
}