{
  "type": "Feature",
  "properties": {
    "gn:admin1_code":"5",
    "gn:admin2_code":"64.0",
    "gn:admin3_code":"6431.0",
    "gn:admin4_code":"6431018.0",
    "gn:asciiname":"Darsberg",
    "gn:country_code":"DE",
    "gn:dem":327,
    "gn:feature_class":"P",
    "gn:feature_code":"PPL",
    "gn:name":"Darsberg",
    "gn:population":0,
    "gn:timezone":"Europe/Berlin",
    "iso:country":"DE",
    "name:deu_x_preferred":[
        "Darsberg"
    ],
    "name:und_x_variant":[
        "D\u00fcrsburg"
    ],
    "wof:name":"Darsberg",
    "wof:placetype":"neighbourhood"
},
  "geometry": {"coordinates":[8.84907,49.41942],"type":"Point"}
}