{
  "type": "Feature",
  "properties": {
    "gn:country":"DE",
    "gn:fcode":"PPL",
    "gn:population":0,
    "iso:country":"DE",
    "name:bre_x_preferred":[
        "Neustadt"
    ],
    "name:cat_x_preferred":[
        "Neustadt"
    ],
    "name:ceb_x_preferred":[
        "Neustadt"
    ],
    "name:dan_x_preferred":[
        "Neustadt"
    ],
    "name:deu_x_preferred":[
        "Neustadt"
    ],
    "name:epo_x_preferred":[
        "Neustadt"
    ],
    "name:fas_x_preferred":[
        "\u0646\u0648\u06cc\u200c\u0627\u0634\u062a\u0627\u062a"
    ],
    "name:fin_x_preferred":[
        "Neustadt"
    ],
    "name:fra_x_preferred":[
        "Neustadt"
    ],
    "name:heb_x_preferred":[
        "\u05e0\u05d5\u05d9\u05e9\u05d8\u05d0\u05d3\u05d8"
    ],
    "name:ita_x_preferred":[
        "Neustadt"
    ],
    "name:jpn_x_preferred":[
        "\u30ce\u30a4\u30b7\u30e5\u30bf\u30c3\u30c8"
    ],
    "name:lmo_x_preferred":[
        "Neustadt"
    ],
    "name:mkd_x_preferred":[
        "\u041d\u043e\u0458\u0448\u0442\u0430\u0442"
    ],
    "name:nds_x_preferred":[
        "Neustadt"
    ],
    "name:nld_x_preferred":[
        "Neustadt"
    ],
    "name:nor_x_preferred":[
        "Neustadt"
    ],
    "name:pol_x_preferred":[
        "Neustadt"
    ],
    "name:por_x_preferred":[
        "Neustadt"
    ],
    "name:ron_x_preferred":[
        "Neustadt"
    ],
    "name:rus_x_preferred":[
        "\u041d\u043e\u0439\u0448\u0442\u0430\u0434\u0442"
    ],
    "name:spa_x_preferred":[
        "Neustadt"
    ],
    "name:swe_x_preferred":[
        "Neustadt"
    ],
    "name:ukr_x_preferred":[
        "\u041d\u043e\u0439\u0448\u0442\u0430\u0434\u0442"
    ],
    "name:vol_x_preferred":[
        "Neustadt"
    ],
    "qs_pg:aaroncc":"DE",
    "qs_pg:gn_country":"DE",
    "qs_pg:gn_fcode":"PPL",
    "qs_pg:gn_pop":0,
    "qs_pg:name":"Neustadt",
    "qs_pg:name_adm0":"Deutschland",
    "qs_pg:name_adm1":"Sachsen",
    "qs_pg:photos":1028,
    "qs_pg:photos_1k":208,
    "qs_pg:photos_9k":5,
    "qs_pg:photos_9r":7,
    "qs_pg:photos_all":1028,
    "qs_pg:photos_sr":11,
    "qs_pg:pop_sr":0,
    "qs_pg:qs_pg_placetype":"neighbourhood",
    "qs_pg:qs_pg_placetype_gp":"Suburb",
    "qs_pg:woe_adm0":23424829,
    "woe:adm0_id":23424829,
    "woe:name_adm0":"Deutschland",
    "woe:name_adm1":"Sachsen",
    "woe:placetype":"Suburb",
    "wof:name":"Neustadt",
    "wof:placetype":"neighbourhood"
},
  "geometry": {"coordinates":[13.50955,51.11335],"type":"Point"}
}