{
  "type": "Feature",
  "properties": {
    "gn:admin1_code":"6",
    "gn:admin2_code":"0.0",
    "gn:admin3_code":"3254.0",
    "gn:admin4_code":"3254003.0",
    "gn:asciiname":"Waetzum",
    "gn:country_code":"DE",
    "gn:dem":86,
    "gn:feature_class":"P",
    "gn:feature_code":"PPL",
    "gn:name":"W\u00e4tzum",
    "gn:population":0,
    "gn:timezone":"Europe/Berlin",
    "iso:country":"DE",
    "wof:name":"Waetzum",
    "wof:placetype":"neighbourhood"
},
  "geometry": {"coordinates":[9.97456,52.27372],"type":"Point"}
}