{
  "type": "Feature",
  "properties": {
    "gn:admin1_code":"1.0",
    "gn:admin2_code":"83.0",
    "gn:admin3_code":"8315.0",
    "gn:admin4_code":"8315037.0",
    "gn:asciiname":"Feldberg-Ort",
    "gn:country_code":"DE",
    "gn:dem":1286,
    "gn:feature_class":"P",
    "gn:feature_code":"PPL",
    "gn:name":"Feldberg-Ort",
    "gn:population":0,
    "gn:timezone":"Europe/Berlin",
    "iso:country":"DE",
    "wof:name":"Feldberg-Ort",
    "wof:placetype":"neighbourhood"
},
  "geometry": {"coordinates":[8.03942,47.85925],"type":"Point"}
}