{
  "type": "Feature",
  "properties": {
    "gn:gn_country":"DE",
    "gn:gn_fcode":"PPLA4",
    "gn:gn_pop":62,
    "gn:population":62,
    "iso:country":"DE",
    "name:baq_x_preferred":[
        "Etgert"
    ],
    "name:chi_x_preferred":[
        "\u57c3\u7279\u683c\u5c14\u7279"
    ],
    "name:dut_x_preferred":[
        "Etgert"
    ],
    "name:eng_x_preferred":[
        "Etgert"
    ],
    "name:epo_x_preferred":[
        "Etgert"
    ],
    "name:fre_x_preferred":[
        "Etgert"
    ],
    "name:ger_x_preferred":[
        "Etgert"
    ],
    "name:hun_x_preferred":[
        "Etgert"
    ],
    "name:ita_x_preferred":[
        "Etgert"
    ],
    "name:jpn_x_preferred":[
        "\u30a8\u30c3\u30c8\u30ac\u30fc\u30c8"
    ],
    "name:kaz_x_preferred":[
        "\u042d\u0442\u0433\u0435\u0440\u0442"
    ],
    "name:kir_x_preferred":[
        "\u042d\u0442\u0433\u0435\u0440\u0442"
    ],
    "name:may_x_preferred":[
        "Etgert"
    ],
    "name:per_x_preferred":[
        "\u0627\u062a\u06af\u0631\u062a"
    ],
    "name:pol_x_preferred":[
        "Etgert"
    ],
    "name:por_x_preferred":[
        "Etgert"
    ],
    "name:rum_x_preferred":[
        "Etgert"
    ],
    "name:rus_x_preferred":[
        "\u042d\u0442\u0433\u0435\u0440\u0442"
    ],
    "name:spa_x_preferred":[
        "Etgert"
    ],
    "name:srp_x_preferred":[
        "\u0415\u0442\u0433\u0435\u0440\u0442"
    ],
    "name:ukr_x_preferred":[
        "\u0415\u0442\u0433\u0435\u0440\u0442"
    ],
    "name:uzb_x_preferred":[
        "Etgert"
    ],
    "name:vie_x_preferred":[
        "Etgert"
    ],
    "name:vol_x_preferred":[
        "Etgert"
    ],
    "name:war_x_preferred":[
        "Etgert"
    ],
    "qs_pg:aaroncc":"DE",
    "qs_pg:gn_country":"DE",
    "qs_pg:gn_fcode":"PPLA4",
    "qs_pg:gn_pop":62,
    "qs_pg:name":"Etgert",
    "qs_pg:photos_9r":0,
    "qs_pg:photos_sr":0,
    "qs_pg:pop_sr":1,
    "qs_pg:qs_pg_placetype":"locality",
    "wof:name":"Etgert",
    "wof:placetype":"locality",
    "wof:population":62
},
  "geometry": {"coordinates":[7.02121,49.77883],"type":"Point"}
}