{
  "type": "Feature",
  "properties": {
    "iso:country":"DE",
    "wof:name":"Querenburg",
    "wof:placetype":"neighbourhood"
},
  "geometry": {"coordinates":[7.2645595472151,51.45067758603307],"type":"Point"}
}