{
  "type": "Feature",
  "properties": {
    "gn:admin1_code":"14",
    "gn:admin2_code":"0.0",
    "gn:admin3_code":"15081.0",
    "gn:admin4_code":"15081135.0",
    "gn:asciiname":"Plitschenwinkel",
    "gn:country_code":"DE",
    "gn:dem":58,
    "gn:feature_class":"P",
    "gn:feature_code":"PPL",
    "gn:name":"Plitschenwinkel",
    "gn:population":0,
    "gn:timezone":"Europe/Berlin",
    "iso:country":"DE",
    "wof:name":"Plitschenwinkel",
    "wof:placetype":"neighbourhood"
},
  "geometry": {"coordinates":[11.1103,52.51625],"type":"Point"}
}