{
  "type": "Feature",
  "properties": {
    "gn:admin1_code":"6",
    "gn:admin2_code":"0.0",
    "gn:admin3_code":"3351.0",
    "gn:admin4_code":"3351008.0",
    "gn:asciiname":"Hohnhorst",
    "gn:country_code":"DE",
    "gn:dem":60,
    "gn:feature_class":"P",
    "gn:feature_code":"PPL",
    "gn:name":"Hohnhorst",
    "gn:population":0,
    "gn:timezone":"Europe/Berlin",
    "iso:country":"DE",
    "wof:name":"Hohnhorst",
    "wof:placetype":"neighbourhood"
},
  "geometry": {"coordinates":[10.32977,52.65349000000001],"type":"Point"}
}