{
  "type": "Feature",
  "properties": {
    "gn:admin1_code":"6",
    "gn:admin2_code":"0.0",
    "gn:admin3_code":"3351.0",
    "gn:admin4_code":"3351008.0",
    "gn:asciiname":"Hohnhorst",
    "gn:country_code":"DE",
    "gn:dem":60,
    "gn:feature_class":"P",
    "gn:feature_code":"PPL",
    "gn:name":"Hohnhorst",
    "gn:population":0,
    "gn:timezone":"Europe/Berlin",
    "iso:country":"DE",
    "name:dan_x_preferred":[
        "Hohnhorst"
    ],
    "name:deu_x_preferred":[
        "Hohnhorst"
    ],
    "name:epo_x_preferred":[
        "Hohnhorst"
    ],
    "name:est_x_preferred":[
        "Hohnhorst"
    ],
    "name:eus_x_preferred":[
        "Hohnhorst"
    ],
    "name:fas_x_preferred":[
        "\u0647\u0648\u0647\u0646\u0647\u0648\u0631\u0634\u062a"
    ],
    "name:fra_x_preferred":[
        "Hohnhorst"
    ],
    "name:hun_x_preferred":[
        "Hohnhorst"
    ],
    "name:ita_x_preferred":[
        "Hohnhorst"
    ],
    "name:jpn_x_preferred":[
        "\u30db\u30fc\u30f3\u30db\u30eb\u30b9\u30c8"
    ],
    "name:kaz_x_preferred":[
        "\u0425\u043e\u043d\u0445\u043e\u0440\u0441\u0442"
    ],
    "name:kir_x_preferred":[
        "\u0425\u043e\u043d\u0445\u043e\u0440\u0441\u0442"
    ],
    "name:mkd_x_preferred":[
        "\u0425\u043e\u043d\u0445\u043e\u0440\u0441\u0442"
    ],
    "name:msa_x_preferred":[
        "Hohnhorst"
    ],
    "name:nld_x_preferred":[
        "Hohnhorst"
    ],
    "name:pol_x_preferred":[
        "Hohnhorst"
    ],
    "name:por_x_preferred":[
        "Hohnhorst"
    ],
    "name:ron_x_preferred":[
        "Hohnhorst"
    ],
    "name:rus_x_preferred":[
        "\u0425\u043e\u043d\u0445\u043e\u0440\u0441\u0442"
    ],
    "name:spa_x_preferred":[
        "Hohnhorst"
    ],
    "name:srp_x_preferred":[
        "\u0425\u043e\u043d\u0445\u043e\u0440\u0441\u0442"
    ],
    "name:ukr_x_preferred":[
        "\u0413\u043e\u043d\u0433\u043e\u0440\u0441\u0442"
    ],
    "name:uzb_x_preferred":[
        "Hohnhorst"
    ],
    "name:vol_x_preferred":[
        "Hohnhorst"
    ],
    "name:war_x_preferred":[
        "Hohnhorst"
    ],
    "name:zho_x_preferred":[
        "\u970d\u6069\u970d\u65af\u7279"
    ],
    "wof:name":"Hohnhorst",
    "wof:placetype":"neighbourhood"
},
  "geometry": {"coordinates":[10.32977,52.65349000000001],"type":"Point"}
}