{
  "type": "Feature",
  "properties": {
    "gn:admin1_code":"2",
    "gn:admin2_code":"93.0",
    "gn:admin3_code":"9375.0",
    "gn:admin4_code":"9375210.0",
    "gn:asciiname":"Oberachdorf",
    "gn:country_code":"DE",
    "gn:dem":324,
    "gn:feature_class":"P",
    "gn:feature_code":"PPL",
    "gn:name":"Oberachdorf",
    "gn:population":0,
    "gn:timezone":"Europe/Berlin",
    "iso:country":"DE",
    "wof:name":"Oberachdorf",
    "wof:placetype":"neighbourhood"
},
  "geometry": {"coordinates":[12.38899,48.99599],"type":"Point"}
}