{
  "type": "Feature",
  "properties": {
    "gn:admin1_code":"2",
    "gn:admin2_code":"97.0",
    "gn:admin3_code":"9776.0",
    "gn:admin4_code":"9776116.0",
    "gn:asciiname":"Sorgers",
    "gn:country_code":"DE",
    "gn:dem":439,
    "gn:feature_class":"P",
    "gn:feature_code":"PPL",
    "gn:name":"Sorgers",
    "gn:population":0,
    "gn:timezone":"Europe/Berlin",
    "iso:country":"DE",
    "wof:name":"Sorgers",
    "wof:placetype":"neighbourhood"
},
  "geometry": {"coordinates":[9.68116,47.57117],"type":"Point"}
}