{
  "type": "Feature",
  "properties": {
    "gn:admin1_code":"2",
    "gn:admin2_code":"91.0",
    "gn:admin3_code":"9173.0",
    "gn:admin4_code":"9173135.0",
    "gn:asciiname":"Fleck",
    "gn:country_code":"DE",
    "gn:dem":698,
    "gn:feature_class":"P",
    "gn:feature_code":"PPL",
    "gn:name":"Fleck",
    "gn:population":0,
    "gn:timezone":"Europe/Berlin",
    "iso:country":"DE",
    "wof:name":"Fleck",
    "wof:placetype":"neighbourhood"
},
  "geometry": {"coordinates":[11.58917,47.65025],"type":"Point"}
}