{
  "type": "Feature",
  "properties": {
    "gn:admin1_code":"2.0",
    "gn:admin2_code":"093",
    "gn:admin3_code":"9375.0",
    "gn:admin4_code":"9375184.0",
    "gn:asciiname":"Zieglhof",
    "gn:country_code":"DE",
    "gn:dem":441,
    "gn:feature_class":"P",
    "gn:feature_code":"PPL",
    "gn:name":"Zieglhof",
    "gn:population":0,
    "gn:timezone":"Europe/Berlin",
    "iso:country":"DE",
    "wof:name":"Zieglhof",
    "wof:placetype":"neighbourhood"
},
  "geometry": {"coordinates":[11.96754,49.06813],"type":"Point"}
}