{
  "type": "Feature",
  "properties": {
    "gn:admin1_code":"13",
    "gn:admin2_code":"0.0",
    "gn:admin3_code":"14730.0",
    "gn:admin4_code":"14730280.0",
    "gn:asciiname":"Kleinwoelkau",
    "gn:country_code":"DE",
    "gn:dem":102,
    "gn:feature_class":"P",
    "gn:feature_code":"PPL",
    "gn:name":"Kleinw\u00f6lkau",
    "gn:population":0,
    "gn:timezone":"Europe/Berlin",
    "iso:country":"DE",
    "wof:name":"Kleinwoelkau",
    "wof:placetype":"neighbourhood"
},
  "geometry": {"coordinates":[12.4966,51.49774],"type":"Point"}
}