{
  "type": "Feature",
  "properties": {
    "gn:admin1_code":"1.0",
    "gn:admin2_code":"81.0",
    "gn:admin3_code":"8116.0",
    "gn:admin4_code":"8116081.0",
    "gn:asciiname":"Aich",
    "gn:country_code":"DE",
    "gn:dem":344,
    "gn:feature_class":"P",
    "gn:feature_code":"PPL",
    "gn:name":"Aich",
    "gn:population":0,
    "gn:timezone":"Europe/Berlin",
    "iso:country":"DE",
    "name:ceb_x_preferred":[
        "Aich"
    ],
    "name:deu_x_preferred":[
        "Aich"
    ],
    "name:fra_x_preferred":[
        "Aich"
    ],
    "name:ita_x_preferred":[
        "Aich"
    ],
    "name:nld_x_preferred":[
        "Aich"
    ],
    "name:pol_x_preferred":[
        "Aich"
    ],
    "name:rus_x_preferred":[
        "\u0410\u0439\u0445"
    ],
    "name:swe_x_preferred":[
        "Aich"
    ],
    "wof:name":"Aich",
    "wof:placetype":"neighbourhood"
},
  "geometry": {"coordinates":[9.23766,48.62409],"type":"Point"}
}