{
  "type": "Feature",
  "properties": {
    "gn:admin1_code":"14.0",
    "gn:admin2_code":"0.0",
    "gn:admin3_code":"15083.0",
    "gn:admin4_code":"15083270.0",
    "gn:asciiname":"Althaldensleben",
    "gn:country_code":"DE",
    "gn:dem":58,
    "gn:feature_class":"P",
    "gn:feature_code":"PPL",
    "gn:name":"Althaldensleben",
    "gn:population":0,
    "gn:timezone":"Europe/Berlin",
    "iso:country":"DE",
    "wof:name":"Althaldensleben",
    "wof:placetype":"neighbourhood"
},
  "geometry": {"coordinates":[11.42372,52.26879],"type":"Point"}
}