{
  "type": "Feature",
  "properties": {
    "gn:admin1_code":"7",
    "gn:admin2_code":"57.0",
    "gn:admin3_code":"5770.0",
    "gn:admin4_code":"5770040.0",
    "gn:asciiname":"Kolkhorst",
    "gn:country_code":"DE",
    "gn:dem":40,
    "gn:feature_class":"P",
    "gn:feature_code":"PPLL",
    "gn:name":"Kolkhorst",
    "gn:population":0,
    "gn:timezone":"Europe/Berlin",
    "iso:country":"DE",
    "wof:name":"Kolkhorst",
    "wof:placetype":"neighbourhood"
},
  "geometry": {"coordinates":[8.56839,52.46563],"type":"Point"}
}