{
  "type": "Feature",
  "properties": {
    "gn:admin1_code":"7",
    "gn:admin2_code":"55.0",
    "gn:admin3_code":"5570.0",
    "gn:admin4_code":"5570032.0",
    "gn:asciiname":"Lehmbrock",
    "gn:country_code":"DE",
    "gn:dem":54,
    "gn:feature_class":"P",
    "gn:feature_code":"PPLL",
    "gn:name":"Lehmbrock",
    "gn:population":0,
    "gn:timezone":"Europe/Berlin",
    "iso:country":"DE",
    "wof:name":"Lehmbrock",
    "wof:placetype":"neighbourhood"
},
  "geometry": {"coordinates":[7.81572,52.03134],"type":"Point"}
}