{
  "type": "Feature",
  "properties": {
    "gn:admin1_code":"2.0",
    "gn:admin2_code":"095",
    "gn:admin3_code":"9574.0",
    "gn:admin4_code":"9574141.0",
    "gn:asciiname":"Weissenbach",
    "gn:country_code":"DE",
    "gn:dem":442,
    "gn:feature_class":"P",
    "gn:feature_code":"PPL",
    "gn:name":"Wei\u00dfenbach",
    "gn:population":0,
    "gn:timezone":"Europe/Berlin",
    "iso:country":"DE",
    "name:ceb_x_preferred":[
        "Weissenbach"
    ],
    "name:epo_x_preferred":[
        "Weissenbach"
    ],
    "name:nld_x_preferred":[
        "Weissenbach"
    ],
    "name:pol_x_preferred":[
        "Weissenbach"
    ],
    "name:swe_x_preferred":[
        "Weissenbach"
    ],
    "wof:name":"Weissenbach",
    "wof:placetype":"neighbourhood"
},
  "geometry": {"coordinates":[11.37136,49.53969],"type":"Point"}
}