{
  "type": "Feature",
  "properties": {
    "gn:admin1_code":"2",
    "gn:admin2_code":"92.0",
    "gn:admin3_code":"9274.0",
    "gn:admin4_code":"9274185.0",
    "gn:asciiname":"Kapfing",
    "gn:country_code":"DE",
    "gn:dem":490,
    "gn:feature_class":"P",
    "gn:feature_code":"PPL",
    "gn:name":"Kapfing",
    "gn:population":0,
    "gn:timezone":"Europe/Berlin",
    "iso:country":"DE",
    "wof:name":"Kapfing",
    "wof:placetype":"neighbourhood"
},
  "geometry": {"coordinates":[12.1068,48.45632],"type":"Point"}
}