{
  "type": "Feature",
  "properties": {
    "gn:admin1_code":"13.0",
    "gn:admin2_code":"00",
    "gn:admin3_code":"14626.0",
    "gn:admin4_code":"14626610.0",
    "gn:asciiname":"Wittgendorf",
    "gn:country_code":"DE",
    "gn:dem":287,
    "gn:feature_class":"P",
    "gn:feature_code":"PPL",
    "gn:name":"Wittgendorf",
    "gn:population":0,
    "gn:timezone":"Europe/Berlin",
    "iso:country":"DE",
    "name:bak_x_preferred":[
        "\u0412\u0438\u0442\u0433\u0435\u043d\u0434\u043e\u0440\u0444"
    ],
    "name:ceb_x_preferred":[
        "Wittgendorf"
    ],
    "name:deu_x_preferred":[
        "Wittgendorf"
    ],
    "name:fas_x_preferred":[
        "\u0648\u06cc\u062a\u06af\u0646\u062f\u0648\u0631\u0641"
    ],
    "name:ita_x_preferred":[
        "Wittgendorf"
    ],
    "name:kaz_x_preferred":[
        "\u0412\u0438\u0442\u0433\u0435\u043d\u0434\u043e\u0440\u0444"
    ],
    "name:kir_x_preferred":[
        "\u0412\u0438\u0442\u0433\u0435\u043d\u0434\u043e\u0440\u0444"
    ],
    "name:mkd_x_preferred":[
        "\u0412\u0438\u0442\u0433\u0435\u043d\u0434\u043e\u0440\u0444"
    ],
    "name:nld_x_preferred":[
        "Wittgendorf"
    ],
    "name:ron_x_preferred":[
        "Wittgendorf"
    ],
    "name:rus_x_preferred":[
        "\u0412\u0438\u0442\u0433\u0435\u043d\u0434\u043e\u0440\u0444"
    ],
    "name:uzb_x_preferred":[
        "Wittgendorf"
    ],
    "name:vie_x_preferred":[
        "Wittgendorf"
    ],
    "name:vol_x_preferred":[
        "Wittgendorf"
    ],
    "name:zho_x_preferred":[
        "\u7ef4\u7279\u6839\u591a\u592b"
    ],
    "wof:name":"Wittgendorf",
    "wof:placetype":"neighbourhood"
},
  "geometry": {"coordinates":[14.83626,50.94575],"type":"Point"}
}