{
  "type": "Feature",
  "properties": {
    "gn:admin1_code":"2",
    "gn:admin2_code":"92.0",
    "gn:admin3_code":"9274.0",
    "gn:admin4_code":"9274134.0",
    "gn:asciiname":"Vogelsang",
    "gn:country_code":"DE",
    "gn:dem":499,
    "gn:feature_class":"P",
    "gn:feature_code":"PPL",
    "gn:name":"Vogelsang",
    "gn:population":0,
    "gn:timezone":"Europe/Berlin",
    "iso:country":"DE",
    "wof:name":"Vogelsang",
    "wof:placetype":"neighbourhood"
},
  "geometry": {"coordinates":[12.2578,48.49961],"type":"Point"}
}