{
  "type": "Feature",
  "properties": {
    "gn:admin1_code":"2",
    "gn:admin2_code":"92.0",
    "gn:admin3_code":"9275.0",
    "gn:admin4_code":"9275122.0",
    "gn:asciiname":"Steinhugl",
    "gn:country_code":"DE",
    "gn:dem":413,
    "gn:feature_class":"P",
    "gn:feature_code":"PPLL",
    "gn:name":"Steinh\u00fcgl",
    "gn:population":0,
    "gn:timezone":"Europe/Berlin",
    "iso:country":"DE",
    "wof:name":"Steinhugl",
    "wof:placetype":"neighbourhood"
},
  "geometry": {"coordinates":[13.29061,48.57848],"type":"Point"}
}