{
  "type": "Feature",
  "properties": {
    "gn:admin1_code":"2",
    "gn:admin2_code":"93.0",
    "gn:admin3_code":"9374.0",
    "gn:admin4_code":"9374162.0",
    "gn:asciiname":"Kaltenbaum",
    "gn:country_code":"DE",
    "gn:dem":594,
    "gn:feature_class":"P",
    "gn:feature_code":"PPL",
    "gn:name":"Kaltenbaum",
    "gn:population":0,
    "gn:timezone":"Europe/Berlin",
    "iso:country":"DE",
    "wof:name":"Kaltenbaum",
    "wof:placetype":"neighbourhood"
},
  "geometry": {"coordinates":[12.30474,49.59262],"type":"Point"}
}