{
  "type": "Feature",
  "properties": {
    "iso:country":"DE",
    "wof:name":"Siedlung Lerchesberg",
    "wof:placetype":"neighbourhood"
},
  "geometry": {"coordinates":[8.68172506784561,50.0814709378558],"type":"Point"}
}