{
  "type": "Feature",
  "properties": {
    "gn:admin1_code":"14",
    "gn:admin2_code":"0.0",
    "gn:admin3_code":"15090.0",
    "gn:admin4_code":"15090010.0",
    "gn:asciiname":"Niedergoerne",
    "gn:country_code":"DE",
    "gn:dem":37,
    "gn:feature_class":"P",
    "gn:feature_code":"PPL",
    "gn:name":"Niederg\u00f6rne",
    "gn:population":0,
    "gn:timezone":"Europe/Berlin",
    "iso:country":"DE",
    "wof:name":"Niedergoerne",
    "wof:placetype":"neighbourhood"
},
  "geometry": {"coordinates":[12.00668,52.72226],"type":"Point"}
}