{
  "type": "Feature",
  "properties": {
    "gn:admin1_code":"2.0",
    "gn:admin2_code":"96.0",
    "gn:admin3_code":"9677.0",
    "gn:admin4_code":"9677114.0",
    "gn:asciiname":"Binsbach",
    "gn:country_code":"DE",
    "gn:dem":263,
    "gn:feature_class":"P",
    "gn:feature_code":"PPL",
    "gn:name":"Binsbach",
    "gn:population":0,
    "gn:timezone":"Europe/Berlin",
    "iso:country":"DE",
    "wof:name":"Binsbach",
    "wof:placetype":"neighbourhood"
},
  "geometry": {"coordinates":[10.00907,49.9509],"type":"Point"}
}