{
  "type": "Feature",
  "properties": {
    "gn:admin1_code":"7",
    "gn:admin2_code":"59.0",
    "gn:admin3_code":"5966.0",
    "gn:admin4_code":"5966024.0",
    "gn:asciiname":"Eichhagen",
    "gn:country_code":"DE",
    "gn:dem":350,
    "gn:feature_class":"P",
    "gn:feature_code":"PPLL",
    "gn:name":"Eichhagen",
    "gn:population":0,
    "gn:timezone":"Europe/Berlin",
    "iso:country":"DE",
    "wof:name":"Eichhagen",
    "wof:placetype":"neighbourhood"
},
  "geometry": {"coordinates":[7.83391,51.057],"type":"Point"}
}