{
  "type": "Feature",
  "properties": {
    "gn:admin1_code":"7.0",
    "gn:admin2_code":"059",
    "gn:admin3_code":"5914.0",
    "gn:admin4_code":"5914000.0",
    "gn:asciiname":"Werninghausen",
    "gn:country_code":"DE",
    "gn:dem":337,
    "gn:feature_class":"P",
    "gn:feature_code":"PPL",
    "gn:name":"Werninghausen",
    "gn:population":0,
    "gn:timezone":"Europe/Berlin",
    "iso:country":"DE",
    "wof:name":"Werninghausen",
    "wof:placetype":"neighbourhood"
},
  "geometry": {"coordinates":[7.51198,51.30121],"type":"Point"}
}