{
  "type": "Feature",
  "properties": {
    "gn:gn_country":"DE",
    "gn:gn_fcode":"PPLA4",
    "gn:gn_pop":184,
    "gn:population":184,
    "iso:country":"DE",
    "name:baq_x_preferred":[
        "Bargstall"
    ],
    "name:chi_x_preferred":[
        "\u5df4\u5c14\u683c\u65af\u5854\u5c14"
    ],
    "name:dan_x_preferred":[
        "Bargstall"
    ],
    "name:dut_x_preferred":[
        "Bargstall"
    ],
    "name:eng_x_preferred":[
        "Bargstall"
    ],
    "name:epo_x_preferred":[
        "Bargstall"
    ],
    "name:fre_x_preferred":[
        "Bargstall"
    ],
    "name:ger_x_preferred":[
        "Bargstall"
    ],
    "name:hun_x_preferred":[
        "Bargstall"
    ],
    "name:ita_x_preferred":[
        "Bargstall"
    ],
    "name:mac_x_preferred":[
        "\u0411\u0430\u0440\u0433\u0441\u0442\u0430\u043b"
    ],
    "name:may_x_preferred":[
        "Bargstall"
    ],
    "name:per_x_preferred":[
        "\u0628\u0627\u0631\u06af\u0634\u062a\u0627\u0644"
    ],
    "name:pol_x_preferred":[
        "Bargstall"
    ],
    "name:por_x_preferred":[
        "Bargstall"
    ],
    "name:rum_x_preferred":[
        "Bargstall"
    ],
    "name:rus_x_preferred":[
        "\u0411\u0430\u0440\u0433\u0441\u0442\u0430\u043b\u043b\u044c"
    ],
    "name:spa_x_preferred":[
        "Bargstall"
    ],
    "name:srp_x_preferred":[
        "\u0411\u0430\u0440\u0433\u0441\u0442\u0430\u043b"
    ],
    "name:tur_x_preferred":[
        "Bargstall"
    ],
    "name:ukr_x_preferred":[
        "\u0411\u0430\u0440\u0433\u0441\u0442\u0430\u043b\u044c"
    ],
    "name:uzb_x_preferred":[
        "Bargstall"
    ],
    "name:vie_x_preferred":[
        "Bargstall"
    ],
    "name:vol_x_preferred":[
        "Bargstall"
    ],
    "name:war_x_preferred":[
        "Bargstall"
    ],
    "qs_pg:aaroncc":"DE",
    "qs_pg:gn_country":"DE",
    "qs_pg:gn_fcode":"PPLA4",
    "qs_pg:gn_pop":184,
    "qs_pg:name":"Bargstall",
    "qs_pg:photos_9r":0,
    "qs_pg:photos_sr":0,
    "qs_pg:pop_sr":1,
    "qs_pg:qs_pg_placetype":"locality",
    "wof:name":"Bargstall",
    "wof:placetype":"locality",
    "wof:population":184
},
  "geometry": {"coordinates":[9.46667,54.26667],"type":"Point"}
}