{
  "type": "Feature",
  "properties": {
    "gn:admin1_code":"2",
    "gn:admin2_code":"92.0",
    "gn:admin3_code":"9272.0",
    "gn:admin4_code":"9272116.0",
    "gn:asciiname":"Furstberg",
    "gn:country_code":"DE",
    "gn:dem":590,
    "gn:feature_class":"P",
    "gn:feature_code":"PPL",
    "gn:name":"F\u00fcrstberg",
    "gn:population":0,
    "gn:timezone":"Europe/Berlin",
    "iso:country":"DE",
    "wof:name":"Furstberg",
    "wof:placetype":"neighbourhood"
},
  "geometry": {"coordinates":[13.30085,48.88225],"type":"Point"}
}