{
  "type": "Feature",
  "properties": {
    "gn:admin1_code":"6",
    "gn:admin2_code":"0.0",
    "gn:admin3_code":"3361.0",
    "gn:admin4_code":"3361005.0",
    "gn:asciiname":"Kreepen",
    "gn:country_code":"DE",
    "gn:dem":59,
    "gn:feature_class":"P",
    "gn:feature_code":"PPL",
    "gn:name":"Kreepen",
    "gn:population":0,
    "gn:timezone":"Europe/Berlin",
    "iso:country":"DE",
    "name:deu_x_preferred":[
        "Kreepen"
    ],
    "name:nds_x_preferred":[
        "Kreepm"
    ],
    "wof:name":"Kreepen",
    "wof:placetype":"neighbourhood"
},
  "geometry": {"coordinates":[9.35297,52.97576],"type":"Point"}
}