{
  "type": "Feature",
  "properties": {
    "gn:admin1_code":"2",
    "gn:admin2_code":"92.0",
    "gn:admin3_code":"9277.0",
    "gn:admin4_code":"9277144.0",
    "gn:asciiname":"Kleinmunchen",
    "gn:country_code":"DE",
    "gn:dem":445,
    "gn:feature_class":"P",
    "gn:feature_code":"PPL",
    "gn:name":"Kleinm\u00fcnchen",
    "gn:population":0,
    "gn:timezone":"Europe/Berlin",
    "iso:country":"DE",
    "wof:name":"Kleinmunchen",
    "wof:placetype":"neighbourhood"
},
  "geometry": {"coordinates":[12.80812,48.49681],"type":"Point"}
}