{
  "type": "Feature",
  "properties": {
    "gn:admin1_code":"8",
    "gn:admin2_code":"0.0",
    "gn:admin3_code":"7140.0",
    "gn:admin4_code":"7140055.0",
    "gn:asciiname":"Gammelshausen",
    "gn:country_code":"DE",
    "gn:dem":482,
    "gn:feature_class":"P",
    "gn:feature_code":"PPL",
    "gn:name":"Gammelshausen",
    "gn:population":0,
    "gn:timezone":"Europe/Berlin",
    "iso:country":"DE",
    "name:als_x_preferred":[
        "Gammelshausen"
    ],
    "name:deu_x_preferred":[
        "Gammelshausen"
    ],
    "name:epo_x_preferred":[
        "Gammelshausen"
    ],
    "name:eus_x_preferred":[
        "Gammelshausen"
    ],
    "name:fas_x_preferred":[
        "\u06af\u0627\u0645\u0644\u0633\u0647\u0627\u0648\u0632\u0646"
    ],
    "name:fra_x_preferred":[
        "Gammelshausen"
    ],
    "name:hun_x_preferred":[
        "Gammelshausen"
    ],
    "name:ita_x_preferred":[
        "Gammelshausen"
    ],
    "name:kaz_x_preferred":[
        "\u0413\u0430\u043c\u043c\u0435\u043b\u044c\u0441\u0445\u0430\u0443\u0437\u0435\u043d"
    ],
    "name:kir_x_preferred":[
        "\u0413\u0430\u043c\u043c\u0435\u043b\u044c\u0441\u0445\u0430\u0443\u0437\u0435\u043d"
    ],
    "name:lat_x_preferred":[
        "Gammelshausen"
    ],
    "name:lmo_x_preferred":[
        "Gammelshausen"
    ],
    "name:msa_x_preferred":[
        "Gammelshausen"
    ],
    "name:nld_x_preferred":[
        "Gammelshausen"
    ],
    "name:pol_x_preferred":[
        "Gammelshausen"
    ],
    "name:por_x_preferred":[
        "Gammelshausen"
    ],
    "name:ron_x_preferred":[
        "Gammelshausen"
    ],
    "name:rus_x_preferred":[
        "\u0413\u0430\u043c\u043c\u0435\u043b\u044c\u0441\u0445\u0430\u0443\u0437\u0435\u043d"
    ],
    "name:srp_x_preferred":[
        "\u0413\u0430\u043c\u0435\u043b\u0441\u0445\u0430\u0443\u0437\u0435\u043d"
    ],
    "name:ukr_x_preferred":[
        "\u0413\u0430\u043c\u043c\u0435\u043b\u044c\u0441\u0433\u0430\u0443\u0437\u0435\u043d"
    ],
    "name:uzb_x_preferred":[
        "Gammelshausen"
    ],
    "name:vie_x_preferred":[
        "Gammelshausen"
    ],
    "name:vol_x_preferred":[
        "Gammelshausen"
    ],
    "name:war_x_preferred":[
        "Gammelshausen"
    ],
    "name:zho_x_preferred":[
        "\u52a0\u9ed8\u5c14\u65af\u8c6a\u68ee"
    ],
    "wof:name":"Gammelshausen",
    "wof:placetype":"neighbourhood"
},
  "geometry": {"coordinates":[7.48337,50.06727],"type":"Point"}
}