{
  "type": "Feature",
  "properties": {
    "gn:admin1_code":"8",
    "gn:admin2_code":"0.0",
    "gn:admin3_code":"7140.0",
    "gn:admin4_code":"7140055.0",
    "gn:asciiname":"Gammelshausen",
    "gn:country_code":"DE",
    "gn:dem":482,
    "gn:feature_class":"P",
    "gn:feature_code":"PPL",
    "gn:name":"Gammelshausen",
    "gn:population":0,
    "gn:timezone":"Europe/Berlin",
    "iso:country":"DE",
    "wof:name":"Gammelshausen",
    "wof:placetype":"neighbourhood"
},
  "geometry": {"coordinates":[7.48337,50.06727],"type":"Point"}
}