{
  "type": "Feature",
  "properties": {
    "gn:admin1_code":"6",
    "gn:admin2_code":"0.0",
    "gn:admin3_code":"3461.0",
    "gn:admin4_code":"3461007.0",
    "gn:asciiname":"Grebswarden",
    "gn:country_code":"DE",
    "gn:dem":2,
    "gn:feature_class":"P",
    "gn:feature_code":"PPL",
    "gn:name":"Grebswarden",
    "gn:population":0,
    "gn:timezone":"Europe/Berlin",
    "iso:country":"DE",
    "wof:name":"Grebswarden",
    "wof:placetype":"neighbourhood"
},
  "geometry": {"coordinates":[8.51008,53.52376999999999],"type":"Point"}
}