{
  "type": "Feature",
  "properties": {
    "gn:admin1_code":"6",
    "gn:admin2_code":"0.0",
    "gn:admin3_code":"3241.0",
    "gn:admin4_code":"3241011.0",
    "gn:asciiname":"Kolshorn",
    "gn:country_code":"DE",
    "gn:dem":60,
    "gn:feature_class":"P",
    "gn:feature_code":"PPL",
    "gn:name":"Kolshorn",
    "gn:population":0,
    "gn:timezone":"Europe/Berlin",
    "iso:country":"DE",
    "wof:name":"Kolshorn",
    "wof:placetype":"neighbourhood"
},
  "geometry": {"coordinates":[9.95384,52.42172],"type":"Point"}
}