{
  "type": "Feature",
  "properties": {
    "gn:admin1_code":"2",
    "gn:admin2_code":"92.0",
    "gn:admin3_code":"9275.0",
    "gn:admin4_code":"9275138.0",
    "gn:asciiname":"Hubing",
    "gn:country_code":"DE",
    "gn:dem":363,
    "gn:feature_class":"P",
    "gn:feature_code":"PPLL",
    "gn:name":"H\u00fcbing",
    "gn:population":0,
    "gn:timezone":"Europe/Berlin",
    "iso:country":"DE",
    "wof:name":"Hubing",
    "wof:placetype":"neighbourhood"
},
  "geometry": {"coordinates":[13.23862,48.5143],"type":"Point"}
}