{
  "type": "Feature",
  "properties": {
    "gn:admin1_code":"2.0",
    "gn:admin2_code":"93.0",
    "gn:admin3_code":"9376.0",
    "gn:admin4_code":"9376116.0",
    "gn:asciiname":"Blechhammer",
    "gn:country_code":"DE",
    "gn:dem":381,
    "gn:feature_class":"P",
    "gn:feature_code":"PPL",
    "gn:name":"Blechhammer",
    "gn:population":0,
    "gn:timezone":"Europe/Berlin",
    "iso:country":"DE",
    "name:fra_x_preferred":[
        "Blechhammer"
    ],
    "name:heb_x_preferred":[
        "\u05d1\u05dc\u05db\u05d4\u05de\u05e8"
    ],
    "name:nld_x_preferred":[
        "Blechhammer"
    ],
    "name:pol_x_preferred":[
        "Blachownia \u015al\u0105ska"
    ],
    "wof:name":"Blechhammer",
    "wof:placetype":"neighbourhood"
},
  "geometry": {"coordinates":[12.32278,49.27859],"type":"Point"}
}