{
  "type": "Feature",
  "properties": {
    "gn:admin1_code":"6",
    "gn:admin2_code":"0.0",
    "gn:admin3_code":"3455.0",
    "gn:admin4_code":"3455026.0",
    "gn:asciiname":"Varelerhafen",
    "gn:country_code":"DE",
    "gn:dem":1,
    "gn:feature_class":"P",
    "gn:feature_code":"PPL",
    "gn:name":"Varelerhafen",
    "gn:population":0,
    "gn:timezone":"Europe/Berlin",
    "iso:country":"DE",
    "wof:name":"Varelerhafen",
    "wof:placetype":"neighbourhood"
},
  "geometry": {"coordinates":[8.16464,53.40636],"type":"Point"}
}