{
  "type": "Feature",
  "properties": {
    "gn:admin1_code":"2.0",
    "gn:admin2_code":"95.0",
    "gn:admin3_code":"9575.0",
    "gn:admin4_code":"9575157.0",
    "gn:asciiname":"Appenfelden",
    "gn:country_code":"DE",
    "gn:dem":369,
    "gn:feature_class":"P",
    "gn:feature_code":"PPL",
    "gn:name":"Appenfelden",
    "gn:population":0,
    "gn:timezone":"Europe/Berlin",
    "iso:country":"DE",
    "wof:name":"Appenfelden",
    "wof:placetype":"neighbourhood"
},
  "geometry": {"coordinates":[10.48704,49.73795],"type":"Point"}
}