{
  "type": "Feature",
  "properties": {
    "gn:admin1_code":"6.0",
    "gn:admin2_code":"00",
    "gn:admin3_code":"3154.0",
    "gn:admin4_code":"3154027.0",
    "gn:asciiname":"Wobeck",
    "gn:country_code":"DE",
    "gn:dem":160,
    "gn:feature_class":"P",
    "gn:feature_code":"PPL",
    "gn:name":"Wobeck",
    "gn:population":0,
    "gn:timezone":"Europe/Berlin",
    "iso:country":"DE",
    "wof:name":"Wobeck",
    "wof:placetype":"neighbourhood"
},
  "geometry": {"coordinates":[10.88968,52.1338],"type":"Point"}
}