{
  "type": "Feature",
  "properties": {
    "gn:admin1_code":"1",
    "gn:admin2_code":"84.0",
    "gn:admin3_code":"8437.0",
    "gn:admin4_code":"8437086.0",
    "gn:asciiname":"Gunzenhausen",
    "gn:country_code":"DE",
    "gn:dem":618,
    "gn:feature_class":"P",
    "gn:feature_code":"PPL",
    "gn:name":"Gunzenhausen",
    "gn:population":0,
    "gn:timezone":"Europe/Berlin",
    "iso:country":"DE",
    "name:ara_x_preferred":[
        "\u063a\u0648\u0646\u062a\u0633\u0646\u0647\u0627\u0648\u0632\u0646"
    ],
    "name:azb_x_preferred":[
        "\u0642\u0648\u0646\u062a\u0633\u0646\u200c\u0647\u0627\u0648\u0632\u0646"
    ],
    "name:bar_x_preferred":[
        "Gunzenhausn"
    ],
    "name:bul_x_preferred":[
        "\u0413\u0443\u043d\u0446\u0435\u043d\u0445\u0430\u0443\u0437\u0435\u043d"
    ],
    "name:ceb_x_preferred":[
        "Gunzenhausen"
    ],
    "name:ces_x_preferred":[
        "Gunzenhausen"
    ],
    "name:deu_x_preferred":[
        "Gunzenhausen"
    ],
    "name:epo_x_preferred":[
        "Gunzenhausen"
    ],
    "name:fas_x_preferred":[
        "\u06af\u0648\u0646\u062a\u0633\u0646\u200c\u0647\u0627\u0648\u0632\u0646"
    ],
    "name:fra_x_preferred":[
        "Gunzenhausen"
    ],
    "name:hun_x_preferred":[
        "Gunzenhausen"
    ],
    "name:hye_x_preferred":[
        "\u0533\u0578\u0582\u0576\u0581\u0565\u0576\u0570\u0561\u0578\u0582\u0566\u0565\u0576"
    ],
    "name:ind_x_preferred":[
        "Gunzenhausen"
    ],
    "name:ita_x_preferred":[
        "Gunzenhausen"
    ],
    "name:kaz_x_preferred":[
        "\u0413\u0443\u043d\u0446\u0435\u043d\u0445\u0430\u0443\u0437\u0435\u043d"
    ],
    "name:kir_x_preferred":[
        "\u0413\u0443\u043d\u0446\u0435\u043d\u0445\u0430\u0443\u0437\u0435\u043d"
    ],
    "name:lmo_x_preferred":[
        "Gunzenhausen"
    ],
    "name:msa_x_preferred":[
        "Gunzenhausen"
    ],
    "name:nld_x_preferred":[
        "Gunzenhausen"
    ],
    "name:pol_x_preferred":[
        "Gunzenhausen"
    ],
    "name:ron_x_preferred":[
        "Gunzenhausen"
    ],
    "name:rus_x_preferred":[
        "\u0413\u0443\u043d\u0446\u0435\u043d\u0445\u0430\u0443\u0437\u0435\u043d"
    ],
    "name:slk_x_preferred":[
        "Gunzenhausen"
    ],
    "name:spa_x_preferred":[
        "Gunzenhausen"
    ],
    "name:srp_x_preferred":[
        "\u0413\u0443\u043d\u0446\u0435\u043d\u0445\u0430\u0443\u0437\u0435\u043d"
    ],
    "name:swe_x_preferred":[
        "Gunzenhausen"
    ],
    "name:tur_x_preferred":[
        "Gunzenhausen"
    ],
    "name:ukr_x_preferred":[
        "\u0490\u0443\u043d\u0446\u0435\u043d\u0433\u0430\u0443\u0437\u0435\u043d"
    ],
    "name:uzb_x_preferred":[
        "Gunzenhausen"
    ],
    "name:vie_x_preferred":[
        "Gunzenhausen"
    ],
    "name:vol_x_preferred":[
        "Gunzenhausen"
    ],
    "name:war_x_preferred":[
        "Gunzenhausen"
    ],
    "name:zho_x_preferred":[
        "\u8d21\u5c91\u8c6a\u68ee"
    ],
    "wof:name":"Gunzenhausen",
    "wof:placetype":"neighbourhood"
},
  "geometry": {"coordinates":[9.38327,47.97744],"type":"Point"}
}