{
  "type": "Feature",
  "properties": {
    "iso:country":"DE",
    "name:ger_x_variant":[
        "Zooviertel"
    ],
    "wof:name":"Zoo",
    "wof:placetype":"neighbourhood"
},
  "geometry": {"coordinates":[7.11286350733095,51.24241212474853],"type":"Point"}
}