{
  "type": "Feature",
  "properties": {
    "gn:admin1_code":"6",
    "gn:admin2_code":"0.0",
    "gn:admin3_code":"3159.0",
    "gn:admin4_code":"3159010.0",
    "gn:asciiname":"Gerblingerode",
    "gn:country_code":"DE",
    "gn:dem":191,
    "gn:feature_class":"P",
    "gn:feature_code":"PPL",
    "gn:name":"Gerblingerode",
    "gn:population":0,
    "gn:timezone":"Europe/Berlin",
    "iso:country":"DE",
    "wof:name":"Gerblingerode",
    "wof:placetype":"neighbourhood"
},
  "geometry": {"coordinates":[10.26312,51.49506],"type":"Point"}
}