{
  "type": "Feature",
  "properties": {
    "gn:admin1_code":"2",
    "gn:admin2_code":"91.0",
    "gn:admin3_code":"9177.0",
    "gn:admin4_code":"9177121.0",
    "gn:asciiname":"Sinzing",
    "gn:country_code":"DE",
    "gn:dem":488,
    "gn:feature_class":"P",
    "gn:feature_code":"PPL",
    "gn:name":"Sinzing",
    "gn:population":0,
    "gn:timezone":"Europe/Berlin",
    "iso:country":"DE",
    "name:ceb_x_preferred":[
        "Sinzing"
    ],
    "name:ces_x_preferred":[
        "Sinzing"
    ],
    "name:deu_x_preferred":[
        "Sinzing"
    ],
    "name:epo_x_preferred":[
        "Sinzing"
    ],
    "name:eus_x_preferred":[
        "Sinzing"
    ],
    "name:fas_x_preferred":[
        "\u0633\u06cc\u0646\u062a\u0633\u06cc\u0646\u06af"
    ],
    "name:fra_x_preferred":[
        "Sinzing"
    ],
    "name:hun_x_preferred":[
        "Sinzing"
    ],
    "name:hye_x_preferred":[
        "\u0536\u056b\u0576\u0581\u056b\u0576\u0563"
    ],
    "name:ita_x_preferred":[
        "Sinzing"
    ],
    "name:kaz_x_preferred":[
        "\u0417\u0438\u043d\u0446\u0438\u043d\u0433"
    ],
    "name:kir_x_preferred":[
        "\u0417\u0438\u043d\u0446\u0438\u043d\u0433"
    ],
    "name:lat_x_preferred":[
        "Sinzing"
    ],
    "name:lmo_x_preferred":[
        "Sinzing"
    ],
    "name:msa_x_preferred":[
        "Sinzing"
    ],
    "name:nld_x_preferred":[
        "Sinzing"
    ],
    "name:pol_x_preferred":[
        "Sinzing"
    ],
    "name:ron_x_preferred":[
        "Sinzing"
    ],
    "name:rus_x_preferred":[
        "\u0417\u0438\u043d\u0446\u0438\u043d\u0433"
    ],
    "name:spa_x_preferred":[
        "Sinzing"
    ],
    "name:srp_x_preferred":[
        "\u0417\u0438\u043d\u0446\u0438\u043d\u0433"
    ],
    "name:swe_x_preferred":[
        "Sinzing"
    ],
    "name:ukr_x_preferred":[
        "\u0417\u0456\u043d\u0446\u0438\u043d\u0433"
    ],
    "name:uzb_x_preferred":[
        "Sinzing"
    ],
    "name:vie_x_preferred":[
        "Sinzing"
    ],
    "name:vol_x_preferred":[
        "Sinzing"
    ],
    "name:war_x_preferred":[
        "Sinzing"
    ],
    "name:zho_x_preferred":[
        "\u8f9b\u94a6\u683c"
    ],
    "wof:name":"Sinzing",
    "wof:placetype":"neighbourhood"
},
  "geometry": {"coordinates":[12.15323,48.39972],"type":"Point"}
}