{
  "type": "Feature",
  "properties": {
    "gn:admin1_code":"1",
    "gn:admin2_code":"83.0",
    "gn:admin3_code":"8327.0",
    "gn:admin4_code":"8327056.0",
    "gn:asciiname":"Russberg",
    "gn:country_code":"DE",
    "gn:dem":849,
    "gn:feature_class":"P",
    "gn:feature_code":"PPL",
    "gn:name":"Ru\u00dfberg",
    "gn:population":0,
    "gn:timezone":"Europe/Berlin",
    "iso:country":"DE",
    "wof:name":"Russberg",
    "wof:placetype":"neighbourhood"
},
  "geometry": {"coordinates":[8.80041,48.02951],"type":"Point"}
}