{
  "type": "Feature",
  "properties": {
    "gn:admin1_code":"6",
    "gn:admin2_code":"0.0",
    "gn:admin3_code":"3461.0",
    "gn:admin4_code":"3461001.0",
    "gn:asciiname":"Harmenhausen",
    "gn:country_code":"DE",
    "gn:dem":1,
    "gn:feature_class":"P",
    "gn:feature_code":"PPL",
    "gn:name":"Harmenhausen",
    "gn:population":0,
    "gn:timezone":"Europe/Berlin",
    "iso:country":"DE",
    "wof:name":"Harmenhausen",
    "wof:placetype":"neighbourhood"
},
  "geometry": {"coordinates":[8.53995,53.15245],"type":"Point"}
}