{
  "type": "Feature",
  "properties": {
    "gn:admin1_code":"11",
    "gn:admin2_code":"0.0",
    "gn:admin3_code":"12071.0",
    "gn:admin4_code":"12071057.0",
    "gn:asciiname":"Jehserig",
    "gn:country_code":"DE",
    "gn:dem":112,
    "gn:feature_class":"P",
    "gn:feature_code":"PPL",
    "gn:name":"Jehserig",
    "gn:population":0,
    "gn:timezone":"Europe/Berlin",
    "iso:country":"DE",
    "name:dsb_x_preferred":[
        "Jazorki"
    ],
    "wof:name":"Jehserig",
    "wof:placetype":"neighbourhood"
},
  "geometry": {"coordinates":[14.25403,51.63676],"type":"Point"}
}