{
  "type": "Feature",
  "properties": {
    "gn:admin1_code":"12",
    "gn:admin2_code":"0.0",
    "gn:admin3_code":"13072.0",
    "gn:admin4_code":"13072016.0",
    "gn:asciiname":"Klein Lunow",
    "gn:country_code":"DE",
    "gn:dem":32,
    "gn:feature_class":"P",
    "gn:feature_code":"PPL",
    "gn:name":"Klein Lunow",
    "gn:population":0,
    "gn:timezone":"Europe/Berlin",
    "iso:country":"DE",
    "wof:name":"Klein Lunow",
    "wof:placetype":"neighbourhood"
},
  "geometry": {"coordinates":[12.6281,53.93871],"type":"Point"}
}