{
  "type": "Feature",
  "properties": {
    "iso:country":"DE",
    "name:deu_x_preferred":[
        "M\u00fclfort"
    ],
    "wof:name":"Muelfort",
    "wof:placetype":"neighbourhood"
},
  "geometry": {"coordinates":[6.46252721525405,51.15215237339783],"type":"Point"}
}