{
  "type": "Feature",
  "properties": {
    "gn:admin1_code":"2",
    "gn:admin2_code":"97.0",
    "gn:admin3_code":"9777.0",
    "gn:admin4_code":"9777129.0",
    "gn:asciiname":"Hof",
    "gn:country_code":"DE",
    "gn:dem":813,
    "gn:feature_class":"P",
    "gn:feature_code":"PPL",
    "gn:name":"Hof",
    "gn:population":0,
    "gn:timezone":"Europe/Berlin",
    "iso:country":"DE",
    "name:afr_x_preferred":[
        "Hof"
    ],
    "name:arg_x_preferred":[
        "Hof"
    ],
    "name:ben_x_preferred":[
        "\u09b9\u09ab"
    ],
    "name:ceb_x_preferred":[
        "Hof"
    ],
    "name:ces_x_preferred":[
        "Hof"
    ],
    "name:dan_x_preferred":[
        "Hof"
    ],
    "name:deu_x_preferred":[
        "Hof"
    ],
    "name:est_x_preferred":[
        "Hof"
    ],
    "name:eus_x_preferred":[
        "Hof"
    ],
    "name:fra_x_preferred":[
        "Hof"
    ],
    "name:fry_x_preferred":[
        "H\u00f4f"
    ],
    "name:hin_x_preferred":[
        "\u0939\u094b\u092b"
    ],
    "name:hrv_x_preferred":[
        "Hof"
    ],
    "name:hye_x_preferred":[
        "\u0540\u0578\u0586"
    ],
    "name:isl_x_preferred":[
        "Hof"
    ],
    "name:lmo_x_preferred":[
        "Hof"
    ],
    "name:nld_x_preferred":[
        "Hof"
    ],
    "name:nor_x_preferred":[
        "Hof"
    ],
    "name:pol_x_preferred":[
        "Hof"
    ],
    "name:por_x_preferred":[
        "Hof"
    ],
    "name:ron_x_preferred":[
        "Hof"
    ],
    "name:rus_x_preferred":[
        "\u0425\u043e\u0444"
    ],
    "name:spa_x_preferred":[
        "Hof"
    ],
    "name:srp_x_preferred":[
        "\u0425\u043e\u0444"
    ],
    "name:swe_x_preferred":[
        "Hof"
    ],
    "name:urd_x_preferred":[
        "\u06c1\u0648\u0641"
    ],
    "name:vol_x_preferred":[
        "Hof"
    ],
    "wof:name":"Hof",
    "wof:placetype":"neighbourhood"
},
  "geometry": {"coordinates":[10.63163,47.58332],"type":"Point"}
}