{
  "type": "Feature",
  "properties": {
    "gn:admin1_code":"2",
    "gn:admin2_code":"91.0",
    "gn:admin3_code":"9177.0",
    "gn:admin4_code":"9177137.0",
    "gn:asciiname":"Purstling am Parstling",
    "gn:country_code":"DE",
    "gn:dem":559,
    "gn:feature_class":"P",
    "gn:feature_code":"PPL",
    "gn:name":"P\u00fcrstling am Parstling",
    "gn:population":0,
    "gn:timezone":"Europe/Berlin",
    "iso:country":"DE",
    "wof:name":"Purstling am Parstling",
    "wof:placetype":"neighbourhood"
},
  "geometry": {"coordinates":[12.22002,48.22551],"type":"Point"}
}