{
  "type": "Feature",
  "properties": {
    "gn:admin1_code":"13",
    "gn:admin2_code":"0.0",
    "gn:admin3_code":"14523.0",
    "gn:admin4_code":"14523080.0",
    "gn:asciiname":"Ebmath",
    "gn:country_code":"DE",
    "gn:dem":601,
    "gn:feature_class":"P",
    "gn:feature_code":"PPL",
    "gn:name":"Ebmath",
    "gn:population":0,
    "gn:timezone":"Europe/Berlin",
    "iso:country":"DE",
    "wof:name":"Ebmath",
    "wof:placetype":"neighbourhood"
},
  "geometry": {"coordinates":[12.15663,50.32568],"type":"Point"}
}