{
  "type": "Feature",
  "properties": {
    "gn:admin1_code":"12",
    "gn:admin2_code":"0.0",
    "gn:admin3_code":"13071.0",
    "gn:admin4_code":"13071174.0",
    "gn:asciiname":"Klockow",
    "gn:country_code":"DE",
    "gn:dem":90,
    "gn:feature_class":"P",
    "gn:feature_code":"PPL",
    "gn:name":"Klockow",
    "gn:population":0,
    "gn:timezone":"Europe/Berlin",
    "iso:country":"DE",
    "wof:name":"Klockow",
    "wof:placetype":"neighbourhood"
},
  "geometry": {"coordinates":[12.87254,53.46966],"type":"Point"}
}