{
  "type": "Feature",
  "properties": {
    "gn:admin1_code":"2.0",
    "gn:admin2_code":"093",
    "gn:admin3_code":"9377.0",
    "gn:admin4_code":"9377154.0",
    "gn:asciiname":"Wondreb",
    "gn:country_code":"DE",
    "gn:dem":531,
    "gn:feature_class":"P",
    "gn:feature_code":"PPL",
    "gn:name":"Wondreb",
    "gn:population":0,
    "gn:timezone":"Europe/Berlin",
    "iso:country":"DE",
    "name:ceb_x_preferred":[
        "Wondreb"
    ],
    "name:ces_x_preferred":[
        "Odrava"
    ],
    "name:deu_x_preferred":[
        "Wondreb"
    ],
    "name:fra_x_preferred":[
        "Wondreb"
    ],
    "name:ita_x_preferred":[
        "Odrava"
    ],
    "name:mkd_x_preferred":[
        "\u0412\u043e\u043d\u0434\u0440\u0435\u0431"
    ],
    "name:pol_x_preferred":[
        "Odrava"
    ],
    "name:swe_x_preferred":[
        "Wondreb"
    ],
    "wof:name":"Wondreb",
    "wof:placetype":"neighbourhood"
},
  "geometry": {"coordinates":[12.38451,49.90901],"type":"Point"}
}