{
  "type": "Feature",
  "properties": {
    "gn:admin1_code":"2.0",
    "gn:admin2_code":"93.0",
    "gn:admin3_code":"9371.0",
    "gn:admin4_code":"9371113.0",
    "gn:asciiname":"Sackdilling",
    "gn:country_code":"DE",
    "gn:dem":459,
    "gn:feature_class":"P",
    "gn:feature_code":"PPLF",
    "gn:name":"Sackdilling",
    "gn:population":0,
    "gn:timezone":"Europe/Berlin",
    "iso:country":"DE",
    "wof:name":"Sackdilling",
    "wof:placetype":"neighbourhood"
},
  "geometry": {"coordinates":[11.63695,49.64683],"type":"Point"}
}