{
  "type": "Feature",
  "properties": {
    "gn:admin1_code":"11",
    "gn:admin2_code":"0.0",
    "gn:admin3_code":"12062.0",
    "gn:admin4_code":"12062453.0",
    "gn:asciiname":"Schadewitz",
    "gn:country_code":"DE",
    "gn:dem":92,
    "gn:feature_class":"P",
    "gn:feature_code":"PPL",
    "gn:name":"Schadewitz",
    "gn:population":0,
    "gn:timezone":"Europe/Berlin",
    "iso:country":"DE",
    "wof:name":"Schadewitz",
    "wof:placetype":"neighbourhood"
},
  "geometry": {"coordinates":[13.48206,51.56069],"type":"Point"}
}