{
  "type": "Feature",
  "properties": {
    "gn:admin1_code":"2",
    "gn:admin2_code":"97.0",
    "gn:admin3_code":"9763.0",
    "gn:admin4_code":"9763000.0",
    "gn:asciiname":"Tannen",
    "gn:country_code":"DE",
    "gn:dem":753,
    "gn:feature_class":"P",
    "gn:feature_code":"PPL",
    "gn:name":"Tannen",
    "gn:population":0,
    "gn:timezone":"Europe/Berlin",
    "iso:country":"DE",
    "wof:name":"Tannen",
    "wof:placetype":"neighbourhood"
},
  "geometry": {"coordinates":[10.36199,47.7242],"type":"Point"}
}