{
  "type": "Feature",
  "properties": {
    "gn:country":"DE",
    "gn:fcode":"PPL",
    "gn:population":0,
    "iso:country":"DE",
    "name:bos_x_preferred":[
        "Altheim"
    ],
    "name:cat_x_preferred":[
        "Altheim"
    ],
    "name:ceb_x_preferred":[
        "Altheim"
    ],
    "name:deu_x_preferred":[
        "Altheim"
    ],
    "name:epo_x_preferred":[
        "Altheim"
    ],
    "name:eus_x_preferred":[
        "Altheim"
    ],
    "name:fas_x_preferred":[
        "\u0627\u0644\u062a\u06cc\u0645"
    ],
    "name:fra_x_preferred":[
        "Altheim"
    ],
    "name:hye_x_preferred":[
        "\u0531\u056c\u0569\u0570\u0561\u0575\u0574"
    ],
    "name:ita_x_preferred":[
        "Altheim"
    ],
    "name:kat_x_preferred":[
        "\u10d0\u10da\u10e2\u10f0\u10d0\u10d8\u10db\u10d8"
    ],
    "name:lmo_x_preferred":[
        "Altheim"
    ],
    "name:nld_x_preferred":[
        "Altheim"
    ],
    "name:pol_x_preferred":[
        "Altheim"
    ],
    "name:slk_x_preferred":[
        "Altheim"
    ],
    "name:srp_x_preferred":[
        "\u0410\u043b\u0442\u0445\u0430\u0458\u043c"
    ],
    "name:swe_x_preferred":[
        "Altheim"
    ],
    "name:vie_x_preferred":[
        "Altheim"
    ],
    "name:vol_x_preferred":[
        "Altheim"
    ],
    "qs_pg:aaroncc":"DE",
    "qs_pg:gn_country":"DE",
    "qs_pg:gn_fcode":"PPL",
    "qs_pg:gn_pop":0,
    "qs_pg:name":"Altheim",
    "qs_pg:name_adm0":"Deutschland",
    "qs_pg:name_adm1":"Saarland",
    "qs_pg:photos":17,
    "qs_pg:photos_1k":3,
    "qs_pg:photos_9k":1,
    "qs_pg:photos_9r":1,
    "qs_pg:photos_all":17,
    "qs_pg:photos_sr":1,
    "qs_pg:pop_sr":0,
    "qs_pg:qs_pg_placetype":"locality",
    "qs_pg:qs_pg_placetype_gp":"Town",
    "qs_pg:woe_adm0":23424829,
    "woe:adm0_id":23424829,
    "woe:name_adm0":"Deutschland",
    "woe:name_adm1":"Saarland",
    "woe:placetype":"Town",
    "wof:name":"Altheim",
    "wof:placetype":"neighbourhood"
},
  "geometry": {"coordinates":[7.31259,49.17189],"type":"Point"}
}