{
  "type": "Feature",
  "properties": {
    "gn:admin1_code":"1.0",
    "gn:admin2_code":"82.0",
    "gn:admin3_code":"8225.0",
    "gn:admin4_code":"8225014.0",
    "gn:asciiname":"Bodigheim",
    "gn:country_code":"DE",
    "gn:dem":315,
    "gn:feature_class":"P",
    "gn:feature_code":"PPL",
    "gn:name":"B\u00f6digheim",
    "gn:population":0,
    "gn:timezone":"Europe/Berlin",
    "iso:country":"DE",
    "wof:name":"Bodigheim",
    "wof:placetype":"neighbourhood"
},
  "geometry": {"coordinates":[9.3137,49.47802],"type":"Point"}
}