{
  "type": "Feature",
  "properties": {
    "gn:gn_country":"DE",
    "gn:gn_fcode":"PPLA4",
    "gn:gn_pop":84,
    "gn:population":84,
    "iso:country":"DE",
    "name:baq_x_preferred":[
        "Str\u00fcbbel"
    ],
    "name:chi_x_preferred":[
        "\u65bd\u7279\u5415\u8d1d\u5c14"
    ],
    "name:dan_x_preferred":[
        "Str\u00fcbbel"
    ],
    "name:dut_x_preferred":[
        "Str\u00fcbbel"
    ],
    "name:eng_x_preferred":[
        "Str\u00fcbbel"
    ],
    "name:epo_x_preferred":[
        "Str\u00fcbbel"
    ],
    "name:fre_x_preferred":[
        "Str\u00fcbbel"
    ],
    "name:ger_x_preferred":[
        "Str\u00fcbbel"
    ],
    "name:hun_x_preferred":[
        "Str\u00fcbbel"
    ],
    "name:ind_x_preferred":[
        "Str\u00fcbbel"
    ],
    "name:ita_x_preferred":[
        "Str\u00fcbbel"
    ],
    "name:mac_x_preferred":[
        "\u0428\u0442\u0440\u0438\u0431\u0435\u043b"
    ],
    "name:may_x_preferred":[
        "Str\u00fcbbel"
    ],
    "name:nob_x_preferred":[
        "Str\u00fcbbel"
    ],
    "name:per_x_preferred":[
        "\u0634\u062a\u0631\u0648\u0628\u0644"
    ],
    "name:pol_x_preferred":[
        "Str\u00fcbbel"
    ],
    "name:por_x_preferred":[
        "Str\u00fcbbel"
    ],
    "name:rum_x_preferred":[
        "Str\u00fcbbel"
    ],
    "name:rus_x_preferred":[
        "\u0428\u0442\u0440\u044e\u0431\u0431\u0435\u043b\u044c"
    ],
    "name:srp_x_preferred":[
        "\u0428\u0442\u0440\u0438\u0431\u0435\u043b"
    ],
    "name:tur_x_preferred":[
        "Str\u00fcbbel"
    ],
    "name:ukr_x_preferred":[
        "\u0428\u0442\u0440\u044e\u0431\u0431\u0435\u043b\u044c"
    ],
    "name:uzb_x_preferred":[
        "Str\u00fcbbel"
    ],
    "name:vie_x_preferred":[
        "Str\u00fcbbel"
    ],
    "name:vol_x_preferred":[
        "Str\u00fcbbel"
    ],
    "name:war_x_preferred":[
        "Str\u00fcbbel"
    ],
    "qs_pg:aaroncc":"DE",
    "qs_pg:gn_country":"DE",
    "qs_pg:gn_fcode":"PPLA4",
    "qs_pg:gn_pop":84,
    "qs_pg:name":"Str\u00fcbbel",
    "qs_pg:photos_9r":0,
    "qs_pg:photos_sr":0,
    "qs_pg:pop_sr":1,
    "qs_pg:qs_pg_placetype":"locality",
    "wof:name":"Str\u00fcbbel",
    "wof:placetype":"locality",
    "wof:population":84
},
  "geometry": {"coordinates":[8.96667,54.26667],"type":"Point"}
}