{
  "type": "Feature",
  "properties": {
    "gn:admin1_code":"2",
    "gn:admin2_code":"92.0",
    "gn:admin3_code":"9275.0",
    "gn:admin4_code":"9275152.0",
    "gn:asciiname":"Kothingrub",
    "gn:country_code":"DE",
    "gn:dem":436,
    "gn:feature_class":"P",
    "gn:feature_code":"PPL",
    "gn:name":"Kothingrub",
    "gn:population":0,
    "gn:timezone":"Europe/Berlin",
    "iso:country":"DE",
    "wof:name":"Kothingrub",
    "wof:placetype":"neighbourhood"
},
  "geometry": {"coordinates":[13.39636,48.75199],"type":"Point"}
}