{
  "type": "Feature",
  "properties": {
    "gn:admin1_code":"2",
    "gn:admin2_code":"93.0",
    "gn:admin3_code":"9376.0",
    "gn:admin4_code":"9376148.0",
    "gn:asciiname":"Sallach",
    "gn:country_code":"DE",
    "gn:dem":506,
    "gn:feature_class":"P",
    "gn:feature_code":"PPL",
    "gn:name":"Sallach",
    "gn:population":0,
    "gn:timezone":"Europe/Berlin",
    "iso:country":"DE",
    "wof:name":"Sallach",
    "wof:placetype":"neighbourhood"
},
  "geometry": {"coordinates":[12.39193,49.42713],"type":"Point"}
}