{
  "type": "Feature",
  "properties": {
    "gn:admin1_code":"2.0",
    "gn:admin2_code":"092",
    "gn:admin3_code":"9276.0",
    "gn:admin4_code":"9276111.0",
    "gn:asciiname":"Wolfertsried",
    "gn:country_code":"DE",
    "gn:dem":637,
    "gn:feature_class":"P",
    "gn:feature_code":"PPL",
    "gn:name":"Wolfertsried",
    "gn:population":0,
    "gn:timezone":"Europe/Berlin",
    "iso:country":"DE",
    "wof:name":"Wolfertsried",
    "wof:placetype":"neighbourhood"
},
  "geometry": {"coordinates":[12.91241,48.97472],"type":"Point"}
}