{
  "type": "Feature",
  "properties": {
    "gn:admin1_code":"2",
    "gn:admin2_code":"95.0",
    "gn:admin3_code":"9572.0",
    "gn:admin4_code":"9572159.0",
    "gn:asciiname":"Dutendorf",
    "gn:country_code":"DE",
    "gn:dem":305,
    "gn:feature_class":"P",
    "gn:feature_code":"PPL",
    "gn:name":"Dutendorf",
    "gn:population":0,
    "gn:timezone":"Europe/Berlin",
    "iso:country":"DE",
    "wof:name":"Dutendorf",
    "wof:placetype":"neighbourhood"
},
  "geometry": {"coordinates":[10.65522,49.69523],"type":"Point"}
}