{
  "type": "Feature",
  "properties": {
    "gn:admin1_code":"11",
    "gn:admin2_code":"0.0",
    "gn:admin3_code":"12066.0",
    "gn:admin4_code":"12066304.0",
    "gn:asciiname":"Sedlitz",
    "gn:country_code":"DE",
    "gn:dem":109,
    "gn:feature_class":"P",
    "gn:feature_code":"PPL",
    "gn:name":"Sedlitz",
    "gn:population":0,
    "gn:timezone":"Europe/Berlin",
    "iso:country":"DE",
    "wof:name":"Sedlitz",
    "wof:placetype":"neighbourhood"
},
  "geometry": {"coordinates":[14.05905,51.55107],"type":"Point"}
}