{
  "type": "Feature",
  "properties": {
    "gn:admin1_code":"2.0",
    "gn:admin2_code":"94.0",
    "gn:admin3_code":"9471.0",
    "gn:admin4_code":"9471152.0",
    "gn:asciiname":"Appendorf",
    "gn:country_code":"DE",
    "gn:dem":266,
    "gn:feature_class":"P",
    "gn:feature_code":"PPL",
    "gn:name":"Appendorf",
    "gn:population":0,
    "gn:timezone":"Europe/Berlin",
    "iso:country":"DE",
    "wof:name":"Appendorf",
    "wof:placetype":"neighbourhood"
},
  "geometry": {"coordinates":[10.79937,49.96843],"type":"Point"}
}