{
  "type": "Feature",
  "properties": {
    "gn:admin1_code":"10",
    "gn:admin2_code":"0.0",
    "gn:admin3_code":"1059.0",
    "gn:admin4_code":"1059184.0",
    "gn:asciiname":"Munkwolstrup",
    "gn:country_code":"DE",
    "gn:dem":38,
    "gn:feature_class":"P",
    "gn:feature_code":"PPL",
    "gn:name":"Munkwolstrup",
    "gn:population":0,
    "gn:timezone":"Europe/Berlin",
    "iso:country":"DE",
    "wof:name":"Munkwolstrup",
    "wof:placetype":"neighbourhood"
},
  "geometry": {"coordinates":[9.45432,54.72495],"type":"Point"}
}