{
  "type": "Feature",
  "properties": {
    "gn:admin1_code":"14.0",
    "gn:admin2_code":"0.0",
    "gn:admin3_code":"15087.0",
    "gn:admin4_code":"15087412.0",
    "gn:asciiname":"Auerberg",
    "gn:country_code":"DE",
    "gn:dem":498,
    "gn:feature_class":"P",
    "gn:feature_code":"PPL",
    "gn:name":"Auerberg",
    "gn:population":0,
    "gn:timezone":"Europe/Berlin",
    "iso:country":"DE",
    "name:deu_x_preferred":[
        "Auerberg"
    ],
    "wof:name":"Auerberg",
    "wof:placetype":"neighbourhood"
},
  "geometry": {"coordinates":[11.01214,51.58861],"type":"Point"}
}