{
  "type": "Feature",
  "properties": {
    "gn:admin1_code":"1",
    "gn:admin2_code":"84.0",
    "gn:admin3_code":"8437.0",
    "gn:admin4_code":"8437053.0",
    "gn:asciiname":"Olkofen",
    "gn:country_code":"DE",
    "gn:dem":561,
    "gn:feature_class":"P",
    "gn:feature_code":"PPL",
    "gn:name":"\u00d6lkofen",
    "gn:population":0,
    "gn:timezone":"Europe/Berlin",
    "iso:country":"DE",
    "wof:name":"Olkofen",
    "wof:placetype":"neighbourhood"
},
  "geometry": {"coordinates":[9.38829,48.03557],"type":"Point"}
}