{
  "type": "Feature",
  "properties": {
    "gn:country":"DE",
    "gn:fcode":"PPL",
    "gn:population":0,
    "iso:country":"DE",
    "name:cat_x_preferred":[
        "Merzdorf"
    ],
    "name:ceb_x_preferred":[
        "Merzdorf"
    ],
    "name:dan_x_preferred":[
        "Merzdorf"
    ],
    "name:deu_x_preferred":[
        "Merzdorf"
    ],
    "name:epo_x_preferred":[
        "Merzdorf"
    ],
    "name:eus_x_preferred":[
        "Merzdorf"
    ],
    "name:hun_x_preferred":[
        "Merzdorf"
    ],
    "name:hye_x_preferred":[
        "\u0544\u0565\u0580\u0581\u0564\u0578\u0580\u0586"
    ],
    "name:ita_x_preferred":[
        "Merzdorf"
    ],
    "name:mkd_x_preferred":[
        "\u041c\u0435\u0440\u0446\u0434\u043e\u0440\u0444"
    ],
    "name:msa_x_preferred":[
        "Merzdorf"
    ],
    "name:nld_x_preferred":[
        "Merzdorf"
    ],
    "name:pol_x_preferred":[
        "Merzdorf"
    ],
    "name:ron_x_preferred":[
        "Merzdorf"
    ],
    "name:rus_x_preferred":[
        "\u041c\u0435\u0440\u0446\u0434\u043e\u0440\u0444"
    ],
    "name:spa_x_preferred":[
        "Merzdorf"
    ],
    "name:srp_x_preferred":[
        "\u041c\u0435\u0440\u0446\u0434\u043e\u0440\u0444"
    ],
    "name:ukr_x_preferred":[
        "\u041c\u0435\u0440\u0446\u0434\u043e\u0440\u0444"
    ],
    "name:uzb_x_preferred":[
        "Merzdorf"
    ],
    "name:vie_x_preferred":[
        "Merzdorf"
    ],
    "name:vol_x_preferred":[
        "Merzdorf"
    ],
    "name:war_x_preferred":[
        "Merzdorf"
    ],
    "name:zho_x_preferred":[
        "\u6885\u5c14\u8328\u591a\u592b"
    ],
    "qs_pg:aaroncc":"DE",
    "qs_pg:gn_country":"DE",
    "qs_pg:gn_fcode":"PPL",
    "qs_pg:gn_pop":0,
    "qs_pg:name":"Merzdorf",
    "qs_pg:name_adm0":"Deutschland",
    "qs_pg:name_adm1":"Sachsen",
    "qs_pg:photos":5,
    "qs_pg:photos_1k":1,
    "qs_pg:photos_9k":1,
    "qs_pg:photos_9r":1,
    "qs_pg:photos_all":5,
    "qs_pg:photos_sr":1,
    "qs_pg:pop_sr":0,
    "qs_pg:qs_pg_placetype":"locality",
    "qs_pg:qs_pg_placetype_gp":"Town",
    "qs_pg:woe_adm0":23424829,
    "woe:adm0_id":23424829,
    "woe:name_adm0":"Deutschland",
    "woe:name_adm1":"Sachsen",
    "woe:placetype":"Town",
    "wof:name":"Merzdorf",
    "wof:placetype":"neighbourhood"
},
  "geometry": {"coordinates":[13.01726,50.92087],"type":"Point"}
}