{
  "type": "Feature",
  "properties": {
    "gn:admin1_code":"2",
    "gn:admin2_code":"97.0",
    "gn:admin3_code":"9778.0",
    "gn:admin4_code":"9778134.0",
    "gn:asciiname":"Leutenbuch",
    "gn:country_code":"DE",
    "gn:dem":574,
    "gn:feature_class":"P",
    "gn:feature_code":"PPL",
    "gn:name":"Leutenbuch",
    "gn:population":0,
    "gn:timezone":"Europe/Berlin",
    "iso:country":"DE",
    "wof:name":"Leutenbuch",
    "wof:placetype":"neighbourhood"
},
  "geometry": {"coordinates":[10.51667,48.21667],"type":"Point"}
}