{
  "type": "Feature",
  "properties": {
    "gn:admin1_code":"9.0",
    "gn:admin2_code":"0.0",
    "gn:admin3_code":"10041.0",
    "gn:admin4_code":"10041100.0",
    "gn:asciiname":"Altenkessel",
    "gn:country_code":"DE",
    "gn:dem":262,
    "gn:feature_class":"P",
    "gn:feature_code":"PPL",
    "gn:name":"Altenkessel",
    "gn:population":0,
    "gn:timezone":"Europe/Berlin",
    "iso:country":"DE",
    "wof:name":"Altenkessel",
    "wof:placetype":"neighbourhood"
},
  "geometry": {"coordinates":[6.91619,49.25998],"type":"Point"}
}