{
  "type": "Feature",
  "properties": {
    "gn:admin1_code":"5",
    "gn:admin2_code":"64.0",
    "gn:admin3_code":"6440.0",
    "gn:admin4_code":"6440016.0",
    "gn:asciiname":"Geiss-Nidda",
    "gn:country_code":"DE",
    "gn:dem":152,
    "gn:feature_class":"P",
    "gn:feature_code":"PPL",
    "gn:name":"Gei\u00df-Nidda",
    "gn:population":0,
    "gn:timezone":"Europe/Berlin",
    "iso:country":"DE",
    "wof:name":"Geiss-Nidda",
    "wof:placetype":"neighbourhood"
},
  "geometry": {"coordinates":[8.96939,50.40389],"type":"Point"}
}