{
  "type": "Feature",
  "properties": {
    "gn:admin1_code":"2",
    "gn:admin2_code":"97.0",
    "gn:admin3_code":"9776.0",
    "gn:admin4_code":"9776125.0",
    "gn:asciiname":"Hagspiel",
    "gn:country_code":"DE",
    "gn:dem":728,
    "gn:feature_class":"P",
    "gn:feature_code":"PPL",
    "gn:name":"Hagspiel",
    "gn:population":0,
    "gn:timezone":"Europe/Berlin",
    "iso:country":"DE",
    "wof:name":"Hagspiel",
    "wof:placetype":"neighbourhood"
},
  "geometry": {"coordinates":[9.8526,47.55472],"type":"Point"}
}