{
  "type": "Feature",
  "properties": {
    "gn:admin1_code":"2",
    "gn:admin2_code":"92.0",
    "gn:admin3_code":"9278.0",
    "gn:admin4_code":"9278149.0",
    "gn:asciiname":"Haberswohr",
    "gn:country_code":"DE",
    "gn:dem":316,
    "gn:feature_class":"P",
    "gn:feature_code":"PPLL",
    "gn:name":"Habersw\u00f6hr",
    "gn:population":0,
    "gn:timezone":"Europe/Berlin",
    "iso:country":"DE",
    "wof:name":"Haberswohr",
    "wof:placetype":"neighbourhood"
},
  "geometry": {"coordinates":[12.8281,48.86513],"type":"Point"}
}