{
  "type": "Feature",
  "properties": {
    "gn:admin1_code":"2",
    "gn:admin2_code":"95.0",
    "gn:admin3_code":"9571.0",
    "gn:admin4_code":"9571139.0",
    "gn:asciiname":"Sulzach",
    "gn:country_code":"DE",
    "gn:dem":446,
    "gn:feature_class":"P",
    "gn:feature_code":"PPL",
    "gn:name":"Sulzach",
    "gn:population":0,
    "gn:timezone":"Europe/Berlin",
    "iso:country":"DE",
    "name:deu_x_preferred":[
        "Sulzach"
    ],
    "wof:name":"Sulzach",
    "wof:placetype":"neighbourhood"
},
  "geometry": {"coordinates":[10.36789,49.12121],"type":"Point"}
}