{
  "type": "Feature",
  "properties": {
    "gn:admin1_code":"2.0",
    "gn:admin2_code":"097",
    "gn:admin3_code":"9778.0",
    "gn:admin4_code":"9778173.0",
    "gn:asciiname":"Westernach",
    "gn:country_code":"DE",
    "gn:dem":592,
    "gn:feature_class":"P",
    "gn:feature_code":"PPL",
    "gn:name":"Westernach",
    "gn:population":0,
    "gn:timezone":"Europe/Berlin",
    "iso:country":"DE",
    "name:ceb_x_preferred":[
        "Westernach"
    ],
    "name:deu_x_preferred":[
        "Westernach"
    ],
    "name:swe_x_preferred":[
        "Westernach"
    ],
    "wof:name":"Westernach",
    "wof:placetype":"neighbourhood"
},
  "geometry": {"coordinates":[10.464,48.07248],"type":"Point"}
}