{
  "type": "Feature",
  "properties": {
    "gn:admin1_code":"1",
    "gn:admin2_code":"82.0",
    "gn:admin3_code":"8216.0",
    "gn:admin4_code":"8216041.0",
    "gn:asciiname":"Unzhurst",
    "gn:country_code":"DE",
    "gn:dem":131,
    "gn:feature_class":"P",
    "gn:feature_code":"PPL",
    "gn:name":"Unzhurst",
    "gn:population":0,
    "gn:timezone":"Europe/Berlin",
    "iso:country":"DE",
    "wof:name":"Unzhurst",
    "wof:placetype":"neighbourhood"
},
  "geometry": {"coordinates":[8.05407,48.68749],"type":"Point"}
}