{
  "type": "Feature",
  "properties": {
    "gn:admin1_code":"7",
    "gn:admin2_code":"57.0",
    "gn:admin3_code":"5766.0",
    "gn:admin4_code":"5766020.0",
    "gn:asciiname":"Obernhausen",
    "gn:country_code":"DE",
    "gn:dem":139,
    "gn:feature_class":"P",
    "gn:feature_code":"PPL",
    "gn:name":"Obernhausen",
    "gn:population":0,
    "gn:timezone":"Europe/Berlin",
    "iso:country":"DE",
    "wof:name":"Obernhausen",
    "wof:placetype":"neighbourhood"
},
  "geometry": {"coordinates":[8.953,51.96442],"type":"Point"}
}