{
  "type": "Feature",
  "properties": {
    "gn:admin1_code":"1",
    "gn:admin2_code":"83.0",
    "gn:admin3_code":"8336.0",
    "gn:admin4_code":"8336080.0",
    "gn:asciiname":"Entenschwand",
    "gn:country_code":"DE",
    "gn:dem":667,
    "gn:feature_class":"P",
    "gn:feature_code":"PPL",
    "gn:name":"Entenschwand",
    "gn:population":0,
    "gn:timezone":"Europe/Berlin",
    "iso:country":"DE",
    "wof:name":"Entenschwand",
    "wof:placetype":"neighbourhood"
},
  "geometry": {"coordinates":[7.88003,47.78885],"type":"Point"}
}