{
  "type": "Feature",
  "properties": {
    "gn:admin1_code":"14",
    "gn:admin2_code":"0.0",
    "gn:admin3_code":"15088.0",
    "gn:admin4_code":"15088020.0",
    "gn:asciiname":"Kauern",
    "gn:country_code":"DE",
    "gn:dem":109,
    "gn:feature_class":"P",
    "gn:feature_code":"PPL",
    "gn:name":"Kauern",
    "gn:population":0,
    "gn:timezone":"Europe/Berlin",
    "iso:country":"DE",
    "name:bak_x_preferred":[
        "\u041a\u0430\u0443\u0435\u0440\u043d"
    ],
    "name:ceb_x_preferred":[
        "Kauern"
    ],
    "name:deu_x_preferred":[
        "Kauern"
    ],
    "name:epo_x_preferred":[
        "Kauern"
    ],
    "name:eus_x_preferred":[
        "Kauern"
    ],
    "name:fas_x_preferred":[
        "\u06a9\u0627\u0648\u0631\u0646"
    ],
    "name:fra_x_preferred":[
        "Kauern"
    ],
    "name:hun_x_preferred":[
        "Kauern"
    ],
    "name:ita_x_preferred":[
        "Kauern"
    ],
    "name:kaz_x_preferred":[
        "\u041a\u0430\u0443\u0435\u0440\u043d"
    ],
    "name:kir_x_preferred":[
        "\u041a\u0430\u0443\u0435\u0440\u043d"
    ],
    "name:mkd_x_preferred":[
        "\u041a\u0430\u0443\u0435\u0440\u043d"
    ],
    "name:msa_x_preferred":[
        "Kauern"
    ],
    "name:nld_x_preferred":[
        "Kauern"
    ],
    "name:pol_x_preferred":[
        "Kauern"
    ],
    "name:por_x_preferred":[
        "Kauern"
    ],
    "name:ron_x_preferred":[
        "Kauern"
    ],
    "name:rus_x_preferred":[
        "\u041a\u0430\u0443\u044d\u0440\u043d"
    ],
    "name:spa_x_preferred":[
        "Kauern"
    ],
    "name:srp_x_preferred":[
        "\u041a\u0430\u0443\u0435\u0440\u043d"
    ],
    "name:ukr_x_preferred":[
        "\u041a\u0430\u0443\u0435\u0440\u043d"
    ],
    "name:uzb_x_preferred":[
        "Kauern"
    ],
    "name:vol_x_preferred":[
        "Kauern"
    ],
    "name:war_x_preferred":[
        "Kauern"
    ],
    "wof:name":"Kauern",
    "wof:placetype":"neighbourhood"
},
  "geometry": {"coordinates":[12.11228,51.27989],"type":"Point"}
}