{
  "type": "Feature",
  "properties": {
    "gn:gn_country":"DE",
    "gn:gn_fcode":"PPLA4",
    "gn:gn_pop":326,
    "gn:population":326,
    "iso:country":"DE",
    "name:bak_x_preferred":[
        "\u0413\u0440\u0438\u0444\u0448\u0442\u0435\u0434\u0442"
    ],
    "name:baq_x_preferred":[
        "Griefstedt"
    ],
    "name:chi_x_preferred":[
        "\u683c\u91cc\u592b\u65af\u7279"
    ],
    "name:dut_x_preferred":[
        "Griefstedt"
    ],
    "name:eng_x_preferred":[
        "Griefstedt"
    ],
    "name:epo_x_preferred":[
        "Griefstedt"
    ],
    "name:fre_x_preferred":[
        "Griefstedt"
    ],
    "name:ger_x_preferred":[
        "Griefstedt"
    ],
    "name:hun_x_preferred":[
        "Griefstedt"
    ],
    "name:ita_x_preferred":[
        "Griefstedt"
    ],
    "name:mac_x_preferred":[
        "\u0413\u0440\u0438\u0444\u0448\u0442\u0435\u0442"
    ],
    "name:may_x_preferred":[
        "Griefstedt"
    ],
    "name:per_x_preferred":[
        "\u06af\u0631\u06cc\u0641\u0634\u062a\u062f\u062a"
    ],
    "name:pol_x_preferred":[
        "Griefstedt"
    ],
    "name:por_x_preferred":[
        "Griefstedt"
    ],
    "name:rum_x_preferred":[
        "Griefstedt"
    ],
    "name:rus_x_preferred":[
        "\u0413\u0440\u0438\u0444\u0448\u0442\u0435\u0434\u0442"
    ],
    "name:srp_x_preferred":[
        "\u0413\u0440\u0438\u0444\u0448\u0442\u0435\u0442"
    ],
    "name:ukr_x_preferred":[
        "\u0413\u0440\u0456\u0444\u0448\u0442\u0435\u0434\u0442"
    ],
    "name:uzb_x_preferred":[
        "Griefstedt"
    ],
    "name:vie_x_preferred":[
        "Griefstedt"
    ],
    "name:vol_x_preferred":[
        "Griefstedt"
    ],
    "name:war_x_preferred":[
        "Griefstedt"
    ],
    "qs_pg:aaroncc":"DE",
    "qs_pg:gn_country":"DE",
    "qs_pg:gn_fcode":"PPLA4",
    "qs_pg:gn_pop":326,
    "qs_pg:name":"Griefstedt",
    "qs_pg:photos_9r":0,
    "qs_pg:photos_sr":0,
    "qs_pg:pop_sr":2,
    "qs_pg:qs_pg_placetype":"locality",
    "wof:name":"Griefstedt",
    "wof:placetype":"locality",
    "wof:population":326
},
  "geometry": {"coordinates":[11.12932,51.22957],"type":"Point"}
}