{
  "type": "Feature",
  "properties": {
    "gn:admin1_code":"6",
    "gn:admin2_code":"0.0",
    "gn:admin3_code":"3353.0",
    "gn:admin4_code":"3353038.0",
    "gn:asciiname":"Kampen",
    "gn:country_code":"DE",
    "gn:dem":62,
    "gn:feature_class":"P",
    "gn:feature_code":"PPL",
    "gn:name":"Kampen",
    "gn:population":0,
    "gn:timezone":"Europe/Berlin",
    "iso:country":"DE",
    "wof:name":"Kampen",
    "wof:placetype":"neighbourhood"
},
  "geometry": {"coordinates":[9.77577,53.24211],"type":"Point"}
}