{
  "type": "Feature",
  "properties": {
    "gn:admin1_code":"6",
    "gn:admin2_code":"0.0",
    "gn:admin3_code":"3353.0",
    "gn:admin4_code":"3353038.0",
    "gn:asciiname":"Kampen",
    "gn:country_code":"DE",
    "gn:dem":62,
    "gn:feature_class":"P",
    "gn:feature_code":"PPL",
    "gn:name":"Kampen",
    "gn:population":0,
    "gn:timezone":"Europe/Berlin",
    "iso:country":"DE",
    "name:afr_x_preferred":[
        "Kampen"
    ],
    "name:ceb_x_preferred":[
        "Kampen"
    ],
    "name:dan_x_preferred":[
        "Kampen"
    ],
    "name:deu_x_preferred":[
        "Kampen"
    ],
    "name:epo_x_preferred":[
        "Kampen"
    ],
    "name:fin_x_preferred":[
        "Kampen"
    ],
    "name:fra_x_preferred":[
        "Kampen"
    ],
    "name:ita_x_preferred":[
        "Kampen"
    ],
    "name:jpn_x_preferred":[
        "\u30ab\u30f3\u30da\u30f3"
    ],
    "name:nds_x_preferred":[
        "Kampen"
    ],
    "name:nld_x_preferred":[
        "Kampen"
    ],
    "name:nor_x_preferred":[
        "Kampen"
    ],
    "name:pol_x_preferred":[
        "Kampen"
    ],
    "name:rus_x_preferred":[
        "\u041a\u0430\u043c\u043f\u0435\u043d"
    ],
    "name:slv_x_preferred":[
        "Kampen"
    ],
    "name:swe_x_preferred":[
        "Kampen"
    ],
    "name:vol_x_preferred":[
        "Kampen"
    ],
    "wof:name":"Kampen",
    "wof:placetype":"neighbourhood"
},
  "geometry": {"coordinates":[9.77577,53.24211],"type":"Point"}
}