{
  "type": "Feature",
  "properties": {
    "gn:gn_country":"DE",
    "gn:gn_fcode":"PPLA4",
    "gn:gn_pop":197,
    "gn:population":197,
    "iso:country":"DE",
    "name:bak_x_preferred":[
        "\u0423\u043d\u0442\u0435\u0440\u0431\u043e\u0434\u043d\u0438\u0446"
    ],
    "name:baq_x_preferred":[
        "Unterbodnitz"
    ],
    "name:chi_x_preferred":[
        "\u7fc1\u7279\u5c14\u535a\u5fb7\u5c3c\u8328"
    ],
    "name:dut_x_preferred":[
        "Unterbodnitz"
    ],
    "name:eng_x_preferred":[
        "Unterbodnitz"
    ],
    "name:epo_x_preferred":[
        "Unterbodnitz"
    ],
    "name:fre_x_preferred":[
        "Unterbodnitz"
    ],
    "name:ger_x_preferred":[
        "Unterbodnitz"
    ],
    "name:hun_x_preferred":[
        "Unterbodnitz"
    ],
    "name:ita_x_preferred":[
        "Unterbodnitz"
    ],
    "name:kaz_x_preferred":[
        "\u0423\u043d\u0442\u0435\u0440\u0431\u043e\u0434\u043d\u0438\u0446"
    ],
    "name:kir_x_preferred":[
        "\u0423\u043d\u0442\u0435\u0440\u0431\u043e\u0434\u043d\u0438\u0446"
    ],
    "name:mac_x_preferred":[
        "\u0423\u043d\u0442\u0435\u0440\u0431\u043e\u0434\u043d\u0438\u0446"
    ],
    "name:may_x_preferred":[
        "Unterbodnitz"
    ],
    "name:per_x_preferred":[
        "\u0627\u0648\u0646\u062a\u0631\u0628\u0648\u062f\u0646\u06cc\u062a\u0633"
    ],
    "name:pol_x_preferred":[
        "Unterbodnitz"
    ],
    "name:por_x_preferred":[
        "Unterbodnitz"
    ],
    "name:rum_x_preferred":[
        "Unterbodnitz"
    ],
    "name:rus_x_preferred":[
        "\u0423\u043d\u0442\u0435\u0440\u0431\u043e\u0434\u043d\u0438\u0446"
    ],
    "name:srp_x_preferred":[
        "\u0423\u043d\u0442\u0435\u0440\u0431\u043e\u0434\u043d\u0438\u0446"
    ],
    "name:ukr_x_preferred":[
        "\u0423\u043d\u0442\u0435\u0440\u0431\u043e\u0434\u043d\u0456\u0446"
    ],
    "name:uzb_x_preferred":[
        "Unterbodnitz"
    ],
    "name:vie_x_preferred":[
        "Unterbodnitz"
    ],
    "name:vol_x_preferred":[
        "Unterbodnitz"
    ],
    "name:war_x_preferred":[
        "Unterbodnitz"
    ],
    "qs_pg:aaroncc":"DE",
    "qs_pg:gn_country":"DE",
    "qs_pg:gn_fcode":"PPLA4",
    "qs_pg:gn_pop":197,
    "qs_pg:name":"Unterbodnitz",
    "qs_pg:photos_9r":0,
    "qs_pg:photos_sr":0,
    "qs_pg:pop_sr":1,
    "qs_pg:qs_pg_placetype":"locality",
    "wof:name":"Unterbodnitz",
    "wof:placetype":"locality",
    "wof:population":197
},
  "geometry": {"coordinates":[11.65,50.81667],"type":"Point"}
}