{
  "type": "Feature",
  "properties": {
    "gn:admin1_code":"14",
    "gn:admin2_code":"0.0",
    "gn:admin3_code":"15089.0",
    "gn:admin4_code":"15089310.0",
    "gn:asciiname":"Rothenfoerde",
    "gn:country_code":"DE",
    "gn:dem":68,
    "gn:feature_class":"P",
    "gn:feature_code":"PPL",
    "gn:name":"Rothenf\u00f6rde",
    "gn:population":0,
    "gn:timezone":"Europe/Berlin",
    "iso:country":"DE",
    "wof:name":"Rothenfoerde",
    "wof:placetype":"neighbourhood"
},
  "geometry": {"coordinates":[11.53032,51.90859],"type":"Point"}
}