{
  "type": "Feature",
  "properties": {
    "gn:admin1_code":"10.0",
    "gn:admin2_code":"0.0",
    "gn:admin3_code":"1058.0",
    "gn:admin4_code":"1058100.0",
    "gn:asciiname":"Lust",
    "gn:country_code":"DE",
    "gn:dem":-2,
    "gn:feature_class":"P",
    "gn:feature_code":"PPLL",
    "gn:name":"Lust",
    "gn:population":0,
    "gn:timezone":"Europe/Berlin",
    "iso:country":"DE",
    "name:ara_x_preferred":[
        "\u0634\u0647\u0648\u0629"
    ],
    "name:ast_x_preferred":[
        "Lluxuria"
    ],
    "name:ben_x_preferred":[
        "\u0995\u09be\u09ae"
    ],
    "name:bre_x_preferred":[
        "Orged"
    ],
    "name:bul_x_preferred":[
        "\u041f\u043e\u0445\u043e\u0442"
    ],
    "name:cat_x_preferred":[
        "Lux\u00faria"
    ],
    "name:ces_x_preferred":[
        "Cht\u00ed\u010d"
    ],
    "name:ckb_x_preferred":[
        "\u0634\u06d5\u06be\u0648\u06d5\u062a"
    ],
    "name:dan_x_preferred":[
        "Beg\u00e6r"
    ],
    "name:deu_x_preferred":[
        "Wollust"
    ],
    "name:eml_x_preferred":[
        "Lus\u00f9ria"
    ],
    "name:epo_x_preferred":[
        "Volupto"
    ],
    "name:eus_x_preferred":[
        "Lizunkeria"
    ],
    "name:fas_x_preferred":[
        "\u0634\u0647\u0648\u062a"
    ],
    "name:fin_x_preferred":[
        "Himo"
    ],
    "name:fra_x_preferred":[
        "Luxure"
    ],
    "name:glg_x_preferred":[
        "Luxuria"
    ],
    "name:heb_x_preferred":[
        "\u05ea\u05e9\u05d5\u05e7\u05d4"
    ],
    "name:hin_x_preferred":[
        "\u0935\u093e\u0938\u0928\u093e"
    ],
    "name:ido_x_preferred":[
        "Luxurio"
    ],
    "name:ind_x_preferred":[
        "Hawa nafsu"
    ],
    "name:ita_x_preferred":[
        "Lussuria"
    ],
    "name:lat_x_preferred":[
        "Luxuries"
    ],
    "name:lim_x_preferred":[
        "L\u00f6s"
    ],
    "name:lit_x_preferred":[
        "Geismas"
    ],
    "name:msa_x_preferred":[
        "Nafsu"
    ],
    "name:new_x_preferred":[
        "\u0935\u093e\u0938\u0928\u093e"
    ],
    "name:nld_x_preferred":[
        "Lust"
    ],
    "name:nor_x_preferred":[
        "Lyst"
    ],
    "name:pan_x_preferred":[
        "\u0a35\u0a3e\u0a38\u0a28\u0a3e"
    ],
    "name:pol_x_preferred":[
        "Po\u017c\u0105danie"
    ],
    "name:por_x_preferred":[
        "Lux\u00faria"
    ],
    "name:ron_x_preferred":[
        "Desfr\u00e2nare"
    ],
    "name:rus_x_preferred":[
        "\u041f\u043e\u0445\u043e\u0442\u044c"
    ],
    "name:sco_x_preferred":[
        "Lust"
    ],
    "name:sna_x_preferred":[
        "Ruchiva"
    ],
    "name:spa_x_preferred":[
        "Lujuria"
    ],
    "name:swa_x_preferred":[
        "Uzinifu"
    ],
    "name:swe_x_preferred":[
        "Lust"
    ],
    "name:tam_x_preferred":[
        "\u0b87\u0b9a\u0bcd\u0b9a\u0bc8"
    ],
    "name:tgl_x_preferred":[
        "Kahalayan"
    ],
    "name:ukr_x_preferred":[
        "\u0425\u0442\u0438\u0432\u0456\u0441\u0442\u044c"
    ],
    "name:war_x_preferred":[
        "Urag"
    ],
    "name:yid_x_preferred":[
        "\u05d2\u05dc\u05d5\u05e1\u05d8"
    ],
    "wof:name":"Lust",
    "wof:placetype":"neighbourhood"
},
  "geometry": {"coordinates":[9.51667,54.16667],"type":"Point"}
}