{
  "type": "Feature",
  "properties": {
    "gn:admin1_code":"2",
    "gn:admin2_code":"94.0",
    "gn:admin3_code":"9476.0",
    "gn:admin4_code":"9476146.0",
    "gn:asciiname":"Nagel",
    "gn:country_code":"DE",
    "gn:dem":289,
    "gn:feature_class":"P",
    "gn:feature_code":"PPL",
    "gn:name":"Nagel",
    "gn:population":0,
    "gn:timezone":"Europe/Berlin",
    "iso:country":"DE",
    "name:ceb_x_preferred":[
        "Nagel"
    ],
    "name:dan_x_preferred":[
        "Nagel"
    ],
    "name:deu_x_preferred":[
        "Nagel"
    ],
    "name:fra_x_preferred":[
        "Nagel"
    ],
    "name:heb_x_preferred":[
        "\u05e0\u05d2\u05dc"
    ],
    "name:jpn_x_preferred":[
        "\u30cd\u30a4\u30eb"
    ],
    "name:nld_x_preferred":[
        "Nagel"
    ],
    "name:pol_x_preferred":[
        "Nagel"
    ],
    "name:rus_x_preferred":[
        "\u041d\u0430\u0433\u0435\u043b\u044c"
    ],
    "name:spa_x_preferred":[
        "Clavo"
    ],
    "name:swe_x_preferred":[
        "Nagel"
    ],
    "name:yid_x_preferred":[
        "\u05e0\u05d0\u05d2\u05dc"
    ],
    "wof:name":"Nagel",
    "wof:placetype":"neighbourhood"
},
  "geometry": {"coordinates":[11.24259,50.1887],"type":"Point"}
}