{
  "type": "Feature",
  "properties": {
    "gn:admin1_code":"13.0",
    "gn:admin2_code":"00",
    "gn:admin3_code":"14627.0",
    "gn:admin4_code":"14627200.0",
    "gn:asciiname":"Zottewitz",
    "gn:country_code":"DE",
    "gn:dem":155,
    "gn:feature_class":"P",
    "gn:feature_code":"PPL",
    "gn:name":"Zottewitz",
    "gn:population":0,
    "gn:timezone":"Europe/Berlin",
    "iso:country":"DE",
    "wof:name":"Zottewitz",
    "wof:placetype":"neighbourhood"
},
  "geometry": {"coordinates":[13.44619,51.24711],"type":"Point"}
}