{
  "type": "Feature",
  "properties": {
    "gn:admin1_code":"6",
    "gn:admin2_code":"0.0",
    "gn:admin3_code":"3151.0",
    "gn:admin4_code":"3151034.0",
    "gn:asciiname":"Eickhorst",
    "gn:country_code":"DE",
    "gn:dem":86,
    "gn:elevation":"85.0",
    "gn:feature_class":"P",
    "gn:feature_code":"PPL",
    "gn:name":"Eickhorst",
    "gn:population":432,
    "gn:timezone":"Europe/Berlin",
    "iso:country":"DE",
    "name:deu_x_preferred":[
        "Eickhorst (Vordorf)"
    ],
    "name:nds_x_preferred":[
        "Eikhost"
    ],
    "name:osx_x_preferred":[
        "Hechorst [a. 1007]"
    ],
    "wof:name":"Eickhorst",
    "wof:placetype":"neighbourhood",
    "wof:population":432
},
  "geometry": {"coordinates":[10.49486,52.35652],"type":"Point"}
}