{
  "type": "Feature",
  "properties": {
    "gn:admin1_code":"11",
    "gn:admin2_code":"0.0",
    "gn:admin3_code":"12071.0",
    "gn:admin4_code":"12071074.0",
    "gn:asciiname":"Friedrichshain",
    "gn:country_code":"DE",
    "gn:dem":144,
    "gn:feature_class":"P",
    "gn:feature_code":"PPL",
    "gn:name":"Friedrichshain",
    "gn:population":0,
    "gn:timezone":"Europe/Berlin",
    "iso:country":"DE",
    "name:bel_x_preferred":[
        "\u0424\u0440\u044b\u0434\u0440\u044b\u0445\u0441\u0433\u0430\u0439\u043d"
    ],
    "name:bre_x_preferred":[
        "Friedrichshain"
    ],
    "name:ceb_x_preferred":[
        "Friedrichshain"
    ],
    "name:dan_x_preferred":[
        "Friedrichshain"
    ],
    "name:deu_x_preferred":[
        "Berlin-Friedrichshain"
    ],
    "name:est_x_preferred":[
        "Friedrichshain"
    ],
    "name:fas_x_preferred":[
        "\u0641\u0631\u06cc\u062f\u0631\u0627\u06cc\u0634\u0633\u0647\u0627\u06cc\u0646"
    ],
    "name:fin_x_preferred":[
        "Friedrichshain"
    ],
    "name:fra_x_preferred":[
        "Berlin-Friedrichshain"
    ],
    "name:heb_x_preferred":[
        "\u05e4\u05e8\u05d9\u05d3\u05e8\u05d9\u05db\u05e1\u05d4\u05d9\u05d9\u05df"
    ],
    "name:ita_x_preferred":[
        "Friedrichshain"
    ],
    "name:lat_x_preferred":[
        "Friedrichshain"
    ],
    "name:nld_x_preferred":[
        "Berlin-Friedrichshain"
    ],
    "name:nor_x_preferred":[
        "Friedrichshain"
    ],
    "name:pnb_x_preferred":[
        "\u0641\u0631\u06cc\u0688\u0631\u0634\u06c1\u0627\u0626\u06cc\u0646-\u06a9\u0631\u06cc\u0648\u0632\u0628\u0631\u06af"
    ],
    "name:pol_x_preferred":[
        "Friedrichshain"
    ],
    "name:rus_x_preferred":[
        "\u0424\u0440\u0438\u0434\u0440\u0438\u0445\u0441\u0445\u0430\u0439\u043d"
    ],
    "name:spa_x_preferred":[
        "Friedrichshain"
    ],
    "name:swe_x_preferred":[
        "Friedrichshain"
    ],
    "name:tur_x_preferred":[
        "Friedrichshain"
    ],
    "name:zho_x_preferred":[
        "\u8153\u7279\u70c8\u65af\u6d77\u6069"
    ],
    "wof:name":"Friedrichshain",
    "wof:placetype":"neighbourhood"
},
  "geometry": {"coordinates":[14.57346,51.60388],"type":"Point"}
}