{
  "type": "Feature",
  "properties": {
    "gn:admin1_code":"2.0",
    "gn:admin2_code":"097",
    "gn:admin3_code":"9771.0",
    "gn:admin4_code":"9771130.0",
    "gn:asciiname":"Wulfertshausen",
    "gn:country_code":"DE",
    "gn:dem":513,
    "gn:feature_class":"P",
    "gn:feature_code":"PPL",
    "gn:name":"Wulfertshausen",
    "gn:population":0,
    "gn:timezone":"Europe/Berlin",
    "iso:country":"DE",
    "wof:name":"Wulfertshausen",
    "wof:placetype":"neighbourhood"
},
  "geometry": {"coordinates":[10.98744,48.38248],"type":"Point"}
}