{
  "type": "Feature",
  "properties": {
    "gn:admin1_code":"11.0",
    "gn:admin2_code":"0.0",
    "gn:admin3_code":"12062.0",
    "gn:admin4_code":"12062224.0",
    "gn:asciiname":"Arnsnesta",
    "gn:country_code":"DE",
    "gn:dem":79,
    "gn:feature_class":"P",
    "gn:feature_code":"PPL",
    "gn:name":"Arnsnesta",
    "gn:population":0,
    "gn:timezone":"Europe/Berlin",
    "iso:country":"DE",
    "wof:name":"Arnsnesta",
    "wof:placetype":"neighbourhood"
},
  "geometry": {"coordinates":[13.16946,51.73909],"type":"Point"}
}