{
  "type": "Feature",
  "properties": {
    "gn:admin1_code":"1",
    "gn:admin2_code":"81.0",
    "gn:admin3_code":"8126.0",
    "gn:admin4_code":"8126060.0",
    "gn:asciiname":"Hermersberg",
    "gn:country_code":"DE",
    "gn:dem":356,
    "gn:feature_class":"P",
    "gn:feature_code":"PPL",
    "gn:name":"Hermersberg",
    "gn:population":0,
    "gn:timezone":"Europe/Berlin",
    "iso:country":"DE",
    "name:ceb_x_preferred":[
        "Hermersberg"
    ],
    "name:deu_x_preferred":[
        "Hermersberg"
    ],
    "name:epo_x_preferred":[
        "Hermersberg"
    ],
    "name:eus_x_preferred":[
        "Hermersberg"
    ],
    "name:fas_x_preferred":[
        "\u0647\u0631\u0645\u0631\u0633\u0628\u0631\u06af"
    ],
    "name:fra_x_preferred":[
        "Hermersberg"
    ],
    "name:hun_x_preferred":[
        "Hermersberg"
    ],
    "name:ita_x_preferred":[
        "Hermersberg"
    ],
    "name:kaz_x_preferred":[
        "\u0425\u0435\u0440\u043c\u0435\u0440\u0441\u0431\u0435\u0440\u0433"
    ],
    "name:kir_x_preferred":[
        "\u0425\u0435\u0440\u043c\u0435\u0440\u0441\u0431\u0435\u0440\u0433"
    ],
    "name:msa_x_preferred":[
        "Hermersberg"
    ],
    "name:nld_x_preferred":[
        "Hermersberg"
    ],
    "name:pfl_x_preferred":[
        "Hermersberg"
    ],
    "name:pol_x_preferred":[
        "Hermersberg"
    ],
    "name:por_x_preferred":[
        "Hermersberg"
    ],
    "name:ron_x_preferred":[
        "Hermersberg"
    ],
    "name:rus_x_preferred":[
        "\u0425\u0435\u0440\u043c\u0435\u0440\u0441\u0431\u0435\u0440\u0433"
    ],
    "name:spa_x_preferred":[
        "Hermersberg"
    ],
    "name:srp_x_preferred":[
        "\u0425\u0435\u0440\u043c\u0435\u0440\u0441\u0431\u0435\u0440\u0433"
    ],
    "name:ukr_x_preferred":[
        "\u0413\u0435\u0440\u043c\u0435\u0440\u0441\u0431\u0435\u0440\u0433"
    ],
    "name:uzb_x_preferred":[
        "Hermersberg"
    ],
    "name:vie_x_preferred":[
        "Hermersberg"
    ],
    "name:vol_x_preferred":[
        "Hermersberg"
    ],
    "name:war_x_preferred":[
        "Hermersberg"
    ],
    "name:zho_x_preferred":[
        "\u9ed1\u9ed8\u65af\u8d1d\u683c"
    ],
    "wof:name":"Hermersberg",
    "wof:placetype":"neighbourhood"
},
  "geometry": {"coordinates":[9.60104,49.27598],"type":"Point"}
}