{
  "type": "Feature",
  "properties": {
    "gn:admin1_code":"11.0",
    "gn:admin2_code":"00",
    "gn:admin3_code":"12072.0",
    "gn:admin4_code":"12072297.0",
    "gn:asciiname":"Wergzahna",
    "gn:country_code":"DE",
    "gn:dem":112,
    "gn:feature_class":"P",
    "gn:feature_code":"PPL",
    "gn:name":"Wergzahna",
    "gn:population":0,
    "gn:timezone":"Europe/Berlin",
    "iso:country":"DE",
    "wof:name":"Wergzahna",
    "wof:placetype":"neighbourhood"
},
  "geometry": {"coordinates":[12.78639,51.97262],"type":"Point"}
}