{
  "type": "Feature",
  "properties": {
    "gn:admin1_code":"6",
    "gn:admin2_code":"0.0",
    "gn:admin3_code":"3254.0",
    "gn:admin4_code":"3254002.0",
    "gn:asciiname":"Eimsen",
    "gn:country_code":"DE",
    "gn:dem":99,
    "gn:feature_class":"P",
    "gn:feature_code":"PPL",
    "gn:name":"Eimsen",
    "gn:population":0,
    "gn:timezone":"Europe/Berlin",
    "iso:country":"DE",
    "wof:name":"Eimsen",
    "wof:placetype":"neighbourhood"
},
  "geometry": {"coordinates":[9.81611,52.00586],"type":"Point"}
}