{
  "type": "Feature",
  "properties": {
    "iso:country":"DE",
    "name:deu_x_preferred":[
        "Dorstfeld"
    ],
    "name:nld_x_preferred":[
        "Station Dortmund-Dorstfeld S\u00fcd"
    ],
    "name:unk_x_variant":[
        "Dorstfeld"
    ],
    "qs:gn_adm0_cc":"DE",
    "qs:gn_fcode":"PPL",
    "qs:gn_local":2935517,
    "qs:gn_nam_loc":"dortmund",
    "qs:gn_namadm1":"07",
    "qs:gn_name":"Dorstfeld",
    "qs:local_max":5685,
    "qs:local_sum":19088,
    "qs:localhoods":60,
    "qs:name":"Dorstfeld",
    "qs:name_adm0":"Deutschland",
    "qs:name_adm1":"Nordrhein-Westfalen",
    "qs:name_adm2":"Stadtkreis Dortmund",
    "qs:name_lau":"Innenstadt-West",
    "qs:name_local":"Dortmund",
    "qs:photo_max":90,
    "qs:photo_sum":487,
    "qs:placetype":"Suburb",
    "qs:quad_count":35,
    "qs:woe_adm0":23424829,
    "qs:woe_adm1":2345487,
    "qs:woe_adm2":12596991,
    "qs:woe_lau":26822135,
    "qs:woe_local":645458,
    "qs:woe_ver":"7.10.0",
    "wof:lang":[
        "ger"
    ],
    "wof:name":"Dorstfeld",
    "wof:placetype":"neighbourhood"
},
  "geometry": {"coordinates":[7.419517,51.507065],"type":"Point"}
}