{
  "type": "Feature",
  "properties": {
    "gn:admin1_code":"6.0",
    "gn:admin2_code":"00",
    "gn:admin3_code":"3254.0",
    "gn:admin4_code":"3254005.0",
    "gn:asciiname":"Wesseln",
    "gn:country_code":"DE",
    "gn:dem":92,
    "gn:feature_class":"P",
    "gn:feature_code":"PPL",
    "gn:name":"Wesseln",
    "gn:population":0,
    "gn:timezone":"Europe/Berlin",
    "iso:country":"DE",
    "name:ceb_x_preferred":[
        "Wesseln"
    ],
    "name:deu_x_preferred":[
        "Wesseln"
    ],
    "name:fas_x_preferred":[
        "\u0648\u0633\u0644\u0646"
    ],
    "wof:name":"Wesseln",
    "wof:placetype":"neighbourhood"
},
  "geometry": {"coordinates":[10.03291,52.08262],"type":"Point"}
}