{
  "type": "Feature",
  "properties": {
    "gn:gn_country":"DE",
    "gn:gn_fcode":"PPLA4",
    "gn:gn_pop":259,
    "gn:population":259,
    "iso:country":"DE",
    "name:baq_x_preferred":[
        "Hummelfeld"
    ],
    "name:chi_x_preferred":[
        "\u80e1\u6885\u5c14\u8d39\u5c14\u5fb7"
    ],
    "name:dan_x_preferred":[
        "Hummelfeld"
    ],
    "name:dut_x_preferred":[
        "Hummelfeld"
    ],
    "name:eng_x_preferred":[
        "Hummelfeld"
    ],
    "name:epo_x_preferred":[
        "Hummelfeld"
    ],
    "name:est_x_preferred":[
        "Hummelfeld"
    ],
    "name:fre_x_preferred":[
        "Hummelfeld"
    ],
    "name:ger_x_preferred":[
        "Hummelfeld"
    ],
    "name:hun_x_preferred":[
        "Hummelfeld"
    ],
    "name:ita_x_preferred":[
        "Hummelfeld"
    ],
    "name:kaz_x_preferred":[
        "\u0425\u0443\u043c\u043c\u0435\u043b\u044c\u0444\u0435\u043b\u044c\u0434"
    ],
    "name:kir_x_preferred":[
        "\u0425\u0443\u043c\u043c\u0435\u043b\u044c\u0444\u0435\u043b\u044c\u0434"
    ],
    "name:mac_x_preferred":[
        "\u0425\u0443\u043c\u0435\u043b\u0444\u0435\u043b\u0434"
    ],
    "name:may_x_preferred":[
        "Hummelfeld"
    ],
    "name:per_x_preferred":[
        "\u0647\u0648\u0645\u0644\u0641\u0644\u062f"
    ],
    "name:pol_x_preferred":[
        "Hummelfeld"
    ],
    "name:por_x_preferred":[
        "Hummelfeld"
    ],
    "name:rum_x_preferred":[
        "Hummelfeld"
    ],
    "name:rus_x_preferred":[
        "\u0425\u0443\u043c\u043c\u0435\u043b\u044c\u0444\u0435\u043b\u044c\u0434"
    ],
    "name:spa_x_preferred":[
        "Hummelfeld"
    ],
    "name:srp_x_preferred":[
        "\u0425\u0443\u043c\u0435\u043b\u0444\u0435\u043b\u0434"
    ],
    "name:tur_x_preferred":[
        "Hummelfeld"
    ],
    "name:ukr_x_preferred":[
        "\u0413\u0443\u043c\u043c\u0435\u043b\u044c\u0444\u0435\u043b\u044c\u0434"
    ],
    "name:uzb_x_preferred":[
        "Hummelfeld"
    ],
    "name:vie_x_preferred":[
        "Hummelfeld"
    ],
    "name:vol_x_preferred":[
        "Hummelfeld"
    ],
    "name:war_x_preferred":[
        "Hummelfeld"
    ],
    "qs_pg:aaroncc":"DE",
    "qs_pg:gn_country":"DE",
    "qs_pg:gn_fcode":"PPLA4",
    "qs_pg:gn_pop":259,
    "qs_pg:name":"Hummelfeld",
    "qs_pg:photos_9r":0,
    "qs_pg:photos_sr":0,
    "qs_pg:pop_sr":2,
    "qs_pg:qs_pg_placetype":"locality",
    "wof:name":"Hummelfeld",
    "wof:placetype":"locality",
    "wof:population":259
},
  "geometry": {"coordinates":[9.71667,54.46667],"type":"Point"}
}