{
  "type": "Feature",
  "properties": {
    "gn:gn_country":"DE",
    "gn:gn_fcode":"PPLA4",
    "gn:gn_pop":183,
    "gn:population":183,
    "iso:country":"DE",
    "name:bak_x_preferred":[
        "\u0412\u0430\u043b\u044c\u0442\u0435\u0440\u0441\u0434\u043e\u0440\u0444"
    ],
    "name:baq_x_preferred":[
        "Waltersdorf"
    ],
    "name:chi_x_preferred":[
        "\u74e6\u5c14\u7279\u5c14\u65af\u591a\u592b"
    ],
    "name:dut_x_preferred":[
        "Waltersdorf"
    ],
    "name:eng_x_preferred":[
        "Waltersdorf"
    ],
    "name:epo_x_preferred":[
        "Waltersdorf"
    ],
    "name:fre_x_preferred":[
        "Waltersdorf"
    ],
    "name:ger_x_preferred":[
        "Waltersdorf"
    ],
    "name:hun_x_preferred":[
        "Waltersdorf"
    ],
    "name:ita_x_preferred":[
        "Waltersdorf"
    ],
    "name:mac_x_preferred":[
        "\u0412\u0430\u043b\u0442\u0435\u0440\u0441\u0434\u043e\u0440\u0444"
    ],
    "name:may_x_preferred":[
        "Waltersdorf"
    ],
    "name:mwl_x_preferred":[
        "Waltersdorf"
    ],
    "name:per_x_preferred":[
        "\u0648\u0627\u0644\u062a\u0631\u0633\u062f\u0648\u0631\u0641"
    ],
    "name:pol_x_preferred":[
        "Waltersdorf"
    ],
    "name:por_x_preferred":[
        "Waltersdorf"
    ],
    "name:rum_x_preferred":[
        "Waltersdorf"
    ],
    "name:rus_x_preferred":[
        "\u0412\u0430\u043b\u044c\u0442\u0435\u0440\u0441\u0434\u043e\u0440\u0444"
    ],
    "name:srp_x_preferred":[
        "\u0412\u0430\u043b\u0442\u0435\u0440\u0441\u0434\u043e\u0440\u0444"
    ],
    "name:ukr_x_preferred":[
        "\u0412\u0430\u043b\u044c\u0442\u0435\u0440\u0441\u0434\u043e\u0440\u0444"
    ],
    "name:uzb_x_preferred":[
        "Waltersdorf"
    ],
    "name:vie_x_preferred":[
        "Waltersdorf"
    ],
    "name:vol_x_preferred":[
        "Waltersdorf"
    ],
    "name:war_x_preferred":[
        "Waltersdorf"
    ],
    "qs_pg:aaroncc":"DE",
    "qs_pg:gn_country":"DE",
    "qs_pg:gn_fcode":"PPLA4",
    "qs_pg:gn_pop":183,
    "qs_pg:name":"Waltersdorf",
    "qs_pg:photos_9r":0,
    "qs_pg:photos_sr":0,
    "qs_pg:pop_sr":1,
    "qs_pg:qs_pg_placetype":"locality",
    "wof:name":"Waltersdorf",
    "wof:placetype":"locality",
    "wof:population":183
},
  "geometry": {"coordinates":[11.75,50.83333],"type":"Point"}
}