{
  "type": "Feature",
  "properties": {
    "gn:country":"DE",
    "gn:fcode":"PPL",
    "gn:population":0,
    "iso:country":"DE",
    "name:als_x_preferred":[
        "Oberkirch"
    ],
    "name:ceb_x_preferred":[
        "Oberkirch"
    ],
    "name:deu_x_preferred":[
        "Oberkirch"
    ],
    "name:epo_x_preferred":[
        "Oberkirch"
    ],
    "name:fra_x_preferred":[
        "Oberkirch"
    ],
    "name:ita_x_preferred":[
        "Oberkirch"
    ],
    "name:nld_x_preferred":[
        "Oberkirch"
    ],
    "name:pol_x_preferred":[
        "Oberkirch"
    ],
    "name:por_x_preferred":[
        "Oberkirch"
    ],
    "name:rus_x_preferred":[
        "\u041e\u0431\u0435\u0440\u043a\u0438\u0440\u0445"
    ],
    "name:swe_x_preferred":[
        "Oberkirch"
    ],
    "name:vol_x_preferred":[
        "Oberkirch"
    ],
    "qs_pg:aaroncc":"DE",
    "qs_pg:gn_country":"DE",
    "qs_pg:gn_fcode":"PPL",
    "qs_pg:gn_pop":0,
    "qs_pg:name":"Oberkirch",
    "qs_pg:name_adm0":"Deutschland",
    "qs_pg:name_adm1":"Bayern",
    "qs_pg:photos":5,
    "qs_pg:photos_1k":1,
    "qs_pg:photos_9k":1,
    "qs_pg:photos_9r":1,
    "qs_pg:photos_all":5,
    "qs_pg:photos_sr":1,
    "qs_pg:pop_sr":0,
    "qs_pg:qs_pg_placetype":"locality",
    "qs_pg:qs_pg_placetype_gp":"Town",
    "qs_pg:woe_adm0":23424829,
    "woe:adm0_id":23424829,
    "woe:name_adm0":"Deutschland",
    "woe:name_adm1":"Bayern",
    "woe:placetype":"Town",
    "wof:name":"Oberkirch",
    "wof:placetype":"neighbourhood"
},
  "geometry": {"coordinates":[10.6241,47.57603],"type":"Point"}
}