{
  "type": "Feature",
  "properties": {
    "gn:admin1_code":"10",
    "gn:admin2_code":"0.0",
    "gn:admin3_code":"1051.0",
    "gn:admin4_code":"1051103.0",
    "gn:asciiname":"Ostermenghusen",
    "gn:country_code":"DE",
    "gn:dem":0,
    "gn:feature_class":"P",
    "gn:feature_code":"PPL",
    "gn:name":"Ostermenghusen",
    "gn:population":0,
    "gn:timezone":"Europe/Berlin",
    "iso:country":"DE",
    "wof:name":"Ostermenghusen",
    "wof:placetype":"neighbourhood"
},
  "geometry": {"coordinates":[9.04564,53.93576],"type":"Point"}
}