{
  "type": "Feature",
  "properties": {
    "gn:admin1_code":"15",
    "gn:admin2_code":"0.0",
    "gn:admin3_code":"16076.0",
    "gn:admin4_code":"16076069.0",
    "gn:asciiname":"Friedmannsdorf",
    "gn:country_code":"DE",
    "gn:dem":298,
    "gn:feature_class":"P",
    "gn:feature_code":"PPL",
    "gn:name":"Friedmannsdorf",
    "gn:population":0,
    "gn:timezone":"Europe/Berlin",
    "iso:country":"DE",
    "wof:name":"Friedmannsdorf",
    "wof:placetype":"neighbourhood"
},
  "geometry": {"coordinates":[12.22618,50.76016],"type":"Point"}
}