{
  "type": "Feature",
  "properties": {
    "gn:admin1_code":"11",
    "gn:admin2_code":"0.0",
    "gn:admin3_code":"12073.0",
    "gn:admin4_code":"12073452.0",
    "gn:asciiname":"Dauer",
    "gn:country_code":"DE",
    "gn:dem":33,
    "gn:feature_class":"P",
    "gn:feature_code":"PPL",
    "gn:name":"Dauer",
    "gn:population":0,
    "gn:timezone":"Europe/Berlin",
    "iso:country":"DE",
    "name:deu_x_preferred":[
        "Dauer"
    ],
    "name:fra_x_preferred":[
        "Dauer"
    ],
    "name:ita_x_preferred":[
        "Dauer"
    ],
    "wof:name":"Dauer",
    "wof:placetype":"neighbourhood"
},
  "geometry": {"coordinates":[13.91187,53.39044000000001],"type":"Point"}
}