{
  "type": "Feature",
  "properties": {
    "gn:admin1_code":"7",
    "gn:admin2_code":"59.0",
    "gn:admin3_code":"5970.0",
    "gn:admin4_code":"5970004.0",
    "gn:asciiname":"Elsoff",
    "gn:country_code":"DE",
    "gn:dem":385,
    "gn:feature_class":"P",
    "gn:feature_code":"PPL",
    "gn:name":"Elsoff",
    "gn:population":0,
    "gn:timezone":"Europe/Berlin",
    "iso:country":"DE",
    "name:ara_x_preferred":[
        "\u0625\u0644\u0633\u0648\u0641"
    ],
    "name:ceb_x_preferred":[
        "Elsoff"
    ],
    "name:deu_x_preferred":[
        "Elsoff"
    ],
    "name:epo_x_preferred":[
        "Elsoff"
    ],
    "name:eus_x_preferred":[
        "Elsoff"
    ],
    "name:fas_x_preferred":[
        "\u0627\u0644\u0633\u0648\u0641"
    ],
    "name:fra_x_preferred":[
        "Elsoff"
    ],
    "name:hun_x_preferred":[
        "Elsoff"
    ],
    "name:ita_x_preferred":[
        "Elsoff"
    ],
    "name:kaz_x_preferred":[
        "\u042d\u043b\u044c\u0437\u043e\u0444"
    ],
    "name:kir_x_preferred":[
        "\u042d\u043b\u044c\u0437\u043e\u0444"
    ],
    "name:msa_x_preferred":[
        "Elsoff"
    ],
    "name:nld_x_preferred":[
        "Elsoff"
    ],
    "name:pol_x_preferred":[
        "Elsoff"
    ],
    "name:por_x_preferred":[
        "Elsoff"
    ],
    "name:ron_x_preferred":[
        "Elsoff"
    ],
    "name:rus_x_preferred":[
        "\u042d\u043b\u044c\u0437\u043e\u0444"
    ],
    "name:spa_x_preferred":[
        "Elsoff"
    ],
    "name:srp_x_preferred":[
        "\u0415\u043b\u0437\u043e\u0444"
    ],
    "name:ukr_x_preferred":[
        "\u0415\u043b\u044c\u0437\u043e\u0444\u0444"
    ],
    "name:und_x_variant":[
        "Elsoft"
    ],
    "name:uzb_x_preferred":[
        "Elsoff"
    ],
    "name:vie_x_preferred":[
        "Elsoff"
    ],
    "name:vol_x_preferred":[
        "Elsoff"
    ],
    "name:war_x_preferred":[
        "Elsoff"
    ],
    "name:zho_x_preferred":[
        "\u57c3\u5c14\u7d22\u592b"
    ],
    "wof:name":"Elsoff",
    "wof:placetype":"neighbourhood"
},
  "geometry": {"coordinates":[8.51051,51.02323],"type":"Point"}
}