{
  "type": "Feature",
  "properties": {
    "gn:admin1_code":"14.0",
    "gn:admin2_code":"0.0",
    "gn:admin3_code":"15083.0",
    "gn:admin4_code":"15083270.0",
    "gn:asciiname":"Haldensleben III",
    "gn:country_code":"DE",
    "gn:dem":89,
    "gn:feature_class":"P",
    "gn:feature_code":"PPL",
    "gn:name":"Haldensleben III",
    "gn:population":0,
    "gn:timezone":"Europe/Berlin",
    "iso:country":"DE",
    "wof:name":"Haldensleben III",
    "wof:placetype":"neighbourhood"
},
  "geometry": {"coordinates":[11.37327,52.28379],"type":"Point"}
}