{
  "type": "Feature",
  "properties": {
    "gn:admin1_code":"6.0",
    "gn:admin2_code":"00",
    "gn:admin3_code":"3252.0",
    "gn:admin4_code":"3252007.0",
    "gn:asciiname":"Zersen",
    "gn:country_code":"DE",
    "gn:dem":103,
    "gn:feature_class":"P",
    "gn:feature_code":"PPL",
    "gn:name":"Zersen",
    "gn:population":0,
    "gn:timezone":"Europe/Berlin",
    "iso:country":"DE",
    "wof:name":"Zersen",
    "wof:placetype":"neighbourhood"
},
  "geometry": {"coordinates":[9.29581,52.18183],"type":"Point"}
}