{
  "type": "Feature",
  "properties": {
    "gn:admin1_code":"2.0",
    "gn:admin2_code":"092",
    "gn:admin3_code":"9275.0",
    "gn:admin4_code":"9275160.0",
    "gn:asciiname":"Witzingerreut",
    "gn:country_code":"DE",
    "gn:dem":472,
    "gn:feature_class":"P",
    "gn:feature_code":"PPL",
    "gn:name":"Witzingerreut",
    "gn:population":0,
    "gn:timezone":"Europe/Berlin",
    "iso:country":"DE",
    "wof:name":"Witzingerreut",
    "wof:placetype":"neighbourhood"
},
  "geometry": {"coordinates":[13.40636,48.74418],"type":"Point"}
}