{
  "type": "Feature",
  "properties": {
    "gn:admin1_code":"15",
    "gn:admin2_code":"0.0",
    "gn:admin3_code":"16077.0",
    "gn:admin4_code":"16077009.0",
    "gn:asciiname":"Schwanditz",
    "gn:country_code":"DE",
    "gn:dem":228,
    "gn:feature_class":"P",
    "gn:feature_code":"PPL",
    "gn:name":"Schwanditz",
    "gn:population":0,
    "gn:timezone":"Europe/Berlin",
    "iso:country":"DE",
    "name:und_x_variant":[
        "G\u00f6llnitz-Schwanditz",
        "Schwanditz"
    ],
    "wof:name":"Schwanditz",
    "wof:placetype":"neighbourhood"
},
  "geometry": {"coordinates":[12.33922,50.95307],"type":"Point"}
}