{
  "type": "Feature",
  "properties": {
    "gn:admin1_code":"7",
    "gn:admin2_code":"57.0",
    "gn:admin3_code":"5758.0",
    "gn:admin4_code":"5758012.0",
    "gn:asciiname":"Diekenheide",
    "gn:country_code":"DE",
    "gn:dem":90,
    "gn:feature_class":"P",
    "gn:feature_code":"PPLL",
    "gn:name":"Diekenheide",
    "gn:population":0,
    "gn:timezone":"Europe/Berlin",
    "iso:country":"DE",
    "wof:name":"Diekenheide",
    "wof:placetype":"neighbourhood"
},
  "geometry": {"coordinates":[8.61667,52.11667],"type":"Point"}
}