{
  "type": "Feature",
  "properties": {
    "gn:admin1_code":"14",
    "gn:admin2_code":"0.0",
    "gn:admin3_code":"15088.0",
    "gn:admin4_code":"15088319.0",
    "gn:asciiname":"Krimpe",
    "gn:country_code":"DE",
    "gn:dem":161,
    "gn:feature_class":"P",
    "gn:feature_code":"PPL",
    "gn:name":"Krimpe",
    "gn:population":0,
    "gn:timezone":"Europe/Berlin",
    "iso:country":"DE",
    "wof:name":"Krimpe",
    "wof:placetype":"neighbourhood"
},
  "geometry": {"coordinates":[11.75444,51.52434],"type":"Point"}
}