{
  "type": "Feature",
  "properties": {
    "gn:admin1_code":"1",
    "gn:admin2_code":"84.0",
    "gn:admin3_code":"8436.0",
    "gn:admin4_code":"8436006.0",
    "gn:asciiname":"Geiselharz",
    "gn:country_code":"DE",
    "gn:dem":562,
    "gn:feature_class":"P",
    "gn:feature_code":"PPL",
    "gn:name":"Geiselharz",
    "gn:population":0,
    "gn:timezone":"Europe/Berlin",
    "iso:country":"DE",
    "wof:name":"Geiselharz",
    "wof:placetype":"neighbourhood"
},
  "geometry": {"coordinates":[9.76206,47.69517000000001],"type":"Point"}
}