{
  "type": "Feature",
  "properties": {
    "gn:admin1_code":"6",
    "gn:admin2_code":"0.0",
    "gn:admin3_code":"3459.0",
    "gn:admin4_code":"3459014.0",
    "gn:asciiname":"Kalkriese",
    "gn:country_code":"DE",
    "gn:dem":58,
    "gn:feature_class":"P",
    "gn:feature_code":"PPL",
    "gn:name":"Kalkriese",
    "gn:population":0,
    "gn:timezone":"Europe/Berlin",
    "iso:country":"DE",
    "name:deu_x_preferred":[
        "Fundregion Kalkriese"
    ],
    "name:epo_x_preferred":[
        "Kalkriese"
    ],
    "name:ind_x_preferred":[
        "Kalkriese"
    ],
    "name:nds_x_preferred":[
        "Kalkreese"
    ],
    "name:nld_x_preferred":[
        "Kalkriese"
    ],
    "name:spa_x_preferred":[
        "Kalkriese"
    ],
    "wof:name":"Kalkriese",
    "wof:placetype":"neighbourhood"
},
  "geometry": {"coordinates":[8.09262,52.40926],"type":"Point"}
}