{
  "type": "Feature",
  "properties": {
    "gn:admin1_code":"11",
    "gn:admin2_code":"0.0",
    "gn:admin3_code":"12061.0",
    "gn:admin4_code":"12061320.0",
    "gn:asciiname":"Frankendorf",
    "gn:country_code":"DE",
    "gn:dem":61,
    "gn:feature_class":"P",
    "gn:feature_code":"PPL",
    "gn:name":"Frankendorf",
    "gn:population":0,
    "gn:timezone":"Europe/Berlin",
    "iso:country":"DE",
    "name:bak_x_preferred":[
        "\u0424\u0440\u0430\u043d\u043a\u0435\u043d\u0434\u043e\u0440\u0444"
    ],
    "name:ceb_x_preferred":[
        "Frankendorf"
    ],
    "name:deu_x_preferred":[
        "Frankendorf"
    ],
    "name:epo_x_preferred":[
        "Frankendorf"
    ],
    "name:eus_x_preferred":[
        "Frankendorf"
    ],
    "name:fas_x_preferred":[
        "\u0641\u0631\u0627\u0646\u06a9\u0646\u062f\u0648\u0631\u0641"
    ],
    "name:fra_x_preferred":[
        "Frankendorf"
    ],
    "name:hun_x_preferred":[
        "Frankendorf"
    ],
    "name:ita_x_preferred":[
        "Frankendorf"
    ],
    "name:mkd_x_preferred":[
        "\u0424\u0440\u0430\u043d\u043a\u0435\u043d\u0434\u043e\u0440\u0444"
    ],
    "name:msa_x_preferred":[
        "Frankendorf"
    ],
    "name:nld_x_preferred":[
        "Frankendorf"
    ],
    "name:pol_x_preferred":[
        "Frankendorf"
    ],
    "name:ron_x_preferred":[
        "Frankendorf"
    ],
    "name:rus_x_preferred":[
        "\u0424\u0440\u0430\u043d\u043a\u0435\u043d\u0434\u043e\u0440\u0444"
    ],
    "name:spa_x_preferred":[
        "Frankendorf"
    ],
    "name:srp_x_preferred":[
        "\u0424\u0440\u0430\u043d\u043a\u0435\u043d\u0434\u043e\u0440\u0444"
    ],
    "name:ukr_x_preferred":[
        "\u0424\u0440\u0430\u043d\u043a\u0435\u043d\u0434\u043e\u0440\u0444"
    ],
    "name:uzb_x_preferred":[
        "Frankendorf"
    ],
    "name:vie_x_preferred":[
        "Frankendorf"
    ],
    "name:vol_x_preferred":[
        "Frankendorf"
    ],
    "name:war_x_preferred":[
        "Frankendorf"
    ],
    "name:zho_x_preferred":[
        "\u5f17\u5170\u80af\u591a\u592b"
    ],
    "wof:name":"Frankendorf",
    "wof:placetype":"neighbourhood"
},
  "geometry": {"coordinates":[13.76023,51.82647],"type":"Point"}
}