{
  "type": "Feature",
  "properties": {
    "gn:admin1_code":"6.0",
    "gn:admin2_code":"0.0",
    "gn:admin3_code":"3359.0",
    "gn:admin4_code":"3359037.0",
    "gn:asciiname":"Bredenhorn",
    "gn:country_code":"DE",
    "gn:dem":42,
    "gn:feature_class":"P",
    "gn:feature_code":"PPL",
    "gn:name":"Bredenhorn",
    "gn:population":0,
    "gn:timezone":"Europe/Berlin",
    "iso:country":"DE",
    "wof:name":"Bredenhorn",
    "wof:placetype":"neighbourhood"
},
  "geometry": {"coordinates":[9.59688,53.37153000000001],"type":"Point"}
}