{
  "type": "Feature",
  "properties": {
    "gn:admin1_code":"6",
    "gn:admin2_code":"0.0",
    "gn:admin3_code":"3458.0",
    "gn:admin4_code":"3458012.0",
    "gn:asciiname":"Rundebusch",
    "gn:country_code":"DE",
    "gn:dem":40,
    "gn:feature_class":"P",
    "gn:feature_code":"PPL",
    "gn:name":"Rundebusch",
    "gn:population":0,
    "gn:timezone":"Europe/Berlin",
    "iso:country":"DE",
    "wof:name":"Rundebusch",
    "wof:placetype":"neighbourhood"
},
  "geometry": {"coordinates":[8.50178,52.92441],"type":"Point"}
}