{
  "type": "Feature",
  "properties": {
    "gn:admin1_code":"8.0",
    "gn:admin2_code":"0.0",
    "gn:admin3_code":"7334.0",
    "gn:admin4_code":"7334022.0",
    "gn:asciiname":"Hardtwald",
    "gn:country_code":"DE",
    "gn:dem":112,
    "gn:feature_class":"P",
    "gn:feature_code":"PPL",
    "gn:name":"Hardtwald",
    "gn:population":0,
    "gn:timezone":"Europe/Berlin",
    "iso:country":"DE",
    "wof:name":"Hardtwald",
    "wof:placetype":"neighbourhood"
},
  "geometry": {"coordinates":[8.31405,49.12362],"type":"Point"}
}