{
  "type": "Feature",
  "properties": {
    "gn:admin1_code":"8.0",
    "gn:admin2_code":"0.0",
    "gn:admin3_code":"7334.0",
    "gn:admin4_code":"7334022.0",
    "gn:asciiname":"Hardtwald",
    "gn:country_code":"DE",
    "gn:dem":112,
    "gn:feature_class":"P",
    "gn:feature_code":"PPL",
    "gn:name":"Hardtwald",
    "gn:population":0,
    "gn:timezone":"Europe/Berlin",
    "iso:country":"DE",
    "name:als_x_preferred":[
        "Hardt"
    ],
    "name:deu_x_preferred":[
        "Hardtwald"
    ],
    "name:rus_x_preferred":[
        "\u0425\u0430\u0440\u0434\u0442\u0432\u0430\u043b\u044c\u0434"
    ],
    "wof:name":"Hardtwald",
    "wof:placetype":"neighbourhood"
},
  "geometry": {"coordinates":[8.31405,49.12362],"type":"Point"}
}