{
  "type": "Feature",
  "properties": {
    "gn:admin1_code":"7.0",
    "gn:admin2_code":"59.0",
    "gn:admin3_code":"5966.0",
    "gn:admin4_code":"5966004.0",
    "gn:asciiname":"Borghausen",
    "gn:country_code":"DE",
    "gn:dem":271,
    "gn:feature_class":"P",
    "gn:feature_code":"PPL",
    "gn:name":"Borghausen",
    "gn:population":0,
    "gn:timezone":"Europe/Berlin",
    "iso:country":"DE",
    "wof:name":"Borghausen",
    "wof:placetype":"neighbourhood"
},
  "geometry": {"coordinates":[7.99403,51.14762],"type":"Point"}
}