{
  "type": "Feature",
  "properties": {
    "gn:admin1_code":"10.0",
    "gn:asciiname":"Westereck",
    "gn:country_code":"DE",
    "gn:dem":0,
    "gn:feature_class":"P",
    "gn:feature_code":"PPL",
    "gn:name":"Westereck",
    "gn:population":0,
    "gn:timezone":"Europe/Berlin",
    "iso:country":"DE",
    "wof:name":"Westereck",
    "wof:placetype":"neighbourhood"
},
  "geometry": {"coordinates":[8.65,54.28333000000001],"type":"Point"}
}