{
  "type": "Feature",
  "properties": {
    "gn:admin1_code":"12",
    "gn:admin2_code":"0.0",
    "gn:admin3_code":"13076.0",
    "gn:admin4_code":"13076077.0",
    "gn:asciiname":"Schlemmin",
    "gn:country_code":"DE",
    "gn:dem":69,
    "gn:feature_class":"P",
    "gn:feature_code":"PPL",
    "gn:name":"Schlemmin",
    "gn:population":0,
    "gn:timezone":"Europe/Berlin",
    "iso:country":"DE",
    "name:ceb_x_preferred":[
        "Schlemmin"
    ],
    "name:deu_x_preferred":[
        "Schlemmin"
    ],
    "name:epo_x_preferred":[
        "Schlemmin"
    ],
    "name:fas_x_preferred":[
        "\u0634\u0644\u0645\u06cc\u0646"
    ],
    "name:fra_x_preferred":[
        "Schlemmin"
    ],
    "name:hun_x_preferred":[
        "Schlemmin"
    ],
    "name:ita_x_preferred":[
        "Schlemmin"
    ],
    "name:kaz_x_preferred":[
        "\u0428\u043b\u0435\u043c\u043c\u0438\u043d"
    ],
    "name:kir_x_preferred":[
        "\u0428\u043b\u0435\u043c\u043c\u0438\u043d"
    ],
    "name:mkd_x_preferred":[
        "\u0428\u043b\u0435\u043c\u0438\u043d"
    ],
    "name:msa_x_preferred":[
        "Schlemmin"
    ],
    "name:nld_x_preferred":[
        "Schlemmin"
    ],
    "name:pol_x_preferred":[
        "Schlemmin"
    ],
    "name:por_x_preferred":[
        "Schlemmin"
    ],
    "name:ron_x_preferred":[
        "Schlemmin"
    ],
    "name:rus_x_preferred":[
        "\u0428\u043b\u0435\u043c\u043c\u0438\u043d"
    ],
    "name:spa_x_preferred":[
        "Schlemmin"
    ],
    "name:srp_x_preferred":[
        "\u0428\u043b\u0435\u043c\u0438\u043d"
    ],
    "name:ukr_x_preferred":[
        "\u0428\u043b\u0435\u043c\u043c\u0456\u043d"
    ],
    "name:uzb_x_preferred":[
        "Schlemmin"
    ],
    "name:vie_x_preferred":[
        "Schlemmin"
    ],
    "name:vol_x_preferred":[
        "Schlemmin"
    ],
    "name:war_x_preferred":[
        "Schlemmin"
    ],
    "name:zho_x_preferred":[
        "\u65bd\u83b1\u660e"
    ],
    "wof:name":"Schlemmin",
    "wof:placetype":"neighbourhood"
},
  "geometry": {"coordinates":[12.1629,53.42948000000001],"type":"Point"}
}