{
  "type": "Feature",
  "properties": {
    "gn:admin1_code":"12",
    "gn:admin2_code":"0.0",
    "gn:admin3_code":"13076.0",
    "gn:admin4_code":"13076077.0",
    "gn:asciiname":"Schlemmin",
    "gn:country_code":"DE",
    "gn:dem":69,
    "gn:feature_class":"P",
    "gn:feature_code":"PPL",
    "gn:name":"Schlemmin",
    "gn:population":0,
    "gn:timezone":"Europe/Berlin",
    "iso:country":"DE",
    "wof:name":"Schlemmin",
    "wof:placetype":"neighbourhood"
},
  "geometry": {"coordinates":[12.1629,53.42948000000001],"type":"Point"}
}