{
  "type": "Feature",
  "properties": {
    "gn:admin1_code":"2",
    "gn:admin2_code":"92.0",
    "gn:admin3_code":"9275.0",
    "gn:admin4_code":"9275119.0",
    "gn:asciiname":"Saderreut",
    "gn:country_code":"DE",
    "gn:dem":457,
    "gn:feature_class":"P",
    "gn:feature_code":"PPL",
    "gn:name":"Saderreut",
    "gn:population":0,
    "gn:timezone":"Europe/Berlin",
    "iso:country":"DE",
    "wof:name":"Saderreut",
    "wof:placetype":"neighbourhood"
},
  "geometry": {"coordinates":[13.50832,48.68151],"type":"Point"}
}