{
  "type": "Feature",
  "properties": {
    "gn:admin1_code":"2.0",
    "gn:admin2_code":"92.0",
    "gn:admin3_code":"9279.0",
    "gn:admin4_code":"9279134.0",
    "gn:asciiname":"Anterskofen",
    "gn:country_code":"DE",
    "gn:dem":406,
    "gn:feature_class":"P",
    "gn:feature_code":"PPL",
    "gn:name":"Anterskofen",
    "gn:population":0,
    "gn:timezone":"Europe/Berlin",
    "iso:country":"DE",
    "name:und_x_variant":[
        "Anderskofen",
        "Anterskofen"
    ],
    "wof:name":"Anterskofen",
    "wof:placetype":"neighbourhood"
},
  "geometry": {"coordinates":[12.56892,48.61446],"type":"Point"}
}