{
  "type": "Feature",
  "properties": {
    "gn:gn_country":"DE",
    "gn:gn_fcode":"PPLA4",
    "gn:gn_pop":123,
    "gn:population":123,
    "iso:country":"DE",
    "name:baq_x_preferred":[
        "Utzenhain"
    ],
    "name:chi_x_preferred":[
        "\u4e4c\u5c91\u6d77\u6069"
    ],
    "name:dut_x_preferred":[
        "Utzenhain"
    ],
    "name:eng_x_preferred":[
        "Utzenhain"
    ],
    "name:epo_x_preferred":[
        "Utzenhain"
    ],
    "name:fre_x_preferred":[
        "Utzenhain"
    ],
    "name:ger_x_preferred":[
        "Utzenhain"
    ],
    "name:hun_x_preferred":[
        "Utzenhain"
    ],
    "name:ita_x_preferred":[
        "Utzenhain"
    ],
    "name:jpn_x_preferred":[
        "\u30a6\u30c3\u30c4\u30a7\u30f3\u30cf\u30a4\u30f3"
    ],
    "name:kaz_x_preferred":[
        "\u0423\u0442\u0446\u0435\u043d\u0445\u0430\u0439\u043d"
    ],
    "name:kir_x_preferred":[
        "\u0423\u0442\u0446\u0435\u043d\u0445\u0430\u0439\u043d"
    ],
    "name:per_x_preferred":[
        "\u0627\u0648\u062a\u0633\u0646\u0647\u0627\u06cc\u0646"
    ],
    "name:pol_x_preferred":[
        "Utzenhain"
    ],
    "name:por_x_preferred":[
        "Utzenhain"
    ],
    "name:rum_x_preferred":[
        "Utzenhain"
    ],
    "name:rus_x_preferred":[
        "\u0423\u0442\u0446\u0435\u043d\u0445\u0430\u0439\u043d"
    ],
    "name:srp_x_preferred":[
        "\u0423\u0446\u0435\u043d\u0445\u0430\u0458\u043d"
    ],
    "name:ukr_x_preferred":[
        "\u0423\u0442\u0446\u0435\u043d\u0433\u0430\u0439\u043d"
    ],
    "name:uzb_x_preferred":[
        "Utzenhain"
    ],
    "name:vie_x_preferred":[
        "Utzenhain"
    ],
    "name:vol_x_preferred":[
        "Utzenhain"
    ],
    "name:war_x_preferred":[
        "Utzenhain"
    ],
    "qs_pg:aaroncc":"DE",
    "qs_pg:gn_country":"DE",
    "qs_pg:gn_fcode":"PPLA4",
    "qs_pg:gn_pop":123,
    "qs_pg:name":"Utzenhain",
    "qs_pg:photos_9r":0,
    "qs_pg:photos_sr":0,
    "qs_pg:pop_sr":1,
    "qs_pg:qs_pg_placetype":"locality",
    "wof:name":"Utzenhain",
    "wof:placetype":"locality",
    "wof:population":123
},
  "geometry": {"coordinates":[7.63333,50.13333],"type":"Point"}
}