{
  "type": "Feature",
  "properties": {
    "gn:admin1_code":"5",
    "gn:admin2_code":"64.0",
    "gn:admin3_code":"6439.0",
    "gn:admin4_code":"6439011.0",
    "gn:asciiname":"Koenigshofen",
    "gn:country_code":"DE",
    "gn:dem":289,
    "gn:feature_class":"P",
    "gn:feature_code":"PPL",
    "gn:name":"K\u00f6nigshofen",
    "gn:population":0,
    "gn:timezone":"Europe/Berlin",
    "iso:country":"DE",
    "name:und_x_variant":[
        "K\u00f6nigshofen"
    ],
    "wof:name":"Koenigshofen",
    "wof:placetype":"neighbourhood"
},
  "geometry": {"coordinates":[8.30196,50.16595],"type":"Point"}
}