{
  "type": "Feature",
  "properties": {
    "gn:admin1_code":"6",
    "gn:admin2_code":"0.0",
    "gn:admin3_code":"3252.0",
    "gn:admin4_code":"3252006.0",
    "gn:asciiname":"Unsen",
    "gn:country_code":"DE",
    "gn:dem":141,
    "gn:feature_class":"P",
    "gn:feature_code":"PPL",
    "gn:name":"Unsen",
    "gn:population":0,
    "gn:timezone":"Europe/Berlin",
    "iso:country":"DE",
    "wof:name":"Unsen",
    "wof:placetype":"neighbourhood"
},
  "geometry": {"coordinates":[9.39898,52.14729000000001],"type":"Point"}
}