{
  "type": "Feature",
  "properties": {
    "gn:admin1_code":"2.0",
    "gn:admin2_code":"97.0",
    "gn:admin3_code":"9777.0",
    "gn:admin4_code":"9777167.0",
    "gn:asciiname":"Apfeltrang",
    "gn:country_code":"DE",
    "gn:dem":764,
    "gn:feature_class":"P",
    "gn:feature_code":"PPL",
    "gn:name":"Apfeltrang",
    "gn:population":0,
    "gn:timezone":"Europe/Berlin",
    "iso:country":"DE",
    "wof:name":"Apfeltrang",
    "wof:placetype":"neighbourhood"
},
  "geometry": {"coordinates":[10.58581,47.83872],"type":"Point"}
}