{
  "type": "Feature",
  "properties": {
    "gn:admin1_code":"10",
    "gn:admin2_code":"0.0",
    "gn:admin3_code":"1054.0",
    "gn:admin4_code":"1054022.0",
    "gn:asciiname":"Osewoldterkoog",
    "gn:country_code":"DE",
    "gn:dem":5,
    "gn:feature_class":"P",
    "gn:feature_code":"PPL",
    "gn:name":"Osewoldterkoog",
    "gn:population":0,
    "gn:timezone":"Europe/Berlin",
    "iso:country":"DE",
    "wof:name":"Osewoldterkoog",
    "wof:placetype":"neighbourhood"
},
  "geometry": {"coordinates":[8.73027,54.72878000000001],"type":"Point"}
}