{
  "type": "Feature",
  "properties": {
    "gn:admin1_code":"11",
    "gn:admin2_code":"0.0",
    "gn:admin3_code":"12070.0",
    "gn:admin4_code":"12070416.0",
    "gn:asciiname":"Klein Breese",
    "gn:country_code":"DE",
    "gn:dem":20,
    "gn:feature_class":"P",
    "gn:feature_code":"PPL",
    "gn:name":"Klein Breese",
    "gn:population":0,
    "gn:timezone":"Europe/Berlin",
    "iso:country":"DE",
    "wof:name":"Klein Breese",
    "wof:placetype":"neighbourhood"
},
  "geometry": {"coordinates":[11.78333,53.01667],"type":"Point"}
}