{
  "type": "Feature",
  "properties": {
    "gn:admin1_code":"2",
    "gn:admin2_code":"91.0",
    "gn:admin3_code":"9179.0",
    "gn:admin4_code":"9179136.0",
    "gn:asciiname":"Nannhofen",
    "gn:country_code":"DE",
    "gn:dem":541,
    "gn:feature_class":"P",
    "gn:feature_code":"PPL",
    "gn:name":"Nannhofen",
    "gn:population":0,
    "gn:timezone":"Europe/Berlin",
    "iso:country":"DE",
    "wof:name":"Nannhofen",
    "wof:placetype":"neighbourhood"
},
  "geometry": {"coordinates":[11.17196,48.219],"type":"Point"}
}