{
  "type": "Feature",
  "properties": {
    "gn:admin1_code":"2",
    "gn:admin2_code":"97.0",
    "gn:admin3_code":"9777.0",
    "gn:admin4_code":"9777170.0",
    "gn:asciiname":"Kirchthal",
    "gn:country_code":"DE",
    "gn:dem":821,
    "gn:feature_class":"P",
    "gn:feature_code":"PPL",
    "gn:name":"Kirchthal",
    "gn:population":0,
    "gn:timezone":"Europe/Berlin",
    "iso:country":"DE",
    "wof:name":"Kirchthal",
    "wof:placetype":"neighbourhood"
},
  "geometry": {"coordinates":[10.61058,47.67704000000001],"type":"Point"}
}