{
  "type": "Feature",
  "properties": {
    "iso:country":"DE",
    "wof:name":"Deutsches Museum",
    "wof:placetype":"neighbourhood"
},
  "geometry": {"coordinates":[11.58185614422471,48.13066748815346],"type":"Point"}
}