{
  "type": "Feature",
  "properties": {
    "gn:admin1_code":"1.0",
    "gn:admin2_code":"83.0",
    "gn:admin3_code":"8337.0",
    "gn:admin4_code":"8337126.0",
    "gn:asciiname":"Aispel",
    "gn:country_code":"DE",
    "gn:dem":581,
    "gn:feature_class":"P",
    "gn:feature_code":"PPL",
    "gn:name":"Aispel",
    "gn:population":0,
    "gn:timezone":"Europe/Berlin",
    "iso:country":"DE",
    "wof:name":"Aispel",
    "wof:placetype":"neighbourhood"
},
  "geometry": {"coordinates":[8.21128,47.66491],"type":"Point"}
}