{
  "type": "Feature",
  "properties": {
    "gn:admin1_code":"2.0",
    "gn:admin2_code":"093",
    "gn:admin3_code":"9372.0",
    "gn:admin4_code":"9372115.0",
    "gn:asciiname":"Wimbach",
    "gn:country_code":"DE",
    "gn:dem":442,
    "gn:feature_class":"P",
    "gn:feature_code":"PPL",
    "gn:name":"Wimbach",
    "gn:population":0,
    "gn:timezone":"Europe/Berlin",
    "iso:country":"DE",
    "wof:name":"Wimbach",
    "wof:placetype":"neighbourhood"
},
  "geometry": {"coordinates":[12.83107,49.13851],"type":"Point"}
}