{
  "type": "Feature",
  "properties": {
    "gn:admin1_code":"1",
    "gn:admin2_code":"82.0",
    "gn:admin3_code":"8235.0",
    "gn:admin4_code":"8235065.0",
    "gn:asciiname":"Buhlhof",
    "gn:country_code":"DE",
    "gn:dem":681,
    "gn:feature_class":"P",
    "gn:feature_code":"PPL",
    "gn:name":"B\u00fchlhof",
    "gn:population":0,
    "gn:timezone":"Europe/Berlin",
    "iso:country":"DE",
    "wof:name":"Buhlhof",
    "wof:placetype":"neighbourhood"
},
  "geometry": {"coordinates":[8.63608,48.78486],"type":"Point"}
}