{
  "type": "Feature",
  "properties": {
    "gn:admin1_code":"8",
    "gn:admin2_code":"0.0",
    "gn:admin3_code":"7132.0",
    "gn:admin4_code":"7132074.0",
    "gn:asciiname":"Fladersbach",
    "gn:country_code":"DE",
    "gn:dem":273,
    "gn:feature_class":"P",
    "gn:feature_code":"PPL",
    "gn:name":"Fladersbach",
    "gn:population":0,
    "gn:timezone":"Europe/Berlin",
    "iso:country":"DE",
    "wof:name":"Fladersbach",
    "wof:placetype":"neighbourhood"
},
  "geometry": {"coordinates":[7.58333,50.68333],"type":"Point"}
}