{
  "type": "Feature",
  "properties": {
    "iso:country":"DE",
    "name:deu_x_preferred":[
        "Flugplatz F\u00fcrstenzell"
    ],
    "name:eng_x_preferred":[
        "Furstenzell Airport"
    ],
    "name:eng_x_variant":[
        "EDMF",
        "F\u00fcrstenzell airfield"
    ],
    "name:msa_x_preferred":[
        "Lapangan Terbang Furstenzell"
    ],
    "oa:elevation_ft":"1345",
    "oa:type":"small_airport",
    "woe:hierarchy":{
        "country_id":23424829,
        "county_id":12596826,
        "localadmin_id":12622936,
        "planet_id":1,
        "state_id":2345482
    },
    "wof:name":"Sportflugplatz F\u00fcrstenzell",
    "wof:placetype":"campus"
},
  "geometry": {"coordinates":[13.346112,48.513055],"type":"Point"}
}