{
  "type": "Feature",
  "properties": {
    "gn:admin1_code":"6.0",
    "gn:admin2_code":"00",
    "gn:admin3_code":"3452.0",
    "gn:admin4_code":"3452025.0",
    "gn:asciiname":"Wiesederfehn",
    "gn:country_code":"DE",
    "gn:dem":8,
    "gn:feature_class":"P",
    "gn:feature_code":"PPL",
    "gn:name":"Wiesederfehn",
    "gn:population":0,
    "gn:timezone":"Europe/Berlin",
    "iso:country":"DE",
    "wof:name":"Wiesederfehn",
    "wof:placetype":"neighbourhood"
},
  "geometry": {"coordinates":[7.75995,53.43115],"type":"Point"}
}