{
  "type": "Feature",
  "properties": {
    "gn:admin1_code":"2",
    "gn:admin2_code":"91.0",
    "gn:admin3_code":"9189.0",
    "gn:admin4_code":"9189145.0",
    "gn:asciiname":"Hachau",
    "gn:country_code":"DE",
    "gn:dem":653,
    "gn:feature_class":"P",
    "gn:feature_code":"PPLL",
    "gn:name":"Hachau",
    "gn:population":0,
    "gn:timezone":"Europe/Berlin",
    "iso:country":"DE",
    "wof:name":"Hachau",
    "wof:placetype":"neighbourhood"
},
  "geometry": {"coordinates":[12.69394,47.8078],"type":"Point"}
}