{
  "type": "Feature",
  "properties": {
    "gn:admin1_code":"10",
    "gn:admin2_code":"0.0",
    "gn:admin3_code":"1055.0",
    "gn:admin4_code":"1055007.0",
    "gn:asciiname":"Thuerk",
    "gn:country_code":"DE",
    "gn:dem":60,
    "gn:feature_class":"P",
    "gn:feature_code":"PPL",
    "gn:name":"Th\u00fcrk",
    "gn:population":0,
    "gn:timezone":"Europe/Berlin",
    "iso:country":"DE",
    "wof:name":"Thuerk",
    "wof:placetype":"neighbourhood"
},
  "geometry": {"coordinates":[10.50026,54.11086],"type":"Point"}
}