{
  "type": "Feature",
  "properties": {
    "iso:country":"DE",
    "name:ceb_x_preferred":[
        "Vorwerk"
    ],
    "name:deu_x_preferred":[
        "Vorwerk"
    ],
    "name:fra_x_preferred":[
        "Vorwerk"
    ],
    "name:ita_x_preferred":[
        "Vorwerk"
    ],
    "name:nld_x_preferred":[
        "Vorwerk"
    ],
    "name:pol_x_preferred":[
        "Vorwerk"
    ],
    "name:unk_x_variant":[
        "Vorwerk"
    ],
    "name:zho_x_preferred":[
        "\u798f\u5c14\u97e6\u5c14\u514b"
    ],
    "qs:gn_adm0_cc":"DE",
    "qs:gn_fcode":"PPLX",
    "qs:gn_local":2875601,
    "qs:gn_namadm1":"10",
    "qs:gn_name":"Vorwerk",
    "qs:local_max":2963,
    "qs:local_sum":12788,
    "qs:localhoods":32,
    "qs:name":"Vorwerk",
    "qs:name_adm0":"Deutschland",
    "qs:name_adm1":"Schleswig-Holstein",
    "qs:name_adm2":"Stadtkreis L\u00fcbeck",
    "qs:name_lau":"Stadtteil St. Lorenz Nord",
    "qs:name_local":"L\u00fcbeck",
    "qs:photo_max":161,
    "qs:photo_sum":269,
    "qs:placetype":"Suburb",
    "qs:quad_count":19,
    "qs:woe_adm0":23424829,
    "qs:woe_adm1":2345490,
    "qs:woe_adm2":12597082,
    "qs:woe_lau":26822945,
    "qs:woe_local":672826,
    "qs:woe_ver":"7.10.0",
    "wd:wordcount":64,
    "wof:lang":[
        "ger"
    ],
    "wof:name":"Vorwerk",
    "wof:placetype":"neighbourhood"
},
  "geometry": {"coordinates":[10.688773,53.897329],"type":"Point"}
}