{
  "type": "Feature",
  "properties": {
    "iso:country":"DE",
    "name:ceb_x_preferred":[
        "M\u00fchlen"
    ],
    "name:deu_x_colloquial":[
        "Muehlen",
        "Muhlen"
    ],
    "name:deu_x_preferred":[
        "M\u00fchlen"
    ],
    "name:epo_x_preferred":[
        "M\u00fchlen"
    ],
    "name:fas_x_preferred":[
        "\u0645\u0648\u0644\u0646"
    ],
    "name:fra_x_preferred":[
        "M\u00fchlen"
    ],
    "name:hun_x_preferred":[
        "M\u00fchlen"
    ],
    "name:ita_x_preferred":[
        "M\u00fchlen"
    ],
    "name:kaz_x_preferred":[
        "\u041c\u044e\u043b\u0435\u043d"
    ],
    "name:nld_x_preferred":[
        "M\u00fchlen"
    ],
    "name:pol_x_preferred":[
        "M\u00fchlen"
    ],
    "name:rus_x_preferred":[
        "\u041c\u044e\u043b\u0435\u043d"
    ],
    "name:slk_x_preferred":[
        "M\u00fchlen"
    ],
    "name:spa_x_preferred":[
        "M\u00fchlen"
    ],
    "name:swe_x_preferred":[
        "M\u00fchlen"
    ],
    "name:uzb_x_preferred":[
        "M\u00fchlen"
    ],
    "name:vie_x_preferred":[
        "M\u00fchlen"
    ],
    "name:vol_x_preferred":[
        "M\u00fchlen"
    ],
    "name:war_x_preferred":[
        "M\u00fchlen"
    ],
    "name:zho_x_preferred":[
        "\u7c73\u4f26"
    ],
    "qs:gn_fcode":"PPL",
    "qs:gn_local":0,
    "qs:gn_namadm1":"05",
    "qs:gn_name":"M\u00fchlen",
    "qs:local_max":62,
    "qs:local_sum":62,
    "qs:localhoods":1,
    "qs:name":"M\u00fchlen",
    "qs:name_adm0":"Deutschland",
    "qs:name_adm1":"Hessen",
    "qs:name_adm2":"Limburg-Weilburg",
    "qs:name_lau":"Stadtteil Eschhofen",
    "qs:name_local":"Stadtteil Eschhofen",
    "qs:photo_max":7,
    "qs:photo_sum":62,
    "qs:placetype":"Suburb",
    "qs:quad_count":27,
    "qs:woe_adm0":23424829,
    "qs:woe_adm1":2345485,
    "qs:woe_adm2":12596878,
    "qs:woe_lau":26822940,
    "qs:woe_local":26822940,
    "qs:woe_ver":"7.10.0",
    "wd:wordcount":30,
    "wof:lang":[
        "ger"
    ],
    "wof:name":"M\u00fchlen",
    "wof:placetype":"neighbourhood"
},
  "geometry": {"coordinates":[8.099842,50.397741],"type":"Point"}
}