{
  "type": "Feature",
  "properties": {
    "gn:admin1_code":"2.0",
    "gn:admin2_code":"97.0",
    "gn:admin3_code":"9778.0",
    "gn:admin4_code":"9778218.0",
    "gn:asciiname":"Bossarts",
    "gn:country_code":"DE",
    "gn:dem":745,
    "gn:feature_class":"P",
    "gn:feature_code":"PPL",
    "gn:name":"Bossarts",
    "gn:population":0,
    "gn:timezone":"Europe/Berlin",
    "iso:country":"DE",
    "wof:name":"Bossarts",
    "wof:placetype":"neighbourhood"
},
  "geometry": {"coordinates":[10.26116,47.91801],"type":"Point"}
}