{
  "type": "Feature",
  "properties": {
    "gn:admin1_code":"6",
    "gn:admin2_code":"0.0",
    "gn:admin3_code":"3457.0",
    "gn:admin4_code":"3457022.0",
    "gn:asciiname":"Steenfelderfeld",
    "gn:country_code":"DE",
    "gn:dem":3,
    "gn:feature_class":"P",
    "gn:feature_code":"PPL",
    "gn:name":"Steenfelderfeld",
    "gn:population":0,
    "gn:timezone":"Europe/Berlin",
    "iso:country":"DE",
    "wof:name":"Steenfelderfeld",
    "wof:placetype":"neighbourhood"
},
  "geometry": {"coordinates":[7.44449,53.12439000000001],"type":"Point"}
}