{
  "type": "Feature",
  "properties": {
    "gn:admin1_code":"11",
    "gn:admin2_code":"0.0",
    "gn:admin3_code":"12061.0",
    "gn:admin4_code":"12061471.0",
    "gn:asciiname":"Eichbusch",
    "gn:country_code":"DE",
    "gn:dem":90,
    "gn:feature_class":"P",
    "gn:feature_code":"PPL",
    "gn:name":"Eichbusch",
    "gn:population":0,
    "gn:timezone":"Europe/Berlin",
    "iso:country":"DE",
    "wof:name":"Eichbusch",
    "wof:placetype":"neighbourhood"
},
  "geometry": {"coordinates":[13.53431,51.96431],"type":"Point"}
}