{
  "type": "Feature",
  "properties": {
    "gn:admin1_code":"5",
    "gn:admin2_code":"66.0",
    "gn:admin3_code":"6635.0",
    "gn:admin4_code":"6635018.0",
    "gn:asciiname":"Rocklinghausen",
    "gn:country_code":"DE",
    "gn:dem":296,
    "gn:feature_class":"P",
    "gn:feature_code":"PPL",
    "gn:name":"Rocklinghausen",
    "gn:population":0,
    "gn:timezone":"Europe/Berlin",
    "iso:country":"DE",
    "wof:name":"Rocklinghausen",
    "wof:placetype":"neighbourhood"
},
  "geometry": {"coordinates":[8.94133,51.31954],"type":"Point"}
}