{
  "type": "Feature",
  "properties": {
    "iso:country":"DE",
    "name:ceb_x_preferred":[
        "P\u00e4idla"
    ],
    "name:deu_x_preferred":[
        "Samhof"
    ],
    "name:est_x_preferred":[
        "P\u00e4idla"
    ],
    "name:hye_x_preferred":[
        "\u054a\u0565\u056b\u0564\u056c\u0561"
    ],
    "name:pol_x_preferred":[
        "P\u00e4idla"
    ],
    "name:swe_x_preferred":[
        "P\u00e4idla"
    ],
    "name:unk_x_variant":[
        "Samhof"
    ],
    "name:vol_x_preferred":[
        "P\u00e4idla"
    ],
    "qs:gn_adm0_cc":"DE",
    "qs:gn_fcode":"PPL",
    "qs:gn_local":2895992,
    "qs:gn_nam_loc":"ingolstadt",
    "qs:gn_namadm1":"02",
    "qs:gn_name":"Ramhof",
    "qs:local_max":2187,
    "qs:local_sum":4335,
    "qs:localhoods":9,
    "qs:name":"Samhof",
    "qs:name_adm0":"Deutschland",
    "qs:name_adm1":"Bayern",
    "qs:name_adm2":"Stadtkreis Ingolstadt",
    "qs:name_lau":"Stadtteil Ingolstadt",
    "qs:name_local":"Ingolstadt",
    "qs:photo_max":30,
    "qs:photo_sum":119,
    "qs:placetype":"Suburb",
    "qs:quad_count":21,
    "qs:woe_adm0":23424829,
    "qs:woe_adm1":2345482,
    "qs:woe_adm2":12597077,
    "qs:woe_lau":26822676,
    "qs:woe_local":663545,
    "qs:woe_ver":"7.10.0",
    "wof:lang":[
        "ger"
    ],
    "wof:name":"Samhof",
    "wof:placetype":"neighbourhood"
},
  "geometry": {"coordinates":[11.387756,48.772793],"type":"Point"}
}