{
  "type": "Feature",
  "properties": {
    "gn:admin1_code":"7",
    "gn:admin2_code":"59.0",
    "gn:admin3_code":"5974.0",
    "gn:admin4_code":"5974036.0",
    "gn:asciiname":"Koertlinghausen",
    "gn:country_code":"DE",
    "gn:dem":376,
    "gn:feature_class":"P",
    "gn:feature_code":"PPL",
    "gn:name":"K\u00f6rtlinghausen",
    "gn:population":0,
    "gn:timezone":"Europe/Berlin",
    "iso:country":"DE",
    "wof:name":"Koertlinghausen",
    "wof:placetype":"neighbourhood"
},
  "geometry": {"coordinates":[8.41667,51.46667],"type":"Point"}
}