{
  "type": "Feature",
  "properties": {
    "gn:admin1_code":"2",
    "gn:admin2_code":"91.0",
    "gn:admin3_code":"9177.0",
    "gn:admin4_code":"9177117.0",
    "gn:asciiname":"Eichenkofen",
    "gn:country_code":"DE",
    "gn:dem":448,
    "gn:feature_class":"P",
    "gn:feature_code":"PPL",
    "gn:name":"Eichenkofen",
    "gn:population":0,
    "gn:timezone":"Europe/Berlin",
    "iso:country":"DE",
    "wof:name":"Eichenkofen",
    "wof:placetype":"neighbourhood"
},
  "geometry": {"coordinates":[11.92259,48.34636],"type":"Point"}
}