{
  "type": "Feature",
  "properties": {
    "gn:admin1_code":"1",
    "gn:admin2_code":"83.0",
    "gn:admin3_code":"8317.0",
    "gn:admin4_code":"8317005.0",
    "gn:asciiname":"Nesselried",
    "gn:country_code":"DE",
    "gn:dem":168,
    "gn:feature_class":"P",
    "gn:feature_code":"PPL",
    "gn:name":"Nesselried",
    "gn:population":0,
    "gn:timezone":"Europe/Berlin",
    "iso:country":"DE",
    "wof:name":"Nesselried",
    "wof:placetype":"neighbourhood"
},
  "geometry": {"coordinates":[8.00397,48.5195],"type":"Point"}
}