{
  "type": "Feature",
  "properties": {
    "gn:admin1_code":"6",
    "gn:admin2_code":"0.0",
    "gn:admin3_code":"3153.0",
    "gn:admin4_code":"3153014.0",
    "gn:asciiname":"Neuwallmoden",
    "gn:country_code":"DE",
    "gn:dem":140,
    "gn:feature_class":"P",
    "gn:feature_code":"PPL",
    "gn:name":"Neuwallmoden",
    "gn:population":0,
    "gn:timezone":"Europe/Berlin",
    "iso:country":"DE",
    "name:deu_x_preferred":[
        "Neuwallmoden (Wallmoden)"
    ],
    "wof:name":"Neuwallmoden",
    "wof:placetype":"neighbourhood"
},
  "geometry": {"coordinates":[10.26226,52.0113],"type":"Point"}
}