{
  "type": "Feature",
  "properties": {
    "gn:admin1_code":"2",
    "gn:admin2_code":"94.0",
    "gn:admin3_code":"9474.0",
    "gn:admin4_code":"9474135.0",
    "gn:asciiname":"Oesdorf",
    "gn:cc2":"DE",
    "gn:country_code":"DE",
    "gn:dem":312,
    "gn:feature_class":"P",
    "gn:feature_code":"PPL",
    "gn:name":"Oesdorf",
    "gn:population":0,
    "gn:timezone":"Europe/Berlin",
    "iso:country":"DE",
    "name:und_x_variant":[
        "\u00d6sdorf"
    ],
    "wof:name":"Oesdorf",
    "wof:placetype":"neighbourhood"
},
  "geometry": {"coordinates":[10.9786,49.70633],"type":"Point"}
}