{
  "type": "Feature",
  "properties": {
    "gn:admin1_code":"2",
    "gn:admin2_code":"94.0",
    "gn:admin3_code":"9477.0",
    "gn:admin4_code":"9477142.0",
    "gn:asciiname":"Unterlaitsch",
    "gn:country_code":"DE",
    "gn:dem":337,
    "gn:feature_class":"P",
    "gn:feature_code":"PPL",
    "gn:name":"Unterlaitsch",
    "gn:population":0,
    "gn:timezone":"Europe/Berlin",
    "iso:country":"DE",
    "wof:name":"Unterlaitsch",
    "wof:placetype":"neighbourhood"
},
  "geometry": {"coordinates":[11.54921,50.03782],"type":"Point"}
}