{
  "type": "Feature",
  "properties": {
    "gn:admin1_code":"1",
    "gn:admin2_code":"84.0",
    "gn:admin3_code":"8436.0",
    "gn:admin4_code":"8436008.0",
    "gn:asciiname":"Rugetsweiler",
    "gn:country_code":"DE",
    "gn:dem":550,
    "gn:feature_class":"P",
    "gn:feature_code":"PPL",
    "gn:name":"Rugetsweiler",
    "gn:population":0,
    "gn:timezone":"Europe/Berlin",
    "iso:country":"DE",
    "wof:name":"Rugetsweiler",
    "wof:placetype":"neighbourhood"
},
  "geometry": {"coordinates":[9.64523,47.93903],"type":"Point"}
}