{
  "type": "Feature",
  "properties": {
    "gn:admin1_code":"6.0",
    "gn:admin2_code":"00",
    "gn:admin3_code":"3241.0",
    "gn:admin4_code":"3241012.0",
    "gn:asciiname":"Wulfelade",
    "gn:country_code":"DE",
    "gn:dem":39,
    "gn:feature_class":"P",
    "gn:feature_code":"PPL",
    "gn:name":"Wulfelade",
    "gn:population":0,
    "gn:timezone":"Europe/Berlin",
    "iso:country":"DE",
    "wof:name":"Wulfelade",
    "wof:placetype":"neighbourhood"
},
  "geometry": {"coordinates":[9.50077,52.57082],"type":"Point"}
}