{
  "type": "Feature",
  "properties": {
    "gn:admin1_code":"2.0",
    "gn:admin2_code":"097",
    "gn:admin3_code":"9780.0",
    "gn:admin4_code":"9780140.0",
    "gn:asciiname":"Winkel",
    "gn:country_code":"DE",
    "gn:dem":922,
    "gn:feature_class":"P",
    "gn:feature_code":"PPL",
    "gn:name":"Winkel",
    "gn:population":0,
    "gn:timezone":"Europe/Berlin",
    "iso:country":"DE",
    "name:als_x_preferred":[
        "Winkel"
    ],
    "name:bre_x_preferred":[
        "Winkel"
    ],
    "name:ceb_x_preferred":[
        "Winkel"
    ],
    "name:deu_x_preferred":[
        "Winkel"
    ],
    "name:epo_x_preferred":[
        "Winkel"
    ],
    "name:eus_x_preferred":[
        "Winkel"
    ],
    "name:fra_x_preferred":[
        "Winkel"
    ],
    "name:fry_x_preferred":[
        "Winkel"
    ],
    "name:ita_x_preferred":[
        "Winkel"
    ],
    "name:nds_x_preferred":[
        "Winkel"
    ],
    "name:nld_x_preferred":[
        "Winkel"
    ],
    "name:pol_x_preferred":[
        "Winkel"
    ],
    "name:por_x_preferred":[
        "Winkel"
    ],
    "name:rus_x_preferred":[
        "\u0412\u0438\u043d\u043a\u0435\u043b\u044c"
    ],
    "name:swe_x_preferred":[
        "Winkel"
    ],
    "name:vol_x_preferred":[
        "Winkel"
    ],
    "wof:name":"Winkel",
    "wof:placetype":"neighbourhood"
},
  "geometry": {"coordinates":[10.36568,47.6468],"type":"Point"}
}