{
  "type": "Feature",
  "properties": {
    "gn:admin1_code":"6.0",
    "gn:admin2_code":"0.0",
    "gn:admin3_code":"3255.0",
    "gn:admin4_code":"3255025.0",
    "gn:asciiname":"Breitenkamp",
    "gn:country_code":"DE",
    "gn:dem":197,
    "gn:feature_class":"P",
    "gn:feature_code":"PPL",
    "gn:name":"Breitenkamp",
    "gn:population":0,
    "gn:timezone":"Europe/Berlin",
    "iso:country":"DE",
    "wof:name":"Breitenkamp",
    "wof:placetype":"neighbourhood"
},
  "geometry": {"coordinates":[9.55004,51.94744],"type":"Point"}
}