{
  "type": "Feature",
  "properties": {
    "gn:admin1_code":"8",
    "gn:admin2_code":"0.0",
    "gn:admin3_code":"7336.0",
    "gn:admin4_code":"7336064.0",
    "gn:asciiname":"Dietschweiler",
    "gn:country_code":"DE",
    "gn:dem":238,
    "gn:feature_class":"P",
    "gn:feature_code":"PPL",
    "gn:name":"Dietschweiler",
    "gn:population":0,
    "gn:timezone":"Europe/Berlin",
    "iso:country":"DE",
    "wof:name":"Dietschweiler",
    "wof:placetype":"neighbourhood"
},
  "geometry": {"coordinates":[7.4327,49.43789],"type":"Point"}
}