{
  "type": "Feature",
  "properties": {
    "gn:admin1_code":"2.0",
    "gn:admin2_code":"96.0",
    "gn:admin3_code":"9673.0",
    "gn:admin4_code":"9673114.0",
    "gn:asciiname":"Bad Neuhaus an der Saale",
    "gn:country_code":"DE",
    "gn:dem":245,
    "gn:feature_class":"P",
    "gn:feature_code":"PPL",
    "gn:name":"Bad Neuhaus an der Saale",
    "gn:population":0,
    "gn:timezone":"Europe/Berlin",
    "iso:country":"DE",
    "name:und_x_variant":[
        "Bad Neuhaus",
        "Bad Neuhaus an der Saale"
    ],
    "wof:name":"Bad Neuhaus an der Saale",
    "wof:placetype":"neighbourhood"
},
  "geometry": {"coordinates":[10.22476,50.3162],"type":"Point"}
}