{
  "type": "Feature",
  "properties": {
    "gn:admin1_code":"8",
    "gn:admin2_code":"0.0",
    "gn:admin3_code":"7133.0",
    "gn:admin4_code":"7133091.0",
    "gn:asciiname":"Lehnmuehle",
    "gn:country_code":"DE",
    "gn:dem":343,
    "gn:feature_class":"P",
    "gn:feature_code":"PPL",
    "gn:name":"Lehnm\u00fchle",
    "gn:population":0,
    "gn:timezone":"Europe/Berlin",
    "iso:country":"DE",
    "wof:name":"Lehnmuehle",
    "wof:placetype":"neighbourhood"
},
  "geometry": {"coordinates":[7.71878,49.94089],"type":"Point"}
}