{
  "type": "Feature",
  "properties": {
    "gn:admin1_code":"11",
    "gn:admin2_code":"0.0",
    "gn:admin3_code":"12071.0",
    "gn:admin4_code":"12071244.0",
    "gn:asciiname":"Gulben",
    "gn:country_code":"DE",
    "gn:dem":61,
    "gn:feature_class":"P",
    "gn:feature_code":"PPL",
    "gn:name":"Gulben",
    "gn:population":0,
    "gn:timezone":"Europe/Berlin",
    "iso:country":"DE",
    "name:und_x_variant":[
        "Golbin",
        "Gulben"
    ],
    "wof:name":"Gulben",
    "wof:placetype":"neighbourhood"
},
  "geometry": {"coordinates":[14.25417,51.78646],"type":"Point"}
}