{
  "type": "Feature",
  "properties": {
    "gn:admin1_code":"13",
    "gn:admin2_code":"0.0",
    "gn:admin3_code":"14627.0",
    "gn:admin4_code":"14627180.0",
    "gn:asciiname":"Klessig",
    "gn:country_code":"DE",
    "gn:dem":207,
    "gn:feature_class":"P",
    "gn:feature_code":"PPL",
    "gn:name":"Klessig",
    "gn:population":0,
    "gn:timezone":"Europe/Berlin",
    "iso:country":"DE",
    "wof:name":"Klessig",
    "wof:placetype":"neighbourhood"
},
  "geometry": {"coordinates":[13.2762,51.10835],"type":"Point"}
}