{
  "type": "Feature",
  "properties": {
    "gn:admin1_code":"12.0",
    "gn:admin2_code":"00",
    "gn:admin3_code":"13072.0",
    "gn:admin4_code":"13072061.0",
    "gn:asciiname":"Zehlendorf",
    "gn:country_code":"DE",
    "gn:dem":21,
    "gn:feature_class":"P",
    "gn:feature_code":"PPL",
    "gn:name":"Zehlendorf",
    "gn:population":0,
    "gn:timezone":"Europe/Berlin",
    "iso:country":"DE",
    "name:deu_x_preferred":[
        "Zehlendorf"
    ],
    "name:epo_x_preferred":[
        "Zehlendorf"
    ],
    "name:ita_x_preferred":[
        "Zehlendorf"
    ],
    "name:nld_x_preferred":[
        "Zehlendorf"
    ],
    "name:pol_x_preferred":[
        "Zehlendorf"
    ],
    "name:swe_x_preferred":[
        "Zehlendorf"
    ],
    "wof:name":"Zehlendorf",
    "wof:placetype":"neighbourhood"
},
  "geometry": {"coordinates":[12.27021,53.86904000000001],"type":"Point"}
}