{
  "type": "Feature",
  "properties": {
    "gn:country":"DE",
    "gn:fcode":"PPLA4",
    "gn:population":228,
    "iso:country":"DE",
    "name:bak_x_preferred":[
        "\u041a\u0430\u0441\u0441\u0438\u043a"
    ],
    "name:ceb_x_preferred":[
        "Kassieck"
    ],
    "name:deu_x_preferred":[
        "Kassieck"
    ],
    "name:epo_x_preferred":[
        "Kassieck"
    ],
    "name:fas_x_preferred":[
        "\u06a9\u0627\u0633\u0633\u06cc\u06a9"
    ],
    "name:ita_x_preferred":[
        "Kassieck"
    ],
    "name:kaz_x_preferred":[
        "\u041a\u0430\u0441\u0441\u0438\u043a"
    ],
    "name:kir_x_preferred":[
        "\u041a\u0430\u0441\u0441\u0438\u043a"
    ],
    "name:nld_x_preferred":[
        "Kassieck"
    ],
    "name:pol_x_preferred":[
        "Kassieck"
    ],
    "name:ron_x_preferred":[
        "Kassieck"
    ],
    "name:rus_x_preferred":[
        "\u041a\u0430\u0441\u0441\u0438\u043a"
    ],
    "name:srp_x_preferred":[
        "\u041a\u0430\u0441\u0438\u043a"
    ],
    "name:uzb_x_preferred":[
        "Kassieck"
    ],
    "name:vie_x_preferred":[
        "Kassieck"
    ],
    "name:vol_x_preferred":[
        "Kassieck"
    ],
    "name:war_x_preferred":[
        "Kassieck"
    ],
    "qs_pg:aaroncc":"DE",
    "qs_pg:gn_country":"DE",
    "qs_pg:gn_fcode":"PPLA4",
    "qs_pg:gn_pop":228,
    "qs_pg:name":"Kassieck",
    "qs_pg:photos_9r":0,
    "qs_pg:photos_sr":0,
    "qs_pg:pop_sr":2,
    "qs_pg:qs_pg_placetype":"locality",
    "wof:name":"Kassieck",
    "wof:placetype":"neighbourhood",
    "wof:population":228
},
  "geometry": {"coordinates":[11.48333,52.58333],"type":"Point"}
}