{
  "type": "Feature",
  "properties": {
    "gn:admin1_code":"1.0",
    "gn:admin2_code":"81.0",
    "gn:admin3_code":"8136.0",
    "gn:admin4_code":"8136010.0",
    "gn:asciiname":"Aufhausen",
    "gn:country_code":"DE",
    "gn:dem":493,
    "gn:feature_class":"P",
    "gn:feature_code":"PPL",
    "gn:name":"Aufhausen",
    "gn:population":0,
    "gn:timezone":"Europe/Berlin",
    "iso:country":"DE",
    "name:ceb_x_preferred":[
        "Aufhausen"
    ],
    "name:deu_x_preferred":[
        "Aufhausen"
    ],
    "name:epo_x_preferred":[
        "Aufhausen"
    ],
    "name:eus_x_preferred":[
        "Aufhausen"
    ],
    "name:fas_x_preferred":[
        "\u0622\u0648\u0641\u0647\u0627\u0648\u0632\u0646"
    ],
    "name:fra_x_preferred":[
        "Aufhausen"
    ],
    "name:hun_x_preferred":[
        "Aufhausen"
    ],
    "name:hye_x_preferred":[
        "\u0531\u0578\u0582\u0586\u0570\u0561\u0578\u0582\u0566\u0565\u0576"
    ],
    "name:ita_x_preferred":[
        "Aufhausen"
    ],
    "name:kaz_x_preferred":[
        "\u0410\u0443\u0444\u0445\u0430\u0443\u0437\u0435\u043d"
    ],
    "name:kir_x_preferred":[
        "\u0410\u0443\u0444\u0445\u0430\u0443\u0437\u0435\u043d"
    ],
    "name:lat_x_preferred":[
        "Aufhausen"
    ],
    "name:lmo_x_preferred":[
        "Aufhausen"
    ],
    "name:msa_x_preferred":[
        "Aufhausen"
    ],
    "name:nld_x_preferred":[
        "Aufhausen"
    ],
    "name:pol_x_preferred":[
        "Aufhausen"
    ],
    "name:por_x_preferred":[
        "Aufhausen"
    ],
    "name:ron_x_preferred":[
        "Aufhausen"
    ],
    "name:rus_x_preferred":[
        "\u0410\u0443\u0444\u0445\u0430\u0443\u0437\u0435\u043d"
    ],
    "name:spa_x_preferred":[
        "Aufhausen"
    ],
    "name:srp_x_preferred":[
        "\u0410\u0443\u0444\u0445\u0430\u0443\u0437\u0435\u043d"
    ],
    "name:ukr_x_preferred":[
        "\u0410\u0443\u0444\u0433\u0430\u0443\u0437\u0435\u043d"
    ],
    "name:uzb_x_preferred":[
        "Aufhausen"
    ],
    "name:vie_x_preferred":[
        "Aufhausen"
    ],
    "name:vol_x_preferred":[
        "Aufhausen"
    ],
    "name:war_x_preferred":[
        "Aufhausen"
    ],
    "name:zho_x_preferred":[
        "\u5965\u592b\u8c6a\u68ee"
    ],
    "wof:name":"Aufhausen",
    "wof:placetype":"neighbourhood"
},
  "geometry": {"coordinates":[10.31779,48.86015],"type":"Point"}
}