{
  "type": "Feature",
  "properties": {
    "gn:admin1_code":"5",
    "gn:admin2_code":"65.0",
    "gn:admin3_code":"6531.0",
    "gn:admin4_code":"6531006.0",
    "gn:asciiname":"Lumda",
    "gn:country_code":"DE",
    "gn:dem":265,
    "gn:feature_class":"P",
    "gn:feature_code":"PPL",
    "gn:name":"Lumda",
    "gn:population":0,
    "gn:timezone":"Europe/Berlin",
    "iso:country":"DE",
    "name:deu_x_preferred":[
        "Lumda"
    ],
    "wof:name":"Lumda",
    "wof:placetype":"neighbourhood"
},
  "geometry": {"coordinates":[8.9436,50.63469],"type":"Point"}
}