{
  "type": "Feature",
  "properties": {
    "gn:admin1_code":"5",
    "gn:admin2_code":"66.0",
    "gn:admin3_code":"6631.0",
    "gn:admin4_code":"6631004.0",
    "gn:asciiname":"Ober-Stellberg",
    "gn:country_code":"DE",
    "gn:dem":468,
    "gn:feature_class":"P",
    "gn:feature_code":"PPL",
    "gn:name":"Ober-Stellberg",
    "gn:population":0,
    "gn:timezone":"Europe/Berlin",
    "iso:country":"DE",
    "wof:name":"Ober-Stellberg",
    "wof:placetype":"neighbourhood"
},
  "geometry": {"coordinates":[9.79929,50.43039],"type":"Point"}
}