{
  "type": "Feature",
  "properties": {
    "gn:admin1_code":"2",
    "gn:admin2_code":"93.0",
    "gn:admin3_code":"9373.0",
    "gn:admin4_code":"9373167.0",
    "gn:asciiname":"Oberwiesenacker",
    "gn:country_code":"DE",
    "gn:dem":512,
    "gn:feature_class":"P",
    "gn:feature_code":"PPL",
    "gn:name":"Oberwiesenacker",
    "gn:population":0,
    "gn:timezone":"Europe/Berlin",
    "iso:country":"DE",
    "wof:name":"Oberwiesenacker",
    "wof:placetype":"neighbourhood"
},
  "geometry": {"coordinates":[11.6171,49.28617],"type":"Point"}
}