{
  "type": "Feature",
  "properties": {
    "gn:admin1_code":"7.0",
    "gn:admin2_code":"53.0",
    "gn:admin3_code":"5370.0",
    "gn:admin4_code":"5370020.0",
    "gn:asciiname":"Brachelen",
    "gn:country_code":"DE",
    "gn:dem":60,
    "gn:feature_class":"P",
    "gn:feature_code":"PPL",
    "gn:name":"Brachelen",
    "gn:population":0,
    "gn:timezone":"Europe/Berlin",
    "iso:country":"DE",
    "wof:name":"Brachelen",
    "wof:placetype":"neighbourhood"
},
  "geometry": {"coordinates":[6.23801,51.00745],"type":"Point"}
}