{
  "type": "Feature",
  "properties": {
    "gn:admin1_code":"2.0",
    "gn:admin2_code":"097",
    "gn:admin3_code":"9780.0",
    "gn:admin4_code":"9780112.0",
    "gn:asciiname":"Wolfen",
    "gn:country_code":"DE",
    "gn:dem":739,
    "gn:feature_class":"P",
    "gn:feature_code":"PPL",
    "gn:name":"Wolfen",
    "gn:population":0,
    "gn:timezone":"Europe/Berlin",
    "iso:country":"DE",
    "name:deu_x_preferred":[
        "Wolfen"
    ],
    "name:fra_x_preferred":[
        "Wolfen"
    ],
    "wof:name":"Wolfen",
    "wof:placetype":"neighbourhood"
},
  "geometry": {"coordinates":[10.24403,47.77553],"type":"Point"}
}