{
  "type": "Feature",
  "properties": {
    "gn:gn_country":"DE",
    "gn:gn_fcode":"PPLA4",
    "gn:gn_pop":502,
    "gn:population":502,
    "iso:country":"DE",
    "qs_pg:aaroncc":"DE",
    "qs_pg:gn_country":"DE",
    "qs_pg:gn_fcode":"PPLA4",
    "qs_pg:gn_pop":502,
    "qs_pg:name":"M\u00f6rsbach",
    "qs_pg:photos_9r":0,
    "qs_pg:photos_sr":0,
    "qs_pg:pop_sr":2,
    "qs_pg:qs_pg_placetype":"locality",
    "wof:name":"M\u00f6rsbach",
    "wof:placetype":"locality",
    "wof:population":502
},
  "geometry": {"coordinates":[7.76667,50.71667],"type":"Point"}
}