{
  "type": "Feature",
  "properties": {
    "gn:admin1_code":"10",
    "gn:admin2_code":"0.0",
    "gn:admin3_code":"1055.0",
    "gn:admin4_code":"1055035.0",
    "gn:asciiname":"Haeven",
    "gn:country_code":"DE",
    "gn:dem":12,
    "gn:feature_class":"P",
    "gn:feature_code":"PPL",
    "gn:name":"H\u00e4ven",
    "gn:population":0,
    "gn:timezone":"Europe/Berlin",
    "iso:country":"DE",
    "wof:name":"Haeven",
    "wof:placetype":"neighbourhood"
},
  "geometry": {"coordinates":[10.83003,53.97994],"type":"Point"}
}