{
  "type": "Feature",
  "properties": {
    "gn:admin1_code":"2",
    "gn:admin2_code":"91.0",
    "gn:admin3_code":"9190.0",
    "gn:admin4_code":"9190158.0",
    "gn:asciiname":"Sankt Leonhard",
    "gn:country_code":"DE",
    "gn:dem":765,
    "gn:feature_class":"P",
    "gn:feature_code":"PPL",
    "gn:name":"Sankt Leonhard",
    "gn:population":0,
    "gn:timezone":"Europe/Berlin",
    "iso:country":"DE",
    "name:ceb_x_preferred":[
        "Sankt Leonhard"
    ],
    "name:deu_x_preferred":[
        "Sankt Leonhard"
    ],
    "name:ita_x_preferred":[
        "Sankt Leonhard"
    ],
    "name:nld_x_preferred":[
        "Sankt Leonhard"
    ],
    "name:pol_x_preferred":[
        "Sankt Leonhard"
    ],
    "name:swe_x_preferred":[
        "Sankt Leonhard"
    ],
    "wof:name":"Sankt Leonhard",
    "wof:placetype":"neighbourhood"
},
  "geometry": {"coordinates":[11.03275,47.84722],"type":"Point"}
}