{
  "type": "Feature",
  "properties": {
    "gn:admin1_code":"6",
    "gn:admin2_code":"0.0",
    "gn:admin3_code":"3151.0",
    "gn:admin4_code":"3151018.0",
    "gn:asciiname":"Ettenbuettel",
    "gn:country_code":"DE",
    "gn:dem":52,
    "gn:feature_class":"P",
    "gn:feature_code":"PPL",
    "gn:name":"Ettenb\u00fcttel",
    "gn:population":0,
    "gn:timezone":"Europe/Berlin",
    "iso:country":"DE",
    "wof:name":"Ettenbuettel",
    "wof:placetype":"neighbourhood"
},
  "geometry": {"coordinates":[10.41306,52.49912],"type":"Point"}
}