{
  "type": "Feature",
  "properties": {
    "gn:admin1_code":"8",
    "gn:admin2_code":"0.0",
    "gn:admin3_code":"7335.0",
    "gn:admin4_code":"7335016.0",
    "gn:asciiname":"Katzenbach",
    "gn:country_code":"DE",
    "gn:dem":254,
    "gn:feature_class":"P",
    "gn:feature_code":"PPL",
    "gn:name":"Katzenbach",
    "gn:population":0,
    "gn:timezone":"Europe/Berlin",
    "iso:country":"DE",
    "name:ceb_x_preferred":[
        "Katzenbach"
    ],
    "name:deu_x_preferred":[
        "Katzenbach"
    ],
    "name:epo_x_preferred":[
        "Katzenbach"
    ],
    "name:fra_x_preferred":[
        "Katzenbach"
    ],
    "name:nld_x_preferred":[
        "Katzenbach"
    ],
    "name:pol_x_preferred":[
        "Katzenbach"
    ],
    "name:swe_x_preferred":[
        "Katzenbach"
    ],
    "wof:name":"Katzenbach",
    "wof:placetype":"neighbourhood"
},
  "geometry": {"coordinates":[7.50228,49.43453],"type":"Point"}
}