{
  "type": "Feature",
  "properties": {
    "gn:admin1_code":"2.0",
    "gn:admin2_code":"95.0",
    "gn:admin3_code":"9574.0",
    "gn:admin4_code":"9574157.0",
    "gn:asciiname":"Altenthann",
    "gn:country_code":"DE",
    "gn:dem":425,
    "gn:feature_class":"P",
    "gn:feature_code":"PPL",
    "gn:name":"Altenthann",
    "gn:population":0,
    "gn:timezone":"Europe/Berlin",
    "iso:country":"DE",
    "name:bar_x_preferred":[
        "Altenthann"
    ],
    "name:ceb_x_preferred":[
        "Altenthann"
    ],
    "name:deu_x_preferred":[
        "Altenthann"
    ],
    "name:epo_x_preferred":[
        "Altenthann"
    ],
    "name:eus_x_preferred":[
        "Altenthann"
    ],
    "name:fas_x_preferred":[
        "\u0627\u0644\u062a\u0646\u062a\u0627\u0646"
    ],
    "name:fra_x_preferred":[
        "Altenthann"
    ],
    "name:hun_x_preferred":[
        "Altenthann"
    ],
    "name:hye_x_preferred":[
        "\u0531\u056c\u057f\u0565\u0576\u0569\u0561\u0576"
    ],
    "name:ita_x_preferred":[
        "Altenthann"
    ],
    "name:lat_x_preferred":[
        "Altenthann"
    ],
    "name:lmo_x_preferred":[
        "Altenthann"
    ],
    "name:msa_x_preferred":[
        "Altenthann"
    ],
    "name:nld_x_preferred":[
        "Altenthann"
    ],
    "name:pol_x_preferred":[
        "Altenthann"
    ],
    "name:por_x_preferred":[
        "Altenthann"
    ],
    "name:ron_x_preferred":[
        "Altenthann"
    ],
    "name:rus_x_preferred":[
        "\u0410\u043b\u044c\u0442\u0435\u043d\u0442\u0430\u043d\u043d"
    ],
    "name:spa_x_preferred":[
        "Altenthann"
    ],
    "name:srp_x_preferred":[
        "\u0410\u043b\u0442\u0435\u043d\u0442\u0430\u043d"
    ],
    "name:ukr_x_preferred":[
        "\u0410\u043b\u044c\u0442\u0435\u043d\u0442\u0430\u043d\u043d"
    ],
    "name:uzb_x_preferred":[
        "Altenthann"
    ],
    "name:vie_x_preferred":[
        "Altenthann"
    ],
    "name:vol_x_preferred":[
        "Altenthann"
    ],
    "name:war_x_preferred":[
        "Altenthann"
    ],
    "name:zho_x_preferred":[
        "\u963f\u5c14\u6ed5\u5766"
    ],
    "wof:name":"Altenthann",
    "wof:placetype":"neighbourhood"
},
  "geometry": {"coordinates":[11.30633,49.36742],"type":"Point"}
}