{
  "type": "Feature",
  "properties": {
    "gn:admin1_code":"1",
    "gn:admin2_code":"83.0",
    "gn:admin3_code":"8337.0",
    "gn:admin4_code":"8337027.0",
    "gn:asciiname":"Innerurberg",
    "gn:country_code":"DE",
    "gn:dem":974,
    "gn:feature_class":"P",
    "gn:feature_code":"PPL",
    "gn:name":"Innerurberg",
    "gn:population":0,
    "gn:timezone":"Europe/Berlin",
    "iso:country":"DE",
    "wof:name":"Innerurberg",
    "wof:placetype":"neighbourhood"
},
  "geometry": {"coordinates":[8.12365,47.73491],"type":"Point"}
}