{
  "type": "Feature",
  "properties": {
    "gn:admin1_code":"13",
    "gn:admin2_code":"0.0",
    "gn:admin3_code":"14626.0",
    "gn:admin4_code":"14626260.0",
    "gn:asciiname":"Kolonie Baruther Berg",
    "gn:country_code":"DE",
    "gn:dem":153,
    "gn:feature_class":"P",
    "gn:feature_code":"PPL",
    "gn:name":"Kolonie Baruther Berg",
    "gn:population":0,
    "gn:timezone":"Europe/Berlin",
    "iso:country":"DE",
    "name:und_x_variant":[
        "Baruther Berg Kolonie",
        "Kolonie Baruther Berg"
    ],
    "wof:name":"Kolonie Baruther Berg",
    "wof:placetype":"neighbourhood"
},
  "geometry": {"coordinates":[14.68444,51.3289],"type":"Point"}
}