{
  "type": "Feature",
  "properties": {
    "gn:admin1_code":"2",
    "gn:admin2_code":"92.0",
    "gn:admin3_code":"9277.0",
    "gn:admin4_code":"9277154.0",
    "gn:asciiname":"Schildthurn",
    "gn:country_code":"DE",
    "gn:dem":486,
    "gn:feature_class":"P",
    "gn:feature_code":"PPL",
    "gn:name":"Schildthurn",
    "gn:population":0,
    "gn:timezone":"Europe/Berlin",
    "iso:country":"DE",
    "wof:name":"Schildthurn",
    "wof:placetype":"neighbourhood"
},
  "geometry": {"coordinates":[12.86087,48.3014],"type":"Point"}
}