{
  "type": "Feature",
  "properties": {
    "gn:admin1_code":"2.0",
    "gn:admin2_code":"093",
    "gn:admin3_code":"9373.0",
    "gn:admin4_code":"9373113.0",
    "gn:asciiname":"Wunricht",
    "gn:country_code":"DE",
    "gn:dem":544,
    "gn:feature_class":"P",
    "gn:feature_code":"PPL",
    "gn:name":"W\u00fcnricht",
    "gn:population":0,
    "gn:timezone":"Europe/Berlin",
    "iso:country":"DE",
    "wof:name":"Wunricht",
    "wof:placetype":"neighbourhood"
},
  "geometry": {"coordinates":[11.47316,49.38818],"type":"Point"}
}