{
  "type": "Feature",
  "properties": {
    "gn:admin1_code":"2",
    "gn:admin2_code":"97.0",
    "gn:admin3_code":"9778.0",
    "gn:admin4_code":"9778113.0",
    "gn:asciiname":"Grunegg",
    "gn:country_code":"DE",
    "gn:dem":662,
    "gn:feature_class":"P",
    "gn:feature_code":"PPL",
    "gn:name":"Gr\u00fcnegg",
    "gn:population":0,
    "gn:timezone":"Europe/Berlin",
    "iso:country":"DE",
    "wof:name":"Grunegg",
    "wof:placetype":"neighbourhood"
},
  "geometry": {"coordinates":[10.46175,47.9814],"type":"Point"}
}