{
  "type": "Feature",
  "properties": {
    "gn:admin1_code":"10",
    "gn:admin2_code":"0.0",
    "gn:admin3_code":"1004.0",
    "gn:admin4_code":"1004000.0",
    "gn:asciiname":"Tungendorf",
    "gn:country_code":"DE",
    "gn:dem":28,
    "gn:feature_class":"P",
    "gn:feature_code":"PPL",
    "gn:name":"Tungendorf",
    "gn:population":0,
    "gn:timezone":"Europe/Berlin",
    "iso:country":"DE",
    "wof:name":"Tungendorf",
    "wof:placetype":"neighbourhood"
},
  "geometry": {"coordinates":[9.9966,54.09878000000001],"type":"Point"}
}