{
  "type": "Feature",
  "properties": {
    "gn:admin1_code":"2",
    "gn:admin2_code":"91.0",
    "gn:admin3_code":"9182.0",
    "gn:admin4_code":"9182129.0",
    "gn:asciiname":"Gutfeld",
    "gn:country_code":"DE",
    "gn:dem":755,
    "gn:feature_class":"P",
    "gn:feature_code":"PPL",
    "gn:name":"Gutfeld",
    "gn:population":0,
    "gn:timezone":"Europe/Berlin",
    "iso:country":"DE",
    "wof:name":"Gutfeld",
    "wof:placetype":"neighbourhood"
},
  "geometry": {"coordinates":[11.80114,47.68685],"type":"Point"}
}