{
  "type": "Feature",
  "properties": {
    "gn:admin1_code":"11",
    "gn:admin2_code":"0.0",
    "gn:admin3_code":"12071.0",
    "gn:admin4_code":"12071074.0",
    "gn:asciiname":"Vorwerk Klein Loitz",
    "gn:country_code":"DE",
    "gn:dem":135,
    "gn:feature_class":"P",
    "gn:feature_code":"PPL",
    "gn:name":"Vorwerk Klein Loitz",
    "gn:population":0,
    "gn:timezone":"Europe/Berlin",
    "iso:country":"DE",
    "wof:name":"Vorwerk Klein Loitz",
    "wof:placetype":"neighbourhood"
},
  "geometry": {"coordinates":[14.51105,51.60658],"type":"Point"}
}