{
  "type": "Feature",
  "properties": {
    "gn:admin1_code":"2",
    "gn:admin2_code":"97.0",
    "gn:admin3_code":"9773.0",
    "gn:admin4_code":"9773164.0",
    "gn:asciiname":"Gremheim",
    "gn:country_code":"DE",
    "gn:dem":417,
    "gn:feature_class":"P",
    "gn:feature_code":"PPL",
    "gn:name":"Gremheim",
    "gn:population":0,
    "gn:timezone":"Europe/Berlin",
    "iso:country":"DE",
    "name:und_x_variant":[
        "Blenheim",
        "Gremheim"
    ],
    "wof:name":"Gremheim",
    "wof:placetype":"neighbourhood"
},
  "geometry": {"coordinates":[10.64714,48.63546],"type":"Point"}
}