{
  "type": "Feature",
  "properties": {
    "gn:admin1_code":"2",
    "gn:admin2_code":"93.0",
    "gn:admin3_code":"9362.0",
    "gn:admin4_code":"9362000.0",
    "gn:asciiname":"Unterisling",
    "gn:country_code":"DE",
    "gn:dem":350,
    "gn:feature_class":"P",
    "gn:feature_code":"PPL",
    "gn:name":"Unterisling",
    "gn:population":0,
    "gn:timezone":"Europe/Berlin",
    "iso:country":"DE",
    "wof:name":"Unterisling",
    "wof:placetype":"neighbourhood"
},
  "geometry": {"coordinates":[12.1181,48.98251],"type":"Point"}
}