{
  "type": "Feature",
  "properties": {
    "gn:country":"DE",
    "gn:fcode":"PPL",
    "gn:population":0,
    "iso:country":"DE",
    "name:cat_x_preferred":[
        "Greetsiel"
    ],
    "name:ceb_x_preferred":[
        "Greetsiel"
    ],
    "name:deu_x_preferred":[
        "Greetsiel"
    ],
    "name:epo_x_preferred":[
        "Greetsiel"
    ],
    "name:fas_x_preferred":[
        "\u06af\u0631\u062a\u0633\u06cc\u0644"
    ],
    "name:fra_x_preferred":[
        "Greetsiel"
    ],
    "name:fry_x_preferred":[
        "Grytsjesyl"
    ],
    "name:fry_x_variant":[
        "Greetsiel"
    ],
    "name:nld_x_preferred":[
        "Greetsiel"
    ],
    "name:stq_x_preferred":[
        "Greetsiel"
    ],
    "qs_pg:aaroncc":"DE",
    "qs_pg:gn_country":"DE",
    "qs_pg:gn_fcode":"PPL",
    "qs_pg:gn_pop":0,
    "qs_pg:name":"Greetsiel",
    "qs_pg:name_adm0":"Deutschland",
    "qs_pg:name_adm1":"Niedersachsen",
    "qs_pg:photos":1202,
    "qs_pg:photos_1k":244,
    "qs_pg:photos_9k":5,
    "qs_pg:photos_9r":7,
    "qs_pg:photos_all":1202,
    "qs_pg:photos_sr":11,
    "qs_pg:pop_sr":0,
    "qs_pg:qs_pg_placetype":"locality",
    "qs_pg:qs_pg_placetype_gp":"Town",
    "qs_pg:woe_adm0":23424829,
    "woe:adm0_id":23424829,
    "woe:name_adm0":"Deutschland",
    "woe:name_adm1":"Niedersachsen",
    "woe:placetype":"Town",
    "wof:name":"Greetsiel",
    "wof:placetype":"neighbourhood"
},
  "geometry": {"coordinates":[7.09445,53.50162],"type":"Point"}
}