{
  "type": "Feature",
  "properties": {
    "gn:admin1_code":"2",
    "gn:admin2_code":"91.0",
    "gn:admin3_code":"9189.0",
    "gn:admin4_code":"9189142.0",
    "gn:asciiname":"Schmidham",
    "gn:country_code":"DE",
    "gn:dem":577,
    "gn:feature_class":"P",
    "gn:feature_code":"PPL",
    "gn:name":"Schmidham",
    "gn:population":0,
    "gn:timezone":"Europe/Berlin",
    "iso:country":"DE",
    "wof:name":"Schmidham",
    "wof:placetype":"neighbourhood"
},
  "geometry": {"coordinates":[12.3988,48.05207],"type":"Point"}
}