{
  "type": "Feature",
  "properties": {
    "gn:admin1_code":"1",
    "gn:admin2_code":"84.0",
    "gn:admin3_code":"8436.0",
    "gn:admin4_code":"8436094.0",
    "gn:asciiname":"Meggen",
    "gn:country_code":"DE",
    "gn:dem":677,
    "gn:feature_class":"P",
    "gn:feature_code":"PPL",
    "gn:name":"Meggen",
    "gn:population":0,
    "gn:timezone":"Europe/Berlin",
    "iso:country":"DE",
    "name:als_x_preferred":[
        "Meggen"
    ],
    "name:ceb_x_preferred":[
        "Meggen"
    ],
    "name:ces_x_preferred":[
        "Meggen"
    ],
    "name:deu_x_preferred":[
        "Meggen"
    ],
    "name:epo_x_preferred":[
        "Meggen"
    ],
    "name:eus_x_preferred":[
        "Meggen"
    ],
    "name:fra_x_preferred":[
        "Meggen"
    ],
    "name:ita_x_preferred":[
        "Meggen"
    ],
    "name:kaz_x_preferred":[
        "\u041c\u0435\u0433\u0433\u0435\u043d"
    ],
    "name:lmo_x_preferred":[
        "Meggen"
    ],
    "name:msa_x_preferred":[
        "Meggen"
    ],
    "name:nld_x_preferred":[
        "Meggen"
    ],
    "name:nno_x_preferred":[
        "Meggen"
    ],
    "name:pms_x_preferred":[
        "Meggen"
    ],
    "name:por_x_preferred":[
        "Meggen"
    ],
    "name:rus_x_preferred":[
        "\u041c\u0435\u0433\u0433\u0435\u043d"
    ],
    "name:spa_x_preferred":[
        "Meggen"
    ],
    "name:sqi_x_preferred":[
        "Meggen"
    ],
    "name:swe_x_preferred":[
        "Meggen"
    ],
    "name:uzb_x_preferred":[
        "Meggen"
    ],
    "name:vol_x_preferred":[
        "Meggen"
    ],
    "name:war_x_preferred":[
        "Meggen"
    ],
    "wof:name":"Meggen",
    "wof:placetype":"neighbourhood"
},
  "geometry": {"coordinates":[9.93784,47.74257],"type":"Point"}
}