{
  "type": "Feature",
  "properties": {
    "gn:admin1_code":"15",
    "gn:admin2_code":"0.0",
    "gn:admin3_code":"16070.0",
    "gn:admin4_code":"16070056.0",
    "gn:asciiname":"Trassdorf",
    "gn:country_code":"DE",
    "gn:dem":403,
    "gn:feature_class":"P",
    "gn:feature_code":"PPL",
    "gn:name":"Tra\u00dfdorf",
    "gn:population":0,
    "gn:timezone":"Europe/Berlin",
    "iso:country":"DE",
    "wof:name":"Trassdorf",
    "wof:placetype":"neighbourhood"
},
  "geometry": {"coordinates":[11.01584,50.74725],"type":"Point"}
}