{
  "type": "Feature",
  "properties": {
    "gn:admin1_code":"6",
    "gn:admin2_code":"0.0",
    "gn:admin3_code":"3459.0",
    "gn:admin4_code":"3459003.0",
    "gn:asciiname":"Essenerberg",
    "gn:country_code":"DE",
    "gn:dem":139,
    "gn:feature_class":"P",
    "gn:feature_code":"PPL",
    "gn:name":"Essenerberg",
    "gn:population":0,
    "gn:timezone":"Europe/Berlin",
    "iso:country":"DE",
    "wof:name":"Essenerberg",
    "wof:placetype":"neighbourhood"
},
  "geometry": {"coordinates":[8.32347,52.30437],"type":"Point"}
}