{
  "type": "Feature",
  "properties": {
    "gn:admin1_code":"1",
    "gn:admin2_code":"82.0",
    "gn:admin3_code":"8215.0",
    "gn:admin4_code":"8215111.0",
    "gn:asciiname":"Liedolsheim",
    "gn:country_code":"DE",
    "gn:dem":101,
    "gn:feature_class":"P",
    "gn:feature_code":"PPL",
    "gn:name":"Liedolsheim",
    "gn:population":0,
    "gn:timezone":"Europe/Berlin",
    "iso:country":"DE",
    "wof:name":"Liedolsheim",
    "wof:placetype":"neighbourhood"
},
  "geometry": {"coordinates":[8.42222,49.15875],"type":"Point"}
}