{
  "type": "Feature",
  "properties": {
    "gn:admin1_code":"10",
    "gn:admin2_code":"0.0",
    "gn:admin3_code":"1057.0",
    "gn:admin4_code":"1057031.0",
    "gn:asciiname":"Klein Havighorst",
    "gn:country_code":"DE",
    "gn:dem":40,
    "gn:feature_class":"P",
    "gn:feature_code":"PPL",
    "gn:name":"Klein Havighorst",
    "gn:population":0,
    "gn:timezone":"Europe/Berlin",
    "iso:country":"DE",
    "name:und_x_variant":[
        "Havighorst Zwei",
        "Klein Havighorst"
    ],
    "wof:name":"Klein Havighorst",
    "wof:placetype":"neighbourhood"
},
  "geometry": {"coordinates":[10.155,54.23365],"type":"Point"}
}