{
  "type": "Feature",
  "properties": {
    "gn:population":1269,
    "iso:country":"DE",
    "name:baq_x_preferred":[
        "Palzem"
    ],
    "name:chi_x_preferred":[
        "\u5e15\u5c14\u7b56\u59c6"
    ],
    "name:deu_x_preferred":[
        "Palzem"
    ],
    "name:dut_x_preferred":[
        "Palzem"
    ],
    "name:eng_x_preferred":[
        "Palzem"
    ],
    "name:epo_x_preferred":[
        "Palzem"
    ],
    "name:eus_x_preferred":[
        "Palzem"
    ],
    "name:fra_x_preferred":[
        "Palzem"
    ],
    "name:fre_x_preferred":[
        "Palzem"
    ],
    "name:ger_x_preferred":[
        "Palzem"
    ],
    "name:hbs_x_preferred":[
        "Palzem"
    ],
    "name:hun_x_preferred":[
        "Palzem"
    ],
    "name:ita_x_preferred":[
        "Palzem"
    ],
    "name:jpn_x_preferred":[
        "\u30d1\u30eb\u30c4\u30a7\u30e0"
    ],
    "name:ltz_x_preferred":[
        "Palzem"
    ],
    "name:may_x_preferred":[
        "Palzem"
    ],
    "name:msa_x_preferred":[
        "Palzem"
    ],
    "name:nld_x_preferred":[
        "Palzem"
    ],
    "name:per_x_preferred":[
        "\u067e\u0627\u0644\u062a\u0633\u0645"
    ],
    "name:pol_x_preferred":[
        "Palzem"
    ],
    "name:por_x_preferred":[
        "Palzem"
    ],
    "name:ron_x_preferred":[
        "Palzem"
    ],
    "name:rum_x_preferred":[
        "Palzem"
    ],
    "name:rus_x_preferred":[
        "\u041f\u0430\u043b\u044c\u0446\u0435\u043c"
    ],
    "name:srp_x_preferred":[
        "\u041f\u0430\u043b\u0446\u0435\u043c"
    ],
    "name:ukr_x_preferred":[
        "\u041f\u0430\u043b\u044c\u0446\u0435\u043c"
    ],
    "name:uzb_x_preferred":[
        "Palzem"
    ],
    "name:vie_x_preferred":[
        "Palzem"
    ],
    "name:vol_x_preferred":[
        "Palzem"
    ],
    "name:war_x_preferred":[
        "Palzem"
    ],
    "name:zho_x_preferred":[
        "\u5e15\u5c14\u7b56\u59c6"
    ],
    "qs:a0":"Bundesrepublik Deutschland",
    "qs:a1":"*Rheinland-Pfalz",
    "qs:a1r":"0",
    "qs:a2":"Trier-Saarburg",
    "qs:adm0":"Bundesrepublik Deutschland",
    "qs:la_lc":"*",
    "qs:level":"locality",
    "qs:loc":"Palzem",
    "qs:loc_alt":"Palzem",
    "qs:pop":0,
    "qs:type":"buffered point",
    "wd:wordcount":47,
    "wof:name":"Palzem",
    "wof:placetype":"locality",
    "wof:population":1269
},
  "geometry": {"coordinates":[6.374663,49.57286],"type":"Point"}
}