{
  "type": "Feature",
  "properties": {
    "gn:admin1_code":"6",
    "gn:admin2_code":"0.0",
    "gn:admin3_code":"3459.0",
    "gn:admin4_code":"3459019.0",
    "gn:asciiname":"Holsten",
    "gn:country_code":"DE",
    "gn:dem":154,
    "gn:feature_class":"P",
    "gn:feature_code":"PPLL",
    "gn:name":"Holsten",
    "gn:population":0,
    "gn:timezone":"Europe/Berlin",
    "iso:country":"DE",
    "wof:name":"Holsten",
    "wof:placetype":"neighbourhood"
},
  "geometry": {"coordinates":[8.14052,52.21634],"type":"Point"}
}