{
  "type": "Feature",
  "properties": {
    "gn:admin1_code":"1",
    "gn:admin2_code":"84.0",
    "gn:admin3_code":"8437.0",
    "gn:admin4_code":"8437107.0",
    "gn:asciiname":"Storzingen",
    "gn:country_code":"DE",
    "gn:dem":637,
    "gn:feature_class":"P",
    "gn:feature_code":"PPL",
    "gn:name":"Storzingen",
    "gn:population":0,
    "gn:timezone":"Europe/Berlin",
    "iso:country":"DE",
    "wof:name":"Storzingen",
    "wof:placetype":"neighbourhood"
},
  "geometry": {"coordinates":[9.12174,48.13379000000001],"type":"Point"}
}