{
  "type": "Feature",
  "properties": {
    "gn:admin1_code":"7",
    "gn:admin2_code":"53.0",
    "gn:admin3_code":"5370.0",
    "gn:admin4_code":"5370036.0",
    "gn:asciiname":"Krafeld",
    "gn:country_code":"DE",
    "gn:dem":36,
    "gn:feature_class":"P",
    "gn:feature_code":"PPL",
    "gn:name":"Krafeld",
    "gn:population":0,
    "gn:timezone":"Europe/Berlin",
    "iso:country":"DE",
    "wof:name":"Krafeld",
    "wof:placetype":"neighbourhood"
},
  "geometry": {"coordinates":[6.1271,51.11011],"type":"Point"}
}