{
  "type": "Feature",
  "properties": {
    "gn:admin1_code":"1",
    "gn:admin2_code":"81.0",
    "gn:admin3_code":"8128.0",
    "gn:admin4_code":"8128137.0",
    "gn:asciiname":"Unterwittighausen",
    "gn:country_code":"DE",
    "gn:dem":243,
    "gn:feature_class":"P",
    "gn:feature_code":"PPL",
    "gn:name":"Unterwittighausen",
    "gn:population":0,
    "gn:timezone":"Europe/Berlin",
    "iso:country":"DE",
    "wof:name":"Unterwittighausen",
    "wof:placetype":"neighbourhood"
},
  "geometry": {"coordinates":[9.83889,49.61333],"type":"Point"}
}