{
  "type": "Feature",
  "properties": {
    "gn:admin1_code":"11",
    "gn:admin2_code":"0.0",
    "gn:admin3_code":"12069.0",
    "gn:admin4_code":"12069474.0",
    "gn:asciiname":"Dahnsdorf",
    "gn:country_code":"DE",
    "gn:dem":74,
    "gn:feature_class":"P",
    "gn:feature_code":"PPL",
    "gn:name":"Dahnsdorf",
    "gn:population":0,
    "gn:timezone":"Europe/Berlin",
    "iso:country":"DE",
    "wof:name":"Dahnsdorf",
    "wof:placetype":"neighbourhood"
},
  "geometry": {"coordinates":[12.66921,52.10121],"type":"Point"}
}