{
  "type": "Feature",
  "properties": {
    "gn:admin1_code":"2",
    "gn:admin2_code":"96.0",
    "gn:admin3_code":"9674.0",
    "gn:admin4_code":"9674180.0",
    "gn:asciiname":"Untertheres",
    "gn:country_code":"DE",
    "gn:dem":228,
    "gn:feature_class":"P",
    "gn:feature_code":"PPL",
    "gn:name":"Untertheres",
    "gn:population":0,
    "gn:timezone":"Europe/Berlin",
    "iso:country":"DE",
    "wof:name":"Untertheres",
    "wof:placetype":"neighbourhood"
},
  "geometry": {"coordinates":[10.41687,50.01723],"type":"Point"}
}