{
  "type": "Feature",
  "properties": {
    "iso:country":"DE",
    "name:deu_x_preferred":[
        "Dreim\u00fchlen"
    ],
    "wof:name":"Dremuehlen",
    "wof:placetype":"neighbourhood"
},
  "geometry": {"coordinates":[11.56202924521071,48.12178733555439],"type":"Point"}
}