{
  "type": "Feature",
  "properties": {
    "gn:admin1_code":"5",
    "gn:admin2_code":"66.0",
    "gn:admin3_code":"6632.0",
    "gn:admin4_code":"6632008.0",
    "gn:asciiname":"Neukirchen",
    "gn:country_code":"DE",
    "gn:dem":240,
    "gn:feature_class":"P",
    "gn:feature_code":"PPL",
    "gn:name":"Neukirchen",
    "gn:population":0,
    "gn:timezone":"Europe/Berlin",
    "iso:country":"DE",
    "name:ceb_x_preferred":[
        "Neukirchen"
    ],
    "name:deu_x_preferred":[
        "Neukirchen"
    ],
    "name:epo_x_preferred":[
        "Neukirchen"
    ],
    "name:eus_x_preferred":[
        "Neukirchen"
    ],
    "name:fas_x_preferred":[
        "\u0646\u0648\u06cc\u06a9\u06cc\u0631\u0634\u0646"
    ],
    "name:fra_x_preferred":[
        "Neukirchen"
    ],
    "name:frr_x_preferred":[
        "Neukirchen"
    ],
    "name:hun_x_preferred":[
        "Neukirchen"
    ],
    "name:ita_x_preferred":[
        "Neukirchen"
    ],
    "name:kaz_x_preferred":[
        "\u041d\u043e\u0439\u043a\u0438\u0440\u0445\u0435\u043d"
    ],
    "name:kir_x_preferred":[
        "\u041d\u043e\u0439\u043a\u0438\u0440\u0445\u0435\u043d"
    ],
    "name:lmo_x_preferred":[
        "Neukirchen"
    ],
    "name:mkd_x_preferred":[
        "\u041d\u043e\u0458\u043a\u0438\u0440\u0445\u0435\u043d"
    ],
    "name:nld_x_preferred":[
        "Neukirchen"
    ],
    "name:nor_x_preferred":[
        "Neukirchen"
    ],
    "name:pol_x_preferred":[
        "Neukirchen"
    ],
    "name:rus_x_preferred":[
        "\u041d\u043e\u0439\u043a\u0438\u0440\u0445\u0435\u043d"
    ],
    "name:spa_x_preferred":[
        "Neukirchen"
    ],
    "name:srp_x_preferred":[
        "\u041d\u043e\u0458\u043a\u0438\u0440\u0445\u0435\u043d"
    ],
    "name:swe_x_preferred":[
        "Neukirchen"
    ],
    "name:vol_x_preferred":[
        "Neukirchen"
    ],
    "wof:name":"Neukirchen",
    "wof:placetype":"neighbourhood"
},
  "geometry": {"coordinates":[9.69647,50.76893],"type":"Point"}
}