{
  "type": "Feature",
  "properties": {
    "gn:admin1_code":"2.0",
    "gn:admin2_code":"093",
    "gn:admin3_code":"9373.0",
    "gn:admin4_code":"9373121.0",
    "gn:asciiname":"Wimpasing",
    "gn:country_code":"DE",
    "gn:dem":491,
    "gn:feature_class":"P",
    "gn:feature_code":"PPL",
    "gn:name":"Wimpasing",
    "gn:population":0,
    "gn:timezone":"Europe/Berlin",
    "iso:country":"DE",
    "wof:name":"Wimpasing",
    "wof:placetype":"neighbourhood"
},
  "geometry": {"coordinates":[11.56938,49.08219],"type":"Point"}
}