{
  "type": "Feature",
  "properties": {
    "gn:admin1_code":"2",
    "gn:admin2_code":"91.0",
    "gn:admin3_code":"9183.0",
    "gn:admin4_code":"9183136.0",
    "gn:asciiname":"Liebhartsberg",
    "gn:country_code":"DE",
    "gn:dem":390,
    "gn:feature_class":"P",
    "gn:feature_code":"PPL",
    "gn:name":"Liebhartsberg",
    "gn:population":0,
    "gn:timezone":"Europe/Berlin",
    "iso:country":"DE",
    "wof:name":"Liebhartsberg",
    "wof:placetype":"neighbourhood"
},
  "geometry": {"coordinates":[12.48609,48.23071],"type":"Point"}
}