{
  "type": "Feature",
  "properties": {
    "gn:admin1_code":"7",
    "gn:admin2_code":"55.0",
    "gn:admin3_code":"5570.0",
    "gn:admin4_code":"5570036.0",
    "gn:asciiname":"Rippelbaum",
    "gn:country_code":"DE",
    "gn:dem":70,
    "gn:feature_class":"P",
    "gn:feature_code":"PPLL",
    "gn:name":"Rippelbaum",
    "gn:population":0,
    "gn:timezone":"Europe/Berlin",
    "iso:country":"DE",
    "wof:name":"Rippelbaum",
    "wof:placetype":"neighbourhood"
},
  "geometry": {"coordinates":[8.06772,52.02613],"type":"Point"}
}