{
  "type": "Feature",
  "properties": {
    "gn:admin1_code":"10",
    "gn:admin2_code":"0.0",
    "gn:admin3_code":"1055.0",
    "gn:admin4_code":"1055016.0",
    "gn:asciiname":"Nienhagen",
    "gn:country_code":"DE",
    "gn:dem":29,
    "gn:feature_class":"P",
    "gn:feature_code":"PPL",
    "gn:name":"Nienhagen",
    "gn:population":0,
    "gn:timezone":"Europe/Berlin",
    "iso:country":"DE",
    "name:ceb_x_preferred":[
        "Nienhagen"
    ],
    "name:deu_x_preferred":[
        "Nienhagen"
    ],
    "name:epo_x_preferred":[
        "Nienhagen"
    ],
    "name:est_x_preferred":[
        "Nienhagen"
    ],
    "name:eus_x_preferred":[
        "Nienhagen"
    ],
    "name:fra_x_preferred":[
        "Nienhagen"
    ],
    "name:hun_x_preferred":[
        "Nienhagen"
    ],
    "name:ita_x_preferred":[
        "Nienhagen"
    ],
    "name:mkd_x_preferred":[
        "\u041d\u0438\u043d\u0445\u0430\u0433\u0435\u043d"
    ],
    "name:nds_x_preferred":[
        "Nienhagen"
    ],
    "name:nld_x_preferred":[
        "Nienhagen"
    ],
    "name:pol_x_preferred":[
        "Nienhagen"
    ],
    "name:rus_x_preferred":[
        "\u041d\u0438\u043d\u0445\u0430\u0433\u0435\u043d"
    ],
    "name:srp_x_preferred":[
        "\u041d\u0438\u043d\u0445\u0430\u0433\u0435\u043d"
    ],
    "name:swe_x_preferred":[
        "Nienhagen"
    ],
    "name:vol_x_preferred":[
        "Nienhagen"
    ],
    "wof:name":"Nienhagen",
    "wof:placetype":"neighbourhood"
},
  "geometry": {"coordinates":[10.9373,54.17299000000001],"type":"Point"}
}