{
  "type": "Feature",
  "properties": {
    "gn:admin1_code":"2",
    "gn:admin2_code":"91.0",
    "gn:admin3_code":"9189.0",
    "gn:admin4_code":"9189148.0",
    "gn:asciiname":"Thunstetten",
    "gn:country_code":"DE",
    "gn:dem":650,
    "gn:feature_class":"P",
    "gn:feature_code":"PPL",
    "gn:name":"Thunstetten",
    "gn:population":0,
    "gn:timezone":"Europe/Berlin",
    "iso:country":"DE",
    "name:als_x_preferred":[
        "Thunstetten"
    ],
    "name:ceb_x_preferred":[
        "Thunstetten"
    ],
    "name:chv_x_preferred":[
        "\u0422\u0443\u043d\u0448\u0442\u0435\u0442\u0442\u0435\u043d"
    ],
    "name:deu_x_preferred":[
        "Thunstetten"
    ],
    "name:epo_x_preferred":[
        "Thunstetten"
    ],
    "name:eus_x_preferred":[
        "Thunstetten"
    ],
    "name:fra_x_preferred":[
        "Thunstetten"
    ],
    "name:ita_x_preferred":[
        "Thunstetten"
    ],
    "name:kaz_x_preferred":[
        "\u0422\u0443\u043d\u0448\u0442\u0435\u0442\u0442\u0435\u043d"
    ],
    "name:lmo_x_preferred":[
        "Thunstetten"
    ],
    "name:msa_x_preferred":[
        "Thunstetten"
    ],
    "name:nld_x_preferred":[
        "Thunstetten"
    ],
    "name:nno_x_preferred":[
        "Thunstetten"
    ],
    "name:rus_x_preferred":[
        "\u0422\u0443\u043d\u0448\u0442\u0435\u0442\u0442\u0435\u043d"
    ],
    "name:spa_x_preferred":[
        "Thunstetten"
    ],
    "name:sqi_x_preferred":[
        "Thunstetten"
    ],
    "name:swe_x_preferred":[
        "Thunstetten"
    ],
    "name:vie_x_preferred":[
        "Thunstetten"
    ],
    "name:vol_x_preferred":[
        "Thunstetten"
    ],
    "name:war_x_preferred":[
        "Thunstetten"
    ],
    "name:zho_x_preferred":[
        "\u901a\u65af\u6cf0\u6ed5"
    ],
    "wof:name":"Thunstetten",
    "wof:placetype":"neighbourhood"
},
  "geometry": {"coordinates":[12.68642,47.86856],"type":"Point"}
}