{
  "type": "Feature",
  "properties": {
    "gn:admin1_code":"11",
    "gn:admin2_code":"0.0",
    "gn:admin3_code":"12063.0",
    "gn:admin4_code":"12063357.0",
    "gn:asciiname":"Priort Siedlung",
    "gn:country_code":"DE",
    "gn:dem":35,
    "gn:feature_class":"P",
    "gn:feature_code":"PPL",
    "gn:name":"Priort Siedlung",
    "gn:population":0,
    "gn:timezone":"Europe/Berlin",
    "iso:country":"DE",
    "wof:name":"Priort Siedlung",
    "wof:placetype":"neighbourhood"
},
  "geometry": {"coordinates":[12.98333,52.51667],"type":"Point"}
}