{
  "type": "Feature",
  "properties": {
    "gn:admin1_code":"15.0",
    "gn:admin2_code":"0.0",
    "gn:admin3_code":"16075.0",
    "gn:admin4_code":"16075134.0",
    "gn:asciiname":"Altengesees",
    "gn:country_code":"DE",
    "gn:dem":538,
    "gn:feature_class":"P",
    "gn:feature_code":"PPL",
    "gn:name":"Altengesees",
    "gn:population":0,
    "gn:timezone":"Europe/Berlin",
    "iso:country":"DE",
    "wof:name":"Altengesees",
    "wof:placetype":"neighbourhood"
},
  "geometry": {"coordinates":[11.54025,50.54845],"type":"Point"}
}