{
  "type": "Feature",
  "properties": {
    "gn:admin1_code":"13",
    "gn:admin2_code":"0.0",
    "gn:admin3_code":"14523.0",
    "gn:admin4_code":"14523080.0",
    "gn:asciiname":"Suessebach",
    "gn:country_code":"DE",
    "gn:dem":556,
    "gn:feature_class":"P",
    "gn:feature_code":"PPL",
    "gn:name":"S\u00fc\u00dfebach",
    "gn:population":0,
    "gn:timezone":"Europe/Berlin",
    "iso:country":"DE",
    "name:und_x_variant":[
        "Ebersbach-S\u00fc\u00dfebach",
        "S\u00fc\u00dfebach"
    ],
    "wof:name":"Suessebach",
    "wof:placetype":"neighbourhood"
},
  "geometry": {"coordinates":[12.15636,50.36182],"type":"Point"}
}