{
  "type": "Feature",
  "properties": {
    "gn:admin1_code":"2",
    "gn:admin2_code":"97.0",
    "gn:admin3_code":"9774.0",
    "gn:admin4_code":"9774111.0",
    "gn:asciiname":"Haupeltshofen",
    "gn:country_code":"DE",
    "gn:dem":533,
    "gn:feature_class":"P",
    "gn:feature_code":"PPL",
    "gn:name":"Haupeltshofen",
    "gn:population":0,
    "gn:timezone":"Europe/Berlin",
    "iso:country":"DE",
    "wof:name":"Haupeltshofen",
    "wof:placetype":"neighbourhood"
},
  "geometry": {"coordinates":[10.38385,48.17969],"type":"Point"}
}