{
  "type": "Feature",
  "properties": {
    "gn:gn_country":"DE",
    "gn:gn_fcode":"PPLA4",
    "gn:gn_pop":301,
    "gn:population":301,
    "iso:country":"DE",
    "name:baq_x_preferred":[
        "Kail"
    ],
    "name:dut_x_preferred":[
        "Kail"
    ],
    "name:eng_x_preferred":[
        "Kail"
    ],
    "name:epo_x_preferred":[
        "Kail"
    ],
    "name:fre_x_preferred":[
        "Kail"
    ],
    "name:ger_x_preferred":[
        "Kail"
    ],
    "name:hun_x_preferred":[
        "Kail"
    ],
    "name:ita_x_preferred":[
        "Kail"
    ],
    "name:jpn_x_preferred":[
        "\u30ab\u30a4\u30eb"
    ],
    "name:may_x_preferred":[
        "Kail"
    ],
    "name:pol_x_preferred":[
        "Kail"
    ],
    "name:por_x_preferred":[
        "Kail"
    ],
    "name:rum_x_preferred":[
        "Kail"
    ],
    "name:rus_x_preferred":[
        "\u041a\u0430\u0439\u043b\u044c"
    ],
    "name:srp_x_preferred":[
        "\u041a\u0430\u0458\u043b"
    ],
    "name:ukr_x_preferred":[
        "\u041a\u0430\u0439\u043b\u044c"
    ],
    "name:uzb_x_preferred":[
        "Kail"
    ],
    "name:vie_x_preferred":[
        "Kail"
    ],
    "name:vol_x_preferred":[
        "Kail"
    ],
    "name:war_x_preferred":[
        "Kail"
    ],
    "qs_pg:aaroncc":"DE",
    "qs_pg:gn_country":"DE",
    "qs_pg:gn_fcode":"PPLA4",
    "qs_pg:gn_pop":301,
    "qs_pg:name":"Kail",
    "qs_pg:photos_9r":0,
    "qs_pg:photos_sr":0,
    "qs_pg:pop_sr":2,
    "qs_pg:qs_pg_placetype":"locality",
    "wof:name":"Kail",
    "wof:placetype":"locality",
    "wof:population":301
},
  "geometry": {"coordinates":[7.23333,50.18333],"type":"Point"}
}