{
  "type": "Feature",
  "properties": {
    "gn:admin1_code":"15",
    "gn:admin2_code":"0.0",
    "gn:admin3_code":"16073.0",
    "gn:admin4_code":"16073028.0",
    "gn:asciiname":"Lichtenhain",
    "gn:country_code":"DE",
    "gn:dem":653,
    "gn:feature_class":"P",
    "gn:feature_code":"PPL",
    "gn:name":"Lichtenhain",
    "gn:population":0,
    "gn:timezone":"Europe/Berlin",
    "iso:country":"DE",
    "name:ces_x_preferred":[
        "Lichtenhain"
    ],
    "name:deu_x_preferred":[
        "Lichtenhain"
    ],
    "name:epo_x_preferred":[
        "Lichtenhain"
    ],
    "name:ita_x_preferred":[
        "Lichtenhain"
    ],
    "wof:name":"Lichtenhain",
    "wof:placetype":"neighbourhood"
},
  "geometry": {"coordinates":[11.31204,50.49943],"type":"Point"}
}