{
  "type": "Feature",
  "properties": {
    "gn:admin1_code":"2",
    "gn:admin2_code":"97.0",
    "gn:admin3_code":"9780.0",
    "gn:admin4_code":"9780143.0",
    "gn:asciiname":"Memholz",
    "gn:cc2":"DE",
    "gn:country_code":"DE",
    "gn:dem":719,
    "gn:feature_class":"P",
    "gn:feature_code":"PPL",
    "gn:name":"Memh\u00f6lz",
    "gn:population":0,
    "gn:timezone":"Europe/Berlin",
    "iso:country":"DE",
    "name:und_x_variant":[
        "Kuhnerwald"
    ],
    "wof:name":"Memholz",
    "wof:placetype":"neighbourhood"
},
  "geometry": {"coordinates":[10.27432,47.64773],"type":"Point"}
}