{
  "type": "Feature",
  "properties": {
    "gn:admin1_code":"7",
    "gn:admin2_code":"59.0",
    "gn:admin3_code":"5970.0",
    "gn:admin4_code":"5970024.0",
    "gn:asciiname":"Kredenbach",
    "gn:country_code":"DE",
    "gn:dem":333,
    "gn:feature_class":"P",
    "gn:feature_code":"PPL",
    "gn:name":"Kredenbach",
    "gn:population":0,
    "gn:timezone":"Europe/Berlin",
    "iso:country":"DE",
    "name:deu_x_preferred":[
        "Kredenbach"
    ],
    "name:fas_x_preferred":[
        "\u06a9\u0631\u062f\u0646\u0628\u0627\u062e"
    ],
    "name:fra_x_preferred":[
        "Kredenbach"
    ],
    "wof:name":"Kredenbach",
    "wof:placetype":"neighbourhood"
},
  "geometry": {"coordinates":[8.0441,50.96385],"type":"Point"}
}