{
  "type": "Feature",
  "properties": {
    "gn:admin1_code":"2",
    "gn:admin2_code":"91.0",
    "gn:admin3_code":"9174.0",
    "gn:admin4_code":"9174115.0",
    "gn:asciiname":"Obergrashof",
    "gn:country_code":"DE",
    "gn:dem":478,
    "gn:feature_class":"P",
    "gn:feature_code":"PPL",
    "gn:name":"Obergrashof",
    "gn:population":0,
    "gn:timezone":"Europe/Berlin",
    "iso:country":"DE",
    "name:und_x_variant":[
        "Grashof",
        "Obergrashof"
    ],
    "wof:name":"Obergrashof",
    "wof:placetype":"neighbourhood"
},
  "geometry": {"coordinates":[11.49156,48.25561],"type":"Point"}
}