{
  "type": "Feature",
  "properties": {
    "iso:country":"DE",
    "name:deu_x_preferred":[
        "Vach"
    ],
    "name:eng_x_preferred":[
        "Vach"
    ],
    "name:fra_x_preferred":[
        "Vach"
    ],
    "name:gle_x_preferred":[
        "Vach"
    ],
    "name:nld_x_preferred":[
        "Vach"
    ],
    "qs:gn_fcode":"PPL",
    "qs:gn_local":0,
    "qs:gn_namadm1":"02",
    "qs:gn_name":"Vach",
    "qs:local_max":1488,
    "qs:local_sum":4358,
    "qs:localhoods":13,
    "qs:name":"Vach",
    "qs:name_adm0":"Deutschland",
    "qs:name_adm1":"Bayern",
    "qs:name_adm2":"Stadtkreis F\u00fcrth",
    "qs:name_lau":"Stadtteil F\u00fcrth",
    "qs:name_local":"Stadtteil F\u00fcrth",
    "qs:photo_max":36,
    "qs:photo_sum":54,
    "qs:placetype":"Suburb",
    "qs:quad_count":9,
    "qs:woe_adm0":23424829,
    "qs:woe_adm1":2345482,
    "qs:woe_adm2":20071091,
    "qs:woe_lau":28350201,
    "qs:woe_local":28350201,
    "qs:woe_ver":"7.10.0",
    "wd:wordcount":217,
    "wof:lang":[
        "ger"
    ],
    "wof:name":"Vach",
    "wof:placetype":"neighbourhood"
},
  "geometry": {"coordinates":[10.965652,49.525226],"type":"Point"}
}