{
  "type": "Feature",
  "properties": {
    "gn:admin1_code":"2",
    "gn:admin2_code":"92.0",
    "gn:admin3_code":"9275.0",
    "gn:admin4_code":"9275124.0",
    "gn:asciiname":"Ober-Grun",
    "gn:country_code":"DE",
    "gn:dem":436,
    "gn:feature_class":"P",
    "gn:feature_code":"PPL",
    "gn:name":"Ober-Gr\u00fcn",
    "gn:population":0,
    "gn:timezone":"Europe/Berlin",
    "iso:country":"DE",
    "wof:name":"Ober-Grun",
    "wof:placetype":"neighbourhood"
},
  "geometry": {"coordinates":[13.21667,48.46667],"type":"Point"}
}