{
  "type": "Feature",
  "properties": {
    "gn:admin1_code":"6.0",
    "gn:admin2_code":"0.0",
    "gn:admin3_code":"3453.0",
    "gn:admin4_code":"3453006.0",
    "gn:asciiname":"Ahausen",
    "gn:country_code":"DE",
    "gn:dem":27,
    "gn:feature_class":"P",
    "gn:feature_code":"PPL",
    "gn:name":"Ahausen",
    "gn:population":0,
    "gn:timezone":"Europe/Berlin",
    "iso:country":"DE",
    "name:dan_x_preferred":[
        "Ahausen"
    ],
    "name:deu_x_preferred":[
        "Ahausen"
    ],
    "name:epo_x_preferred":[
        "Ahausen"
    ],
    "name:est_x_preferred":[
        "Ahausen"
    ],
    "name:eus_x_preferred":[
        "Ahausen"
    ],
    "name:fas_x_preferred":[
        "\u0627\u0647\u0627\u0633\u0646"
    ],
    "name:fra_x_preferred":[
        "Ahausen"
    ],
    "name:hun_x_preferred":[
        "Ahausen"
    ],
    "name:ita_x_preferred":[
        "Ahausen"
    ],
    "name:jpn_x_preferred":[
        "\u30a2\u30cf\u30a6\u30bc\u30f3"
    ],
    "name:kaz_x_preferred":[
        "\u0410\u0445\u0430\u0443\u0437\u0435\u043d"
    ],
    "name:kir_x_preferred":[
        "\u0410\u0445\u0430\u0443\u0437\u0435\u043d"
    ],
    "name:msa_x_preferred":[
        "Ahausen"
    ],
    "name:nds_x_preferred":[
        "Ahusen"
    ],
    "name:nld_x_preferred":[
        "Ahausen"
    ],
    "name:pol_x_preferred":[
        "Ahausen"
    ],
    "name:por_x_preferred":[
        "Ahausen"
    ],
    "name:ron_x_preferred":[
        "Ahausen"
    ],
    "name:rus_x_preferred":[
        "\u0410\u0445\u0430\u0443\u0437\u0435\u043d"
    ],
    "name:spa_x_preferred":[
        "Ahausen"
    ],
    "name:srp_x_preferred":[
        "\u0410\u0445\u0430\u0443\u0437\u0435\u043d"
    ],
    "name:ukr_x_preferred":[
        "\u0410\u0433\u0430\u0443\u0437\u0435\u043d"
    ],
    "name:urd_x_preferred":[
        "\u0627\u06c1\u0627\u0633\u0646"
    ],
    "name:uzb_x_preferred":[
        "Ahausen"
    ],
    "name:vie_x_preferred":[
        "Ahausen"
    ],
    "name:vol_x_preferred":[
        "Ahausen"
    ],
    "name:war_x_preferred":[
        "Ahausen"
    ],
    "name:zho_x_preferred":[
        "\u963f\u8c6a\u68ee"
    ],
    "wof:name":"Ahausen",
    "wof:placetype":"neighbourhood"
},
  "geometry": {"coordinates":[7.91477,52.72273000000001],"type":"Point"}
}