{
  "type": "Feature",
  "properties": {
    "gn:admin1_code":"2.0",
    "gn:admin2_code":"95.0",
    "gn:admin3_code":"9572.0",
    "gn:admin4_code":"9572141.0",
    "gn:asciiname":"Adlitz",
    "gn:country_code":"DE",
    "gn:dem":346,
    "gn:feature_class":"P",
    "gn:feature_code":"PPL",
    "gn:name":"Adlitz",
    "gn:population":0,
    "gn:timezone":"Europe/Berlin",
    "iso:country":"DE",
    "wof:name":"Adlitz",
    "wof:placetype":"neighbourhood"
},
  "geometry": {"coordinates":[11.06375,49.62934],"type":"Point"}
}