{
  "type": "Feature",
  "properties": {
    "gn:admin1_code":"1",
    "gn:admin2_code":"81.0",
    "gn:admin3_code":"8117.0",
    "gn:admin4_code":"8117015.0",
    "gn:asciiname":"Unterweckerstell",
    "gn:country_code":"DE",
    "gn:dem":495,
    "gn:feature_class":"P",
    "gn:feature_code":"PPL",
    "gn:name":"Unterweckerstell",
    "gn:population":0,
    "gn:timezone":"Europe/Berlin",
    "iso:country":"DE",
    "wof:name":"Unterweckerstell",
    "wof:placetype":"neighbourhood"
},
  "geometry": {"coordinates":[9.82581,48.67084000000001],"type":"Point"}
}