{
  "type": "Feature",
  "properties": {
    "gn:admin1_code":"13",
    "gn:admin2_code":"0.0",
    "gn:admin3_code":"14628.0",
    "gn:admin4_code":"14628030.0",
    "gn:asciiname":"Prossen",
    "gn:country_code":"DE",
    "gn:dem":147,
    "gn:feature_class":"P",
    "gn:feature_code":"PPL",
    "gn:name":"Prossen",
    "gn:population":0,
    "gn:timezone":"Europe/Berlin",
    "iso:country":"DE",
    "wof:name":"Prossen",
    "wof:placetype":"neighbourhood"
},
  "geometry": {"coordinates":[14.1152,50.93058],"type":"Point"}
}