{
  "type": "Feature",
  "properties": {
    "gn:admin1_code":"13",
    "gn:admin2_code":"0.0",
    "gn:admin3_code":"14626.0",
    "gn:admin4_code":"14626460.0",
    "gn:asciiname":"Neuhammer",
    "gn:country_code":"DE",
    "gn:dem":146,
    "gn:feature_class":"P",
    "gn:feature_code":"PPL",
    "gn:name":"Neuhammer",
    "gn:population":0,
    "gn:timezone":"Europe/Berlin",
    "iso:country":"DE",
    "name:deu_x_preferred":[
        "Neuhammer"
    ],
    "wof:name":"Neuhammer",
    "wof:placetype":"neighbourhood"
},
  "geometry": {"coordinates":[14.80452,51.39672],"type":"Point"}
}