{
  "type": "Feature",
  "properties": {
    "gn:admin1_code":"7",
    "gn:admin2_code":"55.0",
    "gn:admin3_code":"5554.0",
    "gn:admin4_code":"5554028.0",
    "gn:asciiname":"Leblich",
    "gn:country_code":"DE",
    "gn:dem":70,
    "gn:feature_class":"P",
    "gn:feature_code":"PPL",
    "gn:name":"Leblich",
    "gn:population":0,
    "gn:timezone":"Europe/Berlin",
    "iso:country":"DE",
    "wof:name":"Leblich",
    "wof:placetype":"neighbourhood"
},
  "geometry": {"coordinates":[6.94855,51.81265],"type":"Point"}
}