{
  "type": "Feature",
  "properties": {
    "gn:admin1_code":"2.0",
    "gn:admin2_code":"097",
    "gn:admin3_code":"9778.0",
    "gn:admin4_code":"9778130.0",
    "gn:asciiname":"Wesbach",
    "gn:country_code":"DE",
    "gn:dem":584,
    "gn:feature_class":"P",
    "gn:feature_code":"PPL",
    "gn:name":"Wesbach",
    "gn:population":0,
    "gn:timezone":"Europe/Berlin",
    "iso:country":"DE",
    "wof:name":"Wesbach",
    "wof:placetype":"neighbourhood"
},
  "geometry": {"coordinates":[10.26538,48.09206],"type":"Point"}
}