{
  "type": "Feature",
  "properties": {
    "gn:admin1_code":"7",
    "gn:admin2_code":"57.0",
    "gn:admin3_code":"5766.0",
    "gn:admin4_code":"5766028.0",
    "gn:asciiname":"Hagendorf",
    "gn:country_code":"DE",
    "gn:dem":214,
    "gn:feature_class":"P",
    "gn:feature_code":"PPLL",
    "gn:name":"Hagendorf",
    "gn:population":0,
    "gn:timezone":"Europe/Berlin",
    "iso:country":"DE",
    "name:deu_x_preferred":[
        "Hagendorf"
    ],
    "wof:name":"Hagendorf",
    "wof:placetype":"neighbourhood"
},
  "geometry": {"coordinates":[9.13379,52.11376],"type":"Point"}
}