{
  "type": "Feature",
  "properties": {
    "gn:admin1_code":"12.0",
    "gn:admin2_code":"0.0",
    "gn:admin3_code":"13076.0",
    "gn:admin4_code":"13076088.0",
    "gn:asciiname":"Benz",
    "gn:cc2":"DE",
    "gn:country_code":"DE",
    "gn:dem":14,
    "gn:feature_class":"P",
    "gn:feature_code":"PPL",
    "gn:name":"Benz",
    "gn:population":0,
    "gn:timezone":"Europe/Berlin",
    "iso:country":"DE",
    "name:und_x_variant":[
        "Benz-Briest"
    ],
    "wof:name":"Benz",
    "wof:placetype":"locality"
},
  "geometry": {"coordinates":[11.11542,53.24621],"type":"Point"}
}