{
  "type": "Feature",
  "properties": {
    "gn:admin1_code":"1",
    "gn:admin2_code":"81.0",
    "gn:admin3_code":"8136.0",
    "gn:admin4_code":"8136027.0",
    "gn:asciiname":"Hundsberg",
    "gn:country_code":"DE",
    "gn:dem":480,
    "gn:feature_class":"P",
    "gn:feature_code":"PPL",
    "gn:name":"Hundsberg",
    "gn:population":0,
    "gn:timezone":"Europe/Berlin",
    "iso:country":"DE",
    "name:ceb_x_preferred":[
        "Hunds-Berg"
    ],
    "wof:name":"Hundsberg",
    "wof:placetype":"neighbourhood"
},
  "geometry": {"coordinates":[9.70567,48.91484000000001],"type":"Point"}
}