{
  "type": "Feature",
  "properties": {
    "gn:admin1_code":"2",
    "gn:admin2_code":"91.0",
    "gn:admin3_code":"9190.0",
    "gn:admin4_code":"9190154.0",
    "gn:asciiname":"Fronreiten",
    "gn:country_code":"DE",
    "gn:dem":831,
    "gn:feature_class":"P",
    "gn:feature_code":"PPL",
    "gn:name":"Fronreiten",
    "gn:population":0,
    "gn:timezone":"Europe/Berlin",
    "iso:country":"DE",
    "wof:name":"Fronreiten",
    "wof:placetype":"neighbourhood"
},
  "geometry": {"coordinates":[10.862,47.66659],"type":"Point"}
}