{
  "type": "Feature",
  "properties": {
    "gn:admin1_code":"2",
    "gn:admin2_code":"91.0",
    "gn:admin3_code":"9185.0",
    "gn:admin4_code":"9185123.0",
    "gn:asciiname":"Gerstetten",
    "gn:country_code":"DE",
    "gn:dem":397,
    "gn:feature_class":"P",
    "gn:feature_code":"PPL",
    "gn:name":"Gerstetten",
    "gn:population":0,
    "gn:timezone":"Europe/Berlin",
    "iso:country":"DE",
    "name:als_x_preferred":[
        "Gerstetten"
    ],
    "name:ceb_x_preferred":[
        "Gerstetten"
    ],
    "name:dan_x_preferred":[
        "Gerstetten"
    ],
    "name:deu_x_preferred":[
        "Gerstetten"
    ],
    "name:epo_x_preferred":[
        "Gerstetten"
    ],
    "name:eus_x_preferred":[
        "Gerstetten"
    ],
    "name:fas_x_preferred":[
        "\u06af\u0631\u0634\u062a\u062a\u0646"
    ],
    "name:fra_x_preferred":[
        "Gerstetten"
    ],
    "name:hun_x_preferred":[
        "Gerstetten"
    ],
    "name:ita_x_preferred":[
        "Gerstetten"
    ],
    "name:kaz_x_preferred":[
        "\u0413\u0435\u0440\u0448\u0442\u0435\u0442\u0442\u0435\u043d"
    ],
    "name:kir_x_preferred":[
        "\u0413\u0435\u0440\u0448\u0442\u0435\u0442\u0442\u0435\u043d"
    ],
    "name:lat_x_preferred":[
        "Gerstetten"
    ],
    "name:lmo_x_preferred":[
        "Gerstetten"
    ],
    "name:msa_x_preferred":[
        "Gerstetten"
    ],
    "name:nld_x_preferred":[
        "Gerstetten"
    ],
    "name:pol_x_preferred":[
        "Gerstetten"
    ],
    "name:por_x_preferred":[
        "Gerstetten"
    ],
    "name:ron_x_preferred":[
        "Gerstetten"
    ],
    "name:rus_x_preferred":[
        "\u0413\u0435\u0440\u0448\u0442\u0435\u0442\u0442\u0435\u043d"
    ],
    "name:srp_x_preferred":[
        "\u0413\u0435\u0440\u0448\u0442\u0435\u0442\u0435\u043d"
    ],
    "name:swe_x_preferred":[
        "Gerstetten"
    ],
    "name:ukr_x_preferred":[
        "\u0413\u0435\u0440\u0448\u0442\u0435\u0442\u0442\u0435\u043d"
    ],
    "name:uzb_x_preferred":[
        "Gerstetten"
    ],
    "name:vol_x_preferred":[
        "Gerstetten"
    ],
    "name:war_x_preferred":[
        "Gerstetten"
    ],
    "name:zho_x_preferred":[
        "\u76d6\u65bd\u6cf0\u6ed5"
    ],
    "wof:name":"Gerstetten",
    "wof:placetype":"neighbourhood"
},
  "geometry": {"coordinates":[11.2905,48.62259],"type":"Point"}
}