{
  "type": "Feature",
  "properties": {
    "gn:admin1_code":"2",
    "gn:admin2_code":"94.0",
    "gn:admin3_code":"9472.0",
    "gn:admin4_code":"9472139.0",
    "gn:asciiname":"Hermersreuth",
    "gn:country_code":"DE",
    "gn:dem":536,
    "gn:feature_class":"P",
    "gn:feature_code":"PPL",
    "gn:name":"Hermersreuth",
    "gn:population":0,
    "gn:timezone":"Europe/Berlin",
    "iso:country":"DE",
    "wof:name":"Hermersreuth",
    "wof:placetype":"neighbourhood"
},
  "geometry": {"coordinates":[11.72057,50.06276],"type":"Point"}
}