{
  "type": "Feature",
  "properties": {
    "gn:admin1_code":"1",
    "gn:admin2_code":"81.0",
    "gn:admin3_code":"8127.0",
    "gn:admin4_code":"8127009.0",
    "gn:asciiname":"Geislingen am Kocher",
    "gn:cc2":"DE",
    "gn:country_code":"DE",
    "gn:dem":255,
    "gn:feature_class":"P",
    "gn:feature_code":"PPL",
    "gn:name":"Geislingen am Kocher",
    "gn:population":0,
    "gn:timezone":"Europe/Berlin",
    "iso:country":"DE",
    "name:und_x_variant":[
        "Geislingen",
        "Geislingen am Kocher"
    ],
    "wof:name":"Geislingen am Kocher",
    "wof:placetype":"neighbourhood"
},
  "geometry": {"coordinates":[9.78778,49.16889000000001],"type":"Point"}
}