{
  "type": "Feature",
  "properties": {
    "gn:admin1_code":"6",
    "gn:admin2_code":"0.0",
    "gn:admin3_code":"3361.0",
    "gn:admin4_code":"3361012.0",
    "gn:asciiname":"Hoenisch",
    "gn:country_code":"DE",
    "gn:dem":14,
    "gn:feature_class":"P",
    "gn:feature_code":"PPL",
    "gn:name":"H\u00f6nisch",
    "gn:population":0,
    "gn:timezone":"Europe/Berlin",
    "iso:country":"DE",
    "wof:name":"Hoenisch",
    "wof:placetype":"neighbourhood"
},
  "geometry": {"coordinates":[9.21558,52.91704],"type":"Point"}
}