{
  "type": "Feature",
  "properties": {
    "gn:admin1_code":"2",
    "gn:admin2_code":"93.0",
    "gn:admin3_code":"9375.0",
    "gn:admin4_code":"9375190.0",
    "gn:asciiname":"Stadel",
    "gn:country_code":"DE",
    "gn:dem":350,
    "gn:feature_class":"P",
    "gn:feature_code":"PPL",
    "gn:name":"Stadel",
    "gn:population":0,
    "gn:timezone":"Europe/Berlin",
    "iso:country":"DE",
    "name:ceb_x_preferred":[
        "Stadel"
    ],
    "name:deu_x_preferred":[
        "Stadel"
    ],
    "name:fra_x_preferred":[
        "Stadel"
    ],
    "name:ita_x_preferred":[
        "Stadel"
    ],
    "name:swe_x_preferred":[
        "Stadel"
    ],
    "wof:name":"Stadel",
    "wof:placetype":"neighbourhood"
},
  "geometry": {"coordinates":[12.1569,49.14718],"type":"Point"}
}