{
  "type": "Feature",
  "properties": {
    "gn:admin1_code":"2",
    "gn:admin2_code":"95.0",
    "gn:admin3_code":"9571.0",
    "gn:admin4_code":"9571193.0",
    "gn:asciiname":"Brunzendorf",
    "gn:country_code":"DE",
    "gn:dem":455,
    "gn:feature_class":"P",
    "gn:feature_code":"PPL",
    "gn:name":"Brunzendorf",
    "gn:population":0,
    "gn:timezone":"Europe/Berlin",
    "iso:country":"DE",
    "wof:name":"Brunzendorf",
    "wof:placetype":"neighbourhood"
},
  "geometry": {"coordinates":[10.1395,49.3682],"type":"Point"}
}