{
  "type": "Feature",
  "properties": {
    "gn:admin1_code":"8.0",
    "gn:admin2_code":"00",
    "gn:admin3_code":"7140.0",
    "gn:admin4_code":"7140501.0",
    "gn:asciiname":"Windhausen",
    "gn:country_code":"DE",
    "gn:dem":345,
    "gn:feature_class":"P",
    "gn:feature_code":"PPL",
    "gn:name":"Windhausen",
    "gn:population":0,
    "gn:timezone":"Europe/Berlin",
    "iso:country":"DE",
    "wof:name":"Windhausen",
    "wof:placetype":"neighbourhood"
},
  "geometry": {"coordinates":[7.50287,50.20024],"type":"Point"}
}