{
  "type": "Feature",
  "properties": {
    "gn:admin1_code":"8.0",
    "gn:admin2_code":"00",
    "gn:admin3_code":"7140.0",
    "gn:admin4_code":"7140501.0",
    "gn:asciiname":"Windhausen",
    "gn:country_code":"DE",
    "gn:dem":345,
    "gn:feature_class":"P",
    "gn:feature_code":"PPL",
    "gn:name":"Windhausen",
    "gn:population":0,
    "gn:timezone":"Europe/Berlin",
    "iso:country":"DE",
    "name:ceb_x_preferred":[
        "Windhausen"
    ],
    "name:deu_x_preferred":[
        "Windhausen"
    ],
    "name:epo_x_preferred":[
        "Windhausen"
    ],
    "name:fas_x_preferred":[
        "\u0648\u06cc\u0646\u062f\u0647\u0627\u0648\u0632\u0646"
    ],
    "name:ita_x_preferred":[
        "Windhausen"
    ],
    "name:lat_x_preferred":[
        "Windhausen"
    ],
    "name:mkd_x_preferred":[
        "\u0412\u0438\u043d\u0434\u0445\u0430\u0443\u0437\u0435\u043d"
    ],
    "name:msa_x_preferred":[
        "Windhausen"
    ],
    "name:nld_x_preferred":[
        "Windhausen"
    ],
    "name:pol_x_preferred":[
        "Windhausen"
    ],
    "name:por_x_preferred":[
        "Windhausen"
    ],
    "name:ron_x_preferred":[
        "Windhausen"
    ],
    "name:rus_x_preferred":[
        "\u0412\u0438\u043d\u0434\u0445\u0430\u0443\u0437\u0435\u043d"
    ],
    "name:srp_x_preferred":[
        "\u0412\u0438\u043d\u0434\u0445\u0430\u0443\u0437\u0435\u043d"
    ],
    "name:uzb_x_preferred":[
        "Windhausen"
    ],
    "name:vie_x_preferred":[
        "Windhausen"
    ],
    "name:vol_x_preferred":[
        "Windhausen"
    ],
    "name:war_x_preferred":[
        "Windhausen"
    ],
    "name:zho_x_preferred":[
        "\u6e29\u5fb7\u8c6a\u68ee"
    ],
    "wof:name":"Windhausen",
    "wof:placetype":"neighbourhood"
},
  "geometry": {"coordinates":[7.50287,50.20024],"type":"Point"}
}