{
  "type": "Feature",
  "properties": {
    "gn:admin1_code":"2",
    "gn:admin2_code":"96.0",
    "gn:admin3_code":"9678.0",
    "gn:admin4_code":"9678128.0",
    "gn:asciiname":"Sommersdorf",
    "gn:country_code":"DE",
    "gn:dem":278,
    "gn:feature_class":"P",
    "gn:feature_code":"PPL",
    "gn:name":"S\u00f6mmersdorf",
    "gn:population":0,
    "gn:timezone":"Europe/Berlin",
    "iso:country":"DE",
    "wof:name":"Sommersdorf",
    "wof:placetype":"neighbourhood"
},
  "geometry": {"coordinates":[10.09403,50.06011],"type":"Point"}
}