{
  "type": "Feature",
  "properties": {
    "gn:admin1_code":"7.0",
    "gn:admin2_code":"59.0",
    "gn:admin3_code":"5970.0",
    "gn:admin4_code":"5970028.0",
    "gn:asciiname":"Banfe",
    "gn:country_code":"DE",
    "gn:dem":375,
    "gn:feature_class":"P",
    "gn:feature_code":"PPL",
    "gn:name":"Banfe",
    "gn:population":0,
    "gn:timezone":"Europe/Berlin",
    "iso:country":"DE",
    "name:deu_x_preferred":[
        "Banfe"
    ],
    "name:fas_x_preferred":[
        "\u0628\u0627\u0646\u0641\u0647"
    ],
    "name:nld_x_preferred":[
        "Banfe"
    ],
    "wof:name":"Banfe",
    "wof:placetype":"neighbourhood"
},
  "geometry": {"coordinates":[8.35107,50.91237],"type":"Point"}
}