{
  "type": "Feature",
  "properties": {
    "gn:admin1_code":"10.0",
    "gn:admin2_code":"0.0",
    "gn:admin3_code":"1055.0",
    "gn:admin4_code":"1055035.0",
    "gn:asciiname":"Techau",
    "gn:country_code":"DE",
    "gn:dem":21,
    "gn:feature_class":"P",
    "gn:feature_code":"PPL",
    "gn:name":"Techau",
    "gn:population":0,
    "gn:timezone":"Europe/Berlin",
    "iso:country":"DE",
    "wof:name":"Techau",
    "wof:placetype":"neighbourhood"
},
  "geometry": {"coordinates":[10.7163,53.96422],"type":"Point"}
}