{
  "type": "Feature",
  "properties": {
    "gn:admin1_code":"13",
    "gn:admin2_code":"0.0",
    "gn:admin3_code":"14627.0",
    "gn:admin4_code":"14627110.0",
    "gn:asciiname":"Dorf der Jugend",
    "gn:country_code":"DE",
    "gn:dem":126,
    "gn:feature_class":"P",
    "gn:feature_code":"PPL",
    "gn:name":"Dorf der Jugend",
    "gn:population":0,
    "gn:timezone":"Europe/Berlin",
    "iso:country":"DE",
    "name:und_x_variant":[
        "Adelsdorf",
        "Dorf der Jugend"
    ],
    "wof:name":"Dorf der Jugend",
    "wof:placetype":"neighbourhood"
},
  "geometry": {"coordinates":[13.58344,51.3191],"type":"Point"}
}