{
  "type": "Feature",
  "properties": {
    "gn:country":"DE",
    "gn:fcode":"PPL",
    "gn:population":0,
    "iso:country":"DE",
    "name:als_x_preferred":[
        "Kappel"
    ],
    "name:ceb_x_preferred":[
        "Kappel"
    ],
    "name:deu_x_preferred":[
        "Kappel"
    ],
    "name:epo_x_preferred":[
        "Kappel"
    ],
    "name:fra_x_preferred":[
        "Kappel"
    ],
    "name:ita_x_preferred":[
        "Kappel"
    ],
    "name:nld_x_preferred":[
        "Kappel"
    ],
    "name:pol_x_preferred":[
        "Kappel"
    ],
    "name:spa_x_preferred":[
        "Kappel"
    ],
    "name:swe_x_preferred":[
        "Kappel"
    ],
    "name:vol_x_preferred":[
        "Kappel"
    ],
    "qs_pg:aaroncc":"DE",
    "qs_pg:gn_country":"DE",
    "qs_pg:gn_fcode":"PPL",
    "qs_pg:gn_pop":0,
    "qs_pg:name":"Kappel",
    "qs_pg:name_adm0":"Deutschland",
    "qs_pg:name_adm1":"Baden-W\u00fcrttemberg",
    "qs_pg:photos":11,
    "qs_pg:photos_1k":2,
    "qs_pg:photos_9k":1,
    "qs_pg:photos_9r":1,
    "qs_pg:photos_all":11,
    "qs_pg:photos_sr":1,
    "qs_pg:pop_sr":0,
    "qs_pg:qs_pg_placetype":"locality",
    "qs_pg:qs_pg_placetype_gp":"Town",
    "qs_pg:woe_adm0":23424829,
    "woe:adm0_id":23424829,
    "woe:name_adm0":"Deutschland",
    "woe:name_adm1":"Baden-W\u00fcrttemberg",
    "woe:placetype":"Town",
    "wof:name":"Kappel",
    "wof:placetype":"neighbourhood"
},
  "geometry": {"coordinates":[8.2352,47.87255],"type":"Point"}
}