{
  "type": "Feature",
  "properties": {
    "gn:admin1_code":"7.0",
    "gn:admin2_code":"59.0",
    "gn:admin3_code":"5978.0",
    "gn:admin4_code":"5978032.0",
    "gn:asciiname":"Bork",
    "gn:country_code":"DE",
    "gn:dem":67,
    "gn:feature_class":"P",
    "gn:feature_code":"PPL",
    "gn:name":"Bork",
    "gn:population":0,
    "gn:timezone":"Europe/Berlin",
    "iso:country":"DE",
    "name:ceb_x_preferred":[
        "Bork"
    ],
    "name:deu_x_preferred":[
        "Bork"
    ],
    "name:fra_x_preferred":[
        "Bork"
    ],
    "name:ita_x_preferred":[
        "Bork"
    ],
    "wof:name":"Bork",
    "wof:placetype":"neighbourhood"
},
  "geometry": {"coordinates":[7.46665,51.66216],"type":"Point"}
}