{
  "type": "Feature",
  "properties": {
    "gn:admin1_code":"14",
    "gn:asciiname":"Forsterhof",
    "gn:cc2":"DE",
    "gn:country_code":"DE",
    "gn:dem":57,
    "gn:feature_class":"P",
    "gn:feature_code":"PPL",
    "gn:name":"F\u00f6rsterhof",
    "gn:population":0,
    "gn:timezone":"Europe/Berlin",
    "iso:country":"DE",
    "name:und_x_variant":[
        "F\u00f6rstershof",
        "F\u00f6rsterhof"
    ],
    "wof:name":"Forsterhof",
    "wof:placetype":"neighbourhood"
},
  "geometry": {"coordinates":[12.21667,52.96666999999999],"type":"Point"}
}