{
  "type": "Feature",
  "properties": {
    "gn:admin1_code":"12.0",
    "gn:admin2_code":"00",
    "gn:admin3_code":"13072.0",
    "gn:admin4_code":"13072050.0",
    "gn:asciiname":"Wokrent",
    "gn:country_code":"DE",
    "gn:dem":14,
    "gn:feature_class":"P",
    "gn:feature_code":"PPL",
    "gn:name":"Wokrent",
    "gn:population":0,
    "gn:timezone":"Europe/Berlin",
    "iso:country":"DE",
    "wof:name":"Wokrent",
    "wof:placetype":"neighbourhood"
},
  "geometry": {"coordinates":[11.91789,53.9658],"type":"Point"}
}