{
  "type": "Feature",
  "properties": {
    "gn:admin1_code":"5.0",
    "gn:admin2_code":"064",
    "gn:admin3_code":"6434.0",
    "gn:admin4_code":"6434007.0",
    "gn:asciiname":"Westerfeld",
    "gn:country_code":"DE",
    "gn:dem":287,
    "gn:feature_class":"P",
    "gn:feature_code":"PPL",
    "gn:name":"Westerfeld",
    "gn:population":0,
    "gn:timezone":"Europe/Berlin",
    "iso:country":"DE",
    "wof:name":"Westerfeld",
    "wof:placetype":"neighbourhood"
},
  "geometry": {"coordinates":[8.52436,50.31379],"type":"Point"}
}