{
  "type": "Feature",
  "properties": {
    "gn:admin1_code":"5",
    "gn:admin2_code":"66.0",
    "gn:admin3_code":"6635.0",
    "gn:admin4_code":"6635013.0",
    "gn:asciiname":"Oberholzhausen",
    "gn:country_code":"DE",
    "gn:dem":359,
    "gn:feature_class":"P",
    "gn:feature_code":"PPL",
    "gn:name":"Oberholzhausen",
    "gn:population":0,
    "gn:timezone":"Europe/Berlin",
    "iso:country":"DE",
    "wof:name":"Oberholzhausen",
    "wof:placetype":"neighbourhood"
},
  "geometry": {"coordinates":[8.88978,51.01511],"type":"Point"}
}