{
  "type": "Feature",
  "properties": {
    "gn:admin1_code":"7",
    "gn:admin2_code":"57.0",
    "gn:admin3_code":"5766.0",
    "gn:admin4_code":"5766008.0",
    "gn:asciiname":"Juechen",
    "gn:country_code":"DE",
    "gn:dem":88,
    "gn:feature_class":"P",
    "gn:feature_code":"PPL",
    "gn:name":"J\u00fcchen",
    "gn:population":0,
    "gn:timezone":"Europe/Berlin",
    "iso:country":"DE",
    "wof:name":"Juechen",
    "wof:placetype":"neighbourhood"
},
  "geometry": {"coordinates":[8.75529,52.03268],"type":"Point"}
}