{
  "type": "Feature",
  "properties": {
    "gn:admin1_code":"1",
    "gn:admin2_code":"84.0",
    "gn:admin3_code":"8435.0",
    "gn:admin4_code":"8435042.0",
    "gn:asciiname":"Lustensbach",
    "gn:country_code":"DE",
    "gn:dem":579,
    "gn:feature_class":"P",
    "gn:feature_code":"PPL",
    "gn:name":"Lustensbach",
    "gn:population":0,
    "gn:timezone":"Europe/Berlin",
    "iso:country":"DE",
    "wof:name":"Lustensbach",
    "wof:placetype":"neighbourhood"
},
  "geometry": {"coordinates":[9.71667,47.65],"type":"Point"}
}