{
  "type": "Feature",
  "properties": {
    "gn:admin1_code":"7.0",
    "gn:admin2_code":"53.0",
    "gn:admin3_code":"5334.0",
    "gn:admin4_code":"5334028.0",
    "gn:asciiname":"Rauchenauel",
    "gn:country_code":"DE",
    "gn:dem":301,
    "gn:feature_class":"P",
    "gn:feature_code":"PPL",
    "gn:name":"Rauchenauel",
    "gn:population":0,
    "gn:timezone":"Europe/Berlin",
    "iso:country":"DE",
    "wof:name":"Rauchenauel",
    "wof:placetype":"neighbourhood"
},
  "geometry": {"coordinates":[6.36044,50.5871],"type":"Point"}
}