{
  "type": "Feature",
  "properties": {
    "gn:admin1_code":"2",
    "gn:admin2_code":"93.0",
    "gn:admin3_code":"9377.0",
    "gn:admin4_code":"9377146.0",
    "gn:asciiname":"Krahenhaus",
    "gn:country_code":"DE",
    "gn:dem":552,
    "gn:feature_class":"P",
    "gn:feature_code":"PPL",
    "gn:name":"Kr\u00e4henhaus",
    "gn:population":0,
    "gn:timezone":"Europe/Berlin",
    "iso:country":"DE",
    "wof:name":"Krahenhaus",
    "wof:placetype":"neighbourhood"
},
  "geometry": {"coordinates":[12.31498,49.80084],"type":"Point"}
}