{
  "type": "Feature",
  "properties": {
    "gn:admin1_code":"7",
    "gn:admin2_code":"59.0",
    "gn:admin3_code":"5915.0",
    "gn:admin4_code":"5915000.0",
    "gn:asciiname":"Radbod",
    "gn:cc2":"DE",
    "gn:country_code":"DE",
    "gn:dem":59,
    "gn:feature_class":"P",
    "gn:feature_code":"PPL",
    "gn:name":"Radbod",
    "gn:population":0,
    "gn:timezone":"Europe/Berlin",
    "iso:country":"DE",
    "name:deu_x_preferred":[
        "Radboud"
    ],
    "name:fra_x_preferred":[
        "Radbod"
    ],
    "name:nld_x_preferred":[
        "Radboud"
    ],
    "name:rus_x_preferred":[
        "\u0420\u0430\u0434\u0431\u043e\u0434"
    ],
    "name:und_x_variant":[
        "Kolonie Radbod"
    ],
    "wof:name":"Radbod",
    "wof:placetype":"neighbourhood"
},
  "geometry": {"coordinates":[7.7724,51.69182],"type":"Point"}
}