{
  "type": "Feature",
  "properties": {
    "gn:admin1_code":"2",
    "gn:admin2_code":"92.0",
    "gn:admin3_code":"9274.0",
    "gn:admin4_code":"9274182.0",
    "gn:asciiname":"Gutersdorf",
    "gn:country_code":"DE",
    "gn:dem":502,
    "gn:feature_class":"P",
    "gn:feature_code":"PPL",
    "gn:name":"G\u00fctersdorf",
    "gn:population":0,
    "gn:timezone":"Europe/Berlin",
    "iso:country":"DE",
    "wof:name":"Gutersdorf",
    "wof:placetype":"neighbourhood"
},
  "geometry": {"coordinates":[12.10595,48.47348],"type":"Point"}
}