{
  "type": "Feature",
  "properties": {
    "gn:admin1_code":"6",
    "gn:admin2_code":"0.0",
    "gn:admin3_code":"3257.0",
    "gn:admin4_code":"3257001.0",
    "gn:asciiname":"Neumuehlen",
    "gn:country_code":"DE",
    "gn:dem":81,
    "gn:feature_class":"P",
    "gn:feature_code":"PPL",
    "gn:name":"Neum\u00fchlen",
    "gn:population":0,
    "gn:timezone":"Europe/Berlin",
    "iso:country":"DE",
    "wof:name":"Neumuehlen",
    "wof:placetype":"neighbourhood"
},
  "geometry": {"coordinates":[9.10183,52.25153],"type":"Point"}
}