{
  "type": "Feature",
  "properties": {
    "gn:admin1_code":"6",
    "gn:admin2_code":"0.0",
    "gn:admin3_code":"3359.0",
    "gn:admin4_code":"3359025.0",
    "gn:asciiname":"Loehe",
    "gn:country_code":"DE",
    "gn:dem":-3,
    "gn:feature_class":"P",
    "gn:feature_code":"PPL",
    "gn:name":"L\u00f6he",
    "gn:population":0,
    "gn:timezone":"Europe/Berlin",
    "iso:country":"DE",
    "wof:name":"Loehe",
    "wof:placetype":"neighbourhood"
},
  "geometry": {"coordinates":[9.31667,53.63333000000001],"type":"Point"}
}