{
  "type": "Feature",
  "properties": {
    "iso:country":"DE",
    "name:deu_x_preferred":[
        "Hasenhecke"
    ],
    "name:unk_x_variant":[
        "Hasenhecke"
    ],
    "qs:gn_adm0_cc":"DE",
    "qs:gn_local":2892518,
    "qs:local_max":6102,
    "qs:local_sum":10350,
    "qs:localhoods":8,
    "qs:name":"Hasenhecke",
    "qs:name_adm0":"Deutschland",
    "qs:name_adm1":"Hessen",
    "qs:name_adm2":"Stadtkreis Kassel",
    "qs:name_lau":"Stadtteil Wolfsanger",
    "qs:name_local":"Kassel",
    "qs:photo_max":7,
    "qs:photo_sum":29,
    "qs:placetype":"Suburb",
    "qs:quad_count":11,
    "qs:woe_adm0":23424829,
    "qs:woe_adm1":2345485,
    "qs:woe_adm2":20071100,
    "qs:woe_lau":26822724,
    "qs:woe_local":665077,
    "qs:woe_ver":"7.10.0",
    "wof:lang":[
        "ger"
    ],
    "wof:name":"Hasenhecke",
    "wof:placetype":"neighbourhood"
},
  "geometry": {"coordinates":[9.56161,51.365333],"type":"Point"}
}