{
  "type": "Feature",
  "properties": {
    "gn:admin1_code":"12",
    "gn:admin2_code":"0.0",
    "gn:admin3_code":"13072.0",
    "gn:admin4_code":"13072088.0",
    "gn:asciiname":"Purkshof",
    "gn:country_code":"DE",
    "gn:dem":16,
    "gn:feature_class":"P",
    "gn:feature_code":"PPL",
    "gn:name":"Purkshof",
    "gn:population":0,
    "gn:timezone":"Europe/Berlin",
    "iso:country":"DE",
    "wof:name":"Purkshof",
    "wof:placetype":"neighbourhood"
},
  "geometry": {"coordinates":[12.22906,54.15964],"type":"Point"}
}