{
  "type": "Feature",
  "properties": {
    "gn:admin1_code":"13",
    "gn:admin2_code":"0.0",
    "gn:admin3_code":"14523.0",
    "gn:admin4_code":"14523450.0",
    "gn:asciiname":"Schwand",
    "gn:country_code":"DE",
    "gn:dem":519,
    "gn:feature_class":"P",
    "gn:feature_code":"PPL",
    "gn:name":"Schwand",
    "gn:population":0,
    "gn:timezone":"Europe/Berlin",
    "iso:country":"DE",
    "name:ces_x_preferred":[
        "Schwand"
    ],
    "name:deu_x_preferred":[
        "Schwand"
    ],
    "name:epo_x_preferred":[
        "Schwand"
    ],
    "name:ita_x_preferred":[
        "Schwand"
    ],
    "name:pol_x_preferred":[
        "Schwand"
    ],
    "wof:name":"Schwand",
    "wof:placetype":"neighbourhood"
},
  "geometry": {"coordinates":[12.0083,50.43428],"type":"Point"}
}