{
  "type": "Feature",
  "properties": {
    "gn:admin1_code":"11",
    "gn:admin2_code":"0.0",
    "gn:admin3_code":"12070.0",
    "gn:admin4_code":"12070325.0",
    "gn:asciiname":"Jakobsdorf",
    "gn:country_code":"DE",
    "gn:dem":51,
    "gn:feature_class":"P",
    "gn:feature_code":"PPL",
    "gn:name":"Jakobsdorf",
    "gn:population":0,
    "gn:timezone":"Europe/Berlin",
    "iso:country":"DE",
    "name:ceb_x_preferred":[
        "Jakobsdorf"
    ],
    "name:deu_x_preferred":[
        "Jakobsdorf"
    ],
    "name:epo_x_preferred":[
        "Jakobsdorf"
    ],
    "name:fra_x_preferred":[
        "Jakobsdorf"
    ],
    "name:hun_x_preferred":[
        "Jakobsdorf"
    ],
    "name:ita_x_preferred":[
        "Jakobsdorf"
    ],
    "name:kaz_x_preferred":[
        "\u042f\u043a\u043e\u0431\u0441\u0434\u043e\u0440\u0444"
    ],
    "name:kir_x_preferred":[
        "\u042f\u043a\u043e\u0431\u0441\u0434\u043e\u0440\u0444"
    ],
    "name:mkd_x_preferred":[
        "\u0408\u0430\u043a\u043e\u0431\u0441\u0434\u043e\u0440\u0444"
    ],
    "name:msa_x_preferred":[
        "Jakobsdorf"
    ],
    "name:nld_x_preferred":[
        "Jakobsdorf"
    ],
    "name:pol_x_preferred":[
        "Jakobsdorf"
    ],
    "name:por_x_preferred":[
        "Jakobsdorf"
    ],
    "name:ron_x_preferred":[
        "Jakobsdorf"
    ],
    "name:rus_x_preferred":[
        "\u042f\u043a\u043e\u0431\u0441\u0434\u043e\u0440\u0444"
    ],
    "name:spa_x_preferred":[
        "Jakobsdorf"
    ],
    "name:srp_x_preferred":[
        "\u0408\u0430\u043a\u043e\u0431\u0441\u0434\u043e\u0440\u0444"
    ],
    "name:ukr_x_preferred":[
        "\u042f\u043a\u043e\u0431\u0441\u0434\u043e\u0440\u0444"
    ],
    "name:vie_x_preferred":[
        "Jakobsdorf"
    ],
    "name:vol_x_preferred":[
        "Jakobsdorf"
    ],
    "name:war_x_preferred":[
        "Jakobsdorf"
    ],
    "name:zho_x_preferred":[
        "\u96c5\u5404\u5e03\u65af\u591a\u592b"
    ],
    "wof:name":"Jakobsdorf",
    "wof:placetype":"neighbourhood"
},
  "geometry": {"coordinates":[12.07566,53.18858],"type":"Point"}
}