{
  "type": "Feature",
  "properties": {
    "gn:admin1_code":"6",
    "gn:admin2_code":"0.0",
    "gn:admin3_code":"3451.0",
    "gn:admin4_code":"3451007.0",
    "gn:asciiname":"Halsbek",
    "gn:country_code":"DE",
    "gn:dem":10,
    "gn:feature_class":"P",
    "gn:feature_code":"PPL",
    "gn:name":"Halsbek",
    "gn:population":0,
    "gn:timezone":"Europe/Berlin",
    "iso:country":"DE",
    "wof:name":"Halsbek",
    "wof:placetype":"neighbourhood"
},
  "geometry": {"coordinates":[7.92034,53.31499],"type":"Point"}
}