{
  "type": "Feature",
  "properties": {
    "gn:admin1_code":"7",
    "gn:admin2_code":"51.0",
    "gn:admin3_code":"5166.0",
    "gn:admin4_code":"5166036.0",
    "gn:asciiname":"Eschert",
    "gn:country_code":"DE",
    "gn:dem":39,
    "gn:feature_class":"P",
    "gn:feature_code":"PPL",
    "gn:name":"Eschert",
    "gn:population":0,
    "gn:timezone":"Europe/Berlin",
    "iso:country":"DE",
    "wof:name":"Eschert",
    "wof:placetype":"neighbourhood"
},
  "geometry": {"coordinates":[6.46004,51.27413],"type":"Point"}
}