{
  "type": "Feature",
  "properties": {
    "gn:admin1_code":"7",
    "gn:admin2_code":"51.0",
    "gn:admin3_code":"5166.0",
    "gn:admin4_code":"5166036.0",
    "gn:asciiname":"Eschert",
    "gn:country_code":"DE",
    "gn:dem":39,
    "gn:feature_class":"P",
    "gn:feature_code":"PPL",
    "gn:name":"Eschert",
    "gn:population":0,
    "gn:timezone":"Europe/Berlin",
    "iso:country":"DE",
    "name:als_x_preferred":[
        "Eschert"
    ],
    "name:ceb_x_preferred":[
        "Eschert"
    ],
    "name:chv_x_preferred":[
        "\u042d\u0448\u0435\u0440\u0442"
    ],
    "name:deu_x_preferred":[
        "Eschert"
    ],
    "name:epo_x_preferred":[
        "Eschert"
    ],
    "name:eus_x_preferred":[
        "Eschert"
    ],
    "name:fra_x_preferred":[
        "Eschert"
    ],
    "name:ita_x_preferred":[
        "Eschert"
    ],
    "name:kaz_x_preferred":[
        "\u042d\u0448\u0435\u0440\u0442"
    ],
    "name:lmo_x_preferred":[
        "Eschert"
    ],
    "name:msa_x_preferred":[
        "Eschert"
    ],
    "name:nld_x_preferred":[
        "Eschert"
    ],
    "name:nno_x_preferred":[
        "Eschert"
    ],
    "name:rus_x_preferred":[
        "\u042d\u0448\u0435\u0440\u0442"
    ],
    "name:spa_x_preferred":[
        "Eschert"
    ],
    "name:sqi_x_preferred":[
        "Eschert"
    ],
    "name:swe_x_preferred":[
        "Eschert"
    ],
    "name:vie_x_preferred":[
        "Eschert"
    ],
    "name:vol_x_preferred":[
        "Eschert"
    ],
    "name:war_x_preferred":[
        "Eschert"
    ],
    "name:zho_x_preferred":[
        "\u57c3\u65af\u6b47\u7279"
    ],
    "wof:name":"Eschert",
    "wof:placetype":"neighbourhood"
},
  "geometry": {"coordinates":[6.46004,51.27413],"type":"Point"}
}