{
  "type": "Feature",
  "properties": {
    "gn:admin1_code":"5",
    "gn:admin2_code":"64.0",
    "gn:admin3_code":"6435.0",
    "gn:admin4_code":"6435005.0",
    "gn:asciiname":"Spielberg",
    "gn:country_code":"DE",
    "gn:dem":358,
    "gn:feature_class":"P",
    "gn:feature_code":"PPL",
    "gn:name":"Spielberg",
    "gn:population":0,
    "gn:timezone":"Europe/Berlin",
    "iso:country":"DE",
    "wof:name":"Spielberg",
    "wof:placetype":"neighbourhood"
},
  "geometry": {"coordinates":[9.26919,50.30788],"type":"Point"}
}