{
  "type": "Feature",
  "properties": {
    "gn:country":"DE",
    "gn:fcode":"PPL",
    "gn:population":506,
    "iso:country":"DE",
    "name:bak_x_preferred":[
        "\u041a\u043b\u043e\u0448\u0432\u0438\u0446"
    ],
    "name:ceb_x_preferred":[
        "Kloschwitz"
    ],
    "name:deu_x_preferred":[
        "Kloschwitz"
    ],
    "name:epo_x_preferred":[
        "Kloschwitz"
    ],
    "name:fas_x_preferred":[
        "\u06a9\u0644\u0648\u0634\u0648\u06cc\u062a\u0633"
    ],
    "name:ita_x_preferred":[
        "Kloschwitz"
    ],
    "name:mkd_x_preferred":[
        "\u041a\u043b\u043e\u0448\u0432\u0438\u0446"
    ],
    "name:nld_x_preferred":[
        "Kloschwitz"
    ],
    "name:ron_x_preferred":[
        "Kloschwitz"
    ],
    "name:rus_x_preferred":[
        "\u041a\u043b\u043e\u0448\u0432\u0438\u0446"
    ],
    "name:uzb_x_preferred":[
        "Kloschwitz"
    ],
    "name:vie_x_preferred":[
        "Kloschwitz"
    ],
    "name:vol_x_preferred":[
        "Kloschwitz"
    ],
    "qs_pg:aaroncc":"DE",
    "qs_pg:gn_country":"DE",
    "qs_pg:gn_fcode":"PPL",
    "qs_pg:gn_pop":506,
    "qs_pg:name":"Kloschwitz",
    "qs_pg:name_adm0":"Deutschland",
    "qs_pg:name_adm1":"Sachsen-Anhalt",
    "qs_pg:photos_9r":0,
    "qs_pg:photos_sr":0,
    "qs_pg:pop_sr":2,
    "qs_pg:qs_pg_placetype":"locality",
    "qs_pg:qs_pg_placetype_gp":"Town",
    "qs_pg:woe_adm0":23424829,
    "woe:adm0_id":23424829,
    "woe:name_adm0":"Deutschland",
    "woe:name_adm1":"Sachsen-Anhalt",
    "woe:placetype":"Town",
    "wof:name":"Kloschwitz",
    "wof:placetype":"neighbourhood",
    "wof:population":506
},
  "geometry": {"coordinates":[11.75605,51.58533],"type":"Point"}
}