{
  "type": "Feature",
  "properties": {
    "gn:admin1_code":"2",
    "gn:admin2_code":"91.0",
    "gn:admin3_code":"9187.0",
    "gn:admin4_code":"9187128.0",
    "gn:asciiname":"Gaben",
    "gn:country_code":"DE",
    "gn:dem":537,
    "gn:feature_class":"P",
    "gn:feature_code":"PPLL",
    "gn:name":"Gaben",
    "gn:population":0,
    "gn:timezone":"Europe/Berlin",
    "iso:country":"DE",
    "wof:name":"Gaben",
    "wof:placetype":"neighbourhood"
},
  "geometry": {"coordinates":[12.34262,47.92773],"type":"Point"}
}