{
  "type": "Feature",
  "properties": {
    "gn:admin1_code":"2",
    "gn:admin2_code":"93.0",
    "gn:admin3_code":"9371.0",
    "gn:admin4_code":"9371141.0",
    "gn:asciiname":"Haghof",
    "gn:country_code":"DE",
    "gn:dem":465,
    "gn:feature_class":"P",
    "gn:feature_code":"PPL",
    "gn:name":"Haghof",
    "gn:population":0,
    "gn:timezone":"Europe/Berlin",
    "iso:country":"DE",
    "wof:name":"Haghof",
    "wof:placetype":"neighbourhood"
},
  "geometry": {"coordinates":[11.65855,49.54301],"type":"Point"}
}