{
  "type": "Feature",
  "properties": {
    "gn:admin1_code":"2",
    "gn:admin2_code":"91.0",
    "gn:admin3_code":"9172.0",
    "gn:admin4_code":"9172124.0",
    "gn:asciiname":"Gotschen",
    "gn:country_code":"DE",
    "gn:dem":602,
    "gn:feature_class":"P",
    "gn:feature_code":"PPLL",
    "gn:name":"G\u00f6tschen",
    "gn:population":0,
    "gn:timezone":"Europe/Berlin",
    "iso:country":"DE",
    "wof:name":"Gotschen",
    "wof:placetype":"neighbourhood"
},
  "geometry": {"coordinates":[13.05318,47.69353],"type":"Point"}
}