{
  "type": "Feature",
  "properties": {
    "gn:admin1_code":"11.0",
    "gn:admin2_code":"0.0",
    "gn:admin3_code":"12066.0",
    "gn:admin4_code":"12066052.0",
    "gn:asciiname":"Bolschwitz",
    "gn:country_code":"DE",
    "gn:dem":67,
    "gn:feature_class":"P",
    "gn:feature_code":"PPL",
    "gn:name":"Bolschwitz",
    "gn:population":0,
    "gn:timezone":"Europe/Berlin",
    "iso:country":"DE",
    "name:dsb_x_preferred":[
        "B\u00f3la\u0161ojce"
    ],
    "wof:name":"Bolschwitz",
    "wof:placetype":"neighbourhood"
},
  "geometry": {"coordinates":[14.02932,51.74852],"type":"Point"}
}