{
  "type": "Feature",
  "properties": {
    "gn:admin1_code":"2",
    "gn:admin2_code":"95.0",
    "gn:admin3_code":"9574.0",
    "gn:admin4_code":"9574123.0",
    "gn:asciiname":"Moosbach",
    "gn:country_code":"DE",
    "gn:dem":386,
    "gn:feature_class":"P",
    "gn:feature_code":"PPL",
    "gn:name":"Moosbach",
    "gn:population":0,
    "gn:timezone":"Europe/Berlin",
    "iso:country":"DE",
    "name:ceb_x_preferred":[
        "Moosbach"
    ],
    "name:deu_x_preferred":[
        "Moosbach"
    ],
    "name:epo_x_preferred":[
        "Moosbach"
    ],
    "name:fra_x_preferred":[
        "Moosbach"
    ],
    "name:ita_x_preferred":[
        "Moosbach"
    ],
    "name:nld_x_preferred":[
        "Moosbach"
    ],
    "name:pol_x_preferred":[
        "Moosbach"
    ],
    "name:swe_x_preferred":[
        "Moosbach"
    ],
    "name:vol_x_preferred":[
        "Moosbach"
    ],
    "wof:name":"Moosbach",
    "wof:placetype":"neighbourhood"
},
  "geometry": {"coordinates":[11.26252,49.39341],"type":"Point"}
}