{
  "type": "Feature",
  "properties": {
    "gn:admin1_code":"12",
    "gn:admin2_code":"0.0",
    "gn:admin3_code":"13075.0",
    "gn:admin4_code":"13075098.0",
    "gn:asciiname":"Dargibell",
    "gn:country_code":"DE",
    "gn:dem":6,
    "gn:feature_class":"P",
    "gn:feature_code":"PPL",
    "gn:name":"Dargibell",
    "gn:population":0,
    "gn:timezone":"Europe/Berlin",
    "iso:country":"DE",
    "wof:name":"Dargibell",
    "wof:placetype":"neighbourhood"
},
  "geometry": {"coordinates":[13.70888,53.79376],"type":"Point"}
}