{
  "type": "Feature",
  "properties": {
    "gn:admin1_code":"8",
    "gn:admin2_code":"0.0",
    "gn:admin3_code":"7331.0",
    "gn:admin4_code":"7331048.0",
    "gn:asciiname":"Kriegsheim",
    "gn:country_code":"DE",
    "gn:dem":136,
    "gn:feature_class":"P",
    "gn:feature_code":"PPL",
    "gn:name":"Kriegsheim",
    "gn:population":0,
    "gn:timezone":"Europe/Berlin",
    "iso:country":"DE",
    "wof:name":"Kriegsheim",
    "wof:placetype":"neighbourhood"
},
  "geometry": {"coordinates":[8.22152,49.63871],"type":"Point"}
}