{
  "type": "Feature",
  "properties": {
    "gn:admin1_code":"8",
    "gn:admin2_code":"0.0",
    "gn:admin3_code":"7331.0",
    "gn:admin4_code":"7331048.0",
    "gn:asciiname":"Kriegsheim",
    "gn:country_code":"DE",
    "gn:dem":136,
    "gn:feature_class":"P",
    "gn:feature_code":"PPL",
    "gn:name":"Kriegsheim",
    "gn:population":0,
    "gn:timezone":"Europe/Berlin",
    "iso:country":"DE",
    "name:als_x_preferred":[
        "Kriegsheim"
    ],
    "name:ara_x_preferred":[
        "\u0643\u0631\u064a\u063a\u0634\u064a\u0645"
    ],
    "name:cat_x_preferred":[
        "Kriegsheim"
    ],
    "name:ceb_x_preferred":[
        "Kriegsheim"
    ],
    "name:deu_x_preferred":[
        "Kriegsheim"
    ],
    "name:eus_x_preferred":[
        "Kriegsheim"
    ],
    "name:fas_x_preferred":[
        "\u06a9\u0631\u06cc\u06af\u0633\u0647\u0627\u06cc\u0645"
    ],
    "name:fra_x_preferred":[
        "Kriegsheim"
    ],
    "name:hun_x_preferred":[
        "Kriegsheim"
    ],
    "name:hye_x_preferred":[
        "\u053f\u0580\u056b\u0563\u057d\u0561\u0575\u0574"
    ],
    "name:ita_x_preferred":[
        "Kriegsheim"
    ],
    "name:kaz_x_preferred":[
        "\u041a\u0440\u0438\u0433\u0441\u0430\u0439\u043c"
    ],
    "name:lat_x_preferred":[
        "Kriegsheim"
    ],
    "name:mlg_x_preferred":[
        "Kriegsheim"
    ],
    "name:msa_x_preferred":[
        "Kriegsheim"
    ],
    "name:nld_x_preferred":[
        "Kriegsheim"
    ],
    "name:oci_x_preferred":[
        "Kriegsheim"
    ],
    "name:pfl_x_preferred":[
        "Kriegsheim"
    ],
    "name:pms_x_preferred":[
        "Kriegsheim"
    ],
    "name:pol_x_preferred":[
        "Kriegsheim"
    ],
    "name:por_x_preferred":[
        "Kriegsheim"
    ],
    "name:ron_x_preferred":[
        "Kriegsheim"
    ],
    "name:rus_x_preferred":[
        "\u041a\u0440\u0438\u0433\u0441\u0430\u0439\u043c"
    ],
    "name:slk_x_preferred":[
        "Kriegsheim"
    ],
    "name:slv_x_preferred":[
        "Kriegsheim"
    ],
    "name:spa_x_preferred":[
        "Kriegsheim"
    ],
    "name:srp_x_preferred":[
        "\u041a\u0440\u0438\u0433\u0441\u0445\u0430\u0458\u043c"
    ],
    "name:swe_x_preferred":[
        "Kriegsheim"
    ],
    "name:ukr_x_preferred":[
        "\u041a\u0440\u0438\u0433\u0441\u0430\u0439\u043c"
    ],
    "name:uzb_x_preferred":[
        "Kriegsheim"
    ],
    "name:vie_x_preferred":[
        "Kriegsheim"
    ],
    "name:vol_x_preferred":[
        "Kriegsheim"
    ],
    "name:war_x_preferred":[
        "Kriegsheim"
    ],
    "name:zho_x_preferred":[
        "\u514b\u91cc\u683c\u8d5b\u59c6"
    ],
    "wof:name":"Kriegsheim",
    "wof:placetype":"neighbourhood"
},
  "geometry": {"coordinates":[8.22152,49.63871],"type":"Point"}
}