{
  "type": "Feature",
  "properties": {
    "gn:admin1_code":"6.0",
    "gn:admin2_code":"0.0",
    "gn:admin3_code":"3458.0",
    "gn:admin4_code":"3458005.0",
    "gn:asciiname":"Bissen",
    "gn:country_code":"DE",
    "gn:dem":32,
    "gn:feature_class":"P",
    "gn:feature_code":"PPL",
    "gn:name":"Bissen",
    "gn:population":0,
    "gn:timezone":"Europe/Berlin",
    "iso:country":"DE",
    "name:als_x_preferred":[
        "Biissen"
    ],
    "name:bel_x_preferred":[
        "\u0411\u0456\u0441\u044d\u043d"
    ],
    "name:bul_x_preferred":[
        "\u0411\u0438\u0441\u0435\u043d"
    ],
    "name:cat_x_preferred":[
        "Bissen"
    ],
    "name:ceb_x_preferred":[
        "Bissen"
    ],
    "name:dan_x_preferred":[
        "Bissen"
    ],
    "name:deu_x_preferred":[
        "Bissen"
    ],
    "name:fas_x_preferred":[
        "\u0628\u06cc\u0633\u0646"
    ],
    "name:fra_x_preferred":[
        "Bissen"
    ],
    "name:ita_x_preferred":[
        "Bissen"
    ],
    "name:lit_x_preferred":[
        "Bisenas"
    ],
    "name:ltz_x_preferred":[
        "Gemeng Biissen"
    ],
    "name:msa_x_preferred":[
        "Bissen"
    ],
    "name:nds_x_preferred":[
        "Gemeen Bissen"
    ],
    "name:nld_x_preferred":[
        "Bissen"
    ],
    "name:nor_x_preferred":[
        "Bissen"
    ],
    "name:pol_x_preferred":[
        "Bissen"
    ],
    "name:por_x_preferred":[
        "Bissen"
    ],
    "name:rus_x_preferred":[
        "\u0411\u0438\u0441\u0441\u0435\u043d"
    ],
    "name:slk_x_preferred":[
        "Bissen"
    ],
    "name:swe_x_preferred":[
        "Bissen"
    ],
    "name:ukr_x_preferred":[
        "\u0411\u0456\u0441\u0441\u0435\u043d"
    ],
    "wof:name":"Bissen",
    "wof:placetype":"neighbourhood"
},
  "geometry": {"coordinates":[8.52618,53.06198000000001],"type":"Point"}
}