{
  "type": "Feature",
  "properties": {
    "gn:admin1_code":"9.0",
    "gn:admin2_code":"0.0",
    "gn:admin3_code":"10046.0",
    "gn:admin4_code":"10046118.0",
    "gn:asciiname":"UEberroth-Niederhofen",
    "gn:country_code":"DE",
    "gn:dem":351,
    "gn:feature_class":"P",
    "gn:feature_code":"PPL",
    "gn:name":"\u00dcberroth-Niederhofen",
    "gn:population":0,
    "gn:timezone":"Europe/Berlin",
    "iso:country":"DE",
    "wof:name":"UEberroth-Niederhofen",
    "wof:placetype":"neighbourhood"
},
  "geometry": {"coordinates":[6.94505,49.50059],"type":"Point"}
}