{
  "type": "Feature",
  "properties": {
    "iso:country":"DE",
    "name:deu_x_preferred":[
        "Fliegerhorst Neuburg"
    ],
    "name:fra_x_preferred":[
        "Base a\u00e9rienne de Neubourg"
    ],
    "name:por_x_preferred":[
        "Base a\u00e9rea de Neuburg"
    ],
    "oa:elevation_ft":"1249",
    "oa:type":"medium_airport",
    "wd:wordcount":42,
    "woe:hierarchy":{
        "country_id":23424829,
        "county_id":12596818,
        "localadmin_id":12634661,
        "planet_id":1,
        "state_id":2345482
    },
    "wof:name":"Neuburg Airport",
    "wof:placetype":"campus"
},
  "geometry": {"coordinates":[11.2117,48.7117],"type":"Point"}
}