{
  "type": "Feature",
  "properties": {
    "iso:country":"DE",
    "name:deu_x_preferred":[
        "Fliegerhorst Neuburg"
    ],
    "name:eng_x_preferred":[
        "Neuburg Air Base"
    ],
    "name:eng_x_variant":[
        "ETSN"
    ],
    "name:fin_x_preferred":[
        "Neuburgin lentotukikohta"
    ],
    "name:fra_x_preferred":[
        "Base a\u00e9rienne de Neubourg"
    ],
    "name:jpn_x_preferred":[
        "\u30ce\u30a4\u30d6\u30eb\u30af\u30fb\u30a2\u30f3\u30fb\u30c7\u30a2\u30fb\u30c9\u30ca\u30a6\u822a\u7a7a\u57fa\u5730"
    ],
    "name:msa_x_preferred":[
        "Lapangan Terbang Neuburg AB"
    ],
    "name:msa_x_variant":[
        "Lapangan Terbang Neuburg"
    ],
    "name:por_x_preferred":[
        "Base a\u00e9rea de Neuburg"
    ],
    "name:zho_x_preferred":[
        "\u7ebd\u56e0\u5821\u7a7a\u519b\u57fa\u5730"
    ],
    "oa:elevation_ft":"1249",
    "oa:type":"medium_airport",
    "wd:wordcount":42,
    "woe:hierarchy":{
        "country_id":23424829,
        "county_id":12596818,
        "localadmin_id":12634661,
        "planet_id":1,
        "state_id":2345482
    },
    "wof:name":"Neuburg Airport",
    "wof:placetype":"campus"
},
  "geometry": {"coordinates":[11.2117,48.7117],"type":"Point"}
}