{
  "type": "Feature",
  "properties": {
    "gn:admin1_code":"2",
    "gn:admin2_code":"91.0",
    "gn:admin3_code":"9185.0",
    "gn:admin4_code":"9185131.0",
    "gn:asciiname":"Habertshausen",
    "gn:country_code":"DE",
    "gn:dem":434,
    "gn:feature_class":"P",
    "gn:feature_code":"PPL",
    "gn:name":"Habertshausen",
    "gn:population":0,
    "gn:timezone":"Europe/Berlin",
    "iso:country":"DE",
    "wof:name":"Habertshausen",
    "wof:placetype":"neighbourhood"
},
  "geometry": {"coordinates":[11.23294,48.53194000000001],"type":"Point"}
}