{
  "type": "Feature",
  "properties": {
    "gn:admin1_code":"6",
    "gn:admin2_code":"0.0",
    "gn:admin3_code":"3157.0",
    "gn:admin4_code":"3157009.0",
    "gn:asciiname":"Klein Solschen",
    "gn:country_code":"DE",
    "gn:dem":93,
    "gn:feature_class":"P",
    "gn:feature_code":"PPL",
    "gn:name":"Klein Solschen",
    "gn:population":0,
    "gn:timezone":"Europe/Berlin",
    "iso:country":"DE",
    "name:nds_x_preferred":[
        "L\u00fcttjen Sulschen"
    ],
    "name:nds_x_variant":[
        "L\u00fctschen Sulschen"
    ],
    "wof:name":"Klein Solschen",
    "wof:placetype":"neighbourhood"
},
  "geometry": {"coordinates":[10.14158,52.2711],"type":"Point"}
}