{
  "type": "Feature",
  "properties": {
    "gn:admin1_code":"13",
    "gn:admin2_code":"0.0",
    "gn:admin3_code":"14729.0",
    "gn:admin4_code":"14729430.0",
    "gn:asciiname":"Loebschuetz",
    "gn:country_code":"DE",
    "gn:dem":130,
    "gn:feature_class":"P",
    "gn:feature_code":"PPL",
    "gn:name":"L\u00f6bsch\u00fctz",
    "gn:population":0,
    "gn:timezone":"Europe/Berlin",
    "iso:country":"DE",
    "wof:name":"Loebschuetz",
    "wof:placetype":"neighbourhood"
},
  "geometry": {"coordinates":[12.31647,51.19843],"type":"Point"}
}