{
  "type": "Feature",
  "properties": {
    "gn:admin1_code":"10",
    "gn:admin2_code":"0.0",
    "gn:admin3_code":"1056.0",
    "gn:admin4_code":"1056002.0",
    "gn:asciiname":"Grossendorferheide",
    "gn:country_code":"DE",
    "gn:dem":14,
    "gn:feature_class":"P",
    "gn:feature_code":"PPL",
    "gn:name":"Gro\u00dfendorferheide",
    "gn:population":0,
    "gn:timezone":"Europe/Berlin",
    "iso:country":"DE",
    "wof:name":"Grossendorferheide",
    "wof:placetype":"neighbourhood"
},
  "geometry": {"coordinates":[9.76667,53.81667],"type":"Point"}
}