{
  "type": "Feature",
  "properties": {
    "gn:admin1_code":"1",
    "gn:admin2_code":"84.0",
    "gn:admin3_code":"8436.0",
    "gn:admin4_code":"8436079.0",
    "gn:asciiname":"Edensbach",
    "gn:country_code":"DE",
    "gn:dem":683,
    "gn:feature_class":"P",
    "gn:feature_code":"PPL",
    "gn:name":"Edensbach",
    "gn:population":0,
    "gn:timezone":"Europe/Berlin",
    "iso:country":"DE",
    "wof:name":"Edensbach",
    "wof:placetype":"neighbourhood"
},
  "geometry": {"coordinates":[9.74398,47.7564],"type":"Point"}
}