{
  "type": "Feature",
  "properties": {
    "gn:admin1_code":"1.0",
    "gn:admin2_code":"84.0",
    "gn:admin3_code":"8426.0",
    "gn:admin4_code":"8426078.0",
    "gn:asciiname":"Brackenhofen",
    "gn:country_code":"DE",
    "gn:dem":585,
    "gn:feature_class":"P",
    "gn:feature_code":"PPL",
    "gn:name":"Brackenhofen",
    "gn:population":0,
    "gn:timezone":"Europe/Berlin",
    "iso:country":"DE",
    "wof:name":"Brackenhofen",
    "wof:placetype":"neighbourhood"
},
  "geometry": {"coordinates":[9.60553,48.09183],"type":"Point"}
}