{
  "type": "Feature",
  "properties": {
    "gn:admin1_code":"13",
    "gn:admin2_code":"0.0",
    "gn:admin3_code":"14729.0",
    "gn:admin4_code":"14729080.0",
    "gn:asciiname":"Hausdorf",
    "gn:country_code":"DE",
    "gn:dem":228,
    "gn:feature_class":"P",
    "gn:feature_code":"PPL",
    "gn:name":"Hausdorf",
    "gn:population":0,
    "gn:timezone":"Europe/Berlin",
    "iso:country":"DE",
    "wof:name":"Hausdorf",
    "wof:placetype":"neighbourhood"
},
  "geometry": {"coordinates":[12.83445,51.11769],"type":"Point"}
}