{
  "type": "Feature",
  "properties": {
    "gn:admin1_code":"2",
    "gn:admin2_code":"91.0",
    "gn:admin3_code":"9187.0",
    "gn:admin4_code":"9187176.0",
    "gn:asciiname":"Freiberg",
    "gn:country_code":"DE",
    "gn:dem":512,
    "gn:feature_class":"P",
    "gn:feature_code":"PPL",
    "gn:name":"Freiberg",
    "gn:population":0,
    "gn:timezone":"Europe/Berlin",
    "iso:country":"DE",
    "wof:name":"Freiberg",
    "wof:placetype":"neighbourhood"
},
  "geometry": {"coordinates":[12.26125,48.11861],"type":"Point"}
}