{
  "type": "Feature",
  "properties": {
    "gn:admin1_code":"2.0",
    "gn:admin2_code":"96.0",
    "gn:admin3_code":"9677.0",
    "gn:admin4_code":"9677114.0",
    "gn:asciiname":"Binsfeld",
    "gn:country_code":"DE",
    "gn:dem":200,
    "gn:feature_class":"P",
    "gn:feature_code":"PPL",
    "gn:name":"Binsfeld",
    "gn:population":0,
    "gn:timezone":"Europe/Berlin",
    "iso:country":"DE",
    "name:ceb_x_preferred":[
        "Binsfeld"
    ],
    "name:deu_x_preferred":[
        "Binsfeld"
    ],
    "name:epo_x_preferred":[
        "Binsfeld"
    ],
    "name:eus_x_preferred":[
        "Binsfeld"
    ],
    "name:fas_x_preferred":[
        "\u0628\u06cc\u0646\u0633\u0641\u0644\u062f"
    ],
    "name:fra_x_preferred":[
        "Binsfeld"
    ],
    "name:hun_x_preferred":[
        "Binsfeld"
    ],
    "name:ita_x_preferred":[
        "Binsfeld"
    ],
    "name:kaz_x_preferred":[
        "\u0411\u0438\u043d\u0441\u0444\u0435\u043b\u044c\u0434"
    ],
    "name:kir_x_preferred":[
        "\u0411\u0438\u043d\u0441\u0444\u0435\u043b\u044c\u0434"
    ],
    "name:msa_x_preferred":[
        "Binsfeld"
    ],
    "name:nld_x_preferred":[
        "Binsfeld"
    ],
    "name:pol_x_preferred":[
        "Binsfeld"
    ],
    "name:por_x_preferred":[
        "Binsfeld"
    ],
    "name:ron_x_preferred":[
        "Binsfeld"
    ],
    "name:rus_x_preferred":[
        "\u0411\u0438\u043d\u0441\u0444\u0435\u043b\u044c\u0434"
    ],
    "name:spa_x_preferred":[
        "Binsfeld"
    ],
    "name:srp_x_preferred":[
        "\u0411\u0438\u043d\u0441\u0444\u0435\u043b\u0434"
    ],
    "name:ukr_x_preferred":[
        "\u0411\u0456\u043d\u0441\u0444\u0435\u043b\u044c\u0434"
    ],
    "name:uzb_x_preferred":[
        "Binsfeld"
    ],
    "name:vie_x_preferred":[
        "Binsfeld"
    ],
    "name:vol_x_preferred":[
        "Binsfeld"
    ],
    "name:war_x_preferred":[
        "Binsfeld"
    ],
    "name:zho_x_preferred":[
        "\u5bbe\u65af\u8d39\u5c14\u5fb7"
    ],
    "wof:name":"Binsfeld",
    "wof:placetype":"neighbourhood"
},
  "geometry": {"coordinates":[9.88702,49.95059000000001],"type":"Point"}
}