{
  "type": "Feature",
  "properties": {
    "gn:admin1_code":"2",
    "gn:admin2_code":"94.0",
    "gn:admin3_code":"9471.0",
    "gn:admin4_code":"9471191.0",
    "gn:asciiname":"Unteraurach",
    "gn:country_code":"DE",
    "gn:dem":259,
    "gn:feature_class":"P",
    "gn:feature_code":"PPL",
    "gn:name":"Unteraurach",
    "gn:population":0,
    "gn:timezone":"Europe/Berlin",
    "iso:country":"DE",
    "wof:name":"Unteraurach",
    "wof:placetype":"neighbourhood"
},
  "geometry": {"coordinates":[10.86514,49.85591],"type":"Point"}
}