{
  "type": "Feature",
  "properties": {
    "gn:admin1_code":"6",
    "gn:admin2_code":"0.0",
    "gn:admin3_code":"3352.0",
    "gn:admin4_code":"3352032.0",
    "gn:asciiname":"Friedrich Wilhelmsdorf",
    "gn:country_code":"DE",
    "gn:dem":3,
    "gn:feature_class":"P",
    "gn:feature_code":"PPL",
    "gn:name":"Friedrich Wilhelmsdorf",
    "gn:population":0,
    "gn:timezone":"Europe/Berlin",
    "iso:country":"DE",
    "wof:name":"Friedrich Wilhelmsdorf",
    "wof:placetype":"neighbourhood"
},
  "geometry": {"coordinates":[8.67574,53.46434],"type":"Point"}
}