{
  "type": "Feature",
  "properties": {
    "gn:admin1_code":"2",
    "gn:admin2_code":"95.0",
    "gn:admin3_code":"9574.0",
    "gn:admin4_code":"9574155.0",
    "gn:asciiname":"Enzenreuth",
    "gn:country_code":"DE",
    "gn:dem":495,
    "gn:feature_class":"P",
    "gn:feature_code":"PPL",
    "gn:name":"Enzenreuth",
    "gn:population":0,
    "gn:timezone":"Europe/Berlin",
    "iso:country":"DE",
    "wof:name":"Enzenreuth",
    "wof:placetype":"locality"
},
  "geometry": {"coordinates":[11.36862,49.56107],"type":"Point"}
}