{
  "type": "Feature",
  "properties": {
    "gn:admin1_code":"1",
    "gn:admin2_code":"84.0",
    "gn:admin3_code":"8437.0",
    "gn:admin4_code":"8437124.0",
    "gn:asciiname":"Schwende",
    "gn:country_code":"DE",
    "gn:dem":638,
    "gn:feature_class":"P",
    "gn:feature_code":"PPL",
    "gn:name":"Schwende",
    "gn:population":0,
    "gn:timezone":"Europe/Berlin",
    "iso:country":"DE",
    "name:deu_x_preferred":[
        "Schwende"
    ],
    "wof:name":"Schwende",
    "wof:placetype":"neighbourhood"
},
  "geometry": {"coordinates":[9.19575,47.85181],"type":"Point"}
}