{
  "type": "Feature",
  "properties": {
    "gn:admin1_code":"1",
    "gn:admin2_code":"82.0",
    "gn:admin3_code":"8236.0",
    "gn:admin4_code":"8236072.0",
    "gn:asciiname":"Pfinzweiler",
    "gn:country_code":"DE",
    "gn:dem":365,
    "gn:feature_class":"P",
    "gn:feature_code":"PPL",
    "gn:name":"Pfinzweiler",
    "gn:population":0,
    "gn:timezone":"Europe/Berlin",
    "iso:country":"DE",
    "wof:name":"Pfinzweiler",
    "wof:placetype":"neighbourhood"
},
  "geometry": {"coordinates":[8.51423,48.85291],"type":"Point"}
}