{
  "type": "Feature",
  "properties": {
    "gn:admin1_code":"1",
    "gn:admin2_code":"83.0",
    "gn:admin3_code":"8315.0",
    "gn:admin4_code":"8315016.0",
    "gn:asciiname":"Hinterdorf",
    "gn:country_code":"DE",
    "gn:dem":1022,
    "gn:feature_class":"P",
    "gn:feature_code":"PPL",
    "gn:name":"Hinterdorf",
    "gn:population":0,
    "gn:timezone":"Europe/Berlin",
    "iso:country":"DE",
    "wof:name":"Hinterdorf",
    "wof:placetype":"neighbourhood"
},
  "geometry": {"coordinates":[8.05849,47.93711],"type":"Point"}
}