{
  "type": "Feature",
  "properties": {
    "gn:admin1_code":"2",
    "gn:admin2_code":"91.0",
    "gn:admin3_code":"9187.0",
    "gn:admin4_code":"9187117.0",
    "gn:asciiname":"Holzhausen",
    "gn:country_code":"DE",
    "gn:dem":500,
    "gn:feature_class":"P",
    "gn:feature_code":"PPL",
    "gn:name":"Holzhausen",
    "gn:population":0,
    "gn:timezone":"Europe/Berlin",
    "iso:country":"DE",
    "name:ceb_x_preferred":[
        "Holzhausen"
    ],
    "name:deu_x_preferred":[
        "Holzhausen"
    ],
    "name:epo_x_preferred":[
        "Holzhausen"
    ],
    "name:ita_x_preferred":[
        "Holzhausen"
    ],
    "name:nld_x_preferred":[
        "Holzhausen"
    ],
    "name:pol_x_preferred":[
        "Holzhausen"
    ],
    "name:rus_x_preferred":[
        "\u0425\u043e\u043b\u044c\u0446\u0445\u0430\u0443\u0437\u0435\u043d"
    ],
    "name:swe_x_preferred":[
        "Holzhausen"
    ],
    "name:vol_x_preferred":[
        "Holzhausen"
    ],
    "wof:name":"Holzhausen",
    "wof:placetype":"neighbourhood"
},
  "geometry": {"coordinates":[12.01158,47.90023],"type":"Point"}
}