{
  "type": "Feature",
  "properties": {
    "gn:admin1_code":"13",
    "gn:admin2_code":"0.0",
    "gn:admin3_code":"14627.0",
    "gn:admin4_code":"14627190.0",
    "gn:asciiname":"Diesbar-Seusslitz",
    "gn:country_code":"DE",
    "gn:dem":105,
    "gn:feature_class":"P",
    "gn:feature_code":"PPL",
    "gn:name":"Diesbar-Seusslitz",
    "gn:population":0,
    "gn:timezone":"Europe/Berlin",
    "iso:country":"DE",
    "wof:name":"Diesbar-Seusslitz",
    "wof:placetype":"neighbourhood"
},
  "geometry": {"coordinates":[13.42125,51.23615],"type":"Point"}
}