{
  "type": "Feature",
  "properties": {
    "gn:admin1_code":"1",
    "gn:admin2_code":"84.0",
    "gn:admin3_code":"8437.0",
    "gn:admin4_code":"8437088.0",
    "gn:asciiname":"Mottschiess",
    "gn:country_code":"DE",
    "gn:dem":636,
    "gn:feature_class":"P",
    "gn:feature_code":"PPL",
    "gn:name":"Mottschie\u00df",
    "gn:population":0,
    "gn:timezone":"Europe/Berlin",
    "iso:country":"DE",
    "name:und_x_variant":[
        "Mottschies",
        "Mottschie\u00df"
    ],
    "wof:name":"Mottschiess",
    "wof:placetype":"neighbourhood"
},
  "geometry": {"coordinates":[9.28581,47.96205],"type":"Point"}
}