{
  "type": "Feature",
  "properties": {
    "gn:admin1_code":"2",
    "gn:admin2_code":"94.0",
    "gn:admin3_code":"9474.0",
    "gn:admin4_code":"9474124.0",
    "gn:asciiname":"Hundsboden",
    "gn:country_code":"DE",
    "gn:dem":493,
    "gn:feature_class":"P",
    "gn:feature_code":"PPL",
    "gn:name":"Hundsboden",
    "gn:population":0,
    "gn:timezone":"Europe/Berlin",
    "iso:country":"DE",
    "wof:name":"Hundsboden",
    "wof:placetype":"neighbourhood"
},
  "geometry": {"coordinates":[11.21664,49.71069],"type":"Point"}
}