{
  "type": "Feature",
  "properties": {
    "gn:admin1_code":"11.0",
    "gn:admin2_code":"0.0",
    "gn:admin3_code":"12061.0",
    "gn:admin4_code":"12061260.0",
    "gn:asciiname":"Bindowbrueck",
    "gn:country_code":"DE",
    "gn:dem":38,
    "gn:feature_class":"P",
    "gn:feature_code":"PPL",
    "gn:name":"Bindowbr\u00fcck",
    "gn:population":0,
    "gn:timezone":"Europe/Berlin",
    "iso:country":"DE",
    "wof:name":"Bindowbrueck",
    "wof:placetype":"neighbourhood"
},
  "geometry": {"coordinates":[13.73333,52.28333],"type":"Point"}
}