{
  "type": "Feature",
  "properties": {
    "gn:admin1_code":"6.0",
    "gn:admin2_code":"0.0",
    "gn:admin3_code":"3251.0",
    "gn:admin4_code":"3251044.0",
    "gn:asciiname":"Bockeler Schweiz",
    "gn:country_code":"DE",
    "gn:dem":41,
    "gn:feature_class":"P",
    "gn:feature_code":"PPL",
    "gn:name":"Bockeler Schweiz",
    "gn:population":0,
    "gn:timezone":"Europe/Berlin",
    "iso:country":"DE",
    "wof:name":"Bockeler Schweiz",
    "wof:placetype":"neighbourhood"
},
  "geometry": {"coordinates":[8.55492,52.57468000000001],"type":"Point"}
}