{
  "type": "Feature",
  "properties": {
    "gn:admin1_code":"2",
    "gn:admin2_code":"95.0",
    "gn:admin3_code":"9576.0",
    "gn:admin4_code":"9576126.0",
    "gn:asciiname":"Selingstadt",
    "gn:country_code":"DE",
    "gn:dem":466,
    "gn:feature_class":"P",
    "gn:feature_code":"PPL",
    "gn:name":"Selingstadt",
    "gn:population":0,
    "gn:timezone":"Europe/Berlin",
    "iso:country":"DE",
    "wof:name":"Selingstadt",
    "wof:placetype":"neighbourhood"
},
  "geometry": {"coordinates":[11.14966,49.12905],"type":"Point"}
}