{
  "type": "Feature",
  "properties": {
    "gn:admin1_code":"2.0",
    "gn:admin2_code":"093",
    "gn:admin3_code":"9376.0",
    "gn:admin4_code":"9376116.0",
    "gn:asciiname":"Windmais",
    "gn:country_code":"DE",
    "gn:dem":422,
    "gn:feature_class":"P",
    "gn:feature_code":"PPL",
    "gn:name":"Windmais",
    "gn:population":0,
    "gn:timezone":"Europe/Berlin",
    "iso:country":"DE",
    "wof:name":"Windmais",
    "wof:placetype":"neighbourhood"
},
  "geometry": {"coordinates":[12.34402,49.30196],"type":"Point"}
}