{
  "type": "Feature",
  "properties": {
    "gn:admin1_code":"6",
    "gn:admin2_code":"0.0",
    "gn:admin3_code":"3241.0",
    "gn:admin4_code":"3241010.0",
    "gn:asciiname":"Godshorn",
    "gn:country_code":"DE",
    "gn:dem":57,
    "gn:feature_class":"P",
    "gn:feature_code":"PPL",
    "gn:name":"Godshorn",
    "gn:population":0,
    "gn:timezone":"Europe/Berlin",
    "iso:country":"DE",
    "name:gml_x_preferred":[
        "Gutereshorn [a. 1225]"
    ],
    "name:nds_x_preferred":[
        "Goodshu'ern"
    ],
    "name:nds_x_variant":[
        "Gudszurn"
    ],
    "wof:name":"Godshorn",
    "wof:placetype":"neighbourhood"
},
  "geometry": {"coordinates":[9.70659,52.43896],"type":"Point"}
}