{
  "type": "Feature",
  "properties": {
    "gn:population":2061,
    "iso:country":"DE",
    "name:baq_x_preferred":[
        "Gr\u00fcnendeich"
    ],
    "name:ceb_x_preferred":[
        "Gr\u00fcnendeich"
    ],
    "name:chi_x_preferred":[
        "\u683c\u5415\u5ae9\u4ee3\u5e0c"
    ],
    "name:deu_x_preferred":[
        "Gr\u00fcnendeich"
    ],
    "name:dut_x_preferred":[
        "Gr\u00fcnendeich"
    ],
    "name:eng_x_preferred":[
        "Gr\u00fcnendeich"
    ],
    "name:epo_x_preferred":[
        "Gr\u00fcnendeich"
    ],
    "name:eus_x_preferred":[
        "Gr\u00fcnendeich"
    ],
    "name:fra_x_preferred":[
        "Gr\u00fcnendeich"
    ],
    "name:fre_x_preferred":[
        "Gr\u00fcnendeich"
    ],
    "name:ger_x_preferred":[
        "Gr\u00fcnendeich"
    ],
    "name:hun_x_preferred":[
        "Gr\u00fcnendeich"
    ],
    "name:ita_x_preferred":[
        "Gr\u00fcnendeich"
    ],
    "name:jpn_x_preferred":[
        "\u30b0\u30ea\u30e5\u30fc\u30cd\u30f3\u30c0\u30a4\u30d2"
    ],
    "name:kaz_x_preferred":[
        "\u0413\u0440\u044e\u043d\u0435\u043d\u0434\u0430\u0439\u0445"
    ],
    "name:kir_x_preferred":[
        "\u0413\u0440\u044e\u043d\u0435\u043d\u0434\u0430\u0439\u0445"
    ],
    "name:may_x_preferred":[
        "Gr\u00fcnendeich"
    ],
    "name:nan_x_preferred":[
        "Gr\u00fcnendeich"
    ],
    "name:nds_x_preferred":[
        "Greundiek"
    ],
    "name:per_x_preferred":[
        "\u06af\u0631\u0648\u0646\u0646\u062f\u0627\u06cc\u0634"
    ],
    "name:pol_x_preferred":[
        "Gr\u00fcnendeich"
    ],
    "name:por_x_preferred":[
        "Gr\u00fcnendeich"
    ],
    "name:rum_x_preferred":[
        "Gr\u00fcnendeich"
    ],
    "name:rus_x_preferred":[
        "\u0413\u0440\u044e\u043d\u0435\u043d\u0434\u0430\u0439\u0445"
    ],
    "name:srp_x_preferred":[
        "\u0413\u0440\u0438\u043d\u0435\u043d\u0434\u0430\u0458\u0445"
    ],
    "name:ukr_x_preferred":[
        "\u0413\u0440\u044e\u043d\u0435\u043d\u0434\u0430\u0439\u0445"
    ],
    "name:uzb_x_preferred":[
        "Gr\u00fcnendeich"
    ],
    "name:vol_x_preferred":[
        "Gr\u00fcnendeich"
    ],
    "name:war_x_preferred":[
        "Gr\u00fcnendeich"
    ],
    "qs:a0":"Bundesrepublik Deutschland",
    "qs:a1":"*Niedersachsen",
    "qs:a1r":"0",
    "qs:a2":"Stade",
    "qs:adm0":"Bundesrepublik Deutschland",
    "qs:la_lc":"*",
    "qs:level":"locality",
    "qs:loc":"Gr\u00fcnendeich",
    "qs:loc_alt":"Gruenendeich",
    "qs:pop":0,
    "qs:type":"buffered point",
    "wd:wordcount":118,
    "wof:name":"Gr\u00fcnendeich",
    "wof:placetype":"locality",
    "wof:population":2061
},
  "geometry": {"coordinates":[9.615442,53.572493],"type":"Point"}
}