{
  "type": "Feature",
  "properties": {
    "gn:gn_country":"DE",
    "gn:gn_fcode":"PPLA4",
    "gn:gn_pop":186,
    "gn:population":186,
    "iso:country":"DE",
    "name:bak_x_preferred":[
        "\u041a\u043b\u0430\u0439\u043d\u0435\u0431\u0435\u0440\u0441\u0434\u043e\u0440\u0444"
    ],
    "name:baq_x_preferred":[
        "Kleinebersdorf"
    ],
    "name:chi_x_preferred":[
        "\u514b\u83b1\u5185\u8d1d\u5c14\u65af\u591a\u592b"
    ],
    "name:dut_x_preferred":[
        "Kleinebersdorf"
    ],
    "name:eng_x_preferred":[
        "Kleinebersdorf"
    ],
    "name:epo_x_preferred":[
        "Kleinebersdorf"
    ],
    "name:fre_x_preferred":[
        "Kleinebersdorf"
    ],
    "name:ger_x_preferred":[
        "Kleinebersdorf"
    ],
    "name:hun_x_preferred":[
        "Kleinebersdorf"
    ],
    "name:ita_x_preferred":[
        "Kleinebersdorf"
    ],
    "name:mac_x_preferred":[
        "\u041a\u043b\u0430\u0458\u043d\u0435\u0431\u0435\u0440\u0441\u0434\u043e\u0440\u0444"
    ],
    "name:may_x_preferred":[
        "Kleinebersdorf"
    ],
    "name:per_x_preferred":[
        "\u06a9\u0644\u0627\u06cc\u0646\u0628\u0631\u0633\u062f\u0648\u0631\u0641"
    ],
    "name:pol_x_preferred":[
        "Kleinebersdorf"
    ],
    "name:por_x_preferred":[
        "Kleinebersdorf"
    ],
    "name:rum_x_preferred":[
        "Kleinebersdorf"
    ],
    "name:rus_x_preferred":[
        "\u041a\u043b\u0430\u0439\u043d\u0435\u0431\u0435\u0440\u0441\u0434\u043e\u0440\u0444"
    ],
    "name:srp_x_preferred":[
        "\u041a\u043b\u0430\u0458\u043d\u0435\u0431\u0435\u0440\u0441\u0434\u043e\u0440\u0444"
    ],
    "name:ukr_x_preferred":[
        "\u041a\u043b\u044f\u0439\u043d\u0435\u0431\u0435\u0440\u0441\u0434\u043e\u0440\u0444"
    ],
    "name:uzb_x_preferred":[
        "Kleinebersdorf"
    ],
    "name:vie_x_preferred":[
        "Kleinebersdorf"
    ],
    "name:vol_x_preferred":[
        "Kleinebersdorf"
    ],
    "name:war_x_preferred":[
        "Kleinebersdorf"
    ],
    "qs_pg:aaroncc":"DE",
    "qs_pg:gn_country":"DE",
    "qs_pg:gn_fcode":"PPLA4",
    "qs_pg:gn_pop":186,
    "qs_pg:name":"Kleinebersdorf",
    "qs_pg:photos_9r":0,
    "qs_pg:photos_sr":0,
    "qs_pg:pop_sr":1,
    "qs_pg:qs_pg_placetype":"locality",
    "wof:name":"Kleinebersdorf",
    "wof:placetype":"locality",
    "wof:population":186
},
  "geometry": {"coordinates":[11.83333,50.81667],"type":"Point"}
}