{
  "type": "Feature",
  "properties": {
    "gn:admin1_code":"2",
    "gn:admin2_code":"93.0",
    "gn:admin3_code":"9373.0",
    "gn:admin4_code":"9373113.0",
    "gn:asciiname":"Langenthal",
    "gn:country_code":"DE",
    "gn:dem":440,
    "gn:feature_class":"P",
    "gn:feature_code":"PPL",
    "gn:name":"Langenthal",
    "gn:population":0,
    "gn:timezone":"Europe/Berlin",
    "iso:country":"DE",
    "name:als_x_preferred":[
        "Langenthal"
    ],
    "name:azb_x_preferred":[
        "\u0644\u0627\u0646\u0698\u0627\u0646\u062a\u0644"
    ],
    "name:cat_x_preferred":[
        "Langenthal"
    ],
    "name:chv_x_preferred":[
        "\u041b\u0430\u043d\u0433\u0435\u043d\u0442\u0430\u043b\u044c"
    ],
    "name:deu_x_preferred":[
        "Langenthal"
    ],
    "name:epo_x_preferred":[
        "Langenthal"
    ],
    "name:eus_x_preferred":[
        "Langenthal"
    ],
    "name:fas_x_preferred":[
        "\u0644\u0627\u0646\u0698\u0627\u0646\u062a\u0644"
    ],
    "name:fin_x_preferred":[
        "Langenthal"
    ],
    "name:fra_x_preferred":[
        "Langenthal"
    ],
    "name:gle_x_preferred":[
        "Langenthal"
    ],
    "name:heb_x_preferred":[
        "\u05dc\u05e0\u05d2\u05e0\u05d8\u05dc"
    ],
    "name:hrv_x_preferred":[
        "Langenthal"
    ],
    "name:ita_x_preferred":[
        "Langenthal"
    ],
    "name:kaz_x_preferred":[
        "\u041b\u0430\u043d\u0433\u0435\u043d\u0442\u0430\u043b\u044c"
    ],
    "name:lmo_x_preferred":[
        "Langenthal"
    ],
    "name:msa_x_preferred":[
        "Langenthal"
    ],
    "name:nld_x_preferred":[
        "Langenthal"
    ],
    "name:nno_x_preferred":[
        "Langenthal"
    ],
    "name:pol_x_preferred":[
        "Langenthal"
    ],
    "name:rus_x_preferred":[
        "\u041b\u0430\u043d\u0433\u0435\u043d\u0442\u0430\u043b\u044c"
    ],
    "name:spa_x_preferred":[
        "Langenthal"
    ],
    "name:sqi_x_preferred":[
        "Langenthal"
    ],
    "name:swe_x_preferred":[
        "Langenthal"
    ],
    "name:ukr_x_preferred":[
        "\u041b\u0430\u043d\u0433\u0435\u043d\u0442\u0430\u043b\u044c"
    ],
    "name:vie_x_preferred":[
        "Langenthal"
    ],
    "name:vol_x_preferred":[
        "Langenthal"
    ],
    "name:war_x_preferred":[
        "Langenthal"
    ],
    "name:zho_x_preferred":[
        "\u6717\u6839\u5854\u723e"
    ],
    "wof:name":"Langenthal",
    "wof:placetype":"neighbourhood"
},
  "geometry": {"coordinates":[11.47093,49.36181],"type":"Point"}
}