{
  "type": "Feature",
  "properties": {
    "gn:admin1_code":"11.0",
    "gn:admin2_code":"0.0",
    "gn:admin3_code":"12068.0",
    "gn:admin4_code":"12068320.0",
    "gn:asciiname":"Seehof",
    "gn:country_code":"DE",
    "gn:dem":40,
    "gn:feature_class":"P",
    "gn:feature_code":"PPL",
    "gn:name":"Seehof",
    "gn:population":0,
    "gn:timezone":"Europe/Berlin",
    "iso:country":"DE",
    "name:als_x_preferred":[
        "Seehof"
    ],
    "name:ceb_x_preferred":[
        "Seehof"
    ],
    "name:deu_x_preferred":[
        "Seehof"
    ],
    "name:epo_x_preferred":[
        "Seehof"
    ],
    "name:eus_x_preferred":[
        "Seehof"
    ],
    "name:ita_x_preferred":[
        "Seehof"
    ],
    "name:lav_x_preferred":[
        "Seehof"
    ],
    "name:nld_x_preferred":[
        "Seehof"
    ],
    "name:pol_x_preferred":[
        "Seehof"
    ],
    "name:swe_x_preferred":[
        "Seehof"
    ],
    "name:vol_x_preferred":[
        "Seehof"
    ],
    "wof:name":"Seehof",
    "wof:placetype":"neighbourhood"
},
  "geometry": {"coordinates":[12.84714,52.87426],"type":"Point"}
}