{
  "type": "Feature",
  "properties": {
    "gn:admin1_code":"5",
    "gn:admin2_code":"66.0",
    "gn:admin3_code":"6634.0",
    "gn:admin4_code":"6634001.0",
    "gn:asciiname":"Gombeth",
    "gn:country_code":"DE",
    "gn:dem":174,
    "gn:feature_class":"P",
    "gn:feature_code":"PPL",
    "gn:name":"Gombeth",
    "gn:population":0,
    "gn:timezone":"Europe/Berlin",
    "iso:country":"DE",
    "name:deu_x_preferred":[
        "Gombeth"
    ],
    "wof:name":"Gombeth",
    "wof:placetype":"neighbourhood"
},
  "geometry": {"coordinates":[9.291,51.06439],"type":"Point"}
}