{
  "type": "Feature",
  "properties": {
    "gn:admin1_code":"5.0",
    "gn:admin2_code":"64.0",
    "gn:admin3_code":"6438.0",
    "gn:admin4_code":"6438008.0",
    "gn:asciiname":"Dietesheim",
    "gn:country_code":"DE",
    "gn:dem":105,
    "gn:feature_class":"P",
    "gn:feature_code":"PPL",
    "gn:name":"Dietesheim",
    "gn:population":0,
    "gn:timezone":"Europe/Berlin",
    "iso:country":"DE",
    "wof:name":"Dietesheim",
    "wof:placetype":"neighbourhood"
},
  "geometry": {"coordinates":[8.84494,50.12393],"type":"Point"}
}