{
  "type": "Feature",
  "properties": {
    "gn:admin1_code":"2.0",
    "gn:admin2_code":"092",
    "gn:admin3_code":"9279.0",
    "gn:admin4_code":"9279137.0",
    "gn:asciiname":"Wolfersdorf",
    "gn:country_code":"DE",
    "gn:dem":335,
    "gn:feature_class":"P",
    "gn:feature_code":"PPL",
    "gn:name":"Wolfersdorf",
    "gn:population":0,
    "gn:timezone":"Europe/Berlin",
    "iso:country":"DE",
    "name:ara_x_preferred":[
        "\u0641\u0648\u0644\u0641\u0631\u0633\u062f\u0648\u0631\u0641"
    ],
    "name:dan_x_preferred":[
        "Wolfersdorf"
    ],
    "name:deu_x_preferred":[
        "Wolfersdorf"
    ],
    "name:epo_x_preferred":[
        "Wolfersdorf"
    ],
    "name:eus_x_preferred":[
        "Wolfersdorf"
    ],
    "name:fas_x_preferred":[
        "\u0648\u0644\u0641\u0631\u0633\u062f\u0648\u0631\u0641"
    ],
    "name:fra_x_preferred":[
        "Wolfersdorf"
    ],
    "name:hun_x_preferred":[
        "Wolfersdorf"
    ],
    "name:hye_x_preferred":[
        "\u054e\u0578\u056c\u0586\u0565\u0580\u057d\u0564\u0578\u0580\u0586"
    ],
    "name:ind_x_preferred":[
        "Wolfersdorf"
    ],
    "name:ita_x_preferred":[
        "Wolfersdorf"
    ],
    "name:kaz_x_preferred":[
        "\u0412\u043e\u043b\u044c\u0444\u0435\u0440\u0441\u0434\u043e\u0440\u0444"
    ],
    "name:kir_x_preferred":[
        "\u0412\u043e\u043b\u044c\u0444\u0435\u0440\u0441\u0434\u043e\u0440\u0444"
    ],
    "name:lmo_x_preferred":[
        "Wolfersdorf"
    ],
    "name:msa_x_preferred":[
        "Wolfersdorf"
    ],
    "name:nld_x_preferred":[
        "Wolfersdorf"
    ],
    "name:pol_x_preferred":[
        "Wolfersdorf"
    ],
    "name:por_x_preferred":[
        "Wolfersdorf"
    ],
    "name:ron_x_preferred":[
        "Wolfersdorf"
    ],
    "name:rus_x_preferred":[
        "\u0412\u043e\u043b\u044c\u0444\u0435\u0440\u0441\u0434\u043e\u0440\u0444"
    ],
    "name:spa_x_preferred":[
        "Wolfersdorf"
    ],
    "name:srp_x_preferred":[
        "\u0412\u043e\u043b\u0444\u0435\u0440\u0441\u0434\u043e\u0440\u0444"
    ],
    "name:ukr_x_preferred":[
        "\u0412\u043e\u043b\u044c\u0444\u0435\u0440\u0441\u0434\u043e\u0440\u0444"
    ],
    "name:uzb_x_preferred":[
        "Wolfersdorf"
    ],
    "name:vie_x_preferred":[
        "Wolfersdorf"
    ],
    "name:vol_x_preferred":[
        "Wolfersdorf"
    ],
    "name:war_x_preferred":[
        "Wolfersdorf"
    ],
    "name:zho_x_preferred":[
        "\u6c83\u5c14\u5f17\u65af\u591a\u592b"
    ],
    "wof:name":"Wolfersdorf",
    "wof:placetype":"neighbourhood"
},
  "geometry": {"coordinates":[12.74963,48.76843],"type":"Point"}
}