{
  "type": "Feature",
  "properties": {
    "gn:admin1_code":"6",
    "gn:admin2_code":"0.0",
    "gn:admin3_code":"3252.0",
    "gn:admin4_code":"3252007.0",
    "gn:asciiname":"Wahrendahl",
    "gn:country_code":"DE",
    "gn:dem":153,
    "gn:feature_class":"P",
    "gn:feature_code":"PPL",
    "gn:name":"Wahrendahl",
    "gn:population":0,
    "gn:timezone":"Europe/Berlin",
    "iso:country":"DE",
    "wof:name":"Wahrendahl",
    "wof:placetype":"neighbourhood"
},
  "geometry": {"coordinates":[9.2097,52.11447],"type":"Point"}
}