{
  "type": "Feature",
  "properties": {
    "gn:admin1_code":"11",
    "gn:admin2_code":"0.0",
    "gn:admin3_code":"12070.0",
    "gn:admin4_code":"12070280.0",
    "gn:asciiname":"Buddenhagen",
    "gn:country_code":"DE",
    "gn:dem":96,
    "gn:feature_class":"P",
    "gn:feature_code":"PPL",
    "gn:name":"Buddenhagen",
    "gn:population":0,
    "gn:timezone":"Europe/Berlin",
    "iso:country":"DE",
    "name:ceb_x_preferred":[
        "Buddenhagen"
    ],
    "name:deu_x_preferred":[
        "Buddenhagen"
    ],
    "name:epo_x_preferred":[
        "Buddenhagen"
    ],
    "name:fas_x_preferred":[
        "\u0628\u0648\u062f\u0646\u0647\u0627\u06af\u0646"
    ],
    "name:ita_x_preferred":[
        "Buddenhagen"
    ],
    "name:nld_x_preferred":[
        "Buddenhagen"
    ],
    "name:pol_x_preferred":[
        "Buddenhagen"
    ],
    "name:ron_x_preferred":[
        "Buddenhagen"
    ],
    "name:rus_x_preferred":[
        "\u0411\u0443\u0434\u0434\u0435\u043d\u0445\u0430\u0433\u0435\u043d"
    ],
    "name:srp_x_preferred":[
        "\u0411\u0443\u0434\u0435\u043d\u0445\u0430\u0433\u0435\u043d"
    ],
    "name:uzb_x_preferred":[
        "Buddenhagen"
    ],
    "name:vie_x_preferred":[
        "Buddenhagen"
    ],
    "name:vol_x_preferred":[
        "Buddenhagen"
    ],
    "name:war_x_preferred":[
        "Buddenhagen"
    ],
    "wof:name":"Buddenhagen",
    "wof:placetype":"neighbourhood"
},
  "geometry": {"coordinates":[12.3052,53.30913],"type":"Point"}
}