{
  "type": "Feature",
  "properties": {
    "gn:country":"DE",
    "gn:fcode":"PPLX",
    "gn:population":343,
    "iso:country":"DE",
    "qs_pg:aaroncc":"DE",
    "qs_pg:gn_country":"DE",
    "qs_pg:gn_fcode":"PPLX",
    "qs_pg:gn_pop":343,
    "qs_pg:name":"Sankt Annen-Neufeld",
    "qs_pg:photos_9r":0,
    "qs_pg:photos_sr":0,
    "qs_pg:pop_sr":2,
    "qs_pg:qs_pg_placetype":"neighbourhood",
    "wof:name":"Sankt Annen-Neufeld",
    "wof:placetype":"neighbourhood",
    "wof:population":343
},
  "geometry": {"coordinates":[9.08333,54.35],"type":"Point"}
}