{
  "type": "Feature",
  "properties": {
    "gn:admin1_code":"12.0",
    "gn:admin2_code":"00",
    "gn:admin3_code":"13074.0",
    "gn:admin4_code":"13074076.0",
    "gn:asciiname":"Zarnewenz",
    "gn:country_code":"DE",
    "gn:dem":15,
    "gn:feature_class":"P",
    "gn:feature_code":"PPL",
    "gn:name":"Zarnewenz",
    "gn:population":0,
    "gn:timezone":"Europe/Berlin",
    "iso:country":"DE",
    "name:und_x_variant":[
        "Zarnewenz-Hof",
        "Zarnewenz"
    ],
    "wof:name":"Zarnewenz",
    "wof:placetype":"neighbourhood"
},
  "geometry": {"coordinates":[10.91447,53.89209],"type":"Point"}
}