{
  "type": "Feature",
  "properties": {
    "gn:admin1_code":"2",
    "gn:admin2_code":"91.0",
    "gn:admin3_code":"9187.0",
    "gn:admin4_code":"9187168.0",
    "gn:asciiname":"Ratzing",
    "gn:country_code":"DE",
    "gn:dem":669,
    "gn:feature_class":"P",
    "gn:feature_code":"PPL",
    "gn:name":"Ratzing",
    "gn:population":0,
    "gn:timezone":"Europe/Berlin",
    "iso:country":"DE",
    "wof:name":"Ratzing",
    "wof:placetype":"neighbourhood"
},
  "geometry": {"coordinates":[12.29619,47.87315],"type":"Point"}
}