{
  "type": "Feature",
  "properties": {
    "gn:admin1_code":"2.0",
    "gn:admin2_code":"093",
    "gn:admin3_code":"9362.0",
    "gn:admin4_code":"9362000.0",
    "gn:asciiname":"Ziegetsdorf",
    "gn:country_code":"DE",
    "gn:dem":412,
    "gn:feature_class":"P",
    "gn:feature_code":"PPL",
    "gn:name":"Ziegetsdorf",
    "gn:population":0,
    "gn:timezone":"Europe/Berlin",
    "iso:country":"DE",
    "wof:name":"Ziegetsdorf",
    "wof:placetype":"neighbourhood"
},
  "geometry": {"coordinates":[12.07264,48.99554000000001],"type":"Point"}
}