{
  "type": "Feature",
  "properties": {
    "gn:admin1_code":"1",
    "gn:admin2_code":"84.0",
    "gn:admin3_code":"8425.0",
    "gn:admin4_code":"8425008.0",
    "gn:asciiname":"Hofstett-Emerbuch",
    "gn:country_code":"DE",
    "gn:dem":672,
    "gn:feature_class":"P",
    "gn:feature_code":"PPL",
    "gn:name":"Hofstett-Emerbuch",
    "gn:population":0,
    "gn:timezone":"Europe/Berlin",
    "iso:country":"DE",
    "wof:name":"Hofstett-Emerbuch",
    "wof:placetype":"neighbourhood"
},
  "geometry": {"coordinates":[9.91485,48.58156],"type":"Point"}
}