{
  "type": "Feature",
  "properties": {
    "gn:admin1_code":"2",
    "gn:admin2_code":"91.0",
    "gn:admin3_code":"9187.0",
    "gn:admin4_code":"9187114.0",
    "gn:asciiname":"Innerwald",
    "gn:country_code":"DE",
    "gn:dem":729,
    "gn:feature_class":"P",
    "gn:feature_code":"PPL",
    "gn:name":"Innerwald",
    "gn:population":0,
    "gn:timezone":"Europe/Berlin",
    "iso:country":"DE",
    "wof:name":"Innerwald",
    "wof:placetype":"locality"
},
  "geometry": {"coordinates":[12.28181,47.71317],"type":"Point"}
}