{
  "type": "Feature",
  "properties": {
    "gn:admin1_code":"5.0",
    "gn:admin2_code":"064",
    "gn:admin3_code":"6434.0",
    "gn:admin4_code":"6434013.0",
    "gn:asciiname":"Winden",
    "gn:country_code":"DE",
    "gn:dem":225,
    "gn:feature_class":"P",
    "gn:feature_code":"PPL",
    "gn:name":"Winden",
    "gn:population":0,
    "gn:timezone":"Europe/Berlin",
    "iso:country":"DE",
    "name:ceb_x_preferred":[
        "Winden"
    ],
    "name:deu_x_preferred":[
        "Winden"
    ],
    "name:epo_x_preferred":[
        "Winden"
    ],
    "name:fra_x_preferred":[
        "Winden"
    ],
    "name:ita_x_preferred":[
        "Winden"
    ],
    "name:nld_x_preferred":[
        "Winden"
    ],
    "name:pol_x_preferred":[
        "Winden"
    ],
    "name:rus_x_preferred":[
        "\u0412\u0438\u043d\u0434\u0435\u043d"
    ],
    "name:srp_x_preferred":[
        "\u0412\u0438\u043d\u0434\u0438"
    ],
    "name:swe_x_preferred":[
        "Winden"
    ],
    "wof:name":"Winden",
    "wof:placetype":"neighbourhood"
},
  "geometry": {"coordinates":[8.39149,50.38138],"type":"Point"}
}