{
  "type": "Feature",
  "properties": {
    "gn:admin1_code":"7",
    "gn:admin2_code":"53.0",
    "gn:admin3_code":"5370.0",
    "gn:admin4_code":"5370040.0",
    "gn:asciiname":"Dorp",
    "gn:country_code":"DE",
    "gn:dem":70,
    "gn:feature_class":"P",
    "gn:feature_code":"PPL",
    "gn:name":"Dorp",
    "gn:population":0,
    "gn:timezone":"Europe/Berlin",
    "iso:country":"DE",
    "name:afr_x_preferred":[
        "Dorp"
    ],
    "name:deu_x_preferred":[
        "Dorp"
    ],
    "name:fra_x_preferred":[
        "Dorp"
    ],
    "name:nds_x_preferred":[
        "Dorp"
    ],
    "name:nld_x_preferred":[
        "Dorp"
    ],
    "wof:name":"Dorp",
    "wof:placetype":"neighbourhood"
},
  "geometry": {"coordinates":[6.28308,51.14879000000001],"type":"Point"}
}