{
  "type": "Feature",
  "properties": {
    "gn:admin1_code":"11",
    "gn:admin2_code":"0.0",
    "gn:admin3_code":"12066.0",
    "gn:admin4_code":"12066285.0",
    "gn:asciiname":"Herrnmuehle",
    "gn:country_code":"DE",
    "gn:dem":130,
    "gn:feature_class":"P",
    "gn:feature_code":"PPL",
    "gn:name":"Herrnm\u00fchle",
    "gn:population":0,
    "gn:timezone":"Europe/Berlin",
    "iso:country":"DE",
    "wof:name":"Herrnmuehle",
    "wof:placetype":"neighbourhood"
},
  "geometry": {"coordinates":[13.88782,51.55412000000001],"type":"Point"}
}