{
  "type": "Feature",
  "properties": {
    "gn:admin1_code":"13",
    "gn:admin2_code":"0.0",
    "gn:admin3_code":"14523.0",
    "gn:admin4_code":"14523430.0",
    "gn:asciiname":"Hartmannsgruen",
    "gn:country_code":"DE",
    "gn:dem":444,
    "gn:feature_class":"P",
    "gn:feature_code":"PPL",
    "gn:name":"Hartmannsgr\u00fcn",
    "gn:population":0,
    "gn:timezone":"Europe/Berlin",
    "iso:country":"DE",
    "wof:name":"Hartmannsgruen",
    "wof:placetype":"neighbourhood"
},
  "geometry": {"coordinates":[12.29209,50.56021],"type":"Point"}
}