{
  "type": "Feature",
  "properties": {
    "gn:admin1_code":"6",
    "gn:admin2_code":"0.0",
    "gn:admin3_code":"3251.0",
    "gn:admin4_code":"3251013.0",
    "gn:asciiname":"Cornau",
    "gn:cc2":"DE",
    "gn:country_code":"DE",
    "gn:dem":35,
    "gn:feature_class":"P",
    "gn:feature_code":"PPL",
    "gn:name":"Cornau",
    "gn:population":0,
    "gn:timezone":"Europe/Berlin",
    "iso:country":"DE",
    "name:und_x_variant":[
        "Kornau"
    ],
    "wof:name":"Cornau",
    "wof:placetype":"neighbourhood"
},
  "geometry": {"coordinates":[8.45467,52.67014],"type":"Point"}
}