{
  "type": "Feature",
  "properties": {
    "gn:admin1_code":"15",
    "gn:admin2_code":"0.0",
    "gn:admin3_code":"16075.0",
    "gn:admin4_code":"16075097.0",
    "gn:asciiname":"Seibis",
    "gn:country_code":"DE",
    "gn:dem":548,
    "gn:feature_class":"P",
    "gn:feature_code":"PPL",
    "gn:name":"Seibis",
    "gn:population":0,
    "gn:timezone":"Europe/Berlin",
    "iso:country":"DE",
    "wof:name":"Seibis",
    "wof:placetype":"neighbourhood"
},
  "geometry": {"coordinates":[11.639,50.39872],"type":"Point"}
}