{
  "type": "Feature",
  "properties": {
    "iso:country":"DE",
    "wof:name":"Oberpoyritz",
    "wof:placetype":"neighbourhood"
},
  "geometry": {"coordinates":[13.89587718569953,51.00329550506097],"type":"Point"}
}