{
  "type": "Feature",
  "properties": {
    "gn:admin1_code":"2",
    "gn:admin2_code":"97.0",
    "gn:admin3_code":"9779.0",
    "gn:admin4_code":"9779147.0",
    "gn:asciiname":"Hochstadt",
    "gn:country_code":"DE",
    "gn:dem":464,
    "gn:feature_class":"P",
    "gn:feature_code":"PPL",
    "gn:name":"Hochstadt",
    "gn:population":0,
    "gn:timezone":"Europe/Berlin",
    "iso:country":"DE",
    "name:ceb_x_preferred":[
        "Hochstadt"
    ],
    "name:deu_x_preferred":[
        "Hochstadt"
    ],
    "name:epo_x_preferred":[
        "Hochstadt"
    ],
    "name:fra_x_preferred":[
        "Hochstadt"
    ],
    "name:ita_x_preferred":[
        "Hochstadt"
    ],
    "name:nld_x_preferred":[
        "Hochstadt"
    ],
    "name:pol_x_preferred":[
        "Hochstadt"
    ],
    "name:swe_x_preferred":[
        "Hochstadt"
    ],
    "wof:name":"Hochstadt",
    "wof:placetype":"neighbourhood"
},
  "geometry": {"coordinates":[10.50254,48.99785],"type":"Point"}
}