{
  "type": "Feature",
  "properties": {
    "gn:country":"DE",
    "gn:fcode":"PPL",
    "gn:population":0,
    "iso:country":"DE",
    "name:ceb_x_preferred":[
        "Nu\u00dfdorf"
    ],
    "name:deu_x_preferred":[
        "Nu\u00dfdorf"
    ],
    "name:epo_x_preferred":[
        "Nu\u00dfdorf"
    ],
    "name:fra_x_preferred":[
        "Nu\u00dfdorf"
    ],
    "name:ita_x_preferred":[
        "Nu\u00dfdorf"
    ],
    "name:kaz_x_preferred":[
        "\u041d\u0443\u0441\u0434\u043e\u0440\u0444"
    ],
    "name:nds_x_preferred":[
        "Nu\u00dfdorf"
    ],
    "name:nld_x_preferred":[
        "Nu\u00dfdorf"
    ],
    "name:pol_x_preferred":[
        "Nu\u00dfdorf"
    ],
    "name:ron_x_preferred":[
        "Nu\u00dfdorf"
    ],
    "name:rus_x_preferred":[
        "\u041d\u0443\u0441\u0434\u043e\u0440\u0444"
    ],
    "name:srp_x_preferred":[
        "\u041d\u0443\u0441\u0434\u043e\u0440\u0444"
    ],
    "name:swe_x_preferred":[
        "Nu\u00dfdorf"
    ],
    "name:ukr_x_preferred":[
        "\u041d\u0443\u0441\u0434\u043e\u0440\u0444"
    ],
    "name:zho_x_preferred":[
        "\u52aa\u65af\u591a\u592b"
    ],
    "qs_pg:aaroncc":"DE",
    "qs_pg:gn_country":"DE",
    "qs_pg:gn_fcode":"PPL",
    "qs_pg:gn_pop":0,
    "qs_pg:name":"Nu\u00dfdorf",
    "qs_pg:name_adm0":"Deutschland",
    "qs_pg:name_adm1":"Baden-W\u00fcrttemberg",
    "qs_pg:photos":58,
    "qs_pg:photos_1k":12,
    "qs_pg:photos_9k":1,
    "qs_pg:photos_9r":2,
    "qs_pg:photos_all":58,
    "qs_pg:photos_sr":2,
    "qs_pg:pop_sr":0,
    "qs_pg:qs_pg_placetype":"locality",
    "qs_pg:qs_pg_placetype_gp":"Town",
    "qs_pg:woe_adm0":23424829,
    "woe:adm0_id":23424829,
    "woe:name_adm0":"Deutschland",
    "woe:name_adm1":"Baden-W\u00fcrttemberg",
    "woe:placetype":"Town",
    "wof:name":"Nu\u00dfdorf",
    "wof:placetype":"neighbourhood"
},
  "geometry": {"coordinates":[9.19865,47.75289],"type":"Point"}
}