{
  "type": "Feature",
  "properties": {
    "gn:admin1_code":"2",
    "gn:admin2_code":"94.0",
    "gn:admin3_code":"9474.0",
    "gn:admin4_code":"9474129.0",
    "gn:asciiname":"Kohlstein",
    "gn:country_code":"DE",
    "gn:dem":436,
    "gn:feature_class":"P",
    "gn:feature_code":"PPL",
    "gn:name":"Kohlstein",
    "gn:population":0,
    "gn:timezone":"Europe/Berlin",
    "iso:country":"DE",
    "wof:name":"Kohlstein",
    "wof:placetype":"neighbourhood"
},
  "geometry": {"coordinates":[11.34647,49.7893],"type":"Point"}
}