{
  "type": "Feature",
  "properties": {
    "gn:admin1_code":"2.0",
    "gn:admin2_code":"91.0",
    "gn:admin3_code":"9163.0",
    "gn:admin4_code":"9163000.0",
    "gn:asciiname":"Aising",
    "gn:country_code":"DE",
    "gn:dem":459,
    "gn:feature_class":"P",
    "gn:feature_code":"PPL",
    "gn:name":"Aising",
    "gn:population":0,
    "gn:timezone":"Europe/Berlin",
    "iso:country":"DE",
    "wof:name":"Aising",
    "wof:placetype":"neighbourhood"
},
  "geometry": {"coordinates":[12.10599,47.82923],"type":"Point"}
}