{
  "type": "Feature",
  "properties": {
    "gn:admin1_code":"2.0",
    "gn:admin2_code":"92.0",
    "gn:admin3_code":"9278.0",
    "gn:admin4_code":"9278187.0",
    "gn:asciiname":"Amosried",
    "gn:country_code":"DE",
    "gn:dem":402,
    "gn:feature_class":"P",
    "gn:feature_code":"PPL",
    "gn:name":"Amosried",
    "gn:population":0,
    "gn:timezone":"Europe/Berlin",
    "iso:country":"DE",
    "wof:name":"Amosried",
    "wof:placetype":"neighbourhood"
},
  "geometry": {"coordinates":[12.84981,48.90694000000001],"type":"Point"}
}