{
  "type": "Feature",
  "properties": {
    "gn:admin1_code":"10",
    "gn:admin2_code":"0.0",
    "gn:admin3_code":"1055.0",
    "gn:admin4_code":"1055001.0",
    "gn:asciiname":"Schwienkuhlen",
    "gn:country_code":"DE",
    "gn:dem":47,
    "gn:feature_class":"P",
    "gn:feature_code":"PPL",
    "gn:name":"Schwienkuhlen",
    "gn:population":0,
    "gn:timezone":"Europe/Berlin",
    "iso:country":"DE",
    "wof:name":"Schwienkuhlen",
    "wof:placetype":"neighbourhood"
},
  "geometry": {"coordinates":[10.58274,54.06389],"type":"Point"}
}