{
  "type": "Feature",
  "properties": {
    "iso:country":"DE",
    "name:deu_x_preferred":[
        "Gro\u00df-Buchholz"
    ],
    "wof:name":"Gross-Buchholz",
    "wof:placetype":"neighbourhood"
},
  "geometry": {"coordinates":[9.80393228681951,52.39603508778255],"type":"Point"}
}