{
  "type": "Feature",
  "properties": {
    "gn:admin1_code":"7.0",
    "gn:admin2_code":"59.0",
    "gn:admin3_code":"5962.0",
    "gn:admin4_code":"5962024.0",
    "gn:asciiname":"Ahm",
    "gn:country_code":"DE",
    "gn:dem":198,
    "gn:feature_class":"P",
    "gn:feature_code":"PPL",
    "gn:name":"Ahm",
    "gn:population":0,
    "gn:timezone":"Europe/Berlin",
    "iso:country":"DE",
    "wof:name":"Ahm",
    "wof:placetype":"neighbourhood"
},
  "geometry": {"coordinates":[7.59767,51.35446],"type":"Point"}
}