{
  "type": "Feature",
  "properties": {
    "gn:admin1_code":"2",
    "gn:admin2_code":"94.0",
    "gn:admin3_code":"9475.0",
    "gn:admin4_code":"9475156.0",
    "gn:asciiname":"Holle",
    "gn:country_code":"DE",
    "gn:dem":491,
    "gn:feature_class":"P",
    "gn:feature_code":"PPL",
    "gn:name":"H\u00f6lle",
    "gn:population":0,
    "gn:timezone":"Europe/Berlin",
    "iso:country":"DE",
    "name:dan_x_preferred":[
        "Holle"
    ],
    "name:deu_x_preferred":[
        "Holle"
    ],
    "name:epo_x_preferred":[
        "Holle"
    ],
    "name:est_x_preferred":[
        "Holle"
    ],
    "name:eus_x_preferred":[
        "Holle"
    ],
    "name:fra_x_preferred":[
        "Holle"
    ],
    "name:hun_x_preferred":[
        "Holle"
    ],
    "name:ita_x_preferred":[
        "Holle"
    ],
    "name:kaz_x_preferred":[
        "\u0425\u043e\u043b\u043b\u0435"
    ],
    "name:kir_x_preferred":[
        "\u0425\u043e\u043b\u043b\u0435"
    ],
    "name:lat_x_preferred":[
        "Holle"
    ],
    "name:mkd_x_preferred":[
        "\u0425\u043e\u043b\u0435"
    ],
    "name:msa_x_preferred":[
        "Holle"
    ],
    "name:nld_x_preferred":[
        "Holle"
    ],
    "name:pol_x_preferred":[
        "Holle"
    ],
    "name:por_x_preferred":[
        "Holle"
    ],
    "name:ron_x_preferred":[
        "Holle"
    ],
    "name:rus_x_preferred":[
        "\u0425\u043e\u043b\u043b\u0435"
    ],
    "name:spa_x_preferred":[
        "Holle"
    ],
    "name:srp_x_preferred":[
        "\u0425\u043e\u043b\u0435"
    ],
    "name:ukr_x_preferred":[
        "\u0413\u043e\u043b\u043b\u0435"
    ],
    "name:uzb_x_preferred":[
        "Holle"
    ],
    "name:vie_x_preferred":[
        "Holle"
    ],
    "name:vol_x_preferred":[
        "Holle"
    ],
    "name:war_x_preferred":[
        "Holle"
    ],
    "name:zho_x_preferred":[
        "\u970d\u52d2"
    ],
    "wof:name":"Holle",
    "wof:placetype":"neighbourhood"
},
  "geometry": {"coordinates":[11.69025,50.36719],"type":"Point"}
}