{
  "type": "Feature",
  "properties": {
    "gn:admin1_code":"2",
    "gn:admin2_code":"94.0",
    "gn:admin3_code":"9475.0",
    "gn:admin4_code":"9475156.0",
    "gn:asciiname":"Holle",
    "gn:country_code":"DE",
    "gn:dem":491,
    "gn:feature_class":"P",
    "gn:feature_code":"PPL",
    "gn:name":"H\u00f6lle",
    "gn:population":0,
    "gn:timezone":"Europe/Berlin",
    "iso:country":"DE",
    "wof:name":"Holle",
    "wof:placetype":"neighbourhood"
},
  "geometry": {"coordinates":[11.69025,50.36719],"type":"Point"}
}