{
  "type": "Feature",
  "properties": {
    "gn:admin1_code":"6",
    "gn:admin2_code":"0.0",
    "gn:admin3_code":"3252.0",
    "gn:admin4_code":"3252006.0",
    "gn:asciiname":"Holtensen",
    "gn:country_code":"DE",
    "gn:dem":190,
    "gn:feature_class":"P",
    "gn:feature_code":"PPL",
    "gn:name":"Holtensen",
    "gn:population":0,
    "gn:timezone":"Europe/Berlin",
    "iso:country":"DE",
    "name:deu_x_preferred":[
        "Holtensen"
    ],
    "wof:name":"Holtensen",
    "wof:placetype":"neighbourhood"
},
  "geometry": {"coordinates":[9.37752,52.14213],"type":"Point"}
}