{
  "type": "Feature",
  "properties": {
    "gn:admin1_code":"6",
    "gn:admin2_code":"0.0",
    "gn:admin3_code":"3358.0",
    "gn:admin4_code":"3358019.0",
    "gn:asciiname":"Bult",
    "gn:country_code":"DE",
    "gn:dem":54,
    "gn:feature_class":"P",
    "gn:feature_code":"PPL",
    "gn:name":"Bult",
    "gn:population":0,
    "gn:timezone":"Europe/Berlin",
    "iso:country":"DE",
    "name:bug_x_preferred":[
        "Bult"
    ],
    "name:cat_x_preferred":[
        "Bult"
    ],
    "name:ceb_x_preferred":[
        "Bult"
    ],
    "name:deu_x_preferred":[
        "Bult"
    ],
    "name:eus_x_preferred":[
        "Bult"
    ],
    "name:fra_x_preferred":[
        "Bult"
    ],
    "name:hun_x_preferred":[
        "Bult"
    ],
    "name:ind_x_preferred":[
        "Bult"
    ],
    "name:ita_x_preferred":[
        "Bult"
    ],
    "name:kaz_x_preferred":[
        "\u0411\u044e"
    ],
    "name:mlg_x_preferred":[
        "Bult"
    ],
    "name:msa_x_preferred":[
        "Bult"
    ],
    "name:nld_x_preferred":[
        "Bult"
    ],
    "name:oci_x_preferred":[
        "Bult"
    ],
    "name:pms_x_preferred":[
        "Bult"
    ],
    "name:pol_x_preferred":[
        "Bult"
    ],
    "name:por_x_preferred":[
        "Bult"
    ],
    "name:slk_x_preferred":[
        "Bult"
    ],
    "name:spa_x_preferred":[
        "Bult"
    ],
    "name:srp_x_preferred":[
        "\u0411\u0438"
    ],
    "name:swe_x_preferred":[
        "Bult"
    ],
    "name:ukr_x_preferred":[
        "\u0411\u044e"
    ],
    "name:uzb_x_preferred":[
        "Bult"
    ],
    "name:vie_x_preferred":[
        "Bult"
    ],
    "name:vol_x_preferred":[
        "Bult"
    ],
    "name:war_x_preferred":[
        "Bult"
    ],
    "name:zho_x_preferred":[
        "\u6bd4\u5c14"
    ],
    "wof:name":"Bult",
    "wof:placetype":"neighbourhood"
},
  "geometry": {"coordinates":[9.68197,53.11486],"type":"Point"}
}