{
  "type": "Feature",
  "properties": {
    "gn:admin1_code":"12",
    "gn:admin2_code":"0.0",
    "gn:admin3_code":"13072.0",
    "gn:admin4_code":"13072004.0",
    "gn:asciiname":"Kaemmerich",
    "gn:country_code":"DE",
    "gn:dem":31,
    "gn:feature_class":"P",
    "gn:feature_code":"PPL",
    "gn:name":"K\u00e4mmerich",
    "gn:population":0,
    "gn:timezone":"Europe/Berlin",
    "iso:country":"DE",
    "wof:name":"Kaemmerich",
    "wof:placetype":"neighbourhood"
},
  "geometry": {"coordinates":[12.77135,53.87728000000001],"type":"Point"}
}