{
  "type": "Feature",
  "properties": {
    "gn:admin1_code":"2.0",
    "gn:admin2_code":"92.0",
    "gn:admin3_code":"9277.0",
    "gn:admin4_code":"9277122.0",
    "gn:asciiname":"Braunsberg",
    "gn:country_code":"DE",
    "gn:dem":464,
    "gn:feature_class":"P",
    "gn:feature_code":"PPL",
    "gn:name":"Braunsberg",
    "gn:population":0,
    "gn:timezone":"Europe/Berlin",
    "iso:country":"DE",
    "wof:name":"Braunsberg",
    "wof:placetype":"neighbourhood"
},
  "geometry": {"coordinates":[12.67503,48.34455],"type":"Point"}
}