{
  "type": "Feature",
  "properties": {
    "gn:admin1_code":"6.0",
    "gn:admin2_code":"00",
    "gn:admin3_code":"3452.0",
    "gn:admin4_code":"3452001.0",
    "gn:asciiname":"Westerfeld",
    "gn:country_code":"DE",
    "gn:dem":6,
    "gn:feature_class":"P",
    "gn:feature_code":"PPL",
    "gn:name":"Westerfeld",
    "gn:population":0,
    "gn:timezone":"Europe/Berlin",
    "iso:country":"DE",
    "wof:name":"Westerfeld",
    "wof:placetype":"neighbourhood"
},
  "geometry": {"coordinates":[7.47251,53.45596],"type":"Point"}
}