{
  "type": "Feature",
  "properties": {
    "gn:admin1_code":"2.0",
    "gn:admin2_code":"092",
    "gn:admin3_code":"9276.0",
    "gn:admin4_code":"9276128.0",
    "gn:asciiname":"Winklern",
    "gn:country_code":"DE",
    "gn:dem":570,
    "gn:feature_class":"P",
    "gn:feature_code":"PPL",
    "gn:name":"Winklern",
    "gn:population":0,
    "gn:timezone":"Europe/Berlin",
    "iso:country":"DE",
    "name:ceb_x_preferred":[
        "Winklern"
    ],
    "name:deu_x_preferred":[
        "Winklern"
    ],
    "name:epo_x_preferred":[
        "Winklern"
    ],
    "name:fas_x_preferred":[
        "\u0648\u06cc\u0646\u06a9\u0644\u0631\u0646"
    ],
    "name:fra_x_preferred":[
        "Winklern"
    ],
    "name:fur_x_preferred":[
        "Winklern"
    ],
    "name:hun_x_preferred":[
        "Winklern"
    ],
    "name:ita_x_preferred":[
        "Winklern"
    ],
    "name:kaz_x_preferred":[
        "\u0412\u0438\u043d\u043a\u043b\u0435\u0440\u043d"
    ],
    "name:nld_x_preferred":[
        "Winklern"
    ],
    "name:pol_x_preferred":[
        "Winklern"
    ],
    "name:por_x_preferred":[
        "Winklern"
    ],
    "name:rus_x_preferred":[
        "\u0412\u0438\u043d\u043a\u043b\u0435\u0440\u043d"
    ],
    "name:slk_x_preferred":[
        "Winklern"
    ],
    "name:spa_x_preferred":[
        "Winklern"
    ],
    "name:swe_x_preferred":[
        "Winklern"
    ],
    "name:uzb_x_preferred":[
        "Winklern"
    ],
    "name:vie_x_preferred":[
        "Winklern"
    ],
    "name:vol_x_preferred":[
        "Winklern"
    ],
    "name:war_x_preferred":[
        "Winklern"
    ],
    "name:zho_x_preferred":[
        "\u6e29\u514b\u52d2\u6069"
    ],
    "wof:name":"Winklern",
    "wof:placetype":"neighbourhood"
},
  "geometry": {"coordinates":[12.88834,49.00759],"type":"Point"}
}