{
  "type": "Feature",
  "properties": {
    "gn:admin1_code":"2.0",
    "gn:admin2_code":"092",
    "gn:admin3_code":"9276.0",
    "gn:admin4_code":"9276128.0",
    "gn:asciiname":"Winklern",
    "gn:country_code":"DE",
    "gn:dem":570,
    "gn:feature_class":"P",
    "gn:feature_code":"PPL",
    "gn:name":"Winklern",
    "gn:population":0,
    "gn:timezone":"Europe/Berlin",
    "iso:country":"DE",
    "wof:name":"Winklern",
    "wof:placetype":"neighbourhood"
},
  "geometry": {"coordinates":[12.88834,49.00759],"type":"Point"}
}