{
  "type": "Feature",
  "properties": {
    "gn:gn_country":"DE",
    "gn:gn_fcode":"PPLA4",
    "gn:gn_pop":117,
    "gn:population":117,
    "iso:country":"DE",
    "name:baq_x_preferred":[
        "Philippsheim"
    ],
    "name:chi_x_preferred":[
        "\u83f2\u5229\u666e\u65af\u6d77\u59c6"
    ],
    "name:dut_x_preferred":[
        "Philippsheim"
    ],
    "name:eng_x_preferred":[
        "Philippsheim"
    ],
    "name:epo_x_preferred":[
        "Philippsheim"
    ],
    "name:fre_x_preferred":[
        "Philippsheim"
    ],
    "name:ger_x_preferred":[
        "Philippsheim"
    ],
    "name:hun_x_preferred":[
        "Philippsheim"
    ],
    "name:ita_x_preferred":[
        "Philippsheim"
    ],
    "name:jpn_x_preferred":[
        "\u30d5\u30a3\u30ea\u30c3\u30d7\u30b9\u30cf\u30a4\u30e0"
    ],
    "name:may_x_preferred":[
        "Philippsheim"
    ],
    "name:per_x_preferred":[
        "\u0641\u06cc\u0644\u06cc\u067e\u0633\u0647\u0627\u06cc\u0645"
    ],
    "name:pol_x_preferred":[
        "Philippsheim"
    ],
    "name:por_x_preferred":[
        "Philippsheim"
    ],
    "name:rum_x_preferred":[
        "Philippsheim"
    ],
    "name:rus_x_preferred":[
        "\u0424\u0438\u043b\u0438\u043f\u0441\u0445\u0430\u0439\u043c"
    ],
    "name:srp_x_preferred":[
        "\u0424\u0438\u043b\u0438\u043f\u0441\u0445\u0430\u0458\u043c"
    ],
    "name:ukr_x_preferred":[
        "\u0424\u0456\u043b\u0456\u043f\u043f\u0441\u0433\u0430\u0439\u043c"
    ],
    "name:unk_x_variant":[
        "Phillipsheim"
    ],
    "name:uzb_x_preferred":[
        "Philippsheim"
    ],
    "name:vie_x_preferred":[
        "Philippsheim"
    ],
    "name:vol_x_preferred":[
        "Philippsheim"
    ],
    "name:war_x_preferred":[
        "Philippsheim"
    ],
    "qs_pg:aaroncc":"DE",
    "qs_pg:gn_country":"DE",
    "qs_pg:gn_fcode":"PPLA4",
    "qs_pg:gn_pop":117,
    "qs_pg:name":"Philippsheim",
    "qs_pg:photos_9r":0,
    "qs_pg:photos_sr":0,
    "qs_pg:pop_sr":1,
    "qs_pg:qs_pg_placetype":"locality",
    "wof:name":"Philippsheim",
    "wof:placetype":"locality",
    "wof:population":117
},
  "geometry": {"coordinates":[6.63333,49.95],"type":"Point"}
}