{
  "type": "Feature",
  "properties": {
    "gn:admin1_code":"7.0",
    "gn:admin2_code":"53.0",
    "gn:admin3_code":"5370.0",
    "gn:admin4_code":"5370024.0",
    "gn:asciiname":"Millen",
    "gn:country_code":"DE",
    "gn:dem":43,
    "gn:feature_class":"P",
    "gn:feature_code":"PPL",
    "gn:name":"Millen",
    "gn:population":0,
    "gn:timezone":"Europe/Berlin",
    "iso:country":"DE",
    "name:ceb_x_preferred":[
        "Millen"
    ],
    "name:deu_x_preferred":[
        "Millen"
    ],
    "name:fra_x_preferred":[
        "Millen"
    ],
    "name:ita_x_preferred":[
        "Millen"
    ],
    "name:nds_x_preferred":[
        "Millen"
    ],
    "name:nld_x_preferred":[
        "Millen"
    ],
    "name:pol_x_preferred":[
        "Millen"
    ],
    "name:scn_x_preferred":[
        "Millen"
    ],
    "name:swe_x_preferred":[
        "Millen"
    ],
    "name:vol_x_preferred":[
        "Millen"
    ],
    "wof:name":"Millen",
    "wof:placetype":"neighbourhood"
},
  "geometry": {"coordinates":[5.88206,51.02304],"type":"Point"}
}