{
  "type": "Feature",
  "properties": {
    "gn:admin1_code":"6",
    "gn:admin2_code":"0.0",
    "gn:admin3_code":"3459.0",
    "gn:admin4_code":"3459011.0",
    "gn:asciiname":"Kerkamp",
    "gn:country_code":"DE",
    "gn:dem":45,
    "gn:feature_class":"P",
    "gn:feature_code":"PPL",
    "gn:name":"Kerkamp",
    "gn:population":0,
    "gn:timezone":"Europe/Berlin",
    "iso:country":"DE",
    "wof:name":"Kerkamp",
    "wof:placetype":"neighbourhood"
},
  "geometry": {"coordinates":[7.65867,52.56059000000001],"type":"Point"}
}