{
  "type": "Feature",
  "properties": {
    "gn:admin1_code":"7",
    "gn:admin2_code":"51.0",
    "gn:admin3_code":"5154.0",
    "gn:admin4_code":"5154052.0",
    "gn:asciiname":"Niederdorf",
    "gn:country_code":"DE",
    "gn:dem":30,
    "gn:feature_class":"P",
    "gn:feature_code":"PPL",
    "gn:name":"Niederdorf",
    "gn:population":0,
    "gn:timezone":"Europe/Berlin",
    "iso:country":"DE",
    "name:als_x_preferred":[
        "Niederdorf"
    ],
    "name:ceb_x_preferred":[
        "Niederdorf"
    ],
    "name:deu_x_preferred":[
        "Niederdorf"
    ],
    "name:epo_x_preferred":[
        "Niederdorf"
    ],
    "name:fra_x_preferred":[
        "Niederdorf"
    ],
    "name:hun_x_preferred":[
        "Niederdorf"
    ],
    "name:ita_x_preferred":[
        "Niederdorf"
    ],
    "name:nld_x_preferred":[
        "Niederdorf"
    ],
    "name:pol_x_preferred":[
        "Niederdorf"
    ],
    "name:rus_x_preferred":[
        "\u041d\u0438\u0434\u0435\u0440\u0434\u043e\u0440\u0444"
    ],
    "name:swe_x_preferred":[
        "Niederdorf"
    ],
    "name:vol_x_preferred":[
        "Niederdorf"
    ],
    "wof:name":"Niederdorf",
    "wof:placetype":"neighbourhood"
},
  "geometry": {"coordinates":[6.24277,51.38744000000001],"type":"Point"}
}