{
  "type": "Feature",
  "properties": {
    "gn:gn_country":"DE",
    "gn:gn_fcode":"PPLA4",
    "gn:gn_pop":957,
    "gn:population":957,
    "iso:country":"DE",
    "qs_pg:aaroncc":"DE",
    "qs_pg:gn_country":"DE",
    "qs_pg:gn_fcode":"PPLA4",
    "qs_pg:gn_pop":957,
    "qs_pg:name":"Havetoftloit",
    "qs_pg:photos_9r":0,
    "qs_pg:photos_sr":0,
    "qs_pg:pop_sr":2,
    "qs_pg:qs_pg_placetype":"locality",
    "wof:name":"Havetoftloit",
    "wof:placetype":"neighbourhood",
    "wof:population":957
},
  "geometry": {"coordinates":[9.56667,54.66667],"type":"Point"}
}