{
  "type": "Feature",
  "properties": {
    "gn:country":"DE",
    "gn:fcode":"PPLA4",
    "gn:population":957,
    "iso:country":"DE",
    "name:ceb_x_preferred":[
        "Havetoftloit"
    ],
    "name:dan_x_preferred":[
        "Havetoftl\u00f8jt"
    ],
    "name:deu_x_preferred":[
        "Havetoftloit"
    ],
    "name:epo_x_preferred":[
        "Havetoftloit"
    ],
    "name:fas_x_preferred":[
        "\u0647\u0627\u0641\u062a\u0648\u0641\u062a\u0644\u0648\u06cc\u062a"
    ],
    "name:ita_x_preferred":[
        "Havetoftloit"
    ],
    "name:kaz_x_preferred":[
        "\u0425\u0430\u0444\u0435\u0442\u043e\u0444\u0442\u043b\u043e\u0439\u0442"
    ],
    "name:kir_x_preferred":[
        "\u0425\u0430\u0444\u0435\u0442\u043e\u0444\u0442\u043b\u043e\u0439\u0442"
    ],
    "name:mkd_x_preferred":[
        "\u0425\u0430\u0444\u0435\u0442\u043e\u0444\u0442\u043b\u043e\u0458\u0442"
    ],
    "name:msa_x_preferred":[
        "Havetoftloit"
    ],
    "name:nld_x_preferred":[
        "Havetoftloit"
    ],
    "name:pol_x_preferred":[
        "Havetoftloit"
    ],
    "name:por_x_preferred":[
        "Havetoftloit"
    ],
    "name:ron_x_preferred":[
        "Havetoftloit"
    ],
    "name:rus_x_preferred":[
        "\u0425\u0430\u0432\u0435\u0442\u043e\u0444\u0442\u043b\u043e\u0439\u0442"
    ],
    "name:spa_x_preferred":[
        "Havetoftloit"
    ],
    "name:srp_x_preferred":[
        "\u0425\u0430\u0432\u0435\u0442\u043e\u0444\u0442\u043b\u043e\u0438\u0442"
    ],
    "name:tur_x_preferred":[
        "Havetoftloit"
    ],
    "name:uzb_x_preferred":[
        "Havetoftloit"
    ],
    "name:vie_x_preferred":[
        "Havetoftloit"
    ],
    "name:vol_x_preferred":[
        "Havetoftloit"
    ],
    "name:war_x_preferred":[
        "Havetoftloit"
    ],
    "name:zho_x_preferred":[
        "\u54c8\u8d39\u6258\u592b\u7279\u6d1b\u4f0a\u7279"
    ],
    "qs_pg:aaroncc":"DE",
    "qs_pg:gn_country":"DE",
    "qs_pg:gn_fcode":"PPLA4",
    "qs_pg:gn_pop":957,
    "qs_pg:name":"Havetoftloit",
    "qs_pg:photos_9r":0,
    "qs_pg:photos_sr":0,
    "qs_pg:pop_sr":2,
    "qs_pg:qs_pg_placetype":"locality",
    "wof:name":"Havetoftloit",
    "wof:placetype":"neighbourhood",
    "wof:population":957
},
  "geometry": {"coordinates":[9.56667,54.66667],"type":"Point"}
}