{
  "type": "Feature",
  "properties": {
    "gn:admin1_code":"2",
    "gn:admin2_code":"92.0",
    "gn:admin3_code":"9275.0",
    "gn:admin4_code":"9275154.0",
    "gn:asciiname":"Schwanham",
    "gn:country_code":"DE",
    "gn:dem":336,
    "gn:feature_class":"P",
    "gn:feature_code":"PPL",
    "gn:name":"Schwanham",
    "gn:population":0,
    "gn:timezone":"Europe/Berlin",
    "iso:country":"DE",
    "wof:name":"Schwanham",
    "wof:placetype":"neighbourhood"
},
  "geometry": {"coordinates":[13.12472,48.58084],"type":"Point"}
}