{
  "type": "Feature",
  "properties": {
    "gn:admin1_code":"10",
    "gn:admin2_code":"0.0",
    "gn:admin3_code":"1054.0",
    "gn:admin4_code":"1054088.0",
    "gn:asciiname":"Deezbuell",
    "gn:country_code":"DE",
    "gn:dem":2,
    "gn:feature_class":"P",
    "gn:feature_code":"PPL",
    "gn:name":"Deezb\u00fcll",
    "gn:population":0,
    "gn:timezone":"Europe/Berlin",
    "iso:country":"DE",
    "name:frr_x_preferred":[
        "Deesbel"
    ],
    "wof:name":"Deezbuell",
    "wof:placetype":"neighbourhood"
},
  "geometry": {"coordinates":[8.82116,54.77806999999999],"type":"Point"}
}