{
  "type": "Feature",
  "properties": {
    "gn:admin1_code":"7.0",
    "gn:admin2_code":"059",
    "gn:admin3_code":"5954.0",
    "gn:admin4_code":"5954024.0",
    "gn:asciiname":"Weuste",
    "gn:country_code":"DE",
    "gn:dem":223,
    "gn:feature_class":"P",
    "gn:feature_code":"PPL",
    "gn:name":"Weuste",
    "gn:population":0,
    "gn:timezone":"Europe/Berlin",
    "iso:country":"DE",
    "wof:name":"Weuste",
    "wof:placetype":"neighbourhood"
},
  "geometry": {"coordinates":[7.28433,51.25449],"type":"Point"}
}