{
  "type": "Feature",
  "properties": {
    "gn:admin1_code":"2.0",
    "gn:admin2_code":"094",
    "gn:admin3_code":"9471.0",
    "gn:admin4_code":"9471119.0",
    "gn:asciiname":"Zuckshut",
    "gn:country_code":"DE",
    "gn:dem":277,
    "gn:feature_class":"P",
    "gn:feature_code":"PPL",
    "gn:name":"Z\u00fcckshut",
    "gn:population":0,
    "gn:timezone":"Europe/Berlin",
    "iso:country":"DE",
    "wof:name":"Zuckshut",
    "wof:placetype":"neighbourhood"
},
  "geometry": {"coordinates":[10.92616,49.96691],"type":"Point"}
}