{
  "type": "Feature",
  "properties": {
    "gn:country":"DE",
    "gn:fcode":"PPL",
    "gn:population":0,
    "iso:country":"DE",
    "name:deu_x_preferred":[
        "Below"
    ],
    "name:fra_x_preferred":[
        "Below"
    ],
    "name:ita_x_preferred":[
        "Below"
    ],
    "name:swe_x_preferred":[
        "Below"
    ],
    "qs_pg:aaroncc":"DE",
    "qs_pg:gn_country":"DE",
    "qs_pg:gn_fcode":"PPL",
    "qs_pg:gn_pop":0,
    "qs_pg:name":"Below",
    "qs_pg:name_adm0":"Deutschland",
    "qs_pg:name_adm1":"Mecklenburg-Vorpommern",
    "qs_pg:photos":8,
    "qs_pg:photos_1k":2,
    "qs_pg:photos_9k":1,
    "qs_pg:photos_9r":1,
    "qs_pg:photos_all":8,
    "qs_pg:photos_sr":1,
    "qs_pg:pop_sr":0,
    "qs_pg:qs_pg_placetype":"locality",
    "qs_pg:qs_pg_placetype_gp":"Town",
    "qs_pg:woe_adm0":23424829,
    "woe:adm0_id":23424829,
    "woe:name_adm0":"Deutschland",
    "woe:name_adm1":"Mecklenburg-Vorpommern",
    "woe:placetype":"Town",
    "wof:name":"Below",
    "wof:placetype":"neighbourhood"
},
  "geometry": {"coordinates":[13.01708,53.29795],"type":"Point"}
}