{
  "type": "Feature",
  "properties": {
    "iso:country":"DE",
    "name:deu_x_preferred":[
        "Lechhausen"
    ],
    "qs:gn_local":0,
    "qs:local_max":3569,
    "qs:local_sum":10994,
    "qs:localhoods":12,
    "qs:name":"Lechhausen",
    "qs:name_adm0":"Deutschland",
    "qs:name_adm1":"Bayern",
    "qs:name_adm2":"Stadtkreis Augsburg",
    "qs:name_lau":"Hochzoll-S\u00fcd",
    "qs:name_local":"Augsburg",
    "qs:photo_max":268,
    "qs:photo_sum":2404,
    "qs:placetype":"Suburb",
    "qs:quad_count":81,
    "qs:woe_adm0":23424829,
    "qs:woe_adm1":2345482,
    "qs:woe_adm2":20071092,
    "qs:woe_lau":26821838,
    "qs:woe_local":636080,
    "qs:woe_ver":"7.10.0",
    "wof:lang":[
        "ger"
    ],
    "wof:name":"Lechhausen",
    "wof:placetype":"neighbourhood"
},
  "geometry": {"coordinates":[10.899072,48.369335],"type":"Point"}
}