{
  "type": "Feature",
  "properties": {
    "gn:admin1_code":"12.0",
    "gn:admin2_code":"00",
    "gn:admin3_code":"13072.0",
    "gn:admin4_code":"13072038.0",
    "gn:asciiname":"Wotrum",
    "gn:country_code":"DE",
    "gn:dem":35,
    "gn:feature_class":"P",
    "gn:feature_code":"PPL",
    "gn:name":"Wotrum",
    "gn:population":0,
    "gn:timezone":"Europe/Berlin",
    "iso:country":"DE",
    "wof:name":"Wotrum",
    "wof:placetype":"neighbourhood"
},
  "geometry": {"coordinates":[12.46589,53.78777],"type":"Point"}
}