{
  "type": "Feature",
  "properties": {
    "gn:admin1_code":"2",
    "gn:admin2_code":"92.0",
    "gn:admin3_code":"9278.0",
    "gn:admin4_code":"9278179.0",
    "gn:asciiname":"Oberweinberg",
    "gn:country_code":"DE",
    "gn:dem":492,
    "gn:feature_class":"P",
    "gn:feature_code":"PPL",
    "gn:name":"Oberweinberg",
    "gn:population":0,
    "gn:timezone":"Europe/Berlin",
    "iso:country":"DE",
    "wof:name":"Oberweinberg",
    "wof:placetype":"neighbourhood"
},
  "geometry": {"coordinates":[12.67286,49.03825],"type":"Point"}
}