{
  "type": "Feature",
  "properties": {
    "gn:admin1_code":"2",
    "gn:admin2_code":"96.0",
    "gn:admin3_code":"9675.0",
    "gn:admin4_code":"9675127.0",
    "gn:asciiname":"Ebersbrunn",
    "gn:country_code":"DE",
    "gn:dem":389,
    "gn:feature_class":"P",
    "gn:feature_code":"PPL",
    "gn:name":"Ebersbrunn",
    "gn:population":0,
    "gn:timezone":"Europe/Berlin",
    "iso:country":"DE",
    "wof:name":"Ebersbrunn",
    "wof:placetype":"neighbourhood"
},
  "geometry": {"coordinates":[10.45979,49.80287],"type":"Point"}
}