{
  "type": "Feature",
  "properties": {
    "gn:admin1_code":"2",
    "gn:admin2_code":"93.0",
    "gn:admin3_code":"9373.0",
    "gn:admin4_code":"9373146.0",
    "gn:asciiname":"Wangen",
    "gn:country_code":"DE",
    "gn:dem":451,
    "gn:feature_class":"P",
    "gn:feature_code":"PPL",
    "gn:name":"Wangen",
    "gn:population":0,
    "gn:timezone":"Europe/Berlin",
    "iso:country":"DE",
    "name:als_x_preferred":[
        "Wangen"
    ],
    "name:cat_x_preferred":[
        "Wangen"
    ],
    "name:ceb_x_preferred":[
        "Wangen"
    ],
    "name:deu_x_preferred":[
        "Wangen"
    ],
    "name:epo_x_preferred":[
        "Wangen"
    ],
    "name:fra_x_preferred":[
        "Wangen"
    ],
    "name:ita_x_preferred":[
        "Wangen"
    ],
    "name:kir_x_preferred":[
        "\u0412\u0430\u043d\u0433\u0435\u043d"
    ],
    "name:lmo_x_preferred":[
        "Wangen"
    ],
    "name:nld_x_preferred":[
        "Wangen"
    ],
    "name:pms_x_preferred":[
        "Wangen"
    ],
    "name:pol_x_preferred":[
        "Wangen"
    ],
    "name:por_x_preferred":[
        "Wangen"
    ],
    "name:ron_x_preferred":[
        "Wangen"
    ],
    "name:rus_x_preferred":[
        "\u0412\u0430\u043d\u0433\u0435\u043d"
    ],
    "name:spa_x_preferred":[
        "Wangen"
    ],
    "name:srp_x_preferred":[
        "\u0412\u0430\u043d\u0433\u0435\u043d"
    ],
    "name:swe_x_preferred":[
        "Wangen"
    ],
    "name:vol_x_preferred":[
        "Wangen"
    ],
    "wof:name":"Wangen",
    "wof:placetype":"neighbourhood"
},
  "geometry": {"coordinates":[11.46878,49.19141],"type":"Point"}
}