{
  "type": "Feature",
  "properties": {
    "gn:admin1_code":"2",
    "gn:admin2_code":"93.0",
    "gn:admin3_code":"9374.0",
    "gn:admin4_code":"9374123.0",
    "gn:asciiname":"Losslberg",
    "gn:country_code":"DE",
    "gn:dem":644,
    "gn:feature_class":"P",
    "gn:feature_code":"PPL",
    "gn:name":"L\u00f6\u00dflberg",
    "gn:population":0,
    "gn:timezone":"Europe/Berlin",
    "iso:country":"DE",
    "wof:name":"Losslberg",
    "wof:placetype":"neighbourhood"
},
  "geometry": {"coordinates":[12.45511,49.69787],"type":"Point"}
}