{
  "type": "Feature",
  "properties": {
    "gn:admin1_code":"1",
    "gn:admin2_code":"81.0",
    "gn:admin3_code":"8136.0",
    "gn:admin4_code":"8136019.0",
    "gn:asciiname":"Erpfental",
    "gn:country_code":"DE",
    "gn:dem":472,
    "gn:feature_class":"P",
    "gn:feature_code":"PPL",
    "gn:name":"Erpfental",
    "gn:population":0,
    "gn:timezone":"Europe/Berlin",
    "iso:country":"DE",
    "wof:name":"Erpfental",
    "wof:placetype":"neighbourhood"
},
  "geometry": {"coordinates":[10.2337,48.95433],"type":"Point"}
}