{
  "type": "Feature",
  "properties": {
    "gn:admin1_code":"2.0",
    "gn:admin2_code":"097",
    "gn:admin3_code":"9771.0",
    "gn:admin4_code":"9771155.0",
    "gn:asciiname":"Willprechtszell",
    "gn:country_code":"DE",
    "gn:dem":474,
    "gn:feature_class":"P",
    "gn:feature_code":"PPL",
    "gn:name":"Willprechtszell",
    "gn:population":0,
    "gn:timezone":"Europe/Berlin",
    "iso:country":"DE",
    "wof:name":"Willprechtszell",
    "wof:placetype":"neighbourhood"
},
  "geometry": {"coordinates":[10.99461,48.53392],"type":"Point"}
}