{
  "type": "Feature",
  "properties": {
    "gn:admin1_code":"15.0",
    "gn:admin2_code":"0.0",
    "gn:admin3_code":"16077.0",
    "gn:admin4_code":"16077022.0",
    "gn:asciiname":"Altpoderschau",
    "gn:country_code":"DE",
    "gn:dem":220,
    "gn:feature_class":"P",
    "gn:feature_code":"PPL",
    "gn:name":"Altpoderschau",
    "gn:population":0,
    "gn:timezone":"Europe/Berlin",
    "iso:country":"DE",
    "wof:name":"Altpoderschau",
    "wof:placetype":"neighbourhood"
},
  "geometry": {"coordinates":[12.31233,51.01932],"type":"Point"}
}