{
  "type": "Feature",
  "properties": {
    "gn:admin1_code":"6",
    "gn:admin2_code":"0.0",
    "gn:admin3_code":"3457.0",
    "gn:admin4_code":"3457020.0",
    "gn:asciiname":"Kleinsander",
    "gn:country_code":"DE",
    "gn:dem":7,
    "gn:feature_class":"P",
    "gn:feature_code":"PPL",
    "gn:name":"Kleinsander",
    "gn:population":0,
    "gn:timezone":"Europe/Berlin",
    "iso:country":"DE",
    "wof:name":"Kleinsander",
    "wof:placetype":"neighbourhood"
},
  "geometry": {"coordinates":[7.79495,53.29089000000001],"type":"Point"}
}