{
  "type": "Feature",
  "properties": {
    "iso:country":"DE",
    "name:deu_x_preferred":[
        "N\u00e4chstebreck-West"
    ],
    "wof:name":"Naechstebreck-West",
    "wof:placetype":"neighbourhood"
},
  "geometry": {"coordinates":[7.21800615361746,51.29779469492533],"type":"Point"}
}