{
  "type": "Feature",
  "properties": {
    "iso:country":"DE",
    "name:ger_x_variant":[
        "Wasserturm"
    ],
    "wof:name":"Am Wasserturm",
    "wof:placetype":"neighbourhood"
},
  "geometry": {"coordinates":[6.42584888259045,51.20161166728816],"type":"Point"}
}