{
  "type": "Feature",
  "properties": {
    "gn:admin1_code":"6.0",
    "gn:admin2_code":"0.0",
    "gn:admin3_code":"3356.0",
    "gn:admin4_code":"3356007.0",
    "gn:asciiname":"Myhle",
    "gn:country_code":"DE",
    "gn:dem":15,
    "gn:feature_class":"P",
    "gn:feature_code":"PPL",
    "gn:name":"Myhle",
    "gn:population":0,
    "gn:timezone":"Europe/Berlin",
    "iso:country":"DE",
    "wof:name":"Myhle",
    "wof:placetype":"neighbourhood"
},
  "geometry": {"coordinates":[8.81706,53.26297],"type":"Point"}
}