{
  "type": "Feature",
  "properties": {
    "gn:admin1_code":"2",
    "gn:admin2_code":"97.0",
    "gn:admin3_code":"9777.0",
    "gn:admin4_code":"9777176.0",
    "gn:asciiname":"Eschers",
    "gn:country_code":"DE",
    "gn:dem":892,
    "gn:feature_class":"P",
    "gn:feature_code":"PPL",
    "gn:name":"Eschers",
    "gn:population":0,
    "gn:timezone":"Europe/Berlin",
    "iso:country":"DE",
    "wof:name":"Eschers",
    "wof:placetype":"neighbourhood"
},
  "geometry": {"coordinates":[10.38002,47.84563],"type":"Point"}
}