{
  "type": "Feature",
  "properties": {
    "gn:admin1_code":"13.0",
    "gn:admin2_code":"0.0",
    "gn:admin3_code":"14626.0",
    "gn:admin4_code":"14626450.0",
    "gn:asciiname":"Borda",
    "gn:country_code":"DE",
    "gn:dem":230,
    "gn:feature_class":"P",
    "gn:feature_code":"PPL",
    "gn:name":"Borda",
    "gn:population":0,
    "gn:timezone":"Europe/Berlin",
    "iso:country":"DE",
    "name:arg_x_preferred":[
        "Borda"
    ],
    "name:ceb_x_preferred":[
        "Borda"
    ],
    "name:deu_x_preferred":[
        "Borda"
    ],
    "name:fas_x_preferred":[
        "\u0628\u0631\u062f\u0627"
    ],
    "name:fra_x_preferred":[
        "Borda"
    ],
    "name:ita_x_preferred":[
        "Borda"
    ],
    "name:nds_x_preferred":[
        "Borda"
    ],
    "name:pol_x_preferred":[
        "Borda"
    ],
    "name:por_x_preferred":[
        "Borda"
    ],
    "name:spa_x_preferred":[
        "Borda"
    ],
    "name:srp_x_preferred":[
        "Borda"
    ],
    "name:swe_x_preferred":[
        "Borda"
    ],
    "wof:name":"Borda",
    "wof:placetype":"neighbourhood"
},
  "geometry": {"coordinates":[14.772,51.15224],"type":"Point"}
}