{
  "type": "Feature",
  "properties": {
    "iso:country":"DE",
    "name:deu_x_preferred":[
        "H\u00f6henhaus"
    ],
    "wof:name":"Hoehenhaus",
    "wof:placetype":"neighbourhood"
},
  "geometry": {"coordinates":[7.03612726628034,50.98548385261904],"type":"Point"}
}