{
  "type": "Feature",
  "properties": {
    "gn:admin1_code":"7",
    "gn:admin2_code":"53.0",
    "gn:admin3_code":"5382.0",
    "gn:admin4_code":"5382064.0",
    "gn:asciiname":"Duenstekoven",
    "gn:country_code":"DE",
    "gn:dem":141,
    "gn:feature_class":"P",
    "gn:feature_code":"PPL",
    "gn:name":"D\u00fcnstekoven",
    "gn:population":0,
    "gn:timezone":"Europe/Berlin",
    "iso:country":"DE",
    "name:ceb_x_preferred":[
        "D\u00fcnstekoven"
    ],
    "name:deu_x_preferred":[
        "D\u00fcnstekoven"
    ],
    "name:fra_x_preferred":[
        "D\u00fcnstekoven"
    ],
    "wof:name":"Duenstekoven",
    "wof:placetype":"neighbourhood"
},
  "geometry": {"coordinates":[6.93272,50.69893],"type":"Point"}
}