{
  "type": "Feature",
  "properties": {
    "gn:admin1_code":"2",
    "gn:admin2_code":"91.0",
    "gn:admin3_code":"9190.0",
    "gn:admin4_code":"9190158.0",
    "gn:asciiname":"Schellschwang",
    "gn:country_code":"DE",
    "gn:dem":719,
    "gn:feature_class":"P",
    "gn:feature_code":"PPL",
    "gn:name":"Schellschwang",
    "gn:population":0,
    "gn:timezone":"Europe/Berlin",
    "iso:country":"DE",
    "wof:name":"Schellschwang",
    "wof:placetype":"neighbourhood"
},
  "geometry": {"coordinates":[11.01953,47.89748],"type":"Point"}
}