{
  "type": "Feature",
  "properties": {
    "gn:admin1_code":"9.0",
    "gn:admin2_code":"0.0",
    "gn:admin3_code":"10045.0",
    "gn:admin4_code":"10045114.0",
    "gn:asciiname":"Beeden",
    "gn:country_code":"DE",
    "gn:dem":241,
    "gn:feature_class":"P",
    "gn:feature_code":"PPL",
    "gn:name":"Beeden",
    "gn:population":0,
    "gn:timezone":"Europe/Berlin",
    "iso:country":"DE",
    "wof:name":"Beeden",
    "wof:placetype":"neighbourhood"
},
  "geometry": {"coordinates":[7.31226,49.30722],"type":"Point"}
}