{
  "type": "Feature",
  "properties": {
    "gn:admin1_code":"7",
    "gn:admin2_code":"51.0",
    "gn:admin3_code":"5158.0",
    "gn:admin4_code":"5158032.0",
    "gn:asciiname":"Hardenberg",
    "gn:country_code":"DE",
    "gn:dem":175,
    "gn:feature_class":"P",
    "gn:feature_code":"PPL",
    "gn:name":"Hardenberg",
    "gn:population":0,
    "gn:timezone":"Europe/Berlin",
    "iso:country":"DE",
    "name:ara_x_preferred":[
        "\u0647\u0627\u0631\u062f\u0646\u0628\u064a\u0631\u062e"
    ],
    "name:cat_x_preferred":[
        "Hardenberg"
    ],
    "name:ceb_x_preferred":[
        "Hardenberg"
    ],
    "name:ces_x_preferred":[
        "Hardenberg"
    ],
    "name:deu_x_preferred":[
        "Hardenberg"
    ],
    "name:epo_x_preferred":[
        "Hardenberg"
    ],
    "name:eus_x_preferred":[
        "Hardenberg"
    ],
    "name:fas_x_preferred":[
        "\u0647\u0627\u0631\u062f\u0646\u200c\u0628\u0631\u062e"
    ],
    "name:fra_x_preferred":[
        "Hardenberg"
    ],
    "name:gle_x_preferred":[
        "Hardenberg"
    ],
    "name:heb_x_preferred":[
        "\u05d4\u05d0\u05e8\u05d3\u05e0\u05d1\u05e8\u05da"
    ],
    "name:ind_x_preferred":[
        "Hardenberg"
    ],
    "name:ita_x_preferred":[
        "Hardenberg"
    ],
    "name:kor_x_preferred":[
        "\ud558\ub974\ub374\ubca0\ub974\ud750"
    ],
    "name:lim_x_preferred":[
        "Hardenberg"
    ],
    "name:msa_x_preferred":[
        "Hardenberg"
    ],
    "name:nld_x_preferred":[
        "Hardenberg"
    ],
    "name:nno_x_preferred":[
        "Hardenberg"
    ],
    "name:pol_x_preferred":[
        "Hardenberg"
    ],
    "name:ron_x_preferred":[
        "Hardenberg"
    ],
    "name:sqi_x_preferred":[
        "Hardenberg"
    ],
    "name:stq_x_preferred":[
        "Hardenberg"
    ],
    "name:swe_x_preferred":[
        "Hardenberg"
    ],
    "name:tur_x_preferred":[
        "Hardenberg"
    ],
    "name:vie_x_preferred":[
        "Hardenberg"
    ],
    "name:vol_x_preferred":[
        "Hardenberg"
    ],
    "name:war_x_preferred":[
        "Hardenberg"
    ],
    "name:zho_x_preferred":[
        "\u54c8\u767b\u8c9d\u8d6b"
    ],
    "wof:name":"Hardenberg",
    "wof:placetype":"neighbourhood"
},
  "geometry": {"coordinates":[7.08333,51.31667],"type":"Point"}
}