{
  "type": "Feature",
  "properties": {
    "gn:admin1_code":"5",
    "gn:admin2_code":"66.0",
    "gn:admin3_code":"6633.0",
    "gn:admin4_code":"6633013.0",
    "gn:asciiname":"Huemme",
    "gn:country_code":"DE",
    "gn:dem":133,
    "gn:feature_class":"P",
    "gn:feature_code":"PPL",
    "gn:name":"H\u00fcmme",
    "gn:population":0,
    "gn:timezone":"Europe/Berlin",
    "iso:country":"DE",
    "wof:name":"Huemme",
    "wof:placetype":"neighbourhood"
},
  "geometry": {"coordinates":[9.40636,51.54335],"type":"Point"}
}