{
  "type": "Feature",
  "properties": {
    "gn:gn_country":"DE",
    "gn:gn_fcode":"PPLA4",
    "gn:gn_pop":736,
    "gn:population":736,
    "iso:country":"DE",
    "name:baq_x_preferred":[
        "Rumohr"
    ],
    "name:chi_x_preferred":[
        "\u9c81\u83ab\u5c14"
    ],
    "name:dan_x_preferred":[
        "Rumohr"
    ],
    "name:dut_x_preferred":[
        "Rumohr"
    ],
    "name:eng_x_preferred":[
        "Rumohr"
    ],
    "name:epo_x_preferred":[
        "Rumohr"
    ],
    "name:fre_x_preferred":[
        "Rumohr"
    ],
    "name:ger_x_preferred":[
        "Rumohr"
    ],
    "name:hun_x_preferred":[
        "Rumohr"
    ],
    "name:ita_x_preferred":[
        "Rumohr"
    ],
    "name:mac_x_preferred":[
        "\u0420\u0443\u043c\u043e\u0440"
    ],
    "name:may_x_preferred":[
        "Rumohr"
    ],
    "name:per_x_preferred":[
        "\u0631\u0648\u0645\u0648\u0647\u0631"
    ],
    "name:pol_x_preferred":[
        "Rumohr"
    ],
    "name:por_x_preferred":[
        "Rumohr"
    ],
    "name:rum_x_preferred":[
        "Rumohr"
    ],
    "name:rus_x_preferred":[
        "\u0420\u0443\u043c\u043e\u0440"
    ],
    "name:srp_x_preferred":[
        "\u0420\u0443\u043c\u043e\u0440"
    ],
    "name:tur_x_preferred":[
        "Rumohr"
    ],
    "name:ukr_x_preferred":[
        "\u0420\u0443\u043c\u043e\u0440"
    ],
    "name:uzb_x_preferred":[
        "Rumohr"
    ],
    "name:vie_x_preferred":[
        "Rumohr"
    ],
    "name:vol_x_preferred":[
        "Rumohr"
    ],
    "name:war_x_preferred":[
        "Rumohr"
    ],
    "qs_pg:aaroncc":"DE",
    "qs_pg:gn_country":"DE",
    "qs_pg:gn_fcode":"PPLA4",
    "qs_pg:gn_pop":736,
    "qs_pg:name":"Rumohr",
    "qs_pg:photos_9r":0,
    "qs_pg:photos_sr":0,
    "qs_pg:pop_sr":2,
    "qs_pg:qs_pg_placetype":"locality",
    "wof:name":"Rumohr",
    "wof:placetype":"locality",
    "wof:population":736
},
  "geometry": {"coordinates":[10.03333,54.25],"type":"Point"}
}