{
  "type": "Feature",
  "properties": {
    "gn:gn_country":"DE",
    "gn:gn_fcode":"PPL",
    "gn:gn_pop":6206,
    "gn:population":6206,
    "iso:country":"DE",
    "name:ara_x_preferred":[
        "\u062a\u0633\u0644-\u0625\u0645-\u0641\u064a\u0632\u0646\u062a\u0627\u0644"
    ],
    "name:fas_x_preferred":[
        "\u062a\u0633\u0644 \u062f\u0631 \u0648\u06cc\u0632\u0646\u062a\u0627\u0644"
    ],
    "name:kaz_x_preferred":[
        "\u0426\u0435\u043b\u043b\u044c"
    ],
    "name:rus_x_preferred":[
        "\u0426\u0435\u043b\u043b\u044c-\u0438\u043c-\u0412\u0438\u0437\u0435\u043d\u0442\u0430\u043b\u044c"
    ],
    "name:spa_x_preferred":[
        "Zell en el Valle del Wiese"
    ],
    "name:srp_x_preferred":[
        "\u0426\u0435\u043b \u0438\u043c \u0412\u0438\u0437\u0435\u043d\u0442\u0430\u043b"
    ],
    "name:ukr_x_preferred":[
        "\u0426\u0435\u043b\u043b\u044c-\u0456\u043c-\u0412\u0456\u0437\u0435\u043d\u0442\u0430\u043b\u044c"
    ],
    "name:zho_x_preferred":[
        "\u7ef4\u745f\u6cb3\u8c37\u7b56\u5c14"
    ],
    "qs_pg:aaroncc":"DE",
    "qs_pg:gn_country":"DE",
    "qs_pg:gn_fcode":"PPL",
    "qs_pg:gn_pop":6206,
    "qs_pg:name":"Zell im Wiesental",
    "qs_pg:name_adm0":"Deutschland",
    "qs_pg:name_adm1":"Baden-W\u00fcrttemberg",
    "qs_pg:photos":7,
    "qs_pg:photos_1k":1,
    "qs_pg:photos_9k":1,
    "qs_pg:photos_9r":1,
    "qs_pg:photos_all":7,
    "qs_pg:photos_sr":1,
    "qs_pg:pop_sr":5,
    "qs_pg:qs_pg_placetype":"locality",
    "qs_pg:qs_pg_placetype_gp":"Town",
    "qs_pg:woe_adm0":23424829,
    "woe:adm0_id":23424829,
    "woe:name_adm0":"Deutschland",
    "woe:name_adm1":"Baden-W\u00fcrttemberg",
    "woe:placetype":"Town",
    "wof:name":"Zell im Wiesental",
    "wof:placetype":"locality",
    "wof:population":6206
},
  "geometry": {"coordinates":[7.85248,47.70555],"type":"Point"}
}