{
  "type": "Feature",
  "properties": {
    "gn:admin1_code":"2.0",
    "gn:admin2_code":"091",
    "gn:admin3_code":"9176.0",
    "gn:admin4_code":"9176112.0",
    "gn:asciiname":"Winden",
    "gn:country_code":"DE",
    "gn:dem":521,
    "gn:feature_class":"P",
    "gn:feature_code":"PPL",
    "gn:name":"Winden",
    "gn:population":0,
    "gn:timezone":"Europe/Berlin",
    "iso:country":"DE",
    "wof:name":"Winden",
    "wof:placetype":"neighbourhood"
},
  "geometry": {"coordinates":[11.53411,48.94739000000001],"type":"Point"}
}