{
  "type": "Feature",
  "properties": {
    "gn:admin1_code":"1",
    "gn:admin2_code":"83.0",
    "gn:admin3_code":"8327.0",
    "gn:admin4_code":"8327057.0",
    "gn:asciiname":"Wehstetten",
    "gn:country_code":"DE",
    "gn:dem":802,
    "gn:feature_class":"P",
    "gn:feature_code":"PPL",
    "gn:name":"Wehstetten",
    "gn:population":0,
    "gn:timezone":"Europe/Berlin",
    "iso:country":"DE",
    "wof:name":"Wehstetten",
    "wof:placetype":"neighbourhood"
},
  "geometry": {"coordinates":[8.88216,47.96108],"type":"Point"}
}