{
  "type": "Feature",
  "properties": {
    "gn:admin1_code":"2",
    "gn:admin2_code":"93.0",
    "gn:admin3_code":"9376.0",
    "gn:admin4_code":"9376153.0",
    "gn:asciiname":"Dollnitz",
    "gn:country_code":"DE",
    "gn:dem":452,
    "gn:feature_class":"P",
    "gn:feature_code":"PPL",
    "gn:name":"D\u00f6llnitz",
    "gn:population":0,
    "gn:timezone":"Europe/Berlin",
    "iso:country":"DE",
    "wof:name":"Dollnitz",
    "wof:placetype":"neighbourhood"
},
  "geometry": {"coordinates":[12.1262,49.50122],"type":"Point"}
}