{
  "type": "Feature",
  "properties": {
    "gn:admin1_code":"6.0",
    "gn:admin2_code":"00",
    "gn:admin3_code":"3153.0",
    "gn:admin4_code":"3153002.0",
    "gn:asciiname":"Westerode",
    "gn:country_code":"DE",
    "gn:dem":207,
    "gn:feature_class":"P",
    "gn:feature_code":"PPL",
    "gn:name":"Westerode",
    "gn:population":0,
    "gn:timezone":"Europe/Berlin",
    "iso:country":"DE",
    "wof:name":"Westerode",
    "wof:placetype":"neighbourhood"
},
  "geometry": {"coordinates":[10.5619,51.90181],"type":"Point"}
}