{
  "type": "Feature",
  "properties": {
    "gn:admin1_code":"14",
    "gn:admin2_code":"0.0",
    "gn:admin3_code":"15081.0",
    "gn:admin4_code":"15081455.0",
    "gn:asciiname":"Jeebel",
    "gn:country_code":"DE",
    "gn:dem":26,
    "gn:feature_class":"P",
    "gn:feature_code":"PPL",
    "gn:name":"Jeebel",
    "gn:population":0,
    "gn:timezone":"Europe/Berlin",
    "iso:country":"DE",
    "wof:name":"Jeebel",
    "wof:placetype":"neighbourhood"
},
  "geometry": {"coordinates":[11.26456,52.86575],"type":"Point"}
}