{
  "type": "Feature",
  "properties": {
    "gn:admin1_code":"8",
    "gn:admin2_code":"0.0",
    "gn:admin3_code":"7140.0",
    "gn:admin4_code":"7140202.0",
    "gn:asciiname":"Steffenshof",
    "gn:country_code":"DE",
    "gn:dem":347,
    "gn:feature_class":"P",
    "gn:feature_code":"PPL",
    "gn:name":"Steffenshof",
    "gn:population":0,
    "gn:timezone":"Europe/Berlin",
    "iso:country":"DE",
    "wof:name":"Steffenshof",
    "wof:placetype":"neighbourhood"
},
  "geometry": {"coordinates":[7.44135,50.13366],"type":"Point"}
}