{
  "type": "Feature",
  "properties": {
    "gn:admin1_code":"7",
    "gn:admin2_code":"59.0",
    "gn:admin3_code":"5915.0",
    "gn:admin4_code":"5915000.0",
    "gn:asciiname":"Opsen",
    "gn:country_code":"DE",
    "gn:dem":94,
    "gn:feature_class":"P",
    "gn:feature_code":"PPLL",
    "gn:name":"Opsen",
    "gn:population":0,
    "gn:timezone":"Europe/Berlin",
    "iso:country":"DE",
    "wof:name":"Opsen",
    "wof:placetype":"neighbourhood"
},
  "geometry": {"coordinates":[7.83947,51.60997],"type":"Point"}
}