{
  "type": "Feature",
  "properties": {
    "gn:admin1_code":"2",
    "gn:admin2_code":"94.0",
    "gn:admin3_code":"9474.0",
    "gn:admin4_code":"9474173.0",
    "gn:asciiname":"Dachstadt",
    "gn:country_code":"DE",
    "gn:dem":380,
    "gn:feature_class":"P",
    "gn:feature_code":"PPL",
    "gn:name":"Dachstadt",
    "gn:population":0,
    "gn:timezone":"Europe/Berlin",
    "iso:country":"DE",
    "wof:name":"Dachstadt",
    "wof:placetype":"neighbourhood"
},
  "geometry": {"coordinates":[11.24687,49.63317],"type":"Point"}
}