{
  "type": "Feature",
  "properties": {
    "gn:admin1_code":"6",
    "gn:admin2_code":"0.0",
    "gn:admin3_code":"3358.0",
    "gn:admin4_code":"3358021.0",
    "gn:asciiname":"Loh",
    "gn:country_code":"DE",
    "gn:dem":65,
    "gn:feature_class":"P",
    "gn:feature_code":"PPL",
    "gn:name":"Loh",
    "gn:population":0,
    "gn:timezone":"Europe/Berlin",
    "iso:country":"DE",
    "name:ceb_x_preferred":[
        "Loh"
    ],
    "name:deu_x_preferred":[
        "Loh"
    ],
    "name:nds_x_preferred":[
        "Loh"
    ],
    "name:swe_x_preferred":[
        "Loh"
    ],
    "wof:name":"Loh",
    "wof:placetype":"neighbourhood"
},
  "geometry": {"coordinates":[9.83341,52.9596],"type":"Point"}
}