{
  "type": "Feature",
  "properties": {
    "gn:admin1_code":"5",
    "gn:admin2_code":"64.0",
    "gn:admin3_code":"6435.0",
    "gn:admin4_code":"6435027.0",
    "gn:asciiname":"Jossa",
    "gn:country_code":"DE",
    "gn:dem":223,
    "gn:feature_class":"P",
    "gn:feature_code":"PPL",
    "gn:name":"Jossa",
    "gn:population":0,
    "gn:timezone":"Europe/Berlin",
    "iso:country":"DE",
    "name:ceb_x_preferred":[
        "Jossa"
    ],
    "name:deu_x_preferred":[
        "Jossa"
    ],
    "name:ita_x_preferred":[
        "Jossa"
    ],
    "name:nld_x_preferred":[
        "Jossa"
    ],
    "name:rus_x_preferred":[
        "\u0419\u043e\u0441\u0441\u0430"
    ],
    "name:swe_x_preferred":[
        "Jossa"
    ],
    "wof:name":"Jossa",
    "wof:placetype":"neighbourhood"
},
  "geometry": {"coordinates":[9.59406,50.23931],"type":"Point"}
}