{
  "type": "Feature",
  "properties": {
    "gn:admin1_code":"15",
    "gn:admin2_code":"0.0",
    "gn:admin3_code":"16077.0",
    "gn:admin4_code":"16077001.0",
    "gn:asciiname":"Knau",
    "gn:country_code":"DE",
    "gn:dem":170,
    "gn:feature_class":"P",
    "gn:feature_code":"PPL",
    "gn:name":"Knau",
    "gn:population":0,
    "gn:timezone":"Europe/Berlin",
    "iso:country":"DE",
    "name:bak_x_preferred":[
        "\u041a\u043d\u0430\u0443"
    ],
    "name:ceb_x_preferred":[
        "Knau"
    ],
    "name:deu_x_preferred":[
        "Knau"
    ],
    "name:epo_x_preferred":[
        "Knau"
    ],
    "name:eus_x_preferred":[
        "Knau"
    ],
    "name:fas_x_preferred":[
        "\u06a9\u0646\u0627\u0648"
    ],
    "name:fra_x_preferred":[
        "Knau"
    ],
    "name:hun_x_preferred":[
        "Knau"
    ],
    "name:ita_x_preferred":[
        "Knau"
    ],
    "name:kaz_x_preferred":[
        "\u041a\u043d\u0430\u0443"
    ],
    "name:kir_x_preferred":[
        "\u041a\u043d\u0430\u0443"
    ],
    "name:mkd_x_preferred":[
        "\u041a\u043d\u0430\u0443"
    ],
    "name:msa_x_preferred":[
        "Knau"
    ],
    "name:nld_x_preferred":[
        "Knau"
    ],
    "name:pol_x_preferred":[
        "Knau"
    ],
    "name:por_x_preferred":[
        "Knau"
    ],
    "name:ron_x_preferred":[
        "Knau"
    ],
    "name:rus_x_preferred":[
        "\u041a\u043d\u0430\u0443"
    ],
    "name:spa_x_preferred":[
        "Knau"
    ],
    "name:srp_x_preferred":[
        "\u041a\u043d\u0430\u0443"
    ],
    "name:ukr_x_preferred":[
        "\u041a\u043d\u0430\u0443"
    ],
    "name:uzb_x_preferred":[
        "Knau"
    ],
    "name:vie_x_preferred":[
        "Knau"
    ],
    "name:vol_x_preferred":[
        "Knau"
    ],
    "name:war_x_preferred":[
        "Knau"
    ],
    "wof:name":"Knau",
    "wof:placetype":"neighbourhood"
},
  "geometry": {"coordinates":[12.43879,51.01923],"type":"Point"}
}