{
  "type": "Feature",
  "properties": {
    "gn:admin1_code":"14",
    "gn:admin2_code":"0.0",
    "gn:admin3_code":"15091.0",
    "gn:admin4_code":"15091145.0",
    "gn:asciiname":"Grabo",
    "gn:country_code":"DE",
    "gn:dem":72,
    "gn:feature_class":"P",
    "gn:feature_code":"PPL",
    "gn:name":"Grabo",
    "gn:population":0,
    "gn:timezone":"Europe/Berlin",
    "iso:country":"DE",
    "name:ceb_x_preferred":[
        "Grabo"
    ],
    "name:fra_x_preferred":[
        "Grabo"
    ],
    "name:ita_x_preferred":[
        "Grabo"
    ],
    "name:nld_x_preferred":[
        "Grabo"
    ],
    "name:swe_x_preferred":[
        "Grabo"
    ],
    "wof:name":"Grabo",
    "wof:placetype":"neighbourhood"
},
  "geometry": {"coordinates":[12.93642,51.77244],"type":"Point"}
}