{
  "type": "Feature",
  "properties": {
    "gn:admin1_code":"11",
    "gn:admin2_code":"0.0",
    "gn:admin3_code":"12060.0",
    "gn:admin4_code":"12060250.0",
    "gn:asciiname":"Friedrich-Wilhelmshof",
    "gn:cc2":"DE",
    "gn:country_code":"DE",
    "gn:dem":79,
    "gn:feature_class":"P",
    "gn:feature_code":"PPL",
    "gn:name":"Friedrich-Wilhelmshof",
    "gn:population":0,
    "gn:timezone":"Europe/Berlin",
    "iso:country":"DE",
    "name:und_x_variant":[
        "Friedrich-Wilhelm-Hof"
    ],
    "wof:name":"Friedrich-Wilhelmshof",
    "wof:placetype":"neighbourhood"
},
  "geometry": {"coordinates":[13.73497,52.71799],"type":"Point"}
}