{
  "type": "Feature",
  "properties": {
    "gn:admin1_code":"6",
    "gn:admin2_code":"0.0",
    "gn:admin3_code":"3357.0",
    "gn:admin4_code":"3357051.0",
    "gn:asciiname":"Rosebruch",
    "gn:country_code":"DE",
    "gn:dem":38,
    "gn:feature_class":"P",
    "gn:feature_code":"PPL",
    "gn:name":"Rosebruch",
    "gn:population":0,
    "gn:timezone":"Europe/Berlin",
    "iso:country":"DE",
    "wof:name":"Rosebruch",
    "wof:placetype":"neighbourhood"
},
  "geometry": {"coordinates":[9.57253,53.0439],"type":"Point"}
}