{
  "type": "Feature",
  "properties": {
    "gn:admin1_code":"1",
    "gn:admin2_code":"81.0",
    "gn:admin3_code":"8119.0",
    "gn:admin4_code":"8119084.0",
    "gn:asciiname":"Ekartsweiler",
    "gn:country_code":"DE",
    "gn:dem":534,
    "gn:feature_class":"P",
    "gn:feature_code":"PPL",
    "gn:name":"Ekartsweiler",
    "gn:population":0,
    "gn:timezone":"Europe/Berlin",
    "iso:country":"DE",
    "wof:name":"Ekartsweiler",
    "wof:placetype":"neighbourhood"
},
  "geometry": {"coordinates":[9.62645,48.90435],"type":"Point"}
}