{
  "type": "Feature",
  "properties": {
    "iso:country":"DE",
    "name:deu_x_preferred":[
        "Venn"
    ],
    "name:ita_x_preferred":[
        "Venn"
    ],
    "name:nds_x_preferred":[
        "Venn"
    ],
    "name:spa_x_preferred":[
        "Venn"
    ],
    "wof:name":"Venn",
    "wof:placetype":"neighbourhood"
},
  "geometry": {"coordinates":[6.38711061236693,51.20399585145387],"type":"Point"}
}