{
  "type": "Feature",
  "properties": {
    "gn:admin1_code":"7",
    "gn:admin2_code":"51.0",
    "gn:admin3_code":"5116.0",
    "gn:admin4_code":"5116000.0",
    "gn:asciiname":"Venn",
    "gn:country_code":"DE",
    "gn:dem":71,
    "gn:feature_class":"P",
    "gn:feature_code":"PPL",
    "gn:name":"Venn",
    "gn:population":0,
    "gn:timezone":"Europe/Berlin",
    "iso:country":"DE",
    "name:deu_x_preferred":[
        "Venn"
    ],
    "name:ita_x_preferred":[
        "Venn"
    ],
    "name:nds_x_preferred":[
        "Venn"
    ],
    "name:spa_x_preferred":[
        "Venn"
    ],
    "wof:name":"Venn",
    "wof:placetype":"neighbourhood"
},
  "geometry": {"coordinates":[6.387111,51.203996],"type":"Point"}
}