{
  "type": "Feature",
  "properties": {
    "gn:admin1_code":"10.0",
    "gn:admin2_code":"0.0",
    "gn:admin3_code":"1054.0",
    "gn:admin4_code":"1054149.0",
    "gn:asciiname":"Braderup",
    "gn:country_code":"DE",
    "gn:dem":24,
    "gn:feature_class":"P",
    "gn:feature_code":"PPL",
    "gn:name":"Braderup",
    "gn:population":0,
    "gn:timezone":"Europe/Berlin",
    "iso:country":"DE",
    "name:cat_x_preferred":[
        "Braderup"
    ],
    "name:dan_x_preferred":[
        "Brarup"
    ],
    "name:deu_x_preferred":[
        "Braderup"
    ],
    "name:epo_x_preferred":[
        "Braderup"
    ],
    "name:eus_x_preferred":[
        "Braderup"
    ],
    "name:fas_x_preferred":[
        "\u0628\u0631\u0627\u062f\u0631\u0648\u067e"
    ],
    "name:fra_x_preferred":[
        "Braderup"
    ],
    "name:frr_x_preferred":[
        "Braarep"
    ],
    "name:fry_x_preferred":[
        "Braderup"
    ],
    "name:hun_x_preferred":[
        "Braderup"
    ],
    "name:ita_x_preferred":[
        "Braderup"
    ],
    "name:mkd_x_preferred":[
        "\u0411\u0440\u0430\u0434\u0435\u0440\u0443\u043f"
    ],
    "name:msa_x_preferred":[
        "Braderup"
    ],
    "name:nld_x_preferred":[
        "Braderup"
    ],
    "name:pol_x_preferred":[
        "Braderup"
    ],
    "name:por_x_preferred":[
        "Braderup"
    ],
    "name:ron_x_preferred":[
        "Braderup"
    ],
    "name:rus_x_preferred":[
        "\u0411\u0440\u0430\u0434\u0435\u0440\u0443\u043f"
    ],
    "name:spa_x_preferred":[
        "Braderup"
    ],
    "name:srp_x_preferred":[
        "\u0411\u0440\u0430\u0434\u0435\u0440\u0443\u043f"
    ],
    "name:tur_x_preferred":[
        "Braderup"
    ],
    "name:ukr_x_preferred":[
        "\u0411\u0440\u0430\u0434\u0435\u0440\u0443\u043f"
    ],
    "name:uzb_x_preferred":[
        "Braderup"
    ],
    "name:vie_x_preferred":[
        "Braderup"
    ],
    "name:vol_x_preferred":[
        "Braderup"
    ],
    "name:war_x_preferred":[
        "Braderup"
    ],
    "name:zho_x_preferred":[
        "\u5e03\u62c9\u5fb7\u9c81\u666e"
    ],
    "wof:name":"Braderup",
    "wof:placetype":"neighbourhood"
},
  "geometry": {"coordinates":[8.3509,54.93188000000001],"type":"Point"}
}