{
  "type": "Feature",
  "properties": {
    "gn:admin1_code":"2.0",
    "gn:admin2_code":"94.0",
    "gn:admin3_code":"9476.0",
    "gn:admin4_code":"9476154.0",
    "gn:asciiname":"Steinach an der Steinach",
    "gn:country_code":"DE",
    "gn:dem":302,
    "gn:feature_class":"P",
    "gn:feature_code":"PPL",
    "gn:name":"Steinach an der Steinach",
    "gn:population":0,
    "gn:timezone":"Europe/Berlin",
    "iso:country":"DE",
    "wof:name":"Steinach an der Steinach",
    "wof:placetype":"neighbourhood"
},
  "geometry": {"coordinates":[11.19631,50.24377],"type":"Point"}
}