{
  "type": "Feature",
  "properties": {
    "gn:admin1_code":"13",
    "gn:admin2_code":"0.0",
    "gn:admin3_code":"14627.0",
    "gn:admin4_code":"14627110.0",
    "gn:asciiname":"Niegeroda",
    "gn:country_code":"DE",
    "gn:dem":138,
    "gn:feature_class":"P",
    "gn:feature_code":"PPL",
    "gn:name":"Niegeroda",
    "gn:population":0,
    "gn:timezone":"Europe/Berlin",
    "iso:country":"DE",
    "wof:name":"Niegeroda",
    "wof:placetype":"neighbourhood"
},
  "geometry": {"coordinates":[13.6252,51.34724],"type":"Point"}
}