{
  "type": "Feature",
  "properties": {
    "gn:admin1_code":"13",
    "gn:admin2_code":"0.0",
    "gn:admin3_code":"14625.0",
    "gn:admin4_code":"14625110.0",
    "gn:asciiname":"Guenthersdorf",
    "gn:country_code":"DE",
    "gn:dem":254,
    "gn:feature_class":"P",
    "gn:feature_code":"PPL",
    "gn:name":"G\u00fcnthersdorf",
    "gn:population":0,
    "gn:timezone":"Europe/Berlin",
    "iso:country":"DE",
    "name:hsb_x_preferred":[
        "Hun\u0107ericy"
    ],
    "wof:name":"Guenthersdorf",
    "wof:placetype":"neighbourhood"
},
  "geometry": {"coordinates":[14.31174,51.13737],"type":"Point"}
}