{
  "type": "Feature",
  "properties": {
    "gn:admin1_code":"6.0",
    "gn:admin2_code":"0.0",
    "gn:admin3_code":"3361.0",
    "gn:admin4_code":"3361002.0",
    "gn:asciiname":"Altholtum in der Marsch",
    "gn:country_code":"DE",
    "gn:dem":12,
    "gn:feature_class":"P",
    "gn:feature_code":"PPL",
    "gn:name":"Altholtum in der Marsch",
    "gn:population":0,
    "gn:timezone":"Europe/Berlin",
    "iso:country":"DE",
    "name:und_x_variant":[
        "Alt Holtum",
        "Altholtum in der Marsch"
    ],
    "wof:name":"Altholtum in der Marsch",
    "wof:placetype":"neighbourhood"
},
  "geometry": {"coordinates":[9.09544,52.90715],"type":"Point"}
}