{
  "type": "Feature",
  "properties": {
    "gn:admin1_code":"6",
    "gn:admin2_code":"0.0",
    "gn:admin3_code":"3352.0",
    "gn:admin4_code":"3352020.0",
    "gn:asciiname":"Kleinwoerden",
    "gn:country_code":"DE",
    "gn:dem":-3,
    "gn:feature_class":"P",
    "gn:feature_code":"PPL",
    "gn:name":"Kleinw\u00f6rden",
    "gn:population":0,
    "gn:timezone":"Europe/Berlin",
    "iso:country":"DE",
    "wof:name":"Kleinwoerden",
    "wof:placetype":"neighbourhood"
},
  "geometry": {"coordinates":[9.25811,53.66137],"type":"Point"}
}