{
  "type": "Feature",
  "properties": {
    "gn:admin1_code":"6.0",
    "gn:admin2_code":"0.0",
    "gn:admin3_code":"3461.0",
    "gn:admin4_code":"3461006.0",
    "gn:asciiname":"Braake",
    "gn:country_code":"DE",
    "gn:dem":2,
    "gn:feature_class":"P",
    "gn:feature_code":"PPL",
    "gn:name":"Braake",
    "gn:population":0,
    "gn:timezone":"Europe/Berlin",
    "iso:country":"DE",
    "wof:name":"Braake",
    "wof:placetype":"neighbourhood"
},
  "geometry": {"coordinates":[8.62994,53.12763],"type":"Point"}
}