{
  "type": "Feature",
  "properties": {
    "gn:admin1_code":"12.0",
    "gn:admin2_code":"0.0",
    "gn:admin3_code":"13073.0",
    "gn:admin4_code":"13073075.0",
    "gn:asciiname":"Freudenberg Ausbau",
    "gn:country_code":"DE",
    "gn:dem":14,
    "gn:feature_class":"P",
    "gn:feature_code":"PPL",
    "gn:name":"Freudenberg Ausbau",
    "gn:population":0,
    "gn:timezone":"Europe/Berlin",
    "iso:country":"DE",
    "wof:name":"Freudenberg Ausbau",
    "wof:placetype":"neighbourhood"
},
  "geometry": {"coordinates":[12.47652,54.21893000000001],"type":"Point"}
}