{
  "type": "Feature",
  "properties": {
    "gn:admin1_code":"2",
    "gn:admin2_code":"92.0",
    "gn:admin3_code":"9271.0",
    "gn:admin4_code":"9271128.0",
    "gn:asciiname":"Mairing",
    "gn:country_code":"DE",
    "gn:dem":359,
    "gn:feature_class":"P",
    "gn:feature_code":"PPLL",
    "gn:name":"Mairing",
    "gn:population":0,
    "gn:timezone":"Europe/Berlin",
    "iso:country":"DE",
    "wof:name":"Mairing",
    "wof:placetype":"neighbourhood"
},
  "geometry": {"coordinates":[13.09361,48.62305],"type":"Point"}
}