{
  "type": "Feature",
  "properties": {
    "gn:admin1_code":"1",
    "gn:admin2_code":"84.0",
    "gn:admin3_code":"8417.0",
    "gn:admin4_code":"8417002.0",
    "gn:asciiname":"Erzingen",
    "gn:country_code":"DE",
    "gn:dem":569,
    "gn:feature_class":"P",
    "gn:feature_code":"PPL",
    "gn:name":"Erzingen",
    "gn:population":0,
    "gn:timezone":"Europe/Berlin",
    "iso:country":"DE",
    "wof:name":"Erzingen",
    "wof:placetype":"neighbourhood"
},
  "geometry": {"coordinates":[8.81477,48.25068],"type":"Point"}
}