{
  "type": "Feature",
  "properties": {
    "gn:country":"DE",
    "gn:fcode":"PPL",
    "gn:population":0,
    "iso:country":"DE",
    "name:cat_x_preferred":[
        "Briesen"
    ],
    "name:ceb_x_preferred":[
        "Briesen"
    ],
    "name:che_x_preferred":[
        "\u0411\u0440\u0438\u0437\u0435\u043d"
    ],
    "name:cym_x_preferred":[
        "Briesen"
    ],
    "name:dan_x_preferred":[
        "Briesen"
    ],
    "name:deu_x_preferred":[
        "Briesen"
    ],
    "name:dsb_x_preferred":[
        "Brjazyna"
    ],
    "name:eng_x_preferred":[
        "Briesen"
    ],
    "name:epo_x_preferred":[
        "Briesen"
    ],
    "name:eus_x_preferred":[
        "Briesen"
    ],
    "name:fas_x_preferred":[
        "\u0628\u0631\u0627\u06cc\u0632\u0646"
    ],
    "name:fra_x_preferred":[
        "Briesen"
    ],
    "name:hsb_x_preferred":[
        "Brjazyna"
    ],
    "name:hun_x_preferred":[
        "Briesen"
    ],
    "name:hye_x_preferred":[
        "\u0532\u0580\u056b\u0566\u0565\u0576"
    ],
    "name:ita_x_preferred":[
        "Briesen"
    ],
    "name:jpn_x_preferred":[
        "\u30d6\u30ea\u30fc\u30bc\u30f3"
    ],
    "name:kur_x_preferred":[
        "Briesen"
    ],
    "name:lit_x_preferred":[
        "Bryzenas"
    ],
    "name:lld_x_preferred":[
        "Briesen"
    ],
    "name:mkd_x_preferred":[
        "\u0411\u0440\u0438\u0437\u0435\u043d"
    ],
    "name:msa_x_preferred":[
        "Briesen"
    ],
    "name:nld_x_preferred":[
        "Briesen"
    ],
    "name:nob_x_preferred":[
        "Briesen"
    ],
    "name:pol_x_preferred":[
        "Briesen"
    ],
    "name:por_x_preferred":[
        "Briesen"
    ],
    "name:ron_x_preferred":[
        "Briesen"
    ],
    "name:rus_x_preferred":[
        "\u0411\u0440\u0438\u0437\u0435\u043d"
    ],
    "name:spa_x_preferred":[
        "Briesen"
    ],
    "name:srp_x_preferred":[
        "\u0411\u0440\u0438\u0437\u0435\u043d"
    ],
    "name:swe_x_preferred":[
        "Briesen"
    ],
    "name:tat_x_preferred":[
        "\u0411\u0440\u0438\u0437\u0435\u043d"
    ],
    "name:ukr_x_preferred":[
        "\u0411\u0440\u0456\u0437\u0435\u043d/\u0411\u0440\u044c\u044f\u0446\u0438\u043d\u0430"
    ],
    "name:uzb_x_preferred":[
        "Briesen"
    ],
    "name:vie_x_preferred":[
        "Briesen"
    ],
    "name:vol_x_preferred":[
        "Briesen"
    ],
    "name:war_x_preferred":[
        "Briesen"
    ],
    "name:zho_x_preferred":[
        "\u5e03\u91cc\u68ee"
    ],
    "qs_pg:aaroncc":"DE",
    "qs_pg:gn_country":"DE",
    "qs_pg:gn_fcode":"PPL",
    "qs_pg:gn_pop":0,
    "qs_pg:name":"Briesensee",
    "qs_pg:name_adm0":"Deutschland",
    "qs_pg:name_adm1":"Bundesland Brandenburg",
    "qs_pg:photos":17,
    "qs_pg:photos_1k":3,
    "qs_pg:photos_9k":1,
    "qs_pg:photos_9r":1,
    "qs_pg:photos_all":17,
    "qs_pg:photos_sr":1,
    "qs_pg:pop_sr":0,
    "qs_pg:qs_pg_placetype":"locality",
    "qs_pg:qs_pg_placetype_gp":"Town",
    "qs_pg:woe_adm0":23424829,
    "woe:adm0_id":23424829,
    "woe:name_adm0":"Deutschland",
    "woe:name_adm1":"Bundesland Brandenburg",
    "woe:placetype":"Town",
    "wof:name":"Briesensee",
    "wof:placetype":"neighbourhood"
},
  "geometry": {"coordinates":[14.00471,51.95604],"type":"Point"}
}