{
  "type": "Feature",
  "properties": {
    "gn:admin1_code":"8",
    "gn:admin2_code":"0.0",
    "gn:admin3_code":"7336.0",
    "gn:admin4_code":"7336501.0",
    "gn:asciiname":"Liebsthal",
    "gn:country_code":"DE",
    "gn:dem":278,
    "gn:feature_class":"P",
    "gn:feature_code":"PPL",
    "gn:name":"Liebsthal",
    "gn:population":0,
    "gn:timezone":"Europe/Berlin",
    "iso:country":"DE",
    "wof:name":"Liebsthal",
    "wof:placetype":"neighbourhood"
},
  "geometry": {"coordinates":[7.40122,49.48351],"type":"Point"}
}