{
  "type": "Feature",
  "properties": {
    "gn:admin1_code":"2",
    "gn:admin2_code":"92.0",
    "gn:admin3_code":"9278.0",
    "gn:admin4_code":"9278144.0",
    "gn:asciiname":"Grafentraubach",
    "gn:country_code":"DE",
    "gn:dem":374,
    "gn:feature_class":"P",
    "gn:feature_code":"PPL",
    "gn:name":"Grafentraubach",
    "gn:population":0,
    "gn:timezone":"Europe/Berlin",
    "iso:country":"DE",
    "wof:name":"Grafentraubach",
    "wof:placetype":"neighbourhood"
},
  "geometry": {"coordinates":[12.28416,48.79278],"type":"Point"}
}