{
  "type": "Feature",
  "properties": {
    "gn:admin1_code":"11",
    "gn:admin2_code":"0.0",
    "gn:admin3_code":"12071.0",
    "gn:admin4_code":"12071372.0",
    "gn:asciiname":"Gosda",
    "gn:country_code":"DE",
    "gn:dem":141,
    "gn:feature_class":"P",
    "gn:feature_code":"PPL",
    "gn:name":"Gosda",
    "gn:population":0,
    "gn:timezone":"Europe/Berlin",
    "iso:country":"DE",
    "wof:name":"Gosda",
    "wof:placetype":"neighbourhood"
},
  "geometry": {"coordinates":[14.26667,51.55],"type":"Point"}
}