{
  "type": "Feature",
  "properties": {
    "gn:admin1_code":"14.0",
    "gn:admin2_code":"00",
    "gn:admin3_code":"15090.0",
    "gn:admin4_code":"15090535.0",
    "gn:asciiname":"Wendisch Boergitz",
    "gn:country_code":"DE",
    "gn:dem":54,
    "gn:feature_class":"P",
    "gn:feature_code":"PPL",
    "gn:name":"Wendisch B\u00f6rgitz",
    "gn:population":0,
    "gn:timezone":"Europe/Berlin",
    "iso:country":"DE",
    "wof:name":"Wendisch Boergitz",
    "wof:placetype":"neighbourhood"
},
  "geometry": {"coordinates":[11.62508,52.54624],"type":"Point"}
}