{
  "type": "Feature",
  "properties": {
    "gn:admin1_code":"2",
    "gn:admin2_code":"95.0",
    "gn:admin3_code":"9571.0",
    "gn:admin4_code":"9571194.0",
    "gn:asciiname":"Unternbibert",
    "gn:country_code":"DE",
    "gn:dem":396,
    "gn:feature_class":"P",
    "gn:feature_code":"PPL",
    "gn:name":"Unternbibert",
    "gn:population":0,
    "gn:timezone":"Europe/Berlin",
    "iso:country":"DE",
    "wof:name":"Unternbibert",
    "wof:placetype":"neighbourhood"
},
  "geometry": {"coordinates":[10.58752,49.42219],"type":"Point"}
}