{
  "type": "Feature",
  "properties": {
    "iso:country":"DE",
    "oa:elevation_ft":"1896",
    "oa:type":"small_airport",
    "woe:hierarchy":{
        "country_id":23424829,
        "county_id":12596895,
        "localadmin_id":12624592,
        "planet_id":1,
        "state_id":2345487
    },
    "wof:name":"Dahlemer Binz Airport",
    "wof:placetype":"campus"
},
  "geometry": {"coordinates":[6.52808,50.4059],"type":"Point"}
}