{
  "type": "Feature",
  "properties": {
    "gn:admin1_code":"2",
    "gn:admin2_code":"91.0",
    "gn:admin3_code":"9178.0",
    "gn:admin4_code":"9178155.0",
    "gn:asciiname":"Sixthaselbach",
    "gn:country_code":"DE",
    "gn:dem":454,
    "gn:feature_class":"P",
    "gn:feature_code":"PPL",
    "gn:name":"Sixthaselbach",
    "gn:population":0,
    "gn:timezone":"Europe/Berlin",
    "iso:country":"DE",
    "wof:name":"Sixthaselbach",
    "wof:placetype":"neighbourhood"
},
  "geometry": {"coordinates":[11.87131,48.49778],"type":"Point"}
}