{
  "type": "Feature",
  "properties": {
    "gn:admin1_code":"6",
    "gn:admin2_code":"0.0",
    "gn:admin3_code":"3453.0",
    "gn:admin4_code":"3453006.0",
    "gn:asciiname":"Lage",
    "gn:country_code":"DE",
    "gn:dem":34,
    "gn:feature_class":"P",
    "gn:feature_code":"PPL",
    "gn:name":"Lage",
    "gn:population":0,
    "gn:timezone":"Europe/Berlin",
    "iso:country":"DE",
    "name:ceb_x_preferred":[
        "Lage"
    ],
    "name:deu_x_preferred":[
        "Lage"
    ],
    "name:epo_x_preferred":[
        "Lage"
    ],
    "name:fra_x_preferred":[
        "Lage"
    ],
    "name:jpn_x_preferred":[
        "\u30e9\u30fc\u30b2"
    ],
    "name:nld_x_preferred":[
        "Lage"
    ],
    "name:pol_x_preferred":[
        "Lage"
    ],
    "name:por_x_preferred":[
        "Lage"
    ],
    "name:rus_x_preferred":[
        "\u041b\u0430\u0433\u0435"
    ],
    "name:spa_x_preferred":[
        "Lage"
    ],
    "name:srp_x_preferred":[
        "\u041b\u0430\u0433\u0435"
    ],
    "name:swe_x_preferred":[
        "Lage"
    ],
    "name:vol_x_preferred":[
        "Lage"
    ],
    "wof:name":"Lage",
    "wof:placetype":"neighbourhood"
},
  "geometry": {"coordinates":[8.05801,52.70475],"type":"Point"}
}