{
  "type": "Feature",
  "properties": {
    "gn:admin1_code":"2",
    "gn:admin2_code":"92.0",
    "gn:admin3_code":"9272.0",
    "gn:admin4_code":"9272127.0",
    "gn:asciiname":"Eppenberg",
    "gn:country_code":"DE",
    "gn:dem":678,
    "gn:feature_class":"P",
    "gn:feature_code":"PPL",
    "gn:name":"Eppenberg",
    "gn:population":0,
    "gn:timezone":"Europe/Berlin",
    "iso:country":"DE",
    "name:ceb_x_preferred":[
        "Eppenberg"
    ],
    "name:deu_x_preferred":[
        "Eppenberg"
    ],
    "name:epo_x_preferred":[
        "Eppenberg"
    ],
    "name:eus_x_preferred":[
        "Eppenberg"
    ],
    "name:fas_x_preferred":[
        "\u0627\u067e\u0646\u0628\u0631\u06af"
    ],
    "name:fra_x_preferred":[
        "Eppenberg"
    ],
    "name:hun_x_preferred":[
        "Eppenberg"
    ],
    "name:ita_x_preferred":[
        "Eppenberg"
    ],
    "name:kaz_x_preferred":[
        "\u042d\u043f\u043f\u0435\u043d\u0431\u0435\u0440\u0433"
    ],
    "name:kir_x_preferred":[
        "\u042d\u043f\u043f\u0435\u043d\u0431\u0435\u0440\u0433"
    ],
    "name:msa_x_preferred":[
        "Eppenberg"
    ],
    "name:nld_x_preferred":[
        "Eppenberg"
    ],
    "name:pol_x_preferred":[
        "Eppenberg"
    ],
    "name:por_x_preferred":[
        "Eppenberg"
    ],
    "name:ron_x_preferred":[
        "Eppenberg"
    ],
    "name:rus_x_preferred":[
        "\u042d\u043f\u043f\u0435\u043d\u0431\u0435\u0440\u0433"
    ],
    "name:spa_x_preferred":[
        "Eppenberg"
    ],
    "name:srp_x_preferred":[
        "\u0415\u043f\u0435\u043d\u0431\u0435\u0440\u0433"
    ],
    "name:ukr_x_preferred":[
        "\u0415\u043f\u043f\u0435\u043d\u0431\u0435\u0440\u0433"
    ],
    "name:uzb_x_preferred":[
        "Eppenberg"
    ],
    "name:vie_x_preferred":[
        "Eppenberg"
    ],
    "name:vol_x_preferred":[
        "Eppenberg"
    ],
    "name:war_x_preferred":[
        "Eppenberg"
    ],
    "name:zho_x_preferred":[
        "\u57c3\u5f6d\u8d1d\u683c"
    ],
    "wof:name":"Eppenberg",
    "wof:placetype":"neighbourhood"
},
  "geometry": {"coordinates":[13.48909,48.82902],"type":"Point"}
}