{
  "type": "Feature",
  "properties": {
    "gn:admin1_code":"6.0",
    "gn:admin2_code":"00",
    "gn:admin3_code":"3356.0",
    "gn:admin4_code":"3356005.0",
    "gn:asciiname":"Westerwede",
    "gn:country_code":"DE",
    "gn:dem":6,
    "gn:feature_class":"P",
    "gn:feature_code":"PPL",
    "gn:name":"Westerwede",
    "gn:population":0,
    "gn:timezone":"Europe/Berlin",
    "iso:country":"DE",
    "wof:name":"Westerwede",
    "wof:placetype":"neighbourhood"
},
  "geometry": {"coordinates":[8.91764,53.19749],"type":"Point"}
}