{
  "type": "Feature",
  "properties": {
    "gn:admin1_code":"13",
    "gn:admin2_code":"0.0",
    "gn:admin3_code":"14626.0",
    "gn:admin4_code":"14626610.0",
    "gn:asciiname":"Pethau",
    "gn:country_code":"DE",
    "gn:dem":247,
    "gn:feature_class":"P",
    "gn:feature_code":"PPL",
    "gn:name":"Pethau",
    "gn:population":0,
    "gn:timezone":"Europe/Berlin",
    "iso:country":"DE",
    "wof:name":"Pethau",
    "wof:placetype":"neighbourhood"
},
  "geometry": {"coordinates":[14.76543,50.90067],"type":"Point"}
}