{
  "type": "Feature",
  "properties": {
    "gn:admin1_code":"7.0",
    "gn:admin2_code":"51.0",
    "gn:admin3_code":"5166.0",
    "gn:admin4_code":"5166032.0",
    "gn:asciiname":"Bonesend",
    "gn:country_code":"DE",
    "gn:dem":55,
    "gn:feature_class":"P",
    "gn:feature_code":"PPL",
    "gn:name":"Bonesend",
    "gn:population":0,
    "gn:timezone":"Europe/Berlin",
    "iso:country":"DE",
    "wof:name":"Bonesend",
    "wof:placetype":"neighbourhood"
},
  "geometry": {"coordinates":[6.27806,51.27384],"type":"Point"}
}