{
  "type": "Feature",
  "properties": {
    "gn:admin1_code":"13",
    "gn:admin2_code":"0.0",
    "gn:admin3_code":"14521.0",
    "gn:admin4_code":"14521170.0",
    "gn:asciiname":"Lochhaeuser",
    "gn:country_code":"DE",
    "gn:dem":580,
    "gn:feature_class":"P",
    "gn:feature_code":"PPL",
    "gn:name":"Lochh\u00e4user",
    "gn:population":0,
    "gn:timezone":"Europe/Berlin",
    "iso:country":"DE",
    "wof:name":"Lochhaeuser",
    "wof:placetype":"neighbourhood"
},
  "geometry": {"coordinates":[12.6511,50.50922],"type":"Point"}
}