{
  "type": "Feature",
  "properties": {
    "gn:admin1_code":"2",
    "gn:admin2_code":"91.0",
    "gn:admin3_code":"9182.0",
    "gn:admin4_code":"9182114.0",
    "gn:asciiname":"Stauden",
    "gn:country_code":"DE",
    "gn:dem":754,
    "gn:feature_class":"P",
    "gn:feature_code":"PPL",
    "gn:name":"Stauden",
    "gn:population":0,
    "gn:timezone":"Europe/Berlin",
    "iso:country":"DE",
    "wof:name":"Stauden",
    "wof:placetype":"neighbourhood"
},
  "geometry": {"coordinates":[11.93184,47.70826],"type":"Point"}
}