{
  "type": "Feature",
  "properties": {
    "iso:country":"DE",
    "wof:name":"B\u00fcschberg",
    "wof:placetype":"neighbourhood"
},
  "geometry": {"coordinates":[7.05205243394809,51.17748456405931],"type":"Point"}
}