{
  "type": "Feature",
  "properties": {
    "gn:admin1_code":"7.0",
    "gn:admin2_code":"53.0",
    "gn:admin3_code":"5374.0",
    "gn:admin4_code":"5374004.0",
    "gn:asciiname":"Breloeh",
    "gn:country_code":"DE",
    "gn:dem":280,
    "gn:feature_class":"P",
    "gn:feature_code":"PPL",
    "gn:name":"Brel\u00f6h",
    "gn:population":0,
    "gn:timezone":"Europe/Berlin",
    "iso:country":"DE",
    "wof:name":"Breloeh",
    "wof:placetype":"neighbourhood"
},
  "geometry": {"coordinates":[7.68305,51.01329000000001],"type":"Point"}
}