{
  "type": "Feature",
  "properties": {
    "gn:gn_country":"DE",
    "gn:gn_fcode":"PPL",
    "gn:gn_pop":0,
    "iso:country":"DE",
    "name:deu_x_preferred":[
        "Albachten"
    ],
    "name:unk_x_variant":[
        "Albachten"
    ],
    "qs:gn_fcode":"PPL",
    "qs:gn_local":0,
    "qs:gn_namadm1":"07",
    "qs:gn_name":"Albachten",
    "qs:local_max":4321,
    "qs:local_sum":13562,
    "qs:localhoods":28,
    "qs:name":"Albachten",
    "qs:name_adm0":"Deutschland",
    "qs:name_adm1":"Nordrhein-Westfalen",
    "qs:name_adm2":"Stadtkreis M\u00fcnster",
    "qs:name_lau":"Stadtteil West",
    "qs:name_local":"M\u00fcnster",
    "qs:photo_max":5,
    "qs:photo_sum":16,
    "qs:placetype":"Suburb",
    "qs:quad_count":8,
    "qs:woe_adm0":23424829,
    "qs:woe_adm1":2345487,
    "qs:woe_adm2":12596927,
    "qs:woe_lau":26823105,
    "qs:woe_local":676864,
    "qs:woe_ver":"7.10.0",
    "qs_pg:aaroncc":"DE",
    "qs_pg:gn_country":"DE",
    "qs_pg:gn_fcode":"PPL",
    "qs_pg:gn_pop":0,
    "qs_pg:name":"Albachten",
    "qs_pg:name_adm0":"Deutschland",
    "qs_pg:name_adm1":"Nordrhein-Westfalen",
    "qs_pg:photos":17,
    "qs_pg:photos_1k":3,
    "qs_pg:photos_9k":1,
    "qs_pg:photos_9r":1,
    "qs_pg:photos_all":17,
    "qs_pg:photos_sr":1,
    "qs_pg:pop_sr":0,
    "qs_pg:qs_pg_placetype":"neighbourhood",
    "qs_pg:qs_pg_placetype_gp":"Suburb",
    "qs_pg:woe_adm0":23424829,
    "wof:lang":[
        "ger"
    ],
    "wof:name":"Albachten",
    "wof:placetype":"neighbourhood"
},
  "geometry": {"coordinates":[7.523575,51.928176],"type":"Point"}
}