{
  "type": "Feature",
  "properties": {
    "gn:admin1_code":"1",
    "gn:admin2_code":"81.0",
    "gn:admin3_code":"8127.0",
    "gn:admin4_code":"8127073.0",
    "gn:asciiname":"Horschhausen",
    "gn:country_code":"DE",
    "gn:dem":468,
    "gn:feature_class":"P",
    "gn:feature_code":"PPL",
    "gn:name":"Horschhausen",
    "gn:population":0,
    "gn:timezone":"Europe/Berlin",
    "iso:country":"DE",
    "wof:name":"Horschhausen",
    "wof:placetype":"neighbourhood"
},
  "geometry": {"coordinates":[10.15848,49.17978],"type":"Point"}
}