{
  "type": "Feature",
  "properties": {
    "gn:admin1_code":"2",
    "gn:admin2_code":"91.0",
    "gn:admin3_code":"9175.0",
    "gn:admin4_code":"9175119.0",
    "gn:asciiname":"Tegernau",
    "gn:country_code":"DE",
    "gn:dem":532,
    "gn:feature_class":"P",
    "gn:feature_code":"PPL",
    "gn:name":"Tegernau",
    "gn:population":0,
    "gn:timezone":"Europe/Berlin",
    "iso:country":"DE",
    "name:als_x_preferred":[
        "Tegernau"
    ],
    "name:ceb_x_preferred":[
        "Tegernau"
    ],
    "name:deu_x_preferred":[
        "Tegernau"
    ],
    "name:epo_x_preferred":[
        "Tegernau"
    ],
    "name:fas_x_preferred":[
        "\u062a\u06af\u0631\u0646\u0627\u0648"
    ],
    "name:fra_x_preferred":[
        "Tegernau"
    ],
    "name:ita_x_preferred":[
        "Tegernau"
    ],
    "name:kaz_x_preferred":[
        "\u0422\u0435\u0433\u0435\u0440\u043d\u0430\u0443"
    ],
    "name:kir_x_preferred":[
        "\u0422\u0435\u0433\u0435\u0440\u043d\u0430\u0443"
    ],
    "name:nld_x_preferred":[
        "Tegernau"
    ],
    "name:pol_x_preferred":[
        "Tegernau"
    ],
    "name:por_x_preferred":[
        "Tegernau"
    ],
    "name:ron_x_preferred":[
        "Tegernau"
    ],
    "name:rus_x_preferred":[
        "\u0422\u0435\u0433\u0435\u0440\u043d\u0430\u0443"
    ],
    "name:uzb_x_preferred":[
        "Tegernau"
    ],
    "name:vol_x_preferred":[
        "Tegernau"
    ],
    "wof:name":"Tegernau",
    "wof:placetype":"neighbourhood"
},
  "geometry": {"coordinates":[12.04024,48.02151],"type":"Point"}
}