{
  "type": "Feature",
  "properties": {
    "gn:admin1_code":"2",
    "gn:admin2_code":"95.0",
    "gn:admin3_code":"9571.0",
    "gn:admin4_code":"9571214.0",
    "gn:asciiname":"Obermogersheim",
    "gn:country_code":"DE",
    "gn:dem":459,
    "gn:feature_class":"P",
    "gn:feature_code":"PPL",
    "gn:name":"Oberm\u00f6gersheim",
    "gn:population":0,
    "gn:timezone":"Europe/Berlin",
    "iso:country":"DE",
    "wof:name":"Obermogersheim",
    "wof:placetype":"neighbourhood"
},
  "geometry": {"coordinates":[10.65787,49.05917],"type":"Point"}
}