{
  "type": "Feature",
  "properties": {
    "gn:admin1_code":"2",
    "gn:admin2_code":"91.0",
    "gn:admin3_code":"9187.0",
    "gn:admin4_code":"9187121.0",
    "gn:asciiname":"Urfahrn",
    "gn:country_code":"DE",
    "gn:dem":526,
    "gn:feature_class":"P",
    "gn:feature_code":"PPLL",
    "gn:name":"Urfahrn",
    "gn:population":0,
    "gn:timezone":"Europe/Berlin",
    "iso:country":"DE",
    "wof:name":"Urfahrn",
    "wof:placetype":"neighbourhood"
},
  "geometry": {"coordinates":[12.3882,47.87848],"type":"Point"}
}