{
  "type": "Feature",
  "properties": {
    "iso:country":"DE",
    "wof:name":"Benninghofen",
    "wof:placetype":"neighbourhood"
},
  "geometry": {"coordinates":[7.50837605065455,51.4720909338683],"type":"Point"}
}