{
  "type": "Feature",
  "properties": {
    "gn:admin1_code":"1.0",
    "gn:admin2_code":"83.0",
    "gn:admin3_code":"8315.0",
    "gn:admin4_code":"8315094.0",
    "gn:asciiname":"Glashutte",
    "gn:country_code":"DE",
    "gn:dem":741,
    "gn:feature_class":"P",
    "gn:feature_code":"PPL",
    "gn:name":"Glash\u00fctte",
    "gn:population":0,
    "gn:timezone":"Europe/Berlin",
    "iso:country":"DE",
    "name:und_x_variant":[
        "Glash\u00fctte",
        "Altglash\u00fctte"
    ],
    "wof:name":"Glashutte",
    "wof:placetype":"neighbourhood"
},
  "geometry": {"coordinates":[8.13796,48.00102],"type":"Point"}
}