{
  "type": "Feature",
  "properties": {
    "gn:admin1_code":"6",
    "gn:admin2_code":"0.0",
    "gn:admin3_code":"3358.0",
    "gn:admin4_code":"3358014.0",
    "gn:asciiname":"Hudemuehlen",
    "gn:country_code":"DE",
    "gn:dem":25,
    "gn:feature_class":"P",
    "gn:feature_code":"PPL",
    "gn:name":"Hudem\u00fchlen",
    "gn:population":0,
    "gn:timezone":"Europe/Berlin",
    "iso:country":"DE",
    "wof:name":"Hudemuehlen",
    "wof:placetype":"neighbourhood"
},
  "geometry": {"coordinates":[9.58333,52.76667],"type":"Point"}
}