{
  "type": "Feature",
  "properties": {
    "gn:admin1_code":"7.0",
    "gn:admin2_code":"53.0",
    "gn:admin3_code":"5316.0",
    "gn:admin4_code":"5316000.0",
    "gn:asciiname":"Kueppersteg",
    "gn:country_code":"DE",
    "gn:dem":57,
    "gn:feature_class":"P",
    "gn:feature_code":"PPL",
    "gn:name":"K\u00fcppersteg",
    "gn:population":0,
    "gn:timezone":"Europe/Berlin",
    "iso:country":"DE",
    "wof:name":"Kueppersteg",
    "wof:placetype":"neighbourhood"
},
  "geometry": {"coordinates":[6.99567,51.05046],"type":"Point"}
}