{
  "type": "Feature",
  "properties": {
    "gn:admin1_code":"2",
    "gn:admin2_code":"93.0",
    "gn:admin3_code":"9372.0",
    "gn:admin4_code":"9372171.0",
    "gn:asciiname":"Englmannsbrunn",
    "gn:country_code":"DE",
    "gn:dem":604,
    "gn:feature_class":"P",
    "gn:feature_code":"PPL",
    "gn:name":"Englmannsbrunn",
    "gn:population":0,
    "gn:timezone":"Europe/Berlin",
    "iso:country":"DE",
    "name:und_x_variant":[
        "Engelmannsbrunn",
        "Englmannsbrunn"
    ],
    "wof:name":"Englmannsbrunn",
    "wof:placetype":"neighbourhood"
},
  "geometry": {"coordinates":[12.67155,49.36454000000001],"type":"Point"}
}