{
  "type": "Feature",
  "properties": {
    "gn:admin1_code":"2",
    "gn:admin2_code":"94.0",
    "gn:admin3_code":"9472.0",
    "gn:admin4_code":"9472127.0",
    "gn:asciiname":"Buhl",
    "gn:country_code":"DE",
    "gn:dem":442,
    "gn:feature_class":"P",
    "gn:feature_code":"PPL",
    "gn:name":"B\u00fchl",
    "gn:population":0,
    "gn:timezone":"Europe/Berlin",
    "iso:country":"DE",
    "wof:name":"Buhl",
    "wof:placetype":"neighbourhood"
},
  "geometry": {"coordinates":[11.61731,49.84378],"type":"Point"}
}