{
  "type": "Feature",
  "properties": {
    "gn:admin1_code":"11.0",
    "gn:admin2_code":"0.0",
    "gn:admin3_code":"12068.0",
    "gn:admin4_code":"12068280.0",
    "gn:asciiname":"Banzendorf",
    "gn:country_code":"DE",
    "gn:dem":56,
    "gn:feature_class":"P",
    "gn:feature_code":"PPL",
    "gn:name":"Banzendorf",
    "gn:population":0,
    "gn:timezone":"Europe/Berlin",
    "iso:country":"DE",
    "name:ceb_x_preferred":[
        "Banzendorf"
    ],
    "name:deu_x_preferred":[
        "Banzendorf"
    ],
    "name:fas_x_preferred":[
        "\u0628\u0627\u0646\u062a\u0633\u0646\u062f\u0648\u0631\u0641"
    ],
    "wof:name":"Banzendorf",
    "wof:placetype":"neighbourhood"
},
  "geometry": {"coordinates":[12.99939,53.01568],"type":"Point"}
}