{
  "type": "Feature",
  "properties": {
    "gn:admin1_code":"5",
    "gn:admin2_code":"66.0",
    "gn:admin3_code":"6635.0",
    "gn:admin4_code":"6635019.0",
    "gn:asciiname":"Thalitter",
    "gn:country_code":"DE",
    "gn:dem":305,
    "gn:feature_class":"P",
    "gn:feature_code":"PPL",
    "gn:name":"Thalitter",
    "gn:population":0,
    "gn:timezone":"Europe/Berlin",
    "iso:country":"DE",
    "wof:name":"Thalitter",
    "wof:placetype":"neighbourhood"
},
  "geometry": {"coordinates":[8.89687,51.21914],"type":"Point"}
}