{
  "type": "Feature",
  "properties": {
    "gn:gn_country":"DE",
    "gn:gn_fcode":"PPLA4",
    "gn:gn_pop":233,
    "gn:population":233,
    "iso:country":"DE",
    "name:baq_x_preferred":[
        "Eckenroth"
    ],
    "name:chi_x_preferred":[
        "\u57c3\u80af\u7f57\u7279"
    ],
    "name:dut_x_preferred":[
        "Eckenroth"
    ],
    "name:eng_x_preferred":[
        "Eckenroth"
    ],
    "name:epo_x_preferred":[
        "Eckenroth"
    ],
    "name:fre_x_preferred":[
        "Eckenroth"
    ],
    "name:ger_x_preferred":[
        "Eckenroth"
    ],
    "name:hun_x_preferred":[
        "Eckenroth"
    ],
    "name:ita_x_preferred":[
        "Eckenroth"
    ],
    "name:jpn_x_preferred":[
        "\u30a8\u30c3\u30b1\u30f3\u30ed\u30fc\u30c8"
    ],
    "name:kaz_x_preferred":[
        "\u042d\u043a\u043a\u0435\u043d\u0440\u043e\u0442"
    ],
    "name:kir_x_preferred":[
        "\u042d\u043a\u043a\u0435\u043d\u0440\u043e\u0442"
    ],
    "name:may_x_preferred":[
        "Eckenroth"
    ],
    "name:per_x_preferred":[
        "\u0627\u06a9\u0646\u0631\u0648\u062a"
    ],
    "name:pol_x_preferred":[
        "Eckenroth"
    ],
    "name:por_x_preferred":[
        "Eckenroth"
    ],
    "name:rum_x_preferred":[
        "Eckenroth"
    ],
    "name:rus_x_preferred":[
        "\u042d\u043a\u043a\u0435\u043d\u0440\u043e\u0442"
    ],
    "name:spa_x_preferred":[
        "Eckenroth"
    ],
    "name:srp_x_preferred":[
        "\u0415\u043a\u0435\u043d\u0440\u043e\u0442"
    ],
    "name:ukr_x_preferred":[
        "\u0415\u043a\u043a\u0435\u043d\u0440\u043e\u0442"
    ],
    "name:uzb_x_preferred":[
        "Eckenroth"
    ],
    "name:vie_x_preferred":[
        "Eckenroth"
    ],
    "name:vol_x_preferred":[
        "Eckenroth"
    ],
    "name:war_x_preferred":[
        "Eckenroth"
    ],
    "qs_pg:aaroncc":"DE",
    "qs_pg:gn_country":"DE",
    "qs_pg:gn_fcode":"PPLA4",
    "qs_pg:gn_pop":233,
    "qs_pg:name":"Eckenroth",
    "qs_pg:photos_9r":0,
    "qs_pg:photos_sr":0,
    "qs_pg:pop_sr":2,
    "qs_pg:qs_pg_placetype":"locality",
    "wof:name":"Eckenroth",
    "wof:placetype":"locality",
    "wof:population":233
},
  "geometry": {"coordinates":[7.78333,49.91667],"type":"Point"}
}