{
  "type": "Feature",
  "properties": {
    "gn:gn_country":"DE",
    "gn:gn_fcode":"PPLA4",
    "gn:gn_pop":711,
    "gn:population":711,
    "iso:country":"DE",
    "name:baq_x_preferred":[
        "Allenbach"
    ],
    "name:bul_x_preferred":[
        "\u0410\u043b\u0435\u043d\u0431\u0430\u0445"
    ],
    "name:chi_x_preferred":[
        "\u963f\u4f26\u5df4\u8d6b"
    ],
    "name:dut_x_preferred":[
        "Allenbach"
    ],
    "name:eng_x_preferred":[
        "Allenbach"
    ],
    "name:epo_x_preferred":[
        "Allenbach"
    ],
    "name:fas_x_preferred":[
        "\u0627\u0644\u0646\u0628\u0627\u062e"
    ],
    "name:fre_x_preferred":[
        "Allenbach"
    ],
    "name:ger_x_preferred":[
        "Allenbach"
    ],
    "name:hat_x_preferred":[
        "Allenbach"
    ],
    "name:hun_x_preferred":[
        "Allenbach"
    ],
    "name:ita_x_preferred":[
        "Allenbach"
    ],
    "name:jpn_x_preferred":[
        "\u30a2\u30ec\u30f3\u30d0\u30c3\u30cf"
    ],
    "name:kaz_x_preferred":[
        "\u0410\u043b\u043b\u0435\u043d\u0431\u0430\u0445"
    ],
    "name:kir_x_preferred":[
        "\u0410\u043b\u043b\u0435\u043d\u0431\u0430\u0445"
    ],
    "name:may_x_preferred":[
        "Allenbach"
    ],
    "name:per_x_preferred":[
        "\u0627\u0644\u0646\u0628\u0627\u062e"
    ],
    "name:pol_x_preferred":[
        "Allenbach"
    ],
    "name:por_x_preferred":[
        "Allenbach"
    ],
    "name:rum_x_preferred":[
        "Allenbach"
    ],
    "name:rus_x_preferred":[
        "\u0410\u043b\u043b\u0435\u043d\u0431\u0430\u0445"
    ],
    "name:spa_x_preferred":[
        "Allenbach"
    ],
    "name:srp_x_preferred":[
        "\u0410\u043b\u0435\u043d\u0431\u0430\u0445"
    ],
    "name:ukr_x_preferred":[
        "\u0410\u043b\u043b\u0435\u043d\u0431\u0430\u0445"
    ],
    "name:uzb_x_preferred":[
        "Allenbach"
    ],
    "name:vie_x_preferred":[
        "Allenbach"
    ],
    "name:vol_x_preferred":[
        "Allenbach"
    ],
    "name:war_x_preferred":[
        "Allenbach"
    ],
    "name:zho_x_preferred":[
        "\u963f\u4f26\u5df4\u8d6b"
    ],
    "qs_pg:aaroncc":"DE",
    "qs_pg:gn_country":"DE",
    "qs_pg:gn_fcode":"PPLA4",
    "qs_pg:gn_pop":711,
    "qs_pg:name":"Allenbach",
    "qs_pg:photos_9r":0,
    "qs_pg:photos_sr":0,
    "qs_pg:pop_sr":2,
    "qs_pg:qs_pg_placetype":"locality",
    "wof:name":"Allenbach",
    "wof:placetype":"locality",
    "wof:population":711
},
  "geometry": {"coordinates":[7.16667,49.75],"type":"Point"}
}