{
  "type": "Feature",
  "properties": {
    "gn:admin1_code":"2",
    "gn:admin2_code":"93.0",
    "gn:admin3_code":"9375.0",
    "gn:admin4_code":"9375148.0",
    "gn:asciiname":"Haag",
    "gn:country_code":"DE",
    "gn:dem":537,
    "gn:feature_class":"P",
    "gn:feature_code":"PPL",
    "gn:name":"Haag",
    "gn:population":0,
    "gn:timezone":"Europe/Berlin",
    "iso:country":"DE",
    "name:fas_x_preferred":[
        "\u0647\u0627\u06af"
    ],
    "wof:name":"Haag",
    "wof:placetype":"neighbourhood"
},
  "geometry": {"coordinates":[11.81854,49.05998],"type":"Point"}
}