{
  "type": "Feature",
  "properties": {
    "gn:admin1_code":"2",
    "gn:admin2_code":"97.0",
    "gn:admin3_code":"9775.0",
    "gn:admin4_code":"9775111.0",
    "gn:asciiname":"Filzingen",
    "gn:country_code":"DE",
    "gn:dem":533,
    "gn:feature_class":"P",
    "gn:feature_code":"PPL",
    "gn:name":"Filzingen",
    "gn:population":0,
    "gn:timezone":"Europe/Berlin",
    "iso:country":"DE",
    "wof:name":"Filzingen",
    "wof:placetype":"neighbourhood"
},
  "geometry": {"coordinates":[10.12176,48.14301],"type":"Point"}
}