{
  "type": "Feature",
  "properties": {
    "gn:admin1_code":"7.0",
    "gn:admin2_code":"59.0",
    "gn:admin3_code":"5974.0",
    "gn:admin4_code":"5974004.0",
    "gn:asciiname":"Altengeseke",
    "gn:country_code":"DE",
    "gn:dem":170,
    "gn:feature_class":"P",
    "gn:feature_code":"PPL",
    "gn:name":"Altengeseke",
    "gn:population":0,
    "gn:timezone":"Europe/Berlin",
    "iso:country":"DE",
    "wof:name":"Altengeseke",
    "wof:placetype":"neighbourhood"
},
  "geometry": {"coordinates":[8.2467,51.55646],"type":"Point"}
}