{
  "type": "Feature",
  "properties": {
    "iso:country":"DE",
    "wof:name":"Mittelkattenberg",
    "wof:placetype":"neighbourhood"
},
  "geometry": {"coordinates":[7.04002897895432,51.15433676904524],"type":"Point"}
}