{
  "type": "Feature",
  "properties": {
    "gn:admin1_code":"2",
    "gn:admin2_code":"91.0",
    "gn:admin3_code":"9189.0",
    "gn:admin4_code":"9189141.0",
    "gn:asciiname":"Muhlau",
    "gn:country_code":"DE",
    "gn:dem":597,
    "gn:feature_class":"P",
    "gn:feature_code":"PPLL",
    "gn:name":"M\u00fchlau",
    "gn:population":0,
    "gn:timezone":"Europe/Berlin",
    "iso:country":"DE",
    "wof:name":"Muhlau",
    "wof:placetype":"neighbourhood"
},
  "geometry": {"coordinates":[12.39967,47.72893],"type":"Point"}
}