{
  "type": "Feature",
  "properties": {
    "gn:admin1_code":"8",
    "gn:admin2_code":"0.0",
    "gn:admin3_code":"7131.0",
    "gn:admin4_code":"7131090.0",
    "gn:asciiname":"Lantershofen",
    "gn:country_code":"DE",
    "gn:dem":151,
    "gn:feature_class":"P",
    "gn:feature_code":"PPL",
    "gn:name":"Lantershofen",
    "gn:population":0,
    "gn:timezone":"Europe/Berlin",
    "iso:country":"DE",
    "wof:name":"Lantershofen",
    "wof:placetype":"neighbourhood"
},
  "geometry": {"coordinates":[7.10647,50.5559],"type":"Point"}
}