{
  "type": "Feature",
  "properties": {
    "gn:admin1_code":"7",
    "gn:admin2_code":"55.0",
    "gn:admin3_code":"5566.0",
    "gn:admin4_code":"5566072.0",
    "gn:asciiname":"Espel",
    "gn:country_code":"DE",
    "gn:dem":57,
    "gn:feature_class":"P",
    "gn:feature_code":"PPLL",
    "gn:name":"Espel",
    "gn:population":0,
    "gn:timezone":"Europe/Berlin",
    "iso:country":"DE",
    "name:ceb_x_preferred":[
        "Espel"
    ],
    "name:fas_x_preferred":[
        "\u0627\u0633\u067e\u0644"
    ],
    "name:fin_x_preferred":[
        "Espel"
    ],
    "name:fra_x_preferred":[
        "Espel"
    ],
    "name:nld_x_preferred":[
        "Espel"
    ],
    "name:pol_x_preferred":[
        "Espel"
    ],
    "name:ukr_x_preferred":[
        "\u0415\u0441\u043f\u0435\u043b"
    ],
    "wof:name":"Espel",
    "wof:placetype":"neighbourhood"
},
  "geometry": {"coordinates":[7.74054,52.34691],"type":"Point"}
}