{
  "type": "Feature",
  "properties": {
    "gn:admin1_code":"6",
    "gn:admin2_code":"0.0",
    "gn:admin3_code":"3252.0",
    "gn:admin4_code":"3252008.0",
    "gn:asciiname":"Thueste",
    "gn:country_code":"DE",
    "gn:dem":158,
    "gn:feature_class":"P",
    "gn:feature_code":"PPL",
    "gn:name":"Th\u00fcste",
    "gn:population":0,
    "gn:timezone":"Europe/Berlin",
    "iso:country":"DE",
    "wof:name":"Thueste",
    "wof:placetype":"neighbourhood"
},
  "geometry": {"coordinates":[9.63398,52.02588],"type":"Point"}
}