{
  "type": "Feature",
  "properties": {
    "gn:admin1_code":"5",
    "gn:admin2_code":"65.0",
    "gn:admin3_code":"6532.0",
    "gn:admin4_code":"6532009.0",
    "gn:asciiname":"Hirzenhain Bahnhof",
    "gn:country_code":"DE",
    "gn:dem":495,
    "gn:feature_class":"P",
    "gn:feature_code":"PPL",
    "gn:name":"Hirzenhain Bahnhof",
    "gn:population":0,
    "gn:timezone":"Europe/Berlin",
    "iso:country":"DE",
    "name:und_x_variant":[
        "Bahnhof Hirzenhain",
        "Hirzenhain Bahnhof"
    ],
    "wof:name":"Hirzenhain Bahnhof",
    "wof:placetype":"neighbourhood"
},
  "geometry": {"coordinates":[8.40536,50.7879],"type":"Point"}
}