{
  "type": "Feature",
  "properties": {
    "gn:admin1_code":"11.0",
    "gn:admin2_code":"0.0",
    "gn:admin3_code":"12064.0",
    "gn:admin4_code":"12064539.0",
    "gn:asciiname":"Alt Zeschdorf",
    "gn:country_code":"DE",
    "gn:dem":54,
    "gn:feature_class":"P",
    "gn:feature_code":"PPL",
    "gn:name":"Alt Zeschdorf",
    "gn:population":0,
    "gn:timezone":"Europe/Berlin",
    "iso:country":"DE",
    "wof:name":"Alt Zeschdorf",
    "wof:placetype":"neighbourhood"
},
  "geometry": {"coordinates":[14.44297,52.42613],"type":"Point"}
}