{
  "type": "Feature",
  "properties": {
    "gn:admin1_code":"1.0",
    "gn:admin2_code":"084",
    "gn:admin3_code":"8436.0",
    "gn:admin4_code":"8436095.0",
    "gn:asciiname":"Winterbach",
    "gn:country_code":"DE",
    "gn:dem":599,
    "gn:feature_class":"P",
    "gn:feature_code":"PPL",
    "gn:name":"Winterbach",
    "gn:population":0,
    "gn:timezone":"Europe/Berlin",
    "iso:country":"DE",
    "name:als_x_preferred":[
        "Winterbach"
    ],
    "name:ceb_x_preferred":[
        "Winterbach"
    ],
    "name:deu_x_preferred":[
        "Winterbach"
    ],
    "name:epo_x_preferred":[
        "Winterbach"
    ],
    "name:fra_x_preferred":[
        "Winterbach"
    ],
    "name:ita_x_preferred":[
        "Winterbach"
    ],
    "name:jpn_x_preferred":[
        "\u30f4\u30a3\u30f3\u30bf\u30fc\u30d0\u30c3\u30cf"
    ],
    "name:lmo_x_preferred":[
        "Winterbach"
    ],
    "name:nld_x_preferred":[
        "Winterbach"
    ],
    "name:pol_x_preferred":[
        "Winterbach"
    ],
    "name:por_x_preferred":[
        "Winterbach"
    ],
    "name:rus_x_preferred":[
        "\u0412\u0438\u043d\u0442\u0435\u0440\u0431\u0430\u0445"
    ],
    "name:srp_x_preferred":[
        "\u0412\u0438\u043d\u0442\u0435\u0440\u0431\u0430\u0445"
    ],
    "name:swe_x_preferred":[
        "Winterbach"
    ],
    "name:ukr_x_preferred":[
        "\u0412\u0456\u043d\u0442\u0435\u0440\u0431\u0430\u0445"
    ],
    "name:vol_x_preferred":[
        "Winterbach"
    ],
    "wof:name":"Winterbach",
    "wof:placetype":"neighbourhood"
},
  "geometry": {"coordinates":[9.48558,47.79725],"type":"Point"}
}