{
  "type": "Feature",
  "properties": {
    "gn:admin1_code":"8.0",
    "gn:admin2_code":"00",
    "gn:admin3_code":"7131.0",
    "gn:admin4_code":"7131077.0",
    "gn:asciiname":"Westum",
    "gn:country_code":"DE",
    "gn:dem":106,
    "gn:feature_class":"P",
    "gn:feature_code":"PPL",
    "gn:name":"Westum",
    "gn:population":0,
    "gn:timezone":"Europe/Berlin",
    "iso:country":"DE",
    "wof:name":"Westum",
    "wof:placetype":"neighbourhood"
},
  "geometry": {"coordinates":[7.22902,50.5369],"type":"Point"}
}