{
  "type": "Feature",
  "properties": {
    "gn:admin1_code":"2",
    "gn:admin2_code":"92.0",
    "gn:admin3_code":"9279.0",
    "gn:admin4_code":"9279126.0",
    "gn:asciiname":"Reithen",
    "gn:country_code":"DE",
    "gn:dem":445,
    "gn:feature_class":"P",
    "gn:feature_code":"PPL",
    "gn:name":"Reithen",
    "gn:population":0,
    "gn:timezone":"Europe/Berlin",
    "iso:country":"DE",
    "wof:name":"Reithen",
    "wof:placetype":"neighbourhood"
},
  "geometry": {"coordinates":[12.53956,48.57445],"type":"Point"}
}