{
  "type": "Feature",
  "properties": {
    "gn:admin1_code":"2",
    "gn:admin2_code":"94.0",
    "gn:admin3_code":"9474.0",
    "gn:admin4_code":"9474123.0",
    "gn:asciiname":"Gotzendorf",
    "gn:country_code":"DE",
    "gn:dem":355,
    "gn:feature_class":"P",
    "gn:feature_code":"PPL",
    "gn:name":"G\u00f6tzendorf",
    "gn:population":0,
    "gn:timezone":"Europe/Berlin",
    "iso:country":"DE",
    "wof:name":"Gotzendorf",
    "wof:placetype":"neighbourhood"
},
  "geometry": {"coordinates":[11.11517,49.81906],"type":"Point"}
}