{
  "type": "Feature",
  "properties": {
    "gn:country":"DE",
    "gn:fcode":"PPL",
    "gn:population":0,
    "iso:country":"DE",
    "name:ceb_x_preferred":[
        "Waldrohrbach"
    ],
    "name:deu_x_preferred":[
        "Waldrohrbach"
    ],
    "name:epo_x_preferred":[
        "Waldrohrbach"
    ],
    "name:eus_x_preferred":[
        "Waldrohrbach"
    ],
    "name:fas_x_preferred":[
        "\u0648\u0627\u0644\u062f\u0631\u0648\u0647\u0631\u0628\u0627\u062e"
    ],
    "name:fra_x_preferred":[
        "Waldrohrbach"
    ],
    "name:hun_x_preferred":[
        "Waldrohrbach"
    ],
    "name:ita_x_preferred":[
        "Waldrohrbach"
    ],
    "name:kaz_x_preferred":[
        "\u0412\u0430\u043b\u044c\u0434\u0440\u043e\u0440\u0431\u0430\u0445"
    ],
    "name:kir_x_preferred":[
        "\u0412\u0430\u043b\u044c\u0434\u0440\u043e\u0440\u0431\u0430\u0445"
    ],
    "name:msa_x_preferred":[
        "Waldrohrbach"
    ],
    "name:nld_x_preferred":[
        "Waldrohrbach"
    ],
    "name:pol_x_preferred":[
        "Waldrohrbach"
    ],
    "name:por_x_preferred":[
        "Waldrohrbach"
    ],
    "name:ron_x_preferred":[
        "Waldrohrbach"
    ],
    "name:rus_x_preferred":[
        "\u0412\u0430\u043b\u044c\u0434\u0440\u043e\u0440\u0431\u0430\u0445"
    ],
    "name:spa_x_preferred":[
        "Waldrohrbach"
    ],
    "name:srp_x_preferred":[
        "\u0412\u0430\u043b\u0434\u0440\u043e\u0440\u0431\u0430\u0445"
    ],
    "name:ukr_x_preferred":[
        "\u0412\u0430\u043b\u044c\u0434\u0440\u043e\u0440\u0431\u0430\u0445"
    ],
    "name:uzb_x_preferred":[
        "Waldrohrbach"
    ],
    "name:vie_x_preferred":[
        "Waldrohrbach"
    ],
    "name:vol_x_preferred":[
        "Waldrohrbach"
    ],
    "name:war_x_preferred":[
        "Waldrohrbach"
    ],
    "name:zho_x_preferred":[
        "\u74e6\u5c14\u5fb7\u7f57\u5c14\u5df4\u8d6b"
    ],
    "qs_pg:aaroncc":"DE",
    "qs_pg:gn_country":"DE",
    "qs_pg:gn_fcode":"PPL",
    "qs_pg:gn_pop":0,
    "qs_pg:name":"Waldrohrbach",
    "qs_pg:name_adm0":"Deutschland",
    "qs_pg:name_adm1":"Rheinland-Pfalz",
    "qs_pg:photos":7,
    "qs_pg:photos_1k":1,
    "qs_pg:photos_9k":1,
    "qs_pg:photos_9r":1,
    "qs_pg:photos_all":7,
    "qs_pg:photos_sr":1,
    "qs_pg:pop_sr":0,
    "qs_pg:qs_pg_placetype":"locality",
    "qs_pg:qs_pg_placetype_gp":"Town",
    "qs_pg:woe_adm0":23424829,
    "woe:adm0_id":23424829,
    "woe:name_adm0":"Deutschland",
    "woe:name_adm1":"Rheinland-Pfalz",
    "woe:placetype":"Town",
    "wof:name":"Waldrohrbach",
    "wof:placetype":"neighbourhood"
},
  "geometry": {"coordinates":[7.16506,49.28282],"type":"Point"}
}