{
  "type": "Feature",
  "properties": {
    "gn:admin1_code":"14.0",
    "gn:admin2_code":"0.0",
    "gn:admin3_code":"15084.0",
    "gn:admin4_code":"15084235.0",
    "gn:asciiname":"Boesau",
    "gn:country_code":"DE",
    "gn:dem":150,
    "gn:feature_class":"P",
    "gn:feature_code":"PPL",
    "gn:name":"B\u00f6sau",
    "gn:population":0,
    "gn:timezone":"Europe/Berlin",
    "iso:country":"DE",
    "wof:name":"Boesau",
    "wof:placetype":"neighbourhood"
},
  "geometry": {"coordinates":[12.16207,51.16329],"type":"Point"}
}