{
  "type": "Feature",
  "properties": {
    "gn:admin1_code":"1",
    "gn:admin2_code":"83.0",
    "gn:admin3_code":"8326.0",
    "gn:admin4_code":"8326052.0",
    "gn:asciiname":"Schoren",
    "gn:country_code":"DE",
    "gn:dem":786,
    "gn:feature_class":"P",
    "gn:feature_code":"PPL",
    "gn:name":"Schoren",
    "gn:population":0,
    "gn:timezone":"Europe/Berlin",
    "iso:country":"DE",
    "wof:name":"Schoren",
    "wof:placetype":"neighbourhood"
},
  "geometry": {"coordinates":[8.39235,48.12382],"type":"Point"}
}