{
  "type": "Feature",
  "properties": {
    "gn:admin1_code":"15",
    "gn:admin2_code":"0.0",
    "gn:admin3_code":"16075.0",
    "gn:admin4_code":"16075133.0",
    "gn:asciiname":"Titschendorf",
    "gn:country_code":"DE",
    "gn:dem":600,
    "gn:feature_class":"P",
    "gn:feature_code":"PPL",
    "gn:name":"Titschendorf",
    "gn:population":0,
    "gn:timezone":"Europe/Berlin",
    "iso:country":"DE",
    "wof:name":"Titschendorf",
    "wof:placetype":"neighbourhood"
},
  "geometry": {"coordinates":[11.52678,50.38652],"type":"Point"}
}