{
  "type": "Feature",
  "properties": {
    "gn:admin1_code":"2",
    "gn:admin2_code":"91.0",
    "gn:admin3_code":"9187.0",
    "gn:admin4_code":"9187163.0",
    "gn:asciiname":"Sonnen",
    "gn:country_code":"DE",
    "gn:dem":508,
    "gn:feature_class":"P",
    "gn:feature_code":"PPL",
    "gn:name":"Sonnen",
    "gn:population":0,
    "gn:timezone":"Europe/Berlin",
    "iso:country":"DE",
    "name:ara_x_preferred":[
        "\u0632\u0648\u0646\u0646"
    ],
    "name:ceb_x_preferred":[
        "Sonnen"
    ],
    "name:deu_x_preferred":[
        "Sonnen"
    ],
    "name:epo_x_preferred":[
        "Sonnen"
    ],
    "name:eus_x_preferred":[
        "Sonnen"
    ],
    "name:fas_x_preferred":[
        "\u0632\u0648\u0646\u0646"
    ],
    "name:fin_x_preferred":[
        "Sonnen"
    ],
    "name:fra_x_preferred":[
        "Sonnen"
    ],
    "name:hun_x_preferred":[
        "Sonnen"
    ],
    "name:hye_x_preferred":[
        "\u0536\u0578\u0576\u0565\u0576"
    ],
    "name:ind_x_preferred":[
        "Sonnen"
    ],
    "name:ita_x_preferred":[
        "Sonnen"
    ],
    "name:kaz_x_preferred":[
        "\u0417\u043e\u043d\u043d\u0435\u043d"
    ],
    "name:kir_x_preferred":[
        "\u0417\u043e\u043d\u043d\u0435\u043d"
    ],
    "name:lmo_x_preferred":[
        "Sonnen"
    ],
    "name:msa_x_preferred":[
        "Sonnen"
    ],
    "name:nld_x_preferred":[
        "Sonnen"
    ],
    "name:pol_x_preferred":[
        "Sonnen"
    ],
    "name:por_x_preferred":[
        "Sonnen"
    ],
    "name:ron_x_preferred":[
        "Sonnen"
    ],
    "name:rus_x_preferred":[
        "\u0417\u043e\u043d\u043d\u0435\u043d"
    ],
    "name:spa_x_preferred":[
        "Sonnen"
    ],
    "name:srp_x_preferred":[
        "\u0417\u043e\u043d\u0435\u043d"
    ],
    "name:ukr_x_preferred":[
        "\u0417\u043e\u043d\u043d\u0435\u043d"
    ],
    "name:uzb_x_preferred":[
        "Sonnen"
    ],
    "name:vie_x_preferred":[
        "Sonnen"
    ],
    "name:vol_x_preferred":[
        "Sonnen"
    ],
    "name:war_x_preferred":[
        "Sonnen"
    ],
    "wof:name":"Sonnen",
    "wof:placetype":"neighbourhood"
},
  "geometry": {"coordinates":[12.17521,47.88075],"type":"Point"}
}