{
  "type": "Feature",
  "properties": {
    "gn:admin1_code":"2",
    "gn:admin2_code":"93.0",
    "gn:admin3_code":"9376.0",
    "gn:admin4_code":"9376149.0",
    "gn:asciiname":"Thann",
    "gn:country_code":"DE",
    "gn:dem":365,
    "gn:feature_class":"P",
    "gn:feature_code":"PPL",
    "gn:name":"Thann",
    "gn:population":0,
    "gn:timezone":"Europe/Berlin",
    "iso:country":"DE",
    "name:ceb_x_preferred":[
        "Thann"
    ],
    "name:deu_x_preferred":[
        "Thann"
    ],
    "name:fra_x_preferred":[
        "Thann"
    ],
    "name:pol_x_preferred":[
        "Thann"
    ],
    "name:slk_x_preferred":[
        "Thann"
    ],
    "wof:name":"Thann",
    "wof:placetype":"neighbourhood"
},
  "geometry": {"coordinates":[12.27585,49.21535],"type":"Point"}
}