{
  "type": "Feature",
  "properties": {
    "gn:admin1_code":"2.0",
    "gn:admin2_code":"97.0",
    "gn:admin3_code":"9777.0",
    "gn:admin4_code":"9777149.0",
    "gn:asciiname":"Bichel",
    "gn:country_code":"DE",
    "gn:dem":810,
    "gn:feature_class":"P",
    "gn:feature_code":"PPL",
    "gn:name":"Bichel",
    "gn:population":0,
    "gn:timezone":"Europe/Berlin",
    "iso:country":"DE",
    "name:und_x_variant":[
        "Bichels",
        "Bichel"
    ],
    "wof:name":"Bichel",
    "wof:placetype":"neighbourhood"
},
  "geometry": {"coordinates":[10.5969,47.69549],"type":"Point"}
}