{
  "type": "Feature",
  "properties": {
    "gn:admin1_code":"2",
    "gn:admin2_code":"93.0",
    "gn:admin3_code":"9376.0",
    "gn:admin4_code":"9376149.0",
    "gn:asciiname":"Treidling",
    "gn:country_code":"DE",
    "gn:dem":359,
    "gn:feature_class":"P",
    "gn:feature_code":"PPL",
    "gn:name":"Treidling",
    "gn:population":0,
    "gn:timezone":"Europe/Berlin",
    "iso:country":"DE",
    "wof:name":"Treidling",
    "wof:placetype":"neighbourhood"
},
  "geometry": {"coordinates":[12.32102,49.19263],"type":"Point"}
}