{
  "type": "Feature",
  "properties": {
    "gn:admin1_code":"2",
    "gn:admin2_code":"93.0",
    "gn:admin3_code":"9376.0",
    "gn:admin4_code":"9376141.0",
    "gn:asciiname":"Kappl",
    "gn:country_code":"DE",
    "gn:dem":446,
    "gn:feature_class":"P",
    "gn:feature_code":"PPL",
    "gn:name":"Kappl",
    "gn:population":0,
    "gn:timezone":"Europe/Berlin",
    "iso:country":"DE",
    "name:ceb_x_preferred":[
        "Kappl"
    ],
    "name:ces_x_preferred":[
        "Kappl"
    ],
    "name:deu_x_preferred":[
        "Kappl"
    ],
    "name:est_x_preferred":[
        "Kappl"
    ],
    "name:fas_x_preferred":[
        "\u06a9\u0627\u067e\u0644"
    ],
    "name:fra_x_preferred":[
        "Kappl"
    ],
    "name:hun_x_preferred":[
        "Kappl"
    ],
    "name:ita_x_preferred":[
        "Kappl"
    ],
    "name:kaz_x_preferred":[
        "\u041a\u0430\u043f\u043f\u043b\u044c"
    ],
    "name:nld_x_preferred":[
        "Kappl"
    ],
    "name:pnb_x_preferred":[
        "\u06a9\u0627\u067e\u0644"
    ],
    "name:pol_x_preferred":[
        "Kappl"
    ],
    "name:por_x_preferred":[
        "Kappl"
    ],
    "name:rus_x_preferred":[
        "\u041a\u0430\u043f\u043b\u044c"
    ],
    "name:slk_x_preferred":[
        "Kappl"
    ],
    "name:spa_x_preferred":[
        "Kappl"
    ],
    "name:swe_x_preferred":[
        "Kappl"
    ],
    "name:ukr_x_preferred":[
        "\u041a\u0430\u043f\u043f\u043b\u044c"
    ],
    "name:uzb_x_preferred":[
        "Kappl"
    ],
    "name:vol_x_preferred":[
        "Kappl"
    ],
    "name:war_x_preferred":[
        "Kappl"
    ],
    "name:zho_x_preferred":[
        "\u5361\u666e\u5c14"
    ],
    "wof:name":"Kappl",
    "wof:placetype":"neighbourhood"
},
  "geometry": {"coordinates":[12.13016,49.19126],"type":"Point"}
}