{
  "type": "Feature",
  "properties": {
    "gn:admin1_code":"2",
    "gn:admin2_code":"91.0",
    "gn:admin3_code":"9189.0",
    "gn:admin4_code":"9189140.0",
    "gn:asciiname":"Grashof",
    "gn:country_code":"DE",
    "gn:dem":686,
    "gn:feature_class":"P",
    "gn:feature_code":"PPL",
    "gn:name":"Grashof",
    "gn:population":0,
    "gn:timezone":"Europe/Berlin",
    "iso:country":"DE",
    "name:und_x_variant":[
        "Gras",
        "Grashof"
    ],
    "wof:name":"Grashof",
    "wof:placetype":"neighbourhood"
},
  "geometry": {"coordinates":[12.64878,47.75156],"type":"Point"}
}