{
  "type": "Feature",
  "properties": {
    "gn:admin1_code":"1",
    "gn:admin2_code":"81.0",
    "gn:admin3_code":"8136.0",
    "gn:admin4_code":"8136065.0",
    "gn:asciiname":"Kleindeinbach",
    "gn:country_code":"DE",
    "gn:dem":431,
    "gn:feature_class":"P",
    "gn:feature_code":"PPL",
    "gn:name":"Kleindeinbach",
    "gn:population":0,
    "gn:timezone":"Europe/Berlin",
    "iso:country":"DE",
    "wof:name":"Kleindeinbach",
    "wof:placetype":"neighbourhood"
},
  "geometry": {"coordinates":[9.7503,48.79407],"type":"Point"}
}