{
  "type": "Feature",
  "properties": {
    "gn:admin1_code":"2",
    "gn:admin2_code":"96.0",
    "gn:admin3_code":"9673.0",
    "gn:admin4_code":"9673123.0",
    "gn:asciiname":"Bruchs",
    "gn:country_code":"DE",
    "gn:dem":529,
    "gn:feature_class":"P",
    "gn:feature_code":"PPL",
    "gn:name":"Br\u00fcchs",
    "gn:population":0,
    "gn:timezone":"Europe/Berlin",
    "iso:country":"DE",
    "wof:name":"Bruchs",
    "wof:placetype":"neighbourhood"
},
  "geometry": {"coordinates":[10.15981,50.53677],"type":"Point"}
}