{
  "type": "Feature",
  "properties": {
    "gn:admin1_code":"12",
    "gn:admin2_code":"0.0",
    "gn:admin3_code":"13072.0",
    "gn:admin4_code":"13072067.0",
    "gn:asciiname":"Nienhagen",
    "gn:country_code":"DE",
    "gn:dem":44,
    "gn:feature_class":"P",
    "gn:feature_code":"PPL",
    "gn:name":"Nienhagen",
    "gn:population":0,
    "gn:timezone":"Europe/Berlin",
    "iso:country":"DE",
    "name:ceb_x_preferred":[
        "Nienhagen"
    ],
    "name:deu_x_preferred":[
        "Nienhagen"
    ],
    "name:epo_x_preferred":[
        "Nienhagen"
    ],
    "name:est_x_preferred":[
        "Nienhagen"
    ],
    "name:eus_x_preferred":[
        "Nienhagen"
    ],
    "name:fra_x_preferred":[
        "Nienhagen"
    ],
    "name:hun_x_preferred":[
        "Nienhagen"
    ],
    "name:ita_x_preferred":[
        "Nienhagen"
    ],
    "name:mkd_x_preferred":[
        "\u041d\u0438\u043d\u0445\u0430\u0433\u0435\u043d"
    ],
    "name:nds_x_preferred":[
        "Nienhagen"
    ],
    "name:nld_x_preferred":[
        "Nienhagen"
    ],
    "name:pol_x_preferred":[
        "Nienhagen"
    ],
    "name:rus_x_preferred":[
        "\u041d\u0438\u043d\u0445\u0430\u0433\u0435\u043d"
    ],
    "name:srp_x_preferred":[
        "\u041d\u0438\u043d\u0445\u0430\u0433\u0435\u043d"
    ],
    "name:swe_x_preferred":[
        "Nienhagen"
    ],
    "name:vol_x_preferred":[
        "Nienhagen"
    ],
    "wof:name":"Nienhagen",
    "wof:placetype":"neighbourhood"
},
  "geometry": {"coordinates":[12.08528,53.65876],"type":"Point"}
}