{
  "type": "Feature",
  "properties": {
    "gn:admin1_code":"2",
    "gn:admin2_code":"93.0",
    "gn:admin3_code":"9376.0",
    "gn:admin4_code":"9376173.0",
    "gn:asciiname":"Reisach",
    "gn:country_code":"DE",
    "gn:dem":475,
    "gn:feature_class":"P",
    "gn:feature_code":"PPL",
    "gn:name":"Reisach",
    "gn:population":0,
    "gn:timezone":"Europe/Berlin",
    "iso:country":"DE",
    "wof:name":"Reisach",
    "wof:placetype":"neighbourhood"
},
  "geometry": {"coordinates":[12.27725,49.53438],"type":"Point"}
}