{
  "type": "Feature",
  "properties": {
    "gn:country":"DE",
    "gn:fcode":"PPL",
    "gn:population":351,
    "iso:country":"DE",
    "name:bak_x_preferred":[
        "\u0412\u0430\u0440\u0435\u043d\u0431\u0435\u0440\u0433"
    ],
    "name:ceb_x_preferred":[
        "Wahrenberg"
    ],
    "name:deu_x_preferred":[
        "Wahrenberg"
    ],
    "name:epo_x_preferred":[
        "Wahrenberg"
    ],
    "name:fas_x_preferred":[
        "\u0648\u0627\u0631\u0646\u0628\u0631\u06af"
    ],
    "name:ita_x_preferred":[
        "Wahrenberg"
    ],
    "name:kaz_x_preferred":[
        "\u0412\u0430\u0440\u0435\u043d\u0431\u0435\u0440\u0433"
    ],
    "name:kir_x_preferred":[
        "\u0412\u0430\u0440\u0435\u043d\u0431\u0435\u0440\u0433"
    ],
    "name:nld_x_preferred":[
        "Wahrenberg"
    ],
    "name:ron_x_preferred":[
        "Wahrenberg"
    ],
    "name:rus_x_preferred":[
        "\u0412\u0430\u0440\u0435\u043d\u0431\u0435\u0440\u0433"
    ],
    "name:uzb_x_preferred":[
        "Wahrenberg"
    ],
    "name:vie_x_preferred":[
        "Wahrenberg"
    ],
    "name:vol_x_preferred":[
        "Wahrenberg"
    ],
    "name:war_x_preferred":[
        "Wahrenberg"
    ],
    "qs_pg:aaroncc":"DE",
    "qs_pg:gn_country":"DE",
    "qs_pg:gn_fcode":"PPL",
    "qs_pg:gn_pop":351,
    "qs_pg:name":"Wahrenberg",
    "qs_pg:name_adm0":"Deutschland",
    "qs_pg:name_adm1":"Sachsen-Anhalt",
    "qs_pg:photos_9k":1,
    "qs_pg:photos_9r":1,
    "qs_pg:photos_all":1,
    "qs_pg:photos_sr":0,
    "qs_pg:pop_sr":2,
    "qs_pg:qs_pg_placetype":"locality",
    "qs_pg:qs_pg_placetype_gp":"Town",
    "qs_pg:woe_adm0":23424829,
    "woe:adm0_id":23424829,
    "woe:name_adm0":"Deutschland",
    "woe:name_adm1":"Sachsen-Anhalt",
    "woe:placetype":"Town",
    "wof:name":"Wahrenberg",
    "wof:placetype":"neighbourhood",
    "wof:population":351
},
  "geometry": {"coordinates":[11.67737,52.9843],"type":"Point"}
}