{
  "type": "Feature",
  "properties": {
    "gn:admin1_code":"14",
    "gn:admin2_code":"0.0",
    "gn:admin3_code":"15084.0",
    "gn:admin4_code":"15084130.0",
    "gn:asciiname":"Torna",
    "gn:country_code":"DE",
    "gn:dem":143,
    "gn:feature_class":"P",
    "gn:feature_code":"PPL",
    "gn:name":"Torna",
    "gn:population":0,
    "gn:timezone":"Europe/Berlin",
    "iso:country":"DE",
    "name:ceb_x_preferred":[
        "Torna"
    ],
    "name:deu_x_preferred":[
        "Torna"
    ],
    "name:swe_x_preferred":[
        "Torna"
    ],
    "wof:name":"Torna",
    "wof:placetype":"neighbourhood"
},
  "geometry": {"coordinates":[12.19959,51.08235],"type":"Point"}
}