{
  "type": "Feature",
  "properties": {
    "gn:admin1_code":"1",
    "gn:admin2_code":"83.0",
    "gn:admin3_code":"8325.0",
    "gn:admin4_code":"8325012.0",
    "gn:asciiname":"Dobel",
    "gn:country_code":"DE",
    "gn:dem":543,
    "gn:feature_class":"P",
    "gn:feature_code":"PPL",
    "gn:name":"Dobel",
    "gn:population":0,
    "gn:timezone":"Europe/Berlin",
    "iso:country":"DE",
    "wof:name":"Dobel",
    "wof:placetype":"neighbourhood"
},
  "geometry": {"coordinates":[8.55201,48.35259],"type":"Point"}
}