{
  "type": "Feature",
  "properties": {
    "gn:admin1_code":"1",
    "gn:admin2_code":"83.0",
    "gn:admin3_code":"8325.0",
    "gn:admin4_code":"8325012.0",
    "gn:asciiname":"Dobel",
    "gn:country_code":"DE",
    "gn:dem":543,
    "gn:feature_class":"P",
    "gn:feature_code":"PPL",
    "gn:name":"Dobel",
    "gn:population":0,
    "gn:timezone":"Europe/Berlin",
    "iso:country":"DE",
    "name:als_x_preferred":[
        "Dobel"
    ],
    "name:ceb_x_preferred":[
        "Dobel"
    ],
    "name:deu_x_preferred":[
        "Dobel"
    ],
    "name:epo_x_preferred":[
        "Dobel"
    ],
    "name:eus_x_preferred":[
        "Dobel"
    ],
    "name:fra_x_preferred":[
        "Dobel"
    ],
    "name:hun_x_preferred":[
        "Dobel"
    ],
    "name:hye_x_preferred":[
        "\u0534\u0578\u0562\u0565\u056c"
    ],
    "name:ita_x_preferred":[
        "Dobel"
    ],
    "name:kaz_x_preferred":[
        "\u0414\u043e\u0431\u0435\u043b\u044c"
    ],
    "name:kir_x_preferred":[
        "\u0414\u043e\u0431\u0435\u043b\u044c"
    ],
    "name:lat_x_preferred":[
        "Dobel"
    ],
    "name:lmo_x_preferred":[
        "Dobel"
    ],
    "name:msa_x_preferred":[
        "Dobel"
    ],
    "name:nld_x_preferred":[
        "Dobel"
    ],
    "name:pol_x_preferred":[
        "Dobel"
    ],
    "name:por_x_preferred":[
        "Dobel"
    ],
    "name:ron_x_preferred":[
        "Dobel"
    ],
    "name:rus_x_preferred":[
        "\u0414\u043e\u0431\u0435\u043b\u044c"
    ],
    "name:spa_x_preferred":[
        "Dobel"
    ],
    "name:srp_x_preferred":[
        "\u0414\u043e\u0431\u0435\u043b"
    ],
    "name:ukr_x_preferred":[
        "\u0414\u043e\u0431\u0435\u043b\u044c"
    ],
    "name:uzb_x_preferred":[
        "Dobel"
    ],
    "name:vie_x_preferred":[
        "Dobel"
    ],
    "name:vol_x_preferred":[
        "Dobel"
    ],
    "name:war_x_preferred":[
        "Dobel"
    ],
    "name:zho_x_preferred":[
        "\u591a\u4f2f\u5c14"
    ],
    "wof:name":"Dobel",
    "wof:placetype":"neighbourhood"
},
  "geometry": {"coordinates":[8.55201,48.35259],"type":"Point"}
}