{
  "type": "Feature",
  "properties": {
    "gn:admin1_code":"13",
    "gn:admin2_code":"0.0",
    "gn:admin3_code":"14522.0",
    "gn:admin4_code":"14522320.0",
    "gn:asciiname":"Marbach",
    "gn:country_code":"DE",
    "gn:dem":405,
    "gn:feature_class":"P",
    "gn:feature_code":"PPL",
    "gn:name":"Marbach",
    "gn:population":0,
    "gn:timezone":"Europe/Berlin",
    "iso:country":"DE",
    "name:als_x_preferred":[
        "Marbach"
    ],
    "name:ceb_x_preferred":[
        "Marbach"
    ],
    "name:deu_x_preferred":[
        "Marbach"
    ],
    "name:epo_x_preferred":[
        "Marbach"
    ],
    "name:fra_x_preferred":[
        "Marbach"
    ],
    "name:ita_x_preferred":[
        "Marbach"
    ],
    "name:lmo_x_preferred":[
        "Marbach"
    ],
    "name:nld_x_preferred":[
        "Marbach"
    ],
    "name:pol_x_preferred":[
        "Marbach"
    ],
    "name:por_x_preferred":[
        "Marbach"
    ],
    "name:rus_x_preferred":[
        "\u041c\u0430\u0440\u0431\u0430\u0445"
    ],
    "name:sco_x_preferred":[
        "Marbach"
    ],
    "name:spa_x_preferred":[
        "Marbach"
    ],
    "name:swe_x_preferred":[
        "Marbach"
    ],
    "wof:name":"Marbach",
    "wof:placetype":"neighbourhood"
},
  "geometry": {"coordinates":[13.13389,50.78699],"type":"Point"}
}