{
  "type": "Feature",
  "properties": {
    "gn:admin1_code":"2",
    "gn:admin2_code":"91.0",
    "gn:admin3_code":"9174.0",
    "gn:admin4_code":"9174143.0",
    "gn:asciiname":"Unterhandenzhofen",
    "gn:country_code":"DE",
    "gn:dem":496,
    "gn:feature_class":"P",
    "gn:feature_code":"PPL",
    "gn:name":"Unterhandenzhofen",
    "gn:population":0,
    "gn:timezone":"Europe/Berlin",
    "iso:country":"DE",
    "wof:name":"Unterhandenzhofen",
    "wof:placetype":"neighbourhood"
},
  "geometry": {"coordinates":[11.39184,48.31357],"type":"Point"}
}