{
  "type": "Feature",
  "properties": {
    "gn:admin1_code":"6",
    "gn:admin2_code":"0.0",
    "gn:admin3_code":"3254.0",
    "gn:admin4_code":"3254044.0",
    "gn:asciiname":"Netze",
    "gn:country_code":"DE",
    "gn:dem":179,
    "gn:feature_class":"P",
    "gn:feature_code":"PPL",
    "gn:name":"Netze",
    "gn:population":0,
    "gn:timezone":"Europe/Berlin",
    "iso:country":"DE",
    "wof:name":"Netze",
    "wof:placetype":"neighbourhood"
},
  "geometry": {"coordinates":[9.97302,51.98095],"type":"Point"}
}