{
  "type": "Feature",
  "properties": {
    "gn:admin1_code":"14",
    "gn:admin2_code":"0.0",
    "gn:admin3_code":"15001.0",
    "gn:admin4_code":"15001000.0",
    "gn:asciiname":"Muehlstedt",
    "gn:country_code":"DE",
    "gn:dem":71,
    "gn:feature_class":"P",
    "gn:feature_code":"PPL",
    "gn:name":"M\u00fchlstedt",
    "gn:population":0,
    "gn:timezone":"Europe/Berlin",
    "iso:country":"DE",
    "wof:name":"Muehlstedt",
    "wof:placetype":"neighbourhood"
},
  "geometry": {"coordinates":[12.25879,51.926],"type":"Point"}
}