{
  "type": "Feature",
  "properties": {
    "gn:admin1_code":"5",
    "gn:admin2_code":"65.0",
    "gn:admin3_code":"6534.0",
    "gn:admin4_code":"6534010.0",
    "gn:asciiname":"Erdhausen",
    "gn:country_code":"DE",
    "gn:dem":250,
    "gn:feature_class":"P",
    "gn:feature_code":"PPL",
    "gn:name":"Erdhausen",
    "gn:population":0,
    "gn:timezone":"Europe/Berlin",
    "iso:country":"DE",
    "wof:name":"Erdhausen",
    "wof:placetype":"neighbourhood"
},
  "geometry": {"coordinates":[8.56568,50.75041],"type":"Point"}
}