{
  "type": "Feature",
  "properties": {
    "gn:admin1_code":"7",
    "gn:admin2_code":"57.0",
    "gn:admin3_code":"5770.0",
    "gn:admin4_code":"5770004.0",
    "gn:asciiname":"Kroppeloh",
    "gn:country_code":"DE",
    "gn:dem":100,
    "gn:feature_class":"P",
    "gn:feature_code":"PPL",
    "gn:name":"Kroppeloh",
    "gn:population":0,
    "gn:timezone":"Europe/Berlin",
    "iso:country":"DE",
    "wof:name":"Kroppeloh",
    "wof:placetype":"neighbourhood"
},
  "geometry": {"coordinates":[8.75266,52.25285],"type":"Point"}
}