{
  "type": "Feature",
  "properties": {
    "gn:admin1_code":"1",
    "gn:admin2_code":"81.0",
    "gn:admin3_code":"8126.0",
    "gn:admin4_code":"8126039.0",
    "gn:asciiname":"Stachenhausen",
    "gn:country_code":"DE",
    "gn:dem":373,
    "gn:feature_class":"P",
    "gn:feature_code":"PPL",
    "gn:name":"Stachenhausen",
    "gn:population":0,
    "gn:timezone":"Europe/Berlin",
    "iso:country":"DE",
    "wof:name":"Stachenhausen",
    "wof:placetype":"neighbourhood"
},
  "geometry": {"coordinates":[9.70478,49.33121],"type":"Point"}
}