{
  "type": "Feature",
  "properties": {
    "gn:admin1_code":"7",
    "gn:admin2_code":"59.0",
    "gn:admin3_code":"5915.0",
    "gn:admin4_code":"5915000.0",
    "gn:asciiname":"Mark",
    "gn:country_code":"DE",
    "gn:dem":65,
    "gn:feature_class":"P",
    "gn:feature_code":"PPL",
    "gn:name":"Mark",
    "gn:population":0,
    "gn:timezone":"Europe/Berlin",
    "iso:country":"DE",
    "wof:name":"Mark",
    "wof:placetype":"neighbourhood"
},
  "geometry": {"coordinates":[7.85279,51.68304000000001],"type":"Point"}
}