{
  "type": "Feature",
  "properties": {
    "gn:admin1_code":"7",
    "gn:admin2_code":"59.0",
    "gn:admin3_code":"5915.0",
    "gn:admin4_code":"5915000.0",
    "gn:asciiname":"Mark",
    "gn:country_code":"DE",
    "gn:dem":65,
    "gn:feature_class":"P",
    "gn:feature_code":"PPL",
    "gn:name":"Mark",
    "gn:population":0,
    "gn:timezone":"Europe/Berlin",
    "iso:country":"DE",
    "name:afr_x_preferred":[
        "Mark"
    ],
    "name:ara_x_preferred":[
        "\u0645\u0627\u0631\u0643"
    ],
    "name:ceb_x_preferred":[
        "Mark"
    ],
    "name:dan_x_preferred":[
        "Mark"
    ],
    "name:deu_x_preferred":[
        "Mark"
    ],
    "name:est_x_preferred":[
        "Mark"
    ],
    "name:fas_x_preferred":[
        "\u0645\u0627\u0631\u06a9"
    ],
    "name:fin_x_preferred":[
        "Mark"
    ],
    "name:fra_x_preferred":[
        "Mark"
    ],
    "name:heb_x_preferred":[
        "\u05de\u05e8\u05e7"
    ],
    "name:hun_x_preferred":[
        "Mark"
    ],
    "name:isl_x_preferred":[
        "Mark"
    ],
    "name:ita_x_preferred":[
        "Mark"
    ],
    "name:jpn_x_preferred":[
        "\u30de\u30eb\u30af"
    ],
    "name:kor_x_preferred":[
        "\ub9c8\ub974\ud06c"
    ],
    "name:lav_x_preferred":[
        "Marks"
    ],
    "name:lim_x_preferred":[
        "Mark"
    ],
    "name:mzn_x_preferred":[
        "\u0645\u0627\u0631\u06a9"
    ],
    "name:nld_x_preferred":[
        "Mark"
    ],
    "name:nno_x_preferred":[
        "Mark"
    ],
    "name:nor_x_preferred":[
        "Mark"
    ],
    "name:pol_x_preferred":[
        "Mark"
    ],
    "name:por_x_preferred":[
        "Mark"
    ],
    "name:ron_x_preferred":[
        "Mark"
    ],
    "name:rus_x_preferred":[
        "Mark"
    ],
    "name:slk_x_preferred":[
        "Mark"
    ],
    "name:spa_x_preferred":[
        "Mark"
    ],
    "name:swe_x_preferred":[
        "Mark"
    ],
    "name:tam_x_preferred":[
        "\u0bae\u0bbe\u0bb1\u0bcd\u0b95\u0bc1"
    ],
    "name:tur_x_preferred":[
        "Mark"
    ],
    "name:vie_x_preferred":[
        "Mark"
    ],
    "name:zho_x_preferred":[
        "Mark"
    ],
    "wof:name":"Mark",
    "wof:placetype":"neighbourhood"
},
  "geometry": {"coordinates":[7.85279,51.68304000000001],"type":"Point"}
}