{
  "type": "Feature",
  "properties": {
    "gn:admin1_code":"2.0",
    "gn:admin2_code":"91.0",
    "gn:admin3_code":"9187.0",
    "gn:admin4_code":"9187169.0",
    "gn:asciiname":"Achenmuhle",
    "gn:country_code":"DE",
    "gn:dem":524,
    "gn:feature_class":"P",
    "gn:feature_code":"PPL",
    "gn:name":"Achenm\u00fchle",
    "gn:population":0,
    "gn:timezone":"Europe/Berlin",
    "iso:country":"DE",
    "wof:name":"Achenmuhle",
    "wof:placetype":"neighbourhood"
},
  "geometry": {"coordinates":[12.22847,47.79563],"type":"Point"}
}