{
  "type": "Feature",
  "properties": {
    "gn:admin1_code":"2",
    "gn:admin2_code":"94.0",
    "gn:admin3_code":"9475.0",
    "gn:admin4_code":"9475123.0",
    "gn:asciiname":"Schafhubel",
    "gn:country_code":"DE",
    "gn:dem":515,
    "gn:feature_class":"P",
    "gn:feature_code":"PPL",
    "gn:name":"Schafh\u00fcbel",
    "gn:population":0,
    "gn:timezone":"Europe/Berlin",
    "iso:country":"DE",
    "wof:name":"Schafhubel",
    "wof:placetype":"neighbourhood"
},
  "geometry": {"coordinates":[11.90757,50.36384],"type":"Point"}
}