{
  "type": "Feature",
  "properties": {
    "gn:gn_country":"DE",
    "gn:gn_fcode":"PPLA4",
    "gn:gn_pop":76,
    "gn:population":76,
    "iso:country":"DE",
    "name:baq_x_preferred":[
        "Wennb\u00fcttel"
    ],
    "name:chi_x_preferred":[
        "\u6587\u6bd4\u7279\u5c14"
    ],
    "name:dan_x_preferred":[
        "Wennb\u00fcttel"
    ],
    "name:dut_x_preferred":[
        "Wennb\u00fcttel"
    ],
    "name:eng_x_preferred":[
        "Wennb\u00fcttel"
    ],
    "name:epo_x_preferred":[
        "Wennb\u00fcttel"
    ],
    "name:fre_x_preferred":[
        "Wennb\u00fcttel"
    ],
    "name:ger_x_preferred":[
        "Wennb\u00fcttel"
    ],
    "name:hun_x_preferred":[
        "Wennb\u00fcttel"
    ],
    "name:ind_x_preferred":[
        "Wennb\u00fcttel"
    ],
    "name:ita_x_preferred":[
        "Wennb\u00fcttel"
    ],
    "name:kaz_x_preferred":[
        "\u0412\u0435\u043d\u0431\u044e\u0442\u0442\u0435\u043b\u044c"
    ],
    "name:kir_x_preferred":[
        "\u0412\u0435\u043d\u0431\u044e\u0442\u0442\u0435\u043b\u044c"
    ],
    "name:mac_x_preferred":[
        "\u0412\u0435\u043d\u0431\u0438\u0442\u0435\u043b"
    ],
    "name:may_x_preferred":[
        "Wennb\u00fcttel"
    ],
    "name:nob_x_preferred":[
        "Wennb\u00fcttel"
    ],
    "name:per_x_preferred":[
        "\u0648\u0646\u0628\u0648\u062a\u0644"
    ],
    "name:pol_x_preferred":[
        "Wennb\u00fcttel"
    ],
    "name:por_x_preferred":[
        "Wennb\u00fcttel"
    ],
    "name:rum_x_preferred":[
        "Wennb\u00fcttel"
    ],
    "name:rus_x_preferred":[
        "\u0412\u0435\u043d\u0431\u044e\u0442\u0442\u0435\u043b\u044c"
    ],
    "name:srp_x_preferred":[
        "\u0412\u0435\u043d\u0431\u0438\u0442\u0435\u043b"
    ],
    "name:tur_x_preferred":[
        "Wennb\u00fcttel"
    ],
    "name:ukr_x_preferred":[
        "\u0412\u0435\u043d\u043d\u0431\u044e\u0442\u0442\u0435\u043b\u044c"
    ],
    "name:uzb_x_preferred":[
        "Wennb\u00fcttel"
    ],
    "name:vie_x_preferred":[
        "Wennb\u00fcttel"
    ],
    "name:vol_x_preferred":[
        "Wennb\u00fcttel"
    ],
    "name:war_x_preferred":[
        "Wennb\u00fcttel"
    ],
    "qs_pg:aaroncc":"DE",
    "qs_pg:gn_country":"DE",
    "qs_pg:gn_fcode":"PPLA4",
    "qs_pg:gn_pop":76,
    "qs_pg:name":"Wennb\u00fcttel",
    "qs_pg:photos_9r":0,
    "qs_pg:photos_sr":0,
    "qs_pg:pop_sr":1,
    "qs_pg:qs_pg_placetype":"locality",
    "wof:name":"Wennb\u00fcttel",
    "wof:placetype":"locality",
    "wof:population":76
},
  "geometry": {"coordinates":[9.33333,54.13333],"type":"Point"}
}