{
  "type": "Feature",
  "properties": {
    "gn:admin1_code":"2",
    "gn:admin2_code":"96.0",
    "gn:admin3_code":"9679.0",
    "gn:admin4_code":"9679185.0",
    "gn:asciiname":"Rothof",
    "gn:country_code":"DE",
    "gn:dem":272,
    "gn:feature_class":"P",
    "gn:feature_code":"PPL",
    "gn:name":"Rothof",
    "gn:population":0,
    "gn:timezone":"Europe/Berlin",
    "iso:country":"DE",
    "name:und_x_variant":[
        "Rothhof",
        "Rothof"
    ],
    "wof:name":"Rothof",
    "wof:placetype":"neighbourhood"
},
  "geometry": {"coordinates":[10.05493,49.81197],"type":"Point"}
}