{
  "type": "Feature",
  "properties": {
    "iso:country":"DE",
    "wof:name":"Erfttal",
    "wof:placetype":"neighbourhood"
},
  "geometry": {"coordinates":[6.72720058145623,51.16821116045495],"type":"Point"}
}