{
  "type": "Feature",
  "properties": {
    "gn:admin1_code":"11.0",
    "gn:admin2_code":"0.0",
    "gn:admin3_code":"12065.0",
    "gn:admin4_code":"12065100.0",
    "gn:asciiname":"Ziegelscheune",
    "gn:country_code":"DE",
    "gn:dem":50,
    "gn:feature_class":"P",
    "gn:feature_code":"PPL",
    "gn:name":"Ziegelscheune",
    "gn:population":0,
    "gn:timezone":"Europe/Berlin",
    "iso:country":"DE",
    "wof:name":"Ziegelscheune",
    "wof:placetype":"neighbourhood"
},
  "geometry": {"coordinates":[13.21269,53.01798],"type":"Point"}
}