{
  "type": "Feature",
  "properties": {
    "gn:admin1_code":"1",
    "gn:admin2_code":"83.0",
    "gn:admin3_code":"8335.0",
    "gn:admin4_code":"8335021.0",
    "gn:asciiname":"Reute",
    "gn:country_code":"DE",
    "gn:dem":638,
    "gn:feature_class":"P",
    "gn:feature_code":"PPL",
    "gn:name":"Reute",
    "gn:population":0,
    "gn:timezone":"Europe/Berlin",
    "iso:country":"DE",
    "name:als_x_preferred":[
        "Reute"
    ],
    "name:cat_x_preferred":[
        "Reute"
    ],
    "name:chv_x_preferred":[
        "\u0420\u043e\u0439\u0442\u0435"
    ],
    "name:deu_x_preferred":[
        "Reute"
    ],
    "name:epo_x_preferred":[
        "Reute"
    ],
    "name:eus_x_preferred":[
        "Reute"
    ],
    "name:fin_x_preferred":[
        "Reute"
    ],
    "name:fra_x_preferred":[
        "Reute"
    ],
    "name:ita_x_preferred":[
        "Reute"
    ],
    "name:lmo_x_preferred":[
        "Reute"
    ],
    "name:nld_x_preferred":[
        "Reute"
    ],
    "name:nno_x_preferred":[
        "Reute"
    ],
    "name:pms_x_preferred":[
        "Reute"
    ],
    "name:pol_x_preferred":[
        "Reute"
    ],
    "name:por_x_preferred":[
        "Reute"
    ],
    "name:ron_x_preferred":[
        "Reute"
    ],
    "name:rus_x_preferred":[
        "\u0420\u043e\u0439\u0442\u0435"
    ],
    "name:spa_x_preferred":[
        "Reute"
    ],
    "name:sqi_x_preferred":[
        "Reute"
    ],
    "name:swe_x_preferred":[
        "Reute"
    ],
    "name:uzb_x_preferred":[
        "Reute"
    ],
    "name:vol_x_preferred":[
        "Reute"
    ],
    "name:war_x_preferred":[
        "Reute"
    ],
    "wof:name":"Reute",
    "wof:placetype":"neighbourhood"
},
  "geometry": {"coordinates":[8.90752,47.88839],"type":"Point"}
}