{
  "type": "Feature",
  "properties": {
    "gn:admin1_code":"5",
    "gn:admin2_code":"66.0",
    "gn:admin3_code":"6631.0",
    "gn:admin4_code":"6631005.0",
    "gn:asciiname":"Thaiden",
    "gn:country_code":"DE",
    "gn:dem":481,
    "gn:feature_class":"P",
    "gn:feature_code":"PPL",
    "gn:name":"Thaiden",
    "gn:population":0,
    "gn:timezone":"Europe/Berlin",
    "iso:country":"DE",
    "wof:name":"Thaiden",
    "wof:placetype":"neighbourhood"
},
  "geometry": {"coordinates":[10.0143,50.54273],"type":"Point"}
}