{
  "type": "Feature",
  "properties": {
    "gn:admin1_code":"2",
    "gn:admin2_code":"95.0",
    "gn:admin3_code":"9561.0",
    "gn:admin4_code":"9561000.0",
    "gn:asciiname":"Dombach im Loch",
    "gn:country_code":"DE",
    "gn:dem":457,
    "gn:feature_class":"P",
    "gn:feature_code":"PPL",
    "gn:name":"Dombach im Loch",
    "gn:population":0,
    "gn:timezone":"Europe/Berlin",
    "iso:country":"DE",
    "wof:name":"Dombach im Loch",
    "wof:placetype":"neighbourhood"
},
  "geometry": {"coordinates":[10.53334,49.28058],"type":"Point"}
}