{
  "type": "Feature",
  "properties": {
    "gn:admin1_code":"2.0",
    "gn:admin2_code":"93.0",
    "gn:admin3_code":"9375.0",
    "gn:admin4_code":"9375117.0",
    "gn:asciiname":"Altach",
    "gn:country_code":"DE",
    "gn:dem":327,
    "gn:feature_class":"P",
    "gn:feature_code":"PPL",
    "gn:name":"Altach",
    "gn:population":0,
    "gn:timezone":"Europe/Berlin",
    "iso:country":"DE",
    "name:als_x_preferred":[
        "Altach"
    ],
    "name:bul_x_preferred":[
        "\u0410\u043b\u0442\u0430\u0445"
    ],
    "name:ceb_x_preferred":[
        "Altach"
    ],
    "name:deu_x_preferred":[
        "Altach"
    ],
    "name:est_x_preferred":[
        "Altach"
    ],
    "name:fas_x_preferred":[
        "\u0627\u0644\u062a\u0627\u0686"
    ],
    "name:fra_x_preferred":[
        "Altach"
    ],
    "name:fur_x_preferred":[
        "Altach"
    ],
    "name:hun_x_preferred":[
        "Altach"
    ],
    "name:ind_x_preferred":[
        "Altach"
    ],
    "name:ita_x_preferred":[
        "Altach"
    ],
    "name:jpn_x_preferred":[
        "\u30a2\u30eb\u30bf\u30c3\u30cf"
    ],
    "name:kor_x_preferred":[
        "\uc54c\ud0c0\ud750"
    ],
    "name:lit_x_preferred":[
        "Altachas"
    ],
    "name:lmo_x_preferred":[
        "Altach"
    ],
    "name:nld_x_preferred":[
        "Altach"
    ],
    "name:nno_x_preferred":[
        "Altach"
    ],
    "name:pol_x_preferred":[
        "Altach"
    ],
    "name:por_x_preferred":[
        "Altach"
    ],
    "name:ron_x_preferred":[
        "Altach"
    ],
    "name:rus_x_preferred":[
        "\u0410\u043b\u044c\u0442\u0430\u0445"
    ],
    "name:slk_x_preferred":[
        "Altach"
    ],
    "name:spa_x_preferred":[
        "Altach"
    ],
    "name:swe_x_preferred":[
        "Altach"
    ],
    "name:ukr_x_preferred":[
        "\u0410\u043b\u044c\u0442\u0430\u0445"
    ],
    "name:uzb_x_preferred":[
        "Altach"
    ],
    "name:vie_x_preferred":[
        "Altach"
    ],
    "name:vol_x_preferred":[
        "Altach"
    ],
    "name:war_x_preferred":[
        "Altach"
    ],
    "name:zho_x_preferred":[
        "\u963f\u723e\u7279\u963f\u8d6b"
    ],
    "wof:name":"Altach",
    "wof:placetype":"neighbourhood"
},
  "geometry": {"coordinates":[12.31267,49.00201],"type":"Point"}
}