{
  "type": "Feature",
  "properties": {
    "gn:admin1_code":"2",
    "gn:admin2_code":"93.0",
    "gn:admin3_code":"9375.0",
    "gn:admin4_code":"9375196.0",
    "gn:asciiname":"Oberdeggenbach",
    "gn:country_code":"DE",
    "gn:dem":385,
    "gn:feature_class":"P",
    "gn:feature_code":"PPL",
    "gn:name":"Oberdeggenbach",
    "gn:population":0,
    "gn:timezone":"Europe/Berlin",
    "iso:country":"DE",
    "wof:name":"Oberdeggenbach",
    "wof:placetype":"neighbourhood"
},
  "geometry": {"coordinates":[12.18528,48.82361],"type":"Point"}
}