{
  "type": "Feature",
  "properties": {
    "gn:admin1_code":"1",
    "gn:admin2_code":"84.0",
    "gn:admin3_code":"8436.0",
    "gn:admin4_code":"8436011.0",
    "gn:asciiname":"Kopfingen",
    "gn:country_code":"DE",
    "gn:dem":577,
    "gn:feature_class":"P",
    "gn:feature_code":"PPL",
    "gn:name":"K\u00f6pfingen",
    "gn:population":0,
    "gn:timezone":"Europe/Berlin",
    "iso:country":"DE",
    "name:und_x_variant":[
        "K\u00f6pflingen",
        "K\u00f6pfingen"
    ],
    "wof:name":"Kopfingen",
    "wof:placetype":"neighbourhood"
},
  "geometry": {"coordinates":[9.67259,47.81739],"type":"Point"}
}