{
  "type": "Feature",
  "properties": {
    "iso:country":"DE",
    "qs_pg:aaroncc":"DE",
    "qs_pg:name":"Kiwittsheide",
    "qs_pg:name_adm0":"Deutschland",
    "qs_pg:name_adm1":"Nordrhein-Westfalen",
    "qs_pg:photos":11,
    "qs_pg:photos_1k":2,
    "qs_pg:photos_9k":1,
    "qs_pg:photos_9r":1,
    "qs_pg:photos_all":11,
    "qs_pg:photos_sr":1,
    "qs_pg:pop_sr":0,
    "qs_pg:qs_pg_placetype":"locality",
    "qs_pg:qs_pg_placetype_gp":"Town",
    "qs_pg:woe_adm0":23424829,
    "woe:adm0_id":23424829,
    "woe:name_adm0":"Deutschland",
    "woe:name_adm1":"Nordrhein-Westfalen",
    "woe:placetype":"Town",
    "wof:name":"Kiwittsheide",
    "wof:placetype":"neighbourhood"
},
  "geometry": {"coordinates":[8.172283,52.0164],"type":"Point"}
}