{
  "type": "Feature",
  "properties": {
    "gn:admin1_code":"1.0",
    "gn:admin2_code":"82.0",
    "gn:admin3_code":"8235.0",
    "gn:admin4_code":"8235006.0",
    "gn:asciiname":"Altensteigdorf",
    "gn:country_code":"DE",
    "gn:dem":561,
    "gn:feature_class":"P",
    "gn:feature_code":"PPL",
    "gn:name":"Altensteigdorf",
    "gn:population":0,
    "gn:timezone":"Europe/Berlin",
    "iso:country":"DE",
    "wof:name":"Altensteigdorf",
    "wof:placetype":"neighbourhood"
},
  "geometry": {"coordinates":[8.61199,48.59335],"type":"Point"}
}