{
  "type": "Feature",
  "properties": {
    "gn:admin1_code":"2",
    "gn:admin2_code":"94.0",
    "gn:admin3_code":"9473.0",
    "gn:admin4_code":"9473175.0",
    "gn:asciiname":"Hergramsdorf",
    "gn:country_code":"DE",
    "gn:dem":305,
    "gn:feature_class":"P",
    "gn:feature_code":"PPL",
    "gn:name":"Hergramsdorf",
    "gn:population":0,
    "gn:timezone":"Europe/Berlin",
    "iso:country":"DE",
    "wof:name":"Hergramsdorf",
    "wof:placetype":"neighbourhood"
},
  "geometry": {"coordinates":[10.89177,50.24291],"type":"Point"}
}