{
  "type": "Feature",
  "properties": {
    "iso:country":"DE",
    "name:deu_x_preferred":[
        "Philippinenhof/warteberg"
    ],
    "qs:gn_adm0_cc":"DE",
    "qs:gn_local":2892518,
    "qs:local_max":6102,
    "qs:local_sum":10350,
    "qs:localhoods":8,
    "qs:name":"Philippinenhof/warteberg",
    "qs:name_adm0":"Deutschland",
    "qs:name_adm1":"Hessen",
    "qs:name_adm2":"Stadtkreis Kassel",
    "qs:name_lau":"Stadtteil Philippinenhof",
    "qs:name_local":"Kassel",
    "qs:photo_max":21,
    "qs:photo_sum":41,
    "qs:placetype":"Suburb",
    "qs:quad_count":13,
    "qs:woe_adm0":23424829,
    "qs:woe_adm1":2345485,
    "qs:woe_adm2":20071100,
    "qs:woe_lau":26822717,
    "qs:woe_local":665077,
    "qs:woe_ver":"7.10.0",
    "wof:lang":[
        "ger"
    ],
    "wof:name":"Philippinenhof/warteberg",
    "wof:placetype":"neighbourhood"
},
  "geometry": {"coordinates":[9.500802,51.350186],"type":"Point"}
}