{
  "type": "Feature",
  "properties": {
    "gn:admin1_code":"6",
    "gn:admin2_code":"0.0",
    "gn:admin3_code":"3451.0",
    "gn:admin4_code":"3451005.0",
    "gn:asciiname":"Kleibrok",
    "gn:country_code":"DE",
    "gn:dem":12,
    "gn:feature_class":"P",
    "gn:feature_code":"PPLL",
    "gn:name":"Kleibrok",
    "gn:population":0,
    "gn:timezone":"Europe/Berlin",
    "iso:country":"DE",
    "wof:name":"Kleibrok",
    "wof:placetype":"neighbourhood"
},
  "geometry": {"coordinates":[8.20744,53.26195],"type":"Point"}
}