{
  "type": "Feature",
  "properties": {
    "gn:admin1_code":"2",
    "gn:admin2_code":"91.0",
    "gn:admin3_code":"9163.0",
    "gn:admin4_code":"9163000.0",
    "gn:asciiname":"Hohenofen",
    "gn:country_code":"DE",
    "gn:dem":467,
    "gn:feature_class":"P",
    "gn:feature_code":"PPL",
    "gn:name":"Hohenofen",
    "gn:population":0,
    "gn:timezone":"Europe/Berlin",
    "iso:country":"DE",
    "wof:name":"Hohenofen",
    "wof:placetype":"neighbourhood"
},
  "geometry": {"coordinates":[12.0902,47.83044],"type":"Point"}
}