{
  "type": "Feature",
  "properties": {
    "gn:admin1_code":"9",
    "gn:admin2_code":"0.0",
    "gn:admin3_code":"10043.0",
    "gn:admin4_code":"10043115.0",
    "gn:asciiname":"Neumuenster",
    "gn:country_code":"DE",
    "gn:dem":293,
    "gn:feature_class":"P",
    "gn:feature_code":"PPL",
    "gn:name":"Neum\u00fcnster",
    "gn:population":0,
    "gn:timezone":"Europe/Berlin",
    "iso:country":"DE",
    "wof:name":"Neumuenster",
    "wof:placetype":"neighbourhood"
},
  "geometry": {"coordinates":[7.16916,49.40258],"type":"Point"}
}