{
  "type": "Feature",
  "properties": {
    "gn:admin1_code":"7",
    "gn:admin2_code":"53.0",
    "gn:admin3_code":"5374.0",
    "gn:admin4_code":"5374020.0",
    "gn:asciiname":"Leienhoehe",
    "gn:country_code":"DE",
    "gn:dem":208,
    "gn:feature_class":"P",
    "gn:feature_code":"PPL",
    "gn:name":"Leienh\u00f6he",
    "gn:population":0,
    "gn:timezone":"Europe/Berlin",
    "iso:country":"DE",
    "wof:name":"Leienhoehe",
    "wof:placetype":"neighbourhood"
},
  "geometry": {"coordinates":[7.27552,50.98351],"type":"Point"}
}