{
  "type": "Feature",
  "properties": {
    "gn:admin1_code":"14.0",
    "gn:admin2_code":"00",
    "gn:admin3_code":"15088.0",
    "gn:admin4_code":"15088020.0",
    "gn:asciiname":"Zoellschen",
    "gn:country_code":"DE",
    "gn:dem":111,
    "gn:feature_class":"P",
    "gn:feature_code":"PPL",
    "gn:name":"Z\u00f6llschen",
    "gn:population":0,
    "gn:timezone":"Europe/Berlin",
    "iso:country":"DE",
    "wof:name":"Zoellschen",
    "wof:placetype":"neighbourhood"
},
  "geometry": {"coordinates":[12.11917,51.27262],"type":"Point"}
}