{
  "type": "Feature",
  "properties": {
    "gn:admin1_code":"7",
    "gn:admin2_code":"51.0",
    "gn:admin3_code":"5166.0",
    "gn:admin4_code":"5166012.0",
    "gn:asciiname":"Vinnbrueck",
    "gn:country_code":"DE",
    "gn:dem":34,
    "gn:feature_class":"P",
    "gn:feature_code":"PPL",
    "gn:name":"Vinnbr\u00fcck",
    "gn:population":0,
    "gn:timezone":"Europe/Berlin",
    "iso:country":"DE",
    "wof:name":"Vinnbrueck",
    "wof:placetype":"neighbourhood"
},
  "geometry": {"coordinates":[6.49592,51.40442],"type":"Point"}
}