{
  "type": "Feature",
  "properties": {
    "gn:admin1_code":"8",
    "gn:admin2_code":"0.0",
    "gn:admin3_code":"7235.0",
    "gn:admin4_code":"7235025.0",
    "gn:asciiname":"Rehlingen-Littdorf",
    "gn:country_code":"DE",
    "gn:dem":383,
    "gn:feature_class":"P",
    "gn:feature_code":"PPL",
    "gn:name":"Rehlingen-Littdorf",
    "gn:population":0,
    "gn:timezone":"Europe/Berlin",
    "iso:country":"DE",
    "wof:name":"Rehlingen-Littdorf",
    "wof:placetype":"neighbourhood"
},
  "geometry": {"coordinates":[6.48333,49.61667],"type":"Point"}
}