{
  "type": "Feature",
  "properties": {
    "gn:admin1_code":"1",
    "gn:admin2_code":"82.0",
    "gn:admin3_code":"8216.0",
    "gn:admin4_code":"8216041.0",
    "gn:asciiname":"Hatzenweier",
    "gn:country_code":"DE",
    "gn:dem":134,
    "gn:feature_class":"P",
    "gn:feature_code":"PPL",
    "gn:name":"Hatzenweier",
    "gn:population":0,
    "gn:timezone":"Europe/Berlin",
    "iso:country":"DE",
    "wof:name":"Hatzenweier",
    "wof:placetype":"neighbourhood"
},
  "geometry": {"coordinates":[8.10974,48.6812],"type":"Point"}
}