{
  "type": "Feature",
  "properties": {
    "gn:admin1_code":"6.0",
    "gn:admin2_code":"0.0",
    "gn:admin3_code":"3454.0",
    "gn:admin4_code":"3454035.0",
    "gn:asciiname":"Zuschlaege",
    "gn:country_code":"DE",
    "gn:dem":13,
    "gn:feature_class":"P",
    "gn:feature_code":"PPL",
    "gn:name":"Zuschl\u00e4ge",
    "gn:population":0,
    "gn:timezone":"Europe/Berlin",
    "iso:country":"DE",
    "wof:name":"Zuschlaege",
    "wof:placetype":"neighbourhood"
},
  "geometry": {"coordinates":[7.21667,52.71666999999999],"type":"Point"}
}