{
  "type": "Feature",
  "properties": {
    "gn:admin1_code":"2",
    "gn:admin2_code":"97.0",
    "gn:admin3_code":"9773.0",
    "gn:admin4_code":"9773122.0",
    "gn:asciiname":"Pfaffenhofen",
    "gn:country_code":"DE",
    "gn:dem":413,
    "gn:feature_class":"P",
    "gn:feature_code":"PPL",
    "gn:name":"Pfaffenhofen",
    "gn:population":0,
    "gn:timezone":"Europe/Berlin",
    "iso:country":"DE",
    "name:ceb_x_preferred":[
        "Pfaffenhofen"
    ],
    "name:deu_x_preferred":[
        "Pfaffenhofen"
    ],
    "name:epo_x_preferred":[
        "Pfaffenhofen"
    ],
    "name:fra_x_preferred":[
        "Pfaffenhofen"
    ],
    "name:ita_x_preferred":[
        "Pfaffenhofen"
    ],
    "name:msa_x_preferred":[
        "Pfaffenhofen"
    ],
    "name:nld_x_preferred":[
        "Pfaffenhofen"
    ],
    "name:pol_x_preferred":[
        "Pfaffenhofen"
    ],
    "name:ron_x_preferred":[
        "Pfaffenhofen"
    ],
    "name:rus_x_preferred":[
        "\u041f\u0444\u0430\u0444\u0444\u0435\u043d\u0445\u043e\u0444\u0435\u043d"
    ],
    "name:swe_x_preferred":[
        "Pfaffenhofen"
    ],
    "name:vol_x_preferred":[
        "Pfaffenhofen"
    ],
    "wof:name":"Pfaffenhofen",
    "wof:placetype":"neighbourhood"
},
  "geometry": {"coordinates":[10.71091,48.61077],"type":"Point"}
}