{
  "type": "Feature",
  "properties": {
    "iso:country":"DE",
    "name:als_x_preferred":[
        "Burtscheid"
    ],
    "name:dan_x_preferred":[
        "Burtscheid"
    ],
    "name:deu_x_preferred":[
        "Burtscheid"
    ],
    "name:eng_x_preferred":[
        "Burtscheid"
    ],
    "name:fra_x_preferred":[
        "Burtscheid"
    ],
    "name:gsw_x_preferred":[
        "Burtscheid"
    ],
    "name:ita_x_preferred":[
        "Burtscheid"
    ],
    "name:lim_x_preferred":[
        "B\u00f3tsjet"
    ],
    "name:nld_x_preferred":[
        "Abdijvorstendom Burtscheid"
    ],
    "name:nld_x_variant":[
        "Sticht Burtscheid"
    ],
    "name:rus_x_preferred":[
        "\u0411\u0443\u0440\u0442\u0448\u0430\u0439\u0434"
    ],
    "name:tur_x_preferred":[
        "Burtscheid"
    ],
    "name:unk_x_variant":[
        "Burtscheid"
    ],
    "name:zho_x_preferred":[
        "\u5e03\u7279\u585e\u5fb7"
    ],
    "qs:gn_fcode":"PPLX",
    "qs:gn_local":0,
    "qs:gn_namadm1":"07",
    "qs:gn_name":"Burtscheid",
    "qs:local_max":7923,
    "qs:local_sum":22653,
    "qs:localhoods":31,
    "qs:name":"Burtscheid",
    "qs:name_adm0":"Deutschland",
    "qs:name_adm1":"Nordrhein-Westfalen",
    "qs:name_adm2":"Stadtkreis Aachen",
    "qs:name_lau":"Stadtteil Aachen",
    "qs:name_local":"Aachen",
    "qs:photo_max":1543,
    "qs:photo_sum":7923,
    "qs:placetype":"Suburb",
    "qs:quad_count":90,
    "qs:woe_adm0":23424829,
    "qs:woe_adm1":2345487,
    "qs:woe_adm2":20071103,
    "qs:woe_lau":26821833,
    "qs:woe_local":633175,
    "qs:woe_ver":"7.10.0",
    "wd:wordcount":137,
    "wof:lang":[
        "ger"
    ],
    "wof:name":"Burtscheid",
    "wof:placetype":"neighbourhood"
},
  "geometry": {"coordinates":[6.085309,50.773567],"type":"Point"}
}