{
  "type": "Feature",
  "properties": {
    "gn:admin1_code":"2",
    "gn:admin2_code":"95.0",
    "gn:admin3_code":"9571.0",
    "gn:admin4_code":"9571199.0",
    "gn:asciiname":"Steinbach an der Holzecke",
    "gn:country_code":"DE",
    "gn:dem":480,
    "gn:feature_class":"P",
    "gn:feature_code":"PPL",
    "gn:name":"Steinbach an der Holzecke",
    "gn:population":0,
    "gn:timezone":"Europe/Berlin",
    "iso:country":"DE",
    "name:und_x_variant":[
        "Steinbach",
        "Steinbach an der Holzecke"
    ],
    "wof:name":"Steinbach an der Holzecke",
    "wof:placetype":"neighbourhood"
},
  "geometry": {"coordinates":[10.19187,49.23192],"type":"Point"}
}