{
  "type": "Feature",
  "properties": {
    "gn:admin1_code":"2",
    "gn:admin2_code":"92.0",
    "gn:admin3_code":"9263.0",
    "gn:admin4_code":"9263000.0",
    "gn:asciiname":"Hornstorf",
    "gn:country_code":"DE",
    "gn:dem":318,
    "gn:feature_class":"P",
    "gn:feature_code":"PPL",
    "gn:name":"Hornstorf",
    "gn:population":0,
    "gn:timezone":"Europe/Berlin",
    "iso:country":"DE",
    "name:ceb_x_preferred":[
        "Hornstorf"
    ],
    "name:deu_x_preferred":[
        "Hornstorf"
    ],
    "name:epo_x_preferred":[
        "Hornstorf"
    ],
    "name:fas_x_preferred":[
        "\u0647\u0648\u0631\u0646\u0634\u062a\u0648\u0631\u0641"
    ],
    "name:fra_x_preferred":[
        "Hornstorf"
    ],
    "name:hun_x_preferred":[
        "Hornstorf"
    ],
    "name:ita_x_preferred":[
        "Hornstorf"
    ],
    "name:kaz_x_preferred":[
        "\u0425\u043e\u0440\u043d\u0441\u0442\u043e\u0440\u0444"
    ],
    "name:kir_x_preferred":[
        "\u0425\u043e\u0440\u043d\u0441\u0442\u043e\u0440\u0444"
    ],
    "name:mkd_x_preferred":[
        "\u0425\u043e\u0440\u043d\u0441\u0442\u043e\u0440\u0444"
    ],
    "name:msa_x_preferred":[
        "Hornstorf"
    ],
    "name:nld_x_preferred":[
        "Hornstorf"
    ],
    "name:pol_x_preferred":[
        "Hornstorf"
    ],
    "name:por_x_preferred":[
        "Hornstorf"
    ],
    "name:ron_x_preferred":[
        "Hornstorf"
    ],
    "name:rus_x_preferred":[
        "\u0425\u043e\u0440\u043d\u0441\u0442\u043e\u0440\u0444"
    ],
    "name:spa_x_preferred":[
        "Hornstorf"
    ],
    "name:srp_x_preferred":[
        "\u0425\u043e\u0440\u043d\u0441\u0442\u043e\u0440\u0444"
    ],
    "name:ukr_x_preferred":[
        "\u0413\u043e\u0440\u043d\u0441\u0442\u043e\u0440\u0444"
    ],
    "name:uzb_x_preferred":[
        "Hornstorf"
    ],
    "name:vie_x_preferred":[
        "Hornstorf"
    ],
    "name:vol_x_preferred":[
        "Hornstorf"
    ],
    "name:war_x_preferred":[
        "Hornstorf"
    ],
    "name:zho_x_preferred":[
        "\u970d\u6069\u65af\u6258\u592b"
    ],
    "wof:name":"Hornstorf",
    "wof:placetype":"neighbourhood"
},
  "geometry": {"coordinates":[12.58205,48.90083],"type":"Point"}
}