{
  "type": "Feature",
  "properties": {
    "gn:admin1_code":"2",
    "gn:admin2_code":"92.0",
    "gn:admin3_code":"9263.0",
    "gn:admin4_code":"9263000.0",
    "gn:asciiname":"Hornstorf",
    "gn:country_code":"DE",
    "gn:dem":318,
    "gn:feature_class":"P",
    "gn:feature_code":"PPL",
    "gn:name":"Hornstorf",
    "gn:population":0,
    "gn:timezone":"Europe/Berlin",
    "iso:country":"DE",
    "wof:name":"Hornstorf",
    "wof:placetype":"neighbourhood"
},
  "geometry": {"coordinates":[12.58205,48.90083],"type":"Point"}
}