{
  "type": "Feature",
  "properties": {
    "gn:admin1_code":"10",
    "gn:admin2_code":"0.0",
    "gn:admin3_code":"1062.0",
    "gn:admin4_code":"1062009.0",
    "gn:asciiname":"Stellau",
    "gn:country_code":"DE",
    "gn:dem":59,
    "gn:feature_class":"P",
    "gn:feature_code":"PPL",
    "gn:name":"Stellau",
    "gn:population":0,
    "gn:timezone":"Europe/Berlin",
    "iso:country":"DE",
    "wof:name":"Stellau",
    "wof:placetype":"neighbourhood"
},
  "geometry": {"coordinates":[10.23347,53.59164000000001],"type":"Point"}
}