{
  "type": "Feature",
  "properties": {
    "gn:admin1_code":"2.0",
    "gn:admin2_code":"91.0",
    "gn:admin3_code":"9175.0",
    "gn:admin4_code":"9175121.0",
    "gn:asciiname":"Adling",
    "gn:country_code":"DE",
    "gn:dem":567,
    "gn:feature_class":"P",
    "gn:feature_code":"PPL",
    "gn:name":"Adling",
    "gn:population":0,
    "gn:timezone":"Europe/Berlin",
    "iso:country":"DE",
    "wof:name":"Adling",
    "wof:placetype":"neighbourhood"
},
  "geometry": {"coordinates":[11.86668,48.00087],"type":"Point"}
}