{
  "type": "Feature",
  "properties": {
    "gn:admin1_code":"6",
    "gn:admin2_code":"0.0",
    "gn:admin3_code":"3456.0",
    "gn:admin4_code":"3456025.0",
    "gn:asciiname":"Schwartenpohl",
    "gn:country_code":"DE",
    "gn:dem":22,
    "gn:feature_class":"P",
    "gn:feature_code":"PPL",
    "gn:name":"Schwartenpohl",
    "gn:population":0,
    "gn:timezone":"Europe/Berlin",
    "iso:country":"DE",
    "wof:name":"Schwartenpohl",
    "wof:placetype":"neighbourhood"
},
  "geometry": {"coordinates":[7.16523,52.54306],"type":"Point"}
}