{
  "type": "Feature",
  "properties": {
    "gn:admin1_code":"12.0",
    "gn:admin2_code":"0.0",
    "gn:admin3_code":"13072.0",
    "gn:admin4_code":"13072085.0",
    "gn:asciiname":"Neu Gaarz",
    "gn:country_code":"DE",
    "gn:dem":30,
    "gn:feature_class":"P",
    "gn:feature_code":"PPL",
    "gn:name":"Neu Gaarz",
    "gn:population":0,
    "gn:timezone":"Europe/Berlin",
    "iso:country":"DE",
    "name:ceb_x_preferred":[
        "Neu Gaarz"
    ],
    "name:deu_x_preferred":[
        "Neu Gaarz"
    ],
    "name:epo_x_preferred":[
        "Neu Gaarz"
    ],
    "name:fas_x_preferred":[
        "\u0646\u0648\u06cc \u06af\u0627\u0631\u062a\u0633"
    ],
    "name:fra_x_preferred":[
        "Neu Gaarz"
    ],
    "name:ita_x_preferred":[
        "Neu Gaarz"
    ],
    "name:kaz_x_preferred":[
        "\u041d\u043e\u0439-\u0413\u0430\u0440\u0446"
    ],
    "name:kir_x_preferred":[
        "\u041d\u043e\u0439-\u0413\u0430\u0440\u0446"
    ],
    "name:mkd_x_preferred":[
        "\u041d\u043e\u0458 \u0413\u0430\u0440\u0446"
    ],
    "name:msa_x_preferred":[
        "Neu Gaarz"
    ],
    "name:nld_x_preferred":[
        "Neu Gaarz"
    ],
    "name:pol_x_preferred":[
        "Neu Gaarz"
    ],
    "name:ron_x_preferred":[
        "Neu Gaarz"
    ],
    "name:rus_x_preferred":[
        "\u041d\u043e\u0439-\u0413\u0430\u0440\u0446"
    ],
    "name:spa_x_preferred":[
        "Alt Gaarz"
    ],
    "name:srp_x_preferred":[
        "\u041d\u043e\u0458 \u0413\u0430\u0440\u0446"
    ],
    "name:uzb_x_preferred":[
        "Neu Gaarz"
    ],
    "name:vie_x_preferred":[
        "Neu Gaarz"
    ],
    "name:vol_x_preferred":[
        "Neu Gaarz"
    ],
    "name:war_x_preferred":[
        "Neu Gaarz"
    ],
    "name:zho_x_preferred":[
        "\u8bfa\u4f0a\u52a0\u5c14\u8328"
    ],
    "wof:name":"Neu Gaarz",
    "wof:placetype":"neighbourhood"
},
  "geometry": {"coordinates":[11.63401,54.11404],"type":"Point"}
}