{
  "type": "Feature",
  "properties": {
    "gn:admin1_code":"6.0",
    "gn:admin2_code":"00",
    "gn:admin3_code":"3451.0",
    "gn:admin4_code":"3451001.0",
    "gn:asciiname":"Winkel",
    "gn:country_code":"DE",
    "gn:dem":5,
    "gn:feature_class":"P",
    "gn:feature_code":"PPL",
    "gn:name":"Winkel",
    "gn:population":0,
    "gn:timezone":"Europe/Berlin",
    "iso:country":"DE",
    "wof:name":"Winkel",
    "wof:placetype":"neighbourhood"
},
  "geometry": {"coordinates":[7.84343,53.22427],"type":"Point"}
}