{
  "type": "Feature",
  "properties": {
    "gn:admin1_code":"7",
    "gn:admin2_code":"53.0",
    "gn:admin3_code":"5374.0",
    "gn:admin4_code":"5374020.0",
    "gn:asciiname":"Muellemich",
    "gn:country_code":"DE",
    "gn:dem":179,
    "gn:feature_class":"P",
    "gn:feature_code":"PPL",
    "gn:name":"M\u00fcllemich",
    "gn:population":0,
    "gn:timezone":"Europe/Berlin",
    "iso:country":"DE",
    "wof:name":"Muellemich",
    "wof:placetype":"neighbourhood"
},
  "geometry": {"coordinates":[7.29973,50.98796],"type":"Point"}
}