{
  "type": "Feature",
  "properties": {
    "gn:admin1_code":"6.0",
    "gn:admin2_code":"0.0",
    "gn:admin3_code":"3459.0",
    "gn:admin4_code":"3459019.0",
    "gn:asciiname":"Kiffenbrink",
    "gn:country_code":"DE",
    "gn:dem":147,
    "gn:feature_class":"P",
    "gn:feature_code":"PPL",
    "gn:name":"Kiffenbrink",
    "gn:population":0,
    "gn:timezone":"Europe/Berlin",
    "iso:country":"DE",
    "wof:name":"Kiffenbrink",
    "wof:placetype":"neighbourhood"
},
  "geometry": {"coordinates":[8.0713,52.18793],"type":"Point"}
}