{
  "type": "Feature",
  "properties": {
    "gn:admin1_code":"2",
    "gn:admin2_code":"91.0",
    "gn:admin3_code":"9174.0",
    "gn:admin4_code":"9174111.0",
    "gn:asciiname":"Humersberg",
    "gn:country_code":"DE",
    "gn:dem":535,
    "gn:feature_class":"P",
    "gn:feature_code":"PPL",
    "gn:name":"Humersberg",
    "gn:population":0,
    "gn:timezone":"Europe/Berlin",
    "iso:country":"DE",
    "wof:name":"Humersberg",
    "wof:placetype":"neighbourhood"
},
  "geometry": {"coordinates":[11.22828,48.38695],"type":"Point"}
}