{
  "type": "Feature",
  "properties": {
    "gn:admin1_code":"2.0",
    "gn:admin2_code":"92.0",
    "gn:admin3_code":"9276.0",
    "gn:admin4_code":"9276111.0",
    "gn:asciiname":"Au",
    "gn:country_code":"DE",
    "gn:dem":624,
    "gn:feature_class":"P",
    "gn:feature_code":"PPLL",
    "gn:name":"Au",
    "gn:population":0,
    "gn:timezone":"Europe/Berlin",
    "iso:country":"DE",
    "name:cat_x_preferred":[
        "Au"
    ],
    "name:est_x_preferred":[
        "Au"
    ],
    "name:hun_x_preferred":[
        "Au"
    ],
    "wof:name":"Au",
    "wof:placetype":"neighbourhood"
},
  "geometry": {"coordinates":[12.92177,48.9752],"type":"Point"}
}