{
  "type": "Feature",
  "properties": {
    "gn:admin1_code":"15",
    "gn:admin2_code":"0.0",
    "gn:admin3_code":"16077.0",
    "gn:admin4_code":"16077003.0",
    "gn:asciiname":"Pontewitz",
    "gn:country_code":"DE",
    "gn:dem":249,
    "gn:feature_class":"P",
    "gn:feature_code":"PPL",
    "gn:name":"Pontewitz",
    "gn:population":0,
    "gn:timezone":"Europe/Berlin",
    "iso:country":"DE",
    "wof:name":"Pontewitz",
    "wof:placetype":"neighbourhood"
},
  "geometry": {"coordinates":[12.29337,50.95993],"type":"Point"}
}