{
  "type": "Feature",
  "properties": {
    "gn:admin1_code":"7",
    "gn:admin2_code":"53.0",
    "gn:admin3_code":"5374.0",
    "gn:admin4_code":"5374052.0",
    "gn:asciiname":"Hamboecken",
    "gn:country_code":"DE",
    "gn:dem":266,
    "gn:feature_class":"P",
    "gn:feature_code":"PPL",
    "gn:name":"Hamb\u00f6cken",
    "gn:population":0,
    "gn:timezone":"Europe/Berlin",
    "iso:country":"DE",
    "wof:name":"Hamboecken",
    "wof:placetype":"neighbourhood"
},
  "geometry": {"coordinates":[7.30654,51.07484],"type":"Point"}
}