{
  "type": "Feature",
  "properties": {
    "gn:admin1_code":"15",
    "gn:admin2_code":"0.0",
    "gn:admin3_code":"16065.0",
    "gn:admin4_code":"16065084.0",
    "gn:asciiname":"Feldengel",
    "gn:country_code":"DE",
    "gn:dem":276,
    "gn:feature_class":"P",
    "gn:feature_code":"PPL",
    "gn:name":"Feldengel",
    "gn:population":0,
    "gn:timezone":"Europe/Berlin",
    "iso:country":"DE",
    "wof:name":"Feldengel",
    "wof:placetype":"neighbourhood"
},
  "geometry": {"coordinates":[10.94568,51.27292],"type":"Point"}
}