{
  "type": "Feature",
  "properties": {
    "gn:admin1_code":"6",
    "gn:admin2_code":"0.0",
    "gn:admin3_code":"3453.0",
    "gn:admin4_code":"3453008.0",
    "gn:asciiname":"Kellerhoehe",
    "gn:country_code":"DE",
    "gn:dem":34,
    "gn:feature_class":"P",
    "gn:feature_code":"PPL",
    "gn:name":"Kellerh\u00f6he",
    "gn:population":0,
    "gn:timezone":"Europe/Berlin",
    "iso:country":"DE",
    "name:und_x_variant":[
        "Kolonie Keller",
        "Kellerh\u00f6he"
    ],
    "wof:name":"Kellerhoehe",
    "wof:placetype":"neighbourhood"
},
  "geometry": {"coordinates":[8.07943,52.90651],"type":"Point"}
}