{
  "type": "Feature",
  "properties": {
    "gn:admin1_code":"2",
    "gn:admin2_code":"92.0",
    "gn:admin3_code":"9262.0",
    "gn:admin4_code":"9262000.0",
    "gn:asciiname":"Neustift",
    "gn:country_code":"DE",
    "gn:dem":372,
    "gn:feature_class":"P",
    "gn:feature_code":"PPL",
    "gn:name":"Neustift",
    "gn:population":0,
    "gn:timezone":"Europe/Berlin",
    "iso:country":"DE",
    "name:ceb_x_preferred":[
        "Neustift"
    ],
    "name:deu_x_preferred":[
        "Neustift"
    ],
    "name:ita_x_preferred":[
        "Neustift"
    ],
    "name:nld_x_preferred":[
        "Neustift"
    ],
    "name:pol_x_preferred":[
        "Neustift"
    ],
    "name:swe_x_preferred":[
        "Neustift"
    ],
    "wof:name":"Neustift",
    "wof:placetype":"neighbourhood"
},
  "geometry": {"coordinates":[13.38624,48.57237],"type":"Point"}
}