{
  "type": "Feature",
  "properties": {
    "gn:admin1_code":"1",
    "gn:admin2_code":"83.0",
    "gn:admin3_code":"8337.0",
    "gn:admin4_code":"8337062.0",
    "gn:asciiname":"Geisslingen",
    "gn:country_code":"DE",
    "gn:dem":395,
    "gn:feature_class":"P",
    "gn:feature_code":"PPL",
    "gn:name":"Gei\u00dflingen",
    "gn:population":0,
    "gn:timezone":"Europe/Berlin",
    "iso:country":"DE",
    "wof:name":"Geisslingen",
    "wof:placetype":"neighbourhood"
},
  "geometry": {"coordinates":[8.39186,47.61995],"type":"Point"}
}