{
  "type": "Feature",
  "properties": {
    "gn:admin1_code":"2",
    "gn:admin2_code":"92.0",
    "gn:admin3_code":"9272.0",
    "gn:admin4_code":"9272151.0",
    "gn:asciiname":"Lammersreut",
    "gn:country_code":"DE",
    "gn:dem":572,
    "gn:feature_class":"P",
    "gn:feature_code":"PPL",
    "gn:name":"L\u00e4mmersreut",
    "gn:population":0,
    "gn:timezone":"Europe/Berlin",
    "iso:country":"DE",
    "name:und_x_variant":[
        "L\u00e4mmersreuth",
        "L\u00e4mmersreut"
    ],
    "wof:name":"Lammersreut",
    "wof:placetype":"neighbourhood"
},
  "geometry": {"coordinates":[13.56819,48.765],"type":"Point"}
}