{
  "type": "Feature",
  "properties": {
    "gn:admin1_code":"13",
    "gn:admin2_code":"0.0",
    "gn:admin3_code":"14625.0",
    "gn:admin4_code":"14625430.0",
    "gn:asciiname":"Medingen",
    "gn:country_code":"DE",
    "gn:dem":175,
    "gn:feature_class":"P",
    "gn:feature_code":"PPL",
    "gn:name":"Medingen",
    "gn:population":0,
    "gn:timezone":"Europe/Berlin",
    "iso:country":"DE",
    "name:ceb_x_preferred":[
        "Medingen"
    ],
    "name:deu_x_preferred":[
        "Medingen"
    ],
    "name:ltz_x_preferred":[
        "Medingen"
    ],
    "name:pol_x_preferred":[
        "Medingen"
    ],
    "name:swe_x_preferred":[
        "Medingen"
    ],
    "wof:name":"Medingen",
    "wof:placetype":"neighbourhood"
},
  "geometry": {"coordinates":[13.78821,51.18251],"type":"Point"}
}