{
  "type": "Feature",
  "properties": {
    "gn:admin1_code":"10",
    "gn:admin2_code":"0.0",
    "gn:admin3_code":"1057.0",
    "gn:admin4_code":"1057016.0",
    "gn:asciiname":"Lilienthal",
    "gn:country_code":"DE",
    "gn:dem":60,
    "gn:feature_class":"P",
    "gn:feature_code":"PPL",
    "gn:name":"Lilienthal",
    "gn:population":0,
    "gn:timezone":"Europe/Berlin",
    "iso:country":"DE",
    "name:ast_x_preferred":[
        "Lilienthal"
    ],
    "name:ceb_x_preferred":[
        "Lilienthal"
    ],
    "name:ces_x_preferred":[
        "Lilienthal"
    ],
    "name:dan_x_preferred":[
        "Lilienthal"
    ],
    "name:deu_x_preferred":[
        "Lilienthal"
    ],
    "name:fas_x_preferred":[
        "\u0644\u06cc\u0644\u06cc\u0646\u062a\u0627\u0644"
    ],
    "name:fin_x_preferred":[
        "Lilienthal"
    ],
    "name:fra_x_preferred":[
        "Lilienthal"
    ],
    "name:hun_x_preferred":[
        "Lilienthal"
    ],
    "name:ita_x_preferred":[
        "Lilienthal"
    ],
    "name:lav_x_preferred":[
        "Lilient\u0101ls"
    ],
    "name:nds_x_preferred":[
        "Lilienthal"
    ],
    "name:nld_x_preferred":[
        "Lilienthal"
    ],
    "name:nor_x_preferred":[
        "Lilienthal"
    ],
    "name:pol_x_preferred":[
        "Lilienthal"
    ],
    "name:rus_x_preferred":[
        "\u041b\u0438\u043b\u0438\u0435\u043d\u0442\u0430\u043b\u044c"
    ],
    "name:spa_x_preferred":[
        "Lilienthal"
    ],
    "name:swe_x_preferred":[
        "Lilienthal"
    ],
    "name:ukr_x_preferred":[
        "\u041b\u0456\u043b\u0456\u0454\u043d\u0442\u0430\u043b\u044c"
    ],
    "name:und_x_variant":[
        "Liliental"
    ],
    "wof:name":"Lilienthal",
    "wof:placetype":"neighbourhood"
},
  "geometry": {"coordinates":[10.30191,54.29288],"type":"Point"}
}