{
  "type": "Feature",
  "properties": {
    "gn:admin1_code":"10",
    "gn:admin2_code":"0.0",
    "gn:admin3_code":"1057.0",
    "gn:admin4_code":"1057016.0",
    "gn:asciiname":"Lilienthal",
    "gn:country_code":"DE",
    "gn:dem":60,
    "gn:feature_class":"P",
    "gn:feature_code":"PPL",
    "gn:name":"Lilienthal",
    "gn:population":0,
    "gn:timezone":"Europe/Berlin",
    "iso:country":"DE",
    "name:und_x_variant":[
        "Liliental",
        "Lilienthal"
    ],
    "wof:name":"Lilienthal",
    "wof:placetype":"neighbourhood"
},
  "geometry": {"coordinates":[10.30191,54.29288],"type":"Point"}
}