{
  "type": "Feature",
  "properties": {
    "gn:admin1_code":"2",
    "gn:admin2_code":"96.0",
    "gn:admin3_code":"9674.0",
    "gn:admin4_code":"9674210.0",
    "gn:asciiname":"Gereuth",
    "gn:country_code":"DE",
    "gn:dem":314,
    "gn:feature_class":"P",
    "gn:feature_code":"PPL",
    "gn:name":"Gereuth",
    "gn:population":0,
    "gn:timezone":"Europe/Berlin",
    "iso:country":"DE",
    "wof:name":"Gereuth",
    "wof:placetype":"neighbourhood"
},
  "geometry": {"coordinates":[10.81808,50.12612],"type":"Point"}
}