{
  "type": "Feature",
  "properties": {
    "gn:admin1_code":"7",
    "gn:admin2_code":"59.0",
    "gn:admin3_code":"5954.0",
    "gn:admin4_code":"5954012.0",
    "gn:asciiname":"Knapp",
    "gn:country_code":"DE",
    "gn:dem":163,
    "gn:feature_class":"P",
    "gn:feature_code":"PPL",
    "gn:name":"Knapp",
    "gn:population":0,
    "gn:timezone":"Europe/Berlin",
    "iso:country":"DE",
    "name:ceb_x_preferred":[
        "Knapp"
    ],
    "name:deu_x_preferred":[
        "Knapp"
    ],
    "name:fra_x_preferred":[
        "Knapp"
    ],
    "name:ita_x_preferred":[
        "Knapp"
    ],
    "name:jpn_x_preferred":[
        "\u30ca\u30c3\u30d7"
    ],
    "name:ltz_x_preferred":[
        "Knapp"
    ],
    "name:nor_x_preferred":[
        "Knapp"
    ],
    "name:pol_x_preferred":[
        "Knapp"
    ],
    "name:por_x_preferred":[
        "Knapp"
    ],
    "name:swe_x_preferred":[
        "Knapp"
    ],
    "name:ukr_x_preferred":[
        "\u041d\u0435\u043f\u043f"
    ],
    "wof:name":"Knapp",
    "wof:placetype":"neighbourhood"
},
  "geometry": {"coordinates":[7.37776,51.33884000000001],"type":"Point"}
}