{
  "type": "Feature",
  "properties": {
    "gn:admin1_code":"5",
    "gn:admin2_code":"66.0",
    "gn:admin3_code":"6635.0",
    "gn:admin4_code":"6635003.0",
    "gn:asciiname":"Hundsdorf",
    "gn:country_code":"DE",
    "gn:dem":456,
    "gn:feature_class":"P",
    "gn:feature_code":"PPL",
    "gn:name":"Hundsdorf",
    "gn:population":0,
    "gn:timezone":"Europe/Berlin",
    "iso:country":"DE",
    "name:ara_x_preferred":[
        "\u0647\u0648\u0646\u062f\u0633\u062f\u0648\u0631\u0641"
    ],
    "name:ceb_x_preferred":[
        "Hundsdorf"
    ],
    "name:deu_x_preferred":[
        "Hundsdorf"
    ],
    "name:epo_x_preferred":[
        "Hundsdorf"
    ],
    "name:eus_x_preferred":[
        "Hundsdorf"
    ],
    "name:fas_x_preferred":[
        "\u0647\u0648\u0646\u062f\u0633\u062f\u0648\u0631\u0641"
    ],
    "name:fra_x_preferred":[
        "Hundsdorf"
    ],
    "name:hun_x_preferred":[
        "Hundsdorf"
    ],
    "name:ita_x_preferred":[
        "Hundsdorf"
    ],
    "name:kaz_x_preferred":[
        "\u0425\u0443\u043d\u0434\u0441\u0434\u043e\u0440\u0444"
    ],
    "name:kir_x_preferred":[
        "\u0425\u0443\u043d\u0434\u0441\u0434\u043e\u0440\u0444"
    ],
    "name:msa_x_preferred":[
        "Hundsdorf"
    ],
    "name:nld_x_preferred":[
        "Hundsdorf"
    ],
    "name:pol_x_preferred":[
        "Hundsdorf"
    ],
    "name:por_x_preferred":[
        "Hundsdorf"
    ],
    "name:ron_x_preferred":[
        "Hundsdorf"
    ],
    "name:rus_x_preferred":[
        "\u0425\u0443\u043d\u0434\u0441\u0434\u043e\u0440\u0444"
    ],
    "name:srp_x_preferred":[
        "\u0425\u0443\u043d\u0434\u0441\u0434\u043e\u0440\u0444"
    ],
    "name:ukr_x_preferred":[
        "\u0413\u0443\u043d\u0434\u0441\u0434\u043e\u0440\u0444"
    ],
    "name:uzb_x_preferred":[
        "Hundsdorf"
    ],
    "name:vol_x_preferred":[
        "Hundsdorf"
    ],
    "name:war_x_preferred":[
        "Hundsdorf"
    ],
    "name:zho_x_preferred":[
        "\u6d2a\u8328\u591a\u592b"
    ],
    "wof:name":"Hundsdorf",
    "wof:placetype":"neighbourhood"
},
  "geometry": {"coordinates":[9.04014,51.08103],"type":"Point"}
}