{
  "type": "Feature",
  "properties": {
    "gn:admin1_code":"5.0",
    "gn:admin2_code":"066",
    "gn:admin3_code":"6636.0",
    "gn:admin4_code":"6636004.0",
    "gn:asciiname":"Weissenbach",
    "gn:country_code":"DE",
    "gn:dem":428,
    "gn:feature_class":"P",
    "gn:feature_code":"PPL",
    "gn:name":"Wei\u00dfenbach",
    "gn:population":0,
    "gn:timezone":"Europe/Berlin",
    "iso:country":"DE",
    "name:ceb_x_preferred":[
        "Weissenbach"
    ],
    "name:epo_x_preferred":[
        "Weissenbach"
    ],
    "name:nld_x_preferred":[
        "Weissenbach"
    ],
    "name:pol_x_preferred":[
        "Weissenbach"
    ],
    "name:swe_x_preferred":[
        "Weissenbach"
    ],
    "wof:name":"Weissenbach",
    "wof:placetype":"neighbourhood"
},
  "geometry": {"coordinates":[9.8489,51.25447],"type":"Point"}
}