{
  "type": "Feature",
  "properties": {
    "gn:admin1_code":"2",
    "gn:admin2_code":"93.0",
    "gn:admin3_code":"9375.0",
    "gn:admin4_code":"9375148.0",
    "gn:asciiname":"Hamberg",
    "gn:country_code":"DE",
    "gn:dem":497,
    "gn:feature_class":"P",
    "gn:feature_code":"PPL",
    "gn:name":"Hamberg",
    "gn:population":0,
    "gn:timezone":"Europe/Berlin",
    "iso:country":"DE",
    "name:ceb_x_preferred":[
        "Hamberg"
    ],
    "name:deu_x_preferred":[
        "Hamberg"
    ],
    "name:fin_x_preferred":[
        "Hamberg"
    ],
    "name:por_x_preferred":[
        "Hamberg"
    ],
    "name:swe_x_preferred":[
        "Hamberg"
    ],
    "wof:name":"Hamberg",
    "wof:placetype":"neighbourhood"
},
  "geometry": {"coordinates":[11.80364,49.02409],"type":"Point"}
}