{
  "type": "Feature",
  "properties": {
    "gn:admin1_code":"13.0",
    "gn:admin2_code":"0.0",
    "gn:admin3_code":"14628.0",
    "gn:admin4_code":"14628110.0",
    "gn:asciiname":"Potschappel",
    "gn:country_code":"DE",
    "gn:dem":163,
    "gn:feature_class":"P",
    "gn:feature_code":"PPL",
    "gn:name":"Potschappel",
    "gn:population":0,
    "gn:timezone":"Europe/Berlin",
    "iso:country":"DE",
    "wof:name":"Potschappel",
    "wof:placetype":"neighbourhood"
},
  "geometry": {"coordinates":[13.66077,51.01146],"type":"Point"}
}