{
  "type": "Feature",
  "properties": {
    "gn:admin1_code":"11",
    "gn:admin2_code":"0.0",
    "gn:admin3_code":"12073.0",
    "gn:admin4_code":"12073603.0",
    "gn:asciiname":"Schoenow",
    "gn:country_code":"DE",
    "gn:dem":20,
    "gn:feature_class":"P",
    "gn:feature_code":"PPL",
    "gn:name":"Sch\u00f6now",
    "gn:population":0,
    "gn:timezone":"Europe/Berlin",
    "iso:country":"DE",
    "wof:name":"Schoenow",
    "wof:placetype":"neighbourhood"
},
  "geometry": {"coordinates":[14.15297,53.17888000000001],"type":"Point"}
}