{
  "type": "Feature",
  "properties": {
    "gn:gn_country":"DE",
    "gn:gn_fcode":"PPLA4",
    "gn:gn_pop":580,
    "gn:population":580,
    "iso:country":"DE",
    "name:baq_x_preferred":[
        "Gemmerich"
    ],
    "name:chi_x_preferred":[
        "\u683c\u6885\u91cc\u5e0c"
    ],
    "name:dut_x_preferred":[
        "Gemmerich"
    ],
    "name:eng_x_preferred":[
        "Gemmerich"
    ],
    "name:epo_x_preferred":[
        "Gemmerich"
    ],
    "name:fre_x_preferred":[
        "Gemmerich"
    ],
    "name:ger_x_preferred":[
        "Gemmerich"
    ],
    "name:hun_x_preferred":[
        "Gemmerich"
    ],
    "name:ita_x_preferred":[
        "Gemmerich"
    ],
    "name:jpn_x_preferred":[
        "\u30b2\u30f3\u30de\u30ea\u30c3\u30d2"
    ],
    "name:may_x_preferred":[
        "Gemmerich"
    ],
    "name:per_x_preferred":[
        "\u06af\u0645\u0631\u0627\u06cc\u0634"
    ],
    "name:pol_x_preferred":[
        "Gemmerich"
    ],
    "name:por_x_preferred":[
        "Gemmerich"
    ],
    "name:rum_x_preferred":[
        "Gemmerich"
    ],
    "name:rus_x_preferred":[
        "\u0413\u0435\u043c\u043c\u0435\u0440\u0438\u0445"
    ],
    "name:srp_x_preferred":[
        "\u0413\u0435\u043c\u0435\u0440\u0438\u0445"
    ],
    "name:ukr_x_preferred":[
        "\u0413\u0435\u043c\u043c\u0435\u0440\u0456\u0445"
    ],
    "name:uzb_x_preferred":[
        "Gemmerich"
    ],
    "name:vie_x_preferred":[
        "Gemmerich"
    ],
    "name:vol_x_preferred":[
        "Gemmerich"
    ],
    "name:war_x_preferred":[
        "Gemmerich"
    ],
    "qs_pg:aaroncc":"DE",
    "qs_pg:gn_country":"DE",
    "qs_pg:gn_fcode":"PPLA4",
    "qs_pg:gn_pop":580,
    "qs_pg:name":"Gemmerich",
    "qs_pg:photos_9r":0,
    "qs_pg:photos_sr":0,
    "qs_pg:pop_sr":2,
    "qs_pg:qs_pg_placetype":"locality",
    "wof:name":"Gemmerich",
    "wof:placetype":"locality",
    "wof:population":580
},
  "geometry": {"coordinates":[7.75858,50.22788],"type":"Point"}
}