{
  "type": "Feature",
  "properties": {
    "gn:admin1_code":"14",
    "gn:admin2_code":"0.0",
    "gn:admin3_code":"15088.0",
    "gn:admin4_code":"15088195.0",
    "gn:asciiname":"Rabatz",
    "gn:country_code":"DE",
    "gn:dem":99,
    "gn:feature_class":"P",
    "gn:feature_code":"PPL",
    "gn:name":"Rabatz",
    "gn:population":0,
    "gn:timezone":"Europe/Berlin",
    "iso:country":"DE",
    "wof:name":"Rabatz",
    "wof:placetype":"neighbourhood"
},
  "geometry": {"coordinates":[12.06394,51.50873],"type":"Point"}
}