{
  "type": "Feature",
  "properties": {
    "gn:admin1_code":"12.0",
    "gn:admin2_code":"00",
    "gn:admin3_code":"13073.0",
    "gn:admin4_code":"13073060.0",
    "gn:asciiname":"Zansebuhr",
    "gn:cc2":"DE",
    "gn:country_code":"DE",
    "gn:dem":17,
    "gn:feature_class":"P",
    "gn:feature_code":"PPL",
    "gn:name":"Zansebuhr",
    "gn:population":0,
    "gn:timezone":"Europe/Berlin",
    "iso:country":"DE",
    "name:und_x_variant":[
        "Gro\u00df Zansebuhr"
    ],
    "wof:name":"Zansebuhr",
    "wof:placetype":"neighbourhood"
},
  "geometry": {"coordinates":[12.94593,54.32243],"type":"Point"}
}