{
  "type": "Feature",
  "properties": {
    "gn:admin1_code":"13",
    "gn:admin2_code":"0.0",
    "gn:admin3_code":"14625.0",
    "gn:admin4_code":"14625060.0",
    "gn:asciiname":"Pannewitz am Taucher",
    "gn:country_code":"DE",
    "gn:dem":223,
    "gn:feature_class":"P",
    "gn:feature_code":"PPL",
    "gn:name":"Pannewitz am Taucher",
    "gn:population":0,
    "gn:timezone":"Europe/Berlin",
    "iso:country":"DE",
    "name:hsb_x_preferred":[
        "Panecy"
    ],
    "wof:name":"Pannewitz am Taucher",
    "wof:placetype":"neighbourhood"
},
  "geometry": {"coordinates":[14.24672,51.19979],"type":"Point"}
}