{
  "type": "Feature",
  "properties": {
    "gn:country":"DE",
    "gn:fcode":"PPL",
    "gn:population":0,
    "iso:country":"DE",
    "name:ceb_x_preferred":[
        "Gro\u00dfhaslach"
    ],
    "name:deu_x_preferred":[
        "Gro\u00dfhaslach"
    ],
    "name:fas_x_preferred":[
        "\u06af\u0631\u0648\u0633\u0647\u0627\u0633\u0644\u0627\u062e"
    ],
    "name:nld_x_preferred":[
        "Gro\u00dfhaslach"
    ],
    "qs_pg:aaroncc":"DE",
    "qs_pg:gn_country":"DE",
    "qs_pg:gn_fcode":"PPL",
    "qs_pg:gn_pop":0,
    "qs_pg:name":"Gro\u00dfhaslach",
    "qs_pg:name_adm0":"Deutschland",
    "qs_pg:name_adm1":"Bayern",
    "qs_pg:photos_9r":0,
    "qs_pg:photos_sr":0,
    "qs_pg:pop_sr":0,
    "qs_pg:qs_pg_placetype":"locality",
    "qs_pg:qs_pg_placetype_gp":"Town",
    "qs_pg:woe_adm0":23424829,
    "woe:adm0_id":23424829,
    "woe:name_adm0":"Deutschland",
    "woe:name_adm1":"Bayern",
    "woe:placetype":"Town",
    "wof:name":"Gro\u00dfhaslach",
    "wof:placetype":"neighbourhood"
},
  "geometry": {"coordinates":[10.72844,49.33659],"type":"Point"}
}