{
  "type": "Feature",
  "properties": {
    "gn:admin1_code":"8",
    "gn:admin2_code":"0.0",
    "gn:admin3_code":"7211.0",
    "gn:admin4_code":"7211000.0",
    "gn:asciiname":"Quint",
    "gn:country_code":"DE",
    "gn:dem":142,
    "gn:feature_class":"P",
    "gn:feature_code":"PPL",
    "gn:name":"Quint",
    "gn:population":0,
    "gn:timezone":"Europe/Berlin",
    "iso:country":"DE",
    "name:cat_x_preferred":[
        "Quint"
    ],
    "name:deu_x_preferred":[
        "Quint"
    ],
    "name:fra_x_preferred":[
        "Quint"
    ],
    "name:jpn_x_preferred":[
        "\u30af\u30a4\u30f3\u30c8"
    ],
    "wof:name":"Quint",
    "wof:placetype":"neighbourhood"
},
  "geometry": {"coordinates":[6.7063,49.82436],"type":"Point"}
}