{
  "type": "Feature",
  "properties": {
    "gn:admin1_code":"14",
    "gn:admin2_code":"0.0",
    "gn:admin3_code":"15084.0",
    "gn:admin4_code":"15084115.0",
    "gn:asciiname":"Hassel",
    "gn:country_code":"DE",
    "gn:dem":244,
    "gn:feature_class":"P",
    "gn:feature_code":"PPL",
    "gn:name":"Hassel",
    "gn:population":0,
    "gn:timezone":"Europe/Berlin",
    "iso:country":"DE",
    "name:ceb_x_preferred":[
        "Hassel"
    ],
    "name:deu_x_preferred":[
        "Hassel"
    ],
    "name:epo_x_preferred":[
        "Hassel"
    ],
    "name:fin_x_preferred":[
        "Hassel"
    ],
    "name:fra_x_preferred":[
        "Hassel"
    ],
    "name:heb_x_preferred":[
        "\u05d4\u05d0\u05e1\u05dc"
    ],
    "name:ita_x_preferred":[
        "Hassel"
    ],
    "name:jpn_x_preferred":[
        "\u30cf\u30c3\u30bb\u30eb"
    ],
    "name:nds_x_preferred":[
        "Hassel"
    ],
    "name:nld_x_preferred":[
        "Hassel"
    ],
    "name:pol_x_preferred":[
        "Hassel"
    ],
    "name:por_x_preferred":[
        "Hassel"
    ],
    "name:rus_x_preferred":[
        "\u0425\u0430\u0441\u0441\u0435\u043b\u044c"
    ],
    "name:swe_x_preferred":[
        "Hassel"
    ],
    "name:vol_x_preferred":[
        "Hassel"
    ],
    "wof:name":"Hassel",
    "wof:placetype":"neighbourhood"
},
  "geometry": {"coordinates":[12.00975,51.04046],"type":"Point"}
}