{
  "type": "Feature",
  "properties": {
    "gn:admin1_code":"1",
    "gn:admin2_code":"81.0",
    "gn:admin3_code":"8126.0",
    "gn:admin4_code":"8126058.0",
    "gn:asciiname":"Kesselfeld",
    "gn:country_code":"DE",
    "gn:dem":316,
    "gn:feature_class":"P",
    "gn:feature_code":"PPL",
    "gn:name":"Kesselfeld",
    "gn:population":0,
    "gn:timezone":"Europe/Berlin",
    "iso:country":"DE",
    "wof:name":"Kesselfeld",
    "wof:placetype":"neighbourhood"
},
  "geometry": {"coordinates":[9.61576,49.20157],"type":"Point"}
}