{
  "type": "Feature",
  "properties": {
    "gn:admin1_code":"1",
    "gn:admin2_code":"84.0",
    "gn:admin3_code":"8436.0",
    "gn:admin4_code":"8436014.0",
    "gn:asciiname":"Furt",
    "gn:country_code":"DE",
    "gn:dem":639,
    "gn:feature_class":"P",
    "gn:feature_code":"PPL",
    "gn:name":"Furt",
    "gn:population":0,
    "gn:timezone":"Europe/Berlin",
    "iso:country":"DE",
    "name:ces_x_preferred":[
        "Furt"
    ],
    "name:ind_x_preferred":[
        "Furt"
    ],
    "name:rus_x_preferred":[
        "Furt"
    ],
    "name:spa_x_preferred":[
        "Furt"
    ],
    "wof:name":"Furt",
    "wof:placetype":"neighbourhood"
},
  "geometry": {"coordinates":[9.77918,47.86545],"type":"Point"}
}