{
  "type": "Feature",
  "properties": {
    "gn:admin1_code":"11",
    "gn:admin2_code":"0.0",
    "gn:admin3_code":"12073.0",
    "gn:admin4_code":"12073157.0",
    "gn:asciiname":"Flieth",
    "gn:country_code":"DE",
    "gn:dem":39,
    "gn:feature_class":"P",
    "gn:feature_code":"PPL",
    "gn:name":"Flieth",
    "gn:population":0,
    "gn:timezone":"Europe/Berlin",
    "iso:country":"DE",
    "wof:name":"Flieth",
    "wof:placetype":"neighbourhood"
},
  "geometry": {"coordinates":[13.81316,53.1618],"type":"Point"}
}