{
  "type": "Feature",
  "properties": {
    "gn:admin1_code":"6",
    "gn:admin2_code":"0.0",
    "gn:admin3_code":"3457.0",
    "gn:admin4_code":"3457017.0",
    "gn:asciiname":"Idafehn",
    "gn:country_code":"DE",
    "gn:dem":4,
    "gn:feature_class":"P",
    "gn:feature_code":"PPL",
    "gn:name":"Idafehn",
    "gn:population":0,
    "gn:timezone":"Europe/Berlin",
    "iso:country":"DE",
    "name:und_x_variant":[
        "Kolonie Idafehn",
        "Idafehn"
    ],
    "wof:name":"Idafehn",
    "wof:placetype":"neighbourhood"
},
  "geometry": {"coordinates":[7.63724,53.14007],"type":"Point"}
}