{
  "type": "Feature",
  "properties": {
    "gn:admin1_code":"1",
    "gn:admin2_code":"83.0",
    "gn:admin3_code":"8317.0",
    "gn:admin4_code":"8317041.0",
    "gn:asciiname":"Einbach",
    "gn:country_code":"DE",
    "gn:dem":323,
    "gn:feature_class":"P",
    "gn:feature_code":"PPL",
    "gn:name":"Einbach",
    "gn:population":0,
    "gn:timezone":"Europe/Berlin",
    "iso:country":"DE",
    "wof:name":"Einbach",
    "wof:placetype":"neighbourhood"
},
  "geometry": {"coordinates":[8.17042,48.31359000000001],"type":"Point"}
}