{
  "type": "Feature",
  "properties": {
    "gn:admin1_code":"2",
    "gn:admin2_code":"92.0",
    "gn:admin3_code":"9272.0",
    "gn:admin4_code":"9272140.0",
    "gn:asciiname":"Neidberg",
    "gn:country_code":"DE",
    "gn:dem":469,
    "gn:feature_class":"P",
    "gn:feature_code":"PPL",
    "gn:name":"Neidberg",
    "gn:population":0,
    "gn:timezone":"Europe/Berlin",
    "iso:country":"DE",
    "wof:name":"Neidberg",
    "wof:placetype":"neighbourhood"
},
  "geometry": {"coordinates":[13.46154,48.81643],"type":"Point"}
}