{
  "type": "Feature",
  "properties": {
    "gn:admin1_code":"13.0",
    "gn:admin2_code":"0.0",
    "gn:admin3_code":"14523.0",
    "gn:admin4_code":"14523200.0",
    "gn:asciiname":"Bernitzgruen",
    "gn:country_code":"DE",
    "gn:dem":585,
    "gn:feature_class":"P",
    "gn:feature_code":"PPL",
    "gn:name":"Bernitzgr\u00fcn",
    "gn:population":0,
    "gn:timezone":"Europe/Berlin",
    "iso:country":"DE",
    "wof:name":"Bernitzgruen",
    "wof:placetype":"neighbourhood"
},
  "geometry": {"coordinates":[12.31679,50.332],"type":"Point"}
}