{
  "type": "Feature",
  "properties": {
    "gn:admin1_code":"2",
    "gn:admin2_code":"93.0",
    "gn:admin3_code":"9374.0",
    "gn:admin4_code":"9374160.0",
    "gn:asciiname":"Roschau",
    "gn:country_code":"DE",
    "gn:dem":463,
    "gn:feature_class":"P",
    "gn:feature_code":"PPL",
    "gn:name":"Roschau",
    "gn:population":0,
    "gn:timezone":"Europe/Berlin",
    "iso:country":"DE",
    "wof:name":"Roschau",
    "wof:placetype":"neighbourhood"
},
  "geometry": {"coordinates":[12.18997,49.71738],"type":"Point"}
}