{
  "type": "Feature",
  "properties": {
    "gn:admin1_code":"2",
    "gn:admin2_code":"95.0",
    "gn:admin3_code":"9571.0",
    "gn:admin4_code":"9571165.0",
    "gn:asciiname":"Neuhoflein",
    "gn:country_code":"DE",
    "gn:dem":400,
    "gn:feature_class":"P",
    "gn:feature_code":"PPL",
    "gn:name":"Neuh\u00f6flein",
    "gn:population":0,
    "gn:timezone":"Europe/Berlin",
    "iso:country":"DE",
    "wof:name":"Neuhoflein",
    "wof:placetype":"neighbourhood"
},
  "geometry": {"coordinates":[10.73283,49.36538],"type":"Point"}
}