{
  "type": "Feature",
  "properties": {
    "gn:admin1_code":"12",
    "gn:admin2_code":"0.0",
    "gn:admin3_code":"13073.0",
    "gn:admin4_code":"13073048.0",
    "gn:asciiname":"Neu Reddevitz",
    "gn:country_code":"DE",
    "gn:dem":4,
    "gn:feature_class":"P",
    "gn:feature_code":"PPL",
    "gn:name":"Neu Reddevitz",
    "gn:population":0,
    "gn:timezone":"Europe/Berlin",
    "iso:country":"DE",
    "wof:name":"Neu Reddevitz",
    "wof:placetype":"neighbourhood"
},
  "geometry": {"coordinates":[13.61373,54.33519],"type":"Point"}
}