{
  "type": "Feature",
  "properties": {
    "gn:admin1_code":"6",
    "gn:admin2_code":"0.0",
    "gn:admin3_code":"3159.0",
    "gn:admin4_code":"3159029.0",
    "gn:asciiname":"Sieboldshausen",
    "gn:country_code":"DE",
    "gn:dem":181,
    "gn:feature_class":"P",
    "gn:feature_code":"PPL",
    "gn:name":"Sieboldshausen",
    "gn:population":0,
    "gn:timezone":"Europe/Berlin",
    "iso:country":"DE",
    "wof:name":"Sieboldshausen",
    "wof:placetype":"neighbourhood"
},
  "geometry": {"coordinates":[9.88894,51.47032],"type":"Point"}
}