{
  "type": "Feature",
  "properties": {
    "gn:admin1_code":"7",
    "gn:admin2_code":"55.0",
    "gn:admin3_code":"5562.0",
    "gn:admin4_code":"5562016.0",
    "gn:asciiname":"Eppendorf",
    "gn:country_code":"DE",
    "gn:dem":72,
    "gn:feature_class":"P",
    "gn:feature_code":"PPL",
    "gn:name":"Eppendorf",
    "gn:population":0,
    "gn:timezone":"Europe/Berlin",
    "iso:country":"DE",
    "name:cat_x_preferred":[
        "Eppendorf"
    ],
    "name:ceb_x_preferred":[
        "Eppendorf"
    ],
    "name:deu_x_preferred":[
        "Eppendorf"
    ],
    "name:fra_x_preferred":[
        "Eppendorf"
    ],
    "name:ita_x_preferred":[
        "Eppendorf"
    ],
    "name:pol_x_preferred":[
        "Eppendorf"
    ],
    "name:rus_x_preferred":[
        "\u042d\u043f\u043f\u0435\u043d\u0434\u043e\u0440\u0444"
    ],
    "name:spa_x_preferred":[
        "Eppendorf"
    ],
    "wof:name":"Eppendorf",
    "wof:placetype":"neighbourhood"
},
  "geometry": {"coordinates":[7.10516,51.73286],"type":"Point"}
}