{
  "type": "Feature",
  "properties": {
    "gn:admin1_code":"7",
    "gn:admin2_code":"59.0",
    "gn:admin3_code":"5974.0",
    "gn:admin4_code":"5974012.0",
    "gn:asciiname":"Oberense",
    "gn:country_code":"DE",
    "gn:dem":209,
    "gn:feature_class":"P",
    "gn:feature_code":"PPL",
    "gn:name":"Oberense",
    "gn:population":0,
    "gn:timezone":"Europe/Berlin",
    "iso:country":"DE",
    "wof:name":"Oberense",
    "wof:placetype":"neighbourhood"
},
  "geometry": {"coordinates":[7.99788,51.50928],"type":"Point"}
}