{
  "type": "Feature",
  "properties": {
    "gn:admin1_code":"6",
    "gn:admin2_code":"0.0",
    "gn:admin3_code":"3454.0",
    "gn:admin4_code":"3454026.0",
    "gn:asciiname":"Holte",
    "gn:country_code":"DE",
    "gn:dem":33,
    "gn:feature_class":"P",
    "gn:feature_code":"PPL",
    "gn:name":"Holte",
    "gn:population":0,
    "gn:timezone":"Europe/Berlin",
    "iso:country":"DE",
    "name:dan_x_preferred":[
        "Holte"
    ],
    "name:ita_x_preferred":[
        "Holte"
    ],
    "name:nld_x_preferred":[
        "Holte"
    ],
    "name:nor_x_preferred":[
        "Holte"
    ],
    "name:pol_x_preferred":[
        "Holte"
    ],
    "name:swe_x_preferred":[
        "Holte"
    ],
    "wof:name":"Holte",
    "wof:placetype":"neighbourhood"
},
  "geometry": {"coordinates":[7.61914,52.73861],"type":"Point"}
}