{
  "type": "Feature",
  "properties": {
    "gn:admin1_code":"5",
    "gn:admin2_code":"66.0",
    "gn:admin3_code":"6636.0",
    "gn:admin4_code":"6636006.0",
    "gn:asciiname":"Retterode",
    "gn:country_code":"DE",
    "gn:dem":363,
    "gn:feature_class":"P",
    "gn:feature_code":"PPL",
    "gn:name":"Retterode",
    "gn:population":0,
    "gn:timezone":"Europe/Berlin",
    "iso:country":"DE",
    "wof:name":"Retterode",
    "wof:placetype":"neighbourhood"
},
  "geometry": {"coordinates":[9.72228,51.17336],"type":"Point"}
}