{
  "type": "Feature",
  "properties": {
    "gn:admin1_code":"11",
    "gn:admin2_code":"0.0",
    "gn:admin3_code":"12061.0",
    "gn:admin4_code":"12061320.0",
    "gn:asciiname":"Duben",
    "gn:country_code":"DE",
    "gn:dem":64,
    "gn:feature_class":"P",
    "gn:feature_code":"PPL",
    "gn:name":"Duben",
    "gn:population":0,
    "gn:timezone":"Europe/Berlin",
    "iso:country":"DE",
    "name:deu_x_preferred":[
        "D\u00fcben"
    ],
    "name:und_x_variant":[
        "Dubin",
        "Duben"
    ],
    "wof:name":"Duben",
    "wof:placetype":"neighbourhood"
},
  "geometry": {"coordinates":[13.8074,51.89759],"type":"Point"}
}