{
  "type": "Feature",
  "properties": {
    "gn:admin1_code":"2",
    "gn:admin2_code":"97.0",
    "gn:admin3_code":"9780.0",
    "gn:admin4_code":"9780146.0",
    "gn:asciiname":"Hino",
    "gn:country_code":"DE",
    "gn:dem":886,
    "gn:feature_class":"P",
    "gn:feature_code":"PPL",
    "gn:name":"Hino",
    "gn:population":0,
    "gn:timezone":"Europe/Berlin",
    "iso:country":"DE",
    "name:ara_x_preferred":[
        "\u0647\u064a\u0646\u0648"
    ],
    "name:ceb_x_preferred":[
        "Hino"
    ],
    "name:deu_x_preferred":[
        "Hino"
    ],
    "name:est_x_preferred":[
        "Hino"
    ],
    "name:fin_x_preferred":[
        "Hino"
    ],
    "name:fra_x_preferred":[
        "Hino"
    ],
    "name:ind_x_preferred":[
        "Hino"
    ],
    "name:mlg_x_preferred":[
        "Hino"
    ],
    "name:nld_x_preferred":[
        "Hino"
    ],
    "name:nno_x_preferred":[
        "Hino"
    ],
    "name:por_x_preferred":[
        "Hino"
    ],
    "name:ron_x_preferred":[
        "Hino"
    ],
    "name:rus_x_preferred":[
        "\u0425\u0438\u043d\u043e"
    ],
    "name:swe_x_preferred":[
        "Hino"
    ],
    "name:ukr_x_preferred":[
        "\u0425\u0456\u043d\u043e"
    ],
    "name:vol_x_preferred":[
        "Hino"
    ],
    "wof:name":"Hino",
    "wof:placetype":"neighbourhood"
},
  "geometry": {"coordinates":[10.22725,47.74061],"type":"Point"}
}