{
  "type": "Feature",
  "properties": {
    "gn:admin1_code":"1",
    "gn:admin2_code":"84.0",
    "gn:admin3_code":"8436.0",
    "gn:admin4_code":"8436081.0",
    "gn:asciiname":"Ettensweiler",
    "gn:country_code":"DE",
    "gn:dem":580,
    "gn:feature_class":"P",
    "gn:feature_code":"PPL",
    "gn:name":"Ettensweiler",
    "gn:population":0,
    "gn:timezone":"Europe/Berlin",
    "iso:country":"DE",
    "wof:name":"Ettensweiler",
    "wof:placetype":"neighbourhood"
},
  "geometry": {"coordinates":[9.7748,47.68561],"type":"Point"}
}