{
  "type": "Feature",
  "properties": {
    "gn:admin1_code":"2",
    "gn:admin2_code":"91.0",
    "gn:admin3_code":"9178.0",
    "gn:admin4_code":"9178124.0",
    "gn:asciiname":"Gartelshausen",
    "gn:country_code":"DE",
    "gn:dem":475,
    "gn:feature_class":"P",
    "gn:feature_code":"PPL",
    "gn:name":"Gartelshausen",
    "gn:population":0,
    "gn:timezone":"Europe/Berlin",
    "iso:country":"DE",
    "wof:name":"Gartelshausen",
    "wof:placetype":"neighbourhood"
},
  "geometry": {"coordinates":[11.68823,48.39053],"type":"Point"}
}