{
  "type": "Feature",
  "properties": {
    "gn:admin1_code":"5",
    "gn:admin2_code":"64.0",
    "gn:admin3_code":"6440.0",
    "gn:admin4_code":"6440019.0",
    "gn:asciiname":"Effolderbach",
    "gn:country_code":"DE",
    "gn:dem":138,
    "gn:feature_class":"P",
    "gn:feature_code":"PPL",
    "gn:name":"Effolderbach",
    "gn:population":0,
    "gn:timezone":"Europe/Berlin",
    "iso:country":"DE",
    "wof:name":"Effolderbach",
    "wof:placetype":"neighbourhood"
},
  "geometry": {"coordinates":[9.0088,50.34172],"type":"Point"}
}