{
  "type": "Feature",
  "properties": {
    "gn:admin1_code":"1.0",
    "gn:admin2_code":"82.0",
    "gn:admin3_code":"8222.0",
    "gn:admin4_code":"8222000.0",
    "gn:asciiname":"Schwetzingerstadt",
    "gn:country_code":"DE",
    "gn:dem":99,
    "gn:feature_class":"P",
    "gn:feature_code":"PPL",
    "gn:name":"Schwetzingerstadt",
    "gn:population":0,
    "gn:timezone":"Europe/Berlin",
    "iso:country":"DE",
    "wof:name":"Schwetzingerstadt",
    "wof:placetype":"neighbourhood"
},
  "geometry": {"coordinates":[8.48505,49.47582],"type":"Point"}
}