{
  "type": "Feature",
  "properties": {
    "gn:country":"DE",
    "gn:fcode":"PPL",
    "gn:population":0,
    "iso:country":"DE",
    "name:deu_x_preferred":[
        "Neuenland"
    ],
    "qs_pg:aaroncc":"DE",
    "qs_pg:gn_country":"DE",
    "qs_pg:gn_fcode":"PPL",
    "qs_pg:gn_pop":0,
    "qs_pg:name":"Neuenland",
    "qs_pg:name_adm0":"Deutschland",
    "qs_pg:name_adm1":"Freie Hansestadt Bremen",
    "qs_pg:photos":95,
    "qs_pg:photos_1k":19,
    "qs_pg:photos_9k":1,
    "qs_pg:photos_9r":3,
    "qs_pg:photos_all":95,
    "qs_pg:photos_sr":3,
    "qs_pg:pop_sr":0,
    "qs_pg:qs_pg_placetype":"neighbourhood",
    "qs_pg:qs_pg_placetype_gp":"Suburb",
    "qs_pg:woe_adm0":23424829,
    "woe:adm0_id":23424829,
    "woe:name_adm0":"Deutschland",
    "woe:name_adm1":"Freie Hansestadt Bremen",
    "woe:placetype":"Suburb",
    "wof:name":"Neuenland",
    "wof:placetype":"neighbourhood"
},
  "geometry": {"coordinates":[8.782113,53.051877],"type":"Point"}
}