{
  "type": "Feature",
  "properties": {
    "gn:admin1_code":"11",
    "gn:admin2_code":"0.0",
    "gn:admin3_code":"12064.0",
    "gn:admin4_code":"12064029.0",
    "gn:asciiname":"Neuhoenow",
    "gn:cc2":"DE",
    "gn:country_code":"DE",
    "gn:dem":63,
    "gn:feature_class":"P",
    "gn:feature_code":"PPL",
    "gn:name":"Neuh\u00f6now",
    "gn:population":0,
    "gn:timezone":"Europe/Berlin",
    "iso:country":"DE",
    "name:und_x_variant":[
        "Kolonie Neuh\u00f6now"
    ],
    "wof:name":"Neuhoenow",
    "wof:placetype":"neighbourhood"
},
  "geometry": {"coordinates":[13.73789,52.58188000000001],"type":"Point"}
}