{
  "type": "Feature",
  "properties": {
    "gn:admin1_code":"13",
    "gn:admin2_code":"0.0",
    "gn:admin3_code":"14627.0",
    "gn:admin4_code":"14627170.0",
    "gn:asciiname":"Grossdobritz",
    "gn:country_code":"DE",
    "gn:dem":174,
    "gn:feature_class":"P",
    "gn:feature_code":"PPL",
    "gn:name":"Gro\u00dfdobritz",
    "gn:population":0,
    "gn:timezone":"Europe/Berlin",
    "iso:country":"DE",
    "wof:name":"Grossdobritz",
    "wof:placetype":"neighbourhood"
},
  "geometry": {"coordinates":[13.56916,51.21568],"type":"Point"}
}