{
  "type": "Feature",
  "properties": {
    "gn:gn_country":"DE",
    "gn:gn_fcode":"PPLA4",
    "gn:gn_pop":245,
    "gn:population":245,
    "iso:country":"DE",
    "name:baq_x_preferred":[
        "Arpsdorf"
    ],
    "name:chi_x_preferred":[
        "\u963f\u5c14\u666e\u65af\u591a\u5c14\u592b"
    ],
    "name:dan_x_preferred":[
        "Arpsdorf"
    ],
    "name:dut_x_preferred":[
        "Arpsdorf"
    ],
    "name:eng_x_preferred":[
        "Arpsdorf"
    ],
    "name:epo_x_preferred":[
        "Arpsdorf"
    ],
    "name:fre_x_preferred":[
        "Arpsdorf"
    ],
    "name:ger_x_preferred":[
        "Arpsdorf"
    ],
    "name:hun_x_preferred":[
        "Arpsdorf"
    ],
    "name:ita_x_preferred":[
        "Arpsdorf"
    ],
    "name:mac_x_preferred":[
        "\u0410\u0440\u043f\u0441\u0434\u043e\u0440\u0444"
    ],
    "name:may_x_preferred":[
        "Arpsdorf"
    ],
    "name:pol_x_preferred":[
        "Arpsdorf"
    ],
    "name:por_x_preferred":[
        "Arpsdorf"
    ],
    "name:rum_x_preferred":[
        "Arpsdorf"
    ],
    "name:rus_x_preferred":[
        "\u0410\u0440\u043f\u0441\u0434\u043e\u0440\u0444"
    ],
    "name:spa_x_preferred":[
        "Arpsdorf"
    ],
    "name:srp_x_preferred":[
        "\u0410\u0440\u043f\u0441\u0434\u043e\u0440\u0444"
    ],
    "name:tur_x_preferred":[
        "Arpsdorf"
    ],
    "name:ukr_x_preferred":[
        "\u0410\u0440\u043f\u0441\u0434\u043e\u0440\u0444"
    ],
    "name:uzb_x_preferred":[
        "Arpsdorf"
    ],
    "name:vie_x_preferred":[
        "Arpsdorf"
    ],
    "name:vol_x_preferred":[
        "Arpsdorf"
    ],
    "name:war_x_preferred":[
        "Arpsdorf"
    ],
    "qs_pg:aaroncc":"DE",
    "qs_pg:gn_country":"DE",
    "qs_pg:gn_fcode":"PPLA4",
    "qs_pg:gn_pop":245,
    "qs_pg:name":"Arpsdorf",
    "qs_pg:photos_9r":0,
    "qs_pg:photos_sr":0,
    "qs_pg:pop_sr":2,
    "qs_pg:qs_pg_placetype":"locality",
    "wof:name":"Arpsdorf",
    "wof:placetype":"locality",
    "wof:population":245
},
  "geometry": {"coordinates":[9.86667,54.03333],"type":"Point"}
}