{
  "type": "Feature",
  "properties": {
    "gn:admin1_code":"1",
    "gn:admin2_code":"83.0",
    "gn:admin3_code":"8327.0",
    "gn:admin4_code":"8327025.0",
    "gn:asciiname":"Hattingen",
    "gn:country_code":"DE",
    "gn:dem":758,
    "gn:feature_class":"P",
    "gn:feature_code":"PPL",
    "gn:name":"Hattingen",
    "gn:population":0,
    "gn:timezone":"Europe/Berlin",
    "iso:country":"DE",
    "name:ara_x_preferred":[
        "\u0647\u0627\u062a\u064a\u0646\u063a\u0646"
    ],
    "name:azb_x_preferred":[
        "\u0647\u0627\u062a\u06cc\u0646\u0642\u0646"
    ],
    "name:bul_x_preferred":[
        "\u0425\u0430\u0442\u0438\u043d\u0433\u0435\u043d"
    ],
    "name:ceb_x_preferred":[
        "Hattingen"
    ],
    "name:dan_x_preferred":[
        "Hattingen"
    ],
    "name:deu_x_preferred":[
        "Hattingen"
    ],
    "name:epo_x_preferred":[
        "Hattingen"
    ],
    "name:est_x_preferred":[
        "Hattingen"
    ],
    "name:eus_x_preferred":[
        "Hattingen"
    ],
    "name:fas_x_preferred":[
        "\u0647\u0627\u062a\u06cc\u0646\u06af\u0646"
    ],
    "name:fin_x_preferred":[
        "Hattingen"
    ],
    "name:fra_x_preferred":[
        "Hattingen"
    ],
    "name:hun_x_preferred":[
        "Hattingen"
    ],
    "name:ind_x_preferred":[
        "Hattingen"
    ],
    "name:ita_x_preferred":[
        "Hattingen"
    ],
    "name:kaz_x_preferred":[
        "\u0425\u0430\u0442\u0442\u0438\u043d\u0433\u0435\u043d"
    ],
    "name:kir_x_preferred":[
        "\u0425\u0430\u0442\u0442\u0438\u043d\u0433\u0435\u043d"
    ],
    "name:lim_x_preferred":[
        "Hattingen"
    ],
    "name:msa_x_preferred":[
        "Hattingen"
    ],
    "name:nds_x_preferred":[
        "Hattingen"
    ],
    "name:nld_x_preferred":[
        "Hattingen"
    ],
    "name:nno_x_preferred":[
        "Hattingen"
    ],
    "name:nor_x_preferred":[
        "Hattingen"
    ],
    "name:pnb_x_preferred":[
        "\u06c1\u06cc\u0679\u0646\u06af\u0646"
    ],
    "name:pol_x_preferred":[
        "Hattingen"
    ],
    "name:por_x_preferred":[
        "Hattingen"
    ],
    "name:ron_x_preferred":[
        "Hattingen"
    ],
    "name:rus_x_preferred":[
        "\u0425\u0430\u0442\u0442\u0438\u043d\u0433\u0435\u043d"
    ],
    "name:spa_x_preferred":[
        "Hattingen"
    ],
    "name:srp_x_preferred":[
        "\u0425\u0430\u0442\u0438\u043d\u0433\u0435\u043d"
    ],
    "name:swe_x_preferred":[
        "Hattingen"
    ],
    "name:tat_x_preferred":[
        "\u04ba\u0430\u0442\u0442\u0438\u043d\u0433\u0435\u043d"
    ],
    "name:tur_x_preferred":[
        "Hattingen"
    ],
    "name:uzb_x_preferred":[
        "Hattingen"
    ],
    "name:vol_x_preferred":[
        "Hattingen"
    ],
    "name:war_x_preferred":[
        "Hattingen"
    ],
    "name:zho_x_preferred":[
        "\u54c8\u5ef7\u6839"
    ],
    "wof:name":"Hattingen",
    "wof:placetype":"neighbourhood"
},
  "geometry": {"coordinates":[8.78508,47.92244],"type":"Point"}
}