{
  "type": "Feature",
  "properties": {
    "gn:admin1_code":"2.0",
    "gn:admin2_code":"97.0",
    "gn:admin3_code":"9780.0",
    "gn:admin4_code":"9780112.0",
    "gn:asciiname":"Braunlings",
    "gn:country_code":"DE",
    "gn:dem":789,
    "gn:feature_class":"P",
    "gn:feature_code":"PPL",
    "gn:name":"Br\u00e4unlings",
    "gn:population":0,
    "gn:timezone":"Europe/Berlin",
    "iso:country":"DE",
    "wof:name":"Braunlings",
    "wof:placetype":"neighbourhood"
},
  "geometry": {"coordinates":[10.18645,47.79088],"type":"Point"}
}