{
  "type": "Feature",
  "properties": {
    "gn:admin1_code":"6.0",
    "gn:admin2_code":"0.0",
    "gn:admin3_code":"3458.0",
    "gn:admin4_code":"3458013.0",
    "gn:asciiname":"Benthullen",
    "gn:country_code":"DE",
    "gn:dem":11,
    "gn:feature_class":"P",
    "gn:feature_code":"PPL",
    "gn:name":"Benthullen",
    "gn:population":0,
    "gn:timezone":"Europe/Berlin",
    "iso:country":"DE",
    "name:und_x_variant":[
        "Beuthullen",
        "Benthullen"
    ],
    "wof:name":"Benthullen",
    "wof:placetype":"neighbourhood"
},
  "geometry": {"coordinates":[8.10947,53.03969],"type":"Point"}
}