{
  "type": "Feature",
  "properties": {
    "gn:admin1_code":"1",
    "gn:admin2_code":"84.0",
    "gn:admin3_code":"8426.0",
    "gn:admin4_code":"8426045.0",
    "gn:asciiname":"Unterdill",
    "gn:country_code":"DE",
    "gn:dem":592,
    "gn:feature_class":"P",
    "gn:feature_code":"PPL",
    "gn:name":"Unterdill",
    "gn:population":0,
    "gn:timezone":"Europe/Berlin",
    "iso:country":"DE",
    "wof:name":"Unterdill",
    "wof:placetype":"neighbourhood"
},
  "geometry": {"coordinates":[9.48333,48.08333],"type":"Point"}
}