{
  "type": "Feature",
  "properties": {
    "gn:admin1_code":"2",
    "gn:admin2_code":"94.0",
    "gn:admin3_code":"9475.0",
    "gn:admin4_code":"9475171.0",
    "gn:asciiname":"Huttung",
    "gn:country_code":"DE",
    "gn:dem":574,
    "gn:feature_class":"P",
    "gn:feature_code":"PPL",
    "gn:name":"H\u00fcttung",
    "gn:population":0,
    "gn:timezone":"Europe/Berlin",
    "iso:country":"DE",
    "wof:name":"Huttung",
    "wof:placetype":"neighbourhood"
},
  "geometry": {"coordinates":[11.76923,50.30287],"type":"Point"}
}