{
  "type": "Feature",
  "properties": {
    "iso:country":"DE",
    "name:bar_x_preferred":[
        "Itter"
    ],
    "name:ceb_x_preferred":[
        "Itter"
    ],
    "name:ces_x_preferred":[
        "Itter"
    ],
    "name:deu_x_preferred":[
        "Itter"
    ],
    "name:est_x_preferred":[
        "Itteri vald"
    ],
    "name:fas_x_preferred":[
        "\u0627\u06cc\u062a\u0631"
    ],
    "name:fra_x_preferred":[
        "Itter"
    ],
    "name:hun_x_preferred":[
        "Itter"
    ],
    "name:ita_x_preferred":[
        "Itter"
    ],
    "name:kaz_x_preferred":[
        "\u0418\u0442\u0442\u0435\u0440"
    ],
    "name:nld_x_preferred":[
        "Itter"
    ],
    "name:pnb_x_preferred":[
        "\u0627\u06cc\u062a\u0631"
    ],
    "name:pol_x_preferred":[
        "Itter"
    ],
    "name:rus_x_preferred":[
        "\u0418\u0442\u0442\u0435\u0440"
    ],
    "name:slk_x_preferred":[
        "Itter"
    ],
    "name:spa_x_preferred":[
        "Itter"
    ],
    "name:swe_x_preferred":[
        "Itter"
    ],
    "name:ukr_x_preferred":[
        "\u0406\u0442\u0442\u0435\u0440"
    ],
    "name:uzb_x_preferred":[
        "Itter"
    ],
    "name:vol_x_preferred":[
        "Itter"
    ],
    "name:war_x_preferred":[
        "Itter"
    ],
    "name:zho_x_preferred":[
        "\u4f0a\u7279\u5c14"
    ],
    "wof:name":"Itter",
    "wof:placetype":"neighbourhood"
},
  "geometry": {"coordinates":[6.81814953498531,51.16719708473767],"type":"Point"}
}