{
  "type": "Feature",
  "properties": {
    "iso:country":"DE",
    "wof:name":"Itter",
    "wof:placetype":"neighbourhood"
},
  "geometry": {"coordinates":[6.81814953498531,51.16719708473767],"type":"Point"}
}