{
  "type": "Feature",
  "properties": {
    "gn:admin1_code":"2",
    "gn:admin2_code":"92.0",
    "gn:admin3_code":"9275.0",
    "gn:admin4_code":"9275146.0",
    "gn:asciiname":"Neuhauser",
    "gn:country_code":"DE",
    "gn:dem":409,
    "gn:feature_class":"P",
    "gn:feature_code":"PPL",
    "gn:name":"Neuh\u00e4user",
    "gn:population":0,
    "gn:timezone":"Europe/Berlin",
    "iso:country":"DE",
    "name:fra_x_preferred":[
        "Neuhauser"
    ],
    "wof:name":"Neuhauser",
    "wof:placetype":"neighbourhood"
},
  "geometry": {"coordinates":[13.4791,48.6485],"type":"Point"}
}