{
  "type": "Feature",
  "properties": {
    "gn:admin1_code":"2",
    "gn:admin2_code":"91.0",
    "gn:admin3_code":"9187.0",
    "gn:admin4_code":"9187159.0",
    "gn:asciiname":"Forsting",
    "gn:country_code":"DE",
    "gn:dem":503,
    "gn:feature_class":"P",
    "gn:feature_code":"PPL",
    "gn:name":"Forsting",
    "gn:population":0,
    "gn:timezone":"Europe/Berlin",
    "iso:country":"DE",
    "wof:name":"Forsting",
    "wof:placetype":"neighbourhood"
},
  "geometry": {"coordinates":[12.09071,48.08186],"type":"Point"}
}