{
  "type": "Feature",
  "properties": {
    "gn:admin1_code":"2",
    "gn:admin2_code":"95.0",
    "gn:admin3_code":"9571.0",
    "gn:admin4_code":"9571115.0",
    "gn:asciiname":"Froschau",
    "gn:country_code":"DE",
    "gn:dem":427,
    "gn:feature_class":"P",
    "gn:feature_code":"PPL",
    "gn:name":"Fr\u00f6schau",
    "gn:population":0,
    "gn:timezone":"Europe/Berlin",
    "iso:country":"DE",
    "wof:name":"Froschau",
    "wof:placetype":"neighbourhood"
},
  "geometry": {"coordinates":[10.57402,49.16161],"type":"Point"}
}