{
  "type": "Feature",
  "properties": {
    "gn:admin1_code":"10.0",
    "gn:asciiname":"Enge-Sande",
    "gn:country_code":"DE",
    "gn:dem":1,
    "gn:feature_class":"P",
    "gn:feature_code":"PPL",
    "gn:name":"Enge-Sande",
    "gn:population":0,
    "gn:timezone":"Europe/Berlin",
    "iso:country":"DE",
    "name:cat_x_preferred":[
        "Enge-Sande"
    ],
    "name:ceb_x_preferred":[
        "Enge-Sande"
    ],
    "name:dan_x_preferred":[
        "Enge-Sande"
    ],
    "name:deu_x_preferred":[
        "Enge-Sande"
    ],
    "name:epo_x_preferred":[
        "Enge-Sande"
    ],
    "name:eus_x_preferred":[
        "Enge-Sande"
    ],
    "name:fas_x_preferred":[
        "\u0627\u0646\u06af-\u0632\u0627\u0646\u062f\u0647"
    ],
    "name:fra_x_preferred":[
        "Enge-Sande"
    ],
    "name:frr_x_preferred":[
        "Ding-S\u00f6nj"
    ],
    "name:fry_x_preferred":[
        "Enge-Sande"
    ],
    "name:hun_x_preferred":[
        "Enge-Sande"
    ],
    "name:ita_x_preferred":[
        "Enge-Sande"
    ],
    "name:kaz_x_preferred":[
        "\u042d\u043d\u0433\u0435-\u0417\u0430\u043d\u0434\u0435"
    ],
    "name:kir_x_preferred":[
        "\u042d\u043d\u0433\u0435-\u0417\u0430\u043d\u0434\u0435"
    ],
    "name:mkd_x_preferred":[
        "\u0415\u043d\u0433\u0435-\u0417\u0430\u043d\u0434\u0435"
    ],
    "name:msa_x_preferred":[
        "Enge-Sande"
    ],
    "name:nld_x_preferred":[
        "Enge-Sande"
    ],
    "name:pol_x_preferred":[
        "Enge-Sande"
    ],
    "name:por_x_preferred":[
        "Enge-Sande"
    ],
    "name:ron_x_preferred":[
        "Enge-Sande"
    ],
    "name:rus_x_preferred":[
        "\u042d\u043d\u0433\u0435-\u0417\u0430\u043d\u0434\u0435"
    ],
    "name:spa_x_preferred":[
        "Enge-Sande"
    ],
    "name:srp_x_preferred":[
        "\u0415\u043d\u0433\u0435-\u0417\u0430\u043d\u0434\u0435"
    ],
    "name:tur_x_preferred":[
        "Enge-Sande"
    ],
    "name:ukr_x_preferred":[
        "\u0415\u043d\u0433\u0435-\u0417\u0430\u043d\u0434\u0435"
    ],
    "name:uzb_x_preferred":[
        "Enge-Sande"
    ],
    "name:vie_x_preferred":[
        "Enge-Sande"
    ],
    "name:vol_x_preferred":[
        "Enge-Sande"
    ],
    "name:war_x_preferred":[
        "Enge-Sande"
    ],
    "name:zho_x_preferred":[
        "\u6069\u683c-\u6851\u5fb7"
    ],
    "wof:name":"Enge-Sande",
    "wof:placetype":"neighbourhood"
},
  "geometry": {"coordinates":[9.98333,54.73333],"type":"Point"}
}