{
  "type": "Feature",
  "properties": {
    "gn:admin1_code":"14",
    "gn:admin2_code":"0.0",
    "gn:admin3_code":"15084.0",
    "gn:admin4_code":"15084355.0",
    "gn:asciiname":"Heiligenkreuz",
    "gn:country_code":"DE",
    "gn:dem":255,
    "gn:feature_class":"P",
    "gn:feature_code":"PPL",
    "gn:name":"Heiligenkreuz",
    "gn:population":0,
    "gn:timezone":"Europe/Berlin",
    "iso:country":"DE",
    "name:ceb_x_preferred":[
        "Heiligenkreuz"
    ],
    "name:ces_x_preferred":[
        "Heiligenkreuz"
    ],
    "name:deu_x_preferred":[
        "Heiligenkreuz"
    ],
    "name:fra_x_preferred":[
        "Heiligenkreuz"
    ],
    "name:hun_x_preferred":[
        "Heiligenkreuz"
    ],
    "name:ita_x_preferred":[
        "Heiligenkreuz"
    ],
    "name:nld_x_preferred":[
        "Heiligenkreuz"
    ],
    "name:pol_x_preferred":[
        "Heiligenkreuz"
    ],
    "name:por_x_preferred":[
        "Heiligenkreuz"
    ],
    "name:ron_x_preferred":[
        "Heiligenkreuz"
    ],
    "name:rus_x_preferred":[
        "\u0425\u0430\u0439\u043b\u0438\u0433\u0435\u043d\u043a\u0440\u043e\u0439\u0446"
    ],
    "name:swe_x_preferred":[
        "Heiligenkreuz"
    ],
    "wof:name":"Heiligenkreuz",
    "wof:placetype":"neighbourhood"
},
  "geometry": {"coordinates":[11.75694,51.10689],"type":"Point"}
}