{
  "type": "Feature",
  "properties": {
    "gn:admin1_code":"7",
    "gn:admin2_code":"53.0",
    "gn:admin3_code":"5378.0",
    "gn:admin4_code":"5378008.0",
    "gn:asciiname":"Neuenhaus",
    "gn:country_code":"DE",
    "gn:dem":154,
    "gn:feature_class":"P",
    "gn:feature_code":"PPL",
    "gn:name":"Neuenhaus",
    "gn:population":0,
    "gn:timezone":"Europe/Berlin",
    "iso:country":"DE",
    "name:ara_x_preferred":[
        "\u0646\u0648\u064a\u0646\u0647\u0627\u0648\u0633"
    ],
    "name:azb_x_preferred":[
        "\u0646\u0648\u06cc\u0646\u200c\u0647\u0627\u0648\u0633"
    ],
    "name:ceb_x_preferred":[
        "Neuenhaus"
    ],
    "name:deu_x_preferred":[
        "Neuenhaus"
    ],
    "name:epo_x_preferred":[
        "Neuenhaus"
    ],
    "name:est_x_preferred":[
        "Neuenhaus"
    ],
    "name:eus_x_preferred":[
        "Neuenhaus"
    ],
    "name:fas_x_preferred":[
        "\u0646\u0648\u06cc\u0646\u200c\u0647\u0627\u0648\u0633"
    ],
    "name:fra_x_preferred":[
        "Neuenhaus"
    ],
    "name:hun_x_preferred":[
        "Neuenhaus"
    ],
    "name:ita_x_preferred":[
        "Neuenhaus"
    ],
    "name:kaz_x_preferred":[
        "\u041d\u043e\u0439\u0435\u043d\u0445\u0430\u0443\u0441"
    ],
    "name:kir_x_preferred":[
        "\u041d\u043e\u0439\u0435\u043d\u0445\u0430\u0443\u0441"
    ],
    "name:lat_x_preferred":[
        "Neuenhaus"
    ],
    "name:msa_x_preferred":[
        "Neuenhaus"
    ],
    "name:nld_x_preferred":[
        "Neuenhaus"
    ],
    "name:pol_x_preferred":[
        "Neuenhaus"
    ],
    "name:por_x_preferred":[
        "Neuenhaus"
    ],
    "name:ron_x_preferred":[
        "Neuenhaus"
    ],
    "name:rus_x_preferred":[
        "\u041d\u043e\u0439\u0435\u043d\u0445\u0430\u0443\u0441"
    ],
    "name:spa_x_preferred":[
        "Neuenhaus"
    ],
    "name:srp_x_preferred":[
        "\u041d\u043e\u0458\u0435\u043d\u0445\u0430\u0443\u0441"
    ],
    "name:swe_x_preferred":[
        "Neuenhaus"
    ],
    "name:tur_x_preferred":[
        "Neuenhaus"
    ],
    "name:ukr_x_preferred":[
        "\u041d\u043e\u0454\u043d\u0433\u0430\u0443\u0441"
    ],
    "name:uzb_x_preferred":[
        "Neuenhaus"
    ],
    "name:vie_x_preferred":[
        "Neuenhaus"
    ],
    "name:vol_x_preferred":[
        "Neuenhaus"
    ],
    "name:war_x_preferred":[
        "Neuenhaus"
    ],
    "name:zho_x_preferred":[
        "\u8bfa\u4f0a\u6069\u8c6a\u65af"
    ],
    "wof:name":"Neuenhaus",
    "wof:placetype":"neighbourhood"
},
  "geometry": {"coordinates":[7.08317,51.08866],"type":"Point"}
}