{
  "type": "Feature",
  "properties": {
    "gn:admin1_code":"13",
    "gn:admin2_code":"0.0",
    "gn:admin3_code":"14625.0",
    "gn:admin4_code":"14625550.0",
    "gn:asciiname":"Gruengraebchen",
    "gn:country_code":"DE",
    "gn:dem":133,
    "gn:feature_class":"P",
    "gn:feature_code":"PPL",
    "gn:name":"Gr\u00fcngr\u00e4bchen",
    "gn:population":0,
    "gn:timezone":"Europe/Berlin",
    "iso:country":"DE",
    "wof:name":"Gruengraebchen",
    "wof:placetype":"neighbourhood"
},
  "geometry": {"coordinates":[13.97527,51.35748],"type":"Point"}
}