{
  "type": "Feature",
  "properties": {
    "gn:admin1_code":"14",
    "gn:admin2_code":"0.0",
    "gn:admin3_code":"15003.0",
    "gn:admin4_code":"15003000.0",
    "gn:asciiname":"Malpendorf",
    "gn:country_code":"DE",
    "gn:dem":48,
    "gn:feature_class":"P",
    "gn:feature_code":"PPL",
    "gn:name":"Malpendorf",
    "gn:population":0,
    "gn:timezone":"Europe/Berlin",
    "iso:country":"DE",
    "wof:name":"Malpendorf",
    "wof:placetype":"neighbourhood"
},
  "geometry": {"coordinates":[11.68333,52.05],"type":"Point"}
}