{
  "type": "Feature",
  "properties": {
    "gn:admin1_code":"2",
    "gn:admin2_code":"91.0",
    "gn:admin3_code":"9177.0",
    "gn:admin4_code":"9177120.0",
    "gn:asciiname":"Grosshundlbach",
    "gn:country_code":"DE",
    "gn:dem":461,
    "gn:feature_class":"P",
    "gn:feature_code":"PPL",
    "gn:name":"Gro\u00dfh\u00fcndlbach",
    "gn:population":0,
    "gn:timezone":"Europe/Berlin",
    "iso:country":"DE",
    "wof:name":"Grosshundlbach",
    "wof:placetype":"neighbourhood"
},
  "geometry": {"coordinates":[12.01875,48.345],"type":"Point"}
}