{
  "type": "Feature",
  "properties": {
    "gn:admin1_code":"7",
    "gn:admin2_code":"59.0",
    "gn:admin3_code":"5970.0",
    "gn:admin4_code":"5970024.0",
    "gn:asciiname":"Mittelhees",
    "gn:country_code":"DE",
    "gn:dem":308,
    "gn:feature_class":"P",
    "gn:feature_code":"PPLL",
    "gn:name":"Mittelhees",
    "gn:population":0,
    "gn:timezone":"Europe/Berlin",
    "iso:country":"DE",
    "name:deu_x_preferred":[
        "Mittelhees"
    ],
    "name:fas_x_preferred":[
        "\u0645\u06cc\u062a\u0644\u0647\u0633"
    ],
    "wof:name":"Mittelhees",
    "wof:placetype":"neighbourhood"
},
  "geometry": {"coordinates":[7.95311,50.94638],"type":"Point"}
}