{
  "type": "Feature",
  "properties": {
    "gn:admin1_code":"1",
    "gn:admin2_code":"84.0",
    "gn:admin3_code":"8421.0",
    "gn:admin4_code":"8421000.0",
    "gn:asciiname":"Grimmelfingen",
    "gn:country_code":"DE",
    "gn:dem":513,
    "gn:feature_class":"P",
    "gn:feature_code":"PPL",
    "gn:name":"Grimmelfingen",
    "gn:population":0,
    "gn:timezone":"Europe/Berlin",
    "iso:country":"DE",
    "wof:name":"Grimmelfingen",
    "wof:placetype":"neighbourhood"
},
  "geometry": {"coordinates":[9.93576,48.37185],"type":"Point"}
}