{
  "type": "Feature",
  "properties": {
    "gn:admin1_code":"13",
    "gn:admin2_code":"0.0",
    "gn:admin3_code":"14524.0",
    "gn:admin4_code":"14524160.0",
    "gn:asciiname":"Heinrichsort",
    "gn:country_code":"DE",
    "gn:dem":440,
    "gn:feature_class":"P",
    "gn:feature_code":"PPL",
    "gn:name":"Heinrichsort",
    "gn:population":0,
    "gn:timezone":"Europe/Berlin",
    "iso:country":"DE",
    "wof:name":"Heinrichsort",
    "wof:placetype":"neighbourhood"
},
  "geometry": {"coordinates":[12.63875,50.72647],"type":"Point"}
}