{
  "type": "Feature",
  "properties": {
    "gn:admin1_code":"2",
    "gn:admin2_code":"91.0",
    "gn:admin3_code":"9183.0",
    "gn:admin4_code":"9183139.0",
    "gn:asciiname":"Hochhaus",
    "gn:country_code":"DE",
    "gn:dem":537,
    "gn:feature_class":"P",
    "gn:feature_code":"PPL",
    "gn:name":"Hochhaus",
    "gn:population":0,
    "gn:timezone":"Europe/Berlin",
    "iso:country":"DE",
    "wof:name":"Hochhaus",
    "wof:placetype":"neighbourhood"
},
  "geometry": {"coordinates":[12.16244,48.14158],"type":"Point"}
}