{
  "type": "Feature",
  "properties": {
    "gn:admin1_code":"12",
    "gn:admin2_code":"0.0",
    "gn:admin3_code":"13073.0",
    "gn:admin4_code":"13073105.0",
    "gn:asciiname":"Klein Kirr",
    "gn:country_code":"DE",
    "gn:dem":-2,
    "gn:feature_class":"P",
    "gn:feature_code":"PPL",
    "gn:name":"Klein Kirr",
    "gn:population":0,
    "gn:timezone":"Europe/Berlin",
    "iso:country":"DE",
    "wof:name":"Klein Kirr",
    "wof:placetype":"neighbourhood"
},
  "geometry": {"coordinates":[12.72165,54.42033000000001],"type":"Point"}
}