{
  "type": "Feature",
  "properties": {
    "gn:admin1_code":"12.0",
    "gn:admin2_code":"0.0",
    "gn:admin3_code":"13075.0",
    "gn:admin4_code":"13075098.0",
    "gn:asciiname":"Alt Kosenow",
    "gn:country_code":"DE",
    "gn:dem":3,
    "gn:feature_class":"P",
    "gn:feature_code":"PPL",
    "gn:name":"Alt Kosenow",
    "gn:population":0,
    "gn:timezone":"Europe/Berlin",
    "iso:country":"DE",
    "wof:name":"Alt Kosenow",
    "wof:placetype":"neighbourhood"
},
  "geometry": {"coordinates":[13.75857,53.79316],"type":"Point"}
}