{
  "type": "Feature",
  "properties": {
    "gn:admin1_code":"7",
    "gn:admin2_code":"57.0",
    "gn:admin3_code":"5758.0",
    "gn:admin4_code":"5758012.0",
    "gn:asciiname":"Elsen",
    "gn:country_code":"DE",
    "gn:dem":95,
    "gn:feature_class":"P",
    "gn:feature_code":"PPL",
    "gn:name":"Elsen",
    "gn:population":0,
    "gn:timezone":"Europe/Berlin",
    "iso:country":"DE",
    "name:ceb_x_preferred":[
        "Elsen"
    ],
    "name:deu_x_preferred":[
        "Elsen"
    ],
    "name:fas_x_preferred":[
        "\u0627\u0644\u0632\u0646"
    ],
    "name:por_x_preferred":[
        "Elsen"
    ],
    "wof:name":"Elsen",
    "wof:placetype":"neighbourhood"
},
  "geometry": {"coordinates":[8.63345,52.07708],"type":"Point"}
}