{
  "type": "Feature",
  "properties": {
    "gn:admin1_code":"7",
    "gn:admin2_code":"51.0",
    "gn:admin3_code":"5170.0",
    "gn:admin4_code":"5170048.0",
    "gn:asciiname":"Schuettwick",
    "gn:country_code":"DE",
    "gn:dem":19,
    "gn:feature_class":"P",
    "gn:feature_code":"PPL",
    "gn:name":"Sch\u00fcttwick",
    "gn:population":0,
    "gn:timezone":"Europe/Berlin",
    "iso:country":"DE",
    "wof:name":"Schuettwick",
    "wof:placetype":"neighbourhood"
},
  "geometry": {"coordinates":[6.5187,51.6904],"type":"Point"}
}