{
  "type": "Feature",
  "properties": {
    "gn:admin1_code":"1",
    "gn:admin2_code":"84.0",
    "gn:admin3_code":"8425.0",
    "gn:admin4_code":"8425075.0",
    "gn:asciiname":"Halzhausen",
    "gn:country_code":"DE",
    "gn:dem":574,
    "gn:feature_class":"P",
    "gn:feature_code":"PPL",
    "gn:name":"Halzhausen",
    "gn:population":0,
    "gn:timezone":"Europe/Berlin",
    "iso:country":"DE",
    "wof:name":"Halzhausen",
    "wof:placetype":"neighbourhood"
},
  "geometry": {"coordinates":[9.92619,48.53562],"type":"Point"}
}