{
  "type": "Feature",
  "properties": {
    "gn:admin1_code":"2",
    "gn:admin2_code":"94.0",
    "gn:admin3_code":"9476.0",
    "gn:admin4_code":"9476146.0",
    "gn:asciiname":"Oberlangenstadt",
    "gn:country_code":"DE",
    "gn:dem":287,
    "gn:feature_class":"P",
    "gn:feature_code":"PPL",
    "gn:name":"Oberlangenstadt",
    "gn:population":0,
    "gn:timezone":"Europe/Berlin",
    "iso:country":"DE",
    "name:bar_x_preferred":[
        "Oberlangenstadt"
    ],
    "name:deu_x_preferred":[
        "Oberlangenstadt"
    ],
    "wof:name":"Oberlangenstadt",
    "wof:placetype":"neighbourhood"
},
  "geometry": {"coordinates":[11.25871,50.18915],"type":"Point"}
}