{
  "type": "Feature",
  "properties": {
    "gn:admin1_code":"2",
    "gn:admin2_code":"94.0",
    "gn:admin3_code":"9478.0",
    "gn:admin4_code":"9478111.0",
    "gn:asciiname":"Maineck",
    "gn:country_code":"DE",
    "gn:dem":297,
    "gn:feature_class":"P",
    "gn:feature_code":"PPL",
    "gn:name":"Maineck",
    "gn:population":0,
    "gn:timezone":"Europe/Berlin",
    "iso:country":"DE",
    "wof:name":"Maineck",
    "wof:placetype":"neighbourhood"
},
  "geometry": {"coordinates":[11.29988,50.11686],"type":"Point"}
}