{
  "type": "Feature",
  "properties": {
    "gn:admin1_code":"2",
    "gn:admin2_code":"95.0",
    "gn:admin3_code":"9573.0",
    "gn:admin4_code":"9573125.0",
    "gn:asciiname":"Oedenreuth",
    "gn:country_code":"DE",
    "gn:dem":401,
    "gn:feature_class":"P",
    "gn:feature_code":"PPL",
    "gn:name":"Oedenreuth",
    "gn:population":0,
    "gn:timezone":"Europe/Berlin",
    "iso:country":"DE",
    "name:und_x_variant":[
        "\u00d6denreuth",
        "Oedenreuth"
    ],
    "wof:name":"Oedenreuth",
    "wof:placetype":"neighbourhood"
},
  "geometry": {"coordinates":[10.9108,49.38037],"type":"Point"}
}