{
  "type": "Feature",
  "properties": {
    "gn:admin1_code":"12",
    "gn:admin2_code":"0.0",
    "gn:admin3_code":"13072.0",
    "gn:admin4_code":"13072058.0",
    "gn:asciiname":"Klein Siemen",
    "gn:country_code":"DE",
    "gn:dem":53,
    "gn:feature_class":"P",
    "gn:feature_code":"PPL",
    "gn:name":"Klein Siemen",
    "gn:population":0,
    "gn:timezone":"Europe/Berlin",
    "iso:country":"DE",
    "wof:name":"Klein Siemen",
    "wof:placetype":"neighbourhood"
},
  "geometry": {"coordinates":[11.82648,54.01598000000001],"type":"Point"}
}