{
  "type": "Feature",
  "properties": {
    "gn:admin1_code":"2",
    "gn:admin2_code":"92.0",
    "gn:admin3_code":"9276.0",
    "gn:admin4_code":"9276130.0",
    "gn:asciiname":"Ludwigsthal",
    "gn:country_code":"DE",
    "gn:dem":613,
    "gn:feature_class":"P",
    "gn:feature_code":"PPL",
    "gn:name":"Ludwigsthal",
    "gn:population":0,
    "gn:timezone":"Europe/Berlin",
    "iso:country":"DE",
    "wof:name":"Ludwigsthal",
    "wof:placetype":"neighbourhood"
},
  "geometry": {"coordinates":[13.23621,49.05801],"type":"Point"}
}