{
  "type": "Feature",
  "properties": {
    "gn:admin1_code":"2",
    "gn:admin2_code":"91.0",
    "gn:admin3_code":"9188.0",
    "gn:admin4_code":"9188132.0",
    "gn:asciiname":"Delling",
    "gn:country_code":"DE",
    "gn:dem":587,
    "gn:feature_class":"P",
    "gn:feature_code":"PPL",
    "gn:name":"Delling",
    "gn:population":0,
    "gn:timezone":"Europe/Berlin",
    "iso:country":"DE",
    "name:deu_x_preferred":[
        "Delling"
    ],
    "wof:name":"Delling",
    "wof:placetype":"neighbourhood"
},
  "geometry": {"coordinates":[11.23755,48.05938],"type":"Point"}
}