{
  "type": "Feature",
  "properties": {
    "gn:admin1_code":"2.0",
    "gn:admin2_code":"97.0",
    "gn:admin3_code":"9778.0",
    "gn:admin4_code":"9778173.0",
    "gn:asciiname":"Bergerhausen",
    "gn:country_code":"DE",
    "gn:dem":618,
    "gn:feature_class":"P",
    "gn:feature_code":"PPL",
    "gn:name":"Bergerhausen",
    "gn:population":0,
    "gn:timezone":"Europe/Berlin",
    "iso:country":"DE",
    "name:deu_x_preferred":[
        "Bergerhausen"
    ],
    "wof:name":"Bergerhausen",
    "wof:placetype":"neighbourhood"
},
  "geometry": {"coordinates":[10.4467,48.06802],"type":"Point"}
}