{
  "type": "Feature",
  "properties": {
    "iso:country":"DE",
    "name:deu_x_preferred":[
        "Oberb\u00fcrg"
    ],
    "wof:name":"Oberbuerg",
    "wof:placetype":"neighbourhood"
},
  "geometry": {"coordinates":[11.15460208290361,49.46915300276038],"type":"Point"}
}