{
  "type": "Feature",
  "properties": {
    "gn:admin1_code":"6.0",
    "gn:admin2_code":"0.0",
    "gn:admin3_code":"3154.0",
    "gn:admin4_code":"3154014.0",
    "gn:asciiname":"Beienrode",
    "gn:country_code":"DE",
    "gn:dem":89,
    "gn:feature_class":"P",
    "gn:feature_code":"PPL",
    "gn:name":"Beienrode",
    "gn:population":0,
    "gn:timezone":"Europe/Berlin",
    "iso:country":"DE",
    "name:deu_x_preferred":[
        "Beienrode (Lehre)"
    ],
    "name:deu_x_variant":[
        "Beienrode"
    ],
    "wof:name":"Beienrode",
    "wof:placetype":"neighbourhood"
},
  "geometry": {"coordinates":[10.73836,52.35296],"type":"Point"}
}