{
  "type": "Feature",
  "properties": {
    "gn:admin1_code":"1",
    "gn:admin2_code":"83.0",
    "gn:admin3_code":"8325.0",
    "gn:admin4_code":"8325053.0",
    "gn:asciiname":"Buhl",
    "gn:country_code":"DE",
    "gn:dem":738,
    "gn:feature_class":"P",
    "gn:feature_code":"PPL",
    "gn:name":"B\u00fchl",
    "gn:population":0,
    "gn:timezone":"Europe/Berlin",
    "iso:country":"DE",
    "name:cat_x_preferred":[
        "Buhl"
    ],
    "name:ceb_x_preferred":[
        "Buhl"
    ],
    "name:deu_x_preferred":[
        "Buhl"
    ],
    "name:fin_x_preferred":[
        "Buhl"
    ],
    "name:fra_x_preferred":[
        "Buhl"
    ],
    "name:ita_x_preferred":[
        "Buhl"
    ],
    "name:nds_x_preferred":[
        "Buhl"
    ],
    "name:nld_x_preferred":[
        "Buhl"
    ],
    "name:pms_x_preferred":[
        "Buhl"
    ],
    "name:pol_x_preferred":[
        "Buhl"
    ],
    "name:por_x_preferred":[
        "Buhl"
    ],
    "name:slk_x_preferred":[
        "Buhl"
    ],
    "name:srp_x_preferred":[
        "\u0411\u0443\u043b"
    ],
    "name:swe_x_preferred":[
        "Buhl"
    ],
    "name:ukr_x_preferred":[
        "\u0411\u044e\u043b"
    ],
    "name:vol_x_preferred":[
        "Buhl"
    ],
    "wof:name":"Buhl",
    "wof:placetype":"neighbourhood"
},
  "geometry": {"coordinates":[8.36258,48.19496],"type":"Point"}
}