{
  "type": "Feature",
  "properties": {
    "gn:admin1_code":"11",
    "gn:admin2_code":"0.0",
    "gn:admin3_code":"12069.0",
    "gn:admin4_code":"12069306.0",
    "gn:asciiname":"Pruetzke",
    "gn:country_code":"DE",
    "gn:dem":34,
    "gn:feature_class":"P",
    "gn:feature_code":"PPL",
    "gn:name":"Pr\u00fctzke",
    "gn:population":0,
    "gn:timezone":"Europe/Berlin",
    "iso:country":"DE",
    "name:deu_x_preferred":[
        "Pr\u00fctzke"
    ],
    "wof:name":"Pruetzke",
    "wof:placetype":"neighbourhood"
},
  "geometry": {"coordinates":[12.62866,52.35005],"type":"Point"}
}