{
  "type": "Feature",
  "properties": {
    "gn:admin1_code":"1",
    "gn:admin2_code":"81.0",
    "gn:admin3_code":"8119.0",
    "gn:admin4_code":"8119004.0",
    "gn:asciiname":"Mittel-Voggenhof",
    "gn:country_code":"DE",
    "gn:dem":474,
    "gn:feature_class":"P",
    "gn:feature_code":"PPL",
    "gn:name":"Mittel-Voggenhof",
    "gn:population":0,
    "gn:timezone":"Europe/Berlin",
    "iso:country":"DE",
    "wof:name":"Mittel-Voggenhof",
    "wof:placetype":"neighbourhood"
},
  "geometry": {"coordinates":[9.59059,48.91913],"type":"Point"}
}