{
  "type": "Feature",
  "properties": {
    "gn:admin1_code":"14",
    "gn:admin2_code":"0.0",
    "gn:admin3_code":"15090.0",
    "gn:admin4_code":"15090070.0",
    "gn:asciiname":"Wartenberg",
    "gn:country_code":"DE",
    "gn:dem":39,
    "gn:feature_class":"P",
    "gn:feature_code":"PPL",
    "gn:name":"Wartenberg",
    "gn:population":0,
    "gn:timezone":"Europe/Berlin",
    "iso:country":"DE",
    "name:als_x_preferred":[
        "Wartenberg"
    ],
    "name:ceb_x_preferred":[
        "Wartenberg"
    ],
    "name:deu_x_preferred":[
        "Wartenberg"
    ],
    "name:epo_x_preferred":[
        "Wartenberg"
    ],
    "name:fra_x_preferred":[
        "Wartenberg"
    ],
    "name:hun_x_preferred":[
        "Wartenberg"
    ],
    "name:ita_x_preferred":[
        "Wartenberg"
    ],
    "name:jpn_x_preferred":[
        "\u30f4\u30a1\u30eb\u30c6\u30f3\u30d9\u30eb\u30af"
    ],
    "name:nld_x_preferred":[
        "Wartenberg"
    ],
    "name:pol_x_preferred":[
        "Wartenberg"
    ],
    "name:rus_x_preferred":[
        "\u0412\u0430\u0440\u0442\u0435\u043d\u0431\u0435\u0440\u0433"
    ],
    "name:swe_x_preferred":[
        "Wartenberg"
    ],
    "name:vol_x_preferred":[
        "Wartenberg"
    ],
    "wof:name":"Wartenberg",
    "wof:placetype":"neighbourhood"
},
  "geometry": {"coordinates":[11.51317,52.63841],"type":"Point"}
}