{
  "type": "Feature",
  "properties": {
    "gn:admin1_code":"6.0",
    "gn:admin2_code":"00",
    "gn:admin3_code":"3451.0",
    "gn:admin4_code":"3451008.0",
    "gn:asciiname":"Wiefelstedermoor",
    "gn:country_code":"DE",
    "gn:dem":14,
    "gn:feature_class":"P",
    "gn:feature_code":"PPLL",
    "gn:name":"Wiefelstedermoor",
    "gn:population":0,
    "gn:timezone":"Europe/Berlin",
    "iso:country":"DE",
    "wof:name":"Wiefelstedermoor",
    "wof:placetype":"neighbourhood"
},
  "geometry": {"coordinates":[8.07961,53.25144],"type":"Point"}
}