{
  "type": "Feature",
  "properties": {
    "gn:gn_country":"DE",
    "gn:gn_fcode":"PPLX",
    "gn:gn_pop":0,
    "iso:country":"DE",
    "name:deu_x_preferred":[
        "Jagenberg"
    ],
    "name:unk_x_variant":[
        "Jagenberg"
    ],
    "qs:gn_fcode":"PPLX",
    "qs:gn_local":0,
    "qs:gn_namadm1":"07",
    "qs:gn_name":"Jagenberg",
    "qs:local_max":723,
    "qs:local_sum":3477,
    "qs:localhoods":34,
    "qs:name":"Jagenberg",
    "qs:name_adm0":"Deutschland",
    "qs:name_adm1":"Nordrhein-Westfalen",
    "qs:name_adm2":"Stadtkreis Solingen",
    "qs:name_lau":"Stadtteil Ohlig",
    "qs:name_local":"Stadtteil Ohlig",
    "qs:photo_max":25,
    "qs:photo_sum":51,
    "qs:placetype":"Suburb",
    "qs:quad_count":13,
    "qs:woe_adm0":23424829,
    "qs:woe_adm1":2345487,
    "qs:woe_adm2":12597079,
    "qs:woe_lau":26823245,
    "qs:woe_local":26823245,
    "qs:woe_ver":"7.10.0",
    "qs_pg:aaroncc":"DE",
    "qs_pg:gn_country":"DE",
    "qs_pg:gn_fcode":"PPLX",
    "qs_pg:gn_pop":0,
    "qs_pg:name":"Jagenberg",
    "qs_pg:name_adm0":"Deutschland",
    "qs_pg:name_adm1":"Nordrhein-Westfalen",
    "qs_pg:photos":64,
    "qs_pg:photos_1k":13,
    "qs_pg:photos_9k":1,
    "qs_pg:photos_9r":2,
    "qs_pg:photos_all":64,
    "qs_pg:photos_sr":2,
    "qs_pg:pop_sr":0,
    "qs_pg:qs_pg_placetype":"neighbourhood",
    "qs_pg:qs_pg_placetype_gp":"Suburb",
    "qs_pg:woe_adm0":23424829,
    "wof:lang":[
        "ger"
    ],
    "wof:name":"Jagenberg",
    "wof:placetype":"neighbourhood"
},
  "geometry": {"coordinates":[7.124971,51.147111],"type":"Point"}
}