{
  "type": "Feature",
  "properties": {
    "gn:admin1_code":"2",
    "gn:admin2_code":"94.0",
    "gn:admin3_code":"9472.0",
    "gn:admin4_code":"9472116.0",
    "gn:asciiname":"Micheldorf",
    "gn:country_code":"DE",
    "gn:dem":505,
    "gn:feature_class":"P",
    "gn:feature_code":"PPL",
    "gn:name":"Micheldorf",
    "gn:population":0,
    "gn:timezone":"Europe/Berlin",
    "iso:country":"DE",
    "name:ceb_x_preferred":[
        "Micheldorf"
    ],
    "name:deu_x_preferred":[
        "Micheldorf"
    ],
    "name:epo_x_preferred":[
        "Micheldorf"
    ],
    "name:fas_x_preferred":[
        "\u0645\u06cc\u062e\u0644\u062f\u0648\u0631\u0641"
    ],
    "name:fra_x_preferred":[
        "Micheldorf"
    ],
    "name:fur_x_preferred":[
        "Micheldorf"
    ],
    "name:hun_x_preferred":[
        "Micheldorf"
    ],
    "name:ita_x_preferred":[
        "Micheldorf"
    ],
    "name:kaz_x_preferred":[
        "\u041c\u0438\u0445\u0435\u043b\u044c\u0434\u043e\u0440\u0444"
    ],
    "name:nld_x_preferred":[
        "Micheldorf"
    ],
    "name:pol_x_preferred":[
        "Micheldorf"
    ],
    "name:por_x_preferred":[
        "Micheldorf"
    ],
    "name:rus_x_preferred":[
        "\u041c\u0438\u0445\u0435\u043b\u044c\u0434\u043e\u0440\u0444"
    ],
    "name:slk_x_preferred":[
        "Micheldorf"
    ],
    "name:spa_x_preferred":[
        "Micheldorf"
    ],
    "name:ukr_x_preferred":[
        "\u041c\u0456\u0445\u0435\u043b\u044c\u0434\u043e\u0440\u0444"
    ],
    "name:uzb_x_preferred":[
        "Micheldorf"
    ],
    "name:vie_x_preferred":[
        "Micheldorf"
    ],
    "name:vol_x_preferred":[
        "Micheldorf"
    ],
    "name:war_x_preferred":[
        "Micheldorf"
    ],
    "name:zho_x_preferred":[
        "\u7c73\u6b47\u5c14\u591a\u592b"
    ],
    "wof:name":"Micheldorf",
    "wof:placetype":"neighbourhood"
},
  "geometry": {"coordinates":[11.65131,50.05662],"type":"Point"}
}