{
  "type": "Feature",
  "properties": {
    "gn:admin1_code":"6",
    "gn:admin2_code":"0.0",
    "gn:admin3_code":"3159.0",
    "gn:admin4_code":"3159010.0",
    "gn:asciiname":"Hilkerode",
    "gn:country_code":"DE",
    "gn:dem":168,
    "gn:feature_class":"P",
    "gn:feature_code":"PPL",
    "gn:name":"Hilkerode",
    "gn:population":0,
    "gn:timezone":"Europe/Berlin",
    "iso:country":"DE",
    "wof:name":"Hilkerode",
    "wof:placetype":"neighbourhood"
},
  "geometry": {"coordinates":[10.30906,51.56204],"type":"Point"}
}