{
  "type": "Feature",
  "properties": {
    "gn:admin1_code":"1",
    "gn:admin2_code":"84.0",
    "gn:admin3_code":"8436.0",
    "gn:admin4_code":"8436001.0",
    "gn:asciiname":"Regnitz",
    "gn:country_code":"DE",
    "gn:dem":546,
    "gn:feature_class":"P",
    "gn:feature_code":"PPL",
    "gn:name":"Regnitz",
    "gn:population":0,
    "gn:timezone":"Europe/Berlin",
    "iso:country":"DE",
    "name:ara_x_preferred":[
        "\u0646\u0647\u0631 \u0631\u064a\u063a\u0646\u064a\u062a\u0632"
    ],
    "name:bel_x_preferred":[
        "\u0420\u044d\u0433\u043d\u0456\u0446"
    ],
    "name:ceb_x_preferred":[
        "Regnitz"
    ],
    "name:ces_x_preferred":[
        "Regnitz"
    ],
    "name:chv_x_preferred":[
        "\u0420\u0435\u0433\u043d\u0438\u0446"
    ],
    "name:dan_x_preferred":[
        "Regnitz"
    ],
    "name:deu_x_preferred":[
        "Regnitz"
    ],
    "name:epo_x_preferred":[
        "Regnitz"
    ],
    "name:fas_x_preferred":[
        "\u0631\u06af\u0646\u06cc\u062a\u0633"
    ],
    "name:fra_x_preferred":[
        "Regnitz"
    ],
    "name:hsb_x_preferred":[
        "Regnitz"
    ],
    "name:ita_x_preferred":[
        "Regnitz"
    ],
    "name:jpn_x_preferred":[
        "\u30ec\u30b0\u30cb\u30c3\u30c4\u5ddd"
    ],
    "name:nld_x_preferred":[
        "Regnitz"
    ],
    "name:nno_x_preferred":[
        "Regnitz"
    ],
    "name:nor_x_preferred":[
        "Regnitz"
    ],
    "name:pol_x_preferred":[
        "Regnitz"
    ],
    "name:ron_x_preferred":[
        "Regnitz"
    ],
    "name:rus_x_preferred":[
        "\u0420\u0435\u0433\u043d\u0438\u0446"
    ],
    "name:slk_x_preferred":[
        "Regnitz"
    ],
    "name:spa_x_preferred":[
        "R\u00edo Regnitz"
    ],
    "name:srp_x_preferred":[
        "\u0420\u0435\u0433\u043d\u0438\u0446"
    ],
    "name:ukr_x_preferred":[
        "\u0420\u0435\u0491\u043d\u0456\u0446"
    ],
    "name:vie_x_preferred":[
        "S\u00f4ng Regnitz"
    ],
    "name:zho_x_preferred":[
        "\u96f7\u683c\u5c3c\u8328\u6cb3"
    ],
    "wof:name":"Regnitz",
    "wof:placetype":"neighbourhood"
},
  "geometry": {"coordinates":[9.73333,47.63333],"type":"Point"}
}