{
  "type": "Feature",
  "properties": {
    "gn:admin1_code":"6.0",
    "gn:admin2_code":"0.0",
    "gn:admin3_code":"3354.0",
    "gn:admin4_code":"3354024.0",
    "gn:asciiname":"Bischof",
    "gn:country_code":"DE",
    "gn:dem":50,
    "gn:feature_class":"P",
    "gn:feature_code":"PPL",
    "gn:name":"Bischof",
    "gn:population":0,
    "gn:timezone":"Europe/Berlin",
    "iso:country":"DE",
    "name:deu_x_preferred":[
        "Bischof"
    ],
    "name:fra_x_preferred":[
        "Bischof"
    ],
    "name:por_x_preferred":[
        "Bischof"
    ],
    "name:rus_x_preferred":[
        "\u0411\u0438\u0448\u043e\u0444"
    ],
    "wof:name":"Bischof",
    "wof:placetype":"neighbourhood"
},
  "geometry": {"coordinates":[10.96783,52.97665],"type":"Point"}
}