{
  "type": "Feature",
  "properties": {
    "gn:population":1142,
    "iso:country":"DE",
    "name:baq_x_preferred":[
        "Burgschwalbach"
    ],
    "name:chi_x_preferred":[
        "\u5e03\u5c14\u683c\u65bd\u74e6\u5c14\u5df4\u8d6b"
    ],
    "name:deu_x_preferred":[
        "Burgschwalbach"
    ],
    "name:dut_x_preferred":[
        "Burgschwalbach"
    ],
    "name:eng_x_preferred":[
        "Burgschwalbach"
    ],
    "name:epo_x_preferred":[
        "Burgschwalbach"
    ],
    "name:eus_x_preferred":[
        "Burgschwalbach"
    ],
    "name:fra_x_preferred":[
        "Burgschwalbach"
    ],
    "name:fre_x_preferred":[
        "Burgschwalbach"
    ],
    "name:ger_x_preferred":[
        "Burgschwalbach"
    ],
    "name:hbs_x_preferred":[
        "Burgschwalbach"
    ],
    "name:hun_x_preferred":[
        "Burgschwalbach"
    ],
    "name:ita_x_preferred":[
        "Burgschwalbach"
    ],
    "name:jpn_x_preferred":[
        "\u30d6\u30eb\u30af\u30b7\u30e5\u30f4\u30a1\u30eb\u30d0\u30c3\u30cf"
    ],
    "name:kaz_x_preferred":[
        "\u0411\u0443\u0440\u0433\u0448\u0432\u0430\u043b\u044c\u0431\u0430\u0445"
    ],
    "name:kir_x_preferred":[
        "\u0411\u0443\u0440\u0433\u0448\u0432\u0430\u043b\u044c\u0431\u0430\u0445"
    ],
    "name:may_x_preferred":[
        "Burgschwalbach"
    ],
    "name:msa_x_preferred":[
        "Burgschwalbach"
    ],
    "name:nld_x_preferred":[
        "Burgschwalbach"
    ],
    "name:per_x_preferred":[
        "\u0628\u0648\u0631\u06af\u0634\u0648\u0627\u0644\u0628\u0627\u062e"
    ],
    "name:pol_x_preferred":[
        "Burgschwalbach"
    ],
    "name:por_x_preferred":[
        "Burgschwalbach"
    ],
    "name:ron_x_preferred":[
        "Burgschwalbach"
    ],
    "name:rum_x_preferred":[
        "Burgschwalbach"
    ],
    "name:rus_x_preferred":[
        "\u0411\u0443\u0440\u0433\u0448\u0432\u0430\u043b\u044c\u0431\u0430\u0445"
    ],
    "name:spa_x_preferred":[
        "Burgschwalbach"
    ],
    "name:srp_x_preferred":[
        "\u0411\u0443\u0440\u0433\u0448\u0432\u0430\u043b\u0431\u0430\u0445"
    ],
    "name:ukr_x_preferred":[
        "\u0411\u0443\u0440\u0433\u0448\u0432\u0430\u043b\u044c\u0431\u0430\u0445"
    ],
    "name:uzb_x_preferred":[
        "Burgschwalbach"
    ],
    "name:vie_x_preferred":[
        "Burgschwalbach"
    ],
    "name:vol_x_preferred":[
        "Burgschwalbach"
    ],
    "name:war_x_preferred":[
        "Burgschwalbach"
    ],
    "name:zho_x_preferred":[
        "\u5e03\u5c14\u683c\u65bd\u74e6\u5c14\u5df4\u8d6b"
    ],
    "qs:a0":"Bundesrepublik Deutschland",
    "qs:a1":"*Rheinland-Pfalz",
    "qs:a1r":"0",
    "qs:a2":"Rhein-Lahn-Kreis",
    "qs:adm0":"Bundesrepublik Deutschland",
    "qs:la_lc":"*",
    "qs:level":"locality",
    "qs:loc":"Burgschwalbach",
    "qs:loc_alt":"Burgschwalbach",
    "qs:pop":0,
    "qs:type":"buffered point",
    "wd:wordcount":30,
    "wof:name":"Burgschwalbach",
    "wof:placetype":"locality",
    "wof:population":1142
},
  "geometry": {"coordinates":[8.082173,50.282709],"type":"Point"}
}