{
  "type": "Feature",
  "properties": {
    "gn:admin1_code":"6",
    "gn:admin2_code":"0.0",
    "gn:admin3_code":"3462.0",
    "gn:admin4_code":"3462010.0",
    "gn:asciiname":"Marz",
    "gn:country_code":"DE",
    "gn:dem":1,
    "gn:feature_class":"P",
    "gn:feature_code":"PPL",
    "gn:name":"Marz",
    "gn:population":0,
    "gn:timezone":"Europe/Berlin",
    "iso:country":"DE",
    "name:ceb_x_preferred":[
        "Marz"
    ],
    "name:deu_x_preferred":[
        "Marz"
    ],
    "name:fra_x_preferred":[
        "Marz"
    ],
    "name:ita_x_preferred":[
        "Marz"
    ],
    "name:pol_x_preferred":[
        "Marz"
    ],
    "name:swe_x_preferred":[
        "Marz"
    ],
    "wof:name":"Marz",
    "wof:placetype":"neighbourhood"
},
  "geometry": {"coordinates":[7.63284,53.67399],"type":"Point"}
}