{
  "type": "Feature",
  "properties": {
    "gn:admin1_code":"8",
    "gn:admin2_code":"0.0",
    "gn:admin3_code":"7131.0",
    "gn:admin4_code":"7131007.0",
    "gn:asciiname":"Heppingen",
    "gn:country_code":"DE",
    "gn:dem":89,
    "gn:feature_class":"P",
    "gn:feature_code":"PPL",
    "gn:name":"Heppingen",
    "gn:population":0,
    "gn:timezone":"Europe/Berlin",
    "iso:country":"DE",
    "wof:name":"Heppingen",
    "wof:placetype":"neighbourhood"
},
  "geometry": {"coordinates":[7.16404,50.5506],"type":"Point"}
}