{
  "type": "Feature",
  "properties": {
    "gn:admin1_code":"2",
    "gn:admin2_code":"93.0",
    "gn:admin3_code":"9371.0",
    "gn:admin4_code":"9371127.0",
    "gn:asciiname":"Steiningloh",
    "gn:country_code":"DE",
    "gn:dem":437,
    "gn:feature_class":"P",
    "gn:feature_code":"PPL",
    "gn:name":"Steiningloh",
    "gn:population":0,
    "gn:timezone":"Europe/Berlin",
    "iso:country":"DE",
    "wof:name":"Steiningloh",
    "wof:placetype":"neighbourhood"
},
  "geometry": {"coordinates":[11.88493,49.50617],"type":"Point"}
}