{
  "type": "Feature",
  "properties": {
    "gn:admin1_code":"7",
    "gn:admin2_code":"57.0",
    "gn:admin3_code":"5758.0",
    "gn:admin4_code":"5758004.0",
    "gn:asciiname":"Randringhausen",
    "gn:country_code":"DE",
    "gn:dem":105,
    "gn:feature_class":"P",
    "gn:feature_code":"PPLL",
    "gn:name":"Randringhausen",
    "gn:population":0,
    "gn:timezone":"Europe/Berlin",
    "iso:country":"DE",
    "wof:name":"Randringhausen",
    "wof:placetype":"neighbourhood"
},
  "geometry": {"coordinates":[8.60369,52.23039],"type":"Point"}
}