{
  "type": "Feature",
  "properties": {
    "iso:country":"DE",
    "wof:name":"Rechtsruhr",
    "wof:placetype":"neighbourhood"
},
  "geometry": {"coordinates":[6.91323583182735,51.43384344153372],"type":"Point"}
}