{
  "type": "Feature",
  "properties": {
    "gn:admin1_code":"6.0",
    "gn:admin2_code":"0.0",
    "gn:admin3_code":"3359.0",
    "gn:admin4_code":"3359018.0",
    "gn:asciiname":"Allwoerden",
    "gn:country_code":"DE",
    "gn:dem":0,
    "gn:feature_class":"P",
    "gn:feature_code":"PPL",
    "gn:name":"Allw\u00f6rden",
    "gn:population":0,
    "gn:timezone":"Europe/Berlin",
    "iso:country":"DE",
    "wof:name":"Allwoerden",
    "wof:placetype":"neighbourhood"
},
  "geometry": {"coordinates":[9.2996,53.81096],"type":"Point"}
}