{
  "type": "Feature",
  "properties": {
    "gn:admin1_code":"15",
    "gn:admin2_code":"0.0",
    "gn:admin3_code":"16072.0",
    "gn:admin4_code":"16072018.0",
    "gn:asciiname":"Hohenofen",
    "gn:country_code":"DE",
    "gn:dem":567,
    "gn:feature_class":"P",
    "gn:feature_code":"PPL",
    "gn:name":"Hohenofen",
    "gn:population":0,
    "gn:timezone":"Europe/Berlin",
    "iso:country":"DE",
    "wof:name":"Hohenofen",
    "wof:placetype":"neighbourhood"
},
  "geometry": {"coordinates":[11.19631,50.45875],"type":"Point"}
}