{
  "type": "Feature",
  "properties": {
    "gn:admin1_code":"2",
    "gn:admin2_code":"91.0",
    "gn:admin3_code":"9189.0",
    "gn:admin4_code":"9189149.0",
    "gn:asciiname":"Oberbrunnham",
    "gn:country_code":"DE",
    "gn:dem":524,
    "gn:feature_class":"P",
    "gn:feature_code":"PPL",
    "gn:name":"Oberbrunnham",
    "gn:population":0,
    "gn:timezone":"Europe/Berlin",
    "iso:country":"DE",
    "wof:name":"Oberbrunnham",
    "wof:placetype":"neighbourhood"
},
  "geometry": {"coordinates":[12.54646,48.09173],"type":"Point"}
}