{
  "type": "Feature",
  "properties": {
    "gn:admin1_code":"6.0",
    "gn:admin2_code":"0.0",
    "gn:admin3_code":"3358.0",
    "gn:admin4_code":"3358019.0",
    "gn:asciiname":"Siedlung Grossenwede",
    "gn:country_code":"DE",
    "gn:dem":46,
    "gn:feature_class":"P",
    "gn:feature_code":"PPL",
    "gn:name":"Siedlung Gro\u00dfenwede",
    "gn:population":0,
    "gn:timezone":"Europe/Berlin",
    "iso:country":"DE",
    "wof:name":"Siedlung Grossenwede",
    "wof:placetype":"neighbourhood"
},
  "geometry": {"coordinates":[9.65301,53.13949],"type":"Point"}
}