{
  "type": "Feature",
  "properties": {
    "gn:admin1_code":"1",
    "gn:admin2_code":"84.0",
    "gn:admin3_code":"8437.0",
    "gn:admin4_code":"8437005.0",
    "gn:asciiname":"Oberhausen",
    "gn:country_code":"DE",
    "gn:dem":622,
    "gn:feature_class":"P",
    "gn:feature_code":"PPL",
    "gn:name":"Oberhausen",
    "gn:population":0,
    "gn:timezone":"Europe/Berlin",
    "iso:country":"DE",
    "wof:name":"Oberhausen",
    "wof:placetype":"neighbourhood"
},
  "geometry": {"coordinates":[8.99158,48.05406],"type":"Point"}
}