{
  "type": "Feature",
  "properties": {
    "gn:admin1_code":"2",
    "gn:admin2_code":"92.0",
    "gn:admin3_code":"9277.0",
    "gn:admin4_code":"9277117.0",
    "gn:asciiname":"Martinstodling",
    "gn:country_code":"DE",
    "gn:dem":369,
    "gn:feature_class":"P",
    "gn:feature_code":"PPLL",
    "gn:name":"Martinst\u00f6dling",
    "gn:population":0,
    "gn:timezone":"Europe/Berlin",
    "iso:country":"DE",
    "wof:name":"Martinstodling",
    "wof:placetype":"neighbourhood"
},
  "geometry": {"coordinates":[13.08531,48.54001],"type":"Point"}
}