{
  "type": "Feature",
  "properties": {
    "gn:admin1_code":"1",
    "gn:admin2_code":"84.0",
    "gn:admin3_code":"8421.0",
    "gn:admin4_code":"8421000.0",
    "gn:asciiname":"Oerlingen",
    "gn:country_code":"DE",
    "gn:dem":516,
    "gn:feature_class":"P",
    "gn:feature_code":"PPL",
    "gn:name":"Oerlingen",
    "gn:population":0,
    "gn:timezone":"Europe/Berlin",
    "iso:country":"DE",
    "wof:name":"Oerlingen",
    "wof:placetype":"neighbourhood"
},
  "geometry": {"coordinates":[10.00275,48.42772],"type":"Point"}
}