{
  "type": "Feature",
  "properties": {
    "gn:admin1_code":"1",
    "gn:admin2_code":"81.0",
    "gn:admin3_code":"8128.0",
    "gn:admin4_code":"8128137.0",
    "gn:asciiname":"Lilach",
    "gn:country_code":"DE",
    "gn:dem":332,
    "gn:feature_class":"P",
    "gn:feature_code":"PPL",
    "gn:name":"Lilach",
    "gn:population":0,
    "gn:timezone":"Europe/Berlin",
    "iso:country":"DE",
    "name:und_x_variant":[
        "Hof Lilach",
        "Lilach"
    ],
    "wof:name":"Lilach",
    "wof:placetype":"neighbourhood"
},
  "geometry": {"coordinates":[9.82525,49.65182],"type":"Point"}
}