{
  "type": "Feature",
  "properties": {
    "gn:admin1_code":"9.0",
    "gn:admin2_code":"00",
    "gn:admin3_code":"10043.0",
    "gn:admin4_code":"10043112.0",
    "gn:asciiname":"Wustweilerhof",
    "gn:country_code":"DE",
    "gn:dem":273,
    "gn:feature_class":"P",
    "gn:feature_code":"PPL",
    "gn:name":"Wustweilerhof",
    "gn:population":0,
    "gn:timezone":"Europe/Berlin",
    "iso:country":"DE",
    "wof:name":"Wustweilerhof",
    "wof:placetype":"neighbourhood"
},
  "geometry": {"coordinates":[7.05,49.38333],"type":"Point"}
}