{
  "type": "Feature",
  "properties": {
    "gn:gn_country":"DE",
    "gn:gn_fcode":"PPLA4",
    "gn:gn_pop":248,
    "gn:population":248,
    "iso:country":"DE",
    "name:baq_x_preferred":[
        "Sch\u00fcrdt"
    ],
    "name:dut_x_preferred":[
        "Sch\u00fcrdt"
    ],
    "name:eng_x_preferred":[
        "Sch\u00fcrdt"
    ],
    "name:epo_x_preferred":[
        "Sch\u00fcrdt"
    ],
    "name:fre_x_preferred":[
        "Sch\u00fcrdt"
    ],
    "name:ger_x_preferred":[
        "Sch\u00fcrdt"
    ],
    "name:hun_x_preferred":[
        "Sch\u00fcrdt"
    ],
    "name:ita_x_preferred":[
        "Sch\u00fcrdt"
    ],
    "name:jpn_x_preferred":[
        "\u30b7\u30e5\u30eb\u30c8"
    ],
    "name:may_x_preferred":[
        "Sch\u00fcrdt"
    ],
    "name:per_x_preferred":[
        "\u0634\u06cc\u0648\u0631\u062a"
    ],
    "name:pol_x_preferred":[
        "Sch\u00fcrdt"
    ],
    "name:por_x_preferred":[
        "Sch\u00fcrdt"
    ],
    "name:rum_x_preferred":[
        "Sch\u00fcrdt"
    ],
    "name:rus_x_preferred":[
        "\u0428\u044e\u0440\u0434\u0442"
    ],
    "name:srp_x_preferred":[
        "\u0428\u0438\u0440\u0442"
    ],
    "name:ukr_x_preferred":[
        "\u0428\u044e\u0440\u0434\u0442"
    ],
    "name:uzb_x_preferred":[
        "Sch\u00fcrdt"
    ],
    "name:vie_x_preferred":[
        "Sch\u00fcrdt"
    ],
    "name:vol_x_preferred":[
        "Sch\u00fcrdt"
    ],
    "name:war_x_preferred":[
        "Sch\u00fcrdt"
    ],
    "qs_pg:aaroncc":"DE",
    "qs_pg:gn_country":"DE",
    "qs_pg:gn_fcode":"PPLA4",
    "qs_pg:gn_pop":248,
    "qs_pg:name":"Sch\u00fcrdt",
    "qs_pg:photos_9r":0,
    "qs_pg:photos_sr":0,
    "qs_pg:pop_sr":2,
    "qs_pg:qs_pg_placetype":"locality",
    "wof:name":"Sch\u00fcrdt",
    "wof:placetype":"locality",
    "wof:population":248
},
  "geometry": {"coordinates":[7.55,50.66667],"type":"Point"}
}