{
  "type": "Feature",
  "properties": {
    "gn:admin1_code":"14",
    "gn:admin2_code":"0.0",
    "gn:admin3_code":"15091.0",
    "gn:admin4_code":"15091145.0",
    "gn:asciiname":"Dixfoerda",
    "gn:country_code":"DE",
    "gn:dem":76,
    "gn:feature_class":"P",
    "gn:feature_code":"PPL",
    "gn:name":"Dixf\u00f6rda",
    "gn:population":0,
    "gn:timezone":"Europe/Berlin",
    "iso:country":"DE",
    "wof:name":"Dixfoerda",
    "wof:placetype":"neighbourhood"
},
  "geometry": {"coordinates":[13.03473,51.8094],"type":"Point"}
}