{
  "type": "Feature",
  "properties": {
    "gn:admin1_code":"2",
    "gn:admin2_code":"92.0",
    "gn:admin3_code":"9273.0",
    "gn:admin4_code":"9273165.0",
    "gn:asciiname":"Obereulenbach",
    "gn:country_code":"DE",
    "gn:dem":432,
    "gn:feature_class":"P",
    "gn:feature_code":"PPL",
    "gn:name":"Obereulenbach",
    "gn:population":0,
    "gn:timezone":"Europe/Berlin",
    "iso:country":"DE",
    "wof:name":"Obereulenbach",
    "wof:placetype":"neighbourhood"
},
  "geometry": {"coordinates":[11.97458,48.75043],"type":"Point"}
}