{
  "type": "Feature",
  "properties": {
    "gn:admin1_code":"12",
    "gn:admin2_code":"0.0",
    "gn:admin3_code":"13072.0",
    "gn:admin4_code":"13072026.0",
    "gn:asciiname":"Dobbin",
    "gn:country_code":"DE",
    "gn:dem":59,
    "gn:feature_class":"P",
    "gn:feature_code":"PPL",
    "gn:name":"Dobbin",
    "gn:population":0,
    "gn:timezone":"Europe/Berlin",
    "iso:country":"DE",
    "name:deu_x_preferred":[
        "Dobbin"
    ],
    "name:rus_x_preferred":[
        "\u0414\u043e\u0431\u0431\u0438\u043d"
    ],
    "wof:name":"Dobbin",
    "wof:placetype":"neighbourhood"
},
  "geometry": {"coordinates":[12.33332,53.61646],"type":"Point"}
}