{
  "type": "Feature",
  "properties": {
    "gn:admin1_code":"1.0",
    "gn:admin2_code":"81.0",
    "gn:admin3_code":"8116.0",
    "gn:admin4_code":"8116019.0",
    "gn:asciiname":"Pliensauvorstadt",
    "gn:country_code":"DE",
    "gn:dem":239,
    "gn:feature_class":"P",
    "gn:feature_code":"PPL",
    "gn:name":"Pliensauvorstadt",
    "gn:population":0,
    "gn:timezone":"Europe/Berlin",
    "iso:country":"DE",
    "wof:name":"Pliensauvorstadt",
    "wof:placetype":"neighbourhood"
},
  "geometry": {"coordinates":[9.29422,48.7342],"type":"Point"}
}