{
  "type": "Feature",
  "properties": {
    "gn:admin1_code":"12.0",
    "gn:admin2_code":"00",
    "gn:admin3_code":"13072.0",
    "gn:admin4_code":"13072097.0",
    "gn:asciiname":"Woltow",
    "gn:country_code":"DE",
    "gn:dem":31,
    "gn:feature_class":"P",
    "gn:feature_code":"PPL",
    "gn:name":"Woltow",
    "gn:population":0,
    "gn:timezone":"Europe/Berlin",
    "iso:country":"DE",
    "wof:name":"Woltow",
    "wof:placetype":"neighbourhood"
},
  "geometry": {"coordinates":[12.52565,53.98738],"type":"Point"}
}