{
  "type": "Feature",
  "properties": {
    "gn:admin1_code":"2",
    "gn:admin2_code":"95.0",
    "gn:admin3_code":"9574.0",
    "gn:admin4_code":"9574111.0",
    "gn:asciiname":"Waller",
    "gn:country_code":"DE",
    "gn:dem":577,
    "gn:feature_class":"P",
    "gn:feature_code":"PPL",
    "gn:name":"Waller",
    "gn:population":0,
    "gn:timezone":"Europe/Berlin",
    "iso:country":"DE",
    "name:ceb_x_preferred":[
        "Waller"
    ],
    "name:deu_x_preferred":[
        "Waller"
    ],
    "name:fra_x_preferred":[
        "Waller"
    ],
    "name:heb_x_preferred":[
        "\u05d5\u05d5\u05dc\u05e8"
    ],
    "name:ita_x_preferred":[
        "Waller"
    ],
    "name:jpn_x_preferred":[
        "\u30a6\u30a9\u30fc\u30e9\u30fc"
    ],
    "name:nds_x_preferred":[
        "Waller"
    ],
    "name:nld_x_preferred":[
        "Waller"
    ],
    "name:pol_x_preferred":[
        "Waller"
    ],
    "name:por_x_preferred":[
        "Waller"
    ],
    "name:rus_x_preferred":[
        "\u0423\u043e\u043b\u043b\u0435\u0440"
    ],
    "name:spa_x_preferred":[
        "Waller"
    ],
    "name:vol_x_preferred":[
        "Waller"
    ],
    "wof:name":"Waller",
    "wof:placetype":"neighbourhood"
},
  "geometry": {"coordinates":[11.50217,49.42449000000001],"type":"Point"}
}