{
  "type": "Feature",
  "properties": {
    "gn:admin1_code":"2",
    "gn:admin2_code":"91.0",
    "gn:admin3_code":"9182.0",
    "gn:admin4_code":"9182123.0",
    "gn:asciiname":"Eyrain",
    "gn:country_code":"DE",
    "gn:dem":717,
    "gn:feature_class":"P",
    "gn:feature_code":"PPL",
    "gn:name":"Eyrain",
    "gn:population":0,
    "gn:timezone":"Europe/Berlin",
    "iso:country":"DE",
    "wof:name":"Eyrain",
    "wof:placetype":"neighbourhood"
},
  "geometry": {"coordinates":[11.90866,47.80359],"type":"Point"}
}