{
  "type": "Feature",
  "properties": {
    "gn:admin1_code":"13",
    "gn:admin2_code":"0.0",
    "gn:admin3_code":"14729.0",
    "gn:admin4_code":"14729150.0",
    "gn:asciiname":"Doelitzsch",
    "gn:country_code":"DE",
    "gn:dem":237,
    "gn:feature_class":"P",
    "gn:feature_code":"PPL",
    "gn:name":"D\u00f6litzsch",
    "gn:population":0,
    "gn:timezone":"Europe/Berlin",
    "iso:country":"DE",
    "wof:name":"Doelitzsch",
    "wof:placetype":"neighbourhood"
},
  "geometry": {"coordinates":[12.72736,51.00664],"type":"Point"}
}