{
  "type": "Feature",
  "properties": {
    "gn:admin1_code":"13",
    "gn:admin2_code":"0.0",
    "gn:admin3_code":"14625.0",
    "gn:admin4_code":"14625330.0",
    "gn:asciiname":"Friedersdorf",
    "gn:country_code":"DE",
    "gn:dem":128,
    "gn:feature_class":"P",
    "gn:feature_code":"PPL",
    "gn:name":"Friedersdorf",
    "gn:population":0,
    "gn:timezone":"Europe/Berlin",
    "iso:country":"DE",
    "name:hsb_x_preferred":[
        "Bjedrichecy"
    ],
    "wof:name":"Friedersdorf",
    "wof:placetype":"neighbourhood"
},
  "geometry": {"coordinates":[14.39363,51.36126],"type":"Point"}
}