{
  "type": "Feature",
  "properties": {
    "gn:admin1_code":"13",
    "gn:admin2_code":"0.0",
    "gn:admin3_code":"14625.0",
    "gn:admin4_code":"14625330.0",
    "gn:asciiname":"Friedersdorf",
    "gn:country_code":"DE",
    "gn:dem":128,
    "gn:feature_class":"P",
    "gn:feature_code":"PPL",
    "gn:name":"Friedersdorf",
    "gn:population":0,
    "gn:timezone":"Europe/Berlin",
    "iso:country":"DE",
    "name:ceb_x_preferred":[
        "Friedersdorf"
    ],
    "name:deu_x_preferred":[
        "Friedersdorf"
    ],
    "name:epo_x_preferred":[
        "Friedersdorf"
    ],
    "name:est_x_preferred":[
        "Friedersdorf"
    ],
    "name:hsb_x_preferred":[
        "Bjedrichecy"
    ],
    "name:ita_x_preferred":[
        "Friedersdorf"
    ],
    "name:nld_x_preferred":[
        "Friedersdorf"
    ],
    "name:pol_x_preferred":[
        "Friedersdorf"
    ],
    "name:rus_x_preferred":[
        "\u0424\u0440\u0438\u0434\u0435\u0440\u0441\u0434\u043e\u0440\u0444"
    ],
    "name:swe_x_preferred":[
        "Friedersdorf"
    ],
    "name:vol_x_preferred":[
        "Friedersdorf"
    ],
    "wof:name":"Friedersdorf",
    "wof:placetype":"neighbourhood"
},
  "geometry": {"coordinates":[14.39363,51.36126],"type":"Point"}
}