{
  "type": "Feature",
  "properties": {
    "gn:admin1_code":"2",
    "gn:admin2_code":"93.0",
    "gn:admin3_code":"9377.0",
    "gn:admin4_code":"9377148.0",
    "gn:asciiname":"Pilgramsreuth",
    "gn:country_code":"DE",
    "gn:dem":619,
    "gn:feature_class":"P",
    "gn:feature_code":"PPL",
    "gn:name":"Pilgramsreuth",
    "gn:population":0,
    "gn:timezone":"Europe/Berlin",
    "iso:country":"DE",
    "wof:name":"Pilgramsreuth",
    "wof:placetype":"neighbourhood"
},
  "geometry": {"coordinates":[12.03186,49.94782],"type":"Point"}
}