{
  "type": "Feature",
  "properties": {
    "gn:admin1_code":"13",
    "gn:admin2_code":"0.0",
    "gn:admin3_code":"14730.0",
    "gn:admin4_code":"14730280.0",
    "gn:asciiname":"Grosswoelkau",
    "gn:country_code":"DE",
    "gn:dem":106,
    "gn:feature_class":"P",
    "gn:feature_code":"PPL",
    "gn:name":"Gro\u00dfw\u00f6lkau",
    "gn:population":0,
    "gn:timezone":"Europe/Berlin",
    "iso:country":"DE",
    "wof:name":"Grosswoelkau",
    "wof:placetype":"neighbourhood"
},
  "geometry": {"coordinates":[12.49008,51.48961],"type":"Point"}
}