{
  "type": "Feature",
  "properties": {
    "gn:admin1_code":"2",
    "gn:admin2_code":"91.0",
    "gn:admin3_code":"9175.0",
    "gn:admin4_code":"9175112.0",
    "gn:asciiname":"Pausmuhle",
    "gn:country_code":"DE",
    "gn:dem":517,
    "gn:feature_class":"P",
    "gn:feature_code":"PPL",
    "gn:name":"Pausm\u00fchle",
    "gn:population":0,
    "gn:timezone":"Europe/Berlin",
    "iso:country":"DE",
    "wof:name":"Pausmuhle",
    "wof:placetype":"neighbourhood"
},
  "geometry": {"coordinates":[11.96076,47.98567],"type":"Point"}
}