{
  "type": "Feature",
  "properties": {
    "gn:admin1_code":"2",
    "gn:admin2_code":"91.0",
    "gn:admin3_code":"9186.0",
    "gn:admin4_code":"9186126.0",
    "gn:asciiname":"Prambach",
    "gn:country_code":"DE",
    "gn:dem":447,
    "gn:feature_class":"P",
    "gn:feature_code":"PPL",
    "gn:name":"Prambach",
    "gn:population":0,
    "gn:timezone":"Europe/Berlin",
    "iso:country":"DE",
    "wof:name":"Prambach",
    "wof:placetype":"neighbourhood"
},
  "geometry": {"coordinates":[11.52576,48.50417],"type":"Point"}
}