{
  "type": "Feature",
  "properties": {
    "gn:gn_country":"DE",
    "gn:gn_fcode":"PPLA4",
    "gn:gn_pop":848,
    "gn:population":848,
    "iso:country":"DE",
    "name:baq_x_preferred":[
        "Sommerland"
    ],
    "name:chi_x_preferred":[
        "\u7d22\u6885\u5c14\u5170"
    ],
    "name:dan_x_preferred":[
        "Sommerland"
    ],
    "name:dut_x_preferred":[
        "Sommerland"
    ],
    "name:eng_x_preferred":[
        "Sommerland"
    ],
    "name:epo_x_preferred":[
        "Sommerland"
    ],
    "name:fre_x_preferred":[
        "Sommerland"
    ],
    "name:ger_x_preferred":[
        "Sommerland"
    ],
    "name:hun_x_preferred":[
        "Sommerland"
    ],
    "name:ita_x_preferred":[
        "Sommerland"
    ],
    "name:mac_x_preferred":[
        "\u0417\u043e\u043c\u0435\u0440\u043b\u0430\u043d\u0434"
    ],
    "name:may_x_preferred":[
        "Sommerland"
    ],
    "name:per_x_preferred":[
        "\u0633\u0648\u0645\u0631\u0644\u0627\u0646\u062f"
    ],
    "name:pol_x_preferred":[
        "Sommerland"
    ],
    "name:por_x_preferred":[
        "Sommerland"
    ],
    "name:rum_x_preferred":[
        "Sommerland"
    ],
    "name:rus_x_preferred":[
        "\u0417\u043e\u043c\u043c\u0435\u0440\u043b\u0430\u043d\u0434"
    ],
    "name:srp_x_preferred":[
        "\u0417\u043e\u043c\u0435\u0440\u043b\u0430\u043d\u0434"
    ],
    "name:tur_x_preferred":[
        "Sommerland"
    ],
    "name:ukr_x_preferred":[
        "\u0417\u043e\u043c\u043c\u0435\u0440\u043b\u0430\u043d\u0434"
    ],
    "name:uzb_x_preferred":[
        "Sommerland"
    ],
    "name:vie_x_preferred":[
        "Sommerland"
    ],
    "name:vol_x_preferred":[
        "Sommerland"
    ],
    "name:war_x_preferred":[
        "Sommerland"
    ],
    "qs_pg:aaroncc":"DE",
    "qs_pg:gn_country":"DE",
    "qs_pg:gn_fcode":"PPLA4",
    "qs_pg:gn_pop":848,
    "qs_pg:name":"Sommerland",
    "qs_pg:photos_9r":0,
    "qs_pg:photos_sr":0,
    "qs_pg:pop_sr":2,
    "qs_pg:qs_pg_placetype":"locality",
    "wof:name":"Sommerland",
    "wof:placetype":"locality",
    "wof:population":848
},
  "geometry": {"coordinates":[9.53748,53.8036],"type":"Point"}
}