{
  "type": "Feature",
  "properties": {
    "gn:admin1_code":"2",
    "gn:admin2_code":"92.0",
    "gn:admin3_code":"9277.0",
    "gn:admin4_code":"9277142.0",
    "gn:asciiname":"Unterradlsbach",
    "gn:country_code":"DE",
    "gn:dem":378,
    "gn:feature_class":"P",
    "gn:feature_code":"PPL",
    "gn:name":"Unterradlsbach",
    "gn:population":0,
    "gn:timezone":"Europe/Berlin",
    "iso:country":"DE",
    "wof:name":"Unterradlsbach",
    "wof:placetype":"neighbourhood"
},
  "geometry": {"coordinates":[12.90603,48.56976],"type":"Point"}
}