{
  "type": "Feature",
  "properties": {
    "gn:admin1_code":"2.0",
    "gn:admin2_code":"097",
    "gn:admin3_code":"9780.0",
    "gn:admin4_code":"9780139.0",
    "gn:asciiname":"Westerhofen",
    "gn:country_code":"DE",
    "gn:dem":737,
    "gn:feature_class":"P",
    "gn:feature_code":"PPL",
    "gn:name":"Westerhofen",
    "gn:population":0,
    "gn:timezone":"Europe/Berlin",
    "iso:country":"DE",
    "wof:name":"Westerhofen",
    "wof:placetype":"neighbourhood"
},
  "geometry": {"coordinates":[10.26438,47.51403],"type":"Point"}
}