{
  "type": "Feature",
  "properties": {
    "gn:admin1_code":"2",
    "gn:admin2_code":"94.0",
    "gn:admin3_code":"9474.0",
    "gn:admin4_code":"9474132.0",
    "gn:asciiname":"Rangen",
    "gn:country_code":"DE",
    "gn:dem":489,
    "gn:feature_class":"P",
    "gn:feature_code":"PPL",
    "gn:name":"Rangen",
    "gn:population":0,
    "gn:timezone":"Europe/Berlin",
    "iso:country":"DE",
    "name:als_x_preferred":[
        "Rangen"
    ],
    "name:ara_x_preferred":[
        "\u0631\u0627\u0646\u063a\u064a\u0646"
    ],
    "name:cat_x_preferred":[
        "Rangen"
    ],
    "name:ceb_x_preferred":[
        "Rangen"
    ],
    "name:deu_x_preferred":[
        "Rangen"
    ],
    "name:eus_x_preferred":[
        "Rangen"
    ],
    "name:fas_x_preferred":[
        "\u0631\u0627\u0646\u06af\u0646"
    ],
    "name:fra_x_preferred":[
        "Rangen"
    ],
    "name:hun_x_preferred":[
        "Rangen"
    ],
    "name:hye_x_preferred":[
        "\u054c\u0561\u0576\u056a\u0565\u0576"
    ],
    "name:ita_x_preferred":[
        "Rangen"
    ],
    "name:kaz_x_preferred":[
        "\u0420\u0430\u043d\u0433\u0435\u043d"
    ],
    "name:lat_x_preferred":[
        "Rangen"
    ],
    "name:mlg_x_preferred":[
        "Rangen"
    ],
    "name:msa_x_preferred":[
        "Rangen"
    ],
    "name:nld_x_preferred":[
        "Rangen"
    ],
    "name:oci_x_preferred":[
        "Rangen"
    ],
    "name:pfl_x_preferred":[
        "Rangen"
    ],
    "name:pms_x_preferred":[
        "Rangen"
    ],
    "name:pol_x_preferred":[
        "Rangen"
    ],
    "name:por_x_preferred":[
        "Rangen"
    ],
    "name:ron_x_preferred":[
        "Rangen"
    ],
    "name:rus_x_preferred":[
        "\u0420\u0430\u043d\u0436\u0435\u043d"
    ],
    "name:slk_x_preferred":[
        "Rangen"
    ],
    "name:slv_x_preferred":[
        "Rangen"
    ],
    "name:spa_x_preferred":[
        "Rangen"
    ],
    "name:swe_x_preferred":[
        "Rangen"
    ],
    "name:ukr_x_preferred":[
        "\u0420\u0430\u043d\u0433\u0435\u043d"
    ],
    "name:uzb_x_preferred":[
        "Rangen"
    ],
    "name:vie_x_preferred":[
        "Rangen"
    ],
    "name:vol_x_preferred":[
        "Rangen"
    ],
    "name:war_x_preferred":[
        "Rangen"
    ],
    "name:zho_x_preferred":[
        "\u6717\u6839"
    ],
    "wof:name":"Rangen",
    "wof:placetype":"neighbourhood"
},
  "geometry": {"coordinates":[11.20344,49.66825],"type":"Point"}
}