{
  "type": "Feature",
  "properties": {
    "gn:admin1_code":"1.0",
    "gn:admin2_code":"83.0",
    "gn:admin3_code":"8317.0",
    "gn:admin4_code":"8317096.0",
    "gn:asciiname":"Bohlsbach",
    "gn:country_code":"DE",
    "gn:dem":152,
    "gn:feature_class":"P",
    "gn:feature_code":"PPL",
    "gn:name":"Bohlsbach",
    "gn:population":0,
    "gn:timezone":"Europe/Berlin",
    "iso:country":"DE",
    "wof:name":"Bohlsbach",
    "wof:placetype":"neighbourhood"
},
  "geometry": {"coordinates":[7.947,48.49769000000001],"type":"Point"}
}