{
  "type": "Feature",
  "properties": {
    "gn:gn_country":"DE",
    "gn:gn_fcode":"PPLA4",
    "gn:gn_pop":306,
    "gn:population":306,
    "iso:country":"DE",
    "name:baq_x_preferred":[
        "Kleinfischlingen"
    ],
    "name:chi_x_preferred":[
        "\u5c0f\u83f2\u65bd\u6797\u6839"
    ],
    "name:dut_x_preferred":[
        "Kleinfischlingen"
    ],
    "name:eng_x_preferred":[
        "Kleinfischlingen"
    ],
    "name:epo_x_preferred":[
        "Kleinfischlingen"
    ],
    "name:fre_x_preferred":[
        "Kleinfischlingen"
    ],
    "name:ger_x_preferred":[
        "Kleinfischlingen"
    ],
    "name:hun_x_preferred":[
        "Kleinfischlingen"
    ],
    "name:ita_x_preferred":[
        "Kleinfischlingen"
    ],
    "name:jpn_x_preferred":[
        "\u30af\u30e9\u30a4\u30f3\u30d5\u30a3\u30c3\u30b7\u30e5\u30ea\u30f3\u30b2\u30f3"
    ],
    "name:kaz_x_preferred":[
        "\u041a\u043b\u0430\u0439\u043d\u0444\u0438\u0448\u043b\u0438\u043d\u0433\u0435\u043d"
    ],
    "name:kir_x_preferred":[
        "\u041a\u043b\u0430\u0439\u043d\u0444\u0438\u0448\u043b\u0438\u043d\u0433\u0435\u043d"
    ],
    "name:may_x_preferred":[
        "Kleinfischlingen"
    ],
    "name:per_x_preferred":[
        "\u06a9\u0644\u0627\u06cc\u0646\u0641\u06cc\u0634\u0644\u06cc\u0646\u06af\u0646"
    ],
    "name:pol_x_preferred":[
        "Kleinfischlingen"
    ],
    "name:por_x_preferred":[
        "Kleinfischlingen"
    ],
    "name:rum_x_preferred":[
        "Kleinfischlingen"
    ],
    "name:rus_x_preferred":[
        "\u041a\u043b\u0430\u0439\u043d\u0444\u0438\u0448\u043b\u0438\u043d\u0433\u0435\u043d"
    ],
    "name:srp_x_preferred":[
        "\u041a\u043b\u0430\u0458\u043d\u0444\u0438\u0448\u043b\u0438\u043d\u0433\u0435\u043d"
    ],
    "name:ukr_x_preferred":[
        "\u041a\u043b\u044f\u0439\u043d\u0444\u0456\u0448\u043b\u0456\u043d\u0433\u0435\u043d"
    ],
    "name:uzb_x_preferred":[
        "Kleinfischlingen"
    ],
    "name:vie_x_preferred":[
        "Kleinfischlingen"
    ],
    "name:vol_x_preferred":[
        "Kleinfischlingen"
    ],
    "name:war_x_preferred":[
        "Kleinfischlingen"
    ],
    "qs_pg:aaroncc":"DE",
    "qs_pg:gn_country":"DE",
    "qs_pg:gn_fcode":"PPLA4",
    "qs_pg:gn_pop":306,
    "qs_pg:name":"Kleinfischlingen",
    "qs_pg:photos_9r":0,
    "qs_pg:photos_sr":0,
    "qs_pg:pop_sr":2,
    "qs_pg:qs_pg_placetype":"locality",
    "wof:name":"Kleinfischlingen",
    "wof:placetype":"locality",
    "wof:population":306
},
  "geometry": {"coordinates":[8.18694,49.26333],"type":"Point"}
}