{
  "type": "Feature",
  "properties": {
    "gn:admin1_code":"7",
    "gn:admin2_code":"59.0",
    "gn:admin3_code":"5958.0",
    "gn:admin4_code":"5958004.0",
    "gn:asciiname":"Obereimer",
    "gn:country_code":"DE",
    "gn:dem":177,
    "gn:feature_class":"P",
    "gn:feature_code":"PPL",
    "gn:name":"Obereimer",
    "gn:population":0,
    "gn:timezone":"Europe/Berlin",
    "iso:country":"DE",
    "wof:name":"Obereimer",
    "wof:placetype":"neighbourhood"
},
  "geometry": {"coordinates":[8.04794,51.41144],"type":"Point"}
}