{
  "type": "Feature",
  "properties": {
    "gn:admin1_code":"1",
    "gn:admin2_code":"84.0",
    "gn:admin3_code":"8426.0",
    "gn:admin4_code":"8426135.0",
    "gn:asciiname":"Simmisweiler",
    "gn:country_code":"DE",
    "gn:dem":563,
    "gn:feature_class":"P",
    "gn:feature_code":"PPL",
    "gn:name":"Simmisweiler",
    "gn:population":0,
    "gn:timezone":"Europe/Berlin",
    "iso:country":"DE",
    "wof:name":"Simmisweiler",
    "wof:placetype":"neighbourhood"
},
  "geometry": {"coordinates":[9.9411,48.14165],"type":"Point"}
}