{
  "type": "Feature",
  "properties": {
    "gn:admin1_code":"2",
    "gn:admin2_code":"96.0",
    "gn:admin3_code":"9675.0",
    "gn:admin4_code":"9675158.0",
    "gn:asciiname":"Ilmbach",
    "gn:country_code":"DE",
    "gn:dem":327,
    "gn:feature_class":"P",
    "gn:feature_code":"PPL",
    "gn:name":"Ilmbach",
    "gn:population":0,
    "gn:timezone":"Europe/Berlin",
    "iso:country":"DE",
    "wof:name":"Ilmbach",
    "wof:placetype":"neighbourhood"
},
  "geometry": {"coordinates":[10.40931,49.80377],"type":"Point"}
}