{
  "type": "Feature",
  "properties": {
    "gn:admin1_code":"15.0",
    "gn:admin2_code":"00",
    "gn:admin3_code":"16077.0",
    "gn:admin4_code":"16077036.0",
    "gn:asciiname":"Zumroda",
    "gn:country_code":"DE",
    "gn:dem":265,
    "gn:feature_class":"P",
    "gn:feature_code":"PPL",
    "gn:name":"Zumroda",
    "gn:population":0,
    "gn:timezone":"Europe/Berlin",
    "iso:country":"DE",
    "wof:name":"Zumroda",
    "wof:placetype":"neighbourhood"
},
  "geometry": {"coordinates":[12.50151,50.89851],"type":"Point"}
}