{
  "type": "Feature",
  "properties": {
    "gn:country":"DE",
    "gn:fcode":"PPL",
    "gn:population":0,
    "iso:country":"DE",
    "name:bos_x_preferred":[
        "Neunkirchen"
    ],
    "name:ceb_x_preferred":[
        "Neunkirchen"
    ],
    "name:ces_x_preferred":[
        "Neunkirchen"
    ],
    "name:deu_x_preferred":[
        "Neunkirchen"
    ],
    "name:epo_x_preferred":[
        "Neunkirchen"
    ],
    "name:fin_x_preferred":[
        "Neunkirchen"
    ],
    "name:fra_x_preferred":[
        "Neunkirchen"
    ],
    "name:hun_x_preferred":[
        "Neunkirchen"
    ],
    "name:hye_x_preferred":[
        "\u0546\u0578\u0575\u0576\u056f\u056b\u0580\u056d\u0565\u0576"
    ],
    "name:ita_x_preferred":[
        "Neunkirchen"
    ],
    "name:jpn_x_preferred":[
        "\u30ce\u30a4\u30f3\u30ad\u30eb\u30d2\u30a7\u30f3"
    ],
    "name:kaz_x_preferred":[
        "\u041d\u043e\u0439\u043d\u043a\u0438\u0440\u0445\u0435\u043d"
    ],
    "name:lmo_x_preferred":[
        "Neunkirchen"
    ],
    "name:nds_x_preferred":[
        "Neenkark"
    ],
    "name:nld_x_preferred":[
        "Neunkirchen"
    ],
    "name:nor_x_preferred":[
        "Neunkirchen"
    ],
    "name:pol_x_preferred":[
        "Neunkirchen"
    ],
    "name:por_x_preferred":[
        "Neunkirchen"
    ],
    "name:ron_x_preferred":[
        "Neunkirchen"
    ],
    "name:rus_x_preferred":[
        "\u041d\u043e\u0439\u043d\u043a\u0438\u0440\u0445\u0435\u043d"
    ],
    "name:slk_x_preferred":[
        "Neunkirchen"
    ],
    "name:spa_x_preferred":[
        "Neunkirchen"
    ],
    "name:srp_x_preferred":[
        "\u041d\u043e\u0458\u043d\u043a\u0438\u0440\u0445\u0435\u043d"
    ],
    "name:swe_x_preferred":[
        "Neunkirchen"
    ],
    "name:ukr_x_preferred":[
        "\u041d\u043e\u0439\u043d\u043a\u0456\u0440\u0445\u0435\u043d"
    ],
    "name:vol_x_preferred":[
        "Neunkirchen"
    ],
    "name:zho_x_preferred":[
        "\u8afe\u56e0\u57fa\u8208"
    ],
    "qs_pg:aaroncc":"DE",
    "qs_pg:gn_country":"DE",
    "qs_pg:gn_fcode":"PPL",
    "qs_pg:gn_pop":0,
    "qs_pg:name":"Neunkirchen",
    "qs_pg:name_adm0":"Deutschland",
    "qs_pg:name_adm1":"Hessen",
    "qs_pg:photos":16,
    "qs_pg:photos_1k":3,
    "qs_pg:photos_9k":1,
    "qs_pg:photos_9r":1,
    "qs_pg:photos_all":16,
    "qs_pg:photos_sr":1,
    "qs_pg:pop_sr":0,
    "qs_pg:qs_pg_placetype":"locality",
    "qs_pg:qs_pg_placetype_gp":"Town",
    "qs_pg:woe_adm0":23424829,
    "woe:adm0_id":23424829,
    "woe:name_adm0":"Deutschland",
    "woe:name_adm1":"Hessen",
    "woe:placetype":"Town",
    "wof:name":"Neunkirchen",
    "wof:placetype":"neighbourhood"
},
  "geometry": {"coordinates":[8.77465,49.7342],"type":"Point"}
}