{
  "type": "Feature",
  "properties": {
    "gn:gn_country":"DE",
    "gn:gn_fcode":"PPLX",
    "gn:gn_pop":0,
    "iso:country":"DE",
    "name:deu_x_preferred":[
        "Westen"
    ],
    "name:nld_x_preferred":[
        "West"
    ],
    "name:pol_x_preferred":[
        "Westen"
    ],
    "name:unk_x_variant":[
        "Westen"
    ],
    "qs_pg:aaroncc":"DE",
    "qs_pg:gn_country":"DE",
    "qs_pg:gn_fcode":"PPLX",
    "qs_pg:gn_pop":0,
    "qs_pg:name":"Westen",
    "qs_pg:name_adm0":"Deutschland",
    "qs_pg:name_adm1":"Nordrhein-Westfalen",
    "qs_pg:photos":5,
    "qs_pg:photos_1k":1,
    "qs_pg:photos_9k":1,
    "qs_pg:photos_9r":1,
    "qs_pg:photos_all":5,
    "qs_pg:photos_sr":1,
    "qs_pg:pop_sr":0,
    "qs_pg:qs_pg_placetype":"neighbourhood",
    "qs_pg:qs_pg_placetype_gp":"Suburb",
    "qs_pg:woe_adm0":23424829,
    "woe:adm0_id":23424829,
    "woe:name_adm0":"Deutschland",
    "woe:name_adm1":"Nordrhein-Westfalen",
    "woe:placetype":"Suburb",
    "wof:name":"Westen",
    "wof:placetype":"neighbourhood"
},
  "geometry": {"coordinates":[7.16667,51.26667],"type":"Point"}
}