{
  "type": "Feature",
  "properties": {
    "gn:admin1_code":"13",
    "gn:admin2_code":"0.0",
    "gn:admin3_code":"14729.0",
    "gn:admin4_code":"14729220.0",
    "gn:asciiname":"Dittmannsdorf",
    "gn:country_code":"DE",
    "gn:dem":148,
    "gn:feature_class":"P",
    "gn:feature_code":"PPL",
    "gn:name":"Dittmannsdorf",
    "gn:population":0,
    "gn:timezone":"Europe/Berlin",
    "iso:country":"DE",
    "wof:name":"Dittmannsdorf",
    "wof:placetype":"neighbourhood"
},
  "geometry": {"coordinates":[12.53783,51.15213],"type":"Point"}
}