{
  "type": "Feature",
  "properties": {
    "gn:country":"DE",
    "gn:fcode":"PPL",
    "gn:population":664,
    "iso:country":"DE",
    "name:bak_x_preferred":[
        "\u041a\u043b\u0430\u0439\u043d\u0430\u0443"
    ],
    "name:ceb_x_preferred":[
        "Kleinau"
    ],
    "name:deu_x_preferred":[
        "Kleinau"
    ],
    "name:epo_x_preferred":[
        "Kleinau"
    ],
    "name:fas_x_preferred":[
        "\u06a9\u0644\u0627\u06cc\u0646\u0627\u0648"
    ],
    "name:ita_x_preferred":[
        "Kleinau"
    ],
    "name:kaz_x_preferred":[
        "\u041a\u043b\u0430\u0439\u043d\u0430\u0443"
    ],
    "name:kir_x_preferred":[
        "\u041a\u043b\u0430\u0439\u043d\u0430\u0443"
    ],
    "name:nld_x_preferred":[
        "Kleinau"
    ],
    "name:ron_x_preferred":[
        "Kleinau"
    ],
    "name:rus_x_preferred":[
        "\u041a\u043b\u0430\u0439\u043d\u0430\u0443"
    ],
    "name:und_x_variant":[
        "Kleinhau"
    ],
    "name:uzb_x_preferred":[
        "Kleinau"
    ],
    "name:vie_x_preferred":[
        "Kleinau"
    ],
    "name:vol_x_preferred":[
        "Kleinau"
    ],
    "qs_pg:aaroncc":"DE",
    "qs_pg:gn_country":"DE",
    "qs_pg:gn_fcode":"PPL",
    "qs_pg:gn_pop":664,
    "qs_pg:name":"Kleinau",
    "qs_pg:name_adm0":"Deutschland",
    "qs_pg:name_adm1":"Sachsen-Anhalt",
    "qs_pg:photos_9k":1,
    "qs_pg:photos_9r":1,
    "qs_pg:photos_all":1,
    "qs_pg:photos_sr":0,
    "qs_pg:pop_sr":2,
    "qs_pg:qs_pg_placetype":"locality",
    "qs_pg:qs_pg_placetype_gp":"Town",
    "qs_pg:woe_adm0":23424829,
    "woe:adm0_id":23424829,
    "woe:name_adm0":"Deutschland",
    "woe:name_adm1":"Sachsen-Anhalt",
    "woe:placetype":"Town",
    "wof:name":"Kleinau",
    "wof:placetype":"neighbourhood",
    "wof:population":664
},
  "geometry": {"coordinates":[11.51096,52.79952],"type":"Point"}
}