{
  "type": "Feature",
  "properties": {
    "gn:admin1_code":"15",
    "gn:admin2_code":"0.0",
    "gn:admin3_code":"16076.0",
    "gn:admin4_code":"16076093.0",
    "gn:asciiname":"Hermannsgruen",
    "gn:country_code":"DE",
    "gn:dem":357,
    "gn:feature_class":"P",
    "gn:feature_code":"PPL",
    "gn:name":"Hermannsgr\u00fcn",
    "gn:population":0,
    "gn:timezone":"Europe/Berlin",
    "iso:country":"DE",
    "wof:name":"Hermannsgruen",
    "wof:placetype":"neighbourhood"
},
  "geometry": {"coordinates":[12.25872,50.67553],"type":"Point"}
}