{
  "type": "Feature",
  "properties": {
    "gn:admin1_code":"2",
    "gn:admin2_code":"97.0",
    "gn:admin3_code":"9778.0",
    "gn:admin4_code":"9778186.0",
    "gn:asciiname":"Unterhaslach",
    "gn:country_code":"DE",
    "gn:dem":752,
    "gn:feature_class":"P",
    "gn:feature_code":"PPL",
    "gn:name":"Unterhaslach",
    "gn:population":0,
    "gn:timezone":"Europe/Berlin",
    "iso:country":"DE",
    "wof:name":"Unterhaslach",
    "wof:placetype":"neighbourhood"
},
  "geometry": {"coordinates":[10.34297,47.9236],"type":"Point"}
}