{
  "type": "Feature",
  "properties": {
    "gn:admin1_code":"15",
    "gn:admin2_code":"0.0",
    "gn:admin3_code":"16063.0",
    "gn:admin4_code":"16063075.0",
    "gn:asciiname":"Unterrohn",
    "gn:country_code":"DE",
    "gn:dem":239,
    "gn:feature_class":"P",
    "gn:feature_code":"PPL",
    "gn:name":"Unterrohn",
    "gn:population":0,
    "gn:timezone":"Europe/Berlin",
    "iso:country":"DE",
    "wof:name":"Unterrohn",
    "wof:placetype":"neighbourhood"
},
  "geometry": {"coordinates":[10.19392,50.8297],"type":"Point"}
}