{
  "type": "Feature",
  "properties": {
    "gn:admin1_code":"12.0",
    "gn:admin2_code":"00",
    "gn:admin3_code":"13071.0",
    "gn:admin4_code":"13071037.0",
    "gn:asciiname":"Wittenborn",
    "gn:country_code":"DE",
    "gn:dem":37,
    "gn:feature_class":"P",
    "gn:feature_code":"PPL",
    "gn:name":"Wittenborn",
    "gn:population":0,
    "gn:timezone":"Europe/Berlin",
    "iso:country":"DE",
    "wof:name":"Wittenborn",
    "wof:placetype":"neighbourhood"
},
  "geometry": {"coordinates":[13.66355,53.61325],"type":"Point"}
}