{
  "type": "Feature",
  "properties": {
    "gn:admin1_code":"12.0",
    "gn:admin2_code":"00",
    "gn:admin3_code":"13071.0",
    "gn:admin4_code":"13071037.0",
    "gn:asciiname":"Wittenborn",
    "gn:country_code":"DE",
    "gn:dem":37,
    "gn:feature_class":"P",
    "gn:feature_code":"PPL",
    "gn:name":"Wittenborn",
    "gn:population":0,
    "gn:timezone":"Europe/Berlin",
    "iso:country":"DE",
    "name:ceb_x_preferred":[
        "Wittenborn"
    ],
    "name:dan_x_preferred":[
        "Wittenborn"
    ],
    "name:deu_x_preferred":[
        "Wittenborn"
    ],
    "name:epo_x_preferred":[
        "Wittenborn"
    ],
    "name:eus_x_preferred":[
        "Wittenborn"
    ],
    "name:fas_x_preferred":[
        "\u0648\u06cc\u062a\u0646\u0628\u0648\u0631\u0646"
    ],
    "name:fra_x_preferred":[
        "Wittenborn"
    ],
    "name:hun_x_preferred":[
        "Wittenborn"
    ],
    "name:ind_x_preferred":[
        "Wittenborn"
    ],
    "name:ita_x_preferred":[
        "Wittenborn"
    ],
    "name:mkd_x_preferred":[
        "\u0412\u0438\u0442\u0435\u043d\u0431\u043e\u0440\u043d"
    ],
    "name:msa_x_preferred":[
        "Wittenborn"
    ],
    "name:nld_x_preferred":[
        "Wittenborn"
    ],
    "name:pol_x_preferred":[
        "Wittenborn"
    ],
    "name:por_x_preferred":[
        "Wittenborn"
    ],
    "name:ron_x_preferred":[
        "Wittenborn"
    ],
    "name:rus_x_preferred":[
        "\u0412\u0438\u0442\u0442\u0435\u043d\u0431\u043e\u0440\u043d"
    ],
    "name:srp_x_preferred":[
        "\u0412\u0438\u0442\u0435\u043d\u0431\u043e\u0440\u043d"
    ],
    "name:tur_x_preferred":[
        "Wittenborn"
    ],
    "name:ukr_x_preferred":[
        "\u0412\u0456\u0442\u0442\u0435\u043d\u0431\u043e\u0440\u043d"
    ],
    "name:uzb_x_preferred":[
        "Wittenborn"
    ],
    "name:vie_x_preferred":[
        "Wittenborn"
    ],
    "name:vol_x_preferred":[
        "Wittenborn"
    ],
    "name:war_x_preferred":[
        "Wittenborn"
    ],
    "name:zho_x_preferred":[
        "\u7ef4\u6ed5\u535a\u6069"
    ],
    "wof:name":"Wittenborn",
    "wof:placetype":"neighbourhood"
},
  "geometry": {"coordinates":[13.66355,53.61325],"type":"Point"}
}