{
  "type": "Feature",
  "properties": {
    "gn:country":"DE",
    "gn:fcode":"PPL",
    "gn:population":0,
    "iso:country":"DE",
    "name:und_x_variant":[
        "Clemenshof"
    ],
    "qs_pg:aaroncc":"DE",
    "qs_pg:gn_country":"DE",
    "qs_pg:gn_fcode":"PPL",
    "qs_pg:gn_pop":0,
    "qs_pg:name":"Lemmenh\u00f6fe",
    "qs_pg:name_adm0":"Deutschland",
    "qs_pg:name_adm1":"Nordrhein-Westfalen",
    "qs_pg:photos":1434,
    "qs_pg:photos_1k":291,
    "qs_pg:photos_9k":6,
    "qs_pg:photos_9r":7,
    "qs_pg:photos_all":1434,
    "qs_pg:photos_sr":12,
    "qs_pg:pop_sr":0,
    "qs_pg:qs_pg_placetype":"neighbourhood",
    "qs_pg:qs_pg_placetype_gp":"Suburb",
    "qs_pg:woe_adm0":23424829,
    "woe:adm0_id":23424829,
    "woe:name_adm0":"Deutschland",
    "woe:name_adm1":"Nordrhein-Westfalen",
    "woe:placetype":"Suburb",
    "wof:name":"Lemmenh\u00f6fe",
    "wof:placetype":"neighbourhood"
},
  "geometry": {"coordinates":[6.66262,50.84758],"type":"Point"}
}