{
  "type": "Feature",
  "properties": {
    "iso:country":"DE",
    "wof:name":"Kleinzschocker",
    "wof:placetype":"neighbourhood"
},
  "geometry": {"coordinates":[12.32642558194631,51.31556464362874],"type":"Point"}
}