{
  "type": "Feature",
  "properties": {
    "iso:country":"DE",
    "name:deu_x_preferred":[
        "Heidberg"
    ],
    "name:eng_x_preferred":[
        "SS Heidberg"
    ],
    "name:fas_x_preferred":[
        "\u0627\u0633\u200c\u0627\u0633 \u0647\u06cc\u062f\u0628\u0631\u06af"
    ],
    "name:gle_x_preferred":[
        "SS Heidberg"
    ],
    "qs:gn_fcode":"PPLX",
    "qs:gn_local":0,
    "qs:gn_namadm1":"07",
    "qs:gn_name":"Heidberg",
    "qs:local_max":723,
    "qs:local_sum":3477,
    "qs:localhoods":34,
    "qs:name":"Heidberg",
    "qs:name_adm0":"Deutschland",
    "qs:name_adm1":"Nordrhein-Westfalen",
    "qs:name_adm2":"Stadtkreis Solingen",
    "qs:name_lau":"Stadtteil Ohlig",
    "qs:name_local":"Stadtteil Ohlig",
    "qs:photo_max":3,
    "qs:photo_sum":3,
    "qs:placetype":"Suburb",
    "qs:quad_count":1,
    "qs:woe_adm0":23424829,
    "qs:woe_adm1":2345487,
    "qs:woe_adm2":12597079,
    "qs:woe_lau":26823245,
    "qs:woe_local":26823245,
    "qs:woe_ver":"7.10.0",
    "wd:wordcount":299,
    "wof:lang":[
        "ger"
    ],
    "wof:name":"Heidberg",
    "wof:placetype":"neighbourhood"
},
  "geometry": {"coordinates":[7.067986,51.168761],"type":"Point"}
}