{
  "type": "Feature",
  "properties": {
    "gn:gn_country":"DE",
    "gn:gn_fcode":"PPLA4",
    "gn:gn_pop":197,
    "gn:population":197,
    "iso:country":"DE",
    "name:baq_x_preferred":[
        "Loop"
    ],
    "name:dan_x_preferred":[
        "Loop"
    ],
    "name:dut_x_preferred":[
        "Loop"
    ],
    "name:eng_x_preferred":[
        "Loop"
    ],
    "name:epo_x_preferred":[
        "Loop"
    ],
    "name:fre_x_preferred":[
        "Loop"
    ],
    "name:ger_x_preferred":[
        "Loop"
    ],
    "name:hun_x_preferred":[
        "Loop"
    ],
    "name:ita_x_preferred":[
        "Loop"
    ],
    "name:mac_x_preferred":[
        "\u041b\u043e\u043f"
    ],
    "name:may_x_preferred":[
        "Loop"
    ],
    "name:per_x_preferred":[
        "\u0644\u0648\u0648\u067e"
    ],
    "name:pol_x_preferred":[
        "Loop"
    ],
    "name:por_x_preferred":[
        "Loop"
    ],
    "name:rum_x_preferred":[
        "Loop"
    ],
    "name:rus_x_preferred":[
        "\u041b\u043e\u043f"
    ],
    "name:srp_x_preferred":[
        "\u041b\u043e\u043f"
    ],
    "name:tur_x_preferred":[
        "Loop"
    ],
    "name:ukr_x_preferred":[
        "\u041b\u043e\u043f"
    ],
    "name:uzb_x_preferred":[
        "Loop"
    ],
    "name:vie_x_preferred":[
        "Loop"
    ],
    "name:vol_x_preferred":[
        "Loop"
    ],
    "name:war_x_preferred":[
        "Loop"
    ],
    "qs_pg:aaroncc":"DE",
    "qs_pg:gn_country":"DE",
    "qs_pg:gn_fcode":"PPLA4",
    "qs_pg:gn_pop":197,
    "qs_pg:name":"Loop",
    "qs_pg:photos_9r":0,
    "qs_pg:photos_sr":0,
    "qs_pg:pop_sr":1,
    "qs_pg:qs_pg_placetype":"locality",
    "wof:name":"Loop",
    "wof:placetype":"locality",
    "wof:population":197
},
  "geometry": {"coordinates":[9.95,54.15],"type":"Point"}
}