{
  "type": "Feature",
  "properties": {
    "gn:admin1_code":"6.0",
    "gn:admin2_code":"0.0",
    "gn:admin3_code":"3155.0",
    "gn:admin4_code":"3155003.0",
    "gn:asciiname":"Amelsen",
    "gn:country_code":"DE",
    "gn:dem":161,
    "gn:feature_class":"P",
    "gn:feature_code":"PPL",
    "gn:name":"Amelsen",
    "gn:population":0,
    "gn:timezone":"Europe/Berlin",
    "iso:country":"DE",
    "wof:name":"Amelsen",
    "wof:placetype":"neighbourhood"
},
  "geometry": {"coordinates":[9.76227,51.83537000000001],"type":"Point"}
}