{
  "type": "Feature",
  "properties": {
    "iso:country":"DE",
    "name:deu_x_preferred":[
        "Pfingstweide"
    ],
    "qs:gn_adm0_cc":"DE",
    "qs:gn_local":2875376,
    "qs:gn_nam_loc":"Ludwigshafen am Rhein, Rheinland-Pfalz, DE",
    "qs:gn_namadm1":"08",
    "qs:local_max":1675,
    "qs:local_sum":3883,
    "qs:localhoods":9,
    "qs:name":"Pfingstweide",
    "qs:name_adm0":"Deutschland",
    "qs:name_adm1":"Rheinland-Pfalz",
    "qs:name_adm2":"Stadtkreis Ludwigshafen am Rhein",
    "qs:name_lau":"Stadtteil Ludwigshafen am Rhein",
    "qs:name_local":"Stadtteil Ludwigshafen am Rhein",
    "qs:photo_max":59,
    "qs:photo_sum":99,
    "qs:placetype":"Suburb",
    "qs:quad_count":18,
    "qs:woe_adm0":23424829,
    "qs:woe_adm1":2345488,
    "qs:woe_adm2":12597103,
    "qs:woe_lau":28350228,
    "qs:woe_local":28350228,
    "qs:woe_ver":"7.10.0",
    "qs_pg:name":"Pfingstweide",
    "qs_pg:name_adm0":"Deutschland",
    "qs_pg:name_adm1":"Rheinland-Pfalz",
    "qs_pg:photos":112,
    "qs_pg:photos_1k":23,
    "qs_pg:photos_9k":1,
    "qs_pg:photos_9r":3,
    "qs_pg:photos_all":112,
    "qs_pg:photos_sr":3,
    "qs_pg:pop_sr":0,
    "qs_pg:qs_pg_placetype":"neighbourhood",
    "qs_pg:qs_pg_placetype_gp":"Suburb",
    "qs_pg:woe_adm0":23424829,
    "woe:adm0_id":23424829,
    "woe:name_adm0":"Deutschland",
    "woe:name_adm1":"Rheinland-Pfalz",
    "woe:placetype":"Suburb",
    "wof:lang":[
        "ger"
    ],
    "wof:name":"Pfingstweide",
    "wof:placetype":"neighbourhood"
},
  "geometry": {"coordinates":[8.41371,49.548821],"type":"Point"}
}