{
  "type": "Feature",
  "properties": {
    "iso:country":"DE",
    "name:deu_x_colloquial":[
        "Koerne",
        "Korne"
    ],
    "name:deu_x_preferred":[
        "K\u00f6rne"
    ],
    "name:eng_x_preferred":[
        "K\u00f6rne"
    ],
    "name:nld_x_preferred":[
        "Station Dortmund-K\u00f6rne"
    ],
    "name:unk_x_variant":[
        "K\u00f6rne"
    ],
    "qs:gn_adm0_cc":"DE",
    "qs:gn_fcode":"PPLX",
    "qs:gn_local":2935517,
    "qs:gn_nam_loc":"dortmund",
    "qs:gn_namadm1":"07",
    "qs:gn_name":"K\u00f6rne",
    "qs:local_max":5685,
    "qs:local_sum":19088,
    "qs:localhoods":60,
    "qs:name":"K\u00f6rne",
    "qs:name_adm0":"Deutschland",
    "qs:name_adm1":"Nordrhein-Westfalen",
    "qs:name_adm2":"Stadtkreis Dortmund",
    "qs:name_lau":"Innenstadt-Ost",
    "qs:name_local":"Dortmund",
    "qs:photo_max":486,
    "qs:photo_sum":5685,
    "qs:placetype":"Suburb",
    "qs:quad_count":111,
    "qs:woe_adm0":23424829,
    "qs:woe_adm1":2345487,
    "qs:woe_adm2":12596991,
    "qs:woe_lau":26822117,
    "qs:woe_local":645458,
    "qs:woe_ver":"7.10.0",
    "wof:lang":[
        "ger"
    ],
    "wof:name":"Koerne",
    "wof:placetype":"neighbourhood"
},
  "geometry": {"coordinates":[7.498673,51.514022],"type":"Point"}
}