{
  "type": "Feature",
  "properties": {
    "gn:admin1_code":"13.0",
    "gn:admin2_code":"0.0",
    "gn:admin3_code":"14522.0",
    "gn:admin4_code":"14522440.0",
    "gn:asciiname":"Breitenau",
    "gn:country_code":"DE",
    "gn:dem":361,
    "gn:feature_class":"P",
    "gn:feature_code":"PPL",
    "gn:name":"Breitenau",
    "gn:population":0,
    "gn:timezone":"Europe/Berlin",
    "iso:country":"DE",
    "name:ceb_x_preferred":[
        "Breitenau"
    ],
    "name:deu_x_preferred":[
        "Breitenau"
    ],
    "name:fra_x_preferred":[
        "Breitenau"
    ],
    "name:ita_x_preferred":[
        "Breitenau"
    ],
    "name:nld_x_preferred":[
        "Breitenau"
    ],
    "name:pol_x_preferred":[
        "Breitenau"
    ],
    "name:rus_x_preferred":[
        "\u0411\u0440\u0430\u0439\u0442\u0435\u043d\u0430\u0443"
    ],
    "name:srp_x_preferred":[
        "\u0411\u0440\u0430\u0458\u0442\u0435\u043d\u0430\u0443"
    ],
    "name:swe_x_preferred":[
        "Breitenau"
    ],
    "name:vol_x_preferred":[
        "Breitenau"
    ],
    "wof:name":"Breitenau",
    "wof:placetype":"neighbourhood"
},
  "geometry": {"coordinates":[13.16185,50.8512],"type":"Point"}
}