{
  "type": "Feature",
  "properties": {
    "gn:admin1_code":"2",
    "gn:admin2_code":"91.0",
    "gn:admin3_code":"9189.0",
    "gn:admin4_code":"9189160.0",
    "gn:asciiname":"Hinterwossen",
    "gn:country_code":"DE",
    "gn:dem":646,
    "gn:feature_class":"P",
    "gn:feature_code":"PPL",
    "gn:name":"Hinterw\u00f6ssen",
    "gn:population":0,
    "gn:timezone":"Europe/Berlin",
    "iso:country":"DE",
    "wof:name":"Hinterwossen",
    "wof:placetype":"neighbourhood"
},
  "geometry": {"coordinates":[12.46841,47.7094],"type":"Point"}
}