{
  "type": "Feature",
  "properties": {
    "gn:country":"DE",
    "gn:fcode":"PPL",
    "gn:population":0,
    "iso:country":"DE",
    "name:als_x_preferred":[
        "Steinbach"
    ],
    "name:bre_x_preferred":[
        "Steinbach"
    ],
    "name:ceb_x_preferred":[
        "Steinbach"
    ],
    "name:ces_x_preferred":[
        "Steinbach"
    ],
    "name:deu_x_preferred":[
        "Steinbach"
    ],
    "name:epo_x_preferred":[
        "Steinbach"
    ],
    "name:fra_x_preferred":[
        "Steinbach"
    ],
    "name:heb_x_preferred":[
        "\u05e1\u05d8\u05d9\u05d9\u05d1\u05d0\u05da"
    ],
    "name:hun_x_preferred":[
        "Steinbach"
    ],
    "name:ita_x_preferred":[
        "Steinbach"
    ],
    "name:jpn_x_preferred":[
        "\u30b7\u30e5\u30bf\u30a4\u30f3\u30d0\u30c3\u30cf"
    ],
    "name:nld_x_preferred":[
        "Steinbach"
    ],
    "name:pol_x_preferred":[
        "Steinbach"
    ],
    "name:ron_x_preferred":[
        "Steinbach"
    ],
    "name:rus_x_preferred":[
        "\u0428\u0442\u0430\u0439\u043d\u0431\u0430\u0445"
    ],
    "name:spa_x_preferred":[
        "Steinbach"
    ],
    "name:swe_x_preferred":[
        "Steinbach"
    ],
    "name:vol_x_preferred":[
        "Steinbach"
    ],
    "qs_pg:aaroncc":"DE",
    "qs_pg:gn_country":"DE",
    "qs_pg:gn_fcode":"PPL",
    "qs_pg:gn_pop":0,
    "qs_pg:name":"Steinbach",
    "qs_pg:name_adm0":"Deutschland",
    "qs_pg:name_adm1":"Baden-W\u00fcrttemberg",
    "qs_pg:photos":52,
    "qs_pg:photos_1k":11,
    "qs_pg:photos_9k":1,
    "qs_pg:photos_9r":2,
    "qs_pg:photos_all":52,
    "qs_pg:photos_sr":2,
    "qs_pg:pop_sr":0,
    "qs_pg:qs_pg_placetype":"locality",
    "qs_pg:qs_pg_placetype_gp":"Town",
    "qs_pg:woe_adm0":23424829,
    "woe:adm0_id":23424829,
    "woe:name_adm0":"Deutschland",
    "woe:name_adm1":"Baden-W\u00fcrttemberg",
    "woe:placetype":"Town",
    "wof:name":"Steinbach",
    "wof:placetype":"neighbourhood"
},
  "geometry": {"coordinates":[9.74483,49.10298],"type":"Point"}
}