{
  "type": "Feature",
  "properties": {
    "gn:gn_country":"DE",
    "gn:gn_fcode":"PPLA4",
    "gn:gn_pop":684,
    "gn:population":684,
    "iso:country":"DE",
    "name:baq_x_preferred":[
        "Steineroth"
    ],
    "name:chi_x_preferred":[
        "\u65bd\u6cf0\u5185\u7f57\u7279"
    ],
    "name:dut_x_preferred":[
        "Steineroth"
    ],
    "name:eng_x_preferred":[
        "Steineroth"
    ],
    "name:epo_x_preferred":[
        "Steineroth"
    ],
    "name:fre_x_preferred":[
        "Steineroth"
    ],
    "name:ger_x_preferred":[
        "Steineroth"
    ],
    "name:hun_x_preferred":[
        "Steineroth"
    ],
    "name:ita_x_preferred":[
        "Steineroth"
    ],
    "name:jpn_x_preferred":[
        "\u30b7\u30e5\u30bf\u30a4\u30cd\u30ed\u30fc\u30c8"
    ],
    "name:may_x_preferred":[
        "Steineroth"
    ],
    "name:per_x_preferred":[
        "\u0627\u0634\u062a\u0627\u06cc\u0646\u0631\u0648\u062a"
    ],
    "name:pol_x_preferred":[
        "Steineroth"
    ],
    "name:por_x_preferred":[
        "Steineroth"
    ],
    "name:rum_x_preferred":[
        "Steineroth"
    ],
    "name:rus_x_preferred":[
        "\u0428\u0442\u0430\u0439\u043d\u0435\u0440\u043e\u0442"
    ],
    "name:srp_x_preferred":[
        "\u0428\u0442\u0430\u0458\u043d\u0435\u0440\u043e\u0442"
    ],
    "name:ukr_x_preferred":[
        "\u0428\u0442\u0430\u0439\u043d\u0435\u0440\u043e\u0442"
    ],
    "name:uzb_x_preferred":[
        "Steineroth"
    ],
    "name:vie_x_preferred":[
        "Steineroth"
    ],
    "name:vol_x_preferred":[
        "Steineroth"
    ],
    "name:war_x_preferred":[
        "Steineroth"
    ],
    "qs_pg:aaroncc":"DE",
    "qs_pg:gn_country":"DE",
    "qs_pg:gn_fcode":"PPLA4",
    "qs_pg:gn_pop":684,
    "qs_pg:name":"Steineroth",
    "qs_pg:photos_9r":0,
    "qs_pg:photos_sr":0,
    "qs_pg:pop_sr":2,
    "qs_pg:qs_pg_placetype":"locality",
    "wof:name":"Steineroth",
    "wof:placetype":"locality",
    "wof:population":684
},
  "geometry": {"coordinates":[7.85,50.75],"type":"Point"}
}