{
  "type": "Feature",
  "properties": {
    "gn:admin1_code":"14",
    "gn:admin2_code":"0.0",
    "gn:admin3_code":"15088.0",
    "gn:admin4_code":"15088195.0",
    "gn:asciiname":"Droyssig",
    "gn:country_code":"DE",
    "gn:dem":104,
    "gn:feature_class":"P",
    "gn:feature_code":"PPL",
    "gn:name":"Droy\u00dfig",
    "gn:population":0,
    "gn:timezone":"Europe/Berlin",
    "iso:country":"DE",
    "wof:name":"Droyssig",
    "wof:placetype":"neighbourhood"
},
  "geometry": {"coordinates":[12.10583,51.4983],"type":"Point"}
}