{
  "type": "Feature",
  "properties": {
    "gn:admin1_code":"7.0",
    "gn:admin2_code":"53.0",
    "gn:admin3_code":"5362.0",
    "gn:admin4_code":"5362032.0",
    "gn:asciiname":"Bottenbroich",
    "gn:country_code":"DE",
    "gn:dem":115,
    "gn:feature_class":"P",
    "gn:feature_code":"PPL",
    "gn:name":"Bottenbroich",
    "gn:population":0,
    "gn:timezone":"Europe/Berlin",
    "iso:country":"DE",
    "name:und_x_variant":[
        "Neu-Bottenbroich",
        "Bottenbroich"
    ],
    "wof:name":"Bottenbroich",
    "wof:placetype":"neighbourhood"
},
  "geometry": {"coordinates":[6.72517,50.91583],"type":"Point"}
}