{
  "type": "Feature",
  "properties": {
    "gn:admin1_code":"2",
    "gn:admin2_code":"91.0",
    "gn:admin3_code":"9182.0",
    "gn:admin4_code":"9182120.0",
    "gn:asciiname":"Heignkam",
    "gn:cc2":"DE",
    "gn:country_code":"DE",
    "gn:dem":676,
    "gn:feature_class":"P",
    "gn:feature_code":"PPL",
    "gn:name":"Heignkam",
    "gn:population":0,
    "gn:timezone":"Europe/Berlin",
    "iso:country":"DE",
    "name:und_x_variant":[
        "Heigenkam"
    ],
    "wof:name":"Heignkam",
    "wof:placetype":"neighbourhood"
},
  "geometry": {"coordinates":[11.69297,47.892],"type":"Point"}
}