{
  "type": "Feature",
  "properties": {
    "gn:admin1_code":"2.0",
    "gn:admin2_code":"092",
    "gn:admin3_code":"9275.0",
    "gn:admin4_code":"9275126.0",
    "gn:asciiname":"Wolkar",
    "gn:country_code":"DE",
    "gn:dem":558,
    "gn:feature_class":"P",
    "gn:feature_code":"PPL",
    "gn:name":"Wolkar",
    "gn:population":0,
    "gn:timezone":"Europe/Berlin",
    "iso:country":"DE",
    "wof:name":"Wolkar",
    "wof:placetype":"neighbourhood"
},
  "geometry": {"coordinates":[13.57631,48.65999],"type":"Point"}
}