{
  "type": "Feature",
  "properties": {
    "gn:country":"DE",
    "gn:fcode":"PPL",
    "gn:population":0,
    "iso:country":"DE",
    "name:che_x_preferred":[
        "\u0424\u0440\u0438\u0434\u0440\u0438\u0445\u0441\u0440\u0443"
    ],
    "name:dan_x_preferred":[
        "Friedrichsruh"
    ],
    "name:deu_x_preferred":[
        "Friedrichsruh"
    ],
    "name:epo_x_preferred":[
        "Friedrichsruh"
    ],
    "name:fra_x_preferred":[
        "Friedrichsruh"
    ],
    "name:ita_x_preferred":[
        "Friedrichsruh"
    ],
    "name:nld_x_preferred":[
        "Friedrichsruh"
    ],
    "name:nor_x_preferred":[
        "Friedrichsruh slott"
    ],
    "name:rus_x_preferred":[
        "\u0424\u0440\u0438\u0434\u0440\u0438\u0445\u0441\u0440\u0443"
    ],
    "name:spa_x_preferred":[
        "Friedrichsruh"
    ],
    "name:swe_x_preferred":[
        "Friedrichsruh"
    ],
    "name:ukr_x_preferred":[
        "\u0424\u0440\u0456\u0434\u0440\u0456\u0445\u0441\u0440\u0443"
    ],
    "qs_pg:aaroncc":"DE",
    "qs_pg:gn_country":"DE",
    "qs_pg:gn_fcode":"PPL",
    "qs_pg:gn_pop":0,
    "qs_pg:name":"Friedrichsruh",
    "qs_pg:name_adm0":"Deutschland",
    "qs_pg:name_adm1":"Schleswig-Holstein",
    "qs_pg:photos":196,
    "qs_pg:photos_1k":40,
    "qs_pg:photos_9k":1,
    "qs_pg:photos_9r":4,
    "qs_pg:photos_all":196,
    "qs_pg:photos_sr":4,
    "qs_pg:pop_sr":0,
    "qs_pg:qs_pg_placetype":"locality",
    "qs_pg:qs_pg_placetype_gp":"Town",
    "qs_pg:woe_adm0":23424829,
    "woe:adm0_id":23424829,
    "woe:name_adm0":"Deutschland",
    "woe:name_adm1":"Schleswig-Holstein",
    "woe:placetype":"Town",
    "wof:name":"Friedrichsruh",
    "wof:placetype":"neighbourhood"
},
  "geometry": {"coordinates":[10.33971,53.53043],"type":"Point"}
}