{
  "type": "Feature",
  "properties": {
    "gn:admin1_code":"7",
    "gn:admin2_code":"53.0",
    "gn:admin3_code":"5382.0",
    "gn:admin4_code":"5382024.0",
    "gn:asciiname":"Herresbach",
    "gn:country_code":"DE",
    "gn:dem":140,
    "gn:feature_class":"P",
    "gn:feature_code":"PPLL",
    "gn:name":"Herresbach",
    "gn:population":0,
    "gn:timezone":"Europe/Berlin",
    "iso:country":"DE",
    "wof:name":"Herresbach",
    "wof:placetype":"neighbourhood"
},
  "geometry": {"coordinates":[7.28889,50.70523],"type":"Point"}
}