{
  "type": "Feature",
  "properties": {
    "gn:admin1_code":"7",
    "gn:admin2_code":"53.0",
    "gn:admin3_code":"5382.0",
    "gn:admin4_code":"5382024.0",
    "gn:asciiname":"Herresbach",
    "gn:country_code":"DE",
    "gn:dem":140,
    "gn:feature_class":"P",
    "gn:feature_code":"PPLL",
    "gn:name":"Herresbach",
    "gn:population":0,
    "gn:timezone":"Europe/Berlin",
    "iso:country":"DE",
    "name:ceb_x_preferred":[
        "Herresbach"
    ],
    "name:deu_x_preferred":[
        "Herresbach"
    ],
    "name:epo_x_preferred":[
        "Herresbach"
    ],
    "name:eus_x_preferred":[
        "Herresbach"
    ],
    "name:fas_x_preferred":[
        "\u0647\u0631\u0633\u0628\u0627\u062e"
    ],
    "name:fra_x_preferred":[
        "Herresbach"
    ],
    "name:hun_x_preferred":[
        "Herresbach"
    ],
    "name:ita_x_preferred":[
        "Herresbach"
    ],
    "name:kaz_x_preferred":[
        "\u0425\u0435\u0440\u0440\u0435\u0441\u0431\u0430\u0445"
    ],
    "name:kir_x_preferred":[
        "\u0425\u0435\u0440\u0440\u0435\u0441\u0431\u0430\u0445"
    ],
    "name:msa_x_preferred":[
        "Herresbach"
    ],
    "name:nld_x_preferred":[
        "Herresbach"
    ],
    "name:pol_x_preferred":[
        "Herresbach"
    ],
    "name:por_x_preferred":[
        "Herresbach"
    ],
    "name:ron_x_preferred":[
        "Herresbach"
    ],
    "name:rus_x_preferred":[
        "\u0425\u0435\u0440\u0440\u0435\u0441\u0431\u0430\u0445"
    ],
    "name:srp_x_preferred":[
        "\u0425\u0435\u0440\u0435\u0441\u0431\u0430\u0445"
    ],
    "name:ukr_x_preferred":[
        "\u0413\u0435\u0440\u0440\u0435\u0441\u0431\u0430\u0445"
    ],
    "name:uzb_x_preferred":[
        "Herresbach"
    ],
    "name:vie_x_preferred":[
        "Herresbach"
    ],
    "name:vol_x_preferred":[
        "Herresbach"
    ],
    "name:war_x_preferred":[
        "Herresbach"
    ],
    "name:zho_x_preferred":[
        "\u9ed1\u52d2\u65af\u5df4\u8d6b"
    ],
    "wof:name":"Herresbach",
    "wof:placetype":"neighbourhood"
},
  "geometry": {"coordinates":[7.28889,50.70523],"type":"Point"}
}