{
  "type": "Feature",
  "properties": {
    "gn:admin1_code":"11",
    "gn:admin2_code":"0.0",
    "gn:admin3_code":"12070.0",
    "gn:admin4_code":"12070316.0",
    "gn:asciiname":"Seefeld",
    "gn:country_code":"DE",
    "gn:dem":104,
    "gn:feature_class":"P",
    "gn:feature_code":"PPL",
    "gn:name":"Seefeld",
    "gn:population":0,
    "gn:timezone":"Europe/Berlin",
    "iso:country":"DE",
    "name:ceb_x_preferred":[
        "Seefeld"
    ],
    "name:deu_x_preferred":[
        "Seefeld"
    ],
    "name:epo_x_preferred":[
        "Seefeld"
    ],
    "name:eus_x_preferred":[
        "Seefeld"
    ],
    "name:fra_x_preferred":[
        "Seefeld"
    ],
    "name:ita_x_preferred":[
        "Seefeld"
    ],
    "name:mkd_x_preferred":[
        "\u0417\u0435\u0444\u0435\u043b\u0434"
    ],
    "name:nld_x_preferred":[
        "Seefeld"
    ],
    "name:pol_x_preferred":[
        "Seefeld"
    ],
    "name:ron_x_preferred":[
        "Seefeld"
    ],
    "name:rus_x_preferred":[
        "\u0417\u0435\u0444\u0435\u043b\u044c\u0434"
    ],
    "name:srp_x_preferred":[
        "\u0417\u0435\u0444\u0435\u043b\u0434"
    ],
    "name:swe_x_preferred":[
        "Seefeld"
    ],
    "name:vol_x_preferred":[
        "Seefeld"
    ],
    "wof:name":"Seefeld",
    "wof:placetype":"neighbourhood"
},
  "geometry": {"coordinates":[12.19276,53.09289],"type":"Point"}
}