{
  "type": "Feature",
  "properties": {
    "gn:admin1_code":"11",
    "gn:admin2_code":"0.0",
    "gn:admin3_code":"12070.0",
    "gn:admin4_code":"12070316.0",
    "gn:asciiname":"Seefeld",
    "gn:country_code":"DE",
    "gn:dem":104,
    "gn:feature_class":"P",
    "gn:feature_code":"PPL",
    "gn:name":"Seefeld",
    "gn:population":0,
    "gn:timezone":"Europe/Berlin",
    "iso:country":"DE",
    "wof:name":"Seefeld",
    "wof:placetype":"neighbourhood"
},
  "geometry": {"coordinates":[12.19276,53.09289],"type":"Point"}
}