{
  "type": "Feature",
  "properties": {
    "gn:admin1_code":"7.0",
    "gn:admin2_code":"51.0",
    "gn:admin3_code":"5154.0",
    "gn:admin4_code":"5154044.0",
    "gn:asciiname":"Bergswick",
    "gn:country_code":"DE",
    "gn:dem":18,
    "gn:feature_class":"P",
    "gn:feature_code":"PPL",
    "gn:name":"Bergswick",
    "gn:population":0,
    "gn:timezone":"Europe/Berlin",
    "iso:country":"DE",
    "wof:name":"Bergswick",
    "wof:placetype":"neighbourhood"
},
  "geometry": {"coordinates":[6.42486,51.76236],"type":"Point"}
}