{
  "type": "Feature",
  "properties": {
    "gn:admin1_code":"10.0",
    "gn:admin2_code":"0.0",
    "gn:admin3_code":"1060.0",
    "gn:admin4_code":"1060052.0",
    "gn:asciiname":"Braak",
    "gn:country_code":"DE",
    "gn:dem":47,
    "gn:feature_class":"P",
    "gn:feature_code":"PPL",
    "gn:name":"Braak",
    "gn:population":0,
    "gn:timezone":"Europe/Berlin",
    "iso:country":"DE",
    "name:cat_x_preferred":[
        "Braak"
    ],
    "name:ceb_x_preferred":[
        "Braak"
    ],
    "name:dan_x_preferred":[
        "Braak"
    ],
    "name:deu_x_preferred":[
        "Braak"
    ],
    "name:epo_x_preferred":[
        "Braak"
    ],
    "name:eus_x_preferred":[
        "Braak"
    ],
    "name:fra_x_preferred":[
        "Braak"
    ],
    "name:hun_x_preferred":[
        "Braak"
    ],
    "name:ita_x_preferred":[
        "Braak"
    ],
    "name:mkd_x_preferred":[
        "\u0411\u0440\u0430\u043a"
    ],
    "name:msa_x_preferred":[
        "Braak"
    ],
    "name:nld_x_preferred":[
        "Braak"
    ],
    "name:pol_x_preferred":[
        "Braak"
    ],
    "name:por_x_preferred":[
        "Braak"
    ],
    "name:ron_x_preferred":[
        "Braak"
    ],
    "name:rus_x_preferred":[
        "\u0411\u0440\u0430\u043a"
    ],
    "name:spa_x_preferred":[
        "Braak"
    ],
    "name:srp_x_preferred":[
        "\u0411\u0440\u0430\u043a"
    ],
    "name:swe_x_preferred":[
        "Braak"
    ],
    "name:tur_x_preferred":[
        "Braak"
    ],
    "name:ukr_x_preferred":[
        "\u0411\u0440\u0430\u0430\u043a"
    ],
    "name:uzb_x_preferred":[
        "Braak"
    ],
    "name:vie_x_preferred":[
        "Braak"
    ],
    "name:vol_x_preferred":[
        "Braak"
    ],
    "name:war_x_preferred":[
        "Braak"
    ],
    "wof:name":"Braak",
    "wof:placetype":"neighbourhood"
},
  "geometry": {"coordinates":[10.08965,54.00644000000001],"type":"Point"}
}