{
  "type": "Feature",
  "properties": {
    "gn:admin1_code":"2",
    "gn:admin2_code":"91.0",
    "gn:admin3_code":"9177.0",
    "gn:admin4_code":"9177115.0",
    "gn:asciiname":"Puch",
    "gn:country_code":"DE",
    "gn:dem":462,
    "gn:feature_class":"P",
    "gn:feature_code":"PPL",
    "gn:name":"Puch",
    "gn:population":0,
    "gn:timezone":"Europe/Berlin",
    "iso:country":"DE",
    "name:bar_x_preferred":[
        "Puch"
    ],
    "name:dan_x_preferred":[
        "Puch"
    ],
    "name:deu_x_preferred":[
        "Puch-Werke"
    ],
    "name:fin_x_preferred":[
        "Puch"
    ],
    "name:fra_x_preferred":[
        "Puch"
    ],
    "name:ita_x_preferred":[
        "Puch-Werke"
    ],
    "name:nld_x_preferred":[
        "Puch"
    ],
    "name:nor_x_preferred":[
        "Puch"
    ],
    "name:slv_x_preferred":[
        "Puch"
    ],
    "name:spa_x_preferred":[
        "Puch"
    ],
    "name:srp_x_preferred":[
        "\u041f\u0443\u0445"
    ],
    "name:swe_x_preferred":[
        "Puch"
    ],
    "wof:name":"Puch",
    "wof:placetype":"neighbourhood"
},
  "geometry": {"coordinates":[12.197,48.26794],"type":"Point"}
}