{
  "type": "Feature",
  "properties": {
    "iso:country":"DE",
    "wof:name":"Bergisch Neukirchen",
    "wof:placetype":"neighbourhood"
},
  "geometry": {"coordinates":[7.03521534610466,51.07817356456297],"type":"Point"}
}