{
  "type": "Feature",
  "properties": {
    "gn:gn_country":"DE",
    "gn:gn_fcode":"PPLA4",
    "gn:gn_pop":481,
    "gn:population":481,
    "iso:country":"DE",
    "name:baq_x_preferred":[
        "Kabelhorst"
    ],
    "name:chi_x_preferred":[
        "\u5361\u8d1d\u5c14\u970d\u5c14\u65af\u7279"
    ],
    "name:dan_x_preferred":[
        "Kabelhorst"
    ],
    "name:dut_x_preferred":[
        "Kabelhorst"
    ],
    "name:eng_x_preferred":[
        "Kabelhorst"
    ],
    "name:epo_x_preferred":[
        "Kabelhorst"
    ],
    "name:fre_x_preferred":[
        "Kabelhorst"
    ],
    "name:ger_x_preferred":[
        "Kabelhorst"
    ],
    "name:hun_x_preferred":[
        "Kabelhorst"
    ],
    "name:ita_x_preferred":[
        "Kabelhorst"
    ],
    "name:kaz_x_preferred":[
        "\u041a\u0430\u0431\u0435\u043b\u044c\u0445\u043e\u0440\u0441\u0442"
    ],
    "name:kir_x_preferred":[
        "\u041a\u0430\u0431\u0435\u043b\u044c\u0445\u043e\u0440\u0441\u0442"
    ],
    "name:mac_x_preferred":[
        "\u041a\u0430\u0431\u0435\u043b\u0445\u043e\u0440\u0441\u0442"
    ],
    "name:may_x_preferred":[
        "Kabelhorst"
    ],
    "name:nob_x_preferred":[
        "Kabelhorst"
    ],
    "name:per_x_preferred":[
        "\u06a9\u0627\u0628\u0644\u0647\u0648\u0631\u0634\u062a"
    ],
    "name:pol_x_preferred":[
        "Kabelhorst"
    ],
    "name:por_x_preferred":[
        "Kabelhorst"
    ],
    "name:rum_x_preferred":[
        "Kabelhorst"
    ],
    "name:rus_x_preferred":[
        "\u041a\u0430\u0431\u0435\u043b\u044c\u0445\u043e\u0440\u0441\u0442"
    ],
    "name:spa_x_preferred":[
        "Kabelhorst"
    ],
    "name:srp_x_preferred":[
        "\u041a\u0430\u0431\u0435\u043b\u0445\u043e\u0440\u0441\u0442"
    ],
    "name:tur_x_preferred":[
        "Kabelhorst"
    ],
    "name:ukr_x_preferred":[
        "\u041a\u0430\u0431\u0435\u043b\u044c\u0433\u043e\u0440\u0441\u0442"
    ],
    "name:uzb_x_preferred":[
        "Kabelhorst"
    ],
    "name:vie_x_preferred":[
        "Kabelhorst"
    ],
    "name:vol_x_preferred":[
        "Kabelhorst"
    ],
    "name:war_x_preferred":[
        "Kabelhorst"
    ],
    "qs_pg:aaroncc":"DE",
    "qs_pg:gn_country":"DE",
    "qs_pg:gn_fcode":"PPLA4",
    "qs_pg:gn_pop":481,
    "qs_pg:name":"Kabelhorst",
    "qs_pg:photos_9r":0,
    "qs_pg:photos_sr":0,
    "qs_pg:pop_sr":2,
    "qs_pg:qs_pg_placetype":"locality",
    "wof:name":"Kabelhorst",
    "wof:placetype":"locality",
    "wof:population":481
},
  "geometry": {"coordinates":[10.91667,54.21667],"type":"Point"}
}