{
  "type": "Feature",
  "properties": {
    "gn:admin1_code":"13",
    "gn:admin2_code":"0.0",
    "gn:admin3_code":"14625.0",
    "gn:admin4_code":"14625270.0",
    "gn:asciiname":"Stenz",
    "gn:country_code":"DE",
    "gn:dem":162,
    "gn:feature_class":"P",
    "gn:feature_code":"PPL",
    "gn:name":"Stenz",
    "gn:population":0,
    "gn:timezone":"Europe/Berlin",
    "iso:country":"DE",
    "wof:name":"Stenz",
    "wof:placetype":"neighbourhood"
},
  "geometry": {"coordinates":[13.88606,51.26694000000001],"type":"Point"}
}