{
  "type": "Feature",
  "properties": {
    "gn:admin1_code":"5",
    "gn:admin2_code":"64.0",
    "gn:admin3_code":"6440.0",
    "gn:admin4_code":"6440021.0",
    "gn:asciiname":"Dorn Assenheim",
    "gn:country_code":"DE",
    "gn:dem":136,
    "gn:feature_class":"P",
    "gn:feature_code":"PPL",
    "gn:name":"Dorn Assenheim",
    "gn:population":0,
    "gn:timezone":"Europe/Berlin",
    "iso:country":"DE",
    "wof:name":"Dorn Assenheim",
    "wof:placetype":"neighbourhood"
},
  "geometry": {"coordinates":[8.84175,50.33895],"type":"Point"}
}