{
  "type": "Feature",
  "properties": {
    "gn:admin1_code":"5.0",
    "gn:admin2_code":"064",
    "gn:admin3_code":"6440.0",
    "gn:admin4_code":"6440019.0",
    "gn:asciiname":"Wippenbach",
    "gn:country_code":"DE",
    "gn:dem":199,
    "gn:feature_class":"P",
    "gn:feature_code":"PPL",
    "gn:name":"Wippenbach",
    "gn:population":0,
    "gn:timezone":"Europe/Berlin",
    "iso:country":"DE",
    "wof:name":"Wippenbach",
    "wof:placetype":"neighbourhood"
},
  "geometry": {"coordinates":[9.04201,50.35738],"type":"Point"}
}