{
  "type": "Feature",
  "properties": {
    "gn:admin1_code":"7.0",
    "gn:admin2_code":"057",
    "gn:admin3_code":"5766.0",
    "gn:admin4_code":"5766040.0",
    "gn:asciiname":"Wellenheide",
    "gn:country_code":"DE",
    "gn:dem":129,
    "gn:feature_class":"P",
    "gn:feature_code":"PPL",
    "gn:name":"Wellenheide",
    "gn:population":0,
    "gn:timezone":"Europe/Berlin",
    "iso:country":"DE",
    "wof:name":"Wellenheide",
    "wof:placetype":"neighbourhood"
},
  "geometry": {"coordinates":[8.8288,51.97172],"type":"Point"}
}