{
  "type": "Feature",
  "properties": {
    "iso:country":"DE",
    "wof:name":"Fechenheim",
    "wof:placetype":"neighbourhood"
},
  "geometry": {"coordinates":[8.76183375073053,50.12567767627127],"type":"Point"}
}