{
  "type": "Feature",
  "properties": {
    "iso:country":"DE",
    "name:ceb_x_preferred":[
        "Fechenheim"
    ],
    "name:deu_x_preferred":[
        "Frankfurt-Fechenheim"
    ],
    "name:fas_x_preferred":[
        "\u0641\u0627\u0634\u0646\u0647\u0627\u06cc\u0645"
    ],
    "name:fra_x_preferred":[
        "Fechenheim"
    ],
    "name:nld_x_preferred":[
        "Frankfurt-Fechenheim"
    ],
    "name:pol_x_preferred":[
        "Fechenheim"
    ],
    "name:spa_x_preferred":[
        "Fechenheim"
    ],
    "wof:name":"Fechenheim",
    "wof:placetype":"neighbourhood"
},
  "geometry": {"coordinates":[8.76183375073053,50.12567767627127],"type":"Point"}
}