{
  "type": "Feature",
  "properties": {
    "gn:admin1_code":"13",
    "gn:admin2_code":"0.0",
    "gn:admin3_code":"14523.0",
    "gn:admin4_code":"14523010.0",
    "gn:asciiname":"Remtengruen",
    "gn:country_code":"DE",
    "gn:dem":532,
    "gn:feature_class":"P",
    "gn:feature_code":"PPL",
    "gn:name":"Remtengr\u00fcn",
    "gn:population":0,
    "gn:timezone":"Europe/Berlin",
    "iso:country":"DE",
    "name:und_x_variant":[
        "Adorf-Remtengr\u00fcn",
        "Remtengr\u00fcn"
    ],
    "wof:name":"Remtengruen",
    "wof:placetype":"neighbourhood"
},
  "geometry": {"coordinates":[12.27484,50.31232],"type":"Point"}
}