{
  "type": "Feature",
  "properties": {
    "gn:admin1_code":"6.0",
    "gn:admin2_code":"0.0",
    "gn:admin3_code":"3151.0",
    "gn:admin4_code":"3151019.0",
    "gn:asciiname":"Bottendorf",
    "gn:country_code":"DE",
    "gn:dem":98,
    "gn:feature_class":"P",
    "gn:feature_code":"PPL",
    "gn:name":"Bottendorf",
    "gn:population":0,
    "gn:timezone":"Europe/Berlin",
    "iso:country":"DE",
    "name:deu_x_preferred":[
        "Bottendorf"
    ],
    "name:nds_x_preferred":[
        "Bottend\u00f6rp"
    ],
    "wof:name":"Bottendorf",
    "wof:placetype":"neighbourhood"
},
  "geometry": {"coordinates":[10.58704,52.76481],"type":"Point"}
}