{
  "type": "Feature",
  "properties": {
    "gn:admin1_code":"2",
    "gn:admin2_code":"94.0",
    "gn:admin3_code":"9475.0",
    "gn:admin4_code":"9475137.0",
    "gn:asciiname":"Griesbach",
    "gn:country_code":"DE",
    "gn:dem":575,
    "gn:feature_class":"P",
    "gn:feature_code":"PPL",
    "gn:name":"Griesbach",
    "gn:population":0,
    "gn:timezone":"Europe/Berlin",
    "iso:country":"DE",
    "name:als_x_preferred":[
        "Griesbach"
    ],
    "name:ceb_x_preferred":[
        "Griesbach"
    ],
    "name:deu_x_preferred":[
        "Griesbach"
    ],
    "name:fra_x_preferred":[
        "Griesbach"
    ],
    "name:pol_x_preferred":[
        "Griesbach"
    ],
    "name:por_x_preferred":[
        "Griesbach"
    ],
    "name:rus_x_preferred":[
        "\u0413\u0440\u0438\u0441\u0431\u0430\u0445"
    ],
    "name:swe_x_preferred":[
        "Griesbach"
    ],
    "wof:name":"Griesbach",
    "wof:placetype":"neighbourhood"
},
  "geometry": {"coordinates":[11.72246,50.35778],"type":"Point"}
}