{
  "type": "Feature",
  "properties": {
    "gn:admin1_code":"9.0",
    "gn:admin2_code":"0.0",
    "gn:admin3_code":"10044.0",
    "gn:admin4_code":"10044115.0",
    "gn:asciiname":"Beaumarais",
    "gn:country_code":"DE",
    "gn:dem":210,
    "gn:feature_class":"P",
    "gn:feature_code":"PPL",
    "gn:name":"Beaumarais",
    "gn:population":0,
    "gn:timezone":"Europe/Berlin",
    "iso:country":"DE",
    "wof:name":"Beaumarais",
    "wof:placetype":"neighbourhood"
},
  "geometry": {"coordinates":[6.71741,49.3115],"type":"Point"}
}