{
  "type": "Feature",
  "properties": {
    "gn:admin1_code":"2",
    "gn:admin2_code":"96.0",
    "gn:admin3_code":"9674.0",
    "gn:admin4_code":"9674221.0",
    "gn:asciiname":"Schmachtenberg",
    "gn:country_code":"DE",
    "gn:dem":262,
    "gn:feature_class":"P",
    "gn:feature_code":"PPL",
    "gn:name":"Schmachtenberg",
    "gn:population":0,
    "gn:timezone":"Europe/Berlin",
    "iso:country":"DE",
    "wof:name":"Schmachtenberg",
    "wof:placetype":"neighbourhood"
},
  "geometry": {"coordinates":[10.60174,50.00716],"type":"Point"}
}