{
  "type": "Feature",
  "properties": {
    "gn:admin1_code":"1",
    "gn:admin2_code":"83.0",
    "gn:admin3_code":"8317.0",
    "gn:admin4_code":"8317100.0",
    "gn:asciiname":"Froschlach",
    "gn:country_code":"DE",
    "gn:dem":195,
    "gn:feature_class":"P",
    "gn:feature_code":"PPL",
    "gn:name":"Fr\u00f6schlach",
    "gn:population":0,
    "gn:timezone":"Europe/Berlin",
    "iso:country":"DE",
    "wof:name":"Froschlach",
    "wof:placetype":"neighbourhood"
},
  "geometry": {"coordinates":[7.97737,48.45645],"type":"Point"}
}