{
  "type": "Feature",
  "properties": {
    "gn:admin1_code":"13",
    "gn:admin2_code":"0.0",
    "gn:admin3_code":"14524.0",
    "gn:admin4_code":"14524330.0",
    "gn:asciiname":"Schedewitz",
    "gn:country_code":"DE",
    "gn:dem":286,
    "gn:feature_class":"P",
    "gn:feature_code":"PPL",
    "gn:name":"Schedewitz",
    "gn:population":0,
    "gn:timezone":"Europe/Berlin",
    "iso:country":"DE",
    "wof:name":"Schedewitz",
    "wof:placetype":"neighbourhood"
},
  "geometry": {"coordinates":[12.4835,50.70335],"type":"Point"}
}