{
  "type": "Feature",
  "properties": {
    "gn:admin1_code":"5",
    "gn:admin2_code":"64.0",
    "gn:admin3_code":"6437.0",
    "gn:admin4_code":"6437010.0",
    "gn:asciiname":"Haingrund",
    "gn:country_code":"DE",
    "gn:dem":236,
    "gn:feature_class":"P",
    "gn:feature_code":"PPL",
    "gn:name":"Haingrund",
    "gn:population":0,
    "gn:timezone":"Europe/Berlin",
    "iso:country":"DE",
    "wof:name":"Haingrund",
    "wof:placetype":"neighbourhood"
},
  "geometry": {"coordinates":[9.10277,49.7644],"type":"Point"}
}