{
  "type": "Feature",
  "properties": {
    "gn:gn_country":"DE",
    "gn:gn_fcode":"PPLA4",
    "gn:gn_pop":94,
    "gn:population":94,
    "iso:country":"DE",
    "name:baq_x_preferred":[
        "Dingdorf"
    ],
    "name:chi_x_preferred":[
        "\u4e01\u683c\u591a\u592b"
    ],
    "name:dut_x_preferred":[
        "Dingdorf"
    ],
    "name:eng_x_preferred":[
        "Dingdorf"
    ],
    "name:epo_x_preferred":[
        "Dingdorf"
    ],
    "name:fre_x_preferred":[
        "Dingdorf"
    ],
    "name:ger_x_preferred":[
        "Dingdorf"
    ],
    "name:hun_x_preferred":[
        "Dingdorf"
    ],
    "name:ita_x_preferred":[
        "Dingdorf"
    ],
    "name:jpn_x_preferred":[
        "\u30c7\u30a3\u30f3\u30c9\u30eb\u30d5"
    ],
    "name:kaz_x_preferred":[
        "\u0414\u0438\u043d\u0433\u0434\u043e\u0440\u0444"
    ],
    "name:kir_x_preferred":[
        "\u0414\u0438\u043d\u0433\u0434\u043e\u0440\u0444"
    ],
    "name:may_x_preferred":[
        "Dingdorf"
    ],
    "name:per_x_preferred":[
        "\u062f\u06cc\u0646\u06af\u062f\u0648\u0631\u0641"
    ],
    "name:pol_x_preferred":[
        "Dingdorf"
    ],
    "name:por_x_preferred":[
        "Dingdorf"
    ],
    "name:rum_x_preferred":[
        "Dingdorf"
    ],
    "name:rus_x_preferred":[
        "\u0414\u0438\u043d\u0433\u0434\u043e\u0440\u0444"
    ],
    "name:spa_x_preferred":[
        "Dingdorf"
    ],
    "name:srp_x_preferred":[
        "\u0414\u0438\u043d\u0433\u0434\u043e\u0440\u0444"
    ],
    "name:ukr_x_preferred":[
        "\u0414\u0456\u043d\u0433\u0434\u043e\u0440\u0444"
    ],
    "name:uzb_x_preferred":[
        "Dingdorf"
    ],
    "name:vie_x_preferred":[
        "Dingdorf"
    ],
    "name:vol_x_preferred":[
        "Dingdorf"
    ],
    "name:war_x_preferred":[
        "Dingdorf"
    ],
    "qs_pg:aaroncc":"DE",
    "qs_pg:gn_country":"DE",
    "qs_pg:gn_fcode":"PPLA4",
    "qs_pg:gn_pop":94,
    "qs_pg:name":"Dingdorf",
    "qs_pg:photos_9r":0,
    "qs_pg:photos_sr":0,
    "qs_pg:pop_sr":1,
    "qs_pg:qs_pg_placetype":"locality",
    "wof:name":"Dingdorf",
    "wof:placetype":"locality",
    "wof:population":94
},
  "geometry": {"coordinates":[6.43333,50.15],"type":"Point"}
}