{
  "type": "Feature",
  "properties": {
    "gn:admin1_code":"11",
    "gn:admin2_code":"0.0",
    "gn:admin3_code":"12054.0",
    "gn:admin4_code":"12054000.0",
    "gn:asciiname":"Nattwerder",
    "gn:country_code":"DE",
    "gn:dem":30,
    "gn:feature_class":"P",
    "gn:feature_code":"PPL",
    "gn:name":"Nattwerder",
    "gn:population":0,
    "gn:timezone":"Europe/Berlin",
    "iso:country":"DE",
    "wof:name":"Nattwerder",
    "wof:placetype":"neighbourhood"
},
  "geometry": {"coordinates":[12.93788,52.42548],"type":"Point"}
}