{
  "type": "Feature",
  "properties": {
    "gn:admin1_code":"1",
    "gn:admin2_code":"81.0",
    "gn:admin3_code":"8119.0",
    "gn:admin4_code":"8119006.0",
    "gn:asciiname":"Unterbruden",
    "gn:country_code":"DE",
    "gn:dem":276,
    "gn:feature_class":"P",
    "gn:feature_code":"PPL",
    "gn:name":"Unterbr\u00fcden",
    "gn:population":0,
    "gn:timezone":"Europe/Berlin",
    "iso:country":"DE",
    "wof:name":"Unterbruden",
    "wof:placetype":"neighbourhood"
},
  "geometry": {"coordinates":[9.50021,48.93743],"type":"Point"}
}