{
  "type": "Feature",
  "properties": {
    "gn:admin1_code":"2",
    "gn:admin2_code":"93.0",
    "gn:admin3_code":"9376.0",
    "gn:admin4_code":"9376171.0",
    "gn:asciiname":"Odmiesbach",
    "gn:country_code":"DE",
    "gn:dem":608,
    "gn:feature_class":"P",
    "gn:feature_code":"PPL",
    "gn:name":"\u00d6dmiesbach",
    "gn:population":0,
    "gn:timezone":"Europe/Berlin",
    "iso:country":"DE",
    "wof:name":"Odmiesbach",
    "wof:placetype":"neighbourhood"
},
  "geometry": {"coordinates":[12.3678,49.50485],"type":"Point"}
}