{
  "type": "Feature",
  "properties": {
    "gn:admin1_code":"1",
    "gn:admin2_code":"82.0",
    "gn:admin3_code":"8237.0",
    "gn:admin4_code":"8237004.0",
    "gn:asciiname":"Heselbach",
    "gn:country_code":"DE",
    "gn:dem":562,
    "gn:feature_class":"P",
    "gn:feature_code":"PPL",
    "gn:name":"Heselbach",
    "gn:population":0,
    "gn:timezone":"Europe/Berlin",
    "iso:country":"DE",
    "wof:name":"Heselbach",
    "wof:placetype":"neighbourhood"
},
  "geometry": {"coordinates":[8.40297,48.53979],"type":"Point"}
}