{
  "type": "Feature",
  "properties": {
    "gn:admin1_code":"1",
    "gn:admin2_code":"81.0",
    "gn:admin3_code":"8127.0",
    "gn:admin4_code":"8127047.0",
    "gn:asciiname":"Unterregenbach",
    "gn:country_code":"DE",
    "gn:dem":295,
    "gn:feature_class":"P",
    "gn:feature_code":"PPL",
    "gn:name":"Unterregenbach",
    "gn:population":0,
    "gn:timezone":"Europe/Berlin",
    "iso:country":"DE",
    "wof:name":"Unterregenbach",
    "wof:placetype":"neighbourhood"
},
  "geometry": {"coordinates":[9.83278,49.275],"type":"Point"}
}