{
  "type": "Feature",
  "properties": {
    "gn:gn_country":"DE",
    "gn:gn_fcode":"PPLX",
    "gn:gn_pop":0,
    "iso:country":"DE",
    "name:deu_x_preferred":[
        "Moorenbrunn"
    ],
    "name:unk_x_variant":[
        "Moorenbrunn"
    ],
    "qs:gn_adm0_cc":"DE",
    "qs:gn_fcode":"PPLX",
    "qs:gn_local":2861650,
    "qs:gn_nam_loc":"nurnberg",
    "qs:gn_namadm1":"02",
    "qs:gn_name":"Moorenbrunn",
    "qs:local_max":6346,
    "qs:local_sum":25338,
    "qs:localhoods":37,
    "qs:name":"Moorenbrunn",
    "qs:name_adm0":"Deutschland",
    "qs:name_adm1":"Bayern",
    "qs:name_adm2":"Stadtkreis N\u00fcrnberg",
    "qs:name_lau":"Stadtteil S\u00fcd\u00f6stliche Au\u00dfenstadt",
    "qs:name_local":"N\u00fcrnberg",
    "qs:photo_max":1,
    "qs:photo_sum":1,
    "qs:placetype":"Suburb",
    "qs:quad_count":1,
    "qs:woe_adm0":23424829,
    "qs:woe_adm1":2345482,
    "qs:woe_adm2":12596973,
    "qs:woe_lau":26823120,
    "qs:woe_local":680564,
    "qs:woe_ver":"7.10.0",
    "qs_pg:aaroncc":"DE",
    "qs_pg:gn_country":"DE",
    "qs_pg:gn_fcode":"PPLX",
    "qs_pg:gn_pop":0,
    "qs_pg:name":"Moorenbrunn",
    "qs_pg:name_adm0":"Deutschland",
    "qs_pg:name_adm1":"Bayern",
    "qs_pg:photos":20,
    "qs_pg:photos_1k":4,
    "qs_pg:photos_9k":1,
    "qs_pg:photos_9r":1,
    "qs_pg:photos_all":20,
    "qs_pg:photos_sr":1,
    "qs_pg:pop_sr":0,
    "qs_pg:qs_pg_placetype":"neighbourhood",
    "qs_pg:qs_pg_placetype_gp":"Suburb",
    "qs_pg:woe_adm0":23424829,
    "wof:lang":[
        "ger"
    ],
    "wof:name":"Moorenbrunn",
    "wof:placetype":"neighbourhood"
},
  "geometry": {"coordinates":[11.17218,49.395932],"type":"Point"}
}