{
  "type": "Feature",
  "properties": {
    "gn:gn_country":"DE",
    "gn:gn_fcode":"PPLA4",
    "gn:gn_pop":518,
    "gn:population":518,
    "iso:country":"DE",
    "name:baq_x_preferred":[
        "Klappholz"
    ],
    "name:chi_x_preferred":[
        "\u514b\u62c9\u798f\u5c14\u8328"
    ],
    "name:dan_x_preferred":[
        "Klapholt"
    ],
    "name:dut_x_preferred":[
        "Klappholz"
    ],
    "name:eng_x_preferred":[
        "Klappholz"
    ],
    "name:epo_x_preferred":[
        "Klappholz"
    ],
    "name:fre_x_preferred":[
        "Klappholz"
    ],
    "name:ger_x_preferred":[
        "Klappholz"
    ],
    "name:hun_x_preferred":[
        "Klappholz"
    ],
    "name:ita_x_preferred":[
        "Klappholz"
    ],
    "name:kaz_x_preferred":[
        "\u041a\u043b\u0430\u043f\u0445\u043e\u043b\u044c\u0446"
    ],
    "name:kir_x_preferred":[
        "\u041a\u043b\u0430\u043f\u0445\u043e\u043b\u044c\u0446"
    ],
    "name:mac_x_preferred":[
        "\u041a\u043b\u0430\u043f\u0445\u043e\u043b\u0446"
    ],
    "name:may_x_preferred":[
        "Klappholz"
    ],
    "name:per_x_preferred":[
        "\u06a9\u0644\u0627\u067e\u0641\u0648\u0644\u062a\u0633"
    ],
    "name:pol_x_preferred":[
        "Klappholz"
    ],
    "name:por_x_preferred":[
        "Klappholz"
    ],
    "name:rum_x_preferred":[
        "Klappholz"
    ],
    "name:rus_x_preferred":[
        "\u041a\u043b\u0430\u043f\u0445\u043e\u043b\u044c\u0446"
    ],
    "name:sco_x_preferred":[
        "Klappholz"
    ],
    "name:spa_x_preferred":[
        "Klappholz"
    ],
    "name:srp_x_preferred":[
        "\u041a\u043b\u0430\u043f\u0445\u043e\u043b\u0446"
    ],
    "name:tur_x_preferred":[
        "Klappholz"
    ],
    "name:ukr_x_preferred":[
        "\u041a\u043b\u0430\u043f\u043f\u0433\u043e\u043b\u044c\u0446"
    ],
    "name:uzb_x_preferred":[
        "Klappholz"
    ],
    "name:vie_x_preferred":[
        "Klappholz"
    ],
    "name:vol_x_preferred":[
        "Klappholz"
    ],
    "name:war_x_preferred":[
        "Klappholz"
    ],
    "qs_pg:aaroncc":"DE",
    "qs_pg:gn_country":"DE",
    "qs_pg:gn_fcode":"PPLA4",
    "qs_pg:gn_pop":518,
    "qs_pg:name":"Klappholz",
    "qs_pg:photos_9r":0,
    "qs_pg:photos_sr":0,
    "qs_pg:pop_sr":2,
    "qs_pg:qs_pg_placetype":"locality",
    "wof:name":"Klappholz",
    "wof:placetype":"locality",
    "wof:population":518
},
  "geometry": {"coordinates":[9.55,54.61667],"type":"Point"}
}