{
  "type": "Feature",
  "properties": {
    "gn:admin1_code":"8.0",
    "gn:admin2_code":"0.0",
    "gn:admin3_code":"7340.0",
    "gn:admin4_code":"7340201.0",
    "gn:asciiname":"Boedingerhof",
    "gn:country_code":"DE",
    "gn:dem":233,
    "gn:feature_class":"P",
    "gn:feature_code":"PPL",
    "gn:name":"B\u00f6dingerhof",
    "gn:population":0,
    "gn:timezone":"Europe/Berlin",
    "iso:country":"DE",
    "wof:name":"Boedingerhof",
    "wof:placetype":"neighbourhood"
},
  "geometry": {"coordinates":[7.3649,49.20989],"type":"Point"}
}