{
  "type": "Feature",
  "properties": {
    "gn:admin1_code":"13",
    "gn:admin2_code":"0.0",
    "gn:admin3_code":"14729.0",
    "gn:admin4_code":"14729350.0",
    "gn:asciiname":"Meuchen",
    "gn:country_code":"DE",
    "gn:dem":135,
    "gn:feature_class":"P",
    "gn:feature_code":"PPL",
    "gn:name":"Meuchen",
    "gn:population":0,
    "gn:timezone":"Europe/Berlin",
    "iso:country":"DE",
    "wof:name":"Meuchen",
    "wof:placetype":"neighbourhood"
},
  "geometry": {"coordinates":[12.25,51.18333],"type":"Point"}
}