{
  "type": "Feature",
  "properties": {
    "gn:admin1_code":"2",
    "gn:admin2_code":"95.0",
    "gn:admin3_code":"9575.0",
    "gn:admin4_code":"9575157.0",
    "gn:asciiname":"Oberambach",
    "gn:country_code":"DE",
    "gn:dem":322,
    "gn:feature_class":"P",
    "gn:feature_code":"PPL",
    "gn:name":"Oberambach",
    "gn:population":0,
    "gn:timezone":"Europe/Berlin",
    "iso:country":"DE",
    "wof:name":"Oberambach",
    "wof:placetype":"neighbourhood"
},
  "geometry": {"coordinates":[10.41659,49.68914],"type":"Point"}
}