{
  "type": "Feature",
  "properties": {
    "gn:admin1_code":"7",
    "gn:admin2_code":"57.0",
    "gn:admin3_code":"5770.0",
    "gn:admin4_code":"5770044.0",
    "gn:asciiname":"Oppendorf",
    "gn:country_code":"DE",
    "gn:dem":49,
    "gn:feature_class":"P",
    "gn:feature_code":"PPL",
    "gn:name":"Oppendorf",
    "gn:population":0,
    "gn:timezone":"Europe/Berlin",
    "iso:country":"DE",
    "wof:name":"Oppendorf",
    "wof:placetype":"neighbourhood"
},
  "geometry": {"coordinates":[8.48557,52.45486],"type":"Point"}
}