{
  "type": "Feature",
  "properties": {
    "gn:admin1_code":"1",
    "gn:admin2_code":"82.0",
    "gn:admin3_code":"8236.0",
    "gn:admin4_code":"8236040.0",
    "gn:asciiname":"Lienzingen",
    "gn:country_code":"DE",
    "gn:dem":252,
    "gn:feature_class":"P",
    "gn:feature_code":"PPL",
    "gn:name":"Lienzingen",
    "gn:population":0,
    "gn:timezone":"Europe/Berlin",
    "iso:country":"DE",
    "wof:name":"Lienzingen",
    "wof:placetype":"neighbourhood"
},
  "geometry": {"coordinates":[8.85989,48.97523],"type":"Point"}
}