{
  "type": "Feature",
  "properties": {
    "gn:admin1_code":"15",
    "gn:admin2_code":"0.0",
    "gn:admin3_code":"16077.0",
    "gn:admin4_code":"16077032.0",
    "gn:asciiname":"Mumsdorf",
    "gn:country_code":"DE",
    "gn:dem":178,
    "gn:feature_class":"P",
    "gn:feature_code":"PPL",
    "gn:name":"Mumsdorf",
    "gn:population":0,
    "gn:timezone":"Europe/Berlin",
    "iso:country":"DE",
    "wof:name":"Mumsdorf",
    "wof:placetype":"neighbourhood"
},
  "geometry": {"coordinates":[12.26655,51.06295],"type":"Point"}
}