{
  "type": "Feature",
  "properties": {
    "gn:admin1_code":"6.0",
    "gn:admin2_code":"00",
    "gn:admin3_code":"3452.0",
    "gn:admin4_code":"3452006.0",
    "gn:asciiname":"Wrisse",
    "gn:country_code":"DE",
    "gn:dem":3,
    "gn:feature_class":"P",
    "gn:feature_code":"PPL",
    "gn:name":"Wrisse",
    "gn:population":0,
    "gn:timezone":"Europe/Berlin",
    "iso:country":"DE",
    "wof:name":"Wrisse",
    "wof:placetype":"neighbourhood"
},
  "geometry": {"coordinates":[7.59066,53.42811],"type":"Point"}
}