{
  "type": "Feature",
  "properties": {
    "gn:admin1_code":"1",
    "gn:admin2_code":"84.0",
    "gn:admin3_code":"8425.0",
    "gn:admin4_code":"8425090.0",
    "gn:asciiname":"Datthausen",
    "gn:country_code":"DE",
    "gn:dem":553,
    "gn:feature_class":"P",
    "gn:feature_code":"PPL",
    "gn:name":"Datthausen",
    "gn:population":0,
    "gn:timezone":"Europe/Berlin",
    "iso:country":"DE",
    "wof:name":"Datthausen",
    "wof:placetype":"neighbourhood"
},
  "geometry": {"coordinates":[9.5354,48.21618],"type":"Point"}
}