{
  "type": "Feature",
  "properties": {
    "gn:admin1_code":"15",
    "gn:admin2_code":"0.0",
    "gn:admin3_code":"16075.0",
    "gn:admin4_code":"16075054.0",
    "gn:asciiname":"Kleindembach",
    "gn:country_code":"DE",
    "gn:dem":195,
    "gn:feature_class":"P",
    "gn:feature_code":"PPL",
    "gn:name":"Kleindembach",
    "gn:population":0,
    "gn:timezone":"Europe/Berlin",
    "iso:country":"DE",
    "wof:name":"Kleindembach",
    "wof:placetype":"neighbourhood"
},
  "geometry": {"coordinates":[11.59578,50.73376],"type":"Point"}
}