{
  "type": "Feature",
  "properties": {
    "gn:admin1_code":"2",
    "gn:admin2_code":"93.0",
    "gn:admin3_code":"9374.0",
    "gn:admin4_code":"9374166.0",
    "gn:asciiname":"Durnast",
    "gn:country_code":"DE",
    "gn:dem":415,
    "gn:feature_class":"P",
    "gn:feature_code":"PPL",
    "gn:name":"D\u00fcrnast",
    "gn:population":0,
    "gn:timezone":"Europe/Berlin",
    "iso:country":"DE",
    "wof:name":"Durnast",
    "wof:placetype":"neighbourhood"
},
  "geometry": {"coordinates":[11.97819,49.64262],"type":"Point"}
}