{
  "type": "Feature",
  "properties": {
    "gn:admin1_code":"2",
    "gn:admin2_code":"93.0",
    "gn:admin3_code":"9376.0",
    "gn:admin4_code":"9376151.0",
    "gn:asciiname":"Gartenried",
    "gn:country_code":"DE",
    "gn:dem":576,
    "gn:feature_class":"P",
    "gn:feature_code":"PPL",
    "gn:name":"Gartenried",
    "gn:population":0,
    "gn:timezone":"Europe/Berlin",
    "iso:country":"DE",
    "wof:name":"Gartenried",
    "wof:placetype":"neighbourhood"
},
  "geometry": {"coordinates":[12.44436,49.49474],"type":"Point"}
}