{
  "type": "Feature",
  "properties": {
    "gn:admin1_code":"13",
    "gn:admin2_code":"0.0",
    "gn:admin3_code":"14625.0",
    "gn:admin4_code":"14625350.0",
    "gn:asciiname":"Duerrwicknitz",
    "gn:country_code":"DE",
    "gn:dem":190,
    "gn:feature_class":"P",
    "gn:feature_code":"PPL",
    "gn:name":"D\u00fcrrwicknitz",
    "gn:population":0,
    "gn:timezone":"Europe/Berlin",
    "iso:country":"DE",
    "name:hsb_x_preferred":[
        "W\u011bte\u0144ca"
    ],
    "wof:name":"Duerrwicknitz",
    "wof:placetype":"neighbourhood"
},
  "geometry": {"coordinates":[14.18827,51.25319],"type":"Point"}
}