{
  "type": "Feature",
  "properties": {
    "gn:admin1_code":"2",
    "gn:admin2_code":"92.0",
    "gn:admin3_code":"9274.0",
    "gn:admin4_code":"9274176.0",
    "gn:asciiname":"Schaltdorf",
    "gn:country_code":"DE",
    "gn:dem":421,
    "gn:feature_class":"P",
    "gn:feature_code":"PPL",
    "gn:name":"Schaltdorf",
    "gn:population":0,
    "gn:timezone":"Europe/Berlin",
    "iso:country":"DE",
    "wof:name":"Schaltdorf",
    "wof:placetype":"neighbourhood"
},
  "geometry": {"coordinates":[12.02175,48.72886],"type":"Point"}
}