{
  "type": "Feature",
  "properties": {
    "gn:admin1_code":"11",
    "gn:admin2_code":"0.0",
    "gn:admin3_code":"12063.0",
    "gn:admin4_code":"12063208.0",
    "gn:asciiname":"Kienberg",
    "gn:country_code":"DE",
    "gn:dem":31,
    "gn:feature_class":"P",
    "gn:feature_code":"PPL",
    "gn:name":"Kienberg",
    "gn:population":0,
    "gn:timezone":"Europe/Berlin",
    "iso:country":"DE",
    "name:ceb_x_preferred":[
        "Kienberg"
    ],
    "name:deu_x_preferred":[
        "Kienberg"
    ],
    "name:epo_x_preferred":[
        "Kienberg"
    ],
    "name:eus_x_preferred":[
        "Kienberg"
    ],
    "name:fra_x_preferred":[
        "Kienberg"
    ],
    "name:ita_x_preferred":[
        "Kienberg"
    ],
    "name:nld_x_preferred":[
        "Kienberg"
    ],
    "name:pol_x_preferred":[
        "Kienberg"
    ],
    "name:rus_x_preferred":[
        "\u041a\u0438\u043d\u0431\u0435\u0440\u0433"
    ],
    "name:swe_x_preferred":[
        "Kienberg"
    ],
    "name:vol_x_preferred":[
        "Kienberg"
    ],
    "wof:name":"Kienberg",
    "wof:placetype":"neighbourhood"
},
  "geometry": {"coordinates":[12.90585,52.66295],"type":"Point"}
}