{
  "type": "Feature",
  "properties": {
    "gn:admin1_code":"13",
    "gn:admin2_code":"0.0",
    "gn:admin3_code":"14730.0",
    "gn:admin4_code":"14730210.0",
    "gn:asciiname":"Reppen",
    "gn:country_code":"DE",
    "gn:dem":144,
    "gn:feature_class":"P",
    "gn:feature_code":"PPL",
    "gn:name":"Reppen",
    "gn:population":0,
    "gn:timezone":"Europe/Berlin",
    "iso:country":"DE",
    "name:ceb_x_preferred":[
        "Reppen"
    ],
    "name:deu_x_preferred":[
        "Reppen"
    ],
    "name:nld_x_preferred":[
        "Reppen"
    ],
    "name:nor_x_preferred":[
        "Reppen"
    ],
    "name:swe_x_preferred":[
        "Reppen"
    ],
    "wof:name":"Reppen",
    "wof:placetype":"neighbourhood"
},
  "geometry": {"coordinates":[13.19755,51.27064],"type":"Point"}
}