{
  "type": "Feature",
  "properties": {
    "gn:admin1_code":"2",
    "gn:admin2_code":"91.0",
    "gn:admin3_code":"9174.0",
    "gn:admin4_code":"9174151.0",
    "gn:asciiname":"Edenholzhausen",
    "gn:country_code":"DE",
    "gn:dem":481,
    "gn:feature_class":"P",
    "gn:feature_code":"PPL",
    "gn:name":"Edenholzhausen",
    "gn:population":0,
    "gn:timezone":"Europe/Berlin",
    "iso:country":"DE",
    "wof:name":"Edenholzhausen",
    "wof:placetype":"neighbourhood"
},
  "geometry": {"coordinates":[11.38744,48.39277],"type":"Point"}
}