{
  "type": "Feature",
  "properties": {
    "gn:admin1_code":"7",
    "gn:admin2_code":"53.0",
    "gn:admin3_code":"5370.0",
    "gn:admin4_code":"5370004.0",
    "gn:asciiname":"Scheidt",
    "gn:country_code":"DE",
    "gn:dem":91,
    "gn:feature_class":"P",
    "gn:feature_code":"PPL",
    "gn:name":"Scheidt",
    "gn:population":0,
    "gn:timezone":"Europe/Berlin",
    "iso:country":"DE",
    "name:ceb_x_preferred":[
        "Scheidt"
    ],
    "name:deu_x_preferred":[
        "Scheidt"
    ],
    "name:fra_x_preferred":[
        "Scheidt"
    ],
    "name:nld_x_preferred":[
        "Scheidt"
    ],
    "name:pol_x_preferred":[
        "Scheidt"
    ],
    "name:por_x_preferred":[
        "Scheidt"
    ],
    "name:rus_x_preferred":[
        "\u0428\u0435\u0439\u0434\u0442"
    ],
    "name:swe_x_preferred":[
        "Scheidt"
    ],
    "name:ukr_x_preferred":[
        "\u0428\u0435\u0439\u0434\u0442"
    ],
    "wof:name":"Scheidt",
    "wof:placetype":"neighbourhood"
},
  "geometry": {"coordinates":[6.29597,51.06176],"type":"Point"}
}