{
  "type": "Feature",
  "properties": {
    "gn:admin1_code":"5",
    "gn:admin2_code":"64.0",
    "gn:admin3_code":"6432.0",
    "gn:admin4_code":"6432022.0",
    "gn:asciiname":"Steigerts",
    "gn:country_code":"DE",
    "gn:dem":410,
    "gn:feature_class":"P",
    "gn:feature_code":"PPL",
    "gn:name":"Steigerts",
    "gn:population":0,
    "gn:timezone":"Europe/Berlin",
    "iso:country":"DE",
    "wof:name":"Steigerts",
    "wof:placetype":"neighbourhood"
},
  "geometry": {"coordinates":[8.68333,49.75],"type":"Point"}
}