{
  "type": "Feature",
  "properties": {
    "gn:admin1_code":"11",
    "gn:admin2_code":"0.0",
    "gn:admin3_code":"12063.0",
    "gn:admin4_code":"12063208.0",
    "gn:asciiname":"Schwanebeck",
    "gn:country_code":"DE",
    "gn:dem":38,
    "gn:feature_class":"P",
    "gn:feature_code":"PPL",
    "gn:name":"Schwanebeck",
    "gn:population":0,
    "gn:timezone":"Europe/Berlin",
    "iso:country":"DE",
    "name:ara_x_preferred":[
        "\u0634\u0641\u0627\u0646\u0646\u0628\u0643"
    ],
    "name:azb_x_preferred":[
        "\u0634\u0648\u0627\u0646\u0646\u0628\u06a9"
    ],
    "name:bak_x_preferred":[
        "\u0428\u0432\u0430\u043d\u0435\u0431\u0435\u043a"
    ],
    "name:ceb_x_preferred":[
        "Schwanebeck"
    ],
    "name:deu_x_preferred":[
        "Schwanebeck"
    ],
    "name:epo_x_preferred":[
        "Schwanebeck"
    ],
    "name:fas_x_preferred":[
        "\u0634\u0648\u0627\u0646\u0646\u0628\u06a9"
    ],
    "name:fra_x_preferred":[
        "Schwanebeck"
    ],
    "name:hun_x_preferred":[
        "Schwanebeck"
    ],
    "name:ita_x_preferred":[
        "Schwanebeck"
    ],
    "name:kaz_x_preferred":[
        "\u0428\u0432\u0430\u043d\u0435\u0431\u0435\u043a"
    ],
    "name:kir_x_preferred":[
        "\u0428\u0432\u0430\u043d\u0435\u0431\u0435\u043a"
    ],
    "name:mkd_x_preferred":[
        "\u0428\u0432\u0430\u043d\u0435\u0431\u0435\u043a"
    ],
    "name:msa_x_preferred":[
        "Schwanebeck"
    ],
    "name:nld_x_preferred":[
        "Schwanebeck"
    ],
    "name:pol_x_preferred":[
        "Schwanebeck"
    ],
    "name:ron_x_preferred":[
        "Schwanebeck"
    ],
    "name:rus_x_preferred":[
        "\u0428\u0432\u0430\u043d\u0435\u0431\u0435\u043a"
    ],
    "name:spa_x_preferred":[
        "Schwanebeck"
    ],
    "name:srp_x_preferred":[
        "\u0428\u0432\u0430\u043d\u0435\u0431\u0435\u043a"
    ],
    "name:swe_x_preferred":[
        "Schwanebeck"
    ],
    "name:ukr_x_preferred":[
        "\u0428\u0432\u0430\u043d\u0435\u0431\u0435\u043a"
    ],
    "name:uzb_x_preferred":[
        "Schwanebeck"
    ],
    "name:vie_x_preferred":[
        "Schwanebeck"
    ],
    "name:vol_x_preferred":[
        "Schwanebeck"
    ],
    "name:war_x_preferred":[
        "Schwanebeck"
    ],
    "name:zho_x_preferred":[
        "\u65bd\u74e6\u8bb7\u8d1d\u514b"
    ],
    "wof:name":"Schwanebeck",
    "wof:placetype":"neighbourhood"
},
  "geometry": {"coordinates":[12.79255,52.57291],"type":"Point"}
}