{
  "type": "Feature",
  "properties": {
    "gn:admin1_code":"11",
    "gn:admin2_code":"0.0",
    "gn:admin3_code":"12063.0",
    "gn:admin4_code":"12063208.0",
    "gn:asciiname":"Schwanebeck",
    "gn:country_code":"DE",
    "gn:dem":38,
    "gn:feature_class":"P",
    "gn:feature_code":"PPL",
    "gn:name":"Schwanebeck",
    "gn:population":0,
    "gn:timezone":"Europe/Berlin",
    "iso:country":"DE",
    "wof:name":"Schwanebeck",
    "wof:placetype":"neighbourhood"
},
  "geometry": {"coordinates":[12.79255,52.57291],"type":"Point"}
}