{
  "type": "Feature",
  "properties": {
    "gn:admin1_code":"14",
    "gn:admin2_code":"0.0",
    "gn:admin3_code":"15091.0",
    "gn:admin4_code":"15091145.0",
    "gn:asciiname":"Kleindroeben",
    "gn:country_code":"DE",
    "gn:dem":75,
    "gn:feature_class":"P",
    "gn:feature_code":"PPL",
    "gn:name":"Kleindr\u00f6ben",
    "gn:population":0,
    "gn:timezone":"Europe/Berlin",
    "iso:country":"DE",
    "wof:name":"Kleindroeben",
    "wof:placetype":"neighbourhood"
},
  "geometry": {"coordinates":[12.83941,51.74385],"type":"Point"}
}