{
  "type": "Feature",
  "properties": {
    "gn:admin1_code":"2",
    "gn:admin2_code":"92.0",
    "gn:admin3_code":"9272.0",
    "gn:admin4_code":"9272127.0",
    "gn:asciiname":"Schonbrunn",
    "gn:country_code":"DE",
    "gn:dem":733,
    "gn:feature_class":"P",
    "gn:feature_code":"PPL",
    "gn:name":"Sch\u00f6nbrunn",
    "gn:population":0,
    "gn:timezone":"Europe/Berlin",
    "iso:country":"DE",
    "wof:name":"Schonbrunn",
    "wof:placetype":"neighbourhood"
},
  "geometry": {"coordinates":[13.53383,48.86232],"type":"Point"}
}