{
  "type": "Feature",
  "properties": {
    "gn:admin1_code":"14.0",
    "gn:admin2_code":"00",
    "gn:admin3_code":"15088.0",
    "gn:admin4_code":"15088330.0",
    "gn:asciiname":"Wessmar",
    "gn:country_code":"DE",
    "gn:dem":97,
    "gn:feature_class":"P",
    "gn:feature_code":"PPL",
    "gn:name":"We\u00dfmar",
    "gn:population":0,
    "gn:timezone":"Europe/Berlin",
    "iso:country":"DE",
    "wof:name":"Wessmar",
    "wof:placetype":"neighbourhood"
},
  "geometry": {"coordinates":[12.1102,51.39364000000001],"type":"Point"}
}