{
  "type": "Feature",
  "properties": {
    "gn:admin1_code":"7",
    "gn:admin2_code":"59.0",
    "gn:admin3_code":"5958.0",
    "gn:admin4_code":"5958016.0",
    "gn:asciiname":"Bueemke",
    "gn:country_code":"DE",
    "gn:dem":381,
    "gn:feature_class":"P",
    "gn:feature_code":"PPL",
    "gn:name":"B\u00fcemke",
    "gn:population":0,
    "gn:timezone":"Europe/Berlin",
    "iso:country":"DE",
    "wof:name":"Bueemke",
    "wof:placetype":"neighbourhood"
},
  "geometry": {"coordinates":[8.21712,51.27162],"type":"Point"}
}