{
  "type": "Feature",
  "properties": {
    "gn:admin1_code":"8",
    "gn:admin2_code":"0.0",
    "gn:admin3_code":"7132.0",
    "gn:admin4_code":"7132055.0",
    "gn:asciiname":"Horhausen",
    "gn:country_code":"DE",
    "gn:dem":337,
    "gn:feature_class":"P",
    "gn:feature_code":"PPL",
    "gn:name":"Horhausen",
    "gn:population":1908,
    "gn:timezone":"Europe/Berlin",
    "iso:country":"DE",
    "name:ceb_x_preferred":[
        "Horhausen"
    ],
    "name:deu_x_preferred":[
        "Horhausen"
    ],
    "name:epo_x_preferred":[
        "Horhausen"
    ],
    "name:fra_x_preferred":[
        "Horhausen"
    ],
    "name:ita_x_preferred":[
        "Horhausen"
    ],
    "name:nld_x_preferred":[
        "Horhausen"
    ],
    "name:pol_x_preferred":[
        "Horhausen"
    ],
    "name:rus_x_preferred":[
        "\u0425\u043e\u0440\u0445\u0430\u0443\u0437\u0435\u043d"
    ],
    "name:srp_x_preferred":[
        "\u0425\u043e\u0440\u0445\u0430\u0443\u0437\u0435\u043d"
    ],
    "name:swe_x_preferred":[
        "Horhausen"
    ],
    "wof:name":"Horhausen",
    "wof:placetype":"neighbourhood",
    "wof:population":1908
},
  "geometry": {"coordinates":[7.53028,50.58745],"type":"Point"}
}