{
  "type": "Feature",
  "properties": {
    "gn:admin1_code":"2",
    "gn:admin2_code":"93.0",
    "gn:admin3_code":"9372.0",
    "gn:admin4_code":"9372171.0",
    "gn:asciiname":"Herzogau",
    "gn:country_code":"DE",
    "gn:dem":696,
    "gn:feature_class":"P",
    "gn:feature_code":"PPL",
    "gn:name":"Herzogau",
    "gn:population":0,
    "gn:timezone":"Europe/Berlin",
    "iso:country":"DE",
    "wof:name":"Herzogau",
    "wof:placetype":"neighbourhood"
},
  "geometry": {"coordinates":[12.72078,49.35484],"type":"Point"}
}