{
  "type": "Feature",
  "properties": {
    "gn:admin1_code":"1.0",
    "gn:admin2_code":"081",
    "gn:admin3_code":"8128.0",
    "gn:admin4_code":"8128082.0",
    "gn:asciiname":"Wildentierbach",
    "gn:country_code":"DE",
    "gn:dem":433,
    "gn:feature_class":"P",
    "gn:feature_code":"PPL",
    "gn:name":"Wildentierbach",
    "gn:population":0,
    "gn:timezone":"Europe/Berlin",
    "iso:country":"DE",
    "wof:name":"Wildentierbach",
    "wof:placetype":"neighbourhood"
},
  "geometry": {"coordinates":[9.98194,49.395],"type":"Point"}
}