{
  "type": "Feature",
  "properties": {
    "gn:admin1_code":"2",
    "gn:admin2_code":"94.0",
    "gn:admin3_code":"9475.0",
    "gn:admin4_code":"9475128.0",
    "gn:asciiname":"Hermesgrun",
    "gn:country_code":"DE",
    "gn:dem":660,
    "gn:feature_class":"P",
    "gn:feature_code":"PPL",
    "gn:name":"Hermesgr\u00fcn",
    "gn:population":0,
    "gn:timezone":"Europe/Berlin",
    "iso:country":"DE",
    "wof:name":"Hermesgrun",
    "wof:placetype":"neighbourhood"
},
  "geometry": {"coordinates":[11.5769,50.37672],"type":"Point"}
}