{
  "type": "Feature",
  "properties": {
    "gn:admin1_code":"2",
    "gn:admin2_code":"95.0",
    "gn:admin3_code":"9574.0",
    "gn:admin4_code":"9574138.0",
    "gn:asciiname":"Kotzenhof",
    "gn:country_code":"DE",
    "gn:dem":338,
    "gn:feature_class":"P",
    "gn:feature_code":"PPL",
    "gn:name":"Kotzenhof",
    "gn:population":0,
    "gn:timezone":"Europe/Berlin",
    "iso:country":"DE",
    "wof:name":"Kotzenhof",
    "wof:placetype":"neighbourhood"
},
  "geometry": {"coordinates":[11.2597,49.51496],"type":"Point"}
}