{
  "type": "Feature",
  "properties": {
    "gn:admin1_code":"7",
    "gn:admin2_code":"57.0",
    "gn:admin3_code":"5770.0",
    "gn:admin4_code":"5770028.0",
    "gn:asciiname":"Quetzerfeld",
    "gn:country_code":"DE",
    "gn:dem":43,
    "gn:feature_class":"P",
    "gn:feature_code":"PPL",
    "gn:name":"Quetzerfeld",
    "gn:population":0,
    "gn:timezone":"Europe/Berlin",
    "iso:country":"DE",
    "wof:name":"Quetzerfeld",
    "wof:placetype":"neighbourhood"
},
  "geometry": {"coordinates":[9.01224,52.36046],"type":"Point"}
}