{
  "type": "Feature",
  "properties": {
    "gn:admin1_code":"7",
    "gn:admin2_code":"51.0",
    "gn:admin3_code":"5166.0",
    "gn:admin4_code":"5166024.0",
    "gn:asciiname":"Linde",
    "gn:country_code":"DE",
    "gn:dem":54,
    "gn:feature_class":"P",
    "gn:feature_code":"PPL",
    "gn:name":"Linde",
    "gn:population":0,
    "gn:timezone":"Europe/Berlin",
    "iso:country":"DE",
    "name:als_x_preferred":[
        "Linde"
    ],
    "name:ceb_x_preferred":[
        "Linde"
    ],
    "name:ces_x_preferred":[
        "Linde"
    ],
    "name:dan_x_preferred":[
        "Linde"
    ],
    "name:deu_x_preferred":[
        "Linde"
    ],
    "name:epo_x_preferred":[
        "Linde"
    ],
    "name:fra_x_preferred":[
        "Linde"
    ],
    "name:ita_x_preferred":[
        "Linde"
    ],
    "name:nld_x_preferred":[
        "Linde"
    ],
    "name:pol_x_preferred":[
        "Linde"
    ],
    "name:rus_x_preferred":[
        "\u041b\u0438\u043d\u0434\u0435"
    ],
    "name:spa_x_preferred":[
        "Linde"
    ],
    "name:swe_x_preferred":[
        "Linde"
    ],
    "name:ukr_x_preferred":[
        "\u041b\u0456\u043d\u0434\u0435"
    ],
    "name:vls_x_preferred":[
        "Linde"
    ],
    "wof:name":"Linde",
    "wof:placetype":"neighbourhood"
},
  "geometry": {"coordinates":[6.24473,51.22257000000001],"type":"Point"}
}