{
  "type": "Feature",
  "properties": {
    "gn:admin1_code":"6",
    "gn:admin2_code":"0.0",
    "gn:admin3_code":"3457.0",
    "gn:admin4_code":"3457020.0",
    "gn:asciiname":"Suedgeorgsfehn",
    "gn:country_code":"DE",
    "gn:dem":2,
    "gn:feature_class":"P",
    "gn:feature_code":"PPL",
    "gn:name":"S\u00fcdgeorgsfehn",
    "gn:population":0,
    "gn:timezone":"Europe/Berlin",
    "iso:country":"DE",
    "wof:name":"Suedgeorgsfehn",
    "wof:placetype":"neighbourhood"
},
  "geometry": {"coordinates":[7.74513,53.24416],"type":"Point"}
}