{
  "type": "Feature",
  "properties": {
    "gn:admin1_code":"5.0",
    "gn:admin2_code":"66.0",
    "gn:admin3_code":"6636.0",
    "gn:admin4_code":"6636005.0",
    "gn:asciiname":"Altefeld",
    "gn:country_code":"DE",
    "gn:dem":405,
    "gn:feature_class":"P",
    "gn:feature_code":"PPL",
    "gn:name":"Altefeld",
    "gn:population":0,
    "gn:timezone":"Europe/Berlin",
    "iso:country":"DE",
    "name:deu_x_preferred":[
        "Altefeld"
    ],
    "name:ita_x_preferred":[
        "Altefeld"
    ],
    "name:und_x_variant":[
        "Altenfeld"
    ],
    "wof:name":"Altefeld",
    "wof:placetype":"neighbourhood"
},
  "geometry": {"coordinates":[10.12082,51.05194],"type":"Point"}
}