{
  "type": "Feature",
  "properties": {
    "gn:admin1_code":"13.0",
    "gn:admin2_code":"0.0",
    "gn:admin3_code":"14729.0",
    "gn:admin4_code":"14729170.0",
    "gn:asciiname":"Auligk",
    "gn:country_code":"DE",
    "gn:dem":139,
    "gn:feature_class":"P",
    "gn:feature_code":"PPL",
    "gn:name":"Auligk",
    "gn:population":0,
    "gn:timezone":"Europe/Berlin",
    "iso:country":"DE",
    "wof:name":"Auligk",
    "wof:placetype":"neighbourhood"
},
  "geometry": {"coordinates":[12.23604,51.10727],"type":"Point"}
}