{
  "type": "Feature",
  "properties": {
    "gn:admin1_code":"1",
    "gn:admin2_code":"82.0",
    "gn:admin3_code":"8211.0",
    "gn:admin4_code":"8211000.0",
    "gn:asciiname":"Muhrich",
    "gn:country_code":"DE",
    "gn:dem":153,
    "gn:feature_class":"P",
    "gn:feature_code":"PPLL",
    "gn:name":"M\u00fchrich",
    "gn:population":0,
    "gn:timezone":"Europe/Berlin",
    "iso:country":"DE",
    "name:und_x_variant":[
        "M\u00fcrich",
        "M\u00fchrich"
    ],
    "wof:name":"Muhrich",
    "wof:placetype":"neighbourhood"
},
  "geometry": {"coordinates":[8.16951,48.73218],"type":"Point"}
}