{
  "type": "Feature",
  "properties": {
    "gn:admin1_code":"6",
    "gn:admin2_code":"0.0",
    "gn:admin3_code":"3452.0",
    "gn:admin4_code":"3452007.0",
    "gn:asciiname":"Suedcoldinne",
    "gn:country_code":"DE",
    "gn:dem":2,
    "gn:feature_class":"P",
    "gn:feature_code":"PPLL",
    "gn:name":"S\u00fcdcoldinne",
    "gn:population":0,
    "gn:timezone":"Europe/Berlin",
    "iso:country":"DE",
    "wof:name":"Suedcoldinne",
    "wof:placetype":"neighbourhood"
},
  "geometry": {"coordinates":[7.38968,53.56885],"type":"Point"}
}