{
  "type": "Feature",
  "properties": {
    "gn:admin1_code":"2",
    "gn:admin2_code":"92.0",
    "gn:admin3_code":"9277.0",
    "gn:admin4_code":"9277118.0",
    "gn:asciiname":"Erlat",
    "gn:country_code":"DE",
    "gn:dem":368,
    "gn:feature_class":"P",
    "gn:feature_code":"PPL",
    "gn:name":"Erlat",
    "gn:population":0,
    "gn:timezone":"Europe/Berlin",
    "iso:country":"DE",
    "wof:name":"Erlat",
    "wof:placetype":"neighbourhood"
},
  "geometry": {"coordinates":[13.12973,48.3253],"type":"Point"}
}