{
  "type": "Feature",
  "properties": {
    "gn:admin1_code":"2",
    "gn:admin2_code":"91.0",
    "gn:admin3_code":"9177.0",
    "gn:admin4_code":"9177144.0",
    "gn:asciiname":"Teufstetten",
    "gn:country_code":"DE",
    "gn:dem":487,
    "gn:feature_class":"P",
    "gn:feature_code":"PPL",
    "gn:name":"Teufstetten",
    "gn:population":0,
    "gn:timezone":"Europe/Berlin",
    "iso:country":"DE",
    "wof:name":"Teufstetten",
    "wof:placetype":"neighbourhood"
},
  "geometry": {"coordinates":[11.91446,48.2518],"type":"Point"}
}