{
  "type": "Feature",
  "properties": {
    "gn:admin1_code":"1",
    "gn:admin2_code":"84.0",
    "gn:admin3_code":"8435.0",
    "gn:admin4_code":"8435059.0",
    "gn:asciiname":"Goldbach",
    "gn:country_code":"DE",
    "gn:dem":531,
    "gn:feature_class":"P",
    "gn:feature_code":"PPL",
    "gn:name":"Goldbach",
    "gn:population":0,
    "gn:timezone":"Europe/Berlin",
    "iso:country":"DE",
    "name:ceb_x_preferred":[
        "Goldbach"
    ],
    "name:deu_x_preferred":[
        "Goldbach"
    ],
    "name:epo_x_preferred":[
        "Goldbach"
    ],
    "name:fas_x_preferred":[
        "\u06af\u0644\u062f\u0628\u0627\u062e"
    ],
    "name:fra_x_preferred":[
        "Goldbach"
    ],
    "name:ita_x_preferred":[
        "Goldbach"
    ],
    "name:jpn_x_preferred":[
        "\u30b4\u30eb\u30c8\u30d0\u30c3\u30cf"
    ],
    "name:nld_x_preferred":[
        "Goldbach"
    ],
    "name:pol_x_preferred":[
        "Goldbach"
    ],
    "name:rus_x_preferred":[
        "\u0413\u043e\u043b\u044c\u0434\u0431\u0430\u0445"
    ],
    "name:spa_x_preferred":[
        "Goldbach"
    ],
    "name:srp_x_preferred":[
        "\u0413\u043e\u043b\u0434\u0431\u0430\u0445"
    ],
    "name:swe_x_preferred":[
        "Goldbach"
    ],
    "name:ukr_x_preferred":[
        "\u0413\u043e\u043b\u044c\u0434\u0431\u0430\u0445"
    ],
    "name:vol_x_preferred":[
        "Goldbach"
    ],
    "wof:name":"Goldbach",
    "wof:placetype":"neighbourhood"
},
  "geometry": {"coordinates":[9.15,47.78333],"type":"Point"}
}