{
  "type": "Feature",
  "properties": {
    "gn:admin1_code":"8",
    "gn:admin2_code":"0.0",
    "gn:admin3_code":"7235.0",
    "gn:admin4_code":"7235073.0",
    "gn:asciiname":"Metzdorf",
    "gn:country_code":"DE",
    "gn:dem":153,
    "gn:feature_class":"P",
    "gn:feature_code":"PPL",
    "gn:name":"Metzdorf",
    "gn:population":0,
    "gn:timezone":"Europe/Berlin",
    "iso:country":"DE",
    "wof:name":"Metzdorf",
    "wof:placetype":"neighbourhood"
},
  "geometry": {"coordinates":[6.50279,49.74842],"type":"Point"}
}