{
  "type": "Feature",
  "properties": {
    "gn:admin1_code":"10",
    "gn:admin2_code":"0.0",
    "gn:admin3_code":"1062.0",
    "gn:admin4_code":"1062008.0",
    "gn:asciiname":"Hude",
    "gn:country_code":"DE",
    "gn:dem":11,
    "gn:feature_class":"P",
    "gn:feature_code":"PPL",
    "gn:name":"Hude",
    "gn:population":0,
    "gn:timezone":"Europe/Berlin",
    "iso:country":"DE",
    "name:ang_x_preferred":[
        "Hude"
    ],
    "name:bul_x_preferred":[
        "\u0425\u0443\u0434\u0435"
    ],
    "name:dan_x_preferred":[
        "Hude"
    ],
    "name:deu_x_preferred":[
        "Hude"
    ],
    "name:epo_x_preferred":[
        "Hude"
    ],
    "name:est_x_preferred":[
        "Hude"
    ],
    "name:eus_x_preferred":[
        "Hude"
    ],
    "name:fas_x_preferred":[
        "\u0647\u0648\u062f\u0647"
    ],
    "name:fra_x_preferred":[
        "Hude"
    ],
    "name:hun_x_preferred":[
        "Hude"
    ],
    "name:ita_x_preferred":[
        "Hude"
    ],
    "name:kaz_x_preferred":[
        "\u0425\u0443\u0434\u0435"
    ],
    "name:kir_x_preferred":[
        "\u0425\u0443\u0434\u0435"
    ],
    "name:msa_x_preferred":[
        "Hude"
    ],
    "name:nld_x_preferred":[
        "Hude"
    ],
    "name:pol_x_preferred":[
        "Hude"
    ],
    "name:por_x_preferred":[
        "Hude"
    ],
    "name:ron_x_preferred":[
        "Hude"
    ],
    "name:rus_x_preferred":[
        "\u0425\u0443\u0434\u0435"
    ],
    "name:spa_x_preferred":[
        "Hude"
    ],
    "name:srp_x_preferred":[
        "\u0425\u0443\u0434\u0435"
    ],
    "name:ukr_x_preferred":[
        "\u0413\u0443\u0434\u0435"
    ],
    "name:uzb_x_preferred":[
        "Hude"
    ],
    "name:vie_x_preferred":[
        "Hude"
    ],
    "name:vol_x_preferred":[
        "Hude"
    ],
    "name:war_x_preferred":[
        "Hude"
    ],
    "wof:name":"Hude",
    "wof:placetype":"neighbourhood"
},
  "geometry": {"coordinates":[10.45,53.81667],"type":"Point"}
}