{
  "type": "Feature",
  "properties": {
    "gn:admin1_code":"7",
    "gn:admin2_code":"51.0",
    "gn:admin3_code":"5162.0",
    "gn:admin4_code":"5162012.0",
    "gn:asciiname":"Duerselen",
    "gn:country_code":"DE",
    "gn:dem":74,
    "gn:feature_class":"P",
    "gn:feature_code":"PPL",
    "gn:name":"D\u00fcrselen",
    "gn:population":0,
    "gn:timezone":"Europe/Berlin",
    "iso:country":"DE",
    "wof:name":"Duerselen",
    "wof:placetype":"neighbourhood"
},
  "geometry": {"coordinates":[6.48623,51.13434],"type":"Point"}
}