{
  "type": "Feature",
  "properties": {
    "gn:admin1_code":"2",
    "gn:admin2_code":"93.0",
    "gn:admin3_code":"9377.0",
    "gn:admin4_code":"9377148.0",
    "gn:asciiname":"Lochau",
    "gn:country_code":"DE",
    "gn:dem":533,
    "gn:feature_class":"P",
    "gn:feature_code":"PPL",
    "gn:name":"Lochau",
    "gn:population":0,
    "gn:timezone":"Europe/Berlin",
    "iso:country":"DE",
    "name:als_x_preferred":[
        "Lochau"
    ],
    "name:bul_x_preferred":[
        "\u041b\u043e\u0445\u0430\u0443"
    ],
    "name:cat_x_preferred":[
        "Lochau"
    ],
    "name:ceb_x_preferred":[
        "Lochau"
    ],
    "name:deu_x_preferred":[
        "Lochau"
    ],
    "name:fas_x_preferred":[
        "\u0644\u062e\u0648"
    ],
    "name:fra_x_preferred":[
        "Lochau"
    ],
    "name:fur_x_preferred":[
        "Lochau"
    ],
    "name:hun_x_preferred":[
        "Lochau"
    ],
    "name:ita_x_preferred":[
        "Lochau"
    ],
    "name:lmo_x_preferred":[
        "Lochau"
    ],
    "name:nld_x_preferred":[
        "Lochau"
    ],
    "name:nno_x_preferred":[
        "Lochau"
    ],
    "name:pol_x_preferred":[
        "Lochau"
    ],
    "name:ron_x_preferred":[
        "Lochau"
    ],
    "name:rus_x_preferred":[
        "\u041b\u043e\u0445\u0430\u0443"
    ],
    "name:slk_x_preferred":[
        "Lochau"
    ],
    "name:spa_x_preferred":[
        "Lochau"
    ],
    "name:swe_x_preferred":[
        "Lochau"
    ],
    "name:tur_x_preferred":[
        "Lochau"
    ],
    "name:ukr_x_preferred":[
        "\u041b\u043e\u0445\u0430\u0443"
    ],
    "name:uzb_x_preferred":[
        "Lochau"
    ],
    "name:vol_x_preferred":[
        "Lochau"
    ],
    "name:war_x_preferred":[
        "Lochau"
    ],
    "wof:name":"Lochau",
    "wof:placetype":"neighbourhood"
},
  "geometry": {"coordinates":[11.97544,49.91697],"type":"Point"}
}