{
  "type": "Feature",
  "properties": {
    "gn:admin1_code":"1",
    "gn:admin2_code":"82.0",
    "gn:admin3_code":"8237.0",
    "gn:admin4_code":"8237004.0",
    "gn:asciiname":"Sohlberg",
    "gn:country_code":"DE",
    "gn:dem":581,
    "gn:feature_class":"P",
    "gn:feature_code":"PPL",
    "gn:name":"Sohlberg",
    "gn:population":0,
    "gn:timezone":"Europe/Berlin",
    "iso:country":"DE",
    "name:nor_x_preferred":[
        "Sohlberg"
    ],
    "name:swe_x_preferred":[
        "Sohlberg"
    ],
    "wof:name":"Sohlberg",
    "wof:placetype":"neighbourhood"
},
  "geometry": {"coordinates":[8.36112,48.49487],"type":"Point"}
}