{
  "type": "Feature",
  "properties": {
    "gn:admin1_code":"7",
    "gn:admin2_code":"53.0",
    "gn:admin3_code":"5374.0",
    "gn:admin4_code":"5374032.0",
    "gn:asciiname":"Heide",
    "gn:country_code":"DE",
    "gn:dem":222,
    "gn:feature_class":"P",
    "gn:feature_code":"PPL",
    "gn:name":"Heide",
    "gn:population":0,
    "gn:timezone":"Europe/Berlin",
    "iso:country":"DE",
    "name:ara_x_preferred":[
        "\u0647\u0627\u064a\u062f\u0629"
    ],
    "name:azb_x_preferred":[
        "\u0647\u0627\u06cc\u062f\u0647"
    ],
    "name:ceb_x_preferred":[
        "Heide"
    ],
    "name:dan_x_preferred":[
        "Heide"
    ],
    "name:deu_x_preferred":[
        "Heide"
    ],
    "name:epo_x_preferred":[
        "Heide"
    ],
    "name:eus_x_preferred":[
        "Heide"
    ],
    "name:fas_x_preferred":[
        "\u0647\u0627\u06cc\u062f\u0647"
    ],
    "name:fin_x_preferred":[
        "Heide"
    ],
    "name:fra_x_preferred":[
        "Heide"
    ],
    "name:frr_x_preferred":[
        "Heide"
    ],
    "name:hrv_x_preferred":[
        "Heide"
    ],
    "name:hun_x_preferred":[
        "Heide"
    ],
    "name:ind_x_preferred":[
        "Heide"
    ],
    "name:ita_x_preferred":[
        "Heide"
    ],
    "name:jpn_x_preferred":[
        "\u30cf\u30a4\u30c7"
    ],
    "name:kaz_x_preferred":[
        "\u0425\u0430\u0439\u0434\u0435"
    ],
    "name:kir_x_preferred":[
        "\u0425\u0430\u0439\u0434\u0435"
    ],
    "name:mkd_x_preferred":[
        "\u0425\u0430\u0458\u0434\u0435"
    ],
    "name:msa_x_preferred":[
        "Heide"
    ],
    "name:nds_x_preferred":[
        "Heid"
    ],
    "name:nld_x_preferred":[
        "Heide"
    ],
    "name:nor_x_preferred":[
        "Heide"
    ],
    "name:pol_x_preferred":[
        "Heide"
    ],
    "name:por_x_preferred":[
        "Heide"
    ],
    "name:ron_x_preferred":[
        "Heide"
    ],
    "name:rus_x_preferred":[
        "\u0425\u0430\u0439\u0434\u0435"
    ],
    "name:spa_x_preferred":[
        "Heide"
    ],
    "name:srp_x_preferred":[
        "\u0425\u0430\u0458\u0434\u0435"
    ],
    "name:swa_x_preferred":[
        "Heide"
    ],
    "name:swe_x_preferred":[
        "Heide"
    ],
    "name:tur_x_preferred":[
        "Heide"
    ],
    "name:ukr_x_preferred":[
        "\u0413\u0430\u0439\u0434\u0435"
    ],
    "name:uzb_x_preferred":[
        "Heide"
    ],
    "name:vie_x_preferred":[
        "Heide"
    ],
    "name:vol_x_preferred":[
        "Heide"
    ],
    "name:war_x_preferred":[
        "Heide"
    ],
    "wof:name":"Heide",
    "wof:placetype":"neighbourhood"
},
  "geometry": {"coordinates":[7.47631,50.88921],"type":"Point"}
}