{
  "type": "Feature",
  "properties": {
    "gn:admin1_code":"15",
    "gn:admin2_code":"0.0",
    "gn:admin3_code":"16075.0",
    "gn:admin4_code":"16075009.0",
    "gn:asciiname":"Burgkhammer",
    "gn:country_code":"DE",
    "gn:dem":357,
    "gn:feature_class":"P",
    "gn:feature_code":"PPL",
    "gn:name":"Burgkhammer",
    "gn:population":0,
    "gn:timezone":"Europe/Berlin",
    "iso:country":"DE",
    "wof:name":"Burgkhammer",
    "wof:placetype":"neighbourhood"
},
  "geometry": {"coordinates":[11.71941,50.55026],"type":"Point"}
}