{
  "type": "Feature",
  "properties": {
    "gn:admin1_code":"2",
    "gn:admin2_code":"92.0",
    "gn:admin3_code":"9274.0",
    "gn:admin4_code":"9274127.0",
    "gn:asciiname":"Oberdornbach",
    "gn:country_code":"DE",
    "gn:dem":444,
    "gn:feature_class":"P",
    "gn:feature_code":"PPL",
    "gn:name":"Oberd\u00f6rnbach",
    "gn:population":0,
    "gn:timezone":"Europe/Berlin",
    "iso:country":"DE",
    "wof:name":"Oberdornbach",
    "wof:placetype":"neighbourhood"
},
  "geometry": {"coordinates":[12.17586,48.68794000000001],"type":"Point"}
}