{
  "type": "Feature",
  "properties": {
    "gn:admin1_code":"7.0",
    "gn:admin2_code":"053",
    "gn:admin3_code":"5374.0",
    "gn:admin4_code":"5374020.0",
    "gn:asciiname":"Wuestenhof",
    "gn:country_code":"DE",
    "gn:dem":270,
    "gn:feature_class":"P",
    "gn:feature_code":"PPL",
    "gn:name":"W\u00fcstenhof",
    "gn:population":0,
    "gn:timezone":"Europe/Berlin",
    "iso:country":"DE",
    "wof:name":"Wuestenhof",
    "wof:placetype":"neighbourhood"
},
  "geometry": {"coordinates":[7.35157,50.99196],"type":"Point"}
}