{
  "type": "Feature",
  "properties": {
    "gn:admin1_code":"6.0",
    "gn:admin2_code":"0.0",
    "gn:admin3_code":"3351.0",
    "gn:admin4_code":"3351006.0",
    "gn:asciiname":"Bostel",
    "gn:country_code":"DE",
    "gn:dem":58,
    "gn:feature_class":"P",
    "gn:feature_code":"PPL",
    "gn:name":"Bostel",
    "gn:population":0,
    "gn:timezone":"Europe/Berlin",
    "iso:country":"DE",
    "name:bos_x_preferred":[
        "Bostel"
    ],
    "wof:name":"Bostel",
    "wof:placetype":"neighbourhood"
},
  "geometry": {"coordinates":[10.13334,52.6452],"type":"Point"}
}