{
  "type": "Feature",
  "properties": {
    "gn:admin1_code":"14",
    "gn:admin2_code":"0.0",
    "gn:admin3_code":"15086.0",
    "gn:admin4_code":"15086040.0",
    "gn:asciiname":"Schattberge",
    "gn:country_code":"DE",
    "gn:dem":53,
    "gn:feature_class":"P",
    "gn:feature_code":"PPL",
    "gn:name":"Schattberge",
    "gn:population":0,
    "gn:timezone":"Europe/Berlin",
    "iso:country":"DE",
    "wof:name":"Schattberge",
    "wof:placetype":"neighbourhood"
},
  "geometry": {"coordinates":[12.06001,52.31049],"type":"Point"}
}