{
  "type": "Feature",
  "properties": {
    "iso:country":"DE",
    "name:ceb_x_preferred":[
        "La Torrecilla"
    ],
    "name:deu_x_preferred":[
        "Brandbruch"
    ],
    "name:epo_x_preferred":[
        "Torrecilla"
    ],
    "name:nno_x_preferred":[
        "La Torrecilla"
    ],
    "name:por_x_preferred":[
        "Torrecilla"
    ],
    "name:zho_x_preferred":[
        "\u6258\u96f7\u897f\u5229\u4e9e\u5c71"
    ],
    "qs:gn_adm0_cc":"DE",
    "qs:gn_fcode":"PPL",
    "qs:gn_local":2935517,
    "qs:gn_nam_loc":"dortmund",
    "qs:gn_namadm1":"07",
    "qs:gn_name":"Brandbruch",
    "qs:local_max":5685,
    "qs:local_sum":19088,
    "qs:localhoods":60,
    "qs:name":"Brandbruch",
    "qs:name_adm0":"Deutschland",
    "qs:name_adm1":"Nordrhein-Westfalen",
    "qs:name_adm2":"Stadtkreis Dortmund",
    "qs:name_lau":"Stadtteil H\u00f6rde",
    "qs:name_local":"Dortmund",
    "qs:photo_max":2,
    "qs:photo_sum":3,
    "qs:placetype":"Suburb",
    "qs:quad_count":2,
    "qs:woe_adm0":23424829,
    "qs:woe_adm1":2345487,
    "qs:woe_adm2":12596991,
    "qs:woe_lau":26822121,
    "qs:woe_local":645458,
    "qs:woe_ver":"7.10.0",
    "wof:lang":[
        "ger"
    ],
    "wof:name":"Brandbruch",
    "wof:placetype":"neighbourhood"
},
  "geometry": {"coordinates":[7.482605,51.447733],"type":"Point"}
}