{
  "type": "Feature",
  "properties": {
    "gn:admin1_code":"2",
    "gn:admin2_code":"91.0",
    "gn:admin3_code":"9185.0",
    "gn:admin4_code":"9185149.0",
    "gn:asciiname":"Rohrenhof",
    "gn:country_code":"DE",
    "gn:dem":382,
    "gn:feature_class":"P",
    "gn:feature_code":"PPL",
    "gn:name":"R\u00f6hrenhof",
    "gn:population":0,
    "gn:timezone":"Europe/Berlin",
    "iso:country":"DE",
    "wof:name":"Rohrenhof",
    "wof:placetype":"neighbourhood"
},
  "geometry": {"coordinates":[11.21816,48.72053],"type":"Point"}
}