{
  "type": "Feature",
  "properties": {
    "gn:admin1_code":"2",
    "gn:admin2_code":"94.0",
    "gn:admin3_code":"9475.0",
    "gn:admin4_code":"9475184.0",
    "gn:asciiname":"Bug",
    "gn:country_code":"DE",
    "gn:dem":534,
    "gn:feature_class":"P",
    "gn:feature_code":"PPL",
    "gn:name":"Bug",
    "gn:population":0,
    "gn:timezone":"Europe/Berlin",
    "iso:country":"DE",
    "name:bel_x_preferred":[
        "\u0411\u0443\u0433"
    ],
    "name:ben_x_preferred":[
        "\u09ac\u09be\u0997"
    ],
    "name:bul_x_preferred":[
        "\u0411\u0443\u0433"
    ],
    "name:cat_x_preferred":[
        "Bug"
    ],
    "name:ceb_x_preferred":[
        "Bug"
    ],
    "name:ces_x_preferred":[
        "Bug"
    ],
    "name:dan_x_preferred":[
        "Bug"
    ],
    "name:deu_x_preferred":[
        "Bug"
    ],
    "name:fas_x_preferred":[
        "\u062d\u0634\u0631\u0647"
    ],
    "name:fin_x_preferred":[
        "Bug"
    ],
    "name:fra_x_preferred":[
        "Bug"
    ],
    "name:heb_x_preferred":[
        "\u05d1\u05d5\u05d2"
    ],
    "name:hin_x_preferred":[
        "\u092c\u0917"
    ],
    "name:hrv_x_preferred":[
        "Bug"
    ],
    "name:hun_x_preferred":[
        "Bug"
    ],
    "name:lav_x_preferred":[
        "Bug"
    ],
    "name:lit_x_preferred":[
        "Bugas"
    ],
    "name:nld_x_preferred":[
        "Bug"
    ],
    "name:nno_x_preferred":[
        "Bug"
    ],
    "name:nor_x_preferred":[
        "Bug"
    ],
    "name:oci_x_preferred":[
        "Bug"
    ],
    "name:pol_x_preferred":[
        "Bug"
    ],
    "name:por_x_preferred":[
        "Bug"
    ],
    "name:rus_x_preferred":[
        "\u0411\u0443\u0433"
    ],
    "name:spa_x_preferred":[
        "Bug"
    ],
    "name:srp_x_preferred":[
        "\u0411\u0443\u0433"
    ],
    "name:swa_x_preferred":[
        "Mdudu"
    ],
    "name:swe_x_preferred":[
        "Bug"
    ],
    "name:tgl_x_preferred":[
        "Bug"
    ],
    "name:tha_x_preferred":[
        "\u0e1a\u0e31\u0e4a\u0e01"
    ],
    "name:ukr_x_preferred":[
        "\u0411\u0443\u0433"
    ],
    "name:urd_x_preferred":[
        "\u0628\u06af"
    ],
    "name:uzb_x_preferred":[
        "Bug"
    ],
    "wof:name":"Bug",
    "wof:placetype":"neighbourhood"
},
  "geometry": {"coordinates":[11.84762,50.19413],"type":"Point"}
}