{
  "type": "Feature",
  "properties": {
    "gn:admin1_code":"9",
    "gn:admin2_code":"0.0",
    "gn:admin3_code":"10041.0",
    "gn:admin4_code":"10041100.0",
    "gn:asciiname":"Scheidt",
    "gn:country_code":"DE",
    "gn:dem":210,
    "gn:feature_class":"P",
    "gn:feature_code":"PPL",
    "gn:name":"Scheidt",
    "gn:population":0,
    "gn:timezone":"Europe/Berlin",
    "iso:country":"DE",
    "name:ceb_x_preferred":[
        "Scheidt"
    ],
    "name:deu_x_preferred":[
        "Scheidt"
    ],
    "wof:name":"Scheidt",
    "wof:placetype":"neighbourhood"
},
  "geometry": {"coordinates":[7.05889,49.24596],"type":"Point"}
}