{
  "type": "Feature",
  "properties": {
    "gn:admin1_code":"15",
    "gn:admin2_code":"0.0",
    "gn:admin3_code":"16076.0",
    "gn:admin4_code":"16076022.0",
    "gn:asciiname":"Neugommla",
    "gn:country_code":"DE",
    "gn:dem":399,
    "gn:feature_class":"P",
    "gn:feature_code":"PPL",
    "gn:name":"Neugommla",
    "gn:population":0,
    "gn:timezone":"Europe/Berlin",
    "iso:country":"DE",
    "wof:name":"Neugommla",
    "wof:placetype":"neighbourhood"
},
  "geometry": {"coordinates":[12.16667,50.66667],"type":"Point"}
}