{
  "type": "Feature",
  "properties": {
    "gn:admin1_code":"13.0",
    "gn:admin2_code":"0.0",
    "gn:admin3_code":"14522.0",
    "gn:admin4_code":"14522230.0",
    "gn:asciiname":"Berthelsdorf",
    "gn:country_code":"DE",
    "gn:dem":313,
    "gn:feature_class":"P",
    "gn:feature_code":"PPL",
    "gn:name":"Berthelsdorf",
    "gn:population":0,
    "gn:timezone":"Europe/Berlin",
    "iso:country":"DE",
    "name:bak_x_preferred":[
        "\u0411\u0435\u0440\u0442\u0435\u043b\u044c\u0441\u0434\u043e\u0440\u0444"
    ],
    "name:cat_x_preferred":[
        "Berthelsdorf"
    ],
    "name:ces_x_preferred":[
        "Berthelsdorf"
    ],
    "name:deu_x_preferred":[
        "Berthelsdorf"
    ],
    "name:epo_x_preferred":[
        "Berthelsdorf"
    ],
    "name:est_x_preferred":[
        "Berthelsdorf"
    ],
    "name:fas_x_preferred":[
        "\u0628\u0631\u062a\u0647\u0644\u0633\u062f\u0648\u0631\u0641"
    ],
    "name:fra_x_preferred":[
        "Berthelsdorf"
    ],
    "name:hsb_x_preferred":[
        "Batromjecy"
    ],
    "name:ita_x_preferred":[
        "Berthelsdorf"
    ],
    "name:kaz_x_preferred":[
        "\u0411\u0435\u0440\u0442\u0435\u043b\u044c\u0441\u0434\u043e\u0440\u0444"
    ],
    "name:kir_x_preferred":[
        "\u0411\u0435\u0440\u0442\u0435\u043b\u044c\u0441\u0434\u043e\u0440\u0444"
    ],
    "name:mkd_x_preferred":[
        "\u0411\u0435\u0440\u0442\u0435\u043b\u0441\u0434\u043e\u0440\u0444"
    ],
    "name:msa_x_preferred":[
        "Berthelsdorf"
    ],
    "name:nld_x_preferred":[
        "Berthelsdorf"
    ],
    "name:nor_x_preferred":[
        "Berthelsdorf"
    ],
    "name:pol_x_preferred":[
        "Berthelsdorf"
    ],
    "name:por_x_preferred":[
        "Berthelsdorf"
    ],
    "name:ron_x_preferred":[
        "Berthelsdorf"
    ],
    "name:rus_x_preferred":[
        "\u0411\u0435\u0440\u0442\u0435\u043b\u044c\u0441\u0434\u043e\u0440\u0444"
    ],
    "name:srp_x_preferred":[
        "\u0411\u0435\u0440\u0442\u0435\u043b\u0441\u0434\u043e\u0440\u0444"
    ],
    "name:swe_x_preferred":[
        "Berthelsdorf"
    ],
    "name:uzb_x_preferred":[
        "Berthelsdorf"
    ],
    "name:vie_x_preferred":[
        "Berthelsdorf"
    ],
    "name:vol_x_preferred":[
        "Berthelsdorf"
    ],
    "name:war_x_preferred":[
        "Berthelsdorf"
    ],
    "name:zho_x_preferred":[
        "\u8d1d\u5c14\u7279\u5c14\u65af\u591a\u592b"
    ],
    "wof:name":"Berthelsdorf",
    "wof:placetype":"neighbourhood"
},
  "geometry": {"coordinates":[13.11102,50.95287],"type":"Point"}
}