{
  "type": "Feature",
  "properties": {
    "gn:admin1_code":"2",
    "gn:admin2_code":"93.0",
    "gn:admin3_code":"9376.0",
    "gn:admin4_code":"9376125.0",
    "gn:asciiname":"Freihols",
    "gn:country_code":"DE",
    "gn:dem":390,
    "gn:feature_class":"P",
    "gn:feature_code":"PPL",
    "gn:name":"Freih\u00f6ls",
    "gn:population":0,
    "gn:timezone":"Europe/Berlin",
    "iso:country":"DE",
    "wof:name":"Freihols",
    "wof:placetype":"neighbourhood"
},
  "geometry": {"coordinates":[12.01912,49.40051],"type":"Point"}
}