{
  "type": "Feature",
  "properties": {
    "gn:admin1_code":"7.0",
    "gn:admin2_code":"059",
    "gn:admin3_code":"5974.0",
    "gn:admin4_code":"5974032.0",
    "gn:asciiname":"Westrich",
    "gn:country_code":"DE",
    "gn:dem":237,
    "gn:feature_class":"P",
    "gn:feature_code":"PPL",
    "gn:name":"Westrich",
    "gn:population":0,
    "gn:timezone":"Europe/Berlin",
    "iso:country":"DE",
    "wof:name":"Westrich",
    "wof:placetype":"neighbourhood"
},
  "geometry": {"coordinates":[8.07622,51.49748],"type":"Point"}
}