{
  "type": "Feature",
  "properties": {
    "gn:admin1_code":"15.0",
    "gn:admin2_code":"0.0",
    "gn:admin3_code":"16061.0",
    "gn:admin4_code":"16061114.0",
    "gn:asciiname":"Bleckenrode",
    "gn:country_code":"DE",
    "gn:dem":237,
    "gn:feature_class":"P",
    "gn:feature_code":"PPL",
    "gn:name":"Bleckenrode",
    "gn:population":0,
    "gn:timezone":"Europe/Berlin",
    "iso:country":"DE",
    "wof:name":"Bleckenrode",
    "wof:placetype":"neighbourhood"
},
  "geometry": {"coordinates":[10.2191,51.46768],"type":"Point"}
}