{
  "type": "Feature",
  "properties": {
    "gn:admin1_code":"7",
    "gn:admin2_code":"53.0",
    "gn:admin3_code":"5370.0",
    "gn:admin4_code":"5370016.0",
    "gn:asciiname":"Schleiden",
    "gn:country_code":"DE",
    "gn:dem":62,
    "gn:feature_class":"P",
    "gn:feature_code":"PPL",
    "gn:name":"Schleiden",
    "gn:population":0,
    "gn:timezone":"Europe/Berlin",
    "iso:country":"DE",
    "name:ara_x_preferred":[
        "\u0634\u0644\u0627\u064a\u062f\u0646"
    ],
    "name:azb_x_preferred":[
        "\u0627\u0634\u0644\u0627\u06cc\u062f\u0646"
    ],
    "name:bul_x_preferred":[
        "\u0428\u043b\u0430\u0439\u0434\u0435\u043d"
    ],
    "name:ceb_x_preferred":[
        "Schleiden"
    ],
    "name:dan_x_preferred":[
        "Schleiden"
    ],
    "name:deu_x_preferred":[
        "Schleiden"
    ],
    "name:epo_x_preferred":[
        "Schleiden"
    ],
    "name:eus_x_preferred":[
        "Schleiden"
    ],
    "name:fas_x_preferred":[
        "\u0627\u0634\u0644\u0627\u06cc\u062f\u0646"
    ],
    "name:fra_x_preferred":[
        "Schleiden"
    ],
    "name:hun_x_preferred":[
        "Schleiden"
    ],
    "name:ita_x_preferred":[
        "Schleiden"
    ],
    "name:kaz_x_preferred":[
        "\u0428\u043b\u0430\u0439\u0434\u0435\u043d"
    ],
    "name:kir_x_preferred":[
        "\u0428\u043b\u0430\u0439\u0434\u0435\u043d"
    ],
    "name:lim_x_preferred":[
        "Sjleie"
    ],
    "name:msa_x_preferred":[
        "Schleiden"
    ],
    "name:nld_x_preferred":[
        "Schleiden"
    ],
    "name:nor_x_preferred":[
        "Schleiden"
    ],
    "name:pol_x_preferred":[
        "Schleiden"
    ],
    "name:ron_x_preferred":[
        "Schleiden"
    ],
    "name:rus_x_preferred":[
        "\u0428\u043b\u0430\u0439\u0434\u0435\u043d"
    ],
    "name:srp_x_preferred":[
        "\u0428\u043b\u0430\u0458\u0434\u0435\u043d"
    ],
    "name:swe_x_preferred":[
        "Schleiden"
    ],
    "name:tur_x_preferred":[
        "Schleiden"
    ],
    "name:ukr_x_preferred":[
        "\u0428\u043b\u044f\u0439\u0434\u0435\u043d"
    ],
    "name:uzb_x_preferred":[
        "Schleiden"
    ],
    "name:vol_x_preferred":[
        "Schleiden"
    ],
    "name:war_x_preferred":[
        "Schleiden"
    ],
    "name:zho_x_preferred":[
        "\u65bd\u83b1\u767b"
    ],
    "wof:name":"Schleiden",
    "wof:placetype":"neighbourhood"
},
  "geometry": {"coordinates":[6.10537,51.03916],"type":"Point"}
}