{
  "type": "Feature",
  "properties": {
    "gn:admin1_code":"10",
    "gn:admin2_code":"0.0",
    "gn:admin3_code":"1061.0",
    "gn:admin4_code":"1061042.0",
    "gn:asciiname":"Hohenfiert",
    "gn:country_code":"DE",
    "gn:dem":24,
    "gn:feature_class":"P",
    "gn:feature_code":"PPL",
    "gn:name":"Hohenfiert",
    "gn:population":0,
    "gn:timezone":"Europe/Berlin",
    "iso:country":"DE",
    "wof:name":"Hohenfiert",
    "wof:placetype":"neighbourhood"
},
  "geometry": {"coordinates":[9.63743,54.00615],"type":"Point"}
}