{
  "type": "Feature",
  "properties": {
    "iso:country":"DE",
    "name:deu_x_preferred":[
        "Flugplatz Pritzwalk-Sommersberg"
    ],
    "name:eng_x_preferred":[
        "Pritzwalk-Sommersberg Airport"
    ],
    "name:eng_x_variant":[
        "EDBU",
        "Pritzwalk-Sommersberg airfield"
    ],
    "name:msa_x_preferred":[
        "Lapangan Terbang Sommersberg"
    ],
    "oa:elevation_ft":"289",
    "oa:type":"small_airport",
    "woe:hierarchy":{
        "country_id":23424829,
        "county_id":12596708,
        "localadmin_id":24547303,
        "planet_id":1,
        "state_id":2345491
    },
    "wof:name":"Flugplatz Pritzwalk-sommersberg",
    "wof:placetype":"campus"
},
  "geometry": {"coordinates":[12.185555,53.180833],"type":"Point"}
}