{
  "type": "Feature",
  "properties": {
    "gn:admin1_code":"6.0",
    "gn:admin2_code":"0.0",
    "gn:admin3_code":"3459.0",
    "gn:admin4_code":"3459014.0",
    "gn:asciiname":"Lappenstuhl",
    "gn:country_code":"DE",
    "gn:dem":49,
    "gn:feature_class":"P",
    "gn:feature_code":"PPL",
    "gn:name":"Lappenstuhl",
    "gn:population":0,
    "gn:timezone":"Europe/Berlin",
    "iso:country":"DE",
    "wof:name":"Lappenstuhl",
    "wof:placetype":"neighbourhood"
},
  "geometry": {"coordinates":[8.05686,52.41876],"type":"Point"}
}