{
  "type": "Feature",
  "properties": {
    "gn:admin1_code":"2.0",
    "gn:admin2_code":"097",
    "gn:admin3_code":"9773.0",
    "gn:admin4_code":"9773122.0",
    "gn:asciiname":"Wortelstetten",
    "gn:country_code":"DE",
    "gn:dem":459,
    "gn:feature_class":"P",
    "gn:feature_code":"PPL",
    "gn:name":"Wortelstetten",
    "gn:population":0,
    "gn:timezone":"Europe/Berlin",
    "iso:country":"DE",
    "wof:name":"Wortelstetten",
    "wof:placetype":"neighbourhood"
},
  "geometry": {"coordinates":[10.75075,48.58865],"type":"Point"}
}