{
  "type": "Feature",
  "properties": {
    "gn:admin1_code":"2",
    "gn:admin2_code":"93.0",
    "gn:admin3_code":"9374.0",
    "gn:admin4_code":"9374147.0",
    "gn:asciiname":"Miesbrunn",
    "gn:country_code":"DE",
    "gn:dem":590,
    "gn:feature_class":"P",
    "gn:feature_code":"PPL",
    "gn:name":"Miesbrunn",
    "gn:population":0,
    "gn:timezone":"Europe/Berlin",
    "iso:country":"DE",
    "wof:name":"Miesbrunn",
    "wof:placetype":"neighbourhood"
},
  "geometry": {"coordinates":[12.43155,49.65468],"type":"Point"}
}