{
  "type": "Feature",
  "properties": {
    "gn:admin1_code":"13",
    "gn:admin2_code":"0.0",
    "gn:admin3_code":"14523.0",
    "gn:admin4_code":"14523230.0",
    "gn:asciiname":"Saalig",
    "gn:country_code":"DE",
    "gn:dem":541,
    "gn:feature_class":"P",
    "gn:feature_code":"PPL",
    "gn:name":"Saalig",
    "gn:population":0,
    "gn:timezone":"Europe/Berlin",
    "iso:country":"DE",
    "wof:name":"Saalig",
    "wof:placetype":"neighbourhood"
},
  "geometry": {"coordinates":[12.29306,50.36342],"type":"Point"}
}