{
  "type": "Feature",
  "properties": {
    "iso:country":"DE",
    "name:deu_x_preferred":[
        "Hamburg-Marienthal"
    ],
    "name:dut_x_preferred":[
        "Marienthal"
    ],
    "name:eng_x_preferred":[
        "Marienthal"
    ],
    "name:fre_x_preferred":[
        "Hamburg-Marienthal"
    ],
    "name:ger_x_preferred":[
        "Marienthal"
    ],
    "name:hun_x_preferred":[
        "Marienthal"
    ],
    "name:ita_x_preferred":[
        "Marienthal"
    ],
    "name:lat_x_preferred":[
        "Hamburg-Marienthal"
    ],
    "name:pol_x_preferred":[
        "Marienthal"
    ],
    "name:rus_x_preferred":[
        "\u041c\u0430\u0440\u0438\u043d\u0442\u0430\u043b\u044c"
    ],
    "name:spa_x_preferred":[
        "Marienthal"
    ],
    "wof:name":"Marienthal",
    "wof:placetype":"neighbourhood"
},
  "geometry": {"coordinates":[10.08207309355534,53.56732164764037],"type":"Point"}
}