{
  "type": "Feature",
  "properties": {
    "gn:admin1_code":"2",
    "gn:admin2_code":"93.0",
    "gn:admin3_code":"9372.0",
    "gn:admin4_code":"9372171.0",
    "gn:asciiname":"Hauslarn",
    "gn:country_code":"DE",
    "gn:dem":585,
    "gn:feature_class":"P",
    "gn:feature_code":"PPL",
    "gn:name":"H\u00e4uslarn",
    "gn:population":0,
    "gn:timezone":"Europe/Berlin",
    "iso:country":"DE",
    "wof:name":"Hauslarn",
    "wof:placetype":"neighbourhood"
},
  "geometry": {"coordinates":[12.69411,49.30151],"type":"Point"}
}