{
  "type": "Feature",
  "properties": {
    "gn:admin1_code":"2",
    "gn:admin2_code":"91.0",
    "gn:admin3_code":"9186.0",
    "gn:admin4_code":"9186125.0",
    "gn:asciiname":"Gerenzhausen",
    "gn:country_code":"DE",
    "gn:dem":456,
    "gn:feature_class":"P",
    "gn:feature_code":"PPL",
    "gn:name":"Gerenzhausen",
    "gn:population":0,
    "gn:timezone":"Europe/Berlin",
    "iso:country":"DE",
    "wof:name":"Gerenzhausen",
    "wof:placetype":"neighbourhood"
},
  "geometry": {"coordinates":[11.38718,48.50221],"type":"Point"}
}