{
  "type": "Feature",
  "properties": {
    "iso:country":"DE",
    "name:deu_x_colloquial":[
        "Steinebruck",
        "Steinebrueck"
    ],
    "name:deu_x_preferred":[
        "Steinebr\u00fcck"
    ],
    "name:und_x_variant":[
        "Steinenbr\u00fcck"
    ],
    "qs:gn_fcode":"PPLX",
    "qs:gn_local":0,
    "qs:gn_namadm1":"07",
    "qs:gn_name":"Steinebr\u00fcck",
    "qs:local_max":7923,
    "qs:local_sum":22653,
    "qs:localhoods":31,
    "qs:name":"Steinebr\u00fcck",
    "qs:name_adm0":"Deutschland",
    "qs:name_adm1":"Nordrhein-Westfalen",
    "qs:name_adm2":"Stadtkreis Aachen",
    "qs:name_lau":"Stadtteil Aachen",
    "qs:name_local":"Aachen",
    "qs:photo_max":383,
    "qs:photo_sum":506,
    "qs:placetype":"Suburb",
    "qs:quad_count":24,
    "qs:woe_adm0":23424829,
    "qs:woe_adm1":2345487,
    "qs:woe_adm2":20071103,
    "qs:woe_lau":26821833,
    "qs:woe_local":633175,
    "qs:woe_ver":"7.10.0",
    "wof:lang":[
        "ger"
    ],
    "wof:name":"Steinebr\u00fcck",
    "wof:placetype":"neighbourhood"
},
  "geometry": {"coordinates":[6.091581,50.747073],"type":"Point"}
}