{
  "type": "Feature",
  "properties": {
    "gn:admin1_code":"7",
    "gn:admin2_code":"59.0",
    "gn:admin3_code":"5954.0",
    "gn:admin4_code":"5954032.0",
    "gn:asciiname":"Vosshoeven",
    "gn:country_code":"DE",
    "gn:dem":194,
    "gn:feature_class":"P",
    "gn:feature_code":"PPL",
    "gn:name":"Vo\u00dfh\u00f6ven",
    "gn:population":0,
    "gn:timezone":"Europe/Berlin",
    "iso:country":"DE",
    "wof:name":"Vosshoeven",
    "wof:placetype":"neighbourhood"
},
  "geometry": {"coordinates":[7.34395,51.37875],"type":"Point"}
}