{
  "type": "Feature",
  "properties": {
    "gn:admin1_code":"1",
    "gn:admin2_code":"83.0",
    "gn:admin3_code":"8317.0",
    "gn:admin4_code":"8317041.0",
    "gn:asciiname":"Neuenbach",
    "gn:country_code":"DE",
    "gn:dem":343,
    "gn:feature_class":"P",
    "gn:feature_code":"PPLL",
    "gn:name":"Neuenbach",
    "gn:population":0,
    "gn:timezone":"Europe/Berlin",
    "iso:country":"DE",
    "wof:name":"Neuenbach",
    "wof:placetype":"neighbourhood"
},
  "geometry": {"coordinates":[8.16293,48.30611],"type":"Point"}
}