{
  "type": "Feature",
  "properties": {
    "gn:admin1_code":"5",
    "gn:admin2_code":"64.0",
    "gn:admin3_code":"6439.0",
    "gn:admin4_code":"6439002.0",
    "gn:asciiname":"Ramschied",
    "gn:country_code":"DE",
    "gn:dem":384,
    "gn:feature_class":"P",
    "gn:feature_code":"PPL",
    "gn:name":"Ramschied",
    "gn:population":0,
    "gn:timezone":"Europe/Berlin",
    "iso:country":"DE",
    "name:ceb_x_preferred":[
        "Ramschied"
    ],
    "name:deu_x_preferred":[
        "Ramschied"
    ],
    "name:fas_x_preferred":[
        "\u0631\u0627\u0645\u0634\u0627\u06cc\u062f"
    ],
    "name:nld_x_preferred":[
        "Ramschied"
    ],
    "wof:name":"Ramschied",
    "wof:placetype":"neighbourhood"
},
  "geometry": {"coordinates":[8.03664,50.13439],"type":"Point"}
}