{
  "type": "Feature",
  "properties": {
    "gn:admin1_code":"15",
    "gn:admin2_code":"0.0",
    "gn:admin3_code":"16075.0",
    "gn:admin4_code":"16075062.0",
    "gn:asciiname":"Klein Friesa",
    "gn:country_code":"DE",
    "gn:dem":461,
    "gn:feature_class":"P",
    "gn:feature_code":"PPL",
    "gn:name":"Klein Friesa",
    "gn:population":0,
    "gn:timezone":"Europe/Berlin",
    "iso:country":"DE",
    "wof:name":"Klein Friesa",
    "wof:placetype":"neighbourhood"
},
  "geometry": {"coordinates":[11.668,50.44765],"type":"Point"}
}