{
  "type": "Feature",
  "properties": {
    "gn:admin1_code":"1",
    "gn:admin2_code":"83.0",
    "gn:admin3_code":"8326.0",
    "gn:admin4_code":"8326054.0",
    "gn:asciiname":"Holltal",
    "gn:country_code":"DE",
    "gn:dem":946,
    "gn:feature_class":"P",
    "gn:feature_code":"PPL",
    "gn:name":"H\u00f6lltal",
    "gn:population":0,
    "gn:timezone":"Europe/Berlin",
    "iso:country":"DE",
    "wof:name":"Holltal",
    "wof:placetype":"neighbourhood"
},
  "geometry": {"coordinates":[8.20872,48.11417],"type":"Point"}
}