{
  "type": "Feature",
  "properties": {
    "gn:admin1_code":"8.0",
    "gn:admin2_code":"0.0",
    "gn:admin3_code":"7138.0",
    "gn:admin4_code":"7138050.0",
    "gn:asciiname":"Breibach",
    "gn:country_code":"DE",
    "gn:dem":237,
    "gn:feature_class":"P",
    "gn:feature_code":"PPL",
    "gn:name":"Breibach",
    "gn:population":0,
    "gn:timezone":"Europe/Berlin",
    "iso:country":"DE",
    "wof:name":"Breibach",
    "wof:placetype":"neighbourhood"
},
  "geometry": {"coordinates":[7.59195,50.64968],"type":"Point"}
}