{
  "type": "Feature",
  "properties": {
    "gn:admin1_code":"11",
    "gn:admin2_code":"0.0",
    "gn:admin3_code":"12071.0",
    "gn:admin4_code":"12071193.0",
    "gn:asciiname":"Kolonie Jaenschwalde",
    "gn:country_code":"DE",
    "gn:dem":62,
    "gn:feature_class":"P",
    "gn:feature_code":"PPL",
    "gn:name":"Kolonie J\u00e4nschwalde",
    "gn:population":0,
    "gn:timezone":"Europe/Berlin",
    "iso:country":"DE",
    "name:und_x_variant":[
        "Kolonie"
    ],
    "wof:name":"Kolonie Jaenschwalde",
    "wof:placetype":"neighbourhood"
},
  "geometry": {"coordinates":[14.50897,51.86327],"type":"Point"}
}