{
  "type": "Feature",
  "properties": {
    "gn:admin1_code":"2.0",
    "gn:admin2_code":"92.0",
    "gn:admin3_code":"9278.0",
    "gn:admin4_code":"9278147.0",
    "gn:asciiname":"Bluthensdorf",
    "gn:country_code":"DE",
    "gn:dem":433,
    "gn:feature_class":"P",
    "gn:feature_code":"PPL",
    "gn:name":"Bl\u00fcthensdorf",
    "gn:population":0,
    "gn:timezone":"Europe/Berlin",
    "iso:country":"DE",
    "wof:name":"Bluthensdorf",
    "wof:placetype":"neighbourhood"
},
  "geometry": {"coordinates":[12.65509,49.09566],"type":"Point"}
}