{
  "type": "Feature",
  "properties": {
    "gn:admin1_code":"2",
    "gn:admin2_code":"97.0",
    "gn:admin3_code":"9779.0",
    "gn:admin4_code":"9779111.0",
    "gn:asciiname":"Buhl im Ries",
    "gn:country_code":"DE",
    "gn:dem":412,
    "gn:feature_class":"P",
    "gn:feature_code":"PPL",
    "gn:name":"B\u00fchl im Ries",
    "gn:population":0,
    "gn:timezone":"Europe/Berlin",
    "iso:country":"DE",
    "name:und_x_variant":[
        "B\u00fchl",
        "B\u00fchl im Ries"
    ],
    "wof:name":"Buhl im Ries",
    "wof:placetype":"neighbourhood"
},
  "geometry": {"coordinates":[10.6563,48.83419],"type":"Point"}
}