{
  "type": "Feature",
  "properties": {
    "gn:admin1_code":"1",
    "gn:admin2_code":"82.0",
    "gn:admin3_code":"8226.0",
    "gn:admin4_code":"8226060.0",
    "gn:asciiname":"Maisbach",
    "gn:country_code":"DE",
    "gn:dem":201,
    "gn:feature_class":"P",
    "gn:feature_code":"PPL",
    "gn:name":"Maisbach",
    "gn:population":0,
    "gn:timezone":"Europe/Berlin",
    "iso:country":"DE",
    "wof:name":"Maisbach",
    "wof:placetype":"neighbourhood"
},
  "geometry": {"coordinates":[8.72864,49.32787],"type":"Point"}
}