{
  "type": "Feature",
  "properties": {
    "gn:admin1_code":"5",
    "gn:admin2_code":"66.0",
    "gn:admin3_code":"6631.0",
    "gn:admin4_code":"6631019.0",
    "gn:asciiname":"Oberaschenbach",
    "gn:country_code":"DE",
    "gn:dem":392,
    "gn:feature_class":"P",
    "gn:feature_code":"PPL",
    "gn:name":"Oberaschenbach",
    "gn:population":0,
    "gn:timezone":"Europe/Berlin",
    "iso:country":"DE",
    "wof:name":"Oberaschenbach",
    "wof:placetype":"neighbourhood"
},
  "geometry": {"coordinates":[9.86538,50.65496],"type":"Point"}
}