{
  "type": "Feature",
  "properties": {
    "gn:admin1_code":"1",
    "gn:admin2_code":"81.0",
    "gn:admin3_code":"8116.0",
    "gn:admin4_code":"8116019.0",
    "gn:asciiname":"Oberesslingen",
    "gn:cc2":"DE",
    "gn:country_code":"DE",
    "gn:dem":249,
    "gn:feature_class":"P",
    "gn:feature_code":"PPL",
    "gn:name":"Oberesslingen",
    "gn:population":0,
    "gn:timezone":"Europe/Berlin",
    "iso:country":"DE",
    "name:und_x_variant":[
        "Esslingen-Oberesslingen"
    ],
    "wof:name":"Oberesslingen",
    "wof:placetype":"neighbourhood"
},
  "geometry": {"coordinates":[9.33271,48.73012],"type":"Point"}
}