{
  "type": "Feature",
  "properties": {
    "gn:admin1_code":"1",
    "gn:admin2_code":"84.0",
    "gn:admin3_code":"8435.0",
    "gn:admin4_code":"8435035.0",
    "gn:asciiname":"Schwarzenbach",
    "gn:country_code":"DE",
    "gn:dem":446,
    "gn:feature_class":"P",
    "gn:feature_code":"PPL",
    "gn:name":"Schwarzenbach",
    "gn:population":0,
    "gn:timezone":"Europe/Berlin",
    "iso:country":"DE",
    "name:ceb_x_preferred":[
        "Schwarzenbach"
    ],
    "name:ces_x_preferred":[
        "Schwarzenbach"
    ],
    "name:dan_x_preferred":[
        "Schwarzenbach"
    ],
    "name:deu_x_preferred":[
        "Schwarzenbach"
    ],
    "name:epo_x_preferred":[
        "Schwarzenbach"
    ],
    "name:fra_x_preferred":[
        "Schwarzenbach"
    ],
    "name:ita_x_preferred":[
        "Schwarzenbach"
    ],
    "name:nld_x_preferred":[
        "Schwarzenbach"
    ],
    "name:pol_x_preferred":[
        "Schwarzenbach"
    ],
    "name:rus_x_preferred":[
        "\u0428\u0432\u0430\u0440\u0446\u0435\u043d\u0431\u0430\u0445"
    ],
    "name:swe_x_preferred":[
        "Schwarzenbach"
    ],
    "name:vol_x_preferred":[
        "Schwarzenbach"
    ],
    "wof:name":"Schwarzenbach",
    "wof:placetype":"neighbourhood"
},
  "geometry": {"coordinates":[9.58377,47.72641],"type":"Point"}
}