{
  "type": "Feature",
  "properties": {
    "gn:admin1_code":"1",
    "gn:admin2_code":"81.0",
    "gn:admin3_code":"8136.0",
    "gn:admin4_code":"8136088.0",
    "gn:asciiname":"Weidenfeld",
    "gn:country_code":"DE",
    "gn:dem":452,
    "gn:feature_class":"P",
    "gn:feature_code":"PPL",
    "gn:name":"Weidenfeld",
    "gn:population":0,
    "gn:timezone":"Europe/Berlin",
    "iso:country":"DE",
    "name:deu_x_preferred":[
        "Weidenfeld"
    ],
    "name:fra_x_preferred":[
        "Weidenfeld"
    ],
    "wof:name":"Weidenfeld",
    "wof:placetype":"neighbourhood"
},
  "geometry": {"coordinates":[10.08601,48.85406],"type":"Point"}
}