{
  "type": "Feature",
  "properties": {
    "gn:admin1_code":"1.0",
    "gn:admin2_code":"83.0",
    "gn:admin3_code":"8337.0",
    "gn:admin4_code":"8337125.0",
    "gn:asciiname":"Rheinheim",
    "gn:country_code":"DE",
    "gn:dem":342,
    "gn:feature_class":"P",
    "gn:feature_code":"PPL",
    "gn:name":"Rheinheim",
    "gn:population":0,
    "gn:timezone":"Europe/Berlin",
    "iso:country":"DE",
    "wof:name":"Rheinheim",
    "wof:placetype":"neighbourhood"
},
  "geometry": {"coordinates":[8.303,47.58897],"type":"Point"}
}