{
  "type": "Feature",
  "properties": {
    "iso:country":"DE",
    "wof:name":"Wasserturm",
    "wof:placetype":"neighbourhood"
},
  "geometry": {"coordinates":[7.07588476710635,51.18929393920362],"type":"Point"}
}