{
  "type": "Feature",
  "properties": {
    "gn:admin1_code":"2",
    "gn:admin2_code":"95.0",
    "gn:admin3_code":"9575.0",
    "gn:admin4_code":"9575181.0",
    "gn:asciiname":"Stadelhof",
    "gn:country_code":"DE",
    "gn:dem":317,
    "gn:feature_class":"P",
    "gn:feature_code":"PPL",
    "gn:name":"Stadelhof",
    "gn:population":0,
    "gn:timezone":"Europe/Berlin",
    "iso:country":"DE",
    "wof:name":"Stadelhof",
    "wof:placetype":"neighbourhood"
},
  "geometry": {"coordinates":[10.74308,49.55879],"type":"Point"}
}