{
  "type": "Feature",
  "properties": {
    "gn:admin1_code":"7",
    "gn:admin2_code":"55.0",
    "gn:admin3_code":"5570.0",
    "gn:admin4_code":"5570052.0",
    "gn:asciiname":"Buddenbaum",
    "gn:country_code":"DE",
    "gn:dem":82,
    "gn:feature_class":"P",
    "gn:feature_code":"PPLL",
    "gn:name":"Buddenbaum",
    "gn:population":0,
    "gn:timezone":"Europe/Berlin",
    "iso:country":"DE",
    "wof:name":"Buddenbaum",
    "wof:placetype":"neighbourhood"
},
  "geometry": {"coordinates":[7.96487,51.87063],"type":"Point"}
}