{
  "type": "Feature",
  "properties": {
    "gn:admin1_code":"11",
    "gn:admin2_code":"0.0",
    "gn:admin3_code":"12069.0",
    "gn:admin4_code":"12069665.0",
    "gn:asciiname":"Schlamau",
    "gn:country_code":"DE",
    "gn:dem":147,
    "gn:feature_class":"P",
    "gn:feature_code":"PPL",
    "gn:name":"Schlamau",
    "gn:population":0,
    "gn:timezone":"Europe/Berlin",
    "iso:country":"DE",
    "wof:name":"Schlamau",
    "wof:placetype":"neighbourhood"
},
  "geometry": {"coordinates":[12.44789,52.13182000000001],"type":"Point"}
}