{
  "type": "Feature",
  "properties": {
    "gn:admin1_code":"5",
    "gn:admin2_code":"66.0",
    "gn:admin3_code":"6631.0",
    "gn:admin4_code":"6631015.0",
    "gn:asciiname":"Stendorf",
    "gn:country_code":"DE",
    "gn:dem":381,
    "gn:feature_class":"P",
    "gn:feature_code":"PPL",
    "gn:name":"Stendorf",
    "gn:population":0,
    "gn:timezone":"Europe/Berlin",
    "iso:country":"DE",
    "wof:name":"Stendorf",
    "wof:placetype":"neighbourhood"
},
  "geometry": {"coordinates":[9.8284,50.71982],"type":"Point"}
}