{
  "type": "Feature",
  "properties": {
    "gn:country":"DE",
    "gn:fcode":"PPLX",
    "gn:population":60,
    "iso:country":"DE",
    "name:ceb_x_preferred":[
        "Scheuern"
    ],
    "name:deu_x_preferred":[
        "Scheuern"
    ],
    "name:epo_x_preferred":[
        "Scheuern"
    ],
    "name:eus_x_preferred":[
        "Scheuern"
    ],
    "name:fas_x_preferred":[
        "\u0634\u0648\u06cc\u0631\u0646"
    ],
    "name:fra_x_preferred":[
        "Scheuern"
    ],
    "name:hun_x_preferred":[
        "Scheuern"
    ],
    "name:ita_x_preferred":[
        "Scheuern"
    ],
    "name:msa_x_preferred":[
        "Scheuern"
    ],
    "name:nld_x_preferred":[
        "Scheuern"
    ],
    "name:pol_x_preferred":[
        "Scheuern"
    ],
    "name:por_x_preferred":[
        "Scheuern"
    ],
    "name:ron_x_preferred":[
        "Scheuern"
    ],
    "name:rus_x_preferred":[
        "\u0428\u043e\u0439\u0435\u0440\u043d"
    ],
    "name:spa_x_preferred":[
        "Scheuern"
    ],
    "name:srp_x_preferred":[
        "\u0428\u043e\u0458\u0435\u0440\u043d"
    ],
    "name:ukr_x_preferred":[
        "\u0428\u043e\u0454\u0440\u043d"
    ],
    "name:uzb_x_preferred":[
        "Scheuern"
    ],
    "name:vie_x_preferred":[
        "Scheuern"
    ],
    "name:vol_x_preferred":[
        "Scheuern"
    ],
    "name:war_x_preferred":[
        "Scheuern"
    ],
    "name:zho_x_preferred":[
        "\u7ecd\u4f0a\u5c14\u6069"
    ],
    "qs_pg:aaroncc":"DE",
    "qs_pg:gn_country":"DE",
    "qs_pg:gn_fcode":"PPLX",
    "qs_pg:gn_pop":60,
    "qs_pg:name":"Scheuern",
    "qs_pg:photos_9r":0,
    "qs_pg:photos_sr":0,
    "qs_pg:pop_sr":1,
    "qs_pg:qs_pg_placetype":"neighbourhood",
    "wof:name":"Scheuern",
    "wof:placetype":"neighbourhood",
    "wof:population":60
},
  "geometry": {"coordinates":[6.59308,50.26025],"type":"Point"}
}