{
  "type": "Feature",
  "properties": {
    "gn:admin1_code":"11",
    "gn:admin2_code":"0.0",
    "gn:admin3_code":"12071.0",
    "gn:admin4_code":"12071372.0",
    "gn:asciiname":"Roitz",
    "gn:country_code":"DE",
    "gn:dem":149,
    "gn:feature_class":"P",
    "gn:feature_code":"PPL",
    "gn:name":"Roitz",
    "gn:population":0,
    "gn:timezone":"Europe/Berlin",
    "iso:country":"DE",
    "wof:name":"Roitz",
    "wof:placetype":"neighbourhood"
},
  "geometry": {"coordinates":[14.31667,51.56667],"type":"Point"}
}