{
  "type": "Feature",
  "properties": {
    "gn:admin1_code":"15.0",
    "gn:admin2_code":"00",
    "gn:admin3_code":"16070.0",
    "gn:admin4_code":"16070053.0",
    "gn:asciiname":"Wipfra",
    "gn:country_code":"DE",
    "gn:dem":393,
    "gn:feature_class":"P",
    "gn:feature_code":"PPL",
    "gn:name":"Wipfra",
    "gn:population":0,
    "gn:timezone":"Europe/Berlin",
    "iso:country":"DE",
    "wof:name":"Wipfra",
    "wof:placetype":"neighbourhood"
},
  "geometry": {"coordinates":[10.96985,50.75605],"type":"Point"}
}