{
  "type": "Feature",
  "properties": {
    "gn:admin1_code":"1",
    "gn:admin2_code":"84.0",
    "gn:admin3_code":"8415.0",
    "gn:admin4_code":"8415061.0",
    "gn:asciiname":"Ohmenhausen",
    "gn:country_code":"DE",
    "gn:dem":410,
    "gn:feature_class":"P",
    "gn:feature_code":"PPL",
    "gn:name":"Ohmenhausen",
    "gn:population":0,
    "gn:timezone":"Europe/Berlin",
    "iso:country":"DE",
    "wof:name":"Ohmenhausen",
    "wof:placetype":"neighbourhood"
},
  "geometry": {"coordinates":[9.13998,48.47838],"type":"Point"}
}