{
  "type": "Feature",
  "properties": {
    "gn:admin1_code":"2",
    "gn:admin2_code":"96.0",
    "gn:admin3_code":"9674.0",
    "gn:admin4_code":"9674121.0",
    "gn:asciiname":"Hohnhausen",
    "gn:country_code":"DE",
    "gn:dem":333,
    "gn:feature_class":"P",
    "gn:feature_code":"PPL",
    "gn:name":"Hohnhausen",
    "gn:population":0,
    "gn:timezone":"Europe/Berlin",
    "iso:country":"DE",
    "wof:name":"Hohnhausen",
    "wof:placetype":"neighbourhood"
},
  "geometry": {"coordinates":[10.63118,50.1218],"type":"Point"}
}