{
  "type": "Feature",
  "properties": {
    "gn:admin1_code":"2",
    "gn:admin2_code":"94.0",
    "gn:admin3_code":"9472.0",
    "gn:admin4_code":"9472127.0",
    "gn:asciiname":"Schwurz",
    "gn:country_code":"DE",
    "gn:dem":501,
    "gn:feature_class":"P",
    "gn:feature_code":"PPL",
    "gn:name":"Schw\u00fcrz",
    "gn:population":0,
    "gn:timezone":"Europe/Berlin",
    "iso:country":"DE",
    "wof:name":"Schwurz",
    "wof:placetype":"neighbourhood"
},
  "geometry": {"coordinates":[11.5697,49.84172],"type":"Point"}
}