{
  "type": "Feature",
  "properties": {
    "gn:admin1_code":"2.0",
    "gn:admin2_code":"94.0",
    "gn:admin3_code":"9478.0",
    "gn:admin4_code":"9478165.0",
    "gn:asciiname":"Altenbanz",
    "gn:country_code":"DE",
    "gn:dem":331,
    "gn:feature_class":"P",
    "gn:feature_code":"PPL",
    "gn:name":"Altenbanz",
    "gn:population":0,
    "gn:timezone":"Europe/Berlin",
    "iso:country":"DE",
    "wof:name":"Altenbanz",
    "wof:placetype":"neighbourhood"
},
  "geometry": {"coordinates":[10.9634,50.15309],"type":"Point"}
}