{
  "type": "Feature",
  "properties": {
    "gn:admin1_code":"14",
    "gn:admin2_code":"0.0",
    "gn:admin3_code":"15088.0",
    "gn:admin4_code":"15088065.0",
    "gn:asciiname":"Rossbach",
    "gn:country_code":"DE",
    "gn:dem":124,
    "gn:feature_class":"P",
    "gn:feature_code":"PPL",
    "gn:name":"Ro\u00dfbach",
    "gn:population":0,
    "gn:timezone":"Europe/Berlin",
    "iso:country":"DE",
    "name:ceb_x_preferred":[
        "Rossbach"
    ],
    "name:kaz_x_preferred":[
        "\u0420\u043e\u0441\u0431\u0430\u0445"
    ],
    "name:kir_x_preferred":[
        "\u0420\u043e\u0441\u0431\u0430\u0445"
    ],
    "name:rus_x_preferred":[
        "\u0420\u043e\u0441\u0431\u0430\u0445"
    ],
    "name:srp_x_preferred":[
        "\u0420\u043e\u0441\u0431\u0430\u0445"
    ],
    "name:swe_x_preferred":[
        "Rossbach"
    ],
    "wof:name":"Rossbach",
    "wof:placetype":"neighbourhood"
},
  "geometry": {"coordinates":[11.89504,51.26037],"type":"Point"}
}