{
  "type": "Feature",
  "properties": {
    "gn:admin1_code":"6.0",
    "gn:admin2_code":"00",
    "gn:admin3_code":"3352.0",
    "gn:admin4_code":"3352032.0",
    "gn:asciiname":"Welle",
    "gn:country_code":"DE",
    "gn:dem":1,
    "gn:feature_class":"P",
    "gn:feature_code":"PPL",
    "gn:name":"Welle",
    "gn:population":0,
    "gn:timezone":"Europe/Berlin",
    "iso:country":"DE",
    "name:ceb_x_preferred":[
        "Welle"
    ],
    "name:deu_x_preferred":[
        "Welle"
    ],
    "name:eus_x_preferred":[
        "Welle"
    ],
    "name:fra_x_preferred":[
        "Welle"
    ],
    "name:ita_x_preferred":[
        "Welle"
    ],
    "name:nld_x_preferred":[
        "Welle"
    ],
    "name:pol_x_preferred":[
        "Welle"
    ],
    "name:swe_x_preferred":[
        "Welle"
    ],
    "wof:name":"Welle",
    "wof:placetype":"neighbourhood"
},
  "geometry": {"coordinates":[8.59929,53.47748000000001],"type":"Point"}
}