{
  "type": "Feature",
  "properties": {
    "gn:admin1_code":"15",
    "gn:admin2_code":"0.0",
    "gn:admin3_code":"16074.0",
    "gn:admin4_code":"16074076.0",
    "gn:asciiname":"Geunitz",
    "gn:country_code":"DE",
    "gn:dem":279,
    "gn:feature_class":"P",
    "gn:feature_code":"PPL",
    "gn:name":"Geunitz",
    "gn:population":0,
    "gn:timezone":"Europe/Berlin",
    "iso:country":"DE",
    "wof:name":"Geunitz",
    "wof:placetype":"neighbourhood"
},
  "geometry": {"coordinates":[11.45891,50.80968],"type":"Point"}
}