{
  "type": "Feature",
  "properties": {
    "gn:admin1_code":"7",
    "gn:admin2_code":"53.0",
    "gn:admin3_code":"5382.0",
    "gn:admin4_code":"5382036.0",
    "gn:asciiname":"Kreuzkapelle",
    "gn:country_code":"DE",
    "gn:dem":214,
    "gn:feature_class":"P",
    "gn:feature_code":"PPL",
    "gn:name":"Kreuzkapelle",
    "gn:population":0,
    "gn:timezone":"Europe/Berlin",
    "iso:country":"DE",
    "wof:name":"Kreuzkapelle",
    "wof:placetype":"neighbourhood"
},
  "geometry": {"coordinates":[7.3895,50.88187],"type":"Point"}
}