{
  "type": "Feature",
  "properties": {
    "gn:admin1_code":"8",
    "gn:admin2_code":"0.0",
    "gn:admin3_code":"7233.0",
    "gn:admin4_code":"7233029.0",
    "gn:asciiname":"Niederbettingen",
    "gn:country_code":"DE",
    "gn:dem":386,
    "gn:feature_class":"P",
    "gn:feature_code":"PPL",
    "gn:name":"Niederbettingen",
    "gn:population":0,
    "gn:timezone":"Europe/Berlin",
    "iso:country":"DE",
    "wof:name":"Niederbettingen",
    "wof:placetype":"neighbourhood"
},
  "geometry": {"coordinates":[6.64438,50.26913],"type":"Point"}
}