{
  "type": "Feature",
  "properties": {
    "gn:admin1_code":"7.0",
    "gn:admin2_code":"51.0",
    "gn:admin3_code":"5166.0",
    "gn:admin4_code":"5166020.0",
    "gn:asciiname":"Boscherhausen",
    "gn:country_code":"DE",
    "gn:dem":69,
    "gn:feature_class":"P",
    "gn:feature_code":"PPL",
    "gn:name":"Boscherhausen",
    "gn:population":0,
    "gn:timezone":"Europe/Berlin",
    "iso:country":"DE",
    "wof:name":"Boscherhausen",
    "wof:placetype":"neighbourhood"
},
  "geometry": {"coordinates":[6.19192,51.20359000000001],"type":"Point"}
}