{
  "type": "Feature",
  "properties": {
    "gn:admin1_code":"13",
    "gn:admin2_code":"0.0",
    "gn:admin3_code":"14625.0",
    "gn:admin4_code":"14625200.0",
    "gn:asciiname":"Gemeindebusch",
    "gn:country_code":"DE",
    "gn:dem":305,
    "gn:feature_class":"P",
    "gn:feature_code":"PPL",
    "gn:name":"Gemeindebusch",
    "gn:population":0,
    "gn:timezone":"Europe/Berlin",
    "iso:country":"DE",
    "wof:name":"Gemeindebusch",
    "wof:placetype":"neighbourhood"
},
  "geometry": {"coordinates":[14.04455,51.15751],"type":"Point"}
}