{
  "type": "Feature",
  "properties": {
    "gn:admin1_code":"2",
    "gn:admin2_code":"93.0",
    "gn:admin3_code":"9371.0",
    "gn:admin4_code":"9371136.0",
    "gn:asciiname":"Garmersdorf",
    "gn:country_code":"DE",
    "gn:dem":382,
    "gn:feature_class":"P",
    "gn:feature_code":"PPL",
    "gn:name":"G\u00e4rmersdorf",
    "gn:population":0,
    "gn:timezone":"Europe/Berlin",
    "iso:country":"DE",
    "wof:name":"Garmersdorf",
    "wof:placetype":"neighbourhood"
},
  "geometry": {"coordinates":[11.89797,49.4332],"type":"Point"}
}