{
  "type": "Feature",
  "properties": {
    "gn:admin1_code":"6",
    "gn:admin2_code":"0.0",
    "gn:admin3_code":"3354.0",
    "gn:admin4_code":"3354013.0",
    "gn:asciiname":"Seerau im Drawehn",
    "gn:country_code":"DE",
    "gn:dem":20,
    "gn:feature_class":"P",
    "gn:feature_code":"PPL",
    "gn:name":"Seerau im Drawehn",
    "gn:population":0,
    "gn:timezone":"Europe/Berlin",
    "iso:country":"DE",
    "wof:name":"Seerau im Drawehn",
    "wof:placetype":"neighbourhood"
},
  "geometry": {"coordinates":[11.06667,52.96666999999999],"type":"Point"}
}