{
  "type": "Feature",
  "properties": {
    "gn:admin1_code":"2",
    "gn:admin2_code":"92.0",
    "gn:admin3_code":"9278.0",
    "gn:admin4_code":"9278178.0",
    "gn:asciiname":"Wassesbuhl",
    "gn:country_code":"DE",
    "gn:dem":566,
    "gn:feature_class":"P",
    "gn:feature_code":"PPL",
    "gn:name":"Wassesb\u00fchl",
    "gn:population":0,
    "gn:timezone":"Europe/Berlin",
    "iso:country":"DE",
    "wof:name":"Wassesbuhl",
    "wof:placetype":"neighbourhood"
},
  "geometry": {"coordinates":[12.76606,49.06653],"type":"Point"}
}