{
  "type": "Feature",
  "properties": {
    "gn:admin1_code":"10",
    "gn:admin2_code":"0.0",
    "gn:admin3_code":"1055.0",
    "gn:admin4_code":"1055035.0",
    "gn:asciiname":"Alttechau",
    "gn:cc2":"DE",
    "gn:country_code":"DE",
    "gn:dem":13,
    "gn:feature_class":"P",
    "gn:feature_code":"PPL",
    "gn:name":"Alttechau",
    "gn:population":0,
    "gn:timezone":"Europe/Berlin",
    "iso:country":"DE",
    "name:und_x_variant":[
        "Techau",
        "Alttechau"
    ],
    "wof:name":"Alttechau",
    "wof:placetype":"neighbourhood"
},
  "geometry": {"coordinates":[10.70171,53.97252],"type":"Point"}
}