{
  "type": "Feature",
  "properties": {
    "gn:admin1_code":"13",
    "gn:admin2_code":"0.0",
    "gn:admin3_code":"14625.0",
    "gn:admin4_code":"14625150.0",
    "gn:asciiname":"Storcha",
    "gn:country_code":"DE",
    "gn:dem":204,
    "gn:feature_class":"P",
    "gn:feature_code":"PPL",
    "gn:name":"Storcha",
    "gn:population":0,
    "gn:timezone":"Europe/Berlin",
    "iso:country":"DE",
    "name:hsb_x_preferred":[
        "Ba\u0107o\u0144"
    ],
    "wof:name":"Storcha",
    "wof:placetype":"neighbourhood"
},
  "geometry": {"coordinates":[14.30062,51.22315],"type":"Point"}
}