{
  "type": "Feature",
  "properties": {
    "gn:admin1_code":"14",
    "gn:admin2_code":"0.0",
    "gn:admin3_code":"15088.0",
    "gn:admin4_code":"15088330.0",
    "gn:asciiname":"Rattmannsdorf",
    "gn:country_code":"DE",
    "gn:dem":82,
    "gn:feature_class":"P",
    "gn:feature_code":"PPL",
    "gn:name":"Rattmannsdorf",
    "gn:population":0,
    "gn:timezone":"Europe/Berlin",
    "iso:country":"DE",
    "wof:name":"Rattmannsdorf",
    "wof:placetype":"neighbourhood"
},
  "geometry": {"coordinates":[11.94822,51.41287],"type":"Point"}
}