{
  "type": "Feature",
  "properties": {
    "gn:admin1_code":"14",
    "gn:admin2_code":"0.0",
    "gn:admin3_code":"15086.0",
    "gn:admin4_code":"15086015.0",
    "gn:asciiname":"Niegripp",
    "gn:country_code":"DE",
    "gn:dem":41,
    "gn:feature_class":"P",
    "gn:feature_code":"PPL",
    "gn:name":"Niegripp",
    "gn:population":0,
    "gn:timezone":"Europe/Berlin",
    "iso:country":"DE",
    "wof:name":"Niegripp",
    "wof:placetype":"neighbourhood"
},
  "geometry": {"coordinates":[11.75865,52.26315],"type":"Point"}
}