{
  "type": "Feature",
  "properties": {
    "gn:admin1_code":"14",
    "gn:admin2_code":"0.0",
    "gn:admin3_code":"15082.0",
    "gn:admin4_code":"15082430.0",
    "gn:asciiname":"Pulspforde",
    "gn:country_code":"DE",
    "gn:dem":74,
    "gn:feature_class":"P",
    "gn:feature_code":"PPL",
    "gn:name":"Pulspforde",
    "gn:population":0,
    "gn:timezone":"Europe/Berlin",
    "iso:country":"DE",
    "wof:name":"Pulspforde",
    "wof:placetype":"neighbourhood"
},
  "geometry": {"coordinates":[12.13807,51.9772],"type":"Point"}
}