{
  "type": "Feature",
  "properties": {
    "gn:admin1_code":"14",
    "gn:admin2_code":"0.0",
    "gn:admin3_code":"15090.0",
    "gn:admin4_code":"15090415.0",
    "gn:asciiname":"Schliecksdorf",
    "gn:country_code":"DE",
    "gn:dem":27,
    "gn:feature_class":"P",
    "gn:feature_code":"PPL",
    "gn:name":"Schliecksdorf",
    "gn:population":0,
    "gn:timezone":"Europe/Berlin",
    "iso:country":"DE",
    "wof:name":"Schliecksdorf",
    "wof:placetype":"neighbourhood"
},
  "geometry": {"coordinates":[11.68205,52.79476],"type":"Point"}
}