{
  "type": "Feature",
  "properties": {
    "gn:admin1_code":"1",
    "gn:admin2_code":"83.0",
    "gn:admin3_code":"8317.0",
    "gn:admin4_code":"8317097.0",
    "gn:asciiname":"Buchen",
    "gn:country_code":"DE",
    "gn:dem":204,
    "gn:feature_class":"P",
    "gn:feature_code":"PPL",
    "gn:name":"B\u00fcchen",
    "gn:population":0,
    "gn:timezone":"Europe/Berlin",
    "iso:country":"DE",
    "wof:name":"Buchen",
    "wof:placetype":"neighbourhood"
},
  "geometry": {"coordinates":[7.98921,48.44048],"type":"Point"}
}