{
  "type": "Feature",
  "properties": {
    "gn:gn_country":"DE",
    "gn:gn_fcode":"PPLA4",
    "gn:gn_pop":224,
    "gn:population":224,
    "iso:country":"DE",
    "name:baq_x_preferred":[
        "Helmeroth"
    ],
    "name:chi_x_preferred":[
        "\u9ed1\u5c14\u6885\u7f57\u7279"
    ],
    "name:dut_x_preferred":[
        "Helmeroth"
    ],
    "name:eng_x_preferred":[
        "Helmeroth"
    ],
    "name:epo_x_preferred":[
        "Helmeroth"
    ],
    "name:fre_x_preferred":[
        "Helmeroth"
    ],
    "name:ger_x_preferred":[
        "Helmeroth"
    ],
    "name:hun_x_preferred":[
        "Helmeroth"
    ],
    "name:ita_x_preferred":[
        "Helmeroth"
    ],
    "name:jpn_x_preferred":[
        "\u30d8\u30eb\u30e1\u30ed\u30fc\u30c8"
    ],
    "name:kaz_x_preferred":[
        "\u0425\u0435\u043b\u044c\u043c\u0435\u0440\u043e\u0442"
    ],
    "name:kir_x_preferred":[
        "\u0425\u0435\u043b\u044c\u043c\u0435\u0440\u043e\u0442"
    ],
    "name:may_x_preferred":[
        "Helmeroth"
    ],
    "name:per_x_preferred":[
        "\u0647\u06cc\u0644\u0645\u0631\u0627\u062a"
    ],
    "name:pol_x_preferred":[
        "Helmeroth"
    ],
    "name:por_x_preferred":[
        "Helmeroth"
    ],
    "name:rum_x_preferred":[
        "Helmeroth"
    ],
    "name:rus_x_preferred":[
        "\u0425\u0435\u043b\u044c\u043c\u0435\u0440\u043e\u0442"
    ],
    "name:srp_x_preferred":[
        "\u0425\u0435\u043b\u043c\u0435\u0440\u043e\u0442"
    ],
    "name:ukr_x_preferred":[
        "\u0413\u0435\u043b\u044c\u043c\u0435\u0440\u043e\u0442"
    ],
    "name:uzb_x_preferred":[
        "Helmeroth"
    ],
    "name:vie_x_preferred":[
        "Helmeroth"
    ],
    "name:vol_x_preferred":[
        "Helmeroth"
    ],
    "name:war_x_preferred":[
        "Helmeroth"
    ],
    "qs_pg:aaroncc":"DE",
    "qs_pg:gn_country":"DE",
    "qs_pg:gn_fcode":"PPLA4",
    "qs_pg:gn_pop":224,
    "qs_pg:name":"Helmeroth",
    "qs_pg:photos_9r":0,
    "qs_pg:photos_sr":0,
    "qs_pg:pop_sr":2,
    "qs_pg:qs_pg_placetype":"locality",
    "wof:name":"Helmeroth",
    "wof:placetype":"locality",
    "wof:population":224
},
  "geometry": {"coordinates":[7.73333,50.73333],"type":"Point"}
}