{
  "type": "Feature",
  "properties": {
    "gn:admin1_code":"6",
    "gn:admin2_code":"0.0",
    "gn:admin3_code":"3355.0",
    "gn:admin4_code":"3355009.0",
    "gn:asciiname":"Reesseln",
    "gn:country_code":"DE",
    "gn:dem":44,
    "gn:feature_class":"P",
    "gn:feature_code":"PPL",
    "gn:name":"Reesseln",
    "gn:population":0,
    "gn:timezone":"Europe/Berlin",
    "iso:country":"DE",
    "wof:name":"Reesseln",
    "wof:placetype":"neighbourhood"
},
  "geometry": {"coordinates":[10.85451,53.22789],"type":"Point"}
}