{
  "type": "Feature",
  "properties": {
    "iso:country":"DE",
    "name:deu_x_preferred":[
        "Gartenstadt Reitzenstein"
    ],
    "name:deu_x_variant":[
        "Reika",
        "Reitzenstein"
    ],
    "wof:name":"Reitzenstein",
    "wof:placetype":"neighbourhood"
},
  "geometry": {"coordinates":[6.81729732626699,51.24442272029504],"type":"Point"}
}