{
  "type": "Feature",
  "properties": {
    "gn:admin1_code":"6.0",
    "gn:admin2_code":"00",
    "gn:admin3_code":"3254.0",
    "gn:admin4_code":"3254014.0",
    "gn:asciiname":"Wittenburg",
    "gn:country_code":"DE",
    "gn:dem":111,
    "gn:feature_class":"P",
    "gn:feature_code":"PPL",
    "gn:name":"Wittenburg",
    "gn:population":0,
    "gn:timezone":"Europe/Berlin",
    "iso:country":"DE",
    "name:ara_x_preferred":[
        "\u0641\u064a\u062a\u0646\u0628\u0648\u0631\u063a"
    ],
    "name:azb_x_preferred":[
        "\u0648\u06cc\u062a\u0646\u0628\u0648\u0631\u0642"
    ],
    "name:ceb_x_preferred":[
        "Wittenburg"
    ],
    "name:deu_x_preferred":[
        "Wittenburg"
    ],
    "name:epo_x_preferred":[
        "Wittenburg"
    ],
    "name:fas_x_preferred":[
        "\u0648\u06cc\u062a\u0646\u0628\u0648\u0631\u06af"
    ],
    "name:fra_x_preferred":[
        "Wittenburg"
    ],
    "name:hun_x_preferred":[
        "Wittenburg"
    ],
    "name:ind_x_preferred":[
        "Wittenburg"
    ],
    "name:ita_x_preferred":[
        "Wittenburg"
    ],
    "name:kaz_x_preferred":[
        "\u0412\u0438\u0442\u0442\u0435\u043d\u0431\u0443\u0440\u0433"
    ],
    "name:kir_x_preferred":[
        "\u0412\u0438\u0442\u0442\u0435\u043d\u0431\u0443\u0440\u0433"
    ],
    "name:lav_x_preferred":[
        "Vitenburga"
    ],
    "name:mkd_x_preferred":[
        "\u0412\u0438\u0442\u0435\u043d\u0431\u0443\u0440\u0433"
    ],
    "name:msa_x_preferred":[
        "Wittenburg"
    ],
    "name:nld_x_preferred":[
        "Wittenburg"
    ],
    "name:nor_x_preferred":[
        "Wittenburg"
    ],
    "name:pol_x_preferred":[
        "Wittenburg"
    ],
    "name:por_x_preferred":[
        "Wittenburg"
    ],
    "name:ron_x_preferred":[
        "Wittenburg"
    ],
    "name:rus_x_preferred":[
        "\u0412\u0438\u0442\u0442\u0435\u043d\u0431\u0443\u0440\u0433"
    ],
    "name:spa_x_preferred":[
        "Wittenburg"
    ],
    "name:srp_x_preferred":[
        "\u0412\u0438\u0442\u0435\u043d\u0431\u0443\u0440\u0433"
    ],
    "name:swe_x_preferred":[
        "Wittenburg"
    ],
    "name:tur_x_preferred":[
        "Wittenburg"
    ],
    "name:ukr_x_preferred":[
        "\u0412\u0456\u0442\u0442\u0435\u043d\u0431\u0443\u0440\u0433"
    ],
    "name:uzb_x_preferred":[
        "Wittenburg"
    ],
    "name:vie_x_preferred":[
        "Wittenburg"
    ],
    "name:vol_x_preferred":[
        "Wittenburg"
    ],
    "name:war_x_preferred":[
        "Wittenburg"
    ],
    "name:zho_x_preferred":[
        "\u7ef4\u6ed5\u5821"
    ],
    "wof:name":"Wittenburg",
    "wof:placetype":"neighbourhood"
},
  "geometry": {"coordinates":[9.70318,52.14039],"type":"Point"}
}