{
  "type": "Feature",
  "properties": {
    "gn:admin1_code":"7.0",
    "gn:admin2_code":"053",
    "gn:admin3_code":"5374.0",
    "gn:admin4_code":"5374040.0",
    "gn:asciiname":"Wildberg",
    "gn:country_code":"DE",
    "gn:dem":404,
    "gn:feature_class":"P",
    "gn:feature_code":"PPL",
    "gn:name":"Wildberg",
    "gn:population":0,
    "gn:timezone":"Europe/Berlin",
    "iso:country":"DE",
    "name:als_x_preferred":[
        "Wildberg"
    ],
    "name:ceb_x_preferred":[
        "Wildberg"
    ],
    "name:deu_x_preferred":[
        "Wildberg"
    ],
    "name:epo_x_preferred":[
        "Wildberg"
    ],
    "name:eus_x_preferred":[
        "Wildberg"
    ],
    "name:fra_x_preferred":[
        "Wildberg"
    ],
    "name:ita_x_preferred":[
        "Wildberg"
    ],
    "name:lmo_x_preferred":[
        "Wildberg"
    ],
    "name:mkd_x_preferred":[
        "\u0412\u0438\u043b\u0434\u0431\u0435\u0440\u0433"
    ],
    "name:nld_x_preferred":[
        "Wildberg"
    ],
    "name:pol_x_preferred":[
        "Wildberg"
    ],
    "name:por_x_preferred":[
        "Wildberg"
    ],
    "name:rus_x_preferred":[
        "\u0412\u0438\u043b\u044c\u0434\u0431\u0435\u0440\u0433"
    ],
    "name:srp_x_preferred":[
        "\u0412\u0438\u043b\u0434\u0431\u0435\u0440\u0433"
    ],
    "name:swe_x_preferred":[
        "Wildberg"
    ],
    "name:vol_x_preferred":[
        "Wildberg"
    ],
    "wof:name":"Wildberg",
    "wof:placetype":"neighbourhood"
},
  "geometry": {"coordinates":[7.76747,50.93187],"type":"Point"}
}