{
  "type": "Feature",
  "properties": {
    "iso:country":"DE",
    "name:deu_x_preferred":[
        "Emst-Bissingheim"
    ],
    "name:eng_x_preferred":[
        "Bissingheim"
    ],
    "name:eng_x_variant":[
        "Bissingheim"
    ],
    "qs:gn_fcode":"PPLX",
    "qs:gn_local":0,
    "qs:gn_namadm1":"07",
    "qs:gn_name":"Emst-Bissingheim",
    "qs:local_max":1328,
    "qs:local_sum":3650,
    "qs:localhoods":22,
    "qs:name":"Emst-Bissingheim",
    "qs:name_adm0":"Deutschland",
    "qs:name_adm1":"Nordrhein-Westfalen",
    "qs:name_adm2":"Stadtkreis Hagen",
    "qs:name_en":"Bissingheim",
    "qs:name_lau":"Hagen-Mitte",
    "qs:name_local":"Hagen",
    "qs:photo_max":192,
    "qs:photo_sum":337,
    "qs:placetype":"Suburb",
    "qs:quad_count":10,
    "qs:woe_adm0":23424829,
    "qs:woe_adm1":2345487,
    "qs:woe_adm2":12596856,
    "qs:woe_lau":26822479,
    "qs:woe_local":656385,
    "qs:woe_ver":"7.10.0",
    "wof:lang":[
        "ger"
    ],
    "wof:name":"Emst-Bissingheim",
    "wof:placetype":"neighbourhood"
},
  "geometry": {"coordinates":[7.504661,51.361949],"type":"Point"}
}