{
  "type": "Feature",
  "properties": {
    "gn:admin1_code":"6",
    "gn:admin2_code":"0.0",
    "gn:admin3_code":"3354.0",
    "gn:admin4_code":"3354027.0",
    "gn:asciiname":"Fliessau",
    "gn:country_code":"DE",
    "gn:dem":69,
    "gn:feature_class":"P",
    "gn:feature_code":"PPL",
    "gn:name":"Flie\u00dfau",
    "gn:population":0,
    "gn:timezone":"Europe/Berlin",
    "iso:country":"DE",
    "wof:name":"Fliessau",
    "wof:placetype":"neighbourhood"
},
  "geometry": {"coordinates":[10.94603,53.06008000000001],"type":"Point"}
}