{
  "type": "Feature",
  "properties": {
    "gn:admin1_code":"7.0",
    "gn:admin2_code":"51.0",
    "gn:admin3_code":"5154.0",
    "gn:admin4_code":"5154024.0",
    "gn:asciiname":"Appeldorn",
    "gn:country_code":"DE",
    "gn:dem":19,
    "gn:feature_class":"P",
    "gn:feature_code":"PPL",
    "gn:name":"Appeldorn",
    "gn:population":0,
    "gn:timezone":"Europe/Berlin",
    "iso:country":"DE",
    "wof:name":"Appeldorn",
    "wof:placetype":"neighbourhood"
},
  "geometry": {"coordinates":[6.34905,51.72317],"type":"Point"}
}