{
  "type": "Feature",
  "properties": {
    "gn:admin1_code":"13",
    "gn:admin2_code":"0.0",
    "gn:admin3_code":"14522.0",
    "gn:admin4_code":"14522350.0",
    "gn:asciiname":"Oberelsdorf",
    "gn:country_code":"DE",
    "gn:dem":241,
    "gn:feature_class":"P",
    "gn:feature_code":"PPL",
    "gn:name":"Oberelsdorf",
    "gn:population":0,
    "gn:timezone":"Europe/Berlin",
    "iso:country":"DE",
    "wof:name":"Oberelsdorf",
    "wof:placetype":"neighbourhood"
},
  "geometry": {"coordinates":[12.70803,50.97211],"type":"Point"}
}