{
  "type": "Feature",
  "properties": {
    "gn:admin1_code":"13.0",
    "gn:admin2_code":"00",
    "gn:admin3_code":"14625.0",
    "gn:admin4_code":"14625420.0",
    "gn:asciiname":"Weissig",
    "gn:country_code":"DE",
    "gn:dem":157,
    "gn:feature_class":"P",
    "gn:feature_code":"PPL",
    "gn:name":"Wei\u00dfig",
    "gn:population":0,
    "gn:timezone":"Europe/Berlin",
    "iso:country":"DE",
    "name:hsb_x_preferred":[
        "Wysoka"
    ],
    "name:und_x_variant":[
        "Wei\u00dfig"
    ],
    "wof:name":"Weissig",
    "wof:placetype":"neighbourhood"
},
  "geometry": {"coordinates":[14.1211,51.34932],"type":"Point"}
}