{
  "type": "Feature",
  "properties": {
    "gn:admin1_code":"5",
    "gn:admin2_code":"64.0",
    "gn:admin3_code":"6437.0",
    "gn:admin4_code":"6437012.0",
    "gn:asciiname":"Unter-Mossau",
    "gn:country_code":"DE",
    "gn:dem":311,
    "gn:feature_class":"P",
    "gn:feature_code":"PPL",
    "gn:name":"Unter-Mossau",
    "gn:population":0,
    "gn:timezone":"Europe/Berlin",
    "iso:country":"DE",
    "wof:name":"Unter-Mossau",
    "wof:placetype":"neighbourhood"
},
  "geometry": {"coordinates":[8.93064,49.64866],"type":"Point"}
}