{
  "type": "Feature",
  "properties": {
    "gn:admin1_code":"12",
    "gn:admin2_code":"0.0",
    "gn:admin3_code":"13071.0",
    "gn:admin4_code":"13071063.0",
    "gn:asciiname":"Cramon",
    "gn:country_code":"DE",
    "gn:dem":63,
    "gn:feature_class":"P",
    "gn:feature_code":"PPL",
    "gn:name":"Cramon",
    "gn:population":0,
    "gn:timezone":"Europe/Berlin",
    "iso:country":"DE",
    "wof:name":"Cramon",
    "wof:placetype":"neighbourhood"
},
  "geometry": {"coordinates":[12.45678,53.60865],"type":"Point"}
}