{
  "type": "Feature",
  "properties": {
    "iso:country":"DE",
    "name:ara_x_preferred":[
        "\u0622\u0644\u0633\u0641\u0644\u062f"
    ],
    "name:azb_x_preferred":[
        "\u0622\u0644\u0633\u0641\u0644\u062f"
    ],
    "name:aze_x_preferred":[
        "Alsfeld"
    ],
    "name:bel_x_preferred":[
        "\u0410\u043b\u044c\u0441\u0444\u0435\u043b\u044c\u0434"
    ],
    "name:ceb_x_preferred":[
        "Alsfeld"
    ],
    "name:deu_x_preferred":[
        "Alsfeld"
    ],
    "name:ell_x_preferred":[
        "\u0386\u03bb\u03c3\u03c6\u03b5\u03bb\u03c4"
    ],
    "name:epo_x_preferred":[
        "Alsfeld"
    ],
    "name:fas_x_preferred":[
        "\u0622\u0644\u0633\u0641\u0644\u062f"
    ],
    "name:fra_x_preferred":[
        "Alsfeld"
    ],
    "name:hun_x_preferred":[
        "Alsfeld"
    ],
    "name:ita_x_preferred":[
        "Alsfeld"
    ],
    "name:jpn_x_preferred":[
        "\u30a2\u30eb\u30b9\u30d5\u30a7\u30eb\u30c8"
    ],
    "name:kaz_x_preferred":[
        "\u0410\u043b\u044c\u0441\u0444\u0435\u043b\u044c\u0434"
    ],
    "name:kir_x_preferred":[
        "\u0410\u043b\u044c\u0441\u0444\u0435\u043b\u044c\u0434"
    ],
    "name:msa_x_preferred":[
        "Alsfeld"
    ],
    "name:nld_x_preferred":[
        "Alsfeld"
    ],
    "name:pol_x_preferred":[
        "Alsfeld"
    ],
    "name:por_x_preferred":[
        "Alsfeld"
    ],
    "name:ron_x_preferred":[
        "Alsfeld"
    ],
    "name:rus_x_preferred":[
        "\u0410\u043b\u044c\u0441\u0444\u0435\u043b\u044c\u0434"
    ],
    "name:spa_x_preferred":[
        "Alsfeld"
    ],
    "name:srp_x_preferred":[
        "\u0410\u043b\u0441\u0444\u0435\u043b\u0434"
    ],
    "name:swa_x_preferred":[
        "Alsfeld"
    ],
    "name:tur_x_preferred":[
        "Alsfeld"
    ],
    "name:ukr_x_preferred":[
        "\u0410\u043b\u044c\u0441\u0444\u0435\u043b\u044c\u0434"
    ],
    "name:uzb_x_preferred":[
        "Alsfeld"
    ],
    "name:vol_x_preferred":[
        "Alsfeld"
    ],
    "name:war_x_preferred":[
        "Alsfeld"
    ],
    "name:zho_x_preferred":[
        "\u963f\u5c14\u65af\u8d39\u5c14\u5fb7"
    ],
    "wof:name":"Alsfeld",
    "wof:placetype":"neighbourhood"
},
  "geometry": {"coordinates":[6.84228154937152,51.52944544319024],"type":"Point"}
}