{
  "type": "Feature",
  "properties": {
    "iso:country":"DE",
    "wof:name":"Alsfeld",
    "wof:placetype":"neighbourhood"
},
  "geometry": {"coordinates":[6.84228154937152,51.52944544319024],"type":"Point"}
}