{
  "type": "Feature",
  "properties": {
    "gn:admin1_code":"2",
    "gn:admin2_code":"96.0",
    "gn:admin3_code":"9673.0",
    "gn:admin4_code":"9673114.0",
    "gn:asciiname":"Lohrieth",
    "gn:country_code":"DE",
    "gn:dem":289,
    "gn:feature_class":"P",
    "gn:feature_code":"PPL",
    "gn:name":"L\u00f6hrieth",
    "gn:population":0,
    "gn:timezone":"Europe/Berlin",
    "iso:country":"DE",
    "wof:name":"Lohrieth",
    "wof:placetype":"neighbourhood"
},
  "geometry": {"coordinates":[10.24844,50.29923],"type":"Point"}
}