{
  "type": "Feature",
  "properties": {
    "iso:country":"DE",
    "name:deu_x_colloquial":[
        "Kleingruendlach",
        "Kleingrundlach"
    ],
    "name:deu_x_preferred":[
        "Kleingr\u00fcndlach"
    ],
    "name:eng_x_preferred":[
        "Kleingr\u00fcndlach"
    ],
    "qs:gn_adm0_cc":"DE",
    "qs:gn_fcode":"PPL",
    "qs:gn_local":2861650,
    "qs:gn_nam_loc":"nurnberg",
    "qs:gn_namadm1":"02",
    "qs:gn_name":"Kleingr\u00fcndlach",
    "qs:local_max":6346,
    "qs:local_sum":25338,
    "qs:localhoods":37,
    "qs:name":"Kleingr\u00fcndlach",
    "qs:name_adm0":"Deutschland",
    "qs:name_adm1":"Bayern",
    "qs:name_adm2":"Stadtkreis N\u00fcrnberg",
    "qs:name_lau":"Stadtteil Nordwestliche Au\u00dfenstadt",
    "qs:name_local":"N\u00fcrnberg",
    "qs:photo_max":6,
    "qs:photo_sum":14,
    "qs:placetype":"Suburb",
    "qs:quad_count":6,
    "qs:woe_adm0":23424829,
    "qs:woe_adm1":2345482,
    "qs:woe_adm2":12596973,
    "qs:woe_lau":26823119,
    "qs:woe_local":680564,
    "qs:woe_ver":"7.10.0",
    "wof:lang":[
        "ger"
    ],
    "wof:name":"Kleingruendlach",
    "wof:placetype":"neighbourhood"
},
  "geometry": {"coordinates":[10.995667,49.536856],"type":"Point"}
}