{
  "type": "Feature",
  "properties": {
    "gn:admin1_code":"2",
    "gn:admin2_code":"91.0",
    "gn:admin3_code":"9181.0",
    "gn:admin4_code":"9181122.0",
    "gn:asciiname":"Petzenhofen",
    "gn:country_code":"DE",
    "gn:dem":585,
    "gn:feature_class":"P",
    "gn:feature_code":"PPL",
    "gn:name":"Petzenhofen",
    "gn:population":0,
    "gn:timezone":"Europe/Berlin",
    "iso:country":"DE",
    "wof:name":"Petzenhofen",
    "wof:placetype":"neighbourhood"
},
  "geometry": {"coordinates":[11.00066,48.15159],"type":"Point"}
}