{
  "type": "Feature",
  "properties": {
    "iso:country":"DE",
    "name:deu_x_preferred":[
        "S\u00fcndersb\u00fchl"
    ],
    "wof:name":"Suendersbuehl",
    "wof:placetype":"neighbourhood"
},
  "geometry": {"coordinates":[11.04116246587934,49.44149803880678],"type":"Point"}
}