{
  "type": "Feature",
  "properties": {
    "gn:admin1_code":"8",
    "gn:admin2_code":"0.0",
    "gn:admin3_code":"7340.0",
    "gn:admin4_code":"7340206.0",
    "gn:asciiname":"Offweilerhof",
    "gn:country_code":"DE",
    "gn:dem":305,
    "gn:feature_class":"P",
    "gn:feature_code":"PPL",
    "gn:name":"Offweilerhof",
    "gn:population":0,
    "gn:timezone":"Europe/Berlin",
    "iso:country":"DE",
    "wof:name":"Offweilerhof",
    "wof:placetype":"neighbourhood"
},
  "geometry": {"coordinates":[7.43299,49.22302],"type":"Point"}
}