{
  "type": "Feature",
  "properties": {
    "gn:admin1_code":"13",
    "gn:admin2_code":"0.0",
    "gn:admin3_code":"14612.0",
    "gn:admin4_code":"14612000.0",
    "gn:asciiname":"Schoenfeld",
    "gn:country_code":"DE",
    "gn:dem":294,
    "gn:feature_class":"P",
    "gn:feature_code":"PPL",
    "gn:name":"Sch\u00f6nfeld",
    "gn:population":0,
    "gn:timezone":"Europe/Berlin",
    "iso:country":"DE",
    "name:ceb_x_preferred":[
        "Schoenfeld"
    ],
    "name:deu_x_preferred":[
        "Sch\u00f6nfeld"
    ],
    "name:fra_x_preferred":[
        "Schoenfeld"
    ],
    "name:nld_x_preferred":[
        "Schoenfeld"
    ],
    "name:swe_x_preferred":[
        "Schoenfeld"
    ],
    "name:ukr_x_preferred":[
        "\u0428\u0435\u043d\u0444\u0435\u043b\u044c\u0434"
    ],
    "wof:name":"Schoenfeld",
    "wof:placetype":"neighbourhood"
},
  "geometry": {"coordinates":[13.894418,51.034737],"type":"Point"}
}