{
  "type": "Feature",
  "properties": {
    "iso:country":"DE",
    "name:deu_x_preferred":[
        "Sch\u00f6nfeld"
    ],
    "wof:name":"Schoenfeld",
    "wof:placetype":"neighbourhood"
},
  "geometry": {"coordinates":[13.89441806326127,51.03473736187954],"type":"Point"}
}