{
  "type": "Feature",
  "properties": {
    "gn:admin1_code":"13",
    "gn:admin2_code":"0.0",
    "gn:admin3_code":"14730.0",
    "gn:admin4_code":"14730010.0",
    "gn:asciiname":"Koetten",
    "gn:country_code":"DE",
    "gn:dem":87,
    "gn:feature_class":"P",
    "gn:feature_code":"PPL",
    "gn:name":"K\u00f6tten",
    "gn:population":0,
    "gn:timezone":"Europe/Berlin",
    "iso:country":"DE",
    "name:und_x_variant":[
        "Blumberg-K\u00f6tten",
        "K\u00f6tten"
    ],
    "wof:name":"Koetten",
    "wof:placetype":"neighbourhood"
},
  "geometry": {"coordinates":[13.17005,51.54202],"type":"Point"}
}