{
  "type": "Feature",
  "properties": {
    "gn:admin1_code":"11",
    "gn:admin2_code":"0.0",
    "gn:admin3_code":"12071.0",
    "gn:admin4_code":"12071294.0",
    "gn:asciiname":"Klein Koelzig",
    "gn:country_code":"DE",
    "gn:dem":108,
    "gn:feature_class":"P",
    "gn:feature_code":"PPL",
    "gn:name":"Klein K\u00f6lzig",
    "gn:population":0,
    "gn:timezone":"Europe/Berlin",
    "iso:country":"DE",
    "wof:name":"Klein Koelzig",
    "wof:placetype":"neighbourhood"
},
  "geometry": {"coordinates":[14.5806,51.65391],"type":"Point"}
}