{
  "type": "Feature",
  "properties": {
    "gn:admin1_code":"1.0",
    "gn:admin2_code":"81.0",
    "gn:admin3_code":"8136.0",
    "gn:admin4_code":"8136009.0",
    "gn:asciiname":"Beiswang",
    "gn:country_code":"DE",
    "gn:dem":416,
    "gn:feature_class":"P",
    "gn:feature_code":"PPL",
    "gn:name":"Beiswang",
    "gn:population":0,
    "gn:timezone":"Europe/Berlin",
    "iso:country":"DE",
    "wof:name":"Beiswang",
    "wof:placetype":"neighbourhood"
},
  "geometry": {"coordinates":[9.89426,48.81037],"type":"Point"}
}