{
  "type": "Feature",
  "properties": {
    "iso:country":"DE",
    "name:deu_x_preferred":[
        "Dreckente"
    ],
    "qs:gn_local":0,
    "qs:local_max":8020,
    "qs:local_sum":17049,
    "qs:localhoods":23,
    "qs:name":"Dreckente",
    "qs:name_adm0":"Deutschland",
    "qs:name_adm1":"Sachsen-Anhalt",
    "qs:name_adm2":"Stadtkreis Halle",
    "qs:name_lau":"Halle (Saale)",
    "qs:name_local":"Halle (Saale)",
    "qs:photo_max":16,
    "qs:photo_sum":51,
    "qs:placetype":"Suburb",
    "qs:quad_count":14,
    "qs:woe_adm0":23424829,
    "qs:woe_adm1":2345494,
    "qs:woe_adm2":12597046,
    "qs:woe_lau":56556603,
    "qs:woe_local":56556603,
    "qs:woe_ver":"7.10.0",
    "wof:lang":[
        "ger"
    ],
    "wof:name":"Dreckente",
    "wof:placetype":"neighbourhood"
},
  "geometry": {"coordinates":[11.945285,51.530958],"type":"Point"}
}