{
  "type": "Feature",
  "properties": {
    "gn:admin1_code":"6",
    "gn:admin2_code":"0.0",
    "gn:admin3_code":"3455.0",
    "gn:admin4_code":"3455020.0",
    "gn:asciiname":"Grimmens",
    "gn:country_code":"DE",
    "gn:dem":1,
    "gn:feature_class":"P",
    "gn:feature_code":"PPL",
    "gn:name":"Grimmens",
    "gn:population":0,
    "gn:timezone":"Europe/Berlin",
    "iso:country":"DE",
    "wof:name":"Grimmens",
    "wof:placetype":"neighbourhood"
},
  "geometry": {"coordinates":[7.93982,53.68661],"type":"Point"}
}