{
  "type": "Feature",
  "properties": {
    "gn:population":1089,
    "iso:country":"DE",
    "name:arm_x_preferred":[
        "\u0531\u0584\u057d\u056c\u0561\u056d"
    ],
    "name:baq_x_preferred":[
        "Achslach"
    ],
    "name:bar_x_preferred":[
        "Oxla"
    ],
    "name:ces_x_preferred":[
        "Achslach"
    ],
    "name:chi_x_preferred":[
        "\u963f\u65af\u62c9"
    ],
    "name:cze_x_preferred":[
        "Achslach"
    ],
    "name:deu_x_preferred":[
        "Achslach"
    ],
    "name:dut_x_preferred":[
        "Achslach"
    ],
    "name:eng_x_preferred":[
        "Achslach"
    ],
    "name:epo_x_preferred":[
        "Achslach"
    ],
    "name:eus_x_preferred":[
        "Achslach"
    ],
    "name:fas_x_preferred":[
        "\u0627\u06a9\u0633\u0644\u0627\u0686"
    ],
    "name:fra_x_preferred":[
        "Achslach"
    ],
    "name:fre_x_preferred":[
        "Achslach"
    ],
    "name:ger_x_preferred":[
        "Achslach"
    ],
    "name:hbs_x_preferred":[
        "Achslach"
    ],
    "name:hun_x_preferred":[
        "Achslach"
    ],
    "name:hye_x_preferred":[
        "\u0531\u0584\u057d\u056c\u0561\u056d"
    ],
    "name:ita_x_preferred":[
        "Achslach"
    ],
    "name:lat_x_preferred":[
        "Achslach"
    ],
    "name:lmo_x_preferred":[
        "Achslach"
    ],
    "name:may_x_preferred":[
        "Achslach"
    ],
    "name:msa_x_preferred":[
        "Achslach"
    ],
    "name:nan_x_preferred":[
        "Achslach"
    ],
    "name:nld_x_preferred":[
        "Achslach"
    ],
    "name:per_x_preferred":[
        "\u0627\u06a9\u0633\u0644\u0627\u0686"
    ],
    "name:pol_x_preferred":[
        "Achslach"
    ],
    "name:por_x_preferred":[
        "Achslach"
    ],
    "name:ron_x_preferred":[
        "Achslach"
    ],
    "name:rum_x_preferred":[
        "Achslach"
    ],
    "name:rus_x_preferred":[
        "\u0410\u043a\u0441\u043b\u0430\u0445"
    ],
    "name:srp_x_preferred":[
        "\u0410\u0445\u0441\u043b\u0430\u0445"
    ],
    "name:ukr_x_preferred":[
        "\u0410\u043a\u0441\u043b\u0430\u0445"
    ],
    "name:uzb_x_preferred":[
        "Achslach"
    ],
    "name:vie_x_preferred":[
        "Achslach"
    ],
    "name:vol_x_preferred":[
        "Achslach"
    ],
    "name:war_x_preferred":[
        "Achslach"
    ],
    "name:zho_min_nan_x_preferred":[
        "Achslach"
    ],
    "name:zho_x_preferred":[
        "\u963f\u65af\u62c9"
    ],
    "qs:a0":"Bundesrepublik Deutschland",
    "qs:a1":"*Bayern",
    "qs:a1r":"0",
    "qs:a2":"Regen",
    "qs:adm0":"Bundesrepublik Deutschland",
    "qs:la_lc":"*",
    "qs:level":"locality",
    "qs:loc":"Achslach",
    "qs:loc_alt":"Achslach",
    "qs:pop":0,
    "qs:type":"buffered point",
    "wd:wordcount":26,
    "wof:lang":[
        "ger"
    ],
    "wof:name":"Achslach",
    "wof:placetype":"locality",
    "wof:population":1089
},
  "geometry": {"coordinates":[12.93495,48.970565],"type":"Point"}
}