{
  "type": "Feature",
  "properties": {
    "gn:admin1_code":"2",
    "gn:admin2_code":"94.0",
    "gn:admin3_code":"9479.0",
    "gn:admin4_code":"9479129.0",
    "gn:asciiname":"Mittelschieda",
    "gn:country_code":"DE",
    "gn:dem":552,
    "gn:feature_class":"P",
    "gn:feature_code":"PPL",
    "gn:name":"Mittelschieda",
    "gn:population":0,
    "gn:timezone":"Europe/Berlin",
    "iso:country":"DE",
    "wof:name":"Mittelschieda",
    "wof:placetype":"neighbourhood"
},
  "geometry": {"coordinates":[11.93864,50.19307],"type":"Point"}
}