{
  "type": "Feature",
  "properties": {
    "gn:admin1_code":"12.0",
    "gn:admin2_code":"0.0",
    "gn:admin3_code":"13076.0",
    "gn:admin4_code":"13076014.0",
    "gn:asciiname":"Bahlendorf",
    "gn:country_code":"DE",
    "gn:dem":9,
    "gn:feature_class":"P",
    "gn:feature_code":"PPL",
    "gn:name":"Bahlendorf",
    "gn:population":0,
    "gn:timezone":"Europe/Berlin",
    "iso:country":"DE",
    "wof:name":"Bahlendorf",
    "wof:placetype":"neighbourhood"
},
  "geometry": {"coordinates":[10.75203,53.3684],"type":"Point"}
}