{
  "type": "Feature",
  "properties": {
    "gn:admin1_code":"2",
    "gn:admin2_code":"94.0",
    "gn:admin3_code":"9475.0",
    "gn:admin4_code":"9475162.0",
    "gn:asciiname":"Schonlind",
    "gn:country_code":"DE",
    "gn:dem":618,
    "gn:feature_class":"P",
    "gn:feature_code":"PPL",
    "gn:name":"Sch\u00f6nlind",
    "gn:population":0,
    "gn:timezone":"Europe/Berlin",
    "iso:country":"DE",
    "wof:name":"Schonlind",
    "wof:placetype":"neighbourhood"
},
  "geometry": {"coordinates":[12.11684,50.22664],"type":"Point"}
}