{
  "type": "Feature",
  "properties": {
    "gn:admin1_code":"7",
    "gn:admin2_code":"55.0",
    "gn:admin3_code":"5554.0",
    "gn:admin4_code":"5554032.0",
    "gn:asciiname":"Dwarsefeld",
    "gn:country_code":"DE",
    "gn:dem":15,
    "gn:feature_class":"P",
    "gn:feature_code":"PPL",
    "gn:name":"Dwarsefeld",
    "gn:population":0,
    "gn:timezone":"Europe/Berlin",
    "iso:country":"DE",
    "name:und_x_variant":[
        "Dwarsfeld",
        "Dwarsefeld"
    ],
    "wof:name":"Dwarsefeld",
    "wof:placetype":"neighbourhood"
},
  "geometry": {"coordinates":[6.40953,51.86172],"type":"Point"}
}