{
  "type": "Feature",
  "properties": {
    "gn:admin1_code":"2",
    "gn:admin2_code":"92.0",
    "gn:admin3_code":"9271.0",
    "gn:admin4_code":"9271119.0",
    "gn:asciiname":"Itzling",
    "gn:country_code":"DE",
    "gn:dem":423,
    "gn:feature_class":"P",
    "gn:feature_code":"PPL",
    "gn:name":"Itzling",
    "gn:population":0,
    "gn:timezone":"Europe/Berlin",
    "iso:country":"DE",
    "wof:name":"Itzling",
    "wof:placetype":"neighbourhood"
},
  "geometry": {"coordinates":[12.99008,48.85721],"type":"Point"}
}