{
  "type": "Feature",
  "properties": {
    "gn:admin1_code":"11",
    "gn:admin2_code":"0.0",
    "gn:admin3_code":"12070.0",
    "gn:admin4_code":"12070222.0",
    "gn:asciiname":"Grabow",
    "gn:country_code":"DE",
    "gn:dem":102,
    "gn:feature_class":"P",
    "gn:feature_code":"PPL",
    "gn:name":"Grabow",
    "gn:population":0,
    "gn:timezone":"Europe/Berlin",
    "iso:country":"DE",
    "name:ara_x_preferred":[
        "\u063a\u0631\u0627\u0628\u0648"
    ],
    "name:azb_x_preferred":[
        "\u0642\u0631\u0627\u0628\u0648"
    ],
    "name:dan_x_preferred":[
        "Grabow"
    ],
    "name:deu_x_preferred":[
        "Grabow"
    ],
    "name:epo_x_preferred":[
        "Grabow"
    ],
    "name:fas_x_preferred":[
        "\u06af\u0631\u0627\u0628\u0648"
    ],
    "name:fra_x_preferred":[
        "Grabow"
    ],
    "name:hun_x_preferred":[
        "Grabow"
    ],
    "name:ita_x_preferred":[
        "Grabow"
    ],
    "name:lav_x_preferred":[
        "Gr\u0101bova"
    ],
    "name:mkd_x_preferred":[
        "\u0413\u0440\u0430\u0431\u043e\u0432"
    ],
    "name:msa_x_preferred":[
        "Grabow"
    ],
    "name:nld_x_preferred":[
        "Grabow"
    ],
    "name:pol_x_preferred":[
        "Grabow"
    ],
    "name:ron_x_preferred":[
        "Grabow"
    ],
    "name:rus_x_preferred":[
        "\u0413\u0440\u0430\u0431\u043e\u0432"
    ],
    "name:spa_x_preferred":[
        "Grabow"
    ],
    "name:srp_x_preferred":[
        "\u0413\u0440\u0430\u0431\u043e\u0432"
    ],
    "name:swe_x_preferred":[
        "Grabow"
    ],
    "name:tur_x_preferred":[
        "Grabow"
    ],
    "name:ukr_x_preferred":[
        "\u0413\u0440\u0430\u0431\u043e\u0432"
    ],
    "name:uzb_x_preferred":[
        "Grabow"
    ],
    "name:vie_x_preferred":[
        "Grabow"
    ],
    "name:vol_x_preferred":[
        "Grabow"
    ],
    "name:war_x_preferred":[
        "Grabow"
    ],
    "name:zho_x_preferred":[
        "\u683c\u62c9\u535a"
    ],
    "wof:name":"Grabow",
    "wof:placetype":"neighbourhood"
},
  "geometry": {"coordinates":[12.17221,53.26639],"type":"Point"}
}