{
  "type": "Feature",
  "properties": {
    "gn:admin1_code":"11",
    "gn:admin2_code":"0.0",
    "gn:admin3_code":"12070.0",
    "gn:admin4_code":"12070222.0",
    "gn:asciiname":"Grabow",
    "gn:country_code":"DE",
    "gn:dem":102,
    "gn:feature_class":"P",
    "gn:feature_code":"PPL",
    "gn:name":"Grabow",
    "gn:population":0,
    "gn:timezone":"Europe/Berlin",
    "iso:country":"DE",
    "wof:name":"Grabow",
    "wof:placetype":"neighbourhood"
},
  "geometry": {"coordinates":[12.17221,53.26639],"type":"Point"}
}