{
  "type": "Feature",
  "properties": {
    "gn:admin1_code":"12",
    "gn:admin2_code":"0.0",
    "gn:admin3_code":"13071.0",
    "gn:admin4_code":"13071092.0",
    "gn:asciiname":"Retzow",
    "gn:country_code":"DE",
    "gn:dem":92,
    "gn:feature_class":"P",
    "gn:feature_code":"PPL",
    "gn:name":"Retzow",
    "gn:population":0,
    "gn:timezone":"Europe/Berlin",
    "iso:country":"DE",
    "name:deu_x_preferred":[
        "Retzow"
    ],
    "name:epo_x_preferred":[
        "Retzow"
    ],
    "name:eus_x_preferred":[
        "Retzow"
    ],
    "name:fas_x_preferred":[
        "\u0631\u062a\u0633\u0648\u0648"
    ],
    "name:fra_x_preferred":[
        "Retzow"
    ],
    "name:hun_x_preferred":[
        "Retzow"
    ],
    "name:hye_x_preferred":[
        "\u054c\u0565\u0581\u0578\u057e"
    ],
    "name:ita_x_preferred":[
        "Retzow"
    ],
    "name:mkd_x_preferred":[
        "\u0420\u0435\u0446\u043e\u0432"
    ],
    "name:msa_x_preferred":[
        "Retzow"
    ],
    "name:nld_x_preferred":[
        "Retzow"
    ],
    "name:pol_x_preferred":[
        "Retzow"
    ],
    "name:ron_x_preferred":[
        "Retzow"
    ],
    "name:rus_x_preferred":[
        "\u0420\u0435\u0446\u043e\u0432"
    ],
    "name:spa_x_preferred":[
        "Retzow"
    ],
    "name:srp_x_preferred":[
        "\u0420\u0435\u0446\u043e\u0432"
    ],
    "name:ukr_x_preferred":[
        "\u0420\u0435\u0442\u0446\u043e\u0432"
    ],
    "name:uzb_x_preferred":[
        "Retzow"
    ],
    "name:vie_x_preferred":[
        "Retzow"
    ],
    "name:vol_x_preferred":[
        "Retzow"
    ],
    "name:war_x_preferred":[
        "Retzow"
    ],
    "wof:name":"Retzow",
    "wof:placetype":"neighbourhood"
},
  "geometry": {"coordinates":[12.72019,53.77706],"type":"Point"}
}