{
  "type": "Feature",
  "properties": {
    "gn:admin1_code":"12",
    "gn:admin2_code":"0.0",
    "gn:admin3_code":"13071.0",
    "gn:admin4_code":"13071092.0",
    "gn:asciiname":"Retzow",
    "gn:country_code":"DE",
    "gn:dem":92,
    "gn:feature_class":"P",
    "gn:feature_code":"PPL",
    "gn:name":"Retzow",
    "gn:population":0,
    "gn:timezone":"Europe/Berlin",
    "iso:country":"DE",
    "wof:name":"Retzow",
    "wof:placetype":"neighbourhood"
},
  "geometry": {"coordinates":[12.72019,53.77706],"type":"Point"}
}