{
  "type": "Feature",
  "properties": {
    "gn:admin1_code":"2.0",
    "gn:admin2_code":"92.0",
    "gn:admin3_code":"9278.0",
    "gn:admin4_code":"9278177.0",
    "gn:asciiname":"Bergstorf",
    "gn:country_code":"DE",
    "gn:dem":333,
    "gn:feature_class":"P",
    "gn:feature_code":"PPLL",
    "gn:name":"Bergstorf",
    "gn:population":0,
    "gn:timezone":"Europe/Berlin",
    "iso:country":"DE",
    "wof:name":"Bergstorf",
    "wof:placetype":"neighbourhood"
},
  "geometry": {"coordinates":[12.4558,48.88134],"type":"Point"}
}