{
  "type": "Feature",
  "properties": {
    "gn:admin1_code":"2",
    "gn:admin2_code":"91.0",
    "gn:admin3_code":"9173.0",
    "gn:admin4_code":"9173123.0",
    "gn:asciiname":"Steingrub",
    "gn:country_code":"DE",
    "gn:dem":687,
    "gn:feature_class":"P",
    "gn:feature_code":"PPL",
    "gn:name":"Steingrub",
    "gn:population":0,
    "gn:timezone":"Europe/Berlin",
    "iso:country":"DE",
    "wof:name":"Steingrub",
    "wof:placetype":"neighbourhood"
},
  "geometry": {"coordinates":[11.36667,47.86667],"type":"Point"}
}