{
  "type": "Feature",
  "properties": {
    "gn:admin1_code":"2",
    "gn:admin2_code":"91.0",
    "gn:admin3_code":"9185.0",
    "gn:admin4_code":"9185150.0",
    "gn:asciiname":"Sinning",
    "gn:country_code":"DE",
    "gn:dem":417,
    "gn:feature_class":"P",
    "gn:feature_code":"PPL",
    "gn:name":"Sinning",
    "gn:population":0,
    "gn:timezone":"Europe/Berlin",
    "iso:country":"DE",
    "name:deu_x_preferred":[
        "Sinning"
    ],
    "wof:name":"Sinning",
    "wof:placetype":"neighbourhood"
},
  "geometry": {"coordinates":[11.10681,48.69065],"type":"Point"}
}