{
  "type": "Feature",
  "properties": {
    "gn:admin1_code":"5",
    "gn:admin2_code":"66.0",
    "gn:admin3_code":"6636.0",
    "gn:admin4_code":"6636001.0",
    "gn:asciiname":"Kleinvach",
    "gn:country_code":"DE",
    "gn:dem":154,
    "gn:feature_class":"P",
    "gn:feature_code":"PPL",
    "gn:name":"Kleinvach",
    "gn:population":0,
    "gn:timezone":"Europe/Berlin",
    "iso:country":"DE",
    "name:und_x_variant":[
        "Kleinbach",
        "Kleinvach"
    ],
    "wof:name":"Kleinvach",
    "wof:placetype":"neighbourhood"
},
  "geometry": {"coordinates":[9.99486,51.24836],"type":"Point"}
}