{
  "type": "Feature",
  "properties": {
    "gn:admin1_code":"12.0",
    "gn:admin2_code":"0.0",
    "gn:admin3_code":"13072.0",
    "gn:admin4_code":"13072063.0",
    "gn:asciiname":"Bergfeld",
    "gn:country_code":"DE",
    "gn:dem":54,
    "gn:feature_class":"P",
    "gn:feature_code":"PPL",
    "gn:name":"Bergfeld",
    "gn:population":0,
    "gn:timezone":"Europe/Berlin",
    "iso:country":"DE",
    "name:ceb_x_preferred":[
        "Bergfeld"
    ],
    "name:dan_x_preferred":[
        "Bergfeld"
    ],
    "name:deu_x_preferred":[
        "Bergfeld"
    ],
    "name:epo_x_preferred":[
        "Bergfeld"
    ],
    "name:est_x_preferred":[
        "Bergfeld"
    ],
    "name:eus_x_preferred":[
        "Bergfeld"
    ],
    "name:fas_x_preferred":[
        "\u0628\u0631\u06af\u0641\u0644\u062f"
    ],
    "name:fra_x_preferred":[
        "Bergfeld"
    ],
    "name:hun_x_preferred":[
        "Bergfeld"
    ],
    "name:ita_x_preferred":[
        "Bergfeld"
    ],
    "name:kaz_x_preferred":[
        "\u0411\u0435\u0440\u0433\u0444\u0435\u043b\u044c\u0434"
    ],
    "name:kir_x_preferred":[
        "\u0411\u0435\u0440\u0433\u0444\u0435\u043b\u044c\u0434"
    ],
    "name:lat_x_preferred":[
        "Bergfeld"
    ],
    "name:mkd_x_preferred":[
        "\u0411\u0435\u0440\u0433\u0444\u0435\u043b\u0434"
    ],
    "name:msa_x_preferred":[
        "Bergfeld"
    ],
    "name:nld_x_preferred":[
        "Bergfeld"
    ],
    "name:pol_x_preferred":[
        "Bergfeld"
    ],
    "name:por_x_preferred":[
        "Bergfeld"
    ],
    "name:ron_x_preferred":[
        "Bergfeld"
    ],
    "name:rus_x_preferred":[
        "\u0411\u0435\u0440\u0433\u0444\u0435\u043b\u044c\u0434"
    ],
    "name:spa_x_preferred":[
        "Bergfeld"
    ],
    "name:srp_x_preferred":[
        "\u0411\u0435\u0440\u0433\u0444\u0435\u043b\u0434"
    ],
    "name:ukr_x_preferred":[
        "\u0411\u0435\u0440\u0433\u0444\u0435\u043b\u044c\u0434"
    ],
    "name:uzb_x_preferred":[
        "Bergfeld"
    ],
    "name:vie_x_preferred":[
        "Bergfeld"
    ],
    "name:vol_x_preferred":[
        "Bergfeld"
    ],
    "name:war_x_preferred":[
        "Bergfeld"
    ],
    "name:zho_x_preferred":[
        "\u8d1d\u683c\u8d39\u5c14\u5fb7"
    ],
    "wof:name":"Bergfeld",
    "wof:placetype":"neighbourhood"
},
  "geometry": {"coordinates":[12.45729,53.73196],"type":"Point"}
}