{
  "type": "Feature",
  "properties": {
    "gn:admin1_code":"2",
    "gn:admin2_code":"95.0",
    "gn:admin3_code":"9571.0",
    "gn:admin4_code":"9571145.0",
    "gn:asciiname":"Kuhnhard am Schlegel",
    "gn:country_code":"DE",
    "gn:dem":457,
    "gn:feature_class":"P",
    "gn:feature_code":"PPL",
    "gn:name":"K\u00fchnhard am Schlegel",
    "gn:population":0,
    "gn:timezone":"Europe/Berlin",
    "iso:country":"DE",
    "name:und_x_variant":[
        "K\u00fchnhardt am Schlegel",
        "K\u00fchnhardt",
        "K\u00fchnhard",
        "K\u00fchnhard am Schlegel"
    ],
    "wof:name":"Kuhnhard am Schlegel",
    "wof:placetype":"neighbourhood"
},
  "geometry": {"coordinates":[10.25369,49.15606],"type":"Point"}
}