{
  "type": "Feature",
  "properties": {
    "gn:admin1_code":"13",
    "gn:admin2_code":"0.0",
    "gn:admin3_code":"14521.0",
    "gn:admin4_code":"14521540.0",
    "gn:asciiname":"Schwarzwinkel",
    "gn:country_code":"DE",
    "gn:dem":627,
    "gn:feature_class":"P",
    "gn:feature_code":"PPL",
    "gn:name":"Schwarzwinkel",
    "gn:population":0,
    "gn:timezone":"Europe/Berlin",
    "iso:country":"DE",
    "wof:name":"Schwarzwinkel",
    "wof:placetype":"neighbourhood"
},
  "geometry": {"coordinates":[12.52654,50.51023],"type":"Point"}
}