{
  "type": "Feature",
  "properties": {
    "gn:admin1_code":"2",
    "gn:admin2_code":"93.0",
    "gn:admin3_code":"9371.0",
    "gn:admin4_code":"9371113.0",
    "gn:asciiname":"Steinamwasser",
    "gn:country_code":"DE",
    "gn:dem":435,
    "gn:feature_class":"P",
    "gn:feature_code":"PPL",
    "gn:name":"Steinamwasser",
    "gn:population":0,
    "gn:timezone":"Europe/Berlin",
    "iso:country":"DE",
    "wof:name":"Steinamwasser",
    "wof:placetype":"neighbourhood"
},
  "geometry": {"coordinates":[11.60589,49.7278],"type":"Point"}
}