{
  "type": "Feature",
  "properties": {
    "gn:admin1_code":"2",
    "gn:admin2_code":"92.0",
    "gn:admin3_code":"9272.0",
    "gn:admin4_code":"9272118.0",
    "gn:asciiname":"Konigsfeld",
    "gn:country_code":"DE",
    "gn:dem":671,
    "gn:feature_class":"P",
    "gn:feature_code":"PPL",
    "gn:name":"K\u00f6nigsfeld",
    "gn:population":0,
    "gn:timezone":"Europe/Berlin",
    "iso:country":"DE",
    "wof:name":"Konigsfeld",
    "wof:placetype":"neighbourhood"
},
  "geometry": {"coordinates":[13.53801,48.81923],"type":"Point"}
}