{
  "type": "Feature",
  "properties": {
    "gn:admin1_code":"2",
    "gn:admin2_code":"92.0",
    "gn:admin3_code":"9278.0",
    "gn:admin4_code":"9278148.0",
    "gn:asciiname":"Oberhaselbach",
    "gn:country_code":"DE",
    "gn:dem":418,
    "gn:feature_class":"P",
    "gn:feature_code":"PPL",
    "gn:name":"Oberhaselbach",
    "gn:population":0,
    "gn:timezone":"Europe/Berlin",
    "iso:country":"DE",
    "wof:name":"Oberhaselbach",
    "wof:placetype":"neighbourhood"
},
  "geometry": {"coordinates":[12.15639,48.77653],"type":"Point"}
}