{
  "type": "Feature",
  "properties": {
    "gn:admin1_code":"15",
    "gn:admin2_code":"0.0",
    "gn:admin3_code":"16070.0",
    "gn:admin4_code":"16070053.0",
    "gn:asciiname":"Dannheim",
    "gn:country_code":"DE",
    "gn:dem":366,
    "gn:feature_class":"P",
    "gn:feature_code":"PPL",
    "gn:name":"Dannheim",
    "gn:population":0,
    "gn:timezone":"Europe/Berlin",
    "iso:country":"DE",
    "wof:name":"Dannheim",
    "wof:placetype":"neighbourhood"
},
  "geometry": {"coordinates":[10.98025,50.79678],"type":"Point"}
}