{
  "type": "Feature",
  "properties": {
    "iso:country":"DE",
    "name:deu_x_colloquial":[
        "Russheide"
    ],
    "name:deu_x_preferred":[
        "Ru\u00dfheide"
    ],
    "name:unk_x_variant":[
        "Ru\u00dfheide"
    ],
    "qs:gn_adm0_cc":"DE",
    "qs:gn_fcode":"PPLX",
    "qs:gn_local":2949186,
    "qs:gn_namadm1":"07",
    "qs:gn_name":"Ru\u00dfheide",
    "qs:local_max":3834,
    "qs:local_sum":10586,
    "qs:localhoods":26,
    "qs:name":"Ru\u00dfheide",
    "qs:name_adm0":"Deutschland",
    "qs:name_adm1":"Nordrhein-Westfalen",
    "qs:name_adm2":"Stadtkreis Bielefeld",
    "qs:name_lau":"Stadtteil Mitte",
    "qs:name_local":"Bielefeld",
    "qs:photo_max":399,
    "qs:photo_sum":1593,
    "qs:placetype":"Suburb",
    "qs:quad_count":79,
    "qs:woe_adm0":23424829,
    "qs:woe_adm1":2345487,
    "qs:woe_adm2":12596866,
    "qs:woe_lau":26821926,
    "qs:woe_local":638806,
    "qs:woe_ver":"7.10.0",
    "wof:lang":[
        "ger"
    ],
    "wof:name":"Ru\u00dfheide",
    "wof:placetype":"neighbourhood"
},
  "geometry": {"coordinates":[8.562677,52.024719],"type":"Point"}
}