{
  "type": "Feature",
  "properties": {
    "iso:country":"DE",
    "name:bos_x_preferred":[
        "Kanal Rajna-Majna-Dunav"
    ],
    "name:bul_x_preferred":[
        "\u0420\u0435\u0439\u043d - \u041c\u0430\u0439\u043d - \u0414\u0443\u043d\u0430\u0432"
    ],
    "name:ces_x_preferred":[
        "Pr\u016fplav R\u00fdn-Mohan-Dunaj"
    ],
    "name:dan_x_preferred":[
        "Main-Donau-Kanalen"
    ],
    "name:deu_x_colloquial":[
        "Hafen Nuernberg",
        "Hafen Nurnberg"
    ],
    "name:deu_x_preferred":[
        "Main-Donau-Kanal"
    ],
    "name:deu_x_variant":[
        "Hafen N\u00fcrnberg"
    ],
    "name:ell_x_preferred":[
        "\u039a\u03b1\u03bd\u03ac\u03bb\u03b9 \u03a1\u03ae\u03bd\u03bf\u03c5-\u039c\u03ac\u03b9\u03bd-\u0394\u03bf\u03cd\u03bd\u03b1\u03b2\u03b7"
    ],
    "name:eng_x_preferred":[
        "Hafen N\u00fcrnberg"
    ],
    "name:epo_x_preferred":[
        "Majno-Danubo-Kanalo"
    ],
    "name:est_x_preferred":[
        "Reini-Maini-Doonau kanal"
    ],
    "name:eus_x_preferred":[
        "Rhin-Main-Danubio ubidea"
    ],
    "name:spa_x_preferred":[
        "Canal Rin-Meno-Danubio"
    ],
    "qs:gn_adm0_cc":"DE",
    "qs:gn_local":2861650,
    "qs:gn_nam_loc":"nurnberg",
    "qs:gn_namadm1":"02",
    "qs:local_max":6346,
    "qs:local_sum":25338,
    "qs:localhoods":37,
    "qs:name":"Hafen N\u00fcrnberg",
    "qs:name_adm0":"Deutschland",
    "qs:name_adm1":"Bayern",
    "qs:name_adm2":"Stadtkreis N\u00fcrnberg",
    "qs:name_lau":"Stadtteil S\u00fcdwestliche Au\u00dfenstadt",
    "qs:name_local":"N\u00fcrnberg",
    "qs:photo_max":30,
    "qs:photo_sum":242,
    "qs:placetype":"Suburb",
    "qs:quad_count":33,
    "qs:woe_adm0":23424829,
    "qs:woe_adm1":2345482,
    "qs:woe_adm2":12596973,
    "qs:woe_lau":26823123,
    "qs:woe_local":680564,
    "qs:woe_ver":"7.10.0",
    "wof:lang":[
        "ger"
    ],
    "wof:name":"Nuremburg Harbor",
    "wof:placetype":"neighbourhood"
},
  "geometry": {"coordinates":[11.056821,49.40022],"type":"Point"}
}