{
  "type": "Feature",
  "properties": {
    "gn:admin1_code":"2",
    "gn:admin2_code":"92.0",
    "gn:admin3_code":"9277.0",
    "gn:admin4_code":"9277141.0",
    "gn:asciiname":"Oberrohrbach",
    "gn:country_code":"DE",
    "gn:dem":459,
    "gn:feature_class":"P",
    "gn:feature_code":"PPL",
    "gn:name":"Oberrohrbach",
    "gn:population":0,
    "gn:timezone":"Europe/Berlin",
    "iso:country":"DE",
    "wof:name":"Oberrohrbach",
    "wof:placetype":"neighbourhood"
},
  "geometry": {"coordinates":[12.65986,48.48607],"type":"Point"}
}