{
  "type": "Feature",
  "properties": {
    "gn:admin1_code":"6",
    "gn:admin2_code":"0.0",
    "gn:admin3_code":"3454.0",
    "gn:admin4_code":"3454057.0",
    "gn:asciiname":"Ostenwalde",
    "gn:country_code":"DE",
    "gn:dem":37,
    "gn:feature_class":"P",
    "gn:feature_code":"PPL",
    "gn:name":"Ostenwalde",
    "gn:population":0,
    "gn:timezone":"Europe/Berlin",
    "iso:country":"DE",
    "wof:name":"Ostenwalde",
    "wof:placetype":"neighbourhood"
},
  "geometry": {"coordinates":[7.58856,52.83629000000001],"type":"Point"}
}