{
  "type": "Feature",
  "properties": {
    "gn:gn_country":"DE",
    "gn:gn_fcode":"PPLA4",
    "gn:gn_pop":432,
    "gn:population":432,
    "iso:country":"DE",
    "name:baq_x_preferred":[
        "Mittelstrimmig"
    ],
    "name:chi_x_preferred":[
        "\u7c73\u7279\u5c14\u65af\u7279\u91cc\u7c73\u5e0c"
    ],
    "name:dut_x_preferred":[
        "Mittelstrimmig"
    ],
    "name:eng_x_preferred":[
        "Mittelstrimmig"
    ],
    "name:epo_x_preferred":[
        "Mittelstrimmig"
    ],
    "name:fre_x_preferred":[
        "Mittelstrimmig"
    ],
    "name:ger_x_preferred":[
        "Mittelstrimmig"
    ],
    "name:hun_x_preferred":[
        "Mittelstrimmig"
    ],
    "name:ita_x_preferred":[
        "Mittelstrimmig"
    ],
    "name:jpn_x_preferred":[
        "\u30df\u30c3\u30c6\u30eb\u30b7\u30e5\u30c8\u30ea\u30f3\u30df\u30d2"
    ],
    "name:may_x_preferred":[
        "Mittelstrimmig"
    ],
    "name:per_x_preferred":[
        "\u0645\u06cc\u062a\u0644\u0634\u062a\u0631\u06cc\u0645\u06cc\u06af"
    ],
    "name:pol_x_preferred":[
        "Mittelstrimmig"
    ],
    "name:por_x_preferred":[
        "Mittelstrimmig"
    ],
    "name:rum_x_preferred":[
        "Mittelstrimmig"
    ],
    "name:rus_x_preferred":[
        "\u041c\u0438\u0442\u0442\u0435\u043b\u044c\u0448\u0442\u0440\u0438\u043c\u043c\u0438\u0433"
    ],
    "name:srp_x_preferred":[
        "\u041c\u0438\u0442\u0435\u043b\u0441\u0442\u0440\u0438\u043c\u0438\u0433"
    ],
    "name:ukr_x_preferred":[
        "\u041c\u0456\u0442\u0442\u0435\u043b\u044c\u0441\u0442\u0440\u0456\u043c\u043c\u0456\u0433"
    ],
    "name:uzb_x_preferred":[
        "Mittelstrimmig"
    ],
    "name:vie_x_preferred":[
        "Mittelstrimmig"
    ],
    "name:vol_x_preferred":[
        "Mittelstrimmig"
    ],
    "name:war_x_preferred":[
        "Mittelstrimmig"
    ],
    "name:zho_x_preferred":[
        "\u7c73\u7279\u5c14\u65af\u7279\u91cc\u7c73\u5e0c"
    ],
    "qs_pg:aaroncc":"DE",
    "qs_pg:gn_country":"DE",
    "qs_pg:gn_fcode":"PPLA4",
    "qs_pg:gn_pop":432,
    "qs_pg:name":"Mittelstrimmig",
    "qs_pg:photos_9r":0,
    "qs_pg:photos_sr":0,
    "qs_pg:pop_sr":2,
    "qs_pg:qs_pg_placetype":"locality",
    "wof:name":"Mittelstrimmig",
    "wof:placetype":"locality",
    "wof:population":432
},
  "geometry": {"coordinates":[7.28333,50.08333],"type":"Point"}
}