{
  "type": "Feature",
  "properties": {
    "gn:admin1_code":"10",
    "gn:admin2_code":"0.0",
    "gn:admin3_code":"1060.0",
    "gn:admin4_code":"1060067.0",
    "gn:asciiname":"Eilsdorf",
    "gn:country_code":"DE",
    "gn:dem":58,
    "gn:feature_class":"P",
    "gn:feature_code":"PPL",
    "gn:name":"Eilsdorf",
    "gn:population":0,
    "gn:timezone":"Europe/Berlin",
    "iso:country":"DE",
    "wof:name":"Eilsdorf",
    "wof:placetype":"neighbourhood"
},
  "geometry": {"coordinates":[10.50014,53.96039],"type":"Point"}
}