{
  "type": "Feature",
  "properties": {
    "gn:admin1_code":"2",
    "gn:admin2_code":"95.0",
    "gn:admin3_code":"9561.0",
    "gn:admin4_code":"9561000.0",
    "gn:asciiname":"Neuses",
    "gn:country_code":"DE",
    "gn:dem":408,
    "gn:feature_class":"P",
    "gn:feature_code":"PPL",
    "gn:name":"Neuses",
    "gn:population":0,
    "gn:timezone":"Europe/Berlin",
    "iso:country":"DE",
    "name:deu_x_preferred":[
        "Neuses"
    ],
    "name:nld_x_preferred":[
        "Neuses"
    ],
    "wof:name":"Neuses",
    "wof:placetype":"neighbourhood"
},
  "geometry": {"coordinates":[10.55369,49.31382],"type":"Point"}
}