{
  "type": "Feature",
  "properties": {
    "gn:admin1_code":"6.0",
    "gn:admin2_code":"0.0",
    "gn:admin3_code":"3459.0",
    "gn:admin4_code":"3459033.0",
    "gn:asciiname":"Gruthuegel",
    "gn:country_code":"DE",
    "gn:dem":105,
    "gn:feature_class":"P",
    "gn:feature_code":"PPL",
    "gn:name":"Gruth\u00fcgel",
    "gn:population":0,
    "gn:timezone":"Europe/Berlin",
    "iso:country":"DE",
    "wof:name":"Gruthuegel",
    "wof:placetype":"neighbourhood"
},
  "geometry": {"coordinates":[8.05053,52.32413],"type":"Point"}
}