{
  "type": "Feature",
  "properties": {
    "gn:admin1_code":"6.0",
    "gn:admin2_code":"0.0",
    "gn:admin3_code":"3461.0",
    "gn:admin4_code":"3461009.0",
    "gn:asciiname":"Beckum",
    "gn:country_code":"DE",
    "gn:dem":2,
    "gn:feature_class":"P",
    "gn:feature_code":"PPL",
    "gn:name":"Beckum",
    "gn:population":0,
    "gn:timezone":"Europe/Berlin",
    "iso:country":"DE",
    "name:ceb_x_preferred":[
        "Beckum"
    ],
    "name:deu_x_preferred":[
        "Beckum"
    ],
    "name:fra_x_preferred":[
        "Beckum"
    ],
    "name:nld_x_preferred":[
        "Beckum"
    ],
    "name:pol_x_preferred":[
        "Beckum"
    ],
    "name:por_x_preferred":[
        "Beckum"
    ],
    "wof:name":"Beckum",
    "wof:placetype":"neighbourhood"
},
  "geometry": {"coordinates":[8.43287,53.42974],"type":"Point"}
}