{
  "type": "Feature",
  "properties": {
    "gn:admin1_code":"10",
    "gn:admin2_code":"0.0",
    "gn:admin3_code":"1057.0",
    "gn:admin4_code":"1057011.0",
    "gn:asciiname":"Dosenbek",
    "gn:country_code":"DE",
    "gn:dem":45,
    "gn:feature_class":"P",
    "gn:feature_code":"PPL",
    "gn:name":"Dosenbek",
    "gn:population":0,
    "gn:timezone":"Europe/Berlin",
    "iso:country":"DE",
    "name:ceb_x_preferred":[
        "Dosenbek"
    ],
    "name:deu_x_preferred":[
        "Dosenbek"
    ],
    "wof:name":"Dosenbek",
    "wof:placetype":"neighbourhood"
},
  "geometry": {"coordinates":[10.14825,54.17237],"type":"Point"}
}