{
  "type": "Feature",
  "properties": {
    "iso:country":"DE",
    "name:dut_x_preferred":[
        "Bockum-H\u00f6vel"
    ],
    "name:eng_x_preferred":[
        "Bockum-H\u00f6vel"
    ],
    "name:fre_x_preferred":[
        "Bockum-H\u00f6vel"
    ],
    "name:ger_x_preferred":[
        "Bockum-H\u00f6vel"
    ],
    "name:jpn_x_preferred":[
        "\u30dc\u30c3\u30af\u30e0\uff1d\u30d8\u30fc\u30d5\u30a7\u30eb"
    ],
    "qs_pg:aaroncc":"DE",
    "qs_pg:name":"Bockum-H\u00f6vel",
    "qs_pg:name_adm0":"Deutschland",
    "qs_pg:name_adm1":"Nordrhein-Westfalen",
    "qs_pg:photos":128,
    "qs_pg:photos_1k":26,
    "qs_pg:photos_9k":1,
    "qs_pg:photos_9r":3,
    "qs_pg:photos_all":128,
    "qs_pg:photos_sr":3,
    "qs_pg:pop_sr":0,
    "qs_pg:qs_pg_placetype":"locality",
    "qs_pg:qs_pg_placetype_gp":"Town",
    "qs_pg:woe_adm0":23424829,
    "woe:adm0_id":23424829,
    "woe:name_adm0":"Deutschland",
    "woe:name_adm1":"Nordrhein-Westfalen",
    "woe:placetype":"Town",
    "wof:name":"Bockum-H\u00f6vel",
    "wof:placetype":"neighbourhood"
},
  "geometry": {"coordinates":[7.7535735,51.7009635],"type":"Point"}
}