{
  "type": "Feature",
  "properties": {
    "gn:admin1_code":"12",
    "gn:admin2_code":"0.0",
    "gn:admin3_code":"13071.0",
    "gn:admin4_code":"13071173.0",
    "gn:asciiname":"Rahnenfelde",
    "gn:country_code":"DE",
    "gn:dem":53,
    "gn:feature_class":"P",
    "gn:feature_code":"PPL",
    "gn:name":"Rahnenfelde",
    "gn:population":0,
    "gn:timezone":"Europe/Berlin",
    "iso:country":"DE",
    "wof:name":"Rahnenfelde",
    "wof:placetype":"neighbourhood"
},
  "geometry": {"coordinates":[13.07957,53.52218000000001],"type":"Point"}
}