{
  "type": "Feature",
  "properties": {
    "iso:country":"DE",
    "name:deu_x_colloquial":[
        "Wilkenhoener",
        "Wilkenhoner"
    ],
    "name:deu_x_preferred":[
        "Wilkenh\u00f6ner"
    ],
    "name:unk_x_variant":[
        "Wilkenh\u00f6ner"
    ],
    "qs:gn_adm0_cc":"DE",
    "qs:gn_local":2949186,
    "qs:local_max":3834,
    "qs:local_sum":10586,
    "qs:localhoods":26,
    "qs:name":"Wilkenh\u00f6ner",
    "qs:name_adm0":"Deutschland",
    "qs:name_adm1":"Nordrhein-Westfalen",
    "qs:name_adm2":"Stadtkreis Bielefeld",
    "qs:name_lau":"Stadtteil J\u00f6llenbeck",
    "qs:name_local":"Bielefeld",
    "qs:photo_max":3,
    "qs:photo_sum":4,
    "qs:placetype":"Suburb",
    "qs:quad_count":2,
    "qs:woe_adm0":23424829,
    "qs:woe_adm1":2345487,
    "qs:woe_adm2":12596866,
    "qs:woe_lau":26821923,
    "qs:woe_local":638806,
    "qs:woe_ver":"7.10.0",
    "wof:lang":[
        "ger"
    ],
    "wof:name":"Wilkenh\u00f6ner",
    "wof:placetype":"neighbourhood"
},
  "geometry": {"coordinates":[8.598175,52.110722],"type":"Point"}
}