{
  "type": "Feature",
  "properties": {
    "gn:admin1_code":"1",
    "gn:admin2_code":"82.0",
    "gn:admin3_code":"8225.0",
    "gn:admin4_code":"8225109.0",
    "gn:asciiname":"Glashofen",
    "gn:country_code":"DE",
    "gn:dem":401,
    "gn:feature_class":"P",
    "gn:feature_code":"PPL",
    "gn:name":"Glashofen",
    "gn:population":0,
    "gn:timezone":"Europe/Berlin",
    "iso:country":"DE",
    "wof:name":"Glashofen",
    "wof:placetype":"neighbourhood"
},
  "geometry": {"coordinates":[9.36672,49.6245],"type":"Point"}
}