{
  "type": "Feature",
  "properties": {
    "gn:admin1_code":"13.0",
    "gn:admin2_code":"0.0",
    "gn:admin3_code":"14524.0",
    "gn:admin4_code":"14524310.0",
    "gn:asciiname":"An der Weinleite",
    "gn:country_code":"DE",
    "gn:dem":355,
    "gn:feature_class":"P",
    "gn:feature_code":"PPL",
    "gn:name":"An der Weinleite",
    "gn:population":0,
    "gn:timezone":"Europe/Berlin",
    "iso:country":"DE",
    "wof:name":"An der Weinleite",
    "wof:placetype":"neighbourhood"
},
  "geometry": {"coordinates":[12.61667,50.66667],"type":"Point"}
}