{
  "type": "Feature",
  "properties": {
    "gn:admin1_code":"6",
    "gn:admin2_code":"0.0",
    "gn:admin3_code":"3353.0",
    "gn:admin4_code":"3353026.0",
    "gn:asciiname":"Elstorf",
    "gn:country_code":"DE",
    "gn:dem":49,
    "gn:feature_class":"P",
    "gn:feature_code":"PPL",
    "gn:name":"Elstorf",
    "gn:population":0,
    "gn:timezone":"Europe/Berlin",
    "iso:country":"DE",
    "name:deu_x_preferred":[
        "Elstorf"
    ],
    "name:fas_x_preferred":[
        "\u0627\u0644\u0633\u062a\u0648\u0631\u0641"
    ],
    "name:mkd_x_preferred":[
        "\u0415\u043b\u0441\u0442\u043e\u0440\u0444"
    ],
    "name:nds_x_preferred":[
        "Ilsd\u00f6rp"
    ],
    "wof:name":"Elstorf",
    "wof:placetype":"neighbourhood"
},
  "geometry": {"coordinates":[9.78508,53.42533],"type":"Point"}
}