{
  "type": "Feature",
  "properties": {
    "gn:admin1_code":"2",
    "gn:admin2_code":"93.0",
    "gn:admin3_code":"9372.0",
    "gn:admin4_code":"9372126.0",
    "gn:asciiname":"Grabitz",
    "gn:country_code":"DE",
    "gn:dem":399,
    "gn:feature_class":"P",
    "gn:feature_code":"PPL",
    "gn:name":"Grabitz",
    "gn:population":0,
    "gn:timezone":"Europe/Berlin",
    "iso:country":"DE",
    "wof:name":"Grabitz",
    "wof:placetype":"neighbourhood"
},
  "geometry": {"coordinates":[12.83199,49.30489],"type":"Point"}
}