{
  "type": "Feature",
  "properties": {
    "gn:admin1_code":"14",
    "gn:admin2_code":"0.0",
    "gn:admin3_code":"15088.0",
    "gn:admin4_code":"15088330.0",
    "gn:asciiname":"Kollenbey",
    "gn:country_code":"DE",
    "gn:dem":85,
    "gn:feature_class":"P",
    "gn:feature_code":"PPL",
    "gn:name":"Kollenbey",
    "gn:population":0,
    "gn:timezone":"Europe/Berlin",
    "iso:country":"DE",
    "name:und_x_variant":[
        "Collenbey",
        "Kollenbey"
    ],
    "wof:name":"Kollenbey",
    "wof:placetype":"neighbourhood"
},
  "geometry": {"coordinates":[12.0052,51.39435],"type":"Point"}
}