{
  "type": "Feature",
  "properties": {
    "gn:admin1_code":"15.0",
    "gn:admin2_code":"0.0",
    "gn:admin3_code":"16073.0",
    "gn:admin4_code":"16073105.0",
    "gn:asciiname":"Ammelstaedt",
    "gn:country_code":"DE",
    "gn:dem":225,
    "gn:feature_class":"P",
    "gn:feature_code":"PPL",
    "gn:name":"Ammelst\u00e4dt",
    "gn:population":0,
    "gn:timezone":"Europe/Berlin",
    "iso:country":"DE",
    "wof:name":"Ammelstaedt",
    "wof:placetype":"neighbourhood"
},
  "geometry": {"coordinates":[11.31997,50.74031],"type":"Point"}
}