{
  "type": "Feature",
  "properties": {
    "gn:admin1_code":"1",
    "gn:admin2_code":"84.0",
    "gn:admin3_code":"8436.0",
    "gn:admin4_code":"8436012.0",
    "gn:asciiname":"Friesenhausle",
    "gn:country_code":"DE",
    "gn:dem":469,
    "gn:feature_class":"P",
    "gn:feature_code":"PPL",
    "gn:name":"Friesenh\u00e4usle",
    "gn:population":0,
    "gn:timezone":"Europe/Berlin",
    "iso:country":"DE",
    "wof:name":"Friesenhausle",
    "wof:placetype":"neighbourhood"
},
  "geometry": {"coordinates":[9.65836,47.84887],"type":"Point"}
}