{
  "type": "Feature",
  "properties": {
    "gn:admin1_code":"8",
    "gn:admin2_code":"0.0",
    "gn:admin3_code":"7132.0",
    "gn:admin4_code":"7132072.0",
    "gn:asciiname":"Niederschelderhuette",
    "gn:country_code":"DE",
    "gn:dem":289,
    "gn:feature_class":"P",
    "gn:feature_code":"PPL",
    "gn:name":"Niederschelderh\u00fctte",
    "gn:population":0,
    "gn:timezone":"Europe/Berlin",
    "iso:country":"DE",
    "wof:name":"Niederschelderhuette",
    "wof:placetype":"neighbourhood"
},
  "geometry": {"coordinates":[7.96127,50.84155],"type":"Point"}
}