{
  "type": "Feature",
  "properties": {
    "gn:admin1_code":"12",
    "gn:admin2_code":"0.0",
    "gn:admin3_code":"13073.0",
    "gn:admin4_code":"13073071.0",
    "gn:asciiname":"Goor",
    "gn:country_code":"DE",
    "gn:dem":26,
    "gn:feature_class":"P",
    "gn:feature_code":"PPL",
    "gn:name":"Goor",
    "gn:population":0,
    "gn:timezone":"Europe/Berlin",
    "iso:country":"DE",
    "name:ceb_x_preferred":[
        "Goor"
    ],
    "name:fas_x_preferred":[
        "\u062e\u0648\u0631"
    ],
    "name:fra_x_preferred":[
        "Goor"
    ],
    "name:ita_x_preferred":[
        "Goor"
    ],
    "name:lat_x_preferred":[
        "Gora"
    ],
    "name:nld_x_preferred":[
        "Goor"
    ],
    "name:rus_x_preferred":[
        "\u0413\u043e\u043e\u0440"
    ],
    "wof:name":"Goor",
    "wof:placetype":"neighbourhood"
},
  "geometry": {"coordinates":[13.42098,54.65794],"type":"Point"}
}