{
  "type": "Feature",
  "properties": {
    "gn:admin1_code":"1",
    "gn:admin2_code":"83.0",
    "gn:admin3_code":"8337.0",
    "gn:admin4_code":"8337051.0",
    "gn:asciiname":"Oberweschnegg",
    "gn:country_code":"DE",
    "gn:dem":892,
    "gn:feature_class":"P",
    "gn:feature_code":"PPL",
    "gn:name":"Oberweschnegg",
    "gn:population":0,
    "gn:timezone":"Europe/Berlin",
    "iso:country":"DE",
    "wof:name":"Oberweschnegg",
    "wof:placetype":"neighbourhood"
},
  "geometry": {"coordinates":[8.15515,47.70948],"type":"Point"}
}