{
  "type": "Feature",
  "properties": {
    "gn:admin1_code":"2",
    "gn:admin2_code":"95.0",
    "gn:admin3_code":"9571.0",
    "gn:admin4_code":"9571135.0",
    "gn:asciiname":"Oberschlauersbach",
    "gn:country_code":"DE",
    "gn:dem":366,
    "gn:feature_class":"P",
    "gn:feature_code":"PPL",
    "gn:name":"Oberschlauersbach",
    "gn:population":0,
    "gn:timezone":"Europe/Berlin",
    "iso:country":"DE",
    "wof:name":"Oberschlauersbach",
    "wof:placetype":"neighbourhood"
},
  "geometry": {"coordinates":[10.71337,49.4121],"type":"Point"}
}