{
  "type": "Feature",
  "properties": {
    "gn:admin1_code":"13",
    "gn:admin2_code":"0.0",
    "gn:admin3_code":"14625.0",
    "gn:admin4_code":"14625310.0",
    "gn:asciiname":"Lauta Dorf",
    "gn:country_code":"DE",
    "gn:dem":120,
    "gn:feature_class":"P",
    "gn:feature_code":"PPL",
    "gn:name":"Lauta Dorf",
    "gn:population":0,
    "gn:timezone":"Europe/Berlin",
    "iso:country":"DE",
    "wof:name":"Lauta Dorf",
    "wof:placetype":"neighbourhood"
},
  "geometry": {"coordinates":[14.06888,51.46306],"type":"Point"}
}