{
  "type": "Feature",
  "properties": {
    "gn:admin1_code":"12",
    "gn:admin2_code":"0.0",
    "gn:admin3_code":"13075.0",
    "gn:admin4_code":"13075137.0",
    "gn:asciiname":"Moenchow",
    "gn:country_code":"DE",
    "gn:dem":6,
    "gn:feature_class":"P",
    "gn:feature_code":"PPL",
    "gn:name":"M\u00f6nchow",
    "gn:population":0,
    "gn:timezone":"Europe/Berlin",
    "iso:country":"DE",
    "name:und_x_variant":[
        "Kolonie M\u00f6nchow",
        "M\u00f6nchow"
    ],
    "wof:name":"Moenchow",
    "wof:placetype":"neighbourhood"
},
  "geometry": {"coordinates":[13.87674,53.84343000000001],"type":"Point"}
}