{
  "type": "Feature",
  "properties": {
    "gn:admin1_code":"1",
    "gn:admin2_code":"81.0",
    "gn:admin3_code":"8125.0",
    "gn:admin4_code":"8125021.0",
    "gn:asciiname":"Klingenhof",
    "gn:country_code":"DE",
    "gn:dem":213,
    "gn:feature_class":"P",
    "gn:feature_code":"PPL",
    "gn:name":"Klingenhof",
    "gn:population":0,
    "gn:timezone":"Europe/Berlin",
    "iso:country":"DE",
    "wof:name":"Klingenhof",
    "wof:placetype":"neighbourhood"
},
  "geometry": {"coordinates":[9.33333,49.18333],"type":"Point"}
}