{
  "type": "Feature",
  "properties": {
    "gn:admin1_code":"2",
    "gn:admin2_code":"92.0",
    "gn:admin3_code":"9278.0",
    "gn:admin4_code":"9278123.0",
    "gn:asciiname":"Haindlingberg",
    "gn:country_code":"DE",
    "gn:dem":387,
    "gn:feature_class":"P",
    "gn:feature_code":"PPL",
    "gn:name":"Haindlingberg",
    "gn:population":0,
    "gn:timezone":"Europe/Berlin",
    "iso:country":"DE",
    "wof:name":"Haindlingberg",
    "wof:placetype":"neighbourhood"
},
  "geometry": {"coordinates":[12.41918,48.82553],"type":"Point"}
}