{
  "type": "Feature",
  "properties": {
    "gn:admin1_code":"15",
    "gn:admin2_code":"0.0",
    "gn:admin3_code":"16063.0",
    "gn:admin4_code":"16063004.0",
    "gn:asciiname":"Ettmarshausen",
    "gn:country_code":"DE",
    "gn:dem":246,
    "gn:feature_class":"P",
    "gn:feature_code":"PPL",
    "gn:name":"Ettmarshausen",
    "gn:population":0,
    "gn:timezone":"Europe/Berlin",
    "iso:country":"DE",
    "wof:name":"Ettmarshausen",
    "wof:placetype":"neighbourhood"
},
  "geometry": {"coordinates":[10.26693,50.80179],"type":"Point"}
}