{
  "type": "Feature",
  "properties": {
    "gn:admin1_code":"2",
    "gn:admin2_code":"97.0",
    "gn:admin3_code":"9780.0",
    "gn:admin4_code":"9780133.0",
    "gn:asciiname":"Kornau",
    "gn:country_code":"DE",
    "gn:dem":913,
    "gn:feature_class":"P",
    "gn:feature_code":"PPL",
    "gn:name":"Kornau",
    "gn:population":0,
    "gn:timezone":"Europe/Berlin",
    "iso:country":"DE",
    "wof:name":"Kornau",
    "wof:placetype":"neighbourhood"
},
  "geometry": {"coordinates":[10.24172,47.40516],"type":"Point"}
}