{
  "type": "Feature",
  "properties": {
    "gn:admin1_code":"5.0",
    "gn:admin2_code":"65.0",
    "gn:admin3_code":"6535.0",
    "gn:admin4_code":"6535007.0",
    "gn:asciiname":"Bermuthshain",
    "gn:country_code":"DE",
    "gn:dem":460,
    "gn:feature_class":"P",
    "gn:feature_code":"PPL",
    "gn:name":"Bermuthshain",
    "gn:population":0,
    "gn:timezone":"Europe/Berlin",
    "iso:country":"DE",
    "name:und_x_variant":[
        "Bermutshain",
        "Bermuthshain"
    ],
    "wof:name":"Bermuthshain",
    "wof:placetype":"neighbourhood"
},
  "geometry": {"coordinates":[9.31633,50.4723],"type":"Point"}
}