{
  "type": "Feature",
  "properties": {
    "gn:admin1_code":"5",
    "gn:admin2_code":"66.0",
    "gn:admin3_code":"6636.0",
    "gn:admin4_code":"6636006.0",
    "gn:asciiname":"Kuechen",
    "gn:country_code":"DE",
    "gn:dem":308,
    "gn:feature_class":"P",
    "gn:feature_code":"PPL",
    "gn:name":"K\u00fcchen",
    "gn:population":0,
    "gn:timezone":"Europe/Berlin",
    "iso:country":"DE",
    "wof:name":"Kuechen",
    "wof:placetype":"neighbourhood"
},
  "geometry": {"coordinates":[9.81862,51.1775],"type":"Point"}
}