{
  "type": "Feature",
  "properties": {
    "gn:admin1_code":"6",
    "gn:admin2_code":"0.0",
    "gn:admin3_code":"3353.0",
    "gn:admin4_code":"3353026.0",
    "gn:asciiname":"Schwiederstorf",
    "gn:country_code":"DE",
    "gn:dem":56,
    "gn:feature_class":"P",
    "gn:feature_code":"PPL",
    "gn:name":"Schwiederstorf",
    "gn:population":0,
    "gn:timezone":"Europe/Berlin",
    "iso:country":"DE",
    "name:deu_x_preferred":[
        "Schwiederstorf"
    ],
    "name:fas_x_preferred":[
        "\u0634\u0648\u06cc\u062f\u0631\u0633\u062a\u0648\u0631\u0641"
    ],
    "name:nds_x_preferred":[
        "Swiersd\u00f6rp"
    ],
    "wof:name":"Schwiederstorf",
    "wof:placetype":"neighbourhood"
},
  "geometry": {"coordinates":[9.79932,53.42253],"type":"Point"}
}