{
  "type": "Feature",
  "properties": {
    "gn:admin1_code":"6",
    "gn:admin2_code":"0.0",
    "gn:admin3_code":"3153.0",
    "gn:admin4_code":"3153012.0",
    "gn:asciiname":"Kirchberg",
    "gn:country_code":"DE",
    "gn:dem":193,
    "gn:feature_class":"P",
    "gn:feature_code":"PPL",
    "gn:name":"Kirchberg",
    "gn:population":0,
    "gn:timezone":"Europe/Berlin",
    "iso:country":"DE",
    "wof:name":"Kirchberg",
    "wof:placetype":"neighbourhood"
},
  "geometry": {"coordinates":[10.15921,51.85362],"type":"Point"}
}