{
  "type": "Feature",
  "properties": {
    "gn:admin1_code":"2.0",
    "gn:admin2_code":"94.0",
    "gn:admin3_code":"9473.0",
    "gn:admin4_code":"9473151.0",
    "gn:asciiname":"Boderndorf",
    "gn:country_code":"DE",
    "gn:dem":353,
    "gn:feature_class":"P",
    "gn:feature_code":"PPL",
    "gn:name":"Boderndorf",
    "gn:population":0,
    "gn:timezone":"Europe/Berlin",
    "iso:country":"DE",
    "wof:name":"Boderndorf",
    "wof:placetype":"neighbourhood"
},
  "geometry": {"coordinates":[11.0992,50.29507],"type":"Point"}
}