{
  "type": "Feature",
  "properties": {
    "gn:admin1_code":"2",
    "gn:admin2_code":"93.0",
    "gn:admin3_code":"9371.0",
    "gn:admin4_code":"9371151.0",
    "gn:asciiname":"Prangershof",
    "gn:country_code":"DE",
    "gn:dem":413,
    "gn:feature_class":"P",
    "gn:feature_code":"PPL",
    "gn:name":"Prangershof",
    "gn:population":0,
    "gn:timezone":"Europe/Berlin",
    "iso:country":"DE",
    "wof:name":"Prangershof",
    "wof:placetype":"neighbourhood"
},
  "geometry": {"coordinates":[11.71531,49.51686],"type":"Point"}
}