{
  "type": "Feature",
  "properties": {
    "gn:admin1_code":"13",
    "gn:admin2_code":"0.0",
    "gn:admin3_code":"14627.0",
    "gn:admin4_code":"14627200.0",
    "gn:asciiname":"Dallwitz",
    "gn:country_code":"DE",
    "gn:dem":132,
    "gn:feature_class":"P",
    "gn:feature_code":"PPL",
    "gn:name":"Dallwitz",
    "gn:population":0,
    "gn:timezone":"Europe/Berlin",
    "iso:country":"DE",
    "wof:name":"Dallwitz",
    "wof:placetype":"neighbourhood"
},
  "geometry": {"coordinates":[13.55457,51.24675],"type":"Point"}
}