{
  "type": "Feature",
  "properties": {
    "gn:admin1_code":"12",
    "gn:admin2_code":"0.0",
    "gn:admin3_code":"13076.0",
    "gn:admin4_code":"13076160.0",
    "gn:asciiname":"Meierstorf",
    "gn:country_code":"DE",
    "gn:dem":86,
    "gn:feature_class":"P",
    "gn:feature_code":"PPL",
    "gn:name":"Meierstorf",
    "gn:population":0,
    "gn:timezone":"Europe/Berlin",
    "iso:country":"DE",
    "name:und_x_variant":[
        "Meiersdorf",
        "Meierstorf"
    ],
    "wof:name":"Meierstorf",
    "wof:placetype":"neighbourhood"
},
  "geometry": {"coordinates":[11.85945,53.30537],"type":"Point"}
}