{
  "type": "Feature",
  "properties": {
    "gn:admin1_code":"2",
    "gn:admin2_code":"97.0",
    "gn:admin3_code":"9776.0",
    "gn:admin4_code":"9776128.0",
    "gn:asciiname":"Hege",
    "gn:country_code":"DE",
    "gn:dem":422,
    "gn:feature_class":"P",
    "gn:feature_code":"PPL",
    "gn:name":"Hege",
    "gn:population":0,
    "gn:timezone":"Europe/Berlin",
    "iso:country":"DE",
    "wof:name":"Hege",
    "wof:placetype":"neighbourhood"
},
  "geometry": {"coordinates":[9.62413,47.57658],"type":"Point"}
}