{
  "type": "Feature",
  "properties": {
    "gn:admin1_code":"2",
    "gn:admin2_code":"97.0",
    "gn:admin3_code":"9780.0",
    "gn:admin4_code":"9780119.0",
    "gn:asciiname":"Maierhof",
    "gn:country_code":"DE",
    "gn:dem":707,
    "gn:feature_class":"P",
    "gn:feature_code":"PPL",
    "gn:name":"Maierhof",
    "gn:population":0,
    "gn:timezone":"Europe/Berlin",
    "iso:country":"DE",
    "wof:name":"Maierhof",
    "wof:placetype":"neighbourhood"
},
  "geometry": {"coordinates":[10.20719,47.83396],"type":"Point"}
}