{
  "type": "Feature",
  "properties": {
    "gn:admin1_code":"15",
    "gn:admin2_code":"0.0",
    "gn:admin3_code":"16065.0",
    "gn:admin4_code":"16065033.0",
    "gn:asciiname":"Waldschloesschen",
    "gn:country_code":"DE",
    "gn:dem":157,
    "gn:feature_class":"P",
    "gn:feature_code":"PPL",
    "gn:name":"Waldschl\u00f6sschen",
    "gn:population":0,
    "gn:timezone":"Europe/Berlin",
    "iso:country":"DE",
    "wof:name":"Waldschloesschen",
    "wof:placetype":"neighbourhood"
},
  "geometry": {"coordinates":[11.21573,51.28938],"type":"Point"}
}