{
  "type": "Feature",
  "properties": {
    "gn:admin1_code":"7",
    "gn:admin2_code":"53.0",
    "gn:admin3_code":"5382.0",
    "gn:admin4_code":"5382064.0",
    "gn:asciiname":"Miel",
    "gn:country_code":"DE",
    "gn:dem":150,
    "gn:feature_class":"P",
    "gn:feature_code":"PPL",
    "gn:name":"Miel",
    "gn:population":0,
    "gn:timezone":"Europe/Berlin",
    "iso:country":"DE",
    "name:ceb_x_preferred":[
        "Miel"
    ],
    "name:deu_x_preferred":[
        "Miel"
    ],
    "name:fra_x_preferred":[
        "Miel"
    ],
    "wof:name":"Miel",
    "wof:placetype":"neighbourhood"
},
  "geometry": {"coordinates":[6.91726,50.67089],"type":"Point"}
}