{
  "type": "Feature",
  "properties": {
    "gn:admin1_code":"15",
    "gn:admin2_code":"0.0",
    "gn:admin3_code":"16075.0",
    "gn:admin4_code":"16075014.0",
    "gn:asciiname":"Sorna",
    "gn:country_code":"DE",
    "gn:dem":413,
    "gn:feature_class":"P",
    "gn:feature_code":"PPL",
    "gn:name":"Sorna",
    "gn:population":0,
    "gn:timezone":"Europe/Berlin",
    "iso:country":"DE",
    "name:deu_x_preferred":[
        "Sornay"
    ],
    "name:fas_x_preferred":[
        "\u0633\u0631\u0646\u0627"
    ],
    "name:glk_x_preferred":[
        "\u0633\u0624\u0631\u0646\u0627"
    ],
    "name:spa_x_preferred":[
        "Sorna"
    ],
    "name:uzb_x_preferred":[
        "Surnay"
    ],
    "wof:name":"Sorna",
    "wof:placetype":"neighbourhood"
},
  "geometry": {"coordinates":[11.86751,50.67325],"type":"Point"}
}