{
  "type": "Feature",
  "properties": {
    "gn:admin1_code":"2",
    "gn:admin2_code":"93.0",
    "gn:admin3_code":"9361.0",
    "gn:admin4_code":"9361000.0",
    "gn:asciiname":"Eglsee",
    "gn:country_code":"DE",
    "gn:dem":389,
    "gn:feature_class":"P",
    "gn:feature_code":"PPL",
    "gn:name":"Eglsee",
    "gn:population":0,
    "gn:timezone":"Europe/Berlin",
    "iso:country":"DE",
    "wof:name":"Eglsee",
    "wof:placetype":"neighbourhood"
},
  "geometry": {"coordinates":[11.83197,49.45067],"type":"Point"}
}