{
  "type": "Feature",
  "properties": {
    "gn:admin1_code":"5",
    "gn:admin2_code":"65.0",
    "gn:admin3_code":"6533.0",
    "gn:admin4_code":"6533008.0",
    "gn:asciiname":"Heringen",
    "gn:country_code":"DE",
    "gn:dem":224,
    "gn:feature_class":"P",
    "gn:feature_code":"PPL",
    "gn:name":"Heringen",
    "gn:population":0,
    "gn:timezone":"Europe/Berlin",
    "iso:country":"DE",
    "name:ara_x_preferred":[
        "\u0647\u0631\u064a\u0646\u063a\u0646"
    ],
    "name:azb_x_preferred":[
        "\u0647\u0631\u06cc\u0646\u0642\u0646"
    ],
    "name:deu_x_preferred":[
        "Heringen"
    ],
    "name:epo_x_preferred":[
        "Heringen"
    ],
    "name:fas_x_preferred":[
        "\u0647\u0631\u06cc\u0646\u06af\u0646"
    ],
    "name:fra_x_preferred":[
        "Heringen"
    ],
    "name:hun_x_preferred":[
        "Heringen"
    ],
    "name:ita_x_preferred":[
        "Heringen"
    ],
    "name:jpn_x_preferred":[
        "\u30d8\u30fc\u30ea\u30f3\u30b2\u30f3"
    ],
    "name:msa_x_preferred":[
        "Heringen"
    ],
    "name:nld_x_preferred":[
        "Heringen"
    ],
    "name:pol_x_preferred":[
        "Heringen"
    ],
    "name:ron_x_preferred":[
        "Heringen"
    ],
    "name:rus_x_preferred":[
        "\u0425\u0435\u0440\u0438\u043d\u0433\u0435\u043d"
    ],
    "name:spa_x_preferred":[
        "Heringen"
    ],
    "name:srp_x_preferred":[
        "\u0425\u0435\u0440\u0438\u043d\u0433\u0435\u043d"
    ],
    "name:tur_x_preferred":[
        "Heringen"
    ],
    "name:ukr_x_preferred":[
        "\u0413\u0435\u0440\u0456\u043d\u0433\u0435\u043d"
    ],
    "name:uzb_x_preferred":[
        "Heringen"
    ],
    "name:vol_x_preferred":[
        "Heringen"
    ],
    "name:war_x_preferred":[
        "Heringen"
    ],
    "name:zho_x_preferred":[
        "\u9ed1\u6797\u6839"
    ],
    "wof:name":"Heringen",
    "wof:placetype":"neighbourhood"
},
  "geometry": {"coordinates":[8.11341,50.31673],"type":"Point"}
}