{
  "type": "Feature",
  "properties": {
    "gn:admin1_code":"13",
    "gn:admin2_code":"0.0",
    "gn:admin3_code":"14522.0",
    "gn:admin4_code":"14522290.0",
    "gn:asciiname":"Rabenberg",
    "gn:country_code":"DE",
    "gn:dem":243,
    "gn:feature_class":"P",
    "gn:feature_code":"PPL",
    "gn:name":"Rabenberg",
    "gn:population":0,
    "gn:timezone":"Europe/Berlin",
    "iso:country":"DE",
    "wof:name":"Rabenberg",
    "wof:placetype":"neighbourhood"
},
  "geometry": {"coordinates":[12.80927,50.95854],"type":"Point"}
}