{
  "type": "Feature",
  "properties": {
    "gn:admin1_code":"11.0",
    "gn:admin2_code":"0.0",
    "gn:admin3_code":"12073.0",
    "gn:admin4_code":"12073201.0",
    "gn:asciiname":"Arnimswalde",
    "gn:country_code":"DE",
    "gn:dem":74,
    "gn:feature_class":"P",
    "gn:feature_code":"PPL",
    "gn:name":"Arnimswalde",
    "gn:population":0,
    "gn:timezone":"Europe/Berlin",
    "iso:country":"DE",
    "wof:name":"Arnimswalde",
    "wof:placetype":"neighbourhood"
},
  "geometry": {"coordinates":[13.73789,53.11683000000001],"type":"Point"}
}