{
  "type": "Feature",
  "properties": {
    "gn:admin1_code":"1",
    "gn:admin2_code":"83.0",
    "gn:admin3_code":"8336.0",
    "gn:admin4_code":"8336103.0",
    "gn:asciiname":"Gaisbuhl",
    "gn:country_code":"DE",
    "gn:dem":760,
    "gn:feature_class":"P",
    "gn:feature_code":"PPL",
    "gn:name":"Gaisb\u00fchl",
    "gn:population":0,
    "gn:timezone":"Europe/Berlin",
    "iso:country":"DE",
    "wof:name":"Gaisbuhl",
    "wof:placetype":"neighbourhood"
},
  "geometry": {"coordinates":[7.88475,47.69746],"type":"Point"}
}