{
  "type": "Feature",
  "properties": {
    "gn:admin1_code":"6.0",
    "gn:admin2_code":"0.0",
    "gn:admin3_code":"3453.0",
    "gn:admin4_code":"3453002.0",
    "gn:asciiname":"Aumuehlen",
    "gn:country_code":"DE",
    "gn:dem":9,
    "gn:feature_class":"P",
    "gn:feature_code":"PPL",
    "gn:name":"Aum\u00fchlen",
    "gn:population":0,
    "gn:timezone":"Europe/Berlin",
    "iso:country":"DE",
    "wof:name":"Aumuehlen",
    "wof:placetype":"neighbourhood"
},
  "geometry": {"coordinates":[7.9968,53.00803000000001],"type":"Point"}
}