{
  "type": "Feature",
  "properties": {
    "gn:admin1_code":"11.0",
    "gn:admin2_code":"00",
    "gn:admin3_code":"12064.0",
    "gn:admin4_code":"12064448.0",
    "gn:asciiname":"Zernickow",
    "gn:country_code":"DE",
    "gn:dem":51,
    "gn:feature_class":"P",
    "gn:feature_code":"PPL",
    "gn:name":"Zernickow",
    "gn:population":0,
    "gn:timezone":"Europe/Berlin",
    "iso:country":"DE",
    "wof:name":"Zernickow",
    "wof:placetype":"neighbourhood"
},
  "geometry": {"coordinates":[14.37964,52.52186],"type":"Point"}
}