{
  "type": "Feature",
  "properties": {
    "gn:admin1_code":"7.0",
    "gn:admin2_code":"057",
    "gn:admin3_code":"5770.0",
    "gn:admin4_code":"5770004.0",
    "gn:asciiname":"Wenden",
    "gn:country_code":"DE",
    "gn:dem":163,
    "gn:feature_class":"P",
    "gn:feature_code":"PPLL",
    "gn:name":"Wenden",
    "gn:population":0,
    "gn:timezone":"Europe/Berlin",
    "iso:country":"DE",
    "name:ceb_x_preferred":[
        "Wenden"
    ],
    "name:deu_x_preferred":[
        "Wenden"
    ],
    "name:epo_x_preferred":[
        "Wenden"
    ],
    "name:ita_x_preferred":[
        "Wenden"
    ],
    "name:nld_x_preferred":[
        "Wenden"
    ],
    "name:pol_x_preferred":[
        "Wenden"
    ],
    "name:por_x_preferred":[
        "Wenden"
    ],
    "name:srp_x_preferred":[
        "\u0412\u0435\u043d\u0434\u0438"
    ],
    "name:ukr_x_preferred":[
        "\u0412\u0435\u043d\u0434\u0435\u043d"
    ],
    "name:vol_x_preferred":[
        "Wenden"
    ],
    "wof:name":"Wenden",
    "wof:placetype":"neighbourhood"
},
  "geometry": {"coordinates":[8.78382,52.1726],"type":"Point"}
}