{
  "type": "Feature",
  "properties": {
    "gn:admin1_code":"1",
    "gn:admin2_code":"83.0",
    "gn:admin3_code":"8335.0",
    "gn:admin4_code":"8335021.0",
    "gn:asciiname":"Heudorf",
    "gn:country_code":"DE",
    "gn:dem":630,
    "gn:feature_class":"P",
    "gn:feature_code":"PPL",
    "gn:name":"Heudorf",
    "gn:population":0,
    "gn:timezone":"Europe/Berlin",
    "iso:country":"DE",
    "wof:name":"Heudorf",
    "wof:placetype":"neighbourhood"
},
  "geometry": {"coordinates":[8.93558,47.9137],"type":"Point"}
}