{
  "type": "Feature",
  "properties": {
    "gn:admin1_code":"7",
    "gn:admin2_code":"57.0",
    "gn:admin3_code":"5770.0",
    "gn:admin4_code":"5770040.0",
    "gn:asciiname":"Muehlendamm",
    "gn:country_code":"DE",
    "gn:dem":43,
    "gn:feature_class":"P",
    "gn:feature_code":"PPL",
    "gn:name":"M\u00fchlendamm",
    "gn:population":0,
    "gn:timezone":"Europe/Berlin",
    "iso:country":"DE",
    "wof:name":"Muehlendamm",
    "wof:placetype":"neighbourhood"
},
  "geometry": {"coordinates":[8.59197,52.44268],"type":"Point"}
}