{
  "type": "Feature",
  "properties": {
    "gn:admin1_code":"2",
    "gn:admin2_code":"93.0",
    "gn:admin3_code":"9377.0",
    "gn:admin4_code":"9377159.0",
    "gn:asciiname":"Schonfeld",
    "gn:country_code":"DE",
    "gn:dem":518,
    "gn:feature_class":"P",
    "gn:feature_code":"PPL",
    "gn:name":"Sch\u00f6nfeld",
    "gn:population":0,
    "gn:timezone":"Europe/Berlin",
    "iso:country":"DE",
    "wof:name":"Schonfeld",
    "wof:placetype":"neighbourhood"
},
  "geometry": {"coordinates":[12.19314,49.92336],"type":"Point"}
}