{
  "type": "Feature",
  "properties": {
    "gn:admin1_code":"12",
    "gn:admin2_code":"0.0",
    "gn:admin3_code":"13073.0",
    "gn:admin4_code":"13073055.0",
    "gn:asciiname":"Rostocker Wulfshagen",
    "gn:cc2":"DE",
    "gn:country_code":"DE",
    "gn:dem":27,
    "gn:feature_class":"P",
    "gn:feature_code":"PPL",
    "gn:name":"Rostocker Wulfshagen",
    "gn:population":0,
    "gn:timezone":"Europe/Berlin",
    "iso:country":"DE",
    "name:und_x_variant":[
        "Wulfshagen"
    ],
    "wof:name":"Rostocker Wulfshagen",
    "wof:placetype":"neighbourhood"
},
  "geometry": {"coordinates":[12.39472,54.17906],"type":"Point"}
}