{
  "type": "Feature",
  "properties": {
    "iso:country":"DE",
    "name:deu_x_preferred":[
        "\u017babiny"
    ],
    "name:deu_x_variant":[
        "Seeben"
    ],
    "name:pol_x_preferred":[
        "\u017babiny"
    ],
    "name:urd_x_preferred":[
        "\u0632\u0627\u0628\u0646\u06d2"
    ],
    "qs:gn_fcode":"PPL",
    "qs:gn_local":0,
    "qs:gn_namadm1":"14",
    "qs:gn_name":"Seeben",
    "qs:local_max":8020,
    "qs:local_sum":17049,
    "qs:localhoods":23,
    "qs:name":"Seeben",
    "qs:name_adm0":"Deutschland",
    "qs:name_adm1":"Sachsen-Anhalt",
    "qs:name_adm2":"Stadtkreis Halle",
    "qs:name_lau":"Halle (Saale)",
    "qs:name_local":"Halle (Saale)",
    "qs:photo_max":1,
    "qs:photo_sum":1,
    "qs:placetype":"Suburb",
    "qs:quad_count":1,
    "qs:woe_adm0":23424829,
    "qs:woe_adm1":2345494,
    "qs:woe_adm2":12597046,
    "qs:woe_lau":56556603,
    "qs:woe_local":56556603,
    "qs:woe_ver":"7.10.0",
    "wof:lang":[
        "ger"
    ],
    "wof:name":"Seeben",
    "wof:placetype":"neighbourhood"
},
  "geometry": {"coordinates":[11.977844,51.53096],"type":"Point"}
}