{
  "type": "Feature",
  "properties": {
    "gn:admin1_code":"14",
    "gn:admin2_code":"0.0",
    "gn:admin3_code":"15089.0",
    "gn:admin4_code":"15089075.0",
    "gn:asciiname":"Egeln Nord",
    "gn:country_code":"DE",
    "gn:dem":72,
    "gn:feature_class":"P",
    "gn:feature_code":"PPL",
    "gn:name":"Egeln Nord",
    "gn:population":0,
    "gn:timezone":"Europe/Berlin",
    "iso:country":"DE",
    "name:deu_x_historical":[
        "Bleckendorf"
    ],
    "name:deu_x_preferred":[
        "Bleckendorf"
    ],
    "wof:name":"Egeln Nord",
    "wof:placetype":"neighbourhood"
},
  "geometry": {"coordinates":[11.43479,51.96125],"type":"Point"}
}