{
  "type": "Feature",
  "properties": {
    "gn:country":"DE",
    "gn:fcode":"PPL",
    "gn:population":0,
    "iso:country":"DE",
    "name:bar_x_preferred":[
        "Spyker"
    ],
    "name:ces_x_preferred":[
        "Spyker"
    ],
    "name:deu_x_preferred":[
        "Spyker"
    ],
    "name:fra_x_preferred":[
        "Spyker"
    ],
    "name:hrv_x_preferred":[
        "Spyker"
    ],
    "name:ita_x_preferred":[
        "Spyker"
    ],
    "name:jpn_x_preferred":[
        "\u30b9\u30d1\u30a4\u30ab\u30fc"
    ],
    "name:nld_x_preferred":[
        "Spyker"
    ],
    "name:nor_x_preferred":[
        "Spyker"
    ],
    "name:pol_x_preferred":[
        "Spyker"
    ],
    "name:por_x_preferred":[
        "Spyker"
    ],
    "name:ukr_x_preferred":[
        "Spyker"
    ],
    "qs_pg:aaroncc":"DE",
    "qs_pg:gn_country":"DE",
    "qs_pg:gn_fcode":"PPL",
    "qs_pg:gn_pop":0,
    "qs_pg:name":"Spyker",
    "qs_pg:name_adm0":"Deutschland",
    "qs_pg:name_adm1":"Mecklenburg-Vorpommern",
    "qs_pg:photos_9r":0,
    "qs_pg:photos_sr":0,
    "qs_pg:pop_sr":0,
    "qs_pg:qs_pg_placetype":"locality",
    "qs_pg:qs_pg_placetype_gp":"Town",
    "qs_pg:woe_adm0":23424829,
    "woe:adm0_id":23424829,
    "woe:name_adm0":"Deutschland",
    "woe:name_adm1":"Mecklenburg-Vorpommern",
    "woe:placetype":"Town",
    "wof:name":"Spyker",
    "wof:placetype":"neighbourhood"
},
  "geometry": {"coordinates":[13.51327,54.55688],"type":"Point"}
}