{
  "type": "Feature",
  "properties": {
    "gn:gn_country":"DE",
    "gn:gn_fcode":"ADM4",
    "gn:gn_pop":322,
    "gn:population":312,
    "iso:country":"DE",
    "name:baq_x_preferred":[
        "Rutsweiler am Glan"
    ],
    "name:chi_x_preferred":[
        "\u683c\u5170\u6cb3\u7554\u9c81\u8328\u9b4f\u83b1\u5c14"
    ],
    "name:dut_x_preferred":[
        "Rutsweiler am Glan"
    ],
    "name:eng_x_preferred":[
        "Rutsweiler am Glan"
    ],
    "name:epo_x_preferred":[
        "Rutsweiler am Glan"
    ],
    "name:fre_x_preferred":[
        "Rutsweiler am Glan"
    ],
    "name:ger_x_preferred":[
        "Rutsweiler am Glan"
    ],
    "name:hun_x_preferred":[
        "Rutsweiler am Glan"
    ],
    "name:ita_x_preferred":[
        "Rutsweiler am Glan"
    ],
    "name:jpn_x_preferred":[
        "\u30eb\u30c4\u30f4\u30a1\u30a4\u30e9\u30fc\u30fb\u30a2\u30e0\u30fb\u30b0\u30e9\u30f3"
    ],
    "name:may_x_preferred":[
        "Rutsweiler am Glan"
    ],
    "name:pol_x_preferred":[
        "Rutsweiler am Glan"
    ],
    "name:por_x_preferred":[
        "Rutsweiler am Glan"
    ],
    "name:rum_x_preferred":[
        "Rutsweiler am Glan"
    ],
    "name:rus_x_preferred":[
        "\u0420\u0443\u0442\u0441\u0432\u0430\u0439\u043b\u0435\u0440-\u043d\u0430-\u0413\u043b\u0430\u043d\u0435"
    ],
    "name:srp_x_preferred":[
        "\u0420\u0443\u0442\u0441\u0432\u0430\u0458\u043b\u0435\u0440 \u0430\u043c \u0413\u043b\u0430\u043d"
    ],
    "name:ukr_x_preferred":[
        "\u0420\u0443\u0442\u0441\u0432\u0430\u0439\u043b\u0435\u0440-\u0430\u043c-\u0413\u043b\u0430\u043d"
    ],
    "name:uzb_x_preferred":[
        "Rutsweiler am Glan"
    ],
    "name:vie_x_preferred":[
        "Rutsweiler am Glan"
    ],
    "name:vol_x_preferred":[
        "Rutsweiler am Glan"
    ],
    "name:war_x_preferred":[
        "Rutsweiler am Glan"
    ],
    "qs_pg:aaroncc":"DE",
    "qs_pg:gn_country":"DE",
    "qs_pg:gn_fcode":"ADM4",
    "qs_pg:gn_pop":322,
    "qs_pg:name":"Rutsweiler am Glan",
    "qs_pg:name_adm0":"Deutschland",
    "qs_pg:name_adm1":"Rheinland-Pfalz",
    "qs_pg:photos_9r":0,
    "qs_pg:photos_sr":0,
    "qs_pg:pop_sr":2,
    "qs_pg:qs_pg_placetype":"locality",
    "qs_pg:qs_pg_placetype_gp":"Town",
    "qs_pg:woe_adm0":23424829,
    "woe:adm0_id":23424829,
    "woe:name_adm0":"Deutschland",
    "woe:name_adm1":"Rheinland-Pfalz",
    "woe:placetype":"Town",
    "wof:name":"Rutsweiler am Glan",
    "wof:placetype":"locality",
    "wof:population":312
},
  "geometry": {"coordinates":[7.45,49.5333],"type":"Point"}
}