{
  "type": "Feature",
  "properties": {
    "gn:admin1_code":"2",
    "gn:admin2_code":"93.0",
    "gn:admin3_code":"9371.0",
    "gn:admin4_code":"9371150.0",
    "gn:asciiname":"Forst",
    "gn:country_code":"DE",
    "gn:dem":416,
    "gn:feature_class":"P",
    "gn:feature_code":"PPL",
    "gn:name":"Forst",
    "gn:population":0,
    "gn:timezone":"Europe/Berlin",
    "iso:country":"DE",
    "name:ceb_x_preferred":[
        "Forst"
    ],
    "name:deu_x_preferred":[
        "Forst"
    ],
    "name:epo_x_preferred":[
        "Forst"
    ],
    "name:eus_x_preferred":[
        "Forst"
    ],
    "name:fra_x_preferred":[
        "Forst"
    ],
    "name:hun_x_preferred":[
        "Forst"
    ],
    "name:ita_x_preferred":[
        "Forst"
    ],
    "name:lim_x_preferred":[
        "Forst"
    ],
    "name:nld_x_preferred":[
        "Forst"
    ],
    "name:pfl_x_preferred":[
        "Forst"
    ],
    "name:pol_x_preferred":[
        "Forst"
    ],
    "name:por_x_preferred":[
        "Forst"
    ],
    "name:ron_x_preferred":[
        "Forst"
    ],
    "name:rus_x_preferred":[
        "\u0424\u043e\u0440\u0441\u0442"
    ],
    "name:spa_x_preferred":[
        "Forst"
    ],
    "name:srp_x_preferred":[
        "\u0424\u043e\u0440\u0441\u0442"
    ],
    "name:swe_x_preferred":[
        "Forst"
    ],
    "name:ukr_x_preferred":[
        "\u0424\u043e\u0440\u0441\u0442"
    ],
    "name:vol_x_preferred":[
        "Forst"
    ],
    "wof:name":"Forst",
    "wof:placetype":"neighbourhood"
},
  "geometry": {"coordinates":[12.00696,49.55292],"type":"Point"}
}