{
  "type": "Feature",
  "properties": {
    "gn:admin1_code":"2.0",
    "gn:admin2_code":"91.0",
    "gn:admin3_code":"9172.0",
    "gn:admin4_code":"9172122.0",
    "gn:asciiname":"Abtsee",
    "gn:country_code":"DE",
    "gn:dem":437,
    "gn:feature_class":"P",
    "gn:feature_code":"PPLL",
    "gn:name":"Abtsee",
    "gn:population":0,
    "gn:timezone":"Europe/Berlin",
    "iso:country":"DE",
    "wof:name":"Abtsee",
    "wof:placetype":"neighbourhood"
},
  "geometry": {"coordinates":[12.90716,47.91444],"type":"Point"}
}