{
  "type": "Feature",
  "properties": {
    "gn:admin1_code":"12",
    "gn:admin2_code":"0.0",
    "gn:admin3_code":"13076.0",
    "gn:admin4_code":"13076088.0",
    "gn:asciiname":"Gudow",
    "gn:country_code":"DE",
    "gn:dem":11,
    "gn:feature_class":"P",
    "gn:feature_code":"PPL",
    "gn:name":"Gudow",
    "gn:population":0,
    "gn:timezone":"Europe/Berlin",
    "iso:country":"DE",
    "name:ceb_x_preferred":[
        "Gudow"
    ],
    "name:dan_x_preferred":[
        "Gudow"
    ],
    "name:deu_x_preferred":[
        "Gudow"
    ],
    "name:epo_x_preferred":[
        "Gudow"
    ],
    "name:eus_x_preferred":[
        "Gudow"
    ],
    "name:fas_x_preferred":[
        "\u06af\u0648\u062f\u0648\u0648"
    ],
    "name:fra_x_preferred":[
        "Gudow"
    ],
    "name:hun_x_preferred":[
        "Gudow"
    ],
    "name:ita_x_preferred":[
        "Gudow"
    ],
    "name:mkd_x_preferred":[
        "\u0413\u0443\u0434\u043e\u0432"
    ],
    "name:msa_x_preferred":[
        "Gudow"
    ],
    "name:nld_x_preferred":[
        "Gudow"
    ],
    "name:pol_x_preferred":[
        "Gudow"
    ],
    "name:por_x_preferred":[
        "Gudow"
    ],
    "name:ron_x_preferred":[
        "Gudow"
    ],
    "name:rus_x_preferred":[
        "\u0413\u0443\u0434\u043e\u0432"
    ],
    "name:spa_x_preferred":[
        "Gudow"
    ],
    "name:srp_x_preferred":[
        "\u0413\u0443\u0434\u043e\u0432"
    ],
    "name:tur_x_preferred":[
        "Gudow"
    ],
    "name:ukr_x_preferred":[
        "\u0413\u0443\u0434\u043e\u0432"
    ],
    "name:uzb_x_preferred":[
        "Gudow"
    ],
    "name:vie_x_preferred":[
        "Gudow"
    ],
    "name:vol_x_preferred":[
        "Gudow"
    ],
    "name:war_x_preferred":[
        "Gudow"
    ],
    "name:zho_x_preferred":[
        "\u53e4\u591a\u592b"
    ],
    "wof:name":"Gudow",
    "wof:placetype":"neighbourhood"
},
  "geometry": {"coordinates":[11.00744,53.29334],"type":"Point"}
}