{
  "type": "Feature",
  "properties": {
    "gn:admin1_code":"12.0",
    "gn:admin2_code":"00",
    "gn:admin3_code":"13073.0",
    "gn:admin4_code":"13073071.0",
    "gn:asciiname":"Wollin",
    "gn:country_code":"DE",
    "gn:dem":17,
    "gn:feature_class":"P",
    "gn:feature_code":"PPL",
    "gn:name":"Wollin",
    "gn:population":0,
    "gn:timezone":"Europe/Berlin",
    "iso:country":"DE",
    "wof:name":"Wollin",
    "wof:placetype":"neighbourhood"
},
  "geometry": {"coordinates":[13.37562,54.65141],"type":"Point"}
}