{
  "type": "Feature",
  "properties": {
    "gn:admin1_code":"11",
    "gn:admin2_code":"0.0",
    "gn:admin3_code":"12061.0",
    "gn:admin4_code":"12061405.0",
    "gn:asciiname":"Kolonie Rietze",
    "gn:country_code":"DE",
    "gn:dem":51,
    "gn:feature_class":"P",
    "gn:feature_code":"PPL",
    "gn:name":"Kolonie Rietze",
    "gn:population":0,
    "gn:timezone":"Europe/Berlin",
    "iso:country":"DE",
    "wof:name":"Kolonie Rietze",
    "wof:placetype":"neighbourhood"
},
  "geometry": {"coordinates":[13.6578,52.01706],"type":"Point"}
}