{
  "type": "Feature",
  "properties": {
    "gn:admin1_code":"11",
    "gn:admin2_code":"0.0",
    "gn:admin3_code":"12073.0",
    "gn:admin4_code":"12073008.0",
    "gn:asciiname":"Neuhof",
    "gn:country_code":"DE",
    "gn:dem":59,
    "gn:feature_class":"P",
    "gn:feature_code":"PPL",
    "gn:name":"Neuhof",
    "gn:population":0,
    "gn:timezone":"Europe/Berlin",
    "iso:country":"DE",
    "name:ceb_x_preferred":[
        "Neuhof"
    ],
    "name:deu_x_preferred":[
        "Neuhof"
    ],
    "name:epo_x_preferred":[
        "Neuhof"
    ],
    "name:eus_x_preferred":[
        "Neuhof"
    ],
    "name:fra_x_preferred":[
        "Neuhof"
    ],
    "name:hun_x_preferred":[
        "Neuhof"
    ],
    "name:ita_x_preferred":[
        "Neuhof"
    ],
    "name:lav_x_preferred":[
        "Neuhof"
    ],
    "name:mkd_x_preferred":[
        "\u041d\u043e\u0458\u0445\u043e\u0444"
    ],
    "name:nld_x_preferred":[
        "Neuhof"
    ],
    "name:pol_x_preferred":[
        "Neuhof"
    ],
    "name:rus_x_preferred":[
        "\u041d\u0435\u0439\u0433\u043e\u0444"
    ],
    "name:srp_x_preferred":[
        "\u041d\u043e\u0458\u0445\u043e\u0444"
    ],
    "name:swe_x_preferred":[
        "Neuhof"
    ],
    "name:vol_x_preferred":[
        "Neuhof"
    ],
    "wof:name":"Neuhof",
    "wof:placetype":"neighbourhood"
},
  "geometry": {"coordinates":[14.08241,53.01989],"type":"Point"}
}