{
  "type": "Feature",
  "properties": {
    "gn:country":"DE",
    "gn:fcode":"PPL",
    "gn:population":0,
    "iso:country":"DE",
    "name:ceb_x_preferred":[
        "Sprendlingen"
    ],
    "name:deu_x_preferred":[
        "Sprendlingen"
    ],
    "name:epo_x_preferred":[
        "Sprendlingen"
    ],
    "name:eus_x_preferred":[
        "Sprendlingen"
    ],
    "name:fas_x_preferred":[
        "\u0634\u067e\u0631\u0646\u062f\u0644\u06cc\u0646\u06af\u0646"
    ],
    "name:fra_x_preferred":[
        "Sprendlingen"
    ],
    "name:hun_x_preferred":[
        "Sprendlingen"
    ],
    "name:ita_x_preferred":[
        "Sprendlingen"
    ],
    "name:jpn_x_preferred":[
        "\u30b7\u30e5\u30d7\u30ec\u30f3\u30c8\u30ea\u30f3\u30b2\u30f3"
    ],
    "name:msa_x_preferred":[
        "Sprendlingen"
    ],
    "name:nld_x_preferred":[
        "Sprendlingen"
    ],
    "name:pol_x_preferred":[
        "Sprendlingen"
    ],
    "name:por_x_preferred":[
        "Sprendlingen"
    ],
    "name:ron_x_preferred":[
        "Sprendlingen"
    ],
    "name:rus_x_preferred":[
        "\u0428\u043f\u0440\u0435\u043d\u0434\u043b\u0438\u043d\u0433\u0435\u043d"
    ],
    "name:spa_x_preferred":[
        "Sprendlingen"
    ],
    "name:srp_x_preferred":[
        "\u0428\u043f\u0440\u0435\u043d\u0434\u043b\u0438\u043d\u0433\u0435\u043d"
    ],
    "name:ukr_x_preferred":[
        "\u0428\u043f\u0440\u0435\u043d\u0434\u043b\u0456\u043d\u0433\u0435\u043d"
    ],
    "name:uzb_x_preferred":[
        "Sprendlingen"
    ],
    "name:vol_x_preferred":[
        "Sprendlingen"
    ],
    "name:war_x_preferred":[
        "Sprendlingen"
    ],
    "name:zho_x_preferred":[
        "\u65bd\u666e\u4f26\u5fb7\u6797\u6839"
    ],
    "qs_pg:aaroncc":"DE",
    "qs_pg:gn_country":"DE",
    "qs_pg:gn_fcode":"PPL",
    "qs_pg:gn_pop":0,
    "qs_pg:name":"Sprendlingen",
    "qs_pg:name_adm0":"Deutschland",
    "qs_pg:name_adm1":"Hessen",
    "qs_pg:photos":15,
    "qs_pg:photos_1k":3,
    "qs_pg:photos_9k":1,
    "qs_pg:photos_9r":1,
    "qs_pg:photos_all":15,
    "qs_pg:photos_sr":1,
    "qs_pg:pop_sr":0,
    "qs_pg:qs_pg_placetype":"locality",
    "qs_pg:qs_pg_placetype_gp":"Town",
    "qs_pg:woe_adm0":23424829,
    "woe:adm0_id":23424829,
    "woe:name_adm0":"Deutschland",
    "woe:name_adm1":"Hessen",
    "woe:placetype":"Town",
    "wof:name":"Sprendlingen",
    "wof:placetype":"neighbourhood"
},
  "geometry": {"coordinates":[8.69944,50.02495],"type":"Point"}
}