{
  "type": "Feature",
  "properties": {
    "gn:admin1_code":"7.0",
    "gn:admin2_code":"51.0",
    "gn:admin3_code":"5122.0",
    "gn:admin4_code":"5122000.0",
    "gn:asciiname":"Haesten",
    "gn:country_code":"DE",
    "gn:dem":226,
    "gn:feature_class":"P",
    "gn:feature_code":"PPL",
    "gn:name":"H\u00e4sten",
    "gn:population":0,
    "gn:timezone":"Europe/Berlin",
    "iso:country":"DE",
    "name:deu_x_preferred":[
        "H\u00e4sten"
    ],
    "wof:name":"Haesten",
    "wof:placetype":"neighbourhood"
},
  "geometry": {"coordinates":[7.111969,51.144601],"type":"Point"}
}