{
  "type": "Feature",
  "properties": {
    "iso:country":"DE",
    "name:deu_x_preferred":[
        "H\u00e4sten"
    ],
    "wof:name":"Haesten",
    "wof:placetype":"neighbourhood"
},
  "geometry": {"coordinates":[7.11196943926144,51.14460055455519],"type":"Point"}
}