{
  "type": "Feature",
  "properties": {
    "gn:admin1_code":"2",
    "gn:admin2_code":"91.0",
    "gn:admin3_code":"9186.0",
    "gn:admin4_code":"9186146.0",
    "gn:asciiname":"Langwaid",
    "gn:country_code":"DE",
    "gn:dem":487,
    "gn:feature_class":"P",
    "gn:feature_code":"PPL",
    "gn:name":"Langwaid",
    "gn:population":0,
    "gn:timezone":"Europe/Berlin",
    "iso:country":"DE",
    "wof:name":"Langwaid",
    "wof:placetype":"neighbourhood"
},
  "geometry": {"coordinates":[11.45226,48.45891],"type":"Point"}
}