{
  "type": "Feature",
  "properties": {
    "gn:admin1_code":"2",
    "gn:admin2_code":"92.0",
    "gn:admin3_code":"9277.0",
    "gn:admin4_code":"9277145.0",
    "gn:asciiname":"Mitternberg",
    "gn:country_code":"DE",
    "gn:dem":414,
    "gn:feature_class":"P",
    "gn:feature_code":"PPL",
    "gn:name":"Mitternberg",
    "gn:population":0,
    "gn:timezone":"Europe/Berlin",
    "iso:country":"DE",
    "wof:name":"Mitternberg",
    "wof:placetype":"neighbourhood"
},
  "geometry": {"coordinates":[13.02467,48.28178],"type":"Point"}
}