{
  "type": "Feature",
  "properties": {
    "gn:admin1_code":"15",
    "gn:admin2_code":"0.0",
    "gn:admin3_code":"16075.0",
    "gn:admin4_code":"16075134.0",
    "gn:asciiname":"Roedern",
    "gn:country_code":"DE",
    "gn:dem":522,
    "gn:feature_class":"P",
    "gn:feature_code":"PPL",
    "gn:name":"R\u00f6dern",
    "gn:population":0,
    "gn:timezone":"Europe/Berlin",
    "iso:country":"DE",
    "wof:name":"Roedern",
    "wof:placetype":"neighbourhood"
},
  "geometry": {"coordinates":[11.62407,50.53172],"type":"Point"}
}