{
  "type": "Feature",
  "properties": {
    "iso:country":"DE",
    "name:ceb_x_preferred":[
        "Rotherbaum"
    ],
    "name:deu_x_preferred":[
        "Rotherbaum"
    ],
    "name:eng_x_preferred":[
        "Rotherbaum"
    ],
    "name:fas_x_preferred":[
        "\u0631\u0648\u062a\u0631\u0628\u0627\u0648\u0645"
    ],
    "name:fra_x_preferred":[
        "Hamburg-Rotherbaum"
    ],
    "name:hun_x_preferred":[
        "Rotherbaum"
    ],
    "name:hye_x_preferred":[
        "\u054c\u0578\u057f\u0565\u0580\u0562\u0561\u0578\u0582\u0574"
    ],
    "name:ita_x_preferred":[
        "Rotherbaum"
    ],
    "name:jpn_x_preferred":[
        "\u30ed\u30fc\u30bf\u30fc\u30d0\u30a6\u30e0"
    ],
    "name:lat_x_preferred":[
        "Hamburg-Rotherbaum"
    ],
    "name:mkd_x_preferred":[
        "\u0420\u043e\u0442\u0435\u0440\u0431\u0430\u0443\u043c"
    ],
    "name:nld_x_preferred":[
        "Rotherbaum"
    ],
    "name:pol_x_preferred":[
        "Rotherbaum"
    ],
    "name:rus_x_preferred":[
        "\u0420\u043e\u0442\u0435\u0440\u0431\u0430\u0443\u043c"
    ],
    "name:spa_x_preferred":[
        "Rotherbaum"
    ],
    "name:swe_x_preferred":[
        "Grossluga"
    ],
    "wof:name":"Rotherbaum",
    "wof:placetype":"neighbourhood"
},
  "geometry": {"coordinates":[9.98852474860449,53.56658253310244],"type":"Point"}
}