{
  "type": "Feature",
  "properties": {
    "gn:admin1_code":"2",
    "gn:admin2_code":"92.0",
    "gn:admin3_code":"9275.0",
    "gn:admin4_code":"9275146.0",
    "gn:asciiname":"Frankldorf",
    "gn:country_code":"DE",
    "gn:dem":425,
    "gn:feature_class":"P",
    "gn:feature_code":"PPL",
    "gn:name":"Frankldorf",
    "gn:population":0,
    "gn:timezone":"Europe/Berlin",
    "iso:country":"DE",
    "wof:name":"Frankldorf",
    "wof:placetype":"neighbourhood"
},
  "geometry": {"coordinates":[13.482,48.63014],"type":"Point"}
}