{
  "type": "Feature",
  "properties": {
    "gn:admin1_code":"2.0",
    "gn:admin2_code":"91.0",
    "gn:admin3_code":"9184.0",
    "gn:admin4_code":"9184135.0",
    "gn:asciiname":"Badersfeld",
    "gn:country_code":"DE",
    "gn:dem":479,
    "gn:feature_class":"P",
    "gn:feature_code":"PPL",
    "gn:name":"Badersfeld",
    "gn:population":0,
    "gn:timezone":"Europe/Berlin",
    "iso:country":"DE",
    "wof:name":"Badersfeld",
    "wof:placetype":"neighbourhood"
},
  "geometry": {"coordinates":[11.52005,48.25938],"type":"Point"}
}