{
  "type": "Feature",
  "properties": {
    "gn:admin1_code":"12",
    "gn:admin2_code":"0.0",
    "gn:admin3_code":"13071.0",
    "gn:admin4_code":"13071029.0",
    "gn:asciiname":"Seedorf",
    "gn:country_code":"DE",
    "gn:dem":8,
    "gn:feature_class":"P",
    "gn:feature_code":"PPL",
    "gn:name":"Seedorf",
    "gn:population":0,
    "gn:timezone":"Europe/Berlin",
    "iso:country":"DE",
    "name:als_x_preferred":[
        "Seedorf"
    ],
    "name:cat_x_preferred":[
        "Seedorf"
    ],
    "name:ceb_x_preferred":[
        "Seedorf"
    ],
    "name:dan_x_preferred":[
        "Seedorf"
    ],
    "name:deu_x_preferred":[
        "Seedorf"
    ],
    "name:epo_x_preferred":[
        "Seedorf"
    ],
    "name:eus_x_preferred":[
        "Seedorf"
    ],
    "name:fra_x_preferred":[
        "Seedorf"
    ],
    "name:ita_x_preferred":[
        "Seedorf"
    ],
    "name:jpn_x_preferred":[
        "\u30bc\u30fc\u30c9\u30eb\u30d5"
    ],
    "name:lmo_x_preferred":[
        "Seedorf"
    ],
    "name:mkd_x_preferred":[
        "\u0417\u0435\u0434\u043e\u0440\u0444"
    ],
    "name:nds_x_preferred":[
        "Seedorf"
    ],
    "name:nld_x_preferred":[
        "Seedorf"
    ],
    "name:pol_x_preferred":[
        "Seedorf"
    ],
    "name:por_x_preferred":[
        "Seedorf"
    ],
    "name:rus_x_preferred":[
        "\u0417\u0435\u0434\u043e\u0440\u0444"
    ],
    "name:spa_x_preferred":[
        "Seedorf"
    ],
    "name:srp_x_preferred":[
        "\u0417\u0435\u0434\u043e\u0440\u0444"
    ],
    "name:swe_x_preferred":[
        "Seedorf"
    ],
    "name:vol_x_preferred":[
        "Seedorf"
    ],
    "name:zho_x_preferred":[
        "\u585e\u591a\u592b"
    ],
    "wof:name":"Seedorf",
    "wof:placetype":"neighbourhood"
},
  "geometry": {"coordinates":[13.01468,53.95466999999999],"type":"Point"}
}