{
  "type": "Feature",
  "properties": {
    "gn:population":1346,
    "iso:country":"DE",
    "name:arm_x_preferred":[
        "\u054c\u0561\u0574\u0565\u0580\u0562\u0565\u0580\u0563"
    ],
    "name:baq_x_preferred":[
        "Ramerberg"
    ],
    "name:bar_x_preferred":[
        "Ramerberg"
    ],
    "name:chi_x_preferred":[
        "\u62c9\u6885\u5c14\u8d1d\u5c14\u683c"
    ],
    "name:deu_x_preferred":[
        "Ramerberg"
    ],
    "name:deu_x_variant":[
        "Gemeinde Ramerberg"
    ],
    "name:dut_x_preferred":[
        "Ramerberg"
    ],
    "name:eng_x_preferred":[
        "Ramerberg"
    ],
    "name:epo_x_preferred":[
        "Ramerberg"
    ],
    "name:eus_x_preferred":[
        "Ramerberg"
    ],
    "name:fas_x_preferred":[
        "\u0631\u0627\u0645\u0631\u0628\u0631\u06af"
    ],
    "name:fra_x_preferred":[
        "Ramerberg"
    ],
    "name:fre_x_preferred":[
        "Ramerberg"
    ],
    "name:ger_x_preferred":[
        "Ramerberg"
    ],
    "name:hbs_x_preferred":[
        "Ramerberg"
    ],
    "name:hun_x_preferred":[
        "Ramerberg"
    ],
    "name:hye_x_preferred":[
        "\u054c\u0561\u0574\u0565\u0580\u0562\u0565\u0580\u0563"
    ],
    "name:ind_x_preferred":[
        "Ramerberg"
    ],
    "name:ita_x_preferred":[
        "Ramerberg"
    ],
    "name:kaz_x_preferred":[
        "\u0420\u0430\u043c\u0435\u0440\u0431\u0435\u0440\u0433"
    ],
    "name:kir_x_preferred":[
        "\u0420\u0430\u043c\u0435\u0440\u0431\u0435\u0440\u0433"
    ],
    "name:lmo_x_preferred":[
        "Ramerberg"
    ],
    "name:nan_x_preferred":[
        "Ramerberg"
    ],
    "name:nld_x_preferred":[
        "Ramerberg"
    ],
    "name:per_x_preferred":[
        "\u0631\u0627\u0645\u0631\u0628\u0631\u06af"
    ],
    "name:pol_x_preferred":[
        "Ramerberg"
    ],
    "name:por_x_preferred":[
        "Ramerberg"
    ],
    "name:ron_x_preferred":[
        "Ramerberg"
    ],
    "name:rum_x_preferred":[
        "Ramerberg"
    ],
    "name:rus_x_preferred":[
        "\u0420\u0430\u043c\u0435\u0440\u0431\u0435\u0440\u0433"
    ],
    "name:srp_x_preferred":[
        "\u0420\u0430\u043c\u0435\u0440\u0431\u0435\u0440\u0433"
    ],
    "name:ukr_x_preferred":[
        "\u0420\u0430\u043c\u0435\u0440\u0431\u0435\u0440\u0433"
    ],
    "name:uzb_x_preferred":[
        "Ramerberg"
    ],
    "name:vie_x_preferred":[
        "Ramerberg"
    ],
    "name:vol_x_preferred":[
        "Ramerberg"
    ],
    "name:war_x_preferred":[
        "Ramerberg"
    ],
    "name:zho_min_nan_x_preferred":[
        "Ramerberg"
    ],
    "name:zho_x_preferred":[
        "\u62c9\u9ed8\u8d1d\u683c"
    ],
    "qs:a0":"Bundesrepublik Deutschland",
    "qs:a1":"*Bayern",
    "qs:a1r":"0",
    "qs:a2":"Rosenheim",
    "qs:adm0":"Bundesrepublik Deutschland",
    "qs:la_lc":"*",
    "qs:level":"locality",
    "qs:loc":"Ramerberg",
    "qs:loc_alt":"Ramerberg",
    "qs:pop":0,
    "qs:type":"buffered point",
    "wd:wordcount":26,
    "wof:lang":[
        "ger"
    ],
    "wof:name":"Ramerberg",
    "wof:placetype":"locality",
    "wof:population":1346
},
  "geometry": {"coordinates":[12.145924,48.016215],"type":"Point"}
}