{
  "type": "Feature",
  "properties": {
    "gn:admin1_code":"1",
    "gn:admin2_code":"81.0",
    "gn:admin3_code":"8127.0",
    "gn:admin4_code":"8127063.0",
    "gn:asciiname":"Herlebach",
    "gn:country_code":"DE",
    "gn:dem":412,
    "gn:feature_class":"P",
    "gn:feature_code":"PPL",
    "gn:name":"Herlebach",
    "gn:population":0,
    "gn:timezone":"Europe/Berlin",
    "iso:country":"DE",
    "wof:name":"Herlebach",
    "wof:placetype":"neighbourhood"
},
  "geometry": {"coordinates":[9.82582,49.06982],"type":"Point"}
}