{
  "type": "Feature",
  "properties": {
    "gn:admin1_code":"2",
    "gn:admin2_code":"91.0",
    "gn:admin3_code":"9181.0",
    "gn:admin4_code":"9181141.0",
    "gn:asciiname":"Ummendorf",
    "gn:country_code":"DE",
    "gn:dem":665,
    "gn:feature_class":"P",
    "gn:feature_code":"PPL",
    "gn:name":"Ummendorf",
    "gn:population":0,
    "gn:timezone":"Europe/Berlin",
    "iso:country":"DE",
    "wof:name":"Ummendorf",
    "wof:placetype":"neighbourhood"
},
  "geometry": {"coordinates":[10.91056,48.01303],"type":"Point"}
}