{
  "type": "Feature",
  "properties": {
    "gn:admin1_code":"2",
    "gn:admin2_code":"91.0",
    "gn:admin3_code":"9181.0",
    "gn:admin4_code":"9181141.0",
    "gn:asciiname":"Ummendorf",
    "gn:country_code":"DE",
    "gn:dem":665,
    "gn:feature_class":"P",
    "gn:feature_code":"PPL",
    "gn:name":"Ummendorf",
    "gn:population":0,
    "gn:timezone":"Europe/Berlin",
    "iso:country":"DE",
    "name:ceb_x_preferred":[
        "Ummendorf"
    ],
    "name:deu_x_preferred":[
        "Ummendorf"
    ],
    "name:epo_x_preferred":[
        "Ummendorf"
    ],
    "name:fra_x_preferred":[
        "Ummendorf"
    ],
    "name:ita_x_preferred":[
        "Ummendorf"
    ],
    "name:nds_x_preferred":[
        "Ummendorf"
    ],
    "name:nld_x_preferred":[
        "Ummendorf"
    ],
    "name:pol_x_preferred":[
        "Ummendorf"
    ],
    "name:rus_x_preferred":[
        "\u0423\u043c\u043c\u0435\u043d\u0434\u043e\u0440\u0444"
    ],
    "name:srp_x_preferred":[
        "\u0423\u043c\u0435\u043d\u0434\u043e\u0440\u0444"
    ],
    "name:swe_x_preferred":[
        "Ummendorf"
    ],
    "name:vol_x_preferred":[
        "Ummendorf"
    ],
    "name:zho_x_preferred":[
        "\u4e4c\u95e8\u591a\u592b"
    ],
    "wof:name":"Ummendorf",
    "wof:placetype":"neighbourhood"
},
  "geometry": {"coordinates":[10.91056,48.01303],"type":"Point"}
}