{
  "type": "Feature",
  "properties": {
    "iso:country":"DE",
    "wof:name":"Vogelheim",
    "wof:placetype":"neighbourhood"
},
  "geometry": {"coordinates":[6.98834195263382,51.49210868896935],"type":"Point"}
}