{
  "type": "Feature",
  "properties": {
    "gn:admin1_code":"6",
    "gn:admin2_code":"0.0",
    "gn:admin3_code":"3451.0",
    "gn:admin4_code":"3451004.0",
    "gn:asciiname":"Langendamm",
    "gn:country_code":"DE",
    "gn:dem":6,
    "gn:feature_class":"P",
    "gn:feature_code":"PPL",
    "gn:name":"Langendamm",
    "gn:population":0,
    "gn:timezone":"Europe/Berlin",
    "iso:country":"DE",
    "wof:name":"Langendamm",
    "wof:placetype":"neighbourhood"
},
  "geometry": {"coordinates":[8.05,53.08333],"type":"Point"}
}