{
  "type": "Feature",
  "properties": {
    "gn:admin1_code":"1",
    "gn:admin2_code":"84.0",
    "gn:admin3_code":"8435.0",
    "gn:admin4_code":"8435034.0",
    "gn:asciiname":"Ittendorf",
    "gn:country_code":"DE",
    "gn:dem":449,
    "gn:feature_class":"P",
    "gn:feature_code":"PPL",
    "gn:name":"Ittendorf",
    "gn:population":0,
    "gn:timezone":"Europe/Berlin",
    "iso:country":"DE",
    "wof:name":"Ittendorf",
    "wof:placetype":"neighbourhood"
},
  "geometry": {"coordinates":[9.33828,47.70064],"type":"Point"}
}