{
  "type": "Feature",
  "properties": {
    "gn:admin1_code":"6",
    "gn:admin2_code":"0.0",
    "gn:admin3_code":"3351.0",
    "gn:admin4_code":"3351004.0",
    "gn:asciiname":"Nindorf",
    "gn:country_code":"DE",
    "gn:dem":76,
    "gn:feature_class":"P",
    "gn:feature_code":"PPL",
    "gn:name":"Nindorf",
    "gn:population":0,
    "gn:timezone":"Europe/Berlin",
    "iso:country":"DE",
    "wof:name":"Nindorf",
    "wof:placetype":"neighbourhood"
},
  "geometry": {"coordinates":[9.97267,52.84322],"type":"Point"}
}