{
  "type": "Feature",
  "properties": {
    "gn:admin1_code":"6",
    "gn:admin2_code":"0.0",
    "gn:admin3_code":"3351.0",
    "gn:admin4_code":"3351004.0",
    "gn:asciiname":"Nindorf",
    "gn:country_code":"DE",
    "gn:dem":76,
    "gn:feature_class":"P",
    "gn:feature_code":"PPL",
    "gn:name":"Nindorf",
    "gn:population":0,
    "gn:timezone":"Europe/Berlin",
    "iso:country":"DE",
    "name:ceb_x_preferred":[
        "Nindorf"
    ],
    "name:deu_x_preferred":[
        "Nindorf"
    ],
    "name:fas_x_preferred":[
        "\u0646\u06cc\u0646\u062f\u0648\u0631\u0641"
    ],
    "wof:name":"Nindorf",
    "wof:placetype":"neighbourhood"
},
  "geometry": {"coordinates":[9.97267,52.84322],"type":"Point"}
}