{
  "type": "Feature",
  "properties": {
    "gn:admin1_code":"6",
    "gn:admin2_code":"0.0",
    "gn:admin3_code":"3357.0",
    "gn:admin4_code":"3357016.0",
    "gn:asciiname":"Klenkendorf",
    "gn:country_code":"DE",
    "gn:dem":10,
    "gn:feature_class":"P",
    "gn:feature_code":"PPL",
    "gn:name":"Klenkendorf",
    "gn:population":0,
    "gn:timezone":"Europe/Berlin",
    "iso:country":"DE",
    "wof:name":"Klenkendorf",
    "wof:placetype":"neighbourhood"
},
  "geometry": {"coordinates":[9.07318,53.42332],"type":"Point"}
}