{
  "type": "Feature",
  "properties": {
    "gn:admin1_code":"1",
    "gn:admin2_code":"83.0",
    "gn:admin3_code":"8336.0",
    "gn:admin4_code":"8336081.0",
    "gn:asciiname":"Sattelhof",
    "gn:country_code":"DE",
    "gn:dem":537,
    "gn:feature_class":"P",
    "gn:feature_code":"PPL",
    "gn:name":"Sattelhof",
    "gn:population":0,
    "gn:timezone":"Europe/Berlin",
    "iso:country":"DE",
    "wof:name":"Sattelhof",
    "wof:placetype":"neighbourhood"
},
  "geometry": {"coordinates":[7.87797,47.67348],"type":"Point"}
}