{
  "type": "Feature",
  "properties": {
    "gn:country":"DE",
    "gn:fcode":"PPL",
    "gn:population":184,
    "iso:country":"DE",
    "name:ceb_x_preferred":[
        "Dorna"
    ],
    "name:deu_x_preferred":[
        "Dorna"
    ],
    "name:eng_x_preferred":[
        "Dorna"
    ],
    "name:fas_x_preferred":[
        "\u062f\u0648\u0631\u0646\u0627"
    ],
    "name:fra_x_preferred":[
        "Dorna"
    ],
    "name:gle_x_preferred":[
        "Dorna"
    ],
    "name:ita_x_preferred":[
        "Dorna"
    ],
    "name:nld_x_preferred":[
        "Dorna"
    ],
    "qs_pg:aaroncc":"DE",
    "qs_pg:gn_country":"DE",
    "qs_pg:gn_fcode":"PPL",
    "qs_pg:gn_pop":184,
    "qs_pg:name":"Dorna",
    "qs_pg:name_adm0":"Deutschland",
    "qs_pg:name_adm1":"Sachsen-Anhalt",
    "qs_pg:photos_9r":0,
    "qs_pg:photos_sr":0,
    "qs_pg:pop_sr":1,
    "qs_pg:qs_pg_placetype":"locality",
    "qs_pg:qs_pg_placetype_gp":"Town",
    "qs_pg:woe_adm0":23424829,
    "woe:adm0_id":23424829,
    "woe:name_adm0":"Deutschland",
    "woe:name_adm1":"Sachsen-Anhalt",
    "woe:placetype":"Town",
    "wof:name":"Dorna",
    "wof:placetype":"neighbourhood",
    "wof:population":184
},
  "geometry": {"coordinates":[12.71104,51.78313],"type":"Point"}
}