{
  "type": "Feature",
  "properties": {
    "gn:admin1_code":"12",
    "gn:admin2_code":"0.0",
    "gn:admin3_code":"13072.0",
    "gn:admin4_code":"13072067.0",
    "gn:asciiname":"Gerdshagen Hof",
    "gn:country_code":"DE",
    "gn:dem":85,
    "gn:feature_class":"P",
    "gn:feature_code":"PPL",
    "gn:name":"Gerdshagen Hof",
    "gn:population":0,
    "gn:timezone":"Europe/Berlin",
    "iso:country":"DE",
    "name:und_x_variant":[
        "Gerdshagen",
        "Gerdshagen Hof"
    ],
    "wof:name":"Gerdshagen Hof",
    "wof:placetype":"neighbourhood"
},
  "geometry": {"coordinates":[12.09075,53.72104],"type":"Point"}
}