{
  "type": "Feature",
  "properties": {
    "gn:admin1_code":"2.0",
    "gn:admin2_code":"094",
    "gn:admin3_code":"9473.0",
    "gn:admin4_code":"9473134.0",
    "gn:asciiname":"Zeickhorn",
    "gn:country_code":"DE",
    "gn:dem":331,
    "gn:feature_class":"P",
    "gn:feature_code":"PPL",
    "gn:name":"Zeickhorn",
    "gn:population":0,
    "gn:timezone":"Europe/Berlin",
    "iso:country":"DE",
    "wof:name":"Zeickhorn",
    "wof:placetype":"neighbourhood"
},
  "geometry": {"coordinates":[11.04382,50.22647],"type":"Point"}
}