{
  "type": "Feature",
  "properties": {
    "gn:admin1_code":"6",
    "gn:admin2_code":"0.0",
    "gn:admin3_code":"3462.0",
    "gn:admin4_code":"3462019.0",
    "gn:asciiname":"Funnixer Grosseriege",
    "gn:country_code":"DE",
    "gn:dem":1,
    "gn:feature_class":"P",
    "gn:feature_code":"PPL",
    "gn:name":"Funnixer Gro\u00dferiege",
    "gn:population":0,
    "gn:timezone":"Europe/Berlin",
    "iso:country":"DE",
    "wof:name":"Funnixer Grosseriege",
    "wof:placetype":"neighbourhood"
},
  "geometry": {"coordinates":[7.79582,53.64112],"type":"Point"}
}