{
  "type": "Feature",
  "properties": {
    "gn:admin1_code":"11",
    "gn:admin2_code":"0.0",
    "gn:admin3_code":"12062.0",
    "gn:admin4_code":"12062341.0",
    "gn:asciiname":"Kaitzschhaeuser",
    "gn:country_code":"DE",
    "gn:dem":91,
    "gn:feature_class":"P",
    "gn:feature_code":"PPL",
    "gn:name":"Kaitzschh\u00e4user",
    "gn:population":0,
    "gn:timezone":"Europe/Berlin",
    "iso:country":"DE",
    "wof:name":"Kaitzschhaeuser",
    "wof:placetype":"neighbourhood"
},
  "geometry": {"coordinates":[13.24456,51.3946],"type":"Point"}
}