{
  "type": "Feature",
  "properties": {
    "gn:admin1_code":"2",
    "gn:admin2_code":"92.0",
    "gn:admin3_code":"9271.0",
    "gn:admin4_code":"9271126.0",
    "gn:asciiname":"Kieflitz",
    "gn:country_code":"DE",
    "gn:dem":502,
    "gn:feature_class":"P",
    "gn:feature_code":"PPL",
    "gn:name":"Kieflitz",
    "gn:population":0,
    "gn:timezone":"Europe/Berlin",
    "iso:country":"DE",
    "wof:name":"Kieflitz",
    "wof:placetype":"neighbourhood"
},
  "geometry": {"coordinates":[13.1648,48.83568],"type":"Point"}
}