{
  "type": "Feature",
  "properties": {
    "gn:admin1_code":"2",
    "gn:admin2_code":"91.0",
    "gn:admin3_code":"9183.0",
    "gn:admin4_code":"9183118.0",
    "gn:asciiname":"Horwart",
    "gn:country_code":"DE",
    "gn:dem":499,
    "gn:feature_class":"P",
    "gn:feature_code":"PPL",
    "gn:name":"H\u00f6rwart",
    "gn:population":0,
    "gn:timezone":"Europe/Berlin",
    "iso:country":"DE",
    "wof:name":"Horwart",
    "wof:placetype":"neighbourhood"
},
  "geometry": {"coordinates":[12.24856,48.15677],"type":"Point"}
}