{
  "type": "Feature",
  "properties": {
    "gn:admin1_code":"6",
    "gn:admin2_code":"0.0",
    "gn:admin3_code":"3458.0",
    "gn:admin4_code":"3458007.0",
    "gn:asciiname":"Hollen",
    "gn:country_code":"DE",
    "gn:dem":36,
    "gn:feature_class":"P",
    "gn:feature_code":"PPL",
    "gn:name":"Hollen",
    "gn:population":0,
    "gn:timezone":"Europe/Berlin",
    "iso:country":"DE",
    "name:deu_x_preferred":[
        "Hollen"
    ],
    "name:epo_x_preferred":[
        "Hollen"
    ],
    "name:fas_x_preferred":[
        "\u0647\u0648\u0644\u0646"
    ],
    "name:ita_x_preferred":[
        "Hollen"
    ],
    "name:kaz_x_preferred":[
        "\u0425\u043e\u043b\u043b\u0435\u043d"
    ],
    "name:kir_x_preferred":[
        "\u0425\u043e\u043b\u043b\u0435\u043d"
    ],
    "name:nld_x_preferred":[
        "Hollen"
    ],
    "name:pol_x_preferred":[
        "Hollen"
    ],
    "name:por_x_preferred":[
        "Hollen"
    ],
    "name:ron_x_preferred":[
        "Hollen"
    ],
    "name:rus_x_preferred":[
        "\u0425\u043e\u043b\u043b\u0435\u043d"
    ],
    "name:srp_x_preferred":[
        "\u0425\u043e\u043b\u0435\u043d"
    ],
    "name:uzb_x_preferred":[
        "Hollen"
    ],
    "name:vie_x_preferred":[
        "Hollen"
    ],
    "name:vol_x_preferred":[
        "Hollen"
    ],
    "name:war_x_preferred":[
        "Hollen"
    ],
    "wof:name":"Hollen",
    "wof:placetype":"neighbourhood"
},
  "geometry": {"coordinates":[8.27279,52.9566],"type":"Point"}
}