{
  "type": "Feature",
  "properties": {
    "gn:admin1_code":"6",
    "gn:admin2_code":"0.0",
    "gn:admin3_code":"3458.0",
    "gn:admin4_code":"3458007.0",
    "gn:asciiname":"Hollen",
    "gn:country_code":"DE",
    "gn:dem":36,
    "gn:feature_class":"P",
    "gn:feature_code":"PPL",
    "gn:name":"Hollen",
    "gn:population":0,
    "gn:timezone":"Europe/Berlin",
    "iso:country":"DE",
    "wof:name":"Hollen",
    "wof:placetype":"neighbourhood"
},
  "geometry": {"coordinates":[8.27279,52.9566],"type":"Point"}
}