{
  "type": "Feature",
  "properties": {
    "gn:admin1_code":"6.0",
    "gn:admin2_code":"0.0",
    "gn:admin3_code":"3159.0",
    "gn:admin4_code":"3159029.0",
    "gn:asciiname":"Atzenhausen",
    "gn:country_code":"DE",
    "gn:dem":293,
    "gn:feature_class":"P",
    "gn:feature_code":"PPL",
    "gn:name":"Atzenhausen",
    "gn:population":0,
    "gn:timezone":"Europe/Berlin",
    "iso:country":"DE",
    "wof:name":"Atzenhausen",
    "wof:placetype":"neighbourhood"
},
  "geometry": {"coordinates":[9.81379,51.41979],"type":"Point"}
}