{
  "type": "Feature",
  "properties": {
    "gn:admin1_code":"8",
    "gn:admin2_code":"0.0",
    "gn:admin3_code":"7141.0",
    "gn:admin4_code":"7141114.0",
    "gn:asciiname":"Offenthal",
    "gn:country_code":"DE",
    "gn:dem":273,
    "gn:feature_class":"P",
    "gn:feature_code":"PPL",
    "gn:name":"Offenthal",
    "gn:population":0,
    "gn:timezone":"Europe/Berlin",
    "iso:country":"DE",
    "wof:name":"Offenthal",
    "wof:placetype":"neighbourhood"
},
  "geometry": {"coordinates":[7.7573,50.14756],"type":"Point"}
}