{
  "type": "Feature",
  "properties": {
    "gn:admin1_code":"5",
    "gn:admin2_code":"65.0",
    "gn:admin3_code":"6534.0",
    "gn:admin4_code":"6534020.0",
    "gn:asciiname":"Stedebach",
    "gn:country_code":"DE",
    "gn:dem":209,
    "gn:feature_class":"P",
    "gn:feature_code":"PPL",
    "gn:name":"Stedebach",
    "gn:population":0,
    "gn:timezone":"Europe/Berlin",
    "iso:country":"DE",
    "wof:name":"Stedebach",
    "wof:placetype":"neighbourhood"
},
  "geometry": {"coordinates":[8.67374,50.7283],"type":"Point"}
}