{
  "type": "Feature",
  "properties": {
    "gn:admin1_code":"14",
    "gn:admin2_code":"0.0",
    "gn:admin3_code":"15091.0",
    "gn:admin4_code":"15091391.0",
    "gn:asciiname":"Gallin",
    "gn:country_code":"DE",
    "gn:dem":70,
    "gn:feature_class":"P",
    "gn:feature_code":"PPL",
    "gn:name":"Gallin",
    "gn:population":0,
    "gn:timezone":"Europe/Berlin",
    "iso:country":"DE",
    "name:deu_x_preferred":[
        "Gallin"
    ],
    "name:epo_x_preferred":[
        "Gallin"
    ],
    "name:fas_x_preferred":[
        "\u06af\u0627\u0644\u06cc\u0646"
    ],
    "name:fra_x_preferred":[
        "Gallin"
    ],
    "name:hun_x_preferred":[
        "Gallin"
    ],
    "name:ita_x_preferred":[
        "Gallin"
    ],
    "name:kaz_x_preferred":[
        "\u0413\u0430\u043b\u043b\u0438\u043d"
    ],
    "name:kir_x_preferred":[
        "\u0413\u0430\u043b\u043b\u0438\u043d"
    ],
    "name:mkd_x_preferred":[
        "\u0413\u0430\u043b\u0438\u043d"
    ],
    "name:msa_x_preferred":[
        "Gallin"
    ],
    "name:nld_x_preferred":[
        "Gallin"
    ],
    "name:pol_x_preferred":[
        "Gallin"
    ],
    "name:ron_x_preferred":[
        "Gallin"
    ],
    "name:rus_x_preferred":[
        "\u0413\u0430\u043b\u043b\u0438\u043d"
    ],
    "name:spa_x_preferred":[
        "Gallin"
    ],
    "name:srp_x_preferred":[
        "\u0413\u0430\u043b\u0438\u043d"
    ],
    "name:ukr_x_preferred":[
        "\u0413\u0430\u043b\u043b\u0456\u043d"
    ],
    "name:und_x_variant":[
        "Gallien"
    ],
    "name:uzb_x_preferred":[
        "Gallin"
    ],
    "name:vie_x_preferred":[
        "Gallin"
    ],
    "name:vol_x_preferred":[
        "Gallin"
    ],
    "name:war_x_preferred":[
        "Gallin"
    ],
    "wof:name":"Gallin",
    "wof:placetype":"neighbourhood"
},
  "geometry": {"coordinates":[12.75766,51.83845],"type":"Point"}
}