{
  "type": "Feature",
  "properties": {
    "gn:admin1_code":"1",
    "gn:admin2_code":"83.0",
    "gn:admin3_code":"8317.0",
    "gn:admin4_code":"8317039.0",
    "gn:asciiname":"Steinenbach",
    "gn:country_code":"DE",
    "gn:dem":424,
    "gn:feature_class":"P",
    "gn:feature_code":"PPLL",
    "gn:name":"Steinenbach",
    "gn:population":0,
    "gn:timezone":"Europe/Berlin",
    "iso:country":"DE",
    "wof:name":"Steinenbach",
    "wof:placetype":"neighbourhood"
},
  "geometry": {"coordinates":[8.19374,48.2255],"type":"Point"}
}