{
  "type": "Feature",
  "properties": {
    "gn:admin1_code":"2.0",
    "gn:admin2_code":"91.0",
    "gn:admin3_code":"9190.0",
    "gn:admin4_code":"9190140.0",
    "gn:asciiname":"Berg",
    "gn:country_code":"DE",
    "gn:dem":734,
    "gn:feature_class":"P",
    "gn:feature_code":"PPL",
    "gn:name":"Berg",
    "gn:population":0,
    "gn:timezone":"Europe/Berlin",
    "iso:country":"DE",
    "name:als_x_preferred":[
        "Berg"
    ],
    "name:cat_x_preferred":[
        "Berg"
    ],
    "name:ceb_x_preferred":[
        "Berg"
    ],
    "name:ces_x_preferred":[
        "Berg"
    ],
    "name:deu_x_preferred":[
        "Berg"
    ],
    "name:epo_x_preferred":[
        "Berg"
    ],
    "name:eus_x_preferred":[
        "Berg"
    ],
    "name:fin_x_preferred":[
        "Berg"
    ],
    "name:fra_x_preferred":[
        "Berg"
    ],
    "name:hun_x_preferred":[
        "Berg"
    ],
    "name:hye_x_preferred":[
        "\u0532\u0565\u0580\u0563"
    ],
    "name:ita_x_preferred":[
        "Berg"
    ],
    "name:jpn_x_preferred":[
        "\u30d9\u30eb\u30af"
    ],
    "name:kat_x_preferred":[
        "\u10d1\u10d4\u10e0\u10d2\u10d8"
    ],
    "name:kor_x_preferred":[
        "\ubca0\ub974\ud06c"
    ],
    "name:lim_x_preferred":[
        "Berg"
    ],
    "name:lmo_x_preferred":[
        "Berg"
    ],
    "name:nds_x_preferred":[
        "Berg"
    ],
    "name:nld_x_preferred":[
        "Berg"
    ],
    "name:nno_x_preferred":[
        "Berg"
    ],
    "name:nor_x_preferred":[
        "Berg"
    ],
    "name:pms_x_preferred":[
        "Berg"
    ],
    "name:pol_x_preferred":[
        "Berg"
    ],
    "name:por_x_preferred":[
        "Berg"
    ],
    "name:ron_x_preferred":[
        "Berg"
    ],
    "name:rus_x_preferred":[
        "\u0411\u0435\u0440\u0433"
    ],
    "name:slk_x_preferred":[
        "Berg"
    ],
    "name:spa_x_preferred":[
        "Berg"
    ],
    "name:srp_x_preferred":[
        "\u0411\u0435\u0440\u0433"
    ],
    "name:swe_x_preferred":[
        "Berg"
    ],
    "name:ukr_x_preferred":[
        "\u0411\u0435\u0440\u0433"
    ],
    "name:vol_x_preferred":[
        "Berg"
    ],
    "wof:name":"Berg",
    "wof:placetype":"neighbourhood"
},
  "geometry": {"coordinates":[10.93645,47.862],"type":"Point"}
}