{
  "type": "Feature",
  "properties": {
    "gn:admin1_code":"7",
    "gn:admin2_code":"59.0",
    "gn:admin3_code":"5954.0",
    "gn:admin4_code":"5954008.0",
    "gn:asciiname":"Rueggeberg",
    "gn:country_code":"DE",
    "gn:dem":356,
    "gn:feature_class":"P",
    "gn:feature_code":"PPL",
    "gn:name":"R\u00fcggeberg",
    "gn:population":0,
    "gn:timezone":"Europe/Berlin",
    "iso:country":"DE",
    "wof:name":"Rueggeberg",
    "wof:placetype":"neighbourhood"
},
  "geometry": {"coordinates":[7.38417,51.26636],"type":"Point"}
}