{
  "type": "Feature",
  "properties": {
    "gn:admin1_code":"2",
    "gn:admin2_code":"91.0",
    "gn:admin3_code":"9189.0",
    "gn:admin4_code":"9189118.0",
    "gn:asciiname":"Pietling",
    "gn:country_code":"DE",
    "gn:dem":379,
    "gn:feature_class":"P",
    "gn:feature_code":"PPL",
    "gn:name":"Pietling",
    "gn:population":0,
    "gn:timezone":"Europe/Berlin",
    "iso:country":"DE",
    "wof:name":"Pietling",
    "wof:placetype":"neighbourhood"
},
  "geometry": {"coordinates":[12.79924,48.01663],"type":"Point"}
}