{
  "type": "Feature",
  "properties": {
    "gn:admin1_code":"10.0",
    "gn:admin2_code":"00",
    "gn:admin3_code":"1062.0",
    "gn:admin4_code":"1062009.0",
    "gn:asciiname":"Willinghusen",
    "gn:country_code":"DE",
    "gn:dem":35,
    "gn:feature_class":"P",
    "gn:feature_code":"PPL",
    "gn:name":"Willinghusen",
    "gn:population":0,
    "gn:timezone":"Europe/Berlin",
    "iso:country":"DE",
    "wof:name":"Willinghusen",
    "wof:placetype":"neighbourhood"
},
  "geometry": {"coordinates":[10.20659,53.55931],"type":"Point"}
}