{
  "type": "Feature",
  "properties": {
    "gn:admin1_code":"2",
    "gn:admin2_code":"94.0",
    "gn:admin3_code":"9464.0",
    "gn:admin4_code":"9464000.0",
    "gn:asciiname":"Krotenbruck",
    "gn:country_code":"DE",
    "gn:dem":504,
    "gn:feature_class":"P",
    "gn:feature_code":"PPL",
    "gn:name":"Kr\u00f6tenbruck",
    "gn:population":0,
    "gn:timezone":"Europe/Berlin",
    "iso:country":"DE",
    "wof:name":"Krotenbruck",
    "wof:placetype":"neighbourhood"
},
  "geometry": {"coordinates":[11.90458,50.29228],"type":"Point"}
}