{
  "type": "Feature",
  "properties": {
    "gn:admin1_code":"1",
    "gn:admin2_code":"82.0",
    "gn:admin3_code":"8237.0",
    "gn:admin4_code":"8237004.0",
    "gn:asciiname":"Harlisberg",
    "gn:country_code":"DE",
    "gn:dem":593,
    "gn:feature_class":"P",
    "gn:feature_code":"PPL",
    "gn:name":"Harlisberg",
    "gn:population":0,
    "gn:timezone":"Europe/Berlin",
    "iso:country":"DE",
    "wof:name":"Harlisberg",
    "wof:placetype":"neighbourhood"
},
  "geometry": {"coordinates":[8.36177,48.53163],"type":"Point"}
}