{
  "type": "Feature",
  "properties": {
    "gn:admin1_code":"2.0",
    "gn:admin2_code":"93.0",
    "gn:admin3_code":"9374.0",
    "gn:admin4_code":"9374162.0",
    "gn:asciiname":"Bohmischbruck",
    "gn:country_code":"DE",
    "gn:dem":489,
    "gn:feature_class":"P",
    "gn:feature_code":"PPL",
    "gn:name":"B\u00f6hmischbruck",
    "gn:population":0,
    "gn:timezone":"Europe/Berlin",
    "iso:country":"DE",
    "wof:name":"Bohmischbruck",
    "wof:placetype":"neighbourhood"
},
  "geometry": {"coordinates":[12.35345,49.57434],"type":"Point"}
}