{
  "type": "Feature",
  "properties": {
    "iso:country":"DE",
    "wof:name":"Quellenbusch",
    "wof:placetype":"neighbourhood"
},
  "geometry": {"coordinates":[6.85055852970094,51.22931987482373],"type":"Point"}
}