{
  "type": "Feature",
  "properties": {
    "gn:country":"DE",
    "gn:fcode":"PPL",
    "gn:population":1717,
    "iso:country":"DE",
    "name:ara_x_preferred":[
        "\u0647\u0648\u0631\u0646\u0628\u0627\u062e"
    ],
    "name:bul_x_preferred":[
        "\u0425\u043e\u0440\u043d\u0431\u0430\u0445"
    ],
    "name:ceb_x_preferred":[
        "Horbach"
    ],
    "name:deu_x_preferred":[
        "Horbach"
    ],
    "name:epo_x_preferred":[
        "Horbach"
    ],
    "name:fas_x_preferred":[
        "\u0647\u0648\u0631\u0646\u0628\u0627\u062e"
    ],
    "name:fra_x_preferred":[
        "Horbach"
    ],
    "name:ita_x_preferred":[
        "Horbach"
    ],
    "name:jpn_x_preferred":[
        "\u30db\u30eb\u30f3\u30d0\u30c3\u30cf"
    ],
    "name:kaz_x_preferred":[
        "\u0425\u043e\u0440\u043d\u0431\u0430\u0445"
    ],
    "name:nld_x_preferred":[
        "Horbach"
    ],
    "name:pol_x_preferred":[
        "Horbach"
    ],
    "name:rus_x_preferred":[
        "\u0425\u043e\u0440\u043d\u0431\u0430\u0445"
    ],
    "name:rus_x_variant":[
        "\u0425\u043e\u0440\u0431\u0430\u0445"
    ],
    "name:srp_x_preferred":[
        "\u0425\u043e\u0440\u043d\u0431\u0430\u0445"
    ],
    "name:srp_x_variant":[
        "\u0425\u043e\u0440\u0431\u0430\u0445"
    ],
    "name:swe_x_preferred":[
        "Horbach"
    ],
    "name:und_x_variant":[
        "Hornbach"
    ],
    "name:zho_x_preferred":[
        "\u970d\u6069\u5df4\u8d6b"
    ],
    "qs_pg:aaroncc":"DE",
    "qs_pg:gn_country":"DE",
    "qs_pg:gn_fcode":"PPL",
    "qs_pg:gn_pop":1717,
    "qs_pg:name":"Horbach",
    "qs_pg:name_adm0":"Deutschland",
    "qs_pg:name_adm1":"Rheinland-Pfalz",
    "qs_pg:photos_9r":0,
    "qs_pg:photos_sr":0,
    "qs_pg:pop_sr":3,
    "qs_pg:qs_pg_placetype":"locality",
    "qs_pg:qs_pg_placetype_gp":"Town",
    "qs_pg:woe_adm0":23424829,
    "woe:adm0_id":23424829,
    "woe:name_adm0":"Deutschland",
    "woe:name_adm1":"Rheinland-Pfalz",
    "woe:placetype":"Town",
    "wof:name":"Horbach",
    "wof:placetype":"neighbourhood",
    "wof:population":1717
},
  "geometry": {"coordinates":[7.36882,49.18778],"type":"Point"}
}