{
  "type": "Feature",
  "properties": {
    "gn:admin1_code":"6",
    "gn:admin2_code":"0.0",
    "gn:admin3_code":"3257.0",
    "gn:admin4_code":"3257002.0",
    "gn:asciiname":"Reinsdorf",
    "gn:country_code":"DE",
    "gn:dem":134,
    "gn:feature_class":"P",
    "gn:feature_code":"PPL",
    "gn:name":"Reinsdorf",
    "gn:population":0,
    "gn:timezone":"Europe/Berlin",
    "iso:country":"DE",
    "name:ceb_x_preferred":[
        "Reinsdorf"
    ],
    "name:deu_x_preferred":[
        "Reinsdorf"
    ],
    "name:epo_x_preferred":[
        "Reinsdorf"
    ],
    "name:fra_x_preferred":[
        "Reinsdorf"
    ],
    "name:ita_x_preferred":[
        "Reinsdorf"
    ],
    "name:kaz_x_preferred":[
        "\u0420\u0430\u0439\u043d\u0441\u0434\u043e\u0440\u0444"
    ],
    "name:kir_x_preferred":[
        "\u0420\u0430\u0439\u043d\u0441\u0434\u043e\u0440\u0444"
    ],
    "name:mkd_x_preferred":[
        "\u0420\u0430\u0458\u043d\u0441\u0434\u043e\u0440\u0444"
    ],
    "name:nds_x_preferred":[
        "Raansd\u00f6rpe"
    ],
    "name:nld_x_preferred":[
        "Reinsdorf"
    ],
    "name:pol_x_preferred":[
        "Reinsdorf"
    ],
    "name:rus_x_preferred":[
        "\u0420\u0430\u0439\u043d\u0441\u0434\u043e\u0440\u0444"
    ],
    "name:swe_x_preferred":[
        "Reinsdorf"
    ],
    "name:vol_x_preferred":[
        "Reinsdorf"
    ],
    "wof:name":"Reinsdorf",
    "wof:placetype":"neighbourhood"
},
  "geometry": {"coordinates":[9.2898,52.29168],"type":"Point"}
}