{
  "type": "Feature",
  "properties": {
    "gn:gn_country":"DE",
    "gn:gn_fcode":"PPLA4",
    "gn:gn_pop":154,
    "gn:population":154,
    "iso:country":"DE",
    "name:baq_x_preferred":[
        "M\u00f6ntenich"
    ],
    "name:chi_x_preferred":[
        "\u95e8\u7279\u5c3c\u5e0c"
    ],
    "name:dut_x_preferred":[
        "M\u00f6ntenich"
    ],
    "name:eng_x_preferred":[
        "M\u00f6ntenich"
    ],
    "name:epo_x_preferred":[
        "M\u00f6ntenich"
    ],
    "name:fre_x_preferred":[
        "M\u00f6ntenich"
    ],
    "name:ger_x_preferred":[
        "M\u00f6ntenich"
    ],
    "name:hun_x_preferred":[
        "M\u00f6ntenich"
    ],
    "name:ita_x_preferred":[
        "M\u00f6ntenich"
    ],
    "name:jpn_x_preferred":[
        "\u30e1\u30f3\u30c6\u30cb\u30d2"
    ],
    "name:may_x_preferred":[
        "M\u00f6ntenich"
    ],
    "name:per_x_preferred":[
        "\u0645\u0648\u0646\u062a\u0646\u0627\u06cc\u0634"
    ],
    "name:pol_x_preferred":[
        "M\u00f6ntenich"
    ],
    "name:por_x_preferred":[
        "M\u00f6ntenich"
    ],
    "name:rum_x_preferred":[
        "M\u00f6ntenich"
    ],
    "name:rus_x_preferred":[
        "\u041c\u0451\u043d\u0442\u0435\u043d\u0438\u0445"
    ],
    "name:srp_x_preferred":[
        "\u041c\u0435\u043d\u0442\u0435\u043d\u0438\u0445"
    ],
    "name:ukr_x_preferred":[
        "\u041c\u0435\u043d\u0442\u0435\u043d\u0456\u0445"
    ],
    "name:uzb_x_preferred":[
        "M\u00f6ntenich"
    ],
    "name:vie_x_preferred":[
        "M\u00f6ntenich"
    ],
    "name:vol_x_preferred":[
        "M\u00f6ntenich"
    ],
    "name:war_x_preferred":[
        "M\u00f6ntenich"
    ],
    "qs_pg:aaroncc":"DE",
    "qs_pg:gn_country":"DE",
    "qs_pg:gn_fcode":"PPLA4",
    "qs_pg:gn_pop":154,
    "qs_pg:name":"M\u00f6ntenich",
    "qs_pg:photos_9r":0,
    "qs_pg:photos_sr":0,
    "qs_pg:pop_sr":1,
    "qs_pg:qs_pg_placetype":"locality",
    "wof:name":"M\u00f6ntenich",
    "wof:placetype":"locality",
    "wof:population":154
},
  "geometry": {"coordinates":[7.29921,50.22129],"type":"Point"}
}