{
  "type": "Feature",
  "properties": {
    "gn:admin1_code":"7",
    "gn:admin2_code":"53.0",
    "gn:admin3_code":"5374.0",
    "gn:admin4_code":"5374016.0",
    "gn:asciiname":"Dreibaeumen",
    "gn:country_code":"DE",
    "gn:dem":325,
    "gn:feature_class":"P",
    "gn:feature_code":"PPL",
    "gn:name":"Dreib\u00e4umen",
    "gn:population":0,
    "gn:timezone":"Europe/Berlin",
    "iso:country":"DE",
    "wof:name":"Dreibaeumen",
    "wof:placetype":"neighbourhood"
},
  "geometry": {"coordinates":[7.27278,51.13274000000001],"type":"Point"}
}