{
  "type": "Feature",
  "properties": {
    "gn:country":"DE",
    "gn:fcode":"PPL",
    "gn:population":0,
    "iso:country":"DE",
    "name:als_x_preferred":[
        "Sevelen"
    ],
    "name:ceb_x_preferred":[
        "Sevelen"
    ],
    "name:deu_x_preferred":[
        "Sevelen"
    ],
    "name:epo_x_preferred":[
        "Sevelen"
    ],
    "name:eus_x_preferred":[
        "Sevelen"
    ],
    "name:fra_x_preferred":[
        "Sevelen"
    ],
    "name:hun_x_preferred":[
        "Sevelen"
    ],
    "name:ita_x_preferred":[
        "Sevelen"
    ],
    "name:kaz_x_preferred":[
        "\u0417\u0435\u0444\u0435\u043b\u0435\u043d"
    ],
    "name:lmo_x_preferred":[
        "Sevelen"
    ],
    "name:msa_x_preferred":[
        "Sevelen"
    ],
    "name:nld_x_preferred":[
        "Sevelen"
    ],
    "name:nno_x_preferred":[
        "Sevelen"
    ],
    "name:pms_x_preferred":[
        "Sevelen"
    ],
    "name:por_x_preferred":[
        "Sevelen"
    ],
    "name:rus_x_preferred":[
        "\u0417\u0435\u0432\u0435\u043b\u0435\u043d"
    ],
    "name:spa_x_preferred":[
        "Sevelen"
    ],
    "name:swe_x_preferred":[
        "Sevelen"
    ],
    "name:uzb_x_preferred":[
        "Sevelen"
    ],
    "name:vol_x_preferred":[
        "Sevelen"
    ],
    "name:war_x_preferred":[
        "Sevelen"
    ],
    "name:zho_x_preferred":[
        "\u585e\u6c83\u502b"
    ],
    "qs_pg:aaroncc":"DE",
    "qs_pg:gn_country":"DE",
    "qs_pg:gn_fcode":"PPL",
    "qs_pg:gn_pop":0,
    "qs_pg:name":"Sevelen",
    "qs_pg:name_adm0":"Deutschland",
    "qs_pg:name_adm1":"Nordrhein-Westfalen",
    "qs_pg:photos":16,
    "qs_pg:photos_1k":3,
    "qs_pg:photos_9k":1,
    "qs_pg:photos_9r":1,
    "qs_pg:photos_all":16,
    "qs_pg:photos_sr":1,
    "qs_pg:pop_sr":0,
    "qs_pg:qs_pg_placetype":"locality",
    "qs_pg:qs_pg_placetype_gp":"Town",
    "qs_pg:woe_adm0":23424829,
    "woe:adm0_id":23424829,
    "woe:name_adm0":"Deutschland",
    "woe:name_adm1":"Nordrhein-Westfalen",
    "woe:placetype":"Town",
    "wof:name":"Sevelen",
    "wof:placetype":"neighbourhood"
},
  "geometry": {"coordinates":[6.42869,51.49298],"type":"Point"}
}