{
  "type": "Feature",
  "properties": {
    "gn:admin1_code":"11",
    "gn:admin2_code":"0.0",
    "gn:admin3_code":"12060.0",
    "gn:admin4_code":"12060269.0",
    "gn:asciiname":"Kolonie Kienitz",
    "gn:country_code":"DE",
    "gn:dem":40,
    "gn:feature_class":"P",
    "gn:feature_code":"PPL",
    "gn:name":"Kolonie Kienitz",
    "gn:population":0,
    "gn:timezone":"Europe/Berlin",
    "iso:country":"DE",
    "wof:name":"Kolonie Kienitz",
    "wof:placetype":"neighbourhood"
},
  "geometry": {"coordinates":[13.50675,52.85395],"type":"Point"}
}