{
  "type": "Feature",
  "properties": {
    "gn:admin1_code":"15",
    "gn:admin2_code":"0.0",
    "gn:admin3_code":"16077.0",
    "gn:admin4_code":"16077036.0",
    "gn:asciiname":"Priefel",
    "gn:country_code":"DE",
    "gn:dem":228,
    "gn:feature_class":"P",
    "gn:feature_code":"PPL",
    "gn:name":"Priefel",
    "gn:population":0,
    "gn:timezone":"Europe/Berlin",
    "iso:country":"DE",
    "wof:name":"Priefel",
    "wof:placetype":"neighbourhood"
},
  "geometry": {"coordinates":[12.4814,50.95573],"type":"Point"}
}