{
  "type": "Feature",
  "properties": {
    "gn:gn_country":"DE",
    "gn:gn_fcode":"PPLA4",
    "gn:gn_pop":155,
    "gn:population":155,
    "iso:country":"DE",
    "name:baq_x_preferred":[
        "Bollenbach"
    ],
    "name:chi_x_preferred":[
        "\u535a\u4f26\u5df4\u8d6b"
    ],
    "name:dut_x_preferred":[
        "Bollenbach"
    ],
    "name:eng_x_preferred":[
        "Bollenbach"
    ],
    "name:epo_x_preferred":[
        "Bollenbach"
    ],
    "name:fre_x_preferred":[
        "Bollenbach"
    ],
    "name:ger_x_preferred":[
        "Bollenbach"
    ],
    "name:hun_x_preferred":[
        "Bollenbach"
    ],
    "name:ita_x_preferred":[
        "Bollenbach"
    ],
    "name:jpn_x_preferred":[
        "\u30dc\u30ec\u30f3\u30d0\u30c3\u30cf"
    ],
    "name:kaz_x_preferred":[
        "\u0411\u043e\u043b\u043b\u0435\u043d\u0431\u0430\u0445"
    ],
    "name:kir_x_preferred":[
        "\u0411\u043e\u043b\u043b\u0435\u043d\u0431\u0430\u0445"
    ],
    "name:may_x_preferred":[
        "Bollenbach"
    ],
    "name:per_x_preferred":[
        "\u0628\u0648\u0644\u0646\u0628\u0627\u062e"
    ],
    "name:pol_x_preferred":[
        "Bollenbach"
    ],
    "name:por_x_preferred":[
        "Bollenbach"
    ],
    "name:rum_x_preferred":[
        "Bollenbach"
    ],
    "name:rus_x_preferred":[
        "\u0411\u043e\u043b\u043b\u0435\u043d\u0431\u0430\u0445"
    ],
    "name:spa_x_preferred":[
        "Bollenbach"
    ],
    "name:srp_x_preferred":[
        "\u0411\u043e\u043b\u0435\u043d\u0431\u0430\u0445"
    ],
    "name:ukr_x_preferred":[
        "\u0411\u043e\u043b\u043b\u0435\u043d\u0431\u0430\u0445"
    ],
    "name:uzb_x_preferred":[
        "Bollenbach"
    ],
    "name:vie_x_preferred":[
        "Bollenbach"
    ],
    "name:vol_x_preferred":[
        "Bollenbach"
    ],
    "name:war_x_preferred":[
        "Bollenbach"
    ],
    "qs_pg:aaroncc":"DE",
    "qs_pg:gn_country":"DE",
    "qs_pg:gn_fcode":"PPLA4",
    "qs_pg:gn_pop":155,
    "qs_pg:name":"Bollenbach",
    "qs_pg:photos_9r":0,
    "qs_pg:photos_sr":0,
    "qs_pg:pop_sr":1,
    "qs_pg:qs_pg_placetype":"locality",
    "wof:name":"Bollenbach",
    "wof:placetype":"locality",
    "wof:population":155
},
  "geometry": {"coordinates":[7.35,49.83333],"type":"Point"}
}