{
  "type": "Feature",
  "properties": {
    "gn:admin1_code":"8",
    "gn:admin2_code":"0.0",
    "gn:admin3_code":"7143.0",
    "gn:admin4_code":"7143231.0",
    "gn:asciiname":"Hahn bei Marienberg",
    "gn:cc2":"DE",
    "gn:country_code":"DE",
    "gn:dem":389,
    "gn:feature_class":"P",
    "gn:feature_code":"PPLA4",
    "gn:name":"Hahn bei Marienberg",
    "gn:population":0,
    "gn:timezone":"Europe/Berlin",
    "iso:country":"DE",
    "name:und_x_variant":[
        "Hahn",
        "Hahn bei Marienberg"
    ],
    "wof:name":"Hahn bei Marienberg",
    "wof:placetype":"locality"
},
  "geometry": {"coordinates":[7.94111,50.63278],"type":"Point"}
}