{
  "type": "Feature",
  "properties": {
    "gn:admin1_code":"2.0",
    "gn:admin2_code":"94.0",
    "gn:admin3_code":"9471.0",
    "gn:admin4_code":"9471128.0",
    "gn:asciiname":"Kleingressingen",
    "gn:country_code":"DE",
    "gn:dem":385,
    "gn:feature_class":"P",
    "gn:feature_code":"PPL",
    "gn:name":"Kleingressingen",
    "gn:population":0,
    "gn:timezone":"Europe/Berlin",
    "iso:country":"DE",
    "wof:name":"Kleingressingen",
    "wof:placetype":"neighbourhood"
},
  "geometry": {"coordinates":[10.46791,49.8289],"type":"Point"}
}