{
  "type": "Feature",
  "properties": {
    "gn:admin1_code":"11.0",
    "gn:admin2_code":"00",
    "gn:admin3_code":"12061.0",
    "gn:admin4_code":"12061219.0",
    "gn:asciiname":"Weissack",
    "gn:country_code":"DE",
    "gn:dem":90,
    "gn:feature_class":"P",
    "gn:feature_code":"PPL",
    "gn:name":"Wei\u00dfack",
    "gn:population":0,
    "gn:timezone":"Europe/Berlin",
    "iso:country":"DE",
    "wof:name":"Weissack",
    "wof:placetype":"neighbourhood"
},
  "geometry": {"coordinates":[13.69402,51.75022],"type":"Point"}
}