{
  "type": "Feature",
  "properties": {
    "gn:admin1_code":"7",
    "gn:admin2_code":"53.0",
    "gn:admin3_code":"5382.0",
    "gn:admin4_code":"5382016.0",
    "gn:asciiname":"Forst",
    "gn:country_code":"DE",
    "gn:dem":110,
    "gn:feature_class":"P",
    "gn:feature_code":"PPL",
    "gn:name":"Forst",
    "gn:population":0,
    "gn:timezone":"Europe/Berlin",
    "iso:country":"DE",
    "wof:name":"Forst",
    "wof:placetype":"neighbourhood"
},
  "geometry": {"coordinates":[7.47973,50.76058],"type":"Point"}
}