{
  "type": "Feature",
  "properties": {
    "gn:admin1_code":"7",
    "gn:admin2_code":"53.0",
    "gn:admin3_code":"5358.0",
    "gn:admin4_code":"5358052.0",
    "gn:asciiname":"Hommelsheim",
    "gn:country_code":"DE",
    "gn:dem":133,
    "gn:feature_class":"P",
    "gn:feature_code":"PPL",
    "gn:name":"Hommelsheim",
    "gn:population":0,
    "gn:timezone":"Europe/Berlin",
    "iso:country":"DE",
    "wof:name":"Hommelsheim",
    "wof:placetype":"neighbourhood"
},
  "geometry": {"coordinates":[6.58991,50.79977],"type":"Point"}
}