{
  "type": "Feature",
  "properties": {
    "gn:admin1_code":"6",
    "gn:admin2_code":"0.0",
    "gn:admin3_code":"3155.0",
    "gn:admin4_code":"3155013.0",
    "gn:asciiname":"Stroit",
    "gn:country_code":"DE",
    "gn:dem":197,
    "gn:feature_class":"P",
    "gn:feature_code":"PPL",
    "gn:name":"Stroit",
    "gn:population":0,
    "gn:timezone":"Europe/Berlin",
    "iso:country":"DE",
    "wof:name":"Stroit",
    "wof:placetype":"neighbourhood"
},
  "geometry": {"coordinates":[9.85964,51.88926],"type":"Point"}
}