{
  "type": "Feature",
  "properties": {
    "gn:admin1_code":"2",
    "gn:admin2_code":"91.0",
    "gn:admin3_code":"9179.0",
    "gn:admin4_code":"9179123.0",
    "gn:asciiname":"Neugermering",
    "gn:country_code":"DE",
    "gn:dem":536,
    "gn:feature_class":"P",
    "gn:feature_code":"PPL",
    "gn:name":"Neugermering",
    "gn:population":0,
    "gn:timezone":"Europe/Berlin",
    "iso:country":"DE",
    "wof:name":"Neugermering",
    "wof:placetype":"neighbourhood"
},
  "geometry": {"coordinates":[11.38344,48.13687],"type":"Point"}
}