{
  "type": "Feature",
  "properties": {
    "gn:admin1_code":"12",
    "gn:admin2_code":"0.0",
    "gn:admin3_code":"13076.0",
    "gn:admin4_code":"13076034.0",
    "gn:asciiname":"Klein Schmoelen",
    "gn:country_code":"DE",
    "gn:dem":17,
    "gn:feature_class":"P",
    "gn:feature_code":"PPL",
    "gn:name":"Klein Schm\u00f6len",
    "gn:population":0,
    "gn:timezone":"Europe/Berlin",
    "iso:country":"DE",
    "wof:name":"Klein Schmoelen",
    "wof:placetype":"neighbourhood"
},
  "geometry": {"coordinates":[11.29223,53.13101999999999],"type":"Point"}
}