{
  "type": "Feature",
  "properties": {
    "gn:admin1_code":"8",
    "gn:admin2_code":"0.0",
    "gn:admin3_code":"7143.0",
    "gn:admin4_code":"7143249.0",
    "gn:asciiname":"Elben",
    "gn:country_code":"DE",
    "gn:dem":375,
    "gn:feature_class":"P",
    "gn:feature_code":"PPL",
    "gn:name":"Elben",
    "gn:population":0,
    "gn:timezone":"Europe/Berlin",
    "iso:country":"DE",
    "name:ceb_x_preferred":[
        "Elben"
    ],
    "name:deu_x_preferred":[
        "Elben"
    ],
    "name:epo_x_preferred":[
        "Elben"
    ],
    "name:eus_x_preferred":[
        "Elben"
    ],
    "name:fas_x_preferred":[
        "\u0627\u06cc\u0644\u0628\u0646"
    ],
    "name:fra_x_preferred":[
        "Elben"
    ],
    "name:hun_x_preferred":[
        "Elben"
    ],
    "name:ita_x_preferred":[
        "Elben"
    ],
    "name:kaz_x_preferred":[
        "\u042d\u043b\u044c\u0431\u0435\u043d"
    ],
    "name:kir_x_preferred":[
        "\u042d\u043b\u044c\u0431\u0435\u043d"
    ],
    "name:msa_x_preferred":[
        "Elben"
    ],
    "name:nld_x_preferred":[
        "Elben"
    ],
    "name:pol_x_preferred":[
        "Elben"
    ],
    "name:por_x_preferred":[
        "Elben"
    ],
    "name:ron_x_preferred":[
        "Elben"
    ],
    "name:rus_x_preferred":[
        "\u042d\u043b\u044c\u0431\u0435\u043d"
    ],
    "name:spa_x_preferred":[
        "Elben"
    ],
    "name:srp_x_preferred":[
        "\u0415\u043b\u0431\u0435\u043d"
    ],
    "name:ukr_x_preferred":[
        "\u0415\u043b\u044c\u0431\u0435\u043d"
    ],
    "name:uzb_x_preferred":[
        "Elben"
    ],
    "name:vie_x_preferred":[
        "Elben"
    ],
    "name:vol_x_preferred":[
        "Elben"
    ],
    "name:war_x_preferred":[
        "Elben"
    ],
    "name:zho_x_preferred":[
        "\u57c3\u5c14\u672c"
    ],
    "wof:name":"Elben",
    "wof:placetype":"neighbourhood"
},
  "geometry": {"coordinates":[7.92595,50.54937],"type":"Point"}
}