{
  "type": "Feature",
  "properties": {
    "gn:admin1_code":"8",
    "gn:admin2_code":"0.0",
    "gn:admin3_code":"7132.0",
    "gn:admin4_code":"7132115.0",
    "gn:asciiname":"Hilkhausen",
    "gn:country_code":"DE",
    "gn:dem":253,
    "gn:feature_class":"P",
    "gn:feature_code":"PPL",
    "gn:name":"Hilkhausen",
    "gn:population":0,
    "gn:timezone":"Europe/Berlin",
    "iso:country":"DE",
    "wof:name":"Hilkhausen",
    "wof:placetype":"neighbourhood"
},
  "geometry": {"coordinates":[7.55917,50.70273],"type":"Point"}
}