{
  "type": "Feature",
  "properties": {
    "gn:admin1_code":"2",
    "gn:admin2_code":"93.0",
    "gn:admin3_code":"9377.0",
    "gn:admin4_code":"9377115.0",
    "gn:asciiname":"Grunlas",
    "gn:country_code":"DE",
    "gn:dem":574,
    "gn:feature_class":"P",
    "gn:feature_code":"PPL",
    "gn:name":"Gr\u00fcnlas",
    "gn:population":0,
    "gn:timezone":"Europe/Berlin",
    "iso:country":"DE",
    "wof:name":"Grunlas",
    "wof:placetype":"neighbourhood"
},
  "geometry": {"coordinates":[11.93445,49.96643],"type":"Point"}
}