{
  "type": "Feature",
  "properties": {
    "gn:admin1_code":"2",
    "gn:admin2_code":"93.0",
    "gn:admin3_code":"9375.0",
    "gn:admin4_code":"9375118.0",
    "gn:asciiname":"Rechberg",
    "gn:country_code":"DE",
    "gn:dem":549,
    "gn:feature_class":"P",
    "gn:feature_code":"PPL",
    "gn:name":"Rechberg",
    "gn:population":0,
    "gn:timezone":"Europe/Berlin",
    "iso:country":"DE",
    "wof:name":"Rechberg",
    "wof:placetype":"neighbourhood"
},
  "geometry": {"coordinates":[11.86747,49.13736],"type":"Point"}
}