{
  "type": "Feature",
  "properties": {
    "gn:admin1_code":"6.0",
    "gn:admin2_code":"00",
    "gn:admin3_code":"3459.0",
    "gn:admin4_code":"3459010.0",
    "gn:asciiname":"Woltrup",
    "gn:country_code":"DE",
    "gn:dem":47,
    "gn:feature_class":"P",
    "gn:feature_code":"PPL",
    "gn:name":"Woltrup",
    "gn:population":0,
    "gn:timezone":"Europe/Berlin",
    "iso:country":"DE",
    "wof:name":"Woltrup",
    "wof:placetype":"neighbourhood"
},
  "geometry": {"coordinates":[7.94279,52.53413000000001],"type":"Point"}
}