{
  "type": "Feature",
  "properties": {
    "iso:country":"DE",
    "name:aze_x_preferred":[
        "Bankenviertel"
    ],
    "name:dan_x_preferred":[
        "Bankenviertel"
    ],
    "name:deu_x_preferred":[
        "Frankfurter Bankenviertel"
    ],
    "name:nld_x_preferred":[
        "Bankenviertel"
    ],
    "name:nor_x_preferred":[
        "Bankenviertel"
    ],
    "name:pol_x_preferred":[
        "Bankenviertel"
    ],
    "name:spa_x_preferred":[
        "Bankenviertel"
    ],
    "name:swe_x_preferred":[
        "Bankenviertel"
    ],
    "name:zho_x_preferred":[
        "\u94f6\u884c\u533a"
    ],
    "wof:name":"Bankenviertel",
    "wof:placetype":"neighbourhood"
},
  "geometry": {"coordinates":[6.77704454503371,51.22234559538528],"type":"Point"}
}