{
  "type": "Feature",
  "properties": {
    "iso:country":"DE",
    "wof:name":"Probstheida",
    "wof:placetype":"neighbourhood"
},
  "geometry": {"coordinates":[12.42794274393657,51.30406023966525],"type":"Point"}
}