{
  "type": "Feature",
  "properties": {
    "gn:admin1_code":"2",
    "gn:admin2_code":"91.0",
    "gn:admin3_code":"9176.0",
    "gn:admin4_code":"9176164.0",
    "gn:asciiname":"Kaldorf",
    "gn:country_code":"DE",
    "gn:dem":540,
    "gn:feature_class":"P",
    "gn:feature_code":"PPL",
    "gn:name":"Kaldorf",
    "gn:population":0,
    "gn:timezone":"Europe/Berlin",
    "iso:country":"DE",
    "wof:name":"Kaldorf",
    "wof:placetype":"neighbourhood"
},
  "geometry": {"coordinates":[11.17991,48.99158],"type":"Point"}
}