{
  "type": "Feature",
  "properties": {
    "gn:admin1_code":"2",
    "gn:admin2_code":"92.0",
    "gn:admin3_code":"9277.0",
    "gn:admin4_code":"9277152.0",
    "gn:asciiname":"Pecheigen",
    "gn:country_code":"DE",
    "gn:dem":486,
    "gn:feature_class":"P",
    "gn:feature_code":"PPL",
    "gn:name":"Pecheigen",
    "gn:population":0,
    "gn:timezone":"Europe/Berlin",
    "iso:country":"DE",
    "wof:name":"Pecheigen",
    "wof:placetype":"neighbourhood"
},
  "geometry": {"coordinates":[13.01378,48.34501],"type":"Point"}
}