{
  "type": "Feature",
  "properties": {
    "gn:admin1_code":"2",
    "gn:admin2_code":"94.0",
    "gn:admin3_code":"9479.0",
    "gn:admin4_code":"9479135.0",
    "gn:asciiname":"Habnith",
    "gn:country_code":"DE",
    "gn:dem":535,
    "gn:feature_class":"P",
    "gn:feature_code":"PPL",
    "gn:name":"Habnith",
    "gn:population":0,
    "gn:timezone":"Europe/Berlin",
    "iso:country":"DE",
    "wof:name":"Habnith",
    "wof:placetype":"neighbourhood"
},
  "geometry": {"coordinates":[12.01078,50.11494],"type":"Point"}
}