{
  "type": "Feature",
  "properties": {
    "gn:admin1_code":"2",
    "gn:admin2_code":"95.0",
    "gn:admin3_code":"9574.0",
    "gn:admin4_code":"9574135.0",
    "gn:asciiname":"Steinensittenbach",
    "gn:country_code":"DE",
    "gn:dem":491,
    "gn:feature_class":"P",
    "gn:feature_code":"PPL",
    "gn:name":"Steinensittenbach",
    "gn:population":0,
    "gn:timezone":"Europe/Berlin",
    "iso:country":"DE",
    "wof:name":"Steinensittenbach",
    "wof:placetype":"neighbourhood"
},
  "geometry": {"coordinates":[11.41479,49.59397],"type":"Point"}
}