{
  "type": "Feature",
  "properties": {
    "gn:admin1_code":"6",
    "gn:admin2_code":"0.0",
    "gn:admin3_code":"3158.0",
    "gn:admin4_code":"3158006.0",
    "gn:asciiname":"Hordorf",
    "gn:country_code":"DE",
    "gn:dem":96,
    "gn:feature_class":"P",
    "gn:feature_code":"PPL",
    "gn:name":"Hordorf",
    "gn:population":0,
    "gn:timezone":"Europe/Berlin",
    "iso:country":"DE",
    "wof:name":"Hordorf",
    "wof:placetype":"neighbourhood"
},
  "geometry": {"coordinates":[10.65517,52.29123],"type":"Point"}
}