{
  "type": "Feature",
  "properties": {
    "gn:admin1_code":"6",
    "gn:admin2_code":"0.0",
    "gn:admin3_code":"3358.0",
    "gn:admin4_code":"3358017.0",
    "gn:asciiname":"Sprengel",
    "gn:country_code":"DE",
    "gn:dem":85,
    "gn:feature_class":"P",
    "gn:feature_code":"PPL",
    "gn:name":"Sprengel",
    "gn:population":0,
    "gn:timezone":"Europe/Berlin",
    "iso:country":"DE",
    "wof:name":"Sprengel",
    "wof:placetype":"neighbourhood"
},
  "geometry": {"coordinates":[9.73789,53.06566],"type":"Point"}
}