{
  "type": "Feature",
  "properties": {
    "gn:admin1_code":"2",
    "gn:admin2_code":"92.0",
    "gn:admin3_code":"9275.0",
    "gn:admin4_code":"9275138.0",
    "gn:asciiname":"Steinkirchen",
    "gn:country_code":"DE",
    "gn:dem":348,
    "gn:feature_class":"P",
    "gn:feature_code":"PPL",
    "gn:name":"Steinkirchen",
    "gn:population":0,
    "gn:timezone":"Europe/Berlin",
    "iso:country":"DE",
    "name:ara_x_preferred":[
        "\u0634\u062a\u0622\u064a\u0646\u0643\u064a\u0631\u0634\u064a\u0646"
    ],
    "name:dan_x_preferred":[
        "Steinkirchen"
    ],
    "name:deu_x_preferred":[
        "Steinkirchen"
    ],
    "name:epo_x_preferred":[
        "Steinkirchen"
    ],
    "name:eus_x_preferred":[
        "Steinkirchen"
    ],
    "name:fas_x_preferred":[
        "\u0627\u0634\u062a\u0627\u06cc\u0646 \u06a9\u06cc\u0631\u0634\u0646"
    ],
    "name:fra_x_preferred":[
        "Steinkirchen"
    ],
    "name:hun_x_preferred":[
        "Steinkirchen"
    ],
    "name:ind_x_preferred":[
        "Steinkirchen"
    ],
    "name:ita_x_preferred":[
        "Steinkirchen"
    ],
    "name:kaz_x_preferred":[
        "\u0428\u0442\u0430\u0439\u043d\u043a\u0438\u0440\u0445\u0435\u043d"
    ],
    "name:lmo_x_preferred":[
        "Steinkirchen"
    ],
    "name:msa_x_preferred":[
        "Steinkirchen"
    ],
    "name:nld_x_preferred":[
        "Steinkirchen"
    ],
    "name:pol_x_preferred":[
        "Steinkirchen"
    ],
    "name:por_x_preferred":[
        "Steinkirchen"
    ],
    "name:ron_x_preferred":[
        "Steinkirchen"
    ],
    "name:rus_x_preferred":[
        "\u0428\u0442\u0430\u0439\u043d\u043a\u0438\u0440\u0445\u0435\u043d"
    ],
    "name:srp_x_preferred":[
        "\u0428\u0442\u0430\u0458\u043d\u043a\u0438\u0440\u0445\u0435\u043d"
    ],
    "name:ukr_x_preferred":[
        "\u0428\u0442\u0430\u0439\u043d\u043a\u0456\u0440\u0445\u0435\u043d"
    ],
    "name:uzb_x_preferred":[
        "Steinkirchen"
    ],
    "name:vol_x_preferred":[
        "Steinkirchen"
    ],
    "name:war_x_preferred":[
        "Steinkirchen"
    ],
    "name:zho_x_preferred":[
        "\u65bd\u6cf0\u56e0\u57fa\u5174"
    ],
    "wof:name":"Steinkirchen",
    "wof:placetype":"neighbourhood"
},
  "geometry": {"coordinates":[13.22194,48.53417],"type":"Point"}
}