{
  "type": "Feature",
  "properties": {
    "gn:admin1_code":"2",
    "gn:admin2_code":"92.0",
    "gn:admin3_code":"9277.0",
    "gn:admin4_code":"9277149.0",
    "gn:asciiname":"Lengsham",
    "gn:country_code":"DE",
    "gn:dem":378,
    "gn:feature_class":"P",
    "gn:feature_code":"PPL",
    "gn:name":"Lengsham",
    "gn:population":0,
    "gn:timezone":"Europe/Berlin",
    "iso:country":"DE",
    "wof:name":"Lengsham",
    "wof:placetype":"neighbourhood"
},
  "geometry": {"coordinates":[13.0289,48.41085],"type":"Point"}
}