{
  "type": "Feature",
  "properties": {
    "gn:admin1_code":"2",
    "gn:admin2_code":"97.0",
    "gn:admin3_code":"9776.0",
    "gn:admin4_code":"9776131.0",
    "gn:asciiname":"Itzlings",
    "gn:country_code":"DE",
    "gn:dem":575,
    "gn:feature_class":"P",
    "gn:feature_code":"PPL",
    "gn:name":"Itzlings",
    "gn:population":0,
    "gn:timezone":"Europe/Berlin",
    "iso:country":"DE",
    "wof:name":"Itzlings",
    "wof:placetype":"neighbourhood"
},
  "geometry": {"coordinates":[9.83874,47.65756],"type":"Point"}
}