{
  "type": "Feature",
  "properties": {
    "gn:admin1_code":"2",
    "gn:admin2_code":"92.0",
    "gn:admin3_code":"9277.0",
    "gn:admin4_code":"9277154.0",
    "gn:asciiname":"Lanhofen",
    "gn:country_code":"DE",
    "gn:dem":392,
    "gn:feature_class":"P",
    "gn:feature_code":"PPL",
    "gn:name":"Lanhofen",
    "gn:population":0,
    "gn:timezone":"Europe/Berlin",
    "iso:country":"DE",
    "wof:name":"Lanhofen",
    "wof:placetype":"neighbourhood"
},
  "geometry": {"coordinates":[12.90361,48.26653],"type":"Point"}
}