{
  "type": "Feature",
  "properties": {
    "gn:admin1_code":"2",
    "gn:admin2_code":"94.0",
    "gn:admin3_code":"9479.0",
    "gn:admin4_code":"9479169.0",
    "gn:asciiname":"Hildenbach",
    "gn:country_code":"DE",
    "gn:dem":621,
    "gn:feature_class":"P",
    "gn:feature_code":"PPL",
    "gn:name":"Hildenbach",
    "gn:population":0,
    "gn:timezone":"Europe/Berlin",
    "iso:country":"DE",
    "wof:name":"Hildenbach",
    "wof:placetype":"neighbourhood"
},
  "geometry": {"coordinates":[11.95218,50.04026],"type":"Point"}
}