{
  "type": "Feature",
  "properties": {
    "gn:admin1_code":"5",
    "gn:admin2_code":"64.0",
    "gn:admin3_code":"6440.0",
    "gn:admin4_code":"6440007.0",
    "gn:asciiname":"Staden",
    "gn:country_code":"DE",
    "gn:dem":125,
    "gn:feature_class":"P",
    "gn:feature_code":"PPL",
    "gn:name":"Staden",
    "gn:population":0,
    "gn:timezone":"Europe/Berlin",
    "iso:country":"DE",
    "name:bre_x_preferred":[
        "Staden"
    ],
    "name:bul_x_preferred":[
        "\u0421\u0442\u0430\u0434\u0435\u043d"
    ],
    "name:cat_x_preferred":[
        "Staden"
    ],
    "name:ceb_x_preferred":[
        "Staden"
    ],
    "name:deu_x_preferred":[
        "Staden"
    ],
    "name:epo_x_preferred":[
        "Staden"
    ],
    "name:est_x_preferred":[
        "Staden"
    ],
    "name:eus_x_preferred":[
        "Staden"
    ],
    "name:fas_x_preferred":[
        "\u0633\u062a\u062f\u0627\u0646"
    ],
    "name:fra_x_preferred":[
        "Staden"
    ],
    "name:hun_x_preferred":[
        "Staden"
    ],
    "name:ita_x_preferred":[
        "Staden"
    ],
    "name:lim_x_preferred":[
        "Staden"
    ],
    "name:ltz_x_preferred":[
        "Staden"
    ],
    "name:nld_x_preferred":[
        "Staden"
    ],
    "name:nor_x_preferred":[
        "Staden"
    ],
    "name:oci_x_preferred":[
        "Staden"
    ],
    "name:pol_x_preferred":[
        "Staden"
    ],
    "name:por_x_preferred":[
        "Staden"
    ],
    "name:ron_x_preferred":[
        "Staden"
    ],
    "name:slk_x_preferred":[
        "Staden"
    ],
    "name:spa_x_preferred":[
        "Staden"
    ],
    "name:swe_x_preferred":[
        "Staden"
    ],
    "name:vie_x_preferred":[
        "Staden"
    ],
    "name:vls_x_preferred":[
        "Stoan"
    ],
    "name:vol_x_preferred":[
        "Staden"
    ],
    "name:war_x_preferred":[
        "Staden"
    ],
    "name:zho_x_preferred":[
        "\u65af\u5854\u767b"
    ],
    "wof:name":"Staden",
    "wof:placetype":"neighbourhood"
},
  "geometry": {"coordinates":[8.91247,50.33152000000001],"type":"Point"}
}