{
  "type": "Feature",
  "properties": {
    "gn:admin1_code":"13",
    "gn:admin2_code":"0.0",
    "gn:admin3_code":"14625.0",
    "gn:admin4_code":"14625020.0",
    "gn:asciiname":"Strehla",
    "gn:country_code":"DE",
    "gn:dem":192,
    "gn:feature_class":"P",
    "gn:feature_code":"PPL",
    "gn:name":"Strehla",
    "gn:population":0,
    "gn:timezone":"Europe/Berlin",
    "iso:country":"DE",
    "name:ara_x_preferred":[
        "\u0634\u062a\u0631\u064a\u0644\u0627"
    ],
    "name:azb_x_preferred":[
        "\u0627\u0634\u062a\u0631\u0644\u0627"
    ],
    "name:bak_x_preferred":[
        "\u0428\u0442\u0440\u0435\u043b\u0430"
    ],
    "name:ceb_x_preferred":[
        "Strehla"
    ],
    "name:deu_x_preferred":[
        "Strehla"
    ],
    "name:epo_x_preferred":[
        "Strehla"
    ],
    "name:est_x_preferred":[
        "Strehla"
    ],
    "name:fas_x_preferred":[
        "\u0627\u0634\u062a\u0631\u0644\u0627"
    ],
    "name:fra_x_preferred":[
        "Strehla"
    ],
    "name:hsb_x_preferred":[
        "T\u0159\u011blany"
    ],
    "name:hsb_x_variant":[
        "Strjela"
    ],
    "name:hun_x_preferred":[
        "Strehla"
    ],
    "name:ita_x_preferred":[
        "Strehla"
    ],
    "name:lav_x_preferred":[
        "\u0160tr\u0113la"
    ],
    "name:mkd_x_preferred":[
        "\u0428\u0442\u0440\u0435\u043b\u0430"
    ],
    "name:msa_x_preferred":[
        "Strehla"
    ],
    "name:nld_x_preferred":[
        "Strehla"
    ],
    "name:pol_x_preferred":[
        "Strehla"
    ],
    "name:ron_x_preferred":[
        "Strehla"
    ],
    "name:rus_x_preferred":[
        "\u0428\u0442\u0440\u0435\u043b\u0430"
    ],
    "name:spa_x_preferred":[
        "Strehla"
    ],
    "name:srp_x_preferred":[
        "\u0428\u0442\u0440\u0435\u043b\u0430"
    ],
    "name:swe_x_preferred":[
        "Strehla"
    ],
    "name:ukr_x_preferred":[
        "\u0428\u0442\u0440\u0435\u043b\u0430"
    ],
    "name:uzb_x_preferred":[
        "Strehla"
    ],
    "name:vie_x_preferred":[
        "Strehla"
    ],
    "name:vol_x_preferred":[
        "Strehla"
    ],
    "name:war_x_preferred":[
        "Strehla"
    ],
    "name:zho_x_preferred":[
        "\u65bd\u7279\u96f7\u62c9"
    ],
    "wof:name":"Strehla",
    "wof:placetype":"neighbourhood"
},
  "geometry": {"coordinates":[14.44109,51.16893],"type":"Point"}
}