{
  "type": "Feature",
  "properties": {
    "gn:admin1_code":"2",
    "gn:admin2_code":"93.0",
    "gn:admin3_code":"9372.0",
    "gn:admin4_code":"9372170.0",
    "gn:asciiname":"Kirchenrohrbach",
    "gn:country_code":"DE",
    "gn:dem":377,
    "gn:feature_class":"P",
    "gn:feature_code":"PPL",
    "gn:name":"Kirchenrohrbach",
    "gn:population":0,
    "gn:timezone":"Europe/Berlin",
    "iso:country":"DE",
    "wof:name":"Kirchenrohrbach",
    "wof:placetype":"neighbourhood"
},
  "geometry": {"coordinates":[12.40611,49.18362],"type":"Point"}
}