{
  "type": "Feature",
  "properties": {
    "gn:admin1_code":"1",
    "gn:admin2_code":"83.0",
    "gn:admin3_code":"8337.0",
    "gn:admin4_code":"8337096.0",
    "gn:asciiname":"Rippolingen",
    "gn:country_code":"DE",
    "gn:dem":539,
    "gn:feature_class":"P",
    "gn:feature_code":"PPL",
    "gn:name":"Rippolingen",
    "gn:population":0,
    "gn:timezone":"Europe/Berlin",
    "iso:country":"DE",
    "wof:name":"Rippolingen",
    "wof:placetype":"neighbourhood"
},
  "geometry": {"coordinates":[7.9868,47.5767],"type":"Point"}
}