{
  "type": "Feature",
  "properties": {
    "iso:country":"DE",
    "name:cat_x_preferred":[
        "M\u00f6ggers"
    ],
    "name:ceb_x_preferred":[
        "M\u00f6ggers"
    ],
    "name:che_x_preferred":[
        "\u041c\u043e\u044c\u0433\u0433\u0435\u0440\u0441"
    ],
    "name:deu_x_preferred":[
        "M\u00f6ggers"
    ],
    "name:eng_x_preferred":[
        "M\u00f6ggers"
    ],
    "name:est_x_preferred":[
        "M\u00f6ggers"
    ],
    "name:fas_x_preferred":[
        "\u0645\u0648\u06af\u0631\u0633"
    ],
    "name:fra_x_preferred":[
        "M\u00f6ggers"
    ],
    "name:fur_x_preferred":[
        "M\u00f6ggers"
    ],
    "name:gsw_x_preferred":[
        "M\u00f6ggers"
    ],
    "name:hun_x_preferred":[
        "M\u00f6ggers"
    ],
    "name:ita_x_preferred":[
        "M\u00f6ggers"
    ],
    "name:lld_x_preferred":[
        "M\u00f6ggers"
    ],
    "name:lmo_x_preferred":[
        "M\u00f6ggers"
    ],
    "name:nld_x_preferred":[
        "M\u00f6ggers"
    ],
    "name:nob_x_preferred":[
        "M\u00f6ggers"
    ],
    "name:pol_x_preferred":[
        "M\u00f6ggers"
    ],
    "name:por_x_preferred":[
        "M\u00f6ggers"
    ],
    "name:rus_x_preferred":[
        "\u041c\u0451\u0433\u0433\u0435\u0440\u0441"
    ],
    "name:slk_x_preferred":[
        "M\u00f6ggers"
    ],
    "name:spa_x_preferred":[
        "M\u00f6ggers"
    ],
    "name:swe_x_preferred":[
        "M\u00f6ggers"
    ],
    "name:tat_x_preferred":[
        "\u041c\u0451\u0433\u0433\u0435\u0440\u0441"
    ],
    "name:tgk_x_preferred":[
        "\u041c\u0451\u0433\u0433\u0435\u0440\u0441"
    ],
    "name:ukr_x_preferred":[
        "\u041c\u0435\u0433\u0433\u0435\u0440\u0441"
    ],
    "name:uzb_x_preferred":[
        "M\u00f6ggers"
    ],
    "name:vec_x_preferred":[
        "M\u00f6ggers"
    ],
    "name:vol_x_preferred":[
        "M\u00f6ggers"
    ],
    "name:war_x_preferred":[
        "M\u00f6ggers"
    ],
    "name:zho_x_preferred":[
        "\u9ed8\u683c\u5c14\u65af"
    ],
    "qs_pg:aaroncc":"DE",
    "qs_pg:name":"M\u00f6ggers",
    "qs_pg:name_adm0":"\u00d6sterreich",
    "qs_pg:name_adm1":"Vorarlberg",
    "qs_pg:photos":41,
    "qs_pg:photos_1k":8,
    "qs_pg:photos_9k":1,
    "qs_pg:photos_9r":2,
    "qs_pg:photos_all":41,
    "qs_pg:photos_sr":2,
    "qs_pg:pop_sr":0,
    "qs_pg:qs_pg_placetype":"locality",
    "qs_pg:qs_pg_placetype_gp":"Town",
    "qs_pg:woe_adm0":23424750,
    "woe:adm0_id":23424750,
    "woe:name_adm0":"\u00d6sterreich",
    "woe:name_adm1":"Vorarlberg",
    "woe:placetype":"Town",
    "wof:name":"M\u00f6ggers",
    "wof:placetype":"neighbourhood"
},
  "geometry": {"coordinates":[9.826041,47.564405],"type":"Point"}
}