{
  "type": "Feature",
  "properties": {
    "gn:admin1_code":"10",
    "gn:admin2_code":"0.0",
    "gn:admin3_code":"1061.0",
    "gn:admin4_code":"1061101.0",
    "gn:asciiname":"Duekermuehle",
    "gn:country_code":"DE",
    "gn:dem":-3,
    "gn:feature_class":"P",
    "gn:feature_code":"PPL",
    "gn:name":"D\u00fckerm\u00fchle",
    "gn:population":0,
    "gn:timezone":"Europe/Berlin",
    "iso:country":"DE",
    "wof:name":"Duekermuehle",
    "wof:placetype":"neighbourhood"
},
  "geometry": {"coordinates":[9.53182,53.80457],"type":"Point"}
}