{
  "type": "Feature",
  "properties": {
    "gn:admin1_code":"2",
    "gn:admin2_code":"95.0",
    "gn:admin3_code":"9576.0",
    "gn:admin4_code":"9576111.0",
    "gn:asciiname":"Marienburg",
    "gn:country_code":"DE",
    "gn:dem":387,
    "gn:feature_class":"P",
    "gn:feature_code":"PPL",
    "gn:name":"Marienburg",
    "gn:population":0,
    "gn:timezone":"Europe/Berlin",
    "iso:country":"DE",
    "name:ceb_x_preferred":[
        "Marienburg"
    ],
    "name:dan_x_preferred":[
        "Marienburg"
    ],
    "name:deu_x_preferred":[
        "Marienburg"
    ],
    "name:epo_x_preferred":[
        "Marienburg"
    ],
    "name:est_x_preferred":[
        "Marienburg"
    ],
    "name:fra_x_preferred":[
        "Marienburg"
    ],
    "name:hun_x_preferred":[
        "Marienburg"
    ],
    "name:ita_x_preferred":[
        "Marienburg"
    ],
    "name:nld_x_preferred":[
        "Mari\u00ebnburg"
    ],
    "name:pol_x_preferred":[
        "Marienburg"
    ],
    "name:por_x_preferred":[
        "Marienburg"
    ],
    "name:ron_x_preferred":[
        "Marienburg"
    ],
    "name:swe_x_preferred":[
        "Marienburg"
    ],
    "name:ukr_x_preferred":[
        "\u041c\u0430\u0440\u0456\u0454\u043d\u0431\u0443\u0440\u0433"
    ],
    "wof:name":"Marienburg",
    "wof:placetype":"neighbourhood"
},
  "geometry": {"coordinates":[10.9656,49.23597],"type":"Point"}
}