{
  "type": "Feature",
  "properties": {
    "gn:admin1_code":"9",
    "gn:admin2_code":"0.0",
    "gn:admin3_code":"10045.0",
    "gn:admin4_code":"10045115.0",
    "gn:asciiname":"Kohlhof",
    "gn:country_code":"DE",
    "gn:dem":267,
    "gn:feature_class":"P",
    "gn:feature_code":"PPL",
    "gn:name":"Kohlhof",
    "gn:population":0,
    "gn:timezone":"Europe/Berlin",
    "iso:country":"DE",
    "wof:name":"Kohlhof",
    "wof:placetype":"neighbourhood"
},
  "geometry": {"coordinates":[7.23736,49.32151],"type":"Point"}
}