{
  "type": "Feature",
  "properties": {
    "gn:admin1_code":"6.0",
    "gn:admin2_code":"00",
    "gn:admin3_code":"3459.0",
    "gn:admin4_code":"3459024.0",
    "gn:asciiname":"Westendorf",
    "gn:country_code":"DE",
    "gn:dem":94,
    "gn:feature_class":"P",
    "gn:feature_code":"PPL",
    "gn:name":"Westendorf",
    "gn:population":0,
    "gn:timezone":"Europe/Berlin",
    "iso:country":"DE",
    "name:ceb_x_preferred":[
        "Westendorf"
    ],
    "name:ces_x_preferred":[
        "Westendorf"
    ],
    "name:dan_x_preferred":[
        "Westendorf"
    ],
    "name:deu_x_preferred":[
        "Westendorf"
    ],
    "name:epo_x_preferred":[
        "Westendorf"
    ],
    "name:fra_x_preferred":[
        "Westendorf"
    ],
    "name:ita_x_preferred":[
        "Westendorf"
    ],
    "name:jpn_x_preferred":[
        "\u30f4\u30a7\u30b9\u30c6\u30f3\u30c9\u30eb\u30d5"
    ],
    "name:lmo_x_preferred":[
        "Westendorf"
    ],
    "name:nld_x_preferred":[
        "Westendorf"
    ],
    "name:pol_x_preferred":[
        "Westendorf"
    ],
    "name:rus_x_preferred":[
        "\u0412\u0435\u0441\u0442\u0435\u043d\u0434\u043e\u0440\u0444"
    ],
    "name:srp_x_preferred":[
        "\u0412\u0435\u0441\u0442\u0435\u043d\u0434\u043e\u0440\u0444"
    ],
    "name:swe_x_preferred":[
        "Westendorf"
    ],
    "name:vol_x_preferred":[
        "Westendorf"
    ],
    "wof:name":"Westendorf",
    "wof:placetype":"neighbourhood"
},
  "geometry": {"coordinates":[8.39908,52.17912000000001],"type":"Point"}
}