{
  "type": "Feature",
  "properties": {
    "gn:admin1_code":"1.0",
    "gn:admin2_code":"83.0",
    "gn:admin3_code":"8317.0",
    "gn:admin4_code":"8317146.0",
    "gn:asciiname":"Birach",
    "gn:country_code":"DE",
    "gn:dem":232,
    "gn:feature_class":"P",
    "gn:feature_code":"PPL",
    "gn:name":"Birach",
    "gn:population":0,
    "gn:timezone":"Europe/Berlin",
    "iso:country":"DE",
    "wof:name":"Birach",
    "wof:placetype":"neighbourhood"
},
  "geometry": {"coordinates":[8.07999,48.35043],"type":"Point"}
}