{
  "type": "Feature",
  "properties": {
    "gn:admin1_code":"2",
    "gn:admin2_code":"91.0",
    "gn:admin3_code":"9187.0",
    "gn:admin4_code":"9187137.0",
    "gn:asciiname":"Deutlstatt",
    "gn:country_code":"DE",
    "gn:dem":499,
    "gn:feature_class":"P",
    "gn:feature_code":"PPL",
    "gn:name":"Deutlst\u00e4tt",
    "gn:population":0,
    "gn:timezone":"Europe/Berlin",
    "iso:country":"DE",
    "wof:name":"Deutlstatt",
    "wof:placetype":"neighbourhood"
},
  "geometry": {"coordinates":[12.05578,47.90374],"type":"Point"}
}