{
  "type": "Feature",
  "properties": {
    "gn:admin1_code":"13",
    "gn:admin2_code":"0.0",
    "gn:admin3_code":"14625.0",
    "gn:admin4_code":"14625130.0",
    "gn:asciiname":"Kriepitz",
    "gn:country_code":"DE",
    "gn:dem":202,
    "gn:feature_class":"P",
    "gn:feature_code":"PPL",
    "gn:name":"Kriepitz",
    "gn:population":0,
    "gn:timezone":"Europe/Berlin",
    "iso:country":"DE",
    "name:hsb_x_preferred":[
        "Kr\u011bpjecy"
    ],
    "wof:name":"Kriepitz",
    "wof:placetype":"neighbourhood"
},
  "geometry": {"coordinates":[14.15266,51.22451],"type":"Point"}
}