{
  "type": "Feature",
  "properties": {
    "gn:admin1_code":"2",
    "gn:admin2_code":"92.0",
    "gn:admin3_code":"9274.0",
    "gn:admin4_code":"9274183.0",
    "gn:asciiname":"Hub",
    "gn:country_code":"DE",
    "gn:dem":478,
    "gn:feature_class":"P",
    "gn:feature_code":"PPL",
    "gn:name":"Hub",
    "gn:population":0,
    "gn:timezone":"Europe/Berlin",
    "iso:country":"DE",
    "wof:name":"Hub",
    "wof:placetype":"neighbourhood"
},
  "geometry": {"coordinates":[12.26787,48.40537],"type":"Point"}
}