{
  "type": "Feature",
  "properties": {
    "gn:admin1_code":"2",
    "gn:admin2_code":"91.0",
    "gn:admin3_code":"9187.0",
    "gn:admin4_code":"9187130.0",
    "gn:asciiname":"Reisachod",
    "gn:country_code":"DE",
    "gn:dem":609,
    "gn:feature_class":"P",
    "gn:feature_code":"PPL",
    "gn:name":"Reisach\u00f6d",
    "gn:population":0,
    "gn:timezone":"Europe/Berlin",
    "iso:country":"DE",
    "wof:name":"Reisachod",
    "wof:placetype":"neighbourhood"
},
  "geometry": {"coordinates":[11.88326,47.93455],"type":"Point"}
}