{
  "type": "Feature",
  "properties": {
    "gn:admin1_code":"2",
    "gn:admin2_code":"93.0",
    "gn:admin3_code":"9376.0",
    "gn:admin4_code":"9376150.0",
    "gn:asciiname":"Oberkoblitz",
    "gn:country_code":"DE",
    "gn:dem":385,
    "gn:feature_class":"P",
    "gn:feature_code":"PPL",
    "gn:name":"Oberk\u00f6blitz",
    "gn:population":0,
    "gn:timezone":"Europe/Berlin",
    "iso:country":"DE",
    "wof:name":"Oberkoblitz",
    "wof:placetype":"neighbourhood"
},
  "geometry": {"coordinates":[12.15384,49.54701],"type":"Point"}
}