{
  "type": "Feature",
  "properties": {
    "gn:admin1_code":"13",
    "gn:admin2_code":"0.0",
    "gn:admin3_code":"14628.0",
    "gn:admin4_code":"14628260.0",
    "gn:asciiname":"Krumhermsdorf",
    "gn:country_code":"DE",
    "gn:dem":375,
    "gn:feature_class":"P",
    "gn:feature_code":"PPL",
    "gn:name":"Krumhermsdorf",
    "gn:population":0,
    "gn:timezone":"Europe/Berlin",
    "iso:country":"DE",
    "wof:name":"Krumhermsdorf",
    "wof:placetype":"neighbourhood"
},
  "geometry": {"coordinates":[14.19823,50.98816],"type":"Point"}
}