{
  "type": "Feature",
  "properties": {
    "gn:admin1_code":"5",
    "gn:admin2_code":"65.0",
    "gn:admin3_code":"6531.0",
    "gn:admin4_code":"6531013.0",
    "gn:asciiname":"Ruttershausen",
    "gn:country_code":"DE",
    "gn:dem":172,
    "gn:feature_class":"P",
    "gn:feature_code":"PPL",
    "gn:name":"Ruttershausen",
    "gn:population":0,
    "gn:timezone":"Europe/Berlin",
    "iso:country":"DE",
    "wof:name":"Ruttershausen",
    "wof:placetype":"neighbourhood"
},
  "geometry": {"coordinates":[8.70992,50.66306],"type":"Point"}
}