{
  "type": "Feature",
  "properties": {
    "gn:admin1_code":"7",
    "gn:admin2_code":"57.0",
    "gn:admin3_code":"5766.0",
    "gn:admin4_code":"5766020.0",
    "gn:asciiname":"Diestelbruch",
    "gn:cc2":"DE",
    "gn:country_code":"DE",
    "gn:dem":217,
    "gn:feature_class":"P",
    "gn:feature_code":"PPL",
    "gn:name":"Diestelbruch",
    "gn:population":0,
    "gn:timezone":"Europe/Berlin",
    "iso:country":"DE",
    "name:und_x_variant":[
        "Distelbruch"
    ],
    "wof:name":"Diestelbruch",
    "wof:placetype":"neighbourhood"
},
  "geometry": {"coordinates":[8.94974,51.93188],"type":"Point"}
}