{
  "type": "Feature",
  "properties": {
    "gn:admin1_code":"11",
    "gn:admin2_code":"0.0",
    "gn:admin3_code":"12066.0",
    "gn:admin4_code":"12066285.0",
    "gn:asciiname":"Sauo",
    "gn:country_code":"DE",
    "gn:dem":128,
    "gn:feature_class":"P",
    "gn:feature_code":"PPL",
    "gn:name":"Sauo",
    "gn:population":0,
    "gn:timezone":"Europe/Berlin",
    "iso:country":"DE",
    "wof:name":"Sauo",
    "wof:placetype":"neighbourhood"
},
  "geometry": {"coordinates":[13.96667,51.55],"type":"Point"}
}