{
  "type": "Feature",
  "properties": {
    "gn:admin1_code":"5.0",
    "gn:admin2_code":"66.0",
    "gn:admin3_code":"6635.0",
    "gn:admin4_code":"6635019.0",
    "gn:asciiname":"Asel-Sued/Voehl",
    "gn:country_code":"DE",
    "gn:dem":271,
    "gn:feature_class":"P",
    "gn:feature_code":"PPL",
    "gn:name":"Asel-S\u00fcd/V\u00f6hl",
    "gn:population":0,
    "gn:timezone":"Europe/Berlin",
    "iso:country":"DE",
    "wof:name":"Asel-Sued/Voehl",
    "wof:placetype":"neighbourhood"
},
  "geometry": {"coordinates":[8.95487,51.18106],"type":"Point"}
}