{
  "type": "Feature",
  "properties": {
    "gn:admin1_code":"7.0",
    "gn:admin2_code":"059",
    "gn:admin3_code":"5978.0",
    "gn:admin4_code":"5978012.0",
    "gn:asciiname":"Westick",
    "gn:country_code":"DE",
    "gn:dem":131,
    "gn:feature_class":"P",
    "gn:feature_code":"PPL",
    "gn:name":"Westick",
    "gn:population":0,
    "gn:timezone":"Europe/Berlin",
    "iso:country":"DE",
    "wof:name":"Westick",
    "wof:placetype":"neighbourhood"
},
  "geometry": {"coordinates":[7.78777,51.4732],"type":"Point"}
}