{
  "type": "Feature",
  "properties": {
    "gn:admin1_code":"7.0",
    "gn:admin2_code":"059",
    "gn:admin3_code":"5970.0",
    "gn:admin4_code":"5970032.0",
    "gn:asciiname":"Werthenbach",
    "gn:country_code":"DE",
    "gn:dem":388,
    "gn:feature_class":"P",
    "gn:feature_code":"PPL",
    "gn:name":"Werthenbach",
    "gn:population":0,
    "gn:timezone":"Europe/Berlin",
    "iso:country":"DE",
    "wof:name":"Werthenbach",
    "wof:placetype":"neighbourhood"
},
  "geometry": {"coordinates":[8.21568,50.86951],"type":"Point"}
}