{
  "type": "Feature",
  "properties": {
    "gn:admin1_code":"1",
    "gn:admin2_code":"83.0",
    "gn:admin3_code":"8325.0",
    "gn:admin4_code":"8325045.0",
    "gn:asciiname":"Gruner Berg",
    "gn:country_code":"DE",
    "gn:dem":471,
    "gn:feature_class":"P",
    "gn:feature_code":"PPL",
    "gn:name":"Gr\u00fcner Berg",
    "gn:population":0,
    "gn:timezone":"Europe/Berlin",
    "iso:country":"DE",
    "wof:name":"Gruner Berg",
    "wof:placetype":"neighbourhood"
},
  "geometry": {"coordinates":[8.58294,48.28231],"type":"Point"}
}