{
  "type": "Feature",
  "properties": {
    "gn:admin1_code":"2",
    "gn:admin2_code":"92.0",
    "gn:admin3_code":"9272.0",
    "gn:admin4_code":"9272147.0",
    "gn:asciiname":"Eberhardsreuth",
    "gn:country_code":"DE",
    "gn:dem":483,
    "gn:feature_class":"P",
    "gn:feature_code":"PPL",
    "gn:name":"Eberhardsreuth",
    "gn:population":0,
    "gn:timezone":"Europe/Berlin",
    "iso:country":"DE",
    "wof:name":"Eberhardsreuth",
    "wof:placetype":"neighbourhood"
},
  "geometry": {"coordinates":[13.35857,48.81625],"type":"Point"}
}