{
  "type": "Feature",
  "properties": {
    "iso:country":"DE",
    "name:deu_x_preferred":[
        "R\u00f6ttgen"
    ],
    "wof:name":"Roettgen",
    "wof:placetype":"neighbourhood"
},
  "geometry": {"coordinates":[7.07025688589877,50.67607233812826],"type":"Point"}
}