{
  "type": "Feature",
  "properties": {
    "gn:admin1_code":"7",
    "gn:admin2_code":"53.0",
    "gn:admin3_code":"5314.0",
    "gn:admin4_code":"5314000.0",
    "gn:asciiname":"Roettgen",
    "gn:country_code":"DE",
    "gn:dem":171,
    "gn:feature_class":"P",
    "gn:feature_code":"PPL",
    "gn:name":"R\u00f6ttgen",
    "gn:population":0,
    "gn:timezone":"Europe/Berlin",
    "iso:country":"DE",
    "name:deu_x_preferred":[
        "R\u00f6ttgen"
    ],
    "wof:name":"Roettgen",
    "wof:placetype":"neighbourhood"
},
  "geometry": {"coordinates":[7.070257,50.676072],"type":"Point"}
}