{
  "type": "Feature",
  "properties": {
    "gn:admin1_code":"7",
    "gn:admin2_code":"59.0",
    "gn:admin3_code":"5966.0",
    "gn:admin4_code":"5966004.0",
    "gn:asciiname":"Lichtringhausen",
    "gn:country_code":"DE",
    "gn:dem":368,
    "gn:feature_class":"P",
    "gn:feature_code":"PPL",
    "gn:name":"Lichtringhausen",
    "gn:population":0,
    "gn:timezone":"Europe/Berlin",
    "iso:country":"DE",
    "wof:name":"Lichtringhausen",
    "wof:placetype":"neighbourhood"
},
  "geometry": {"coordinates":[7.84228,51.15051],"type":"Point"}
}