{
  "type": "Feature",
  "properties": {
    "gn:admin1_code":"2",
    "gn:admin2_code":"92.0",
    "gn:admin3_code":"9275.0",
    "gn:admin4_code":"9275126.0",
    "gn:asciiname":"Innerhartsberg",
    "gn:country_code":"DE",
    "gn:dem":463,
    "gn:feature_class":"P",
    "gn:feature_code":"PPL",
    "gn:name":"Innerhartsberg",
    "gn:population":0,
    "gn:timezone":"Europe/Berlin",
    "iso:country":"DE",
    "wof:name":"Innerhartsberg",
    "wof:placetype":"neighbourhood"
},
  "geometry": {"coordinates":[13.60665,48.62184],"type":"Point"}
}