{
  "type": "Feature",
  "properties": {
    "gn:admin1_code":"10.0",
    "gn:admin2_code":"0.0",
    "gn:admin3_code":"1055.0",
    "gn:admin4_code":"1055016.0",
    "gn:asciiname":"Brenkenhagen",
    "gn:country_code":"DE",
    "gn:dem":32,
    "gn:feature_class":"P",
    "gn:feature_code":"PPL",
    "gn:name":"Brenkenhagen",
    "gn:population":0,
    "gn:timezone":"Europe/Berlin",
    "iso:country":"DE",
    "wof:name":"Brenkenhagen",
    "wof:placetype":"neighbourhood"
},
  "geometry": {"coordinates":[10.9148,54.15864000000001],"type":"Point"}
}