{
  "type": "Feature",
  "properties": {
    "gn:admin1_code":"15",
    "gn:admin2_code":"0.0",
    "gn:admin3_code":"16072.0",
    "gn:admin4_code":"16072023.0",
    "gn:asciiname":"Korberoth",
    "gn:country_code":"DE",
    "gn:dem":478,
    "gn:feature_class":"P",
    "gn:feature_code":"PPL",
    "gn:name":"Korberoth",
    "gn:population":0,
    "gn:timezone":"Europe/Berlin",
    "iso:country":"DE",
    "wof:name":"Korberoth",
    "wof:placetype":"neighbourhood"
},
  "geometry": {"coordinates":[11.07759,50.35907],"type":"Point"}
}