{
  "type": "Feature",
  "properties": {
    "gn:admin1_code":"2",
    "gn:admin2_code":"91.0",
    "gn:admin3_code":"9182.0",
    "gn:admin4_code":"9182124.0",
    "gn:asciiname":"Point",
    "gn:country_code":"DE",
    "gn:dem":769,
    "gn:feature_class":"P",
    "gn:feature_code":"PPL",
    "gn:name":"Point",
    "gn:population":0,
    "gn:timezone":"Europe/Berlin",
    "iso:country":"DE",
    "name:asm_x_preferred":[
        "\u09ac\u09bf\u09a8\u09cd\u09a6\u09c1"
    ],
    "name:aze_x_preferred":[
        "N\u00f6qt\u0259"
    ],
    "name:ceb_x_preferred":[
        "Point"
    ],
    "name:ces_x_preferred":[
        "Point"
    ],
    "name:cym_x_preferred":[
        "Pwynt"
    ],
    "name:deu_x_preferred":[
        "Point"
    ],
    "name:ell_x_preferred":[
        "\u03a3\u03b7\u03bc\u03b5\u03af\u03bf"
    ],
    "name:fra_x_preferred":[
        "Point"
    ],
    "name:heb_x_preferred":[
        "\u05e0\u05e7\u05d5\u05d3\u05d4"
    ],
    "name:ita_x_preferred":[
        "Point"
    ],
    "name:jpn_x_preferred":[
        "\u30dd\u30a4\u30f3\u30c8"
    ],
    "name:kor_x_preferred":[
        "\ud3ec\uc778\ud2b8"
    ],
    "name:lav_x_preferred":[
        "Punkts"
    ],
    "name:nld_x_preferred":[
        "Point"
    ],
    "name:pol_x_preferred":[
        "Point"
    ],
    "name:por_x_preferred":[
        "Point"
    ],
    "name:ron_x_preferred":[
        "Point"
    ],
    "name:rus_x_preferred":[
        "\u041f\u043e\u0439\u043d\u0442"
    ],
    "name:spa_x_preferred":[
        "Point"
    ],
    "name:urd_x_preferred":[
        "\u067e\u0648\u0627\u0626\u0646\u0679"
    ],
    "wof:name":"Point",
    "wof:placetype":"neighbourhood"
},
  "geometry": {"coordinates":[11.74343,47.66166],"type":"Point"}
}