{
  "type": "Feature",
  "properties": {
    "gn:admin1_code":"2",
    "gn:admin2_code":"91.0",
    "gn:admin3_code":"9177.0",
    "gn:admin4_code":"9177124.0",
    "gn:asciiname":"Burgharting",
    "gn:country_code":"DE",
    "gn:dem":473,
    "gn:feature_class":"P",
    "gn:feature_code":"PPL",
    "gn:name":"Burgharting",
    "gn:population":0,
    "gn:timezone":"Europe/Berlin",
    "iso:country":"DE",
    "wof:name":"Burgharting",
    "wof:placetype":"neighbourhood"
},
  "geometry": {"coordinates":[12.09379,48.42377000000001],"type":"Point"}
}