{
  "type": "Feature",
  "properties": {
    "gn:admin1_code":"14",
    "gn:admin2_code":"0.0",
    "gn:admin3_code":"15090.0",
    "gn:admin4_code":"15090546.0",
    "gn:asciiname":"Grossschwarzlosen",
    "gn:country_code":"DE",
    "gn:dem":45,
    "gn:feature_class":"P",
    "gn:feature_code":"PPL",
    "gn:name":"Gro\u00dfschwarzlosen",
    "gn:population":0,
    "gn:timezone":"Europe/Berlin",
    "iso:country":"DE",
    "name:osx_x_preferred":[
        "Svartesele"
    ],
    "wof:name":"Grossschwarzlosen",
    "wof:placetype":"neighbourhood"
},
  "geometry": {"coordinates":[11.75743,52.50346999999999],"type":"Point"}
}