{
  "type": "Feature",
  "properties": {
    "gn:admin1_code":"7",
    "gn:admin2_code":"59.0",
    "gn:admin3_code":"5954.0",
    "gn:admin4_code":"5954016.0",
    "gn:asciiname":"Niederbonsfeld",
    "gn:country_code":"DE",
    "gn:dem":162,
    "gn:feature_class":"P",
    "gn:feature_code":"PPLL",
    "gn:name":"Niederbonsfeld",
    "gn:population":0,
    "gn:timezone":"Europe/Berlin",
    "iso:country":"DE",
    "wof:name":"Niederbonsfeld",
    "wof:placetype":"neighbourhood"
},
  "geometry": {"coordinates":[7.13242,51.38902],"type":"Point"}
}