{
  "type": "Feature",
  "properties": {
    "gn:admin1_code":"11",
    "gn:admin2_code":"0.0",
    "gn:admin3_code":"12066.0",
    "gn:admin4_code":"12066124.0",
    "gn:asciiname":"Lipsa",
    "gn:cc2":"DE",
    "gn:country_code":"DE",
    "gn:dem":123,
    "gn:feature_class":"P",
    "gn:feature_code":"PPL",
    "gn:name":"Lipsa",
    "gn:population":0,
    "gn:timezone":"Europe/Berlin",
    "iso:country":"DE",
    "name:und_x_variant":[
        "Lindenort"
    ],
    "wof:name":"Lipsa",
    "wof:placetype":"neighbourhood"
},
  "geometry": {"coordinates":[13.90629,51.39155],"type":"Point"}
}