{
  "type": "Feature",
  "properties": {
    "gn:admin1_code":"7.0",
    "gn:admin2_code":"059",
    "gn:admin3_code":"5958.0",
    "gn:admin4_code":"5958044.0",
    "gn:asciiname":"Weninghausen",
    "gn:country_code":"DE",
    "gn:dem":326,
    "gn:feature_class":"P",
    "gn:feature_code":"PPL",
    "gn:name":"Weninghausen",
    "gn:population":0,
    "gn:timezone":"Europe/Berlin",
    "iso:country":"DE",
    "wof:name":"Weninghausen",
    "wof:placetype":"neighbourhood"
},
  "geometry": {"coordinates":[8.05699,51.31238],"type":"Point"}
}