{
  "type": "Feature",
  "properties": {
    "gn:admin1_code":"11",
    "gn:admin2_code":"0.0",
    "gn:admin3_code":"12073.0",
    "gn:admin4_code":"12073069.0",
    "gn:asciiname":"Bruesenwalde",
    "gn:country_code":"DE",
    "gn:dem":77,
    "gn:feature_class":"P",
    "gn:feature_code":"PPL",
    "gn:name":"Br\u00fcsenwalde",
    "gn:population":0,
    "gn:timezone":"Europe/Berlin",
    "iso:country":"DE",
    "wof:name":"Bruesenwalde",
    "wof:placetype":"neighbourhood"
},
  "geometry": {"coordinates":[13.47257,53.25178],"type":"Point"}
}