{
  "type": "Feature",
  "properties": {
    "gn:admin1_code":"2",
    "gn:admin2_code":"93.0",
    "gn:admin3_code":"9374.0",
    "gn:admin4_code":"9374146.0",
    "gn:asciiname":"Hochdorf",
    "gn:country_code":"DE",
    "gn:dem":447,
    "gn:feature_class":"P",
    "gn:feature_code":"PPL",
    "gn:name":"Hochdorf",
    "gn:population":0,
    "gn:timezone":"Europe/Berlin",
    "iso:country":"DE",
    "name:als_x_preferred":[
        "Hochdorf"
    ],
    "name:ceb_x_preferred":[
        "Hochdorf"
    ],
    "name:deu_x_preferred":[
        "Hochdorf"
    ],
    "name:epo_x_preferred":[
        "Hochdorf"
    ],
    "name:fra_x_preferred":[
        "Hochdorf"
    ],
    "name:hun_x_preferred":[
        "Hochdorf"
    ],
    "name:hye_x_preferred":[
        "\u0540\u0578\u056d\u0564\u0578\u0580\u0586"
    ],
    "name:ita_x_preferred":[
        "Hochdorf"
    ],
    "name:nld_x_preferred":[
        "Hochdorf"
    ],
    "name:pol_x_preferred":[
        "Hochdorf"
    ],
    "name:por_x_preferred":[
        "Hochdorf"
    ],
    "name:rus_x_preferred":[
        "\u0425\u043e\u0445\u0434\u043e\u0440\u0444"
    ],
    "name:swe_x_preferred":[
        "Hochdorf"
    ],
    "name:vol_x_preferred":[
        "Hochdorf"
    ],
    "wof:name":"Hochdorf",
    "wof:placetype":"neighbourhood"
},
  "geometry": {"coordinates":[12.18768,49.61632],"type":"Point"}
}