{
  "type": "Feature",
  "properties": {
    "gn:admin1_code":"7",
    "gn:admin2_code":"53.0",
    "gn:admin3_code":"5382.0",
    "gn:admin4_code":"5382020.0",
    "gn:asciiname":"Niederkuempel",
    "gn:country_code":"DE",
    "gn:dem":192,
    "gn:feature_class":"P",
    "gn:feature_code":"PPL",
    "gn:name":"Niederk\u00fcmpel",
    "gn:population":0,
    "gn:timezone":"Europe/Berlin",
    "iso:country":"DE",
    "wof:name":"Niederkuempel",
    "wof:placetype":"neighbourhood"
},
  "geometry": {"coordinates":[7.28333,50.75],"type":"Point"}
}