{
  "type": "Feature",
  "properties": {
    "gn:gn_country":"DE",
    "gn:gn_fcode":"PPLA4",
    "gn:gn_pop":278,
    "gn:population":278,
    "iso:country":"DE",
    "name:baq_x_preferred":[
        "Orfgen"
    ],
    "name:chi_x_preferred":[
        "\u5965\u5c14\u592b\u6839"
    ],
    "name:dut_x_preferred":[
        "Orfgen"
    ],
    "name:eng_x_preferred":[
        "Orfgen"
    ],
    "name:epo_x_preferred":[
        "Orfgen"
    ],
    "name:fre_x_preferred":[
        "Orfgen"
    ],
    "name:ger_x_preferred":[
        "Orfgen"
    ],
    "name:hun_x_preferred":[
        "Orfgen"
    ],
    "name:ita_x_preferred":[
        "Orfgen"
    ],
    "name:jpn_x_preferred":[
        "\u30aa\u30eb\u30d5\u30b2\u30f3"
    ],
    "name:may_x_preferred":[
        "Orfgen"
    ],
    "name:per_x_preferred":[
        "\u0627\u0648\u0631\u0641\u06af\u0646"
    ],
    "name:pol_x_preferred":[
        "Orfgen"
    ],
    "name:por_x_preferred":[
        "Orfgen"
    ],
    "name:rum_x_preferred":[
        "Orfgen"
    ],
    "name:rus_x_preferred":[
        "\u041e\u0440\u0444\u0433\u0435\u043d"
    ],
    "name:srp_x_preferred":[
        "\u041e\u0440\u0444\u0433\u0435\u043d"
    ],
    "name:ukr_x_preferred":[
        "\u041e\u0440\u0444\u0433\u0435\u043d"
    ],
    "name:uzb_x_preferred":[
        "Orfgen"
    ],
    "name:vie_x_preferred":[
        "Orfgen"
    ],
    "name:vol_x_preferred":[
        "Orfgen"
    ],
    "name:war_x_preferred":[
        "Orfgen"
    ],
    "qs_pg:aaroncc":"DE",
    "qs_pg:gn_country":"DE",
    "qs_pg:gn_fcode":"PPLA4",
    "qs_pg:gn_pop":278,
    "qs_pg:name":"Orfgen",
    "qs_pg:photos_9r":0,
    "qs_pg:photos_sr":0,
    "qs_pg:pop_sr":2,
    "qs_pg:qs_pg_placetype":"locality",
    "wof:name":"Orfgen",
    "wof:placetype":"locality",
    "wof:population":278
},
  "geometry": {"coordinates":[7.53333,50.66667],"type":"Point"}
}