{
  "type": "Feature",
  "properties": {
    "gn:admin1_code":"5",
    "gn:admin2_code":"65.0",
    "gn:admin3_code":"6533.0",
    "gn:admin4_code":"6533005.0",
    "gn:asciiname":"Heuchelheim",
    "gn:country_code":"DE",
    "gn:dem":187,
    "gn:feature_class":"P",
    "gn:feature_code":"PPL",
    "gn:name":"Heuchelheim",
    "gn:population":0,
    "gn:timezone":"Europe/Berlin",
    "iso:country":"DE",
    "name:ceb_x_preferred":[
        "Heuchelheim"
    ],
    "name:deu_x_preferred":[
        "Heuchelheim"
    ],
    "name:epo_x_preferred":[
        "Heuchelheim"
    ],
    "name:eus_x_preferred":[
        "Heuchelheim"
    ],
    "name:fas_x_preferred":[
        "\u0647\u0648\u06cc\u0634\u0644\u0647\u0627\u06cc\u0645"
    ],
    "name:fra_x_preferred":[
        "Heuchelheim"
    ],
    "name:hun_x_preferred":[
        "Heuchelheim"
    ],
    "name:ita_x_preferred":[
        "Heuchelheim"
    ],
    "name:jpn_x_preferred":[
        "\u30db\u30a4\u30d2\u30a7\u30eb\u30cf\u30a4\u30e0"
    ],
    "name:msa_x_preferred":[
        "Heuchelheim"
    ],
    "name:nld_x_preferred":[
        "Heuchelheim"
    ],
    "name:pol_x_preferred":[
        "Heuchelheim"
    ],
    "name:ron_x_preferred":[
        "Heuchelheim"
    ],
    "name:rus_x_preferred":[
        "\u0425\u043e\u0439\u0445\u0435\u043b\u044c\u0445\u0430\u0439\u043c"
    ],
    "name:spa_x_preferred":[
        "Heuchelheim"
    ],
    "name:srp_x_preferred":[
        "\u0425\u043e\u0458\u0445\u0435\u043b\u0445\u0430\u0458\u043c"
    ],
    "name:ukr_x_preferred":[
        "\u0413\u043e\u0439\u0445\u0435\u043b\u044c\u0433\u0430\u0439\u043c"
    ],
    "name:uzb_x_preferred":[
        "Heuchelheim"
    ],
    "name:vol_x_preferred":[
        "Heuchelheim"
    ],
    "name:war_x_preferred":[
        "Heuchelheim"
    ],
    "name:zho_x_preferred":[
        "\u970d\u4f0a\u9ed1\u5c14\u6d77\u59c6"
    ],
    "wof:name":"Heuchelheim",
    "wof:placetype":"neighbourhood"
},
  "geometry": {"coordinates":[8.05745,50.49557],"type":"Point"}
}