{
  "type": "Feature",
  "properties": {
    "iso:country":"DE",
    "name:deu_x_colloquial":[
        "Alte Muehle",
        "Alte Muhle"
    ],
    "name:deu_x_preferred":[
        "Ba\u0142am\u0105tek"
    ],
    "name:deu_x_variant":[
        "Alte M\u00fchle"
    ],
    "name:pol_x_preferred":[
        "Ba\u0142am\u0105tek"
    ],
    "qs:gn_local":0,
    "qs:local_max":122,
    "qs:local_sum":398,
    "qs:localhoods":10,
    "qs:name":"Alte M\u00fchle",
    "qs:name_adm0":"Deutschland",
    "qs:name_adm1":"Niedersachsen",
    "qs:name_adm2":"Stadtkreis Salzgitter",
    "qs:name_lau":"Stadtteil Reppner",
    "qs:name_local":"Salzgitter",
    "qs:photo_max":21,
    "qs:photo_sum":21,
    "qs:placetype":"Suburb",
    "qs:quad_count":1,
    "qs:woe_adm0":23424829,
    "qs:woe_adm1":2345486,
    "qs:woe_adm2":12596994,
    "qs:woe_lau":26823214,
    "qs:woe_local":690863,
    "qs:woe_ver":"7.10.0",
    "qs_pg:name":"Alte M\u00fchle",
    "qs_pg:name_adm0":"Deutschland",
    "qs_pg:name_adm1":"Niedersachsen",
    "qs_pg:photos":22,
    "qs_pg:photos_1k":4,
    "qs_pg:photos_9k":1,
    "qs_pg:photos_9r":1,
    "qs_pg:photos_all":22,
    "qs_pg:photos_sr":1,
    "qs_pg:pop_sr":0,
    "qs_pg:qs_pg_placetype":"neighbourhood",
    "qs_pg:qs_pg_placetype_gp":"Suburb",
    "qs_pg:woe_adm0":23424829,
    "woe:adm0_id":23424829,
    "woe:name_adm0":"Deutschland",
    "woe:name_adm1":"Niedersachsen",
    "woe:placetype":"Suburb",
    "wof:lang":[
        "ger"
    ],
    "wof:name":"Alte M\u00fchle",
    "wof:placetype":"neighbourhood"
},
  "geometry": {"coordinates":[10.313416,52.168877],"type":"Point"}
}