{
  "type": "Feature",
  "properties": {
    "gn:admin1_code":"2",
    "gn:admin2_code":"97.0",
    "gn:admin3_code":"9774.0",
    "gn:admin4_code":"9774198.0",
    "gn:asciiname":"Schonebach",
    "gn:country_code":"DE",
    "gn:dem":476,
    "gn:feature_class":"P",
    "gn:feature_code":"PPL",
    "gn:name":"Sch\u00f6nebach",
    "gn:population":0,
    "gn:timezone":"Europe/Berlin",
    "iso:country":"DE",
    "wof:name":"Schonebach",
    "wof:placetype":"neighbourhood"
},
  "geometry": {"coordinates":[10.57898,48.30786],"type":"Point"}
}