{
  "type": "Feature",
  "properties": {
    "gn:admin1_code":"7.0",
    "gn:admin2_code":"57.0",
    "gn:admin3_code":"5766.0",
    "gn:admin4_code":"5766060.0",
    "gn:asciiname":"Brakelsiek",
    "gn:country_code":"DE",
    "gn:dem":187,
    "gn:feature_class":"P",
    "gn:feature_code":"PPL",
    "gn:name":"Brakelsiek",
    "gn:population":0,
    "gn:timezone":"Europe/Berlin",
    "iso:country":"DE",
    "wof:name":"Brakelsiek",
    "wof:placetype":"neighbourhood"
},
  "geometry": {"coordinates":[9.16852,51.89133],"type":"Point"}
}