{
  "type": "Feature",
  "properties": {
    "gn:admin1_code":"7",
    "gn:admin2_code":"53.0",
    "gn:admin3_code":"5366.0",
    "gn:admin4_code":"5366004.0",
    "gn:asciiname":"Scheuerheck",
    "gn:country_code":"DE",
    "gn:dem":446,
    "gn:feature_class":"P",
    "gn:feature_code":"PPL",
    "gn:name":"Scheuerheck",
    "gn:population":0,
    "gn:timezone":"Europe/Berlin",
    "iso:country":"DE",
    "wof:name":"Scheuerheck",
    "wof:placetype":"neighbourhood"
},
  "geometry": {"coordinates":[6.85278,50.53423],"type":"Point"}
}