{
  "type": "Feature",
  "properties": {
    "gn:admin1_code":"7",
    "gn:admin2_code":"53.0",
    "gn:admin3_code":"5378.0",
    "gn:admin4_code":"5378032.0",
    "gn:asciiname":"Oberrautenbach",
    "gn:country_code":"DE",
    "gn:dem":286,
    "gn:feature_class":"P",
    "gn:feature_code":"PPL",
    "gn:name":"Oberrautenbach",
    "gn:population":0,
    "gn:timezone":"Europe/Berlin",
    "iso:country":"DE",
    "wof:name":"Oberrautenbach",
    "wof:placetype":"neighbourhood"
},
  "geometry": {"coordinates":[7.26357,51.12307],"type":"Point"}
}