{
  "type": "Feature",
  "properties": {
    "gn:admin1_code":"6.0",
    "gn:admin2_code":"00",
    "gn:admin3_code":"3257.0",
    "gn:admin4_code":"3257001.0",
    "gn:asciiname":"Widdensen",
    "gn:country_code":"DE",
    "gn:dem":104,
    "gn:feature_class":"P",
    "gn:feature_code":"PPL",
    "gn:name":"Widdensen",
    "gn:population":0,
    "gn:timezone":"Europe/Berlin",
    "iso:country":"DE",
    "wof:name":"Widdensen",
    "wof:placetype":"neighbourhood"
},
  "geometry": {"coordinates":[9.09132,52.25208],"type":"Point"}
}