{
  "type": "Feature",
  "properties": {
    "gn:admin1_code":"10",
    "gn:admin2_code":"0.0",
    "gn:admin3_code":"1057.0",
    "gn:admin4_code":"1057068.0",
    "gn:asciiname":"Hollenbek",
    "gn:country_code":"DE",
    "gn:dem":36,
    "gn:feature_class":"P",
    "gn:feature_code":"PPL",
    "gn:name":"Hollenbek",
    "gn:population":0,
    "gn:timezone":"Europe/Berlin",
    "iso:country":"DE",
    "name:ceb_x_preferred":[
        "Hollenbek"
    ],
    "name:dan_x_preferred":[
        "Hollenbek"
    ],
    "name:deu_x_preferred":[
        "Hollenbek"
    ],
    "name:epo_x_preferred":[
        "Hollenbek"
    ],
    "name:eus_x_preferred":[
        "Hollenbek"
    ],
    "name:fas_x_preferred":[
        "\u0647\u0648\u0644\u0646\u0628\u06a9"
    ],
    "name:fra_x_preferred":[
        "Hollenbek"
    ],
    "name:hun_x_preferred":[
        "Hollenbek"
    ],
    "name:ita_x_preferred":[
        "Hollenbek"
    ],
    "name:kaz_x_preferred":[
        "\u0425\u043e\u043b\u043b\u0435\u043d\u0431\u0435\u043a"
    ],
    "name:kir_x_preferred":[
        "\u0425\u043e\u043b\u043b\u0435\u043d\u0431\u0435\u043a"
    ],
    "name:mkd_x_preferred":[
        "\u0425\u043e\u043b\u0435\u043d\u0431\u0435\u043a"
    ],
    "name:msa_x_preferred":[
        "Hollenbek"
    ],
    "name:nld_x_preferred":[
        "Hollenbek"
    ],
    "name:pol_x_preferred":[
        "Hollenbek"
    ],
    "name:por_x_preferred":[
        "Hollenbek"
    ],
    "name:ron_x_preferred":[
        "Hollenbek"
    ],
    "name:rus_x_preferred":[
        "\u0425\u043e\u043b\u043b\u0435\u043d\u0431\u0435\u043a"
    ],
    "name:spa_x_preferred":[
        "Hollenbek"
    ],
    "name:srp_x_preferred":[
        "\u0425\u043e\u043b\u0435\u043d\u0431\u0435\u043a"
    ],
    "name:tur_x_preferred":[
        "Hollenbek"
    ],
    "name:ukr_x_preferred":[
        "\u0413\u043e\u043b\u043b\u0435\u043d\u0431\u0435\u043a"
    ],
    "name:uzb_x_preferred":[
        "Hollenbek"
    ],
    "name:vie_x_preferred":[
        "Hollenbek"
    ],
    "name:vol_x_preferred":[
        "Hollenbek"
    ],
    "name:war_x_preferred":[
        "Hollenbek"
    ],
    "name:zho_x_preferred":[
        "\u970d\u4f26\u8d1d\u514b"
    ],
    "wof:name":"Hollenbek",
    "wof:placetype":"neighbourhood"
},
  "geometry": {"coordinates":[10.12363,54.078],"type":"Point"}
}