{
  "type": "Feature",
  "properties": {
    "gn:admin1_code":"14",
    "gn:admin2_code":"0.0",
    "gn:admin3_code":"15084.0",
    "gn:admin4_code":"15084355.0",
    "gn:asciiname":"Schieben",
    "gn:country_code":"DE",
    "gn:dem":182,
    "gn:feature_class":"P",
    "gn:feature_code":"PPL",
    "gn:name":"Schieben",
    "gn:population":0,
    "gn:timezone":"Europe/Berlin",
    "iso:country":"DE",
    "wof:name":"Schieben",
    "wof:placetype":"neighbourhood"
},
  "geometry": {"coordinates":[11.70817,51.09067],"type":"Point"}
}