{
  "type": "Feature",
  "properties": {
    "gn:admin1_code":"2",
    "gn:admin2_code":"92.0",
    "gn:admin3_code":"9278.0",
    "gn:admin4_code":"9278197.0",
    "gn:asciiname":"Hotzelsdorf",
    "gn:country_code":"DE",
    "gn:dem":658,
    "gn:feature_class":"P",
    "gn:feature_code":"PPL",
    "gn:name":"H\u00f6tzelsdorf",
    "gn:population":0,
    "gn:timezone":"Europe/Berlin",
    "iso:country":"DE",
    "wof:name":"Hotzelsdorf",
    "wof:placetype":"neighbourhood"
},
  "geometry": {"coordinates":[12.59227,49.05431],"type":"Point"}
}