{
  "type": "Feature",
  "properties": {
    "gn:admin1_code":"2",
    "gn:admin2_code":"92.0",
    "gn:admin3_code":"9275.0",
    "gn:admin4_code":"9275137.0",
    "gn:asciiname":"Haar",
    "gn:country_code":"DE",
    "gn:dem":531,
    "gn:feature_class":"P",
    "gn:feature_code":"PPL",
    "gn:name":"Haar",
    "gn:population":0,
    "gn:timezone":"Europe/Berlin",
    "iso:country":"DE",
    "name:ceb_x_preferred":[
        "Haar"
    ],
    "name:deu_x_preferred":[
        "Haar"
    ],
    "name:est_x_preferred":[
        "Haar"
    ],
    "name:fas_x_preferred":[
        "\u0647\u0627\u0631"
    ],
    "name:fra_x_preferred":[
        "Haar"
    ],
    "name:nld_x_preferred":[
        "Haar"
    ],
    "name:pol_x_preferred":[
        "Haar"
    ],
    "name:swe_x_preferred":[
        "Haar"
    ],
    "wof:name":"Haar",
    "wof:placetype":"neighbourhood"
},
  "geometry": {"coordinates":[13.59996,48.57473],"type":"Point"}
}