{
  "type": "Feature",
  "properties": {
    "gn:admin1_code":"7",
    "gn:admin2_code":"59.0",
    "gn:admin3_code":"5958.0",
    "gn:admin4_code":"5958012.0",
    "gn:asciiname":"Plattenberg",
    "gn:country_code":"DE",
    "gn:dem":492,
    "gn:feature_class":"P",
    "gn:feature_code":"PPL",
    "gn:name":"Plattenberg",
    "gn:population":0,
    "gn:timezone":"Europe/Berlin",
    "iso:country":"DE",
    "name:ceb_x_preferred":[
        "Plattenberg"
    ],
    "name:ita_x_preferred":[
        "Plattenberg"
    ],
    "name:nno_x_preferred":[
        "Plattenberg"
    ],
    "name:pol_x_preferred":[
        "Plattenberg"
    ],
    "wof:name":"Plattenberg",
    "wof:placetype":"neighbourhood"
},
  "geometry": {"coordinates":[8.64733,51.39001],"type":"Point"}
}