{
  "type": "Feature",
  "properties": {
    "gn:admin1_code":"2",
    "gn:admin2_code":"93.0",
    "gn:admin3_code":"9374.0",
    "gn:admin4_code":"9374118.0",
    "gn:asciiname":"Tillyschanz",
    "gn:country_code":"DE",
    "gn:dem":523,
    "gn:feature_class":"P",
    "gn:feature_code":"PPL",
    "gn:name":"Tillyschanz",
    "gn:population":0,
    "gn:timezone":"Europe/Berlin",
    "iso:country":"DE",
    "wof:name":"Tillyschanz",
    "wof:placetype":"neighbourhood"
},
  "geometry": {"coordinates":[12.57523,49.58429],"type":"Point"}
}