{
  "type": "Feature",
  "properties": {
    "gn:admin1_code":"8",
    "gn:admin2_code":"0.0",
    "gn:admin3_code":"7331.0",
    "gn:admin4_code":"7331023.0",
    "gn:asciiname":"Nieder-Floersheim",
    "gn:country_code":"DE",
    "gn:dem":158,
    "gn:feature_class":"P",
    "gn:feature_code":"PPL",
    "gn:name":"Nieder-Fl\u00f6rsheim",
    "gn:population":0,
    "gn:timezone":"Europe/Berlin",
    "iso:country":"DE",
    "wof:name":"Nieder-Floersheim",
    "wof:placetype":"neighbourhood"
},
  "geometry": {"coordinates":[8.21068,49.65241],"type":"Point"}
}