{
  "type": "Feature",
  "properties": {
    "gn:admin1_code":"2.0",
    "gn:admin2_code":"91.0",
    "gn:admin3_code":"9184.0",
    "gn:admin4_code":"9184137.0",
    "gn:asciiname":"Blindham",
    "gn:country_code":"DE",
    "gn:dem":653,
    "gn:feature_class":"P",
    "gn:feature_code":"PPL",
    "gn:name":"Blindham",
    "gn:population":0,
    "gn:timezone":"Europe/Berlin",
    "iso:country":"DE",
    "wof:name":"Blindham",
    "wof:placetype":"neighbourhood"
},
  "geometry": {"coordinates":[11.81361,47.9302],"type":"Point"}
}