{
  "type": "Feature",
  "properties": {
    "gn:admin1_code":"13",
    "gn:admin2_code":"0.0",
    "gn:admin3_code":"14627.0",
    "gn:admin4_code":"14627340.0",
    "gn:asciiname":"Streumen",
    "gn:country_code":"DE",
    "gn:dem":97,
    "gn:feature_class":"P",
    "gn:feature_code":"PPL",
    "gn:name":"Streumen",
    "gn:population":0,
    "gn:timezone":"Europe/Berlin",
    "iso:country":"DE",
    "wof:name":"Streumen",
    "wof:placetype":"neighbourhood"
},
  "geometry": {"coordinates":[13.40351,51.35669],"type":"Point"}
}