{
  "type": "Feature",
  "properties": {
    "gn:admin1_code":"1",
    "gn:admin2_code":"83.0",
    "gn:admin3_code":"8317.0",
    "gn:admin4_code":"8317093.0",
    "gn:asciiname":"Unterwasser",
    "gn:country_code":"DE",
    "gn:dem":427,
    "gn:feature_class":"P",
    "gn:feature_code":"PPLL",
    "gn:name":"Unterwasser",
    "gn:population":0,
    "gn:timezone":"Europe/Berlin",
    "iso:country":"DE",
    "name:ceb_x_preferred":[
        "Unterwasser"
    ],
    "name:deu_x_preferred":[
        "Unterwasser"
    ],
    "name:fra_x_preferred":[
        "Unterwasser"
    ],
    "name:swe_x_preferred":[
        "Unterwasser"
    ],
    "wof:name":"Unterwasser",
    "wof:placetype":"neighbourhood"
},
  "geometry": {"coordinates":[8.23333,48.35],"type":"Point"}
}