{
  "type": "Feature",
  "properties": {
    "gn:admin1_code":"2",
    "gn:admin2_code":"93.0",
    "gn:admin3_code":"9375.0",
    "gn:admin4_code":"9375119.0",
    "gn:asciiname":"Kurn",
    "gn:country_code":"DE",
    "gn:dem":520,
    "gn:feature_class":"P",
    "gn:feature_code":"PPL",
    "gn:name":"K\u00fcrn",
    "gn:population":0,
    "gn:timezone":"Europe/Berlin",
    "iso:country":"DE",
    "wof:name":"Kurn",
    "wof:placetype":"neighbourhood"
},
  "geometry": {"coordinates":[12.21545,49.11761],"type":"Point"}
}