{
  "type": "Feature",
  "properties": {
    "gn:admin1_code":"2",
    "gn:admin2_code":"94.0",
    "gn:admin3_code":"9477.0",
    "gn:admin4_code":"9477148.0",
    "gn:asciiname":"Elbersreuth",
    "gn:country_code":"DE",
    "gn:dem":596,
    "gn:feature_class":"P",
    "gn:feature_code":"PPL",
    "gn:name":"Elbersreuth",
    "gn:population":0,
    "gn:timezone":"Europe/Berlin",
    "iso:country":"DE",
    "wof:name":"Elbersreuth",
    "wof:placetype":"neighbourhood"
},
  "geometry": {"coordinates":[11.56108,50.24823],"type":"Point"}
}