{
  "type": "Feature",
  "properties": {
    "iso:country":"DE",
    "name:baq_x_preferred":[
        "Kirchsahr"
    ],
    "name:chi_x_preferred":[
        "\u57fa\u5c14\u5e0c\u8428\u5c14"
    ],
    "name:dut_x_preferred":[
        "Kirchsahr"
    ],
    "name:eng_x_preferred":[
        "Kirchsahr"
    ],
    "name:epo_x_preferred":[
        "Kirchsahr"
    ],
    "name:fre_x_preferred":[
        "Kirchsahr"
    ],
    "name:ger_x_preferred":[
        "Kirchsahr"
    ],
    "name:hun_x_preferred":[
        "Kirchsahr"
    ],
    "name:ita_x_preferred":[
        "Kirchsahr"
    ],
    "name:jpn_x_preferred":[
        "\u30ad\u30eb\u30d2\u30b7\u30e3\u30fc\u30eb"
    ],
    "name:kaz_x_preferred":[
        "\u041a\u0438\u0440\u043a\u0441\u0430\u0440"
    ],
    "name:kir_x_preferred":[
        "\u041a\u0438\u0440\u043a\u0441\u0430\u0440"
    ],
    "name:may_x_preferred":[
        "Kirchsahr"
    ],
    "name:per_x_preferred":[
        "\u06a9\u06cc\u0631\u0634\u0632\u0627\u0647\u0631"
    ],
    "name:pol_x_preferred":[
        "Kirchsahr"
    ],
    "name:por_x_preferred":[
        "Kirchsahr"
    ],
    "name:rum_x_preferred":[
        "Kirchsahr"
    ],
    "name:rus_x_preferred":[
        "\u041a\u0438\u0440\u043a\u0441\u0430\u0440"
    ],
    "name:srp_x_preferred":[
        "\u041a\u0438\u0440\u0445\u0441\u0430\u0440"
    ],
    "name:ukr_x_preferred":[
        "\u041a\u0456\u0440\u0445\u0437\u0430\u0440"
    ],
    "name:uzb_x_preferred":[
        "Kirchsahr"
    ],
    "name:vie_x_preferred":[
        "Kirchsahr"
    ],
    "name:vol_x_preferred":[
        "Kirchsahr"
    ],
    "name:war_x_preferred":[
        "Kirchsahr"
    ],
    "qs_pg:aaroncc":"DE",
    "qs_pg:name":"Kirchsahr",
    "qs_pg:name_adm0":"Deutschland",
    "qs_pg:name_adm1":"Rheinland-Pfalz",
    "qs_pg:photos":167,
    "qs_pg:photos_1k":34,
    "qs_pg:photos_9k":1,
    "qs_pg:photos_9r":4,
    "qs_pg:photos_all":167,
    "qs_pg:photos_sr":4,
    "qs_pg:pop_sr":0,
    "qs_pg:qs_pg_placetype":"locality",
    "qs_pg:qs_pg_placetype_gp":"Town",
    "qs_pg:woe_adm0":23424829,
    "woe:adm0_id":23424829,
    "woe:name_adm0":"Deutschland",
    "woe:name_adm1":"Rheinland-Pfalz",
    "woe:placetype":"Town",
    "wof:name":"Kirchsahr",
    "wof:placetype":"locality"
},
  "geometry": {"coordinates":[6.882591,50.525316],"type":"Point"}
}