{
  "type": "Feature",
  "properties": {
    "gn:admin1_code":"1",
    "gn:admin2_code":"81.0",
    "gn:admin3_code":"8125.0",
    "gn:admin4_code":"8125098.0",
    "gn:asciiname":"Unterheinriet",
    "gn:country_code":"DE",
    "gn:dem":249,
    "gn:feature_class":"P",
    "gn:feature_code":"PPL",
    "gn:name":"Unterheinriet",
    "gn:population":0,
    "gn:timezone":"Europe/Berlin",
    "iso:country":"DE",
    "wof:name":"Unterheinriet",
    "wof:placetype":"neighbourhood"
},
  "geometry": {"coordinates":[9.32161,49.08577],"type":"Point"}
}