{
  "type": "Feature",
  "properties": {
    "gn:admin1_code":"1",
    "gn:admin2_code":"81.0",
    "gn:admin3_code":"8136.0",
    "gn:admin4_code":"8136088.0",
    "gn:asciiname":"Fachsenfeld",
    "gn:country_code":"DE",
    "gn:dem":473,
    "gn:feature_class":"P",
    "gn:feature_code":"PPL",
    "gn:name":"Fachsenfeld",
    "gn:population":0,
    "gn:timezone":"Europe/Berlin",
    "iso:country":"DE",
    "name:ceb_x_preferred":[
        "Fachsenfeld"
    ],
    "name:deu_x_preferred":[
        "Fachsenfeld"
    ],
    "name:eus_x_preferred":[
        "Fachsenfeld"
    ],
    "name:fas_x_preferred":[
        "\u0641\u0627\u062e\u0632\u0646\u0641\u0644\u062f"
    ],
    "name:urd_x_preferred":[
        "\u0641\u0627\u0686\u0633\u06cc\u0646\u0641\u06cc\u0644\u0688"
    ],
    "wof:name":"Fachsenfeld",
    "wof:placetype":"neighbourhood"
},
  "geometry": {"coordinates":[10.04738,48.88492],"type":"Point"}
}