{
  "type": "Feature",
  "properties": {
    "gn:admin1_code":"14.0",
    "gn:admin2_code":"0.0",
    "gn:admin3_code":"15084.0",
    "gn:admin4_code":"15084341.0",
    "gn:asciiname":"Aue",
    "gn:country_code":"DE",
    "gn:dem":269,
    "gn:feature_class":"P",
    "gn:feature_code":"PPL",
    "gn:name":"Aue",
    "gn:population":0,
    "gn:timezone":"Europe/Berlin",
    "iso:country":"DE",
    "name:azb_x_preferred":[
        "\u0622\u0626\u0648"
    ],
    "name:bak_x_preferred":[
        "\u0410\u0443\u044d"
    ],
    "name:cat_x_preferred":[
        "Aue"
    ],
    "name:ceb_x_preferred":[
        "Aue"
    ],
    "name:ces_x_preferred":[
        "Aue"
    ],
    "name:dan_x_preferred":[
        "Aue"
    ],
    "name:deu_x_preferred":[
        "Aue"
    ],
    "name:epo_x_preferred":[
        "Aue"
    ],
    "name:est_x_preferred":[
        "Aue"
    ],
    "name:fas_x_preferred":[
        "\u0622\u0626\u0648"
    ],
    "name:fin_x_preferred":[
        "Aue"
    ],
    "name:fra_x_preferred":[
        "Aue"
    ],
    "name:hsb_x_preferred":[
        "Aue"
    ],
    "name:hun_x_preferred":[
        "Aue"
    ],
    "name:ile_x_preferred":[
        "Aue"
    ],
    "name:ita_x_preferred":[
        "Aue"
    ],
    "name:jpn_x_preferred":[
        "\u30a2\u30a6\u30a8"
    ],
    "name:kaz_x_preferred":[
        "\u0410\u0443\u044d"
    ],
    "name:kir_x_preferred":[
        "\u0410\u0443\u044d"
    ],
    "name:kor_x_preferred":[
        "\uc544\uc6b0\uc5d0"
    ],
    "name:lav_x_preferred":[
        "Aue"
    ],
    "name:lit_x_preferred":[
        "Auj\u0117"
    ],
    "name:mkd_x_preferred":[
        "\u0410\u0443\u0435"
    ],
    "name:msa_x_preferred":[
        "Aue"
    ],
    "name:nld_x_preferred":[
        "Aue"
    ],
    "name:nor_x_preferred":[
        "Aue"
    ],
    "name:pol_x_preferred":[
        "Aue"
    ],
    "name:por_x_preferred":[
        "Aue"
    ],
    "name:ron_x_preferred":[
        "Aue"
    ],
    "name:rus_x_preferred":[
        "\u0410\u0443\u044d"
    ],
    "name:sco_x_preferred":[
        "Aue"
    ],
    "name:spa_x_preferred":[
        "Aue"
    ],
    "name:srp_x_preferred":[
        "\u0410\u0443\u0435"
    ],
    "name:swe_x_preferred":[
        "Aue"
    ],
    "name:tur_x_preferred":[
        "Aue"
    ],
    "name:ukr_x_preferred":[
        "\u0410\u0443\u0435"
    ],
    "name:uzb_x_preferred":[
        "Aue"
    ],
    "name:vol_x_preferred":[
        "Aue"
    ],
    "name:war_x_preferred":[
        "Aue"
    ],
    "wof:name":"Aue",
    "wof:placetype":"neighbourhood"
},
  "geometry": {"coordinates":[11.80012,51.0596],"type":"Point"}
}