{
  "type": "Feature",
  "properties": {
    "gn:admin1_code":"14.0",
    "gn:admin2_code":"0.0",
    "gn:admin3_code":"15084.0",
    "gn:admin4_code":"15084341.0",
    "gn:asciiname":"Aue",
    "gn:country_code":"DE",
    "gn:dem":269,
    "gn:feature_class":"P",
    "gn:feature_code":"PPL",
    "gn:name":"Aue",
    "gn:population":0,
    "gn:timezone":"Europe/Berlin",
    "iso:country":"DE",
    "wof:name":"Aue",
    "wof:placetype":"neighbourhood"
},
  "geometry": {"coordinates":[11.80012,51.0596],"type":"Point"}
}