{
  "type": "Feature",
  "properties": {
    "gn:admin1_code":"1.0",
    "gn:admin2_code":"84.0",
    "gn:admin3_code":"8436.0",
    "gn:admin4_code":"8436010.0",
    "gn:asciiname":"Bauhofen",
    "gn:country_code":"DE",
    "gn:dem":652,
    "gn:feature_class":"P",
    "gn:feature_code":"PPL",
    "gn:name":"Bauhofen",
    "gn:population":0,
    "gn:timezone":"Europe/Berlin",
    "iso:country":"DE",
    "wof:name":"Bauhofen",
    "wof:placetype":"neighbourhood"
},
  "geometry": {"coordinates":[9.9333,47.86692],"type":"Point"}
}