{
  "type": "Feature",
  "properties": {
    "gn:admin1_code":"2",
    "gn:admin2_code":"95.0",
    "gn:admin3_code":"9575.0",
    "gn:admin4_code":"9575121.0",
    "gn:asciiname":"Rennhofen",
    "gn:country_code":"DE",
    "gn:dem":380,
    "gn:feature_class":"P",
    "gn:feature_code":"PPL",
    "gn:name":"Rennhofen",
    "gn:population":0,
    "gn:timezone":"Europe/Berlin",
    "iso:country":"DE",
    "wof:name":"Rennhofen",
    "wof:placetype":"neighbourhood"
},
  "geometry": {"coordinates":[10.66269,49.55029],"type":"Point"}
}