{
  "type": "Feature",
  "properties": {
    "gn:admin1_code":"10.0",
    "gn:admin2_code":"0.0",
    "gn:admin3_code":"1059.0",
    "gn:admin4_code":"1059145.0",
    "gn:asciiname":"Bockholmwik",
    "gn:country_code":"DE",
    "gn:dem":9,
    "gn:feature_class":"P",
    "gn:feature_code":"PPL",
    "gn:name":"Bockholmwik",
    "gn:population":0,
    "gn:timezone":"Europe/Berlin",
    "iso:country":"DE",
    "name:und_x_variant":[
        "Bockholmwick",
        "Bockholmwik"
    ],
    "wof:name":"Bockholmwik",
    "wof:placetype":"neighbourhood"
},
  "geometry": {"coordinates":[9.60785,54.82896],"type":"Point"}
}