{
  "type": "Feature",
  "properties": {
    "gn:admin1_code":"5",
    "gn:admin2_code":"66.0",
    "gn:admin3_code":"6632.0",
    "gn:admin4_code":"6632012.0",
    "gn:asciiname":"Hainrode",
    "gn:country_code":"DE",
    "gn:dem":413,
    "gn:feature_class":"P",
    "gn:feature_code":"PPL",
    "gn:name":"Hainrode",
    "gn:population":0,
    "gn:timezone":"Europe/Berlin",
    "iso:country":"DE",
    "name:bak_x_preferred":[
        "\u0425\u0430\u0439\u043d\u0440\u043e\u0434\u0435"
    ],
    "name:ceb_x_preferred":[
        "Hainrode"
    ],
    "name:deu_x_preferred":[
        "Hainrode"
    ],
    "name:epo_x_preferred":[
        "Hainrode"
    ],
    "name:fas_x_preferred":[
        "\u0647\u0627\u06cc\u0646\u0631\u0648\u062f"
    ],
    "name:ita_x_preferred":[
        "Hainrode"
    ],
    "name:kaz_x_preferred":[
        "\u0425\u0430\u0439\u043d\u0440\u043e\u0434\u0435"
    ],
    "name:mkd_x_preferred":[
        "\u0425\u0430\u0458\u043d\u0440\u043e\u0434\u0435"
    ],
    "name:nld_x_preferred":[
        "Hainrode"
    ],
    "name:ron_x_preferred":[
        "Hainrode"
    ],
    "name:rus_x_preferred":[
        "\u0425\u0430\u0439\u043d\u0440\u043e\u0434\u0435"
    ],
    "name:uzb_x_preferred":[
        "Hainrode"
    ],
    "name:vie_x_preferred":[
        "Hainrode"
    ],
    "name:vol_x_preferred":[
        "Hainrode"
    ],
    "wof:name":"Hainrode",
    "wof:placetype":"neighbourhood"
},
  "geometry": {"coordinates":[9.5766,50.96579000000001],"type":"Point"}
}