{
  "type": "Feature",
  "properties": {
    "gn:admin1_code":"14",
    "gn:admin2_code":"0.0",
    "gn:admin3_code":"15081.0",
    "gn:admin4_code":"15081030.0",
    "gn:asciiname":"Schernikau",
    "gn:country_code":"DE",
    "gn:dem":34,
    "gn:feature_class":"P",
    "gn:feature_code":"PPL",
    "gn:name":"Schernikau",
    "gn:population":0,
    "gn:timezone":"Europe/Berlin",
    "iso:country":"DE",
    "name:bak_x_preferred":[
        "\u0428\u0435\u0440\u043d\u0438\u043a\u0430\u0443"
    ],
    "name:ceb_x_preferred":[
        "Schernikau"
    ],
    "name:deu_x_preferred":[
        "Schernikau"
    ],
    "name:epo_x_preferred":[
        "Schernikau"
    ],
    "name:fas_x_preferred":[
        "\u0634\u0631\u0646\u06cc\u06a9\u0627\u0648"
    ],
    "name:ita_x_preferred":[
        "Schernikau"
    ],
    "name:kaz_x_preferred":[
        "\u0428\u0435\u0440\u043d\u0438\u043a\u0430\u0443"
    ],
    "name:kir_x_preferred":[
        "\u0428\u0435\u0440\u043d\u0438\u043a\u0430\u0443"
    ],
    "name:mkd_x_preferred":[
        "\u0428\u0435\u0440\u043d\u0438\u043a\u0430\u0443"
    ],
    "name:nld_x_preferred":[
        "Schernikau"
    ],
    "name:ron_x_preferred":[
        "Schernikau"
    ],
    "name:rus_x_preferred":[
        "\u0428\u0435\u0440\u043d\u0438\u043a\u0430\u0443"
    ],
    "name:uzb_x_preferred":[
        "Schernikau"
    ],
    "name:vie_x_preferred":[
        "Schernikau"
    ],
    "name:vol_x_preferred":[
        "Schernikau"
    ],
    "wof:name":"Schernikau",
    "wof:placetype":"neighbourhood"
},
  "geometry": {"coordinates":[11.39305,52.82943],"type":"Point"}
}