{
  "type": "Feature",
  "properties": {
    "gn:admin1_code":"15",
    "gn:admin2_code":"0.0",
    "gn:admin3_code":"16074.0",
    "gn:admin4_code":"16074018.0",
    "gn:asciiname":"Saasa",
    "gn:country_code":"DE",
    "gn:dem":296,
    "gn:feature_class":"P",
    "gn:feature_code":"PPL",
    "gn:name":"Saasa",
    "gn:population":0,
    "gn:timezone":"Europe/Berlin",
    "iso:country":"DE",
    "name:jpn_x_preferred":[
        "\u3055\u3041\u3055"
    ],
    "wof:name":"Saasa",
    "wof:placetype":"neighbourhood"
},
  "geometry": {"coordinates":[11.87776,50.97022],"type":"Point"}
}