{
  "type": "Feature",
  "properties": {
    "iso:country":"DE",
    "name:deu_x_preferred":[
        "S\u00fcdgiesing"
    ],
    "wof:name":"Suedgiesing",
    "wof:placetype":"neighbourhood"
},
  "geometry": {"coordinates":[11.59827127165514,48.09320765451695],"type":"Point"}
}