{
  "type": "Feature",
  "properties": {
    "gn:admin1_code":"11.0",
    "gn:admin2_code":"00",
    "gn:admin3_code":"12073.0",
    "gn:admin4_code":"12073429.0",
    "gn:asciiname":"Wittstock",
    "gn:country_code":"DE",
    "gn:dem":75,
    "gn:feature_class":"P",
    "gn:feature_code":"PPL",
    "gn:name":"Wittstock",
    "gn:population":0,
    "gn:timezone":"Europe/Berlin",
    "iso:country":"DE",
    "name:ara_x_preferred":[
        "\u0641\u064a\u062a\u0634\u062a\u0648\u0643"
    ],
    "name:ceb_x_preferred":[
        "Wittstock"
    ],
    "name:dan_x_preferred":[
        "Wittstock"
    ],
    "name:deu_x_preferred":[
        "Wittstock/Dosse"
    ],
    "name:epo_x_preferred":[
        "Wittstock"
    ],
    "name:fas_x_preferred":[
        "\u0648\u06cc\u062a\u200c\u0627\u0634\u062a\u0648\u06a9"
    ],
    "name:fra_x_preferred":[
        "Wittstock/Dosse"
    ],
    "name:hun_x_preferred":[
        "Wittstock/Dosse"
    ],
    "name:hye_x_preferred":[
        "\u054e\u056b\u057f\u0577\u057f\u0578\u056f"
    ],
    "name:ita_x_preferred":[
        "Wittstock/Dosse"
    ],
    "name:kaz_x_preferred":[
        "\u0412\u0438\u0442\u0448\u0442\u043e\u043a"
    ],
    "name:kir_x_preferred":[
        "\u0412\u0438\u0442\u0448\u0442\u043e\u043a"
    ],
    "name:lat_x_preferred":[
        "Witstochium"
    ],
    "name:lav_x_preferred":[
        "Vit\u0161toka/Dose"
    ],
    "name:mkd_x_preferred":[
        "\u0412\u0438\u0442\u0448\u0442\u043e\u043a"
    ],
    "name:msa_x_preferred":[
        "Wittstock"
    ],
    "name:nld_x_preferred":[
        "Wittstock/Dosse"
    ],
    "name:pol_x_preferred":[
        "Wittstock/Dosse"
    ],
    "name:ron_x_preferred":[
        "Wittstock/Dosse"
    ],
    "name:rus_x_preferred":[
        "\u0412\u0438\u0442\u0448\u0442\u043e\u043a"
    ],
    "name:spa_x_preferred":[
        "Wittstock"
    ],
    "name:srp_x_preferred":[
        "\u0412\u0438\u0442\u0448\u0442\u043e\u043a"
    ],
    "name:swe_x_preferred":[
        "Wittstock"
    ],
    "name:tur_x_preferred":[
        "Wittstock/Dosse"
    ],
    "name:ukr_x_preferred":[
        "\u0412\u0456\u0442\u0442\u0448\u0442\u043e\u043a"
    ],
    "name:uzb_x_preferred":[
        "Wittstock/Dosse"
    ],
    "name:vie_x_preferred":[
        "Wittstock"
    ],
    "name:vol_x_preferred":[
        "Wittstock/Dosse"
    ],
    "name:war_x_preferred":[
        "Wittstock"
    ],
    "name:zho_x_preferred":[
        "\u7ef4\u8328\u6258\u514b"
    ],
    "wof:name":"Wittstock",
    "wof:placetype":"neighbourhood"
},
  "geometry": {"coordinates":[13.69402,53.37426],"type":"Point"}
}