{
  "type": "Feature",
  "properties": {
    "gn:admin1_code":"11.0",
    "gn:admin2_code":"00",
    "gn:admin3_code":"12073.0",
    "gn:admin4_code":"12073429.0",
    "gn:asciiname":"Wittstock",
    "gn:country_code":"DE",
    "gn:dem":75,
    "gn:feature_class":"P",
    "gn:feature_code":"PPL",
    "gn:name":"Wittstock",
    "gn:population":0,
    "gn:timezone":"Europe/Berlin",
    "iso:country":"DE",
    "wof:name":"Wittstock",
    "wof:placetype":"neighbourhood"
},
  "geometry": {"coordinates":[13.69402,53.37426],"type":"Point"}
}