{
  "type": "Feature",
  "properties": {
    "gn:admin1_code":"2",
    "gn:admin2_code":"95.0",
    "gn:admin3_code":"9575.0",
    "gn:admin4_code":"9575161.0",
    "gn:asciiname":"Schnodsenbach",
    "gn:country_code":"DE",
    "gn:dem":315,
    "gn:feature_class":"P",
    "gn:feature_code":"PPL",
    "gn:name":"Schnodsenbach",
    "gn:population":0,
    "gn:timezone":"Europe/Berlin",
    "iso:country":"DE",
    "wof:name":"Schnodsenbach",
    "wof:placetype":"neighbourhood"
},
  "geometry": {"coordinates":[10.44545,49.68247],"type":"Point"}
}