{
  "type": "Feature",
  "properties": {
    "gn:admin1_code":"13",
    "gn:admin2_code":"0.0",
    "gn:admin3_code":"14625.0",
    "gn:admin4_code":"14625460.0",
    "gn:asciiname":"Neujessnitz",
    "gn:country_code":"DE",
    "gn:dem":192,
    "gn:feature_class":"P",
    "gn:feature_code":"PPL",
    "gn:name":"Neuje\u00dfnitz",
    "gn:population":0,
    "gn:timezone":"Europe/Berlin",
    "iso:country":"DE",
    "name:hsb_x_preferred":[
        "Nowa Jase\u0144ca"
    ],
    "name:und_x_variant":[
        "Neuje\u00dfnitz"
    ],
    "wof:name":"Neujessnitz",
    "wof:placetype":"neighbourhood"
},
  "geometry": {"coordinates":[14.28318,51.24077],"type":"Point"}
}