{
  "type": "Feature",
  "properties": {
    "gn:admin1_code":"15",
    "gn:admin2_code":"0.0",
    "gn:admin3_code":"16062.0",
    "gn:admin4_code":"16062041.0",
    "gn:asciiname":"Salza",
    "gn:country_code":"DE",
    "gn:dem":193,
    "gn:feature_class":"P",
    "gn:feature_code":"PPL",
    "gn:name":"Salza",
    "gn:population":0,
    "gn:timezone":"Europe/Berlin",
    "iso:country":"DE",
    "wof:name":"Salza",
    "wof:placetype":"neighbourhood"
},
  "geometry": {"coordinates":[10.77239,51.51459000000001],"type":"Point"}
}