{
  "type": "Feature",
  "properties": {
    "gn:admin1_code":"15",
    "gn:admin2_code":"0.0",
    "gn:admin3_code":"16062.0",
    "gn:admin4_code":"16062041.0",
    "gn:asciiname":"Salza",
    "gn:country_code":"DE",
    "gn:dem":193,
    "gn:feature_class":"P",
    "gn:feature_code":"PPL",
    "gn:name":"Salza",
    "gn:population":0,
    "gn:timezone":"Europe/Berlin",
    "iso:country":"DE",
    "name:cat_x_preferred":[
        "Salzan"
    ],
    "name:ceb_x_preferred":[
        "Salza"
    ],
    "name:deu_x_preferred":[
        "Salza"
    ],
    "name:eus_x_preferred":[
        "Salza"
    ],
    "name:fra_x_preferred":[
        "Salza"
    ],
    "name:hun_x_preferred":[
        "Salza"
    ],
    "name:hye_x_preferred":[
        "\u054d\u0561\u056c\u0566\u0561"
    ],
    "name:ita_x_preferred":[
        "Salza"
    ],
    "name:kaz_x_preferred":[
        "\u0421\u0430\u043b\u044c\u0437\u0430"
    ],
    "name:lat_x_preferred":[
        "Salza"
    ],
    "name:mlg_x_preferred":[
        "Salza"
    ],
    "name:msa_x_preferred":[
        "Salza"
    ],
    "name:nld_x_preferred":[
        "Salza"
    ],
    "name:oci_x_preferred":[
        "Salzan"
    ],
    "name:pol_x_preferred":[
        "Salza"
    ],
    "name:por_x_preferred":[
        "Salza"
    ],
    "name:ron_x_preferred":[
        "Salza"
    ],
    "name:rus_x_preferred":[
        "\u0421\u0430\u043b\u044c\u0437\u0430"
    ],
    "name:slk_x_preferred":[
        "Salza"
    ],
    "name:spa_x_preferred":[
        "Salza"
    ],
    "name:swe_x_preferred":[
        "Salza"
    ],
    "name:ukr_x_preferred":[
        "\u0421\u0430\u043b\u044c\u0437\u0430"
    ],
    "name:vie_x_preferred":[
        "Salza"
    ],
    "name:vol_x_preferred":[
        "Salza"
    ],
    "name:war_x_preferred":[
        "Salza"
    ],
    "name:zho_x_preferred":[
        "\u8428\u5c14\u624e"
    ],
    "wof:name":"Salza",
    "wof:placetype":"neighbourhood"
},
  "geometry": {"coordinates":[10.77239,51.51459000000001],"type":"Point"}
}