{
  "type": "Feature",
  "properties": {
    "gn:admin1_code":"1",
    "gn:admin2_code":"81.0",
    "gn:admin3_code":"8118.0",
    "gn:admin4_code":"8118076.0",
    "gn:asciiname":"Hohenhaslach",
    "gn:country_code":"DE",
    "gn:dem":244,
    "gn:feature_class":"P",
    "gn:feature_code":"PPL",
    "gn:name":"Hohenhaslach",
    "gn:population":0,
    "gn:timezone":"Europe/Berlin",
    "iso:country":"DE",
    "wof:name":"Hohenhaslach",
    "wof:placetype":"neighbourhood"
},
  "geometry": {"coordinates":[9.01997,49.00109000000001],"type":"Point"}
}