{
  "type": "Feature",
  "properties": {
    "gn:admin1_code":"2",
    "gn:admin2_code":"91.0",
    "gn:admin3_code":"9174.0",
    "gn:admin4_code":"9174151.0",
    "gn:asciiname":"Erlbach",
    "gn:country_code":"DE",
    "gn:dem":469,
    "gn:feature_class":"P",
    "gn:feature_code":"PPL",
    "gn:name":"Erlbach",
    "gn:population":0,
    "gn:timezone":"Europe/Berlin",
    "iso:country":"DE",
    "name:ceb_x_preferred":[
        "Erlbach"
    ],
    "name:deu_x_preferred":[
        "Erlbach"
    ],
    "name:epo_x_preferred":[
        "Erlbach"
    ],
    "name:eus_x_preferred":[
        "Erlbach"
    ],
    "name:fra_x_preferred":[
        "Erlbach"
    ],
    "name:ita_x_preferred":[
        "Erlbach"
    ],
    "name:nld_x_preferred":[
        "Erlbach"
    ],
    "name:pol_x_preferred":[
        "Erlbach"
    ],
    "name:rus_x_preferred":[
        "\u042d\u0440\u043b\u044c\u0431\u0430\u0445"
    ],
    "name:swe_x_preferred":[
        "Erlbach"
    ],
    "name:vol_x_preferred":[
        "Erlbach"
    ],
    "wof:name":"Erlbach",
    "wof:placetype":"neighbourhood"
},
  "geometry": {"coordinates":[11.40217,48.37991],"type":"Point"}
}