{
  "type": "Feature",
  "properties": {
    "gn:admin1_code":"5",
    "gn:admin2_code":"64.0",
    "gn:admin3_code":"6434.0",
    "gn:admin4_code":"6434004.0",
    "gn:asciiname":"Naunstadt",
    "gn:country_code":"DE",
    "gn:dem":299,
    "gn:feature_class":"P",
    "gn:feature_code":"PPL",
    "gn:name":"Naunstadt",
    "gn:population":0,
    "gn:timezone":"Europe/Berlin",
    "iso:country":"DE",
    "wof:name":"Naunstadt",
    "wof:placetype":"neighbourhood"
},
  "geometry": {"coordinates":[8.45034,50.37481],"type":"Point"}
}