{
  "type": "Feature",
  "properties": {
    "gn:admin1_code":"2",
    "gn:admin2_code":"97.0",
    "gn:admin3_code":"9777.0",
    "gn:admin4_code":"9777168.0",
    "gn:asciiname":"Guggemoosen",
    "gn:country_code":"DE",
    "gn:dem":858,
    "gn:feature_class":"P",
    "gn:feature_code":"PPL",
    "gn:name":"Guggemoosen",
    "gn:population":0,
    "gn:timezone":"Europe/Berlin",
    "iso:country":"DE",
    "name:und_x_variant":[
        "Guggenmosen",
        "Guggemoosen"
    ],
    "wof:name":"Guggemoosen",
    "wof:placetype":"neighbourhood"
},
  "geometry": {"coordinates":[10.56226,47.6509],"type":"Point"}
}