{
  "type": "Feature",
  "properties": {
    "gn:admin1_code":"10.0",
    "gn:admin2_code":"0.0",
    "gn:admin3_code":"1054.0",
    "gn:admin4_code":"1054075.0",
    "gn:asciiname":"Ostlangenhorn",
    "gn:country_code":"DE",
    "gn:dem":2,
    "gn:feature_class":"P",
    "gn:feature_code":"PPL",
    "gn:name":"Ostlangenhorn",
    "gn:population":0,
    "gn:timezone":"Europe/Berlin",
    "iso:country":"DE",
    "wof:name":"Ostlangenhorn",
    "wof:placetype":"neighbourhood"
},
  "geometry": {"coordinates":[8.92094,54.67753],"type":"Point"}
}