{
  "type": "Feature",
  "properties": {
    "gn:admin1_code":"5",
    "gn:admin2_code":"66.0",
    "gn:admin3_code":"6631.0",
    "gn:admin4_code":"6631002.0",
    "gn:asciiname":"Schlotzau",
    "gn:country_code":"DE",
    "gn:dem":309,
    "gn:feature_class":"P",
    "gn:feature_code":"PPL",
    "gn:name":"Schlotzau",
    "gn:population":0,
    "gn:timezone":"Europe/Berlin",
    "iso:country":"DE",
    "wof:name":"Schlotzau",
    "wof:placetype":"neighbourhood"
},
  "geometry": {"coordinates":[9.64447,50.68899],"type":"Point"}
}