{
  "type": "Feature",
  "properties": {
    "gn:admin1_code":"2.0",
    "gn:admin2_code":"92.0",
    "gn:admin3_code":"9274.0",
    "gn:admin4_code":"9274183.0",
    "gn:asciiname":"Atzmannsdorf",
    "gn:country_code":"DE",
    "gn:dem":464,
    "gn:feature_class":"P",
    "gn:feature_code":"PPL",
    "gn:name":"Atzmannsdorf",
    "gn:population":0,
    "gn:timezone":"Europe/Berlin",
    "iso:country":"DE",
    "wof:name":"Atzmannsdorf",
    "wof:placetype":"neighbourhood"
},
  "geometry": {"coordinates":[12.2471,48.37693],"type":"Point"}
}