{
  "type": "Feature",
  "properties": {
    "gn:admin1_code":"1.0",
    "gn:admin2_code":"83.0",
    "gn:admin3_code":"8325.0",
    "gn:admin4_code":"8325045.0",
    "gn:asciiname":"Boll",
    "gn:country_code":"DE",
    "gn:dem":613,
    "gn:feature_class":"P",
    "gn:feature_code":"PPL",
    "gn:name":"Boll",
    "gn:population":0,
    "gn:timezone":"Europe/Berlin",
    "iso:country":"DE",
    "name:ceb_x_preferred":[
        "Boll"
    ],
    "name:ces_x_preferred":[
        "Boll"
    ],
    "name:deu_x_preferred":[
        "Boll"
    ],
    "name:epo_x_preferred":[
        "Boll"
    ],
    "name:fra_x_preferred":[
        "Boll"
    ],
    "name:ita_x_preferred":[
        "Boll"
    ],
    "name:nld_x_preferred":[
        "Boll"
    ],
    "name:pol_x_preferred":[
        "Boll"
    ],
    "name:rus_x_preferred":[
        "\u0411\u043e\u043b\u043b\u044c"
    ],
    "wof:name":"Boll",
    "wof:placetype":"neighbourhood"
},
  "geometry": {"coordinates":[8.5974,48.30024],"type":"Point"}
}