{
  "type": "Feature",
  "properties": {
    "gn:admin1_code":"2.0",
    "gn:admin2_code":"091",
    "gn:admin3_code":"9171.0",
    "gn:admin4_code":"9171134.0",
    "gn:asciiname":"Zaiselham",
    "gn:country_code":"DE",
    "gn:dem":508,
    "gn:feature_class":"P",
    "gn:feature_code":"PPL",
    "gn:name":"Zaiselham",
    "gn:population":0,
    "gn:timezone":"Europe/Berlin",
    "iso:country":"DE",
    "wof:name":"Zaiselham",
    "wof:placetype":"neighbourhood"
},
  "geometry": {"coordinates":[12.69008,48.06555],"type":"Point"}
}