{
  "type": "Feature",
  "properties": {
    "gn:admin1_code":"1",
    "gn:admin2_code":"83.0",
    "gn:admin3_code":"8316.0",
    "gn:admin4_code":"8316042.0",
    "gn:asciiname":"Hinterhaslach",
    "gn:country_code":"DE",
    "gn:dem":523,
    "gn:feature_class":"P",
    "gn:feature_code":"PPL",
    "gn:name":"Hinterhaslach",
    "gn:population":0,
    "gn:timezone":"Europe/Berlin",
    "iso:country":"DE",
    "wof:name":"Hinterhaslach",
    "wof:placetype":"neighbourhood"
},
  "geometry": {"coordinates":[8.07995,48.1146],"type":"Point"}
}