{
  "type": "Feature",
  "properties": {
    "gn:admin1_code":"12",
    "gn:admin2_code":"0.0",
    "gn:admin3_code":"13072.0",
    "gn:admin4_code":"13072068.0",
    "gn:asciiname":"Gottesgabe",
    "gn:country_code":"DE",
    "gn:dem":18,
    "gn:feature_class":"P",
    "gn:feature_code":"PPL",
    "gn:name":"Gottesgabe",
    "gn:population":0,
    "gn:timezone":"Europe/Berlin",
    "iso:country":"DE",
    "wof:name":"Gottesgabe",
    "wof:placetype":"neighbourhood"
},
  "geometry": {"coordinates":[12.61823,53.97191],"type":"Point"}
}