{
  "type": "Feature",
  "properties": {
    "gn:admin1_code":"12",
    "gn:admin2_code":"0.0",
    "gn:admin3_code":"13072.0",
    "gn:admin4_code":"13072068.0",
    "gn:asciiname":"Gottesgabe",
    "gn:country_code":"DE",
    "gn:dem":18,
    "gn:feature_class":"P",
    "gn:feature_code":"PPL",
    "gn:name":"Gottesgabe",
    "gn:population":0,
    "gn:timezone":"Europe/Berlin",
    "iso:country":"DE",
    "name:ceb_x_preferred":[
        "Gottesgabe"
    ],
    "name:deu_x_preferred":[
        "Gottesgabe"
    ],
    "name:epo_x_preferred":[
        "Gottesgabe"
    ],
    "name:fas_x_preferred":[
        "\u06af\u0648\u062a\u0633\u06af\u0627\u0628\u0647"
    ],
    "name:hun_x_preferred":[
        "Gottesgabe"
    ],
    "name:ita_x_preferred":[
        "Gottesgabe"
    ],
    "name:kaz_x_preferred":[
        "\u0413\u043e\u0442\u0442\u0435\u0441\u0433\u0430\u0431\u0435"
    ],
    "name:kir_x_preferred":[
        "\u0413\u043e\u0442\u0442\u0435\u0441\u0433\u0430\u0431\u0435"
    ],
    "name:mkd_x_preferred":[
        "\u0413\u043e\u0442\u0435\u0441\u0433\u0430\u0431\u0435"
    ],
    "name:msa_x_preferred":[
        "Gottesgabe"
    ],
    "name:nld_x_preferred":[
        "Gottesgabe"
    ],
    "name:pol_x_preferred":[
        "Gottesgabe"
    ],
    "name:por_x_preferred":[
        "Gottesgabe"
    ],
    "name:ron_x_preferred":[
        "Gottesgabe"
    ],
    "name:rus_x_preferred":[
        "\u0413\u043e\u0442\u0442\u0435\u0441\u0433\u0430\u0431\u0435"
    ],
    "name:spa_x_preferred":[
        "Gottesgabe"
    ],
    "name:srp_x_preferred":[
        "\u0413\u043e\u0442\u0435\u0441\u0433\u0430\u0431\u0435"
    ],
    "name:ukr_x_preferred":[
        "\u0413\u043e\u0442\u0442\u0435\u0441\u0433\u0430\u0431\u0435"
    ],
    "name:uzb_x_preferred":[
        "Gottesgabe"
    ],
    "name:vie_x_preferred":[
        "Gottesgabe"
    ],
    "name:vol_x_preferred":[
        "Gottesgabe"
    ],
    "name:war_x_preferred":[
        "Gottesgabe"
    ],
    "name:zho_x_preferred":[
        "\u6208\u7279\u65af\u52a0\u4f2f"
    ],
    "wof:name":"Gottesgabe",
    "wof:placetype":"neighbourhood"
},
  "geometry": {"coordinates":[12.61823,53.97191],"type":"Point"}
}