{
  "type": "Feature",
  "properties": {
    "gn:admin1_code":"11",
    "gn:admin2_code":"0.0",
    "gn:admin3_code":"12070.0",
    "gn:admin4_code":"12070236.0",
    "gn:asciiname":"Luetkenwisch",
    "gn:country_code":"DE",
    "gn:dem":21,
    "gn:feature_class":"P",
    "gn:feature_code":"PPL",
    "gn:name":"L\u00fctkenwisch",
    "gn:population":0,
    "gn:timezone":"Europe/Berlin",
    "iso:country":"DE",
    "wof:name":"Luetkenwisch",
    "wof:placetype":"neighbourhood"
},
  "geometry": {"coordinates":[11.5868,53.03853],"type":"Point"}
}