{
  "type": "Feature",
  "properties": {
    "gn:admin1_code":"8",
    "gn:admin2_code":"0.0",
    "gn:admin3_code":"7138.0",
    "gn:admin4_code":"7138057.0",
    "gn:asciiname":"Niederdreis",
    "gn:country_code":"DE",
    "gn:dem":227,
    "gn:feature_class":"P",
    "gn:feature_code":"PPL",
    "gn:name":"Niederdreis",
    "gn:population":0,
    "gn:timezone":"Europe/Berlin",
    "iso:country":"DE",
    "wof:name":"Niederdreis",
    "wof:placetype":"neighbourhood"
},
  "geometry": {"coordinates":[7.6286,50.59511],"type":"Point"}
}