{
  "type": "Feature",
  "properties": {
    "gn:admin1_code":"5",
    "gn:admin2_code":"65.0",
    "gn:admin3_code":"6532.0",
    "gn:admin4_code":"6532013.0",
    "gn:asciiname":"Hohensolms",
    "gn:country_code":"DE",
    "gn:dem":413,
    "gn:feature_class":"P",
    "gn:feature_code":"PPL",
    "gn:name":"Hohensolms",
    "gn:population":0,
    "gn:timezone":"Europe/Berlin",
    "iso:country":"DE",
    "wof:name":"Hohensolms",
    "wof:placetype":"neighbourhood"
},
  "geometry": {"coordinates":[8.51783,50.65167],"type":"Point"}
}