{
  "type": "Feature",
  "properties": {
    "gn:admin1_code":"12",
    "gn:admin2_code":"0.0",
    "gn:admin3_code":"13076.0",
    "gn:admin4_code":"13076069.0",
    "gn:asciiname":"Neu Karstaedt",
    "gn:country_code":"DE",
    "gn:dem":26,
    "gn:feature_class":"P",
    "gn:feature_code":"PPL",
    "gn:name":"Neu Karst\u00e4dt",
    "gn:population":0,
    "gn:timezone":"Europe/Berlin",
    "iso:country":"DE",
    "wof:name":"Neu Karstaedt",
    "wof:placetype":"neighbourhood"
},
  "geometry": {"coordinates":[11.49028,53.28009],"type":"Point"}
}