{
  "type": "Feature",
  "properties": {
    "gn:admin1_code":"1.0",
    "gn:admin2_code":"081",
    "gn:admin3_code":"8127.0",
    "gn:admin4_code":"8127075.0",
    "gn:asciiname":"Wittmersklingen",
    "gn:country_code":"DE",
    "gn:dem":459,
    "gn:feature_class":"P",
    "gn:feature_code":"PPL",
    "gn:name":"Wittmersklingen",
    "gn:population":0,
    "gn:timezone":"Europe/Berlin",
    "iso:country":"DE",
    "wof:name":"Wittmersklingen",
    "wof:placetype":"neighbourhood"
},
  "geometry": {"coordinates":[9.87295,49.34087],"type":"Point"}
}