{
  "type": "Feature",
  "properties": {
    "gn:admin1_code":"2",
    "gn:admin2_code":"92.0",
    "gn:admin3_code":"9276.0",
    "gn:admin4_code":"9276129.0",
    "gn:asciiname":"Nebelberg",
    "gn:country_code":"DE",
    "gn:dem":579,
    "gn:feature_class":"P",
    "gn:feature_code":"PPL",
    "gn:name":"Nebelberg",
    "gn:population":0,
    "gn:timezone":"Europe/Berlin",
    "iso:country":"DE",
    "name:ceb_x_preferred":[
        "Nebelberg"
    ],
    "name:deu_x_preferred":[
        "Nebelberg"
    ],
    "name:fas_x_preferred":[
        "\u0646\u0628\u0644\u0628\u0631\u06af"
    ],
    "name:fra_x_preferred":[
        "Nebelberg"
    ],
    "name:hun_x_preferred":[
        "Nebelberg"
    ],
    "name:ita_x_preferred":[
        "Nebelberg"
    ],
    "name:kaz_x_preferred":[
        "\u041d\u0435\u0431\u0435\u043b\u044c\u0431\u0435\u0440\u0433"
    ],
    "name:nld_x_preferred":[
        "Nebelberg"
    ],
    "name:pol_x_preferred":[
        "Nebelberg"
    ],
    "name:por_x_preferred":[
        "Nebelberg"
    ],
    "name:rus_x_preferred":[
        "\u041d\u0435\u0431\u0435\u043b\u044c\u0431\u0435\u0440\u0433"
    ],
    "name:slk_x_preferred":[
        "Nebelberg"
    ],
    "name:spa_x_preferred":[
        "Nebelberg"
    ],
    "name:swe_x_preferred":[
        "Nebelberg"
    ],
    "name:uzb_x_preferred":[
        "Nebelberg"
    ],
    "name:vol_x_preferred":[
        "Nebelberg"
    ],
    "name:war_x_preferred":[
        "Nebelberg"
    ],
    "name:zho_x_preferred":[
        "\u5185\u4f2f\u5c14\u8d1d\u683c"
    ],
    "wof:name":"Nebelberg",
    "wof:placetype":"neighbourhood"
},
  "geometry": {"coordinates":[13.16044,49.02125],"type":"Point"}
}