{
  "type": "Feature",
  "properties": {
    "gn:admin1_code":"1",
    "gn:admin2_code":"81.0",
    "gn:admin3_code":"8136.0",
    "gn:admin4_code":"8136060.0",
    "gn:asciiname":"Hohenberg",
    "gn:country_code":"DE",
    "gn:dem":516,
    "gn:feature_class":"P",
    "gn:feature_code":"PPL",
    "gn:name":"Hohenberg",
    "gn:population":0,
    "gn:timezone":"Europe/Berlin",
    "iso:country":"DE",
    "name:ceb_x_preferred":[
        "Hohenberg"
    ],
    "name:deu_x_preferred":[
        "Hohenberg"
    ],
    "name:fra_x_preferred":[
        "Hohenberg"
    ],
    "name:ita_x_preferred":[
        "Hohenberg"
    ],
    "name:jpn_x_preferred":[
        "\u30db\u30fc\u30a8\u30f3\u30d9\u30eb\u30af"
    ],
    "name:lav_x_preferred":[
        "Hohenberg"
    ],
    "name:nld_x_preferred":[
        "Hohenberg"
    ],
    "name:pol_x_preferred":[
        "Hohenberg"
    ],
    "name:rus_x_preferred":[
        "\u0413\u043e\u0433\u0435\u043d\u0431\u0435\u0440\u0433"
    ],
    "name:swe_x_preferred":[
        "Hohenberg"
    ],
    "wof:name":"Hohenberg",
    "wof:placetype":"neighbourhood"
},
  "geometry": {"coordinates":[10.04661,49.00142],"type":"Point"}
}