{
  "type": "Feature",
  "properties": {
    "gn:admin1_code":"14",
    "gn:admin2_code":"0.0",
    "gn:admin3_code":"15090.0",
    "gn:admin4_code":"15090225.0",
    "gn:asciiname":"Dahlen",
    "gn:country_code":"DE",
    "gn:dem":30,
    "gn:feature_class":"P",
    "gn:feature_code":"PPL",
    "gn:name":"Dahlen",
    "gn:population":0,
    "gn:timezone":"Europe/Berlin",
    "iso:country":"DE",
    "name:ceb_x_preferred":[
        "Dahlen"
    ],
    "name:deu_x_preferred":[
        "Dahlen"
    ],
    "name:epo_x_preferred":[
        "Dahlen"
    ],
    "name:est_x_preferred":[
        "Dahlen"
    ],
    "name:fra_x_preferred":[
        "Dahlen"
    ],
    "name:ita_x_preferred":[
        "Dahlen"
    ],
    "name:kaz_x_preferred":[
        "\u0414\u0430\u043b\u0435\u043d"
    ],
    "name:kir_x_preferred":[
        "\u0414\u0430\u043b\u0435\u043d"
    ],
    "name:lav_x_preferred":[
        "Dahlen"
    ],
    "name:nds_x_preferred":[
        "Dahlen"
    ],
    "name:nld_x_preferred":[
        "Dahlen"
    ],
    "name:pol_x_preferred":[
        "Dahlen"
    ],
    "name:rus_x_preferred":[
        "\u0414\u0430\u043b\u0435\u043d"
    ],
    "name:vol_x_preferred":[
        "Dahlen"
    ],
    "wof:name":"Dahlen",
    "wof:placetype":"neighbourhood"
},
  "geometry": {"coordinates":[12.05108,52.86008],"type":"Point"}
}