{
  "type": "Feature",
  "properties": {
    "gn:admin1_code":"12",
    "gn:admin2_code":"0.0",
    "gn:admin3_code":"13073.0",
    "gn:admin4_code":"13073089.0",
    "gn:asciiname":"Grischow",
    "gn:country_code":"DE",
    "gn:dem":22,
    "gn:feature_class":"P",
    "gn:feature_code":"PPL",
    "gn:name":"Grischow",
    "gn:population":0,
    "gn:timezone":"Europe/Berlin",
    "iso:country":"DE",
    "name:ceb_x_preferred":[
        "Grischow"
    ],
    "name:deu_x_preferred":[
        "Grischow"
    ],
    "name:epo_x_preferred":[
        "Grischow"
    ],
    "name:fas_x_preferred":[
        "\u06af\u0631\u06cc\u0634\u0648\u0648"
    ],
    "name:fra_x_preferred":[
        "Grischow"
    ],
    "name:hun_x_preferred":[
        "Grischow"
    ],
    "name:ita_x_preferred":[
        "Grischow"
    ],
    "name:kaz_x_preferred":[
        "\u0413\u0440\u0438\u0448\u043e\u0432"
    ],
    "name:kir_x_preferred":[
        "\u0413\u0440\u0438\u0448\u043e\u0432"
    ],
    "name:mkd_x_preferred":[
        "\u0413\u0440\u0438\u0448\u043e\u0432"
    ],
    "name:msa_x_preferred":[
        "Grischow"
    ],
    "name:nld_x_preferred":[
        "Grischow"
    ],
    "name:pol_x_preferred":[
        "Grischow"
    ],
    "name:ron_x_preferred":[
        "Grischow"
    ],
    "name:rus_x_preferred":[
        "\u0413\u0440\u0438\u0448\u043e\u0432"
    ],
    "name:spa_x_preferred":[
        "Grischow"
    ],
    "name:srp_x_preferred":[
        "\u0413\u0440\u0438\u0448\u043e\u0432"
    ],
    "name:ukr_x_preferred":[
        "\u0413\u0440\u0456\u0448\u043e\u0432"
    ],
    "name:uzb_x_preferred":[
        "Grischow"
    ],
    "name:vie_x_preferred":[
        "Grischow"
    ],
    "name:vol_x_preferred":[
        "Grischow"
    ],
    "name:war_x_preferred":[
        "Grischow"
    ],
    "name:zho_x_preferred":[
        "\u683c\u91cc\u7ecd"
    ],
    "wof:name":"Grischow",
    "wof:placetype":"neighbourhood"
},
  "geometry": {"coordinates":[13.06523,54.05566],"type":"Point"}
}