{
  "type": "Feature",
  "properties": {
    "gn:admin1_code":"11",
    "gn:admin2_code":"0.0",
    "gn:admin3_code":"12065.0",
    "gn:admin4_code":"12065084.0",
    "gn:asciiname":"Neuthymen",
    "gn:country_code":"DE",
    "gn:dem":66,
    "gn:feature_class":"P",
    "gn:feature_code":"PPL",
    "gn:name":"Neuthymen",
    "gn:population":0,
    "gn:timezone":"Europe/Berlin",
    "iso:country":"DE",
    "wof:name":"Neuthymen",
    "wof:placetype":"neighbourhood"
},
  "geometry": {"coordinates":[13.19627,53.21664000000001],"type":"Point"}
}