{
  "type": "Feature",
  "properties": {
    "gn:admin1_code":"11.0",
    "gn:admin2_code":"0.0",
    "gn:admin3_code":"12065.0",
    "gn:admin4_code":"12065100.0",
    "gn:asciiname":"Altluedersdorf",
    "gn:cc2":"DE",
    "gn:country_code":"DE",
    "gn:dem":55,
    "gn:feature_class":"P",
    "gn:feature_code":"PPL",
    "gn:name":"Altl\u00fcdersdorf",
    "gn:population":0,
    "gn:timezone":"Europe/Berlin",
    "iso:country":"DE",
    "name:und_x_variant":[
        "Altlandersdorf"
    ],
    "wof:name":"Altluedersdorf",
    "wof:placetype":"neighbourhood"
},
  "geometry": {"coordinates":[13.19235,53.03755],"type":"Point"}
}