{
  "type": "Feature",
  "properties": {
    "gn:admin1_code":"10",
    "gn:admin2_code":"0.0",
    "gn:admin3_code":"1059.0",
    "gn:admin4_code":"1059116.0",
    "gn:asciiname":"Kollerup",
    "gn:country_code":"DE",
    "gn:dem":39,
    "gn:feature_class":"P",
    "gn:feature_code":"PPL",
    "gn:name":"Kollerup",
    "gn:population":0,
    "gn:timezone":"Europe/Berlin",
    "iso:country":"DE",
    "wof:name":"Kollerup",
    "wof:placetype":"neighbourhood"
},
  "geometry": {"coordinates":[9.55797,54.71100000000001],"type":"Point"}
}