{
  "type": "Feature",
  "properties": {
    "gn:admin1_code":"11",
    "gn:admin2_code":"0.0",
    "gn:admin3_code":"12064.0",
    "gn:admin4_code":"12064472.0",
    "gn:asciiname":"Neue Muehle",
    "gn:country_code":"DE",
    "gn:dem":61,
    "gn:feature_class":"P",
    "gn:feature_code":"PPL",
    "gn:name":"Neue M\u00fchle",
    "gn:population":0,
    "gn:timezone":"Europe/Berlin",
    "iso:country":"DE",
    "wof:name":"Neue Muehle",
    "wof:placetype":"neighbourhood"
},
  "geometry": {"coordinates":[13.83333,52.53333000000001],"type":"Point"}
}