{
  "type": "Feature",
  "properties": {
    "iso:country":"DE",
    "wof:name":"Barbaraviertel",
    "wof:placetype":"neighbourhood"
},
  "geometry": {"coordinates":[6.69241052488926,51.21807435851644],"type":"Point"}
}