{
  "type": "Feature",
  "properties": {
    "gn:admin1_code":"1",
    "gn:admin2_code":"81.0",
    "gn:admin3_code":"8117.0",
    "gn:admin4_code":"8117018.0",
    "gn:asciiname":"Weiler ob der Fils",
    "gn:country_code":"DE",
    "gn:dem":333,
    "gn:feature_class":"P",
    "gn:feature_code":"PPL",
    "gn:name":"Weiler ob der Fils",
    "gn:population":0,
    "gn:timezone":"Europe/Berlin",
    "iso:country":"DE",
    "wof:name":"Weiler ob der Fils",
    "wof:placetype":"neighbourhood"
},
  "geometry": {"coordinates":[9.50678,48.70543],"type":"Point"}
}