{
  "type": "Feature",
  "properties": {
    "gn:admin1_code":"7.0",
    "gn:admin2_code":"51.0",
    "gn:admin3_code":"5162.0",
    "gn:admin4_code":"5162028.0",
    "gn:asciiname":"Butzheim",
    "gn:country_code":"DE",
    "gn:dem":69,
    "gn:feature_class":"P",
    "gn:feature_code":"PPL",
    "gn:name":"Butzheim",
    "gn:population":0,
    "gn:timezone":"Europe/Berlin",
    "iso:country":"DE",
    "wof:name":"Butzheim",
    "wof:placetype":"neighbourhood"
},
  "geometry": {"coordinates":[6.71076,51.04722],"type":"Point"}
}