{
  "type": "Feature",
  "properties": {
    "gn:admin1_code":"6",
    "gn:asciiname":"Silberhutte",
    "gn:cc2":"DE",
    "gn:country_code":"DE",
    "gn:dem":494,
    "gn:feature_class":"P",
    "gn:feature_code":"PPL",
    "gn:name":"Silberh\u00fctte",
    "gn:population":0,
    "gn:timezone":"Europe/Berlin",
    "iso:country":"DE",
    "name:und_x_variant":[
        "Altenauer Silberh\u00fctten",
        "Silberh\u00fctte"
    ],
    "wof:name":"Silberhutte",
    "wof:placetype":"locality"
},
  "geometry": {"coordinates":[10.45,51.81667],"type":"Point"}
}