{
  "type": "Feature",
  "properties": {
    "gn:admin1_code":"11",
    "gn:admin2_code":"0.0",
    "gn:admin3_code":"12073.0",
    "gn:admin4_code":"12073429.0",
    "gn:asciiname":"Charlottenhoehe",
    "gn:country_code":"DE",
    "gn:dem":76,
    "gn:feature_class":"P",
    "gn:feature_code":"PPL",
    "gn:name":"Charlottenh\u00f6he",
    "gn:population":0,
    "gn:timezone":"Europe/Berlin",
    "iso:country":"DE",
    "name:und_x_variant":[
        "Charlottenh\u00f6h",
        "Charlottenh\u00f6he"
    ],
    "wof:name":"Charlottenhoehe",
    "wof:placetype":"neighbourhood"
},
  "geometry": {"coordinates":[13.79644,53.26358000000001],"type":"Point"}
}