{
  "type": "Feature",
  "properties": {
    "gn:admin1_code":"8",
    "gn:admin2_code":"0.0",
    "gn:admin3_code":"7336.0",
    "gn:admin4_code":"7336064.0",
    "gn:asciiname":"Nanzweiler",
    "gn:country_code":"DE",
    "gn:dem":235,
    "gn:feature_class":"P",
    "gn:feature_code":"PPL",
    "gn:name":"Nanzweiler",
    "gn:population":0,
    "gn:timezone":"Europe/Berlin",
    "iso:country":"DE",
    "wof:name":"Nanzweiler",
    "wof:placetype":"neighbourhood"
},
  "geometry": {"coordinates":[7.43548,49.44513],"type":"Point"}
}