{
  "type": "Feature",
  "properties": {
    "gn:admin1_code":"7",
    "gn:admin2_code":"53.0",
    "gn:admin3_code":"5362.0",
    "gn:admin4_code":"5362036.0",
    "gn:asciiname":"Ingendorf",
    "gn:country_code":"DE",
    "gn:dem":76,
    "gn:feature_class":"P",
    "gn:feature_code":"PPL",
    "gn:name":"Ingendorf",
    "gn:population":0,
    "gn:timezone":"Europe/Berlin",
    "iso:country":"DE",
    "name:ceb_x_preferred":[
        "Ingendorf"
    ],
    "name:deu_x_preferred":[
        "Ingendorf"
    ],
    "name:epo_x_preferred":[
        "Ingendorf"
    ],
    "name:eus_x_preferred":[
        "Ingendorf"
    ],
    "name:fas_x_preferred":[
        "\u0627\u06cc\u0646\u06af\u0646\u062f\u0648\u0631\u0641"
    ],
    "name:fra_x_preferred":[
        "Ingendorf"
    ],
    "name:hun_x_preferred":[
        "Ingendorf"
    ],
    "name:ita_x_preferred":[
        "Ingendorf"
    ],
    "name:kaz_x_preferred":[
        "\u0418\u043d\u0433\u0435\u043d\u0434\u043e\u0440\u0444"
    ],
    "name:kir_x_preferred":[
        "\u0418\u043d\u0433\u0435\u043d\u0434\u043e\u0440\u0444"
    ],
    "name:msa_x_preferred":[
        "Ingendorf"
    ],
    "name:nld_x_preferred":[
        "Ingendorf"
    ],
    "name:pol_x_preferred":[
        "Ingendorf"
    ],
    "name:por_x_preferred":[
        "Ingendorf"
    ],
    "name:ron_x_preferred":[
        "Ingendorf"
    ],
    "name:rus_x_preferred":[
        "\u0418\u043d\u0433\u0435\u043d\u0434\u043e\u0440\u0444"
    ],
    "name:spa_x_preferred":[
        "Ingendorf"
    ],
    "name:srp_x_preferred":[
        "\u0418\u043d\u0433\u0435\u043d\u0434\u043e\u0440\u0444"
    ],
    "name:ukr_x_preferred":[
        "\u0406\u043d\u0433\u0435\u043d\u0434\u043e\u0440\u0444"
    ],
    "name:uzb_x_preferred":[
        "Ingendorf"
    ],
    "name:vie_x_preferred":[
        "Ingendorf"
    ],
    "name:vol_x_preferred":[
        "Ingendorf"
    ],
    "name:war_x_preferred":[
        "Ingendorf"
    ],
    "name:zho_x_preferred":[
        "\u82f1\u6839\u591a\u592b"
    ],
    "wof:name":"Ingendorf",
    "wof:placetype":"neighbourhood"
},
  "geometry": {"coordinates":[6.73101,51.00987],"type":"Point"}
}