{
  "type": "Feature",
  "properties": {
    "gn:admin1_code":"14.0",
    "gn:admin2_code":"0.0",
    "gn:admin3_code":"15090.0",
    "gn:admin4_code":"15090415.0",
    "gn:asciiname":"Berken",
    "gn:country_code":"DE",
    "gn:dem":21,
    "gn:feature_class":"P",
    "gn:feature_code":"PPL",
    "gn:name":"Berken",
    "gn:population":0,
    "gn:timezone":"Europe/Berlin",
    "iso:country":"DE",
    "name:als_x_preferred":[
        "Berken"
    ],
    "name:ceb_x_preferred":[
        "Berken"
    ],
    "name:deu_x_preferred":[
        "Berken"
    ],
    "name:epo_x_preferred":[
        "Berken"
    ],
    "name:eus_x_preferred":[
        "Berken"
    ],
    "name:fra_x_preferred":[
        "Berken"
    ],
    "name:ita_x_preferred":[
        "Berken"
    ],
    "name:kaz_x_preferred":[
        "\u0411\u0435\u0440\u043a\u0435\u043d"
    ],
    "name:lmo_x_preferred":[
        "Berken"
    ],
    "name:msa_x_preferred":[
        "Berken"
    ],
    "name:nld_x_preferred":[
        "Berken"
    ],
    "name:nno_x_preferred":[
        "Berken"
    ],
    "name:rus_x_preferred":[
        "\u0411\u0435\u0440\u043a\u0435\u043d"
    ],
    "name:spa_x_preferred":[
        "Berken"
    ],
    "name:sqi_x_preferred":[
        "Berken"
    ],
    "name:swe_x_preferred":[
        "Berken"
    ],
    "name:vie_x_preferred":[
        "Berken"
    ],
    "name:vol_x_preferred":[
        "Berken"
    ],
    "name:war_x_preferred":[
        "Berken"
    ],
    "wof:name":"Berken",
    "wof:placetype":"neighbourhood"
},
  "geometry": {"coordinates":[11.79851,52.81952],"type":"Point"}
}