{
  "type": "Feature",
  "properties": {
    "gn:admin1_code":"1",
    "gn:admin2_code":"82.0",
    "gn:admin3_code":"8237.0",
    "gn:admin4_code":"8237045.0",
    "gn:asciiname":"Schomberg",
    "gn:country_code":"DE",
    "gn:dem":743,
    "gn:feature_class":"P",
    "gn:feature_code":"PPL",
    "gn:name":"Sch\u00f6mberg",
    "gn:population":0,
    "gn:timezone":"Europe/Berlin",
    "iso:country":"DE",
    "name:ceb_x_preferred":[
        "Schomberg"
    ],
    "name:deu_x_preferred":[
        "Schomberg"
    ],
    "name:fra_x_preferred":[
        "Schomberg"
    ],
    "name:ita_x_preferred":[
        "Schomberg"
    ],
    "name:rus_x_preferred":[
        "\u0428\u043e\u043c\u0431\u0435\u0440\u0433"
    ],
    "name:swe_x_preferred":[
        "Schomberg"
    ],
    "name:ukr_x_preferred":[
        "\u0428\u043e\u043c\u0431\u0435\u0440\u0433"
    ],
    "wof:name":"Schomberg",
    "wof:placetype":"neighbourhood"
},
  "geometry": {"coordinates":[8.40717,48.39559000000001],"type":"Point"}
}