{
  "type": "Feature",
  "properties": {
    "gn:admin1_code":"1",
    "gn:admin2_code":"82.0",
    "gn:admin3_code":"8235.0",
    "gn:admin4_code":"8235066.0",
    "gn:asciiname":"Funfbronn",
    "gn:country_code":"DE",
    "gn:dem":742,
    "gn:feature_class":"P",
    "gn:feature_code":"PPL",
    "gn:name":"F\u00fcnfbronn",
    "gn:population":0,
    "gn:timezone":"Europe/Berlin",
    "iso:country":"DE",
    "wof:name":"Funfbronn",
    "wof:placetype":"neighbourhood"
},
  "geometry": {"coordinates":[8.49578,48.61147],"type":"Point"}
}