{
  "type": "Feature",
  "properties": {
    "iso:country":"DE",
    "name:deu_x_preferred":[
        "Ehrenfeld"
    ],
    "name:pol_x_preferred":[
        "Ehrenfeld"
    ],
    "wof:name":"Ehrenfeld",
    "wof:placetype":"neighbourhood"
},
  "geometry": {"coordinates":[7.21431995894867,51.47231754283443],"type":"Point"}
}