{
  "type": "Feature",
  "properties": {
    "gn:admin1_code":"1",
    "gn:admin2_code":"84.0",
    "gn:admin3_code":"8426.0",
    "gn:admin4_code":"8426031.0",
    "gn:asciiname":"Kleinkellmunz",
    "gn:cc2":"DE",
    "gn:country_code":"DE",
    "gn:dem":537,
    "gn:feature_class":"P",
    "gn:feature_code":"PPL",
    "gn:name":"Kleinkellm\u00fcnz",
    "gn:population":0,
    "gn:timezone":"Europe/Berlin",
    "iso:country":"DE",
    "name:und_x_variant":[
        "Kellm\u00fcnz",
        "Kleinkellm\u00fcnz"
    ],
    "wof:name":"Kleinkellmunz",
    "wof:placetype":"neighbourhood"
},
  "geometry": {"coordinates":[10.11991,48.11981],"type":"Point"}
}