{
  "type": "Feature",
  "properties": {
    "gn:admin1_code":"2",
    "gn:admin2_code":"97.0",
    "gn:admin3_code":"9778.0",
    "gn:admin4_code":"9778168.0",
    "gn:asciiname":"Frechenrieden",
    "gn:country_code":"DE",
    "gn:dem":642,
    "gn:feature_class":"P",
    "gn:feature_code":"PPL",
    "gn:name":"Frechenrieden",
    "gn:population":0,
    "gn:timezone":"Europe/Berlin",
    "iso:country":"DE",
    "wof:name":"Frechenrieden",
    "wof:placetype":"neighbourhood"
},
  "geometry": {"coordinates":[10.36181,47.97565],"type":"Point"}
}