{
  "type": "Feature",
  "properties": {
    "gn:admin1_code":"2",
    "gn:admin2_code":"92.0",
    "gn:admin3_code":"9276.0",
    "gn:admin4_code":"9276138.0",
    "gn:asciiname":"Metten",
    "gn:country_code":"DE",
    "gn:dem":550,
    "gn:feature_class":"P",
    "gn:feature_code":"PPL",
    "gn:name":"Metten",
    "gn:population":0,
    "gn:timezone":"Europe/Berlin",
    "iso:country":"DE",
    "name:ara_x_preferred":[
        "\u0645\u064a\u062a\u0646"
    ],
    "name:bar_x_preferred":[
        "Metten"
    ],
    "name:ceb_x_preferred":[
        "Metten"
    ],
    "name:dan_x_preferred":[
        "Metten"
    ],
    "name:deu_x_preferred":[
        "Metten"
    ],
    "name:epo_x_preferred":[
        "Metten"
    ],
    "name:eus_x_preferred":[
        "Metten"
    ],
    "name:fas_x_preferred":[
        "\u0645\u062a\u0646"
    ],
    "name:fra_x_preferred":[
        "Metten"
    ],
    "name:hun_x_preferred":[
        "Metten"
    ],
    "name:hye_x_preferred":[
        "\u0544\u0565\u0569\u0565\u0576"
    ],
    "name:ind_x_preferred":[
        "Metten"
    ],
    "name:ita_x_preferred":[
        "Metten"
    ],
    "name:kaz_x_preferred":[
        "\u041c\u0435\u0442\u0442\u0435\u043d"
    ],
    "name:kir_x_preferred":[
        "\u041c\u0435\u0442\u0442\u0435\u043d"
    ],
    "name:lmo_x_preferred":[
        "Metten"
    ],
    "name:msa_x_preferred":[
        "Metten"
    ],
    "name:nld_x_preferred":[
        "Metten"
    ],
    "name:pol_x_preferred":[
        "Metten"
    ],
    "name:por_x_preferred":[
        "Metten"
    ],
    "name:ron_x_preferred":[
        "Metten"
    ],
    "name:rus_x_preferred":[
        "\u041c\u0435\u0442\u0442\u0435\u043d"
    ],
    "name:spa_x_preferred":[
        "Metten"
    ],
    "name:srp_x_preferred":[
        "\u041c\u0435\u0442\u0435\u043d"
    ],
    "name:ukr_x_preferred":[
        "\u041c\u0435\u0442\u0442\u0435\u043d"
    ],
    "name:uzb_x_preferred":[
        "Metten"
    ],
    "name:vie_x_preferred":[
        "Metten"
    ],
    "name:vol_x_preferred":[
        "Metten"
    ],
    "name:war_x_preferred":[
        "Metten"
    ],
    "wof:name":"Metten",
    "wof:placetype":"neighbourhood"
},
  "geometry": {"coordinates":[13.09351,48.97608],"type":"Point"}
}