{
  "type": "Feature",
  "properties": {
    "gn:country":"DE",
    "gn:fcode":"PPL",
    "gn:population":0,
    "iso:country":"DE",
    "name:als_x_preferred":[
        "Braunsbach"
    ],
    "name:ceb_x_preferred":[
        "Braunsbach"
    ],
    "name:deu_x_preferred":[
        "Braunsbach"
    ],
    "name:epo_x_preferred":[
        "Braunsbach"
    ],
    "name:eus_x_preferred":[
        "Braunsbach"
    ],
    "name:fas_x_preferred":[
        "\u0628\u0631\u0627\u0648\u0646\u0633\u0628\u0627\u062e"
    ],
    "name:fra_x_preferred":[
        "Braunsbach"
    ],
    "name:hun_x_preferred":[
        "Braunsbach"
    ],
    "name:ita_x_preferred":[
        "Braunsbach"
    ],
    "name:jpn_x_preferred":[
        "\u30d6\u30e9\u30a6\u30f3\u30b9\u30d0\u30c3\u30cf"
    ],
    "name:kaz_x_preferred":[
        "\u0411\u0440\u0430\u0443\u043d\u0441\u0431\u0430\u0445"
    ],
    "name:kir_x_preferred":[
        "\u0411\u0440\u0430\u0443\u043d\u0441\u0431\u0430\u0445"
    ],
    "name:lat_x_preferred":[
        "Braunsbach"
    ],
    "name:lmo_x_preferred":[
        "Braunsbach"
    ],
    "name:msa_x_preferred":[
        "Braunsbach"
    ],
    "name:nld_x_preferred":[
        "Braunsbach"
    ],
    "name:pol_x_preferred":[
        "Braunsbach"
    ],
    "name:por_x_preferred":[
        "Braunsbach"
    ],
    "name:ron_x_preferred":[
        "Braunsbach"
    ],
    "name:rus_x_preferred":[
        "\u0411\u0440\u0430\u0443\u043d\u0441\u0431\u0430\u0445"
    ],
    "name:spa_x_preferred":[
        "Braunsbach"
    ],
    "name:srp_x_preferred":[
        "\u0411\u0440\u0430\u0443\u043d\u0441\u0431\u0430\u0445"
    ],
    "name:ukr_x_preferred":[
        "\u0411\u0440\u0430\u0443\u043d\u0441\u0431\u0430\u0445"
    ],
    "name:uzb_x_preferred":[
        "Braunsbach"
    ],
    "name:vie_x_preferred":[
        "Braunsbach"
    ],
    "name:vol_x_preferred":[
        "Braunsbach"
    ],
    "name:war_x_preferred":[
        "Braunsbach"
    ],
    "name:zho_x_preferred":[
        "\u5e03\u52b3\u6069\u65af\u5df4\u8d6b"
    ],
    "qs_pg:aaroncc":"DE",
    "qs_pg:gn_country":"DE",
    "qs_pg:gn_fcode":"PPL",
    "qs_pg:gn_pop":0,
    "qs_pg:name":"Braunsbach",
    "qs_pg:name_adm0":"Deutschland",
    "qs_pg:name_adm1":"Bayern",
    "qs_pg:photos":4,
    "qs_pg:photos_1k":1,
    "qs_pg:photos_9k":1,
    "qs_pg:photos_9r":1,
    "qs_pg:photos_all":4,
    "qs_pg:photos_sr":1,
    "qs_pg:pop_sr":0,
    "qs_pg:qs_pg_placetype":"neighbourhood",
    "qs_pg:qs_pg_placetype_gp":"Suburb",
    "qs_pg:woe_adm0":23424829,
    "woe:adm0_id":23424829,
    "woe:name_adm0":"Deutschland",
    "woe:name_adm1":"Bayern",
    "woe:placetype":"Suburb",
    "wof:name":"Braunsbach",
    "wof:placetype":"neighbourhood"
},
  "geometry": {"coordinates":[11.01629,49.50239],"type":"Point"}
}