{
  "type": "Feature",
  "properties": {
    "gn:country":"DE",
    "gn:fcode":"PPL",
    "gn:population":0,
    "iso:country":"DE",
    "name:ceb_x_preferred":[
        "Glane"
    ],
    "name:deu_x_preferred":[
        "Glane"
    ],
    "name:fra_x_preferred":[
        "Glane"
    ],
    "name:nld_x_preferred":[
        "Glane"
    ],
    "name:swe_x_preferred":[
        "Glane"
    ],
    "qs_pg:aaroncc":"DE",
    "qs_pg:gn_country":"DE",
    "qs_pg:gn_fcode":"PPL",
    "qs_pg:gn_pop":0,
    "qs_pg:name":"Glane",
    "qs_pg:name_adm0":"Deutschland",
    "qs_pg:name_adm1":"Niedersachsen",
    "qs_pg:photos_9r":0,
    "qs_pg:photos_sr":0,
    "qs_pg:pop_sr":0,
    "qs_pg:qs_pg_placetype":"locality",
    "qs_pg:qs_pg_placetype_gp":"Town",
    "qs_pg:woe_adm0":23424829,
    "woe:adm0_id":23424829,
    "woe:name_adm0":"Deutschland",
    "woe:name_adm1":"Niedersachsen",
    "woe:placetype":"Town",
    "wof:name":"Glane",
    "wof:placetype":"neighbourhood"
},
  "geometry": {"coordinates":[8.05406,52.14684],"type":"Point"}
}