{
  "type": "Feature",
  "properties": {
    "gn:admin1_code":"2.0",
    "gn:admin2_code":"93.0",
    "gn:admin3_code":"9376.0",
    "gn:admin4_code":"9376162.0",
    "gn:asciiname":"Altfalter",
    "gn:country_code":"DE",
    "gn:dem":398,
    "gn:feature_class":"P",
    "gn:feature_code":"PPL",
    "gn:name":"Altfalter",
    "gn:population":0,
    "gn:timezone":"Europe/Berlin",
    "iso:country":"DE",
    "wof:name":"Altfalter",
    "wof:placetype":"neighbourhood"
},
  "geometry": {"coordinates":[12.20753,49.39712],"type":"Point"}
}