{
  "type": "Feature",
  "properties": {
    "gn:country":"DE",
    "gn:fcode":"PPL",
    "gn:population":0,
    "iso:country":"DE",
    "name:hun_x_preferred":[
        "Steinberg"
    ],
    "name:jpn_x_preferred":[
        "\u30b9\u30bf\u30a4\u30f3\u30d0\u30fc\u30b0"
    ],
    "name:kor_x_preferred":[
        "\uc2a4\ud14c\uc778\ubc84\uadf8"
    ],
    "name:nld_x_preferred":[
        "Steinberg"
    ],
    "name:por_x_preferred":[
        "Steinberg"
    ],
    "name:spa_x_preferred":[
        "Steinberg"
    ],
    "name:swe_x_preferred":[
        "Steinberg"
    ],
    "name:tha_x_preferred":[
        "\u0e2a\u0e44\u0e15\u0e19\u0e4c\u0e40\u0e1a\u0e34\u0e23\u0e4c\u0e01"
    ],
    "name:tur_x_preferred":[
        "Steinberg"
    ],
    "name:ukr_x_preferred":[
        "Steinberg"
    ],
    "name:zho_x_preferred":[
        "Steinberg"
    ],
    "qs_pg:aaroncc":"DE",
    "qs_pg:gn_country":"DE",
    "qs_pg:gn_fcode":"PPL",
    "qs_pg:gn_pop":0,
    "qs_pg:name":"Steinberg",
    "qs_pg:name_adm0":"Deutschland",
    "qs_pg:name_adm1":"Baden-W\u00fcrttemberg",
    "qs_pg:photos":2,
    "qs_pg:photos_1k":1,
    "qs_pg:photos_9k":1,
    "qs_pg:photos_9r":1,
    "qs_pg:photos_all":2,
    "qs_pg:photos_sr":1,
    "qs_pg:pop_sr":0,
    "qs_pg:qs_pg_placetype":"locality",
    "qs_pg:qs_pg_placetype_gp":"Town",
    "qs_pg:woe_adm0":23424829,
    "woe:adm0_id":23424829,
    "woe:name_adm0":"Deutschland",
    "woe:name_adm1":"Baden-W\u00fcrttemberg",
    "woe:placetype":"Town",
    "wof:name":"Steinberg",
    "wof:placetype":"neighbourhood"
},
  "geometry": {"coordinates":[10.0036,48.30009],"type":"Point"}
}