{
  "type": "Feature",
  "properties": {
    "iso:country":"DE",
    "wof:name":"Weixdorf",
    "wof:placetype":"neighbourhood"
},
  "geometry": {"coordinates":[13.79715753916575,51.14361983702009],"type":"Point"}
}