{
  "type": "Feature",
  "properties": {
    "gn:admin1_code":"13",
    "gn:admin2_code":"0.0",
    "gn:admin3_code":"14730.0",
    "gn:admin4_code":"14730330.0",
    "gn:asciiname":"Reckwitz",
    "gn:country_code":"DE",
    "gn:dem":165,
    "gn:feature_class":"P",
    "gn:feature_code":"PPL",
    "gn:name":"Reckwitz",
    "gn:population":0,
    "gn:timezone":"Europe/Berlin",
    "iso:country":"DE",
    "wof:name":"Reckwitz",
    "wof:placetype":"neighbourhood"
},
  "geometry": {"coordinates":[12.93494,51.27052],"type":"Point"}
}