{
  "type": "Feature",
  "properties": {
    "gn:admin1_code":"2",
    "gn:admin2_code":"92.0",
    "gn:admin3_code":"9273.0",
    "gn:admin4_code":"9273141.0",
    "gn:asciiname":"Mitterschneidhart",
    "gn:country_code":"DE",
    "gn:dem":386,
    "gn:feature_class":"P",
    "gn:feature_code":"PPL",
    "gn:name":"Mitterschneidhart",
    "gn:population":0,
    "gn:timezone":"Europe/Berlin",
    "iso:country":"DE",
    "wof:name":"Mitterschneidhart",
    "wof:placetype":"neighbourhood"
},
  "geometry": {"coordinates":[12.04461,48.85717],"type":"Point"}
}