{
  "type": "Feature",
  "properties": {
    "gn:admin1_code":"1",
    "gn:admin2_code":"84.0",
    "gn:admin3_code":"8426.0",
    "gn:admin4_code":"8426121.0",
    "gn:asciiname":"Dietelhofen",
    "gn:country_code":"DE",
    "gn:dem":584,
    "gn:feature_class":"P",
    "gn:feature_code":"PPL",
    "gn:name":"Dietelhofen",
    "gn:population":0,
    "gn:timezone":"Europe/Berlin",
    "iso:country":"DE",
    "wof:name":"Dietelhofen",
    "wof:placetype":"neighbourhood"
},
  "geometry": {"coordinates":[9.56841,48.18314],"type":"Point"}
}