{
  "type": "Feature",
  "properties": {
    "gn:admin1_code":"6",
    "gn:admin2_code":"0.0",
    "gn:admin3_code":"3155.0",
    "gn:admin4_code":"3155007.0",
    "gn:asciiname":"Suterode",
    "gn:country_code":"DE",
    "gn:dem":168,
    "gn:feature_class":"P",
    "gn:feature_code":"PPL",
    "gn:name":"Suterode",
    "gn:population":0,
    "gn:timezone":"Europe/Berlin",
    "iso:country":"DE",
    "wof:name":"Suterode",
    "wof:placetype":"neighbourhood"
},
  "geometry": {"coordinates":[10.06135,51.67101],"type":"Point"}
}