{
  "type": "Feature",
  "properties": {
    "gn:admin1_code":"1.0",
    "gn:admin2_code":"083",
    "gn:admin3_code":"8325.0",
    "gn:admin4_code":"8325049.0",
    "gn:asciiname":"Zepfenhan",
    "gn:country_code":"DE",
    "gn:dem":686,
    "gn:feature_class":"P",
    "gn:feature_code":"PPL",
    "gn:name":"Zepfenhan",
    "gn:population":0,
    "gn:timezone":"Europe/Berlin",
    "iso:country":"DE",
    "wof:name":"Zepfenhan",
    "wof:placetype":"neighbourhood"
},
  "geometry": {"coordinates":[8.71409,48.19138],"type":"Point"}
}