{
  "type": "Feature",
  "properties": {
    "gn:admin1_code":"6",
    "gn:admin2_code":"0.0",
    "gn:admin3_code":"3359.0",
    "gn:admin4_code":"3359038.0",
    "gn:asciiname":"Hohenwedel",
    "gn:country_code":"DE",
    "gn:dem":7,
    "gn:feature_class":"P",
    "gn:feature_code":"PPL",
    "gn:name":"Hohenwedel",
    "gn:population":0,
    "gn:timezone":"Europe/Berlin",
    "iso:country":"DE",
    "wof:name":"Hohenwedel",
    "wof:placetype":"neighbourhood"
},
  "geometry": {"coordinates":[9.44378,53.60694],"type":"Point"}
}