{
  "type": "Feature",
  "properties": {
    "gn:admin1_code":"6",
    "gn:admin2_code":"0.0",
    "gn:admin3_code":"3351.0",
    "gn:admin4_code":"3351025.0",
    "gn:asciiname":"Habighorst",
    "gn:country_code":"DE",
    "gn:dem":68,
    "gn:feature_class":"P",
    "gn:feature_code":"PPLA4",
    "gn:name":"Habighorst",
    "gn:population":0,
    "gn:timezone":"Europe/Berlin",
    "iso:country":"DE",
    "name:ceb_x_preferred":[
        "Habighorst"
    ],
    "name:deu_x_preferred":[
        "Habighorst"
    ],
    "name:epo_x_preferred":[
        "Habighorst"
    ],
    "name:eus_x_preferred":[
        "Habighorst"
    ],
    "name:fas_x_preferred":[
        "\u0647\u0627\u0628\u06cc\u06af\u0647\u0648\u0631\u0634\u062a"
    ],
    "name:fra_x_preferred":[
        "Habighorst"
    ],
    "name:ita_x_preferred":[
        "Habighorst"
    ],
    "name:kaz_x_preferred":[
        "\u0425\u0430\u0431\u0438\u0433\u0445\u043e\u0440\u0441\u0442"
    ],
    "name:kir_x_preferred":[
        "\u0425\u0430\u0431\u0438\u0433\u0445\u043e\u0440\u0441\u0442"
    ],
    "name:lat_x_preferred":[
        "Habighorst"
    ],
    "name:mkd_x_preferred":[
        "\u0425\u0430\u0431\u0438\u0433\u0445\u043e\u0440\u0441\u0442"
    ],
    "name:msa_x_preferred":[
        "Habighorst"
    ],
    "name:nld_x_preferred":[
        "Habighorst"
    ],
    "name:pol_x_preferred":[
        "Habighorst"
    ],
    "name:por_x_preferred":[
        "Habighorst"
    ],
    "name:ron_x_preferred":[
        "Habighorst"
    ],
    "name:rus_x_preferred":[
        "\u0425\u0430\u0431\u0438\u0433\u0445\u043e\u0440\u0441\u0442"
    ],
    "name:srp_x_preferred":[
        "\u0425\u0430\u0431\u0438\u0433\u0445\u043e\u0440\u0441\u0442"
    ],
    "name:uzb_x_preferred":[
        "Habighorst"
    ],
    "name:vie_x_preferred":[
        "Habighorst"
    ],
    "name:vol_x_preferred":[
        "Habighorst"
    ],
    "name:war_x_preferred":[
        "Habighorst"
    ],
    "name:zho_x_preferred":[
        "\u54c8\u6bd4\u5e0c\u970d\u65af\u7279"
    ],
    "wof:name":"Habighorst",
    "wof:placetype":"neighbourhood"
},
  "geometry": {"coordinates":[10.22741,52.70864],"type":"Point"}
}