{
  "type": "Feature",
  "properties": {
    "gn:admin1_code":"7",
    "gn:admin2_code":"59.0",
    "gn:admin3_code":"5966.0",
    "gn:admin4_code":"5966028.0",
    "gn:asciiname":"Heid",
    "gn:country_code":"DE",
    "gn:dem":394,
    "gn:feature_class":"P",
    "gn:feature_code":"PPL",
    "gn:name":"Heid",
    "gn:population":0,
    "gn:timezone":"Europe/Berlin",
    "iso:country":"DE",
    "name:deu_x_preferred":[
        "Heid"
    ],
    "name:fra_x_preferred":[
        "Heid"
    ],
    "name:nds_x_preferred":[
        "Heid"
    ],
    "wof:name":"Heid",
    "wof:placetype":"neighbourhood"
},
  "geometry": {"coordinates":[7.8072,50.94861],"type":"Point"}
}