{
  "type": "Feature",
  "properties": {
    "gn:admin1_code":"6",
    "gn:admin2_code":"0.0",
    "gn:admin3_code":"3461.0",
    "gn:admin4_code":"3461003.0",
    "gn:asciiname":"Isenserwisch",
    "gn:country_code":"DE",
    "gn:dem":1,
    "gn:feature_class":"P",
    "gn:feature_code":"PPL",
    "gn:name":"Isenserwisch",
    "gn:population":0,
    "gn:timezone":"Europe/Berlin",
    "iso:country":"DE",
    "wof:name":"Isenserwisch",
    "wof:placetype":"neighbourhood"
},
  "geometry": {"coordinates":[8.3887,53.54188000000001],"type":"Point"}
}