{
  "type": "Feature",
  "properties": {
    "gn:admin1_code":"13",
    "gn:admin2_code":"0.0",
    "gn:admin3_code":"14522.0",
    "gn:admin4_code":"14522400.0",
    "gn:asciiname":"Frauenbach",
    "gn:country_code":"DE",
    "gn:dem":595,
    "gn:feature_class":"P",
    "gn:feature_code":"PPL",
    "gn:name":"Frauenbach",
    "gn:population":0,
    "gn:timezone":"Europe/Berlin",
    "iso:country":"DE",
    "wof:name":"Frauenbach",
    "wof:placetype":"neighbourhood"
},
  "geometry": {"coordinates":[13.47949,50.66934000000001],"type":"Point"}
}