{
  "type": "Feature",
  "properties": {
    "gn:admin1_code":"13",
    "gn:admin2_code":"0.0",
    "gn:admin3_code":"14627.0",
    "gn:admin4_code":"14627080.0",
    "gn:asciiname":"Sornitz",
    "gn:country_code":"DE",
    "gn:dem":152,
    "gn:feature_class":"P",
    "gn:feature_code":"PPL",
    "gn:name":"Sornitz",
    "gn:population":0,
    "gn:timezone":"Europe/Berlin",
    "iso:country":"DE",
    "wof:name":"Sornitz",
    "wof:placetype":"neighbourhood"
},
  "geometry": {"coordinates":[13.35536,51.15866],"type":"Point"}
}