{
  "type": "Feature",
  "properties": {
    "gn:admin1_code":"2",
    "gn:admin2_code":"93.0",
    "gn:admin3_code":"9375.0",
    "gn:admin4_code":"9375196.0",
    "gn:asciiname":"Kraxenhofen",
    "gn:country_code":"DE",
    "gn:dem":366,
    "gn:feature_class":"P",
    "gn:feature_code":"PPL",
    "gn:name":"Kraxenh\u00f6fen",
    "gn:population":0,
    "gn:timezone":"Europe/Berlin",
    "iso:country":"DE",
    "wof:name":"Kraxenhofen",
    "wof:placetype":"neighbourhood"
},
  "geometry": {"coordinates":[12.1825,48.84834],"type":"Point"}
}