{
  "type": "Feature",
  "properties": {
    "gn:admin1_code":"2",
    "gn:admin2_code":"92.0",
    "gn:admin3_code":"9279.0",
    "gn:admin4_code":"9279122.0",
    "gn:asciiname":"Kothingeichendorf",
    "gn:country_code":"DE",
    "gn:dem":373,
    "gn:feature_class":"P",
    "gn:feature_code":"PPLL",
    "gn:name":"Kothingeichendorf",
    "gn:population":0,
    "gn:timezone":"Europe/Berlin",
    "iso:country":"DE",
    "wof:name":"Kothingeichendorf",
    "wof:placetype":"neighbourhood"
},
  "geometry": {"coordinates":[12.74548,48.68338],"type":"Point"}
}