{
  "type": "Feature",
  "properties": {
    "gn:admin1_code":"7",
    "gn:admin2_code":"57.0",
    "gn:admin3_code":"5770.0",
    "gn:admin4_code":"5770008.0",
    "gn:asciiname":"Schmalge",
    "gn:country_code":"DE",
    "gn:dem":49,
    "gn:feature_class":"P",
    "gn:feature_code":"PPLL",
    "gn:name":"Schmalge",
    "gn:population":0,
    "gn:timezone":"Europe/Berlin",
    "iso:country":"DE",
    "wof:name":"Schmalge",
    "wof:placetype":"neighbourhood"
},
  "geometry": {"coordinates":[8.65599,52.39419],"type":"Point"}
}