{
  "type": "Feature",
  "properties": {
    "gn:gn_country":"DE",
    "gn:gn_fcode":"PPLA4",
    "gn:gn_pop":690,
    "gn:population":690,
    "iso:country":"DE",
    "name:baq_x_preferred":[
        "Dorsheim"
    ],
    "name:chi_x_preferred":[
        "\u591a\u5c14\u65af\u6d77\u59c6"
    ],
    "name:dut_x_preferred":[
        "Dorsheim"
    ],
    "name:eng_x_preferred":[
        "Dorsheim"
    ],
    "name:epo_x_preferred":[
        "Dorsheim"
    ],
    "name:fre_x_preferred":[
        "Dorsheim"
    ],
    "name:ger_x_preferred":[
        "Dorsheim"
    ],
    "name:hun_x_preferred":[
        "Dorsheim"
    ],
    "name:ita_x_preferred":[
        "Dorsheim"
    ],
    "name:jpn_x_preferred":[
        "\u30c9\u30eb\u30b9\u30cf\u30a4\u30e0"
    ],
    "name:kaz_x_preferred":[
        "\u0414\u043e\u0440\u0441\u0445\u0430\u0439\u043c"
    ],
    "name:kir_x_preferred":[
        "\u0414\u043e\u0440\u0441\u0445\u0430\u0439\u043c"
    ],
    "name:may_x_preferred":[
        "Dorsheim"
    ],
    "name:per_x_preferred":[
        "\u062f\u0648\u0631\u0633\u0647\u0627\u06cc\u0645"
    ],
    "name:pol_x_preferred":[
        "Dorsheim"
    ],
    "name:por_x_preferred":[
        "Dorsheim"
    ],
    "name:rum_x_preferred":[
        "Dorsheim"
    ],
    "name:rus_x_preferred":[
        "\u0414\u043e\u0440\u0441\u0445\u0430\u0439\u043c"
    ],
    "name:spa_x_preferred":[
        "Dorsheim"
    ],
    "name:srp_x_preferred":[
        "\u0414\u043e\u0440\u0441\u0445\u0430\u0458\u043c"
    ],
    "name:ukr_x_preferred":[
        "\u0414\u043e\u0440\u0441\u0433\u0430\u0439\u043c"
    ],
    "name:uzb_x_preferred":[
        "Dorsheim"
    ],
    "name:vie_x_preferred":[
        "Dorsheim"
    ],
    "name:vol_x_preferred":[
        "Dorsheim"
    ],
    "name:war_x_preferred":[
        "Dorsheim"
    ],
    "qs_pg:aaroncc":"DE",
    "qs_pg:gn_country":"DE",
    "qs_pg:gn_fcode":"PPLA4",
    "qs_pg:gn_pop":690,
    "qs_pg:name":"Dorsheim",
    "qs_pg:photos_9r":0,
    "qs_pg:photos_sr":0,
    "qs_pg:pop_sr":2,
    "qs_pg:qs_pg_placetype":"locality",
    "wof:name":"Dorsheim",
    "wof:placetype":"locality",
    "wof:population":690
},
  "geometry": {"coordinates":[7.86667,49.91667],"type":"Point"}
}