{
  "type": "Feature",
  "properties": {
    "gn:admin1_code":"1",
    "gn:admin2_code":"81.0",
    "gn:admin3_code":"8127.0",
    "gn:admin4_code":"8127013.0",
    "gn:asciiname":"Mangoldshausen",
    "gn:country_code":"DE",
    "gn:dem":485,
    "gn:feature_class":"P",
    "gn:feature_code":"PPL",
    "gn:name":"Mangoldshausen",
    "gn:population":0,
    "gn:timezone":"Europe/Berlin",
    "iso:country":"DE",
    "wof:name":"Mangoldshausen",
    "wof:placetype":"neighbourhood"
},
  "geometry": {"coordinates":[9.95593,48.9935],"type":"Point"}
}