{
  "type": "Feature",
  "properties": {
    "gn:admin1_code":"6.0",
    "gn:admin2_code":"0.0",
    "gn:admin3_code":"3459.0",
    "gn:admin4_code":"3459004.0",
    "gn:asciiname":"Auf dem Donnerbrink",
    "gn:country_code":"DE",
    "gn:dem":76,
    "gn:feature_class":"P",
    "gn:feature_code":"PPLL",
    "gn:name":"Auf dem Donnerbrink",
    "gn:population":0,
    "gn:timezone":"Europe/Berlin",
    "iso:country":"DE",
    "wof:name":"Auf dem Donnerbrink",
    "wof:placetype":"neighbourhood"
},
  "geometry": {"coordinates":[8.01902,52.11747],"type":"Point"}
}