{
  "type": "Feature",
  "properties": {
    "gn:admin1_code":"6.0",
    "gn:admin2_code":"0.0",
    "gn:admin3_code":"3453.0",
    "gn:admin4_code":"3453011.0",
    "gn:asciiname":"Angelbeck",
    "gn:country_code":"DE",
    "gn:dem":25,
    "gn:feature_class":"P",
    "gn:feature_code":"PPL",
    "gn:name":"Angelbeck",
    "gn:population":0,
    "gn:timezone":"Europe/Berlin",
    "iso:country":"DE",
    "name:und_x_variant":[
        "Angelbek",
        "Angelbeck"
    ],
    "wof:name":"Angelbeck",
    "wof:placetype":"neighbourhood"
},
  "geometry": {"coordinates":[7.76768,52.71923],"type":"Point"}
}