{
  "type": "Feature",
  "properties": {
    "gn:admin1_code":"2.0",
    "gn:admin2_code":"92.0",
    "gn:admin3_code":"9272.0",
    "gn:admin4_code":"9272118.0",
    "gn:asciiname":"Aigenstadl",
    "gn:country_code":"DE",
    "gn:dem":565,
    "gn:feature_class":"P",
    "gn:feature_code":"PPL",
    "gn:name":"Aigenstadl",
    "gn:population":0,
    "gn:timezone":"Europe/Berlin",
    "iso:country":"DE",
    "name:und_x_variant":[
        "Aigenstadel",
        "Aigenstadl"
    ],
    "wof:name":"Aigenstadl",
    "wof:placetype":"neighbourhood"
},
  "geometry": {"coordinates":[13.50051,48.80556],"type":"Point"}
}