{
  "type": "Feature",
  "properties": {
    "gn:admin1_code":"2",
    "gn:admin2_code":"97.0",
    "gn:admin3_code":"9778.0",
    "gn:admin4_code":"9778119.0",
    "gn:asciiname":"Gunzegg",
    "gn:country_code":"DE",
    "gn:dem":804,
    "gn:feature_class":"P",
    "gn:feature_code":"PPL",
    "gn:name":"G\u00fcnzegg",
    "gn:population":0,
    "gn:timezone":"Europe/Berlin",
    "iso:country":"DE",
    "wof:name":"Gunzegg",
    "wof:placetype":"neighbourhood"
},
  "geometry": {"coordinates":[10.34254,47.87944],"type":"Point"}
}