{
  "type": "Feature",
  "properties": {
    "gn:admin1_code":"2",
    "gn:admin2_code":"95.0",
    "gn:admin3_code":"9574.0",
    "gn:admin4_code":"9574140.0",
    "gn:asciiname":"Hofen",
    "gn:country_code":"DE",
    "gn:dem":446,
    "gn:feature_class":"P",
    "gn:feature_code":"PPL",
    "gn:name":"H\u00f6fen",
    "gn:population":0,
    "gn:timezone":"Europe/Berlin",
    "iso:country":"DE",
    "name:deu_x_preferred":[
        "Hofen"
    ],
    "name:epo_x_preferred":[
        "Hofen"
    ],
    "name:ita_x_preferred":[
        "Hofen"
    ],
    "name:pol_x_preferred":[
        "Hofen"
    ],
    "wof:name":"Hofen",
    "wof:placetype":"neighbourhood"
},
  "geometry": {"coordinates":[11.51009,49.64256],"type":"Point"}
}