{
  "type": "Feature",
  "properties": {
    "gn:admin1_code":"7.0",
    "gn:admin2_code":"59.0",
    "gn:admin3_code":"5958.0",
    "gn:admin4_code":"5958040.0",
    "gn:asciiname":"Berghausen",
    "gn:country_code":"DE",
    "gn:dem":401,
    "gn:feature_class":"P",
    "gn:feature_code":"PPL",
    "gn:name":"Berghausen",
    "gn:population":0,
    "gn:timezone":"Europe/Berlin",
    "iso:country":"DE",
    "name:ceb_x_preferred":[
        "Berghausen"
    ],
    "name:ces_x_preferred":[
        "Berghausen"
    ],
    "name:deu_x_preferred":[
        "Berghausen"
    ],
    "name:fra_x_preferred":[
        "Berghausen"
    ],
    "name:ita_x_preferred":[
        "Berghausen"
    ],
    "name:nld_x_preferred":[
        "Berghausen"
    ],
    "name:pol_x_preferred":[
        "Berghausen"
    ],
    "name:rus_x_preferred":[
        "\u0411\u0435\u0440\u0433\u0445\u0430\u0443\u0437\u0435\u043d"
    ],
    "name:slk_x_preferred":[
        "Berghausen"
    ],
    "name:swe_x_preferred":[
        "Berghausen"
    ],
    "name:vol_x_preferred":[
        "Berghausen"
    ],
    "wof:name":"Berghausen",
    "wof:placetype":"neighbourhood"
},
  "geometry": {"coordinates":[8.24542,51.18583],"type":"Point"}
}