{
  "type": "Feature",
  "properties": {
    "gn:admin1_code":"1",
    "gn:admin2_code":"81.0",
    "gn:admin3_code":"8119.0",
    "gn:admin4_code":"8119061.0",
    "gn:asciiname":"Unterschlechtbach",
    "gn:country_code":"DE",
    "gn:dem":274,
    "gn:feature_class":"P",
    "gn:feature_code":"PPL",
    "gn:name":"Unterschlechtbach",
    "gn:population":0,
    "gn:timezone":"Europe/Berlin",
    "iso:country":"DE",
    "wof:name":"Unterschlechtbach",
    "wof:placetype":"neighbourhood"
},
  "geometry": {"coordinates":[9.53021,48.87386],"type":"Point"}
}