{
  "type": "Feature",
  "properties": {
    "gn:admin1_code":"7",
    "gn:admin2_code":"59.0",
    "gn:admin3_code":"5958.0",
    "gn:admin4_code":"5958040.0",
    "gn:asciiname":"Gleidorf",
    "gn:country_code":"DE",
    "gn:dem":404,
    "gn:feature_class":"P",
    "gn:feature_code":"PPL",
    "gn:name":"Gleidorf",
    "gn:population":0,
    "gn:timezone":"Europe/Berlin",
    "iso:country":"DE",
    "wof:name":"Gleidorf",
    "wof:placetype":"neighbourhood"
},
  "geometry": {"coordinates":[8.3141,51.16621],"type":"Point"}
}