{
  "type": "Feature",
  "properties": {
    "gn:admin1_code":"9.0",
    "gn:admin2_code":"0.0",
    "gn:admin3_code":"10042.0",
    "gn:admin4_code":"10042116.0",
    "gn:asciiname":"Bardenbach",
    "gn:country_code":"DE",
    "gn:dem":267,
    "gn:feature_class":"P",
    "gn:feature_code":"PPL",
    "gn:name":"Bardenbach",
    "gn:population":0,
    "gn:timezone":"Europe/Berlin",
    "iso:country":"DE",
    "wof:name":"Bardenbach",
    "wof:placetype":"neighbourhood"
},
  "geometry": {"coordinates":[6.87136,49.50958],"type":"Point"}
}