{
  "type": "Feature",
  "properties": {
    "gn:admin1_code":"2",
    "gn:admin2_code":"93.0",
    "gn:admin3_code":"9375.0",
    "gn:admin4_code":"9375180.0",
    "gn:asciiname":"Niedergebraching",
    "gn:country_code":"DE",
    "gn:dem":404,
    "gn:feature_class":"P",
    "gn:feature_code":"PPL",
    "gn:name":"Niedergebraching",
    "gn:population":0,
    "gn:timezone":"Europe/Berlin",
    "iso:country":"DE",
    "wof:name":"Niedergebraching",
    "wof:placetype":"neighbourhood"
},
  "geometry": {"coordinates":[12.06768,48.95814],"type":"Point"}
}