{
  "type": "Feature",
  "properties": {
    "gn:admin1_code":"2",
    "gn:admin2_code":"93.0",
    "gn:admin3_code":"9375.0",
    "gn:admin4_code":"9375205.0",
    "gn:asciiname":"Untersanding",
    "gn:country_code":"DE",
    "gn:dem":369,
    "gn:feature_class":"P",
    "gn:feature_code":"PPL",
    "gn:name":"Untersanding",
    "gn:population":0,
    "gn:timezone":"Europe/Berlin",
    "iso:country":"DE",
    "wof:name":"Untersanding",
    "wof:placetype":"neighbourhood"
},
  "geometry": {"coordinates":[12.17187,48.89058],"type":"Point"}
}