{
  "type": "Feature",
  "properties": {
    "gn:admin1_code":"7",
    "gn:admin2_code":"53.0",
    "gn:admin3_code":"5382.0",
    "gn:admin4_code":"5382012.0",
    "gn:asciiname":"Dersdorf",
    "gn:country_code":"DE",
    "gn:dem":77,
    "gn:feature_class":"P",
    "gn:feature_code":"PPL",
    "gn:name":"Dersdorf",
    "gn:population":0,
    "gn:timezone":"Europe/Berlin",
    "iso:country":"DE",
    "wof:name":"Dersdorf",
    "wof:placetype":"neighbourhood"
},
  "geometry": {"coordinates":[6.9655,50.76152],"type":"Point"}
}