{
  "type": "Feature",
  "properties": {
    "gn:admin1_code":"6",
    "gn:admin2_code":"0.0",
    "gn:admin3_code":"3154.0",
    "gn:admin4_code":"3154025.0",
    "gn:asciiname":"Kissleberfeld",
    "gn:country_code":"DE",
    "gn:dem":138,
    "gn:feature_class":"P",
    "gn:feature_code":"PPL",
    "gn:name":"Ki\u00dfleberfeld",
    "gn:population":0,
    "gn:timezone":"Europe/Berlin",
    "iso:country":"DE",
    "wof:name":"Kissleberfeld",
    "wof:placetype":"neighbourhood"
},
  "geometry": {"coordinates":[10.94788,52.17625],"type":"Point"}
}