{
  "type": "Feature",
  "properties": {
    "gn:admin1_code":"2",
    "gn:admin2_code":"93.0",
    "gn:admin3_code":"9374.0",
    "gn:admin4_code":"9374148.0",
    "gn:asciiname":"Preissach",
    "gn:country_code":"DE",
    "gn:dem":456,
    "gn:feature_class":"P",
    "gn:feature_code":"PPL",
    "gn:name":"Prei\u00dfach",
    "gn:population":0,
    "gn:timezone":"Europe/Berlin",
    "iso:country":"DE",
    "name:und_x_variant":[
        "Pressat",
        "Prei\u00dfach"
    ],
    "wof:name":"Preissach",
    "wof:placetype":"neighbourhood"
},
  "geometry": {"coordinates":[11.8709,49.8017],"type":"Point"}
}