{
  "type": "Feature",
  "properties": {
    "gn:admin1_code":"2",
    "gn:admin2_code":"92.0",
    "gn:admin3_code":"9276.0",
    "gn:admin4_code":"9276128.0",
    "gn:asciiname":"Taging",
    "gn:country_code":"DE",
    "gn:dem":507,
    "gn:feature_class":"P",
    "gn:feature_code":"PPL",
    "gn:name":"Taging",
    "gn:population":0,
    "gn:timezone":"Europe/Berlin",
    "iso:country":"DE",
    "wof:name":"Taging",
    "wof:placetype":"neighbourhood"
},
  "geometry": {"coordinates":[12.94061,49.04029],"type":"Point"}
}