{
  "type": "Feature",
  "properties": {
    "gn:admin1_code":"11",
    "gn:admin2_code":"0.0",
    "gn:admin3_code":"12072.0",
    "gn:admin4_code":"12072053.0",
    "gn:asciiname":"Schoena",
    "gn:country_code":"DE",
    "gn:dem":102,
    "gn:feature_class":"P",
    "gn:feature_code":"PPL",
    "gn:name":"Sch\u00f6na",
    "gn:population":0,
    "gn:timezone":"Europe/Berlin",
    "iso:country":"DE",
    "wof:name":"Schoena",
    "wof:placetype":"neighbourhood"
},
  "geometry": {"coordinates":[13.44748,51.81407],"type":"Point"}
}