{
  "type": "Feature",
  "properties": {
    "gn:admin1_code":"2",
    "gn:admin2_code":"93.0",
    "gn:admin3_code":"9371.0",
    "gn:admin4_code":"9371141.0",
    "gn:asciiname":"Lockenricht",
    "gn:cc2":"DE",
    "gn:country_code":"DE",
    "gn:dem":458,
    "gn:feature_class":"P",
    "gn:feature_code":"PPL",
    "gn:name":"Lockenricht",
    "gn:population":0,
    "gn:timezone":"Europe/Berlin",
    "iso:country":"DE",
    "name:und_x_variant":[
        "Lokenricht"
    ],
    "wof:name":"Lockenricht",
    "wof:placetype":"neighbourhood"
},
  "geometry": {"coordinates":[11.66611,49.52766],"type":"Point"}
}