{
  "type": "Feature",
  "properties": {
    "gn:admin1_code":"1",
    "gn:admin2_code":"81.0",
    "gn:admin3_code":"8126.0",
    "gn:admin4_code":"8126047.0",
    "gn:asciiname":"Einweiler",
    "gn:country_code":"DE",
    "gn:dem":407,
    "gn:feature_class":"P",
    "gn:feature_code":"PPL",
    "gn:name":"Einweiler",
    "gn:population":0,
    "gn:timezone":"Europe/Berlin",
    "iso:country":"DE",
    "wof:name":"Einweiler",
    "wof:placetype":"neighbourhood"
},
  "geometry": {"coordinates":[9.73367,49.1965],"type":"Point"}
}