{
  "type": "Feature",
  "properties": {
    "gn:admin1_code":"2",
    "gn:admin2_code":"92.0",
    "gn:admin3_code":"9279.0",
    "gn:admin4_code":"9279130.0",
    "gn:asciiname":"Reith",
    "gn:country_code":"DE",
    "gn:dem":454,
    "gn:feature_class":"P",
    "gn:feature_code":"PPL",
    "gn:name":"Reith",
    "gn:population":0,
    "gn:timezone":"Europe/Berlin",
    "iso:country":"DE",
    "wof:name":"Reith",
    "wof:placetype":"neighbourhood"
},
  "geometry": {"coordinates":[12.36928,48.58481],"type":"Point"}
}