{
  "type": "Feature",
  "properties": {
    "gn:admin1_code":"13.0",
    "gn:admin2_code":"00",
    "gn:admin3_code":"14625.0",
    "gn:admin4_code":"14625550.0",
    "gn:asciiname":"Zeisholz",
    "gn:country_code":"DE",
    "gn:dem":125,
    "gn:feature_class":"P",
    "gn:feature_code":"PPL",
    "gn:name":"Zeisholz",
    "gn:population":0,
    "gn:timezone":"Europe/Berlin",
    "iso:country":"DE",
    "wof:name":"Zeisholz",
    "wof:placetype":"neighbourhood"
},
  "geometry": {"coordinates":[13.89998,51.36926],"type":"Point"}
}