{
  "type": "Feature",
  "properties": {
    "gn:admin1_code":"6",
    "gn:admin2_code":"0.0",
    "gn:admin3_code":"3352.0",
    "gn:admin4_code":"3352061.0",
    "gn:asciiname":"Dueringer Weg",
    "gn:country_code":"DE",
    "gn:dem":2,
    "gn:feature_class":"P",
    "gn:feature_code":"PPL",
    "gn:name":"D\u00fcringer Weg",
    "gn:population":0,
    "gn:timezone":"Europe/Berlin",
    "iso:country":"DE",
    "wof:name":"Dueringer Weg",
    "wof:placetype":"neighbourhood"
},
  "geometry": {"coordinates":[8.56399,53.72869],"type":"Point"}
}