{
  "type": "Feature",
  "properties": {
    "gn:admin1_code":"1",
    "gn:admin2_code":"83.0",
    "gn:admin3_code":"8317.0",
    "gn:admin4_code":"8317046.0",
    "gn:asciiname":"Salmensbach",
    "gn:country_code":"DE",
    "gn:dem":327,
    "gn:feature_class":"P",
    "gn:feature_code":"PPLL",
    "gn:name":"Salmensbach",
    "gn:population":0,
    "gn:timezone":"Europe/Berlin",
    "iso:country":"DE",
    "wof:name":"Salmensbach",
    "wof:placetype":"neighbourhood"
},
  "geometry": {"coordinates":[8.05035,48.2433],"type":"Point"}
}