{
  "type": "Feature",
  "properties": {
    "iso:country":"DE",
    "wof:name":"Nordstadt",
    "wof:placetype":"neighbourhood"
},
  "geometry": {"coordinates":[7.13907049073188,51.26214556752173],"type":"Point"}
}