{
  "type": "Feature",
  "properties": {
    "gn:admin1_code":"2.0",
    "gn:admin2_code":"092",
    "gn:admin3_code":"9273.0",
    "gn:admin4_code":"9273152.0",
    "gn:asciiname":"Wohr",
    "gn:country_code":"DE",
    "gn:dem":351,
    "gn:feature_class":"P",
    "gn:feature_code":"PPL",
    "gn:name":"W\u00f6hr",
    "gn:population":0,
    "gn:timezone":"Europe/Berlin",
    "iso:country":"DE",
    "wof:name":"Wohr",
    "wof:placetype":"neighbourhood"
},
  "geometry": {"coordinates":[11.75251,48.81466],"type":"Point"}
}