{
  "type": "Feature",
  "properties": {
    "gn:country":"DE",
    "gn:fcode":"PPL",
    "gn:population":307,
    "iso:country":"DE",
    "name:bak_x_preferred":[
        "\u0425\u044e\u0437\u0435\u043b\u0438\u0446"
    ],
    "name:ceb_x_preferred":[
        "H\u00fcselitz"
    ],
    "name:che_x_preferred":[
        "\u0425\u0443\u044c\u0437\u0435\u043b\u0438\u0446"
    ],
    "name:deu_x_preferred":[
        "H\u00fcselitz"
    ],
    "name:eng_x_preferred":[
        "H\u00fcselitz"
    ],
    "name:epo_x_preferred":[
        "H\u00fcselitz"
    ],
    "name:fas_x_preferred":[
        "\u0647\u0648\u0632\u0644\u06cc\u062a\u0633"
    ],
    "name:fra_x_preferred":[
        "H\u00fcselitz"
    ],
    "name:gle_x_preferred":[
        "H\u00fcselitz"
    ],
    "name:ita_x_preferred":[
        "H\u00fcselitz"
    ],
    "name:kaz_x_preferred":[
        "\u0425\u044e\u0437\u0435\u043b\u0438\u0446"
    ],
    "name:kir_x_preferred":[
        "\u0425\u044e\u0437\u0435\u043b\u0438\u0446"
    ],
    "name:nld_x_preferred":[
        "H\u00fcselitz"
    ],
    "name:ron_x_preferred":[
        "H\u00fcselitz"
    ],
    "name:rus_x_preferred":[
        "\u0425\u044e\u0437\u0435\u043b\u0438\u0446"
    ],
    "name:tat_x_preferred":[
        "\u0425\u044e\u0437\u0435\u043b\u0438\u0446"
    ],
    "name:uzb_x_preferred":[
        "H\u00fcselitz"
    ],
    "name:vie_x_preferred":[
        "H\u00fcselitz"
    ],
    "name:vol_x_preferred":[
        "H\u00fcselitz"
    ],
    "name:war_x_preferred":[
        "H\u00fcselitz"
    ],
    "qs_pg:aaroncc":"DE",
    "qs_pg:gn_country":"DE",
    "qs_pg:gn_fcode":"PPL",
    "qs_pg:gn_pop":307,
    "qs_pg:name":"H\u00fcselitz",
    "qs_pg:name_adm0":"Deutschland",
    "qs_pg:name_adm1":"Sachsen-Anhalt",
    "qs_pg:photos_9r":0,
    "qs_pg:photos_sr":0,
    "qs_pg:pop_sr":2,
    "qs_pg:qs_pg_placetype":"locality",
    "qs_pg:qs_pg_placetype_gp":"Town",
    "qs_pg:woe_adm0":23424829,
    "woe:adm0_id":23424829,
    "woe:name_adm0":"Deutschland",
    "woe:name_adm1":"Sachsen-Anhalt",
    "woe:placetype":"Town",
    "wof:name":"H\u00fcselitz",
    "wof:placetype":"neighbourhood",
    "wof:population":307
},
  "geometry": {"coordinates":[11.80859,52.50891],"type":"Point"}
}