{
  "type": "Feature",
  "properties": {
    "gn:admin1_code":"6",
    "gn:admin2_code":"0.0",
    "gn:admin3_code":"3351.0",
    "gn:admin4_code":"3351025.0",
    "gn:asciiname":"Rebberlah",
    "gn:country_code":"DE",
    "gn:dem":83,
    "gn:feature_class":"P",
    "gn:feature_code":"PPL",
    "gn:name":"Rebberlah",
    "gn:population":0,
    "gn:timezone":"Europe/Berlin",
    "iso:country":"DE",
    "wof:name":"Rebberlah",
    "wof:placetype":"neighbourhood"
},
  "geometry": {"coordinates":[10.16941,52.74183000000001],"type":"Point"}
}