{
  "type": "Feature",
  "properties": {
    "gn:admin1_code":"1.0",
    "gn:admin2_code":"83.0",
    "gn:admin3_code":"8315.0",
    "gn:admin4_code":"8315113.0",
    "gn:asciiname":"Schwaerzenbach",
    "gn:country_code":"DE",
    "gn:dem":1030,
    "gn:feature_class":"P",
    "gn:feature_code":"PPL",
    "gn:name":"Schw\u00e4rzenbach",
    "gn:population":0,
    "gn:timezone":"Europe/Berlin",
    "iso:country":"DE",
    "wof:name":"Schwaerzenbach",
    "wof:placetype":"neighbourhood"
},
  "geometry": {"coordinates":[8.23704,47.94935],"type":"Point"}
}