{
  "type": "Feature",
  "properties": {
    "gn:admin1_code":"7",
    "gn:admin2_code":"59.0",
    "gn:admin3_code":"5974.0",
    "gn:admin4_code":"5974008.0",
    "gn:asciiname":"Herringserhoefe",
    "gn:country_code":"DE",
    "gn:dem":205,
    "gn:feature_class":"P",
    "gn:feature_code":"PPLL",
    "gn:name":"Herringserh\u00f6fe",
    "gn:population":0,
    "gn:timezone":"Europe/Berlin",
    "iso:country":"DE",
    "wof:name":"Herringserhoefe",
    "wof:placetype":"neighbourhood"
},
  "geometry": {"coordinates":[8.21257,51.53399],"type":"Point"}
}