{
  "type": "Feature",
  "properties": {
    "gn:admin1_code":"2",
    "gn:admin2_code":"97.0",
    "gn:admin3_code":"9776.0",
    "gn:admin4_code":"9776113.0",
    "gn:asciiname":"Pfarrenberg",
    "gn:country_code":"DE",
    "gn:dem":895,
    "gn:feature_class":"P",
    "gn:feature_code":"PPL",
    "gn:name":"Pfarrenberg",
    "gn:population":0,
    "gn:timezone":"Europe/Berlin",
    "iso:country":"DE",
    "wof:name":"Pfarrenberg",
    "wof:placetype":"neighbourhood"
},
  "geometry": {"coordinates":[10.0526,47.60898],"type":"Point"}
}