{
  "type": "Feature",
  "properties": {
    "gn:admin1_code":"2",
    "gn:admin2_code":"92.0",
    "gn:admin3_code":"9278.0",
    "gn:admin4_code":"9278189.0",
    "gn:asciiname":"Utzmannsdorf",
    "gn:country_code":"DE",
    "gn:dem":432,
    "gn:feature_class":"P",
    "gn:feature_code":"PPL",
    "gn:name":"Utzmannsdorf",
    "gn:population":0,
    "gn:timezone":"Europe/Berlin",
    "iso:country":"DE",
    "wof:name":"Utzmannsdorf",
    "wof:placetype":"neighbourhood"
},
  "geometry": {"coordinates":[12.64379,49.07654],"type":"Point"}
}