{
  "type": "Feature",
  "properties": {
    "iso:country":"DE",
    "name:deu_x_preferred":[
        "B\u00f6hlitz-Ehrenberg"
    ],
    "wof:name":"Boehlitz-Ehrenberg",
    "wof:placetype":"neighbourhood"
},
  "geometry": {"coordinates":[12.29185010220828,51.36006097928102],"type":"Point"}
}