{
  "type": "Feature",
  "properties": {
    "gn:admin1_code":"13.0",
    "gn:admin2_code":"0.0",
    "gn:admin3_code":"14713.0",
    "gn:admin4_code":"14713000.0",
    "gn:asciiname":"Boehlitz-Ehrenberg",
    "gn:country_code":"DE",
    "gn:dem":110,
    "gn:feature_class":"P",
    "gn:feature_code":"PPL",
    "gn:name":"B\u00f6hlitz-Ehrenberg",
    "gn:population":0,
    "gn:timezone":"Europe/Berlin",
    "iso:country":"DE",
    "name:deu_x_preferred":[
        "B\u00f6hlitz-Ehrenberg"
    ],
    "wof:name":"Boehlitz-Ehrenberg",
    "wof:placetype":"neighbourhood"
},
  "geometry": {"coordinates":[12.29185,51.360061],"type":"Point"}
}