{
  "type": "Feature",
  "properties": {
    "gn:admin1_code":"2",
    "gn:admin2_code":"92.0",
    "gn:admin3_code":"9274.0",
    "gn:admin4_code":"9274112.0",
    "gn:asciiname":"Loizenkirchen",
    "gn:country_code":"DE",
    "gn:dem":427,
    "gn:feature_class":"P",
    "gn:feature_code":"PPL",
    "gn:name":"Loizenkirchen",
    "gn:population":0,
    "gn:timezone":"Europe/Berlin",
    "iso:country":"DE",
    "wof:name":"Loizenkirchen",
    "wof:placetype":"neighbourhood"
},
  "geometry": {"coordinates":[12.46747,48.53358],"type":"Point"}
}