{
  "type": "Feature",
  "properties": {
    "gn:admin1_code":"13",
    "gn:admin2_code":"0.0",
    "gn:admin3_code":"14730.0",
    "gn:admin4_code":"14730230.0",
    "gn:asciiname":"Kreischa",
    "gn:country_code":"DE",
    "gn:dem":130,
    "gn:feature_class":"P",
    "gn:feature_code":"PPL",
    "gn:name":"Kreischa",
    "gn:population":0,
    "gn:timezone":"Europe/Berlin",
    "iso:country":"DE",
    "name:bak_x_preferred":[
        "\u041a\u0440\u0430\u0439\u0448\u0430"
    ],
    "name:ceb_x_preferred":[
        "Kreischa"
    ],
    "name:ces_x_preferred":[
        "Kreischa"
    ],
    "name:deu_x_preferred":[
        "Kreischa"
    ],
    "name:epo_x_preferred":[
        "Kreischa"
    ],
    "name:eus_x_preferred":[
        "Kreischa"
    ],
    "name:fas_x_preferred":[
        "\u06a9\u0631\u0627\u06cc\u0634\u0627"
    ],
    "name:fra_x_preferred":[
        "Kreischa"
    ],
    "name:hun_x_preferred":[
        "Kreischa"
    ],
    "name:ido_x_preferred":[
        "Kreischa"
    ],
    "name:ita_x_preferred":[
        "Kreischa"
    ],
    "name:mkd_x_preferred":[
        "\u041a\u0440\u0430\u0458\u0448\u0430"
    ],
    "name:msa_x_preferred":[
        "Kreischa"
    ],
    "name:nld_x_preferred":[
        "Kreischa"
    ],
    "name:nor_x_preferred":[
        "Kreischa"
    ],
    "name:pol_x_preferred":[
        "Kreischa"
    ],
    "name:ron_x_preferred":[
        "Kreischa"
    ],
    "name:rus_x_preferred":[
        "\u041a\u0440\u0430\u0439\u0448\u0430"
    ],
    "name:spa_x_preferred":[
        "Kreischa"
    ],
    "name:srp_x_preferred":[
        "\u041a\u0440\u0430\u0458\u0448\u0430"
    ],
    "name:swe_x_preferred":[
        "Kreischa"
    ],
    "name:ukr_x_preferred":[
        "\u041a\u0440\u0430\u0439\u0448\u0430"
    ],
    "name:uzb_x_preferred":[
        "Kreischa"
    ],
    "name:vie_x_preferred":[
        "Kreischa"
    ],
    "name:vol_x_preferred":[
        "Kreischa"
    ],
    "name:war_x_preferred":[
        "Kreischa"
    ],
    "name:zho_x_preferred":[
        "\u514b\u8d56\u6c99"
    ],
    "wof:name":"Kreischa",
    "wof:placetype":"neighbourhood"
},
  "geometry": {"coordinates":[13.0905,51.28008],"type":"Point"}
}