{
  "type": "Feature",
  "properties": {
    "gn:admin1_code":"13",
    "gn:admin2_code":"0.0",
    "gn:admin3_code":"14730.0",
    "gn:admin4_code":"14730230.0",
    "gn:asciiname":"Kreischa",
    "gn:country_code":"DE",
    "gn:dem":130,
    "gn:feature_class":"P",
    "gn:feature_code":"PPL",
    "gn:name":"Kreischa",
    "gn:population":0,
    "gn:timezone":"Europe/Berlin",
    "iso:country":"DE",
    "wof:name":"Kreischa",
    "wof:placetype":"neighbourhood"
},
  "geometry": {"coordinates":[13.0905,51.28008],"type":"Point"}
}