{
  "type": "Feature",
  "properties": {
    "gn:admin1_code":"11.0",
    "gn:admin2_code":"00",
    "gn:admin3_code":"12068.0",
    "gn:admin4_code":"12068501.0",
    "gn:asciiname":"Zernitz",
    "gn:country_code":"DE",
    "gn:dem":30,
    "gn:feature_class":"P",
    "gn:feature_code":"PPL",
    "gn:name":"Zernitz",
    "gn:population":0,
    "gn:timezone":"Europe/Berlin",
    "iso:country":"DE",
    "name:bak_x_preferred":[
        "\u0426\u0435\u0440\u043d\u0438\u0446"
    ],
    "name:ceb_x_preferred":[
        "Zernitz"
    ],
    "name:deu_x_preferred":[
        "Zernitz"
    ],
    "name:epo_x_preferred":[
        "Zernitz"
    ],
    "name:fas_x_preferred":[
        "\u062a\u0633\u0631\u0646\u06cc\u062a\u0633"
    ],
    "name:ita_x_preferred":[
        "Zernitz"
    ],
    "name:kaz_x_preferred":[
        "\u0426\u0435\u0440\u043d\u0438\u0446"
    ],
    "name:kir_x_preferred":[
        "\u0426\u0435\u0440\u043d\u0438\u0446"
    ],
    "name:mkd_x_preferred":[
        "\u0426\u0435\u0440\u043d\u0438\u0446"
    ],
    "name:nld_x_preferred":[
        "Zernitz"
    ],
    "name:pol_x_preferred":[
        "Zernitz"
    ],
    "name:ron_x_preferred":[
        "Zernitz"
    ],
    "name:rus_x_preferred":[
        "\u0426\u0435\u0440\u043d\u0438\u0446"
    ],
    "name:uzb_x_preferred":[
        "Zernitz"
    ],
    "name:vie_x_preferred":[
        "Zernitz"
    ],
    "name:vol_x_preferred":[
        "Zernitz"
    ],
    "wof:name":"Zernitz",
    "wof:placetype":"neighbourhood"
},
  "geometry": {"coordinates":[12.36847,52.88288000000001],"type":"Point"}
}