{
  "type": "Feature",
  "properties": {
    "gn:admin1_code":"2",
    "gn:admin2_code":"92.0",
    "gn:admin3_code":"9272.0",
    "gn:admin4_code":"9272151.0",
    "gn:asciiname":"Neidlingerberg",
    "gn:country_code":"DE",
    "gn:dem":791,
    "gn:feature_class":"P",
    "gn:feature_code":"PPLL",
    "gn:name":"Neidlingerberg",
    "gn:population":0,
    "gn:timezone":"Europe/Berlin",
    "iso:country":"DE",
    "wof:name":"Neidlingerberg",
    "wof:placetype":"neighbourhood"
},
  "geometry": {"coordinates":[13.61009,48.69294],"type":"Point"}
}