{
  "type": "Feature",
  "properties": {
    "gn:admin1_code":"2",
    "gn:admin2_code":"91.0",
    "gn:admin3_code":"9189.0",
    "gn:admin4_code":"9189152.0",
    "gn:asciiname":"Dandlberg",
    "gn:country_code":"DE",
    "gn:dem":460,
    "gn:feature_class":"P",
    "gn:feature_code":"PPL",
    "gn:name":"Dandlberg",
    "gn:population":0,
    "gn:timezone":"Europe/Berlin",
    "iso:country":"DE",
    "wof:name":"Dandlberg",
    "wof:placetype":"neighbourhood"
},
  "geometry": {"coordinates":[12.75771,48.0621],"type":"Point"}
}