{
  "type": "Feature",
  "properties": {
    "gn:admin1_code":"7",
    "gn:admin2_code":"53.0",
    "gn:admin3_code":"5358.0",
    "gn:admin4_code":"5358036.0",
    "gn:asciiname":"Gevenich",
    "gn:country_code":"DE",
    "gn:dem":105,
    "gn:elevation":"105.0",
    "gn:feature_class":"P",
    "gn:feature_code":"PPL",
    "gn:name":"Gevenich",
    "gn:population":0,
    "gn:timezone":"Europe/Berlin",
    "iso:country":"DE",
    "name:ceb_x_preferred":[
        "Gevenich"
    ],
    "name:deu_x_preferred":[
        "Gevenich"
    ],
    "name:epo_x_preferred":[
        "Gevenich"
    ],
    "name:eus_x_preferred":[
        "Gevenich"
    ],
    "name:fas_x_preferred":[
        "\u06af\u0641\u0646\u0627\u06cc\u0634"
    ],
    "name:fra_x_preferred":[
        "Gevenich"
    ],
    "name:hun_x_preferred":[
        "Gevenich"
    ],
    "name:ita_x_preferred":[
        "Gevenich"
    ],
    "name:msa_x_preferred":[
        "Gevenich"
    ],
    "name:nld_x_preferred":[
        "Gevenich"
    ],
    "name:pol_x_preferred":[
        "Gevenich"
    ],
    "name:por_x_preferred":[
        "Gevenich"
    ],
    "name:ron_x_preferred":[
        "Gevenich"
    ],
    "name:rus_x_preferred":[
        "\u0413\u0435\u0432\u0435\u043d\u0438\u0445"
    ],
    "name:spa_x_preferred":[
        "Gevenich"
    ],
    "name:srp_x_preferred":[
        "\u0413\u0435\u0432\u0435\u043d\u0438\u0445"
    ],
    "name:ukr_x_preferred":[
        "\u0413\u0435\u0444\u0435\u043d\u0456\u0445"
    ],
    "name:uzb_x_preferred":[
        "Gevenich"
    ],
    "name:vie_x_preferred":[
        "Gevenich"
    ],
    "name:vol_x_preferred":[
        "Gevenich"
    ],
    "name:war_x_preferred":[
        "Gevenich"
    ],
    "name:zho_x_preferred":[
        "\u76d6\u6c83\u5c3c\u5e0c"
    ],
    "wof:name":"Gevenich",
    "wof:placetype":"neighbourhood"
},
  "geometry": {"coordinates":[6.309,50.98796],"type":"Point"}
}