{
  "type": "Feature",
  "properties": {
    "iso:country":"DE",
    "wof:name":"Salingen",
    "wof:placetype":"neighbourhood"
},
  "geometry": {"coordinates":[7.39676033668851,51.47111514056265],"type":"Point"}
}