{
  "type": "Feature",
  "properties": {
    "gn:country":"DE",
    "gn:fcode":"PPL",
    "gn:population":0,
    "iso:country":"DE",
    "name:ceb_x_preferred":[
        "Keitum"
    ],
    "name:dan_x_preferred":[
        "Kejtum"
    ],
    "name:deu_x_preferred":[
        "Keitum"
    ],
    "name:fas_x_preferred":[
        "\u06a9\u0627\u06cc\u062a\u0648\u0645"
    ],
    "name:frr_x_preferred":[
        "Kairem"
    ],
    "name:fry_x_preferred":[
        "Keitum"
    ],
    "name:ita_x_preferred":[
        "Keitum"
    ],
    "name:nds_x_preferred":[
        "Keitum"
    ],
    "qs_pg:aaroncc":"DE",
    "qs_pg:gn_country":"DE",
    "qs_pg:gn_fcode":"PPL",
    "qs_pg:gn_pop":0,
    "qs_pg:name":"Keitum",
    "qs_pg:name_adm0":"Deutschland",
    "qs_pg:name_adm1":"Schleswig-Holstein",
    "qs_pg:photos":98,
    "qs_pg:photos_1k":20,
    "qs_pg:photos_9k":1,
    "qs_pg:photos_9r":3,
    "qs_pg:photos_all":98,
    "qs_pg:photos_sr":3,
    "qs_pg:pop_sr":0,
    "qs_pg:qs_pg_placetype":"locality",
    "qs_pg:qs_pg_placetype_gp":"Town",
    "qs_pg:woe_adm0":23424829,
    "woe:adm0_id":23424829,
    "woe:name_adm0":"Deutschland",
    "woe:name_adm1":"Schleswig-Holstein",
    "woe:placetype":"Town",
    "wof:name":"Keitum",
    "wof:placetype":"neighbourhood",
    "wof:population":1250
},
  "geometry": {"coordinates":[8.3709,54.8929],"type":"Point"}
}