{
  "type": "Feature",
  "properties": {
    "gn:country":"DE",
    "gn:fcode":"PPL",
    "gn:population":0,
    "iso:country":"DE",
    "name:als_x_preferred":[
        "H\u00fctten"
    ],
    "name:ceb_x_preferred":[
        "H\u00fctten"
    ],
    "name:deu_x_preferred":[
        "H\u00fctten"
    ],
    "name:epo_x_preferred":[
        "H\u00fctten"
    ],
    "name:eus_x_preferred":[
        "H\u00fctten"
    ],
    "name:fra_x_preferred":[
        "H\u00fctten"
    ],
    "name:ita_x_preferred":[
        "H\u00fctten"
    ],
    "name:mkd_x_preferred":[
        "\u0425\u0438\u0442\u0435\u043d"
    ],
    "name:nld_x_preferred":[
        "H\u00fctten"
    ],
    "name:pol_x_preferred":[
        "H\u00fctten"
    ],
    "name:rus_x_preferred":[
        "\u0425\u044e\u0442\u0442\u0435\u043d"
    ],
    "name:srp_x_preferred":[
        "\u0425\u0438\u0442\u0435\u043d"
    ],
    "name:swe_x_preferred":[
        "H\u00fctten"
    ],
    "name:vol_x_preferred":[
        "H\u00fctten"
    ],
    "qs_pg:aaroncc":"DE",
    "qs_pg:gn_country":"DE",
    "qs_pg:gn_fcode":"PPL",
    "qs_pg:gn_pop":0,
    "qs_pg:name":"H\u00fctten",
    "qs_pg:name_adm0":"Deutschland",
    "qs_pg:name_adm1":"Baden-W\u00fcrttemberg",
    "qs_pg:photos":31,
    "qs_pg:photos_1k":6,
    "qs_pg:photos_9k":1,
    "qs_pg:photos_9r":2,
    "qs_pg:photos_all":31,
    "qs_pg:photos_sr":2,
    "qs_pg:pop_sr":0,
    "qs_pg:qs_pg_placetype":"locality",
    "qs_pg:qs_pg_placetype_gp":"Town",
    "qs_pg:woe_adm0":23424829,
    "woe:adm0_id":23424829,
    "woe:name_adm0":"Deutschland",
    "woe:name_adm1":"Baden-W\u00fcrttemberg",
    "woe:placetype":"Town",
    "wof:name":"H\u00fctten",
    "wof:placetype":"neighbourhood"
},
  "geometry": {"coordinates":[9.63831,48.37341],"type":"Point"}
}