{
  "type": "Feature",
  "properties": {
    "gn:admin1_code":"7",
    "gn:admin2_code":"59.0",
    "gn:admin3_code":"5978.0",
    "gn:admin4_code":"5978028.0",
    "gn:asciiname":"Reingsen",
    "gn:country_code":"DE",
    "gn:dem":189,
    "gn:feature_class":"P",
    "gn:feature_code":"PPL",
    "gn:name":"Reingsen",
    "gn:population":0,
    "gn:timezone":"Europe/Berlin",
    "iso:country":"DE",
    "wof:name":"Reingsen",
    "wof:placetype":"neighbourhood"
},
  "geometry": {"coordinates":[7.62488,51.40262],"type":"Point"}
}