{
  "type": "Feature",
  "properties": {
    "gn:admin1_code":"2",
    "gn:admin2_code":"93.0",
    "gn:admin3_code":"9375.0",
    "gn:admin4_code":"9375205.0",
    "gn:asciiname":"Untermassing",
    "gn:country_code":"DE",
    "gn:dem":372,
    "gn:feature_class":"P",
    "gn:feature_code":"PPL",
    "gn:name":"Untermassing",
    "gn:population":0,
    "gn:timezone":"Europe/Berlin",
    "iso:country":"DE",
    "wof:name":"Untermassing",
    "wof:placetype":"neighbourhood"
},
  "geometry": {"coordinates":[12.09767,48.91686],"type":"Point"}
}