{
  "type": "Feature",
  "properties": {
    "iso:country":"DE",
    "name:ceb_x_preferred":[
        "Wilhelmstadt"
    ],
    "name:deu_x_preferred":[
        "Wilhelmstadt"
    ],
    "name:eng_x_preferred":[
        "Wilhelmstadt"
    ],
    "name:fas_x_preferred":[
        "\u0648\u06cc\u0644\u0647\u0644\u0645\u0634\u062a\u0627\u062f\u062a"
    ],
    "name:fra_x_preferred":[
        "Berlin-Wilhelmstadt"
    ],
    "name:heb_x_preferred":[
        "\u05d5\u05d9\u05dc\u05d4\u05dc\u05de\u05e9\u05d8\u05d0\u05d8"
    ],
    "name:ita_x_preferred":[
        "Wilhelmstadt"
    ],
    "name:jpn_x_preferred":[
        "\u30d9\u30eb\u30ea\u30f3\uff1d\u30f4\u30a3\u30eb\u30d8\u30eb\u30e0\u30b7\u30e5\u30bf\u30c3\u30c8"
    ],
    "name:nld_x_preferred":[
        "Berlin-Wilhelmstadt"
    ],
    "name:nob_x_preferred":[
        "Wilhelmstadt"
    ],
    "name:pol_x_preferred":[
        "Wilhelmstadt"
    ],
    "name:swe_x_preferred":[
        "Wilhelmstadt"
    ],
    "name:unk_x_variant":[
        "Wilhelmstadt"
    ],
    "qs:gn_fcode":"PPLX",
    "qs:gn_local":0,
    "qs:gn_namadm1":"14",
    "qs:gn_name":"Wilhelmstadt",
    "qs:local_max":6444,
    "qs:local_sum":9658,
    "qs:localhoods":9,
    "qs:name":"Wilhelmstadt",
    "qs:name_adm0":"Deutschland",
    "qs:name_adm1":"Sachsen-Anhalt",
    "qs:name_adm2":"Stadtkreis Magdeburg",
    "qs:name_lau":"Magdeburg",
    "qs:name_local":"Magdeburg",
    "qs:photo_max":895,
    "qs:photo_sum":6444,
    "qs:placetype":"Suburb",
    "qs:quad_count":137,
    "qs:woe_adm0":23424829,
    "qs:woe_adm1":2345494,
    "qs:woe_adm2":12597084,
    "qs:woe_lau":56556506,
    "qs:woe_local":56556506,
    "qs:woe_ver":"7.10.0",
    "wd:wordcount":329,
    "wof:lang":[
        "ger"
    ],
    "wof:name":"Wilhelmstadt",
    "wof:placetype":"neighbourhood"
},
  "geometry": {"coordinates":[11.634078,52.1295],"type":"Point"}
}