{
  "type": "Feature",
  "properties": {
    "gn:admin1_code":"10",
    "gn:admin2_code":"0.0",
    "gn:admin3_code":"1054.0",
    "gn:admin4_code":"1054074.0",
    "gn:asciiname":"Honkenswarf",
    "gn:cc2":"DE",
    "gn:country_code":"DE",
    "gn:dem":1,
    "gn:feature_class":"P",
    "gn:feature_code":"PPL",
    "gn:name":"Honkenswarf",
    "gn:population":0,
    "gn:timezone":"Europe/Berlin",
    "iso:country":"DE",
    "name:und_x_variant":[
        "Honkenswarft",
        "Honkenswarf"
    ],
    "wof:name":"Honkenswarf",
    "wof:placetype":"neighbourhood"
},
  "geometry": {"coordinates":[8.6203,54.64386],"type":"Point"}
}