{
  "type": "Feature",
  "properties": {
    "gn:admin1_code":"2.0",
    "gn:admin2_code":"095",
    "gn:admin3_code":"9571.0",
    "gn:admin4_code":"9571145.0",
    "gn:asciiname":"Zumhaus",
    "gn:country_code":"DE",
    "gn:dem":452,
    "gn:feature_class":"P",
    "gn:feature_code":"PPL",
    "gn:name":"Zumhaus",
    "gn:population":0,
    "gn:timezone":"Europe/Berlin",
    "iso:country":"DE",
    "wof:name":"Zumhaus",
    "wof:placetype":"neighbourhood"
},
  "geometry": {"coordinates":[10.2479,49.21189],"type":"Point"}
}