{
  "type": "Feature",
  "properties": {
    "gn:admin1_code":"14",
    "gn:admin2_code":"0.0",
    "gn:admin3_code":"15088.0",
    "gn:admin4_code":"15088340.0",
    "gn:asciiname":"Schafsee",
    "gn:country_code":"DE",
    "gn:dem":146,
    "gn:feature_class":"P",
    "gn:feature_code":"PPL",
    "gn:name":"Schafsee",
    "gn:population":0,
    "gn:timezone":"Europe/Berlin",
    "iso:country":"DE",
    "wof:name":"Schafsee",
    "wof:placetype":"neighbourhood"
},
  "geometry": {"coordinates":[11.64874,51.43203],"type":"Point"}
}