{
  "type": "Feature",
  "properties": {
    "gn:admin1_code":"2",
    "gn:admin2_code":"97.0",
    "gn:admin3_code":"9779.0",
    "gn:admin4_code":"9779188.0",
    "gn:asciiname":"Schworsheim",
    "gn:country_code":"DE",
    "gn:dem":413,
    "gn:feature_class":"P",
    "gn:feature_code":"PPL",
    "gn:name":"Schw\u00f6rsheim",
    "gn:population":0,
    "gn:timezone":"Europe/Berlin",
    "iso:country":"DE",
    "wof:name":"Schworsheim",
    "wof:placetype":"neighbourhood"
},
  "geometry": {"coordinates":[10.61888,48.91183],"type":"Point"}
}