{
  "type": "Feature",
  "properties": {
    "gn:admin1_code":"2",
    "gn:admin2_code":"91.0",
    "gn:admin3_code":"9187.0",
    "gn:admin4_code":"9187132.0",
    "gn:asciiname":"Greimelberg",
    "gn:country_code":"DE",
    "gn:dem":646,
    "gn:feature_class":"P",
    "gn:feature_code":"PPL",
    "gn:name":"Greimelberg",
    "gn:population":0,
    "gn:timezone":"Europe/Berlin",
    "iso:country":"DE",
    "wof:name":"Greimelberg",
    "wof:placetype":"neighbourhood"
},
  "geometry": {"coordinates":[12.29849,47.82127],"type":"Point"}
}