{
  "type": "Feature",
  "properties": {
    "gn:admin1_code":"1",
    "gn:admin2_code":"83.0",
    "gn:admin3_code":"8311.0",
    "gn:admin4_code":"8311000.0",
    "gn:asciiname":"Kappel",
    "gn:country_code":"DE",
    "gn:dem":373,
    "gn:feature_class":"P",
    "gn:feature_code":"PPL",
    "gn:name":"Kappel",
    "gn:population":0,
    "gn:timezone":"Europe/Berlin",
    "iso:country":"DE",
    "name:als_x_preferred":[
        "Kappel"
    ],
    "name:ceb_x_preferred":[
        "Kappel"
    ],
    "name:deu_x_preferred":[
        "Kappel"
    ],
    "name:epo_x_preferred":[
        "Kappel"
    ],
    "name:fra_x_preferred":[
        "Kappel"
    ],
    "name:ita_x_preferred":[
        "Kappel"
    ],
    "name:nld_x_preferred":[
        "Kappel"
    ],
    "name:pol_x_preferred":[
        "Kappel"
    ],
    "name:spa_x_preferred":[
        "Kappel"
    ],
    "name:swe_x_preferred":[
        "Kappel"
    ],
    "name:vol_x_preferred":[
        "Kappel"
    ],
    "wof:name":"Kappel",
    "wof:placetype":"neighbourhood"
},
  "geometry": {"coordinates":[7.90846,47.96914],"type":"Point"}
}