{
  "type": "Feature",
  "properties": {
    "iso:country":"DE",
    "wof:name":"Innenstadt",
    "wof:placetype":"neighbourhood"
},
  "geometry": {"coordinates":[6.95766127107949,50.94008467643877],"type":"Point"}
}