{
  "type": "Feature",
  "properties": {
    "iso:country":"DE",
    "name:deu_x_preferred":[
        "Innenstadt"
    ],
    "name:ita_x_preferred":[
        "Innenstadt"
    ],
    "name:pol_x_preferred":[
        "Innenstadt"
    ],
    "wof:name":"Innenstadt",
    "wof:placetype":"neighbourhood"
},
  "geometry": {"coordinates":[6.95766127107949,50.94008467643877],"type":"Point"}
}