{
  "type": "Feature",
  "properties": {
    "gn:admin1_code":"14",
    "gn:admin2_code":"0.0",
    "gn:admin3_code":"15082.0",
    "gn:admin4_code":"15082377.0",
    "gn:asciiname":"Storkau",
    "gn:country_code":"DE",
    "gn:dem":79,
    "gn:feature_class":"P",
    "gn:feature_code":"PPL",
    "gn:name":"Storkau",
    "gn:population":0,
    "gn:timezone":"Europe/Berlin",
    "iso:country":"DE",
    "name:ceb_x_preferred":[
        "Storkau"
    ],
    "name:deu_x_preferred":[
        "Storkau"
    ],
    "name:epo_x_preferred":[
        "Storkau"
    ],
    "name:nld_x_preferred":[
        "Storkau"
    ],
    "name:rus_x_preferred":[
        "\u0428\u0442\u043e\u0440\u043a\u0430\u0443"
    ],
    "name:swe_x_preferred":[
        "Storkau"
    ],
    "wof:name":"Storkau",
    "wof:placetype":"neighbourhood"
},
  "geometry": {"coordinates":[12.08473,51.74254000000001],"type":"Point"}
}