{
  "type": "Feature",
  "properties": {
    "gn:admin1_code":"6.0",
    "gn:admin2_code":"0.0",
    "gn:admin3_code":"3241.0",
    "gn:admin4_code":"3241016.0",
    "gn:asciiname":"Bilm",
    "gn:country_code":"DE",
    "gn:dem":70,
    "gn:feature_class":"P",
    "gn:feature_code":"PPL",
    "gn:name":"Bilm",
    "gn:population":0,
    "gn:timezone":"Europe/Berlin",
    "iso:country":"DE",
    "wof:name":"Bilm",
    "wof:placetype":"neighbourhood"
},
  "geometry": {"coordinates":[9.91355,52.33971],"type":"Point"}
}