{
  "type": "Feature",
  "properties": {
    "iso:country":"DE",
    "name:deu_x_preferred":[
        "Aplerbeck"
    ],
    "name:ell_x_preferred":[
        "\u0391\u03c0\u03bb\u03b5\u03c1\u03bc\u03c0\u03ad\u03ba"
    ],
    "name:fas_x_preferred":[
        "\u0622\u0644\u067e\u0631\u0628\u06a9"
    ],
    "name:pol_x_preferred":[
        "Aplerbeck"
    ],
    "name:ron_x_preferred":[
        "Dortmund-Aplerbeck"
    ],
    "name:rus_x_preferred":[
        "\u0410\u043f\u043b\u0435\u0440\u0431\u0435\u043a"
    ],
    "name:slk_x_preferred":[
        "Dortmund-Aplerbeck"
    ],
    "wof:name":"Aplerbeck",
    "wof:placetype":"neighbourhood"
},
  "geometry": {"coordinates":[7.55569739404445,51.49229569877632],"type":"Point"}
}