{
  "type": "Feature",
  "properties": {
    "iso:country":"DE",
    "wof:name":"Aplerbeck",
    "wof:placetype":"neighbourhood"
},
  "geometry": {"coordinates":[7.55569739404445,51.49229569877632],"type":"Point"}
}