{
  "type": "Feature",
  "properties": {
    "gn:admin1_code":"8",
    "gn:admin2_code":"0.0",
    "gn:admin3_code":"7339.0",
    "gn:admin4_code":"7339003.0",
    "gn:asciiname":"Steeg",
    "gn:country_code":"DE",
    "gn:dem":132,
    "gn:feature_class":"P",
    "gn:feature_code":"PPL",
    "gn:name":"Steeg",
    "gn:population":0,
    "gn:timezone":"Europe/Berlin",
    "iso:country":"DE",
    "name:ceb_x_preferred":[
        "Steeg"
    ],
    "name:deu_x_preferred":[
        "Steeg"
    ],
    "name:fra_x_preferred":[
        "Steeg"
    ],
    "name:ita_x_preferred":[
        "Steeg"
    ],
    "name:pol_x_preferred":[
        "Steeg"
    ],
    "name:swe_x_preferred":[
        "Steeg"
    ],
    "wof:name":"Steeg",
    "wof:placetype":"neighbourhood"
},
  "geometry": {"coordinates":[7.74734,50.054],"type":"Point"}
}