{
  "type": "Feature",
  "properties": {
    "gn:admin1_code":"7",
    "gn:admin2_code":"53.0",
    "gn:admin3_code":"5378.0",
    "gn:admin4_code":"5378016.0",
    "gn:asciiname":"Raderhof",
    "gn:country_code":"DE",
    "gn:dem":189,
    "gn:feature_class":"P",
    "gn:feature_code":"PPL",
    "gn:name":"Raderhof",
    "gn:population":0,
    "gn:timezone":"Europe/Berlin",
    "iso:country":"DE",
    "wof:name":"Raderhof",
    "wof:placetype":"neighbourhood"
},
  "geometry": {"coordinates":[7.10761,51.13041],"type":"Point"}
}