{
  "type": "Feature",
  "properties": {
    "gn:admin1_code":"7",
    "gn:admin2_code":"59.0",
    "gn:admin3_code":"5978.0",
    "gn:admin4_code":"5978004.0",
    "gn:asciiname":"Heil",
    "gn:country_code":"DE",
    "gn:dem":56,
    "gn:feature_class":"P",
    "gn:feature_code":"PPL",
    "gn:name":"Heil",
    "gn:population":0,
    "gn:timezone":"Europe/Berlin",
    "iso:country":"DE",
    "name:deu_x_preferred":[
        "Heil"
    ],
    "name:fin_x_preferred":[
        "Heil"
    ],
    "name:fra_x_preferred":[
        "Heil"
    ],
    "name:ita_x_preferred":[
        "Heil"
    ],
    "name:pol_x_preferred":[
        "Heil"
    ],
    "name:rus_x_preferred":[
        "\u0425\u0430\u0439\u043b\u044c"
    ],
    "name:swe_x_preferred":[
        "Heil"
    ],
    "wof:name":"Heil",
    "wof:placetype":"neighbourhood"
},
  "geometry": {"coordinates":[7.58548,51.63402],"type":"Point"}
}