{
  "type": "Feature",
  "properties": {
    "gn:admin1_code":"7",
    "gn:admin2_code":"57.0",
    "gn:admin3_code":"5766.0",
    "gn:admin4_code":"5766036.0",
    "gn:asciiname":"Langenholzhausen",
    "gn:country_code":"DE",
    "gn:dem":95,
    "gn:feature_class":"P",
    "gn:feature_code":"PPL",
    "gn:name":"Langenholzhausen",
    "gn:population":0,
    "gn:timezone":"Europe/Berlin",
    "iso:country":"DE",
    "wof:name":"Langenholzhausen",
    "wof:placetype":"neighbourhood"
},
  "geometry": {"coordinates":[8.96544,52.14697],"type":"Point"}
}